Workbook

Sheet 报价汇总-装修工程
B1: D座塔楼办公室3903-04-05-06装饰工程汇总 装修工程 | J1: =2450/83 -> 29.518072 | L1: =40*83 -> 3320
A2: 序号 | B2: 名称 | C2: 金额（元） | D2: 面积（㎡） | E2: 单方价格（元/㎡） | F2: 备注 | M2: =100/83 -> 1.2048193
A3: 一 | B3: 装饰工程 | C3: =不含空调消防清单!G3 -> 653982.63
A4: （一） | B4: 拆除工程 | C4: =不含空调消防清单!G4 -> 22177.008
A5: （二） | B5: 隔墙工程 | C5: =不含空调消防清单!G8 -> 172720.41
A6: （三） | B6: 办公室一 | C6: =不含空调消防清单!G14 -> 75493.417
A7: （四） | B7: 办公室二 | C7: =不含空调消防清单!G32 -> 55916.234
A8: （五） | B8: 办公室三 | C8: =不含空调消防清单!G50 -> 48771.897
A9: （六） | B9: 办公室四 | C9: =不含空调消防清单!G68 -> 39052.824
A10: （七） | B10: 办公室五 | C10: =不含空调消防清单!G86 -> 41796.512
A11: （八） | B11: 办公室六 | C11: =不含空调消防清单!G104 -> 102911.5
A12: （九） | B12: 办公室七 | C12: =不含空调消防清单!G123 -> 45389.108
A13: （十） | B13: 办公室八 | C13: =不含空调消防清单!G141 -> 49753.722
A14: 二 | B14: 安装工程 | C14: =不含空调消防清单!G159 -> 205172.92
A15: （一） | B15: 办公室一安装工程 | C15: =不含空调消防清单!G160 -> 32647
A16: （二） | B16: 办公室二安装工程 | C16: =不含空调消防清单!G175 -> 24303.417
A17: （三） | B17: 办公室三安装工程 | C17: =不含空调消防清单!G190 -> 22195.167
A18: （四） | B18: 办公室四安装工程 | C18: =不含空调消防清单!G205 -> 18135.167
A19: （五） | B19: 办公室五安装工程 | C19: =不含空调消防清单!G220 -> 21797.667
A20: （六） | B20: 办公室六安装工程 | C20: =不含空调消防清单!G235 -> 45150.667
A21: （七） | B21: 办公室七安装工程 | C21: =不含空调消防清单!G250 -> 20399.417
A22: （八） | B22: 办公室八安装工程 | C22: =不含空调消防清单!G265 -> 20544.417
A23: 三 | B23: 其他工程 | C23: =不含空调消防清单!G280 -> 187720.02
A24: 四 | B24: 小计：一+二+三 | C24: =C3+C14+C23 -> 1046875.6 | D24: 864.74 | E24: =C24/D24 -> 1210.6247 | G24: 含消防空调成本总价 | H24: 255733.89 | I24: =C24+'报价汇总-空调消防'!C13 -> 1490105.9
A25: 五 | B25: 管理费 | C25: =不含空调消防清单!G290 -> 52343.778 | G25: 含消防空调单方造价 | H25: =H24/D24 -> 295.735 | I25: =I24/D24 -> 1723.1837
A26: 六 | B26: 税金 | C26: =不含空调消防清单!G291 -> 32976.58
A27: 七 | B27: 合计=四+五+六 | C27: =C24+C25+C26 -> 1132195.9 | D27: 864.74 | E27: =C27/D27 -> 1309.2906
A28: 八 | B28: 施工图、效果图设计费 | C28: 0
A29: 九 | B29: 总计:七+八 | C29: =C28+C27 -> 1132195.9 | D29: 864.74 | E29: =C29/D29 -> 1309.2906 | G29: =C29+'报价汇总-空调消防'!C16 -> 1611549.5 | H29: =H24*1.43 -> 365699.46
B31: 空调消防工程 | C31: ='报价汇总-空调消防'!C16 -> 479353.57
B32: 总计 | C32: =C29+C31 -> 1611549.5
B34: 装饰成本 | C34: =1011875.56878667+30000 -> 1041875.6 | E34: =C24 -> 1046875.6 | F34: =E34-C34 -> 5000
B35: 空调成本 | C35: ='报价汇总-空调消防'!G3 -> 252000 | E35: ='报价汇总-空调消防'!C3 -> 319500 | F35: =E35-C35 -> 67500
B36: 消防成本 | C36: ='报价汇总-空调消防'!G12 -> 88645.8 | E36: ='报价汇总-空调消防'!C12 -> 123730.3 | F36: =E36-C36 -> 35084.5
C37: =SUM(C34:C36) -> 1382521.4 | E37: =SUM(E34:E36) -> 1490105.9 | F37: =E37-C37 -> 107584.5
B38: 管理费 | C38: 0 | E38: =E37*0.05 -> 74505.293
B39: 直接费 | C39: =SUM(C37:C38) -> 1382521.4 | E39: =SUM(E37:E38) -> 1564611.2
B40: 税金 | C40: =C39*0.03 -> 41475.641 | E40: =E39*0.03 -> 46938.335
B41: 含税合计 | C41: =C39+C40 -> 1423997 | E41: =E39+E40 -> 1611549.5 | F41: =(E41-C41)/C41 -> 0.13170848

Sheet 不含空调消防清单
A1: D座塔楼办公室3903-04-05-06装饰工程- （不含空调消防） | I1: =G292 -> 1132195.9 | Q1: 1 | S1: =$Q$1 -> 1 | T1: =$Q$1 -> 1 | U1: =$Q$1 -> 1 | V1: ='报价汇总-装修工程'!G29 -> 1611549.5 | W1: =18.84+18.31+39.39+16.39+7.1+10.25+8.68+2.78 -> 121.74
A2: 序号 | B2: 项目名称 | C2: 项目特征 | D2: 单位 | E2: 工程量 | F2: 综合单价（不含税） | G2: 合价 | H2: 备注 | I2: 综合单价（不含税） | J2: 主材费 | K2: 主材损耗率 | L2: 人工费 | M2: 辅材费 | N2: 机械费 | O2: 合计 | P2: 成本价 | Q2: 主材费 | R2: 主材损耗率 | S2: 人工费 | T2: 辅材费 | U2: 机械费
A3: 一 | B3: 装饰工程 | G3: =SUBTOTAL(9,G4:G158) -> 653982.63
A4: （一） | B4: 拆除工程 | G4: =SUBTOTAL(9,G5:G7) -> 22177.008
A5: 1 | B5: 拆除原有砖墙 （150mm厚） | C5: 1、人工拆除 2、机械设备 3、防护措施 4、垃圾清理装袋 | D5: ㎡ | E5: =3.81*(4.3+2.4+10.08+9.93)-1.5*2.2+1.5*2.2*3 -> 108.3651 | F5: =I5 -> 141.9 | G5: =F5*E5 -> 15377.008 | I5: =J5+J5*K5+L5+M5+N5 -> 141.9 | J5: =Q5*$Q$1 -> 40 | K5: =R5 -> 0.01 | L5: =S5*$S$1 -> 70 | M5: =T5*$T$1 -> 30 | N5: =U5*$U$1 -> 1.5 | O5: =E5*I5 -> 15377.008 | P5: =Q5*(1+R5)+S5+T5+U5 -> 141.9 | Q5: =10*4 -> 40 | R5: 0.01 | S5: 70 | T5: 30 | U5: 1.5
A6: 2 | B6: 原墙面开门洞后加固 （1500*2200） | C6: 1、横梁槽钢加固 2、门洞侧边水泥砂浆修补 3、12mm阻燃版封边 | D6: 樘 | E6: 3 | F6: =I6 -> 1500 | G6: =F6*E6 -> 4500 | I6: =J6+J6*K6+L6+M6+N6 -> 1500 | J6: =Q6*$Q$1 -> 1000 | K6: =R6 -> 0 | L6: =S6*$S$1 -> 500 | M6: =T6*$T$1 -> 0 | N6: =U6*$U$1 -> 0 | O6: =E6*I6 -> 4500 | P6: =Q6*(1+R6)+S6+T6+U6 -> 1500 | Q6: 1000 | S6: 500
A7: 3 | B7: 原墙面开门洞后加固 （4300*2200） | C7: 1、横梁槽钢加固 2、门洞侧边水泥砂浆修补 3、12mm阻燃版封边 | D7: 樘 | E7: 1 | F7: =I7 -> 2300 | G7: =F7*E7 -> 2300 | I7: =J7+J7*K7+L7+M7+N7 -> 2300 | J7: =Q7*$Q$1 -> 1500 | K7: =R7 -> 0 | L7: =S7*$S$1 -> 800 | M7: =T7*$T$1 -> 0 | N7: =U7*$U$1 -> 0 | O7: =E7*I7 -> 2300 | P7: =Q7*(1+R7)+S7+T7+U7 -> 2300 | Q7: 1500 | S7: 800
A8: （二） | B8: 隔墙工程 | G8: =SUBTOTAL(9,G9:G13) -> 172720.41
A9: 1 | B9: 轻钢龙骨隔墙 | C9: 双层双面轻钢龙骨隔墙 1、墙厚120mm; 2、75mm轻钢龙骨； 3、50mm厚，48kg/m3的吸音棉； 4、9.5mm厚石膏板 | D9: ㎡ | E9: =3.81*(3.71+3.38*3+0.83+1.63+3+12.8+3.19*3+12.26+2.8+3.19*2+10.08+3.8+3.08+11.16+3.52+3.21+0.1+0.25+0.4+0.43+0.23+4.22+4.15+4.19+0.44+0.3+2.81+0.55+0.52+4.3+2.75+9.93+0.55+1.56+2.8+3*2+11.88+0.44+1.56+2.8+2.74*2+0.55+0.33+0.8+0.8)+1.31*(1.8+1.7+1.2+1.6+1.6+2.18+1.67+1.2+1.2) -> 662.7694 | F9: =I9 -> 135.95 | G9: =F9*E9 -> 90103.5 | I9: =J9+J9*K9+L9+M9+N9 -> 135.95 | J9: =Q9*$Q$1 -> 30 | K9: =R9 -> 0.01 | L9: =S9*$S$1 -> 70 | M9: =T9*$T$1 -> 34.15 | N9: =U9*$U$1 -> 1.5 | O9: =E9*I9 -> 90103.5 | P9: =Q9*(1+R9)+S9+T9+U9 -> 135.95 | Q9: =7.5*4 -> 30 | R9: 0.01 | S9: 70 | T9: =22.5+11.65 -> 34.15 | U9: 1.5
A10: 2 | B10: 新建轻质砖墙 （150mm厚） | C10: 1、成品砂浆、15#轻质砖 2、完成面150mm厚 | D10: ㎡ | E10: =1.5*2.2*3+3.81*(6.76+2.28)-1.5*2.2 -> 41.0424 | F10: =I10 -> 98.4 | G10: =F10*E10 -> 4038.5722 | I10: =J10+J10*K10+L10+M10+N10 -> 98.4 | J10: =Q10*$Q$1 -> 42.9 | K10: =R10 -> 0 | L10: =S10*$S$1 -> 45 | M10: =T10*$T$1 -> 10 | N10: =U10*$U$1 -> 0.5 | O10: =E10*I10 -> 4038.5722 | P10: =Q10*(1+R10)+S10+T10+U10 -> 98.4 | Q10: =286*0.15 -> 42.9 | R10: 0 | S10: 45 | T10: 10 | U10: 0.5
A11: 3 | B11: 内墙水泥砂浆抹灰 | C11: 1、基层墙体：砌体墙、混凝土墙 2、厚度：20mm 3、做法：墙面基层清理，不同界面交接处、阴角转角处、管线开槽处，挂镀锌电焊网，公区人流通道等局部砌体墙满挂镀锌电焊网，面层压入1道耐碱网格布，水泥砂浆找平、压实抹光； | D11: ㎡ | E11: =E10*2 -> 82.0848 | F11: =I11 -> 38.5 | G11: =F11*E11 -> 3160.2648 | I11: =J11+J11*K11+L11+M11+N11 -> 38.5 | J11: =Q11*$Q$1 -> 0 | K11: =R11 -> 0.01 | L11: =S11*$S$1 -> 30 | M11: =T11*$T$1 -> 8.5 | N11: =U11*$U$1 -> 0 | O11: =E11*I11 -> 3160.2648 | P11: =Q11*(1+R11)+S11+T11+U11 -> 38.5 | R11: 0.01 | S11: 30 | T11: 8.5
A12: 4 | B12: GL-01 中空钢化玻璃隔断（含免漆板隔断） | C12: 1、GL-01 5+5mm钢化玻璃; 2、铝框包边 3、五金配件等制作安装 | D12: ㎡ | E12: =2.8*(1.88+10.25+10.65+1.25+9.13+8.85+6.55+1.86+7.12+2.85+1+9.18+1+7.23+0.91)-0.9*2.4*25 -> 169.188 | F12: =I12 -> 328.5 | G12: =F12*E12 -> 55578.258 | I12: =J12+J12*K12+L12+M12+N12 -> 328.5 | J12: =Q12*$Q$1 -> 300 | K12: =R12 -> 0.01 | L12: =S12*$S$1 -> 15 | M12: =T12*$T$1 -> 10.5 | N12: =U12*$U$1 -> 0 | O12: =E12*I12 -> 55578.258 | P12: =Q12*(1+R12)+S12+T12+U12 -> 328.5 | Q12: 300 | R12: 0.01 | S12: 15 | T12: 10.5
A13: 5 | B13: 玻璃隔断上方封板 | C13: 双层双面钢结构龙骨隔墙 1、墙厚100mm; 2、钢结构龙骨； 3、50mm厚，48kg/m3的吸音棉； 4、12mm厚阻燃夹板+9.5mm厚石膏板 | D13: ㎡ | E13: =1.31*(1.88+10.25+10.65+1.25+9.13+8.85+6.55+1.86+7.12+2.85+1+9.18+1+7.23+0.91) -> 104.4201 | F13: =I13 -> 190 | G13: =F13*E13 -> 19839.819 | I13: =J13+J13*K13+L13+M13+N13 -> 190 | J13: =Q13*$Q$1 -> 85 | K13: =R13 -> 0.01 | L13: =S13*$S$1 -> 70 | M13: =T13*$T$1 -> 34.15 | N13: =U13*$U$1 -> 0 | O13: =E13*I13 -> 19839.819 | P13: =Q13*(1+R13)+S13+T13+U13 -> 190 | Q13: =35*2+7.5*2 -> 85 | R13: 0.01 | S13: 70 | T13: =22.5+11.65 -> 34.15
A14: （三） | B14: 办公室一 | G14: =SUBTOTAL(9,G15:G31) -> 75493.417
A15: 1 | B15: 地面架空层 | C15: 1、100mm高 2、500*500mm架空地板 | D15: ㎡ | E15: =19.02+9.71+9.38+25.69+16.52+53.48-2.25 -> 131.55 | F15: =I15 -> 126.25 | G15: =F15*E15 -> 16608.188 | I15: =J15+J15*K15+L15+M15+N15 -> 126.25 | J15: =Q15*$Q$1 -> 125 | K15: =R15 -> 0.01 | L15: =S15*$S$1 -> 0 | M15: =T15*$T$1 -> 0 | N15: =U15*$U$1 -> 0 | O15: =E15*I15 -> 16608.188 | P15: =Q15*(1+R15)+S15+T15+U15 -> 126.25 | Q15: 125 | R15: 0.01 | U15: 0
A16: 2 | B16: 地面地毯 | C16: 1、规格尺寸：500*500 2、地毯专用胶，厚度包干，后期不因厚度调整价格； | D16: ㎡ | E16: =E15 -> 131.55 | F16: =I16 -> 71.5 | G16: =F16*E16 -> 9405.825 | I16: =J16+J16*K16+L16+M16+N16 -> 71.5 | J16: =Q16*$Q$1 -> 60 | K16: =R16 -> 0.025 | L16: =S16*$S$1 -> 5 | M16: =T16*$T$1 -> 5 | N16: =U16*$U$1 -> 0 | O16: =E16*I16 -> 9405.825 | P16: =Q16*(1+R16)+S16+T16+U16 -> 71.5 | Q16: 60 | R16: 0.025 | S16: 5 | T16: 5 | U16: 0
A17: 3 | B17: 原天棚喷乳胶漆PT-02 (含墙体上部) | C17: 1、面层：PT-02深色涂料两遍 2、包含各种管道 | D17: ㎡ | E17: =53.48+33.9*1.31 -> 97.889 | F17: =I17 -> 20.08 | G17: =F17*E17 -> 1965.6111 | I17: =J17+J17*K17+L17+M17+N17 -> 20.08 | J17: =Q17*$Q$1 -> 8 | K17: =R17 -> 0.01 | L17: =S17*$S$1 -> 10 | M17: =T17*$T$1 -> 0.5 | N17: =U17*$U$1 -> 1.5 | O17: =E17*I17 -> 1965.6111 | P17: =Q17*(1+R17)+S17+T17+U17 -> 20.08 | Q17: 8 | R17: 0.01 | S17: 10 | T17: 0.5 | U17: 1.5
A18: 4 | B18: 石膏板天花吊顶 | C18: 1、吊顶形式：平级+跌级吊顶 2、基层：轻钢龙骨+双层9.5mm厚石膏板 | D18: ㎡ | E18: =19.02+9.71+9.38+25.69+16.52-2.25 -> 78.07 | F18: =I18 -> 144.18 | G18: =F18*E18 -> 11256.133 | I18: =J18+J18*K18+L18+M18+N18 -> 144.18 | J18: =Q18*$Q$1 -> 18 | K18: =R18 -> 0.01 | L18: =S18*$S$1 -> 100 | M18: =T18*$T$1 -> 26 | N18: =U18*$U$1 -> 0 | O18: =E18*I18 -> 11256.133 | P18: =Q18*(1+R18)+S18+T18+U18 -> 144.18 | Q18: 18 | R18: 0.01 | S18: 100 | T18: 26
A19: 5 | B19: 天花板缝贴纸带刮平整 | C19: 1、螺丝钉刷防锈漆 2、缝贴纸带刮平整 | D19: ㎡ | E19: =$E$18 -> 78.07 | F19: =I19 -> 8.5 | G19: =F19*E19 -> 663.595 | I19: =J19+J19*K19+L19+M19+N19 -> 8.5 | J19: =Q19*$Q$1 -> 3.5 | K19: =R19 -> 0 | L19: =S19*$S$1 -> 5 | M19: =T19*$T$1 -> 0 | N19: =U19*$U$1 -> 0 | O19: =E19*I19 -> 663.595 | P19: =Q19*(1+R19)+S19+T19+U19 -> 8.5 | Q19: 3.5 | R19: 0 | S19: 5 | T19: 0 | U19: 0
A20: 6 | B20: 天花挂耐水腻子 | C20: 1、耐水腻子2道，含打磨、修补 | D20: ㎡ | E20: =$E$18 -> 78.07 | F20: =I20 -> 23.5 | G20: =F20*E20 -> 1834.645 | I20: =J20+J20*K20+L20+M20+N20 -> 23.5 | J20: =Q20*$Q$1 -> 3.5 | K20: =R20 -> 0 | L20: =S20*$S$1 -> 20 | M20: =T20*$T$1 -> 0 | N20: =U20*$U$1 -> 0 | O20: =E20*I20 -> 1834.645 | P20: =Q20*(1+R20)+S20+T20+U20 -> 23.5 | Q20: 3.5 | R20: 0 | S20: 20 | T20: 0 | U20: 0
A21: 7 | B21: 天棚乳胶漆 | C21: 1、面层：PT-01无机白色涂料一底二面 | D21: ㎡ | E21: =$E$18 -> 78.07 | F21: =I21 -> 13 | G21: =F21*E21 -> 1014.91 | I21: =J21+J21*K21+L21+M21+N21 -> 13 | J21: =Q21*$Q$1 -> 3 | K21: =R21 -> 0 | L21: =S21*$S$1 -> 10 | M21: =T21*$T$1 -> 0 | N21: =U21*$U$1 -> 0 | O21: =E21*I21 -> 1014.91 | P21: =Q21*(1+R21)+S21+T21+U21 -> 13 | Q21: 3 | R21: 0 | S21: 10 | T21: 0 | U21: 0
A22: 8 | B22: 窗帘盒 | C22: 1、基层：钢结构龙骨+阻燃板基层 2、面层：9.5mm厚石膏板 | D22: m | E22: =3.48+2.63+2.53+7+3.28+4.9 -> 23.82 | F22: =I22 -> 195.17 | G22: =F22*E22 -> 4648.9494 | I22: =J22+J22*K22+L22+M22+N22 -> 195.17 | J22: =Q22*$Q$1 -> 131.67 | K22: =R22 -> 0 | L22: =S22*$S$1 -> 55 | M22: =T22*$T$1 -> 8.5 | N22: =U22*$U$1 -> 0 | O22: =E22*I22 -> 4648.9494 | P22: =Q22*(1+R22)+S22+T22+U22 -> 195.17 | Q22: =4.2*5.7*5.5 -> 131.67 | S22: 55 | T22: 8.5
A23: 9 | B23: 窗帘 | C23: 1、成品窗帘 | D23: ㎡ | E23: =(3.48+2.63+2.53+7+3.28+4.9)*2.8 -> 66.696 | F23: =I23 -> 75 | G23: =F23*E23 -> 5002.2 | I23: =J23+J23*K23+L23+M23+N23 -> 75 | J23: =Q23*$Q$1 -> 68 | K23: =R23 -> 0 | L23: =S23*$S$1 -> 5 | M23: =T23*$T$1 -> 1.5 | N23: =U23*$U$1 -> 0.5 | O23: =E23*I23 -> 5002.2 | P23: =Q23*(1+R23)+S23+T23+U23 -> 75 | Q23: 68 | S23: 5 | T23: 1.5 | U23: 0.5
A24: 10 | B24: 墙面缝贴纸带刮平整 | C24: 1、螺丝钉刷防锈漆 2、缝贴纸带刮平整 | D24: ㎡ | E24: =2.8*(5.3+0.625*2+3.59+3.41*4+3.69*2+0.83*2+6+1.63+2.95+3.71+3+5.51+0.1+3+9.58)-1.5*2.2 -> 187.94 | F24: =I24 -> 8.5 | G24: =F24*E24 -> 1597.49 | I24: =J24+J24*K24+L24+M24+N24 -> 8.5 | J24: =Q24*$Q$1 -> 3.5 | K24: =R24 -> 0 | L24: =S24*$S$1 -> 5 | M24: =T24*$T$1 -> 0 | N24: =U24*$U$1 -> 0 | O24: =E24*I24 -> 1597.49 | P24: =Q24*(1+R24)+S24+T24+U24 -> 8.5 | Q24: =Q19 -> 3.5 | R24: =R19 -> 0 | S24: =S19 -> 5 | T24: =T19 -> 0 | U24: 0
A25: 11 | B25: 墙面挂耐水腻子 | C25: 耐水腻子2道，含打磨、修补 | D25: ㎡ | E25: =E24 -> 187.94 | F25: =I25 -> 23.5 | G25: =F25*E25 -> 4416.59 | I25: =J25+J25*K25+L25+M25+N25 -> 23.5 | J25: =Q25*$Q$1 -> 3.5 | K25: =R25 -> 0 | L25: =S25*$S$1 -> 20 | M25: =T25*$T$1 -> 0 | N25: =U25*$U$1 -> 0 | O25: =E25*I25 -> 4416.59 | P25: =Q25*(1+R25)+S25+T25+U25 -> 23.5 | Q25: =Q20 -> 3.5 | R25: =R20 -> 0 | S25: =S20 -> 20 | T25: =T20 -> 0 | U25: 0
A26: 12 | B26: 墙面乳胶漆PT-01 | C26: 1、面层：PT-01无机白色涂料一底二面 | D26: ㎡ | E26: =E24-10.39 -> 177.55 | F26: =I26 -> 13 | G26: =F26*E26 -> 2308.15 | I26: =J26+J26*K26+L26+M26+N26 -> 13 | J26: =Q26*$Q$1 -> 3 | K26: =R26 -> 0 | L26: =S26*$S$1 -> 10 | M26: =T26*$T$1 -> 0 | N26: =U26*$U$1 -> 0 | O26: =E26*I26 -> 2308.15 | P26: =Q26*(1+R26)+S26+T26+U26 -> 13 | Q26: =Q21 -> 3 | R26: =R21 -> 0 | S26: =S21 -> 10 | T26: =T21 -> 0 | U26: 0
A27: 13 | B27: 墙面艺术涂料 | C27: 1、面层：艺术涂料一底二面 | D27: ㎡ | E27: =2.8*3.71 -> 10.388 | F27: =I27 -> 120.85 | G27: =F27*E27 -> 1255.3898 | I27: =J27+J27*K27+L27+M27+N27 -> 120.85 | J27: =Q27*$Q$1 -> 85 | K27: =R27 -> 0.01 | L27: =S27*$S$1 -> 35 | M27: =T27*$T$1 -> 0 | N27: =U27*$U$1 -> 0 | O27: =E27*I27 -> 1255.3898 | P27: =Q27*(1+R27)+S27+T27+U27 -> 120.85 | Q27: 85 | R27: 0.01 | S27: 35 | T27: 0 | U27: 0
A28: 14 | B28: MT-01 1.2mm厚不锈钢踢脚线 | C28: 1、规格尺寸：50mm高 2、面层：MT-01 1.2mm厚不锈钢 3、基层：轻钢龙骨+12mm厚阻燃夹板 | D28: m | E28: =5.3+0.625*2+3.59+3.41*4+3.69*2+0.83*2+6+1.63+2.95+3.71+3+5.51+0.1+3+9.58-1.5 -> 66.8 | F28: =I28 -> 42.062 | G28: =F28*E28 -> 2809.7416 | I28: =J28+J28*K28+L28+M28+N28 -> 42.062 | J28: =Q28*$Q$1 -> 23.1 | K28: =R28 -> 0.02 | L28: =S28*$S$1 -> 15 | M28: =T28*$T$1 -> 3.5 | N28: =U28*$U$1 -> 0 | O28: =E28*I28 -> 2809.7416 | P28: =Q28*(1+R28)+S28+T28+U28 -> 42.062 | Q28: =0.06*360+1.5 -> 23.1 | R28: 0.02 | S28: 15 | T28: 3.5
A29: 15 | B29: 门禁系统安装 | C29: 1、门洞尺寸：1500*2200mm 2、包含设备、管线、调试等 | D29: 项 | E29: 1 | F29: =I29 -> 2050 | G29: =F29*E29 -> 2050 | I29: =J29+J29*K29+L29+M29+N29 -> 2050 | J29: =Q29*$Q$1 -> 1200 | K29: =R29 -> 0 | L29: =S29*$S$1 -> 800 | M29: =T29*$T$1 -> 50 | N29: =U29*$U$1 -> 0 | O29: =E29*I29 -> 2050 | P29: =Q29*(1+R29)+S29+T29+U29 -> 2050 | Q29: 1200 | S29: 800 | T29: 50
A30: 16 | B30: 隔断免漆板单开门 | C30: 1、免漆板单开门 2、门洞尺寸：800mm*2400mm 4、含门锁.五金等制作安装 | D30: 樘 | E30: 4 | F30: =I30 -> 1800 | G30: =F30*E30 -> 7200 | I30: =J30+J30*K30+L30+M30+N30 -> 1800 | J30: =Q30*$Q$1 -> 1620 | K30: =R30 -> 0 | L30: =S30*$S$1 -> 180 | M30: =T30*$T$1 -> 0 | N30: =U30*$U$1 -> 0 | O30: =E30*I30 -> 7200 | P30: =Q30*(1+R30)+S30+T30+U30 -> 1800 | Q30: =750*0.9*2.4 -> 1620 | S30: 180
A31: 17 | B31: 玻璃双开门 （无框） | C31: 1、10mm厚钢化玻璃门 2、门洞尺寸：1500mm*2200mm 4、含门锁.不锈钢扶手五金等制作安装 | D31: 樘 | E31: 1 | F31: =I31 -> 1456 | G31: =F31*E31 -> 1456 | I31: =J31+J31*K31+L31+M31+N31 -> 1456 | J31: =Q31*$Q$1 -> 396 | K31: =R31 -> 0 | L31: =S31*$S$1 -> 360 | M31: =T31*$T$1 -> 700 | N31: =U31*$U$1 -> 0 | O31: =E31*I31 -> 1456 | P31: =Q31*(1+R31)+S31+T31+U31 -> 1456 | Q31: =120*1.5*2.2 -> 396 | S31: =180*2 -> 360 | T31: =350*2 -> 700
A32: （四） | B32: 办公室二 | G32: =SUBTOTAL(9,G33:G49) -> 55916.234
A33: 1 | B33: 地面架空层 | C33: 1、100mm高 2、500*500mm架空地板 | D33: ㎡ | E33: =14.88+5.92+7.67+11.08+16+47.63-2.56 -> 100.62 | F33: =I33 -> 126.25 | G33: =F33*E33 -> 12703.275 | I33: =J33+J33*K33+L33+M33+N33 -> 126.25 | J33: =Q33*$Q$1 -> 125 | K33: =R33 -> 0.01 | L33: =S33*$S$1 -> 0 | M33: =T33*$T$1 -> 0 | N33: =U33*$U$1 -> 0 | O33: =E33*I33 -> 12703.275 | P33: =Q33*(1+R33)+S33+T33+U33 -> 126.25 | Q33: =$Q$15 -> 125 | R33: =$R$15 -> 0.01 | S33: =$S$15 -> 0 | T33: =$T$15 -> 0 | U33: =$U$15 -> 0
A34: 2 | B34: 地面地毯 | C34: 1、规格尺寸：500*500 2、地毯专用胶，厚度包干，后期不因厚度调整价格； | D34: ㎡ | E34: =E33 -> 100.62 | F34: =I34 -> 71.5 | G34: =F34*E34 -> 7194.33 | I34: =J34+J34*K34+L34+M34+N34 -> 71.5 | J34: =Q34*$Q$1 -> 60 | K34: =R34 -> 0.025 | L34: =S34*$S$1 -> 5 | M34: =T34*$T$1 -> 5 | N34: =U34*$U$1 -> 0 | O34: =E34*I34 -> 7194.33 | P34: =Q34*(1+R34)+S34+T34+U34 -> 71.5 | Q34: =$Q$16 -> 60 | R34: =$R$16 -> 0.025 | S34: =$S$16 -> 5 | T34: =$T$16 -> 5 | U34: =$U$16 -> 0
A35: 3 | B35: 原天棚喷乳胶漆PT-02 (含墙体上部) | C35: 1、面层：PT-02深色涂料两遍 2、包含各种管道 | D35: ㎡ | E35: =47.63-2.56+1.31*(33.02+6.4) -> 96.7102 | F35: =I35 -> 20.08 | G35: =F35*E35 -> 1941.9408 | I35: =J35+J35*K35+L35+M35+N35 -> 20.08 | J35: =Q35*$Q$1 -> 8 | K35: =R35 -> 0.01 | L35: =S35*$S$1 -> 10 | M35: =T35*$T$1 -> 0.5 | N35: =U35*$U$1 -> 1.5 | O35: =E35*I35 -> 1941.9408 | P35: =Q35*(1+R35)+S35+T35+U35 -> 20.08 | Q35: =$Q$17 -> 8 | R35: =$R$17 -> 0.01 | S35: =$S$17 -> 10 | T35: =$T$17 -> 0.5 | U35: =$U$17 -> 1.5
A36: 4 | B36: 石膏板天花吊顶 | C36: 1、吊顶形式：平级+跌级吊顶 2、基层：轻钢龙骨+双层9.5mm厚石膏板 | D36: ㎡ | E36: =14.88+5.92+7.67+11.08+16 -> 55.55 | F36: =I36 -> 144.18 | G36: =F36*E36 -> 8009.199 | I36: =J36+J36*K36+L36+M36+N36 -> 144.18 | J36: =Q36*$Q$1 -> 18 | K36: =R36 -> 0.01 | L36: =S36*$S$1 -> 100 | M36: =T36*$T$1 -> 26 | N36: =U36*$U$1 -> 0 | O36: =E36*I36 -> 8009.199 | P36: =Q36*(1+R36)+S36+T36+U36 -> 144.18 | Q36: =$Q$18 -> 18 | R36: =$R$18 -> 0.01 | S36: =$S$18 -> 100 | T36: =$T$18 -> 26 | U36: =$U$18 -> 0
A37: 5 | B37: 天花板缝贴纸带刮平整 | C37: 1、螺丝钉刷防锈漆 2、缝贴纸带刮平整 | D37: ㎡ | E37: =$E$36 -> 55.55 | F37: =I37 -> 8.5 | G37: =F37*E37 -> 472.175 | I37: =J37+J37*K37+L37+M37+N37 -> 8.5 | J37: =Q37*$Q$1 -> 3.5 | K37: =R37 -> 0 | L37: =S37*$S$1 -> 5 | M37: =T37*$T$1 -> 0 | N37: =U37*$U$1 -> 0 | O37: =E37*I37 -> 472.175 | P37: =Q37*(1+R37)+S37+T37+U37 -> 8.5 | Q37: =$Q$19 -> 3.5 | R37: =$R$19 -> 0 | S37: =$S$19 -> 5 | T37: =$T$19 -> 0 | U37: =$U$19 -> 0
A38: 6 | B38: 天花挂耐水腻子 | C38: 1、耐水腻子2道，含打磨、修补 | D38: ㎡ | E38: =$E$36 -> 55.55 | F38: =I38 -> 23.5 | G38: =F38*E38 -> 1305.425 | I38: =J38+J38*K38+L38+M38+N38 -> 23.5 | J38: =Q38*$Q$1 -> 3.5 | K38: =R38 -> 0 | L38: =S38*$S$1 -> 20 | M38: =T38*$T$1 -> 0 | N38: =U38*$U$1 -> 0 | O38: =E38*I38 -> 1305.425 | P38: =Q38*(1+R38)+S38+T38+U38 -> 23.5 | Q38: =$Q$20 -> 3.5 | R38: =$R$20 -> 0 | S38: =$S$20 -> 20 | T38: =$T$20 -> 0 | U38: =$U$20 -> 0
A39: 7 | B39: 天棚乳胶漆 | C39: 1、面层：PT-01无机白色涂料一底二面 | D39: ㎡ | E39: =$E$36 -> 55.55 | F39: =I39 -> 13 | G39: =F39*E39 -> 722.15 | I39: =J39+J39*K39+L39+M39+N39 -> 13 | J39: =Q39*$Q$1 -> 3 | K39: =R39 -> 0 | L39: =S39*$S$1 -> 10 | M39: =T39*$T$1 -> 0 | N39: =U39*$U$1 -> 0 | O39: =E39*I39 -> 722.15 | P39: =Q39*(1+R39)+S39+T39+U39 -> 13 | Q39: =$Q$21 -> 3 | R39: =$R$21 -> 0 | S39: =$S$21 -> 10 | T39: =$T$21 -> 0 | U39: =$U$21 -> 0
A40: 8 | B40: 窗帘盒 | C40: 1、基层：钢结构龙骨+阻燃板基层 2、面层：9.5mm厚石膏板 | D40: m | E40: 7.08 | F40: =I40 -> 195.17 | G40: =F40*E40 -> 1381.8036 | I40: =J40+J40*K40+L40+M40+N40 -> 195.17 | J40: =Q40*$Q$1 -> 131.67 | K40: =R40 -> 0 | L40: =S40*$S$1 -> 55 | M40: =T40*$T$1 -> 8.5 | N40: =U40*$U$1 -> 0 | O40: =E40*I40 -> 1381.8036 | P40: =Q40*(1+R40)+S40+T40+U40 -> 195.17 | Q40: =$Q$22 -> 131.67 | R40: =$R$22 -> 0 | S40: =$S$22 -> 55 | T40: =$T$22 -> 8.5 | U40: =$U$22 -> 0
A41: 9 | B41: 窗帘 | C41: 1、成品窗帘 | D41: ㎡ | E41: =(7.08)*2.8 -> 19.824 | F41: =I41 -> 75 | G41: =F41*E41 -> 1486.8 | I41: =J41+J41*K41+L41+M41+N41 -> 75 | J41: =Q41*$Q$1 -> 68 | K41: =R41 -> 0 | L41: =S41*$S$1 -> 5 | M41: =T41*$T$1 -> 1.5 | N41: =U41*$U$1 -> 0.5 | O41: =E41*I41 -> 1486.8 | P41: =Q41*(1+R41)+S41+T41+U41 -> 75 | Q41: =$Q$23 -> 68 | R41: =$R$23 -> 0 | S41: =$S$23 -> 5 | T41: =$T$23 -> 1.5 | U41: =$U$23 -> 0.5
A42: 10 | B42: 墙面缝贴纸带刮平整 | C42: 1、螺丝钉刷防锈漆 2、缝贴纸带刮平整 | D42: ㎡ | E42: =2.8*(6.76+2.25+6.76+7.02+12.8-0.12*3+3.29+3.19*5+6.4+12.26)-1.5*2.2*3 -> 194.864 | F42: =I42 -> 8.5 | G42: =F42*E42 -> 1656.344 | I42: =J42+J42*K42+L42+M42+N42 -> 8.5 | J42: =Q42*$Q$1 -> 3.5 | K42: =R42 -> 0 | L42: =S42*$S$1 -> 5 | M42: =T42*$T$1 -> 0 | N42: =U42*$U$1 -> 0 | O42: =E42*I42 -> 1656.344 | P42: =Q42*(1+R42)+S42+T42+U42 -> 8.5 | Q42: =$Q$24 -> 3.5 | R42: =$R$24 -> 0 | S42: =$S$24 -> 5 | T42: =$T$24 -> 0 | U42: =$U$24 -> 0
A43: 11 | B43: 墙面挂耐水腻子 | C43: 耐水腻子2道，含打磨、修补 | D43: ㎡ | E43: =E42 -> 194.864 | F43: =I43 -> 23.5 | G43: =F43*E43 -> 4579.304 | I43: =J43+J43*K43+L43+M43+N43 -> 23.5 | J43: =Q43*$Q$1 -> 3.5 | K43: =R43 -> 0 | L43: =S43*$S$1 -> 20 | M43: =T43*$T$1 -> 0 | N43: =U43*$U$1 -> 0 | O43: =E43*I43 -> 4579.304 | P43: =Q43*(1+R43)+S43+T43+U43 -> 23.5 | Q43: =$Q$25 -> 3.5 | R43: =$R$25 -> 0 | S43: =$S$25 -> 20 | T43: =$T$25 -> 0 | U43: =$U$25 -> 0
A44: 12 | B44: 墙面乳胶漆PT-01 | C44: 1、面层：PT-01无机白色涂料一底二面 | D44: ㎡ | E44: =E42-9.21 -> 185.654 | F44: =I44 -> 13 | G44: =F44*E44 -> 2413.502 | I44: =J44+J44*K44+L44+M44+N44 -> 13 | J44: =Q44*$Q$1 -> 3 | K44: =R44 -> 0 | L44: =S44*$S$1 -> 10 | M44: =T44*$T$1 -> 0 | N44: =U44*$U$1 -> 0 | O44: =E44*I44 -> 2413.502 | P44: =Q44*(1+R44)+S44+T44+U44 -> 13 | Q44: =$Q$26 -> 3 | R44: =$R$26 -> 0 | S44: =$S$26 -> 10 | T44: =$T$26 -> 0 | U44: =$U$26 -> 0
A45: 13 | B45: 墙面艺术涂料 | C45: 1、面层：PT-02艺术涂料一底二面 | D45: ㎡ | E45: =2.8*3.29 -> 9.212 | F45: =I45 -> 120.85 | G45: =F45*E45 -> 1113.2702 | I45: =J45+J45*K45+L45+M45+N45 -> 120.85 | J45: =Q45*$Q$1 -> 85 | K45: =R45 -> 0.01 | L45: =S45*$S$1 -> 35 | M45: =T45*$T$1 -> 0 | N45: =U45*$U$1 -> 0 | O45: =E45*I45 -> 1113.2702 | P45: =Q45*(1+R45)+S45+T45+U45 -> 120.85 | Q45: =$Q$27 -> 85 | R45: =$R$27 -> 0.01 | S45: =$S$27 -> 35 | T45: =$T$27 -> 0 | U45: =$U$27 -> 0
A46: 14 | B46: MT-01 1.2mm厚不锈钢踢脚线 | C46: 1、规格尺寸：50mm高 2、面层：MT-01 1.2mm厚不锈钢 3、基层：轻钢龙骨+12mm厚阻燃夹板 | D46: m | E46: =6.76+2.25+6.76+7.02+12.8-0.12*3+3.29+3.19*5+6.4+12.26-1.5*3 -> 68.63 | F46: =I46 -> 42.062 | G46: =F46*E46 -> 2886.7151 | I46: =J46+J46*K46+L46+M46+N46 -> 42.062 | J46: =Q46*$Q$1 -> 23.1 | K46: =R46 -> 0.02 | L46: =S46*$S$1 -> 15 | M46: =T46*$T$1 -> 3.5 | N46: =U46*$U$1 -> 0 | O46: =E46*I46 -> 2886.7151 | P46: =Q46*(1+R46)+S46+T46+U46 -> 42.062 | Q46: =$Q$28 -> 23.1 | R46: =$R$28 -> 0.02 | S46: =$S$28 -> 15 | T46: =$T$28 -> 3.5 | U46: =$U$28 -> 0
A47: 15 | B47: 门禁系统安装 | C47: 1、门洞尺寸：1500*2200mm 2、包含设备、管线、调试等 | D47: 项 | E47: 1 | F47: =I47 -> 2050 | G47: =F47*E47 -> 2050 | I47: =J47+J47*K47+L47+M47+N47 -> 2050 | J47: =Q47*$Q$1 -> 1200 | K47: =R47 -> 0 | L47: =S47*$S$1 -> 800 | M47: =T47*$T$1 -> 50 | N47: =U47*$U$1 -> 0 | O47: =E47*I47 -> 2050 | P47: =Q47*(1+R47)+S47+T47+U47 -> 2050 | Q47: =$Q$29 -> 1200 | R47: =$R$29 -> 0 | S47: =$S$29 -> 800 | T47: =$T$29 -> 50 | U47: =$U$29 -> 0
A48: 16 | B48: 隔断免漆板单开门 | C48: 1、免漆板单开门 2、门洞尺寸：900mm*2400mm 4、含门锁.五金等制作安装 | D48: 樘 | E48: 3 | F48: =I48 -> 1800 | G48: =F48*E48 -> 5400 | I48: =J48+J48*K48+L48+M48+N48 -> 1800 | J48: =Q48*$Q$1 -> 1620 | K48: =R48 -> 0 | L48: =S48*$S$1 -> 180 | M48: =T48*$T$1 -> 0 | N48: =U48*$U$1 -> 0 | O48: =E48*I48 -> 5400 | P48: =Q48*(1+R48)+S48+T48+U48 -> 1800 | Q48: =$Q$30 -> 1620 | R48: =$R$30 -> 0 | S48: =$S$30 -> 180 | T48: =$T$30 -> 0 | U48: =$U$30 -> 0
A49: 17 | B49: 原玻璃双开门拆除后安装 | C49: 1、原玻璃双开门拆除后安装 2、保护性拆除 | D49: 樘 | E49: 1 | F49: =I49 -> 600 | G49: =F49*E49 -> 600 | I49: =J49+J49*K49+L49+M49+N49 -> 600 | J49: =Q49*$Q$1 -> 0 | K49: =R49 -> 0 | L49: =S49*$S$1 -> 600 | M49: =T49*$T$1 -> 0 | N49: =U49*$U$1 -> 0 | O49: =E49*I49 -> 600 | P49: =Q49*(1+R49)+S49+T49+U49 -> 600 | S49: 600
A50: （五） | B50: 办公室三 | G50: =SUBTOTAL(9,G51:G67) -> 48771.897
A51: 1 | B51: 地面架空层 | C51: 1、100mm高 2、500*500mm架空地板 | D51: ㎡ | E51: =7.29+38.39+12.26+11.48+18.41 -> 87.83 | F51: =I51 -> 126.25 | G51: =F51*E51 -> 11088.538 | I51: =J51+J51*K51+L51+M51+N51 -> 126.25 | J51: =Q51*$Q$1 -> 125 | K51: =R51 -> 0.01 | L51: =S51*$S$1 -> 0 | M51: =T51*$T$1 -> 0 | N51: =U51*$U$1 -> 0 | O51: =E51*I51 -> 11088.538 | P51: =Q51*(1+R51)+S51+T51+U51 -> 126.25 | Q51: =$Q$15 -> 125 | R51: =$R$15 -> 0.01 | S51: =$S$15 -> 0 | T51: =$T$15 -> 0 | U51: =$U$15 -> 0
A52: 2 | B52: 地面地毯 | C52: 1、规格尺寸：500*500 2、地毯专用胶，厚度包干，后期不因厚度调整价格； | D52: ㎡ | E52: =E51 -> 87.83 | F52: =I52 -> 71.5 | G52: =F52*E52 -> 6279.845 | I52: =J52+J52*K52+L52+M52+N52 -> 71.5 | J52: =Q52*$Q$1 -> 60 | K52: =R52 -> 0.025 | L52: =S52*$S$1 -> 5 | M52: =T52*$T$1 -> 5 | N52: =U52*$U$1 -> 0 | O52: =E52*I52 -> 6279.845 | P52: =Q52*(1+R52)+S52+T52+U52 -> 71.5 | Q52: =$Q$16 -> 60 | R52: =$R$16 -> 0.025 | S52: =$S$16 -> 5 | T52: =$T$16 -> 5 | U52: =$U$16 -> 0
A53: 3 | B53: 原天棚喷乳胶漆PT-02 (含墙体上部) | C53: 1、面层：PT-02深色涂料两遍 2、包含各种管道 | D53: ㎡ | E53: =38.39+1.31*(27.17) -> 73.9827 | F53: =I53 -> 20.08 | G53: =F53*E53 -> 1485.5726 | I53: =J53+J53*K53+L53+M53+N53 -> 20.08 | J53: =Q53*$Q$1 -> 8 | K53: =R53 -> 0.01 | L53: =S53*$S$1 -> 10 | M53: =T53*$T$1 -> 0.5 | N53: =U53*$U$1 -> 1.5 | O53: =E53*I53 -> 1485.5726 | P53: =Q53*(1+R53)+S53+T53+U53 -> 20.08 | Q53: =$Q$17 -> 8 | R53: =$R$17 -> 0.01 | S53: =$S$17 -> 10 | T53: =$T$17 -> 0.5 | U53: =$U$17 -> 1.5
A54: 4 | B54: 石膏板天花吊顶 | C54: 1、吊顶形式：平级+跌级吊顶 2、基层：轻钢龙骨+双层9.5mm厚石膏板 | D54: ㎡ | E54: =7.29+12.26+11.48+18.41 -> 49.44 | F54: =I54 -> 144.18 | G54: =F54*E54 -> 7128.2592 | I54: =J54+J54*K54+L54+M54+N54 -> 144.18 | J54: =Q54*$Q$1 -> 18 | K54: =R54 -> 0.01 | L54: =S54*$S$1 -> 100 | M54: =T54*$T$1 -> 26 | N54: =U54*$U$1 -> 0 | O54: =E54*I54 -> 7128.2592 | P54: =Q54*(1+R54)+S54+T54+U54 -> 144.18 | Q54: =$Q$18 -> 18 | R54: =$R$18 -> 0.01 | S54: =$S$18 -> 100 | T54: =$T$18 -> 26 | U54: =$U$18 -> 0
A55: 5 | B55: 天花板缝贴纸带刮平整 | C55: 1、螺丝钉刷防锈漆 2、缝贴纸带刮平整 | D55: ㎡ | E55: =E54 -> 49.44 | F55: =I55 -> 8.5 | G55: =F55*E55 -> 420.24 | I55: =J55+J55*K55+L55+M55+N55 -> 8.5 | J55: =Q55*$Q$1 -> 3.5 | K55: =R55 -> 0 | L55: =S55*$S$1 -> 5 | M55: =T55*$T$1 -> 0 | N55: =U55*$U$1 -> 0 | O55: =E55*I55 -> 420.24 | P55: =Q55*(1+R55)+S55+T55+U55 -> 8.5 | Q55: =$Q$19 -> 3.5 | R55: =$R$19 -> 0 | S55: =$S$19 -> 5 | T55: =$T$19 -> 0 | U55: =$U$19 -> 0
A56: 6 | B56: 天花挂耐水腻子 | C56: 1、耐水腻子2道，含打磨、修补 | D56: ㎡ | E56: =E55 -> 49.44 | F56: =I56 -> 23.5 | G56: =F56*E56 -> 1161.84 | I56: =J56+J56*K56+L56+M56+N56 -> 23.5 | J56: =Q56*$Q$1 -> 3.5 | K56: =R56 -> 0 | L56: =S56*$S$1 -> 20 | M56: =T56*$T$1 -> 0 | N56: =U56*$U$1 -> 0 | O56: =E56*I56 -> 1161.84 | P56: =Q56*(1+R56)+S56+T56+U56 -> 23.5 | Q56: =$Q$20 -> 3.5 | R56: =$R$20 -> 0 | S56: =$S$20 -> 20 | T56: =$T$20 -> 0 | U56: =$U$20 -> 0
A57: 7 | B57: 天棚乳胶漆 | C57: 1、面层：PT-01无机白色涂料一底二面 | D57: ㎡ | E57: =E56 -> 49.44 | F57: =I57 -> 13 | G57: =F57*E57 -> 642.72 | I57: =J57+J57*K57+L57+M57+N57 -> 13 | J57: =Q57*$Q$1 -> 3 | K57: =R57 -> 0 | L57: =S57*$S$1 -> 10 | M57: =T57*$T$1 -> 0 | N57: =U57*$U$1 -> 0 | O57: =E57*I57 -> 642.72 | P57: =Q57*(1+R57)+S57+T57+U57 -> 13 | Q57: =$Q$21 -> 3 | R57: =$R$21 -> 0 | S57: =$S$21 -> 10 | T57: =$T$21 -> 0 | U57: =$U$21 -> 0
A58: 8 | B58: 窗帘盒 | C58: 1、基层：钢结构龙骨+阻燃板基层 2、面层：9.5mm厚石膏板 | D58: m | E58: =4.03+4.78 -> 8.81 | F58: =I58 -> 195.17 | G58: =F58*E58 -> 1719.4477 | I58: =J58+J58*K58+L58+M58+N58 -> 195.17 | J58: =Q58*$Q$1 -> 131.67 | K58: =R58 -> 0 | L58: =S58*$S$1 -> 55 | M58: =T58*$T$1 -> 8.5 | N58: =U58*$U$1 -> 0 | O58: =E58*I58 -> 1719.4477 | P58: =Q58*(1+R58)+S58+T58+U58 -> 195.17 | Q58: =$Q$22 -> 131.67 | R58: =$R$22 -> 0 | S58: =$S$22 -> 55 | T58: =$T$22 -> 8.5 | U58: =$U$22 -> 0
A59: 9 | B59: 窗帘 | C59: 1、成品窗帘 | D59: ㎡ | E59: =(4.03+4.78)*2.8 -> 24.668 | F59: =I59 -> 75 | G59: =F59*E59 -> 1850.1 | I59: =J59+J59*K59+L59+M59+N59 -> 75 | J59: =Q59*$Q$1 -> 68 | K59: =R59 -> 0 | L59: =S59*$S$1 -> 5 | M59: =T59*$T$1 -> 1.5 | N59: =U59*$U$1 -> 0.5 | O59: =E59*I59 -> 1850.1 | P59: =Q59*(1+R59)+S59+T59+U59 -> 75 | Q59: =$Q$23 -> 68 | R59: =$R$23 -> 0 | S59: =$S$23 -> 5 | T59: =$T$23 -> 1.5 | U59: =$U$23 -> 0.5
A60: 10 | B60: 墙面缝贴纸带刮平整 | C60: 1、螺丝钉刷防锈漆 2、缝贴纸带刮平整 | D60: ㎡ | E60: =2.8*(2.64+12.26-0.12+1.45*2+2.8+2.8+4.54+2.7+3.19*4+3.61+4.89+0.1)-1.5*2.2*1 -> 141.964 | F60: =I60 -> 8.5 | G60: =F60*E60 -> 1206.694 | I60: =J60+J60*K60+L60+M60+N60 -> 8.5 | J60: =Q60*$Q$1 -> 3.5 | K60: =R60 -> 0 | L60: =S60*$S$1 -> 5 | M60: =T60*$T$1 -> 0 | N60: =U60*$U$1 -> 0 | O60: =E60*I60 -> 1206.694 | P60: =Q60*(1+R60)+S60+T60+U60 -> 8.5 | Q60: =$Q$24 -> 3.5 | R60: =$R$24 -> 0 | S60: =$S$24 -> 5 | T60: =$T$24 -> 0 | U60: =$U$24 -> 0
A61: 11 | B61: 墙面挂耐水腻子 | C61: 耐水腻子2道，含打磨、修补 | D61: ㎡ | E61: =E60 -> 141.964 | F61: =I61 -> 23.5 | G61: =F61*E61 -> 3336.154 | I61: =J61+J61*K61+L61+M61+N61 -> 23.5 | J61: =Q61*$Q$1 -> 3.5 | K61: =R61 -> 0 | L61: =S61*$S$1 -> 20 | M61: =T61*$T$1 -> 0 | N61: =U61*$U$1 -> 0 | O61: =E61*I61 -> 3336.154 | P61: =Q61*(1+R61)+S61+T61+U61 -> 23.5 | Q61: =$Q$25 -> 3.5 | R61: =$R$25 -> 0 | S61: =$S$25 -> 20 | T61: =$T$25 -> 0 | U61: =$U$25 -> 0
A62: 12 | B62: 墙面乳胶漆PT-01 | C62: 1、面层：PT-01无机白色涂料一底二面 | D62: ㎡ | E62: =E60-4.06 -> 137.904 | F62: =I62 -> 13 | G62: =F62*E62 -> 1792.752 | I62: =J62+J62*K62+L62+M62+N62 -> 13 | J62: =Q62*$Q$1 -> 3 | K62: =R62 -> 0 | L62: =S62*$S$1 -> 10 | M62: =T62*$T$1 -> 0 | N62: =U62*$U$1 -> 0 | O62: =E62*I62 -> 1792.752 | P62: =Q62*(1+R62)+S62+T62+U62 -> 13 | Q62: =$Q$26 -> 3 | R62: =$R$26 -> 0 | S62: =$S$26 -> 10 | T62: =$T$26 -> 0 | U62: =$U$26 -> 0
A63: 13 | B63: 墙面艺术涂料 | C63: 1、面层：PT-02艺术涂料一底二面 | D63: ㎡ | E63: =2.8*1.45 -> 4.06 | F63: =I63 -> 120.85 | G63: =F63*E63 -> 490.651 | I63: =J63+J63*K63+L63+M63+N63 -> 120.85 | J63: =Q63*$Q$1 -> 85 | K63: =R63 -> 0.01 | L63: =S63*$S$1 -> 35 | M63: =T63*$T$1 -> 0 | N63: =U63*$U$1 -> 0 | O63: =E63*I63 -> 490.651 | P63: =Q63*(1+R63)+S63+T63+U63 -> 120.85 | Q63: =$Q$27 -> 85 | R63: =$R$27 -> 0.01 | S63: =$S$27 -> 35 | T63: =$T$27 -> 0 | U63: =$U$27 -> 0
A64: 14 | B64: MT-01 1.2mm厚不锈钢踢脚线 | C64: 1、规格尺寸：50mm高 2、面层：MT-01 1.2mm厚不锈钢 3、基层：轻钢龙骨+12mm厚阻燃夹板 | D64: m | E64: =2.64+12.26-0.12+1.45*2+2.8+2.8+4.54+2.7+3.19*4+3.61+4.89+0.1-1.5*1 -> 50.38 | F64: =I64 -> 42.062 | G64: =F64*E64 -> 2119.0836 | I64: =J64+J64*K64+L64+M64+N64 -> 42.062 | J64: =Q64*$Q$1 -> 23.1 | K64: =R64 -> 0.02 | L64: =S64*$S$1 -> 15 | M64: =T64*$T$1 -> 3.5 | N64: =U64*$U$1 -> 0 | O64: =E64*I64 -> 2119.0836 | P64: =Q64*(1+R64)+S64+T64+U64 -> 42.062 | Q64: =$Q$28 -> 23.1 | R64: =$R$28 -> 0.02 | S64: =$S$28 -> 15 | T64: =$T$28 -> 3.5 | U64: =$U$28 -> 0
A65: 15 | B65: 门禁系统安装 | C65: 1、门洞尺寸：1500*2200mm 2、包含设备、管线、调试等 | D65: 项 | E65: 1 | F65: =I65 -> 2050 | G65: =F65*E65 -> 2050 | I65: =J65+J65*K65+L65+M65+N65 -> 2050 | J65: =Q65*$Q$1 -> 1200 | K65: =R65 -> 0 | L65: =S65*$S$1 -> 800 | M65: =T65*$T$1 -> 50 | N65: =U65*$U$1 -> 0 | O65: =E65*I65 -> 2050 | P65: =Q65*(1+R65)+S65+T65+U65 -> 2050 | Q65: =$Q$29 -> 1200 | R65: =$R$29 -> 0 | S65: =$S$29 -> 800 | T65: =$T$29 -> 50 | U65: =$U$29 -> 0
A66: 16 | B66: 隔断免漆板单开门 | C66: 1、免漆板单开门 2、门洞尺寸：900mm*2400mm 4、含门锁.五金等制作安装 | D66: 樘 | E66: 3 | F66: =I66 -> 1800 | G66: =F66*E66 -> 5400 | I66: =J66+J66*K66+L66+M66+N66 -> 1800 | J66: =Q66*$Q$1 -> 1620 | K66: =R66 -> 0 | L66: =S66*$S$1 -> 180 | M66: =T66*$T$1 -> 0 | N66: =U66*$U$1 -> 0 | O66: =E66*I66 -> 5400 | P66: =Q66*(1+R66)+S66+T66+U66 -> 1800 | Q66: =$Q$30 -> 1620 | R66: =$R$30 -> 0 | S66: =$S$30 -> 180 | T66: =$T$30 -> 0 | U66: =$U$30 -> 0
A67: 17 | B67: 原玻璃双开门拆除后安装 | C67: 1、原玻璃双开门拆除后安装 2、保护性拆除 | D67: 樘 | E67: 1 | F67: =I67 -> 600 | G67: =F67*E67 -> 600 | I67: =J67+J67*K67+L67+M67+N67 -> 600 | J67: =Q67*$Q$1 -> 0 | K67: =R67 -> 0 | L67: =S67*$S$1 -> 600 | M67: =T67*$T$1 -> 0 | N67: =U67*$U$1 -> 0 | O67: =E67*I67 -> 600 | P67: =Q67*(1+R67)+S67+T67+U67 -> 600 | Q67: =$Q$49 -> 0 | R67: =$R$49 -> 0 | S67: =$S$49 -> 600 | T67: =$T$49 -> 0 | U67: =$U$49 -> 0
A68: （六） | B68: 办公室四 | G68: =SUBTOTAL(9,G69:G85) -> 39052.824
A69: 1 | B69: 地面架空层 | C69: 1、100mm高 2、500*500mm架空地板 | D69: ㎡ | E69: =7.66+9.92+15.03+42.39 -> 75 | F69: =I69 -> 126.25 | G69: =F69*E69 -> 9468.75 | I69: =J69+J69*K69+L69+M69+N69 -> 126.25 | J69: =Q69*$Q$1 -> 125 | K69: =R69 -> 0.01 | L69: =S69*$S$1 -> 0 | M69: =T69*$T$1 -> 0 | N69: =U69*$U$1 -> 0 | O69: =E69*I69 -> 9468.75 | P69: =Q69*(1+R69)+S69+T69+U69 -> 126.25 | Q69: =$Q$15 -> 125 | R69: =$R$15 -> 0.01 | S69: =$S$15 -> 0 | T69: =$T$15 -> 0 | U69: =$U$15 -> 0
A70: 2 | B70: 地面地毯 | C70: 1、规格尺寸：500*500 2、地毯专用胶，厚度包干，后期不因厚度调整价格； | D70: ㎡ | E70: =E69 -> 75 | F70: =I70 -> 71.5 | G70: =F70*E70 -> 5362.5 | I70: =J70+J70*K70+L70+M70+N70 -> 71.5 | J70: =Q70*$Q$1 -> 60 | K70: =R70 -> 0.025 | L70: =S70*$S$1 -> 5 | M70: =T70*$T$1 -> 5 | N70: =U70*$U$1 -> 0 | O70: =E70*I70 -> 5362.5 | P70: =Q70*(1+R70)+S70+T70+U70 -> 71.5 | Q70: =$Q$16 -> 60 | R70: =$R$16 -> 0.025 | S70: =$S$16 -> 5 | T70: =$T$16 -> 5 | U70: =$U$16 -> 0
A71: 3 | B71: 原天棚喷乳胶漆PT-02 (含墙体上部) | C71: 1、面层：PT-02深色涂料两遍 2、包含各种管道 | D71: ㎡ | E71: =42.39+1.31*(30.61) -> 82.4891 | F71: =I71 -> 20.08 | G71: =F71*E71 -> 1656.3811 | I71: =J71+J71*K71+L71+M71+N71 -> 20.08 | J71: =Q71*$Q$1 -> 8 | K71: =R71 -> 0.01 | L71: =S71*$S$1 -> 10 | M71: =T71*$T$1 -> 0.5 | N71: =U71*$U$1 -> 1.5 | O71: =E71*I71 -> 1656.3811 | P71: =Q71*(1+R71)+S71+T71+U71 -> 20.08 | Q71: =$Q$17 -> 8 | R71: =$R$17 -> 0.01 | S71: =$S$17 -> 10 | T71: =$T$17 -> 0.5 | U71: =$U$17 -> 1.5
A72: 4 | B72: 石膏板天花吊顶 | C72: 1、吊顶形式：平级+跌级吊顶 2、基层：轻钢龙骨+双层9.5mm厚石膏板 | D72: ㎡ | E72: =7.66+9.92+15.03 -> 32.61 | F72: =I72 -> 144.18 | G72: =F72*E72 -> 4701.7098 | I72: =J72+J72*K72+L72+M72+N72 -> 144.18 | J72: =Q72*$Q$1 -> 18 | K72: =R72 -> 0.01 | L72: =S72*$S$1 -> 100 | M72: =T72*$T$1 -> 26 | N72: =U72*$U$1 -> 0 | O72: =E72*I72 -> 4701.7098 | P72: =Q72*(1+R72)+S72+T72+U72 -> 144.18 | Q72: =$Q$18 -> 18 | R72: =$R$18 -> 0.01 | S72: =$S$18 -> 100 | T72: =$T$18 -> 26 | U72: =$U$18 -> 0
A73: 5 | B73: 天花板缝贴纸带刮平整 | C73: 1、螺丝钉刷防锈漆 2、缝贴纸带刮平整 | D73: ㎡ | E73: =E72 -> 32.61 | F73: =I73 -> 8.5 | G73: =F73*E73 -> 277.185 | I73: =J73+J73*K73+L73+M73+N73 -> 8.5 | J73: =Q73*$Q$1 -> 3.5 | K73: =R73 -> 0 | L73: =S73*$S$1 -> 5 | M73: =T73*$T$1 -> 0 | N73: =U73*$U$1 -> 0 | O73: =E73*I73 -> 277.185 | P73: =Q73*(1+R73)+S73+T73+U73 -> 8.5 | Q73: =$Q$19 -> 3.5 | R73: =$R$19 -> 0 | S73: =$S$19 -> 5 | T73: =$T$19 -> 0 | U73: =$U$19 -> 0
A74: 6 | B74: 天花挂耐水腻子 | C74: 1、耐水腻子2道，含打磨、修补 | D74: ㎡ | E74: =E73 -> 32.61 | F74: =I74 -> 23.5 | G74: =F74*E74 -> 766.335 | I74: =J74+J74*K74+L74+M74+N74 -> 23.5 | J74: =Q74*$Q$1 -> 3.5 | K74: =R74 -> 0 | L74: =S74*$S$1 -> 20 | M74: =T74*$T$1 -> 0 | N74: =U74*$U$1 -> 0 | O74: =E74*I74 -> 766.335 | P74: =Q74*(1+R74)+S74+T74+U74 -> 23.5 | Q74: =$Q$20 -> 3.5 | R74: =$R$20 -> 0 | S74: =$S$20 -> 20 | T74: =$T$20 -> 0 | U74: =$U$20 -> 0
A75: 7 | B75: 天棚乳胶漆 | C75: 1、面层：PT-01无机白色涂料一底二面 | D75: ㎡ | E75: =E74 -> 32.61 | F75: =I75 -> 13 | G75: =F75*E75 -> 423.93 | I75: =J75+J75*K75+L75+M75+N75 -> 13 | J75: =Q75*$Q$1 -> 3 | K75: =R75 -> 0 | L75: =S75*$S$1 -> 10 | M75: =T75*$T$1 -> 0 | N75: =U75*$U$1 -> 0 | O75: =E75*I75 -> 423.93 | P75: =Q75*(1+R75)+S75+T75+U75 -> 13 | Q75: =$Q$21 -> 3 | R75: =$R$21 -> 0 | S75: =$S$21 -> 10 | T75: =$T$21 -> 0 | U75: =$U$21 -> 0
A76: 8 | B76: 窗帘盒 | C76: 1、基层：钢结构龙骨+阻燃板基层 2、面层：9.5mm厚石膏板 | D76: m | E76: =1.67+3.49 -> 5.16 | F76: =I76 -> 195.17 | G76: =F76*E76 -> 1007.0772 | I76: =J76+J76*K76+L76+M76+N76 -> 195.17 | J76: =Q76*$Q$1 -> 131.67 | K76: =R76 -> 0 | L76: =S76*$S$1 -> 55 | M76: =T76*$T$1 -> 8.5 | N76: =U76*$U$1 -> 0 | O76: =E76*I76 -> 1007.0772 | P76: =Q76*(1+R76)+S76+T76+U76 -> 195.17 | Q76: =$Q$22 -> 131.67 | R76: =$R$22 -> 0 | S76: =$S$22 -> 55 | T76: =$T$22 -> 8.5 | U76: =$U$22 -> 0
A77: 9 | B77: 窗帘 | C77: 1、成品窗帘 | D77: ㎡ | E77: =(1.67+3.49)*2.8 -> 14.448 | F77: =I77 -> 75 | G77: =F77*E77 -> 1083.6 | I77: =J77+J77*K77+L77+M77+N77 -> 75 | J77: =Q77*$Q$1 -> 68 | K77: =R77 -> 0 | L77: =S77*$S$1 -> 5 | M77: =T77*$T$1 -> 1.5 | N77: =U77*$U$1 -> 0.5 | O77: =E77*I77 -> 1083.6 | P77: =Q77*(1+R77)+S77+T77+U77 -> 75 | Q77: =$Q$23 -> 68 | R77: =$R$23 -> 0 | S77: =$S$23 -> 5 | T77: =$T$23 -> 1.5 | U77: =$U$23 -> 0.5
A78: 10 | B78: 墙面缝贴纸带刮平整 | C78: 1、螺丝钉刷防锈漆 2、缝贴纸带刮平整 | D78: ㎡ | E78: =2.8*(6.8+10.08-0.12*2+3.2+3.08*3+1.6*2+11.16)-1.5*2.2*1 -> 118.332 | F78: =I78 -> 8.5 | G78: =F78*E78 -> 1005.822 | I78: =J78+J78*K78+L78+M78+N78 -> 8.5 | J78: =Q78*$Q$1 -> 3.5 | K78: =R78 -> 0 | L78: =S78*$S$1 -> 5 | M78: =T78*$T$1 -> 0 | N78: =U78*$U$1 -> 0 | O78: =E78*I78 -> 1005.822 | P78: =Q78*(1+R78)+S78+T78+U78 -> 8.5 | Q78: =$Q$24 -> 3.5 | R78: =$R$24 -> 0 | S78: =$S$24 -> 5 | T78: =$T$24 -> 0 | U78: =$U$24 -> 0
A79: 11 | B79: 墙面挂耐水腻子 | C79: 耐水腻子2道，含打磨、修补 | D79: ㎡ | E79: =E78 -> 118.332 | F79: =I79 -> 23.5 | G79: =F79*E79 -> 2780.802 | I79: =J79+J79*K79+L79+M79+N79 -> 23.5 | J79: =Q79*$Q$1 -> 3.5 | K79: =R79 -> 0 | L79: =S79*$S$1 -> 20 | M79: =T79*$T$1 -> 0 | N79: =U79*$U$1 -> 0 | O79: =E79*I79 -> 2780.802 | P79: =Q79*(1+R79)+S79+T79+U79 -> 23.5 | Q79: =$Q$25 -> 3.5 | R79: =$R$25 -> 0 | S79: =$S$25 -> 20 | T79: =$T$25 -> 0 | U79: =$U$25 -> 0
A80: 12 | B80: 墙面乳胶漆PT-01 | C80: 1、面层：PT-01无机白色涂料一底二面 | D80: ㎡ | E80: =E78-8.96 -> 109.372 | F80: =I80 -> 13 | G80: =F80*E80 -> 1421.836 | I80: =J80+J80*K80+L80+M80+N80 -> 13 | J80: =Q80*$Q$1 -> 3 | K80: =R80 -> 0 | L80: =S80*$S$1 -> 10 | M80: =T80*$T$1 -> 0 | N80: =U80*$U$1 -> 0 | O80: =E80*I80 -> 1421.836 | P80: =Q80*(1+R80)+S80+T80+U80 -> 13 | Q80: =$Q$26 -> 3 | R80: =$R$26 -> 0 | S80: =$S$26 -> 10 | T80: =$T$26 -> 0 | U80: =$U$26 -> 0
A81: 13 | B81: 墙面艺术涂料 | C81: 1、面层：PT-02艺术涂料一底二面 | D81: ㎡ | E81: =2.8*3.2 -> 8.96 | F81: =I81 -> 120.85 | G81: =F81*E81 -> 1082.816 | I81: =J81+J81*K81+L81+M81+N81 -> 120.85 | J81: =Q81*$Q$1 -> 85 | K81: =R81 -> 0.01 | L81: =S81*$S$1 -> 35 | M81: =T81*$T$1 -> 0 | N81: =U81*$U$1 -> 0 | O81: =E81*I81 -> 1082.816 | P81: =Q81*(1+R81)+S81+T81+U81 -> 120.85 | Q81: =$Q$27 -> 85 | R81: =$R$27 -> 0.01 | S81: =$S$27 -> 35 | T81: =$T$27 -> 0 | U81: =$U$27 -> 0
A82: 14 | B82: MT-01 1.2mm厚不锈钢踢脚线 | C82: 1、规格尺寸：50mm高 2、面层：MT-01 1.2mm厚不锈钢 3、基层：轻钢龙骨+12mm厚阻燃夹板 | D82: m | E82: =6.8+10.08-0.12*2+3.2+3.08*3+1.6*2+11.16-1.5*1 -> 41.94 | F82: =I82 -> 42.062 | G82: =F82*E82 -> 1764.0803 | I82: =J82+J82*K82+L82+M82+N82 -> 42.062 | J82: =Q82*$Q$1 -> 23.1 | K82: =R82 -> 0.02 | L82: =S82*$S$1 -> 15 | M82: =T82*$T$1 -> 3.5 | N82: =U82*$U$1 -> 0 | O82: =E82*I82 -> 1764.0803 | P82: =Q82*(1+R82)+S82+T82+U82 -> 42.062 | Q82: =$Q$28 -> 23.1 | R82: =$R$28 -> 0.02 | S82: =$S$28 -> 15 | T82: =$T$28 -> 3.5 | U82: =$U$28 -> 0
A83: 15 | B83: 门禁系统安装 | C83: 1、门洞尺寸：1500*2200mm 2、包含设备、管线、调试等 | D83: 项 | E83: 1 | F83: =I83 -> 2050 | G83: =F83*E83 -> 2050 | I83: =J83+J83*K83+L83+M83+N83 -> 2050 | J83: =Q83*$Q$1 -> 1200 | K83: =R83 -> 0 | L83: =S83*$S$1 -> 800 | M83: =T83*$T$1 -> 50 | N83: =U83*$U$1 -> 0 | O83: =E83*I83 -> 2050 | P83: =Q83*(1+R83)+S83+T83+U83 -> 2050 | Q83: =$Q$29 -> 1200 | R83: =$R$29 -> 0 | S83: =$S$29 -> 800 | T83: =$T$29 -> 50 | U83: =$U$29 -> 0
A84: 16 | B84: 隔断免漆板单开门 | C84: 1、免漆板单开门 2、门洞尺寸：900mm*2400mm 4、含门锁.五金等制作安装 | D84: 樘 | E84: 2 | F84: =I84 -> 1800 | G84: =F84*E84 -> 3600 | I84: =J84+J84*K84+L84+M84+N84 -> 1800 | J84: =Q84*$Q$1 -> 1620 | K84: =R84 -> 0 | L84: =S84*$S$1 -> 180 | M84: =T84*$T$1 -> 0 | N84: =U84*$U$1 -> 0 | O84: =E84*I84 -> 3600 | P84: =Q84*(1+R84)+S84+T84+U84 -> 1800 | Q84: =$Q$30 -> 1620 | R84: =$R$30 -> 0 | S84: =$S$30 -> 180 | T84: =$T$30 -> 0 | U84: =$U$30 -> 0
A85: 17 | B85: 原玻璃双开门拆除后安装 | C85: 1、原玻璃双开门拆除后安装 2、保护性拆除 | D85: 樘 | E85: 1 | F85: =I85 -> 600 | G85: =F85*E85 -> 600 | I85: =J85+J85*K85+L85+M85+N85 -> 600 | J85: =Q85*$Q$1 -> 0 | K85: =R85 -> 0 | L85: =S85*$S$1 -> 600 | M85: =T85*$T$1 -> 0 | N85: =U85*$U$1 -> 0 | O85: =E85*I85 -> 600 | P85: =Q85*(1+R85)+S85+T85+U85 -> 600 | Q85: =$Q$49 -> 0 | R85: =$R$49 -> 0 | S85: =$S$49 -> 600 | T85: =$T$49 -> 0 | U85: =$U$49 -> 0
A86: （七） | B86: 办公室五 | G86: =SUBTOTAL(9,G87:G103) -> 41796.512
A87: 1 | B87: 地面架空层 | C87: 1、100mm高 2、500*500mm架空地板 | D87: ㎡ | E87: =39.8+8.36+10+14.81 -> 72.97 | F87: =I87 -> 126.25 | G87: =F87*E87 -> 9212.4625 | I87: =J87+J87*K87+L87+M87+N87 -> 126.25 | J87: =Q87*$Q$1 -> 125 | K87: =R87 -> 0.01 | L87: =S87*$S$1 -> 0 | M87: =T87*$T$1 -> 0 | N87: =U87*$U$1 -> 0 | O87: =E87*I87 -> 9212.4625 | P87: =Q87*(1+R87)+S87+T87+U87 -> 126.25 | Q87: =$Q$15 -> 125 | R87: =$R$15 -> 0.01 | S87: =$S$15 -> 0 | T87: =$T$15 -> 0 | U87: =$U$15 -> 0
A88: 2 | B88: 地面地毯 | C88: 1、规格尺寸：500*500 2、地毯专用胶，厚度包干，后期不因厚度调整价格； | D88: ㎡ | E88: =E87 -> 72.97 | F88: =I88 -> 71.5 | G88: =F88*E88 -> 5217.355 | I88: =J88+J88*K88+L88+M88+N88 -> 71.5 | J88: =Q88*$Q$1 -> 60 | K88: =R88 -> 0.025 | L88: =S88*$S$1 -> 5 | M88: =T88*$T$1 -> 5 | N88: =U88*$U$1 -> 0 | O88: =E88*I88 -> 5217.355 | P88: =Q88*(1+R88)+S88+T88+U88 -> 71.5 | Q88: =$Q$16 -> 60 | R88: =$R$16 -> 0.025 | S88: =$S$16 -> 5 | T88: =$T$16 -> 5 | U88: =$U$16 -> 0
A89: 3 | B89: 原天棚喷乳胶漆PT-02 (含墙体上部) | C89: 1、面层：PT-02深色涂料两遍 2、包含各种管道 | D89: ㎡ | E89: =39.8+1.31*(29.69) -> 78.6939 | F89: =I89 -> 20.08 | G89: =F89*E89 -> 1580.1735 | I89: =J89+J89*K89+L89+M89+N89 -> 20.08 | J89: =Q89*$Q$1 -> 8 | K89: =R89 -> 0.01 | L89: =S89*$S$1 -> 10 | M89: =T89*$T$1 -> 0.5 | N89: =U89*$U$1 -> 1.5 | O89: =E89*I89 -> 1580.1735 | P89: =Q89*(1+R89)+S89+T89+U89 -> 20.08 | Q89: =$Q$17 -> 8 | R89: =$R$17 -> 0.01 | S89: =$S$17 -> 10 | T89: =$T$17 -> 0.5 | U89: =$U$17 -> 1.5
A90: 4 | B90: 石膏板天花吊顶 | C90: 1、吊顶形式：平级+跌级吊顶 2、基层：轻钢龙骨+双层9.5mm厚石膏板 | D90: ㎡ | E90: =8.36+10+14.81 -> 33.17 | F90: =I90 -> 144.18 | G90: =F90*E90 -> 4782.4506 | I90: =J90+J90*K90+L90+M90+N90 -> 144.18 | J90: =Q90*$Q$1 -> 18 | K90: =R90 -> 0.01 | L90: =S90*$S$1 -> 100 | M90: =T90*$T$1 -> 26 | N90: =U90*$U$1 -> 0 | O90: =E90*I90 -> 4782.4506 | P90: =Q90*(1+R90)+S90+T90+U90 -> 144.18 | Q90: =$Q$18 -> 18 | R90: =$R$18 -> 0.01 | S90: =$S$18 -> 100 | T90: =$T$18 -> 26 | U90: =$U$18 -> 0
A91: 5 | B91: 天花板缝贴纸带刮平整 | C91: 1、螺丝钉刷防锈漆 2、缝贴纸带刮平整 | D91: ㎡ | E91: =E90 -> 33.17 | F91: =I91 -> 8.5 | G91: =F91*E91 -> 281.945 | I91: =J91+J91*K91+L91+M91+N91 -> 8.5 | J91: =Q91*$Q$1 -> 3.5 | K91: =R91 -> 0 | L91: =S91*$S$1 -> 5 | M91: =T91*$T$1 -> 0 | N91: =U91*$U$1 -> 0 | O91: =E91*I91 -> 281.945 | P91: =Q91*(1+R91)+S91+T91+U91 -> 8.5 | Q91: =$Q$19 -> 3.5 | R91: =$R$19 -> 0 | S91: =$S$19 -> 5 | T91: =$T$19 -> 0 | U91: =$U$19 -> 0
A92: 6 | B92: 天花挂耐水腻子 | C92: 1、耐水腻子2道，含打磨、修补 | D92: ㎡ | E92: =E91 -> 33.17 | F92: =I92 -> 23.5 | G92: =F92*E92 -> 779.495 | I92: =J92+J92*K92+L92+M92+N92 -> 23.5 | J92: =Q92*$Q$1 -> 3.5 | K92: =R92 -> 0 | L92: =S92*$S$1 -> 20 | M92: =T92*$T$1 -> 0 | N92: =U92*$U$1 -> 0 | O92: =E92*I92 -> 779.495 | P92: =Q92*(1+R92)+S92+T92+U92 -> 23.5 | Q92: =$Q$20 -> 3.5 | R92: =$R$20 -> 0 | S92: =$S$20 -> 20 | T92: =$T$20 -> 0 | U92: =$U$20 -> 0
A93: 7 | B93: 天棚乳胶漆 | C93: 1、面层：PT-01无机白色涂料一底二面 | D93: ㎡ | E93: =E92 -> 33.17 | F93: =I93 -> 13 | G93: =F93*E93 -> 431.21 | I93: =J93+J93*K93+L93+M93+N93 -> 13 | J93: =Q93*$Q$1 -> 3 | K93: =R93 -> 0 | L93: =S93*$S$1 -> 10 | M93: =T93*$T$1 -> 0 | N93: =U93*$U$1 -> 0 | O93: =E93*I93 -> 431.21 | P93: =Q93*(1+R93)+S93+T93+U93 -> 13 | Q93: =$Q$21 -> 3 | R93: =$R$21 -> 0 | S93: =$S$21 -> 10 | T93: =$T$21 -> 0 | U93: =$U$21 -> 0
A94: 8 | B94: 窗帘盒 | C94: 1、基层：钢结构龙骨+阻燃板基层 2、面层：9.5mm厚石膏板 | D94: m | E94: =3.48+3.08+5.69 -> 12.25 | F94: =I94 -> 195.17 | G94: =F94*E94 -> 2390.8325 | I94: =J94+J94*K94+L94+M94+N94 -> 195.17 | J94: =Q94*$Q$1 -> 131.67 | K94: =R94 -> 0 | L94: =S94*$S$1 -> 55 | M94: =T94*$T$1 -> 8.5 | N94: =U94*$U$1 -> 0 | O94: =E94*I94 -> 2390.8325 | P94: =Q94*(1+R94)+S94+T94+U94 -> 195.17 | Q94: =$Q$22 -> 131.67 | R94: =$R$22 -> 0 | S94: =$S$22 -> 55 | T94: =$T$22 -> 8.5 | U94: =$U$22 -> 0
A95: 9 | B95: 窗帘 | C95: 1、成品窗帘 | D95: ㎡ | E95: =(3.48+3.08+5.69)*2.8 -> 34.3 | F95: =I95 -> 75 | G95: =F95*E95 -> 2572.5 | I95: =J95+J95*K95+L95+M95+N95 -> 75 | J95: =Q95*$Q$1 -> 68 | K95: =R95 -> 0 | L95: =S95*$S$1 -> 5 | M95: =T95*$T$1 -> 1.5 | N95: =U95*$U$1 -> 0.5 | O95: =E95*I95 -> 2572.5 | P95: =Q95*(1+R95)+S95+T95+U95 -> 75 | Q95: =$Q$23 -> 68 | R95: =$R$23 -> 0 | S95: =$S$23 -> 5 | T95: =$T$23 -> 1.5 | U95: =$U$23 -> 0.5
A96: 10 | B96: 墙面缝贴纸带刮平整 | C96: 1、螺丝钉刷防锈漆 2、缝贴纸带刮平整 | D96: ㎡ | E96: =2.8*(7.03+11.16+0.25*2+6+0.3*2+3.21*2+0.4+0.22+1.4+0.58+0.49+3.52*2+2.4)-1.5*2.2*1 -> 120.572 | F96: =I96 -> 8.5 | G96: =F96*E96 -> 1024.862 | I96: =J96+J96*K96+L96+M96+N96 -> 8.5 | J96: =Q96*$Q$1 -> 3.5 | K96: =R96 -> 0 | L96: =S96*$S$1 -> 5 | M96: =T96*$T$1 -> 0 | N96: =U96*$U$1 -> 0 | O96: =E96*I96 -> 1024.862 | P96: =Q96*(1+R96)+S96+T96+U96 -> 8.5 | Q96: =$Q$24 -> 3.5 | R96: =$R$24 -> 0 | S96: =$S$24 -> 5 | T96: =$T$24 -> 0 | U96: =$U$24 -> 0
A97: 11 | B97: 墙面挂耐水腻子 | C97: 耐水腻子2道，含打磨、修补 | D97: ㎡ | E97: =E96 -> 120.572 | F97: =I97 -> 23.5 | G97: =F97*E97 -> 2833.442 | I97: =J97+J97*K97+L97+M97+N97 -> 23.5 | J97: =Q97*$Q$1 -> 3.5 | K97: =R97 -> 0 | L97: =S97*$S$1 -> 20 | M97: =T97*$T$1 -> 0 | N97: =U97*$U$1 -> 0 | O97: =E97*I97 -> 2833.442 | P97: =Q97*(1+R97)+S97+T97+U97 -> 23.5 | Q97: =$Q$25 -> 3.5 | R97: =$R$25 -> 0 | S97: =$S$25 -> 20 | T97: =$T$25 -> 0 | U97: =$U$25 -> 0
A98: 12 | B98: 墙面乳胶漆PT-01 | C98: 1、面层：PT-01无机白色涂料一底二面 | D98: ㎡ | E98: =E96-8.96 -> 111.612 | F98: =I98 -> 13 | G98: =F98*E98 -> 1450.956 | I98: =J98+J98*K98+L98+M98+N98 -> 13 | J98: =Q98*$Q$1 -> 3 | K98: =R98 -> 0 | L98: =S98*$S$1 -> 10 | M98: =T98*$T$1 -> 0 | N98: =U98*$U$1 -> 0 | O98: =E98*I98 -> 1450.956 | P98: =Q98*(1+R98)+S98+T98+U98 -> 13 | Q98: =$Q$26 -> 3 | R98: =$R$26 -> 0 | S98: =$S$26 -> 10 | T98: =$T$26 -> 0 | U98: =$U$26 -> 0
A99: 13 | B99: 墙面艺术涂料 | C99: 1、面层：PT-02艺术涂料一底二面 | D99: ㎡ | E99: =2.8*3.52 -> 9.856 | F99: =I99 -> 120.85 | G99: =F99*E99 -> 1191.0976 | I99: =J99+J99*K99+L99+M99+N99 -> 120.85 | J99: =Q99*$Q$1 -> 85 | K99: =R99 -> 0.01 | L99: =S99*$S$1 -> 35 | M99: =T99*$T$1 -> 0 | N99: =U99*$U$1 -> 0 | O99: =E99*I99 -> 1191.0976 | P99: =Q99*(1+R99)+S99+T99+U99 -> 120.85 | Q99: =$Q$27 -> 85 | R99: =$R$27 -> 0.01 | S99: =$S$27 -> 35 | T99: =$T$27 -> 0 | U99: =$U$27 -> 0
A100: 14 | B100: MT-01 1.2mm厚不锈钢踢脚线 | C100: 1、规格尺寸：50mm高 2、面层：MT-01 1.2mm厚不锈钢 3、基层：轻钢龙骨+12mm厚阻燃夹板 | D100: m | E100: =7.03+11.16+0.25*2+6+0.3*2+3.21*2+0.4+0.22+1.4+0.58+0.49+3.52*2+2.4-1.5*1 -> 42.74 | F100: =I100 -> 42.062 | G100: =F100*E100 -> 1797.7299 | I100: =J100+J100*K100+L100+M100+N100 -> 42.062 | J100: =Q100*$Q$1 -> 23.1 | K100: =R100 -> 0.02 | L100: =S100*$S$1 -> 15 | M100: =T100*$T$1 -> 3.5 | N100: =U100*$U$1 -> 0 | O100: =E100*I100 -> 1797.7299 | P100: =Q100*(1+R100)+S100+T100+U100 -> 42.062 | Q100: =$Q$28 -> 23.1 | R100: =$R$28 -> 0.02 | S100: =$S$28 -> 15 | T100: =$T$28 -> 3.5 | U100: =$U$28 -> 0
...

Sheet 报价汇总-空调消防
B1: D座塔楼办公室3903-04-05-06装饰工程汇总 空调消防
A2: 序号 | B2: 名称 | C2: 金额（元） | D2: 面积（㎡） | E2: 单方价格（元/㎡） | F2: 备注 | G2: 成本
A3: 一 | B3: =空调消防清单!B3 -> 空调工程 | C3: =空调消防清单!G3 -> 319500 | G3: =6000*42 -> 252000 | H3: =(C3-G3)/G3 -> 0.26785714
A4: （一） | B4: 办公室一空调工程 | C4: =空调消防清单!G4 -> 45500
A5: （二） | B5: 办公室二空调工程 | C5: =空调消防清单!G7 -> 38000
A6: （三） | B6: 办公室三空调工程 | C6: =空调消防清单!G10 -> 38000
A7: （四） | B7: 办公室四空调工程 | C7: =空调消防清单!G13 -> 30500
A8: （五） | B8: 办公室五空调工程 | C8: =空调消防清单!G16 -> 30500
A9: （六） | B9: 办公室六空调工程 | C9: =空调消防清单!G19 -> 61000
A10: （七） | B10: 办公室七空调工程 | C10: =空调消防清单!G22 -> 38000
A11: （八） | B11: 办公室八空调工程 | C11: =空调消防清单!G25 -> 38000
A12: 二 | B12: =空调消防清单!B28 -> 消防改造 | C12: =空调消防清单!G28 -> 123730.3 | G12: =1404.86*30+250*170+4000 -> 88645.8 | H12: =(C12-G12)/G12 -> 0.39578299
A13: 三 | B13: 合计：一+二 | C13: =C3+C12 -> 443230.3 | G13: =SUM(G3:G12) -> 340645.8
A14: 四 | B14: 管理费 | C14: =空调消防清单!G46 -> 22161.515
A15: 五 | B15: 税金 | C15: =空调消防清单!G47 -> 13961.754
A16: 六 | B16: 合计=三+四+五 | C16: =C13+C14+C15 -> 479353.57 | D16: ='报价汇总-装修工程'!D29 -> 864.74 | E16: =C16/D16 -> 554.3326

Sheet 空调消防清单
A1: D座塔楼办公室3903-04-05-06装饰工程清单 空调消防 | I1: =G48 -> 479353.57 | Q1: 1.35 | S1: =$Q$1 -> 1.35 | T1: =$Q$1 -> 1.35 | U1: =$Q$1 -> 1.35 | V1: =(18+7+7)*170 -> 5440 | W1: =232.32*30 -> 6969.6 | X1: =V1+W1 -> 12409.6
A2: 序号 | B2: 项目名称 | C2: 项目特征 | D2: 单位 | E2: 工程量 | F2: 综合单价（不含税） | G2: 合价 | H2: 备注 | I2: 综合单价（不含税） | J2: 主材费 | K2: 主材损耗率 | L2: 人工费 | M2: 辅材费 | N2: 机械费 | O2: 合计 | P2: 成本价 | Q2: 主材费 | R2: 主材损耗率 | S2: 人工费 | T2: 辅材费 | U2: 机械费
A3: 一 | B3: 空调工程 | G3: =SUBTOTAL(9,G5:G27) -> 319500
A4: （一） | B4: 办公室一 | G4: =SUBTOTAL(9,G5:G6) -> 45500
A5: 1 | B5: 空调风机盘管1P | C5: 1、包含铝合金风口、空调管道、帆布、钢结构支架等 | D5: 台 | E5: 5 | F5: =I5 -> 7500 | G5: =F5*E5 -> 37500 | H5: 品牌：麦克维尔 | I5: 7500 | J5: =Q5*$Q$1 -> 7830 | K5: =R5 -> 0 | L5: =S5*$S$1 -> 472.5 | M5: =T5*$T$1 -> 0 | N5: =U5*$U$1 -> 0 | O5: =E5*I5 -> 37500 | P5: =Q5*(1+R5)+S5+T5+U5 -> 6150 | Q5: 5800 | S5: 350
A6: 2 | B6: 空调风机盘管2P | C6: 1、包含铝合金风口、空调管道、帆布、钢结构支架等 | D6: 台 | E6: 1 | F6: =I6 -> 8000 | G6: =F6*E6 -> 8000 | H6: 品牌：麦克维尔 | I6: 8000 | J6: =Q6*$Q$1 -> 8505 | K6: =R6 -> 0 | L6: =S6*$S$1 -> 472.5 | M6: =T6*$T$1 -> 0 | N6: =U6*$U$1 -> 0 | O6: =E6*I6 -> 8000 | P6: =Q6*(1+R6)+S6+T6+U6 -> 6650 | Q6: 6300 | S6: 350
A7: （二） | B7: 办公室二 | G7: =SUBTOTAL(9,G8:G9) -> 38000
A8: 1 | B8: 空调风机盘管1P | C8: 1、包含铝合金风口、空调管道、帆布、钢结构支架等 | D8: 台 | E8: 4 | F8: =I8 -> 7500 | G8: =F8*E8 -> 30000 | H8: 品牌：麦克维尔 | I8: =$I$5 -> 7500 | J8: =Q8*$Q$1 -> 7830 | K8: =R8 -> 0 | L8: =S8*$S$1 -> 472.5 | M8: =T8*$T$1 -> 0 | N8: =U8*$U$1 -> 0 | O8: =E8*I8 -> 30000 | P8: =Q8*(1+R8)+S8+T8+U8 -> 6150 | Q8: =$Q$5 -> 5800 | R8: =$R$5 -> 0 | S8: =$S$5 -> 350 | T8: =$T$5 -> 0 | U8: =$U$5 -> 0
A9: 2 | B9: 空调风机盘管2P | C9: 1、包含铝合金风口、空调管道、帆布、钢结构支架等 | D9: 台 | E9: 1 | F9: =I9 -> 8000 | G9: =F9*E9 -> 8000 | H9: 品牌：麦克维尔 | I9: =$I$6 -> 8000 | J9: =Q9*$Q$1 -> 8505 | K9: =R9 -> 0 | L9: =S9*$S$1 -> 472.5 | M9: =T9*$T$1 -> 0 | N9: =U9*$U$1 -> 0 | O9: =E9*I9 -> 8000 | P9: =Q9*(1+R9)+S9+T9+U9 -> 6650 | Q9: =$Q$6 -> 6300 | R9: =$R$6 -> 0 | S9: =$S$6 -> 350 | T9: =$T$6 -> 0 | U9: =$U$6 -> 0
A10: （三） | B10: 办公室三 | G10: =SUBTOTAL(9,G11:G12) -> 38000
A11: 1 | B11: 空调风机盘管1P | C11: 1、包含铝合金风口、空调管道、帆布、钢结构支架等 | D11: 台 | E11: 4 | F11: =I11 -> 7500 | G11: =F11*E11 -> 30000 | H11: 品牌：麦克维尔 | I11: =$I$5 -> 7500 | J11: =Q11*$Q$1 -> 7830 | K11: =R11 -> 0 | L11: =S11*$S$1 -> 472.5 | M11: =T11*$T$1 -> 0 | N11: =U11*$U$1 -> 0 | O11: =E11*I11 -> 30000 | P11: =Q11*(1+R11)+S11+T11+U11 -> 6150 | Q11: =$Q$5 -> 5800 | R11: =$R$5 -> 0 | S11: =$S$5 -> 350 | T11: =$T$5 -> 0 | U11: =$U$5 -> 0
A12: 2 | B12: 空调风机盘管2P | C12: 1、包含铝合金风口、空调管道、帆布、钢结构支架等 | D12: 台 | E12: 1 | F12: =I12 -> 8000 | G12: =F12*E12 -> 8000 | H12: 品牌：麦克维尔 | I12: =$I$6 -> 8000 | J12: =Q12*$Q$1 -> 8505 | K12: =R12 -> 0 | L12: =S12*$S$1 -> 472.5 | M12: =T12*$T$1 -> 0 | N12: =U12*$U$1 -> 0 | O12: =E12*I12 -> 8000 | P12: =Q12*(1+R12)+S12+T12+U12 -> 6650 | Q12: =$Q$6 -> 6300 | R12: =$R$6 -> 0 | S12: =$S$6 -> 350 | T12: =$T$6 -> 0 | U12: =$U$6 -> 0
A13: （四） | B13: 办公室四 | G13: =SUBTOTAL(9,G14:G15) -> 30500
A14: 1 | B14: 空调风机盘管1P | C14: 1、包含铝合金风口、空调管道、帆布、钢结构支架等 | D14: 台 | E14: 3 | F14: =I14 -> 7500 | G14: =F14*E14 -> 22500 | H14: 品牌：麦克维尔 | I14: =$I$5 -> 7500 | J14: =Q14*$Q$1 -> 7830 | K14: =R14 -> 0 | L14: =S14*$S$1 -> 472.5 | M14: =T14*$T$1 -> 0 | N14: =U14*$U$1 -> 0 | O14: =E14*I14 -> 22500 | P14: =Q14*(1+R14)+S14+T14+U14 -> 6150 | Q14: =$Q$5 -> 5800 | R14: =$R$5 -> 0 | S14: =$S$5 -> 350 | T14: =$T$5 -> 0 | U14: =$U$5 -> 0
A15: 2 | B15: 空调风机盘管2P | C15: 1、包含铝合金风口、空调管道、帆布、钢结构支架等 | D15: 台 | E15: 1 | F15: =I15 -> 8000 | G15: =F15*E15 -> 8000 | H15: 品牌：麦克维尔 | I15: =$I$6 -> 8000 | J15: =Q15*$Q$1 -> 8505 | K15: =R15 -> 0 | L15: =S15*$S$1 -> 472.5 | M15: =T15*$T$1 -> 0 | N15: =U15*$U$1 -> 0 | O15: =E15*I15 -> 8000 | P15: =Q15*(1+R15)+S15+T15+U15 -> 6650 | Q15: =$Q$6 -> 6300 | R15: =$R$6 -> 0 | S15: =$S$6 -> 350 | T15: =$T$6 -> 0 | U15: =$U$6 -> 0
A16: （五） | B16: 办公室五 | G16: =SUBTOTAL(9,G17:G18) -> 30500
A17: 1 | B17: 空调风机盘管1P | C17: 1、包含铝合金风口、空调管道、帆布、钢结构支架等 | D17: 台 | E17: 3 | F17: =I17 -> 7500 | G17: =F17*E17 -> 22500 | H17: 品牌：麦克维尔 | I17: =$I$5 -> 7500 | J17: =Q17*$Q$1 -> 7830 | K17: =R17 -> 0 | L17: =S17*$S$1 -> 472.5 | M17: =T17*$T$1 -> 0 | N17: =U17*$U$1 -> 0 | O17: =E17*I17 -> 22500 | P17: =Q17*(1+R17)+S17+T17+U17 -> 6150 | Q17: =$Q$5 -> 5800 | R17: =$R$5 -> 0 | S17: =$S$5 -> 350 | T17: =$T$5 -> 0 | U17: =$U$5 -> 0
A18: 2 | B18: 空调风机盘管2P | C18: 1、包含铝合金风口、空调管道、帆布、钢结构支架等 | D18: 台 | E18: 1 | F18: =I18 -> 8000 | G18: =F18*E18 -> 8000 | H18: 品牌：麦克维尔 | I18: =$I$6 -> 8000 | J18: =Q18*$Q$1 -> 8505 | K18: =R18 -> 0 | L18: =S18*$S$1 -> 472.5 | M18: =T18*$T$1 -> 0 | N18: =U18*$U$1 -> 0 | O18: =E18*I18 -> 8000 | P18: =Q18*(1+R18)+S18+T18+U18 -> 6650 | Q18: =$Q$6 -> 6300 | R18: =$R$6 -> 0 | S18: =$S$6 -> 350 | T18: =$T$6 -> 0 | U18: =$U$6 -> 0
A19: （六） | B19: 办公室六 | G19: =SUBTOTAL(9,G20:G21) -> 61000
A20: 1 | B20: 空调风机盘管1P | C20: 1、包含铝合金风口、空调管道、帆布、钢结构支架等 | D20: 台 | E20: 6 | F20: =I20 -> 7500 | G20: =F20*E20 -> 45000 | H20: 品牌：麦克维尔 | I20: =$I$5 -> 7500 | J20: =Q20*$Q$1 -> 7830 | K20: =R20 -> 0 | L20: =S20*$S$1 -> 472.5 | M20: =T20*$T$1 -> 0 | N20: =U20*$U$1 -> 0 | O20: =E20*I20 -> 45000 | P20: =Q20*(1+R20)+S20+T20+U20 -> 6150 | Q20: =$Q$5 -> 5800 | R20: =$R$5 -> 0 | S20: =$S$5 -> 350 | T20: =$T$5 -> 0 | U20: =$U$5 -> 0
A21: 2 | B21: 空调风机盘管2P | C21: 1、包含铝合金风口、空调管道、帆布、钢结构支架等 | D21: 台 | E21: 2 | F21: =I21 -> 8000 | G21: =F21*E21 -> 16000 | H21: 品牌：麦克维尔 | I21: =$I$6 -> 8000 | J21: =Q21*$Q$1 -> 8505 | K21: =R21 -> 0 | L21: =S21*$S$1 -> 472.5 | M21: =T21*$T$1 -> 0 | N21: =U21*$U$1 -> 0 | O21: =E21*I21 -> 16000 | P21: =Q21*(1+R21)+S21+T21+U21 -> 6650 | Q21: =$Q$6 -> 6300 | R21: =$R$6 -> 0 | S21: =$S$6 -> 350 | T21: =$T$6 -> 0 | U21: =$U$6 -> 0
A22: （七） | B22: 办公室七 | G22: =SUBTOTAL(9,G23:G24) -> 38000
A23: 1 | B23: 空调风机盘管1P | C23: 1、包含铝合金风口、空调管道、帆布、钢结构支架等 | D23: 台 | E23: 4 | F23: =I23 -> 7500 | G23: =F23*E23 -> 30000 | H23: 品牌：麦克维尔 | I23: =$I$5 -> 7500 | J23: =Q23*$Q$1 -> 7830 | K23: =R23 -> 0 | L23: =S23*$S$1 -> 472.5 | M23: =T23*$T$1 -> 0 | N23: =U23*$U$1 -> 0 | O23: =E23*I23 -> 30000 | P23: =Q23*(1+R23)+S23+T23+U23 -> 6150 | Q23: =$Q$5 -> 5800 | R23: =$R$5 -> 0 | S23: =$S$5 -> 350 | T23: =$T$5 -> 0 | U23: =$U$5 -> 0
A24: 2 | B24: 空调风机盘管2P | C24: 1、包含铝合金风口、空调管道、帆布、钢结构支架等 | D24: 台 | E24: 1 | F24: =I24 -> 8000 | G24: =F24*E24 -> 8000 | H24: 品牌：麦克维尔 | I24: =$I$6 -> 8000 | J24: =Q24*$Q$1 -> 8505 | K24: =R24 -> 0 | L24: =S24*$S$1 -> 472.5 | M24: =T24*$T$1 -> 0 | N24: =U24*$U$1 -> 0 | O24: =E24*I24 -> 8000 | P24: =Q24*(1+R24)+S24+T24+U24 -> 6650 | Q24: =$Q$6 -> 6300 | R24: =$R$6 -> 0 | S24: =$S$6 -> 350 | T24: =$T$6 -> 0 | U24: =$U$6 -> 0
A25: （八） | B25: 办公室八 | G25: =SUBTOTAL(9,G26:G27) -> 38000
A26: 1 | B26: 空调风机盘管1P | C26: 1、包含铝合金风口、空调管道、帆布、钢结构支架等 | D26: 台 | E26: 4 | F26: =I26 -> 7500 | G26: =F26*E26 -> 30000 | H26: 品牌：麦克维尔 | I26: =$I$5 -> 7500 | J26: =Q26*$Q$1 -> 7830 | K26: =R26 -> 0 | L26: =S26*$S$1 -> 472.5 | M26: =T26*$T$1 -> 0 | N26: =U26*$U$1 -> 0 | O26: =E26*I26 -> 30000 | P26: =Q26*(1+R26)+S26+T26+U26 -> 6150 | Q26: =$Q$5 -> 5800 | R26: =$R$5 -> 0 | S26: =$S$5 -> 350 | T26: =$T$5 -> 0 | U26: =$U$5 -> 0
A27: 2 | B27: 空调风机盘管2P | C27: 1、包含铝合金风口、空调管道、帆布、钢结构支架等 | D27: 台 | E27: 1 | F27: =I27 -> 8000 | G27: =F27*E27 -> 8000 | H27: 品牌：麦克维尔 | I27: =$I$6 -> 8000 | J27: =Q27*$Q$1 -> 8505 | K27: =R27 -> 0 | L27: =S27*$S$1 -> 472.5 | M27: =T27*$T$1 -> 0 | N27: =U27*$U$1 -> 0 | O27: =E27*I27 -> 8000 | P27: =Q27*(1+R27)+S27+T27+U27 -> 6650 | Q27: =$Q$6 -> 6300 | R27: =$R$6 -> 0 | S27: =$S$6 -> 350 | T27: =$T$6 -> 0 | U27: =$U$6 -> 0
A28: 二 | B28: 消防改造 | G28: =SUBTOTAL(9,G30:G44) -> 123730.3
A29: （一） | B29: 火灾自动报警系统
A30: 1 | B30: 探测器拆除、安装 | C30: 1、含配合装修 2、含布管布线及其他辅材 | D30: 套 | E30: =18 -> 18 | F30: =I30 -> 191.4 | G30: =F30*E30 -> 3445.2 | H30: 按实结算 | I30: 191.4 | J30: =Q30*$Q$1 -> 258.39 | K30: =R30 -> 0 | L30: =S30*$S$1 -> 0 | M30: =T30*$T$1 -> 0 | N30: =U30*$U$1 -> 0 | O30: =E30*I30 -> 3445.2 | P30: =Q30*(1+R30)+S30+T30+U30 -> 191.4 | Q30: 191.4
A31: 2 | B31: 探测器新增、安装 | C31: 1、含设备增加及配合装修 2、含布管布线及其他辅材 | D31: 套 | E31: =7+7+6+5+5+10+6+6 -> 52 | F31: =I31 -> 261 | G31: =F31*E31 -> 13572 | H31: 按实结算 | I31: 261 | J31: =Q31*$Q$1 -> 352.35 | K31: =R31 -> 0 | L31: =S31*$S$1 -> 0 | M31: =T31*$T$1 -> 0 | N31: =U31*$U$1 -> 0 | O31: =E31*I31 -> 13572 | P31: =Q31*(1+R31)+S31+T31+U31 -> 261 | Q31: 261
A32: 3 | B32: 消防广播拆除、安装 | C32: 1、含配合装修 2、含布管布线及其他辅材 | D32: 套 | E32: 4 | F32: =I32 -> 191.4 | G32: =F32*E32 -> 765.6 | H32: 按实结算 | I32: 191.4 | J32: =Q32*$Q$1 -> 258.39 | K32: =R32 -> 0 | L32: =S32*$S$1 -> 0 | M32: =T32*$T$1 -> 0 | N32: =U32*$U$1 -> 0 | O32: =E32*I32 -> 765.6 | P32: =Q32*(1+R32)+S32+T32+U32 -> 191.4 | Q32: 191.4
A33: 4 | B33: 消防广播新增、安装 | C33: 1、含设备增加及配合装修 2、含布管布线及其他辅材 | D33: 套 | E33: 8 | F33: =I33 -> 261 | G33: =F33*E33 -> 2088 | H33: 按实结算 | I33: 261 | J33: =Q33*$Q$1 -> 352.35 | K33: =R33 -> 0 | L33: =S33*$S$1 -> 0 | M33: =T33*$T$1 -> 0 | N33: =U33*$U$1 -> 0 | O33: =E33*I33 -> 2088 | P33: =Q33*(1+R33)+S33+T33+U33 -> 261 | Q33: 261
A34: 5 | B34: 应急照明拆除、安装 | C34: 1、含配合装修 2、含布管布线及其他辅材 | D34: 套 | E34: 8 | F34: =I34 -> 191.4 | G34: =F34*E34 -> 1531.2 | H34: 按实结算 | I34: 191.4 | J34: =Q34*$Q$1 -> 258.39 | K34: =R34 -> 0 | L34: =S34*$S$1 -> 0 | M34: =T34*$T$1 -> 0 | N34: =U34*$U$1 -> 0 | O34: =E34*I34 -> 1531.2 | P34: =Q34*(1+R34)+S34+T34+U34 -> 191.4 | Q34: 191.4
A35: 6 | B35: 应急照明新增、安装 | C35: 1、含设备增加及配合装修 2、含布管布线及其他辅材 | D35: 套 | E35: 26 | F35: =I35 -> 261 | G35: =F35*E35 -> 6786 | H35: 按实结算 | I35: 261 | J35: =Q35*$Q$1 -> 352.35 | K35: =R35 -> 0 | L35: =S35*$S$1 -> 0 | M35: =T35*$T$1 -> 0 | N35: =U35*$U$1 -> 0 | O35: =E35*I35 -> 6786 | P35: =Q35*(1+R35)+S35+T35+U35 -> 261 | Q35: 261
A36: 7 | B36: 编程入网、系统接驳 | C36: 1、由大厦原消防施工单位负责，物业统一收费 | D36: ㎡ | E36: =244.34+336.33+258.32+565.87 -> 1404.86 | F36: =I36 -> 30 | G36: =F36*E36 -> 42145.8 | H36: 1、不足4000元的按最低4000元计算。超过4000元的按建筑面积30元/㎡计算。 | I36: 30 | J36: =Q36*$Q$1 -> 0 | K36: =R36 -> 0 | L36: =S36*$S$1 -> 27 | M36: =T36*$T$1 -> 0 | N36: =U36*$U$1 -> 0 | O36: =E36*I36 -> 42145.8 | P36: =Q36*(1+R36)+S36+T36+U36 -> 20 | S36: 20
A37: （二） | B37: 自动喷淋灭火系统
A38: 1 | B38: 喷头拆除、安装 | C38: 1、含配合装修 2、含消防管道、管件及其他辅材 | D38: 个 | E38: =7+5+4+3+3+11+4+4 -> 41 | F38: =I38 -> 174 | G38: =F38*E38 -> 7134 | H38: 按实结算 | I38: 174 | J38: =Q38*$Q$1 -> 234.9 | K38: =R38 -> 0 | L38: =S38*$S$1 -> 0 | M38: =T38*$T$1 -> 0 | N38: =U38*$U$1 -> 0 | O38: =E38*I38 -> 7134 | P38: =Q38*(1+R38)+S38+T38+U38 -> 174 | Q38: 174
A39: 2 | B39: 喷头新增、安装 | C39: 1、含设备增加及配合装修 2、含消防管道、管件及其他辅材 | D39: 个 | E39: =15+11+9+8+8+24+9+9 -> 93 | F39: =I39 -> 217.5 | G39: =F39*E39 -> 20227.5 | H39: 按实结算 | I39: 217.5 | J39: =Q39*$Q$1 -> 293.625 | K39: =R39 -> 0 | L39: =S39*$S$1 -> 0 | M39: =T39*$T$1 -> 0 | N39: =U39*$U$1 -> 0 | O39: =E39*I39 -> 20227.5 | P39: =Q39*(1+R39)+S39+T39+U39 -> 217.5 | Q39: 217.5
A40: 3 | B40: 喷淋管网排水费 | C40: 1、含管网排水费 及人工 | D40: 项 | E40: 1 | F40: =I40 -> 800 | G40: =F40*E40 -> 800 | I40: 800 | J40: =Q40*$Q$1 -> 0 | K40: =R40 -> 0 | L40: =S40*$S$1 -> 0 | M40: =T40*$T$1 -> 0 | N40: =U40*$U$1 -> 0 | O40: =E40*I40 -> 800 | P40: =Q40*(1+R40)+S40+T40+U40 -> 0
A41: 4 | B41: 喷淋管网试压 | C41: 1、管网冲洗、试 压、调试 | D41: 项 | E41: 1 | F41: =I41 -> 870 | G41: =F41*E41 -> 870 | I41: 870 | J41: =Q41*$Q$1 -> 0 | K41: =R41 -> 0 | L41: =S41*$S$1 -> 0 | M41: =T41*$T$1 -> 0 | N41: =U41*$U$1 -> 0 | O41: =E41*I41 -> 870 | P41: =Q41*(1+R41)+S41+T41+U41 -> 0
A42: （三） | B42: 其他
A43: 1 | B43: 消防报验 | C43: 含相关部门收取的报验费用。 | D43: 项 | E43: 1 | F43: =I43 -> 20450 | G43: =F43*E43 -> 20450 | I43: 20450 | J43: =Q43*$Q$1 -> 0 | K43: =R43 -> 0 | L43: =S43*$S$1 -> 0 | M43: =T43*$T$1 -> 0 | N43: =U43*$U$1 -> 0 | O43: =E43*I43 -> 20450 | P43: =Q43*(1+R43)+S43+T43+U43 -> 0
A44: 2 | B44: 综合专业设计出图 | D44: 套 | E44: 1 | F44: =I44 -> 3915 | G44: =F44*E44 -> 3915 | I44: 3915 | P44: =Q44*(1+R44)+S44+T44+U44 -> 0
A45: 三 | B45: 小计 | D45: 项 | E45: 1 | G45: =G3+G28 -> 443230.3 | I45: =SUBTOTAL(9,G3:G44) -> 443230.3
A46: 四 | B46: 管理费 | C46: =不含空调消防清单!C290 -> 0.05 | D46: 项 | E46: 1 | G46: =G45*C46 -> 22161.515
A47: 五 | B47: 税金 | C47: =不含空调消防清单!C291 -> 0.03 | D47: 项 | E47: 1 | G47: =(G45+G46)*C47 -> 13961.754
A48: 六 | B48: 合计 | D48: 项 | E48: 1 | G48: =G47+G46+G45 -> 479353.57

Sheet 材料设备参考品牌
A1: 材料设备参考品牌
A2: 序号 | B2: 专业 | C2: 材料名称 | D2: 品牌 | E2: 备注
A3: 1 | B3: 装饰 | C3: 地砖 | D3: 东鹏、马可罗兰
A4: 2 | B4: 装饰 | C4: 墙砖 | D4: 东鹏、马可罗兰
A5: 3 | B5: 装饰 | C5: 方块地毯 | D5: 国产
A6: 4 | B6: 装饰 | C6: 500*500mm架空地板 | D6: 深圳沈飞
A7: 5 | B7: 装饰 | C7: 石膏板 | D7: 泰山、深耐福
A8: 6 | B8: 装饰 | C8: 乳胶漆 | D8: 立邦
A9: 7 | B9: 装饰 | C9: 腻子 | D9: 立邦
A10: 8 | B10: 安装 | C10: 照明，强电用线 | D10: 南洋、成天泰
A11: 9 | B11: 安装 | C11: 筒灯 | D11: 佛山照明
A12: 10 | B12: 安装 | C12: LED灯带 | D12: 佛山照明
A13: 11 | B13: 安装 | C13: 照明开关 | D13: 公牛
A14: 12 | B14: 安装 | C14: 插座 | D14: 公牛
... A17: 15 | B17: 空调 | C17: 空调风机盘管 | D17: 麦克维尔
