Workbook

Sheet 报价汇总-装修工程
B1: 岁宝壹品苑D栋3901办公室装修汇总 装修工程
A2: 序号 | B2: 名称 | C2: 金额（元） | D2: 面积（㎡） | E2: 单方价格（元/㎡） | F2: 备注
A3: 一 | B3: 装饰工程 | C3: =不含空调消防清单!G3 -> 169645.07 | G3: 成本
A4: （一） | B4: 隔墙工程 | C4: =不含空调消防清单!G4 -> 53466.411 | G4: 装饰 | H4: =不含空调消防清单!G92 -> 239782.42
A5: （二） | B5: 地面工程 | C5: =不含空调消防清单!G22 -> 34168.421 | G5: 空调 | H5: 48600
A6: （三） | B6: 天花工程 | C6: =不含空调消防清单!G28 -> 37942.385 | G6: 消防 | H6: 12500
A7: （四） | B7: 墙面工程 | C7: =不含空调消防清单!G41 -> 21072.015 | G7: 合计 | H7: =SUM(H4:H6) -> 300882.42
A8: （五） | B8: 固定家具及门窗工程 | C8: =不含空调消防清单!G48 -> 22995.837 | H8: =C13+C14+'报价汇总-空调消防'!C5+'报价汇总-空调消防'!C6 -> 344019.41
A9: 二 | B9: 安装工程 | C9: =不含空调消防清单!G66 -> 45325.202 | H9: =(H8-H7)/H7 -> 0.14336827
A10: （一） | B10: 强电工程 | C10: =不含空调消防清单!G67 -> 37343.602
A11: （二） | B11: 弱电工程 | C11: =不含空调消防清单!G81 -> 7981.6
A12: 三 | B12: 其他工程 | C12: =不含空调消防清单!G84 -> 24812.15
A13: 四 | B13: 小计：一+二+三 | C13: =C3+C9+C12 -> 239782.42
A14: 五 | B14: 管理费 | C14: =不含空调消防清单!G93 -> 8392.3847
A15: 六 | B15: 税金 | C15: 0
A16: 七 | B16: 装饰合计=四+五+六 （不含消防空调） | C16: =C13+C14+C15 -> 248174.8 | D16: =193.06+0.7 -> 193.76 | E16: =C16/D16 -> 1280.8361 | F16: 建筑面积319.15㎡
A17: 八 | B17: 消防空调 | C17: ='报价汇总-空调消防'!C8 -> 95844.607 | D17: =$D$16 -> 193.76 | E17: =C17/D17 -> 494.65631
A18: 九 | B18: 总计: （装饰+消防空调） | C18: =C16+C17 -> 344019.41 | D18: =$D$16 -> 193.76 | E18: =C18/D18 -> 1775.4924 | F18: =F16 -> 建筑面积319.15㎡

Sheet 不含空调消防清单
A1: 岁宝壹品苑D栋3901办公室装修清单 （不含空调消防） | I1: =G95 -> 248174.8 | Q1: 1 | S1: 1 | T1: =$Q$1 -> 1 | U1: =$Q$1 -> 1 | V1: ='报价汇总-装修工程'!G17 -> 0
A2: 序号 | B2: 项目名称 | C2: 项目特征 | D2: 单位 | E2: 工程量 | F2: 综合单价（不含税） | G2: 合价 | H2: 备注 | I2: 综合单价（不含税） | J2: 主材费 | K2: 主材损耗率 | L2: 人工费 | M2: 辅材费 | N2: 机械费 | O2: 合计 | P2: 成本价 | Q2: 主材费 | R2: 主材损耗率 | S2: 人工费 | T2: 辅材费 | U2: 机械费 | V2: 成本合计
A3: 一 | B3: 装饰工程 | G3: =SUBTOTAL(9,G4:G65) -> 169645.07
A4: （一） | B4: 隔墙工程 | G4: =SUBTOTAL(9,G5:G21) -> 53466.411
A5: 1 | B5: 拆除原有砖墙 （150mm厚） | C5: 1、人工拆除 2、机械设备 3、防护措施 4、垃圾清理装袋 | D5: ㎡ | E5: =(1.7+1)*2.8 -> 7.56 | F5: =I5 -> 100 | G5: =F5*E5 -> 756 | I5: =J5+J5*K5+L5+M5+N5 -> 100 | J5: =Q5*$Q$1 -> 0 | K5: =R5 -> 0 | L5: =S5*$S$1 -> 70 | M5: =T5*$T$1 -> 30 | N5: =U5*$U$1 -> 0 | O5: =E5*I5 -> 756 | P5: =Q5+Q5*R5+S5+T5+U5 -> 100 | S5: 70 | T5: 30 | V5: =E5*P5 -> 756
A6: 2 | B6: 门洞顶部横梁槽钢加固 | C6: 1、原墙面开门洞后横梁槽钢加固 | D6: m | E6: =1.7+1+0.2*4 -> 3.5 | F6: =I6 -> 500 | G6: =F6*E6 -> 1750 | I6: =J6+J6*K6+L6+M6+N6 -> 500 | J6: =Q6*$Q$1 -> 300 | K6: =R6 -> 0 | L6: =S6*$S$1 -> 200 | M6: =T6*$T$1 -> 0 | N6: =U6*$U$1 -> 0 | O6: =E6*I6 -> 1750 | P6: =Q6+Q6*R6+S6+T6+U6 -> 500 | Q6: 300 | S6: 200 | V6: =E6*P6 -> 1750
A7: 3 | B7: 门洞侧边水泥砂浆修补 | C7: 1、门洞侧边水泥砂浆修补 | D7: m | E7: =(2.8*4+3.5) -> 14.7 | F7: =I7 -> 41.12 | G7: =F7*E7 -> 604.464 | I7: =J7+J7*K7+L7+M7+N7 -> 41.12 | J7: =Q7*$Q$1 -> 6 | K7: =R7 -> 0.02 | L7: =S7*$S$1 -> 35 | M7: =T7*$T$1 -> 0 | N7: =U7*$U$1 -> 0 | O7: =E7*I7 -> 604.464 | P7: =Q7+Q7*R7+S7+T7+U7 -> 41.12 | Q7: =12*0.5 -> 6 | R7: 0.02 | S7: 35 | V7: =E7*P7 -> 604.464
A8: 4 | B8: 门洞侧边12mm阻燃夹板封边 | C8: 1、原墙面开门洞后12mm阻燃夹板封边 | D8: m | E8: =(2.8*4+3.5) -> 14.7 | F8: =I8 -> 25.6 | G8: =F8*E8 -> 376.32 | I8: =J8+J8*K8+L8+M8+N8 -> 25.6 | J8: =Q8*$Q$1 -> 5.6 | K8: =R8 -> 0 | L8: =S8*$S$1 -> 20 | M8: =T8*$T$1 -> 0 | N8: =U8*$U$1 -> 0 | O8: =E8*I8 -> 376.32 | P8: =Q8+Q8*R8+S8+T8+U8 -> 25.6 | Q8: =28*0.2 -> 5.6 | S8: 20 | V8: =E8*P8 -> 376.32
A9: 5 | B9: 新建轻质砖墙-旧门洞封堵 （150mm厚） | C9: 1、成品砂浆、15#轻质砖 2、完成面150mm厚 | D9: ㎡ | E9: =1.5*2.2*2 -> 6.6 | F9: =I9 -> 98.4 | G9: =F9*E9 -> 649.44 | I9: =J9+J9*K9+L9+M9+N9 -> 98.4 | J9: =Q9*$Q$1 -> 42.9 | K9: =R9 -> 0 | L9: =S9*$S$1 -> 45 | M9: =T9*$T$1 -> 10 | N9: =U9*$U$1 -> 0.5 | O9: =E9*I9 -> 649.44 | P9: =Q9+Q9*R9+S9+T9+U9 -> 98.4 | Q9: =286*0.15 -> 42.9 | R9: 0 | S9: 45 | T9: 10 | U9: 0.5 | V9: =E9*P9 -> 649.44
A10: 6 | B10: 内墙水泥砂浆抹灰 | C10: 1、基层墙体：砌体墙、混凝土墙 2、厚度：20mm 3、做法：墙面基层清理，不同界面交接处、阴角转角处、管线开槽处，挂镀锌电焊网，公区人流通道等局部砌体墙满挂镀锌电焊网，面层压入1道耐碱网格布，水泥砂浆找平、压实抹光； | D10: ㎡ | E10: =3.93*(30.85+5.6)-(1+1.7)*2.8+6.6 -> 142.2885 | F10: =I10 -> 39 | G10: =F10*E10 -> 5549.2515 | I10: =J10+J10*K10+L10+M10+N10 -> 39 | J10: =Q10*$Q$1 -> 0 | K10: =R10 -> 0.01 | L10: =S10*$S$1 -> 30 | M10: =T10*$T$1 -> 8.5 | N10: =U10*$U$1 -> 0.5 | O10: =E10*I10 -> 5549.2515 | P10: =Q10+Q10*R10+S10+T10+U10 -> 39 | R10: 0.01 | S10: 30 | T10: 8.5 | U10: 0.5 | V10: =E10*P10 -> 5549.2515
A11: 7 | B11: 轻钢龙骨隔墙 | C11: 双层双面轻钢龙骨隔墙 1、墙厚120mm; 2、75mm轻钢龙骨； 3、50mm厚，48kg/m3的吸音棉； 4、12mm阻燃夹板+9.5mm厚石膏板 | D11: ㎡ | E11: =E12 -> 141.1207 | I11: =J11+J11*K11+L11+M11+N11 -> 0 | J11: =Q11*$Q$1 -> 0 | K11: =R11 -> 0 | L11: =S11*$S$1 -> 0 | M11: =T11*$T$1 -> 0 | N11: =U11*$U$1 -> 0 | O11: =E11*I11 -> 0 | P11: =Q11+Q11*R11+S11+T11+U11 -> 0 | V11: =E11*P11 -> 0
A12: 7.1 | B12: 轻钢龙骨 | C12: 1、天地龙骨 2、竖龙骨 3、穿心龙骨 4、其他辅材 | D12: ㎡ | E12: =3.93*(1.17+2.56+11.05+7.5+5.07+5.07+5.17)-0.85*2.8*2-0.66*2.8 -> 141.1207 | F12: =I12 -> 53.5 | G12: =F12*E12 -> 7549.9574 | I12: =J12+J12*K12+L12+M12+N12 -> 53.5 | J12: =Q12*$Q$1 -> 26 | K12: =R12 -> 0 | L12: =S12*$S$1 -> 26 | M12: =T12*$T$1 -> 0 | N12: =U12*$U$1 -> 1.5 | O12: =E12*I12 -> 7549.9574 | P12: =Q12+Q12*R12+S12+T12+U12 -> 53.5 | Q12: 26 | S12: 26 | U12: 1.5 | V12: =E12*P12 -> 7549.9574
A13: 7.2 | B13: 50mm厚吸音棉 | C13: 1、50mm厚，48kg/m3的吸音棉 | D13: ㎡ | E13: =E12 -> 141.1207 | F13: =I13 -> 21.65 | G13: =F13*E13 -> 3055.2632 | I13: =J13+J13*K13+L13+M13+N13 -> 21.65 | J13: =Q13*$Q$1 -> 11.65 | K13: =R13 -> 0 | L13: =S13*$S$1 -> 10 | M13: =T13*$T$1 -> 0 | N13: =U13*$U$1 -> 0 | O13: =E13*I13 -> 3055.2632 | P13: =Q13+Q13*R13+S13+T13+U13 -> 21.65 | Q13: 11.65 | S13: 10 | V13: =E13*P13 -> 3055.2632
A14: 7.3 | B14: 12mm阻燃夹板 | C14: 1、双面单层12mm阻燃夹板打底 | D14: ㎡ | E14: =E12*2 -> 282.2414 | F14: =I14 -> 50.8 | G14: =F14*E14 -> 14337.863 | I14: =J14+J14*K14+L14+M14+N14 -> 50.8 | J14: =Q14*$Q$1 -> 28 | K14: =R14 -> 0 | L14: =S14*$S$1 -> 22 | M14: =T14*$T$1 -> 0.8 | N14: =U14*$U$1 -> 0 | O14: =E14*I14 -> 14337.863 | P14: =Q14+Q14*R14+S14+T14+U14 -> 50.8 | Q14: 28 | S14: 22 | T14: 0.8 | V14: =E14*P14 -> 14337.863
A15: 7.4 | B15: 9.5mm厚石膏板 | C15: 1、双面单层9.5mm厚石膏板 | D15: ㎡ | E15: =E12*2 -> 282.2414 | F15: =I15 -> 26.3 | G15: =F15*E15 -> 7422.9488 | I15: =J15+J15*K15+L15+M15+N15 -> 26.3 | J15: =Q15*$Q$1 -> 7.5 | K15: =R15 -> 0 | L15: =S15*$S$1 -> 18 | M15: =T15*$T$1 -> 0.8 | N15: =U15*$U$1 -> 0 | O15: =E15*I15 -> 7422.9488 | P15: =Q15+Q15*R15+S15+T15+U15 -> 26.3 | Q15: =7.5 -> 7.5 | S15: 18 | T15: 0.8 | V15: =E15*P15 -> 7422.9488
A16: 8 | B16: GL-01 中空钢化玻璃隔断（含免漆板隔断） | C16: 1、GL-01 5+5mm钢化玻璃; 2、铝框包边 3、五金配件等制作安装 | D16: ㎡ | E16: =2.8*(8.97+3)-0.85*2.8*4 -> 23.996 | F16: =I16 -> 325 | G16: =F16*E16 -> 7798.7 | I16: =J16+J16*K16+L16+M16+N16 -> 325 | J16: =Q16*$Q$1 -> 300 | K16: =R16 -> 0.01 | L16: =S16*$S$1 -> 10 | M16: =T16*$T$1 -> 10.5 | N16: =U16*$U$1 -> 1.5 | O16: =E16*I16 -> 7798.7 | P16: =Q16+Q16*R16+S16+T16+U16 -> 325 | Q16: 300 | R16: 0.01 | S16: 10 | T16: 10.5 | U16: 1.5 | V16: =E16*P16 -> 7798.7
A17: 9 | B17: 钢化玻璃隔断上方封板 | C17: 双层双面钢结构龙骨隔墙 1、墙厚120mm; 2、钢结构龙骨； 3、50mm厚，48kg/m3的吸音棉； 4、12mm厚阻燃夹板+9.5mm厚石膏板 | D17: ㎡ | E17: =E18 -> 13.5261
A18: 9.1 | B18: 钢结构龙骨 | C18: 1、钢结构龙骨 2、刷防锈漆 3、其他辅材 | D18: ㎡ | E18: =1.13*(8.97+3) -> 13.5261 | F18: =I18 -> 91.5 | G18: =F18*E18 -> 1237.6381 | I18: =J18+J18*K18+L18+M18+N18 -> 91.5 | J18: =Q18*$Q$1 -> 55 | K18: =R18 -> 0 | L18: =S18*$S$1 -> 35 | M18: =T18*$T$1 -> 0 | N18: =U18*$U$1 -> 1.5 | O18: =E18*I18 -> 1237.6381 | P18: =Q18+Q18*R18+S18+T18+U18 -> 91.5 | Q18: 55 | S18: 35 | U18: 1.5 | V18: =E18*P18 -> 1237.6381
A19: 9.2 | B19: 50mm厚吸音棉 | C19: 1、50mm厚，48kg/m3的吸音棉 | D19: ㎡ | E19: =E18 -> 13.5261 | F19: =I19 -> 21.65 | G19: =F19*E19 -> 292.84006 | I19: =J19+J19*K19+L19+M19+N19 -> 21.65 | J19: =Q19*$Q$1 -> 11.65 | K19: =R19 -> 0 | L19: =S19*$S$1 -> 10 | M19: =T19*$T$1 -> 0 | N19: =U19*$U$1 -> 0 | O19: =E19*I19 -> 292.84006 | P19: =Q19+Q19*R19+S19+T19+U19 -> 21.65 | Q19: 11.65 | S19: 10 | V19: =E19*P19 -> 292.84006
A20: 9.3 | B20: 12mm阻燃夹板 | C20: 1、单层12mm阻燃夹板打底 | D20: ㎡ | E20: =E18*2 -> 27.0522 | F20: =I20 -> 50.8 | G20: =F20*E20 -> 1374.2518 | I20: =J20+J20*K20+L20+M20+N20 -> 50.8 | J20: =Q20*$Q$1 -> 28 | K20: =R20 -> 0 | L20: =S20*$S$1 -> 22 | M20: =T20*$T$1 -> 0.8 | N20: =U20*$U$1 -> 0 | O20: =E20*I20 -> 1374.2518 | P20: =Q20+Q20*R20+S20+T20+U20 -> 50.8 | Q20: 28 | S20: 22 | T20: 0.8 | V20: =E20*P20 -> 1374.2518
A21: 9.4 | B21: 9.5mm厚石膏板 | C21: 1、双面单层9.5mm厚石膏板 | D21: ㎡ | E21: =E18*2 -> 27.0522 | F21: =I21 -> 26.3 | G21: =F21*E21 -> 711.47286 | I21: =J21+J21*K21+L21+M21+N21 -> 26.3 | J21: =Q21*$Q$1 -> 7.5 | K21: =R21 -> 0 | L21: =S21*$S$1 -> 18 | M21: =T21*$T$1 -> 0.8 | N21: =U21*$U$1 -> 0 | O21: =E21*I21 -> 711.47286 | P21: =Q21+Q21*R21+S21+T21+U21 -> 26.3 | Q21: =7.5 -> 7.5 | S21: =$S$15 -> 18 | T21: 0.8 | V21: =E21*P21 -> 711.47286
A22: （二） | B22: 地面工程 | G22: =SUBTOTAL(9,G23:G27) -> 34168.421
A23: 1 | B23: 100mm厚陶粒拌混泥土垫层 | C23: 1、100mm厚陶粒拌混泥土垫层 | D23: ㎡ | E23: 35.33 | F23: =I23 -> 76.93 | G23: =F23*E23 -> 2717.9369 | I23: =J23+J23*K23+L23+M23+N23 -> 76.93 | J23: =Q23*$Q$1 -> 43 | K23: =R23 -> 0.01 | L23: =S23*$S$1 -> 30 | M23: =T23*$T$1 -> 3.5 | N23: =U23*$U$1 -> 0 | O23: =E23*I23 -> 2717.9369 | P23: =Q23+Q23*R23+S23+T23+U23 -> 76.93 | Q23: 43 | R23: 0.01 | S23: 30 | T23: 3.5 | U23: 0 | V23: =E23*P23 -> 2717.9369
A24: 2 | B24: 地面块料 | C24: 1、CT-01灰色地砖 2、瓷砖规格：750*1500 3、瓷砖专用胶泥结合层，厚度包干，后期不因厚度调整价格； 4、白水泥擦缝 | D24: ㎡ | E24: 35.33 | F24: =I24 -> 142.3 | G24: =F24*E24 -> 5027.459 | I24: =J24+J24*K24+L24+M24+N24 -> 142.3 | J24: =Q24*$Q$1 -> 65 | K24: =R24 -> 0.02 | L24: =S24*$S$1 -> 60 | M24: =T24*$T$1 -> 16 | N24: =U24*$U$1 -> 0 | O24: =E24*I24 -> 5027.459 | P24: =Q24+Q24*R24+S24+T24+U24 -> 142.3 | Q24: 65 | R24: 0.02 | S24: 60 | T24: 16 | V24: =E24*P24 -> 5027.459
A25: 3 | B25: 美缝 | C25: 1、专业美缝剂美缝 | D25: ㎡ | E25: 35.33 | F25: 0 | G25: =F25*E25 -> 0 | I25: =J25+J25*K25+L25+M25+N25 -> 20 | J25: =Q25*$Q$1 -> 0 | K25: =R25 -> 0.02 | L25: =S25*$S$1 -> 16 | M25: =T25*$T$1 -> 4 | N25: =U25*$U$1 -> 0 | O25: =E25*I25 -> 706.6 | P25: =Q25+Q25*R25+S25+T25+U25 -> 20 | R25: 0.02 | S25: 16 | T25: 4 | V25: =E25*P25 -> 706.6
A26: 4 | B26: 地面架空层 | C26: 1、100mm高 2、500*500mm架空地板 | D26: ㎡ | E26: =54.41+18.93+4.79+13.74+12.77+11.76+20.26+6.09 -> 142.75 | F26: =I26 -> 128.75 | G26: =F26*E26 -> 18379.062 | I26: =J26+J26*K26+L26+M26+N26 -> 128.75 | J26: =Q26*$Q$1 -> 125 | K26: =R26 -> 0.03 | L26: =S26*$S$1 -> 0 | M26: =T26*$T$1 -> 0 | N26: =U26*$U$1 -> 0 | O26: =E26*I26 -> 18379.062 | P26: =Q26+Q26*R26+S26+T26+U26 -> 128.75 | Q26: 125 | R26: 0.03 | S26: 0 | T26: 0 | V26: =E26*P26 -> 18379.062
A27: 5 | B27: 地面地毯 | C27: 1、规格尺寸：500*500 2、地毯专用胶，厚度包干，后期不因厚度调整价格； | D27: ㎡ | E27: =E26 -> 142.75 | F27: =I27 -> 56.35 | G27: =F27*E27 -> 8043.9625 | I27: =J27+J27*K27+L27+M27+N27 -> 56.35 | J27: =Q27*$Q$1 -> 45 | K27: =R27 -> 0.03 | L27: =S27*$S$1 -> 5 | M27: =T27*$T$1 -> 5 | N27: =U27*$U$1 -> 0 | O27: =E27*I27 -> 8043.9625 | P27: =Q27+Q27*R27+S27+T27+U27 -> 56.35 | Q27: 45 | R27: 0.03 | S27: 5 | T27: 5 | V27: =E27*P27 -> 8043.9625
A28: （三） | B28: 天花工程 | G28: =SUBTOTAL(9,G29:G40) -> 37942.385
A29: 1 | B29: 原天棚喷乳胶漆PT-02 (含墙体上部) | C29: 1、面层：PT-02深色涂料两遍 2、包含各种管道 | D29: ㎡ | E29: =45.22+1.13*(26.95-13.47) -> 60.4524 | F29: =I29 -> 20.16 | G29: =F29*E29 -> 1218.7204 | I29: =J29+J29*K29+L29+M29+N29 -> 20.16 | J29: =Q29*$Q$1 -> 8 | K29: =R29 -> 0.02 | L29: =S29*$S$1 -> 10 | M29: =T29*$T$1 -> 0.5 | N29: =U29*$U$1 -> 1.5 | O29: =E29*I29 -> 1218.7204 | P29: =Q29+Q29*R29+S29+T29+U29 -> 20.16 | Q29: 8 | R29: 0.02 | S29: 10 | T29: 0.5 | U29: 1.5 | V29: =E29*P29 -> 1218.7204
A30: 2 | B30: 办公室高晶硅钙板吊顶 | C30: 1、吊顶形式：平级 2、基层：轻钢龙骨+高晶硅钙板 3.含各种灯具、检修口、风口开口 | D30: ㎡ | E30: =20.26 -> 20.26 | F30: =I30 -> 128.3 | G30: =F30*E30 -> 2599.358 | I30: =J30+J30*K30+L30+M30+N30 -> 128.3 | J30: =Q30*$Q$1 -> 65 | K30: =R30 -> 0.02 | L30: =S30*$S$1 -> 60 | M30: =T30*$T$1 -> 0.5 | N30: =U30*$U$1 -> 1.5 | O30: =E30*I30 -> 2599.358 | P30: =Q30+Q30*R30+S30+T30+U30 -> 128.3 | Q30: 65 | R30: 0.02 | S30: 60 | T30: 0.5 | U30: 1.5 | V30: =E30*P30 -> 2599.358
A31: 3 | B31: 石膏板天花吊顶 | C31: 1、吊顶形式：平级+跌级吊顶 2、基层：轻钢龙骨+双层9.5mm厚石膏板 3.含各种灯具、检修口、风口开口 | D31: ㎡
A32: 3.1 | B32: 轻钢龙骨 | C32: 1、轻钢龙骨吊顶 2、其他辅材 | D32: ㎡ | E32: =54.41-45.22+35.33+18.93+4.79+13.74+12.77+11.76+6.09 -> 112.6 | F32: =I32 -> 71.5 | G32: =F32*E32 -> 8050.9 | I32: =J32+J32*K32+L32+M32+N32 -> 71.5 | J32: =Q32*$Q$1 -> 0 | K32: =R32 -> 0 | L32: =S32*$S$1 -> 35 | M32: =T32*$T$1 -> 35 | N32: =U32*$U$1 -> 1.5 | O32: =E32*I32 -> 8050.9 | P32: =Q32+Q32*R32+S32+T32+U32 -> 71.5 | S32: 35 | T32: 35 | U32: 1.5 | V32: =E32*P32 -> 8050.9
A33: 3.2 | B33: 12mm阻燃夹板 | C33: 1、12mm阻燃夹板 | D33: ㎡ | E33: =E32 -> 112.6 | F33: =I33 -> 48.8 | G33: =F33*E33 -> 5494.88 | I33: =J33+J33*K33+L33+M33+N33 -> 48.8 | J33: =Q33*$Q$1 -> 28 | K33: =R33 -> 0 | L33: =S33*$S$1 -> 20 | M33: =T33*$T$1 -> 0.8 | N33: =U33*$U$1 -> 0 | O33: =E33*I33 -> 5494.88 | P33: =Q33+Q33*R33+S33+T33+U33 -> 48.8 | Q33: 28 | S33: 20 | T33: 0.8 | V33: =E33*P33 -> 5494.88
A34: 3.3 | B34: 9.5mm厚石膏板 | C34: 1、双面单层9.5mm厚石膏板 | D34: ㎡ | E34: =E32 -> 112.6 | F34: =I34 -> 26.3 | G34: =F34*E34 -> 2961.38 | I34: =J34+J34*K34+L34+M34+N34 -> 26.3 | J34: =Q34*$Q$1 -> 7.5 | K34: =R34 -> 0 | L34: =S34*$S$1 -> 18 | M34: =T34*$T$1 -> 0.8 | N34: =U34*$U$1 -> 0 | O34: =E34*I34 -> 2961.38 | P34: =Q34+Q34*R34+S34+T34+U34 -> 26.3 | Q34: =7.5 -> 7.5 | S34: =$S$15 -> 18 | T34: 0.8 | V34: =E34*P34 -> 2961.38
A35: 4 | B35: 天花板缝贴纸带刮平整 | D35: ㎡ | E35: =54.41-45.22+35.33+18.93+4.79+13.74+12.77+11.76+20.26+6.09+1.13*13.47 -> 148.0811 | F35: =I35 -> 8.5 | G35: =F35*E35 -> 1258.6894 | I35: =J35+J35*K35+L35+M35+N35 -> 8.5 | J35: =Q35*$Q$1 -> 3.5 | K35: =R35 -> 0 | L35: =S35*$S$1 -> 5 | M35: =T35*$T$1 -> 0 | N35: =U35*$U$1 -> 0 | O35: =E35*I35 -> 1258.6894 | P35: =Q35+Q35*R35+S35+T35+U35 -> 8.5 | Q35: 3.5 | R35: 0 | S35: 5 | T35: 0 | U35: 0 | V35: =E35*P35 -> 1258.6894
A36: 5 | B36: 天花挂耐水腻子 | C36: 1、耐水腻子2道，含打磨、修补 | D36: ㎡ | E36: =E35 -> 148.0811 | F36: =I36 -> 21.5 | G36: =F36*E36 -> 3183.7436 | I36: =J36+J36*K36+L36+M36+N36 -> 21.5 | J36: =Q36*$Q$1 -> 3.5 | K36: =R36 -> 0 | L36: =S36*$S$1 -> 18 | M36: =T36*$T$1 -> 0 | N36: =U36*$U$1 -> 0 | O36: =E36*I36 -> 3183.7436 | P36: =Q36+Q36*R36+S36+T36+U36 -> 21.5 | Q36: 3.5 | R36: 0 | S36: 18 | T36: 0 | U36: 0 | V36: =E36*P36 -> 3183.7436
A37: 6 | B37: 天棚乳胶漆 | C37: 1、面层：PT-01无机白色涂料一底二面 | D37: ㎡ | E37: =E35 -> 148.0811 | F37: =I37 -> 13 | G37: =F37*E37 -> 1925.0543 | I37: =J37+J37*K37+L37+M37+N37 -> 13 | J37: =Q37*$Q$1 -> 3 | K37: =R37 -> 0 | L37: =S37*$S$1 -> 10 | M37: =T37*$T$1 -> 0 | N37: =U37*$U$1 -> 0 | O37: =E37*I37 -> 1925.0543 | P37: =Q37+Q37*R37+S37+T37+U37 -> 13 | Q37: 3 | R37: 0 | S37: 10 | T37: 0 | U37: 0 | V37: =E37*P37 -> 1925.0543
A38: 7 | B38: 天花灯槽 | C38: 1、规格：100*100*100mm天花灯槽 2、基层：轻钢龙骨 3、面层：12mm厚阻燃夹板+9.5mm厚石膏板 | D38: m | E38: =3.08+8.66+9.7 -> 21.44 | F38: =I38 -> 70 | G38: =F38*E38 -> 1500.8 | I38: =J38+J38*K38+L38+M38+N38 -> 70 | J38: =Q38*$Q$1 -> 13.5 | K38: =R38 -> 0 | L38: =S38*$S$1 -> 55 | M38: =T38*$T$1 -> 1.5 | N38: =U38*$U$1 -> 0 | O38: =E38*I38 -> 1500.8 | P38: =Q38+Q38*R38+S38+T38+U38 -> 70 | Q38: =0.3*(35+10) -> 13.5 | S38: 55 | T38: 1.5 | V38: =E38*P38 -> 1500.8
A39: 8 | B39: 窗帘盒 | C39: 1、基层：钢结构龙骨+阻燃板基层 2、面层：9.5mm厚石膏板 | D39: m | E39: =10.68+3.4+2.4+2.85+3.48+2.68+5.28 -> 30.77 | F39: =I39 -> 171.23 | G39: =F39*E39 -> 5268.7471 | I39: =J39+J39*K39+L39+M39+N39 -> 171.23 | J39: =Q39*$Q$1 -> 107.73 | K39: =R39 -> 0 | L39: =S39*$S$1 -> 55 | M39: =T39*$T$1 -> 8.5 | N39: =U39*$U$1 -> 0 | O39: =E39*I39 -> 5268.7471 | P39: =Q39+Q39*R39+S39+T39+U39 -> 171.23 | Q39: =4.2*5.7*4.5 -> 107.73 | S39: 55 | T39: 8.5 | V39: =E39*P39 -> 5268.7471
A40: 9 | B40: 窗帘 | C40: 1、成品窗帘 | D40: ㎡ | E40: =(10.68+3.4+2.4+2.85+3.48+2.68+5.28)*2.8 -> 86.156 | F40: =I40 -> 52 | G40: =F40*E40 -> 4480.112 | I40: =J40+J40*K40+L40+M40+N40 -> 52 | J40: =Q40*$Q$1 -> 45 | K40: =R40 -> 0 | L40: =S40*$S$1 -> 5 | M40: =T40*$T$1 -> 1.5 | N40: =U40*$U$1 -> 0.5 | O40: =E40*I40 -> 4480.112 | P40: =Q40+Q40*R40+S40+T40+U40 -> 52 | Q40: 45 | S40: 5 | T40: 1.5 | U40: 0.5 | V40: =E40*P40 -> 4480.112
A41: （四） | B41: 墙面工程 | G41: =SUBTOTAL(9,G42:G47) -> 21072.015
A42: 1 | B42: 墙面缝贴纸带刮平整 | D42: ㎡ | E42: =3*(13.11+14.71+6.33+29.8+1.05+5.17+5.07*4+7.5+7.4)-0.85*2.8*4-0.66*2.8*2-(1+1.7)*2.8+1.5*2.2*2 -> 301.874 | F42: =I42 -> 8.5 | G42: =F42*E42 -> 2565.929 | I42: =J42+J42*K42+L42+M42+N42 -> 8.5 | J42: =Q42*$Q$1 -> 3.5 | K42: =R42 -> 0 | L42: =S42*$S$1 -> 5 | M42: =T42*$T$1 -> 0 | N42: =U42*$U$1 -> 0 | O42: =E42*I42 -> 2565.929 | P42: =Q42+Q42*R42+S42+T42+U42 -> 8.5 | Q42: =Q35 -> 3.5 | R42: =R35 -> 0 | S42: =S35 -> 5 | T42: =T35 -> 0 | U42: 0 | V42: =E42*P42 -> 2565.929
A43: 2 | B43: 墙面挂耐水腻子 | C43: 耐水腻子2道，含打磨、修补 | D43: ㎡ | E43: =E42 -> 301.874 | F43: =I43 -> 21.5 | G43: =F43*E43 -> 6490.291 | I43: =J43+J43*K43+L43+M43+N43 -> 21.5 | J43: =Q43*$Q$1 -> 3.5 | K43: =R43 -> 0 | L43: =S43*$S$1 -> 18 | M43: =T43*$T$1 -> 0 | N43: =U43*$U$1 -> 0 | O43: =E43*I43 -> 6490.291 | P43: =Q43+Q43*R43+S43+T43+U43 -> 21.5 | Q43: =Q36 -> 3.5 | R43: =R36 -> 0 | S43: =S36 -> 18 | T43: =T36 -> 0 | U43: 0 | V43: =E43*P43 -> 6490.291
A44: 3 | B44: 墙面乳胶漆PT-01 | C44: 1、面层：PT-01无机白色涂料一底二面 | D44: ㎡ | E44: =E42 -> 301.874 | F44: =I44 -> 13 | G44: =F44*E44 -> 3924.362 | I44: =J44+J44*K44+L44+M44+N44 -> 13 | J44: =Q44*$Q$1 -> 3 | K44: =R44 -> 0 | L44: =S44*$S$1 -> 10 | M44: =T44*$T$1 -> 0 | N44: =U44*$U$1 -> 0 | O44: =E44*I44 -> 3924.362 | P44: =Q44+Q44*R44+S44+T44+U44 -> 13 | Q44: =Q37 -> 3 | R44: =R37 -> 0 | S44: =S37 -> 10 | T44: =T37 -> 0 | U44: 0 | V44: =E44*P44 -> 3924.362
A45: 4 | B45: 会议室白色烤漆玻璃饰面 | C45: 1、面层：白色烤漆玻璃 2、基层：12mm厚阻燃夹板 | D45: ㎡ | E45: =2.4*1.35 -> 3.24 | F45: 0 | G45: =F45*E45 -> 0 | I45: =J45+J45*K45+L45+M45+N45 -> 329.05 | J45: =Q45*$Q$1 -> 265 | K45: =R45 -> 0.03 | L45: =S45*$S$1 -> 55 | M45: =T45*$T$1 -> 0.8 | N45: =U45*$U$1 -> 0.3 | O45: =E45*I45 -> 1066.122 | P45: =Q45+Q45*R45+S45+T45+U45 -> 329.05 | Q45: 265 | R45: 0.03 | S45: 55 | T45: 0.8 | U45: 0.3 | V45: =E45*P45 -> 1066.122
A46: 5 | B46: MT-01 1.2mm厚不锈钢踢脚线 | C46: 1、规格尺寸：50mm高 2、面层：MT-01 1.2mm厚不锈钢 3、基层：轻钢龙骨+12mm厚阻燃夹板 | D46: m | E46: =(13.11+14.71+6.33+29.8+1.05+5.17+5.07*4+7.5+7.4)-0.85*4-0.66*2-(1+1.7)+1.5*2 -> 100.93 | F46: =I46 -> 44.831 | G46: =F46*E46 -> 4524.7928 | I46: =J46+J46*K46+L46+M46+N46 -> 44.831 | J46: =Q46*$Q$1 -> 23.1 | K46: =R46 -> 0.01 | L46: =S46*$S$1 -> 18 | M46: =T46*$T$1 -> 3.5 | N46: =U46*$U$1 -> 0 | O46: =E46*I46 -> 4524.7928 | P46: =Q46+Q46*R46+S46+T46+U46 -> 44.831 | Q46: =0.06*360+1.5 -> 23.1 | R46: 0.01 | S46: 18 | T46: 3.5 | V46: =E46*P46 -> 4524.7928
A47: 6 | B47: 岩板墙饰面 （前台处） | C47: 1、面层：CT-02成品岩板9mm厚 2、基层：12mm厚阻燃夹板 | D47: ㎡ | E47: =3.08*3 -> 9.24 | F47: =I47 -> 386 | G47: =F47*E47 -> 3566.64 | I47: =J47+J47*K47+L47+M47+N47 -> 386 | J47: =Q47*$Q$1 -> 220 | K47: =R47 -> 0 | L47: =S47*$S$1 -> 120 | M47: =T47*$T$1 -> 46 | N47: =U47*$U$1 -> 0 | O47: =E47*I47 -> 3566.64 | P47: =Q47+Q47*R47+S47+T47+U47 -> 386 | Q47: 220 | S47: 120 | T47: 46 | V47: =E47*P47 -> 3566.64
A48: （五） | B48: 固定家具及门窗工程 | G48: =SUBTOTAL(9,G49:G65) -> 22995.837
A49: 1 | B49: 门禁系统安装 | C49: 1、门洞尺寸：1600*2500mm 2、门洞开口及修补加固 3、玻璃门保护性拆除及拆除后重新安装 | D49: 项 | E49: 1 | F49: =I49 -> 2050 | G49: =F49*E49 -> 2050 | I49: =J49+J49*K49+L49+M49+N49 -> 2050 | J49: =Q49*$Q$1 -> 1200 | K49: =R49 -> 0 | L49: =S49*$S$1 -> 800 | M49: =T49*$T$1 -> 50 | N49: =U49*$U$1 -> 0 | O49: =E49*I49 -> 2050 | P49: =Q49+Q49*R49+S49+T49+U49 -> 2050 | Q49: 1200 | S49: 800 | T49: 50 | V49: =E49*P49 -> 2050
A50: 2.1 | B50: 玻璃双开门 | C50: 1、10mm厚钢化玻璃门 2、门洞尺寸：1700mm*2800mm 3、含门锁.不锈钢扶手五金等制作安装 | D50: 樘 | E50: 1 | F50: =I50 -> 966.2 | G50: =F50*E50 -> 966.2 | I50: =J50+J50*K50+L50+M50+N50 -> 966.2 | J50: =Q50*$Q$1 -> 571.2 | K50: =R50 -> 0 | L50: =S50*$S$1 -> 360 | M50: =T50*$T$1 -> 35 | N50: =U50*$U$1 -> 0 | O50: =E50*I50 -> 966.2 | P50: =Q50+Q50*R50+S50+T50+U50 -> 966.2 | Q50: =120*1.7*2.8 -> 571.2 | S50: =180*2 -> 360 | T50: =35 -> 35 | V50: =E50*P50 -> 966.2
A51: 2.2 | B51: 扶手 | D51: 副 | E51: 2 | F51: =I51 -> 150 | G51: =F51*E51 -> 300 | I51: 150 | J51: =Q51*$Q$1 -> 150 | K51: =R51 -> 0 | L51: =S51*$S$1 -> 0 | M51: =T51*$T$1 -> 0 | N51: =U51*$U$1 -> 0 | O51: =E51*I51 -> 300 | P51: =Q51+Q51*R51+S51+T51+U51 -> 150 | Q51: 150 | V51: =E51*P51 -> 300
A52: 2.3 | B52: 门夹 | D52: 副 | E52: 4 | F52: =I52 -> 45 | G52: =F52*E52 -> 180 | I52: 45 | J52: =Q52*$Q$1 -> 45 | K52: =R52 -> 0 | L52: =S52*$S$1 -> 0 | M52: =T52*$T$1 -> 0 | N52: =U52*$U$1 -> 0 | O52: =E52*I52 -> 180 | P52: =Q52+Q52*R52+S52+T52+U52 -> 45 | Q52: 45 | V52: =E52*P52 -> 180
A53: 2.3 | B53: 地弹簧 | D53: 副 | E53: 2 | F53: =I53 -> 450 | G53: =F53*E53 -> 900 | I53: 450 | J53: =Q53*$Q$1 -> 450 | K53: =R53 -> 0 | L53: =S53*$S$1 -> 0 | M53: =T53*$T$1 -> 0 | N53: =U53*$U$1 -> 0 | O53: =E53*I53 -> 900 | P53: =Q53+Q53*R53+S53+T53+U53 -> 450 | Q53: 450 | V53: =E53*P53 -> 900
A54: 3.1 | B54: 玻璃单开门 | C54: 1、10mm厚钢化玻璃门 2、门洞尺寸：1000mm*2800mm 3、含门锁.不锈钢扶手五金等制作安装 | D54: 樘 | E54: 1 | F54: =I54 -> 533.5 | G54: =F54*E54 -> 533.5 | I54: =J54+J54*K54+L54+M54+N54 -> 533.5 | J54: =Q54*$Q$1 -> 336 | K54: =R54 -> 0 | L54: =S54*$S$1 -> 180 | M54: =T54*$T$1 -> 17.5 | N54: =U54*$U$1 -> 0 | O54: =E54*I54 -> 533.5 | P54: =Q54+Q54*R54+S54+T54+U54 -> 533.5 | Q54: =120*1*2.8 -> 336 | S54: =180 -> 180 | T54: =17.5 -> 17.5 | V54: =E54*P54 -> 533.5
A55: 3.2 | B55: 扶手 | D55: 副 | E55: 1 | F55: =I55 -> 150 | G55: =F55*E55 -> 150 | I55: 150 | J55: =Q55*$Q$1 -> 150 | K55: =R55 -> 0 | L55: =S55*$S$1 -> 0 | M55: =T55*$T$1 -> 0 | N55: =U55*$U$1 -> 0 | O55: =E55*I55 -> 150 | P55: =Q55+Q55*R55+S55+T55+U55 -> 150 | Q55: 150 | V55: =E55*P55 -> 150
A56: 3.3 | B56: 门夹 | D56: 副 | E56: 2 | F56: =I56 -> 45 | G56: =F56*E56 -> 90 | I56: 45 | J56: =Q56*$Q$1 -> 45 | K56: =R56 -> 0 | L56: =S56*$S$1 -> 0 | M56: =T56*$T$1 -> 0 | N56: =U56*$U$1 -> 0 | O56: =E56*I56 -> 90 | P56: =Q56+Q56*R56+S56+T56+U56 -> 45 | Q56: 45 | V56: =E56*P56 -> 90
A57: 3.4 | B57: 地弹簧 | D57: 副 | E57: 1 | F57: =I57 -> 450 | G57: =F57*E57 -> 450 | I57: 450 | J57: =Q57*$Q$1 -> 450 | K57: =R57 -> 0 | L57: =S57*$S$1 -> 0 | M57: =T57*$T$1 -> 0 | N57: =U57*$U$1 -> 0 | O57: =E57*I57 -> 450 | P57: =Q57+Q57*R57+S57+T57+U57 -> 450 | Q57: 450 | V57: =E57*P57 -> 450
A58: 4.1 | B58: 木饰面单开门 | C58: 1、木饰面单开门 2、门洞尺寸：850mm*2800mm 3、含门套、门锁五金、门吸等制作安装 | D58: 樘 | E58: 7 | F58: =I58 -> 1286 | G58: =F58*E58 -> 9002 | I58: =J58+J58*K58+L58+M58+N58 -> 1286 | J58: =Q58*$Q$1 -> 1071 | K58: =R58 -> 0 | L58: =S58*$S$1 -> 180 | M58: =T58*$T$1 -> 35 | N58: =U58*$U$1 -> 0 | O58: =E58*I58 -> 9002 | P58: =Q58+Q58*R58+S58+T58+U58 -> 1286 | Q58: =450*0.85*2.8 -> 1071 | S58: 180 | T58: 35 | V58: =E58*P58 -> 9002
A59: 4.2 | B59: 门锁 | D59: 个 | E59: 7 | F59: =I59 -> 170 | G59: =F59*E59 -> 1190 | I59: 170 | J59: =Q59*$Q$1 -> 170 | K59: =R59 -> 0 | L59: =S59*$S$1 -> 0 | M59: =T59*$T$1 -> 0 | N59: =U59*$U$1 -> 0 | O59: =E59*I59 -> 1190 | P59: =Q59+Q59*R59+S59+T59+U59 -> 170 | Q59: 170 | V59: =E59*P59 -> 1190
A60: 4.3 | B60: 合页 | D60: 个 | E60: =3*7 -> 21 | F60: =I60 -> 25 | G60: =F60*E60 -> 525 | I60: 25 | J60: =Q60*$Q$1 -> 10.5 | K60: =R60 -> 0 | L60: =S60*$S$1 -> 0 | M60: =T60*$T$1 -> 0 | N60: =U60*$U$1 -> 0 | O60: =E60*I60 -> 525 | P60: =Q60+Q60*R60+S60+T60+U60 -> 10.5 | Q60: 10.5 | V60: =E60*P60 -> 220.5
A61: 4.4 | B61: 门吸 | D61: 个 | E61: 7 | F61: =I61 -> 25 | G61: =F61*E61 -> 175 | I61: 25 | J61: =Q61*$Q$1 -> 15 | K61: =R61 -> 0 | L61: =S61*$S$1 -> 0 | M61: =T61*$T$1 -> 0 | N61: =U61*$U$1 -> 0 | O61: =E61*I61 -> 175 | P61: =Q61+Q61*R61+S61+T61+U61 -> 15 | Q61: 15 | V61: =E61*P61 -> 105
A62: 4.5 | B62: 拉手 | D62: 副 | E62: 7 | F62: =I62 -> 125 | G62: =F62*E62 -> 875 | I62: 125 | J62: =Q62*$Q$1 -> 125 | K62: =R62 -> 0 | L62: =S62*$S$1 -> 0 | M62: =T62*$T$1 -> 0 | N62: =U62*$U$1 -> 0 | O62: =E62*I62 -> 875 | P62: =Q62+Q62*R62+S62+T62+U62 -> 125 | Q62: 125 | V62: =E62*P62 -> 875
A63: 5 | B63: 拉丝不锈钢装饰门套 | C63: 1、规格：150*20mm 2、基层：12mm厚阻燃夹板 3、面层：1mm厚拉丝不锈钢 | D63: ㎡ | E63: =0.19*(2.8*4+1+1.7) -> 2.641 | F63: =I63 -> 426.5 | G63: =F63*E63 -> 1126.3865 | I63: =J63+J63*K63+L63+M63+N63 -> 426.5 | J63: =Q63*$Q$1 -> 350 | K63: =R63 -> 0.03 | L63: =S63*$S$1 -> 55 | M63: =T63*$T$1 -> 10.5 | N63: =U63*$U$1 -> 0.5 | O63: =E63*I63 -> 1126.3865 | P63: =Q63+Q63*R63+S63+T63+U63 -> 426.5 | Q63: 350 | R63: 0.03 | S63: 55 | T63: 10.5 | U63: 0.5 | V63: =E63*P63 -> 1126.3865
A64: 6 | B64: 休闲室地柜 | C64: 1、规格尺寸：2150*450*850mm 2、木饰面板柜体，人造石台面； 3、按平面投影面积计算,综合考虑柜体尺寸及内部做法； 4、含包边、饰面、柜体五金、抽屉及其他所需材料安装施工； 5、满足设计图纸、招标要求及国家有关现行施工及验收规范要求 | D64: ㎡ | E64: =2.15*0.85 -> 1.8275 | F64: =I64 -> 1350 | G64: =F64*E64 -> 2467.125 | I64: =J64+J64*K64+L64+M64+N64 -> 1350 | J64: =Q64*$Q$1 -> 1350 | K64: =R64 -> 0 | L64: =S64*$S$1 -> 0 | M64: =T64*$T$1 -> 0 | N64: =U64*$U$1 -> 0 | O64: =E64*I64 -> 2467.125 | P64: =Q64+Q64*R64+S64+T64+U64 -> 1350 | Q64: 1350 | V64: =E64*P64 -> 2467.125
A65: 7 | B65: 休闲室吊柜 | C65: 1、规格尺寸：2150*350*1250mm 2、木饰面板柜体； 3、按平面投影面积计算,综合考虑柜体尺寸及内部做法； 4、含包边、饰面、柜体五金、抽屉及其他所需材料安装施工； 5、满足设计图纸、招标要求及国家有关现行施工及验收规范要求 | D65: ㎡ | E65: =2.15*1.25 -> 2.6875 | F65: =I65 -> 750 | G65: =F65*E65 -> 2015.625 | I65: =J65+J65*K65+L65+M65+N65 -> 750 | J65: =Q65*$Q$1 -> 750 | K65: =R65 -> 0 | L65: =S65*$S$1 -> 0 | M65: =T65*$T$1 -> 0 | N65: =U65*$U$1 -> 0 | O65: =E65*I65 -> 2015.625 | P65: =Q65+Q65*R65+S65+T65+U65 -> 750 | Q65: 750 | V65: =E65*P65 -> 2015.625
A66: 二 | B66: 安装工程 | G66: =SUBTOTAL(9,G67:G83) -> 45325.202
A67: （一） | B67: 强电工程 | G67: =SUBTOTAL(9,G68:G80) -> 37343.602
A68: 1 | B68: 强电部分(不含照明灯具及开关插座) | C68: 1、成天泰2.5、4平方国标电源线； 2、照明线用wdz-byj-2.5m²,每路线负荷220V/2500W; 3、插座线用wdz-byj-4m²,每路线负荷 220V/4000W 4、含人工及镀锌金属线管 | D68: ㎡ | E68: ='报价汇总-装修工程'!D16 -> 193.76 | F68: =I68 -> 85 | G68: =F68*E68 -> 16469.6 | I68: =J68+J68*K68+L68+M68+N68 -> 85 | J68: =Q68*$Q$1 -> 25 | K68: =R68 -> 0 | L68: =S68*$S$1 -> 60 | M68: =T68*$T$1 -> 0 | N68: =U68*$U$1 -> 0 | O68: =E68*I68 -> 16469.6 | P68: =Q68+Q68*R68+S68+T68+U68 -> 85 | Q68: 25 | S68: 60 | V68: =E68*P68 -> 16469.6
A69: 2 | B69: 强电配电箱移位 | D69: 个 | E69: 1 | F69: =I69 -> 800 | G69: =F69*E69 -> 800 | I69: =J69+J69*K69+L69+M69+N69 -> 800 | J69: =Q69*$Q$1 -> 0 | K69: =R69 -> 0 | L69: =S69*$S$1 -> 800 | M69: =T69*$T$1 -> 0 | N69: =U69*$U$1 -> 0 | O69: =E69*I69 -> 800 | P69: =Q69+Q69*R69+S69+T69+U69 -> 800 | S69: 800 | V69: =E69*P69 -> 800
A70: 3 | B70: 弱电配电箱移位 | D70: 个 | E70: 1 | F70: =I70 -> 500 | G70: =F70*E70 -> 500 | I70: =J70+J70*K70+L70+M70+N70 -> 500 | J70: =Q70*$Q$1 -> 0 | K70: =R70 -> 0 | L70: =S70*$S$1 -> 500 | M70: =T70*$T$1 -> 0 | N70: =U70*$U$1 -> 0 | O70: =E70*I70 -> 500 | P70: =Q70+Q70*R70+S70+T70+U70 -> 500 | S70: 500 | V70: =E70*P70 -> 500
A71: 4 | B71: 开放办公室装饰吊灯 | C71: 1、名称:定制装饰吊灯 2、规格:4800*150mm 3、安装形式:吊装 4、其他:满足设计及施工要求 | D71: 个 | E71: 3 | F71: =I71 -> 880 | G71: =F71*E71 -> 2640 | I71: =J71+J71*K71+L71+M71+N71 -> 880 | J71: =Q71*$Q$1 -> 800 | K71: =R71 -> 0 | L71: =S71*$S$1 -> 80 | M71: =T71*$T$1 -> 0 | N71: =U71*$U$1 -> 0 | O71: =E71*I71 -> 2640 | P71: =Q71+Q71*R71+S71+T71+U71 -> 880 | Q71: 800 | S71: 80 | V71: =E71*P71 -> 2640
A72: 5 | B72: 总总裁办公室吊灯 | C72: 1、名称:装饰吊灯 2、规格: 3、安装形式:吊装 4、其他:满足设计及施工要求 | D72: 个 | E72: 1 | F72: =I72 -> 700 | G72: =F72*E72 -> 700 | I72: =J72+J72*K72+L72+M72+N72 -> 700 | J72: =Q72*$Q$1 -> 650 | K72: =R72 -> 0 | L72: =S72*$S$1 -> 50 | M72: =T72*$T$1 -> 0 | N72: =U72*$U$1 -> 0 | O72: =E72*I72 -> 700 | P72: =Q72+Q72*R72+S72+T72+U72 -> 700 | Q72: 650 | S72: 50 | V72: =E72*P72 -> 700
A73: 6 | B73: 装饰筒灯 | C73: 1、名称:筒灯 2、规格: 3、安装形式:嵌入式 4、其他:满足设计及施工要求 | D73: 个 | E73: =3+3+12+9 -> 27 | F73: =I73 -> 95 | G73: =F73*E73 -> 2565 | I73: =J73+J73*K73+L73+M73+N73 -> 95 | J73: =Q73*$Q$1 -> 75 | K73: =R73 -> 0 | L73: =S73*$S$1 -> 20 | M73: =T73*$T$1 -> 0 | N73: =U73*$U$1 -> 0 | O73: =E73*I73 -> 2565 | P73: =Q73+Q73*R73+S73+T73+U73 -> 95 | Q73: 75 | S73: 20 | V73: =E73*P73 -> 2565
A74: 7 | B74: 装饰明装筒灯 | C74: 1、名称:明装筒灯 2、规格: 3、安装形式:吊装 4、其他:满足设计及施工要求 | D74: 个 | E74: 12 | F74: =I74 -> 85 | G74: =F74*E74 -> 1020 | I74: =J74+J74*K74+L74+M74+N74 -> 85 | J74: =Q74*$Q$1 -> 65 | K74: =R74 -> 0 | L74: =S74*$S$1 -> 20 | M74: =T74*$T$1 -> 0 | N74: =U74*$U$1 -> 0 | O74: =E74*I74 -> 1020 | P74: =Q74+Q74*R74+S74+T74+U74 -> 85 | Q74: 65 | S74: 20 | V74: =E74*P74 -> 1020
A75: 8 | B75: 可调节射灯 | C75: 1、名称:可调节射灯 2、规格: 3、安装形式:嵌入式 4、其他:满足设计及施工要求 | D75: 个 | E75: 6 | F75: =I75 -> 155 | G75: =F75*E75 -> 930 | I75: =J75+J75*K75+L75+M75+N75 -> 155 | J75: =Q75*$Q$1 -> 135 | K75: =R75 -> 0 | L75: =S75*$S$1 -> 20 | M75: =T75*$T$1 -> 0 | N75: =U75*$U$1 -> 0 | O75: =E75*I75 -> 930 | P75: =Q75+Q75*R75+S75+T75+U75 -> 155 | Q75: 135 | S75: 20 | V75: =E75*P75 -> 930
A76: 9 | B76: 磁吸灯 | C76: 1、名称:磁吸灯 2、规格: 3、安装形式:嵌入式 4、其他:满足设计及施工要求 | D76: m | E76: =9.5+15 -> 24.5 | F76: =I76 -> 103.33333 | G76: =F76*E76 -> 2531.6667 | I76: =J76+J76*K76+L76+M76+N76 -> 103.33333 | J76: =Q76*$Q$1 -> 83.333333 | K76: =R76 -> 0 | L76: =S76*$S$1 -> 20 | M76: =T76*$T$1 -> 0 | N76: =U76*$U$1 -> 0 | O76: =E76*I76 -> 2531.6667 | P76: =Q76+Q76*R76+S76+T76+U76 -> 103.33333 | Q76: =50/0.6 -> 83.333333 | S76: 20 | V76: =E76*P76 -> 2531.6667
A77: 10 | B77: 天花灯带 | C77: 1、led灯带 | D77: m | E77: =E39 -> 30.77 | F77: =I77 -> 35.5 | G77: =F77*E77 -> 1092.335 | I77: =J77+J77*K77+L77+M77+N77 -> 35.5 | J77: =Q77*$Q$1 -> 23.5 | K77: =R77 -> 0 | L77: =S77*$S$1 -> 12 | M77: =T77*$T$1 -> 0 | N77: =U77*$U$1 -> 0 | O77: =E77*I77 -> 1092.335 | P77: =Q77+Q77*R77+S77+T77+U77 -> 35.5 | Q77: 23.5 | S77: 12 | V77: =E77*P77 -> 1092.335
A78: 12 | B78: 照明开关 | C78: (1)名称:各种开关 (2)安装方式:距地1.3米安装 (3)其他:满足设计及施工要求 | D78: 个 | E78: 10 | F78: =I78 -> 27 | G78: =F78*E78 -> 270 | I78: =J78+J78*K78+L78+M78+N78 -> 27 | J78: =Q78*$Q$1 -> 17 | K78: =R78 -> 0 | L78: =S78*$S$1 -> 10 | M78: =T78*$T$1 -> 0 | N78: =U78*$U$1 -> 0 | O78: =E78*I78 -> 270 | P78: =Q78+Q78*R78+S78+T78+U78 -> 27 | Q78: 17 | S78: 10 | V78: =E78*P78 -> 270
A79: 13 | B79: 插座 | C79: (1)名称:单相二.三孔普通插座 (2)规格:250V 10A 安全型 (3)安装方式:详见图纸 (4)其他:满足设计及施工要求 | D79: 个 | E79: =30*3+31 -> 121 | F79: =I79 -> 25 | G79: =F79*E79 -> 3025 | I79: =J79+J79*K79+L79+M79+N79 -> 25 | J79: =Q79*$Q$1 -> 15 | K79: =R79 -> 0 | L79: =S79*$S$1 -> 10 | M79: =T79*$T$1 -> 0 | N79: =U79*$U$1 -> 0 | O79: =E79*I79 -> 3025 | P79: =Q79+Q79*R79+S79+T79+U79 -> 25 | Q79: 15 | S79: 10 | V79: =E79*P79 -> 3025
A80: 14 | B80: 窗户自动开关器 | C80: 1、窗户自动开关器 | D80: 个 | E80: 6 | F80: =I80 -> 800 | G80: =F80*E80 -> 4800 | I80: =J80+J80*K80+L80+M80+N80 -> 800 | J80: =Q80*$Q$1 -> 800 | K80: =R80 -> 0 | L80: =S80*$S$1 -> 0 | M80: =T80*$T$1 -> 0 | N80: =U80*$U$1 -> 0 | O80: =E80*I80 -> 4800 | P80: =Q80+Q80*R80+S80+T80+U80 -> 800 | Q80: 800 | R80: 0 | S80: 0 | T80: 0 | V80: =E80*P80 -> 4800
A81: （二） | B81: 弱电工程 | G81: =SUBTOTAL(9,G82:G83) -> 7981.6
A82: 1 | B82: 弱电部分（含信号线、网线，不含信号插座） | C82: 1、紧定式镀锌电线管 2、信号线、网线 3、智能模块 | D82: ㎡ | E82: ='报价汇总-装修工程'!D16 -> 193.76 | F82: =I82 -> 35 | G82: =F82*E82 -> 6781.6 | I82: =J82+J82*K82+L82+M82+N82 -> 35 | J82: =Q82*$Q$1 -> 10 | K82: =R82 -> 0 | L82: =S82*$S$1 -> 25 | M82: =T82*$T$1 -> 0 | N82: =U82*$U$1 -> 0 | O82: =E82*I82 -> 6781.6 | P82: =Q82+Q82*R82+S82+T82+U82 -> 35 | Q82: 10 | R82: 0 | S82: 25 | T82: 0 | V82: =E82*P82 -> 6781.6
A83: 2 | B83: 网络插座 | D83: 个 | E83: 40 | F83: =I83 -> 30 | G83: =F83*E83 -> 1200 | I83: =J83+J83*K83+L83+M83+N83 -> 30 | J83: =Q83*$Q$1 -> 20 | K83: =R83 -> 0 | L83: =S83*$S$1 -> 10 | M83: =T83*$T$1 -> 0 | N83: =U83*$U$1 -> 0 | O83: =E83*I83 -> 1200 | P83: =Q83+Q83*R83+S83+T83+U83 -> 30 | Q83: 20 | R83: 0 | S83: 10 | T83: 0 | V83: =E83*P83 -> 1200
A84: 三 | B84: 其他工程 | G84: =SUBTOTAL(9,G85:G91) -> 24812.15
A85: 1 | B85: 垃圾清运费 | C85: 1.将垃圾运至物业指定小区内装修垃圾存放点。2.物业运至外部垃圾厂。（含物业收取的垃圾外运费） | D85: ㎡ | E85: 319.15 | F85: =I85 -> 30 | G85: =F85*E85 -> 9574.5 | H85: ='报价汇总-装修工程'!F16 -> 建筑面积319.15㎡ | I85: 30 | J85: =Q85*$Q$1 -> 30 | K85: =R85 -> 0 | L85: =S85*$S$1 -> 0 | M85: =T85*$T$1 -> 0 | N85: =U85*$U$1 -> 0 | O85: =E85*I85 -> 9574.5 | P85: =Q85+Q85*R85+S85+T85+U85 -> 30 | Q85: 30 | V85: =E85*P85 -> 9574.5
A86: 2 | B86: 安全文明施工费 | D86: ㎡ | E86: =E85 -> 319.15 | F86: =I86 -> 15 | G86: =F86*E86 -> 4787.25 | H86: =H85 -> 建筑面积319.15㎡ | I86: 15 | J86: =Q86*$Q$1 -> 15 | K86: =R86 -> 0 | L86: =S86*$S$1 -> 0 | M86: =T86*$T$1 -> 0 | N86: =U86*$U$1 -> 0 | O86: =E86*I86 -> 4787.25 | P86: =Q86+Q86*R86+S86+T86+U86 -> 15 | Q86: 15 | V86: =E86*P86 -> 4787.25
A87: 3 | B87: 保洁交付 | D87: ㎡ | E87: ='报价汇总-装修工程'!D16 -> 193.76 | F87: =I87 -> 10 | G87: =F87*E87 -> 1937.6 | I87: 10 | J87: =Q87*$Q$1 -> 10 | K87: =R87 -> 0 | L87: =S87*$S$1 -> 0 | M87: =T87*$T$1 -> 0 | N87: =U87*$U$1 -> 0 | O87: =E87*I87 -> 1937.6 | P87: =Q87+Q87*R87+S87+T87+U87 -> 10 | Q87: 10 | V87: =E87*P87 -> 1937.6
A88: 4 | B88: 材料搬运费 | D88: ㎡ | E88: =E87 -> 193.76 | F88: =I88 -> 30 | G88: =F88*E88 -> 5812.8 | I88: 30 | J88: =Q88*$Q$1 -> 30 | K88: =R88 -> 0 | L88: =S88*$S$1 -> 0 | M88: =T88*$T$1 -> 0 | N88: =U88*$U$1 -> 0 | O88: =E88*I88 -> 5812.8 | P88: =Q88+Q88*R88+S88+T88+U88 -> 30 | Q88: 30 | V88: =E88*P88 -> 5812.8
A89: 5 | B89: 安全生产责任险 | D89: 项 | E89: 1 | F89: =I89 -> 1200 | G89: =F89*E89 -> 1200 | I89: 1200 | J89: =Q89*$Q$1 -> 1200 | K89: =R89 -> 0 | L89: =S89*$S$1 -> 0 | M89: =T89*$T$1 -> 0 | N89: =U89*$U$1 -> 0 | O89: =E89*I89 -> 1200 | P89: =Q89+Q89*R89+S89+T89+U89 -> 1200 | Q89: 1200 | V89: =E89*P89 -> 1200
A90: 6 | B90: 甲醛处理 | D90: ㎡ | E90: =E87 -> 193.76 | F90: 0 | G90: =F90*E90 -> 0 | I90: 20 | J90: =Q90*$Q$1 -> 20 | K90: =R90 -> 0 | L90: =S90*$S$1 -> 0 | M90: =T90*$T$1 -> 0 | N90: =U90*$U$1 -> 0 | O90: =E90*I90 -> 3875.2 | P90: =Q90+Q90*R90+S90+T90+U90 -> 20 | Q90: 20 | V90: =E90*P90 -> 3875.2
A91: 7 | B91: 现场成品保护 | C91: 1.根据物业标准，电梯厅，过道地面、墙面全屋做成品保护 | D91: 项 | E91: 1 | F91: =I91 -> 1500 | G91: =F91*E91 -> 1500 | I91: 1500 | J91: =Q91*$Q$1 -> 1500 | K91: =R91 -> 0 | L91: =S91*$S$1 -> 0 | M91: =T91*$T$1 -> 0 | N91: =U91*$U$1 -> 0 | O91: =E91*I91 -> 1500 | P91: =Q91+Q91*R91+S91+T91+U91 -> 1500 | Q91: 1500 | V91: =E91*P91 -> 1500
A92: 四 | B92: 小计 | D92: 项 | E92: 1 | G92: =G3+G66+G84 -> 239782.42 | I92: =SUBTOTAL(9,G3:G91) -> 239782.42 | O92: =SUBTOTAL(9,O3:O91) -> 245430.34 | V92: =SUBTOTAL(9,V3:V91) -> 245055.84
A93: 五 | B93: 管理费 | C93: 0.035 | D93: 项 | E93: 1 | G93: =G92*C93 -> 8392.3847
A94: 六 | B94: 税金 | C94: 0.09 | D94: 项 | E94: 1 | G94: 0
A95: 七 | B95: 合计 | D95: 项 | E95: 1 | G95: =G94+G93+G92 -> 248174.8

Sheet 报价汇总-空调消防
B1: 岁宝壹品苑D栋3901办公室装修汇总 空调消防
A2: 序号 | B2: 名称 | C2: 金额（元） | D2: 面积（㎡） | E2: 单方价格（元/㎡） | F2: 备注
A3: 一 | B3: =空调消防清单!B3 -> 空调工程 | C3: =空调消防清单!G3 -> 66000
A4: 二 | B4: =空调消防清单!B6 -> 消防改造 | C4: =空调消防清单!G6 -> 26603.485
A5: 三 | B5: 合计：一+二 | C5: =C3+C4 -> 92603.485
A6: 四 | B6: 管理费 | C6: =空调消防清单!G38 -> 3241.122
A7: 五 | B7: 税金 | C7: =空调消防清单!G39 -> 0
A8: 六 | B8: 合计=三+四+五 | C8: =C5+C6+C7 -> 95844.607 | D8: 156.78 | E8: =C8/D8 -> 611.33185

Sheet 空调消防清单
A1: 岁宝壹品苑D栋3901办公室装修清单 空调消防 | I1: =G40 -> 95844.607 | O1: =G6 -> 26603.485 | Q1: =不含空调消防清单!Q1 -> 1 | S1: =不含空调消防清单!S1 -> 1 | T1: =不含空调消防清单!T1 -> 1 | U1: =不含空调消防清单!U1 -> 1
A2: 序号 | B2: 项目名称 | C2: 项目特征 | D2: 单位 | E2: 工程量 | F2: 综合单价（不含税） | G2: 合价 | H2: 备注 | I2: 综合单价（不含税） | J2: 主材费 | K2: 主材损耗率 | L2: 人工费 | M2: 辅材费 | N2: 机械费 | O2: 合计 | P2: 成本价 | Q2: 主材费 | R2: 主材损耗率 | S2: 人工费 | T2: 辅材费 | U2: 机械费 | V2: 成本合计
A3: 一 | B3: 空调工程 | G3: =SUBTOTAL(9,G4:G5) -> 66000
A4: 1 | B4: 空调风机盘管1P | C4: 1、包含铝合金风口、空调管道、帆布、钢结构支架等 | D4: 台 | E4: 7 | F4: 7200 | G4: =F4*E4 -> 50400 | I4: =J4+J4*K4+L4+M4+N4 -> 6000 | J4: =Q4*$Q$1 -> 6000 | K4: =R4 -> 0 | L4: =S4*$S$1 -> 0 | M4: =T4*$T$1 -> 0 | N4: =U4*$U$1 -> 0 | O4: =E4*I4 -> 42000 | P4: =Q4+Q4*R4+S4+T4+U4 -> 6000 | Q4: 6000 | V4: =E4*P4 -> 42000
A5: 1 | B5: 空调风机盘管2P | C5: 1、包含铝合金风口、空调管道、帆布、钢结构支架等 | D5: 台 | E5: 2 | F5: 7800 | G5: =F5*E5 -> 15600 | I5: =J5+J5*K5+L5+M5+N5 -> 6300 | J5: =Q5*$Q$1 -> 6300 | K5: =R5 -> 0 | L5: =S5*$S$1 -> 0 | M5: =T5*$T$1 -> 0 | N5: =U5*$U$1 -> 0 | O5: =E5*I5 -> 12600 | P5: =Q5+Q5*R5+S5+T5+U5 -> 6300 | Q5: 6300 | V5: =E5*P5 -> 12600
A6: 二 | B6: 消防改造 | G6: =SUBTOTAL(9,G8:G36) -> 26603.485
A7: （一） | B7: 火灾自动报警系统
A8: 1 | B8: 探测器拆除、安装 | C8: 1.名称：感烟 2.型号.规格： | D8: 套 | E8: 3 | F8: =I8 -> 191.4 | G8: =F8*E8 -> 574.2 | I8: 191.4 | J8: =Q8*$Q$1 -> 0 | K8: =R8 -> 0 | L8: =S8*$S$1 -> 0 | M8: =T8*$T$1 -> 0 | N8: =U8*$U$1 -> 0 | O8: =E8*I8 -> 574.2 | P8: =Q8+Q8*R8+S8+T8+U8 -> 0 | V8: =E8*P8 -> 0
A9: 2 | B9: 探测器新增、安装 | C9: 1.规格型号:感烟 2.其它：符合规范和设计要求 | D9: 套 | E9: 3 | F9: =I9 -> 261 | G9: =F9*E9 -> 783 | I9: 261 | J9: =Q9*$Q$1 -> 0 | K9: =R9 -> 0 | L9: =S9*$S$1 -> 0 | M9: =T9*$T$1 -> 0 | N9: =U9*$U$1 -> 0 | O9: =E9*I9 -> 783 | P9: =Q9+Q9*R9+S9+T9+U9 -> 0 | V9: =E9*P9 -> 0
A10: 3 | B10: 消防广播拆除、安装 | C10: 1.名称：消防广播 2.型号.规格： | D10: 套 | E10: 1 | F10: =I10 -> 191.4 | G10: =F10*E10 -> 191.4 | I10: 191.4 | J10: =Q10*$Q$1 -> 0 | K10: =R10 -> 0 | L10: =S10*$S$1 -> 0 | M10: =T10*$T$1 -> 0 | N10: =U10*$U$1 -> 0 | O10: =E10*I10 -> 191.4 | P10: =Q10+Q10*R10+S10+T10+U10 -> 0 | V10: =E10*P10 -> 0
A11: 4 | B11: 电气配管 | C11: 1.型号规格：JDG20 2.敷设形式：综合考虑 3.含接线盒 4.根据现场情况改造到位 | D11: 米 | E11: 20 | F11: =I11 -> 24.36 | G11: =F11*E11 -> 487.2 | I11: 24.36 | J11: =Q11*$Q$1 -> 0 | K11: =R11 -> 0 | L11: =S11*$S$1 -> 0 | M11: =T11*$T$1 -> 0 | N11: =U11*$U$1 -> 0 | O11: =E11*I11 -> 487.2 | P11: =Q11+Q11*R11+S11+T11+U11 -> 0 | V11: =E11*P11 -> 0
A12: 5 | B12: 金属软管 | C12: 1.型号规格：φ20 2.敷设形式：综合考虑 | D12: 米 | E12: 3 | F12: =I12 -> 10.44 | G12: =F12*E12 -> 31.32 | I12: 10.44 | J12: =Q12*$Q$1 -> 0 | K12: =R12 -> 0 | L12: =S12*$S$1 -> 0 | M12: =T12*$T$1 -> 0 | N12: =U12*$U$1 -> 0 | O12: =E12*I12 -> 31.32 | P12: =Q12+Q12*R12+S12+T12+U12 -> 0 | V12: =E12*P12 -> 0
A13: 6 | B13: 电气配线 | C13: 1.名称:阻燃屏蔽双绞线 2.型号规格：ZR-RVS-2*1.5mm 3.敷设方式：穿管及线槽敷设 | D13: 米 | E13: 40 | F13: =I13 -> 6.96 | G13: =F13*E13 -> 278.4 | I13: 6.96 | J13: =Q13*$Q$1 -> 0 | K13: =R13 -> 0 | L13: =S13*$S$1 -> 0 | M13: =T13*$T$1 -> 0 | N13: =U13*$U$1 -> 0 | O13: =E13*I13 -> 278.4 | P13: =Q13+Q13*R13+S13+T13+U13 -> 0 | V13: =E13*P13 -> 0
A14: 7 | B14: 报警系统调试 | C14: 1、仅限我司施工 的项目 | D14: 项 | E14: 1 | F14: =I14 -> 800 | G14: =F14*E14 -> 800 | I14: 800 | J14: =Q14*$Q$1 -> 0 | K14: =R14 -> 0 | L14: =S14*$S$1 -> 0 | M14: =T14*$T$1 -> 0 | N14: =U14*$U$1 -> 0 | O14: =E14*I14 -> 800 | P14: =Q14+Q14*R14+S14+T14+U14 -> 0 | V14: =E14*P14 -> 0
A15: 8 | B15: 编程入网、系统接驳 | C15: 1、由大厦原消防施工单位负责，物业统一收费 | D15: ㎡ | E15: =不含空调消防清单!E85 -> 319.15 | F15: =I15 -> 30 | G15: =F15*E15 -> 9574.5 | H15: 不足4000元的按最低4000元计算。超过4000元的按建筑面积30元/㎡计算。 | I15: 30 | J15: =Q15*$Q$1 -> 0 | K15: =R15 -> 0 | L15: =S15*$S$1 -> 20 | M15: =T15*$T$1 -> 0 | N15: =U15*$U$1 -> 0 | O15: =E15*I15 -> 9574.5 | P15: =Q15+Q15*R15+S15+T15+U15 -> 20 | S15: 20 | V15: =E15*P15 -> 6383
A16: （二） | B16: 自动喷淋灭火系统 | G16: =F16*E16 -> 0
A17: 1 | B17: 保护性拆除明装喷头 | C17: 1.名称：上喷头保护性拆除 2.型号.规格： | D17: 个 | E17: 10 | F17: =I17 -> 174 | G17: =F17*E17 -> 1740 | I17: 174 | J17: =Q17*$Q$1 -> 0 | K17: =R17 -> 0 | L17: =S17*$S$1 -> 0 | M17: =T17*$T$1 -> 0 | N17: =U17*$U$1 -> 0 | O17: =E17*I17 -> 1740 | P17: =Q17+Q17*R17+S17+T17+U17 -> 0 | V17: =E17*P17 -> 0
A18: 2 | B18: 明装喷头 | C18: 1.名称：明装喷头 2.型号.规格： 3.其它：符合规范和设计要求 | D18: 个 | E18: 12 | F18: =I18 -> 217.5 | G18: =F18*E18 -> 2610 | I18: 217.5 | J18: =Q18*$Q$1 -> 0 | K18: =R18 -> 0 | L18: =S18*$S$1 -> 0 | M18: =T18*$T$1 -> 0 | N18: =U18*$U$1 -> 0 | O18: =E18*I18 -> 2610 | P18: =Q18+Q18*R18+S18+T18+U18 -> 0 | V18: =E18*P18 -> 0
A19: 3 | B19: 管网支吊架 | C19: 1、含钢制作、安装 | D19: KG | E19: 12 | F19: =I19 -> 21.75 | G19: =F19*E19 -> 261 | I19: 21.75 | J19: =Q19*$Q$1 -> 0 | K19: =R19 -> 0 | L19: =S19*$S$1 -> 0 | M19: =T19*$T$1 -> 0 | N19: =U19*$U$1 -> 0 | O19: =E19*I19 -> 261 | P19: =Q19+Q19*R19+S19+T19+U19 -> 0 | V19: =E19*P19 -> 0
A20: 4 | B20: 大红油漆（含人工及天那水） | C20: 1、含油漆、天那水、人工 | D20: 桶 | E20: 1 | F20: =I20 -> 435 | G20: =F20*E20 -> 435 | I20: 435 | J20: =Q20*$Q$1 -> 0 | K20: =R20 -> 0 | L20: =S20*$S$1 -> 0 | M20: =T20*$T$1 -> 0 | N20: =U20*$U$1 -> 0 | O20: =E20*I20 -> 435 | P20: =Q20+Q20*R20+S20+T20+U20 -> 0 | V20: =E20*P20 -> 0
A21: 5 | B21: 消防喷淋管 DN25 | C21: 1.安装部位：室内 2.介质:喷淋给水 3.材质、规格:内外壁热镀锌钢管DN25 4.连接方式:螺纹连接 含管件 5.其他要求:满足施工图纸技术规范要求 | D21: 米 | E21: 16.5 | F21: =I21 -> 50.46 | G21: =F21*E21 -> 832.59 | I21: 50.46 | J21: =Q21*$Q$1 -> 0 | K21: =R21 -> 0 | L21: =S21*$S$1 -> 0 | M21: =T21*$T$1 -> 0 | N21: =U21*$U$1 -> 0 | O21: =E21*I21 -> 832.59 | P21: =Q21+Q21*R21+S21+T21+U21 -> 0 | V21: =E21*P21 -> 0
A22: 6 | B22: 消防喷淋管 DN32 | C22: 1.安装部位：室内 2.介质:喷淋给水 3.材质、规格:内外壁热镀锌钢管DN32 4.连接方式:螺纹连接 含管件 5.其他要求:满足施工图纸技术规范要求 | D22: 米 | E22: 8.5 | F22: =I22 -> 56.55 | G22: =F22*E22 -> 480.675 | I22: 56.55 | J22: =Q22*$Q$1 -> 0 | K22: =R22 -> 0 | L22: =S22*$S$1 -> 0 | M22: =T22*$T$1 -> 0 | N22: =U22*$U$1 -> 0 | O22: =E22*I22 -> 480.675 | P22: =Q22+Q22*R22+S22+T22+U22 -> 0 | V22: =E22*P22 -> 0
A23: 7 | B23: 消防喷淋管 DN40 | C23: 1.安装部位：室内 2.介质:喷淋给水 3.材质、规格:内外壁热镀锌钢管DN40 4.连接方式:螺纹连接 含管件 5.其他要求:满足施工图纸技术规范要求 | D23: 米 | E23: 3.5 | F23: =I23 -> 65.25 | G23: =F23*E23 -> 228.375 | I23: 65.25 | J23: =Q23*$Q$1 -> 0 | K23: =R23 -> 0 | L23: =S23*$S$1 -> 0 | M23: =T23*$T$1 -> 0 | N23: =U23*$U$1 -> 0 | O23: =E23*I23 -> 228.375 | P23: =Q23+Q23*R23+S23+T23+U23 -> 0 | V23: =E23*P23 -> 0
A24: 8 | B24: 消防喷淋管 DN50 | C24: 1.安装部位：室内 2.介质:喷淋给水 3.材质、规格:内外壁热镀锌钢管DN50 4.连接方式:螺纹连接 含管件 5.其他要求:满足施工图纸技术规范要求 | D24: 米 | E24: 2.5 | F24: =I24 -> 80.91 | G24: =F24*E24 -> 202.275 | I24: 80.91 | J24: =Q24*$Q$1 -> 0 | K24: =R24 -> 0 | L24: =S24*$S$1 -> 0 | M24: =T24*$T$1 -> 0 | N24: =U24*$U$1 -> 0 | O24: =E24*I24 -> 202.275 | P24: =Q24+Q24*R24+S24+T24+U24 -> 0 | V24: =E24*P24 -> 0
A25: 9 | B25: 喷淋管网排水费 | C25: 1、含管网排水费及人工 | D25: 项 | E25: 1 | F25: =I25 -> 800 | G25: =F25*E25 -> 800 | I25: 800 | J25: =Q25*$Q$1 -> 0 | K25: =R25 -> 0 | L25: =S25*$S$1 -> 0 | M25: =T25*$T$1 -> 0 | N25: =U25*$U$1 -> 0 | O25: =E25*I25 -> 800 | P25: =Q25+Q25*R25+S25+T25+U25 -> 0 | V25: =E25*P25 -> 0
A26: 10 | B26: 喷淋管网试压 | C26: 1、管网冲洗、试压、调试 | D26: 项 | E26: 1 | F26: =I26 -> 870 | G26: =F26*E26 -> 870 | I26: 870 | J26: =Q26*$Q$1 -> 0 | K26: =R26 -> 0 | L26: =S26*$S$1 -> 0 | M26: =T26*$T$1 -> 0 | N26: =U26*$U$1 -> 0 | O26: =E26*I26 -> 870 | P26: =Q26+Q26*R26+S26+T26+U26 -> 0 | V26: =E26*P26 -> 0
A27: （三） | B27: 机械排烟系统
A28: 1 | B28: 镀锌风管拆除、移位 | D28: ㎡ | E28: 4.5 | F28: =I28 -> 156.6 | G28: =F28*E28 -> 704.7 | I28: 156.6 | J28: =Q28*$Q$1 -> 0 | K28: =R28 -> 0 | L28: =S28*$S$1 -> 0 | M28: =T28*$T$1 -> 0 | N28: =U28*$U$1 -> 0 | O28: =E28*I28 -> 704.7 | P28: =Q28+Q28*R28+S28+T28+U28 -> 0 | V28: =E28*P28 -> 0
A29: 2 | B29: 镀锌风管新增、安装 | C29: 1.风管的制作与安装 2.法兰、支架的制作、防锈与安装固定 | D29: ㎡ | E29: 1.5 | F29: =I29 -> 147.9 | G29: =F29*E29 -> 221.85 | I29: 147.9 | J29: =Q29*$Q$1 -> 0 | K29: =R29 -> 0 | L29: =S29*$S$1 -> 0 | M29: =T29*$T$1 -> 0 | N29: =U29*$U$1 -> 0 | O29: =E29*I29 -> 221.85 | P29: =Q29+Q29*R29+S29+T29+U29 -> 0 | V29: =E29*P29 -> 0
A30: 3 | B30: 风管防火包裹 | D30: ㎡ | E30: 3 | F30: =I30 -> 87 | G30: =F30*E30 -> 261 | I30: 87 | J30: =Q30*$Q$1 -> 0 | K30: =R30 -> 0 | L30: =S30*$S$1 -> 0 | M30: =T30*$T$1 -> 0 | N30: =U30*$U$1 -> 0 | O30: =E30*I30 -> 261 | P30: =Q30+Q30*R30+S30+T30+U30 -> 0 | V30: =E30*P30 -> 0
A31: 4 | B31: 280℃防火阀拆除、安装 | C31: 1.型号：防火阀280℃ 2.包含设备及辅材安装费 3.包含电源线接驳 | D31: 套 | E31: 1 | F31: =I31 -> 870 | G31: =F31*E31 -> 870 | I31: 870 | J31: =Q31*$Q$1 -> 0 | K31: =R31 -> 0 | L31: =S31*$S$1 -> 0 | M31: =T31*$T$1 -> 0 | N31: =U31*$U$1 -> 0 | O31: =E31*I31 -> 870 | P31: =Q31+Q31*R31+S31+T31+U31 -> 0 | V31: =E31*P31 -> 0
A32: 5 | B32: 常开百叶风口 | C32: 1、规格：成品铝框架百叶风口供货及安装 2、包含但不限于编制说明、图纸、技术要求中的相关内容及完成该项目的一切所需 | D32: 个 | E32: 2 | F32: =I32 -> 348 | G32: =F32*E32 -> 696 | I32: 348 | J32: =Q32*$Q$1 -> 0 | K32: =R32 -> 0 | L32: =S32*$S$1 -> 0 | M32: =T32*$T$1 -> 0 | N32: =U32*$U$1 -> 0 | O32: =E32*I32 -> 696 | P32: =Q32+Q32*R32+S32+T32+U32 -> 0 | V32: =E32*P32 -> 0
A33: 6 | B33: 排烟系统调试 | D33: 项 | E33: 1 | F33: =I33 -> 800 | G33: =F33*E33 -> 800 | I33: 800 | J33: =Q33*$Q$1 -> 0 | K33: =R33 -> 0 | L33: =S33*$S$1 -> 0 | M33: =T33*$T$1 -> 0 | N33: =U33*$U$1 -> 0 | O33: 1000 | P33: =Q33+Q33*R33+S33+T33+U33 -> 0 | V33: =E33*P33 -> 0
A34: （四） | B34: 其他
A35: 1 | B35: 消防报验 | C35: 含相关部门收取的报验费用。 | D35: 项 | E35: 1 | F35: =I35 -> 1000 | G35: =F35*E35 -> 1000 | I35: 1000 | J35: =Q35*$Q$1 -> 0 | K35: =R35 -> 0 | L35: =S35*$S$1 -> 0 | M35: =T35*$T$1 -> 0 | N35: =U35*$U$1 -> 0 | O35: 1500 | P35: =Q35+Q35*R35+S35+T35+U35 -> 0 | V35: =E35*P35 -> 0
A36: 2 | B36: 综合专业设计出图 | D36: 套 | E36: 1 | F36: =I36 -> 870 | G36: =F36*E36 -> 870 | I36: 870 | P36: =Q36+Q36*R36+S36+T36+U36 -> 0 | V36: =E36*P36 -> 0
A37: 三 | B37: 小计 | D37: 项 | E37: 1 | G37: =G3+G6 -> 92603.485 | I37: =SUBTOTAL(9,G3:G36) -> 92603.485
A38: 四 | B38: 管理费 | C38: =不含空调消防清单!C93 -> 0.035 | D38: 项 | E38: 1 | G38: =G37*C38 -> 3241.122
A39: 五 | B39: 税金 | C39: =不含空调消防清单!C94 -> 0.09 | D39: 项 | E39: 1 | G39: 0
A40: 六 | B40: 合计 | D40: 项 | E40: 1 | G40: =G39+G38+G37 -> 95844.607

Sheet 材料设备参考品牌
A1: 3901材料设备参考品牌
A2: 序号 | B2: 专业 | C2: 材料名称 | D2: 中高档品牌，报两三个品牌 | E2: 备注
A3: 1 | B3: 装饰 | C3: 地砖 | D3: 玛格罗兰、简一
A4: 2 | B4: 装饰 | C4: 岩板（800*1600） | D4: 伊诺、玛格罗兰
A5: 3 | B5: 装饰 | C5: 木饰面 | D5: 定制
A6: 4 | B6: 装饰 | C6: 不锈钢 | D6: 国产优质
A7: 5 | B7: 装饰 | C7: 石膏板 | D7: 深耐福
A8: 6 | B8: 装饰 | C8: 夹板、阻燃板 | D8: 深耐福
A9: 7 | B9: 装饰 | C9: 艺术漆 | D9: =D6 -> 国产优质
A10: 8 | B10: 装饰 | C10: 乳胶漆 | D10: 立邦
A11: 9 | B11: 装饰 | C11: 腻子 | D11: 立邦
A12: 10 | B12: 安装 | C12: 照明，强电用线 | D12: 南洋
A13: 11 | B13: 安装 | C13: 灯具（射灯、筒灯） | D13: 三雄、欧普
A14: 12 | B14: 安装 | C14: LED灯带 | D14: 三雄、欧普
A15: 13 | B15: 安装 | C15: 照明开关 | D15: 公牛
A16: 14 | B16: 安装 | C16: 插座 | D16: 公牛
A17: 15 | B17: 安装 | C17: 网络插座 | D17: 公牛
A18: 16 | B18: 安装 | C18: 信号线、网线 | D18: 海康
A19: 17 | B19: 空调 | C19: 空调风机盘管 | D19: 麦克维尔
A20: 18 | B20: 安装 | C20: 电动窗帘电机 | D20: 国产杜亚
