Workbook

Sheet 报价汇总-装修工程
B1: 岁宝壹品苑D栋3206办公室装修汇总 装修工程
A2: 序号 | B2: 名称 | C2: 金额（元） | D2: 面积（㎡） | E2: 单方价格（元/㎡） | F2: 备注
A3: 一 | B3: 装饰工程 | C3: =不含空调消防清单!G3 -> 317676.81 | G3: 成本
A4: （一） | B4: 隔墙工程 | C4: =不含空调消防清单!G4 -> 24078.489 | G4: 装饰 | H4: 346675.71
A5: （二） | B5: 地面工程 | C5: =不含空调消防清单!G26 -> 137888 | G5: 空调 | H5: 30000
A6: （三） | B6: 天花工程 | C6: =不含空调消防清单!G31 -> 53883.904 | G6: 消防 | H6: 17789.3
A7: （四） | B7: 墙面工程 | C7: =不含空调消防清单!G43 -> 59987.487 | G7: 合计 | H7: =SUM(H4:H6) -> 394465.01
A8: （五） | B8: 固定家具及门窗工程 | C8: =不含空调消防清单!G55 -> 41838.936 | H8: =C13+C14+'报价汇总-空调消防'!C5+'报价汇总-空调消防'!C6 -> 475364.98
A9: 二 | B9: 安装工程 | C9: =不含空调消防清单!G78 -> 44640.75 | H9: =(H8-H7)/H7 -> 0.20508782
A10: （一） | B10: 强电工程 | C10: =不含空调消防清单!G79 -> 38883.45
A11: （二） | B11: 弱电工程 | C11: =不含空调消防清单!G94 -> 5757.3
A12: 三 | B12: 其他工程 | C12: =不含空调消防清单!G97 -> 27090.75
A13: 四 | B13: 小计：一+二+三 | C13: =C3+C9+C12 -> 389408.31
A14: 五 | B14: 管理费 | C14: =不含空调消防清单!G106 -> 19470.416
A15: 六 | B15: 税金 | C15: =不含空调消防清单!G107 -> 36799.086
A16: 七 | B16: 装饰合计=四+五+六 | C16: =C13+C14+C15 -> 445677.82 | D16: 156.78 | E16: =C16/D16 -> 2842.6956
A17: 八 | B17: 消防空调 | C17: ='报价汇总-空调消防'!C8 -> 72470.009 | D17: 156.78 | E17: =C17/D17 -> 462.24014
A18: 九 | B18: 总计: （装饰+消防空调） | C18: =C16+C17 -> 518147.82 | D18: 156.78 | E18: =C18/D18 -> 3304.9357
A19: 十 | B19: 施工图、效果图设计费 | C19: -24000
A20: 十一 | B20: 共计:九+十 | C20: =C18+C19 -> 494147.82 | D20: 156.78 | E20: =C20/D20 -> 3151.855

Sheet 不含空调消防清单
A1: 岁宝壹品苑D栋3206办公室装修清单（不含空调消防） | I1: =G108 -> 445677.82 | Q1: 1 | S1: =$Q$1 -> 1 | T1: =$Q$1 -> 1 | U1: =$Q$1 -> 1 | V1: ='报价汇总-装修工程'!G17 -> 0
A2: 序号 | B2: 项目名称 | C2: 项目特征 | D2: 单位 | E2: 工程量 | F2: 综合单价（不含税） | G2: 合价 | H2: 备注 | I2: 综合单价（不含税） | J2: 主材费 | K2: 主材损耗率 | L2: 人工费 | M2: 辅材费 | N2: 机械费 | O2: 合计 | P2: 成本价 | Q2: 主材费 | R2: 主材损耗率 | S2: 人工费 | T2: 辅材费 | U2: 机械费 | V2: 成本合计
A3: 一 | B3: 装饰工程 | G3: =SUBTOTAL(9,G4:G77) -> 317676.81
A4: （一） | B4: 隔墙工程 | G4: =SUBTOTAL(9,G5:G25) -> 24078.489
A5: 1.1 | B5: 拆除原有砖墙 （200mm厚） | C5: 1、人工拆除 2、机械设备 3、防护措施 4、垃圾清理装袋 | D5: ㎡ | E5: =0.9*2.8*2+1.63*0.4 -> 5.692 | F5: =I5 -> 100 | G5: =F5*E5 -> 569.2 | I5: =J5+J5*K5+L5+M5+N5 -> 100 | J5: =Q5*$Q$1 -> 0 | K5: =R5 -> 0 | L5: =S5*$S$1 -> 70 | M5: =T5*$T$1 -> 30 | N5: =U5*$U$1 -> 0 | O5: =E5*I5 -> 569.2 | P5: =Q5+Q5*R5+S5+T5+U5 -> 100 | S5: 70 | T5: 30 | V5: =E5*P5 -> 569.2
A6: 1.2 | B6: 横梁槽钢加固 | C6: 1、原墙面开门洞后横梁槽钢加固 | D6: m | E6: 3.4 | F6: =I6 -> 500 | G6: =F6*E6 -> 1700 | I6: =J6+J6*K6+L6+M6+N6 -> 500 | J6: =Q6*$Q$1 -> 300 | K6: =R6 -> 0 | L6: =S6*$S$1 -> 200 | M6: =T6*$T$1 -> 0 | N6: =U6*$U$1 -> 0 | O6: =E6*I6 -> 1700 | P6: =Q6+Q6*R6+S6+T6+U6 -> 500 | Q6: 300 | S6: 200 | V6: =E6*P6 -> 1700
A7: 1.3 | B7: 水泥砂浆修补 | C7: 1、门洞侧边水泥砂浆修补 | D7: m | E7: =(2.8*2+3.4) -> 9 | F7: =I7 -> 31.12 | G7: =F7*E7 -> 280.08 | I7: =J7+J7*K7+L7+M7+N7 -> 31.12 | J7: =Q7*$Q$1 -> 6 | K7: =R7 -> 0.02 | L7: =S7*$S$1 -> 25 | M7: =T7*$T$1 -> 0 | N7: =U7*$U$1 -> 0 | O7: =E7*I7 -> 280.08 | P7: =Q7+Q7*R7+S7+T7+U7 -> 31.12 | Q7: =12*0.5 -> 6 | R7: 0.02 | S7: 25 | V7: =E7*P7 -> 280.08
A8: 1.4 | B8: 12mm阻燃夹板封边 | C8: 1、原墙面开门洞后12mm阻燃夹板封边 | D8: m | E8: =(2.8*2+3.4) -> 9 | F8: =I8 -> 25.6 | G8: =F8*E8 -> 230.4 | I8: =J8+J8*K8+L8+M8+N8 -> 25.6 | J8: =Q8*$Q$1 -> 5.6 | K8: =R8 -> 0 | L8: =S8*$S$1 -> 20 | M8: =T8*$T$1 -> 0 | N8: =U8*$U$1 -> 0 | O8: =E8*I8 -> 230.4 | P8: =Q8+Q8*R8+S8+T8+U8 -> 25.6 | Q8: =28*0.2 -> 5.6 | S8: 20 | V8: =E8*P8 -> 230.4
A9: 2 | B9: 轻钢龙骨隔墙 | C9: 双层双面轻钢龙骨隔墙 1、墙厚120mm; 2、75mm轻钢龙骨； 3、50mm厚，48kg/m3的吸音棉； 4、12mm阻燃夹板+9.5mm厚石膏板 | D9: ㎡ | E9: =3.81*(2+0.57+6.23+0.75+2+0.35+0.6+4.93)-0.7*2.4 -> 64.7283 | I9: =J9+J9*K9+L9+M9+N9 -> 0 | J9: =Q9*$Q$1 -> 0 | K9: =R9 -> 0 | L9: =S9*$S$1 -> 0 | M9: =T9*$T$1 -> 0 | N9: =U9*$U$1 -> 0 | O9: =E9*I9 -> 0 | P9: =Q9+Q9*R9+S9+T9+U9 -> 0 | V9: =E9*P9 -> 0
A10: 2.1 | B10: 轻钢龙骨 | C10: 1、天地龙骨 2、竖龙骨 3、穿心龙骨 4、其他辅材 | D10: ㎡ | E10: =3.81*(2+0.57+6.23+0.75+2+0.35+0.6+4.93)-0.7*2.4 -> 64.7283 | F10: =I10 -> 53.5 | G10: =F10*E10 -> 3462.9641 | I10: =J10+J10*K10+L10+M10+N10 -> 53.5 | J10: =Q10*$Q$1 -> 26 | K10: =R10 -> 0 | L10: =S10*$S$1 -> 26 | M10: =T10*$T$1 -> 0 | N10: =U10*$U$1 -> 1.5 | O10: =E10*I10 -> 3462.9641 | P10: =Q10+Q10*R10+S10+T10+U10 -> 53.5 | Q10: 26 | S10: 26 | U10: 1.5 | V10: =E10*P10 -> 3462.9641
A11: 2.2 | B11: 50mm厚吸音棉 | C11: 1、50mm厚，48kg/m3的吸音棉 | D11: ㎡ | E11: =3.81*(2+0.57+6.23+0.75+2+0.35+0.6+4.93)-0.7*2.4 -> 64.7283 | F11: =I11 -> 21.65 | G11: =F11*E11 -> 1401.3677 | I11: =J11+J11*K11+L11+M11+N11 -> 21.65 | J11: =Q11*$Q$1 -> 11.65 | K11: =R11 -> 0 | L11: =S11*$S$1 -> 10 | M11: =T11*$T$1 -> 0 | N11: =U11*$U$1 -> 0 | O11: =E11*I11 -> 1401.3677 | P11: =Q11+Q11*R11+S11+T11+U11 -> 21.65 | Q11: 11.65 | S11: 10 | V11: =E11*P11 -> 1401.3677
A12: 2.3 | B12: 12mm阻燃夹板 | C12: 1、单层12mm阻燃夹板打底 | D12: ㎡ | E12: =3.81*(2+0.57+6.23+0.75+2+0.35+0.6+4.93)-0.7*2.4 -> 64.7283 | F12: =I12 -> 48.8 | G12: =F12*E12 -> 3158.741 | I12: =J12+J12*K12+L12+M12+N12 -> 48.8 | J12: =Q12*$Q$1 -> 28 | K12: =R12 -> 0 | L12: =S12*$S$1 -> 20 | M12: =T12*$T$1 -> 0.8 | N12: =U12*$U$1 -> 0 | O12: =E12*I12 -> 3158.741 | P12: =Q12+Q12*R12+S12+T12+U12 -> 48.8 | Q12: 28 | S12: 20 | T12: 0.8 | V12: =E12*P12 -> 3158.741
A13: 2.4 | B13: 9.5mm厚石膏板 | C13: 1、双面单层9.5mm厚石膏板 | D13: ㎡ | E13: =E10*2.5 -> 161.82075 | F13: =I13 -> 28.3 | G13: =F13*E13 -> 4579.5272 | I13: =J13+J13*K13+L13+M13+N13 -> 28.3 | J13: =Q13*$Q$1 -> 7.5 | K13: =R13 -> 0 | L13: =S13*$S$1 -> 20 | M13: =T13*$T$1 -> 0.8 | N13: =U13*$U$1 -> 0 | O13: =E13*I13 -> 4579.5272 | P13: =Q13+Q13*R13+S13+T13+U13 -> 28.3 | Q13: =7.5 -> 7.5 | S13: 20 | T13: 0.8 | V13: =E13*P13 -> 4579.5272
A14: 3.1 | B14: GL-01 10mm厚钢化玻璃隔断 （总裁办公室、大门处） | C14: 1、GL-01 10mm厚钢化玻璃; 2、玻璃胶收口 | D14: ㎡ | E14: =2.8*(7.73-0.6-1.7+0.89*2) -> 20.188 | F14: =I14 -> 181.6 | G14: =F14*E14 -> 3666.1408 | I14: =J14+J14*K14+L14+M14+N14 -> 181.6 | J14: =Q14*$Q$1 -> 110 | K14: =R14 -> 0.01 | L14: =S14*$S$1 -> 60 | M14: =T14*$T$1 -> 10.5 | N14: =U14*$U$1 -> 0 | O14: =E14*I14 -> 3666.1408 | P14: =Q14+Q14*R14+S14+T14+U14 -> 181.6 | Q14: =110 -> 110 | R14: 0.01 | S14: 60 | T14: 10.5 | V14: =E14*P14 -> 3666.1408
A15: 3.2 | B15: 不锈钢包边 （总裁办公室、大门处） | C15: 1、MT-01不锈钢 2、12mm厚阻燃夹板 | D15: ㎡ | E15: =0.2*(7.73-0.6-1.7+2.8*2+3.4+2.8*2) -> 4.006 | F15: =I15 -> 409.35 | G15: =F15*E15 -> 1639.8561 | I15: =J15+J15*K15+L15+M15+N15 -> 409.35 | J15: =Q15*$Q$1 -> 285 | K15: =R15 -> 0.01 | L15: =S15*$S$1 -> 90 | M15: =T15*$T$1 -> 31.5 | N15: =U15*$U$1 -> 0 | O15: =E15*I15 -> 1639.8561 | P15: =Q15+Q15*R15+S15+T15+U15 -> 409.35 | Q15: 285 | R15: 0.01 | S15: =30+60 -> 90 | T15: =28+3.5 -> 31.5 | V15: =E15*P15 -> 1639.8561
A16: 4 | B16: 钢化玻璃隔断上方封板 | C16: 双层双面钢结构龙骨隔墙 1、墙厚120mm; 2、钢结构龙骨； 3、50mm厚，48kg/m3的吸音棉； 4、12mm厚阻燃夹板+9.5mm厚石膏板 | D16: ㎡ | E16: =1.31*(7.73-0.6-1.7) -> 7.1133 | I16: =J16+J16*K16+L16+M16+N16 -> 0 | J16: =Q16*$Q$1 -> 0 | K16: =R16 -> 0 | L16: =S16*$S$1 -> 0 | M16: =T16*$T$1 -> 0 | N16: =U16*$U$1 -> 0 | O16: =E16*I16 -> 0 | V16: =E16*P16 -> 0
A17: 4.1 | B17: 钢结构龙骨 | C17: 1、钢结构龙骨 2、刷防锈漆 3、其他辅材 | D17: ㎡ | E17: =E16 -> 7.1133 | F17: =I17 -> 91.5 | G17: =F17*E17 -> 650.86695 | I17: =J17+J17*K17+L17+M17+N17 -> 91.5 | J17: =Q17*$Q$1 -> 55 | K17: =R17 -> 0 | L17: =S17*$S$1 -> 35 | M17: =T17*$T$1 -> 0 | N17: =U17*$U$1 -> 1.5 | O17: =E17*I17 -> 650.86695 | P17: =Q17+Q17*R17+S17+T17+U17 -> 91.5 | Q17: 55 | S17: 35 | U17: 1.5 | V17: =E17*P17 -> 650.86695
A18: 4.2 | B18: 50mm厚吸音棉 | C18: 1、50mm厚，48kg/m3的吸音棉 | D18: ㎡ | E18: =E16 -> 7.1133 | F18: =I18 -> 21.65 | G18: =F18*E18 -> 154.00295 | I18: =J18+J18*K18+L18+M18+N18 -> 21.65 | J18: =Q18*$Q$1 -> 11.65 | K18: =R18 -> 0 | L18: =S18*$S$1 -> 10 | M18: =T18*$T$1 -> 0 | N18: =U18*$U$1 -> 0 | O18: =E18*I18 -> 154.00295 | P18: =Q18+Q18*R18+S18+T18+U18 -> 21.65 | Q18: 11.65 | S18: 10 | V18: =E18*P18 -> 154.00295
A19: 4.3 | B19: 12mm阻燃夹板 | C19: 1、单层12mm阻燃夹板打底 | D19: ㎡ | E19: =E16*2 -> 14.2266 | F19: =I19 -> 48.8 | G19: =F19*E19 -> 694.25808 | I19: =J19+J19*K19+L19+M19+N19 -> 48.8 | J19: =Q19*$Q$1 -> 28 | K19: =R19 -> 0 | L19: =S19*$S$1 -> 20 | M19: =T19*$T$1 -> 0.8 | N19: =U19*$U$1 -> 0 | O19: =E19*I19 -> 694.25808 | P19: =Q19+Q19*R19+S19+T19+U19 -> 48.8 | Q19: 28 | S19: 20 | T19: 0.8 | V19: =E19*P19 -> 694.25808
A20: 4.4 | B20: 9.5mm厚石膏板 | C20: 1、双面单层9.5mm厚石膏板 | D20: ㎡ | E20: =E16*2 -> 14.2266 | F20: =I20 -> 28.3 | G20: =F20*E20 -> 402.61278 | I20: =J20+J20*K20+L20+M20+N20 -> 28.3 | J20: =Q20*$Q$1 -> 7.5 | K20: =R20 -> 0 | L20: =S20*$S$1 -> 20 | M20: =T20*$T$1 -> 0.8 | N20: =U20*$U$1 -> 0 | O20: =E20*I20 -> 402.61278 | P20: =Q20+Q20*R20+S20+T20+U20 -> 28.3 | Q20: =7.5 -> 7.5 | S20: 20 | T20: 0.8 | V20: =E20*P20 -> 402.61278
A21: 5 | B21: 隐藏式折叠门上方钢结构加固封板 | C21: 双层双面钢结构龙骨隔墙 1、墙厚120mm; 2、钢结构龙骨； 3、50mm厚，48kg/m3的吸音棉； 4、12mm厚阻燃夹板+9.5mm厚石膏板 | D21: ㎡ | E21: =1.31*4.25 -> 5.5675 | I21: =J21+J21*K21+L21+M21+N21 -> 171.4 | J21: =Q21*$Q$1 -> 90 | K21: =R21 -> 0.01 | L21: =S21*$S$1 -> 70 | M21: =T21*$T$1 -> 10.5 | N21: =U21*$U$1 -> 0 | O21: =E21*I21 -> 954.2695 | P21: =Q21+Q21*R21+S21+T21+U21 -> 171.4 | Q21: =35*2+10*2 -> 90 | R21: 0.01 | S21: 70 | T21: 10.5 | V21: =E21*P21 -> 954.2695
A22: 5.1 | B22: 钢结构龙骨 | C22: 1、钢结构龙骨 2、刷防锈漆 3、其他辅材 | D22: ㎡ | E22: =E21 -> 5.5675 | F22: =I22 -> 91.5 | G22: =F22*E22 -> 509.42625 | I22: =J22+J22*K22+L22+M22+N22 -> 91.5 | J22: =Q22*$Q$1 -> 55 | K22: =R22 -> 0 | L22: =S22*$S$1 -> 35 | M22: =T22*$T$1 -> 0 | N22: =U22*$U$1 -> 1.5 | O22: =E22*I22 -> 509.42625 | P22: =Q22+Q22*R22+S22+T22+U22 -> 91.5 | Q22: 55 | S22: =S17 -> 35 | U22: 1.5 | V22: =E22*P22 -> 509.42625
A23: 5.2 | B23: 50mm厚吸音棉 | C23: 1、50mm厚，48kg/m3的吸音棉 | D23: ㎡ | E23: =E21 -> 5.5675 | F23: =I23 -> 21.65 | G23: =F23*E23 -> 120.53638 | I23: =J23+J23*K23+L23+M23+N23 -> 21.65 | J23: =Q23*$Q$1 -> 11.65 | K23: =R23 -> 0 | L23: =S23*$S$1 -> 10 | M23: =T23*$T$1 -> 0 | N23: =U23*$U$1 -> 0 | O23: =E23*I23 -> 120.53638 | P23: =Q23+Q23*R23+S23+T23+U23 -> 21.65 | Q23: 11.65 | S23: =S18 -> 10 | V23: =E23*P23 -> 120.53638
A24: 5.3 | B24: 12mm阻燃夹板 | C24: 1、单层12mm阻燃夹板打底 | D24: ㎡ | E24: =E21*2 -> 11.135 | F24: =I24 -> 48.8 | G24: =F24*E24 -> 543.388 | I24: =J24+J24*K24+L24+M24+N24 -> 48.8 | J24: =Q24*$Q$1 -> 28 | K24: =R24 -> 0 | L24: =S24*$S$1 -> 20 | M24: =T24*$T$1 -> 0.8 | N24: =U24*$U$1 -> 0 | O24: =E24*I24 -> 543.388 | P24: =Q24+Q24*R24+S24+T24+U24 -> 48.8 | Q24: 28 | S24: =S19 -> 20 | T24: 0.8 | V24: =E24*P24 -> 543.388
A25: 5.4 | B25: 9.5mm厚石膏板 | C25: 1、双面单层9.5mm厚石膏板 | D25: ㎡ | E25: =E21*2 -> 11.135 | F25: =I25 -> 28.3 | G25: =F25*E25 -> 315.1205 | I25: =J25+J25*K25+L25+M25+N25 -> 28.3 | J25: =Q25*$Q$1 -> 7.5 | K25: =R25 -> 0 | L25: =S25*$S$1 -> 20 | M25: =T25*$T$1 -> 0.8 | N25: =U25*$U$1 -> 0 | O25: =E25*I25 -> 315.1205 | P25: =Q25+Q25*R25+S25+T25+U25 -> 28.3 | Q25: =7.5 -> 7.5 | S25: =S20 -> 20 | T25: 0.8 | V25: =E25*P25 -> 315.1205
A26: （二） | B26: 地面工程 | G26: =SUBTOTAL(9,G27:G30) -> 137888
A27: 1 | B27: 100mm厚陶粒拌混泥土垫层 | C27: 1、100mm厚陶粒拌混泥土垫层 | D27: ㎡ | E27: =158.91-1.96 -> 156.95 | F27: =I27 -> 76.93 | G27: =F27*E27 -> 12074.164 | I27: =J27+J27*K27+L27+M27+N27 -> 76.93 | J27: =Q27*$Q$1 -> 43 | K27: =R27 -> 0.01 | L27: =S27*$S$1 -> 30 | M27: =T27*$T$1 -> 3.5 | N27: =U27*$U$1 -> 0 | O27: =E27*I27 -> 12074.164 | P27: =Q27+Q27*R27+S27+T27+U27 -> 76.93 | Q27: 43 | R27: 0.01 | S27: 30 | T27: 3.5 | U27: 0 | V27: =E27*P27 -> 12074.164
A28: 2 | B28: 地面岩板 | C28: 1、CT-01岩板9mm厚 2、规格：800*1600 3、专用胶泥结合层，厚度包干，后期不因厚度调整价格； | D28: ㎡ | E28: =7.29+12.13+37.84+26.23+72.43+0.68+0.08+0.2+0.2+0.3-1.96 -> 155.42 | F28: =I28 -> 789 | G28: =F28*E28 -> 122626.38 | I28: =J28+J28*K28+L28+M28+N28 -> 789 | J28: =Q28*$Q$1 -> 650 | K28: =R28 -> 0.02 | L28: =S28*$S$1 -> 80 | M28: =T28*$T$1 -> 46 | N28: =U28*$U$1 -> 0 | O28: =E28*I28 -> 122626.38 | P28: =Q28+Q28*R28+S28+T28+U28 -> 789 | Q28: 650 | R28: 0.02 | S28: 80 | T28: 46 | V28: =E28*P28 -> 122626.38
A29: 3 | B29: 美缝 | C29: 1、专业美缝剂美缝 | D29: ㎡ | E29: =E28 -> 155.42 | F29: =I29 -> 20 | G29: =F29*E29 -> 3108.4 | I29: =J29+J29*K29+L29+M29+N29 -> 20 | J29: =Q29*$Q$1 -> 0 | K29: =R29 -> 0.02 | L29: =S29*$S$1 -> 16 | M29: =T29*$T$1 -> 4 | N29: =U29*$U$1 -> 0 | O29: =E29*I29 -> 3108.4 | P29: =Q29+Q29*R29+S29+T29+U29 -> 20 | R29: 0.02 | S29: 16 | T29: 4 | V29: =E29*P29 -> 3108.4
A30: 4 | B30: 5mm厚不锈钢地面收口条 | C30: 1、5mm厚不锈钢收口条 | D30: m | E30: 1.63 | F30: =I30 -> 48.5 | G30: =F30*E30 -> 79.055 | I30: =J30+J30*K30+L30+M30+N30 -> 48.5 | J30: =Q30*$Q$1 -> 35 | K30: =R30 -> 0.02 | L30: =S30*$S$1 -> 12 | M30: =T30*$T$1 -> 0.8 | N30: =U30*$U$1 -> 0 | O30: =E30*I30 -> 79.055 | P30: =Q30+Q30*R30+S30+T30+U30 -> 48.5 | Q30: 35 | R30: 0.02 | S30: 12 | T30: 0.8 | V30: =E30*P30 -> 79.055
A31: （三） | B31: 天花工程 | G31: =SUBTOTAL(9,G32:G42) -> 53883.904
A32: 1 | B32: 石膏板跌级天花吊顶 | C32: 1、吊顶形式：平级+跌级吊顶 2、基层：轻钢龙骨+双层9.5mm厚石膏板 3.含各种灯具、检修口、风口开口 | D32: ㎡ | E32: =7.29+12.13+37.84+26.23+72.43-1.96 -> 153.96 | I32: =J32+J32*K32+L32+M32+N32 -> 146.2 | J32: =Q32*$Q$1 -> 20 | K32: =R32 -> 0.01 | L32: =S32*$S$1 -> 100 | M32: =T32*$T$1 -> 26 | N32: =U32*$U$1 -> 0 | O32: =E32*I32 -> 22508.952 | P32: =Q32+Q32*R32+S32+T32+U32 -> 146.2 | Q32: 20 | R32: 0.01 | S32: 100 | T32: 26 | V32: =E32*P32 -> 22508.952
A33: 1.1 | B33: 轻钢龙骨 | C33: 1、轻钢龙骨吊顶 2、其他辅材 | D33: ㎡ | E33: =E32 -> 153.96 | F33: =I33 -> 71.5 | G33: =F33*E33 -> 11008.14 | I33: =J33+J33*K33+L33+M33+N33 -> 71.5 | J33: =Q33*$Q$1 -> 0 | K33: =R33 -> 0 | L33: =S33*$S$1 -> 35 | M33: =T33*$T$1 -> 35 | N33: =U33*$U$1 -> 1.5 | O33: =E33*I33 -> 11008.14 | P33: =Q33+Q33*R33+S33+T33+U33 -> 71.5 | S33: 35 | T33: 35 | U33: 1.5 | V33: =E33*P33 -> 11008.14
A34: 1.2 | B34: 12mm阻燃夹板 | C34: 1、12mm阻燃夹板 | D34: ㎡ | E34: =E32*0.15 -> 23.094 | F34: =I34 -> 48.8 | G34: =F34*E34 -> 1126.9872 | I34: =J34+J34*K34+L34+M34+N34 -> 48.8 | J34: =Q34*$Q$1 -> 28 | K34: =R34 -> 0 | L34: =S34*$S$1 -> 20 | M34: =T34*$T$1 -> 0.8 | N34: =U34*$U$1 -> 0 | O34: =E34*I34 -> 1126.9872 | P34: =Q34+Q34*R34+S34+T34+U34 -> 48.8 | Q34: 28 | S34: 20 | T34: 0.8 | V34: =E34*P34 -> 1126.9872
A35: 1.3 | B35: 9.5mm厚石膏板 | C35: 1、双面单层9.5mm厚石膏板 | D35: ㎡ | E35: =E33*2 -> 307.92 | F35: =I35 -> 28.3 | G35: =F35*E35 -> 8714.136 | I35: =J35+J35*K35+L35+M35+N35 -> 28.3 | J35: =Q35*$Q$1 -> 7.5 | K35: =R35 -> 0 | L35: =S35*$S$1 -> 20 | M35: =T35*$T$1 -> 0.8 | N35: =U35*$U$1 -> 0 | O35: =E35*I35 -> 8714.136 | P35: =Q35+Q35*R35+S35+T35+U35 -> 28.3 | Q35: =7.5 -> 7.5 | S35: 20 | T35: 0.8 | V35: =E35*P35 -> 8714.136
A36: 2 | B36: 天花板缝贴纸带刮平整 | D36: ㎡ | E36: =E32 -> 153.96 | F36: =I36 -> 8.5 | G36: =F36*E36 -> 1308.66 | I36: =J36+J36*K36+L36+M36+N36 -> 8.5 | J36: =Q36*$Q$1 -> 3.5 | K36: =R36 -> 0 | L36: =S36*$S$1 -> 5 | M36: =T36*$T$1 -> 0 | N36: =U36*$U$1 -> 0 | O36: =E36*I36 -> 1308.66 | P36: =Q36+Q36*R36+S36+T36+U36 -> 8.5 | Q36: 3.5 | R36: 0 | S36: 5 | T36: 0 | U36: 0 | V36: =E36*P36 -> 1308.66
A37: 3 | B37: 天花挂耐水腻子 | C37: 1、耐水腻子2道，含打磨、修补 | D37: ㎡ | E37: =153.96+83.5*0.2+22.43*0.4 -> 179.632 | F37: =I37 -> 23.5 | G37: =F37*E37 -> 4221.352 | I37: =J37+J37*K37+L37+M37+N37 -> 23.5 | J37: =Q37*$Q$1 -> 3.5 | K37: =R37 -> 0 | L37: =S37*$S$1 -> 20 | M37: =T37*$T$1 -> 0 | N37: =U37*$U$1 -> 0 | O37: =E37*I37 -> 4221.352 | P37: =Q37+Q37*R37+S37+T37+U37 -> 23.5 | Q37: 3.5 | R37: 0 | S37: 20 | T37: 0 | U37: 0 | V37: =E37*P37 -> 4221.352
A38: 4 | B38: 天棚乳胶漆 | C38: 1、面层：PT-01无机白色涂料一底二面 | D38: ㎡ | E38: =E37 -> 179.632 | F38: =I38 -> 13 | G38: =F38*E38 -> 2335.216 | I38: =J38+J38*K38+L38+M38+N38 -> 13 | J38: =Q38*$Q$1 -> 3 | K38: =R38 -> 0 | L38: =S38*$S$1 -> 10 | M38: =T38*$T$1 -> 0 | N38: =U38*$U$1 -> 0 | O38: =E38*I38 -> 2335.216 | P38: =Q38+Q38*R38+S38+T38+U38 -> 13 | Q38: 3 | R38: 0 | S38: 10 | T38: 0 | U38: 0 | V38: =E38*P38 -> 2335.216
A39: 5 | B39: 天花灯槽 | C39: 1、规格：100*100*100mm天花灯槽 2、基层：轻钢龙骨 3、面层：12mm厚阻燃夹板+9.5mm厚石膏板 | D39: m | E39: =9.7+22.68+19.24+31.88 -> 83.5 | F39: =I39 -> 70 | G39: =F39*E39 -> 5845 | I39: =J39+J39*K39+L39+M39+N39 -> 70 | J39: =Q39*$Q$1 -> 13.5 | K39: =R39 -> 0 | L39: =S39*$S$1 -> 55 | M39: =T39*$T$1 -> 1.5 | N39: =U39*$U$1 -> 0 | O39: =E39*I39 -> 5845 | P39: =Q39+Q39*R39+S39+T39+U39 -> 70 | Q39: =0.3*(35+10) -> 13.5 | S39: 55 | T39: 1.5 | V39: =E39*P39 -> 5845
A40: 6 | B40: 窗帘盒 | C40: 1、基层：钢结构龙骨+阻燃板基层 2、面层：9.5mm厚石膏板 | D40: m | E40: =5.28+5.02+12.13 -> 22.43 | F40: =I40 -> 195.17 | G40: =F40*E40 -> 4377.6631 | I40: =J40+J40*K40+L40+M40+N40 -> 195.17 | J40: =Q40*$Q$1 -> 131.67 | K40: =R40 -> 0 | L40: =S40*$S$1 -> 55 | M40: =T40*$T$1 -> 8.5 | N40: =U40*$U$1 -> 0 | O40: =E40*I40 -> 4377.6631 | P40: =Q40+Q40*R40+S40+T40+U40 -> 195.17 | Q40: =4.2*5.7*5.5 -> 131.67 | S40: 55 | T40: 8.5 | V40: =E40*P40 -> 4377.6631
A41: 7 | B41: 窗帘 | C41: 1、成品窗帘 | D41: ㎡ | E41: =(5.28+5.02+12.13)*3 -> 67.29 | F41: =I41 -> 75 | G41: =F41*E41 -> 5046.75 | I41: =J41+J41*K41+L41+M41+N41 -> 75 | J41: =Q41*$Q$1 -> 68 | K41: =R41 -> 0 | L41: =S41*$S$1 -> 5 | M41: =T41*$T$1 -> 1.5 | N41: =U41*$U$1 -> 0.5 | O41: =E41*I41 -> 5046.75 | P41: =Q41+Q41*R41+S41+T41+U41 -> 75 | Q41: 68 | S41: 5 | T41: 1.5 | U41: 0.5 | V41: =E41*P41 -> 5046.75
A42: 8 | B42: 电动窗帘电机 | C42: 1、电动窗帘电机 2、含各种辅材 | D42: 台 | E42: 6 | F42: =I42 -> 1650 | G42: =F42*E42 -> 9900 | I42: =J42+J42*K42+L42+M42+N42 -> 1650 | J42: =Q42*$Q$1 -> 1300 | K42: =R42 -> 0 | L42: =S42*$S$1 -> 300 | M42: =T42*$T$1 -> 35 | N42: =U42*$U$1 -> 15 | O42: =E42*I42 -> 9900 | P42: =Q42+Q42*R42+S42+T42+U42 -> 1650 | Q42: 1300 | S42: 300 | T42: 35 | U42: 15 | V42: =E42*P42 -> 9900
A43: （四） | B43: 墙面工程 | G43: =SUBTOTAL(9,G44:G54) -> 59987.487
A44: 1 | B44: 墙面缝贴纸带刮平整 | D44: ㎡ | E44: =3*(1.12+1.95+1.55+2+2.34+0.57+4.12+6.37+0.58+0.35+0.2)-0.7*2.4-1.5*2.2+16.8 -> 75.27 | F44: =I44 -> 8.5 | G44: =F44*E44 -> 639.795 | I44: =J44+J44*K44+L44+M44+N44 -> 8.5 | J44: =Q44*$Q$1 -> 3.5 | K44: =R44 -> 0 | L44: =S44*$S$1 -> 5 | M44: =T44*$T$1 -> 0 | N44: =U44*$U$1 -> 0 | O44: =E44*I44 -> 639.795 | P44: =Q44+Q44*R44+S44+T44+U44 -> 8.5 | Q44: =Q36 -> 3.5 | R44: =R36 -> 0 | S44: =S36 -> 5 | T44: =T36 -> 0 | U44: 0 | V44: =E44*P44 -> 639.795
A45: 2 | B45: 墙面挂耐水腻子 | C45: 耐水腻子2道，含打磨、修补 | D45: ㎡ | E45: =E44 -> 75.27 | F45: =I45 -> 23.5 | G45: =F45*E45 -> 1768.845 | I45: =J45+J45*K45+L45+M45+N45 -> 23.5 | J45: =Q45*$Q$1 -> 3.5 | K45: =R45 -> 0 | L45: =S45*$S$1 -> 20 | M45: =T45*$T$1 -> 0 | N45: =U45*$U$1 -> 0 | O45: =E45*I45 -> 1768.845 | P45: =Q45+Q45*R45+S45+T45+U45 -> 23.5 | Q45: =Q37 -> 3.5 | R45: =R37 -> 0 | S45: =S37 -> 20 | T45: =T37 -> 0 | U45: 0 | V45: =E45*P45 -> 1768.845
A46: 3 | B46: 墙面乳胶漆PT-01 | C46: 1、面层：PT-01无机白色涂料一底二面 | D46: ㎡ | E46: =3*(1.12+1.95+1.55+2+2.34+0.57+4.12+6.37+0.58+0.35+0.2)-0.7*2.4-1.5*2.2 -> 58.47 | F46: =I46 -> 13 | G46: =F46*E46 -> 760.11 | I46: =J46+J46*K46+L46+M46+N46 -> 13 | J46: =Q46*$Q$1 -> 3 | K46: =R46 -> 0 | L46: =S46*$S$1 -> 10 | M46: =T46*$T$1 -> 0 | N46: =U46*$U$1 -> 0 | O46: =E46*I46 -> 760.11 | P46: =Q46+Q46*R46+S46+T46+U46 -> 13 | Q46: =Q38 -> 3 | R46: =R38 -> 0 | S46: =S38 -> 10 | T46: =T38 -> 0 | U46: 0 | V46: =E46*P46 -> 760.11
A47: 4 | B47: 墙面艺术涂料PT-02 | C47: 1、面层：PT-02艺术涂料一底二面 | D47: ㎡ | E47: =3*5.6 -> 16.8 | F47: =I47 -> 318.25 | G47: =F47*E47 -> 5346.6 | I47: =J47+J47*K47+L47+M47+N47 -> 318.25 | J47: =Q47*$Q$1 -> 275 | K47: =R47 -> 0.03 | L47: =S47*$S$1 -> 35 | M47: =T47*$T$1 -> 0 | N47: =U47*$U$1 -> 0 | O47: =E47*I47 -> 5346.6 | P47: =Q47+Q47*R47+S47+T47+U47 -> 318.25 | Q47: 275 | R47: 0.03 | S47: 35 | V47: =E47*P47 -> 5346.6
A48: 5 | B48: 木饰面饰面 | C48: 1、面层：木饰面饰面 2、基层：12mm厚阻燃夹板 | D48: ㎡ | E48: =3*(2+0.25+1.82+1+1+0.15*2+0.6*2+0.6*3+0.6*2+0.12+6.23+0.35+0.6+4.93*2+1.9)-0.7*2.4 -> 87.21 | F48: =I48 -> 385.7 | G48: =F48*E48 -> 33636.897 | I48: =J48+J48*K48+L48+M48+N48 -> 385.7 | J48: =Q48*$Q$1 -> 320 | K48: =R48 -> 0.03 | L48: =S48*$S$1 -> 55 | M48: =T48*$T$1 -> 0.8 | N48: =U48*$U$1 -> 0.3 | O48: =E48*I48 -> 33636.897 | P48: =Q48+Q48*R48+S48+T48+U48 -> 385.7 | Q48: 320 | R48: 0.03 | S48: 55 | T48: 0.8 | U48: 0.3 | V48: =E48*P48 -> 33636.897
A49: 6 | B49: logo招牌 （背景墙） | C49: 1、面层：成品定制 | D49: 套 | E49: 1 | F49: =I49 -> 2000 | G49: =F49*E49 -> 2000 | I49: =J49+J49*K49+L49+M49+N49 -> 2000 | J49: =Q49*$Q$1 -> 2000 | K49: =R49 -> 0 | L49: =S49*$S$1 -> 0 | M49: =T49*$T$1 -> 0 | N49: =U49*$U$1 -> 0 | O49: =E49*I49 -> 2000 | P49: =Q49+Q49*R49+S49+T49+U49 -> 2000 | Q49: 2000 | V49: =E49*P49 -> 2000
A50: 7 | B50: MT-01 1.2mm厚不锈钢踢脚线 | C50: 1、规格尺寸：50mm高 2、面层：MT-01 1.2mm厚不锈钢 3、基层：轻钢龙骨+12mm厚阻燃夹板 | D50: m | E50: =1.12+1.54+2+2.34+0.57-0.7+2+1.82+0.6+0.3+0.3+0.6+0.12+0.6+0.6+0.3+0.6+4.12-1.5+6.37+4.93+0.6+0.34+6.23-0.7+0.57+0.12+0.35+0.6+4.93 -> 41.67 | F50: =I50 -> 44.831 | G50: =F50*E50 -> 1868.1078 | I50: =J50+J50*K50+L50+M50+N50 -> 44.831 | J50: =Q50*$Q$1 -> 23.1 | K50: =R50 -> 0.01 | L50: =S50*$S$1 -> 18 | M50: =T50*$T$1 -> 3.5 | N50: =U50*$U$1 -> 0 | O50: =E50*I50 -> 1868.1078 | P50: =Q50+Q50*R50+S50+T50+U50 -> 44.831 | Q50: =0.06*360+1.5 -> 23.1 | R50: 0.01 | S50: 18 | T50: 3.5 | V50: =E50*P50 -> 1868.1078
A51: 8 | B51: 墙面灯槽 | C51: 1、规格：100*50mm灯槽 2、基层：轻钢龙骨 3、面层：12mm厚阻燃夹板+9.5mm厚石膏板 | D51: m | E51: =3*2 -> 6 | F51: =I51 -> 65.1 | G51: =F51*E51 -> 390.6 | I51: =J51+J51*K51+L51+M51+N51 -> 65.1 | J51: =Q51*$Q$1 -> 10 | K51: =R51 -> 0.01 | L51: =S51*$S$1 -> 55 | M51: =T51*$T$1 -> 0 | N51: =U51*$U$1 -> 0 | O51: =E51*I51 -> 390.6 | P51: =Q51+Q51*R51+S51+T51+U51 -> 65.1 | Q51: =(35+15)*0.2 -> 10 | R51: 0.01 | S51: 55 | V51: =E51*P51 -> 390.6
A52: 9 | B52: 岩板墙饰面 （前台处） | C52: 1、面层：CT-02成品岩板6mm厚 2、基层：12mm厚阻燃夹板 | D52: ㎡ | E52: =(1.8+1.4)*3 -> 9.6 | F52: =I52 -> 1266 | G52: =F52*E52 -> 12153.6 | I52: =J52+J52*K52+L52+M52+N52 -> 1266 | J52: =Q52*$Q$1 -> 1100 | K52: =R52 -> 0 | L52: =S52*$S$1 -> 120 | M52: =T52*$T$1 -> 46 | N52: =U52*$U$1 -> 0 | O52: =E52*I52 -> 12153.6 | P52: =Q52+Q52*R52+S52+T52+U52 -> 1266 | Q52: 1100 | S52: 120 | T52: 46 | V52: =E52*P52 -> 12153.6
A53: 10 | B53: 前台岩板置物台 | C53: 1、规格尺寸：1200*300*150mm 2、面层：CT-02岩板 3、基层：钢结构龙骨+12mm厚阻燃夹板 | D53: m | E53: 1.4 | F53: =I53 -> 655 | G53: =F53*E53 -> 917 | I53: =J53+J53*K53+L53+M53+N53 -> 655 | J53: =Q53*$Q$1 -> 495 | K53: =R53 -> 0 | L53: =S53*$S$1 -> 135 | M53: =T53*$T$1 -> 25 | N53: =U53*$U$1 -> 0 | O53: =E53*I53 -> 917 | P53: =Q53+Q53*R53+S53+T53+U53 -> 655 | Q53: =0.45*1100 -> 495 | S53: =80+55 -> 135 | T53: 25 | V53: =E53*P53 -> 917
A54: 11 | B54: 玻璃磨砂膜 | C54: 1.基层清理 2.提供及安装玻璃磨砂膜 | D54: ㎡ | E54: =(7.73+0.89*2)*0.8 -> 7.608 | F54: =I54 -> 66.5 | G54: =F54*E54 -> 505.932 | I54: =J54+J54*K54+L54+M54+N54 -> 66.5 | J54: =Q54*$Q$1 -> 50 | K54: =R54 -> 0 | L54: =S54*$S$1 -> 15 | M54: =T54*$T$1 -> 1.5 | N54: =U54*$U$1 -> 0 | O54: =E54*I54 -> 505.932 | P54: =Q54+Q54*R54+S54+T54+U54 -> 66.5 | Q54: 50 | S54: 15 | T54: 1.5 | V54: =E54*P54 -> 505.932
A55: （五） | B55: 固定家具及门窗工程 | G55: =SUBTOTAL(9,G56:G77) -> 41838.936
A56: 1 | B56: 门禁系统安装 | C56: 1、门洞尺寸：1600*2500mm 2、门洞开口及修补加固 3、玻璃门保护性拆除及拆除后重新安装 | D56: 项 | E56: 1 | F56: =I56 -> 2050 | G56: =F56*E56 -> 2050 | I56: =J56+J56*K56+L56+M56+N56 -> 2050 | J56: =Q56*$Q$1 -> 1200 | K56: =R56 -> 0 | L56: =S56*$S$1 -> 800 | M56: =T56*$T$1 -> 50 | N56: =U56*$U$1 -> 0 | O56: =E56*I56 -> 2050 | P56: =Q56+Q56*R56+S56+T56+U56 -> 2050 | Q56: 1200 | S56: 800 | T56: 50 | V56: =E56*P56 -> 2050
A57: 2.1 | B57: 玻璃双开门 | C57: 1、10mm厚钢化玻璃门 2、门洞尺寸：1625mm*2800mm 3、含门锁.不锈钢扶手五金等制作安装 | D57: 樘 | E57: 1 | F57: =I57 -> 941 | G57: =F57*E57 -> 941 | I57: =J57+J57*K57+L57+M57+N57 -> 941 | J57: =Q57*$Q$1 -> 546 | K57: =R57 -> 0 | L57: =S57*$S$1 -> 360 | M57: =T57*$T$1 -> 35 | N57: =U57*$U$1 -> 0 | O57: =E57*I57 -> 941 | P57: =Q57+Q57*R57+S57+T57+U57 -> 941 | Q57: =120*1.625*2.8 -> 546 | S57: =180*2 -> 360 | T57: =35 -> 35 | V57: =E57*P57 -> 941
A58: 2.2 | B58: 扶手 | D58: 副 | E58: 2 | F58: =I58 -> 150 | G58: =F58*E58 -> 300 | I58: 150 | J58: =Q58*$Q$1 -> 150 | K58: =R58 -> 0 | L58: =S58*$S$1 -> 0 | M58: =T58*$T$1 -> 0 | N58: =U58*$U$1 -> 0 | O58: =E58*I58 -> 300 | P58: =Q58+Q58*R58+S58+T58+U58 -> 150 | Q58: 150 | V58: =E58*P58 -> 300
A59: 2.3 | B59: 门夹 | D59: 副 | E59: 2 | F59: =I59 -> 45 | G59: =F59*E59 -> 90 | I59: 45 | J59: =Q59*$Q$1 -> 45 | K59: =R59 -> 0 | L59: =S59*$S$1 -> 0 | M59: =T59*$T$1 -> 0 | N59: =U59*$U$1 -> 0 | O59: =E59*I59 -> 90 | P59: =Q59+Q59*R59+S59+T59+U59 -> 45 | Q59: 45 | V59: =E59*P59 -> 90
A60: 2.3 | B60: 地弹簧 | D60: 副 | E60: 2 | F60: =I60 -> 450 | G60: =F60*E60 -> 900 | I60: 450 | J60: =Q60*$Q$1 -> 450 | K60: =R60 -> 0 | L60: =S60*$S$1 -> 0 | M60: =T60*$T$1 -> 0 | N60: =U60*$U$1 -> 0 | O60: =E60*I60 -> 900 | P60: =Q60+Q60*R60+S60+T60+U60 -> 450 | Q60: 450 | V60: =E60*P60 -> 900
A61: 3.1 | B61: 木饰面单开门 | C61: 1、木饰面单开门 2、门洞尺寸：800mm*2400mm 3、含门套、门锁五金、门吸等制作安装 | D61: 樘 | E61: 1 | F61: =I61 -> 1847 | G61: =F61*E61 -> 1847 | I61: =J61+J61*K61+L61+M61+N61 -> 1847 | J61: =Q61*$Q$1 -> 1632 | K61: =R61 -> 0 | L61: =S61*$S$1 -> 180 | M61: =T61*$T$1 -> 35 | N61: =U61*$U$1 -> 0 | O61: =E61*I61 -> 1847 | P61: =Q61+Q61*R61+S61+T61+U61 -> 1847 | Q61: =850*0.8*2.4 -> 1632 | S61: 180 | T61: 35 | V61: =E61*P61 -> 1847
A62: 3.2 | B62: 门锁 | D62: 个 | E62: 1 | F62: =I62 -> 170 | G62: =F62*E62 -> 170 | I62: 170 | J62: =Q62*$Q$1 -> 170 | K62: =R62 -> 0 | L62: =S62*$S$1 -> 0 | M62: =T62*$T$1 -> 0 | N62: =U62*$U$1 -> 0 | O62: =E62*I62 -> 170 | P62: =Q62+Q62*R62+S62+T62+U62 -> 170 | Q62: 170 | V62: =E62*P62 -> 170
A63: 3.3 | B63: 合页 | D63: 个 | E63: 3 | F63: =I63 -> 25 | G63: =F63*E63 -> 75 | I63: 25 | J63: =Q63*$Q$1 -> 25 | K63: =R63 -> 0 | L63: =S63*$S$1 -> 0 | M63: =T63*$T$1 -> 0 | N63: =U63*$U$1 -> 0 | O63: =E63*I63 -> 75 | P63: =Q63+Q63*R63+S63+T63+U63 -> 25 | Q63: 25 | V63: =E63*P63 -> 75
A64: 3.4 | B64: 门吸 | D64: 个 | E64: 1 | F64: =I64 -> 25 | G64: =F64*E64 -> 25 | I64: 25 | J64: =Q64*$Q$1 -> 25 | K64: =R64 -> 0 | L64: =S64*$S$1 -> 0 | M64: =T64*$T$1 -> 0 | N64: =U64*$U$1 -> 0 | O64: =E64*I64 -> 25 | P64: =Q64+Q64*R64+S64+T64+U64 -> 25 | Q64: 25 | V64: =E64*P64 -> 25
A65: 3.5 | B65: 拉手 | D65: 副 | E65: 1 | F65: =I65 -> 125 | G65: =F65*E65 -> 125 | I65: 125 | J65: =Q65*$Q$1 -> 125 | K65: =R65 -> 0 | L65: =S65*$S$1 -> 0 | M65: =T65*$T$1 -> 0 | N65: =U65*$U$1 -> 0 | O65: =E65*I65 -> 125 | P65: =Q65+Q65*R65+S65+T65+U65 -> 125 | Q65: 125 | V65: =E65*P65 -> 125
A66: 4.1 | B66: 木饰面双开门 （总裁办公室） | C66: 1、木饰面双开门 2、门洞尺寸：1700mm*2800mm 3、含门套、门锁五金、门吸等制作安装 | D66: 樘 | E66: 1 | F66: =I66 -> 4441 | G66: =F66*E66 -> 4441 | I66: =J66+J66*K66+L66+M66+N66 -> 4441 | J66: =Q66*$Q$1 -> 4046 | K66: =R66 -> 0 | L66: =S66*$S$1 -> 360 | M66: =T66*$T$1 -> 35 | N66: =U66*$U$1 -> 0 | O66: =E66*I66 -> 4441 | P66: =Q66+Q66*R66+S66+T66+U66 -> 4441 | Q66: =850*1.7*2.8 -> 4046 | S66: =180*2 -> 360 | T66: =35 -> 35 | V66: =E66*P66 -> 4441
A67: 4.2 | B67: 门锁 | D67: 个 | E67: 1 | F67: =I67 -> 650 | G67: =F67*E67 -> 650 | I67: 650 | J67: =Q67*$Q$1 -> 650 | K67: =R67 -> 0 | L67: =S67*$S$1 -> 0 | M67: =T67*$T$1 -> 0 | N67: =U67*$U$1 -> 0 | O67: =E67*I67 -> 650 | P67: =Q67+Q67*R67+S67+T67+U67 -> 650 | Q67: 650 | V67: =E67*P67 -> 650
A68: 4.3 | B68: 合页 | D68: 个 | E68: 6 | F68: =I68 -> 25 | G68: =F68*E68 -> 150 | I68: 25 | J68: =Q68*$Q$1 -> 25 | K68: =R68 -> 0 | L68: =S68*$S$1 -> 0 | M68: =T68*$T$1 -> 0 | N68: =U68*$U$1 -> 0 | O68: =E68*I68 -> 150 | P68: =Q68+Q68*R68+S68+T68+U68 -> 25 | Q68: 25 | V68: =E68*P68 -> 150
A69: 4.4 | B69: 门吸 | D69: 个 | E69: 2 | F69: =I69 -> 25 | G69: =F69*E69 -> 50 | I69: 25 | J69: =Q69*$Q$1 -> 25 | K69: =R69 -> 0 | L69: =S69*$S$1 -> 0 | M69: =T69*$T$1 -> 0 | N69: =U69*$U$1 -> 0 | O69: =E69*I69 -> 50 | P69: =Q69+Q69*R69+S69+T69+U69 -> 25 | Q69: 25 | V69: =E69*P69 -> 50
A70: 4.5 | B70: 拉手 | D70: 副 | E70: 2 | F70: =I70 -> 150 | G70: =F70*E70 -> 300 | I70: 150 | J70: =Q70*$Q$1 -> 150 | K70: =R70 -> 0 | L70: =S70*$S$1 -> 0 | M70: =T70*$T$1 -> 0 | N70: =U70*$U$1 -> 0 | O70: =E70*I70 -> 300 | P70: =Q70+Q70*R70+S70+T70+U70 -> 150 | Q70: 150 | V70: =E70*P70 -> 300
A71: 5.1 | B71: 隔断旋转门WD-01 （大会议室） | C71: 1、隔断旋转门（5扇门） 2、门洞尺寸：4250mm*3000mm 3、含门套、门锁五金、导轨等制作安装 | D71: ㎡ | E71: =4.25*3 -> 12.75 | F71: =I71 -> 449 | G71: =F71*E71 -> 5724.75 | I71: =J71+J71*K71+L71+M71+N71 -> 449 | J71: =Q71*$Q$1 -> 350 | K71: =R71 -> 0.01 | L71: =S71*$S$1 -> 85 | M71: =T71*$T$1 -> 10.5 | N71: =U71*$U$1 -> 0 | O71: =E71*I71 -> 5724.75 | P71: =Q71+Q71*R71+S71+T71+U71 -> 449 | Q71: =350 -> 350 | R71: 0.01 | S71: 85 | T71: 10.5 | V71: =E71*P71 -> 5724.75
A72: 5.2 | B72: 移门导轨 | D72: m | E72: 4.25 | F72: =I72 -> 86 | G72: =F72*E72 -> 365.5 | I72: 86 | J72: =Q72*$Q$1 -> 86 | K72: =R72 -> 0 | L72: =S72*$S$1 -> 0 | M72: =T72*$T$1 -> 0 | N72: =U72*$U$1 -> 0 | O72: =E72*I72 -> 365.5 | P72: =Q72+Q72*R72+S72+T72+U72 -> 86 | Q72: 86 | V72: =E72*P72 -> 365.5
A73: 5.3 | B73: 隐藏拉手 | D73: 个 | E73: 5 | F73: =I73 -> 25 | G73: =F73*E73 -> 125 | I73: 25 | J73: =Q73*$Q$1 -> 25 | K73: =R73 -> 0 | L73: =S73*$S$1 -> 0 | M73: =T73*$T$1 -> 0 | N73: =U73*$U$1 -> 0 | O73: =E73*I73 -> 125 | P73: =Q73+Q73*R73+S73+T73+U73 -> 25 | Q73: 25 | V73: =E73*P73 -> 125
A74: 6 | B74: 柜顶封板 （总经理办公室） | C74: 1、12mm厚阻燃夹板+9.5mm厚石膏板 2、轻钢龙骨 | D74: m2 | E74: =1.31*3.55 -> 4.6505 | F74: =I74 -> 141.5 | G74: =F74*E74 -> 658.04575 | I74: =J74+J74*K74+L74+M74+N74 -> 141.5 | J74: =Q74*$Q$1 -> 45.5 | K74: =R74 -> 0 | L74: =S74*$S$1 -> 70 | M74: =T74*$T$1 -> 26 | N74: =U74*$U$1 -> 0 | O74: =E74*I74 -> 658.04575 | P74: =Q74+Q74*R74+S74+T74+U74 -> 141.5 | Q74: =35+10.5 -> 45.5 | S74: =35+20+15 -> 70 | T74: 26 | V74: =E74*P74 -> 658.04575
A75: 7 | B75: 储藏室柜 | C75: 1、规格尺寸：2000*2800*400mm 2、木饰面板柜体； 3、按平面投影面积计算,综合考虑柜体尺寸及内部做法； 4、含包边、饰面、柜体五金、抽屉及其他所需材料安装施工； 5、满足设计图纸、招标要求及国家有关现行施工及验收规范要求 | D75: m2 | E75: =2*2.8 -> 5.6 | F75: =I75 -> 1050 | G75: =F75*E75 -> 5880 | I75: =J75+J75*K75+L75+M75+N75 -> 1050 | J75: =Q75*$Q$1 -> 1050 | K75: =R75 -> 0 | L75: =S75*$S$1 -> 0 | M75: =T75*$T$1 -> 0 | N75: =U75*$U$1 -> 0 | O75: =E75*I75 -> 5880 | P75: =Q75+Q75*R75+S75+T75+U75 -> 1050 | Q75: 1050 | V75: =E75*P75 -> 5880
A76: 8 | B76: 总裁办公室柜 | C76: 1、规格尺寸：3530*600*2800 2、木饰面板柜体； 3、按平面投影面积计算,综合考虑柜体尺寸及内部做法； 4、含包边、饰面、柜体五金、抽屉及其他所需材料安装施工； 5、满足设计图纸、招标要求及国家有关现行施工及验收规范要求 | D76: m2 | E76: =3.53*2.8 -> 9.884 | F76: =I76 -> 1250 | G76: =F76*E76 -> 12355 | I76: =J76+J76*K76+L76+M76+N76 -> 1250 | J76: =Q76*$Q$1 -> 1250 | K76: =R76 -> 0 | L76: =S76*$S$1 -> 0 | M76: =T76*$T$1 -> 0 | N76: =U76*$U$1 -> 0 | O76: =E76*I76 -> 12355 | P76: =Q76+Q76*R76+S76+T76+U76 -> 1250 | Q76: 1250 | V76: =E76*P76 -> 12355
A77: 9 | B77: 岩板墙饰面 （总裁办公室柜） | C77: 1、面层：CT-03成品岩板6mm厚 2、基层：12mm厚阻燃夹板 | D77: m2 | E77: =(0.6+1.2)*2.8 -> 5.04 | F77: =I77 -> 916 | G77: =F77*E77 -> 4616.64 | I77: =J77+J77*K77+L77+M77+N77 -> 916 | J77: =Q77*$Q$1 -> 750 | K77: =R77 -> 0 | L77: =S77*$S$1 -> 120 | M77: =T77*$T$1 -> 46 | N77: =U77*$U$1 -> 0 | O77: =E77*I77 -> 4616.64 | P77: =Q77+Q77*R77+S77+T77+U77 -> 916 | Q77: 750 | S77: 120 | T77: 46 | V77: =E77*P77 -> 4616.64
A78: 二 | B78: 安装工程 | G78: =SUBTOTAL(9,G79:G96) -> 44640.75
A79: （一） | B79: 强电工程 | G79: =SUBTOTAL(9,G80:G93) -> 38883.45
A80: 1 | B80: 强电部分(不含照明灯具及开关插座) | C80: 1、成天泰2.5、4平方国标电源线； 2、照明线用wdz-byj-2.5m²,每路线负荷220V/2500W; 3、插座线用wdz-byj-4m²,每路线负荷 220V/4000W 4、含人工及镀锌金属线管 | D80: ㎡ | E80: 156.78 | F80: =I80 -> 90 | G80: =F80*E80 -> 14110.2 | I80: =J80+J80*K80+L80+M80+N80 -> 90 | J80: =Q80*$Q$1 -> 30 | K80: =R80 -> 0 | L80: =S80*$S$1 -> 60 | M80: =T80*$T$1 -> 0 | N80: =U80*$U$1 -> 0 | O80: =E80*I80 -> 14110.2 | P80: =Q80+Q80*R80+S80+T80+U80 -> 90 | Q80: 30 | S80: 60 | V80: =E80*P80 -> 14110.2
A81: 2 | B81: 强电配电箱移位 | D81: 个 | E81: 1 | F81: =I81 -> 800 | G81: =F81*E81 -> 800 | I81: =J81+J81*K81+L81+M81+N81 -> 800 | J81: =Q81*$Q$1 -> 0 | K81: =R81 -> 0 | L81: =S81*$S$1 -> 800 | M81: =T81*$T$1 -> 0 | N81: =U81*$U$1 -> 0 | O81: =E81*I81 -> 800 | P81: =Q81+Q81*R81+S81+T81+U81 -> 800 | S81: 800 | V81: =E81*P81 -> 800
A82: 3 | B82: 弱电配电箱移位 | D82: 个 | E82: 1 | F82: =I82 -> 500 | G82: =F82*E82 -> 500 | I82: =J82+J82*K82+L82+M82+N82 -> 500 | J82: =Q82*$Q$1 -> 0 | K82: =R82 -> 0 | L82: =S82*$S$1 -> 500 | M82: =T82*$T$1 -> 0 | N82: =U82*$U$1 -> 0 | O82: =E82*I82 -> 500 | P82: =Q82+Q82*R82+S82+T82+U82 -> 500 | S82: 500 | V82: =E82*P82 -> 500
A83: 4 | B83: 装饰吊灯 | C83: 1、名称:定制装饰吊灯 2、规格:2400*350mm 3、安装形式:吊装 4、其他:满足设计及施工要求 | D83: 个 | E83: 1 | F83: =I83 -> 880 | G83: =F83*E83 -> 880 | I83: =J83+J83*K83+L83+M83+N83 -> 880 | J83: =Q83*$Q$1 -> 800 | K83: =R83 -> 0 | L83: =S83*$S$1 -> 80 | M83: =T83*$T$1 -> 0 | N83: =U83*$U$1 -> 0 | O83: =E83*I83 -> 880 | P83: =Q83+Q83*R83+S83+T83+U83 -> 880 | Q83: 800 | S83: 80 | V83: =E83*P83 -> 880
A84: 5 | B84: 总总裁办公室吊灯 | C84: 1、名称:装饰吊灯 2、规格: 3、安装形式:吊装 4、其他:满足设计及施工要求 | D84: 个 | E84: 2 | F84: =I84 -> 700 | G84: =F84*E84 -> 1400 | I84: =J84+J84*K84+L84+M84+N84 -> 700 | J84: =Q84*$Q$1 -> 650 | K84: =R84 -> 0 | L84: =S84*$S$1 -> 50 | M84: =T84*$T$1 -> 0 | N84: =U84*$U$1 -> 0 | O84: =E84*I84 -> 1400 | P84: =Q84+Q84*R84+S84+T84+U84 -> 700 | Q84: 650 | S84: 50 | V84: =E84*P84 -> 1400
A85: 6 | B85: 装饰筒灯 | C85: 1、名称:筒灯 2、规格: 3、安装形式:嵌入式 4、其他:满足设计及施工要求 | D85: 个 | E85: =3+3+12+9 -> 27 | F85: =I85 -> 95 | G85: =F85*E85 -> 2565 | I85: =J85+J85*K85+L85+M85+N85 -> 95 | J85: =Q85*$Q$1 -> 75 | K85: =R85 -> 0 | L85: =S85*$S$1 -> 20 | M85: =T85*$T$1 -> 0 | N85: =U85*$U$1 -> 0 | O85: =E85*I85 -> 2565 | P85: =Q85+Q85*R85+S85+T85+U85 -> 95 | Q85: 75 | S85: 20 | V85: =E85*P85 -> 2565
A86: 7 | B86: 装饰明装筒灯 | C86: 1、名称:明装筒灯 2、规格: 3、安装形式:吊装 4、其他:满足设计及施工要求 | D86: 个 | E86: 10 | F86: =I86 -> 85 | G86: =F86*E86 -> 850 | I86: =J86+J86*K86+L86+M86+N86 -> 85 | J86: =Q86*$Q$1 -> 65 | K86: =R86 -> 0 | L86: =S86*$S$1 -> 20 | M86: =T86*$T$1 -> 0 | N86: =U86*$U$1 -> 0 | O86: =E86*I86 -> 850 | P86: =Q86+Q86*R86+S86+T86+U86 -> 85 | Q86: 65 | S86: 20 | V86: =E86*P86 -> 850
A87: 8 | B87: 可调节射灯 | C87: 1、名称:可调节射灯 2、规格: 3、安装形式:嵌入式 4、其他:满足设计及施工要求 | D87: 个 | E87: =3+6 -> 9 | F87: =I87 -> 155 | G87: =F87*E87 -> 1395 | I87: =J87+J87*K87+L87+M87+N87 -> 155 | J87: =Q87*$Q$1 -> 135 | K87: =R87 -> 0 | L87: =S87*$S$1 -> 20 | M87: =T87*$T$1 -> 0 | N87: =U87*$U$1 -> 0 | O87: =E87*I87 -> 1395 | P87: =Q87+Q87*R87+S87+T87+U87 -> 155 | Q87: 135 | S87: 20 | V87: =E87*P87 -> 1395
A88: 9 | B88: 磁吸灯 | C88: 1、名称:磁吸灯 2、规格: 3、安装形式:嵌入式 4、其他:满足设计及施工要求 | D88: m | E88: =18.5+18.5+12.5 -> 49.5 | F88: =I88 -> 103.33333 | G88: =F88*E88 -> 5115 | I88: =J88+J88*K88+L88+M88+N88 -> 103.33333 | J88: =Q88*$Q$1 -> 83.333333 | K88: =R88 -> 0 | L88: =S88*$S$1 -> 20 | M88: =T88*$T$1 -> 0 | N88: =U88*$U$1 -> 0 | O88: =E88*I88 -> 5115 | P88: =Q88+Q88*R88+S88+T88+U88 -> 103.33333 | Q88: =50/0.6 -> 83.333333 | S88: 20 | V88: =E88*P88 -> 5115
A89: 10 | B89: 天花灯带 | C89: 1、led灯带 | D89: m | E89: =E39 -> 83.5 | F89: =I89 -> 35.5 | G89: =F89*E89 -> 2964.25 | I89: =J89+J89*K89+L89+M89+N89 -> 35.5 | J89: =Q89*$Q$1 -> 23.5 | K89: =R89 -> 0 | L89: =S89*$S$1 -> 12 | M89: =T89*$T$1 -> 0 | N89: =U89*$U$1 -> 0 | O89: =E89*I89 -> 2964.25 | P89: =Q89+Q89*R89+S89+T89+U89 -> 35.5 | Q89: 23.5 | S89: 12 | V89: =E89*P89 -> 2964.25
A90: 11 | B90: 墙面灯带 | C90: 1、led灯带 | D90: m | E90: 6 | F90: =I90 -> 35.5 | G90: =F90*E90 -> 213 | I90: =J90+J90*K90+L90+M90+N90 -> 35.5 | J90: =Q90*$Q$1 -> 23.5 | K90: =R90 -> 0 | L90: =S90*$S$1 -> 12 | M90: =T90*$T$1 -> 0 | N90: =U90*$U$1 -> 0 | O90: =E90*I90 -> 213 | P90: =Q90+Q90*R90+S90+T90+U90 -> 35.5 | Q90: 23.5 | S90: 12 | V90: =E90*P90 -> 213
A91: 12 | B91: 照明开关 | C91: (1)名称:各种开关 (2)安装方式:距地1.3米安装 (3)其他:满足设计及施工要求 | D91: 个 | E91: 8 | F91: =I91 -> 27 | G91: =F91*E91 -> 216 | I91: =J91+J91*K91+L91+M91+N91 -> 27 | J91: =Q91*$Q$1 -> 17 | K91: =R91 -> 0 | L91: =S91*$S$1 -> 10 | M91: =T91*$T$1 -> 0 | N91: =U91*$U$1 -> 0 | O91: =E91*I91 -> 216 | P91: =Q91+Q91*R91+S91+T91+U91 -> 27 | Q91: 17 | S91: 10 | V91: =E91*P91 -> 216
A92: 13 | B92: 插座 | C92: (1)名称:单相二.三孔普通插座 (2)规格:250V 10A 安全型 (3)安装方式:详见图纸 (4)其他:满足设计及施工要求 | D92: 个 | E92: 27 | F92: =I92 -> 25 | G92: =F92*E92 -> 675 | I92: =J92+J92*K92+L92+M92+N92 -> 25 | J92: =Q92*$Q$1 -> 15 | K92: =R92 -> 0 | L92: =S92*$S$1 -> 10 | M92: =T92*$T$1 -> 0 | N92: =U92*$U$1 -> 0 | O92: =E92*I92 -> 675 | P92: =Q92+Q92*R92+S92+T92+U92 -> 25 | Q92: 15 | S92: 10 | V92: =E92*P92 -> 675
A93: 14 | B93: 窗户自动开关器 | C93: 1、窗户自动开关器 | D93: 个 | E93: 9 | F93: =I93 -> 800 | G93: =F93*E93 -> 7200 | I93: =J93+J93*K93+L93+M93+N93 -> 800 | J93: =Q93*$Q$1 -> 800 | K93: =R93 -> 0 | L93: =S93*$S$1 -> 0 | M93: =T93*$T$1 -> 0 | N93: =U93*$U$1 -> 0 | O93: =E93*I93 -> 7200 | P93: =Q93+Q93*R93+S93+T93+U93 -> 800 | Q93: 800 | R93: 0 | S93: 0 | T93: 0 | V93: =E93*P93 -> 7200
A94: （二） | B94: 弱电工程 | G94: =SUBTOTAL(9,G95:G96) -> 5757.3
A95: 1 | B95: 弱电部分（含信号线、网线，不含信号插座） | C95: 1、紧定式镀锌电线管 2、信号线、网线 3、智能模块 | D95: ㎡ | E95: 156.78 | F95: =I95 -> 35 | G95: =F95*E95 -> 5487.3 | I95: =J95+J95*K95+L95+M95+N95 -> 35 | J95: =Q95*$Q$1 -> 10 | K95: =R95 -> 0 | L95: =S95*$S$1 -> 25 | M95: =T95*$T$1 -> 0 | N95: =U95*$U$1 -> 0 | O95: =E95*I95 -> 5487.3 | P95: =Q95+Q95*R95+S95+T95+U95 -> 35 | Q95: 10 | R95: 0 | S95: 25 | T95: 0 | V95: =E95*P95 -> 5487.3
A96: 2 | B96: 网络插座 | D96: 个 | E96: 9 | F96: =I96 -> 30 | G96: =F96*E96 -> 270 | I96: =J96+J96*K96+L96+M96+N96 -> 30 | J96: =Q96*$Q$1 -> 20 | K96: =R96 -> 0 | L96: =S96*$S$1 -> 10 | M96: =T96*$T$1 -> 0 | N96: =U96*$U$1 -> 0 | O96: =E96*I96 -> 270 | P96: =Q96+Q96*R96+S96+T96+U96 -> 30 | Q96: 20 | R96: 0 | S96: 10 | T96: 0 | V96: =E96*P96 -> 270
A97: 三 | B97: 其他工程 | G97: =SUBTOTAL(9,G98:G104) -> 27090.75
A98: 1 | B98: 垃圾清运费 | C98: 1.将垃圾运至物业指定小区内装修垃圾存放点。2.物业运至外部垃圾厂。（含物业收取的垃圾外运费） | D98: ㎡ | E98: 266.31 | F98: =I98 -> 30 | G98: =F98*E98 -> 7989.3 | H98: 建筑面积266.31㎡ | I98: 30 | J98: =Q98*$Q$1 -> 30 | K98: =R98 -> 0 | L98: =S98*$S$1 -> 0 | M98: =T98*$T$1 -> 0 | N98: =U98*$U$1 -> 0 | O98: =E98*I98 -> 7989.3 | P98: =Q98+Q98*R98+S98+T98+U98 -> 30 | Q98: 30 | V98: =E98*P98 -> 7989.3
A99: 2 | B99: 安全文明施工费 | D99: ㎡ | E99: =E98 -> 266.31 | F99: =I99 -> 15 | G99: =F99*E99 -> 3994.65 | H99: =H98 -> 建筑面积266.31㎡ | I99: 15 | J99: =Q99*$Q$1 -> 15 | K99: =R99 -> 0 | L99: =S99*$S$1 -> 0 | M99: =T99*$T$1 -> 0 | N99: =U99*$U$1 -> 0 | O99: =E99*I99 -> 3994.65 | P99: =Q99+Q99*R99+S99+T99+U99 -> 15 | Q99: 15 | V99: =E99*P99 -> 3994.65
A100: 3 | B100: 保洁交付 | D100: ㎡ | E100: 156.78 | F100: =I100 -> 10 | G100: =F100*E100 -> 1567.8 | I100: 10 | J100: =Q100*$Q$1 -> 10 | K100: =R100 -> 0 | L100: =S100*$S$1 -> 0 | M100: =T100*$T$1 -> 0 | N100: =U100*$U$1 -> 0 | O100: =E100*I100 -> 1567.8 | P100: =Q100+Q100*R100+S100+T100+U100 -> 10 | Q100: 10 | V100: =E100*P100 -> 1567.8
...

Sheet 报价汇总-空调消防
B1: 岁宝壹品苑D栋3206办公室装修汇总 空调消防
A2: 序号 | B2: 名称 | C2: 金额（元） | D2: 面积（㎡） | E2: 单方价格（元/㎡） | F2: 备注
A3: 一 | B3: =空调消防清单!B3 -> 空调工程 | C3: =空调消防清单!G3 -> 31500
A4: 二 | B4: =空调消防清单!B5 -> 消防改造 | C4: =空调消防清单!G5 -> 31820.235
A5: 三 | B5: 合计：一+二 | C5: =C3+C4 -> 63320.235
A6: 四 | B6: 管理费 | C6: =空调消防清单!G37 -> 3166.0118
A7: 五 | B7: 税金 | C7: =空调消防清单!G38 -> 5983.7622
A8: 六 | B8: 合计=三+四+五 | C8: =C5+C6+C7 -> 72470.009 | D8: 156.78 | E8: =C8/D8 -> 462.24014

Sheet 空调消防清单
A1: 岁宝壹品苑D栋3206办公室装修清单 空调消防 | I1: =G39 -> 72470.009 | Q1: =不含空调消防清单!Q1 -> 1 | S1: =不含空调消防清单!S1 -> 1 | T1: =不含空调消防清单!T1 -> 1 | U1: =不含空调消防清单!U1 -> 1
A2: 序号 | B2: 项目名称 | C2: 项目特征 | D2: 单位 | E2: 工程量 | F2: 综合单价（不含税） | G2: 合价 | H2: 备注 | I2: 综合单价（不含税） | J2: 主材费 | K2: 主材损耗率 | L2: 人工费 | M2: 辅材费 | N2: 机械费 | O2: 合计 | P2: 成本价 | Q2: 主材费 | R2: 主材损耗率 | S2: 人工费 | T2: 辅材费 | U2: 机械费 | V2: 成本合计
A3: 一 | B3: 空调工程 | G3: =SUBTOTAL(9,G4:G4) -> 31500
A4: 1 | B4: 空调风机盘管2P | C4: 1、包含铝合金风口、空调管道、帆布、钢结构支架等 | D4: 台 | E4: 5 | F4: =I4 -> 6300 | G4: =F4*E4 -> 31500 | I4: =J4+J4*K4+L4+M4+N4 -> 6300 | J4: =Q4*$Q$1 -> 6300 | K4: =R4 -> 0 | L4: =S4*$S$1 -> 0 | M4: =T4*$T$1 -> 0 | N4: =U4*$U$1 -> 0 | O4: =E4*I4 -> 31500 | P4: =Q4+Q4*R4+S4+T4+U4 -> 6300 | Q4: 6300 | V4: =E4*P4 -> 31500
A5: 二 | B5: 消防改造 | G5: =SUBTOTAL(9,G7:G35) -> 31820.235
A6: （一） | B6: 火灾自动报警系统
A7: 1 | B7: 探测器拆除、安装 | C7: 1.名称：感烟 2.型号.规格： | D7: 套 | E7: 3 | F7: =I7 -> 191.4 | G7: =F7*E7 -> 574.2 | I7: 191.4 | J7: =Q7*$Q$1 -> 0 | K7: =R7 -> 0 | L7: =S7*$S$1 -> 0 | M7: =T7*$T$1 -> 0 | N7: =U7*$U$1 -> 0 | O7: =E7*I7 -> 574.2 | P7: =Q7+Q7*R7+S7+T7+U7 -> 0 | V7: =E7*P7 -> 0
A8: 2 | B8: 探测器新增、安装 | C8: 1.规格型号:感烟 2.其它：符合规范和设计要求 | D8: 套 | E8: 3 | F8: =I8 -> 261 | G8: =F8*E8 -> 783 | I8: 261 | J8: =Q8*$Q$1 -> 0 | K8: =R8 -> 0 | L8: =S8*$S$1 -> 0 | M8: =T8*$T$1 -> 0 | N8: =U8*$U$1 -> 0 | O8: =E8*I8 -> 783 | P8: =Q8+Q8*R8+S8+T8+U8 -> 0 | V8: =E8*P8 -> 0
A9: 3 | B9: 消防广播拆除、安装 | C9: 1.名称：消防广播 2.型号.规格： | D9: 套 | E9: 1 | F9: =I9 -> 191.4 | G9: =F9*E9 -> 191.4 | I9: 191.4 | J9: =Q9*$Q$1 -> 0 | K9: =R9 -> 0 | L9: =S9*$S$1 -> 0 | M9: =T9*$T$1 -> 0 | N9: =U9*$U$1 -> 0 | O9: =E9*I9 -> 191.4 | P9: =Q9+Q9*R9+S9+T9+U9 -> 0 | V9: =E9*P9 -> 0
A10: 4 | B10: 电气配管 | C10: 1.型号规格：JDG20 2.敷设形式：综合考虑 3.含接线盒 4.根据现场情况改造到位 | D10: 米 | E10: 25 | F10: =I10 -> 24.36 | G10: =F10*E10 -> 609 | I10: 24.36 | J10: =Q10*$Q$1 -> 0 | K10: =R10 -> 0 | L10: =S10*$S$1 -> 0 | M10: =T10*$T$1 -> 0 | N10: =U10*$U$1 -> 0 | O10: =E10*I10 -> 609 | P10: =Q10+Q10*R10+S10+T10+U10 -> 0 | V10: =E10*P10 -> 0
A11: 5 | B11: 金属软管 | C11: 1.型号规格：φ20 2.敷设形式：综合考虑 | D11: 米 | E11: 3 | F11: =I11 -> 10.44 | G11: =F11*E11 -> 31.32 | I11: 10.44 | J11: =Q11*$Q$1 -> 0 | K11: =R11 -> 0 | L11: =S11*$S$1 -> 0 | M11: =T11*$T$1 -> 0 | N11: =U11*$U$1 -> 0 | O11: =E11*I11 -> 31.32 | P11: =Q11+Q11*R11+S11+T11+U11 -> 0 | V11: =E11*P11 -> 0
A12: 6 | B12: 电气配线 | C12: 1.名称:阻燃屏蔽双绞线 2.型号规格：ZR-RVS-2*1.5mm 3.敷设方式：穿管及线槽敷设 | D12: 米 | E12: 45 | F12: =I12 -> 6.96 | G12: =F12*E12 -> 313.2 | I12: 6.96 | J12: =Q12*$Q$1 -> 0 | K12: =R12 -> 0 | L12: =S12*$S$1 -> 0 | M12: =T12*$T$1 -> 0 | N12: =U12*$U$1 -> 0 | O12: =E12*I12 -> 313.2 | P12: =Q12+Q12*R12+S12+T12+U12 -> 0 | V12: =E12*P12 -> 0
A13: 7 | B13: 报警系统调试 | C13: 1、仅限我司施工 的项目 | D13: 项 | E13: 1 | F13: =I13 -> 1000 | G13: =F13*E13 -> 1000 | I13: 1000 | J13: =Q13*$Q$1 -> 0 | K13: =R13 -> 0 | L13: =S13*$S$1 -> 0 | M13: =T13*$T$1 -> 0 | N13: =U13*$U$1 -> 0 | O13: =E13*I13 -> 1000 | P13: =Q13+Q13*R13+S13+T13+U13 -> 0 | V13: =E13*P13 -> 0
A14: 8 | B14: 编程入网、系统接驳 | C14: 1、由大厦原消防施工单位负责，物业统一收费 | D14: ㎡ | E14: 266.31 | F14: =I14 -> 30 | G14: =F14*E14 -> 7989.3 | H14: 不足4000元的按最低4000元计算。超过4000元的按建筑面积30元/㎡计算。 | I14: 30 | J14: =Q14*$Q$1 -> 0 | K14: =R14 -> 0 | L14: =S14*$S$1 -> 20 | M14: =T14*$T$1 -> 0 | N14: =U14*$U$1 -> 0 | O14: =E14*I14 -> 7989.3 | P14: =Q14+Q14*R14+S14+T14+U14 -> 20 | S14: 20 | V14: =E14*P14 -> 5326.2
A15: （二） | B15: 自动喷淋灭火系统 | G15: =F15*E15 -> 0
A16: 1 | B16: 保护性拆除明装喷头 | C16: 1.名称：上喷头保护性拆除 2.型号.规格： | D16: 个 | E16: 16 | F16: =I16 -> 174 | G16: =F16*E16 -> 2784 | I16: 174 | J16: =Q16*$Q$1 -> 0 | K16: =R16 -> 0 | L16: =S16*$S$1 -> 0 | M16: =T16*$T$1 -> 0 | N16: =U16*$U$1 -> 0 | O16: =E16*I16 -> 2784 | P16: =Q16+Q16*R16+S16+T16+U16 -> 0 | V16: =E16*P16 -> 0
A17: 2 | B17: 明装喷头 | C17: 1.名称：明装喷头 2.型号.规格： 3.其它：符合规范和设计要求 | D17: 个 | E17: 17 | F17: =I17 -> 217.5 | G17: =F17*E17 -> 3697.5 | I17: 217.5 | J17: =Q17*$Q$1 -> 0 | K17: =R17 -> 0 | L17: =S17*$S$1 -> 0 | M17: =T17*$T$1 -> 0 | N17: =U17*$U$1 -> 0 | O17: =E17*I17 -> 3697.5 | P17: =Q17+Q17*R17+S17+T17+U17 -> 0 | V17: =E17*P17 -> 0
A18: 3 | B18: 管网支吊架 | C18: 1、含钢制作、安装 | D18: KG | E18: 15 | F18: =I18 -> 21.75 | G18: =F18*E18 -> 326.25 | I18: 21.75 | J18: =Q18*$Q$1 -> 0 | K18: =R18 -> 0 | L18: =S18*$S$1 -> 0 | M18: =T18*$T$1 -> 0 | N18: =U18*$U$1 -> 0 | O18: =E18*I18 -> 326.25 | P18: =Q18+Q18*R18+S18+T18+U18 -> 0 | V18: =E18*P18 -> 0
A19: 4 | B19: 大红油漆（含人工及天那水） | C19: 1、含油漆、天那水、人工 | D19: 桶 | E19: 1 | F19: =I19 -> 435 | G19: =F19*E19 -> 435 | I19: 435 | J19: =Q19*$Q$1 -> 0 | K19: =R19 -> 0 | L19: =S19*$S$1 -> 0 | M19: =T19*$T$1 -> 0 | N19: =U19*$U$1 -> 0 | O19: =E19*I19 -> 435 | P19: =Q19+Q19*R19+S19+T19+U19 -> 0 | V19: =E19*P19 -> 0
A20: 5 | B20: 消防喷淋管 DN25 | C20: 1.安装部位：室内 2.介质:喷淋给水 3.材质、规格:内外壁热镀锌钢管DN25 4.连接方式:螺纹连接 含管件 5.其他要求:满足施工图纸技术规范要求 | D20: 米 | E20: 16.5 | F20: =I20 -> 50.46 | G20: =F20*E20 -> 832.59 | I20: 50.46 | J20: =Q20*$Q$1 -> 0 | K20: =R20 -> 0 | L20: =S20*$S$1 -> 0 | M20: =T20*$T$1 -> 0 | N20: =U20*$U$1 -> 0 | O20: =E20*I20 -> 832.59 | P20: =Q20+Q20*R20+S20+T20+U20 -> 0 | V20: =E20*P20 -> 0
A21: 6 | B21: 消防喷淋管 DN32 | C21: 1.安装部位：室内 2.介质:喷淋给水 3.材质、规格:内外壁热镀锌钢管DN32 4.连接方式:螺纹连接 含管件 5.其他要求:满足施工图纸技术规范要求 | D21: 米 | E21: 8.5 | F21: =I21 -> 56.55 | G21: =F21*E21 -> 480.675 | I21: 56.55 | J21: =Q21*$Q$1 -> 0 | K21: =R21 -> 0 | L21: =S21*$S$1 -> 0 | M21: =T21*$T$1 -> 0 | N21: =U21*$U$1 -> 0 | O21: =E21*I21 -> 480.675 | P21: =Q21+Q21*R21+S21+T21+U21 -> 0 | V21: =E21*P21 -> 0
A22: 7 | B22: 消防喷淋管 DN40 | C22: 1.安装部位：室内 2.介质:喷淋给水 3.材质、规格:内外壁热镀锌钢管DN40 4.连接方式:螺纹连接 含管件 5.其他要求:满足施工图纸技术规范要求 | D22: 米 | E22: 3.5 | F22: =I22 -> 65.25 | G22: =F22*E22 -> 228.375 | I22: 65.25 | J22: =Q22*$Q$1 -> 0 | K22: =R22 -> 0 | L22: =S22*$S$1 -> 0 | M22: =T22*$T$1 -> 0 | N22: =U22*$U$1 -> 0 | O22: =E22*I22 -> 228.375 | P22: =Q22+Q22*R22+S22+T22+U22 -> 0 | V22: =E22*P22 -> 0
A23: 8 | B23: 消防喷淋管 DN50 | C23: 1.安装部位：室内 2.介质:喷淋给水 3.材质、规格:内外壁热镀锌钢管DN50 4.连接方式:螺纹连接 含管件 5.其他要求:满足施工图纸技术规范要求 | D23: 米 | E23: 2.5 | F23: =I23 -> 80.91 | G23: =F23*E23 -> 202.275 | I23: 80.91 | J23: =Q23*$Q$1 -> 0 | K23: =R23 -> 0 | L23: =S23*$S$1 -> 0 | M23: =T23*$T$1 -> 0 | N23: =U23*$U$1 -> 0 | O23: =E23*I23 -> 202.275 | P23: =Q23+Q23*R23+S23+T23+U23 -> 0 | V23: =E23*P23 -> 0
A24: 9 | B24: 喷淋管网排水费 | C24: 1、含管网排水费及人工 | D24: 项 | E24: 1 | F24: =I24 -> 800 | G24: =F24*E24 -> 800 | I24: 800 | J24: =Q24*$Q$1 -> 0 | K24: =R24 -> 0 | L24: =S24*$S$1 -> 0 | M24: =T24*$T$1 -> 0 | N24: =U24*$U$1 -> 0 | O24: =E24*I24 -> 800 | P24: =Q24+Q24*R24+S24+T24+U24 -> 0 | V24: =E24*P24 -> 0
A25: 10 | B25: 喷淋管网试压 | C25: 1、管网冲洗、试压、调试 | D25: 项 | E25: 1 | F25: =I25 -> 870 | G25: =F25*E25 -> 870 | I25: 870 | J25: =Q25*$Q$1 -> 0 | K25: =R25 -> 0 | L25: =S25*$S$1 -> 0 | M25: =T25*$T$1 -> 0 | N25: =U25*$U$1 -> 0 | O25: =E25*I25 -> 870 | P25: =Q25+Q25*R25+S25+T25+U25 -> 0 | V25: =E25*P25 -> 0
A26: （三） | B26: 机械排烟系统
A27: 1 | B27: 镀锌风管拆除、移位 | D27: ㎡ | E27: 5.5 | F27: =I27 -> 156.6 | G27: =F27*E27 -> 861.3 | I27: 156.6 | J27: =Q27*$Q$1 -> 0 | K27: =R27 -> 0 | L27: =S27*$S$1 -> 0 | M27: =T27*$T$1 -> 0 | N27: =U27*$U$1 -> 0 | O27: =E27*I27 -> 861.3 | P27: =Q27+Q27*R27+S27+T27+U27 -> 0 | V27: =E27*P27 -> 0
A28: 2 | B28: 镀锌风管新增、安装 | C28: 1.风管的制作与安装 2.法兰、支架的制作、防锈与安装固定 | D28: ㎡ | E28: 1.5 | F28: =I28 -> 147.9 | G28: =F28*E28 -> 221.85 | I28: 147.9 | J28: =Q28*$Q$1 -> 0 | K28: =R28 -> 0 | L28: =S28*$S$1 -> 0 | M28: =T28*$T$1 -> 0 | N28: =U28*$U$1 -> 0 | O28: =E28*I28 -> 221.85 | P28: =Q28+Q28*R28+S28+T28+U28 -> 0 | V28: =E28*P28 -> 0
A29: 3 | B29: 风管防火包裹 | D29: ㎡ | E29: =E27+E28 -> 7 | F29: =I29 -> 87 | G29: =F29*E29 -> 609 | I29: 87 | J29: =Q29*$Q$1 -> 0 | K29: =R29 -> 0 | L29: =S29*$S$1 -> 0 | M29: =T29*$T$1 -> 0 | N29: =U29*$U$1 -> 0 | O29: =E29*I29 -> 609 | P29: =Q29+Q29*R29+S29+T29+U29 -> 0 | V29: =E29*P29 -> 0
A30: 4 | B30: 280℃防火阀拆除、安装 | C30: 1.型号：防火阀280℃ 2.包含设备及辅材安装费 3.包含电源线接驳 | D30: 套 | E30: 1 | F30: =I30 -> 870 | G30: =F30*E30 -> 870 | I30: 870 | J30: =Q30*$Q$1 -> 0 | K30: =R30 -> 0 | L30: =S30*$S$1 -> 0 | M30: =T30*$T$1 -> 0 | N30: =U30*$U$1 -> 0 | O30: =E30*I30 -> 870 | P30: =Q30+Q30*R30+S30+T30+U30 -> 0 | V30: =E30*P30 -> 0
A31: 5 | B31: 常开百叶风口 | C31: 1、规格：成品铝框架百叶风口供货及安装 2、包含但不限于编制说明、图纸、技术要求中的相关内容及完成该项目的一切所需 | D31: 个 | E31: 5 | F31: =I31 -> 348 | G31: =F31*E31 -> 1740 | I31: 348 | J31: =Q31*$Q$1 -> 0 | K31: =R31 -> 0 | L31: =S31*$S$1 -> 0 | M31: =T31*$T$1 -> 0 | N31: =U31*$U$1 -> 0 | O31: =E31*I31 -> 1740 | P31: =Q31+Q31*R31+S31+T31+U31 -> 0 | V31: =E31*P31 -> 0
A32: 6 | B32: 排烟系统调试 | D32: 项 | E32: 1 | F32: =I32 -> 1500 | G32: =F32*E32 -> 1500 | I32: 1500 | J32: =Q32*$Q$1 -> 0 | K32: =R32 -> 0 | L32: =S32*$S$1 -> 0 | M32: =T32*$T$1 -> 0 | N32: =U32*$U$1 -> 0 | O32: =E32*I32 -> 1500 | P32: =Q32+Q32*R32+S32+T32+U32 -> 0 | V32: =E32*P32 -> 0
A33: （四） | B33: 其他
A34: 1 | B34: 消防报验 | C34: 含相关部门收取的报验费用。 | D34: 项 | E34: 1 | F34: =I34 -> 3000 | G34: =F34*E34 -> 3000 | I34: 3000 | J34: =Q34*$Q$1 -> 0 | K34: =R34 -> 0 | L34: =S34*$S$1 -> 0 | M34: =T34*$T$1 -> 0 | N34: =U34*$U$1 -> 0 | O34: =E34*I34 -> 3000 | P34: =Q34+Q34*R34+S34+T34+U34 -> 0 | V34: =E34*P34 -> 0
A35: 2 | B35: 综合专业设计出图 | D35: 套 | E35: 1 | F35: =I35 -> 870 | G35: =F35*E35 -> 870 | I35: 870 | P35: =Q35+Q35*R35+S35+T35+U35 -> 0 | V35: =E35*P35 -> 0
A36: 三 | B36: 小计 | D36: 项 | E36: 1 | G36: =G3+G5 -> 63320.235 | I36: =SUBTOTAL(9,G3:G35) -> 63320.235
A37: 四 | B37: 管理费 | C37: =不含空调消防清单!C106 -> 0.05 | D37: 项 | E37: 1 | G37: =G36*C37 -> 3166.0118
A38: 五 | B38: 税金 | C38: =不含空调消防清单!C107 -> 0.09 | D38: 项 | E38: 1 | G38: =(G36+G37)*C38 -> 5983.7622
A39: 六 | B39: 合计 | D39: 项 | E39: 1 | G39: =G38+G37+G36 -> 72470.009

Sheet 材料设备参考品牌
A1: 3206材料设备参考品牌
A2: 序号 | B2: 专业 | C2: 材料名称 | D2: 中高档品牌，报两三个品牌 | E2: 备注
A3: 1 | B3: 装饰 | C3: 地砖 | D3: 玛格罗兰、简一
A4: 2 | B4: 装饰 | C4: 岩板（800*1600） | D4: 伊诺、玛格罗兰
A5: 3 | B5: 装饰 | C5: 木饰面 | D5: 定制
A6: 4 | B6: 装饰 | C6: 不锈钢 | D6: 国产优质
A7: 5 | B7: 装饰 | C7: 石膏板 | D7: 深耐福
A8: 6 | B8: 装饰 | C8: 夹板、阻燃板 | D8: 深耐福
A9: 7 | B9: 装饰 | C9: 艺术漆 | D9: =D6 -> 国产优质
A10: 8 | B10: 装饰 | C10: 乳胶漆 | D10: 立邦
A11: 9 | B11: 装饰 | C11: 腻子 | D11: 立邦
A12: 10 | B12: 安装 | C12: 照明，强电用线 | D12: 南洋
A13: 11 | B13: 安装 | C13: 灯具（射灯、筒灯） | D13: 三雄、欧普
A14: 12 | B14: 安装 | C14: LED灯带 | D14: 三雄、欧普
A15: 13 | B15: 安装 | C15: 照明开关 | D15: 公牛
A16: 14 | B16: 安装 | C16: 插座 | D16: 公牛
A17: 15 | B17: 安装 | C17: 网络插座 | D17: 公牛
A18: 16 | B18: 安装 | C18: 信号线、网线 | D18: 海康
A19: 17 | B19: 空调 | C19: 空调风机盘管 | D19: 麦克维尔
A20: 18 | B20: 安装 | C20: 电动窗帘电机 | D20: 国产杜亚
