Workbook

Sheet 汇总表
A1: 汇总表
A2: 序号 | B2: 单位工程 | C2: 含税合价 | D2: 不含税控制合价 | E2: 含税控制合价 | F2: 备注
A3: 1 | B3: 架空层安装工程 | C3: =架空层安装工程!M62 | D3: 88648.61 | E3: =D3*1.09
A4: 2 | B4: 会所售楼部安装工程 | C4: =会所售楼部安装工程!M141 | D4: 597991.63 | E4: =D4*1.09
A5: 3 | B5: 样板房安装工程 | C5: =样板房安装工程!M261 | D5: 177912.2 | E5: =D5*1.09
A6: 4 | B6: 公共区域安装工程 | C6: =公共区域安装工程!M25 | D6: 103574.11 | E6: =D6*1.09
A7: 5 | B7: 户内交标安装工程 | C7: =户内交标安装工程!M66 | D7: 1011928 | E7: =D7*1.09
A8: 6 | B8: 会所售楼处消防电工程 | C8: =会所售楼处消防电工程!M24 | D8: 19891.5 | E8: =D8*1.09
A9: 7 | B9: 会所售楼处消防水工程 | C9: =会所售楼处消防水工程!M20 | D9: 63764.22 | E9: =D9*1.09
A10: 小计 | D10: =SUM(D3:D9) | E10: =SUM(E3:E9)

Sheet 架空层安装工程
A1: 架空层安装工程工程量清单 | O1: 成本单价组成（投标人填写）
A2: 序号 | B2: 编码 | C2: 项目名称 | D2: 项目特征 | E2: 单位 | F2: 工程量 | G2: 人工费 | H2: 材料费 | I2: 机械费 | J2: 管理费 | K2: 利润 | L2: 不含税单价 | M2: 合价 | O2: 单价合计 | P2: 主材费 | Q2: 主材损耗率 | R2: 人工费 | S2: 辅材费 | T2: 机械费 | U2: 合计
J3: 0 | K3: 0 | P3: 1 | R3: 1 | S3: 1 | T3: 1
B4: 单位工程
C5: 电气工程
C6: 灯具
A7: 1 | B7: 30413002007 | C7: LA-01 筒灯 | D7: 1.名称：LA-01 筒灯 2.规格：12W 4000K 灯体尺寸Φ118*50mm 3.安装方式：嵌装 4.其他：包括但不限于满足图纸、招标文件、规范及验收要求等一切相关费用 | E7: 套 | F7: 100 | G7: =R7*$R$3 | H7: =P7*(1+Q7)*$P$3+S7*$S$3 | I7: =T7*$T$3 | J7: =(G7+H7+I7)*$J$3 | K7: =(G7+H7+I7+J7)*$K$3 | L7: =G7+H7+I7+J7+K7 | M7: =F7*L7 | O7: =P7*(1+Q7)+R7+S7+T7 | P7: 70 | Q7: 0 | R7: 20 | S7: 6 | T7: 0 | U7: =F7*O7
A8: 2 | B8: 30413002008 | C8: LA-06 LED明装筒灯 | D8: 1.名称：LA-06 LED明装筒灯 2.规格：9W 4000K 灯体尺寸Φ150*100mm 3.安装方式：明装 4.其他：包括但不限于满足图纸、招标文件、规范及验收要求等一切相关费用 | E8: 套 | F8: 93 | G8: =R8*$R$3 | H8: =P8*(1+Q8)*$P$3+S8*$S$3 | I8: =T8*$T$3 | J8: =(G8+H8+I8)*$J$3 | K8: =(G8+H8+I8+J8)*$K$3 | L8: =G8+H8+I8+J8+K8 | M8: =F8*L8 | O8: =P8*(1+Q8)+R8+S8+T8 | P8: 70 | Q8: 0 | R8: 20 | S8: 6 | T8: 0 | U8: =F8*O8
A9: 3 | B9: 30413002009 | C9: LA-03 LED灯带 | D9: 1.名称：LA-03 LED灯带 2.规格：8W/米 4000K 3.安装方式：天花 4.其他：包括但不限于满足图纸、招标文件、规范及验收要求等一切相关费用 | E9: m | F9: 63.63 | G9: =R9*$R$3 | H9: =P9*(1+Q9)*$P$3+S9*$S$3 | I9: =T9*$T$3 | J9: =(G9+H9+I9)*$J$3 | K9: =(G9+H9+I9+J9)*$K$3 | L9: =G9+H9+I9+J9+K9 | M9: =F9*L9 | O9: =P9*(1+Q9)+R9+S9+T9 | P9: 20.4 | Q9: 0 | R9: 12.5 | S9: 0.41 | T9: 0 | U9: =F9*O9
A10: 4 | B10: 30413009002 | C10: LED 灯带驱动电源 | D10: 1.名称：LED 灯带驱动电源 2.规格：60W 工作电压：220V 输出电压：24V 3.尺寸：L140*W45*H29mm 4.其他：包括但不限于满足图纸、招标文件、规范及验收要求等一切相关费用 | E10: 个 | F10: 8 | G10: =R10*$R$3 | H10: =P10*(1+Q10)*$P$3+S10*$S$3 | I10: =T10*$T$3 | J10: =(G10+H10+I10)*$J$3 | K10: =(G10+H10+I10+J10)*$K$3 | L10: =G10+H10+I10+J10+K10 | M10: =F10*L10 | O10: =P10*(1+Q10)+R10+S10+T10 | P10: 20 | Q10: 0 | R10: 3 | S10: 0.5 | T10: 0 | U10: =F10*O10
A11: 5 | B11: 30413002010 | C11: LA-05 吊装硬条灯 | D11: 1.名称：LA-05 吊装硬条灯 2.规格：4000K 3.安装方式：吊装 4.其他：包括但不限于满足图纸、招标文件、规范及验收要求等一切相关费用 | E11: m | F11: 79.02 | G11: =R11*$R$3 | H11: =P11*(1+Q11)*$P$3+S11*$S$3 | I11: =T11*$T$3 | J11: =(G11+H11+I11)*$J$3 | K11: =(G11+H11+I11+J11)*$K$3 | L11: =G11+H11+I11+J11+K11 | M11: =F11*L11 | O11: =P11*(1+Q11)+R11+S11+T11 | P11: 180 | Q11: 0 | R11: 15 | S11: 2 | T11: 0 | U11: =F11*O11
A12: 6 | B12: 30413002011 | C12: LA-04 艺术吊灯 | D12: 1.名称：LA-04 艺术吊灯 2.规格：铁艺+铝材+玻璃 颜色：磨砂黑+烟灰灯罩 色温4000K 3.安装方式：吊装 4.其他：包括但不限于满足图纸、招标文件、规范及验收要求等一切相关费用 | E12: 套 | F12: 1 | G12: =R12*$R$3 | H12: =P12*(1+Q12)*$P$3+S12*$S$3 | I12: =T12*$T$3 | J12: =(G12+H12+I12)*$J$3 | K12: =(G12+H12+I12+J12)*$K$3 | L12: =G12+H12+I12+J12+K12 | M12: =F12*L12 | O12: =P12*(1+Q12)+R12+S12+T12 | P12: 800 | Q12: 0 | R12: 30 | S12: 10 | T12: 0 | U12: =F12*O12
A13: 7 | B13: 30413002012 | C13: LA-07 LED云朵灯 | D13: 1.名称：LA-07 LED云朵灯 2.规格：48W 4000K 产品尺寸：L800*W35mm 3.安装方式：吊装 4.其他：包括但不限于满足图纸、招标文件、规范及验收要求等一切相关费用 | E13: 套 | F13: 2 | G13: =R13*$R$3 | H13: =P13*(1+Q13)*$P$3+S13*$S$3 | I13: =T13*$T$3 | J13: =(G13+H13+I13)*$J$3 | K13: =(G13+H13+I13+J13)*$K$3 | L13: =G13+H13+I13+J13+K13 | M13: =F13*L13 | O13: =P13*(1+Q13)+R13+S13+T13 | P13: 280 | Q13: 0 | R13: 20 | S13: 3 | T13: 0 | U13: =F13*O13
C14: 开关插座 | U14: =F14*O14
A15: 8 | B15: 30413013004 | C15: 照明开关 | D15: 1.名称：单联单控开关 2.规格：86*86mm 3.安装方式：暗装 4.其他：包括但不限于满足图纸、招标文件、规范及验收要求等一切相关费用 | E15: 套 | F15: 5 | G15: =R15*$R$3 | H15: =P15*(1+Q15)*$P$3+S15*$S$3 | I15: =T15*$T$3 | J15: =(G15+H15+I15)*$J$3 | K15: =(G15+H15+I15+J15)*$K$3 | L15: =G15+H15+I15+J15+K15 | M15: =F15*L15 | O15: =P15*(1+Q15)+R15+S15+T15 | P15: ='公共区域安装工程'!P14 | Q15: ='公共区域安装工程'!Q14 | R15: ='公共区域安装工程'!R14 | S15: ='公共区域安装工程'!S14 | T15: ='公共区域安装工程'!T14 | U15: =F15*O15
A16: 9 | B16: 30413013005 | C16: 照明开关 | D16: 1.名称：双联单控开关 2.规格：86*86mm 3.安装方式：暗装 4.其他：包括但不限于满足图纸、招标文件、规范及验收要求等一切相关费用 | E16: 套 | F16: 5 | G16: =R16*$R$3 | H16: =P16*(1+Q16)*$P$3+S16*$S$3 | I16: =T16*$T$3 | J16: =(G16+H16+I16)*$J$3 | K16: =(G16+H16+I16+J16)*$K$3 | L16: =G16+H16+I16+J16+K16 | M16: =F16*L16 | O16: =P16*(1+Q16)+R16+S16+T16 | P16: 18 | Q16: 0 | R16: 10 | S16: 1.5 | T16: 0 | U16: =F16*O16
A17: 10 | B17: 30413013006 | C17: 照明开关 | D17: 1.名称：三联单控开关 2.规格：86*86mm 3.安装方式：暗装 4.其他：包括但不限于满足图纸、招标文件、规范及验收要求等一切相关费用 | E17: 套 | F17: 10 | G17: =R17*$R$3 | H17: =P17*(1+Q17)*$P$3+S17*$S$3 | I17: =T17*$T$3 | J17: =(G17+H17+I17)*$J$3 | K17: =(G17+H17+I17+J17)*$K$3 | L17: =G17+H17+I17+J17+K17 | M17: =F17*L17 | O17: =P17*(1+Q17)+R17+S17+T17 | P17: ='公共区域安装工程'!P15 | Q17: ='公共区域安装工程'!Q15 | R17: ='公共区域安装工程'!R15 | S17: ='公共区域安装工程'!S15 | T17: ='公共区域安装工程'!T15 | U17: =F17*O17
A18: 11 | B18: 30413014001 | C18: 插座 | D18: 1.名称：五孔插座 2.规格：86*86mm 3.安装方式：暗装 4.其他：包括但不限于满足图纸、招标文件、规范及验收要求等一切相关费用 | E18: 套 | F18: 14 | G18: =R18*$R$3 | H18: =P18*(1+Q18)*$P$3+S18*$S$3 | I18: =T18*$T$3 | J18: =(G18+H18+I18)*$J$3 | K18: =(G18+H18+I18+J18)*$K$3 | L18: =G18+H18+I18+J18+K18 | M18: =F18*L18 | O18: =P18*(1+Q18)+R18+S18+T18 | P18: ='公共区域安装工程'!P16 | Q18: ='公共区域安装工程'!Q16 | R18: ='公共区域安装工程'!R16 | S18: ='公共区域安装工程'!S16 | T18: ='公共区域安装工程'!T16 | U18: =F18*O18
A19: 12 | B19: 30413014002 | C19: 插座 | D19: 1.名称：地面五孔插座 2.规格：86*86mm 3.安装方式：暗装 4.其他：包括但不限于满足图纸、招标文件、规范及验收要求等一切相关费用 | E19: 套 | F19: 6 | G19: =R19*$R$3 | H19: =P19*(1+Q19)*$P$3+S19*$S$3 | I19: =T19*$T$3 | J19: =(G19+H19+I19)*$J$3 | K19: =(G19+H19+I19+J19)*$K$3 | L19: =G19+H19+I19+J19+K19 | M19: =F19*L19 | O19: =P19*(1+Q19)+R19+S19+T19 | P19: 14.62 | Q19: 0 | R19: 6.31 | S19: 1.12 | T19: 0 | U19: =F19*O19
C20: 配线 | U20: =F20*O20
A21: 13 | B21: 30412004002 | C21: 配线 | D21: 1.名称：电气配线 2.型号规格：WDZC-BYJ-2.5 3.安装方式：管内穿线 4.其他：包括但不限于满足图纸、招标文件、规范及验收要求等一切相关费用 | E21: m | F21: 3020.18 | G21: =R21*$R$3 | H21: =P21*(1+Q21)*$P$3+S21*$S$3 | I21: =T21*$T$3 | J21: =(G21+H21+I21)*$J$3 | K21: =(G21+H21+I21+J21)*$K$3 | L21: =G21+H21+I21+J21+K21 | M21: =F21*L21 | O21: =P21*(1+Q21)+R21+S21+T21 | P21: ='公共区域安装工程'!P17 | Q21: ='公共区域安装工程'!Q17 | R21: ='公共区域安装工程'!R17 | S21: ='公共区域安装工程'!S17 | T21: ='公共区域安装工程'!T17 | U21: =F21*O21
A22: 14 | B22: 30412004003 | C22: 配线 | D22: 1.名称：电气配线 2.型号规格：WDZC-BYJ-6 3.安装方式：管内穿线 4.其他：包括但不限于满足图纸、招标文件、规范及验收要求等一切相关费用 | E22: m | F22: 372.91 | G22: =R22*$R$3 | H22: =P22*(1+Q22)*$P$3+S22*$S$3 | I22: =T22*$T$3 | J22: =(G22+H22+I22)*$J$3 | K22: =(G22+H22+I22+J22)*$K$3 | L22: =G22+H22+I22+J22+K22 | M22: =F22*L22 | O22: =P22*(1+Q22)+R22+S22+T22 | P22: 133.4 | Q22: 0.02 | R22: 15 | S22: 1.07 | T22: 1.07 | U22: =F22*O22
A23: 15 | B23: 30412004004 | C23: 配线 | D23: 1.名称：电气配线 2.型号规格：RVS-4*1.0 3.安装方式：管内穿线 4.其他：包括但不限于满足图纸、招标文件、规范及验收要求等一切相关费用 | E23: m | F23: 87.49 | G23: =R23*$R$3 | H23: =P23*(1+Q23)*$P$3+S23*$S$3 | I23: =T23*$T$3 | J23: =(G23+H23+I23)*$J$3 | K23: =(G23+H23+I23+J23)*$K$3 | L23: =G23+H23+I23+J23+K23 | M23: =F23*L23 | O23: =P23*(1+Q23)+R23+S23+T23 | P23: 3.8 | Q23: 0.02 | R23: 5.2 | S23: 0.23 | T23: 0.05 | U23: =F23*O23
C24: 空调工程 | U24: =F24*O24
C25: 设备 | U25: =F25*O25
A26: 16 | B26: 30701003001 | C26: 风管机 | D26: 1.名称：风管机 F22 2.规格：制冷量2.2kW 制热量2.6kW 风量480m3/h 机外静压10Pa 额定功率0.05kW 运转噪音≤37dB(A) 3.安装方式：吊装 4.其他：包括但不限于满足图纸、招标文件、规范及验收要求等一切相关费用 | E26: 台 | F26: 2 | G26: =R26*$R$3 | H26: =P26*(1+Q26)*$P$3+S26*$S$3 | I26: =T26*$T$3 | J26: =(G26+H26+I26)*$J$3 | K26: =(G26+H26+I26+J26)*$K$3 | L26: =G26+H26+I26+J26+K26 | M26: =F26*L26 | O26: =P26*(1+Q26)+R26+S26+T26 | P26: 3600 | Q26: 0 | R26: 1000 | S26: 1200 | T26: 45 | U26: =F26*O26
A27: 17 | B27: 30701003002 | C27: 风管机 | D27: 1.名称：风管机 F32 2.规格：制冷量3.2kW 制热量3.6kW 风量570m3/h 机外静压30Pa 额定功率0.05kW 运转噪音≤37dB(A) 3.安装方式：吊装 4.其他：包括但不限于满足图纸、招标文件、规范及验收要求等一切相关费用 | E27: 台 | F27: 1 | G27: =R27*$R$3 | H27: =P27*(1+Q27)*$P$3+S27*$S$3 | I27: =T27*$T$3 | J27: =(G27+H27+I27)*$J$3 | K27: =(G27+H27+I27+J27)*$K$3 | L27: =G27+H27+I27+J27+K27 | M27: =F27*L27 | O27: =P27*(1+Q27)+R27+S27+T27 | P27: 3600 | Q27: 0 | R27: 1000 | S27: 1200 | T27: 45 | U27: =F27*O27
A28: 18 | B28: 30701003003 | C28: 风管机 | D28: 1.名称：风管机 F45 2.规格：制冷量4.5kW 制热量5.0kW 风量800m3/h 机外静压30Pa 额定功率0.05kW 运转噪音≤37dB(A) 3.安装方式：吊装 4.其他：包括但不限于满足图纸、招标文件、规范及验收要求等一切相关费用 | E28: 台 | F28: 1 | G28: =R28*$R$3 | H28: =P28*(1+Q28)*$P$3+S28*$S$3 | I28: =T28*$T$3 | J28: =(G28+H28+I28)*$J$3 | K28: =(G28+H28+I28+J28)*$K$3 | L28: =G28+H28+I28+J28+K28 | M28: =F28*L28 | O28: =P28*(1+Q28)+R28+S28+T28 | P28: 3600 | Q28: 0 | R28: 1000 | S28: 1200 | T28: 45 | U28: =F28*O28
A29: 19 | B29: 30701003004 | C29: 风管机 | D29: 1.名称：风管机 F56 2.规格：制冷量5.6kW 制热量6.3kW 风量550m3/h 机外静压10Pa 额定功率0.05kW 运转噪音≤37dB(A) 3.安装方式：吊装 4.其他：包括但不限于满足图纸、招标文件、规范及验收要求等一切相关费用 | E29: 台 | F29: 4 | G29: =R29*$R$3 | H29: =P29*(1+Q29)*$P$3+S29*$S$3 | I29: =T29*$T$3 | J29: =(G29+H29+I29)*$J$3 | K29: =(G29+H29+I29+J29)*$K$3 | L29: =G29+H29+I29+J29+K29 | M29: =F29*L29 | O29: =P29*(1+Q29)+R29+S29+T29 | P29: 3600 | Q29: 0 | R29: 1000 | S29: 1200 | T29: 45 | U29: =F29*O29
A30: 20 | B30: 30701003006 | C30: 风管机 | D30: 1.名称：风管机 F63 2.规格：制冷量6.3kW 制热量7.1kW 风量1000m3/h 机外静压30Pa 额定功率0.11kW 运转噪音≤40dB(A) 3.安装方式：吊装 4.其他：包括但不限于满足图纸、招标文件、规范及验收要求等一切相关费用 | E30: 台 | F30: 1 | G30: =R30*$R$3 | H30: =P30*(1+Q30)*$P$3+S30*$S$3 | I30: =T30*$T$3 | J30: =(G30+H30+I30)*$J$3 | K30: =(G30+H30+I30+J30)*$K$3 | L30: =G30+H30+I30+J30+K30 | M30: =F30*L30 | O30: =P30*(1+Q30)+R30+S30+T30 | P30: 3600 | Q30: 0 | R30: 1000 | S30: 1200 | T30: 45 | U30: =F30*O30
A31: 21 | B31: 30701003007 | C31: 风管机 | D31: 1.名称：风管机 F90 2.规格：制冷量9.0kW 制热量10.0kW 风量1450m3/h 机外静压30Pa 额定功率0.11kW 运转噪音≤40dB(A) 3.安装方式：吊装 4.其他：包括但不限于满足图纸、招标文件、规范及验收要求等一切相关费用 | E31: 台 | F31: 1 | G31: =R31*$R$3 | H31: =P31*(1+Q31)*$P$3+S31*$S$3 | I31: =T31*$T$3 | J31: =(G31+H31+I31)*$J$3 | K31: =(G31+H31+I31+J31)*$K$3 | L31: =G31+H31+I31+J31+K31 | M31: =F31*L31 | O31: =P31*(1+Q31)+R31+S31+T31 | P31: 3600 | Q31: 0 | R31: 1000 | S31: 1200 | T31: 45 | U31: =F31*O31
A32: 22 | B32: 30701003005 | C32: 多联式室外机 | D32: 1.名称：多联式室外机 L-1#-1/2 2.规格：制冷量24.0kW 制热量26.0kW 风量10000m3/h 机外静压-Pa 额定功率7.6kW 运转噪音≤61dB(A) 3.安装方式：落地 4.其他：包括但不限于满足图纸、招标文件、规范及验收要求等一切相关费用 | E32: 台 | F32: 2 | G32: =R32*$R$3 | H32: =P32*(1+Q32)*$P$3+S32*$S$3 | I32: =T32*$T$3 | J32: =(G32+H32+I32)*$J$3 | K32: =(G32+H32+I32+J32)*$K$3 | L32: =G32+H32+I32+J32+K32 | M32: =F32*L32 | O32: =P32*(1+Q32)+R32+S32+T32 | P32: 12000 | Q32: 0 | R32: 800 | S32: 80 | T32: 60 | U32: =F32*O32
A33: 23 | B33: 30413013010 | C33: 空调温控面板 | D33: 1.名称：空调温控面板 2.规格：86*86mm 3.安装方式：暗装 4.其他：包括但不限于满足图纸、招标文件、规范及验收要求等一切相关费用 | E33: 套 | F33: 7 | G33: =R33*$R$3 | H33: =P33*(1+Q33)*$P$3+S33*$S$3 | I33: =T33*$T$3 | J33: =(G33+H33+I33)*$J$3 | K33: =(G33+H33+I33+J33)*$K$3 | L33: =G33+H33+I33+J33+K33 | M33: =F33*L33 | O33: =P33*(1+Q33)+R33+S33+T33 | P33: 95 | Q33: 0 | R33: 35 | S33: 8 | T33: 0 | U33: =F33*O33
A34: 24 | B34: 30703007001 | C34: 单层百叶风口 | D34: 1.名称：单层百叶风口 2.周长：≤1800mm 3.规格：500*150 4.其他：包括但不限于满足图纸、招标文件、规范及验收要求等一切相关费用 | E34: 个 | F34: 4 | G34: =R34*$R$3 | H34: =P34*(1+Q34)*$P$3+S34*$S$3 | I34: =T34*$T$3 | J34: =(G34+H34+I34)*$J$3 | K34: =(G34+H34+I34+J34)*$K$3 | L34: =G34+H34+I34+J34+K34 | M34: =F34*L34 | O34: =P34*(1+Q34)+R34+S34+T34 | P34: 75 | Q34: 0 | R34: 20 | S34: 6 | T34: 0 | U34: =F34*O34
A35: 25 | B35: 30703007006 | C35: 单层百叶风口 | D35: 1.名称：单层百叶风口 2.周长：≤1800mm 3.规格：600*150 4.其他：包括但不限于满足图纸、招标文件、规范及验收要求等一切相关费用 | E35: 个 | F35: 2 | G35: =R35*$R$3 | H35: =P35*(1+Q35)*$P$3+S35*$S$3 | I35: =T35*$T$3 | J35: =(G35+H35+I35)*$J$3 | K35: =(G35+H35+I35+J35)*$K$3 | L35: =G35+H35+I35+J35+K35 | M35: =F35*L35 | O35: =P35*(1+Q35)+R35+S35+T35 | P35: 75 | Q35: 0 | R35: 20 | S35: 6 | T35: 0 | U35: =F35*O35
A36: 26 | B36: 30703007007 | C36: 单层百叶风口 | D36: 1.名称：单层百叶风口 2.周长：≤1800mm 3.规格：700*150 4.其他：包括但不限于满足图纸、招标文件、规范及验收要求等一切相关费用 | E36: 个 | F36: 2 | G36: =R36*$R$3 | H36: =P36*(1+Q36)*$P$3+S36*$S$3 | I36: =T36*$T$3 | J36: =(G36+H36+I36)*$J$3 | K36: =(G36+H36+I36+J36)*$K$3 | L36: =G36+H36+I36+J36+K36 | M36: =F36*L36 | O36: =P36*(1+Q36)+R36+S36+T36 | P36: 75 | Q36: 0 | R36: 20 | S36: 6 | T36: 0 | U36: =F36*O36
A37: 27 | B37: 30703007004 | C37: 单层百叶风口 | D37: 1.名称：单层百叶风口 2.周长：≤3300mm 3.规格：900*150 4.其他：包括但不限于满足图纸、招标文件、规范及验收要求等一切相关费用 | E37: 个 | F37: 8 | G37: =R37*$R$3 | H37: =P37*(1+Q37)*$P$3+S37*$S$3 | I37: =T37*$T$3 | J37: =(G37+H37+I37)*$J$3 | K37: =(G37+H37+I37+J37)*$K$3 | L37: =G37+H37+I37+J37+K37 | M37: =F37*L37 | O37: =P37*(1+Q37)+R37+S37+T37 | P37: 75 | Q37: 0 | R37: 20 | S37: 6 | T37: 0 | U37: =F37*O37
A38: 28 | B38: 30703007008 | C38: 单层百叶风口 | D38: 1.名称：单层百叶风口 2.周长：≤4200mm 3.规格：1250*150 4.其他：包括但不限于满足图纸、招标文件、规范及验收要求等一切相关费用 | E38: 个 | F38: 4 | G38: =R38*$R$3 | H38: =P38*(1+Q38)*$P$3+S38*$S$3 | I38: =T38*$T$3 | J38: =(G38+H38+I38)*$J$3 | K38: =(G38+H38+I38+J38)*$K$3 | L38: =G38+H38+I38+J38+K38 | M38: =F38*L38 | O38: =P38*(1+Q38)+R38+S38+T38 | P38: 75 | Q38: 0 | R38: 20 | S38: 6 | T38: 0 | U38: =F38*O38
C39: 风管 | U39: =F39*O39
A40: 29 | B40: 30702001001 | C40: 碳钢通风管道 | D40: 1.名称：矩形风管 2.材质：镀锌薄钢板 3.厚度：0.6mm 4.长边：≤1000mm 5.其他：包括但不限于满足图纸、招标文件、规范及验收要求等一切相关费用 | E40: m2 | F40: 6.28 | G40: =R40*$R$3 | H40: =P40*(1+Q40)*$P$3+S40*$S$3 | I40: =T40*$T$3 | J40: =(G40+H40+I40)*$J$3 | K40: =(G40+H40+I40+J40)*$K$3 | L40: =G40+H40+I40+J40+K40 | M40: =F40*L40 | O40: =P40*(1+Q40)+R40+S40+T40 | P40: 85 | Q40: 0.03 | R40: 48 | S40: 12 | T40: 2 | U40: =F40*O40
A41: 30 | B41: 30702001002 | C41: 碳钢通风管道 | D41: 1.名称：矩形风管 2.材质：镀锌薄钢板 3.厚度：0.75mm 4.长边：≤1000mm 5.其他：包括但不限于满足图纸、招标文件、规范及验收要求等一切相关费用 | E41: m2 | F41: 27.07 | G41: =R41*$R$3 | H41: =P41*(1+Q41)*$P$3+S41*$S$3 | I41: =T41*$T$3 | J41: =(G41+H41+I41)*$J$3 | K41: =(G41+H41+I41+J41)*$K$3 | L41: =G41+H41+I41+J41+K41 | M41: =F41*L41 | O41: =P41*(1+Q41)+R41+S41+T41 | P41: 85 | Q41: 0.03 | R41: 48 | S41: 12 | T41: 2 | U41: =F41*O41
A42: 31 | B42: 30702001003 | C42: 碳钢通风管道 | D42: 1.名称：矩形风管 2.材质：镀锌薄钢板 3.厚度：1.0mm 4.长边：≤1250mm 5.其他：包括但不限于满足图纸、招标文件、规范及验收要求等一切相关费用 | E42: m2 | F42: 20.66 | G42: =R42*$R$3 | H42: =P42*(1+Q42)*$P$3+S42*$S$3 | I42: =T42*$T$3 | J42: =(G42+H42+I42)*$J$3 | K42: =(G42+H42+I42+J42)*$K$3 | L42: =G42+H42+I42+J42+K42 | M42: =F42*L42 | O42: =P42*(1+Q42)+R42+S42+T42 | P42: 85 | Q42: 0.03 | R42: 48 | S42: 12 | T42: 2 | U42: =F42*O42
A43: 32 | B43: 30703019001 | C43: 柔性接口 | D43: 1.名称：帆布软接口 2.材质：帆布 3.厚度：满足验收要求 4.其他：包括但不限于满足图纸、招标文件、规范及验收要求等一切相关费用 | E43: m2 | F43: 8.16 | G43: =R43*$R$3 | H43: =P43*(1+Q43)*$P$3+S43*$S$3 | I43: =T43*$T$3 | J43: =(G43+H43+I43)*$J$3 | K43: =(G43+H43+I43+J43)*$K$3 | L43: =G43+H43+I43+J43+K43 | M43: =F43*L43 | O43: =P43*(1+Q43)+R43+S43+T43 | P43: 19.49 | Q43: 0 | R43: 55 | S43: 59.4 | T43: 2.75 | U43: =F43*O43
A44: 33 | B44: 31301005001 | C44: 风管支架刷油 | D44: 1.名称：风管支架刷油 2.按图纸及规范要求 3.其他：包括但不限于以上内容，综合考虑按图纸、招标文件和规范要求而实施、完成这项工程的一切有关费用 | E44: kg | F44: 208.7 | G44: =R44*$R$3 | H44: =P44*(1+Q44)*$P$3+S44*$S$3 | I44: =T44*$T$3 | J44: =(G44+H44+I44)*$J$3 | K44: =(G44+H44+I44+J44)*$K$3 | L44: =G44+H44+I44+J44+K44 | M44: =F44*L44 | O44: =P44*(1+Q44)+R44+S44+T44 | P44: 6.87 | Q44: 0 | R44: 5.77 | S44: 0 | T44: 1.21 | U44: =F44*O44
A45: 34 | B45: 31208003001 | C45: 通风管道绝热 | D45: 1.名称：空调风管保温 2.材质：难燃级B1级橡塑保温材料，不燃A级铝箔贴面，湿阻因子≥10000，符合国家GB8624-2012中的管状绝热材料B标准 3.厚度：20mm 4.其他：包括但不限于满足图纸、招标文件、规范及验收要求等一切相关费用 | E45: m2 | F45: 47.31 | G45: =R45*$R$3 | H45: =P45*(1+Q45)*$P$3+S45*$S$3 | I45: =T45*$T$3 | J45: =(G45+H45+I45)*$J$3 | K45: =(G45+H45+I45+J45)*$K$3 | L45: =G45+H45+I45+J45+K45 | M45: =F45*L45 | O45: =P45*(1+Q45)+R45+S45+T45 | P45: 400 | Q45: 0 | R45: 48 | S45: 12 | T45: 2 | U45: =F45*O45
A46: 35 | B46: 30704001001 | C46: 通风工程检测、调试 | D46: 1.名称：风管漏光试验、漏风试验 | E46: 系统 | F46: 1 | G46: =R46*$R$3 | H46: =P46*(1+Q46)*$P$3+S46*$S$3 | I46: =T46*$T$3 | J46: =(G46+H46+I46)*$J$3 | K46: =(G46+H46+I46+J46)*$K$3 | L46: =G46+H46+I46+J46+K46 | M46: =F46*L46 | O46: =P46*(1+Q46)+R46+S46+T46 | P46: 400 | Q46: 0 | R46: 380 | S46: 200 | T46: 20 | U46: =F46*O46
C47: 水管 | U47: =F47*O47
A48: 36 | B48: 31001005001 | C48: 铜管 | D48: 1.名称：紫铜管 2.规格：φ6.4 3.厚度：0.8mm 4.连接方式：钎焊连结 5.其他：包括但不限于满足图纸、招标文件、规范及验收要求等一切相关费用 | E48: m | F48: 24.46 | G48: =R48*$R$3 | H48: =P48*(1+Q48)*$P$3+S48*$S$3 | I48: =T48*$T$3 | J48: =(G48+H48+I48)*$J$3 | K48: =(G48+H48+I48+J48)*$K$3 | L48: =G48+H48+I48+J48+K48 | M48: =F48*L48 | O48: =P48*(1+Q48)+R48+S48+T48 | P48: 10.72 | Q48: 0.03 | R48: 9.64 | S48: 2.14 | T48: 0 | U48: =F48*O48
A49: 37 | B49: 31001005002 | C49: 铜管 | D49: 1.名称：紫铜管 2.规格：φ9.5 3.厚度：0.8mm 4.连接方式：钎焊连结 5.其他：包括但不限于满足图纸、招标文件、规范及验收要求等一切相关费用 | E49: m | F49: 35.16 | G49: =R49*$R$3 | H49: =P49*(1+Q49)*$P$3+S49*$S$3 | I49: =T49*$T$3 | J49: =(G49+H49+I49)*$J$3 | K49: =(G49+H49+I49+J49)*$K$3 | L49: =G49+H49+I49+J49+K49 | M49: =F49*L49 | O49: =P49*(1+Q49)+R49+S49+T49 | P49: 14.44 | Q49: 0.03 | R49: 14.29 | S49: 2.89 | T49: 0 | U49: =F49*O49
A50: 38 | B50: 31001005003 | C50: 铜管 | D50: 1.名称：紫铜管 2.规格：φ12.7 3.厚度：0.8mm 4.连接方式：钎焊连结 5.其他：包括但不限于满足图纸、招标文件、规范及验收要求等一切相关费用 | E50: m | F50: 24.46 | G50: =R50*$R$3 | H50: =P50*(1+Q50)*$P$3+S50*$S$3 | I50: =T50*$T$3 | J50: =(G50+H50+I50)*$J$3 | K50: =(G50+H50+I50+J50)*$K$3 | L50: =G50+H50+I50+J50+K50 | M50: =F50*L50 | O50: =P50*(1+Q50)+R50+S50+T50 | P50: 15.46 | Q50: 0.03 | R50: 19.09 | S50: 3.09 | T50: 0 | U50: =F50*O50
A51: 39 | B51: 31001005004 | C51: 铜管 | D51: 1.名称：紫铜管 2.规格：φ15.9 3.厚度：1.0mm 4.连接方式：钎焊连结 5.其他：包括但不限于满足图纸、招标文件、规范及验收要求等一切相关费用 | E51: m | F51: 16.04 | G51: =R51*$R$3 | H51: =P51*(1+Q51)*$P$3+S51*$S$3 | I51: =T51*$T$3 | J51: =(G51+H51+I51)*$J$3 | K51: =(G51+H51+I51+J51)*$K$3 | L51: =G51+H51+I51+J51+K51 | M51: =F51*L51 | O51: =P51*(1+Q51)+R51+S51+T51 | P51: 21.54 | Q51: 0.03 | R51: 23.89 | S51: 4.31 | T51: 0 | U51: =F51*O51
A52: 40 | B52: 31001005005 | C52: 铜管 | D52: 1.名称：紫铜管 2.规格：φ19.1 3.厚度：1.0mm 4.连接方式：钎焊连结 5.其他：包括但不限于满足图纸、招标文件、规范及验收要求等一切相关费用 | E52: m | F52: 9.37 | G52: =R52*$R$3 | H52: =P52*(1+Q52)*$P$3+S52*$S$3 | I52: =T52*$T$3 | J52: =(G52+H52+I52)*$J$3 | K52: =(G52+H52+I52+J52)*$K$3 | L52: =G52+H52+I52+J52+K52 | M52: =F52*L52 | O52: =P52*(1+Q52)+R52+S52+T52 | P52: 29.13 | Q52: 0.03 | R52: 28.7 | S52: 5.83 | T52: 0 | U52: =F52*O52
A53: 41 | B53: 31001005006 | C53: 铜管 | D53: 1.名称：紫铜管 2.规格：φ22.2 3.厚度：1.0mm 4.连接方式：钎焊连结 5.其他：包括但不限于满足图纸、招标文件、规范及验收要求等一切相关费用 | E53: m | F53: 9.75 | G53: =R53*$R$3 | H53: =P53*(1+Q53)*$P$3+S53*$S$3 | I53: =T53*$T$3 | J53: =(G53+H53+I53)*$J$3 | K53: =(G53+H53+I53+J53)*$K$3 | L53: =G53+H53+I53+J53+K53 | M53: =F53*L53 | O53: =P53*(1+Q53)+R53+S53+T53 | P53: 32.23 | Q53: 0.03 | R53: 33.34 | S53: 6.45 | T53: 0 | U53: =F53*O53
A54: 42 | B54: 31002001001 | C54: 分歧器 | D54: 1.名称：分歧器 2.规格：公称直径20mm以内 3.其他：包括但不限于满足图纸、招标文件、规范及验收要求等一切相关费用 | E54: 个 | F54: 8 | G54: =R54*$R$3 | H54: =P54*(1+Q54)*$P$3+S54*$S$3 | I54: =T54*$T$3 | J54: =(G54+H54+I54)*$J$3 | K54: =(G54+H54+I54+J54)*$K$3 | L54: =G54+H54+I54+J54+K54 | M54: =F54*L54 | O54: =P54*(1+Q54)+R54+S54+T54 | P54: 118 | Q54: 0 | R54: 94 | S54: 59 | T54: 4.7 | U54: =F54*O54
A55: 43 | B55: 31001008002 | C55: 塑料管 | D55: 1.名称：UPVC管 2.规格：DN25 3.介质：冷凝水 4.连接方式：粘接 5.其他：包括但不限于满足图纸、招标文件、规范及验收要求等一切相关费用 | E55: m | F55: 36.98 | G55: =R55*$R$3 | H55: =P55*(1+Q55)*$P$3+S55*$S$3 | I55: =T55*$T$3 | J55: =(G55+H55+I55)*$J$3 | K55: =(G55+H55+I55+J55)*$K$3 | L55: =G55+H55+I55+J55+K55 | M55: =F55*L55 | O55: =P55*(1+Q55)+R55+S55+T55 | P55: 8.5 | Q55: 0 | R55: 22.09 | S55: 0.26 | T55: 0.04 | U55: =F55*O55
A56: 44 | B56: 31001008003 | C56: 塑料管 | D56: 1.名称：UPVC管 2.规格：DN32 3.介质：冷凝水 4.连接方式：粘接 5.其他：包括但不限于满足图纸、招标文件、规范及验收要求等一切相关费用 | E56: m | F56: 7.5 | G56: =R56*$R$3 | H56: =P56*(1+Q56)*$P$3+S56*$S$3 | I56: =T56*$T$3 | J56: =(G56+H56+I56)*$J$3 | K56: =(G56+H56+I56+J56)*$K$3 | L56: =G56+H56+I56+J56+K56 | M56: =F56*L56 | O56: =P56*(1+Q56)+R56+S56+T56 | P56: 11.59 | Q56: 0 | R56: 23.68 | S56: 0.27 | T56: 0.05 | U56: =F56*O56
A57: 45 | B57: 31001008004 | C57: 塑料管 | D57: 1.名称：UPVC管 2.规格：DN40 3.介质：冷凝水 4.连接方式：粘接 5.其他：包括但不限于满足图纸、招标文件、规范及验收要求等一切相关费用 | E57: m | F57: 9.32 | G57: =R57*$R$3 | H57: =P57*(1+Q57)*$P$3+S57*$S$3 | I57: =T57*$T$3 | J57: =(G57+H57+I57)*$J$3 | K57: =(G57+H57+I57+J57)*$K$3 | L57: =G57+H57+I57+J57+K57 | M57: =F57*L57 | O57: =P57*(1+Q57)+R57+S57+T57 | P57: 20.12 | Q57: 0 | R57: 23.68 | S57: 0.32 | T57: 0.06 | U57: =F57*O57
A58: 46 | B58: 31208002001 | C58: 其他管道绝热 | D58: 1.名称：冷媒管保温 2.材质：难燃B1级橡塑 3.厚度：20mm 4.其他：包括但不限于满足图纸、招标文件、规范及验收要求等一切相关费用 | E58: m3 | F58: 0.27 | G58: =R58*$R$3 | H58: =P58*(1+Q58)*$P$3+S58*$S$3 | I58: =T58*$T$3 | J58: =(G58+H58+I58)*$J$3 | K58: =(G58+H58+I58+J58)*$K$3 | L58: =G58+H58+I58+J58+K58 | M58: =F58*L58 | O58: =P58*(1+Q58)+R58+S58+T58 | P58: 400 | Q58: 0 | R58: 120 | S58: 10 | T58: 5 | U58: =F58*O58
A59: 47 | B59: 31208002002 | C59: 其他管道绝热 | D59: 1.名称：冷凝管保温 2.材质：难燃B1级橡塑 3.厚度：13mm 4.其他：包括但不限于满足图纸、招标文件、规范及验收要求等一切相关费用 | E59: m3 | F59: 0.11 | G59: =R59*$R$3 | H59: =P59*(1+Q59)*$P$3+S59*$S$3 | I59: =T59*$T$3 | J59: =(G59+H59+I59)*$J$3 | K59: =(G59+H59+I59+J59)*$K$3 | L59: =G59+H59+I59+J59+K59 | M59: =F59*L59 | O59: =P59*(1+Q59)+R59+S59+T59 | P59: 400 | Q59: 0 | R59: 120 | S59: 10 | T59: 5 | U59: =F59*O59
B60: 税前合价 | E60: 元 | M60: =SUM(M4:M59)
B61: 税金 | E61: 元 | M61: =M60*0.09
B62: 含税合价 | E62: 元 | M62: =M60+M61

Sheet 会所售楼部安装工程
A1: 会所售楼部安装工程工程量清单 | O1: 成本单价组成（投标人填写）
A2: 序号 | B2: 编码 | C2: 项目名称 | D2: 项目特征 | E2: 单位 | F2: 工程量 | G2: 人工费 | H2: 材料费 | I2: 机械费 | J2: 管理费 | K2: 利润 | L2: 不含税单价 | M2: 合价 | O2: 单价合计 | P2: 主材费 | Q2: 主材损耗率 | R2: 人工费 | S2: 辅材费 | T2: 机械费 | U2: 合计
J3: 0 | K3: 0 | P3: =架空层安装工程!$P$3 | R3: =架空层安装工程!$R$3 | S3: =架空层安装工程!$S$3 | T3: =架空层安装工程!$T$3
B4: 单位工程
C5: 电气工程
C6: 灯具、电器
A7: 1 | B7: 30413002001 | C7: L1 嵌入式LED可调射灯 | D7: 1.名称：L1 嵌入式LED可调射灯 2.规格：LED COB 15W 3000K±50 3.尺寸：φ77mm*H90mm 4.安装方式：嵌装 5.其他：包括但不限于满足图纸、招标文件、规范及验收要求等一切相关费用 | E7: 套 | F7: 68 | G7: =R7*$R$3 | H7: =P7*(1+Q7)*$P$3+S7*$S$3 | I7: =T7*$T$3 | J7: =(G7+H7+I7)*$J$3 | K7: =(G7+H7+I7+J7)*$K$3 | L7: =G7+H7+I7+J7+K7 | M7: =F7*L7 | O7: =P7*(1+Q7)+R7+S7+T7 | P7: 135 | Q7: 0 | R7: 115 | S7: 2 | T7: 4 | U7: =F7*O7
A8: 2 | B8: 30413002002 | C8: L2 嵌入式LED筒灯 | D8: 1.名称：L2 嵌入式LED筒灯 2.规格：LED COB 15W 3000K±50 3.尺寸：φ77mm*H99mm 4.安装方式：嵌装 5.其他：包括但不限于满足图纸、招标文件、规范及验收要求等一切相关费用 | E8: 套 | F8: 16 | G8: =R8*$R$3 | H8: =P8*(1+Q8)*$P$3+S8*$S$3 | I8: =T8*$T$3 | J8: =(G8+H8+I8)*$J$3 | K8: =(G8+H8+I8+J8)*$K$3 | L8: =G8+H8+I8+J8+K8 | M8: =F8*L8 | O8: =P8*(1+Q8)+R8+S8+T8 | P8: 120 | Q8: 0 | R8: 18 | S8: 6 | T8: 8 | U8: =F8*O8
A9: 3 | B9: 30413002003 | C9: L3 嵌入式LED可调射灯 | D9: 1.名称：L3 嵌入式LED可调射灯 2.规格：LED COB 7W 2700K±50 3.尺寸：φ77mm*H78mm 4.安装方式：嵌装 5.其他：包括但不限于满足图纸、招标文件、规范及验收要求等一切相关费用 | E9: 套 | F9: 156 | G9: =R9*$R$3 | H9: =P9*(1+Q9)*$P$3+S9*$S$3 | I9: =T9*$T$3 | J9: =(G9+H9+I9)*$J$3 | K9: =(G9+H9+I9+J9)*$K$3 | L9: =G9+H9+I9+J9+K9 | M9: =F9*L9 | O9: =P9*(1+Q9)+R9+S9+T9 | P9: 135 | Q9: 0 | R9: 115 | S9: 2 | T9: 4 | U9: =F9*O9
A10: 4 | B10: 30413002004 | C10: L4 嵌入式LED可调射灯 | D10: 1.名称：L4 嵌入式LED可调射灯 2.规格：LED COB 9W 2700K±50 3.尺寸：φ77mm*H78mm 4.安装方式：嵌装 5.其他：包括但不限于满足图纸、招标文件、规范及验收要求等一切相关费用 | E10: 套 | F10: 21 | G10: =R10*$R$3 | H10: =P10*(1+Q10)*$P$3+S10*$S$3 | I10: =T10*$T$3 | J10: =(G10+H10+I10)*$J$3 | K10: =(G10+H10+I10+J10)*$K$3 | L10: =G10+H10+I10+J10+K10 | M10: =F10*L10 | O10: =P10*(1+Q10)+R10+S10+T10 | P10: 135 | Q10: 0 | R10: 115 | S10: 2 | T10: 4 | U10: =F10*O10
A11: 5 | B11: 30413002005 | C11: L5 明装LED可调射灯 | D11: 1.名称：L5 明装LED可调射灯 2.规格：LED COB 15W 3500K±50 3.尺寸：L85mm*W85mm*H90mm 4.安装方式：明装 5.其他：包括但不限于满足图纸、招标文件、规范及验收要求等一切相关费用 | E11: 套 | F11: 4 | G11: =R11*$R$3 | H11: =P11*(1+Q11)*$P$3+S11*$S$3 | I11: =T11*$T$3 | J11: =(G11+H11+I11)*$J$3 | K11: =(G11+H11+I11+J11)*$K$3 | L11: =G11+H11+I11+J11+K11 | M11: =F11*L11 | O11: =P11*(1+Q11)+R11+S11+T11 | P11: 135 | Q11: 0 | R11: 115 | S11: 2 | T11: 4 | U11: =F11*O11
A12: 6 | B12: 30413002006 | C12: L6 嵌入式LED可调射灯 | D12: 1.名称：L6 嵌入式LED可调射灯 2.规格：LED COB 12W 2700K±50 3.尺寸：φ77mm*H78mm 4.安装方式：嵌装 5.其他：包括但不限于满足图纸、招标文件、规范及验收要求等一切相关费用 | E12: 套 | F12: 2 | G12: =R12*$R$3 | H12: =P12*(1+Q12)*$P$3+S12*$S$3 | I12: =T12*$T$3 | J12: =(G12+H12+I12)*$J$3 | K12: =(G12+H12+I12+J12)*$K$3 | L12: =G12+H12+I12+J12+K12 | M12: =F12*L12 | O12: =P12*(1+Q12)+R12+S12+T12 | P12: 135 | Q12: 0 | R12: 115 | S12: 2 | T12: 4 | U12: =F12*O12
A13: 7 | B13: 30413002007 | C13: L7 嵌入式LED可调射灯 | D13: 1.名称：L7 嵌入式LED可调射灯 2.规格：LED COB 12W 2700K±50 3.尺寸：φ77mm*H78mm 4.安装方式：嵌装 5.其他：包括但不限于满足图纸、招标文件、规范及验收要求等一切相关费用 | E13: 套 | F13: 11 | G13: =R13*$R$3 | H13: =P13*(1+Q13)*$P$3+S13*$S$3 | I13: =T13*$T$3 | J13: =(G13+H13+I13)*$J$3 | K13: =(G13+H13+I13+J13)*$K$3 | L13: =G13+H13+I13+J13+K13 | M13: =F13*L13 | O13: =P13*(1+Q13)+R13+S13+T13 | P13: 135 | Q13: 0 | R13: 115 | S13: 2 | T13: 4 | U13: =F13*O13
A14: 8 | B14: 30413002008 | C14: L8 嵌入式LED可调射灯 | D14: 1.名称：L8 嵌入式LED可调射灯 2.规格：LED COB 7W 2700K±50 3.尺寸：φ77mm*H78mm 4.安装方式：嵌装 5.其他：包括但不限于满足图纸、招标文件、规范及验收要求等一切相关费用 | E14: 套 | F14: 7 | G14: =R14*$R$3 | H14: =P14*(1+Q14)*$P$3+S14*$S$3 | I14: =T14*$T$3 | J14: =(G14+H14+I14)*$J$3 | K14: =(G14+H14+I14+J14)*$K$3 | L14: =G14+H14+I14+J14+K14 | M14: =F14*L14 | O14: =P14*(1+Q14)+R14+S14+T14 | P14: 135 | Q14: 0 | R14: 115 | S14: 2 | T14: 4 | U14: =F14*O14
A15: 9 | B15: 30413002009 | C15: L10 嵌入式LED可调射灯 | D15: 1.名称：L10 嵌入式LED可调射灯 2.规格：LED COB 7W 2700K±50 3.尺寸：φ77mm*H78mm 4.安装方式：嵌装 5.其他：包括但不限于满足图纸、招标文件、规范及验收要求等一切相关费用 | E15: 套 | F15: 20 | G15: =R15*$R$3 | H15: =P15*(1+Q15)*$P$3+S15*$S$3 | I15: =T15*$T$3 | J15: =(G15+H15+I15)*$J$3 | K15: =(G15+H15+I15+J15)*$K$3 | L15: =G15+H15+I15+J15+K15 | M15: =F15*L15 | O15: =P15*(1+Q15)+R15+S15+T15 | P15: 135 | Q15: 0 | R15: 115 | S15: 2 | T15: 4 | U15: =F15*O15
A16: 10 | B16: 30413001001 | C16: L11 吊线办公灯 | D16: 1.名称：L11 吊线办公灯 2.规格：LED 30W 4000K±50 3.尺寸：L1206mm*W75mm*H73.5mm 4.安装方式：吊装 5.其他：包括但不限于满足图纸、招标文件、规范及验收要求等一切相关费用 | E16: 套 | F16: 7 | G16: =R16*$R$3 | H16: =P16*(1+Q16)*$P$3+S16*$S$3 | I16: =T16*$T$3 | J16: =(G16+H16+I16)*$J$3 | K16: =(G16+H16+I16+J16)*$K$3 | L16: =G16+H16+I16+J16+K16 | M16: =F16*L16 | O16: =P16*(1+Q16)+R16+S16+T16 | P16: 120 | Q16: 0 | R16: 18 | S16: 6 | T16: 8 | U16: =F16*O16
A17: 11 | B17: 30413001002 | C17: L12 吸顶灯 | D17: 1.名称：L12 吸顶灯 2.规格：LED 18W 4000K±50 3.尺寸：Φ290mm*H54.5mm 4.安装方式：吸顶 5.其他：包括但不限于满足图纸、招标文件、规范及验收要求等一切相关费用 | E17: 套 | F17: 4 | G17: =R17*$R$3 | H17: =P17*(1+Q17)*$P$3+S17*$S$3 | I17: =T17*$T$3 | J17: =(G17+H17+I17)*$J$3 | K17: =(G17+H17+I17+J17)*$K$3 | L17: =G17+H17+I17+J17+K17 | M17: =F17*L17 | O17: =P17*(1+Q17)+R17+S17+T17 | P17: 60 | Q17: 0 | R17: 18 | S17: 6 | T17: 8 | U17: =F17*O17
A18: 12 | B18: 30413004001 | C18: L13 LED地埋灯 | D18: 1.名称：L13 LED地埋灯 2.规格：LED 1W 2700K±50 3.尺寸：Φ42mm*H75mm 4.安装方式：埋地 5.其他：包括但不限于满足图纸、招标文件、规范及验收要求等一切相关费用 | E18: 套 | F18: 3 | G18: =R18*$R$3 | H18: =P18*(1+Q18)*$P$3+S18*$S$3 | I18: =T18*$T$3 | J18: =(G18+H18+I18)*$J$3 | K18: =(G18+H18+I18+J18)*$K$3 | L18: =G18+H18+I18+J18+K18 | M18: =F18*L18 | O18: =P18*(1+Q18)+R18+S18+T18 | P18: 120 | Q18: 0 | R18: 18 | S18: 6 | T18: 8 | U18: =F18*O18
... A28: 22 | B28: 30413002018 | C28: R7 地面洗墙灯 | D28: 1.名称：R7 地面洗墙灯 2.规格：LED 18W 2700K±50 3.尺寸：1000*43*53mm，灯体截面29*45mm 4.安装方式：地面 5.其他：包括但不限于满足图纸、招标文件、规范及验收要求等一切相关费用 | E28: m | F28: 4 | G28: =R28*$R$3 | H28: =P28*(1+Q28)*$P$3+S28*$S$3 | I28: =T28*$T$3 | J28: =(G28+H28+I28)*$J$3 | K28: =(G28+H28+I28+J28)*$K$3 | L28: =G28+H28+I28+J28+K28 | M28: =F28*L28 | O28: =P28*(1+Q28)+R28+S28+T28 | P28: 85 | Q28: 0 | R28: 22 | S28: 6 | T28: 4 | U28: =F28*O28
A29: 23 | B29: 30413009001 | C29: LED 灯带驱动电源 | D29: 1.名称：LED 灯带驱动电源 2.规格：60W 工作电压：220V 输出电压：24V 3.尺寸：L140*W45*H29mm 4.其他：包括但不限于满足图纸、招标文件、规范及验收要求等一切相关费用 | E29: 个 | F29: 280 | G29: =R29*$R$3 | H29: =P29*(1+Q29)*$P$3+S29*$S$3 | I29: =T29*$T$3 | J29: =(G29+H29+I29)*$J$3 | K29: =(G29+H29+I29+J29)*$K$3 | L29: =G29+H29+I29+J29+K29 | M29: =F29*L29 | O29: =P29*(1+Q29)+R29+S29+T29 | P29: ='架空层安装工程'!P10 | Q29: ='架空层安装工程'!Q10 | R29: ='架空层安装工程'!R10 | S29: ='架空层安装工程'!S10 | T29: ='架空层安装工程'!T10 | U29: =F29*O29
A30: 24 | B30: 30405017001 | C30: 洗碗机 | D30: 1.名称：洗碗机 2.规格：- 3.尺寸：详见物料表 4.其他：包括但不限于满足图纸、招标文件、规范及验收要求等一切相关费用 | E30: 台 | F30: 1 | G30: =R30*$R$3 | H30: =P30*(1+Q30)*$P$3+S30*$S$3 | I30: =T30*$T$3 | J30: =(G30+H30+I30)*$J$3 | K30: =(G30+H30+I30+J30)*$K$3 | L30: =G30+H30+I30+J30+K30 | M30: =F30*L30 | O30: =P30*(1+Q30)+R30+S30+T30 | P30: ='样板房安装工程'!P19 | Q30: ='样板房安装工程'!Q19 | R30: ='样板房安装工程'!R19 | S30: ='样板房安装工程'!S19 | T30: ='样板房安装工程'!T19 | U30: =F30*O30
C31: 开关插座
A32: 25 | B32: 30413013001 | C32: 照明开关 | D32: 1.名称：单联单控开关 2.规格：86*86mm 3.安装方式：暗装 4.其他：包括但不限于满足图纸、招标文件、规范及验收要求等一切相关费用 | E32: 套 | F32: 5 | G32: =R32*$R$3 | H32: =P32*(1+Q32)*$P$3+S32*$S$3 | I32: =T32*$T$3 | J32: =(G32+H32+I32)*$J$3 | K32: =(G32+H32+I32+J32)*$K$3 | L32: =G32+H32+I32+J32+K32 | M32: =F32*L32 | O32: =P32*(1+Q32)+R32+S32+T32 | P32: ='公共区域安装工程'!P14 | Q32: ='公共区域安装工程'!Q14 | R32: ='公共区域安装工程'!R14 | S32: ='公共区域安装工程'!S14 | T32: ='公共区域安装工程'!T14 | U32: =F32*O32
A33: 26 | B33: 30413013002 | C33: 照明开关 | D33: 1.名称：双联单控开关 2.规格：86*86mm 3.安装方式：暗装 4.其他：包括但不限于满足图纸、招标文件、规范及验收要求等一切相关费用 | E33: 套 | F33: 10 | G33: =R33*$R$3 | H33: =P33*(1+Q33)*$P$3+S33*$S$3 | I33: =T33*$T$3 | J33: =(G33+H33+I33)*$J$3 | K33: =(G33+H33+I33+J33)*$K$3 | L33: =G33+H33+I33+J33+K33 | M33: =F33*L33 | O33: =P33*(1+Q33)+R33+S33+T33 | P33: ='架空层安装工程'!P16 | Q33: ='架空层安装工程'!Q16 | R33: ='架空层安装工程'!R16 | S33: ='架空层安装工程'!S16 | T33: ='架空层安装工程'!T16 | U33: =F33*O33
A34: 27 | B34: 30413013003 | C34: 照明开关 | D34: 1.名称：三联单控开关 2.规格：86*86mm 3.安装方式：暗装 4.其他：包括但不限于满足图纸、招标文件、规范及验收要求等一切相关费用 | E34: 套 | F34: 23 | G34: =R34*$R$3 | H34: =P34*(1+Q34)*$P$3+S34*$S$3 | I34: =T34*$T$3 | J34: =(G34+H34+I34)*$J$3 | K34: =(G34+H34+I34+J34)*$K$3 | L34: =G34+H34+I34+J34+K34 | M34: =F34*L34 | O34: =P34*(1+Q34)+R34+S34+T34 | P34: ='公共区域安装工程'!P15 | Q34: ='公共区域安装工程'!Q15 | R34: ='公共区域安装工程'!R15 | S34: ='公共区域安装工程'!S15 | T34: ='公共区域安装工程'!T15 | U34: =F34*O34
A35: 28 | B35: 30413013004 | C35: 照明开关 | D35: 1.名称：卫生间排风开关 2.规格：86*86mm 3.安装方式：暗装 4.其他：包括但不限于满足图纸、招标文件、规范及验收要求等一切相关费用 | E35: 套 | F35: 4 | G35: =R35*$R$3 | H35: =P35*(1+Q35)*$P$3+S35*$S$3 | I35: =T35*$T$3 | J35: =(G35+H35+I35)*$J$3 | K35: =(G35+H35+I35+J35)*$K$3 | L35: =G35+H35+I35+J35+K35 | M35: =F35*L35 | O35: =P35*(1+Q35)+R35+S35+T35 | P35: 14.62 | Q35: 0 | R35: 6.31 | S35: 1.12 | T35: 0 | U35: =F35*O35
A36: 29 | B36: 30413014001 | C36: 插座 | D36: 1.名称：三孔插座 2.规格：86*86mm 3.安装方式：暗装 4.其他：包括但不限于满足图纸、招标文件、规范及验收要求等一切相关费用 | E36: 套 | F36: 2 | G36: =R36*$R$3 | H36: =P36*(1+Q36)*$P$3+S36*$S$3 | I36: =T36*$T$3 | J36: =(G36+H36+I36)*$J$3 | K36: =(G36+H36+I36+J36)*$K$3 | L36: =G36+H36+I36+J36+K36 | M36: =F36*L36 | O36: =P36*(1+Q36)+R36+S36+T36 | P36: ='户内交标安装工程'!P27 | Q36: ='户内交标安装工程'!Q27 | R36: ='户内交标安装工程'!R27 | S36: ='户内交标安装工程'!S27 | T36: ='户内交标安装工程'!T27 | U36: =F36*O36
A37: 30 | B37: 30413014002 | C37: 插座 | D37: 1.名称：五孔插座 2.规格：86*86mm 3.安装方式：暗装 4.其他：包括但不限于满足图纸、招标文件、规范及验收要求等一切相关费用 | E37: 套 | F37: 63 | G37: =R37*$R$3 | H37: =P37*(1+Q37)*$P$3+S37*$S$3 | I37: =T37*$T$3 | J37: =(G37+H37+I37)*$J$3 | K37: =(G37+H37+I37+J37)*$K$3 | L37: =G37+H37+I37+J37+K37 | M37: =F37*L37 | O37: =P37*(1+Q37)+R37+S37+T37 | P37: ='公共区域安装工程'!P16 | Q37: ='公共区域安装工程'!Q16 | R37: ='公共区域安装工程'!R16 | S37: ='公共区域安装工程'!S16 | T37: ='公共区域安装工程'!T16 | U37: =F37*O37
A38: 31 | B38: 30413014003 | C38: 插座 | D38: 1.名称：五孔插座（带防溅盒） 2.规格：86*86mm 3.安装方式：暗装 4.其他：包括但不限于满足图纸、招标文件、规范及验收要求等一切相关费用 | E38: 套 | F38: 15 | G38: =R38*$R$3 | H38: =P38*(1+Q38)*$P$3+S38*$S$3 | I38: =T38*$T$3 | J38: =(G38+H38+I38)*$J$3 | K38: =(G38+H38+I38+J38)*$K$3 | L38: =G38+H38+I38+J38+K38 | M38: =F38*L38 | O38: =P38*(1+Q38)+R38+S38+T38 | P38: ='样板房安装工程'!P28 | Q38: ='样板房安装工程'!Q28 | R38: ='样板房安装工程'!R28 | S38: ='样板房安装工程'!S28 | T38: ='样板房安装工程'!T28 | U38: =F38*O38
A39: 32 | B39: 30413014004 | C39: 插座 | D39: 1.名称：五孔插座带开关 2.规格：86*86mm 3.安装方式：暗装 4.其他：包括但不限于满足图纸、招标文件、规范及验收要求等一切相关费用 | E39: 套 | F39: 21 | G39: =R39*$R$3 | H39: =P39*(1+Q39)*$P$3+S39*$S$3 | I39: =T39*$T$3 | J39: =(G39+H39+I39)*$J$3 | K39: =(G39+H39+I39+J39)*$K$3 | L39: =G39+H39+I39+J39+K39 | M39: =F39*L39 | O39: =P39*(1+Q39)+R39+S39+T39 | P39: ='户内交标安装工程'!P25 | Q39: ='户内交标安装工程'!Q25 | R39: ='户内交标安装工程'!R25 | S39: ='户内交标安装工程'!S25 | T39: ='户内交标安装工程'!T25 | U39: =F39*O39
A40: 33 | B40: 30413014005 | C40: 插座 | D40: 1.名称：五孔插座带开关（带防溅盒） 2.规格：86*86mm 3.安装方式：暗装 4.其他：包括但不限于满足图纸、招标文件、规范及验收要求等一切相关费用 | E40: 套 | F40: 4 | G40: =R40*$R$3 | H40: =P40*(1+Q40)*$P$3+S40*$S$3 | I40: =T40*$T$3 | J40: =(G40+H40+I40)*$J$3 | K40: =(G40+H40+I40+J40)*$K$3 | L40: =G40+H40+I40+J40+K40 | M40: =F40*L40 | O40: =P40*(1+Q40)+R40+S40+T40 | P40: ='样板房安装工程'!P31 | Q40: ='样板房安装工程'!Q31 | R40: ='样板房安装工程'!R31 | S40: ='样板房安装工程'!S31 | T40: ='样板房安装工程'!T31 | U40: =F40*O40
A41: 34 | B41: 30413014006 | C41: 插座 | D41: 1.名称：五孔地面插座 2.规格：86*86mm 3.安装方式：暗装 4.其他：包括但不限于满足图纸、招标文件、规范及验收要求等一切相关费用 | E41: 套 | F41: 51 | G41: =R41*$R$3 | H41: =P41*(1+Q41)*$P$3+S41*$S$3 | I41: =T41*$T$3 | J41: =(G41+H41+I41)*$J$3 | K41: =(G41+H41+I41+J41)*$K$3 | L41: =G41+H41+I41+J41+K41 | M41: =F41*L41 | O41: =P41*(1+Q41)+R41+S41+T41 | P41: 14.62 | Q41: 0 | R41: 6.31 | S41: 1.12 | T41: 0 | U41: =F41*O41
C42: 配管配线
A43: 35 | B43: 30412001001 | C43: 配管 | D43: 1.名称：电气配管 2.规格：JDG20 3.安装方式：暗装 4.其他：包括但不限于满足图纸、招标文件、规范及验收要求等一切相关费用 | E43: m | F43: 2169.81 | G43: =R43*$R$3 | H43: =P43*(1+Q43)*$P$3+S43*$S$3 | I43: =T43*$T$3 | J43: =(G43+H43+I43)*$J$3 | K43: =(G43+H43+I43+J43)*$K$3 | L43: =G43+H43+I43+J43+K43 | M43: =F43*L43 | O43: =P43*(1+Q43)+R43+S43+T43 | P43: 1.57 | Q43: 0 | R43: 2.61 | S43: 0.23 | T43: 0.09 | U43: =F43*O43
A44: 36 | B44: 30412001002 | C44: 配管 | D44: 1.名称：电气配管 2.规格：JDG25 3.安装方式：暗装 4.其他：包括但不限于满足图纸、招标文件、规范及验收要求等一切相关费用 | E44: m | F44: 324.48 | G44: =R44*$R$3 | H44: =P44*(1+Q44)*$P$3+S44*$S$3 | I44: =T44*$T$3 | J44: =(G44+H44+I44)*$J$3 | K44: =(G44+H44+I44+J44)*$K$3 | L44: =G44+H44+I44+J44+K44 | M44: =F44*L44 | O44: =P44*(1+Q44)+R44+S44+T44 | P44: 6.5 | Q44: 0.03 | R44: 10.8 | S44: 0.44 | T44: 0.2 | U44: =F44*O44
A45: 37 | B45: 30412001003 | C45: 配管 | D45: 1.名称：电气配管 2.规格：PC20 3.安装方式：暗装 4.其他：包括但不限于满足图纸、招标文件、规范及验收要求等一切相关费用 | E45: m | F45: 616.28 | G45: =R45*$R$3 | H45: =P45*(1+Q45)*$P$3+S45*$S$3 | I45: =T45*$T$3 | J45: =(G45+H45+I45)*$J$3 | K45: =(G45+H45+I45+J45)*$K$3 | L45: =G45+H45+I45+J45+K45 | M45: =F45*L45 | O45: =P45*(1+Q45)+R45+S45+T45 | P45: 6 | Q45: 0.03 | R45: 8.5 | S45: 0.48 | T45: 0.2 | U45: =F45*O45
A46: 38 | B46: 30412001004 | C46: 配管 | D46: 1.名称：电气配管 2.规格：PC25 3.安装方式：暗装 4.其他：包括但不限于满足图纸、招标文件、规范及验收要求等一切相关费用 | E46: m | F46: 932.93 | G46: =R46*$R$3 | H46: =P46*(1+Q46)*$P$3+S46*$S$3 | I46: =T46*$T$3 | J46: =(G46+H46+I46)*$J$3 | K46: =(G46+H46+I46+J46)*$K$3 | L46: =G46+H46+I46+J46+K46 | M46: =F46*L46 | O46: =P46*(1+Q46)+R46+S46+T46 | P46: 6 | Q46: 0.03 | R46: 8.5 | S46: 0.48 | T46: 0.2 | U46: =F46*O46
A47: 39 | B47: 30412001005 | C47: 配管 | D47: 1.名称：电气配管 2.规格：PC32 3.安装方式：暗装 4.其他：包括但不限于满足图纸、招标文件、规范及验收要求等一切相关费用 | E47: m | F47: 24.68 | G47: =R47*$R$3 | H47: =P47*(1+Q47)*$P$3+S47*$S$3 | I47: =T47*$T$3 | J47: =(G47+H47+I47)*$J$3 | K47: =(G47+H47+I47+J47)*$K$3 | L47: =G47+H47+I47+J47+K47 | M47: =F47*L47 | O47: =P47*(1+Q47)+R47+S47+T47 | P47: 6 | Q47: 0.03 | R47: 8.5 | S47: 0.48 | T47: 0.2 | U47: =F47*O47
A48: 40 | B48: 30412001006 | C48: 配管 | D48: 1.名称：金属软管 2.规格：DN20 3.安装方式：吊顶内安装 4.其他：包括但不限于满足图纸、招标文件、规范及验收要求等一切相关费用 | E48: m | F48: 686.43 | G48: =R48*$R$3 | H48: =P48*(1+Q48)*$P$3+S48*$S$3 | I48: =T48*$T$3 | J48: =(G48+H48+I48)*$J$3 | K48: =(G48+H48+I48+J48)*$K$3 | L48: =G48+H48+I48+J48+K48 | M48: =F48*L48 | O48: =P48*(1+Q48)+R48+S48+T48 | P48: 8.1 | Q48: 0.03 | R48: 7.6 | S48: 0.65 | T48: 0.2 | U48: =F48*O48
A49: 41 | B49: 30412001007 | C49: 配管 | D49: 1.名称：金属软管 2.规格：DN25 3.安装方式：吊顶内安装 4.其他：包括但不限于满足图纸、招标文件、规范及验收要求等一切相关费用 | E49: m | F49: 286.28 | G49: =R49*$R$3 | H49: =P49*(1+Q49)*$P$3+S49*$S$3 | I49: =T49*$T$3 | J49: =(G49+H49+I49)*$J$3 | K49: =(G49+H49+I49+J49)*$K$3 | L49: =G49+H49+I49+J49+K49 | M49: =F49*L49 | O49: =P49*(1+Q49)+R49+S49+T49 | P49: 9.5 | Q49: 0.03 | R49: 8.5 | S49: 0.76 | T49: 0.2 | U49: =F49*O49
A50: 42 | B50: 31301001001 | C50: 凿槽及修复 | D50: 1.名称：凿槽及修复 2.规格：70*70 3.部位：砖、混凝土结构综合考虑 4.其他：包括但不限于满足图纸、招标文件、规范及验收要求等一切相关费用 | E50: m | F50: 606.51 | G50: =R50*$R$3 | H50: =P50*(1+Q50)*$P$3+S50*$S$3 | I50: =T50*$T$3 | J50: =(G50+H50+I50)*$J$3 | K50: =(G50+H50+I50+J50)*$K$3 | L50: =G50+H50+I50+J50+K50 | M50: =F50*L50 | O50: =P50*(1+Q50)+R50+S50+T50 | P50: 0 | Q50: 0 | R50: 17.65 | S50: 0 | T50: 2.41 | U50: =F50*O50
A51: 43 | B51: 30412006001 | C51: 接线盒 | D51: 1.名称：接线盒 2.材质：钢制 3.安装方式：暗装 4.其他：包括但不限于满足图纸、招标文件、规范及验收要求等一切相关费用 | E51: 个 | F51: 861 | G51: =R51*$R$3 | H51: =P51*(1+Q51)*$P$3+S51*$S$3 | I51: =T51*$T$3 | J51: =(G51+H51+I51)*$J$3 | K51: =(G51+H51+I51+J51)*$K$3 | L51: =G51+H51+I51+J51+K51 | M51: =F51*L51 | O51: =P51*(1+Q51)+R51+S51+T51 | P51: 2.28 | Q51: 0 | R51: 2.17 | S51: 0.3 | T51: 0 | U51: =F51*O51
A52: 44 | B52: 30412006002 | C52: 开关（插座）盒 | D52: 1.名称：开关（插座）盒 2.材质：钢制 3.安装方式：暗装 4.其他：包括但不限于满足图纸、招标文件、规范及验收要求等一切相关费用 | E52: 个 | F52: 73 | G52: =R52*$R$3 | H52: =P52*(1+Q52)*$P$3+S52*$S$3 | I52: =T52*$T$3 | J52: =(G52+H52+I52)*$J$3 | K52: =(G52+H52+I52+J52)*$K$3 | L52: =G52+H52+I52+J52+K52 | M52: =F52*L52 | O52: =P52*(1+Q52)+R52+S52+T52 | P52: 15 | Q52: 0 | R52: 10 | S52: 1 | T52: 0 | U52: =F52*O52
A53: 45 | B53: 30412006003 | C53: 开关（插座）盒 | D53: 1.名称：开关（插座）盒 2.材质：塑料 3.安装方式：暗装 4.其他：包括但不限于满足图纸、招标文件、规范及验收要求等一切相关费用 | E53: 个 | F53: 162 | G53: =R53*$R$3 | H53: =P53*(1+Q53)*$P$3+S53*$S$3 | I53: =T53*$T$3 | J53: =(G53+H53+I53)*$J$3 | K53: =(G53+H53+I53+J53)*$K$3 | L53: =G53+H53+I53+J53+K53 | M53: =F53*L53 | O53: =P53*(1+Q53)+R53+S53+T53 | P53: 15 | Q53: 0 | R53: 10 | S53: 1 | T53: 0 | U53: =F53*O53
A54: 46 | B54: 30412004001 | C54: 配线 | D54: 1.名称：电气配线 2.型号规格：WDZC-BYJ-2.5 3.安装方式：管内穿线 4.其他：包括但不限于满足图纸、招标文件、规范及验收要求等一切相关费用 | E54: m | F54: 10389.06 | G54: =R54*$R$3 | H54: =P54*(1+Q54)*$P$3+S54*$S$3 | I54: =T54*$T$3 | J54: =(G54+H54+I54)*$J$3 | K54: =(G54+H54+I54+J54)*$K$3 | L54: =G54+H54+I54+J54+K54 | M54: =F54*L54 | O54: =P54*(1+Q54)+R54+S54+T54 | P54: ='公共区域安装工程'!P17 | Q54: ='公共区域安装工程'!Q17 | R54: ='公共区域安装工程'!R17 | S54: ='公共区域安装工程'!S17 | T54: ='公共区域安装工程'!T17 | U54: =F54*O54
A55: 47 | B55: 30412004002 | C55: 配线 | D55: 1.名称：电气配线 2.型号规格：WDZC-BYJ-2.5 3.安装方式：线槽配线 4.其他：包括但不限于满足图纸、招标文件、规范及验收要求等一切相关费用 | E55: m | F55: 311.04 | G55: =R55*$R$3 | H55: =P55*(1+Q55)*$P$3+S55*$S$3 | I55: =T55*$T$3 | J55: =(G55+H55+I55)*$J$3 | K55: =(G55+H55+I55+J55)*$K$3 | L55: =G55+H55+I55+J55+K55 | M55: =F55*L55 | O55: =P55*(1+Q55)+R55+S55+T55 | P55: 2.92 | Q55: 0.02 | R55: 2.2 | S55: 0.21 | T55: 0.02 | U55: =F55*O55
A56: 48 | B56: 30412004003 | C56: 配线 | D56: 1.名称：电气配线 2.型号规格：WDZC-BYJ-4 3.安装方式：管内穿线 4.其他：包括但不限于满足图纸、招标文件、规范及验收要求等一切相关费用 | E56: m | F56: 3896.09 | G56: =R56*$R$3 | H56: =P56*(1+Q56)*$P$3+S56*$S$3 | I56: =T56*$T$3 | J56: =(G56+H56+I56)*$J$3 | K56: =(G56+H56+I56+J56)*$K$3 | L56: =G56+H56+I56+J56+K56 | M56: =F56*L56 | O56: =P56*(1+Q56)+R56+S56+T56 | P56: 130.6 | Q56: 0.02 | R56: 14 | S56: 1.04 | T56: 1.04 | U56: =F56*O56
A57: 49 | B57: 30412004004 | C57: 配线 | D57: 1.名称：电气配线 2.型号规格：WDZC-BYJ-4 3.安装方式：线槽配线 4.其他：包括但不限于满足图纸、招标文件、规范及验收要求等一切相关费用 | E57: m | F57: 1846.08 | G57: =R57*$R$3 | H57: =P57*(1+Q57)*$P$3+S57*$S$3 | I57: =T57*$T$3 | J57: =(G57+H57+I57)*$J$3 | K57: =(G57+H57+I57+J57)*$K$3 | L57: =G57+H57+I57+J57+K57 | M57: =F57*L57 | O57: =P57*(1+Q57)+R57+S57+T57 | P57: 35.2 | Q57: 0.02 | R57: 21.2 | S57: 0.85 | T57: 0.21 | U57: =F57*O57
A58: 50 | B58: 30412004005 | C58: 配线 | D58: 1.名称：电气配线 2.型号规格：WDZC-BYJ-6 3.安装方式：管内穿线 4.其他：包括但不限于满足图纸、招标文件、规范及验收要求等一切相关费用 | E58: m | F58: 96.51 | G58: =R58*$R$3 | H58: =P58*(1+Q58)*$P$3+S58*$S$3 | I58: =T58*$T$3 | J58: =(G58+H58+I58)*$J$3 | K58: =(G58+H58+I58+J58)*$K$3 | L58: =G58+H58+I58+J58+K58 | M58: =F58*L58 | O58: =P58*(1+Q58)+R58+S58+T58 | P58: ='架空层安装工程'!P22 | Q58: ='架空层安装工程'!Q22 | R58: ='架空层安装工程'!R22 | S58: ='架空层安装工程'!S22 | T58: ='架空层安装工程'!T22 | U58: =F58*O58
A59: 51 | B59: 30412004006 | C59: 配线 | D59: 1.名称：电气配线 2.型号规格：WDZC-BYJ-6 3.安装方式：线槽配线 4.其他：包括但不限于满足图纸、招标文件、规范及验收要求等一切相关费用 | E59: m | F59: 140.84 | G59: =R59*$R$3 | H59: =P59*(1+Q59)*$P$3+S59*$S$3 | I59: =T59*$T$3 | J59: =(G59+H59+I59)*$J$3 | K59: =(G59+H59+I59+J59)*$K$3 | L59: =G59+H59+I59+J59+K59 | M59: =F59*L59 | O59: =P59*(1+Q59)+R59+S59+T59 | P59: 37.8 | Q59: 0.02 | R59: 21.8 | S59: 0.91 | T59: 0.22 | U59: =F59*O59
A60: 52 | B60: 30412004007 | C60: 配线 | D60: 1.名称：电气配线 2.型号规格：RVS-4*1.0 3.安装方式：管内穿线 4.其他：包括但不限于满足图纸、招标文件、规范及验收要求等一切相关费用 | E60: m | F60: 581.65 | G60: =R60*$R$3 | H60: =P60*(1+Q60)*$P$3+S60*$S$3 | I60: =T60*$T$3 | J60: =(G60+H60+I60)*$J$3 | K60: =(G60+H60+I60+J60)*$K$3 | L60: =G60+H60+I60+J60+K60 | M60: =F60*L60 | O60: =P60*(1+Q60)+R60+S60+T60 | P60: ='架空层安装工程'!P23 | Q60: ='架空层安装工程'!Q23 | R60: ='架空层安装工程'!R23 | S60: ='架空层安装工程'!S23 | T60: ='架空层安装工程'!T23 | U60: =F60*O60
C61: 给排水工程
C62: 给排水管
A63: 53 | B63: 31001008001 | C63: 冷水 PPR管 | D63: 1.名称：冷水 PPR管 2.规格：DN15 3.连接方式：热熔连接 4.压力试验及吹、洗要求：水压试验、水冲洗、消毒冲洗、管道标识等 5.其他：包括但不限于满足图纸、招标文件、规范及验收要求等一切相关费用 | E63: m | F63: 108.55 | G63: =R63*$R$3 | H63: =P63*(1+Q63)*$P$3+S63*$S$3 | I63: =T63*$T$3 | J63: =(G63+H63+I63)*$J$3 | K63: =(G63+H63+I63+J63)*$K$3 | L63: =G63+H63+I63+J63+K63 | M63: =F63*L63 | O63: =P63*(1+Q63)+R63+S63+T63 | P63: 3.2 | Q63: 0 | R63: 20 | S63: 0.77 | T63: 0.13 | U63: =F63*O63
A64: 54 | B64: 31001008002 | C64: 冷水 PPR管 | D64: 1.名称：冷水 PPR管 2.规格：DN20 3.连接方式：热熔连接 4.压力试验及吹、洗要求：水压试验、水冲洗、消毒冲洗、管道标识等 5.其他：包括但不限于满足图纸、招标文件、规范及验收要求等一切相关费用 | E64: m | F64: 24.67 | G64: =R64*$R$3 | H64: =P64*(1+Q64)*$P$3+S64*$S$3 | I64: =T64*$T$3 | J64: =(G64+H64+I64)*$J$3 | K64: =(G64+H64+I64+J64)*$K$3 | L64: =G64+H64+I64+J64+K64 | M64: =F64*L64 | O64: =P64*(1+Q64)+R64+S64+T64 | P64: 4.5 | Q64: 0 | R64: 18 | S64: 0.26 | T64: 0.04 | U64: =F64*O64
A65: 55 | B65: 31001008003 | C65: 冷水 PPR管 | D65: 1.名称：冷水 PPR管 2.规格：DN25 3.连接方式：热熔连接 4.压力试验及吹、洗要求：水压试验、水冲洗、消毒冲洗、管道标识等 5.其他：包括但不限于满足图纸、招标文件、规范及验收要求等一切相关费用 | E65: m | F65: 21.64 | G65: =R65*$R$3 | H65: =P65*(1+Q65)*$P$3+S65*$S$3 | I65: =T65*$T$3 | J65: =(G65+H65+I65)*$J$3 | K65: =(G65+H65+I65+J65)*$K$3 | L65: =G65+H65+I65+J65+K65 | M65: =F65*L65 | O65: =P65*(1+Q65)+R65+S65+T65 | P65: 8.5 | Q65: 0 | R65: 22.09 | S65: 0.26 | T65: 0.04 | U65: =F65*O65
A66: 56 | B66: 31001008004 | C66: 冷水 PPR管 | D66: 1.名称：冷水 PPR管 2.规格：DN32 3.连接方式：热熔连接 4.压力试验及吹、洗要求：水压试验、水冲洗、消毒冲洗、管道标识等 5.其他：包括但不限于满足图纸、招标文件、规范及验收要求等一切相关费用 | E66: m | F66: 16.52 | G66: =R66*$R$3 | H66: =P66*(1+Q66)*$P$3+S66*$S$3 | I66: =T66*$T$3 | J66: =(G66+H66+I66)*$J$3 | K66: =(G66+H66+I66+J66)*$K$3 | L66: =G66+H66+I66+J66+K66 | M66: =F66*L66 | O66: =P66*(1+Q66)+R66+S66+T66 | P66: 11.59 | Q66: 0 | R66: 23.68 | S66: 0.27 | T66: 0.05 | U66: =F66*O66
A67: 57 | B67: 31001008005 | C67: 热水 PPR管 | D67: 1.名称：热水 PPR管 2.规格：DN15 3.连接方式：热熔连接 4.压力试验及吹、洗要求：水压试验、水冲洗、消毒冲洗、管道标识等 5.其他：包括但不限于满足图纸、招标文件、规范及验收要求等一切相关费用 | E67: m | F67: 27.1 | G67: =R67*$R$3 | H67: =P67*(1+Q67)*$P$3+S67*$S$3 | I67: =T67*$T$3 | J67: =(G67+H67+I67)*$J$3 | K67: =(G67+H67+I67+J67)*$K$3 | L67: =G67+H67+I67+J67+K67 | M67: =F67*L67 | O67: =P67*(1+Q67)+R67+S67+T67 | P67: 3.2 | Q67: 0 | R67: 20 | S67: 0.77 | T67: 0.13 | U67: =F67*O67
A68: 58 | B68: 31001008006 | C68: 热水 PPR管 | D68: 1.名称：热水 PPR管 2.规格：DN20 3.连接方式：热熔连接 4.压力试验及吹、洗要求：水压试验、水冲洗、消毒冲洗、管道标识等 5.其他：包括但不限于满足图纸、招标文件、规范及验收要求等一切相关费用 | E68: m | F68: 23.43 | G68: =R68*$R$3 | H68: =P68*(1+Q68)*$P$3+S68*$S$3 | I68: =T68*$T$3 | J68: =(G68+H68+I68)*$J$3 | K68: =(G68+H68+I68+J68)*$K$3 | L68: =G68+H68+I68+J68+K68 | M68: =F68*L68 | O68: =P68*(1+Q68)+R68+S68+T68 | P68: 4.5 | Q68: 0 | R68: 18 | S68: 0.26 | T68: 0.04 | U68: =F68*O68
A69: 59 | B69: 31001008007 | C69: 热水 PPR管 | D69: 1.名称：热水 PPR管 2.规格：DN25 3.连接方式：热熔连接 4.压力试验及吹、洗要求：水压试验、水冲洗、消毒冲洗、管道标识等 5.其他：包括但不限于满足图纸、招标文件、规范及验收要求等一切相关费用 | E69: m | F69: 14.1 | G69: =R69*$R$3 | H69: =P69*(1+Q69)*$P$3+S69*$S$3 | I69: =T69*$T$3 | J69: =(G69+H69+I69)*$J$3 | K69: =(G69+H69+I69+J69)*$K$3 | L69: =G69+H69+I69+J69+K69 | M69: =F69*L69 | O69: =P69*(1+Q69)+R69+S69+T69 | P69: 8.5 | Q69: 0 | R69: 22.09 | S69: 0.26 | T69: 0.04 | U69: =F69*O69
A70: 60 | B70: 31301001002 | C70: 凿槽及修复 | D70: 1.名称：凿槽及修复 2.规格：70*70 3.部位：砖、混凝土结构综合考虑 4.其他：包括但不限于满足图纸、招标文件、规范及验收要求等一切相关费用 | E70: m | F70: 51.2 | G70: =R70*$R$3 | H70: =P70*(1+Q70)*$P$3+S70*$S$3 | I70: =T70*$T$3 | J70: =(G70+H70+I70)*$J$3 | K70: =(G70+H70+I70+J70)*$K$3 | L70: =G70+H70+I70+J70+K70 | M70: =F70*L70 | O70: =P70*(1+Q70)+R70+S70+T70 | P70: =P50 | Q70: =Q50 | R70: =R50 | S70: =S50 | T70: =T50 | U70: =F70*O70
A71: 61 | B71: 31001008008 | C71: UPVC排水管 | D71: 1.名称：UPVC排水管 2.规格：DN50 3.连接方式：粘接 4.压力试验及吹、洗要求：水压试验、管道标识等 5.其他：包括但不限于满足图纸、招标文件、规范及验收要求等一切相关费用 | E71: m | F71: 18.49 | G71: =R71*$R$3 | H71: =P71*(1+Q71)*$P$3+S71*$S$3 | I71: =T71*$T$3 | J71: =(G71+H71+I71)*$J$3 | K71: =(G71+H71+I71+J71)*$K$3 | L71: =G71+H71+I71+J71+K71 | M71: =F71*L71 | O71: =P71*(1+Q71)+R71+S71+T71 | P71: ='样板房安装工程'!P46 | Q71: ='样板房安装工程'!Q46 | R71: ='样板房安装工程'!R46 | S71: ='样板房安装工程'!S46 | T71: ='样板房安装工程'!T46 | U71: =F71*O71
A72: 62 | B72: 31001008009 | C72: UPVC排水管 | D72: 1.名称：UPVC排水管 2.规格：DN75 3.连接方式：粘接 4.压力试验及吹、洗要求：水压试验、管道标识等 5.其他：包括但不限于满足图纸、招标文件、规范及验收要求等一切相关费用 | E72: m | F72: 41.77 | G72: =R72*$R$3 | H72: =P72*(1+Q72)*$P$3+S72*$S$3 | I72: =T72*$T$3 | J72: =(G72+H72+I72)*$J$3 | K72: =(G72+H72+I72+J72)*$K$3 | L72: =G72+H72+I72+J72+K72 | M72: =F72*L72 | O72: =P72*(1+Q72)+R72+S72+T72 | P72: ='样板房安装工程'!P47 | Q72: ='样板房安装工程'!Q47 | R72: ='样板房安装工程'!R47 | S72: ='样板房安装工程'!S47 | T72: ='样板房安装工程'!T47 | U72: =F72*O72
A73: 63 | B73: 31001008010 | C73: UPVC排水管 | D73: 1.名称：UPVC排水管 2.规格：DN100 3.连接方式：粘接 4.压力试验及吹、洗要求：水压试验、管道标识等 5.其他：包括但不限于满足图纸、招标文件、规范及验收要求等一切相关费用 | E73: m | F73: 31.35 | G73: =R73*$R$3 | H73: =P73*(1+Q73)*$P$3+S73*$S$3 | I73: =T73*$T$3 | J73: =(G73+H73+I73)*$J$3 | K73: =(G73+H73+I73+J73)*$K$3 | L73: =G73+H73+I73+J73+K73 | M73: =F73*L73 | O73: =P73*(1+Q73)+R73+S73+T73 | P73: ='样板房安装工程'!P48 | Q73: ='样板房安装工程'!Q48 | R73: ='样板房安装工程'!R48 | S73: ='样板房安装工程'!S48 | T73: ='样板房安装工程'!T48 | U73: =F73*O73
C74: 洁具五金
A75: 64 | B75: 31003006001 | C75: 轻智能马桶 | D75: 1.名称：轻智能马桶 2.型号规格：详见物料表 3.其他：包括但不限于满足图纸、招标文件、规范及验收要求等一切相关费用 | E75: 组 | F75: 7 | G75: =R75*$R$3 | H75: =P75*(1+Q75)*$P$3+S75*$S$3 | I75: =T75*$T$3 | J75: =(G75+H75+I75)*$J$3 | K75: =(G75+H75+I75+J75)*$K$3 | L75: =G75+H75+I75+J75+K75 | M75: =F75*L75 | O75: =P75*(1+Q75)+R75+S75+T75 | P75: 0 | Q75: 0 | R75: 100 | S75: 120 | T75: 0 | U75: =F75*O75
A76: 65 | B76: 31003007001 | C76: 挂墙式自动感应小便器 | D76: 1.名称：挂墙式自动感应小便器 2.型号规格：详见物料表 3.其他：包括但不限于满足图纸、招标文件、规范及验收要求等一切相关费用 | E76: 组 | F76: 3 | G76: =R76*$R$3 | H76: =P76*(1+Q76)*$P$3+S76*$S$3 | I76: =T76*$T$3 | J76: =(G76+H76+I76)*$J$3 | K76: =(G76+H76+I76+J76)*$K$3 | L76: =G76+H76+I76+J76+K76 | M76: =F76*L76 | O76: =P76*(1+Q76)+R76+S76+T76 | P76: 480 | Q76: 0 | R76: 85 | S76: 35 | T76: 0 | U76: =F76*O76
A77: 66 | B77: 31003010001 | C77: 淋浴器 | D77: 1.名称：淋浴花洒 2.型号规格：详见物料表 3.其他：包括但不限于满足图纸、招标文件、规范及验收要求等一切相关费用 | E77: 套 | F77: 2 | G77: =R77*$R$3 | H77: =P77*(1+Q77)*$P$3+S77*$S$3 | I77: =T77*$T$3 | J77: =(G77+H77+I77)*$J$3 | K77: =(G77+H77+I77+J77)*$K$3 | L77: =G77+H77+I77+J77+K77 | M77: =F77*L77 | O77: =P77*(1+Q77)+R77+S77+T77 | P77: 1100 | Q77: 0 | R77: 90 | S77: 35 | T77: 0 | U77: =F77*O77
A78: 67 | B78: 31003008001 | C78: 拖把池及龙头 | D78: 1.名称：拖把池及冷热龙头 2.型号规格：详见物料表 3.其他：包括但不限于满足图纸、招标文件、规范及验收要求等一切相关费用 | E78: 组 | F78: 1 | G78: =R78*$R$3 | H78: =P78*(1+Q78)*$P$3+S78*$S$3 | I78: =T78*$T$3 | J78: =(G78+H78+I78)*$J$3 | K78: =(G78+H78+I78+J78)*$K$3 | L78: =G78+H78+I78+J78+K78 | M78: =F78*L78 | O78: =P78*(1+Q78)+R78+S78+T78 | P78: 350 | Q78: 0 | R78: 65 | S78: 25 | T78: 0 | U78: =F78*O78
A79: 68 | B79: 31003003001 | C79: 台下盆及龙头 | D79: 1.名称：洗手盆及冷热龙头 2.型号规格：详见物料表 3.其他：包括但不限于满足图纸、招标文件、规范及验收要求等一切相关费用 | E79: 组 | F79: 4 | G79: =R79*$R$3 | H79: =P79*(1+Q79)*$P$3+S79*$S$3 | I79: =T79*$T$3 | J79: =(G79+H79+I79)*$J$3 | K79: =(G79+H79+I79+J79)*$K$3 | L79: =G79+H79+I79+J79+K79 | M79: =F79*L79 | O79: =P79*(1+Q79)+R79+S79+T79 | P79: 550 | Q79: 0 | R79: 90 | S79: 12 | T79: 0 | U79: =F79*O79
A80: 69 | B80: 31003004001 | C80: 吧台水槽及龙头 | D80: 1.名称：吧台水槽及冷热龙头 2.型号规格：详见物料表 3.其他：包括但不限于满足图纸、招标文件、规范及验收要求等一切相关费用 | E80: 组 | F80: 1 | G80: =R80*$R$3 | H80: =P80*(1+Q80)*$P$3+S80*$S$3 | I80: =T80*$T$3 | J80: =(G80+H80+I80)*$J$3 | K80: =(G80+H80+I80+J80)*$K$3 | L80: =G80+H80+I80+J80+K80 | M80: =F80*L80 | O80: =P80*(1+Q80)+R80+S80+T80 | P80: 520 | Q80: 0 | R80: 95 | S80: 40 | T80: 0 | U80: =F80*O80
A81: 70 | B81: 31003014001 | C81: 隐藏地漏 | D81: 1.名称：隐藏地漏 2.型号规格：100*100*19mm 3.其他：包括但不限于满足图纸、招标文件、规范及验收要求等一切相关费用 | E81: 个 | F81: 14 | G81: =R81*$R$3 | H81: =P81*(1+Q81)*$P$3+S81*$S$3 | I81: =T81*$T$3 | J81: =(G81+H81+I81)*$J$3 | K81: =(G81+H81+I81+J81)*$K$3 | L81: =G81+H81+I81+J81+K81 | M81: =F81*L81 | O81: =P81*(1+Q81)+R81+S81+T81 | P81: 35 | Q81: 0 | R81: 18 | S81: 5 | T81: 0 | U81: =F81*O81
A82: 71 | B82: 31002001001 | C82: 角阀 | D82: 1.名称：角阀（热水器、洗碗机、制冰机） 2.型号规格：DN15 3.其他：包括但不限于满足图纸、招标文件、规范及验收要求等一切相关费用 | E82: 个 | F82: 5 | G82: =R82*$R$3 | H82: =P82*(1+Q82)*$P$3+S82*$S$3 | I82: =T82*$T$3 | J82: =(G82+H82+I82)*$J$3 | K82: =(G82+H82+I82+J82)*$K$3 | L82: =G82+H82+I82+J82+K82 | M82: =F82*L82 | O82: =P82*(1+Q82)+R82+S82+T82 | P82: 1504.2 | Q82: 0 | R82: 167.09 | S82: 0 | T82: 12.03 | U82: =F82*O82
A83: 72 | B83: 31003014002 | C83: 纸巾架 | D83: 1.名称：纸巾架 2.型号规格：170*120*81mm 3.其他：包括但不限于满足图纸、招标文件、规范及验收要求等一切相关费用 | E83: 个 | F83: 7 | G83: =R83*$R$3 | H83: =P83*(1+Q83)*$P$3+S83*$S$3 | I83: =T83*$T$3 | J83: =(G83+H83+I83)*$J$3 | K83: =(G83+H83+I83+J83)*$K$3 | L83: =G83+H83+I83+J83+K83 | M83: =F83*L83 | O83: =P83*(1+Q83)+R83+S83+T83 | P83: 181.74 | Q83: 0 | R83: 34.95 | S83: 11.65 | T83: 4.66 | U83: =F83*O83
A84: 73 | B84: 31003014003 | C84: 挂衣钩 | D84: 1.名称：挂衣钩 2.型号规格：详见物料表 3.其他：包括但不限于满足图纸、招标文件、规范及验收要求等一切相关费用 | E84: 个 | F84: 7 | G84: =R84*$R$3 | H84: =P84*(1+Q84)*$P$3+S84*$S$3 | I84: =T84*$T$3 | J84: =(G84+H84+I84)*$J$3 | K84: =(G84+H84+I84+J84)*$K$3 | L84: =G84+H84+I84+J84+K84 | M84: =F84*L84 | O84: =P84*(1+Q84)+R84+S84+T84 | P84: 28 | Q84: 0 | R84: 6.45 | S84: 0 | T84: 0 | U84: =F84*O84
C85: 多联机空调
C86: 设备
A87: 74 | B87: 30701003001 | C87: 风管机 | D87: 1.名称：风管机 F25 2.规格：制冷量2.5kW 制热量3.2kW 风量450m3/h 机外静压30Pa 额定功率0.10kW 运转噪音≤37dB(A) 带冷凝水提升水泵 3.安装方式：吊装 4.其他：包括但不限于满足图纸、招标文件、规范及验收要求等一切相关费用 | E87: 台 | F87: 2 | G87: =R87*$R$3 | H87: =P87*(1+Q87)*$P$3+S87*$S$3 | I87: =T87*$T$3 | J87: =(G87+H87+I87)*$J$3 | K87: =(G87+H87+I87+J87)*$K$3 | L87: =G87+H87+I87+J87+K87 | M87: =F87*L87 | O87: =P87*(1+Q87)+R87+S87+T87 | P87: 3600 | Q87: 0 | R87: 1000 | S87: 1200 | T87: 45 | U87: =F87*O87
A88: 75 | B88: 30701003002 | C88: 风管机 | D88: 1.名称：风管机 F36 2.规格：制冷量3.6kW 制热量4.2kW 风量780m3/h 机外静压50Pa 额定功率0.10kW 运转噪音≤37dB(A) 带冷凝水提升水泵 3.安装方式：吊装 4.其他：包括但不限于满足图纸、招标文件、规范及验收要求等一切相关费用 | E88: 台 | F88: 1 | G88: =R88*$R$3 | H88: =P88*(1+Q88)*$P$3+S88*$S$3 | I88: =T88*$T$3 | J88: =(G88+H88+I88)*$J$3 | K88: =(G88+H88+I88+J88)*$K$3 | L88: =G88+H88+I88+J88+K88 | M88: =F88*L88 | O88: =P88*(1+Q88)+R88+S88+T88 | P88: 3600 | Q88: 0 | R88: 1000 | S88: 1200 | T88: 45 | U88: =F88*O88
A89: 76 | B89: 30701003003 | C89: 风管机 | D89: 1.名称：风管机 F40 2.规格：制冷量4.0kW 制热量4.5kW 风量780m3/h 机外静压50Pa 额定功率0.14kW 运转噪音≤37dB(A) 带冷凝水提升水泵 3.安装方式：吊装 4.其他：包括但不限于满足图纸、招标文件、规范及验收要求等一切相关费用 | E89: 台 | F89: 3 | G89: =R89*$R$3 | H89: =P89*(1+Q89)*$P$3+S89*$S$3 | I89: =T89*$T$3 | J89: =(G89+H89+I89)*$J$3 | K89: =(G89+H89+I89+J89)*$K$3 | L89: =G89+H89+I89+J89+K89 | M89: =F89*L89 | O89: =P89*(1+Q89)+R89+S89+T89 | P89: 3600 | Q89: 0 | R89: 1000 | S89: 1200 | T89: 45 | U89: =F89*O89
A90: 77 | B90: 30701003004 | C90: 风管机 | D90: 1.名称：风管机 F50 2.规格：制冷量5.0kW 制热量5.6kW 风量900m3/h 机外静压50Pa 额定功率0.17kW 运转噪音≤37dB(A) 带冷凝水提升水泵 3.安装方式：吊装 4.其他：包括但不限于满足图纸、招标文件、规范及验收要求等一切相关费用 | E90: 台 | F90: 3 | G90: =R90*$R$3 | H90: =P90*(1+Q90)*$P$3+S90*$S$3 | I90: =T90*$T$3 | J90: =(G90+H90+I90)*$J$3 | K90: =(G90+H90+I90+J90)*$K$3 | L90: =G90+H90+I90+J90+K90 | M90: =F90*L90 | O90: =P90*(1+Q90)+R90+S90+T90 | P90: 3600 | Q90: 0 | R90: 1000 | S90: 1200 | T90: 45 | U90: =F90*O90
A91: 78 | B91: 30701003005 | C91: 风管机 | D91: 1.名称：风管机 F90 2.规格：制冷量9.0kW 制热量10kW 风量1000m3/h 机外静压50Pa 额定功率0.28kW 运转噪音≤40dB(A) 带冷凝水提升水泵 3.安装方式：吊装 4.其他：包括但不限于满足图纸、招标文件、规范及验收要求等一切相关费用 | E91: 台 | F91: 1 | G91: =R91*$R$3 | H91: =P91*(1+Q91)*$P$3+S91*$S$3 | I91: =T91*$T$3 | J91: =(G91+H91+I91)*$J$3 | K91: =(G91+H91+I91+J91)*$K$3 | L91: =G91+H91+I91+J91+K91 | M91: =F91*L91 | O91: =P91*(1+Q91)+R91+S91+T91 | P91: 3600 | Q91: 0 | R91: 1000 | S91: 1200 | T91: 45 | U91: =F91*O91
A92: 79 | B92: 30701003006 | C92: 风管机 | D92: 1.名称：风管机 F100 2.规格：制冷量10.0kW 制热量11.2kW 风量1400m3/h 机外静压50Pa 额定功率0.28kW 运转噪音≤40dB(A) 带冷凝水提升水泵 3.安装方式：吊装 4.其他：包括但不限于满足图纸、招标文件、规范及验收要求等一切相关费用 | E92: 台 | F92: 3 | G92: =R92*$R$3 | H92: =P92*(1+Q92)*$P$3+S92*$S$3 | I92: =T92*$T$3 | J92: =(G92+H92+I92)*$J$3 | K92: =(G92+H92+I92+J92)*$K$3 | L92: =G92+H92+I92+J92+K92 | M92: =F92*L92 | O92: =P92*(1+Q92)+R92+S92+T92 | P92: 3600 | Q92: 0 | R92: 1000 | S92: 1200 | T92: 45 | U92: =F92*O92
A93: 80 | B93: 30701003007 | C93: 风管机 | D93: 1.名称：风管机 F112 2.规格：制冷量11.2kW 制热量12.5kW 风量1400m3/h 机外静压50Pa 额定功率0.28kW 运转噪音≤40dB(A) 带冷凝水提升水泵 3.安装方式：吊装 4.其他：包括但不限于满足图纸、招标文件、规范及验收要求等一切相关费用 | E93: 台 | F93: 8 | G93: =R93*$R$3 | H93: =P93*(1+Q93)*$P$3+S93*$S$3 | I93: =T93*$T$3 | J93: =(G93+H93+I93)*$J$3 | K93: =(G93+H93+I93+J93)*$K$3 | L93: =G93+H93+I93+J93+K93 | M93: =F93*L93 | O93: =P93*(1+Q93)+R93+S93+T93 | P93: 3600 | Q93: 0 | R93: 1000 | S93: 1200 | T93: 45 | U93: =F93*O93
A94: 81 | B94: 30701003008 | C94: 风管机 | D94: 1.名称：风管机 F140 2.规格：制冷量14.0kW 制热量16.3kW 风量2220m3/h 机外静压90Pa 额定功率0.28kW 运转噪音≤40dB(A) 带冷凝水提升水泵 3.安装方式：吊装 4.其他：包括但不限于满足图纸、招标文件、规范及验收要求等一切相关费用 | E94: 台 | F94: 3 | G94: =R94*$R$3 | H94: =P94*(1+Q94)*$P$3+S94*$S$3 | I94: =T94*$T$3 | J94: =(G94+H94+I94)*$J$3 | K94: =(G94+H94+I94+J94)*$K$3 | L94: =G94+H94+I94+J94+K94 | M94: =F94*L94 | O94: =P94*(1+Q94)+R94+S94+T94 | P94: 3600 | Q94: 0 | R94: 1000 | S94: 1200 | T94: 45 | U94: =F94*O94
A95: 82 | B95: 30701003009 | C95: 风管机 | D95: 1.名称：风管机 F160 2.规格：制冷量16.0kW 制热量18.0kW 风量2300m3/h 机外静压90Pa 额定功率0.4kW 运转噪音≤45dB(A) 带冷凝水提升水泵 3.安装方式：吊装 4.其他：包括但不限于满足图纸、招标文件、规范及验收要求等一切相关费用 | E95: 台 | F95: 6 | G95: =R95*$R$3 | H95: =P95*(1+Q95)*$P$3+S95*$S$3 | I95: =T95*$T$3 | J95: =(G95+H95+I95)*$J$3 | K95: =(G95+H95+I95+J95)*$K$3 | L95: =G95+H95+I95+J95+K95 | M95: =F95*L95 | O95: =P95*(1+Q95)+R95+S95+T95 | P95: 3600 | Q95: 0 | R95: 1000 | S95: 1200 | T95: 45 | U95: =F95*O95
A96: 83 | B96: 30701003010 | C96: 多联式室外机 | D96: 1.名称：多联式室外机 L-1 2.规格：制冷量170.0kW 制热量190.0kW 风量50400m3/h 机外静压-Pa 额定功率49.2kW 运转噪音≤61dB(A) 3.安装方式：落地 4.其他：包括但不限于满足图纸、招标文件、规范及验收要求等一切相关费用 | E96: 台 | F96: 1 | G96: =R96*$R$3 | H96: =P96*(1+Q96)*$P$3+S96*$S$3 | I96: =T96*$T$3 | J96: =(G96+H96+I96)*$J$3 | K96: =(G96+H96+I96+J96)*$K$3 | L96: =G96+H96+I96+J96+K96 | M96: =F96*L96 | O96: =P96*(1+Q96)+R96+S96+T96 | P96: 12000 | Q96: 0 | R96: 800 | S96: 80 | T96: 60 | U96: =F96*O96
A97: 84 | B97: 30701003011 | C97: 多联式室外机 | D97: 1.名称：多联式室外机 L-2 2.规格：制冷量61.5kW 制热量69.0kW 风量20700m3/h 机外静压-Pa 额定功率16.4kW 运转噪音≤61dB(A) 3.安装方式：落地 4.其他：包括但不限于满足图纸、招标文件、规范及验收要求等一切相关费用 | E97: 台 | F97: 1 | G97: =R97*$R$3 | H97: =P97*(1+Q97)*$P$3+S97*$S$3 | I97: =T97*$T$3 | J97: =(G97+H97+I97)*$J$3 | K97: =(G97+H97+I97+J97)*$K$3 | L97: =G97+H97+I97+J97+K97 | M97: =F97*L97 | O97: =P97*(1+Q97)+R97+S97+T97 | P97: 12000 | Q97: 0 | R97: 800 | S97: 80 | T97: 60 | U97: =F97*O97
A98: 85 | B98: 30701003012 | C98: 多联式室外机 | D98: 1.名称：多联式室外机 L-3 2.规格：制冷量68.0kW 制热量75.0kW 风量21000m3/h 机外静压-Pa 额定功率18.4kW 运转噪音≤61dB(A) 3.安装方式：落地 4.其他：包括但不限于满足图纸、招标文件、规范及验收要求等一切相关费用 | E98: 台 | F98: 1 | G98: =R98*$R$3 | H98: =P98*(1+Q98)*$P$3+S98*$S$3 | I98: =T98*$T$3 | J98: =(G98+H98+I98)*$J$3 | K98: =(G98+H98+I98+J98)*$K$3 | L98: =G98+H98+I98+J98+K98 | M98: =F98*L98 | O98: =P98*(1+Q98)+R98+S98+T98 | P98: 12000 | Q98: 0 | R98: 800 | S98: 80 | T98: 60 | U98: =F98*O98
A99: 86 | B99: 30413013005 | C99: 空调温控面板 | D99: 1.名称：空调温控面板 2.规格：86*86mm 3.安装方式：暗装 4.其他：包括但不限于满足图纸、招标文件、规范及验收要求等一切相关费用 | E99: 套 | F99: 30 | G99: =R99*$R$3 | H99: =P99*(1+Q99)*$P$3+S99*$S$3 | I99: =T99*$T$3 | J99: =(G99+H99+I99)*$J$3 | K99: =(G99+H99+I99+J99)*$K$3 | L99: =G99+H99+I99+J99+K99 | M99: =F99*L99 | O99: =P99*(1+Q99)+R99+S99+T99 | P99: ='架空层安装工程'!P33 | Q99: ='架空层安装工程'!Q33 | R99: ='架空层安装工程'!R33 | S99: ='架空层安装工程'!S33 | T99: ='架空层安装工程'!T33 | U99: =F99*O99
C100: 风管
A101: 87 | B101: 30702001001 | C101: 碳钢通风管道 | D101: 1.名称：矩形风管 2.材质：镀锌薄钢板 3.厚度：0.6mm 4.长边：≤1000mm 5.其他：包括但不限于满足图纸、招标文件、规范及验收要求等一切相关费用 | E101: m2 | F101: 44.37 | G101: =R101*$R$3 | H101: =P101*(1+Q101)*$P$3+S101*$S$3 | I101: =T101*$T$3 | J101: =(G101+H101+I101)*$J$3 | K101: =(G101+H101+I101+J101)*$K$3 | L101: =G101+H101+I101+J101+K101 | M101: =F101*L101 | O101: =P101*(1+Q101)+R101+S101+T101 | P101: ='架空层安装工程'!P40 | Q101: ='架空层安装工程'!Q40 | R101: ='架空层安装工程'!R40 | S101: ='架空层安装工程'!S40 | T101: ='架空层安装工程'!T40 | U101: =F101*O101
A102: 88 | B102: 30702001002 | C102: 碳钢通风管道 | D102: 1.名称：矩形风管 2.材质：镀锌薄钢板 3.厚度：0.75mm 4.长边：≤1000mm 5.其他：包括但不限于满足图纸、招标文件、规范及验收要求等一切相关费用 | E102: m2 | F102: 45.59 | G102: =R102*$R$3 | H102: =P102*(1+Q102)*$P$3+S102*$S$3 | I102: =T102*$T$3 | J102: =(G102+H102+I102)*$J$3 | K102: =(G102+H102+I102+J102)*$K$3 | L102: =G102+H102+I102+J102+K102 | M102: =F102*L102 | O102: =P102*(1+Q102)+R102+S102+T102 | P102: ='架空层安装工程'!P41 | Q102: ='架空层安装工程'!Q41 | R102: ='架空层安装工程'!R41 | S102: ='架空层安装工程'!S41 | T102: ='架空层安装工程'!T41 | U102: =F102*O102
A103: 89 | B103: 30702001003 | C103: 碳钢通风管道 | D103: 1.名称：矩形风管 2.材质：镀锌薄钢板 3.厚度：1.0mm 4.长边：≤1250mm 5.其他：包括但不限于满足图纸、招标文件、规范及验收要求等一切相关费用 | E103: m2 | F103: 66.86 | G103: =R103*$R$3 | H103: =P103*(1+Q103)*$P$3+S103*$S$3 | I103: =T103*$T$3 | J103: =(G103+H103+I103)*$J$3 | K103: =(G103+H103+I103+J103)*$K$3 | L103: =G103+H103+I103+J103+K103 | M103: =F103*L103 | O103: =P103*(1+Q103)+R103+S103+T103 | P103: ='架空层安装工程'!P42 | Q103: ='架空层安装工程'!Q42 | R103: ='架空层安装工程'!R42 | S103: ='架空层安装工程'!S42 | T103: ='架空层安装工程'!T42 | U103: =F103*O103
A104: 90 | B104: 30702001004 | C104: 碳钢通风管道 | D104: 1.名称：矩形风管 2.材质：镀锌薄钢板 3.厚度：1.0mm 4.长边：≤2000mm 5.其他：包括但不限于满足图纸、招标文件、规范及验收要求等一切相关费用 | E104: m2 | F104: 279.53 | G104: =R104*$R$3 | H104: =P104*(1+Q104)*$P$3+S104*$S$3 | I104: =T104*$T$3 | J104: =(G104+H104+I104)*$J$3 | K104: =(G104+H104+I104+J104)*$K$3 | L104: =G104+H104+I104+J104+K104 | M104: =F104*L104 | O104: =P104*(1+Q104)+R104+S104+T104 | P104: 85 | Q104: 0.03 | R104: 48 | S104: 12 | T104: 2 | U104: =F104*O104
A105: 91 | B105: 30703019001 | C105: 柔性接口 | D105: 1.名称：帆布软接口 2.材质：帆布 3.厚度：满足验收要求 4.其他：包括但不限于满足图纸、招标文件、规范及验收要求等一切相关费用 | E105: m2 | F105: 32.82 | G105: =R105*$R$3 | H105: =P105*(1+Q105)*$P$3+S105*$S$3 | I105: =T105*$T$3 | J105: =(G105+H105+I105)*$J$3 | K105: =(G105+H105+I105+J105)*$K$3 | L105: =G105+H105+I105+J105+K105 | M105: =F105*L105 | O105: =P105*(1+Q105)+R105+S105+T105 | P105: ='架空层安装工程'!P43 | Q105: ='架空层安装工程'!Q43 | R105: ='架空层安装工程'!R43 | S105: ='架空层安装工程'!S43 | T105: ='架空层安装工程'!T43 | U105: =F105*O105
A106: 92 | B106: 31301005001 | C106: 风管支架刷油 | D106: 1.名称：风管支架刷油 2.按图纸及规范要求 3.其他：包括但不限于以上内容，综合考虑按图纸、招标文件和规范要求而实施、完成这项工程的一切有关费用 | E106: kg | F106: 1884.04 | G106: =R106*$R$3 | H106: =P106*(1+Q106)*$P$3+S106*$S$3 | I106: =T106*$T$3 | J106: =(G106+H106+I106)*$J$3 | K106: =(G106+H106+I106+J106)*$K$3 | L106: =G106+H106+I106+J106+K106 | M106: =F106*L106 | O106: =P106*(1+Q106)+R106+S106+T106 | P106: ='架空层安装工程'!P44 | Q106: ='架空层安装工程'!Q44 | R106: ='架空层安装工程'!R44 | S106: ='架空层安装工程'!S44 | T106: ='架空层安装工程'!T44 | U106: =F106*O106
A107: 93 | B107: 31208003001 | C107: 通风管道绝热 | D107: 1.名称：空调风管保温 2.材质：难燃级B1级橡塑保温材料，不燃A级铝箔贴面，湿阻因子≥10000，符合国家GB8624-2012中的管状绝热材料B标准 3.厚度：20mm 4.其他：包括但不限于满足图纸、招标文件、规范及验收要求等一切相关费用 | E107: m2 | F107: 469.67 | G107: =R107*$R$3 | H107: =P107*(1+Q107)*$P$3+S107*$S$3 | I107: =T107*$T$3 | J107: =(G107+H107+I107)*$J$3 | K107: =(G107+H107+I107+J107)*$K$3 | L107: =G107+H107+I107+J107+K107 | M107: =F107*L107 | O107: =P107*(1+Q107)+R107+S107+T107 | P107: ='架空层安装工程'!P45 | Q107: ='架空层安装工程'!Q45 | R107: ='架空层安装工程'!R45 | S107: ='架空层安装工程'!S45 | T107: ='架空层安装工程'!T45 | U107: =F107*O107
A108: 94 | B108: 30704001001 | C108: 通风工程检测、调试 | D108: 1.名称：风管漏光试验、漏风试验 | E108: 系统 | F108: 1 | G108: =R108*$R$3 | H108: =P108*(1+Q108)*$P$3+S108*$S$3 | I108: =T108*$T$3 | J108: =(G108+H108+I108)*$J$3 | K108: =(G108+H108+I108+J108)*$K$3 | L108: =G108+H108+I108+J108+K108 | M108: =F108*L108 | O108: =P108*(1+Q108)+R108+S108+T108 | P108: ='架空层安装工程'!P46 | Q108: ='架空层安装工程'!Q46 | R108: ='架空层安装工程'!R46 | S108: ='架空层安装工程'!S46 | T108: ='架空层安装工程'!T46 | U108: =F108*O108
C109: 风管部件
...

Sheet 样板房安装工程
A1: 样板房安装工程工程量清单 | O1: 成本单价组成（投标人填写）
A2: 序号 | B2: 编码 | C2: 项目名称 | D2: 项目特征 | E2: 单位 | F2: 工程量 | G2: 人工费 | H2: 材料费 | I2: 机械费 | J2: 管理费 | K2: 利润 | L2: 不含税单价 | M2: 合价 | O2: 单价合计 | P2: 主材费 | Q2: 主材损耗率 | R2: 人工费 | S2: 辅材费 | T2: 机械费 | U2: 合计
J3: 0 | K3: 0 | P3: =架空层安装工程!$P$3 | R3: =架空层安装工程!$R$3 | S3: =架空层安装工程!$S$3 | T3: =架空层安装工程!$T$3
B4: 单位工程
C5: 109户型
C6: 电气工程
C7: 灯具、电器
A8: 1 | B8: 30413002001 | C8: R1 LED嵌入式射灯 | D8: 1.名称：R1 LED嵌入式射灯 2.规格：12W、3000K、光束角36° 3.安装方式：嵌装 4.其他：包括但不限于满足图纸、招标文件、规范及验收要求等一切相关费用 | E8: 套 | F8: 20 | G8: =R8*$R$3 | H8: =P8*(1+Q8)*$P$3+S8*$S$3 | I8: =T8*$T$3 | J8: =(G8+H8+I8)*$J$3 | K8: =(G8+H8+I8+J8)*$K$3 | L8: =G8+H8+I8+J8+K8 | M8: =F8*L8 | O8: =P8*(1+Q8)+R8+S8+T8 | P8: 120 | Q8: 0 | R8: 18 | S8: 6 | T8: 8 | U8: =F8*O8
A9: 2 | B9: 30413002002 | C9: R2 LED嵌入式可调角射灯 | D9: 1.名称：R2 LED嵌入式可调角射灯 2.规格：12W、3000K、光束角24° 3.安装方式：嵌装 4.其他：包括但不限于满足图纸、招标文件、规范及验收要求等一切相关费用 | E9: 套 | F9: 4 | G9: =R9*$R$3 | H9: =P9*(1+Q9)*$P$3+S9*$S$3 | I9: =T9*$T$3 | J9: =(G9+H9+I9)*$J$3 | K9: =(G9+H9+I9+J9)*$K$3 | L9: =G9+H9+I9+J9+K9 | M9: =F9*L9 | O9: =P9*(1+Q9)+R9+S9+T9 | P9: 120 | Q9: 0 | R9: 18 | S9: 6 | T9: 8 | U9: =F9*O9
A10: 3 | B10: 30413002003 | C10: R3 嵌入式防雾射灯 | D10: 1.名称：R3 嵌入式防雾射灯 2.规格：12W、3000K、光束角36° 3.安装方式：嵌装 4.其他：包括但不限于满足图纸、招标文件、规范及验收要求等一切相关费用 | E10: 套 | F10: 6 | G10: =R10*$R$3 | H10: =P10*(1+Q10)*$P$3+S10*$S$3 | I10: =T10*$T$3 | J10: =(G10+H10+I10)*$J$3 | K10: =(G10+H10+I10+J10)*$K$3 | L10: =G10+H10+I10+J10+K10 | M10: =F10*L10 | O10: =P10*(1+Q10)+R10+S10+T10 | P10: 120 | Q10: 0 | R10: 18 | S10: 6 | T10: 8 | U10: =F10*O10
A11: 4 | B11: 30413002004 | C11: R4 明装双头射灯 | D11: 1.名称：R4 明装双头射灯 2.规格：12W、3000K、光束角36° 3.安装方式：嵌装 4.其他：包括但不限于满足图纸、招标文件、规范及验收要求等一切相关费用 | E11: 套 | F11: 3 | G11: =R11*$R$3 | H11: =P11*(1+Q11)*$P$3+S11*$S$3 | I11: =T11*$T$3 | J11: =(G11+H11+I11)*$J$3 | K11: =(G11+H11+I11+J11)*$K$3 | L11: =G11+H11+I11+J11+K11 | M11: =F11*L11 | O11: =P11*(1+Q11)+R11+S11+T11 | P11: 120 | Q11: 0 | R11: 18 | S11: 6 | T11: 8 | U11: =F11*O11
A12: 5 | B12: 30413002005 | C12: R5 明装单头射灯 | D12: 1.名称：R5 明装单头射灯 2.规格：12W、3000K、光束角36° 3.安装方式：嵌装 4.其他：包括但不限于满足图纸、招标文件、规范及验收要求等一切相关费用 | E12: 套 | F12: 5 | G12: =R12*$R$3 | H12: =P12*(1+Q12)*$P$3+S12*$S$3 | I12: =T12*$T$3 | J12: =(G12+H12+I12)*$J$3 | K12: =(G12+H12+I12+J12)*$K$3 | L12: =G12+H12+I12+J12+K12 | M12: =F12*L12 | O12: =P12*(1+Q12)+R12+S12+T12 | P12: 120 | Q12: 0 | R12: 18 | S12: 6 | T12: 8 | U12: =F12*O12
A13: 6 | B13: 30413002006 | C13: L1 LED灯条（天花） | D13: 1.名称：L1 LED灯条（天花） 2.规格：14W/米,3000K,120珠/米 3.安装方式：天花 4.其他：包括但不限于满足图纸、招标文件、规范及验收要求等一切相关费用 | E13: m | F13: 72.19 | G13: =R13*$R$3 | H13: =P13*(1+Q13)*$P$3+S13*$S$3 | I13: =T13*$T$3 | J13: =(G13+H13+I13)*$J$3 | K13: =(G13+H13+I13+J13)*$K$3 | L13: =G13+H13+I13+J13+K13 | M13: =F13*L13 | O13: =P13*(1+Q13)+R13+S13+T13 | P13: 12 | Q13: 0 | R13: 2.5 | S13: 0.5 | T13: 0 | U13: =F13*O13
A14: 7 | B14: 30413002007 | C14: L2 LED灯条（墙立面） | D14: 1.名称：L2 LED灯条（墙立面） 2.规格：7W/米,3000K,120珠/米 3.安装方式：天花 4.其他：包括但不限于满足图纸、招标文件、规范及验收要求等一切相关费用 | E14: m | F14: 22.14 | G14: =R14*$R$3 | H14: =P14*(1+Q14)*$P$3+S14*$S$3 | I14: =T14*$T$3 | J14: =(G14+H14+I14)*$J$3 | K14: =(G14+H14+I14+J14)*$K$3 | L14: =G14+H14+I14+J14+K14 | M14: =F14*L14 | O14: =P14*(1+Q14)+R14+S14+T14 | P14: 12 | Q14: 0 | R14: 2.5 | S14: 0.5 | T14: 0 | U14: =F14*O14
A15: 8 | B15: 30413002008 | C15: L3 LED灯条（柜子） | D15: 1.名称：L3 LED灯条（柜子） 2.规格：4W/米,3000K,120珠/米 3.安装方式：天花 4.其他：包括但不限于满足图纸、招标文件、规范及验收要求等一切相关费用 | E15: m | F15: 15.01 | G15: =R15*$R$3 | H15: =P15*(1+Q15)*$P$3+S15*$S$3 | I15: =T15*$T$3 | J15: =(G15+H15+I15)*$J$3 | K15: =(G15+H15+I15+J15)*$K$3 | L15: =G15+H15+I15+J15+K15 | M15: =F15*L15 | O15: =P15*(1+Q15)+R15+S15+T15 | P15: 12 | Q15: 0 | R15: 2.5 | S15: 0.5 | T15: 0 | U15: =F15*O15
A16: 9 | B16: 30413009001 | C16: LED 灯带驱动电源 | D16: 1.名称：LED 灯带驱动电源 2.规格：60W 工作电压：220V 输出电压：24V 3.尺寸：L140*W45*H29mm 4.其他：包括但不限于满足图纸、招标文件、规范及验收要求等一切相关费用 | E16: 个 | F16: 26 | G16: =R16*$R$3 | H16: =P16*(1+Q16)*$P$3+S16*$S$3 | I16: =T16*$T$3 | J16: =(G16+H16+I16)*$J$3 | K16: =(G16+H16+I16+J16)*$K$3 | L16: =G16+H16+I16+J16+K16 | M16: =F16*L16 | O16: =P16*(1+Q16)+R16+S16+T16 | P16: ='架空层安装工程'!P10 | Q16: ='架空层安装工程'!Q10 | R16: ='架空层安装工程'!R10 | S16: ='架空层安装工程'!S10 | T16: ='架空层安装工程'!T10 | U16: =F16*O16
A17: 10 | B17: 30405015001 | C17: 线型凉霸及开关 | D17: 1.名称：线型凉霸及开关 2.规格：34W 3.尺寸：详见物料表 4.其他：包括但不限于满足图纸、招标文件、规范及验收要求等一切相关费用 | E17: 台 | F17: 1 | G17: =R17*$R$3 | H17: =P17*(1+Q17)*$P$3+S17*$S$3 | I17: =T17*$T$3 | J17: =(G17+H17+I17)*$J$3 | K17: =(G17+H17+I17+J17)*$K$3 | L17: =G17+H17+I17+J17+K17 | M17: =F17*L17 | O17: =P17*(1+Q17)+R17+S17+T17 | P17: 280 | Q17: 0 | R17: 25 | S17: 3 | T17: 0 | U17: =F17*O17
A18: 11 | B18: 30405015002 | C18: 线型浴霸及开关 | D18: 1.名称：线型浴霸及开关 2.规格：40W 3.尺寸：详见物料表 4.其他：包括但不限于满足图纸、招标文件、规范及验收要求等一切相关费用 | E18: 台 | F18: 2 | G18: =R18*$R$3 | H18: =P18*(1+Q18)*$P$3+S18*$S$3 | I18: =T18*$T$3 | J18: =(G18+H18+I18)*$J$3 | K18: =(G18+H18+I18+J18)*$K$3 | L18: =G18+H18+I18+J18+K18 | M18: =F18*L18 | O18: =P18*(1+Q18)+R18+S18+T18 | P18: 450 | Q18: 0 | R18: 30 | S18: 3 | T18: 0 | U18: =F18*O18
A19: 12 | B19: 30405017001 | C19: 洗碗机 | D19: 1.名称：洗碗机 2.规格：- 3.尺寸：详见物料表 4.其他：包括但不限于满足图纸、招标文件、规范及验收要求等一切相关费用 | E19: 台 | F19: 1 | G19: =R19*$R$3 | H19: =P19*(1+Q19)*$P$3+S19*$S$3 | I19: =T19*$T$3 | J19: =(G19+H19+I19)*$J$3 | K19: =(G19+H19+I19+J19)*$K$3 | L19: =G19+H19+I19+J19+K19 | M19: =F19*L19 | O19: =P19*(1+Q19)+R19+S19+T19 | P19: 4200 | Q19: 0 | R19: 250 | S19: 35 | T19: 8.5 | U19: =F19*O19
C20: 开关插座 | O20: =P20*(1+Q20)+R20+S20+T20 | U20: =F20*O20
A21: 13 | B21: 30413013001 | C21: 照明开关 | D21: 1.名称：单联单控开关 2.规格：86*86mm 3.安装方式：暗装 4.其他：包括但不限于满足图纸、招标文件、规范及验收要求等一切相关费用 | E21: 套 | F21: 2 | G21: =R21*$R$3 | H21: =P21*(1+Q21)*$P$3+S21*$S$3 | I21: =T21*$T$3 | J21: =(G21+H21+I21)*$J$3 | K21: =(G21+H21+I21+J21)*$K$3 | L21: =G21+H21+I21+J21+K21 | M21: =F21*L21 | O21: =P21*(1+Q21)+R21+S21+T21 | P21: ='公共区域安装工程'!P14 | Q21: ='公共区域安装工程'!Q14 | R21: ='公共区域安装工程'!R14 | S21: ='公共区域安装工程'!S14 | T21: ='公共区域安装工程'!T14 | U21: =F21*O21
A22: 14 | B22: 30413013002 | C22: 照明开关 | D22: 1.名称：双联单控开关 2.规格：86*86mm 3.安装方式：暗装 4.其他：包括但不限于满足图纸、招标文件、规范及验收要求等一切相关费用 | E22: 套 | F22: 1 | G22: =R22*$R$3 | H22: =P22*(1+Q22)*$P$3+S22*$S$3 | I22: =T22*$T$3 | J22: =(G22+H22+I22)*$J$3 | K22: =(G22+H22+I22+J22)*$K$3 | L22: =G22+H22+I22+J22+K22 | M22: =F22*L22 | O22: =P22*(1+Q22)+R22+S22+T22 | P22: ='架空层安装工程'!P16 | Q22: ='架空层安装工程'!Q16 | R22: ='架空层安装工程'!R16 | S22: ='架空层安装工程'!S16 | T22: ='架空层安装工程'!T16 | U22: =F22*O22
A23: 15 | B23: 30413013003 | C23: 照明开关 | D23: 1.名称：三联单控开关 2.规格：86*86mm 3.安装方式：暗装 4.其他：包括但不限于满足图纸、招标文件、规范及验收要求等一切相关费用 | E23: 套 | F23: 2 | G23: =R23*$R$3 | H23: =P23*(1+Q23)*$P$3+S23*$S$3 | I23: =T23*$T$3 | J23: =(G23+H23+I23)*$J$3 | K23: =(G23+H23+I23+J23)*$K$3 | L23: =G23+H23+I23+J23+K23 | M23: =F23*L23 | O23: =P23*(1+Q23)+R23+S23+T23 | P23: ='公共区域安装工程'!P15 | Q23: ='公共区域安装工程'!Q15 | R23: ='公共区域安装工程'!R15 | S23: ='公共区域安装工程'!S15 | T23: ='公共区域安装工程'!T15 | U23: =F23*O23
A24: 16 | B24: 30413013004 | C24: 照明开关 | D24: 1.名称：双联双控开关 2.规格：86*86mm 3.安装方式：暗装 4.其他：包括但不限于满足图纸、招标文件、规范及验收要求等一切相关费用 | E24: 套 | F24: 2 | G24: =R24*$R$3 | H24: =P24*(1+Q24)*$P$3+S24*$S$3 | I24: =T24*$T$3 | J24: =(G24+H24+I24)*$J$3 | K24: =(G24+H24+I24+J24)*$K$3 | L24: =G24+H24+I24+J24+K24 | M24: =F24*L24 | O24: =P24*(1+Q24)+R24+S24+T24 | P24: ='户内交标安装工程'!P21 | Q24: ='户内交标安装工程'!Q21 | R24: ='户内交标安装工程'!R21 | S24: ='户内交标安装工程'!S21 | T24: ='户内交标安装工程'!T21 | U24: =F24*O24
A25: 17 | B25: 30413013005 | C25: 照明开关 | D25: 1.名称：三联双控开关 2.规格：86*86mm 3.安装方式：暗装 4.其他：包括但不限于满足图纸、招标文件、规范及验收要求等一切相关费用 | E25: 套 | F25: 8 | G25: =R25*$R$3 | H25: =P25*(1+Q25)*$P$3+S25*$S$3 | I25: =T25*$T$3 | J25: =(G25+H25+I25)*$J$3 | K25: =(G25+H25+I25+J25)*$K$3 | L25: =G25+H25+I25+J25+K25 | M25: =F25*L25 | O25: =P25*(1+Q25)+R25+S25+T25 | P25: ='户内交标安装工程'!P22 | Q25: ='户内交标安装工程'!Q22 | R25: ='户内交标安装工程'!R22 | S25: ='户内交标安装工程'!S22 | T25: ='户内交标安装工程'!T22 | U25: =F25*O25
A26: 18 | B26: 30413013006 | C26: 照明开关 | D26: 1.名称：四联双控开关 2.规格：86*86mm 3.安装方式：暗装 4.其他：包括但不限于满足图纸、招标文件、规范及验收要求等一切相关费用 | E26: 套 | F26: 4 | G26: =R26*$R$3 | H26: =P26*(1+Q26)*$P$3+S26*$S$3 | I26: =T26*$T$3 | J26: =(G26+H26+I26)*$J$3 | K26: =(G26+H26+I26+J26)*$K$3 | L26: =G26+H26+I26+J26+K26 | M26: =F26*L26 | O26: =P26*(1+Q26)+R26+S26+T26 | P26: 14.62 | Q26: 0 | R26: 6.31 | S26: 1.12 | T26: 0 | U26: =F26*O26
A27: 19 | B27: 30413014001 | C27: 插座 | D27: 1.名称：五孔插座 2.规格：86*86mm 3.安装方式：暗装 4.其他：包括但不限于满足图纸、招标文件、规范及验收要求等一切相关费用 | E27: 套 | F27: 31 | G27: =R27*$R$3 | H27: =P27*(1+Q27)*$P$3+S27*$S$3 | I27: =T27*$T$3 | J27: =(G27+H27+I27)*$J$3 | K27: =(G27+H27+I27+J27)*$K$3 | L27: =G27+H27+I27+J27+K27 | M27: =F27*L27 | O27: =P27*(1+Q27)+R27+S27+T27 | P27: ='公共区域安装工程'!P16 | Q27: ='公共区域安装工程'!Q16 | R27: ='公共区域安装工程'!R16 | S27: ='公共区域安装工程'!S16 | T27: ='公共区域安装工程'!T16 | U27: =F27*O27
A28: 20 | B28: 30413014002 | C28: 插座 | D28: 1.名称：五孔插座（带防溅盒） 2.规格：86*86mm 3.安装方式：暗装 4.其他：包括但不限于满足图纸、招标文件、规范及验收要求等一切相关费用 | E28: 套 | F28: 12 | G28: =R28*$R$3 | H28: =P28*(1+Q28)*$P$3+S28*$S$3 | I28: =T28*$T$3 | J28: =(G28+H28+I28)*$J$3 | K28: =(G28+H28+I28+J28)*$K$3 | L28: =G28+H28+I28+J28+K28 | M28: =F28*L28 | O28: =P28*(1+Q28)+R28+S28+T28 | P28: 14.62 | Q28: 0 | R28: 6.31 | S28: 1.12 | T28: 0 | U28: =F28*O28
A29: 21 | B29: 30413014003 | C29: 插座 | D29: 1.名称：五孔插座带USB 2.规格：86*86mm 3.安装方式：暗装 4.其他：包括但不限于满足图纸、招标文件、规范及验收要求等一切相关费用 | E29: 套 | F29: 3 | G29: =R29*$R$3 | H29: =P29*(1+Q29)*$P$3+S29*$S$3 | I29: =T29*$T$3 | J29: =(G29+H29+I29)*$J$3 | K29: =(G29+H29+I29+J29)*$K$3 | L29: =G29+H29+I29+J29+K29 | M29: =F29*L29 | O29: =P29*(1+Q29)+R29+S29+T29 | P29: 14.62 | Q29: 0 | R29: 6.31 | S29: 1.12 | T29: 0 | U29: =F29*O29
A30: 22 | B30: 30413014004 | C30: 插座 | D30: 1.名称：五孔插座带开关 2.规格：86*86mm 3.安装方式：暗装 4.其他：包括但不限于满足图纸、招标文件、规范及验收要求等一切相关费用 | E30: 套 | F30: 2 | G30: =R30*$R$3 | H30: =P30*(1+Q30)*$P$3+S30*$S$3 | I30: =T30*$T$3 | J30: =(G30+H30+I30)*$J$3 | K30: =(G30+H30+I30+J30)*$K$3 | L30: =G30+H30+I30+J30+K30 | M30: =F30*L30 | O30: =P30*(1+Q30)+R30+S30+T30 | P30: ='户内交标安装工程'!P25 | Q30: ='户内交标安装工程'!Q25 | R30: ='户内交标安装工程'!R25 | S30: ='户内交标安装工程'!S25 | T30: ='户内交标安装工程'!T25 | U30: =F30*O30
A31: 23 | B31: 30413014005 | C31: 插座 | D31: 1.名称：五孔插座带开关（带防溅盒） 2.规格：86*86mm 3.安装方式：暗装 4.其他：包括但不限于满足图纸、招标文件、规范及验收要求等一切相关费用 | E31: 套 | F31: 2 | G31: =R31*$R$3 | H31: =P31*(1+Q31)*$P$3+S31*$S$3 | I31: =T31*$T$3 | J31: =(G31+H31+I31)*$J$3 | K31: =(G31+H31+I31+J31)*$K$3 | L31: =G31+H31+I31+J31+K31 | M31: =F31*L31 | O31: =P31*(1+Q31)+R31+S31+T31 | P31: 14.62 | Q31: 0 | R31: 6.31 | S31: 1.12 | T31: 0 | U31: =F31*O31
A32: 24 | B32: 30413014006 | C32: 插座 | D32: 1.名称：地面五孔插座 2.规格：86*86mm 3.安装方式：暗装 4.其他：包括但不限于满足图纸、招标文件、规范及验收要求等一切相关费用 | E32: 套 | F32: 2 | G32: =R32*$R$3 | H32: =P32*(1+Q32)*$P$3+S32*$S$3 | I32: =T32*$T$3 | J32: =(G32+H32+I32)*$J$3 | K32: =(G32+H32+I32+J32)*$K$3 | L32: =G32+H32+I32+J32+K32 | M32: =F32*L32 | O32: =P32*(1+Q32)+R32+S32+T32 | P32: ='架空层安装工程'!P19 | Q32: ='架空层安装工程'!Q19 | R32: ='架空层安装工程'!R19 | S32: ='架空层安装工程'!S19 | T32: ='架空层安装工程'!T19 | U32: =F32*O32
C33: 配管配线 | O33: =P33*(1+Q33)+R33+S33+T33 | U33: =F33*O33
A34: 25 | B34: 30412004001 | C34: 配线 | D34: 1.名称：电气配线 2.型号规格：BV-1.5 3.安装方式：管内穿线 4.其他：包括但不限于满足图纸、招标文件、规范及验收要求等一切相关费用 | E34: m | F34: 278.13 | G34: =R34*$R$3 | H34: =P34*(1+Q34)*$P$3+S34*$S$3 | I34: =T34*$T$3 | J34: =(G34+H34+I34)*$J$3 | K34: =(G34+H34+I34+J34)*$K$3 | L34: =G34+H34+I34+J34+K34 | M34: =F34*L34 | O34: =P34*(1+Q34)+R34+S34+T34 | P34: 1.9 | Q34: 0.02 | R34: 1.58 | S34: 0.19 | T34: 0.02 | U34: =F34*O34
A35: 26 | B35: 30412004002 | C35: 配线 | D35: 1.名称：电气配线 2.型号规格：BV-2.5 3.安装方式：管内穿线 4.其他：包括但不限于满足图纸、招标文件、规范及验收要求等一切相关费用 | E35: m | F35: 1134.55 | G35: =R35*$R$3 | H35: =P35*(1+Q35)*$P$3+S35*$S$3 | I35: =T35*$T$3 | J35: =(G35+H35+I35)*$J$3 | K35: =(G35+H35+I35+J35)*$K$3 | L35: =G35+H35+I35+J35+K35 | M35: =F35*L35 | O35: =P35*(1+Q35)+R35+S35+T35 | P35: ='公共区域安装工程'!P22 | Q35: ='公共区域安装工程'!Q22 | R35: ='公共区域安装工程'!R22 | S35: ='公共区域安装工程'!S22 | T35: ='公共区域安装工程'!T22 | U35: =F35*O35
A36: 27 | B36: 30412004003 | C36: 配线 | D36: 1.名称：电气配线 2.型号规格：BV-4 3.安装方式：管内穿线 4.其他：包括但不限于满足图纸、招标文件、规范及验收要求等一切相关费用 | E36: m | F36: 720.6 | G36: =R36*$R$3 | H36: =P36*(1+Q36)*$P$3+S36*$S$3 | I36: =T36*$T$3 | J36: =(G36+H36+I36)*$J$3 | K36: =(G36+H36+I36+J36)*$K$3 | L36: =G36+H36+I36+J36+K36 | M36: =F36*L36 | O36: =P36*(1+Q36)+R36+S36+T36 | P36: ='户内交标安装工程'!P32 | Q36: ='户内交标安装工程'!Q32 | R36: ='户内交标安装工程'!R32 | S36: ='户内交标安装工程'!S32 | T36: ='户内交标安装工程'!T32 | U36: =F36*O36
A37: 28 | B37: 30412004004 | C37: 配线 | D37: 1.名称：电气配线 2.型号规格：BV-10 3.安装方式：管内穿线 4.其他：包括但不限于满足图纸、招标文件、规范及验收要求等一切相关费用 | E37: m | F37: 31.52 | G37: =R37*$R$3 | H37: =P37*(1+Q37)*$P$3+S37*$S$3 | I37: =T37*$T$3 | J37: =(G37+H37+I37)*$J$3 | K37: =(G37+H37+I37+J37)*$K$3 | L37: =G37+H37+I37+J37+K37 | M37: =F37*L37 | O37: =P37*(1+Q37)+R37+S37+T37 | P37: 9 | Q37: 0.02 | R37: 2 | S37: 0.33 | T37: 0.02 | U37: =F37*O37
C38: 弱电工程 | O38: =P38*(1+Q38)+R38+S38+T38 | U38: =F38*O38
A39: 29 | B39: 30413014007 | C39: 插座 | D39: 1.名称：网络插座 2.规格：86*86mm 3.安装方式：暗装 4.其他：包括但不限于满足图纸、招标文件、规范及验收要求等一切相关费用 | E39: 套 | F39: 4 | G39: =R39*$R$3 | H39: =P39*(1+Q39)*$P$3+S39*$S$3 | I39: =T39*$T$3 | J39: =(G39+H39+I39)*$J$3 | K39: =(G39+H39+I39+J39)*$K$3 | L39: =G39+H39+I39+J39+K39 | M39: =F39*L39 | O39: =P39*(1+Q39)+R39+S39+T39 | P39: 14.62 | Q39: 0 | R39: 6.31 | S39: 1.12 | T39: 0 | U39: =F39*O39
A40: 30 | B40: 30413014008 | C40: 插座 | D40: 1.名称：电视插座 2.规格：86*86mm 3.安装方式：暗装 4.其他：包括但不限于满足图纸、招标文件、规范及验收要求等一切相关费用 | E40: 套 | F40: 2 | G40: =R40*$R$3 | H40: =P40*(1+Q40)*$P$3+S40*$S$3 | I40: =T40*$T$3 | J40: =(G40+H40+I40)*$J$3 | K40: =(G40+H40+I40+J40)*$K$3 | L40: =G40+H40+I40+J40+K40 | M40: =F40*L40 | O40: =P40*(1+Q40)+R40+S40+T40 | P40: 14.62 | Q40: 0 | R40: 6.31 | S40: 1.12 | T40: 0 | U40: =F40*O40
A41: 31 | B41: 30413013007 | C41: 紧急按钮 | D41: 1.名称：紧急按钮 2.规格：86*86mm 3.安装方式：暗装 4.其他：包括但不限于满足图纸、招标文件、规范及验收要求等一切相关费用 | E41: 套 | F41: 1 | G41: =R41*$R$3 | H41: =P41*(1+Q41)*$P$3+S41*$S$3 | I41: =T41*$T$3 | J41: =(G41+H41+I41)*$J$3 | K41: =(G41+H41+I41+J41)*$K$3 | L41: =G41+H41+I41+J41+K41 | M41: =F41*L41 | O41: =P41*(1+Q41)+R41+S41+T41 | P41: 27 | Q41: 0 | R41: 12 | S41: 2 | T41: 0 | U41: =F41*O41
A42: 32 | B42: 30502003001 | C42: 双绞线缆 | D42: 1.名称：超六类网线 2.型号规格：CAT6e 3.敷设方式：管内穿线 4.其他：包括但不限于满足图纸、招标文件、规范及验收要求等一切相关费用 | E42: m | F42: 69.6 | G42: =R42*$R$3 | H42: =P42*(1+Q42)*$P$3+S42*$S$3 | I42: =T42*$T$3 | J42: =(G42+H42+I42)*$J$3 | K42: =(G42+H42+I42+J42)*$K$3 | L42: =G42+H42+I42+J42+K42 | M42: =F42*L42 | O42: =P42*(1+Q42)+R42+S42+T42 | P42: 2.5 | Q42: 0 | R42: 0.8 | S42: 0.1 | T42: 0.1 | U42: =F42*O42
A43: 33 | B43: 30502003002 | C43: 多芯软导线 | D43: 1.名称：多芯软导线 2.型号规格：RVV-2*1.0 3.敷设方式：管内穿线 4.其他：包括但不限于满足图纸、招标文件、规范及验收要求等一切相关费用 | E43: m | F43: 14.63 | G43: =R43*$R$3 | H43: =P43*(1+Q43)*$P$3+S43*$S$3 | I43: =T43*$T$3 | J43: =(G43+H43+I43)*$J$3 | K43: =(G43+H43+I43+J43)*$K$3 | L43: =G43+H43+I43+J43+K43 | M43: =F43*L43 | O43: =P43*(1+Q43)+R43+S43+T43 | P43: 3 | Q43: 0.02 | R43: 1.73 | S43: 0.12 | T43: 0.02 | U43: =F43*O43
C44: 给排水工程 | O44: =P44*(1+Q44)+R44+S44+T44 | U44: =F44*O44
C45: 排水管 | O45: =P45*(1+Q45)+R45+S45+T45 | U45: =F45*O45
A46: 34 | B46: 31001008007 | C46: UPVC排水管 | D46: 1.名称：UPVC排水管 2.规格：DN50 3.连接方式：粘接 4.压力试验及吹、洗要求：水压试验、管道标识等 5.其他：包括但不限于满足图纸、招标文件、规范及验收要求等一切相关费用 | E46: m | F46: 6.1 | G46: =R46*$R$3 | H46: =P46*(1+Q46)*$P$3+S46*$S$3 | I46: =T46*$T$3 | J46: =(G46+H46+I46)*$J$3 | K46: =(G46+H46+I46+J46)*$K$3 | L46: =G46+H46+I46+J46+K46 | M46: =F46*L46 | O46: =P46*(1+Q46)+R46+S46+T46 | P46: 15 | Q46: 0 | R46: 24 | S46: 1.27 | T46: 0.23 | U46: =F46*O46
A47: 35 | B47: 31001008008 | C47: UPVC排水管 | D47: 1.名称：UPVC排水管 2.规格：DN75 3.连接方式：粘接 4.压力试验及吹、洗要求：水压试验、管道标识等 5.其他：包括但不限于满足图纸、招标文件、规范及验收要求等一切相关费用 | E47: m | F47: 1.97 | G47: =R47*$R$3 | H47: =P47*(1+Q47)*$P$3+S47*$S$3 | I47: =T47*$T$3 | J47: =(G47+H47+I47)*$J$3 | K47: =(G47+H47+I47+J47)*$K$3 | L47: =G47+H47+I47+J47+K47 | M47: =F47*L47 | O47: =P47*(1+Q47)+R47+S47+T47 | P47: 25 | Q47: 0 | R47: 55 | S47: 3 | T47: 3 | U47: =F47*O47
A48: 36 | B48: 31001008009 | C48: UPVC排水管 | D48: 1.名称：UPVC排水管 2.规格：DN100 3.连接方式：粘接 4.压力试验及吹、洗要求：水压试验、管道标识等 5.其他：包括但不限于满足图纸、招标文件、规范及验收要求等一切相关费用 | E48: m | F48: 1.53 | G48: =R48*$R$3 | H48: =P48*(1+Q48)*$P$3+S48*$S$3 | I48: =T48*$T$3 | J48: =(G48+H48+I48)*$J$3 | K48: =(G48+H48+I48+J48)*$K$3 | L48: =G48+H48+I48+J48+K48 | M48: =F48*L48 | O48: =P48*(1+Q48)+R48+S48+T48 | P48: 36 | Q48: 0 | R48: 30 | S48: 2.12 | T48: 0.38 | U48: =F48*O48
C49: 洁具五金 | O49: =P49*(1+Q49)+R49+S49+T49 | U49: =F49*O49
A50: 37 | B50: 31003006001 | C50: 大便器 | D50: 1.名称：智能坐便器-主卫 2.型号：详见物料表 3.其他：包括但不限于满足图纸、招标文件、规范及验收要求等一切相关费用 | E50: 组 | F50: 1 | G50: =R50*$R$3 | H50: =P50*(1+Q50)*$P$3+S50*$S$3 | I50: =T50*$T$3 | J50: =(G50+H50+I50)*$J$3 | K50: =(G50+H50+I50+J50)*$K$3 | L50: =G50+H50+I50+J50+K50 | M50: =F50*L50 | O50: =P50*(1+Q50)+R50+S50+T50 | P50: 800 | Q50: 0 | R50: 130 | S50: 15 | T50: 0.8 | U50: =F50*O50
A51: 38 | B51: 31003006002 | C51: 大便器 | D51: 1.名称：连体坐便器-公卫 2.型号：详见物料表 3.其他：包括但不限于满足图纸、招标文件、规范及验收要求等一切相关费用 | E51: 组 | F51: 1 | G51: =R51*$R$3 | H51: =P51*(1+Q51)*$P$3+S51*$S$3 | I51: =T51*$T$3 | J51: =(G51+H51+I51)*$J$3 | K51: =(G51+H51+I51+J51)*$K$3 | L51: =G51+H51+I51+J51+K51 | M51: =F51*L51 | O51: =P51*(1+Q51)+R51+S51+T51 | P51: 800 | Q51: 0 | R51: 130 | S51: 15 | T51: 0.8 | U51: =F51*O51
A52: 39 | B52: 31003010001 | C52: 淋浴器 | D52: 1.名称：淋浴花洒3-主卫 2.型号：详见物料表 3.其他：包括但不限于满足图纸、招标文件、规范及验收要求等一切相关费用 | E52: 套 | F52: 1 | G52: =R52*$R$3 | H52: =P52*(1+Q52)*$P$3+S52*$S$3 | I52: =T52*$T$3 | J52: =(G52+H52+I52)*$J$3 | K52: =(G52+H52+I52+J52)*$K$3 | L52: =G52+H52+I52+J52+K52 | M52: =F52*L52 | O52: =P52*(1+Q52)+R52+S52+T52 | P52: 1100 | Q52: 0 | R52: 90 | S52: 35 | T52: 0 | U52: =F52*O52
A53: 40 | B53: 31003010002 | C53: 淋浴器 | D53: 1.名称：淋浴花洒2-公卫 2.型号：详见物料表 3.其他：包括但不限于满足图纸、招标文件、规范及验收要求等一切相关费用 | E53: 套 | F53: 1 | G53: =R53*$R$3 | H53: =P53*(1+Q53)*$P$3+S53*$S$3 | I53: =T53*$T$3 | J53: =(G53+H53+I53)*$J$3 | K53: =(G53+H53+I53+J53)*$K$3 | L53: =G53+H53+I53+J53+K53 | M53: =F53*L53 | O53: =P53*(1+Q53)+R53+S53+T53 | P53: 1100 | Q53: 0 | R53: 90 | S53: 35 | T53: 0 | U53: =F53*O53
A54: 41 | B54: 31003003001 | C54: 台下盆及龙头 | D54: 1.名称：台下盆方形及龙头-主卫 2.型号：详见物料表 3.其他：包括但不限于满足图纸、招标文件、规范及验收要求等一切相关费用 | E54: 组 | F54: 1 | G54: =R54*$R$3 | H54: =P54*(1+Q54)*$P$3+S54*$S$3 | I54: =T54*$T$3 | J54: =(G54+H54+I54)*$J$3 | K54: =(G54+H54+I54+J54)*$K$3 | L54: =G54+H54+I54+J54+K54 | M54: =F54*L54 | O54: =P54*(1+Q54)+R54+S54+T54 | P54: 550 | Q54: 0 | R54: 90 | S54: 12 | T54: 0 | U54: =F54*O54
A55: 42 | B55: 31003003002 | C55: 台下盆及龙头 | D55: 1.名称：台下盆方形及龙头-公卫 2.型号：详见物料表 3.其他：包括但不限于满足图纸、招标文件、规范及验收要求等一切相关费用 | E55: 组 | F55: 1 | G55: =R55*$R$3 | H55: =P55*(1+Q55)*$P$3+S55*$S$3 | I55: =T55*$T$3 | J55: =(G55+H55+I55)*$J$3 | K55: =(G55+H55+I55+J55)*$K$3 | L55: =G55+H55+I55+J55+K55 | M55: =F55*L55 | O55: =P55*(1+Q55)+R55+S55+T55 | P55: 550 | Q55: 0 | R55: 90 | S55: 12 | T55: 0 | U55: =F55*O55
A56: 43 | B56: 31003004001 | C56: 水槽及龙头 | D56: 1.名称：厨房大单盆水槽 2.型号：详见物料表 3.其他：包括但不限于满足图纸、招标文件、规范及验收要求等一切相关费用 | E56: 组 | F56: 1 | G56: =R56*$R$3 | H56: =P56*(1+Q56)*$P$3+S56*$S$3 | I56: =T56*$T$3 | J56: =(G56+H56+I56)*$J$3 | K56: =(G56+H56+I56+J56)*$K$3 | L56: =G56+H56+I56+J56+K56 | M56: =F56*L56 | O56: =P56*(1+Q56)+R56+S56+T56 | P56: 950 | Q56: 0 | R56: 60 | S56: 40 | T56: 0 | U56: =F56*O56
A57: 44 | B57: 31003014001 | C57: 地漏 | D57: 1.名称：隐藏式地漏-干区 2.规格：DN50 3.型号：详见物料表 4.其他：包括但不限于满足图纸、招标文件、规范及验收要求等一切相关费用 | E57: 个 | F57: 2 | G57: =R57*$R$3 | H57: =P57*(1+Q57)*$P$3+S57*$S$3 | I57: =T57*$T$3 | J57: =(G57+H57+I57)*$J$3 | K57: =(G57+H57+I57+J57)*$K$3 | L57: =G57+H57+I57+J57+K57 | M57: =F57*L57 | O57: =P57*(1+Q57)+R57+S57+T57 | P57: 35 | Q57: 0 | R57: 18 | S57: 5 | T57: 0 | U57: =F57*O57
A58: 45 | B58: 31003014002 | C58: 地漏 | D58: 1.名称：隐形长地漏-淋浴间 2.规格：DN75 3.型号：详见物料表 4.其他：包括但不限于满足图纸、招标文件、规范及验收要求等一切相关费用 | E58: 个 | F58: 2 | G58: =R58*$R$3 | H58: =P58*(1+Q58)*$P$3+S58*$S$3 | I58: =T58*$T$3 | J58: =(G58+H58+I58)*$J$3 | K58: =(G58+H58+I58+J58)*$K$3 | L58: =G58+H58+I58+J58+K58 | M58: =F58*L58 | O58: =P58*(1+Q58)+R58+S58+T58 | P58: 55 | Q58: 0 | R58: 25 | S58: 1.5 | T58: 0.2 | U58: =F58*O58
A59: 46 | B59: 31003014003 | C59: 地漏 | D59: 1.名称：隐藏式地漏-阳台 2.规格：DN75 3.型号：详见物料表 4.其他：包括但不限于满足图纸、招标文件、规范及验收要求等一切相关费用 | E59: 个 | F59: 2 | G59: =R59*$R$3 | H59: =P59*(1+Q59)*$P$3+S59*$S$3 | I59: =T59*$T$3 | J59: =(G59+H59+I59)*$J$3 | K59: =(G59+H59+I59+J59)*$K$3 | L59: =G59+H59+I59+J59+K59 | M59: =F59*L59 | O59: =P59*(1+Q59)+R59+S59+T59 | P59: 55 | Q59: 0 | R59: 25 | S59: 1.5 | T59: 0.2 | U59: =F59*O59
A60: 47 | B60: 31003014004 | C60: 地漏 | D60: 1.名称：洗衣机地漏 2.规格：DN75 3.型号：详见物料表 4.其他：包括但不限于满足图纸、招标文件、规范及验收要求等一切相关费用 | E60: 个 | F60: 1 | G60: =R60*$R$3 | H60: =P60*(1+Q60)*$P$3+S60*$S$3 | I60: =T60*$T$3 | J60: =(G60+H60+I60)*$J$3 | K60: =(G60+H60+I60+J60)*$K$3 | L60: =G60+H60+I60+J60+K60 | M60: =F60*L60 | O60: =P60*(1+Q60)+R60+S60+T60 | P60: 35 | Q60: 0 | R60: 18 | S60: 5 | T60: 0 | U60: =F60*O60
A61: 48 | B61: 31003014005 | C61: 洗衣机龙头 | D61: 1.名称：洗衣机龙头 2.规格：DN15 3.型号：详见物料表 4.其他：包括但不限于满足图纸、招标文件、规范及验收要求等一切相关费用 | E61: 个 | F61: 1 | G61: =R61*$R$3 | H61: =P61*(1+Q61)*$P$3+S61*$S$3 | I61: =T61*$T$3 | J61: =(G61+H61+I61)*$J$3 | K61: =(G61+H61+I61+J61)*$K$3 | L61: =G61+H61+I61+J61+K61 | M61: =F61*L61 | O61: =P61*(1+Q61)+R61+S61+T61 | P61: 465 | Q61: 0 | R61: 55 | S61: 20 | T61: 0 | U61: =F61*O61
A62: 49 | B62: 31002001004 | C62: 角阀 | D62: 1.名称：角阀（热水器、洗碗机、扫地机、阳台洗手盆） 2.型号规格：DN15 3.其他：包括但不限于满足图纸、招标文件、规范及验收要求等一切相关费用 | E62: 个 | F62: 6 | G62: =R62*$R$3 | H62: =P62*(1+Q62)*$P$3+S62*$S$3 | I62: =T62*$T$3 | J62: =(G62+H62+I62)*$J$3 | K62: =(G62+H62+I62+J62)*$K$3 | L62: =G62+H62+I62+J62+K62 | M62: =F62*L62 | O62: =P62*(1+Q62)+R62+S62+T62 | P62: 1504.2 | Q62: 0 | R62: 167.09 | S62: 0 | T62: 12.03 | U62: =F62*O62
C63: 空调工程 | O63: =P63*(1+Q63)+R63+S63+T63 | U63: =F63*O63
C64: 设备 | O64: =P64*(1+Q64)+R64+S64+T64 | U64: =F64*O64
A65: 50 | B65: 30701003001 | C65: 风管机 | D65: 1.名称：超薄风管式室内机 FF25 2.规格：制冷量2.5kW 制冷功率40W 制热量3.0kW 制热功率40W 风量500m3/h 运转噪音≤29dB(A) 3.安装方式：吊装 4.其他：包括但不限于满足图纸、招标文件、规范及验收要求等一切相关费用 | E65: 台 | F65: 1 | G65: =R65*$R$3 | H65: =P65*(1+Q65)*$P$3+S65*$S$3 | I65: =T65*$T$3 | J65: =(G65+H65+I65)*$J$3 | K65: =(G65+H65+I65+J65)*$K$3 | L65: =G65+H65+I65+J65+K65 | M65: =F65*L65 | O65: =P65*(1+Q65)+R65+S65+T65 | P65: 3600 | Q65: 0 | R65: 1000 | S65: 1200 | T65: 45 | U65: =F65*O65
A66: 51 | B66: 30701003002 | C66: 风管机 | D66: 1.名称：超薄风管式室内机 FF36 2.规格：制冷量3.6kW 制冷功率50W 制热量4.5kW 制热功率50W 风量550m3/h 运转噪音≤29dB(A) 3.安装方式：吊装 4.其他：包括但不限于满足图纸、招标文件、规范及验收要求等一切相关费用 | E66: 台 | F66: 2 | G66: =R66*$R$3 | H66: =P66*(1+Q66)*$P$3+S66*$S$3 | I66: =T66*$T$3 | J66: =(G66+H66+I66)*$J$3 | K66: =(G66+H66+I66+J66)*$K$3 | L66: =G66+H66+I66+J66+K66 | M66: =F66*L66 | O66: =P66*(1+Q66)+R66+S66+T66 | P66: 3600 | Q66: 0 | R66: 1000 | S66: 1200 | T66: 45 | U66: =F66*O66
A67: 52 | B67: 30701003003 | C67: 风管机 | D67: 1.名称：超薄风管式室内机 FF45 2.规格：制冷量4.5kW 制冷功率60W 制热量5.0kW 制热功率60W 风量800m3/h 运转噪音≤30dB(A) 3.安装方式：吊装 4.其他：包括但不限于满足图纸、招标文件、规范及验收要求等一切相关费用 | E67: 台 | F67: 1 | G67: =R67*$R$3 | H67: =P67*(1+Q67)*$P$3+S67*$S$3 | I67: =T67*$T$3 | J67: =(G67+H67+I67)*$J$3 | K67: =(G67+H67+I67+J67)*$K$3 | L67: =G67+H67+I67+J67+K67 | M67: =F67*L67 | O67: =P67*(1+Q67)+R67+S67+T67 | P67: 3600 | Q67: 0 | R67: 1000 | S67: 1200 | T67: 45 | U67: =F67*O67
A68: 53 | B68: 30701003004 | C68: 风管机 | D68: 1.名称：超薄风管式室内机 FF56 2.规格：制冷量5.6kW 制冷功率60W 制热量6.3kW 制热功率60W 风量850m3/h 运转噪音≤33dB(A) 3.安装方式：吊装 4.其他：包括但不限于满足图纸、招标文件、规范及验收要求等一切相关费用 | E68: 台 | F68: 2 | G68: =R68*$R$3 | H68: =P68*(1+Q68)*$P$3+S68*$S$3 | I68: =T68*$T$3 | J68: =(G68+H68+I68)*$J$3 | K68: =(G68+H68+I68+J68)*$K$3 | L68: =G68+H68+I68+J68+K68 | M68: =F68*L68 | O68: =P68*(1+Q68)+R68+S68+T68 | P68: 3600 | Q68: 0 | R68: 1000 | S68: 1200 | T68: 45 | U68: =F68*O68
A69: 54 | B69: 30701003005 | C69: 多联式室外机 | D69: 1.名称：多联式室外机 SWJ-224 2.规格：制冷量24.4kW 制冷功率6300W 制热量24.5kW 制热功率6000W 风量9500m3/h 运转噪音≤60dB(A) 3.安装方式：落地 4.其他：包括但不限于满足图纸、招标文件、规范及验收要求等一切相关费用 | E69: 台 | F69: 1 | G69: =R69*$R$3 | H69: =P69*(1+Q69)*$P$3+S69*$S$3 | I69: =T69*$T$3 | J69: =(G69+H69+I69)*$J$3 | K69: =(G69+H69+I69+J69)*$K$3 | L69: =G69+H69+I69+J69+K69 | M69: =F69*L69 | O69: =P69*(1+Q69)+R69+S69+T69 | P69: 12000 | Q69: 0 | R69: 732.5 | S69: 600 | T69: 25 | U69: =F69*O69
A70: 55 | B70: 30413013008 | C70: 空调温控面板 | D70: 1.名称：空调温控面板 2.规格：86*86mm 3.安装方式：暗装 4.其他：包括但不限于满足图纸、招标文件、规范及验收要求等一切相关费用 | E70: 套 | F70: 6 | G70: =R70*$R$3 | H70: =P70*(1+Q70)*$P$3+S70*$S$3 | I70: =T70*$T$3 | J70: =(G70+H70+I70)*$J$3 | K70: =(G70+H70+I70+J70)*$K$3 | L70: =G70+H70+I70+J70+K70 | M70: =F70*L70 | O70: =P70*(1+Q70)+R70+S70+T70 | P70: ='架空层安装工程'!P33 | Q70: ='架空层安装工程'!Q33 | R70: ='架空层安装工程'!R33 | S70: ='架空层安装工程'!S33 | T70: ='架空层安装工程'!T33 | U70: =F70*O70
C71: 风管 | O71: =P71*(1+Q71)+R71+S71+T71 | U71: =F71*O71
A72: 56 | B72: 30702001001 | C72: 碳钢通风管道 | D72: 1.名称：矩形风管 2.材质：镀锌薄钢板 3.厚度：0.6mm 4.长边：≤1000mm 5.其他：包括但不限于满足图纸、招标文件、规范及验收要求等一切相关费用 | E72: m2 | F72: 3.71 | G72: =R72*$R$3 | H72: =P72*(1+Q72)*$P$3+S72*$S$3 | I72: =T72*$T$3 | J72: =(G72+H72+I72)*$J$3 | K72: =(G72+H72+I72+J72)*$K$3 | L72: =G72+H72+I72+J72+K72 | M72: =F72*L72 | O72: =P72*(1+Q72)+R72+S72+T72 | P72: ='架空层安装工程'!P40 | Q72: ='架空层安装工程'!Q40 | R72: ='架空层安装工程'!R40 | S72: ='架空层安装工程'!S40 | T72: ='架空层安装工程'!T40 | U72: =F72*O72
A73: 57 | B73: 30703019001 | C73: 柔性接口 | D73: 1.名称：帆布软接口 2.材质：帆布 3.厚度：满足验收要求 4.其他：包括但不限于满足图纸、招标文件、规范及验收要求等一切相关费用 | E73: m2 | F73: 1.82 | G73: =R73*$R$3 | H73: =P73*(1+Q73)*$P$3+S73*$S$3 | I73: =T73*$T$3 | J73: =(G73+H73+I73)*$J$3 | K73: =(G73+H73+I73+J73)*$K$3 | L73: =G73+H73+I73+J73+K73 | M73: =F73*L73 | O73: =P73*(1+Q73)+R73+S73+T73 | P73: ='架空层安装工程'!P43 | Q73: ='架空层安装工程'!Q43 | R73: ='架空层安装工程'!R43 | S73: ='架空层安装工程'!S43 | T73: ='架空层安装工程'!T43 | U73: =F73*O73
A74: 58 | B74: 31301005001 | C74: 风管支架刷油 | D74: 1.名称：风管支架刷油 2.按图纸及规范要求 3.其他：包括但不限于以上内容，综合考虑按图纸、招标文件和规范要求而实施、完成这项工程的一切有关费用 | E74: kg | F74: 13.48 | G74: =R74*$R$3 | H74: =P74*(1+Q74)*$P$3+S74*$S$3 | I74: =T74*$T$3 | J74: =(G74+H74+I74)*$J$3 | K74: =(G74+H74+I74+J74)*$K$3 | L74: =G74+H74+I74+J74+K74 | M74: =F74*L74 | O74: =P74*(1+Q74)+R74+S74+T74 | P74: ='架空层安装工程'!P44 | Q74: ='架空层安装工程'!Q44 | R74: ='架空层安装工程'!R44 | S74: ='架空层安装工程'!S44 | T74: ='架空层安装工程'!T44 | U74: =F74*O74
A75: 59 | B75: 31208003001 | C75: 通风管道绝热 | D75: 1.名称：空调风管保温 2.材质：难燃级B1级橡塑保温材料，不燃A级铝箔贴面，湿阻因子≥10000，符合国家GB8624-2012中的管状绝热材料B标准 3.厚度：20mm 4.其他：包括但不限于满足图纸、招标文件、规范及验收要求等一切相关费用 | E75: m2 | F75: 3.71 | G75: =R75*$R$3 | H75: =P75*(1+Q75)*$P$3+S75*$S$3 | I75: =T75*$T$3 | J75: =(G75+H75+I75)*$J$3 | K75: =(G75+H75+I75+J75)*$K$3 | L75: =G75+H75+I75+J75+K75 | M75: =F75*L75 | O75: =P75*(1+Q75)+R75+S75+T75 | P75: ='架空层安装工程'!P45 | Q75: ='架空层安装工程'!Q45 | R75: ='架空层安装工程'!R45 | S75: ='架空层安装工程'!S45 | T75: ='架空层安装工程'!T45 | U75: =F75*O75
A76: 60 | B76: 30704001001 | C76: 通风工程检测、调试 | D76: 1.名称：风管漏光试验、漏风试验 | E76: 系统 | F76: 1 | G76: =R76*$R$3 | H76: =P76*(1+Q76)*$P$3+S76*$S$3 | I76: =T76*$T$3 | J76: =(G76+H76+I76)*$J$3 | K76: =(G76+H76+I76+J76)*$K$3 | L76: =G76+H76+I76+J76+K76 | M76: =F76*L76 | O76: =P76*(1+Q76)+R76+S76+T76 | P76: ='架空层安装工程'!P46 | Q76: ='架空层安装工程'!Q46 | R76: ='架空层安装工程'!R46 | S76: ='架空层安装工程'!S46 | T76: ='架空层安装工程'!T46 | U76: =F76*O76
C77: 水管 | O77: =P77*(1+Q77)+R77+S77+T77 | U77: =F77*O77
A78: 61 | B78: 31001005001 | C78: 铜管 | D78: 1.名称：紫铜管 2.规格：φ6.4 3.厚度：0.8mm 4.连接方式：钎焊连结 5.其他：包括但不限于满足图纸、招标文件、规范及验收要求等一切相关费用 | E78: m | F78: 9.18 | G78: =R78*$R$3 | H78: =P78*(1+Q78)*$P$3+S78*$S$3 | I78: =T78*$T$3 | J78: =(G78+H78+I78)*$J$3 | K78: =(G78+H78+I78+J78)*$K$3 | L78: =G78+H78+I78+J78+K78 | M78: =F78*L78 | O78: =P78*(1+Q78)+R78+S78+T78 | P78: ='架空层安装工程'!P48 | Q78: ='架空层安装工程'!Q48 | R78: ='架空层安装工程'!R48 | S78: ='架空层安装工程'!S48 | T78: ='架空层安装工程'!T48 | U78: =F78*O78
A79: 62 | B79: 31001005002 | C79: 铜管 | D79: 1.名称：紫铜管 2.规格：φ9.5 3.厚度：0.8mm 4.连接方式：钎焊连结 5.其他：包括但不限于满足图纸、招标文件、规范及验收要求等一切相关费用 | E79: m | F79: 15.88 | G79: =R79*$R$3 | H79: =P79*(1+Q79)*$P$3+S79*$S$3 | I79: =T79*$T$3 | J79: =(G79+H79+I79)*$J$3 | K79: =(G79+H79+I79+J79)*$K$3 | L79: =G79+H79+I79+J79+K79 | M79: =F79*L79 | O79: =P79*(1+Q79)+R79+S79+T79 | P79: ='架空层安装工程'!P49 | Q79: ='架空层安装工程'!Q49 | R79: ='架空层安装工程'!R49 | S79: ='架空层安装工程'!S49 | T79: ='架空层安装工程'!T49 | U79: =F79*O79
A80: 63 | B80: 31001005003 | C80: 铜管 | D80: 1.名称：紫铜管 2.规格：φ12.7 3.厚度：0.8mm 4.连接方式：钎焊连结 5.其他：包括但不限于满足图纸、招标文件、规范及验收要求等一切相关费用 | E80: m | F80: 9.18 | G80: =R80*$R$3 | H80: =P80*(1+Q80)*$P$3+S80*$S$3 | I80: =T80*$T$3 | J80: =(G80+H80+I80)*$J$3 | K80: =(G80+H80+I80+J80)*$K$3 | L80: =G80+H80+I80+J80+K80 | M80: =F80*L80 | O80: =P80*(1+Q80)+R80+S80+T80 | P80: ='架空层安装工程'!P50 | Q80: ='架空层安装工程'!Q50 | R80: ='架空层安装工程'!R50 | S80: ='架空层安装工程'!S50 | T80: ='架空层安装工程'!T50 | U80: =F80*O80
A81: 64 | B81: 31001005004 | C81: 铜管 | D81: 1.名称：紫铜管 2.规格：φ15.9 3.厚度：1.0mm 4.连接方式：钎焊连结 5.其他：包括但不限于满足图纸、招标文件、规范及验收要求等一切相关费用 | E81: m | F81: 15.88 | G81: =R81*$R$3 | H81: =P81*(1+Q81)*$P$3+S81*$S$3 | I81: =T81*$T$3 | J81: =(G81+H81+I81)*$J$3 | K81: =(G81+H81+I81+J81)*$K$3 | L81: =G81+H81+I81+J81+K81 | M81: =F81*L81 | O81: =P81*(1+Q81)+R81+S81+T81 | P81: ='架空层安装工程'!P51 | Q81: ='架空层安装工程'!Q51 | R81: ='架空层安装工程'!R51 | S81: ='架空层安装工程'!S51 | T81: ='架空层安装工程'!T51 | U81: =F81*O81
A82: 65 | B82: 31002001001 | C82: 分歧器 | D82: 1.名称：分歧器 2.规格：公称直径20mm以内 3.其他：包括但不限于满足图纸、招标文件、规范及验收要求等一切相关费用 | E82: 个 | F82: 5 | G82: =R82*$R$3 | H82: =P82*(1+Q82)*$P$3+S82*$S$3 | I82: =T82*$T$3 | J82: =(G82+H82+I82)*$J$3 | K82: =(G82+H82+I82+J82)*$K$3 | L82: =G82+H82+I82+J82+K82 | M82: =F82*L82 | O82: =P82*(1+Q82)+R82+S82+T82 | P82: ='架空层安装工程'!P54 | Q82: ='架空层安装工程'!Q54 | R82: ='架空层安装工程'!R54 | S82: ='架空层安装工程'!S54 | T82: ='架空层安装工程'!T54 | U82: =F82*O82
A83: 66 | B83: 31001008010 | C83: 塑料管 | D83: 1.名称：UPVC管 2.规格：DN20 3.介质：冷凝水 4.连接方式：粘接 5.其他：包括但不限于满足图纸、招标文件、规范及验收要求等一切相关费用 | E83: m | F83: 15.87 | G83: =R83*$R$3 | H83: =P83*(1+Q83)*$P$3+S83*$S$3 | I83: =T83*$T$3 | J83: =(G83+H83+I83)*$J$3 | K83: =(G83+H83+I83+J83)*$K$3 | L83: =G83+H83+I83+J83+K83 | M83: =F83*L83 | O83: =P83*(1+Q83)+R83+S83+T83 | P83: 4.5 | Q83: 0 | R83: 18 | S83: 0.26 | T83: 0.04 | U83: =F83*O83
A84: 67 | B84: 31001008011 | C84: 塑料管 | D84: 1.名称：UPVC管 2.规格：DN25 3.介质：冷凝水 4.连接方式：粘接 5.其他：包括但不限于满足图纸、招标文件、规范及验收要求等一切相关费用 | E84: m | F84: 3.81 | G84: =R84*$R$3 | H84: =P84*(1+Q84)*$P$3+S84*$S$3 | I84: =T84*$T$3 | J84: =(G84+H84+I84)*$J$3 | K84: =(G84+H84+I84+J84)*$K$3 | L84: =G84+H84+I84+J84+K84 | M84: =F84*L84 | O84: =P84*(1+Q84)+R84+S84+T84 | P84: ='架空层安装工程'!P55 | Q84: ='架空层安装工程'!Q55 | R84: ='架空层安装工程'!R55 | S84: ='架空层安装工程'!S55 | T84: ='架空层安装工程'!T55 | U84: =F84*O84
A85: 68 | B85: 31208002003 | C85: 其他管道绝热 | D85: 1.名称：冷媒管保温 2.材质：难燃B1级橡塑 3.厚度：20mm 4.其他：包括但不限于满足图纸、招标文件、规范及验收要求等一切相关费用 | E85: m3 | F85: 0.11 | G85: =R85*$R$3 | H85: =P85*(1+Q85)*$P$3+S85*$S$3 | I85: =T85*$T$3 | J85: =(G85+H85+I85)*$J$3 | K85: =(G85+H85+I85+J85)*$K$3 | L85: =G85+H85+I85+J85+K85 | M85: =F85*L85 | O85: =P85*(1+Q85)+R85+S85+T85 | P85: ='架空层安装工程'!P58 | Q85: ='架空层安装工程'!Q58 | R85: ='架空层安装工程'!R58 | S85: ='架空层安装工程'!S58 | T85: ='架空层安装工程'!T58 | U85: =F85*O85
A86: 69 | B86: 31208002004 | C86: 其他管道绝热 | D86: 1.名称：冷凝管保温 2.材质：难燃B1级橡塑 3.厚度：13mm 4.其他：包括但不限于满足图纸、招标文件、规范及验收要求等一切相关费用 | E86: m3 | F86: 0.03 | G86: =R86*$R$3 | H86: =P86*(1+Q86)*$P$3+S86*$S$3 | I86: =T86*$T$3 | J86: =(G86+H86+I86)*$J$3 | K86: =(G86+H86+I86+J86)*$K$3 | L86: =G86+H86+I86+J86+K86 | M86: =F86*L86 | O86: =P86*(1+Q86)+R86+S86+T86 | P86: ='架空层安装工程'!P59 | Q86: ='架空层安装工程'!Q59 | R86: ='架空层安装工程'!R59 | S86: ='架空层安装工程'!S59 | T86: ='架空层安装工程'!T59 | U86: =F86*O86
C87: 119户型 | O87: =P87*(1+Q87)+R87+S87+T87 | U87: =F87*O87
C88: 电气工程 | O88: =P88*(1+Q88)+R88+S88+T88 | U88: =F88*O88
C89: 灯具、电器 | O89: =P89*(1+Q89)+R89+S89+T89 | U89: =F89*O89
A90: 70 | B90: 30413002009 | C90: R1 LED嵌入式射灯 | D90: 1.名称：R1 LED嵌入式射灯 2.规格：12W、3000K、光束角36° 3.安装方式：嵌装 4.其他：包括但不限于满足图纸、招标文件、规范及验收要求等一切相关费用 | E90: 套 | F90: 24 | G90: =R90*$R$3 | H90: =P90*(1+Q90)*$P$3+S90*$S$3 | I90: =T90*$T$3 | J90: =(G90+H90+I90)*$J$3 | K90: =(G90+H90+I90+J90)*$K$3 | L90: =G90+H90+I90+J90+K90 | M90: =F90*L90 | O90: =P90*(1+Q90)+R90+S90+T90 | P90: =P8 | Q90: =Q8 | R90: =R8 | S90: =S8 | T90: =T8 | U90: =F90*O90
A91: 71 | B91: 30413002010 | C91: R2 LED嵌入式可调角射灯 | D91: 1.名称：R2 LED嵌入式可调角射灯 2.规格：12W、3000K、光束角24° 3.安装方式：嵌装 4.其他：包括但不限于满足图纸、招标文件、规范及验收要求等一切相关费用 | E91: 套 | F91: 26 | G91: =R91*$R$3 | H91: =P91*(1+Q91)*$P$3+S91*$S$3 | I91: =T91*$T$3 | J91: =(G91+H91+I91)*$J$3 | K91: =(G91+H91+I91+J91)*$K$3 | L91: =G91+H91+I91+J91+K91 | M91: =F91*L91 | O91: =P91*(1+Q91)+R91+S91+T91 | P91: =P9 | Q91: =Q9 | R91: =R9 | S91: =S9 | T91: =T9 | U91: =F91*O91
A92: 72 | B92: 30413002011 | C92: R5 明装单头射灯 | D92: 1.名称：R5 明装单头射灯 2.规格：12W、3000K、光束角36° 3.安装方式：嵌装 4.其他：包括但不限于满足图纸、招标文件、规范及验收要求等一切相关费用 | E92: 套 | F92: 5 | G92: =R92*$R$3 | H92: =P92*(1+Q92)*$P$3+S92*$S$3 | I92: =T92*$T$3 | J92: =(G92+H92+I92)*$J$3 | K92: =(G92+H92+I92+J92)*$K$3 | L92: =G92+H92+I92+J92+K92 | M92: =F92*L92 | O92: =P92*(1+Q92)+R92+S92+T92 | P92: =P12 | Q92: =Q12 | R92: =R12 | S92: =S12 | T92: =T12 | U92: =F92*O92
A93: 73 | B93: 30413002012 | C93: L1 LED灯条（天花） | D93: 1.名称：L1 LED灯条（天花） 2.规格：14W/米,3000K,120珠/米 3.安装方式：天花 4.其他：包括但不限于满足图纸、招标文件、规范及验收要求等一切相关费用 | E93: m | F93: 51.35 | G93: =R93*$R$3 | H93: =P93*(1+Q93)*$P$3+S93*$S$3 | I93: =T93*$T$3 | J93: =(G93+H93+I93)*$J$3 | K93: =(G93+H93+I93+J93)*$K$3 | L93: =G93+H93+I93+J93+K93 | M93: =F93*L93 | O93: =P93*(1+Q93)+R93+S93+T93 | P93: =P13 | Q93: =Q13 | R93: =R13 | S93: =S13 | T93: =T13 | U93: =F93*O93
A94: 74 | B94: 30413002013 | C94: L3 LED灯条（柜子） | D94: 1.名称：L3 LED灯条（柜子） 2.规格：4W/米,3000K,120珠/米 3.安装方式：天花 4.其他：包括但不限于满足图纸、招标文件、规范及验收要求等一切相关费用 | E94: m | F94: 45.73 | G94: =R94*$R$3 | H94: =P94*(1+Q94)*$P$3+S94*$S$3 | I94: =T94*$T$3 | J94: =(G94+H94+I94)*$J$3 | K94: =(G94+H94+I94+J94)*$K$3 | L94: =G94+H94+I94+J94+K94 | M94: =F94*L94 | O94: =P94*(1+Q94)+R94+S94+T94 | P94: =P15 | Q94: =Q15 | R94: =R15 | S94: =S15 | T94: =T15 | U94: =F94*O94
A95: 75 | B95: 30413009002 | C95: LED 灯带驱动电源 | D95: 1.名称：LED 灯带驱动电源 2.规格：60W 工作电压：220V 输出电压：24V 3.尺寸：L140*W45*H29mm 4.其他：包括但不限于满足图纸、招标文件、规范及验收要求等一切相关费用 | E95: 个 | F95: 19 | G95: =R95*$R$3 | H95: =P95*(1+Q95)*$P$3+S95*$S$3 | I95: =T95*$T$3 | J95: =(G95+H95+I95)*$J$3 | K95: =(G95+H95+I95+J95)*$K$3 | L95: =G95+H95+I95+J95+K95 | M95: =F95*L95 | O95: =P95*(1+Q95)+R95+S95+T95 | P95: ='架空层安装工程'!P10 | Q95: ='架空层安装工程'!Q10 | R95: ='架空层安装工程'!R10 | S95: ='架空层安装工程'!S10 | T95: ='架空层安装工程'!T10 | U95: =F95*O95
A96: 76 | B96: 30405015003 | C96: 线型凉霸及开关 | D96: 1.名称：线型凉霸及开关 2.规格：34W 3.尺寸：详见物料表 4.其他：包括但不限于满足图纸、招标文件、规范及验收要求等一切相关费用 | E96: 台 | F96: 1 | G96: =R96*$R$3 | H96: =P96*(1+Q96)*$P$3+S96*$S$3 | I96: =T96*$T$3 | J96: =(G96+H96+I96)*$J$3 | K96: =(G96+H96+I96+J96)*$K$3 | L96: =G96+H96+I96+J96+K96 | M96: =F96*L96 | O96: =P96*(1+Q96)+R96+S96+T96 | P96: =P17 | Q96: =Q17 | R96: =R17 | S96: =S17 | T96: =T17 | U96: =F96*O96
A97: 77 | B97: 30405015004 | C97: 暖风机及开关 | D97: 1.名称：暖风机及开关 2.规格：40W 3.尺寸：详见物料表 4.其他：包括但不限于满足图纸、招标文件、规范及验收要求等一切相关费用 | E97: 台 | F97: 3 | G97: =R97*$R$3 | H97: =P97*(1+Q97)*$P$3+S97*$S$3 | I97: =T97*$T$3 | J97: =(G97+H97+I97)*$J$3 | K97: =(G97+H97+I97+J97)*$K$3 | L97: =G97+H97+I97+J97+K97 | M97: =F97*L97 | O97: =P97*(1+Q97)+R97+S97+T97 | P97: 550 | Q97: 0 | R97: 30 | S97: 3 | T97: 0 | U97: =F97*O97
A98: 78 | B98: 30405015005 | C98: 排气扇及开关 | D98: 1.名称：排气扇及开关 2.规格：- 3.尺寸：详见物料表 4.其他：包括但不限于满足图纸、招标文件、规范及验收要求等一切相关费用 | E98: 台 | F98: 3 | G98: =R98*$R$3 | H98: =P98*(1+Q98)*$P$3+S98*$S$3 | I98: =T98*$T$3 | J98: =(G98+H98+I98)*$J$3 | K98: =(G98+H98+I98+J98)*$K$3 | L98: =G98+H98+I98+J98+K98 | M98: =F98*L98 | O98: =P98*(1+Q98)+R98+S98+T98 | P98: 155 | Q98: 0 | R98: 21 | S98: 2 | T98: 0 | U98: =F98*O98
A99: 79 | B99: 30405017002 | C99: 洗碗机 | D99: 1.名称：洗碗机 2.规格：- 3.尺寸：详见物料表 4.其他：包括但不限于满足图纸、招标文件、规范及验收要求等一切相关费用 | E99: 台 | F99: 1 | G99: =R99*$R$3 | H99: =P99*(1+Q99)*$P$3+S99*$S$3 | I99: =T99*$T$3 | J99: =(G99+H99+I99)*$J$3 | K99: =(G99+H99+I99+J99)*$K$3 | L99: =G99+H99+I99+J99+K99 | M99: =F99*L99 | O99: =P99*(1+Q99)+R99+S99+T99 | P99: =P19 | Q99: =Q19 | R99: =R19 | S99: =S19 | T99: =T19 | U99: =F99*O99
C100: 开关插座 | O100: =P100*(1+Q100)+R100+S100+T100 | U100: =F100*O100
...

Sheet 公共区域安装工程
A1: 公共区域安装工程工程量清单 | O1: 成本单价组成（投标人填写）
A2: 序号 | B2: 编码 | C2: 项目名称 | D2: 项目特征 | E2: 单位 | F2: 工程量 | G2: 人工费 | H2: 材料费 | I2: 机械费 | J2: 管理费 | K2: 利润 | L2: 不含税单价 | M2: 合价 | O2: 单价合计 | P2: 主材费 | Q2: 主材损耗率 | R2: 人工费 | S2: 辅材费 | T2: 机械费 | U2: 合计
J3: 0 | K3: 0 | P3: =架空层安装工程!$P$3 | R3: =架空层安装工程!$R$3 | S3: =架空层安装工程!$S$3 | T3: =架空层安装工程!$T$3
B4: 单位工程
C5: 批量公区
A6: 1 | B6: 30413002001 | C6: LA-01 嵌入式筒灯 | D6: 1.名称：LA-01 嵌入式筒灯 2.规格：12W 4000K 灯体尺寸Φ118*50mm 3.安装方式：嵌装 4.其他：包括但不限于满足图纸、招标文件、规范及验收要求等一切相关费用 | E6: 套 | F6: 65 | G6: =R6*$R$3 | H6: =P6*(1+Q6)*$P$3+S6*$S$3 | I6: =T6*$T$3 | J6: =(G6+H6+I6)*$J$3 | K6: =(G6+H6+I6+J6)*$K$3 | L6: =G6+H6+I6+J6+K6 | M6: =F6*L6 | O6: =P6*(1+Q6)+R6+S6+T6 | P6: 70 | Q6: 0 | R6: 20 | S6: 6 | T6: 0 | U6: =F6*O6
A7: 2 | B7: 30413002002 | C7: LA-02 射灯 | D7: 1.名称：LA-02 射灯 2.规格：12W 4000K 灯体尺寸Φ118*50mm 3.安装方式：嵌装 4.其他：包括但不限于满足图纸、招标文件、规范及验收要求等一切相关费用 | E7: 套 | F7: 61 | G7: =R7*$R$3 | H7: =P7*(1+Q7)*$P$3+S7*$S$3 | I7: =T7*$T$3 | J7: =(G7+H7+I7)*$J$3 | K7: =(G7+H7+I7+J7)*$K$3 | L7: =G7+H7+I7+J7+K7 | M7: =F7*L7 | O7: =P7*(1+Q7)+R7+S7+T7 | P7: 120 | Q7: 0 | R7: 18 | S7: 3.5 | T7: 0.5 | U7: =F7*O7
A8: 3 | B8: 30413002003 | C8: LA-04 红外人体感应筒灯 | D8: 1.名称：LA-04 红外人体感应筒灯 2.规格：9W 4000K 灯体尺寸Φ118*50mm 3.安装方式：嵌装 4.其他：包括但不限于满足图纸、招标文件、规范及验收要求等一切相关费用 | E8: 套 | F8: 10 | G8: =R8*$R$3 | H8: =P8*(1+Q8)*$P$3+S8*$S$3 | I8: =T8*$T$3 | J8: =(G8+H8+I8)*$J$3 | K8: =(G8+H8+I8+J8)*$K$3 | L8: =G8+H8+I8+J8+K8 | M8: =F8*L8 | O8: =P8*(1+Q8)+R8+S8+T8 | P8: 70 | Q8: 0 | R8: 20 | S8: 6 | T8: 0 | U8: =F8*O8
A9: 4 | B9: 30413002004 | C9: LA-05 明装红外人体感应筒灯 | D9: 1.名称：LA-05 明装红外人体感应筒灯 2.规格：9W 4000K 灯体尺寸Φ150*100mm 3.安装方式：明装 4.其他：包括但不限于满足图纸、招标文件、规范及验收要求等一切相关费用 | E9: 套 | F9: 100 | G9: =R9*$R$3 | H9: =P9*(1+Q9)*$P$3+S9*$S$3 | I9: =T9*$T$3 | J9: =(G9+H9+I9)*$J$3 | K9: =(G9+H9+I9+J9)*$K$3 | L9: =G9+H9+I9+J9+K9 | M9: =F9*L9 | O9: =P9*(1+Q9)+R9+S9+T9 | P9: 70 | Q9: 0 | R9: 20 | S9: 6 | T9: 0 | U9: =F9*O9
A10: 5 | B10: 30413002005 | C10: LA-06 LED明装筒灯 | D10: 1.名称：LA-06 LED明装筒灯 2.规格：9W 4000K 灯体尺寸Φ150*100mm 3.安装方式：明装 4.其他：包括但不限于满足图纸、招标文件、规范及验收要求等一切相关费用 | E10: 套 | F10: 117 | G10: =R10*$R$3 | H10: =P10*(1+Q10)*$P$3+S10*$S$3 | I10: =T10*$T$3 | J10: =(G10+H10+I10)*$J$3 | K10: =(G10+H10+I10+J10)*$K$3 | L10: =G10+H10+I10+J10+K10 | M10: =F10*L10 | O10: =P10*(1+Q10)+R10+S10+T10 | P10: ='架空层安装工程'!P8 | Q10: ='架空层安装工程'!Q8 | R10: ='架空层安装工程'!R8 | S10: ='架空层安装工程'!S8 | T10: ='架空层安装工程'!T8 | U10: =F10*O10
A11: 6 | B11: 30413002006 | C11: LA-07 LED明装筒灯(带红外感应) | D11: 1.名称：LA-07 LED明装筒灯(带红外感应) 2.规格：9W 4000K 灯体尺寸Φ150*100mm 3.安装方式：明装 4.其他：包括但不限于满足图纸、招标文件、规范及验收要求等一切相关费用 | E11: 套 | F11: 233 | G11: =R11*$R$3 | H11: =P11*(1+Q11)*$P$3+S11*$S$3 | I11: =T11*$T$3 | J11: =(G11+H11+I11)*$J$3 | K11: =(G11+H11+I11+J11)*$K$3 | L11: =G11+H11+I11+J11+K11 | M11: =F11*L11 | O11: =P11*(1+Q11)+R11+S11+T11 | P11: 70 | Q11: 0 | R11: 20 | S11: 6 | T11: 0 | U11: =F11*O11
A12: 7 | B12: 30413002007 | C12: LA-03 LED灯带 | D12: 1.名称：LA-03 LED灯带 2.规格：8W/米 4000K L170*W170*H25mm 3.安装方式：天花 4.其他：包括但不限于满足图纸、招标文件、规范及验收要求等一切相关费用 | E12: m | F12: 1471 | G12: =R12*$R$3 | H12: =P12*(1+Q12)*$P$3+S12*$S$3 | I12: =T12*$T$3 | J12: =(G12+H12+I12)*$J$3 | K12: =(G12+H12+I12+J12)*$K$3 | L12: =G12+H12+I12+J12+K12 | M12: =F12*L12 | O12: =P12*(1+Q12)+R12+S12+T12 | P12: 20.4 | Q12: 0 | R12: 12.5 | S12: 0.41 | T12: 0 | U12: =F12*O12
A13: 8 | B13: 30413009001 | C13: LED 灯带驱动电源 | D13: 1.名称：LED 灯带驱动电源 2.规格：60W 工作电压：220V 输出电压：24V 3.尺寸：L140*W45*H29mm 4.其他：包括但不限于满足图纸、招标文件、规范及验收要求等一切相关费用 | E13: 个 | F13: 2245 | G13: =R13*$R$3 | H13: =P13*(1+Q13)*$P$3+S13*$S$3 | I13: =T13*$T$3 | J13: =(G13+H13+I13)*$J$3 | K13: =(G13+H13+I13+J13)*$K$3 | L13: =G13+H13+I13+J13+K13 | M13: =F13*L13 | O13: =P13*(1+Q13)+R13+S13+T13 | P13: ='架空层安装工程'!P10 | Q13: ='架空层安装工程'!Q10 | R13: ='架空层安装工程'!R10 | S13: ='架空层安装工程'!S10 | T13: ='架空层安装工程'!T10 | U13: =F13*O13
A14: 9 | B14: 30413013001 | C14: 照明开关 | D14: 1.名称：单联单控开关 2.规格：86*86mm 3.安装方式：暗装 4.其他：包括但不限于满足图纸、招标文件、规范及验收要求等一切相关费用 | E14: 套 | F14: 117 | G14: =R14*$R$3 | H14: =P14*(1+Q14)*$P$3+S14*$S$3 | I14: =T14*$T$3 | J14: =(G14+H14+I14)*$J$3 | K14: =(G14+H14+I14+J14)*$K$3 | L14: =G14+H14+I14+J14+K14 | M14: =F14*L14 | O14: =P14*(1+Q14)+R14+S14+T14 | P14: 14.62 | Q14: 0 | R14: 6.31 | S14: 1.12 | T14: 0 | U14: =F14*O14
A15: 10 | B15: 30413013003 | C15: 照明开关 | D15: 1.名称：三联单控开关 2.规格：86*86mm 3.安装方式：暗装 4.其他：包括但不限于满足图纸、招标文件、规范及验收要求等一切相关费用 | E15: 套 | F15: 4 | G15: =R15*$R$3 | H15: =P15*(1+Q15)*$P$3+S15*$S$3 | I15: =T15*$T$3 | J15: =(G15+H15+I15)*$J$3 | K15: =(G15+H15+I15+J15)*$K$3 | L15: =G15+H15+I15+J15+K15 | M15: =F15*L15 | O15: =P15*(1+Q15)+R15+S15+T15 | P15: 20 | Q15: 0 | R15: 12 | S15: 1.5 | T15: 0 | U15: =F15*O15
A16: 11 | B16: 30413014001 | C16: 插座 | D16: 1.名称：五孔插座 2.规格：86*86mm 3.安装方式：暗装 4.其他：包括但不限于满足图纸、招标文件、规范及验收要求等一切相关费用 | E16: 套 | F16: 2 | G16: =R16*$R$3 | H16: =P16*(1+Q16)*$P$3+S16*$S$3 | I16: =T16*$T$3 | J16: =(G16+H16+I16)*$J$3 | K16: =(G16+H16+I16+J16)*$K$3 | L16: =G16+H16+I16+J16+K16 | M16: =F16*L16 | O16: =P16*(1+Q16)+R16+S16+T16 | P16: 14.62 | Q16: 0 | R16: 6.31 | S16: 1.12 | T16: 0 | U16: =F16*O16
A17: 12 | B17: 30412004001 | C17: 配线 | D17: 1.名称：电气配线 2.型号规格：WDZC-BYJ-2.5 3.安装方式：管内穿线 4.其他：包括但不限于满足图纸、招标文件、规范及验收要求等一切相关费用 | E17: m | F17: 11412 | G17: =R17*$R$3 | H17: =P17*(1+Q17)*$P$3+S17*$S$3 | I17: =T17*$T$3 | J17: =(G17+H17+I17)*$J$3 | K17: =(G17+H17+I17+J17)*$K$3 | L17: =G17+H17+I17+J17+K17 | M17: =F17*L17 | O17: =P17*(1+Q17)+R17+S17+T17 | P17: 2.92 | Q17: 0.02 | R17: 2.2 | S17: 0.21 | T17: 0.02 | U17: =F17*O17
C18: 电梯轿厢
A19: 13 | B19: 30413002008 | C19: 嵌入式筒灯 | D19: 1.名称：嵌入式筒灯 2.规格：- 3.安装方式：嵌装 4.其他：包括但不限于满足图纸、招标文件、规范及验收要求等一切相关费用 | E19: 套 | F19: 8 | G19: =R19*$R$3 | H19: =P19*(1+Q19)*$P$3+S19*$S$3 | I19: =T19*$T$3 | J19: =(G19+H19+I19)*$J$3 | K19: =(G19+H19+I19+J19)*$K$3 | L19: =G19+H19+I19+J19+K19 | M19: =F19*L19 | O19: =P19*(1+Q19)+R19+S19+T19 | P19: 70 | Q19: 0 | R19: 20 | S19: 6 | T19: 0 | U19: =F19*O19
A20: 14 | B20: 30413002009 | C20: LED灯带 | D20: 1.名称：LED灯带 2.规格：8W/米 4000K L170*W170*H25mm 3.安装方式：天花 4.其他：包括但不限于满足图纸、招标文件、规范及验收要求等一切相关费用 | E20: m | F20: 39.68 | G20: =R20*$R$3 | H20: =P20*(1+Q20)*$P$3+S20*$S$3 | I20: =T20*$T$3 | J20: =(G20+H20+I20)*$J$3 | K20: =(G20+H20+I20+J20)*$K$3 | L20: =G20+H20+I20+J20+K20 | M20: =F20*L20 | O20: =P20*(1+Q20)+R20+S20+T20 | P20: 20.4 | Q20: 0 | R20: 12.5 | S20: 0.41 | T20: 0 | U20: =F20*O20
A21: 15 | B21: 30413009002 | C21: LED 灯带驱动电源 | D21: 1.名称：LED 灯带驱动电源 2.规格：60W 工作电压：220V 输出电压：24V 3.尺寸：L140*W45*H29mm 4.其他：包括但不限于满足图纸、招标文件、规范及验收要求等一切相关费用 | E21: 个 | F21: 8 | G21: =R21*$R$3 | H21: =P21*(1+Q21)*$P$3+S21*$S$3 | I21: =T21*$T$3 | J21: =(G21+H21+I21)*$J$3 | K21: =(G21+H21+I21+J21)*$K$3 | L21: =G21+H21+I21+J21+K21 | M21: =F21*L21 | O21: =P21*(1+Q21)+R21+S21+T21 | P21: ='架空层安装工程'!P10 | Q21: ='架空层安装工程'!Q10 | R21: ='架空层安装工程'!R10 | S21: ='架空层安装工程'!S10 | T21: ='架空层安装工程'!T10 | U21: =F21*O21
A22: 16 | B22: 30412004002 | C22: 配线 | D22: 1.名称：电气配线 2.型号规格：BV-2.5 3.安装方式：管内穿线 4.其他：包括但不限于满足图纸、招标文件、规范及验收要求等一切相关费用 | E22: m | F22: 240 | G22: =R22*$R$3 | H22: =P22*(1+Q22)*$P$3+S22*$S$3 | I22: =T22*$T$3 | J22: =(G22+H22+I22)*$J$3 | K22: =(G22+H22+I22+J22)*$K$3 | L22: =G22+H22+I22+J22+K22 | M22: =F22*L22 | O22: =P22*(1+Q22)+R22+S22+T22 | P22: 2.77 | Q22: 0.02 | R22: 2.1 | S22: 0.21 | T22: 0.02 | U22: =F22*O22
B23: 税前合价 | E23: 元 | M23: =SUM(M4:M22)
B24: 税金 | E24: 元 | M24: =M23*0.09
B25: 含税合价 | E25: 元 | M25: =M23+M24

Sheet 户内交标安装工程
A1: 户内交标安装工程工程量清单 | O1: 成本单价组成（投标人填写）
A2: 序号 | B2: 编码 | C2: 项目名称 | D2: 项目特征 | E2: 单位 | F2: 工程量 | G2: 人工费 | H2: 材料费 | I2: 机械费 | J2: 管理费 | K2: 利润 | L2: 不含税单价 | M2: 合价 | O2: 单价合计 | P2: 主材费 | Q2: 主材损耗率 | R2: 人工费 | S2: 辅材费 | T2: 机械费 | U2: 合计
J3: 0 | K3: 0 | P3: =架空层安装工程!$P$3 | R3: =架空层安装工程!$R$3 | S3: =架空层安装工程!$S$3 | T3: =架空层安装工程!$T$3
B4: 单位工程
C5: 电气
A6: 1 | B6: 30413002001 | C6: LA-01 筒灯 | D6: 1.名称：LA-01 筒灯 2.规格：8.5W 4000K 尺寸Φ138*32mm 3.安装方式：嵌装 4.其他：包括但不限于满足图纸、招标文件、规范及验收要求等一切相关费用 | E6: 套 | F6: 730.33333 | G6: =R6*$R$3 | H6: =P6*(1+Q6)*$P$3+S6*$S$3 | I6: =T6*$T$3 | J6: =(G6+H6+I6)*$J$3 | K6: =(G6+H6+I6+J6)*$K$3 | L6: =G6+H6+I6+J6+K6 | M6: =F6*L6 | O6: =P6*(1+Q6)+R6+S6+T6 | P6: 70 | Q6: 0 | R6: 20 | S6: 6 | T6: 0 | U6: =F6*O6
A7: 2 | B7: 30413002002 | C7: LA-02 LED嵌入式射灯 | D7: 1.名称：LA-02 LED嵌入式射灯 2.规格：7.5W 4000K 尺寸Φ85*57mm 3.安装方式：嵌装 4.其他：包括但不限于满足图纸、招标文件、规范及验收要求等一切相关费用 | E7: 套 | F7: 254 | G7: =R7*$R$3 | H7: =P7*(1+Q7)*$P$3+S7*$S$3 | I7: =T7*$T$3 | J7: =(G7+H7+I7)*$J$3 | K7: =(G7+H7+I7+J7)*$K$3 | L7: =G7+H7+I7+J7+K7 | M7: =F7*L7 | O7: =P7*(1+Q7)+R7+S7+T7 | P7: 120 | Q7: 0 | R7: 18 | S7: 3.5 | T7: 0.5 | U7: =F7*O7
A8: 3 | B8: 30413002003 | C8: LA-03 防雾射灯 | D8: 1.名称：LA-03 防雾射灯 2.规格：7W 3500K 尺寸Φ86*86mm 3.安装方式：嵌装 4.其他：包括但不限于满足图纸、招标文件、规范及验收要求等一切相关费用 | E8: 套 | F8: 231 | G8: =R8*$R$3 | H8: =P8*(1+Q8)*$P$3+S8*$S$3 | I8: =T8*$T$3 | J8: =(G8+H8+I8)*$J$3 | K8: =(G8+H8+I8+J8)*$K$3 | L8: =G8+H8+I8+J8+K8 | M8: =F8*L8 | O8: =P8*(1+Q8)+R8+S8+T8 | P8: 120 | Q8: 0 | R8: 18 | S8: 3.5 | T8: 0.5 | U8: =F8*O8
A9: 4 | B9: 30413002004 | C9: LA-05 平板灯300*600 | D9: 1.名称：LA-05 平板灯300*600 2.规格：12W 4000K 尺寸300*600mm 3.安装方式：嵌装 4.其他：包括但不限于满足图纸、招标文件、规范及验收要求等一切相关费用 | E9: 套 | F9: 403.33333 | G9: =R9*$R$3 | H9: =P9*(1+Q9)*$P$3+S9*$S$3 | I9: =T9*$T$3 | J9: =(G9+H9+I9)*$J$3 | K9: =(G9+H9+I9+J9)*$K$3 | L9: =G9+H9+I9+J9+K9 | M9: =F9*L9 | O9: =P9*(1+Q9)+R9+S9+T9 | P9: 125 | Q9: 0 | R9: 38 | S9: 8 | T9: 0 | U9: =F9*O9
A10: 5 | B10: 30413001001 | C10: LA-06 吸顶灯 | D10: 1.名称：LA-06 吸顶灯 2.规格：18W 4000K 尺寸φ330*H48mm 3.安装方式：嵌装 4.其他：包括但不限于满足图纸、招标文件、规范及验收要求等一切相关费用 | E10: 套 | F10: 185 | G10: =R10*$R$3 | H10: =P10*(1+Q10)*$P$3+S10*$S$3 | I10: =T10*$T$3 | J10: =(G10+H10+I10)*$J$3 | K10: =(G10+H10+I10+J10)*$K$3 | L10: =G10+H10+I10+J10+K10 | M10: =F10*L10 | O10: =P10*(1+Q10)+R10+S10+T10 | P10: 60 | Q10: 0 | R10: 10 | S10: 2 | T10: 0 | U10: =F10*O10
A11: 6 | B11: 30413001003 | C11: 普通灯具 | D11: 1.名称：LA-08 LED灯泡+灯座 2.规格：5W 4000K 86*86mm E27螺口 3.安装方式：嵌装 4.其他：包括但不限于满足图纸、招标文件、规范及验收要求等一切相关费用 | E11: 套 | F11: 756.33333 | G11: =R11*$R$3 | H11: =P11*(1+Q11)*$P$3+S11*$S$3 | I11: =T11*$T$3 | J11: =(G11+H11+I11)*$J$3 | K11: =(G11+H11+I11+J11)*$K$3 | L11: =G11+H11+I11+J11+K11 | M11: =F11*L11 | O11: =P11*(1+Q11)+R11+S11+T11 | P11: 48 | Q11: 0 | R11: 18 | S11: 1.5 | T11: 0.2 | U11: =F11*O11
A12: 7 | B12: 30413002005 | C12: LA-04 线条灯 | D12: 1.名称：LA-04 线条灯 2.规格：12W/m 尺寸20*10mm 3.安装方式：吊装 4.其他：包括但不限于满足图纸、招标文件、规范及验收要求等一切相关费用 | E12: m | F12: 230.34 | G12: =R12*$R$3 | H12: =P12*(1+Q12)*$P$3+S12*$S$3 | I12: =T12*$T$3 | J12: =(G12+H12+I12)*$J$3 | K12: =(G12+H12+I12+J12)*$K$3 | L12: =G12+H12+I12+J12+K12 | M12: =F12*L12 | O12: =P12*(1+Q12)+R12+S12+T12 | P12: 40 | Q12: 0 | R12: 5 | S12: 1 | T12: 0 | U12: =F12*O12
A13: 8 | B13: 30413002006 | C13: LA-07 LED灯带 | D13: 1.名称：LA-07 LED灯带 2.规格：8W/米 4000K 3.安装方式：天花 4.其他：包括但不限于满足图纸、招标文件、规范及验收要求等一切相关费用 | E13: m | F13: 818.02333 | G13: =R13*$R$3 | H13: =P13*(1+Q13)*$P$3+S13*$S$3 | I13: =T13*$T$3 | J13: =(G13+H13+I13)*$J$3 | K13: =(G13+H13+I13+J13)*$K$3 | L13: =G13+H13+I13+J13+K13 | M13: =F13*L13 | O13: =P13*(1+Q13)+R13+S13+T13 | P13: 20.4 | Q13: 0 | R13: 12.5 | S13: 0.41 | T13: 0 | U13: =F13*O13
A14: 9 | B14: 30413009001 | C14: LED 灯带驱动电源 | D14: 1.名称：LED 灯带驱动电源 2.规格：60W 工作电压：220V 输出电压：24V 3.尺寸：L140*W45*H29mm 4.其他：包括但不限于满足图纸、招标文件、规范及验收要求等一切相关费用 | E14: 个 | F14: 136.33333 | G14: =R14*$R$3 | H14: =P14*(1+Q14)*$P$3+S14*$S$3 | I14: =T14*$T$3 | J14: =(G14+H14+I14)*$J$3 | K14: =(G14+H14+I14+J14)*$K$3 | L14: =G14+H14+I14+J14+K14 | M14: =F14*L14 | O14: =P14*(1+Q14)+R14+S14+T14 | P14: ='架空层安装工程'!P10 | Q14: ='架空层安装工程'!Q10 | R14: ='架空层安装工程'!R10 | S14: ='架空层安装工程'!S10 | T14: ='架空层安装工程'!T10 | U14: =F14*O14
A15: 10 | B15: 30405015001 | C15: 排气扇 | D15: 1.名称：排气扇 2.规格：40W 风量235m3/h 3.尺寸：详见物料表 4.其他：包括但不限于满足图纸、招标文件、规范及验收要求等一切相关费用 | E15: 台 | F15: 268 | G15: =R15*$R$3 | H15: =P15*(1+Q15)*$P$3+S15*$S$3 | I15: =T15*$T$3 | J15: =(G15+H15+I15)*$J$3 | K15: =(G15+H15+I15+J15)*$K$3 | L15: =G15+H15+I15+J15+K15 | M15: =F15*L15 | O15: =P15*(1+Q15)+R15+S15+T15 | P15: 155 | Q15: 0 | R15: 21 | S15: 2 | T15: 0 | U15: =F15*O15
A16: 11 | B16: 30413013001 | C16: 照明开关 | D16: 1.名称：一键开关 2.规格：86*86mm 3.安装方式：暗装 4.其他：包括但不限于满足图纸、招标文件、规范及验收要求等一切相关费用 | E16: 套 | F16: 117.66667 | G16: =R16*$R$3 | H16: =P16*(1+Q16)*$P$3+S16*$S$3 | I16: =T16*$T$3 | J16: =(G16+H16+I16)*$J$3 | K16: =(G16+H16+I16+J16)*$K$3 | L16: =G16+H16+I16+J16+K16 | M16: =F16*L16 | O16: =P16*(1+Q16)+R16+S16+T16 | P16: 14.62 | Q16: 0 | R16: 6.31 | S16: 1.12 | T16: 0 | U16: =F16*O16
A17: 12 | B17: 30413013002 | C17: 照明开关 | D17: 1.名称：单联单控开关 2.规格：86*86mm 3.安装方式：暗装 4.其他：包括但不限于满足图纸、招标文件、规范及验收要求等一切相关费用 | E17: 套 | F17: 386 | G17: =R17*$R$3 | H17: =P17*(1+Q17)*$P$3+S17*$S$3 | I17: =T17*$T$3 | J17: =(G17+H17+I17)*$J$3 | K17: =(G17+H17+I17+J17)*$K$3 | L17: =G17+H17+I17+J17+K17 | M17: =F17*L17 | O17: =P17*(1+Q17)+R17+S17+T17 | P17: ='公共区域安装工程'!P14 | Q17: ='公共区域安装工程'!Q14 | R17: ='公共区域安装工程'!R14 | S17: ='公共区域安装工程'!S14 | T17: ='公共区域安装工程'!T14 | U17: =F17*O17
A18: 13 | B18: 30413013003 | C18: 照明开关 | D18: 1.名称：双联单控开关 2.规格：86*86mm 3.安装方式：暗装 4.其他：包括但不限于满足图纸、招标文件、规范及验收要求等一切相关费用 | E18: 套 | F18: 234 | G18: =R18*$R$3 | H18: =P18*(1+Q18)*$P$3+S18*$S$3 | I18: =T18*$T$3 | J18: =(G18+H18+I18)*$J$3 | K18: =(G18+H18+I18+J18)*$K$3 | L18: =G18+H18+I18+J18+K18 | M18: =F18*L18 | O18: =P18*(1+Q18)+R18+S18+T18 | P18: ='架空层安装工程'!P16 | Q18: ='架空层安装工程'!Q16 | R18: ='架空层安装工程'!R16 | S18: ='架空层安装工程'!S16 | T18: ='架空层安装工程'!T16 | U18: =F18*O18
A19: 14 | B19: 30413013004 | C19: 照明开关 | D19: 1.名称：三联单控开关 2.规格：86*86mm 3.安装方式：暗装 4.其他：包括但不限于满足图纸、招标文件、规范及验收要求等一切相关费用 | E19: 套 | F19: 100.33333 | G19: =R19*$R$3 | H19: =P19*(1+Q19)*$P$3+S19*$S$3 | I19: =T19*$T$3 | J19: =(G19+H19+I19)*$J$3 | K19: =(G19+H19+I19+J19)*$K$3 | L19: =G19+H19+I19+J19+K19 | M19: =F19*L19 | O19: =P19*(1+Q19)+R19+S19+T19 | P19: ='公共区域安装工程'!P15 | Q19: ='公共区域安装工程'!Q15 | R19: ='公共区域安装工程'!R15 | S19: ='公共区域安装工程'!S15 | T19: ='公共区域安装工程'!T15 | U19: =F19*O19
A20: 15 | B20: 30413013005 | C20: 照明开关 | D20: 1.名称：单联双控开关 2.规格：86*86mm 3.安装方式：暗装 4.其他：包括但不限于满足图纸、招标文件、规范及验收要求等一切相关费用 | E20: 套 | F20: 708.66667 | G20: =R20*$R$3 | H20: =P20*(1+Q20)*$P$3+S20*$S$3 | I20: =T20*$T$3 | J20: =(G20+H20+I20)*$J$3 | K20: =(G20+H20+I20+J20)*$K$3 | L20: =G20+H20+I20+J20+K20 | M20: =F20*L20 | O20: =P20*(1+Q20)+R20+S20+T20 | P20: 14.62 | Q20: 0 | R20: 6.31 | S20: 1.12 | T20: 0 | U20: =F20*O20
A21: 16 | B21: 30413013006 | C21: 照明开关 | D21: 1.名称：双联双控开关 2.规格：86*86mm 3.安装方式：暗装 4.其他：包括但不限于满足图纸、招标文件、规范及验收要求等一切相关费用 | E21: 套 | F21: 463.66667 | G21: =R21*$R$3 | H21: =P21*(1+Q21)*$P$3+S21*$S$3 | I21: =T21*$T$3 | J21: =(G21+H21+I21)*$J$3 | K21: =(G21+H21+I21+J21)*$K$3 | L21: =G21+H21+I21+J21+K21 | M21: =F21*L21 | O21: =P21*(1+Q21)+R21+S21+T21 | P21: 18 | Q21: 0 | R21: 10 | S21: 1.5 | T21: 0 | U21: =F21*O21
A22: 17 | B22: 30413013007 | C22: 照明开关 | D22: 1.名称：三联双控开关 2.规格：86*86mm 3.安装方式：暗装 4.其他：包括但不限于满足图纸、招标文件、规范及验收要求等一切相关费用 | E22: 套 | F22: 169.33333 | G22: =R22*$R$3 | H22: =P22*(1+Q22)*$P$3+S22*$S$3 | I22: =T22*$T$3 | J22: =(G22+H22+I22)*$J$3 | K22: =(G22+H22+I22+J22)*$K$3 | L22: =G22+H22+I22+J22+K22 | M22: =F22*L22 | O22: =P22*(1+Q22)+R22+S22+T22 | P22: 20 | Q22: 0 | R22: 12 | S22: 1.5 | T22: 0 | U22: =F22*O22
A23: 18 | B23: 30413014001 | C23: 插座 | D23: 1.名称：五孔插座 2.规格：86*86mm 3.安装方式：暗装 4.其他：包括但不限于满足图纸、招标文件、规范及验收要求等一切相关费用 | E23: 套 | F23: 2499 | G23: =R23*$R$3 | H23: =P23*(1+Q23)*$P$3+S23*$S$3 | I23: =T23*$T$3 | J23: =(G23+H23+I23)*$J$3 | K23: =(G23+H23+I23+J23)*$K$3 | L23: =G23+H23+I23+J23+K23 | M23: =F23*L23 | O23: =P23*(1+Q23)+R23+S23+T23 | P23: ='公共区域安装工程'!P16 | Q23: ='公共区域安装工程'!Q16 | R23: ='公共区域安装工程'!R16 | S23: ='公共区域安装工程'!S16 | T23: ='公共区域安装工程'!T16 | U23: =F23*O23
A24: 19 | B24: 30413014002 | C24: 插座 | D24: 1.名称：五孔插座（防溅） 2.规格：86*86mm 3.安装方式：暗装 4.其他：包括但不限于满足图纸、招标文件、规范及验收要求等一切相关费用 | E24: 套 | F24: 871 | G24: =R24*$R$3 | H24: =P24*(1+Q24)*$P$3+S24*$S$3 | I24: =T24*$T$3 | J24: =(G24+H24+I24)*$J$3 | K24: =(G24+H24+I24+J24)*$K$3 | L24: =G24+H24+I24+J24+K24 | M24: =F24*L24 | O24: =P24*(1+Q24)+R24+S24+T24 | P24: 14.62 | Q24: 0 | R24: 6.31 | S24: 1.12 | T24: 0 | U24: =F24*O24
A25: 20 | B25: 30413014003 | C25: 插座 | D25: 1.名称：五孔插座带开关 2.规格：86*86mm 3.安装方式：暗装 4.其他：包括但不限于满足图纸、招标文件、规范及验收要求等一切相关费用 | E25: 套 | F25: 235.33333 | G25: =R25*$R$3 | H25: =P25*(1+Q25)*$P$3+S25*$S$3 | I25: =T25*$T$3 | J25: =(G25+H25+I25)*$J$3 | K25: =(G25+H25+I25+J25)*$K$3 | L25: =G25+H25+I25+J25+K25 | M25: =F25*L25 | O25: =P25*(1+Q25)+R25+S25+T25 | P25: 14.62 | Q25: 0 | R25: 6.31 | S25: 1.12 | T25: 0 | U25: =F25*O25
A26: 21 | B26: 30413014004 | C26: 插座 | D26: 1.名称：五孔插座带USB接口 2.规格：86*86mm 3.安装方式：暗装 4.其他：包括但不限于满足图纸、招标文件、规范及验收要求等一切相关费用 | E26: 套 | F26: 200.33333 | G26: =R26*$R$3 | H26: =P26*(1+Q26)*$P$3+S26*$S$3 | I26: =T26*$T$3 | J26: =(G26+H26+I26)*$J$3 | K26: =(G26+H26+I26+J26)*$K$3 | L26: =G26+H26+I26+J26+K26 | M26: =F26*L26 | O26: =P26*(1+Q26)+R26+S26+T26 | P26: 14.62 | Q26: 0 | R26: 6.31 | S26: 1.12 | T26: 0 | U26: =F26*O26
A27: 22 | B27: 30413014005 | C27: 插座 | D27: 1.名称：三孔插座 2.规格：86*86mm 3.安装方式：暗装 4.其他：包括但不限于满足图纸、招标文件、规范及验收要求等一切相关费用 | E27: 套 | F27: 691.66667 | G27: =R27*$R$3 | H27: =P27*(1+Q27)*$P$3+S27*$S$3 | I27: =T27*$T$3 | J27: =(G27+H27+I27)*$J$3 | K27: =(G27+H27+I27+J27)*$K$3 | L27: =G27+H27+I27+J27+K27 | M27: =F27*L27 | O27: =P27*(1+Q27)+R27+S27+T27 | P27: 14.62 | Q27: 0 | R27: 6.31 | S27: 1.12 | T27: 0 | U27: =F27*O27
A28: 23 | B28: 30413014006 | C28: 插座 | D28: 1.名称：三孔插座 16A 2.规格：86*86mm 3.安装方式：暗装 4.其他：包括但不限于满足图纸、招标文件、规范及验收要求等一切相关费用 | E28: 套 | F28: 2.6666667 | G28: =R28*$R$3 | H28: =P28*(1+Q28)*$P$3+S28*$S$3 | I28: =T28*$T$3 | J28: =(G28+H28+I28)*$J$3 | K28: =(G28+H28+I28+J28)*$K$3 | L28: =G28+H28+I28+J28+K28 | M28: =F28*L28 | O28: =P28*(1+Q28)+R28+S28+T28 | P28: 14.62 | Q28: 0 | R28: 6.31 | S28: 1.12 | T28: 0 | U28: =F28*O28
A29: 24 | B29: 30413014007 | C29: 插座 | D29: 1.名称：三孔插座带开关（防溅） 2.规格：86*86mm 3.安装方式：暗装 4.其他：包括但不限于满足图纸、招标文件、规范及验收要求等一切相关费用 | E29: 套 | F29: 117.66667 | G29: =R29*$R$3 | H29: =P29*(1+Q29)*$P$3+S29*$S$3 | I29: =T29*$T$3 | J29: =(G29+H29+I29)*$J$3 | K29: =(G29+H29+I29+J29)*$K$3 | L29: =G29+H29+I29+J29+K29 | M29: =F29*L29 | O29: =P29*(1+Q29)+R29+S29+T29 | P29: 14.62 | Q29: 0 | R29: 6.31 | S29: 1.12 | T29: 0 | U29: =F29*O29
A30: 25 | B30: 30413014008 | C30: 小夜灯 | D30: 1.名称：小夜灯 2.规格：86*86mm 3.安装方式：暗装 4.其他：包括但不限于满足图纸、招标文件、规范及验收要求等一切相关费用 | E30: 套 | F30: 115.66667 | G30: =R30*$R$3 | H30: =P30*(1+Q30)*$P$3+S30*$S$3 | I30: =T30*$T$3 | J30: =(G30+H30+I30)*$J$3 | K30: =(G30+H30+I30+J30)*$K$3 | L30: =G30+H30+I30+J30+K30 | M30: =F30*L30 | O30: =P30*(1+Q30)+R30+S30+T30 | P30: 15 | Q30: 0 | R30: 5 | S30: 0.5 | T30: 0 | U30: =F30*O30
A31: 26 | B31: 30412004001 | C31: 配线 | D31: 1.名称：电气配线 2.型号规格：BV-2.5 3.安装方式：管内穿线 4.其他：包括但不限于满足图纸、招标文件、规范及验收要求等一切相关费用 | E31: m | F31: 56229.66 | G31: =R31*$R$3 | H31: =P31*(1+Q31)*$P$3+S31*$S$3 | I31: =T31*$T$3 | J31: =(G31+H31+I31)*$J$3 | K31: =(G31+H31+I31+J31)*$K$3 | L31: =G31+H31+I31+J31+K31 | M31: =F31*L31 | O31: =P31*(1+Q31)+R31+S31+T31 | P31: ='公共区域安装工程'!P22 | Q31: ='公共区域安装工程'!Q22 | R31: ='公共区域安装工程'!R22 | S31: ='公共区域安装工程'!S22 | T31: ='公共区域安装工程'!T22 | U31: =F31*O31
A32: 27 | B32: 30412004002 | C32: 配线 | D32: 1.名称：电气配线 2.型号规格：BV-4 3.安装方式：管内穿线 4.其他：包括但不限于满足图纸、招标文件、规范及验收要求等一切相关费用 | E32: m | F32: 76002.463 | G32: =R32*$R$3 | H32: =P32*(1+Q32)*$P$3+S32*$S$3 | I32: =T32*$T$3 | J32: =(G32+H32+I32)*$J$3 | K32: =(G32+H32+I32+J32)*$K$3 | L32: =G32+H32+I32+J32+K32 | M32: =F32*L32 | O32: =P32*(1+Q32)+R32+S32+T32 | P32: 3.68 | Q32: 0.02 | R32: 1.4 | S32: 0.22 | T32: 0.01 | U32: =F32*O32
A33: 28 | B33: 30412004006 | C33: 配线 | D33: 1.名称：电气配线 2.型号规格：RVS-4*1.0 3.安装方式：管内穿线 4.其他：包括但不限于满足图纸、招标文件、规范及验收要求等一切相关费用 | E33: m | F33: 1266.87 | G33: =R33*$R$3 | H33: =P33*(1+Q33)*$P$3+S33*$S$3 | I33: =T33*$T$3 | J33: =(G33+H33+I33)*$J$3 | K33: =(G33+H33+I33+J33)*$K$3 | L33: =G33+H33+I33+J33+K33 | M33: =F33*L33 | O33: =P33*(1+Q33)+R33+S33+T33 | P33: ='架空层安装工程'!P23 | Q33: ='架空层安装工程'!Q23 | R33: ='架空层安装工程'!R23 | S33: ='架空层安装工程'!S23 | T33: ='架空层安装工程'!T23 | U33: =F33*O33
A34: 29 | B34: 30412004004 | C34: 配线 | D34: 1.名称：电气配线 2.型号规格：BV-2.5 3.安装方式：管内穿线 4.其他：包括但不限于满足图纸、招标文件、规范及验收要求等一切相关费用 | E34: m | F34: 1100.8933 | G34: =R34*$R$3 | H34: =P34*(1+Q34)*$P$3+S34*$S$3 | I34: =T34*$T$3 | J34: =(G34+H34+I34)*$J$3 | K34: =(G34+H34+I34+J34)*$K$3 | L34: =G34+H34+I34+J34+K34 | M34: =F34*L34 | O34: =P34*(1+Q34)+R34+S34+T34 | P34: ='公共区域安装工程'!P22 | Q34: ='公共区域安装工程'!Q22 | R34: ='公共区域安装工程'!R22 | S34: ='公共区域安装工程'!S22 | T34: ='公共区域安装工程'!T22 | U34: =F34*O34
A35: 30 | B35: 30412004005 | C35: 配线 | D35: 1.名称：电气配线 2.型号规格：BV-4 3.安装方式：管内穿线 4.其他：包括但不限于满足图纸、招标文件、规范及验收要求等一切相关费用 | E35: m | F35: 1253.5333 | G35: =R35*$R$3 | H35: =P35*(1+Q35)*$P$3+S35*$S$3 | I35: =T35*$T$3 | J35: =(G35+H35+I35)*$J$3 | K35: =(G35+H35+I35+J35)*$K$3 | L35: =G35+H35+I35+J35+K35 | M35: =F35*L35 | O35: =P35*(1+Q35)+R35+S35+T35 | P35: =P32 | Q35: =Q32 | R35: =R32 | S35: =S32 | T35: =T32 | U35: =F35*O35
C36: 弱电
A37: 31 | B37: 30413014009 | C37: 插座 | D37: 1.名称：单口网络插座 2.规格：86*86mm 3.安装方式：暗装 4.其他：包括但不限于满足图纸、招标文件、规范及验收要求等一切相关费用 | E37: 套 | F37: 201 | G37: =R37*$R$3 | H37: =P37*(1+Q37)*$P$3+S37*$S$3 | I37: =T37*$T$3 | J37: =(G37+H37+I37)*$J$3 | K37: =(G37+H37+I37+J37)*$K$3 | L37: =G37+H37+I37+J37+K37 | M37: =F37*L37 | O37: =P37*(1+Q37)+R37+S37+T37 | P37: 14.62 | Q37: 0 | R37: 6.31 | S37: 1.12 | T37: 0 | U37: =F37*O37
A38: 32 | B38: 30413014010 | C38: 插座 | D38: 1.名称：单口网络插座 2.规格：86*86mm 3.安装方式：暗装 4.其他：包括但不限于满足图纸、招标文件、规范及验收要求等一切相关费用 | E38: 套 | F38: 84.666667 | G38: =R38*$R$3 | H38: =P38*(1+Q38)*$P$3+S38*$S$3 | I38: =T38*$T$3 | J38: =(G38+H38+I38)*$J$3 | K38: =(G38+H38+I38+J38)*$K$3 | L38: =G38+H38+I38+J38+K38 | M38: =F38*L38 | O38: =P38*(1+Q38)+R38+S38+T38 | P38: =P37 | Q38: =Q37 | R38: =R37 | S38: =S37 | T38: =T37 | U38: =F38*O38
A39: 33 | B39: 30413014011 | C39: 插座 | D39: 1.名称：双口插座(网络+电视) 2.规格：86*86mm 3.安装方式：暗装 4.其他：包括但不限于满足图纸、招标文件、规范及验收要求等一切相关费用 | E39: 套 | F39: 117.66667 | G39: =R39*$R$3 | H39: =P39*(1+Q39)*$P$3+S39*$S$3 | I39: =T39*$T$3 | J39: =(G39+H39+I39)*$J$3 | K39: =(G39+H39+I39+J39)*$K$3 | L39: =G39+H39+I39+J39+K39 | M39: =F39*L39 | O39: =P39*(1+Q39)+R39+S39+T39 | P39: 14.62 | Q39: 0 | R39: 6.31 | S39: 1.12 | T39: 0 | U39: =F39*O39
A40: 34 | B40: 30413014012 | C40: 插座 | D40: 1.名称：双口地插(网络+电话) 2.规格：86*86mm 3.安装方式：暗装 4.其他：包括但不限于满足图纸、招标文件、规范及验收要求等一切相关费用 | E40: 套 | F40: 33 | G40: =R40*$R$3 | H40: =P40*(1+Q40)*$P$3+S40*$S$3 | I40: =T40*$T$3 | J40: =(G40+H40+I40)*$J$3 | K40: =(G40+H40+I40+J40)*$K$3 | L40: =G40+H40+I40+J40+K40 | M40: =F40*L40 | O40: =P40*(1+Q40)+R40+S40+T40 | P40: 14.62 | Q40: 0 | R40: 6.31 | S40: 1.12 | T40: 0 | U40: =F40*O40
A41: 35 | B41: 30413013008 | C41: 紧急按钮 | D41: 1.名称：紧急按钮 2.规格：86*86mm 3.安装方式：暗装 4.其他：包括但不限于满足图纸、招标文件、规范及验收要求等一切相关费用 | E41: 套 | F41: 150.66667 | G41: =R41*$R$3 | H41: =P41*(1+Q41)*$P$3+S41*$S$3 | I41: =T41*$T$3 | J41: =(G41+H41+I41)*$J$3 | K41: =(G41+H41+I41+J41)*$K$3 | L41: =G41+H41+I41+J41+K41 | M41: =F41*L41 | O41: =P41*(1+Q41)+R41+S41+T41 | P41: ='样板房安装工程'!P41 | Q41: ='样板房安装工程'!Q41 | R41: ='样板房安装工程'!R41 | S41: ='样板房安装工程'!S41 | T41: ='样板房安装工程'!T41 | U41: =F41*O41
A42: 36 | B42: 30502003001 | C42: 双绞线缆 | D42: 1.名称：超六类网线 2.型号规格：CAT6 3.敷设方式：管内穿线 4.其他：包括但不限于满足图纸、招标文件、规范及验收要求等一切相关费用 | E42: m | F42: 6817.96 | G42: =R42*$R$3 | H42: =P42*(1+Q42)*$P$3+S42*$S$3 | I42: =T42*$T$3 | J42: =(G42+H42+I42)*$J$3 | K42: =(G42+H42+I42+J42)*$K$3 | L42: =G42+H42+I42+J42+K42 | M42: =F42*L42 | O42: =P42*(1+Q42)+R42+S42+T42 | P42: 2.5 | Q42: 0 | R42: 0.8 | S42: 0.1 | T42: 0.1 | U42: =F42*O42
A43: 37 | B43: 30502003002 | C43: 多芯软导线 | D43: 1.名称：多芯软导线 2.型号规格：RVV-2*1.0 3.敷设方式：管内穿线 4.其他：包括但不限于满足图纸、招标文件、规范及验收要求等一切相关费用 | E43: m | F43: 1970.6033 | G43: =R43*$R$3 | H43: =P43*(1+Q43)*$P$3+S43*$S$3 | I43: =T43*$T$3 | J43: =(G43+H43+I43)*$J$3 | K43: =(G43+H43+I43+J43)*$K$3 | L43: =G43+H43+I43+J43+K43 | M43: =F43*L43 | O43: =P43*(1+Q43)+R43+S43+T43 | P43: ='样板房安装工程'!P43 | Q43: ='样板房安装工程'!Q43 | R43: ='样板房安装工程'!R43 | S43: ='样板房安装工程'!S43 | T43: ='样板房安装工程'!T43 | U43: =F43*O43
A44: 38 | B44: 30502003003 | C44: 双绞线缆 | D44: 1.名称：超六类网线 2.型号规格：CAT6 3.敷设方式：管内穿线 4.其他：包括但不限于满足图纸、招标文件、规范及验收要求等一切相关费用 | E44: m | F44: 86.293333 | G44: =R44*$R$3 | H44: =P44*(1+Q44)*$P$3+S44*$S$3 | I44: =T44*$T$3 | J44: =(G44+H44+I44)*$J$3 | K44: =(G44+H44+I44+J44)*$K$3 | L44: =G44+H44+I44+J44+K44 | M44: =F44*L44 | O44: =P44*(1+Q44)+R44+S44+T44 | P44: =P42 | Q44: =Q42 | R44: =R42 | S44: =S42 | T44: =T42 | U44: =F44*O44
A45: 39 | B45: 30502003004 | C45: 多芯软导线 | D45: 1.名称：多芯软导线 2.型号规格：RVV-2*1.0 3.敷设方式：管内穿线 4.其他：包括但不限于满足图纸、招标文件、规范及验收要求等一切相关费用 | E45: m | F45: 23.313333 | G45: =R45*$R$3 | H45: =P45*(1+Q45)*$P$3+S45*$S$3 | I45: =T45*$T$3 | J45: =(G45+H45+I45)*$J$3 | K45: =(G45+H45+I45+J45)*$K$3 | L45: =G45+H45+I45+J45+K45 | M45: =F45*L45 | O45: =P45*(1+Q45)+R45+S45+T45 | P45: ='样板房安装工程'!P43 | Q45: ='样板房安装工程'!Q43 | R45: ='样板房安装工程'!R43 | S45: ='样板房安装工程'!S43 | T45: ='样板房安装工程'!T43 | U45: =F45*O45
C46: 洁具五金、排水管
A47: 40 | B47: 31003006001 | C47: 连体马桶 | D47: 1.名称：连体马桶 2.型号：详见物料表(主材甲供) 3.其他：包括但不限于满足图纸、招标文件、规范及验收要求等一切相关费用 | E47: 组 | F47: 301.33333 | G47: =R47*$R$3 | H47: =P47*(1+Q47)*$P$3+S47*$S$3 | I47: =T47*$T$3 | J47: =(G47+H47+I47)*$J$3 | K47: =(G47+H47+I47+J47)*$K$3 | L47: =G47+H47+I47+J47+K47 | M47: =F47*L47 | O47: =P47*(1+Q47)+R47+S47+T47 | Q47: 0 | R47: 60 | S47: 10 | T47: 0 | U47: =F47*O47
A48: 41 | B48: 31003010001 | C48: 淋浴器 | D48: 1.名称：淋浴花洒-主卫 2.型号：详见物料表(主材甲供) 3.其他：包括但不限于满足图纸、招标文件、规范及验收要求等一切相关费用 | E48: 套 | F48: 117.66667 | G48: =R48*$R$3 | H48: =P48*(1+Q48)*$P$3+S48*$S$3 | I48: =T48*$T$3 | J48: =(G48+H48+I48)*$J$3 | K48: =(G48+H48+I48+J48)*$K$3 | L48: =G48+H48+I48+J48+K48 | M48: =F48*L48 | O48: =P48*(1+Q48)+R48+S48+T48 | Q48: 0 | R48: 90 | S48: 35 | T48: 0 | U48: =F48*O48
A49: 42 | B49: 31003010002 | C49: 淋浴器 | D49: 1.名称：淋浴花洒-公卫、次卫(主材甲供) 3.其他：包括但不限于满足图纸、招标文件、规范及验收要求等一切相关费用 | E49: 套 | F49: 183.66667 | G49: =R49*$R$3 | H49: =P49*(1+Q49)*$P$3+S49*$S$3 | I49: =T49*$T$3 | J49: =(G49+H49+I49)*$J$3 | K49: =(G49+H49+I49+J49)*$K$3 | L49: =G49+H49+I49+J49+K49 | M49: =F49*L49 | O49: =P49*(1+Q49)+R49+S49+T49 | Q49: 0 | R49: 90 | S49: 35 | T49: 0 | U49: =F49*O49
A50: 43 | B50: 31003003001 | C50: 台下盆及龙头 | D50: 1.名称：台下盆及龙头 2.型号：详见物料表(主材甲供) 3.其他：包括但不限于满足图纸、招标文件、规范及验收要求等一切相关费用 | E50: 组 | F50: 334.33333 | G50: =R50*$R$3 | H50: =P50*(1+Q50)*$P$3+S50*$S$3 | I50: =T50*$T$3 | J50: =(G50+H50+I50)*$J$3 | K50: =(G50+H50+I50+J50)*$K$3 | L50: =G50+H50+I50+J50+K50 | M50: =F50*L50 | O50: =P50*(1+Q50)+R50+S50+T50 | Q50: 0 | R50: 90 | S50: 12 | T50: 0 | U50: =F50*O50
A51: 44 | B51: 31003004001 | C51: 水槽及龙头 | D51: 1.名称：厨房大单盆水槽及龙头 2.型号：详见物料表(主材甲供) 3.其他：包括但不限于满足图纸、招标文件、规范及验收要求等一切相关费用 | E51: 组 | F51: 117.66667 | G51: =R51*$R$3 | H51: =P51*(1+Q51)*$P$3+S51*$S$3 | I51: =T51*$T$3 | J51: =(G51+H51+I51)*$J$3 | K51: =(G51+H51+I51+J51)*$K$3 | L51: =G51+H51+I51+J51+K51 | M51: =F51*L51 | O51: =P51*(1+Q51)+R51+S51+T51 | Q51: 0 | R51: 60 | S51: 40 | T51: 0 | U51: =F51*O51
A52: 45 | B52: 31003014001 | C52: 地漏 | D52: 1.名称：不锈钢地漏-干区 2.规格：DN50 3.型号：详见物料表(主材甲供) 4.其他：包括但不限于满足图纸、招标文件、规范及验收要求等一切相关费用 | E52: 个 | F52: 334.33333 | G52: =R52*$R$3 | H52: =P52*(1+Q52)*$P$3+S52*$S$3 | I52: =T52*$T$3 | J52: =(G52+H52+I52)*$J$3 | K52: =(G52+H52+I52+J52)*$K$3 | L52: =G52+H52+I52+J52+K52 | M52: =F52*L52 | O52: =P52*(1+Q52)+R52+S52+T52 | Q52: 0 | R52: 18 | S52: 5 | T52: 0 | U52: =F52*O52
A53: 46 | B53: 31003014002 | C53: 地漏 | D53: 1.名称：不锈钢地漏-淋浴间 2.规格：DN75 3.型号：详见物料表(主材甲供) 4.其他：包括但不限于满足图纸、招标文件、规范及验收要求等一切相关费用 | E53: 个 | F53: 301.33333 | G53: =R53*$R$3 | H53: =P53*(1+Q53)*$P$3+S53*$S$3 | I53: =T53*$T$3 | J53: =(G53+H53+I53)*$J$3 | K53: =(G53+H53+I53+J53)*$K$3 | L53: =G53+H53+I53+J53+K53 | M53: =F53*L53 | O53: =P53*(1+Q53)+R53+S53+T53 | Q53: 0 | R53: 25 | S53: 1.5 | T53: 0.2 | U53: =F53*O53
A54: 47 | B54: 31003014003 | C54: 地漏 | D54: 1.名称：不锈钢地漏-阳台 2.规格：DN75 3.型号：详见物料表(主材甲供) 4.其他：包括但不限于满足图纸、招标文件、规范及验收要求等一切相关费用 | E54: 个 | F54: 183.66667 | G54: =R54*$R$3 | H54: =P54*(1+Q54)*$P$3+S54*$S$3 | I54: =T54*$T$3 | J54: =(G54+H54+I54)*$J$3 | K54: =(G54+H54+I54+J54)*$K$3 | L54: =G54+H54+I54+J54+K54 | M54: =F54*L54 | O54: =P54*(1+Q54)+R54+S54+T54 | Q54: 0 | R54: 25 | S54: 1.5 | T54: 0.2 | U54: =F54*O54
A55: 48 | B55: 31003014004 | C55: 地漏 | D55: 1.名称：洗衣机地漏 2.规格：DN75 3.型号：详见物料表(主材甲供) 4.其他：包括但不限于满足图纸、招标文件、规范及验收要求等一切相关费用 | E55: 个 | F55: 117.66667 | G55: =R55*$R$3 | H55: =P55*(1+Q55)*$P$3+S55*$S$3 | I55: =T55*$T$3 | J55: =(G55+H55+I55)*$J$3 | K55: =(G55+H55+I55+J55)*$K$3 | L55: =G55+H55+I55+J55+K55 | M55: =F55*L55 | O55: =P55*(1+Q55)+R55+S55+T55 | Q55: 0 | R55: 18 | S55: 5 | T55: 0 | U55: =F55*O55
A56: 49 | B56: 31003014005 | C56: 洗衣机龙头 | D56: 1.名称：洗衣机龙头 2.规格：DN15 3.型号：详见物料表(主材甲供) 4.其他：包括但不限于满足图纸、招标文件、规范及验收要求等一切相关费用 | E56: 个 | F56: 117.66667 | G56: =R56*$R$3 | H56: =P56*(1+Q56)*$P$3+S56*$S$3 | I56: =T56*$T$3 | J56: =(G56+H56+I56)*$J$3 | K56: =(G56+H56+I56+J56)*$K$3 | L56: =G56+H56+I56+J56+K56 | M56: =F56*L56 | O56: =P56*(1+Q56)+R56+S56+T56 | Q56: 0 | R56: 55 | S56: 20 | T56: 0 | U56: =F56*O56
A57: 50 | B57: 31002001001 | C57: 角阀 | D57: 1.名称：热水器角阀(主材甲供) 2.型号规格：DN15 3.其他：包括但不限于满足图纸、招标文件、规范及验收要求等一切相关费用 | E57: 个 | F57: 235.33333 | G57: =R57*$R$3 | H57: =P57*(1+Q57)*$P$3+S57*$S$3 | I57: =T57*$T$3 | J57: =(G57+H57+I57)*$J$3 | K57: =(G57+H57+I57+J57)*$K$3 | L57: =G57+H57+I57+J57+K57 | M57: =F57*L57 | O57: =P57*(1+Q57)+R57+S57+T57 | Q57: 0 | R57: 167.09 | S57: 0 | T57: 12.03 | U57: =F57*O57
A58: 51 | B58: 31001008001 | C58: UPVC排水管 | D58: 1.名称：UPVC排水管 2.规格：DN50 3.连接方式：粘接 4.压力试验及吹、洗要求：水压试验、管道标识等 5.其他：包括但不限于满足图纸、招标文件、规范及验收要求等一切相关费用 | E58: m | F58: 883.64667 | G58: =R58*$R$3 | H58: =P58*(1+Q58)*$P$3+S58*$S$3 | I58: =T58*$T$3 | J58: =(G58+H58+I58)*$J$3 | K58: =(G58+H58+I58+J58)*$K$3 | L58: =G58+H58+I58+J58+K58 | M58: =F58*L58 | O58: =P58*(1+Q58)+R58+S58+T58 | P58: ='样板房安装工程'!P46 | Q58: ='样板房安装工程'!Q46 | R58: ='样板房安装工程'!R46 | S58: ='样板房安装工程'!S46 | T58: ='样板房安装工程'!T46 | U58: =F58*O58
A59: 52 | B59: 31001008002 | C59: UPVC排水管 | D59: 1.名称：UPVC排水管 2.规格：DN75 3.连接方式：粘接 4.压力试验及吹、洗要求：水压试验、管道标识等 5.其他：包括但不限于满足图纸、招标文件、规范及验收要求等一切相关费用 | E59: m | F59: 743.49 | G59: =R59*$R$3 | H59: =P59*(1+Q59)*$P$3+S59*$S$3 | I59: =T59*$T$3 | J59: =(G59+H59+I59)*$J$3 | K59: =(G59+H59+I59+J59)*$K$3 | L59: =G59+H59+I59+J59+K59 | M59: =F59*L59 | O59: =P59*(1+Q59)+R59+S59+T59 | P59: ='样板房安装工程'!P47 | Q59: ='样板房安装工程'!Q47 | R59: ='样板房安装工程'!R47 | S59: ='样板房安装工程'!S47 | T59: ='样板房安装工程'!T47 | U59: =F59*O59
A60: 53 | B60: 31001008003 | C60: UPVC排水管 | D60: 1.名称：UPVC排水管 2.规格：DN100 3.连接方式：粘接 4.压力试验及吹、洗要求：水压试验、管道标识等 5.其他：包括但不限于满足图纸、招标文件、规范及验收要求等一切相关费用 | E60: m | F60: 268.99667 | G60: =R60*$R$3 | H60: =P60*(1+Q60)*$P$3+S60*$S$3 | I60: =T60*$T$3 | J60: =(G60+H60+I60)*$J$3 | K60: =(G60+H60+I60+J60)*$K$3 | L60: =G60+H60+I60+J60+K60 | M60: =F60*L60 | O60: =P60*(1+Q60)+R60+S60+T60 | P60: ='样板房安装工程'!P48 | Q60: ='样板房安装工程'!Q48 | R60: ='样板房安装工程'!R48 | S60: ='样板房安装工程'!S48 | T60: ='样板房安装工程'!T48 | U60: =F60*O60
A61: 54 | B61: 31001008004 | C61: UPVC排水管 | D61: 1.名称：UPVC排水管 2.规格：DN50 3.连接方式：粘接 4.压力试验及吹、洗要求：水压试验、管道标识等 5.其他：包括但不限于满足图纸、招标文件、规范及验收要求等一切相关费用 | E61: m | F61: 11.98 | G61: =R61*$R$3 | H61: =P61*(1+Q61)*$P$3+S61*$S$3 | I61: =T61*$T$3 | J61: =(G61+H61+I61)*$J$3 | K61: =(G61+H61+I61+J61)*$K$3 | L61: =G61+H61+I61+J61+K61 | M61: =F61*L61 | O61: =P61*(1+Q61)+R61+S61+T61 | P61: ='样板房安装工程'!P46 | Q61: ='样板房安装工程'!Q46 | R61: ='样板房安装工程'!R46 | S61: ='样板房安装工程'!S46 | T61: ='样板房安装工程'!T46 | U61: =F61*O61
A62: 55 | B62: 31001008005 | C62: UPVC排水管 | D62: 1.名称：UPVC排水管 2.规格：DN75 3.连接方式：粘接 4.压力试验及吹、洗要求：水压试验、管道标识等 5.其他：包括但不限于满足图纸、招标文件、规范及验收要求等一切相关费用 | E62: m | F62: 5.7666667 | G62: =R62*$R$3 | H62: =P62*(1+Q62)*$P$3+S62*$S$3 | I62: =T62*$T$3 | J62: =(G62+H62+I62)*$J$3 | K62: =(G62+H62+I62+J62)*$K$3 | L62: =G62+H62+I62+J62+K62 | M62: =F62*L62 | O62: =P62*(1+Q62)+R62+S62+T62 | P62: ='样板房安装工程'!P47 | Q62: ='样板房安装工程'!Q47 | R62: ='样板房安装工程'!R47 | S62: ='样板房安装工程'!S47 | T62: ='样板房安装工程'!T47 | U62: =F62*O62
A63: 56 | B63: 31001008006 | C63: UPVC排水管 | D63: 1.名称：UPVC排水管 2.规格：DN100 3.连接方式：粘接 4.压力试验及吹、洗要求：水压试验、管道标识等 5.其他：包括但不限于满足图纸、招标文件、规范及验收要求等一切相关费用 | E63: m | F63: 2.6333333 | G63: =R63*$R$3 | H63: =P63*(1+Q63)*$P$3+S63*$S$3 | I63: =T63*$T$3 | J63: =(G63+H63+I63)*$J$3 | K63: =(G63+H63+I63+J63)*$K$3 | L63: =G63+H63+I63+J63+K63 | M63: =F63*L63 | O63: =P63*(1+Q63)+R63+S63+T63 | P63: ='样板房安装工程'!P48 | Q63: ='样板房安装工程'!Q48 | R63: ='样板房安装工程'!R48 | S63: ='样板房安装工程'!S48 | T63: ='样板房安装工程'!T48 | U63: =F63*O63
B64: 税前合价 | E64: 元 | M64: =SUM(M4:M63)
B65: 税金 | E65: 元 | M65: =M64*0.09
B66: 含税合价 | E66: 元 | M66: =M64+M65

Sheet 会所售楼处消防电工程
A1: 会所售楼处消防电工程工程量清单 | O1: 成本单价组成（投标人填写）
A2: 序号 | B2: 编码 | C2: 项目名称 | D2: 项目特征 | E2: 单位 | F2: 工程量 | G2: 人工费 | H2: 材料费 | I2: 机械费 | J2: 管理费 | K2: 利润 | L2: 不含税单价 | M2: 合价 | O2: 单价合计 | P2: 主材费 | Q2: 主材损耗率 | R2: 人工费 | S2: 辅材费 | T2: 机械费 | U2: 合计
J3: 0 | K3: 0 | P3: =架空层安装工程!$P$3 | R3: =架空层安装工程!$R$3 | S3: =架空层安装工程!$S$3 | T3: =架空层安装工程!$T$3
B4: 单位工程
C5: 消防自动报警系统
A6: 1 | B6: 30904008001 | C6: 消防模块箱 | D6: 1、名称：消防模块箱 2、安装方式：按图纸要求综合考虑 3、其他：包括但不限于以上内容，综合考虑按图纸、招标文件和规范要求而实施、完成这项工程的一切有关费用 | E6: 台 | F6: 2 | G6: =R6*$R$3 | H6: =P6*(1+Q6)*$P$3+S6*$S$3 | I6: =T6*$T$3 | J6: =(G6+H6+I6)*$J$3 | K6: =(G6+H6+I6+J6)*$K$3 | L6: =G6+H6+I6+J6+K6 | M6: =F6*L6 | O6: =P6*(1+Q6)+R6+S6+T6 | P6: 450 | Q6: 0 | R6: 60 | S6: 5 | T6: 0 | U6: =F6*O6
A7: 2 | B7: 30904007001 | C7: 总线短路隔离器 | D7: 1、名称：总线短路隔离器 2、安装方式：按图纸要求综合考虑 3、其他：包括但不限于以上内容，综合考虑按图纸、招标文件和规范要求而实施、完成这项工程的一切有关费用 | E7: 个 | F7: 2 | G7: =R7*$R$3 | H7: =P7*(1+Q7)*$P$3+S7*$S$3 | I7: =T7*$T$3 | J7: =(G7+H7+I7)*$J$3 | K7: =(G7+H7+I7+J7)*$K$3 | L7: =G7+H7+I7+J7+K7 | M7: =F7*L7 | O7: =P7*(1+Q7)+R7+S7+T7 | P7: 52 | Q7: 0 | R7: 49.4 | S7: 10 | T7: 0 | U7: =F7*O7
A8: 3 | B8: 30904007003 | C8: 消防模块 | D8: 1、名称：编码单输入/输出模块 2、安装方式：按图纸要求综合考虑 3、其他：包括但不限于以上内容，综合考虑按图纸、招标文件和规范要求而实施、完成这项工程的一切有关费用 | E8: 个 | F8: 6 | G8: =R8*$R$3 | H8: =P8*(1+Q8)*$P$3+S8*$S$3 | I8: =T8*$T$3 | J8: =(G8+H8+I8)*$J$3 | K8: =(G8+H8+I8+J8)*$K$3 | L8: =G8+H8+I8+J8+K8 | M8: =F8*L8 | O8: =P8*(1+Q8)+R8+S8+T8 | P8: 150 | Q8: 0 | R8: 120 | S8: 15 | T8: 0 | U8: =F8*O8
A9: 4 | B9: 30904001001 | C9: 点型探测器 | D9: 1、名称：智能型感烟探测器 2、安装方式：按图纸要求综合考虑 3、其他：包括但不限于以上内容，综合考虑按图纸、招标文件和规范要求而实施、完成这项工程的一切有关费用 | E9: 个 | F9: 26 | G9: =R9*$R$3 | H9: =P9*(1+Q9)*$P$3+S9*$S$3 | I9: =T9*$T$3 | J9: =(G9+H9+I9)*$J$3 | K9: =(G9+H9+I9+J9)*$K$3 | L9: =G9+H9+I9+J9+K9 | M9: =F9*L9 | O9: =P9*(1+Q9)+R9+S9+T9 | P9: 40 | Q9: 0 | R9: 65 | S9: 10 | T9: 3 | U9: =F9*O9
A10: 5 | B10: 30904005001 | C10: 消防报警电话插孔(电话) | D10: 1、名称：消防电话插孔 2、安装方式：按图纸要求综合考虑 3、其他：包括但不限于以上内容，综合考虑按图纸、招标文件和规范要求而实施、完成这项工程的一切有关费用 | E10: 个 | F10: 5 | G10: =R10*$R$3 | H10: =P10*(1+Q10)*$P$3+S10*$S$3 | I10: =T10*$T$3 | J10: =(G10+H10+I10)*$J$3 | K10: =(G10+H10+I10+J10)*$K$3 | L10: =G10+H10+I10+J10+K10 | M10: =F10*L10 | O10: =P10*(1+Q10)+R10+S10+T10 | P10: 25 | Q10: 0 | R10: 8 | S10: 1 | T10: 0 | U10: =F10*O10
A11: 6 | B11: 30904003001 | C11: 按钮 | D11: 1、名称：编码型手动报警按钮 2、安装方式：按图纸要求综合考虑 3、其他：包括但不限于以上内容，综合考虑按图纸、招标文件和规范要求而实施、完成这项工程的一切有关费用 | E11: 个 | F11: 5 | G11: =R11*$R$3 | H11: =P11*(1+Q11)*$P$3+S11*$S$3 | I11: =T11*$T$3 | J11: =(G11+H11+I11)*$J$3 | K11: =(G11+H11+I11+J11)*$K$3 | L11: =G11+H11+I11+J11+K11 | M11: =F11*L11 | O11: =P11*(1+Q11)+R11+S11+T11 | P11: 27 | Q11: 0 | R11: 12 | S11: 2 | T11: 0 | U11: =F11*O11
A12: 7 | B12: 30904003002 | C12: 按钮 | D12: 1、名称：编码型消火栓按钮 2、安装方式：按图纸要求综合考虑 3、其他：包括但不限于以上内容，综合考虑按图纸、招标文件和规范要求而实施、完成这项工程的一切有关费用 | E12: 个 | F12: 12 | G12: =R12*$R$3 | H12: =P12*(1+Q12)*$P$3+S12*$S$3 | I12: =T12*$T$3 | J12: =(G12+H12+I12)*$J$3 | K12: =(G12+H12+I12+J12)*$K$3 | L12: =G12+H12+I12+J12+K12 | M12: =F12*L12 | O12: =P12*(1+Q12)+R12+S12+T12 | P12: 27 | Q12: 0 | R12: 12 | S12: 2 | T12: 0 | U12: =F12*O12
A13: 8 | B13: 30904004001 | C13: 声光报警器 | D13: 1、名称：声光报警器 2、安装方式：按图纸要求综合考虑 3、其他：包括但不限于以上内容，综合考虑按图纸、招标文件和规范要求而实施、完成这项工程的一切有关费用 | E13: 个 | F13: 5 | G13: =R13*$R$3 | H13: =P13*(1+Q13)*$P$3+S13*$S$3 | I13: =T13*$T$3 | J13: =(G13+H13+I13)*$J$3 | K13: =(G13+H13+I13+J13)*$K$3 | L13: =G13+H13+I13+J13+K13 | M13: =F13*L13 | O13: =P13*(1+Q13)+R13+S13+T13 | P13: 165 | Q13: 0 | R13: 60 | S13: 10 | T13: 0 | U13: =F13*O13
A14: 9 | B14: 30904005002 | C14: 消防电话分机 | D14: 1、名称：消防电话分机 2、安装方式：按图纸要求综合考虑 3、其他：包括但不限于以上内容，综合考虑按图纸、招标文件和规范要求而实施、完成这项工程的一切有关费用 | E14: 个 | F14: 5 | G14: =R14*$R$3 | H14: =P14*(1+Q14)*$P$3+S14*$S$3 | I14: =T14*$T$3 | J14: =(G14+H14+I14)*$J$3 | K14: =(G14+H14+I14+J14)*$K$3 | L14: =G14+H14+I14+J14+K14 | M14: =F14*L14 | O14: =P14*(1+Q14)+R14+S14+T14 | P14: 110 | Q14: 0 | R14: 12 | S14: 2 | T14: 0 | U14: =F14*O14
A15: 10 | B15: 30904007004 | C15: 消防模块 | D15: 1、名称：广播模块 2、安装方式：按图纸要求综合考虑 3、其他：包括但不限于以上内容，综合考虑按图纸、招标文件和规范要求而实施、完成这项工程的一切有关费用 | E15: 个 | F15: 2 | G15: =R15*$R$3 | H15: =P15*(1+Q15)*$P$3+S15*$S$3 | I15: =T15*$T$3 | J15: =(G15+H15+I15)*$J$3 | K15: =(G15+H15+I15+J15)*$K$3 | L15: =G15+H15+I15+J15+K15 | M15: =F15*L15 | O15: =P15*(1+Q15)+R15+S15+T15 | P15: 150 | Q15: 0 | R15: 120 | S15: 15 | T15: 0 | U15: =F15*O15
A16: 11 | B16: 30904006001 | C16: 吸顶式扬声器 | D16: 1、名称：吸顶式扬声器 2、安装方式：按图纸要求综合考虑 3、其他：包括但不限于以上内容，综合考虑按图纸、招标文件和规范要求而实施、完成这项工程的一切有关费用 | E16: 个 | F16: 10 | G16: =R16*$R$3 | H16: =P16*(1+Q16)*$P$3+S16*$S$3 | I16: =T16*$T$3 | J16: =(G16+H16+I16)*$J$3 | K16: =(G16+H16+I16+J16)*$K$3 | L16: =G16+H16+I16+J16+K16 | M16: =F16*L16 | O16: =P16*(1+Q16)+R16+S16+T16 | P16: 55 | Q16: 0 | R16: 10 | S16: 1 | T16: 0 | U16: =F16*O16
A17: 12 | B17: 30412001001 | C17: 配管 | D17: 1、名称:电气配管JDG20 2、配置形式:暗配 3、厚度:按国标 4、其他：包括但不限于以上内容，综合考虑按图纸、招标文件和规范要求而实施、完成这项工程的一切有关费用 | E17: m | F17: 578.69 | G17: =R17*$R$3 | H17: =P17*(1+Q17)*$P$3+S17*$S$3 | I17: =T17*$T$3 | J17: =(G17+H17+I17)*$J$3 | K17: =(G17+H17+I17+J17)*$K$3 | L17: =G17+H17+I17+J17+K17 | M17: =F17*L17 | O17: =P17*(1+Q17)+R17+S17+T17 | P17: 5.57 | Q17: 0.03 | R17: 9.12 | S17: 1.05 | T17: 0.54 | U17: =F17*O17
... A21: 16 | B21: 30412004011 | C21: 剔槽 | D21: 1、名称：线管剔槽 2、型号及规格：70×70mm 3、配置形式、部位：综合考虑 4、其他：包括但不限于以上内容，综合考虑按图纸、招标文件和规范要求而实施、完成这项工程的一切有关费用 | E21: m | F21: 50 | G21: =R21*$R$3 | H21: =P21*(1+Q21)*$P$3+S21*$S$3 | I21: =T21*$T$3 | J21: =(G21+H21+I21)*$J$3 | K21: =(G21+H21+I21+J21)*$K$3 | L21: =G21+H21+I21+J21+K21 | M21: =F21*L21 | O21: =P21*(1+Q21)+R21+S21+T21 | P21: 0 | Q21: 0 | R21: 20 | S21: 0 | T21: 2.5 | U21: =F21*O21
B22: 税前合价 | E22: 元 | M22: =SUM(M4:M21)
B23: 税金 | E23: 元 | M23: =M22*0.09
B24: 含税合价 | E24: 元 | M24: =M22+M23

Sheet 会所售楼处消防水工程
A1: 会所售楼处消防水工程工程量清单 | O1: 成本单价组成（投标人填写）
A2: 序号 | B2: 编码 | C2: 项目名称 | D2: 项目特征 | E2: 单位 | F2: 工程量 | G2: 人工费 | H2: 材料费 | I2: 机械费 | J2: 管理费 | K2: 利润 | L2: 不含税单价 | M2: 合价 | O2: 单价合计 | P2: 主材费 | Q2: 主材损耗率 | R2: 人工费 | S2: 辅材费 | T2: 机械费 | U2: 合计
J3: 0 | K3: 0 | P3: =架空层安装工程!$P$3 | R3: =架空层安装工程!$R$3 | S3: =架空层安装工程!$S$3 | T3: =架空层安装工程!$T$3
C4: 消防喷淋系统
A5: 2 | B5: 30901001002 | C5: 热浸镀锌钢管 | D5: 1、安装部位：室内 2、材质、规格：热浸镀锌钢管DN150 3、连接形式：按图纸要求 4、钢管镀锌设计要求：国标 5、压力试验及冲洗设计要求：液压试验，水冲洗 6、管道标识设计要求：按图纸要求 7、其他：包括但不限于以上内容，综合考虑按图纸、招标文件和规范要求而实施、完成这项工程的一切有关费用 | E5: m | F5: 11 | G5: =R5*$R$3 | H5: =P5*(1+Q5)*$P$3+S5*$S$3 | I5: =T5*$T$3 | J5: =(G5+H5+I5)*$J$3 | K5: =(G5+H5+I5+J5)*$K$3 | L5: =G5+H5+I5+J5+K5 | M5: =F5*L5 | O5: =P5*(1+Q5)+R5+S5+T5 | P5: 100 | Q5: 0.03 | R5: 45 | S5: 0 | T5: 4 | U5: =F5*O5
A6: 3 | B6: 30901001003 | C6: 热浸镀锌钢管 | D6: 1、安装部位：室内 2、材质、规格：热浸镀锌钢管DN100 3、连接形式：按图纸要求 4、钢管镀锌设计要求：国标 5、压力试验及冲洗设计要求：液压试验，水冲洗 6、管道标识设计要求：按图纸要求 7、其他：包括但不限于以上内容，综合考虑按图纸、招标文件和规范要求而实施、完成这项工程的一切有关费用 | E6: m | F6: 41 | G6: =R6*$R$3 | H6: =P6*(1+Q6)*$P$3+S6*$S$3 | I6: =T6*$T$3 | J6: =(G6+H6+I6)*$J$3 | K6: =(G6+H6+I6+J6)*$K$3 | L6: =G6+H6+I6+J6+K6 | M6: =F6*L6 | O6: =P6*(1+Q6)+R6+S6+T6 | P6: 64 | Q6: 0.03 | R6: 51 | S6: 0 | T6: 2.56 | U6: =F6*O6
A7: 4 | B7: 30901001004 | C7: 热浸镀锌钢管 | D7: 1、安装部位：室内 2、材质、规格：热浸镀锌钢管DN80 3、连接形式：按图纸要求 4、钢管镀锌设计要求：国标 5、压力试验及冲洗设计要求：液压试验，水冲洗 6、管道标识设计要求：按图纸要求 7、其他：包括但不限于以上内容，综合考虑按图纸、招标文件和规范要求而实施、完成这项工程的一切有关费用 | E7: m | F7: 54 | G7: =R7*$R$3 | H7: =P7*(1+Q7)*$P$3+S7*$S$3 | I7: =T7*$T$3 | J7: =(G7+H7+I7)*$J$3 | K7: =(G7+H7+I7+J7)*$K$3 | L7: =G7+H7+I7+J7+K7 | M7: =F7*L7 | O7: =P7*(1+Q7)+R7+S7+T7 | P7: 65 | Q7: 0.03 | R7: 30 | S7: 0 | T7: 1.62 | U7: =F7*O7
A8: 5 | B8: 30901001005 | C8: 热浸镀锌钢管 | D8: 1、安装部位：室内 2、材质、规格：热浸镀锌钢管DN65 3、连接形式：按图纸要求 4、钢管镀锌设计要求：国标 5、压力试验及冲洗设计要求：液压试验，水冲洗 6、管道标识设计要求：按图纸要求 7、其他：包括但不限于以上内容，综合考虑按图纸、招标文件和规范要求而实施、完成这项工程的一切有关费用 | E8: m | F8: 28 | G8: =R8*$R$3 | H8: =P8*(1+Q8)*$P$3+S8*$S$3 | I8: =T8*$T$3 | J8: =(G8+H8+I8)*$J$3 | K8: =(G8+H8+I8+J8)*$K$3 | L8: =G8+H8+I8+J8+K8 | M8: =F8*L8 | O8: =P8*(1+Q8)+R8+S8+T8 | P8: 40 | Q8: 0.03 | R8: 43 | S8: 0 | T8: 0.5 | U8: =F8*O8
A9: 6 | B9: 30901001006 | C9: 热浸镀锌钢管 | D9: 1、安装部位：室内 2、材质、规格：热浸镀锌钢管DN50 3、连接形式：按图纸要求 4、钢管镀锌设计要求：国标 5、压力试验及冲洗设计要求：液压试验，水冲洗 6、管道标识设计要求：按图纸要求 7、其他：包括但不限于以上内容，综合考虑按图纸、招标文件和规范要求而实施、完成这项工程的一切有关费用 | E9: m | F9: 83 | G9: =R9*$R$3 | H9: =P9*(1+Q9)*$P$3+S9*$S$3 | I9: =T9*$T$3 | J9: =(G9+H9+I9)*$J$3 | K9: =(G9+H9+I9+J9)*$K$3 | L9: =G9+H9+I9+J9+K9 | M9: =F9*L9 | O9: =P9*(1+Q9)+R9+S9+T9 | P9: 30 | Q9: 0.03 | R9: 22 | S9: 0 | T9: 0.5 | U9: =F9*O9
A10: 7 | B10: 30901001007 | C10: 热浸镀锌钢管 | D10: 1、安装部位：室内 2、材质、规格：热浸镀锌钢管DN40 3、连接形式：按图纸要求 4、钢管镀锌设计要求：国标 5、压力试验及冲洗设计要求：液压试验，水冲洗 6、管道标识设计要求：按图纸要求 7、其他：包括但不限于以上内容，综合考虑按图纸、招标文件和规范要求而实施、完成这项工程的一切有关费用 | E10: m | F10: 38 | G10: =R10*$R$3 | H10: =P10*(1+Q10)*$P$3+S10*$S$3 | I10: =T10*$T$3 | J10: =(G10+H10+I10)*$J$3 | K10: =(G10+H10+I10+J10)*$K$3 | L10: =G10+H10+I10+J10+K10 | M10: =F10*L10 | O10: =P10*(1+Q10)+R10+S10+T10 | P10: 22 | Q10: 0.03 | R10: 20 | S10: 0 | T10: 0.5 | U10: =F10*O10
A11: 8 | B11: 30901001008 | C11: 热浸镀锌钢管 | D11: 1、安装部位：室内 2、材质、规格：热浸镀锌钢管DN32 3、连接形式：按图纸要求 4、钢管镀锌设计要求：国标 5、压力试验及冲洗设计要求：液压试验，水冲洗 6、管道标识设计要求：按图纸要求 7、其他：包括但不限于以上内容，综合考虑按图纸、招标文件和规范要求而实施、完成这项工程的一切有关费用 | E11: m | F11: 175 | G11: =R11*$R$3 | H11: =P11*(1+Q11)*$P$3+S11*$S$3 | I11: =T11*$T$3 | J11: =(G11+H11+I11)*$J$3 | K11: =(G11+H11+I11+J11)*$K$3 | L11: =G11+H11+I11+J11+K11 | M11: =F11*L11 | O11: =P11*(1+Q11)+R11+S11+T11 | P11: 18 | Q11: 0.03 | R11: 18 | S11: 0 | T11: 0.5 | U11: =F11*O11
A12: 9 | B12: 30901001009 | C12: 热浸镀锌钢管 | D12: 1、安装部位：室内 2、材质、规格：热浸镀锌钢管DN25 3、连接形式：按图纸要求 4、钢管镀锌设计要求：国标 5、压力试验及冲洗设计要求：液压试验，水冲洗 6、管道标识设计要求：按图纸要求 7、其他：包括但不限于以上内容，综合考虑按图纸、招标文件和规范要求而实施、完成这项工程的一切有关费用 | E12: m | F12: 420 | G12: =R12*$R$3 | H12: =P12*(1+Q12)*$P$3+S12*$S$3 | I12: =T12*$T$3 | J12: =(G12+H12+I12)*$J$3 | K12: =(G12+H12+I12+J12)*$K$3 | L12: =G12+H12+I12+J12+K12 | M12: =F12*L12 | O12: =P12*(1+Q12)+R12+S12+T12 | P12: 14 | Q12: 0.03 | R12: 15 | S12: 0 | T12: 0.5 | U12: =F12*O12
A13: 10 | B13: 31301005003 | C13: 管道支架 | D13: 1、名称：管道支架 2、刷油防腐：除锈后樟丹防锈漆二道,醇酸磁漆二道 3、其他：包括但不限于以上内容，综合考虑按图纸、招标文件和规范要求而实施、完成这项工程的一切有关费用 | E13: Kg | F13: 425 | G13: =R13*$R$3 | H13: =P13*(1+Q13)*$P$3+S13*$S$3 | I13: =T13*$T$3 | J13: =(G13+H13+I13)*$J$3 | K13: =(G13+H13+I13+J13)*$K$3 | L13: =G13+H13+I13+J13+K13 | M13: =F13*L13 | O13: =P13*(1+Q13)+R13+S13+T13 | P13: 7 | Q13: 0 | R13: 1.5 | S13: 0.5 | T13: 0.3 | U13: =F13*O13
A14: 14 | B14: 31002001005 | C14: 铜截止阀 | D14: 1、类型：铜截止阀 2、材质：按图纸要求 3、规格、压力等级：DN25 4、其他：包括但不限于以上内容，综合考虑按图纸、招标文件和规范要求而实施、完成这项工程的一切有关费用 | E14: 个 | F14: 3 | G14: =R14*$R$3 | H14: =P14*(1+Q14)*$P$3+S14*$S$3 | I14: =T14*$T$3 | J14: =(G14+H14+I14)*$J$3 | K14: =(G14+H14+I14+J14)*$K$3 | L14: =G14+H14+I14+J14+K14 | M14: =F14*L14 | O14: =P14*(1+Q14)+R14+S14+T14 | P14: 34 | Q14: 0 | R14: 25.06 | S14: 12 | T14: 0 | U14: =F14*O14
A15: 15 | B15: 31002001023 | C15: 截止阀 | D15: 1、名称：截止阀 2、材质：符合设计要求材质 3、型号、规格：DN50 4、连接形式：按图纸要求 5、其他：包括但不限于以上内容，综合考虑按图纸、招标文件和规范要求而实施、完成这项工程的一切有关费用 | E15: 个 | F15: 2 | G15: =R15*$R$3 | H15: =P15*(1+Q15)*$P$3+S15*$S$3 | I15: =T15*$T$3 | J15: =(G15+H15+I15)*$J$3 | K15: =(G15+H15+I15+J15)*$K$3 | L15: =G15+H15+I15+J15+K15 | M15: =F15*L15 | O15: =P15*(1+Q15)+R15+S15+T15 | P15: 34 | Q15: 0 | R15: 25.06 | S15: 12 | T15: 0 | U15: =F15*O15
A16: 29 | B16: 30902007003 | C16: 直立式喷头 | D16: 1、名称：直立式喷头 2、型号、规格：公称动作温度 68°C 3、本体安装及调试 4、其他：包括但不限于以上内容，综合考虑按图纸、招标文件和规范要求而实施、完成这项工程的一切有关费用 | E16: 个 | F16: 213 | G16: =R16*$R$3 | H16: =P16*(1+Q16)*$P$3+S16*$S$3 | I16: =T16*$T$3 | J16: =(G16+H16+I16)*$J$3 | K16: =(G16+H16+I16+J16)*$K$3 | L16: =G16+H16+I16+J16+K16 | M16: =F16*L16 | O16: =P16*(1+Q16)+R16+S16+T16 | P16: 65 | Q16: 0 | R16: 42 | S16: 5 | T16: 0 | U16: =F16*O16
A17: 30 | B17: 30902007004 | C17: 直立式喷头 | D17: 1、名称：直立式喷头 2、型号、规格：公称动作温度 93°C 3、本体安装及调试 4、其他：包括但不限于以上内容，综合考虑按图纸、招标文件和规范要求而实施、完成这项工程的一切有关费用 | E17: 个 | F17: 2 | G17: =R17*$R$3 | H17: =P17*(1+Q17)*$P$3+S17*$S$3 | I17: =T17*$T$3 | J17: =(G17+H17+I17)*$J$3 | K17: =(G17+H17+I17+J17)*$K$3 | L17: =G17+H17+I17+J17+K17 | M17: =F17*L17 | O17: =P17*(1+Q17)+R17+S17+T17 | P17: 65 | Q17: 0 | R17: 42 | S17: 5 | T17: 0 | U17: =F17*O17
B18: 税前合价 | E18: 元 | M18: =SUM(M4:M17)
B19: 税金 | E19: 元 | M19: =M18*0.09
B20: 含税合价 | E20: 元 | M20: =M18+M19

Sheet 项目甲供清单
A1: 项目甲供材种类清单
A2: 序号 | B2: 材料名称 | C2: 供货及安装方式 | D2: 备注
A3: 1 | B3: 入户门 | C3: 供货+安装
A4: 2 | B4: 墙地砖 | C4: 仅供货
A5: 3 | B5: 户内门锁 | C5: 供货+安装
A6: 4 | B6: 户内门 | C6: 供货+安装
A7: 5 | B7: 星盆及龙头 | C7: 仅供货
A8: 6 | B8: 洁具 | C8: 仅供货
A9: 7 | B9: 龙头 | C9: 仅供货
A10: 8 | B10: 卫浴五金 | C10: 仅供货
A11: 9 | B11: 橱柜 | C11: 供货+安装
A12: 10 | B12: 镜浴柜 | C12: 供货+安装
A13: 11 | B13: 厨房电器 | C13: 供货+安装
A14: 12 | B14: 空调 | C14: 供货+安装
A15: 13 | B15: 电子门锁 | C15: 供货+安装
