Workbook

Sheet 汇总表
A1: 汇总表
A2: 序号 | B2: 单位工程 | C2: 含税合价 | D2: 不含税控制合价 | E2: 含税控制合价 | F2: 备注
A3: 1 | B3: 架空层安装工程 | C3: =架空层安装工程!$M$62 -> 266391 | D3: 88648.61 | E3: =D3*1.09 -> 96626.985
A4: 2 | B4: 会所售楼部安装工程 | C4: =会所售楼部安装工程!$M$141 -> 1775100.6 | D4: 597991.63 | E4: =D4*1.09 -> 651810.88
A5: 3 | B5: 样板房安装工程 | C5: =样板房安装工程!$M$261 -> 368565.65 | D5: 177912.2 | E5: =D5*1.09 -> 193924.3
A6: 4 | B6: 公共区域安装工程 | C6: =公共区域安装工程!$M$25 -> 249405.25 | D6: 103574.11 | E6: =D6*1.09 -> 112895.78
A7: 5 | B7: 户内交标安装工程 | C7: =户内交标安装工程!$M$66 -> 1736540.6 | D7: 1011928 | E7: =D7*1.09 -> 1103001.5
A8: 6 | B8: 会所售楼处消防电工程 | C8: =会所售楼处消防电工程!$M$24 -> 19632.936 | D8: 19891.5 | E8: =D8*1.09 -> 21681.735
A9: 7 | B9: 会所售楼处消防水工程 | C9: =会所售楼处消防水工程!$M$20 -> 57612.8 | D9: 63764.22 | E9: =D9*1.09 -> 69503
A10: 小计 | C10: =SUM(C3:C9) -> 4473248.8 | D10: =SUM(D3:D9) -> 2063710.2 | E10: =SUM(E3:E9) -> 2249444.2

Sheet 架空层安装工程
A1: 架空层安装工程工程量清单 | O1: 成本单价组成（投标人填写）
A2: 序号 | B2: 编码 | C2: 项目名称 | D2: 项目特征 | E2: 单位 | F2: 工程量 | G2: 人工费 | H2: 材料费 | I2: 机械费 | J2: 管理费 | K2: 利润 | L2: 不含税单价 | M2: 合价 | O2: 单价合计 | P2: 主材费 | Q2: 主材损耗率 | R2: 人工费 | S2: 辅材费 | T2: 机械费 | U2: 合计
J3: 0 | K3: 0 | P3: 1 | R3: 1 | S3: 1 | T3: 1
B4: 单位工程
C5: 电气工程
C6: 灯具
A7: 1 | B7: 30413002007 | C7: LA-01 筒灯 | D7: 1.名称：LA-01 筒灯 2.规格：12W 4000K 灯体尺寸Φ118*50mm 3.安装方式：嵌装 4.其他：包括但不限于满足图纸、招标文件、规范及验收要求等一切相关费用 | E7: 套 | F7: 100 | G7: =R7*$R$3 -> 20 | H7: =P7*(1+Q7)*$P$3+S7*$S$3 -> 76 | I7: =T7*$T$3 -> 0 | J7: =(G7+H7+I7)*$J$3 -> 0 | K7: =(G7+H7+I7+J7)*$K$3 -> 0 | L7: =G7+H7+I7+J7+K7 -> 96 | M7: =F7*L7 -> 9600 | O7: =P7*(1+Q7)+R7+S7+T7 -> 96 | P7: 70 | Q7: 0 | R7: 20 | S7: 6 | T7: 0 | U7: =F7*O7 -> 9600
A8: 2 | B8: 30413002008 | C8: LA-06 LED明装筒灯 | D8: 1.名称：LA-06 LED明装筒灯 2.规格：9W 4000K 灯体尺寸Φ150*100mm 3.安装方式：明装 4.其他：包括但不限于满足图纸、招标文件、规范及验收要求等一切相关费用 | E8: 套 | F8: 93 | G8: =R8*$R$3 -> 20 | H8: =P8*(1+Q8)*$P$3+S8*$S$3 -> 76 | I8: =T8*$T$3 -> 0 | J8: =(G8+H8+I8)*$J$3 -> 0 | K8: =(G8+H8+I8+J8)*$K$3 -> 0 | L8: =G8+H8+I8+J8+K8 -> 96 | M8: =F8*L8 -> 8928 | O8: =P8*(1+Q8)+R8+S8+T8 -> 96 | P8: 70 | Q8: 0 | R8: 20 | S8: 6 | T8: 0 | U8: =F8*O8 -> 8928
A9: 3 | B9: 30413002009 | C9: LA-03 LED灯带 | D9: 1.名称：LA-03 LED灯带 2.规格：8W/米 4000K 3.安装方式：天花 4.其他：包括但不限于满足图纸、招标文件、规范及验收要求等一切相关费用 | E9: m | F9: 63.63 | G9: =R9*$R$3 -> 12.5 | H9: =P9*(1+Q9)*$P$3+S9*$S$3 -> 20.81 | I9: =T9*$T$3 -> 0 | J9: =(G9+H9+I9)*$J$3 -> 0 | K9: =(G9+H9+I9+J9)*$K$3 -> 0 | L9: =G9+H9+I9+J9+K9 -> 33.31 | M9: =F9*L9 -> 2119.5153 | O9: =P9*(1+Q9)+R9+S9+T9 -> 33.31 | P9: 20.4 | Q9: 0 | R9: 12.5 | S9: 0.41 | T9: 0 | U9: =F9*O9 -> 2119.5153
A10: 4 | B10: 30413009002 | C10: LED 灯带驱动电源 | D10: 1.名称：LED 灯带驱动电源 2.规格：60W 工作电压：220V 输出电压：24V 3.尺寸：L140*W45*H29mm 4.其他：包括但不限于满足图纸、招标文件、规范及验收要求等一切相关费用 | E10: 个 | F10: 8 | G10: =R10*$R$3 -> 3 | H10: =P10*(1+Q10)*$P$3+S10*$S$3 -> 20.5 | I10: =T10*$T$3 -> 0 | J10: =(G10+H10+I10)*$J$3 -> 0 | K10: =(G10+H10+I10+J10)*$K$3 -> 0 | L10: =G10+H10+I10+J10+K10 -> 23.5 | M10: =F10*L10 -> 188 | O10: =P10*(1+Q10)+R10+S10+T10 -> 23.5 | P10: 20 | Q10: 0 | R10: 3 | S10: 0.5 | T10: 0 | U10: =F10*O10 -> 188
A11: 5 | B11: 30413002010 | C11: LA-05 吊装硬条灯 | D11: 1.名称：LA-05 吊装硬条灯 2.规格：4000K 3.安装方式：吊装 4.其他：包括但不限于满足图纸、招标文件、规范及验收要求等一切相关费用 | E11: m | F11: 79.02 | G11: =R11*$R$3 -> 15 | H11: =P11*(1+Q11)*$P$3+S11*$S$3 -> 182 | I11: =T11*$T$3 -> 0 | J11: =(G11+H11+I11)*$J$3 -> 0 | K11: =(G11+H11+I11+J11)*$K$3 -> 0 | L11: =G11+H11+I11+J11+K11 -> 197 | M11: =F11*L11 -> 15566.94 | O11: =P11*(1+Q11)+R11+S11+T11 -> 197 | P11: 180 | Q11: 0 | R11: 15 | S11: 2 | T11: 0 | U11: =F11*O11 -> 15566.94
A12: 6 | B12: 30413002011 | C12: LA-04 艺术吊灯 | D12: 1.名称：LA-04 艺术吊灯 2.规格：铁艺+铝材+玻璃 颜色：磨砂黑+烟灰灯罩 色温4000K 3.安装方式：吊装 4.其他：包括但不限于满足图纸、招标文件、规范及验收要求等一切相关费用 | E12: 套 | F12: 1 | G12: =R12*$R$3 -> 30 | H12: =P12*(1+Q12)*$P$3+S12*$S$3 -> 810 | I12: =T12*$T$3 -> 0 | J12: =(G12+H12+I12)*$J$3 -> 0 | K12: =(G12+H12+I12+J12)*$K$3 -> 0 | L12: =G12+H12+I12+J12+K12 -> 840 | M12: =F12*L12 -> 840 | O12: =P12*(1+Q12)+R12+S12+T12 -> 840 | P12: 800 | Q12: 0 | R12: 30 | S12: 10 | T12: 0 | U12: =F12*O12 -> 840
A13: 7 | B13: 30413002012 | C13: LA-07 LED云朵灯 | D13: 1.名称：LA-07 LED云朵灯 2.规格：48W 4000K 产品尺寸：L800*W35mm 3.安装方式：吊装 4.其他：包括但不限于满足图纸、招标文件、规范及验收要求等一切相关费用 | E13: 套 | F13: 2 | G13: =R13*$R$3 -> 20 | H13: =P13*(1+Q13)*$P$3+S13*$S$3 -> 283 | I13: =T13*$T$3 -> 0 | J13: =(G13+H13+I13)*$J$3 -> 0 | K13: =(G13+H13+I13+J13)*$K$3 -> 0 | L13: =G13+H13+I13+J13+K13 -> 303 | M13: =F13*L13 -> 606 | O13: =P13*(1+Q13)+R13+S13+T13 -> 303 | P13: 280 | Q13: 0 | R13: 20 | S13: 3 | T13: 0 | U13: =F13*O13 -> 606
C14: 开关插座 | U14: =F14*O14 -> 0
A15: 8 | B15: 30413013004 | C15: 照明开关 | D15: 1.名称：单联单控开关 2.规格：86*86mm 3.安装方式：暗装 4.其他：包括但不限于满足图纸、招标文件、规范及验收要求等一切相关费用 | E15: 套 | F15: 5 | G15: =R15*$R$3 -> 6.31 | H15: =P15*(1+Q15)*$P$3+S15*$S$3 -> 15.74 | I15: =T15*$T$3 -> 0 | J15: =(G15+H15+I15)*$J$3 -> 0 | K15: =(G15+H15+I15+J15)*$K$3 -> 0 | L15: =G15+H15+I15+J15+K15 -> 22.05 | M15: =F15*L15 -> 110.25 | O15: =P15*(1+Q15)+R15+S15+T15 -> 22.05 | P15: =公共区域安装工程!$P$14 -> 14.62 | Q15: =公共区域安装工程!$Q$14 -> 0 | R15: =公共区域安装工程!$R$14 -> 6.31 | S15: =公共区域安装工程!$S$14 -> 1.12 | T15: =公共区域安装工程!$T$14 -> 0 | U15: =F15*O15 -> 110.25
A16: 9 | B16: 30413013005 | C16: 照明开关 | D16: 1.名称：双联单控开关 2.规格：86*86mm 3.安装方式：暗装 4.其他：包括但不限于满足图纸、招标文件、规范及验收要求等一切相关费用 | E16: 套 | F16: 5 | G16: =R16*$R$3 -> 10 | H16: =P16*(1+Q16)*$P$3+S16*$S$3 -> 19.5 | I16: =T16*$T$3 -> 0 | J16: =(G16+H16+I16)*$J$3 -> 0 | K16: =(G16+H16+I16+J16)*$K$3 -> 0 | L16: =G16+H16+I16+J16+K16 -> 29.5 | M16: =F16*L16 -> 147.5 | O16: =P16*(1+Q16)+R16+S16+T16 -> 29.5 | P16: 18 | Q16: 0 | R16: 10 | S16: 1.5 | T16: 0 | U16: =F16*O16 -> 147.5
A17: 10 | B17: 30413013006 | C17: 照明开关 | D17: 1.名称：三联单控开关 2.规格：86*86mm 3.安装方式：暗装 4.其他：包括但不限于满足图纸、招标文件、规范及验收要求等一切相关费用 | E17: 套 | F17: 10 | G17: =R17*$R$3 -> 12 | H17: =P17*(1+Q17)*$P$3+S17*$S$3 -> 21.5 | I17: =T17*$T$3 -> 0 | J17: =(G17+H17+I17)*$J$3 -> 0 | K17: =(G17+H17+I17+J17)*$K$3 -> 0 | L17: =G17+H17+I17+J17+K17 -> 33.5 | M17: =F17*L17 -> 335 | O17: =P17*(1+Q17)+R17+S17+T17 -> 33.5 | P17: =公共区域安装工程!$P$15 -> 20 | Q17: =公共区域安装工程!$Q$15 -> 0 | R17: =公共区域安装工程!$R$15 -> 12 | S17: =公共区域安装工程!$S$15 -> 1.5 | T17: =公共区域安装工程!$T$15 -> 0 | U17: =F17*O17 -> 335
A18: 11 | B18: 30413014001 | C18: 插座 | D18: 1.名称：五孔插座 2.规格：86*86mm 3.安装方式：暗装 4.其他：包括但不限于满足图纸、招标文件、规范及验收要求等一切相关费用 | E18: 套 | F18: 14 | G18: =R18*$R$3 -> 6.31 | H18: =P18*(1+Q18)*$P$3+S18*$S$3 -> 15.74 | I18: =T18*$T$3 -> 0 | J18: =(G18+H18+I18)*$J$3 -> 0 | K18: =(G18+H18+I18+J18)*$K$3 -> 0 | L18: =G18+H18+I18+J18+K18 -> 22.05 | M18: =F18*L18 -> 308.7 | O18: =P18*(1+Q18)+R18+S18+T18 -> 22.05 | P18: =公共区域安装工程!$P$16 -> 14.62 | Q18: =公共区域安装工程!$Q$16 -> 0 | R18: =公共区域安装工程!$R$16 -> 6.31 | S18: =公共区域安装工程!$S$16 -> 1.12 | T18: =公共区域安装工程!$T$16 -> 0 | U18: =F18*O18 -> 308.7
A19: 12 | B19: 30413014002 | C19: 插座 | D19: 1.名称：地面五孔插座 2.规格：86*86mm 3.安装方式：暗装 4.其他：包括但不限于满足图纸、招标文件、规范及验收要求等一切相关费用 | E19: 套 | F19: 6 | G19: =R19*$R$3 -> 6.31 | H19: =P19*(1+Q19)*$P$3+S19*$S$3 -> 15.74 | I19: =T19*$T$3 -> 0 | J19: =(G19+H19+I19)*$J$3 -> 0 | K19: =(G19+H19+I19+J19)*$K$3 -> 0 | L19: =G19+H19+I19+J19+K19 -> 22.05 | M19: =F19*L19 -> 132.3 | O19: =P19*(1+Q19)+R19+S19+T19 -> 22.05 | P19: 14.62 | Q19: 0 | R19: 6.31 | S19: 1.12 | T19: 0 | U19: =F19*O19 -> 132.3
C20: 配线 | U20: =F20*O20 -> 0
A21: 13 | B21: 30412004002 | C21: 配线 | D21: 1.名称：电气配线 2.型号规格：WDZC-BYJ-2.5 3.安装方式：管内穿线 4.其他：包括但不限于满足图纸、招标文件、规范及验收要求等一切相关费用 | E21: m | F21: 3020.18 | G21: =R21*$R$3 -> 2.2 | H21: =P21*(1+Q21)*$P$3+S21*$S$3 -> 3.1884 | I21: =T21*$T$3 -> 0.02 | J21: =(G21+H21+I21)*$J$3 -> 0 | K21: =(G21+H21+I21+J21)*$K$3 -> 0 | L21: =G21+H21+I21+J21+K21 -> 5.4084 | M21: =F21*L21 -> 16334.342 | O21: =P21*(1+Q21)+R21+S21+T21 -> 5.4084 | P21: =公共区域安装工程!$P$17 -> 2.92 | Q21: =公共区域安装工程!$Q$17 -> 0.02 | R21: =公共区域安装工程!$R$17 -> 2.2 | S21: =公共区域安装工程!$S$17 -> 0.21 | T21: =公共区域安装工程!$T$17 -> 0.02 | U21: =F21*O21 -> 16334.342
A22: 14 | B22: 30412004003 | C22: 配线 | D22: 1.名称：电气配线 2.型号规格：WDZC-BYJ-6 3.安装方式：管内穿线 4.其他：包括但不限于满足图纸、招标文件、规范及验收要求等一切相关费用 | E22: m | F22: 372.91 | G22: =R22*$R$3 -> 15 | H22: =P22*(1+Q22)*$P$3+S22*$S$3 -> 137.138 | I22: =T22*$T$3 -> 1.07 | J22: =(G22+H22+I22)*$J$3 -> 0 | K22: =(G22+H22+I22+J22)*$K$3 -> 0 | L22: =G22+H22+I22+J22+K22 -> 153.208 | M22: =F22*L22 -> 57132.795 | O22: =P22*(1+Q22)+R22+S22+T22 -> 153.208 | P22: 133.4 | Q22: 0.02 | R22: 15 | S22: 1.07 | T22: 1.07 | U22: =F22*O22 -> 57132.795
A23: 15 | B23: 30412004004 | C23: 配线 | D23: 1.名称：电气配线 2.型号规格：RVS-4*1.0 3.安装方式：管内穿线 4.其他：包括但不限于满足图纸、招标文件、规范及验收要求等一切相关费用 | E23: m | F23: 87.49 | G23: =R23*$R$3 -> 5.2 | H23: =P23*(1+Q23)*$P$3+S23*$S$3 -> 4.106 | I23: =T23*$T$3 -> 0.05 | J23: =(G23+H23+I23)*$J$3 -> 0 | K23: =(G23+H23+I23+J23)*$K$3 -> 0 | L23: =G23+H23+I23+J23+K23 -> 9.356 | M23: =F23*L23 -> 818.55644 | O23: =P23*(1+Q23)+R23+S23+T23 -> 9.356 | P23: 3.8 | Q23: 0.02 | R23: 5.2 | S23: 0.23 | T23: 0.05 | U23: =F23*O23 -> 818.55644
C24: 空调工程 | U24: =F24*O24 -> 0
C25: 设备 | U25: =F25*O25 -> 0
A26: 16 | B26: 30701003001 | C26: 风管机 | D26: 1.名称：风管机 F22 2.规格：制冷量2.2kW 制热量2.6kW 风量480m3/h 机外静压10Pa 额定功率0.05kW 运转噪音≤37dB(A) 3.安装方式：吊装 4.其他：包括但不限于满足图纸、招标文件、规范及验收要求等一切相关费用 | E26: 台 | F26: 2 | G26: =R26*$R$3 -> 1000 | H26: =P26*(1+Q26)*$P$3+S26*$S$3 -> 4800 | I26: =T26*$T$3 -> 45 | J26: =(G26+H26+I26)*$J$3 -> 0 | K26: =(G26+H26+I26+J26)*$K$3 -> 0 | L26: =G26+H26+I26+J26+K26 -> 5845 | M26: =F26*L26 -> 11690 | O26: =P26*(1+Q26)+R26+S26+T26 -> 5845 | P26: 3600 | Q26: 0 | R26: 1000 | S26: 1200 | T26: 45 | U26: =F26*O26 -> 11690
A27: 17 | B27: 30701003002 | C27: 风管机 | D27: 1.名称：风管机 F32 2.规格：制冷量3.2kW 制热量3.6kW 风量570m3/h 机外静压30Pa 额定功率0.05kW 运转噪音≤37dB(A) 3.安装方式：吊装 4.其他：包括但不限于满足图纸、招标文件、规范及验收要求等一切相关费用 | E27: 台 | F27: 1 | G27: =R27*$R$3 -> 1000 | H27: =P27*(1+Q27)*$P$3+S27*$S$3 -> 4800 | I27: =T27*$T$3 -> 45 | J27: =(G27+H27+I27)*$J$3 -> 0 | K27: =(G27+H27+I27+J27)*$K$3 -> 0 | L27: =G27+H27+I27+J27+K27 -> 5845 | M27: =F27*L27 -> 5845 | O27: =P27*(1+Q27)+R27+S27+T27 -> 5845 | P27: 3600 | Q27: 0 | R27: 1000 | S27: 1200 | T27: 45 | U27: =F27*O27 -> 5845
A28: 18 | B28: 30701003003 | C28: 风管机 | D28: 1.名称：风管机 F45 2.规格：制冷量4.5kW 制热量5.0kW 风量800m3/h 机外静压30Pa 额定功率0.05kW 运转噪音≤37dB(A) 3.安装方式：吊装 4.其他：包括但不限于满足图纸、招标文件、规范及验收要求等一切相关费用 | E28: 台 | F28: 1 | G28: =R28*$R$3 -> 1000 | H28: =P28*(1+Q28)*$P$3+S28*$S$3 -> 4800 | I28: =T28*$T$3 -> 45 | J28: =(G28+H28+I28)*$J$3 -> 0 | K28: =(G28+H28+I28+J28)*$K$3 -> 0 | L28: =G28+H28+I28+J28+K28 -> 5845 | M28: =F28*L28 -> 5845 | O28: =P28*(1+Q28)+R28+S28+T28 -> 5845 | P28: 3600 | Q28: 0 | R28: 1000 | S28: 1200 | T28: 45 | U28: =F28*O28 -> 5845
A29: 19 | B29: 30701003004 | C29: 风管机 | D29: 1.名称：风管机 F56 2.规格：制冷量5.6kW 制热量6.3kW 风量550m3/h 机外静压10Pa 额定功率0.05kW 运转噪音≤37dB(A) 3.安装方式：吊装 4.其他：包括但不限于满足图纸、招标文件、规范及验收要求等一切相关费用 | E29: 台 | F29: 4 | G29: =R29*$R$3 -> 1000 | H29: =P29*(1+Q29)*$P$3+S29*$S$3 -> 4800 | I29: =T29*$T$3 -> 45 | J29: =(G29+H29+I29)*$J$3 -> 0 | K29: =(G29+H29+I29+J29)*$K$3 -> 0 | L29: =G29+H29+I29+J29+K29 -> 5845 | M29: =F29*L29 -> 23380 | O29: =P29*(1+Q29)+R29+S29+T29 -> 5845 | P29: 3600 | Q29: 0 | R29: 1000 | S29: 1200 | T29: 45 | U29: =F29*O29 -> 23380
A30: 20 | B30: 30701003006 | C30: 风管机 | D30: 1.名称：风管机 F63 2.规格：制冷量6.3kW 制热量7.1kW 风量1000m3/h 机外静压30Pa 额定功率0.11kW 运转噪音≤40dB(A) 3.安装方式：吊装 4.其他：包括但不限于满足图纸、招标文件、规范及验收要求等一切相关费用 | E30: 台 | F30: 1 | G30: =R30*$R$3 -> 1000 | H30: =P30*(1+Q30)*$P$3+S30*$S$3 -> 4800 | I30: =T30*$T$3 -> 45 | J30: =(G30+H30+I30)*$J$3 -> 0 | K30: =(G30+H30+I30+J30)*$K$3 -> 0 | L30: =G30+H30+I30+J30+K30 -> 5845 | M30: =F30*L30 -> 5845 | O30: =P30*(1+Q30)+R30+S30+T30 -> 5845 | P30: 3600 | Q30: 0 | R30: 1000 | S30: 1200 | T30: 45 | U30: =F30*O30 -> 5845
A31: 21 | B31: 30701003007 | C31: 风管机 | D31: 1.名称：风管机 F90 2.规格：制冷量9.0kW 制热量10.0kW 风量1450m3/h 机外静压30Pa 额定功率0.11kW 运转噪音≤40dB(A) 3.安装方式：吊装 4.其他：包括但不限于满足图纸、招标文件、规范及验收要求等一切相关费用 | E31: 台 | F31: 1 | G31: =R31*$R$3 -> 1000 | H31: =P31*(1+Q31)*$P$3+S31*$S$3 -> 4800 | I31: =T31*$T$3 -> 45 | J31: =(G31+H31+I31)*$J$3 -> 0 | K31: =(G31+H31+I31+J31)*$K$3 -> 0 | L31: =G31+H31+I31+J31+K31 -> 5845 | M31: =F31*L31 -> 5845 | O31: =P31*(1+Q31)+R31+S31+T31 -> 5845 | P31: 3600 | Q31: 0 | R31: 1000 | S31: 1200 | T31: 45 | U31: =F31*O31 -> 5845
A32: 22 | B32: 30701003005 | C32: 多联式室外机 | D32: 1.名称：多联式室外机 L-1#-1/2 2.规格：制冷量24.0kW 制热量26.0kW 风量10000m3/h 机外静压-Pa 额定功率7.6kW 运转噪音≤61dB(A) 3.安装方式：落地 4.其他：包括但不限于满足图纸、招标文件、规范及验收要求等一切相关费用 | E32: 台 | F32: 2 | G32: =R32*$R$3 -> 800 | H32: =P32*(1+Q32)*$P$3+S32*$S$3 -> 12080 | I32: =T32*$T$3 -> 60 | J32: =(G32+H32+I32)*$J$3 -> 0 | K32: =(G32+H32+I32+J32)*$K$3 -> 0 | L32: =G32+H32+I32+J32+K32 -> 12940 | M32: =F32*L32 -> 25880 | O32: =P32*(1+Q32)+R32+S32+T32 -> 12940 | P32: 12000 | Q32: 0 | R32: 800 | S32: 80 | T32: 60 | U32: =F32*O32 -> 25880
A33: 23 | B33: 30413013010 | C33: 空调温控面板 | D33: 1.名称：空调温控面板 2.规格：86*86mm 3.安装方式：暗装 4.其他：包括但不限于满足图纸、招标文件、规范及验收要求等一切相关费用 | E33: 套 | F33: 7 | G33: =R33*$R$3 -> 35 | H33: =P33*(1+Q33)*$P$3+S33*$S$3 -> 103 | I33: =T33*$T$3 -> 0 | J33: =(G33+H33+I33)*$J$3 -> 0 | K33: =(G33+H33+I33+J33)*$K$3 -> 0 | L33: =G33+H33+I33+J33+K33 -> 138 | M33: =F33*L33 -> 966 | O33: =P33*(1+Q33)+R33+S33+T33 -> 138 | P33: 95 | Q33: 0 | R33: 35 | S33: 8 | T33: 0 | U33: =F33*O33 -> 966
A34: 24 | B34: 30703007001 | C34: 单层百叶风口 | D34: 1.名称：单层百叶风口 2.周长：≤1800mm 3.规格：500*150 4.其他：包括但不限于满足图纸、招标文件、规范及验收要求等一切相关费用 | E34: 个 | F34: 4 | G34: =R34*$R$3 -> 20 | H34: =P34*(1+Q34)*$P$3+S34*$S$3 -> 81 | I34: =T34*$T$3 -> 0 | J34: =(G34+H34+I34)*$J$3 -> 0 | K34: =(G34+H34+I34+J34)*$K$3 -> 0 | L34: =G34+H34+I34+J34+K34 -> 101 | M34: =F34*L34 -> 404 | O34: =P34*(1+Q34)+R34+S34+T34 -> 101 | P34: 75 | Q34: 0 | R34: 20 | S34: 6 | T34: 0 | U34: =F34*O34 -> 404
A35: 25 | B35: 30703007006 | C35: 单层百叶风口 | D35: 1.名称：单层百叶风口 2.周长：≤1800mm 3.规格：600*150 4.其他：包括但不限于满足图纸、招标文件、规范及验收要求等一切相关费用 | E35: 个 | F35: 2 | G35: =R35*$R$3 -> 20 | H35: =P35*(1+Q35)*$P$3+S35*$S$3 -> 81 | I35: =T35*$T$3 -> 0 | J35: =(G35+H35+I35)*$J$3 -> 0 | K35: =(G35+H35+I35+J35)*$K$3 -> 0 | L35: =G35+H35+I35+J35+K35 -> 101 | M35: =F35*L35 -> 202 | O35: =P35*(1+Q35)+R35+S35+T35 -> 101 | P35: 75 | Q35: 0 | R35: 20 | S35: 6 | T35: 0 | U35: =F35*O35 -> 202
A36: 26 | B36: 30703007007 | C36: 单层百叶风口 | D36: 1.名称：单层百叶风口 2.周长：≤1800mm 3.规格：700*150 4.其他：包括但不限于满足图纸、招标文件、规范及验收要求等一切相关费用 | E36: 个 | F36: 2 | G36: =R36*$R$3 -> 20 | H36: =P36*(1+Q36)*$P$3+S36*$S$3 -> 81 | I36: =T36*$T$3 -> 0 | J36: =(G36+H36+I36)*$J$3 -> 0 | K36: =(G36+H36+I36+J36)*$K$3 -> 0 | L36: =G36+H36+I36+J36+K36 -> 101 | M36: =F36*L36 -> 202 | O36: =P36*(1+Q36)+R36+S36+T36 -> 101 | P36: 75 | Q36: 0 | R36: 20 | S36: 6 | T36: 0 | U36: =F36*O36 -> 202
A37: 27 | B37: 30703007004 | C37: 单层百叶风口 | D37: 1.名称：单层百叶风口 2.周长：≤3300mm 3.规格：900*150 4.其他：包括但不限于满足图纸、招标文件、规范及验收要求等一切相关费用 | E37: 个 | F37: 8 | G37: =R37*$R$3 -> 20 | H37: =P37*(1+Q37)*$P$3+S37*$S$3 -> 81 | I37: =T37*$T$3 -> 0 | J37: =(G37+H37+I37)*$J$3 -> 0 | K37: =(G37+H37+I37+J37)*$K$3 -> 0 | L37: =G37+H37+I37+J37+K37 -> 101 | M37: =F37*L37 -> 808 | O37: =P37*(1+Q37)+R37+S37+T37 -> 101 | P37: 75 | Q37: 0 | R37: 20 | S37: 6 | T37: 0 | U37: =F37*O37 -> 808
A38: 28 | B38: 30703007008 | C38: 单层百叶风口 | D38: 1.名称：单层百叶风口 2.周长：≤4200mm 3.规格：1250*150 4.其他：包括但不限于满足图纸、招标文件、规范及验收要求等一切相关费用 | E38: 个 | F38: 4 | G38: =R38*$R$3 -> 20 | H38: =P38*(1+Q38)*$P$3+S38*$S$3 -> 81 | I38: =T38*$T$3 -> 0 | J38: =(G38+H38+I38)*$J$3 -> 0 | K38: =(G38+H38+I38+J38)*$K$3 -> 0 | L38: =G38+H38+I38+J38+K38 -> 101 | M38: =F38*L38 -> 404 | O38: =P38*(1+Q38)+R38+S38+T38 -> 101 | P38: 75 | Q38: 0 | R38: 20 | S38: 6 | T38: 0 | U38: =F38*O38 -> 404
C39: 风管 | U39: =F39*O39 -> 0
A40: 29 | B40: 30702001001 | C40: 碳钢通风管道 | D40: 1.名称：矩形风管 2.材质：镀锌薄钢板 3.厚度：0.6mm 4.长边：≤1000mm 5.其他：包括但不限于满足图纸、招标文件、规范及验收要求等一切相关费用 | E40: m2 | F40: 6.28 | G40: =R40*$R$3 -> 48 | H40: =P40*(1+Q40)*$P$3+S40*$S$3 -> 99.55 | I40: =T40*$T$3 -> 2 | J40: =(G40+H40+I40)*$J$3 -> 0 | K40: =(G40+H40+I40+J40)*$K$3 -> 0 | L40: =G40+H40+I40+J40+K40 -> 149.55 | M40: =F40*L40 -> 939.174 | O40: =P40*(1+Q40)+R40+S40+T40 -> 149.55 | P40: 85 | Q40: 0.03 | R40: 48 | S40: 12 | T40: 2 | U40: =F40*O40 -> 939.174
A41: 30 | B41: 30702001002 | C41: 碳钢通风管道 | D41: 1.名称：矩形风管 2.材质：镀锌薄钢板 3.厚度：0.75mm 4.长边：≤1000mm 5.其他：包括但不限于满足图纸、招标文件、规范及验收要求等一切相关费用 | E41: m2 | F41: 27.07 | G41: =R41*$R$3 -> 48 | H41: =P41*(1+Q41)*$P$3+S41*$S$3 -> 99.55 | I41: =T41*$T$3 -> 2 | J41: =(G41+H41+I41)*$J$3 -> 0 | K41: =(G41+H41+I41+J41)*$K$3 -> 0 | L41: =G41+H41+I41+J41+K41 -> 149.55 | M41: =F41*L41 -> 4048.3185 | O41: =P41*(1+Q41)+R41+S41+T41 -> 149.55 | P41: 85 | Q41: 0.03 | R41: 48 | S41: 12 | T41: 2 | U41: =F41*O41 -> 4048.3185
A42: 31 | B42: 30702001003 | C42: 碳钢通风管道 | D42: 1.名称：矩形风管 2.材质：镀锌薄钢板 3.厚度：1.0mm 4.长边：≤1250mm 5.其他：包括但不限于满足图纸、招标文件、规范及验收要求等一切相关费用 | E42: m2 | F42: 20.66 | G42: =R42*$R$3 -> 48 | H42: =P42*(1+Q42)*$P$3+S42*$S$3 -> 99.55 | I42: =T42*$T$3 -> 2 | J42: =(G42+H42+I42)*$J$3 -> 0 | K42: =(G42+H42+I42+J42)*$K$3 -> 0 | L42: =G42+H42+I42+J42+K42 -> 149.55 | M42: =F42*L42 -> 3089.703 | O42: =P42*(1+Q42)+R42+S42+T42 -> 149.55 | P42: 85 | Q42: 0.03 | R42: 48 | S42: 12 | T42: 2 | U42: =F42*O42 -> 3089.703
A43: 32 | B43: 30703019001 | C43: 柔性接口 | D43: 1.名称：帆布软接口 2.材质：帆布 3.厚度：满足验收要求 4.其他：包括但不限于满足图纸、招标文件、规范及验收要求等一切相关费用 | E43: m2 | F43: 8.16 | G43: =R43*$R$3 -> 55 | H43: =P43*(1+Q43)*$P$3+S43*$S$3 -> 78.89 | I43: =T43*$T$3 -> 2.75 | J43: =(G43+H43+I43)*$J$3 -> 0 | K43: =(G43+H43+I43+J43)*$K$3 -> 0 | L43: =G43+H43+I43+J43+K43 -> 136.64 | M43: =F43*L43 -> 1114.9824 | O43: =P43*(1+Q43)+R43+S43+T43 -> 136.64 | P43: 19.49 | Q43: 0 | R43: 55 | S43: 59.4 | T43: 2.75 | U43: =F43*O43 -> 1114.9824
A44: 33 | B44: 31301005001 | C44: 风管支架刷油 | D44: 1.名称：风管支架刷油 2.按图纸及规范要求 3.其他：包括但不限于以上内容，综合考虑按图纸、招标文件和规范要求而实施、完成这项工程的一切有关费用 | E44: kg | F44: 208.7 | G44: =R44*$R$3 -> 5.77 | H44: =P44*(1+Q44)*$P$3+S44*$S$3 -> 6.87 | I44: =T44*$T$3 -> 1.21 | J44: =(G44+H44+I44)*$J$3 -> 0 | K44: =(G44+H44+I44+J44)*$K$3 -> 0 | L44: =G44+H44+I44+J44+K44 -> 13.85 | M44: =F44*L44 -> 2890.495 | O44: =P44*(1+Q44)+R44+S44+T44 -> 13.85 | P44: 6.87 | Q44: 0 | R44: 5.77 | S44: 0 | T44: 1.21 | U44: =F44*O44 -> 2890.495
A45: 34 | B45: 31208003001 | C45: 通风管道绝热 | D45: 1.名称：空调风管保温 2.材质：难燃级B1级橡塑保温材料，不燃A级铝箔贴面，湿阻因子≥10000，符合国家GB8624-2012中的管状绝热材料B标准 3.厚度：20mm 4.其他：包括但不限于满足图纸、招标文件、规范及验收要求等一切相关费用 | E45: m2 | F45: 47.31 | G45: =R45*$R$3 -> 48 | H45: =P45*(1+Q45)*$P$3+S45*$S$3 -> 412 | I45: =T45*$T$3 -> 2 | J45: =(G45+H45+I45)*$J$3 -> 0 | K45: =(G45+H45+I45+J45)*$K$3 -> 0 | L45: =G45+H45+I45+J45+K45 -> 462 | M45: =F45*L45 -> 21857.22 | O45: =P45*(1+Q45)+R45+S45+T45 -> 462 | P45: 400 | Q45: 0 | R45: 48 | S45: 12 | T45: 2 | U45: =F45*O45 -> 21857.22
A46: 35 | B46: 30704001001 | C46: 通风工程检测、调试 | D46: 1.名称：风管漏光试验、漏风试验 | E46: 系统 | F46: 1 | G46: =R46*$R$3 -> 380 | H46: =P46*(1+Q46)*$P$3+S46*$S$3 -> 600 | I46: =T46*$T$3 -> 20 | J46: =(G46+H46+I46)*$J$3 -> 0 | K46: =(G46+H46+I46+J46)*$K$3 -> 0 | L46: =G46+H46+I46+J46+K46 -> 1000 | M46: =F46*L46 -> 1000 | O46: =P46*(1+Q46)+R46+S46+T46 -> 1000 | P46: 400 | Q46: 0 | R46: 380 | S46: 200 | T46: 20 | U46: =F46*O46 -> 1000
C47: 水管 | U47: =F47*O47 -> 0
A48: 36 | B48: 31001005001 | C48: 铜管 | D48: 1.名称：紫铜管 2.规格：φ6.4 3.厚度：0.8mm 4.连接方式：钎焊连结 5.其他：包括但不限于满足图纸、招标文件、规范及验收要求等一切相关费用 | E48: m | F48: 24.46 | G48: =R48*$R$3 -> 9.64 | H48: =P48*(1+Q48)*$P$3+S48*$S$3 -> 13.1816 | I48: =T48*$T$3 -> 0 | J48: =(G48+H48+I48)*$J$3 -> 0 | K48: =(G48+H48+I48+J48)*$K$3 -> 0 | L48: =G48+H48+I48+J48+K48 -> 22.8216 | M48: =F48*L48 -> 558.21634 | O48: =P48*(1+Q48)+R48+S48+T48 -> 22.8216 | P48: 10.72 | Q48: 0.03 | R48: 9.64 | S48: 2.14 | T48: 0 | U48: =F48*O48 -> 558.21634
A49: 37 | B49: 31001005002 | C49: 铜管 | D49: 1.名称：紫铜管 2.规格：φ9.5 3.厚度：0.8mm 4.连接方式：钎焊连结 5.其他：包括但不限于满足图纸、招标文件、规范及验收要求等一切相关费用 | E49: m | F49: 35.16 | G49: =R49*$R$3 -> 14.29 | H49: =P49*(1+Q49)*$P$3+S49*$S$3 -> 17.7632 | I49: =T49*$T$3 -> 0 | J49: =(G49+H49+I49)*$J$3 -> 0 | K49: =(G49+H49+I49+J49)*$K$3 -> 0 | L49: =G49+H49+I49+J49+K49 -> 32.0532 | M49: =F49*L49 -> 1126.9905 | O49: =P49*(1+Q49)+R49+S49+T49 -> 32.0532 | P49: 14.44 | Q49: 0.03 | R49: 14.29 | S49: 2.89 | T49: 0 | U49: =F49*O49 -> 1126.9905
A50: 38 | B50: 31001005003 | C50: 铜管 | D50: 1.名称：紫铜管 2.规格：φ12.7 3.厚度：0.8mm 4.连接方式：钎焊连结 5.其他：包括但不限于满足图纸、招标文件、规范及验收要求等一切相关费用 | E50: m | F50: 24.46 | G50: =R50*$R$3 -> 19.09 | H50: =P50*(1+Q50)*$P$3+S50*$S$3 -> 19.0138 | I50: =T50*$T$3 -> 0 | J50: =(G50+H50+I50)*$J$3 -> 0 | K50: =(G50+H50+I50+J50)*$K$3 -> 0 | L50: =G50+H50+I50+J50+K50 -> 38.1038 | M50: =F50*L50 -> 932.01895 | O50: =P50*(1+Q50)+R50+S50+T50 -> 38.1038 | P50: 15.46 | Q50: 0.03 | R50: 19.09 | S50: 3.09 | T50: 0 | U50: =F50*O50 -> 932.01895
A51: 39 | B51: 31001005004 | C51: 铜管 | D51: 1.名称：紫铜管 2.规格：φ15.9 3.厚度：1.0mm 4.连接方式：钎焊连结 5.其他：包括但不限于满足图纸、招标文件、规范及验收要求等一切相关费用 | E51: m | F51: 16.04 | G51: =R51*$R$3 -> 23.89 | H51: =P51*(1+Q51)*$P$3+S51*$S$3 -> 26.4962 | I51: =T51*$T$3 -> 0 | J51: =(G51+H51+I51)*$J$3 -> 0 | K51: =(G51+H51+I51+J51)*$K$3 -> 0 | L51: =G51+H51+I51+J51+K51 -> 50.3862 | M51: =F51*L51 -> 808.19465 | O51: =P51*(1+Q51)+R51+S51+T51 -> 50.3862 | P51: 21.54 | Q51: 0.03 | R51: 23.89 | S51: 4.31 | T51: 0 | U51: =F51*O51 -> 808.19465
A52: 40 | B52: 31001005005 | C52: 铜管 | D52: 1.名称：紫铜管 2.规格：φ19.1 3.厚度：1.0mm 4.连接方式：钎焊连结 5.其他：包括但不限于满足图纸、招标文件、规范及验收要求等一切相关费用 | E52: m | F52: 9.37 | G52: =R52*$R$3 -> 28.7 | H52: =P52*(1+Q52)*$P$3+S52*$S$3 -> 35.8339 | I52: =T52*$T$3 -> 0 | J52: =(G52+H52+I52)*$J$3 -> 0 | K52: =(G52+H52+I52+J52)*$K$3 -> 0 | L52: =G52+H52+I52+J52+K52 -> 64.5339 | M52: =F52*L52 -> 604.68264 | O52: =P52*(1+Q52)+R52+S52+T52 -> 64.5339 | P52: 29.13 | Q52: 0.03 | R52: 28.7 | S52: 5.83 | T52: 0 | U52: =F52*O52 -> 604.68264
A53: 41 | B53: 31001005006 | C53: 铜管 | D53: 1.名称：紫铜管 2.规格：φ22.2 3.厚度：1.0mm 4.连接方式：钎焊连结 5.其他：包括但不限于满足图纸、招标文件、规范及验收要求等一切相关费用 | E53: m | F53: 9.75 | G53: =R53*$R$3 -> 33.34 | H53: =P53*(1+Q53)*$P$3+S53*$S$3 -> 39.6469 | I53: =T53*$T$3 -> 0 | J53: =(G53+H53+I53)*$J$3 -> 0 | K53: =(G53+H53+I53+J53)*$K$3 -> 0 | L53: =G53+H53+I53+J53+K53 -> 72.9869 | M53: =F53*L53 -> 711.62227 | O53: =P53*(1+Q53)+R53+S53+T53 -> 72.9869 | P53: 32.23 | Q53: 0.03 | R53: 33.34 | S53: 6.45 | T53: 0 | U53: =F53*O53 -> 711.62227
A54: 42 | B54: 31002001001 | C54: 分歧器 | D54: 1.名称：分歧器 2.规格：公称直径20mm以内 3.其他：包括但不限于满足图纸、招标文件、规范及验收要求等一切相关费用 | E54: 个 | F54: 8 | G54: =R54*$R$3 -> 94 | H54: =P54*(1+Q54)*$P$3+S54*$S$3 -> 177 | I54: =T54*$T$3 -> 4.7 | J54: =(G54+H54+I54)*$J$3 -> 0 | K54: =(G54+H54+I54+J54)*$K$3 -> 0 | L54: =G54+H54+I54+J54+K54 -> 275.7 | M54: =F54*L54 -> 2205.6 | O54: =P54*(1+Q54)+R54+S54+T54 -> 275.7 | P54: 118 | Q54: 0 | R54: 94 | S54: 59 | T54: 4.7 | U54: =F54*O54 -> 2205.6
A55: 43 | B55: 31001008002 | C55: 塑料管 | D55: 1.名称：UPVC管 2.规格：DN25 3.介质：冷凝水 4.连接方式：粘接 5.其他：包括但不限于满足图纸、招标文件、规范及验收要求等一切相关费用 | E55: m | F55: 36.98 | G55: =R55*$R$3 -> 22.09 | H55: =P55*(1+Q55)*$P$3+S55*$S$3 -> 8.76 | I55: =T55*$T$3 -> 0.04 | J55: =(G55+H55+I55)*$J$3 -> 0 | K55: =(G55+H55+I55+J55)*$K$3 -> 0 | L55: =G55+H55+I55+J55+K55 -> 30.89 | M55: =F55*L55 -> 1142.3122 | O55: =P55*(1+Q55)+R55+S55+T55 -> 30.89 | P55: 8.5 | Q55: 0 | R55: 22.09 | S55: 0.26 | T55: 0.04 | U55: =F55*O55 -> 1142.3122
A56: 44 | B56: 31001008003 | C56: 塑料管 | D56: 1.名称：UPVC管 2.规格：DN32 3.介质：冷凝水 4.连接方式：粘接 5.其他：包括但不限于满足图纸、招标文件、规范及验收要求等一切相关费用 | E56: m | F56: 7.5 | G56: =R56*$R$3 -> 23.68 | H56: =P56*(1+Q56)*$P$3+S56*$S$3 -> 11.86 | I56: =T56*$T$3 -> 0.05 | J56: =(G56+H56+I56)*$J$3 -> 0 | K56: =(G56+H56+I56+J56)*$K$3 -> 0 | L56: =G56+H56+I56+J56+K56 -> 35.59 | M56: =F56*L56 -> 266.925 | O56: =P56*(1+Q56)+R56+S56+T56 -> 35.59 | P56: 11.59 | Q56: 0 | R56: 23.68 | S56: 0.27 | T56: 0.05 | U56: =F56*O56 -> 266.925
A57: 45 | B57: 31001008004 | C57: 塑料管 | D57: 1.名称：UPVC管 2.规格：DN40 3.介质：冷凝水 4.连接方式：粘接 5.其他：包括但不限于满足图纸、招标文件、规范及验收要求等一切相关费用 | E57: m | F57: 9.32 | G57: =R57*$R$3 -> 23.68 | H57: =P57*(1+Q57)*$P$3+S57*$S$3 -> 20.44 | I57: =T57*$T$3 -> 0.06 | J57: =(G57+H57+I57)*$J$3 -> 0 | K57: =(G57+H57+I57+J57)*$K$3 -> 0 | L57: =G57+H57+I57+J57+K57 -> 44.18 | M57: =F57*L57 -> 411.7576 | O57: =P57*(1+Q57)+R57+S57+T57 -> 44.18 | P57: 20.12 | Q57: 0 | R57: 23.68 | S57: 0.32 | T57: 0.06 | U57: =F57*O57 -> 411.7576
A58: 46 | B58: 31208002001 | C58: 其他管道绝热 | D58: 1.名称：冷媒管保温 2.材质：难燃B1级橡塑 3.厚度：20mm 4.其他：包括但不限于满足图纸、招标文件、规范及验收要求等一切相关费用 | E58: m3 | F58: 0.27 | G58: =R58*$R$3 -> 120 | H58: =P58*(1+Q58)*$P$3+S58*$S$3 -> 410 | I58: =T58*$T$3 -> 5 | J58: =(G58+H58+I58)*$J$3 -> 0 | K58: =(G58+H58+I58+J58)*$K$3 -> 0 | L58: =G58+H58+I58+J58+K58 -> 535 | M58: =F58*L58 -> 144.45 | O58: =P58*(1+Q58)+R58+S58+T58 -> 535 | P58: 400 | Q58: 0 | R58: 120 | S58: 10 | T58: 5 | U58: =F58*O58 -> 144.45
A59: 47 | B59: 31208002002 | C59: 其他管道绝热 | D59: 1.名称：冷凝管保温 2.材质：难燃B1级橡塑 3.厚度：13mm 4.其他：包括但不限于满足图纸、招标文件、规范及验收要求等一切相关费用 | E59: m3 | F59: 0.11 | G59: =R59*$R$3 -> 120 | H59: =P59*(1+Q59)*$P$3+S59*$S$3 -> 410 | I59: =T59*$T$3 -> 5 | J59: =(G59+H59+I59)*$J$3 -> 0 | K59: =(G59+H59+I59+J59)*$K$3 -> 0 | L59: =G59+H59+I59+J59+K59 -> 535 | M59: =F59*L59 -> 58.85 | O59: =P59*(1+Q59)+R59+S59+T59 -> 535 | P59: 400 | Q59: 0 | R59: 120 | S59: 10 | T59: 5 | U59: =F59*O59 -> 58.85
B60: 税前合价 | E60: 元 | M60: =SUM(M4:M59) -> 244395.41
B61: 税金 | E61: 元 | M61: =$M$60*0.09 -> 21995.587
B62: 含税合价 | E62: 元 | M62: =$M$60+$M$61 -> 266391

Sheet 会所售楼部安装工程
A1: 会所售楼部安装工程工程量清单 | O1: 成本单价组成（投标人填写）
A2: 序号 | B2: 编码 | C2: 项目名称 | D2: 项目特征 | E2: 单位 | F2: 工程量 | G2: 人工费 | H2: 材料费 | I2: 机械费 | J2: 管理费 | K2: 利润 | L2: 不含税单价 | M2: 合价 | O2: 单价合计 | P2: 主材费 | Q2: 主材损耗率 | R2: 人工费 | S2: 辅材费 | T2: 机械费 | U2: 合计
J3: 0 | K3: 0 | P3: =架空层安装工程!$P$3 -> 1 | R3: =架空层安装工程!$R$3 -> 1 | S3: =架空层安装工程!$S$3 -> 1 | T3: =架空层安装工程!$T$3 -> 1
B4: 单位工程
C5: 电气工程
C6: 灯具、电器
A7: 1 | B7: 30413002001 | C7: L1 嵌入式LED可调射灯 | D7: 1.名称：L1 嵌入式LED可调射灯 2.规格：LED COB 15W 3000K±50 3.尺寸：φ77mm*H90mm 4.安装方式：嵌装 5.其他：包括但不限于满足图纸、招标文件、规范及验收要求等一切相关费用 | E7: 套 | F7: 68 | G7: =R7*$R$3 -> 115 | H7: =P7*(1+Q7)*$P$3+S7*$S$3 -> 137 | I7: =T7*$T$3 -> 4 | J7: =(G7+H7+I7)*$J$3 -> 0 | K7: =(G7+H7+I7+J7)*$K$3 -> 0 | L7: =G7+H7+I7+J7+K7 -> 256 | M7: =F7*L7 -> 17408 | O7: =P7*(1+Q7)+R7+S7+T7 -> 256 | P7: 135 | Q7: 0 | R7: 115 | S7: 2 | T7: 4 | U7: =F7*O7 -> 17408
A8: 2 | B8: 30413002002 | C8: L2 嵌入式LED筒灯 | D8: 1.名称：L2 嵌入式LED筒灯 2.规格：LED COB 15W 3000K±50 3.尺寸：φ77mm*H99mm 4.安装方式：嵌装 5.其他：包括但不限于满足图纸、招标文件、规范及验收要求等一切相关费用 | E8: 套 | F8: 16 | G8: =R8*$R$3 -> 18 | H8: =P8*(1+Q8)*$P$3+S8*$S$3 -> 126 | I8: =T8*$T$3 -> 8 | J8: =(G8+H8+I8)*$J$3 -> 0 | K8: =(G8+H8+I8+J8)*$K$3 -> 0 | L8: =G8+H8+I8+J8+K8 -> 152 | M8: =F8*L8 -> 2432 | O8: =P8*(1+Q8)+R8+S8+T8 -> 152 | P8: 120 | Q8: 0 | R8: 18 | S8: 6 | T8: 8 | U8: =F8*O8 -> 2432
A9: 3 | B9: 30413002003 | C9: L3 嵌入式LED可调射灯 | D9: 1.名称：L3 嵌入式LED可调射灯 2.规格：LED COB 7W 2700K±50 3.尺寸：φ77mm*H78mm 4.安装方式：嵌装 5.其他：包括但不限于满足图纸、招标文件、规范及验收要求等一切相关费用 | E9: 套 | F9: 156 | G9: =R9*$R$3 -> 115 | H9: =P9*(1+Q9)*$P$3+S9*$S$3 -> 137 | I9: =T9*$T$3 -> 4 | J9: =(G9+H9+I9)*$J$3 -> 0 | K9: =(G9+H9+I9+J9)*$K$3 -> 0 | L9: =G9+H9+I9+J9+K9 -> 256 | M9: =F9*L9 -> 39936 | O9: =P9*(1+Q9)+R9+S9+T9 -> 256 | P9: 135 | Q9: 0 | R9: 115 | S9: 2 | T9: 4 | U9: =F9*O9 -> 39936
A10: 4 | B10: 30413002004 | C10: L4 嵌入式LED可调射灯 | D10: 1.名称：L4 嵌入式LED可调射灯 2.规格：LED COB 9W 2700K±50 3.尺寸：φ77mm*H78mm 4.安装方式：嵌装 5.其他：包括但不限于满足图纸、招标文件、规范及验收要求等一切相关费用 | E10: 套 | F10: 21 | G10: =R10*$R$3 -> 115 | H10: =P10*(1+Q10)*$P$3+S10*$S$3 -> 137 | I10: =T10*$T$3 -> 4 | J10: =(G10+H10+I10)*$J$3 -> 0 | K10: =(G10+H10+I10+J10)*$K$3 -> 0 | L10: =G10+H10+I10+J10+K10 -> 256 | M10: =F10*L10 -> 5376 | O10: =P10*(1+Q10)+R10+S10+T10 -> 256 | P10: 135 | Q10: 0 | R10: 115 | S10: 2 | T10: 4 | U10: =F10*O10 -> 5376
A11: 5 | B11: 30413002005 | C11: L5 明装LED可调射灯 | D11: 1.名称：L5 明装LED可调射灯 2.规格：LED COB 15W 3500K±50 3.尺寸：L85mm*W85mm*H90mm 4.安装方式：明装 5.其他：包括但不限于满足图纸、招标文件、规范及验收要求等一切相关费用 | E11: 套 | F11: 4 | G11: =R11*$R$3 -> 115 | H11: =P11*(1+Q11)*$P$3+S11*$S$3 -> 137 | I11: =T11*$T$3 -> 4 | J11: =(G11+H11+I11)*$J$3 -> 0 | K11: =(G11+H11+I11+J11)*$K$3 -> 0 | L11: =G11+H11+I11+J11+K11 -> 256 | M11: =F11*L11 -> 1024 | O11: =P11*(1+Q11)+R11+S11+T11 -> 256 | P11: 135 | Q11: 0 | R11: 115 | S11: 2 | T11: 4 | U11: =F11*O11 -> 1024
A12: 6 | B12: 30413002006 | C12: L6 嵌入式LED可调射灯 | D12: 1.名称：L6 嵌入式LED可调射灯 2.规格：LED COB 12W 2700K±50 3.尺寸：φ77mm*H78mm 4.安装方式：嵌装 5.其他：包括但不限于满足图纸、招标文件、规范及验收要求等一切相关费用 | E12: 套 | F12: 2 | G12: =R12*$R$3 -> 115 | H12: =P12*(1+Q12)*$P$3+S12*$S$3 -> 137 | I12: =T12*$T$3 -> 4 | J12: =(G12+H12+I12)*$J$3 -> 0 | K12: =(G12+H12+I12+J12)*$K$3 -> 0 | L12: =G12+H12+I12+J12+K12 -> 256 | M12: =F12*L12 -> 512 | O12: =P12*(1+Q12)+R12+S12+T12 -> 256 | P12: 135 | Q12: 0 | R12: 115 | S12: 2 | T12: 4 | U12: =F12*O12 -> 512
A13: 7 | B13: 30413002007 | C13: L7 嵌入式LED可调射灯 | D13: 1.名称：L7 嵌入式LED可调射灯 2.规格：LED COB 12W 2700K±50 3.尺寸：φ77mm*H78mm 4.安装方式：嵌装 5.其他：包括但不限于满足图纸、招标文件、规范及验收要求等一切相关费用 | E13: 套 | F13: 11 | G13: =R13*$R$3 -> 115 | H13: =P13*(1+Q13)*$P$3+S13*$S$3 -> 137 | I13: =T13*$T$3 -> 4 | J13: =(G13+H13+I13)*$J$3 -> 0 | K13: =(G13+H13+I13+J13)*$K$3 -> 0 | L13: =G13+H13+I13+J13+K13 -> 256 | M13: =F13*L13 -> 2816 | O13: =P13*(1+Q13)+R13+S13+T13 -> 256 | P13: 135 | Q13: 0 | R13: 115 | S13: 2 | T13: 4 | U13: =F13*O13 -> 2816
A14: 8 | B14: 30413002008 | C14: L8 嵌入式LED可调射灯 | D14: 1.名称：L8 嵌入式LED可调射灯 2.规格：LED COB 7W 2700K±50 3.尺寸：φ77mm*H78mm 4.安装方式：嵌装 5.其他：包括但不限于满足图纸、招标文件、规范及验收要求等一切相关费用 | E14: 套 | F14: 7 | G14: =R14*$R$3 -> 115 | H14: =P14*(1+Q14)*$P$3+S14*$S$3 -> 137 | I14: =T14*$T$3 -> 4 | J14: =(G14+H14+I14)*$J$3 -> 0 | K14: =(G14+H14+I14+J14)*$K$3 -> 0 | L14: =G14+H14+I14+J14+K14 -> 256 | M14: =F14*L14 -> 1792 | O14: =P14*(1+Q14)+R14+S14+T14 -> 256 | P14: 135 | Q14: 0 | R14: 115 | S14: 2 | T14: 4 | U14: =F14*O14 -> 1792
A15: 9 | B15: 30413002009 | C15: L10 嵌入式LED可调射灯 | D15: 1.名称：L10 嵌入式LED可调射灯 2.规格：LED COB 7W 2700K±50 3.尺寸：φ77mm*H78mm 4.安装方式：嵌装 5.其他：包括但不限于满足图纸、招标文件、规范及验收要求等一切相关费用 | E15: 套 | F15: 20 | G15: =R15*$R$3 -> 115 | H15: =P15*(1+Q15)*$P$3+S15*$S$3 -> 137 | I15: =T15*$T$3 -> 4 | J15: =(G15+H15+I15)*$J$3 -> 0 | K15: =(G15+H15+I15+J15)*$K$3 -> 0 | L15: =G15+H15+I15+J15+K15 -> 256 | M15: =F15*L15 -> 5120 | O15: =P15*(1+Q15)+R15+S15+T15 -> 256 | P15: 135 | Q15: 0 | R15: 115 | S15: 2 | T15: 4 | U15: =F15*O15 -> 5120
A16: 10 | B16: 30413001001 | C16: L11 吊线办公灯 | D16: 1.名称：L11 吊线办公灯 2.规格：LED 30W 4000K±50 3.尺寸：L1206mm*W75mm*H73.5mm 4.安装方式：吊装 5.其他：包括但不限于满足图纸、招标文件、规范及验收要求等一切相关费用 | E16: 套 | F16: 7 | G16: =R16*$R$3 -> 18 | H16: =P16*(1+Q16)*$P$3+S16*$S$3 -> 126 | I16: =T16*$T$3 -> 8 | J16: =(G16+H16+I16)*$J$3 -> 0 | K16: =(G16+H16+I16+J16)*$K$3 -> 0 | L16: =G16+H16+I16+J16+K16 -> 152 | M16: =F16*L16 -> 1064 | O16: =P16*(1+Q16)+R16+S16+T16 -> 152 | P16: 120 | Q16: 0 | R16: 18 | S16: 6 | T16: 8 | U16: =F16*O16 -> 1064
A17: 11 | B17: 30413001002 | C17: L12 吸顶灯 | D17: 1.名称：L12 吸顶灯 2.规格：LED 18W 4000K±50 3.尺寸：Φ290mm*H54.5mm 4.安装方式：吸顶 5.其他：包括但不限于满足图纸、招标文件、规范及验收要求等一切相关费用 | E17: 套 | F17: 4 | G17: =R17*$R$3 -> 18 | H17: =P17*(1+Q17)*$P$3+S17*$S$3 -> 66 | I17: =T17*$T$3 -> 8 | J17: =(G17+H17+I17)*$J$3 -> 0 | K17: =(G17+H17+I17+J17)*$K$3 -> 0 | L17: =G17+H17+I17+J17+K17 -> 92 | M17: =F17*L17 -> 368 | O17: =P17*(1+Q17)+R17+S17+T17 -> 92 | P17: 60 | Q17: 0 | R17: 18 | S17: 6 | T17: 8 | U17: =F17*O17 -> 368
A18: 12 | B18: 30413004001 | C18: L13 LED地埋灯 | D18: 1.名称：L13 LED地埋灯 2.规格：LED 1W 2700K±50 3.尺寸：Φ42mm*H75mm 4.安装方式：埋地 5.其他：包括但不限于满足图纸、招标文件、规范及验收要求等一切相关费用 | E18: 套 | F18: 3 | G18: =R18*$R$3 -> 18 | H18: =P18*(1+Q18)*$P$3+S18*$S$3 -> 126 | I18: =T18*$T$3 -> 8 | J18: =(G18+H18+I18)*$J$3 -> 0 | K18: =(G18+H18+I18+J18)*$K$3 -> 0 | L18: =G18+H18+I18+J18+K18 -> 152 | M18: =F18*L18 -> 456 | O18: =P18*(1+Q18)+R18+S18+T18 -> 152 | P18: 120 | Q18: 0 | R18: 18 | S18: 6 | T18: 8 | U18: =F18*O18 -> 456
... A28: 22 | B28: 30413002018 | C28: R7 地面洗墙灯 | D28: 1.名称：R7 地面洗墙灯 2.规格：LED 18W 2700K±50 3.尺寸：1000*43*53mm，灯体截面29*45mm 4.安装方式：地面 5.其他：包括但不限于满足图纸、招标文件、规范及验收要求等一切相关费用 | E28: m | F28: 4 | G28: =R28*$R$3 -> 22 | H28: =P28*(1+Q28)*$P$3+S28*$S$3 -> 91 | I28: =T28*$T$3 -> 4 | J28: =(G28+H28+I28)*$J$3 -> 0 | K28: =(G28+H28+I28+J28)*$K$3 -> 0 | L28: =G28+H28+I28+J28+K28 -> 117 | M28: =F28*L28 -> 468 | O28: =P28*(1+Q28)+R28+S28+T28 -> 117 | P28: 85 | Q28: 0 | R28: 22 | S28: 6 | T28: 4 | U28: =F28*O28 -> 468
A29: 23 | B29: 30413009001 | C29: LED 灯带驱动电源 | D29: 1.名称：LED 灯带驱动电源 2.规格：60W 工作电压：220V 输出电压：24V 3.尺寸：L140*W45*H29mm 4.其他：包括但不限于满足图纸、招标文件、规范及验收要求等一切相关费用 | E29: 个 | F29: 280 | G29: =R29*$R$3 -> 3 | H29: =P29*(1+Q29)*$P$3+S29*$S$3 -> 20.5 | I29: =T29*$T$3 -> 0 | J29: =(G29+H29+I29)*$J$3 -> 0 | K29: =(G29+H29+I29+J29)*$K$3 -> 0 | L29: =G29+H29+I29+J29+K29 -> 23.5 | M29: =F29*L29 -> 6580 | O29: =P29*(1+Q29)+R29+S29+T29 -> 23.5 | P29: =架空层安装工程!$P$10 -> 20 | Q29: =架空层安装工程!$Q$10 -> 0 | R29: =架空层安装工程!$R$10 -> 3 | S29: =架空层安装工程!$S$10 -> 0.5 | T29: =架空层安装工程!$T$10 -> 0 | U29: =F29*O29 -> 6580
A30: 24 | B30: 30405017001 | C30: 洗碗机 | D30: 1.名称：洗碗机 2.规格：- 3.尺寸：详见物料表 4.其他：包括但不限于满足图纸、招标文件、规范及验收要求等一切相关费用 | E30: 台 | F30: 1 | G30: =R30*$R$3 -> 250 | H30: =P30*(1+Q30)*$P$3+S30*$S$3 -> 4235 | I30: =T30*$T$3 -> 8.5 | J30: =(G30+H30+I30)*$J$3 -> 0 | K30: =(G30+H30+I30+J30)*$K$3 -> 0 | L30: =G30+H30+I30+J30+K30 -> 4493.5 | M30: =F30*L30 -> 4493.5 | O30: =P30*(1+Q30)+R30+S30+T30 -> 4493.5 | P30: =样板房安装工程!$P$19 -> 4200 | Q30: =样板房安装工程!$Q$19 -> 0 | R30: =样板房安装工程!$R$19 -> 250 | S30: =样板房安装工程!$S$19 -> 35 | T30: =样板房安装工程!$T$19 -> 8.5 | U30: =F30*O30 -> 4493.5
C31: 开关插座
A32: 25 | B32: 30413013001 | C32: 照明开关 | D32: 1.名称：单联单控开关 2.规格：86*86mm 3.安装方式：暗装 4.其他：包括但不限于满足图纸、招标文件、规范及验收要求等一切相关费用 | E32: 套 | F32: 5 | G32: =R32*$R$3 -> 6.31 | H32: =P32*(1+Q32)*$P$3+S32*$S$3 -> 15.74 | I32: =T32*$T$3 -> 0 | J32: =(G32+H32+I32)*$J$3 -> 0 | K32: =(G32+H32+I32+J32)*$K$3 -> 0 | L32: =G32+H32+I32+J32+K32 -> 22.05 | M32: =F32*L32 -> 110.25 | O32: =P32*(1+Q32)+R32+S32+T32 -> 22.05 | P32: =公共区域安装工程!$P$14 -> 14.62 | Q32: =公共区域安装工程!$Q$14 -> 0 | R32: =公共区域安装工程!$R$14 -> 6.31 | S32: =公共区域安装工程!$S$14 -> 1.12 | T32: =公共区域安装工程!$T$14 -> 0 | U32: =F32*O32 -> 110.25
A33: 26 | B33: 30413013002 | C33: 照明开关 | D33: 1.名称：双联单控开关 2.规格：86*86mm 3.安装方式：暗装 4.其他：包括但不限于满足图纸、招标文件、规范及验收要求等一切相关费用 | E33: 套 | F33: 10 | G33: =R33*$R$3 -> 10 | H33: =P33*(1+Q33)*$P$3+S33*$S$3 -> 19.5 | I33: =T33*$T$3 -> 0 | J33: =(G33+H33+I33)*$J$3 -> 0 | K33: =(G33+H33+I33+J33)*$K$3 -> 0 | L33: =G33+H33+I33+J33+K33 -> 29.5 | M33: =F33*L33 -> 295 | O33: =P33*(1+Q33)+R33+S33+T33 -> 29.5 | P33: =架空层安装工程!$P$16 -> 18 | Q33: =架空层安装工程!$Q$16 -> 0 | R33: =架空层安装工程!$R$16 -> 10 | S33: =架空层安装工程!$S$16 -> 1.5 | T33: =架空层安装工程!$T$16 -> 0 | U33: =F33*O33 -> 295
A34: 27 | B34: 30413013003 | C34: 照明开关 | D34: 1.名称：三联单控开关 2.规格：86*86mm 3.安装方式：暗装 4.其他：包括但不限于满足图纸、招标文件、规范及验收要求等一切相关费用 | E34: 套 | F34: 23 | G34: =R34*$R$3 -> 12 | H34: =P34*(1+Q34)*$P$3+S34*$S$3 -> 21.5 | I34: =T34*$T$3 -> 0 | J34: =(G34+H34+I34)*$J$3 -> 0 | K34: =(G34+H34+I34+J34)*$K$3 -> 0 | L34: =G34+H34+I34+J34+K34 -> 33.5 | M34: =F34*L34 -> 770.5 | O34: =P34*(1+Q34)+R34+S34+T34 -> 33.5 | P34: =公共区域安装工程!$P$15 -> 20 | Q34: =公共区域安装工程!$Q$15 -> 0 | R34: =公共区域安装工程!$R$15 -> 12 | S34: =公共区域安装工程!$S$15 -> 1.5 | T34: =公共区域安装工程!$T$15 -> 0 | U34: =F34*O34 -> 770.5
A35: 28 | B35: 30413013004 | C35: 照明开关 | D35: 1.名称：卫生间排风开关 2.规格：86*86mm 3.安装方式：暗装 4.其他：包括但不限于满足图纸、招标文件、规范及验收要求等一切相关费用 | E35: 套 | F35: 4 | G35: =R35*$R$3 -> 6.31 | H35: =P35*(1+Q35)*$P$3+S35*$S$3 -> 15.74 | I35: =T35*$T$3 -> 0 | J35: =(G35+H35+I35)*$J$3 -> 0 | K35: =(G35+H35+I35+J35)*$K$3 -> 0 | L35: =G35+H35+I35+J35+K35 -> 22.05 | M35: =F35*L35 -> 88.2 | O35: =P35*(1+Q35)+R35+S35+T35 -> 22.05 | P35: 14.62 | Q35: 0 | R35: 6.31 | S35: 1.12 | T35: 0 | U35: =F35*O35 -> 88.2
A36: 29 | B36: 30413014001 | C36: 插座 | D36: 1.名称：三孔插座 2.规格：86*86mm 3.安装方式：暗装 4.其他：包括但不限于满足图纸、招标文件、规范及验收要求等一切相关费用 | E36: 套 | F36: 2 | G36: =R36*$R$3 -> 6.31 | H36: =P36*(1+Q36)*$P$3+S36*$S$3 -> 15.74 | I36: =T36*$T$3 -> 0 | J36: =(G36+H36+I36)*$J$3 -> 0 | K36: =(G36+H36+I36+J36)*$K$3 -> 0 | L36: =G36+H36+I36+J36+K36 -> 22.05 | M36: =F36*L36 -> 44.1 | O36: =P36*(1+Q36)+R36+S36+T36 -> 22.05 | P36: =户内交标安装工程!$P$27 -> 14.62 | Q36: =户内交标安装工程!$Q$27 -> 0 | R36: =户内交标安装工程!$R$27 -> 6.31 | S36: =户内交标安装工程!$S$27 -> 1.12 | T36: =户内交标安装工程!$T$27 -> 0 | U36: =F36*O36 -> 44.1
A37: 30 | B37: 30413014002 | C37: 插座 | D37: 1.名称：五孔插座 2.规格：86*86mm 3.安装方式：暗装 4.其他：包括但不限于满足图纸、招标文件、规范及验收要求等一切相关费用 | E37: 套 | F37: 63 | G37: =R37*$R$3 -> 6.31 | H37: =P37*(1+Q37)*$P$3+S37*$S$3 -> 15.74 | I37: =T37*$T$3 -> 0 | J37: =(G37+H37+I37)*$J$3 -> 0 | K37: =(G37+H37+I37+J37)*$K$3 -> 0 | L37: =G37+H37+I37+J37+K37 -> 22.05 | M37: =F37*L37 -> 1389.15 | O37: =P37*(1+Q37)+R37+S37+T37 -> 22.05 | P37: =公共区域安装工程!$P$16 -> 14.62 | Q37: =公共区域安装工程!$Q$16 -> 0 | R37: =公共区域安装工程!$R$16 -> 6.31 | S37: =公共区域安装工程!$S$16 -> 1.12 | T37: =公共区域安装工程!$T$16 -> 0 | U37: =F37*O37 -> 1389.15
A38: 31 | B38: 30413014003 | C38: 插座 | D38: 1.名称：五孔插座（带防溅盒） 2.规格：86*86mm 3.安装方式：暗装 4.其他：包括但不限于满足图纸、招标文件、规范及验收要求等一切相关费用 | E38: 套 | F38: 15 | G38: =R38*$R$3 -> 6.31 | H38: =P38*(1+Q38)*$P$3+S38*$S$3 -> 15.74 | I38: =T38*$T$3 -> 0 | J38: =(G38+H38+I38)*$J$3 -> 0 | K38: =(G38+H38+I38+J38)*$K$3 -> 0 | L38: =G38+H38+I38+J38+K38 -> 22.05 | M38: =F38*L38 -> 330.75 | O38: =P38*(1+Q38)+R38+S38+T38 -> 22.05 | P38: =样板房安装工程!$P$28 -> 14.62 | Q38: =样板房安装工程!$Q$28 -> 0 | R38: =样板房安装工程!$R$28 -> 6.31 | S38: =样板房安装工程!$S$28 -> 1.12 | T38: =样板房安装工程!$T$28 -> 0 | U38: =F38*O38 -> 330.75
A39: 32 | B39: 30413014004 | C39: 插座 | D39: 1.名称：五孔插座带开关 2.规格：86*86mm 3.安装方式：暗装 4.其他：包括但不限于满足图纸、招标文件、规范及验收要求等一切相关费用 | E39: 套 | F39: 21 | G39: =R39*$R$3 -> 6.31 | H39: =P39*(1+Q39)*$P$3+S39*$S$3 -> 15.74 | I39: =T39*$T$3 -> 0 | J39: =(G39+H39+I39)*$J$3 -> 0 | K39: =(G39+H39+I39+J39)*$K$3 -> 0 | L39: =G39+H39+I39+J39+K39 -> 22.05 | M39: =F39*L39 -> 463.05 | O39: =P39*(1+Q39)+R39+S39+T39 -> 22.05 | P39: =户内交标安装工程!$P$25 -> 14.62 | Q39: =户内交标安装工程!$Q$25 -> 0 | R39: =户内交标安装工程!$R$25 -> 6.31 | S39: =户内交标安装工程!$S$25 -> 1.12 | T39: =户内交标安装工程!$T$25 -> 0 | U39: =F39*O39 -> 463.05
A40: 33 | B40: 30413014005 | C40: 插座 | D40: 1.名称：五孔插座带开关（带防溅盒） 2.规格：86*86mm 3.安装方式：暗装 4.其他：包括但不限于满足图纸、招标文件、规范及验收要求等一切相关费用 | E40: 套 | F40: 4 | G40: =R40*$R$3 -> 6.31 | H40: =P40*(1+Q40)*$P$3+S40*$S$3 -> 15.74 | I40: =T40*$T$3 -> 0 | J40: =(G40+H40+I40)*$J$3 -> 0 | K40: =(G40+H40+I40+J40)*$K$3 -> 0 | L40: =G40+H40+I40+J40+K40 -> 22.05 | M40: =F40*L40 -> 88.2 | O40: =P40*(1+Q40)+R40+S40+T40 -> 22.05 | P40: =样板房安装工程!$P$31 -> 14.62 | Q40: =样板房安装工程!$Q$31 -> 0 | R40: =样板房安装工程!$R$31 -> 6.31 | S40: =样板房安装工程!$S$31 -> 1.12 | T40: =样板房安装工程!$T$31 -> 0 | U40: =F40*O40 -> 88.2
A41: 34 | B41: 30413014006 | C41: 插座 | D41: 1.名称：五孔地面插座 2.规格：86*86mm 3.安装方式：暗装 4.其他：包括但不限于满足图纸、招标文件、规范及验收要求等一切相关费用 | E41: 套 | F41: 51 | G41: =R41*$R$3 -> 6.31 | H41: =P41*(1+Q41)*$P$3+S41*$S$3 -> 15.74 | I41: =T41*$T$3 -> 0 | J41: =(G41+H41+I41)*$J$3 -> 0 | K41: =(G41+H41+I41+J41)*$K$3 -> 0 | L41: =G41+H41+I41+J41+K41 -> 22.05 | M41: =F41*L41 -> 1124.55 | O41: =P41*(1+Q41)+R41+S41+T41 -> 22.05 | P41: 14.62 | Q41: 0 | R41: 6.31 | S41: 1.12 | T41: 0 | U41: =F41*O41 -> 1124.55
C42: 配管配线
A43: 35 | B43: 30412001001 | C43: 配管 | D43: 1.名称：电气配管 2.规格：JDG20 3.安装方式：暗装 4.其他：包括但不限于满足图纸、招标文件、规范及验收要求等一切相关费用 | E43: m | F43: 2169.81 | G43: =R43*$R$3 -> 2.61 | H43: =P43*(1+Q43)*$P$3+S43*$S$3 -> 1.8 | I43: =T43*$T$3 -> 0.09 | J43: =(G43+H43+I43)*$J$3 -> 0 | K43: =(G43+H43+I43+J43)*$K$3 -> 0 | L43: =G43+H43+I43+J43+K43 -> 4.5 | M43: =F43*L43 -> 9764.145 | O43: =P43*(1+Q43)+R43+S43+T43 -> 4.5 | P43: 1.57 | Q43: 0 | R43: 2.61 | S43: 0.23 | T43: 0.09 | U43: =F43*O43 -> 9764.145
A44: 36 | B44: 30412001002 | C44: 配管 | D44: 1.名称：电气配管 2.规格：JDG25 3.安装方式：暗装 4.其他：包括但不限于满足图纸、招标文件、规范及验收要求等一切相关费用 | E44: m | F44: 324.48 | G44: =R44*$R$3 -> 10.8 | H44: =P44*(1+Q44)*$P$3+S44*$S$3 -> 7.135 | I44: =T44*$T$3 -> 0.2 | J44: =(G44+H44+I44)*$J$3 -> 0 | K44: =(G44+H44+I44+J44)*$K$3 -> 0 | L44: =G44+H44+I44+J44+K44 -> 18.135 | M44: =F44*L44 -> 5884.4448 | O44: =P44*(1+Q44)+R44+S44+T44 -> 18.135 | P44: 6.5 | Q44: 0.03 | R44: 10.8 | S44: 0.44 | T44: 0.2 | U44: =F44*O44 -> 5884.4448
A45: 37 | B45: 30412001003 | C45: 配管 | D45: 1.名称：电气配管 2.规格：PC20 3.安装方式：暗装 4.其他：包括但不限于满足图纸、招标文件、规范及验收要求等一切相关费用 | E45: m | F45: 616.28 | G45: =R45*$R$3 -> 8.5 | H45: =P45*(1+Q45)*$P$3+S45*$S$3 -> 6.66 | I45: =T45*$T$3 -> 0.2 | J45: =(G45+H45+I45)*$J$3 -> 0 | K45: =(G45+H45+I45+J45)*$K$3 -> 0 | L45: =G45+H45+I45+J45+K45 -> 15.36 | M45: =F45*L45 -> 9466.0608 | O45: =P45*(1+Q45)+R45+S45+T45 -> 15.36 | P45: 6 | Q45: 0.03 | R45: 8.5 | S45: 0.48 | T45: 0.2 | U45: =F45*O45 -> 9466.0608
A46: 38 | B46: 30412001004 | C46: 配管 | D46: 1.名称：电气配管 2.规格：PC25 3.安装方式：暗装 4.其他：包括但不限于满足图纸、招标文件、规范及验收要求等一切相关费用 | E46: m | F46: 932.93 | G46: =R46*$R$3 -> 8.5 | H46: =P46*(1+Q46)*$P$3+S46*$S$3 -> 6.66 | I46: =T46*$T$3 -> 0.2 | J46: =(G46+H46+I46)*$J$3 -> 0 | K46: =(G46+H46+I46+J46)*$K$3 -> 0 | L46: =G46+H46+I46+J46+K46 -> 15.36 | M46: =F46*L46 -> 14329.805 | O46: =P46*(1+Q46)+R46+S46+T46 -> 15.36 | P46: 6 | Q46: 0.03 | R46: 8.5 | S46: 0.48 | T46: 0.2 | U46: =F46*O46 -> 14329.805
A47: 39 | B47: 30412001005 | C47: 配管 | D47: 1.名称：电气配管 2.规格：PC32 3.安装方式：暗装 4.其他：包括但不限于满足图纸、招标文件、规范及验收要求等一切相关费用 | E47: m | F47: 24.68 | G47: =R47*$R$3 -> 8.5 | H47: =P47*(1+Q47)*$P$3+S47*$S$3 -> 6.66 | I47: =T47*$T$3 -> 0.2 | J47: =(G47+H47+I47)*$J$3 -> 0 | K47: =(G47+H47+I47+J47)*$K$3 -> 0 | L47: =G47+H47+I47+J47+K47 -> 15.36 | M47: =F47*L47 -> 379.0848 | O47: =P47*(1+Q47)+R47+S47+T47 -> 15.36 | P47: 6 | Q47: 0.03 | R47: 8.5 | S47: 0.48 | T47: 0.2 | U47: =F47*O47 -> 379.0848
A48: 40 | B48: 30412001006 | C48: 配管 | D48: 1.名称：金属软管 2.规格：DN20 3.安装方式：吊顶内安装 4.其他：包括但不限于满足图纸、招标文件、规范及验收要求等一切相关费用 | E48: m | F48: 686.43 | G48: =R48*$R$3 -> 7.6 | H48: =P48*(1+Q48)*$P$3+S48*$S$3 -> 8.993 | I48: =T48*$T$3 -> 0.2 | J48: =(G48+H48+I48)*$J$3 -> 0 | K48: =(G48+H48+I48+J48)*$K$3 -> 0 | L48: =G48+H48+I48+J48+K48 -> 16.793 | M48: =F48*L48 -> 11527.219 | O48: =P48*(1+Q48)+R48+S48+T48 -> 16.793 | P48: 8.1 | Q48: 0.03 | R48: 7.6 | S48: 0.65 | T48: 0.2 | U48: =F48*O48 -> 11527.219
A49: 41 | B49: 30412001007 | C49: 配管 | D49: 1.名称：金属软管 2.规格：DN25 3.安装方式：吊顶内安装 4.其他：包括但不限于满足图纸、招标文件、规范及验收要求等一切相关费用 | E49: m | F49: 286.28 | G49: =R49*$R$3 -> 8.5 | H49: =P49*(1+Q49)*$P$3+S49*$S$3 -> 10.545 | I49: =T49*$T$3 -> 0.2 | J49: =(G49+H49+I49)*$J$3 -> 0 | K49: =(G49+H49+I49+J49)*$K$3 -> 0 | L49: =G49+H49+I49+J49+K49 -> 19.245 | M49: =F49*L49 -> 5509.4586 | O49: =P49*(1+Q49)+R49+S49+T49 -> 19.245 | P49: 9.5 | Q49: 0.03 | R49: 8.5 | S49: 0.76 | T49: 0.2 | U49: =F49*O49 -> 5509.4586
A50: 42 | B50: 31301001001 | C50: 凿槽及修复 | D50: 1.名称：凿槽及修复 2.规格：70*70 3.部位：砖、混凝土结构综合考虑 4.其他：包括但不限于满足图纸、招标文件、规范及验收要求等一切相关费用 | E50: m | F50: 606.51 | G50: =R50*$R$3 -> 17.65 | H50: =P50*(1+Q50)*$P$3+S50*$S$3 -> 0 | I50: =T50*$T$3 -> 2.41 | J50: =(G50+H50+I50)*$J$3 -> 0 | K50: =(G50+H50+I50+J50)*$K$3 -> 0 | L50: =G50+H50+I50+J50+K50 -> 20.06 | M50: =F50*L50 -> 12166.591 | O50: =P50*(1+Q50)+R50+S50+T50 -> 20.06 | P50: 0 | Q50: 0 | R50: 17.65 | S50: 0 | T50: 2.41 | U50: =F50*O50 -> 12166.591
A51: 43 | B51: 30412006001 | C51: 接线盒 | D51: 1.名称：接线盒 2.材质：钢制 3.安装方式：暗装 4.其他：包括但不限于满足图纸、招标文件、规范及验收要求等一切相关费用 | E51: 个 | F51: 861 | G51: =R51*$R$3 -> 2.17 | H51: =P51*(1+Q51)*$P$3+S51*$S$3 -> 2.58 | I51: =T51*$T$3 -> 0 | J51: =(G51+H51+I51)*$J$3 -> 0 | K51: =(G51+H51+I51+J51)*$K$3 -> 0 | L51: =G51+H51+I51+J51+K51 -> 4.75 | M51: =F51*L51 -> 4089.75 | O51: =P51*(1+Q51)+R51+S51+T51 -> 4.75 | P51: 2.28 | Q51: 0 | R51: 2.17 | S51: 0.3 | T51: 0 | U51: =F51*O51 -> 4089.75
A52: 44 | B52: 30412006002 | C52: 开关（插座）盒 | D52: 1.名称：开关（插座）盒 2.材质：钢制 3.安装方式：暗装 4.其他：包括但不限于满足图纸、招标文件、规范及验收要求等一切相关费用 | E52: 个 | F52: 73 | G52: =R52*$R$3 -> 10 | H52: =P52*(1+Q52)*$P$3+S52*$S$3 -> 16 | I52: =T52*$T$3 -> 0 | J52: =(G52+H52+I52)*$J$3 -> 0 | K52: =(G52+H52+I52+J52)*$K$3 -> 0 | L52: =G52+H52+I52+J52+K52 -> 26 | M52: =F52*L52 -> 1898 | O52: =P52*(1+Q52)+R52+S52+T52 -> 26 | P52: 15 | Q52: 0 | R52: 10 | S52: 1 | T52: 0 | U52: =F52*O52 -> 1898
A53: 45 | B53: 30412006003 | C53: 开关（插座）盒 | D53: 1.名称：开关（插座）盒 2.材质：塑料 3.安装方式：暗装 4.其他：包括但不限于满足图纸、招标文件、规范及验收要求等一切相关费用 | E53: 个 | F53: 162 | G53: =R53*$R$3 -> 10 | H53: =P53*(1+Q53)*$P$3+S53*$S$3 -> 16 | I53: =T53*$T$3 -> 0 | J53: =(G53+H53+I53)*$J$3 -> 0 | K53: =(G53+H53+I53+J53)*$K$3 -> 0 | L53: =G53+H53+I53+J53+K53 -> 26 | M53: =F53*L53 -> 4212 | O53: =P53*(1+Q53)+R53+S53+T53 -> 26 | P53: 15 | Q53: 0 | R53: 10 | S53: 1 | T53: 0 | U53: =F53*O53 -> 4212
A54: 46 | B54: 30412004001 | C54: 配线 | D54: 1.名称：电气配线 2.型号规格：WDZC-BYJ-2.5 3.安装方式：管内穿线 4.其他：包括但不限于满足图纸、招标文件、规范及验收要求等一切相关费用 | E54: m | F54: 10389.06 | G54: =R54*$R$3 -> 2.2 | H54: =P54*(1+Q54)*$P$3+S54*$S$3 -> 3.1884 | I54: =T54*$T$3 -> 0.02 | J54: =(G54+H54+I54)*$J$3 -> 0 | K54: =(G54+H54+I54+J54)*$K$3 -> 0 | L54: =G54+H54+I54+J54+K54 -> 5.4084 | M54: =F54*L54 -> 56188.192 | O54: =P54*(1+Q54)+R54+S54+T54 -> 5.4084 | P54: =公共区域安装工程!$P$17 -> 2.92 | Q54: =公共区域安装工程!$Q$17 -> 0.02 | R54: =公共区域安装工程!$R$17 -> 2.2 | S54: =公共区域安装工程!$S$17 -> 0.21 | T54: =公共区域安装工程!$T$17 -> 0.02 | U54: =F54*O54 -> 56188.192
A55: 47 | B55: 30412004002 | C55: 配线 | D55: 1.名称：电气配线 2.型号规格：WDZC-BYJ-2.5 3.安装方式：线槽配线 4.其他：包括但不限于满足图纸、招标文件、规范及验收要求等一切相关费用 | E55: m | F55: 311.04 | G55: =R55*$R$3 -> 2.2 | H55: =P55*(1+Q55)*$P$3+S55*$S$3 -> 3.1884 | I55: =T55*$T$3 -> 0.02 | J55: =(G55+H55+I55)*$J$3 -> 0 | K55: =(G55+H55+I55+J55)*$K$3 -> 0 | L55: =G55+H55+I55+J55+K55 -> 5.4084 | M55: =F55*L55 -> 1682.2287 | O55: =P55*(1+Q55)+R55+S55+T55 -> 5.4084 | P55: 2.92 | Q55: 0.02 | R55: 2.2 | S55: 0.21 | T55: 0.02 | U55: =F55*O55 -> 1682.2287
A56: 48 | B56: 30412004003 | C56: 配线 | D56: 1.名称：电气配线 2.型号规格：WDZC-BYJ-4 3.安装方式：管内穿线 4.其他：包括但不限于满足图纸、招标文件、规范及验收要求等一切相关费用 | E56: m | F56: 3896.09 | G56: =R56*$R$3 -> 14 | H56: =P56*(1+Q56)*$P$3+S56*$S$3 -> 134.252 | I56: =T56*$T$3 -> 1.04 | J56: =(G56+H56+I56)*$J$3 -> 0 | K56: =(G56+H56+I56+J56)*$K$3 -> 0 | L56: =G56+H56+I56+J56+K56 -> 149.292 | M56: =F56*L56 -> 581655.07 | O56: =P56*(1+Q56)+R56+S56+T56 -> 149.292 | P56: 130.6 | Q56: 0.02 | R56: 14 | S56: 1.04 | T56: 1.04 | U56: =F56*O56 -> 581655.07
A57: 49 | B57: 30412004004 | C57: 配线 | D57: 1.名称：电气配线 2.型号规格：WDZC-BYJ-4 3.安装方式：线槽配线 4.其他：包括但不限于满足图纸、招标文件、规范及验收要求等一切相关费用 | E57: m | F57: 1846.08 | G57: =R57*$R$3 -> 21.2 | H57: =P57*(1+Q57)*$P$3+S57*$S$3 -> 36.754 | I57: =T57*$T$3 -> 0.21 | J57: =(G57+H57+I57)*$J$3 -> 0 | K57: =(G57+H57+I57+J57)*$K$3 -> 0 | L57: =G57+H57+I57+J57+K57 -> 58.164 | M57: =F57*L57 -> 107375.4 | O57: =P57*(1+Q57)+R57+S57+T57 -> 58.164 | P57: 35.2 | Q57: 0.02 | R57: 21.2 | S57: 0.85 | T57: 0.21 | U57: =F57*O57 -> 107375.4
A58: 50 | B58: 30412004005 | C58: 配线 | D58: 1.名称：电气配线 2.型号规格：WDZC-BYJ-6 3.安装方式：管内穿线 4.其他：包括但不限于满足图纸、招标文件、规范及验收要求等一切相关费用 | E58: m | F58: 96.51 | G58: =R58*$R$3 -> 15 | H58: =P58*(1+Q58)*$P$3+S58*$S$3 -> 137.138 | I58: =T58*$T$3 -> 1.07 | J58: =(G58+H58+I58)*$J$3 -> 0 | K58: =(G58+H58+I58+J58)*$K$3 -> 0 | L58: =G58+H58+I58+J58+K58 -> 153.208 | M58: =F58*L58 -> 14786.104 | O58: =P58*(1+Q58)+R58+S58+T58 -> 153.208 | P58: =架空层安装工程!$P$22 -> 133.4 | Q58: =架空层安装工程!$Q$22 -> 0.02 | R58: =架空层安装工程!$R$22 -> 15 | S58: =架空层安装工程!$S$22 -> 1.07 | T58: =架空层安装工程!$T$22 -> 1.07 | U58: =F58*O58 -> 14786.104
A59: 51 | B59: 30412004006 | C59: 配线 | D59: 1.名称：电气配线 2.型号规格：WDZC-BYJ-6 3.安装方式：线槽配线 4.其他：包括但不限于满足图纸、招标文件、规范及验收要求等一切相关费用 | E59: m | F59: 140.84 | G59: =R59*$R$3 -> 21.8 | H59: =P59*(1+Q59)*$P$3+S59*$S$3 -> 39.466 | I59: =T59*$T$3 -> 0.22 | J59: =(G59+H59+I59)*$J$3 -> 0 | K59: =(G59+H59+I59+J59)*$K$3 -> 0 | L59: =G59+H59+I59+J59+K59 -> 61.486 | M59: =F59*L59 -> 8659.6882 | O59: =P59*(1+Q59)+R59+S59+T59 -> 61.486 | P59: 37.8 | Q59: 0.02 | R59: 21.8 | S59: 0.91 | T59: 0.22 | U59: =F59*O59 -> 8659.6882
A60: 52 | B60: 30412004007 | C60: 配线 | D60: 1.名称：电气配线 2.型号规格：RVS-4*1.0 3.安装方式：管内穿线 4.其他：包括但不限于满足图纸、招标文件、规范及验收要求等一切相关费用 | E60: m | F60: 581.65 | G60: =R60*$R$3 -> 5.2 | H60: =P60*(1+Q60)*$P$3+S60*$S$3 -> 4.106 | I60: =T60*$T$3 -> 0.05 | J60: =(G60+H60+I60)*$J$3 -> 0 | K60: =(G60+H60+I60+J60)*$K$3 -> 0 | L60: =G60+H60+I60+J60+K60 -> 9.356 | M60: =F60*L60 -> 5441.9174 | O60: =P60*(1+Q60)+R60+S60+T60 -> 9.356 | P60: =架空层安装工程!$P$23 -> 3.8 | Q60: =架空层安装工程!$Q$23 -> 0.02 | R60: =架空层安装工程!$R$23 -> 5.2 | S60: =架空层安装工程!$S$23 -> 0.23 | T60: =架空层安装工程!$T$23 -> 0.05 | U60: =F60*O60 -> 5441.9174
C61: 给排水工程
C62: 给排水管
A63: 53 | B63: 31001008001 | C63: 冷水 PPR管 | D63: 1.名称：冷水 PPR管 2.规格：DN15 3.连接方式：热熔连接 4.压力试验及吹、洗要求：水压试验、水冲洗、消毒冲洗、管道标识等 5.其他：包括但不限于满足图纸、招标文件、规范及验收要求等一切相关费用 | E63: m | F63: 108.55 | G63: =R63*$R$3 -> 20 | H63: =P63*(1+Q63)*$P$3+S63*$S$3 -> 3.97 | I63: =T63*$T$3 -> 0.13 | J63: =(G63+H63+I63)*$J$3 -> 0 | K63: =(G63+H63+I63+J63)*$K$3 -> 0 | L63: =G63+H63+I63+J63+K63 -> 24.1 | M63: =F63*L63 -> 2616.055 | O63: =P63*(1+Q63)+R63+S63+T63 -> 24.1 | P63: 3.2 | Q63: 0 | R63: 20 | S63: 0.77 | T63: 0.13 | U63: =F63*O63 -> 2616.055
A64: 54 | B64: 31001008002 | C64: 冷水 PPR管 | D64: 1.名称：冷水 PPR管 2.规格：DN20 3.连接方式：热熔连接 4.压力试验及吹、洗要求：水压试验、水冲洗、消毒冲洗、管道标识等 5.其他：包括但不限于满足图纸、招标文件、规范及验收要求等一切相关费用 | E64: m | F64: 24.67 | G64: =R64*$R$3 -> 18 | H64: =P64*(1+Q64)*$P$3+S64*$S$3 -> 4.76 | I64: =T64*$T$3 -> 0.04 | J64: =(G64+H64+I64)*$J$3 -> 0 | K64: =(G64+H64+I64+J64)*$K$3 -> 0 | L64: =G64+H64+I64+J64+K64 -> 22.8 | M64: =F64*L64 -> 562.476 | O64: =P64*(1+Q64)+R64+S64+T64 -> 22.8 | P64: 4.5 | Q64: 0 | R64: 18 | S64: 0.26 | T64: 0.04 | U64: =F64*O64 -> 562.476
A65: 55 | B65: 31001008003 | C65: 冷水 PPR管 | D65: 1.名称：冷水 PPR管 2.规格：DN25 3.连接方式：热熔连接 4.压力试验及吹、洗要求：水压试验、水冲洗、消毒冲洗、管道标识等 5.其他：包括但不限于满足图纸、招标文件、规范及验收要求等一切相关费用 | E65: m | F65: 21.64 | G65: =R65*$R$3 -> 22.09 | H65: =P65*(1+Q65)*$P$3+S65*$S$3 -> 8.76 | I65: =T65*$T$3 -> 0.04 | J65: =(G65+H65+I65)*$J$3 -> 0 | K65: =(G65+H65+I65+J65)*$K$3 -> 0 | L65: =G65+H65+I65+J65+K65 -> 30.89 | M65: =F65*L65 -> 668.4596 | O65: =P65*(1+Q65)+R65+S65+T65 -> 30.89 | P65: 8.5 | Q65: 0 | R65: 22.09 | S65: 0.26 | T65: 0.04 | U65: =F65*O65 -> 668.4596
A66: 56 | B66: 31001008004 | C66: 冷水 PPR管 | D66: 1.名称：冷水 PPR管 2.规格：DN32 3.连接方式：热熔连接 4.压力试验及吹、洗要求：水压试验、水冲洗、消毒冲洗、管道标识等 5.其他：包括但不限于满足图纸、招标文件、规范及验收要求等一切相关费用 | E66: m | F66: 16.52 | G66: =R66*$R$3 -> 23.68 | H66: =P66*(1+Q66)*$P$3+S66*$S$3 -> 11.86 | I66: =T66*$T$3 -> 0.05 | J66: =(G66+H66+I66)*$J$3 -> 0 | K66: =(G66+H66+I66+J66)*$K$3 -> 0 | L66: =G66+H66+I66+J66+K66 -> 35.59 | M66: =F66*L66 -> 587.9468 | O66: =P66*(1+Q66)+R66+S66+T66 -> 35.59 | P66: 11.59 | Q66: 0 | R66: 23.68 | S66: 0.27 | T66: 0.05 | U66: =F66*O66 -> 587.9468
A67: 57 | B67: 31001008005 | C67: 热水 PPR管 | D67: 1.名称：热水 PPR管 2.规格：DN15 3.连接方式：热熔连接 4.压力试验及吹、洗要求：水压试验、水冲洗、消毒冲洗、管道标识等 5.其他：包括但不限于满足图纸、招标文件、规范及验收要求等一切相关费用 | E67: m | F67: 27.1 | G67: =R67*$R$3 -> 20 | H67: =P67*(1+Q67)*$P$3+S67*$S$3 -> 3.97 | I67: =T67*$T$3 -> 0.13 | J67: =(G67+H67+I67)*$J$3 -> 0 | K67: =(G67+H67+I67+J67)*$K$3 -> 0 | L67: =G67+H67+I67+J67+K67 -> 24.1 | M67: =F67*L67 -> 653.11 | O67: =P67*(1+Q67)+R67+S67+T67 -> 24.1 | P67: 3.2 | Q67: 0 | R67: 20 | S67: 0.77 | T67: 0.13 | U67: =F67*O67 -> 653.11
A68: 58 | B68: 31001008006 | C68: 热水 PPR管 | D68: 1.名称：热水 PPR管 2.规格：DN20 3.连接方式：热熔连接 4.压力试验及吹、洗要求：水压试验、水冲洗、消毒冲洗、管道标识等 5.其他：包括但不限于满足图纸、招标文件、规范及验收要求等一切相关费用 | E68: m | F68: 23.43 | G68: =R68*$R$3 -> 18 | H68: =P68*(1+Q68)*$P$3+S68*$S$3 -> 4.76 | I68: =T68*$T$3 -> 0.04 | J68: =(G68+H68+I68)*$J$3 -> 0 | K68: =(G68+H68+I68+J68)*$K$3 -> 0 | L68: =G68+H68+I68+J68+K68 -> 22.8 | M68: =F68*L68 -> 534.204 | O68: =P68*(1+Q68)+R68+S68+T68 -> 22.8 | P68: 4.5 | Q68: 0 | R68: 18 | S68: 0.26 | T68: 0.04 | U68: =F68*O68 -> 534.204
A69: 59 | B69: 31001008007 | C69: 热水 PPR管 | D69: 1.名称：热水 PPR管 2.规格：DN25 3.连接方式：热熔连接 4.压力试验及吹、洗要求：水压试验、水冲洗、消毒冲洗、管道标识等 5.其他：包括但不限于满足图纸、招标文件、规范及验收要求等一切相关费用 | E69: m | F69: 14.1 | G69: =R69*$R$3 -> 22.09 | H69: =P69*(1+Q69)*$P$3+S69*$S$3 -> 8.76 | I69: =T69*$T$3 -> 0.04 | J69: =(G69+H69+I69)*$J$3 -> 0 | K69: =(G69+H69+I69+J69)*$K$3 -> 0 | L69: =G69+H69+I69+J69+K69 -> 30.89 | M69: =F69*L69 -> 435.549 | O69: =P69*(1+Q69)+R69+S69+T69 -> 30.89 | P69: 8.5 | Q69: 0 | R69: 22.09 | S69: 0.26 | T69: 0.04 | U69: =F69*O69 -> 435.549
A70: 60 | B70: 31301001002 | C70: 凿槽及修复 | D70: 1.名称：凿槽及修复 2.规格：70*70 3.部位：砖、混凝土结构综合考虑 4.其他：包括但不限于满足图纸、招标文件、规范及验收要求等一切相关费用 | E70: m | F70: 51.2 | G70: =R70*$R$3 -> 17.65 | H70: =P70*(1+Q70)*$P$3+S70*$S$3 -> 0 | I70: =T70*$T$3 -> 2.41 | J70: =(G70+H70+I70)*$J$3 -> 0 | K70: =(G70+H70+I70+J70)*$K$3 -> 0 | L70: =G70+H70+I70+J70+K70 -> 20.06 | M70: =F70*L70 -> 1027.072 | O70: =P70*(1+Q70)+R70+S70+T70 -> 20.06 | P70: =$P$50 -> 0 | Q70: =$Q$50 -> 0 | R70: =$R$50 -> 17.65 | S70: =$S$50 -> 0 | T70: =$T$50 -> 2.41 | U70: =F70*O70 -> 1027.072
A71: 61 | B71: 31001008008 | C71: UPVC排水管 | D71: 1.名称：UPVC排水管 2.规格：DN50 3.连接方式：粘接 4.压力试验及吹、洗要求：水压试验、管道标识等 5.其他：包括但不限于满足图纸、招标文件、规范及验收要求等一切相关费用 | E71: m | F71: 18.49 | G71: =R71*$R$3 -> 24 | H71: =P71*(1+Q71)*$P$3+S71*$S$3 -> 16.27 | I71: =T71*$T$3 -> 0.23 | J71: =(G71+H71+I71)*$J$3 -> 0 | K71: =(G71+H71+I71+J71)*$K$3 -> 0 | L71: =G71+H71+I71+J71+K71 -> 40.5 | M71: =F71*L71 -> 748.845 | O71: =P71*(1+Q71)+R71+S71+T71 -> 40.5 | P71: =样板房安装工程!$P$46 -> 15 | Q71: =样板房安装工程!$Q$46 -> 0 | R71: =样板房安装工程!$R$46 -> 24 | S71: =样板房安装工程!$S$46 -> 1.27 | T71: =样板房安装工程!$T$46 -> 0.23 | U71: =F71*O71 -> 748.845
A72: 62 | B72: 31001008009 | C72: UPVC排水管 | D72: 1.名称：UPVC排水管 2.规格：DN75 3.连接方式：粘接 4.压力试验及吹、洗要求：水压试验、管道标识等 5.其他：包括但不限于满足图纸、招标文件、规范及验收要求等一切相关费用 | E72: m | F72: 41.77 | G72: =R72*$R$3 -> 55 | H72: =P72*(1+Q72)*$P$3+S72*$S$3 -> 28 | I72: =T72*$T$3 -> 3 | J72: =(G72+H72+I72)*$J$3 -> 0 | K72: =(G72+H72+I72+J72)*$K$3 -> 0 | L72: =G72+H72+I72+J72+K72 -> 86 | M72: =F72*L72 -> 3592.22 | O72: =P72*(1+Q72)+R72+S72+T72 -> 86 | P72: =样板房安装工程!$P$47 -> 25 | Q72: =样板房安装工程!$Q$47 -> 0 | R72: =样板房安装工程!$R$47 -> 55 | S72: =样板房安装工程!$S$47 -> 3 | T72: =样板房安装工程!$T$47 -> 3 | U72: =F72*O72 -> 3592.22
A73: 63 | B73: 31001008010 | C73: UPVC排水管 | D73: 1.名称：UPVC排水管 2.规格：DN100 3.连接方式：粘接 4.压力试验及吹、洗要求：水压试验、管道标识等 5.其他：包括但不限于满足图纸、招标文件、规范及验收要求等一切相关费用 | E73: m | F73: 31.35 | G73: =R73*$R$3 -> 30 | H73: =P73*(1+Q73)*$P$3+S73*$S$3 -> 38.12 | I73: =T73*$T$3 -> 0.38 | J73: =(G73+H73+I73)*$J$3 -> 0 | K73: =(G73+H73+I73+J73)*$K$3 -> 0 | L73: =G73+H73+I73+J73+K73 -> 68.5 | M73: =F73*L73 -> 2147.475 | O73: =P73*(1+Q73)+R73+S73+T73 -> 68.5 | P73: =样板房安装工程!$P$48 -> 36 | Q73: =样板房安装工程!$Q$48 -> 0 | R73: =样板房安装工程!$R$48 -> 30 | S73: =样板房安装工程!$S$48 -> 2.12 | T73: =样板房安装工程!$T$48 -> 0.38 | U73: =F73*O73 -> 2147.475
C74: 洁具五金
A75: 64 | B75: 31003006001 | C75: 轻智能马桶 | D75: 1.名称：轻智能马桶 2.型号规格：详见物料表 3.其他：包括但不限于满足图纸、招标文件、规范及验收要求等一切相关费用 | E75: 组 | F75: 7 | G75: =R75*$R$3 -> 100 | H75: =P75*(1+Q75)*$P$3+S75*$S$3 -> 120 | I75: =T75*$T$3 -> 0 | J75: =(G75+H75+I75)*$J$3 -> 0 | K75: =(G75+H75+I75+J75)*$K$3 -> 0 | L75: =G75+H75+I75+J75+K75 -> 220 | M75: =F75*L75 -> 1540 | O75: =P75*(1+Q75)+R75+S75+T75 -> 220 | P75: 0 | Q75: 0 | R75: 100 | S75: 120 | T75: 0 | U75: =F75*O75 -> 1540
A76: 65 | B76: 31003007001 | C76: 挂墙式自动感应小便器 | D76: 1.名称：挂墙式自动感应小便器 2.型号规格：详见物料表 3.其他：包括但不限于满足图纸、招标文件、规范及验收要求等一切相关费用 | E76: 组 | F76: 3 | G76: =R76*$R$3 -> 85 | H76: =P76*(1+Q76)*$P$3+S76*$S$3 -> 515 | I76: =T76*$T$3 -> 0 | J76: =(G76+H76+I76)*$J$3 -> 0 | K76: =(G76+H76+I76+J76)*$K$3 -> 0 | L76: =G76+H76+I76+J76+K76 -> 600 | M76: =F76*L76 -> 1800 | O76: =P76*(1+Q76)+R76+S76+T76 -> 600 | P76: 480 | Q76: 0 | R76: 85 | S76: 35 | T76: 0 | U76: =F76*O76 -> 1800
A77: 66 | B77: 31003010001 | C77: 淋浴器 | D77: 1.名称：淋浴花洒 2.型号规格：详见物料表 3.其他：包括但不限于满足图纸、招标文件、规范及验收要求等一切相关费用 | E77: 套 | F77: 2 | G77: =R77*$R$3 -> 90 | H77: =P77*(1+Q77)*$P$3+S77*$S$3 -> 1135 | I77: =T77*$T$3 -> 0 | J77: =(G77+H77+I77)*$J$3 -> 0 | K77: =(G77+H77+I77+J77)*$K$3 -> 0 | L77: =G77+H77+I77+J77+K77 -> 1225 | M77: =F77*L77 -> 2450 | O77: =P77*(1+Q77)+R77+S77+T77 -> 1225 | P77: 1100 | Q77: 0 | R77: 90 | S77: 35 | T77: 0 | U77: =F77*O77 -> 2450
A78: 67 | B78: 31003008001 | C78: 拖把池及龙头 | D78: 1.名称：拖把池及冷热龙头 2.型号规格：详见物料表 3.其他：包括但不限于满足图纸、招标文件、规范及验收要求等一切相关费用 | E78: 组 | F78: 1 | G78: =R78*$R$3 -> 65 | H78: =P78*(1+Q78)*$P$3+S78*$S$3 -> 375 | I78: =T78*$T$3 -> 0 | J78: =(G78+H78+I78)*$J$3 -> 0 | K78: =(G78+H78+I78+J78)*$K$3 -> 0 | L78: =G78+H78+I78+J78+K78 -> 440 | M78: =F78*L78 -> 440 | O78: =P78*(1+Q78)+R78+S78+T78 -> 440 | P78: 350 | Q78: 0 | R78: 65 | S78: 25 | T78: 0 | U78: =F78*O78 -> 440
A79: 68 | B79: 31003003001 | C79: 台下盆及龙头 | D79: 1.名称：洗手盆及冷热龙头 2.型号规格：详见物料表 3.其他：包括但不限于满足图纸、招标文件、规范及验收要求等一切相关费用 | E79: 组 | F79: 4 | G79: =R79*$R$3 -> 90 | H79: =P79*(1+Q79)*$P$3+S79*$S$3 -> 562 | I79: =T79*$T$3 -> 0 | J79: =(G79+H79+I79)*$J$3 -> 0 | K79: =(G79+H79+I79+J79)*$K$3 -> 0 | L79: =G79+H79+I79+J79+K79 -> 652 | M79: =F79*L79 -> 2608 | O79: =P79*(1+Q79)+R79+S79+T79 -> 652 | P79: 550 | Q79: 0 | R79: 90 | S79: 12 | T79: 0 | U79: =F79*O79 -> 2608
A80: 69 | B80: 31003004001 | C80: 吧台水槽及龙头 | D80: 1.名称：吧台水槽及冷热龙头 2.型号规格：详见物料表 3.其他：包括但不限于满足图纸、招标文件、规范及验收要求等一切相关费用 | E80: 组 | F80: 1 | G80: =R80*$R$3 -> 95 | H80: =P80*(1+Q80)*$P$3+S80*$S$3 -> 560 | I80: =T80*$T$3 -> 0 | J80: =(G80+H80+I80)*$J$3 -> 0 | K80: =(G80+H80+I80+J80)*$K$3 -> 0 | L80: =G80+H80+I80+J80+K80 -> 655 | M80: =F80*L80 -> 655 | O80: =P80*(1+Q80)+R80+S80+T80 -> 655 | P80: 520 | Q80: 0 | R80: 95 | S80: 40 | T80: 0 | U80: =F80*O80 -> 655
A81: 70 | B81: 31003014001 | C81: 隐藏地漏 | D81: 1.名称：隐藏地漏 2.型号规格：100*100*19mm 3.其他：包括但不限于满足图纸、招标文件、规范及验收要求等一切相关费用 | E81: 个 | F81: 14 | G81: =R81*$R$3 -> 18 | H81: =P81*(1+Q81)*$P$3+S81*$S$3 -> 40 | I81: =T81*$T$3 -> 0 | J81: =(G81+H81+I81)*$J$3 -> 0 | K81: =(G81+H81+I81+J81)*$K$3 -> 0 | L81: =G81+H81+I81+J81+K81 -> 58 | M81: =F81*L81 -> 812 | O81: =P81*(1+Q81)+R81+S81+T81 -> 58 | P81: 35 | Q81: 0 | R81: 18 | S81: 5 | T81: 0 | U81: =F81*O81 -> 812
A82: 71 | B82: 31002001001 | C82: 角阀 | D82: 1.名称：角阀（热水器、洗碗机、制冰机） 2.型号规格：DN15 3.其他：包括但不限于满足图纸、招标文件、规范及验收要求等一切相关费用 | E82: 个 | F82: 5 | G82: =R82*$R$3 -> 167.09 | H82: =P82*(1+Q82)*$P$3+S82*$S$3 -> 1504.2 | I82: =T82*$T$3 -> 12.03 | J82: =(G82+H82+I82)*$J$3 -> 0 | K82: =(G82+H82+I82+J82)*$K$3 -> 0 | L82: =G82+H82+I82+J82+K82 -> 1683.32 | M82: =F82*L82 -> 8416.6 | O82: =P82*(1+Q82)+R82+S82+T82 -> 1683.32 | P82: 1504.2 | Q82: 0 | R82: 167.09 | S82: 0 | T82: 12.03 | U82: =F82*O82 -> 8416.6
A83: 72 | B83: 31003014002 | C83: 纸巾架 | D83: 1.名称：纸巾架 2.型号规格：170*120*81mm 3.其他：包括但不限于满足图纸、招标文件、规范及验收要求等一切相关费用 | E83: 个 | F83: 7 | G83: =R83*$R$3 -> 34.95 | H83: =P83*(1+Q83)*$P$3+S83*$S$3 -> 193.39 | I83: =T83*$T$3 -> 4.66 | J83: =(G83+H83+I83)*$J$3 -> 0 | K83: =(G83+H83+I83+J83)*$K$3 -> 0 | L83: =G83+H83+I83+J83+K83 -> 233 | M83: =F83*L83 -> 1631 | O83: =P83*(1+Q83)+R83+S83+T83 -> 233 | P83: 181.74 | Q83: 0 | R83: 34.95 | S83: 11.65 | T83: 4.66 | U83: =F83*O83 -> 1631
A84: 73 | B84: 31003014003 | C84: 挂衣钩 | D84: 1.名称：挂衣钩 2.型号规格：详见物料表 3.其他：包括但不限于满足图纸、招标文件、规范及验收要求等一切相关费用 | E84: 个 | F84: 7 | G84: =R84*$R$3 -> 6.45 | H84: =P84*(1+Q84)*$P$3+S84*$S$3 -> 28 | I84: =T84*$T$3 -> 0 | J84: =(G84+H84+I84)*$J$3 -> 0 | K84: =(G84+H84+I84+J84)*$K$3 -> 0 | L84: =G84+H84+I84+J84+K84 -> 34.45 | M84: =F84*L84 -> 241.15 | O84: =P84*(1+Q84)+R84+S84+T84 -> 34.45 | P84: 28 | Q84: 0 | R84: 6.45 | S84: 0 | T84: 0 | U84: =F84*O84 -> 241.15
C85: 多联机空调
C86: 设备
A87: 74 | B87: 30701003001 | C87: 风管机 | D87: 1.名称：风管机 F25 2.规格：制冷量2.5kW 制热量3.2kW 风量450m3/h 机外静压30Pa 额定功率0.10kW 运转噪音≤37dB(A) 带冷凝水提升水泵 3.安装方式：吊装 4.其他：包括但不限于满足图纸、招标文件、规范及验收要求等一切相关费用 | E87: 台 | F87: 2 | G87: =R87*$R$3 -> 1000 | H87: =P87*(1+Q87)*$P$3+S87*$S$3 -> 4800 | I87: =T87*$T$3 -> 45 | J87: =(G87+H87+I87)*$J$3 -> 0 | K87: =(G87+H87+I87+J87)*$K$3 -> 0 | L87: =G87+H87+I87+J87+K87 -> 5845 | M87: =F87*L87 -> 11690 | O87: =P87*(1+Q87)+R87+S87+T87 -> 5845 | P87: 3600 | Q87: 0 | R87: 1000 | S87: 1200 | T87: 45 | U87: =F87*O87 -> 11690
A88: 75 | B88: 30701003002 | C88: 风管机 | D88: 1.名称：风管机 F36 2.规格：制冷量3.6kW 制热量4.2kW 风量780m3/h 机外静压50Pa 额定功率0.10kW 运转噪音≤37dB(A) 带冷凝水提升水泵 3.安装方式：吊装 4.其他：包括但不限于满足图纸、招标文件、规范及验收要求等一切相关费用 | E88: 台 | F88: 1 | G88: =R88*$R$3 -> 1000 | H88: =P88*(1+Q88)*$P$3+S88*$S$3 -> 4800 | I88: =T88*$T$3 -> 45 | J88: =(G88+H88+I88)*$J$3 -> 0 | K88: =(G88+H88+I88+J88)*$K$3 -> 0 | L88: =G88+H88+I88+J88+K88 -> 5845 | M88: =F88*L88 -> 5845 | O88: =P88*(1+Q88)+R88+S88+T88 -> 5845 | P88: 3600 | Q88: 0 | R88: 1000 | S88: 1200 | T88: 45 | U88: =F88*O88 -> 5845
A89: 76 | B89: 30701003003 | C89: 风管机 | D89: 1.名称：风管机 F40 2.规格：制冷量4.0kW 制热量4.5kW 风量780m3/h 机外静压50Pa 额定功率0.14kW 运转噪音≤37dB(A) 带冷凝水提升水泵 3.安装方式：吊装 4.其他：包括但不限于满足图纸、招标文件、规范及验收要求等一切相关费用 | E89: 台 | F89: 3 | G89: =R89*$R$3 -> 1000 | H89: =P89*(1+Q89)*$P$3+S89*$S$3 -> 4800 | I89: =T89*$T$3 -> 45 | J89: =(G89+H89+I89)*$J$3 -> 0 | K89: =(G89+H89+I89+J89)*$K$3 -> 0 | L89: =G89+H89+I89+J89+K89 -> 5845 | M89: =F89*L89 -> 17535 | O89: =P89*(1+Q89)+R89+S89+T89 -> 5845 | P89: 3600 | Q89: 0 | R89: 1000 | S89: 1200 | T89: 45 | U89: =F89*O89 -> 17535
A90: 77 | B90: 30701003004 | C90: 风管机 | D90: 1.名称：风管机 F50 2.规格：制冷量5.0kW 制热量5.6kW 风量900m3/h 机外静压50Pa 额定功率0.17kW 运转噪音≤37dB(A) 带冷凝水提升水泵 3.安装方式：吊装 4.其他：包括但不限于满足图纸、招标文件、规范及验收要求等一切相关费用 | E90: 台 | F90: 3 | G90: =R90*$R$3 -> 1000 | H90: =P90*(1+Q90)*$P$3+S90*$S$3 -> 4800 | I90: =T90*$T$3 -> 45 | J90: =(G90+H90+I90)*$J$3 -> 0 | K90: =(G90+H90+I90+J90)*$K$3 -> 0 | L90: =G90+H90+I90+J90+K90 -> 5845 | M90: =F90*L90 -> 17535 | O90: =P90*(1+Q90)+R90+S90+T90 -> 5845 | P90: 3600 | Q90: 0 | R90: 1000 | S90: 1200 | T90: 45 | U90: =F90*O90 -> 17535
A91: 78 | B91: 30701003005 | C91: 风管机 | D91: 1.名称：风管机 F90 2.规格：制冷量9.0kW 制热量10kW 风量1000m3/h 机外静压50Pa 额定功率0.28kW 运转噪音≤40dB(A) 带冷凝水提升水泵 3.安装方式：吊装 4.其他：包括但不限于满足图纸、招标文件、规范及验收要求等一切相关费用 | E91: 台 | F91: 1 | G91: =R91*$R$3 -> 1000 | H91: =P91*(1+Q91)*$P$3+S91*$S$3 -> 4800 | I91: =T91*$T$3 -> 45 | J91: =(G91+H91+I91)*$J$3 -> 0 | K91: =(G91+H91+I91+J91)*$K$3 -> 0 | L91: =G91+H91+I91+J91+K91 -> 5845 | M91: =F91*L91 -> 5845 | O91: =P91*(1+Q91)+R91+S91+T91 -> 5845 | P91: 3600 | Q91: 0 | R91: 1000 | S91: 1200 | T91: 45 | U91: =F91*O91 -> 5845
A92: 79 | B92: 30701003006 | C92: 风管机 | D92: 1.名称：风管机 F100 2.规格：制冷量10.0kW 制热量11.2kW 风量1400m3/h 机外静压50Pa 额定功率0.28kW 运转噪音≤40dB(A) 带冷凝水提升水泵 3.安装方式：吊装 4.其他：包括但不限于满足图纸、招标文件、规范及验收要求等一切相关费用 | E92: 台 | F92: 3 | G92: =R92*$R$3 -> 1000 | H92: =P92*(1+Q92)*$P$3+S92*$S$3 -> 4800 | I92: =T92*$T$3 -> 45 | J92: =(G92+H92+I92)*$J$3 -> 0 | K92: =(G92+H92+I92+J92)*$K$3 -> 0 | L92: =G92+H92+I92+J92+K92 -> 5845 | M92: =F92*L92 -> 17535 | O92: =P92*(1+Q92)+R92+S92+T92 -> 5845 | P92: 3600 | Q92: 0 | R92: 1000 | S92: 1200 | T92: 45 | U92: =F92*O92 -> 17535
A93: 80 | B93: 30701003007 | C93: 风管机 | D93: 1.名称：风管机 F112 2.规格：制冷量11.2kW 制热量12.5kW 风量1400m3/h 机外静压50Pa 额定功率0.28kW 运转噪音≤40dB(A) 带冷凝水提升水泵 3.安装方式：吊装 4.其他：包括但不限于满足图纸、招标文件、规范及验收要求等一切相关费用 | E93: 台 | F93: 8 | G93: =R93*$R$3 -> 1000 | H93: =P93*(1+Q93)*$P$3+S93*$S$3 -> 4800 | I93: =T93*$T$3 -> 45 | J93: =(G93+H93+I93)*$J$3 -> 0 | K93: =(G93+H93+I93+J93)*$K$3 -> 0 | L93: =G93+H93+I93+J93+K93 -> 5845 | M93: =F93*L93 -> 46760 | O93: =P93*(1+Q93)+R93+S93+T93 -> 5845 | P93: 3600 | Q93: 0 | R93: 1000 | S93: 1200 | T93: 45 | U93: =F93*O93 -> 46760
A94: 81 | B94: 30701003008 | C94: 风管机 | D94: 1.名称：风管机 F140 2.规格：制冷量14.0kW 制热量16.3kW 风量2220m3/h 机外静压90Pa 额定功率0.28kW 运转噪音≤40dB(A) 带冷凝水提升水泵 3.安装方式：吊装 4.其他：包括但不限于满足图纸、招标文件、规范及验收要求等一切相关费用 | E94: 台 | F94: 3 | G94: =R94*$R$3 -> 1000 | H94: =P94*(1+Q94)*$P$3+S94*$S$3 -> 4800 | I94: =T94*$T$3 -> 45 | J94: =(G94+H94+I94)*$J$3 -> 0 | K94: =(G94+H94+I94+J94)*$K$3 -> 0 | L94: =G94+H94+I94+J94+K94 -> 5845 | M94: =F94*L94 -> 17535 | O94: =P94*(1+Q94)+R94+S94+T94 -> 5845 | P94: 3600 | Q94: 0 | R94: 1000 | S94: 1200 | T94: 45 | U94: =F94*O94 -> 17535
A95: 82 | B95: 30701003009 | C95: 风管机 | D95: 1.名称：风管机 F160 2.规格：制冷量16.0kW 制热量18.0kW 风量2300m3/h 机外静压90Pa 额定功率0.4kW 运转噪音≤45dB(A) 带冷凝水提升水泵 3.安装方式：吊装 4.其他：包括但不限于满足图纸、招标文件、规范及验收要求等一切相关费用 | E95: 台 | F95: 6 | G95: =R95*$R$3 -> 1000 | H95: =P95*(1+Q95)*$P$3+S95*$S$3 -> 4800 | I95: =T95*$T$3 -> 45 | J95: =(G95+H95+I95)*$J$3 -> 0 | K95: =(G95+H95+I95+J95)*$K$3 -> 0 | L95: =G95+H95+I95+J95+K95 -> 5845 | M95: =F95*L95 -> 35070 | O95: =P95*(1+Q95)+R95+S95+T95 -> 5845 | P95: 3600 | Q95: 0 | R95: 1000 | S95: 1200 | T95: 45 | U95: =F95*O95 -> 35070
A96: 83 | B96: 30701003010 | C96: 多联式室外机 | D96: 1.名称：多联式室外机 L-1 2.规格：制冷量170.0kW 制热量190.0kW 风量50400m3/h 机外静压-Pa 额定功率49.2kW 运转噪音≤61dB(A) 3.安装方式：落地 4.其他：包括但不限于满足图纸、招标文件、规范及验收要求等一切相关费用 | E96: 台 | F96: 1 | G96: =R96*$R$3 -> 800 | H96: =P96*(1+Q96)*$P$3+S96*$S$3 -> 12080 | I96: =T96*$T$3 -> 60 | J96: =(G96+H96+I96)*$J$3 -> 0 | K96: =(G96+H96+I96+J96)*$K$3 -> 0 | L96: =G96+H96+I96+J96+K96 -> 12940 | M96: =F96*L96 -> 12940 | O96: =P96*(1+Q96)+R96+S96+T96 -> 12940 | P96: 12000 | Q96: 0 | R96: 800 | S96: 80 | T96: 60 | U96: =F96*O96 -> 12940
A97: 84 | B97: 30701003011 | C97: 多联式室外机 | D97: 1.名称：多联式室外机 L-2 2.规格：制冷量61.5kW 制热量69.0kW 风量20700m3/h 机外静压-Pa 额定功率16.4kW 运转噪音≤61dB(A) 3.安装方式：落地 4.其他：包括但不限于满足图纸、招标文件、规范及验收要求等一切相关费用 | E97: 台 | F97: 1 | G97: =R97*$R$3 -> 800 | H97: =P97*(1+Q97)*$P$3+S97*$S$3 -> 12080 | I97: =T97*$T$3 -> 60 | J97: =(G97+H97+I97)*$J$3 -> 0 | K97: =(G97+H97+I97+J97)*$K$3 -> 0 | L97: =G97+H97+I97+J97+K97 -> 12940 | M97: =F97*L97 -> 12940 | O97: =P97*(1+Q97)+R97+S97+T97 -> 12940 | P97: 12000 | Q97: 0 | R97: 800 | S97: 80 | T97: 60 | U97: =F97*O97 -> 12940
A98: 85 | B98: 30701003012 | C98: 多联式室外机 | D98: 1.名称：多联式室外机 L-3 2.规格：制冷量68.0kW 制热量75.0kW 风量21000m3/h 机外静压-Pa 额定功率18.4kW 运转噪音≤61dB(A) 3.安装方式：落地 4.其他：包括但不限于满足图纸、招标文件、规范及验收要求等一切相关费用 | E98: 台 | F98: 1 | G98: =R98*$R$3 -> 800 | H98: =P98*(1+Q98)*$P$3+S98*$S$3 -> 12080 | I98: =T98*$T$3 -> 60 | J98: =(G98+H98+I98)*$J$3 -> 0 | K98: =(G98+H98+I98+J98)*$K$3 -> 0 | L98: =G98+H98+I98+J98+K98 -> 12940 | M98: =F98*L98 -> 12940 | O98: =P98*(1+Q98)+R98+S98+T98 -> 12940 | P98: 12000 | Q98: 0 | R98: 800 | S98: 80 | T98: 60 | U98: =F98*O98 -> 12940
A99: 86 | B99: 30413013005 | C99: 空调温控面板 | D99: 1.名称：空调温控面板 2.规格：86*86mm 3.安装方式：暗装 4.其他：包括但不限于满足图纸、招标文件、规范及验收要求等一切相关费用 | E99: 套 | F99: 30 | G99: =R99*$R$3 -> 35 | H99: =P99*(1+Q99)*$P$3+S99*$S$3 -> 103 | I99: =T99*$T$3 -> 0 | J99: =(G99+H99+I99)*$J$3 -> 0 | K99: =(G99+H99+I99+J99)*$K$3 -> 0 | L99: =G99+H99+I99+J99+K99 -> 138 | M99: =F99*L99 -> 4140 | O99: =P99*(1+Q99)+R99+S99+T99 -> 138 | P99: =架空层安装工程!$P$33 -> 95 | Q99: =架空层安装工程!$Q$33 -> 0 | R99: =架空层安装工程!$R$33 -> 35 | S99: =架空层安装工程!$S$33 -> 8 | T99: =架空层安装工程!$T$33 -> 0 | U99: =F99*O99 -> 4140
C100: 风管
A101: 87 | B101: 30702001001 | C101: 碳钢通风管道 | D101: 1.名称：矩形风管 2.材质：镀锌薄钢板 3.厚度：0.6mm 4.长边：≤1000mm 5.其他：包括但不限于满足图纸、招标文件、规范及验收要求等一切相关费用 | E101: m2 | F101: 44.37 | G101: =R101*$R$3 -> 48 | H101: =P101*(1+Q101)*$P$3+S101*$S$3 -> 99.55 | I101: =T101*$T$3 -> 2 | J101: =(G101+H101+I101)*$J$3 -> 0 | K101: =(G101+H101+I101+J101)*$K$3 -> 0 | L101: =G101+H101+I101+J101+K101 -> 149.55 | M101: =F101*L101 -> 6635.5335 | O101: =P101*(1+Q101)+R101+S101+T101 -> 149.55 | P101: =架空层安装工程!$P$40 -> 85 | Q101: =架空层安装工程!$Q$40 -> 0.03 | R101: =架空层安装工程!$R$40 -> 48 | S101: =架空层安装工程!$S$40 -> 12 | T101: =架空层安装工程!$T$40 -> 2 | U101: =F101*O101 -> 6635.5335
A102: 88 | B102: 30702001002 | C102: 碳钢通风管道 | D102: 1.名称：矩形风管 2.材质：镀锌薄钢板 3.厚度：0.75mm 4.长边：≤1000mm 5.其他：包括但不限于满足图纸、招标文件、规范及验收要求等一切相关费用 | E102: m2 | F102: 45.59 | G102: =R102*$R$3 -> 48 | H102: =P102*(1+Q102)*$P$3+S102*$S$3 -> 99.55 | I102: =T102*$T$3 -> 2 | J102: =(G102+H102+I102)*$J$3 -> 0 | K102: =(G102+H102+I102+J102)*$K$3 -> 0 | L102: =G102+H102+I102+J102+K102 -> 149.55 | M102: =F102*L102 -> 6817.9845 | O102: =P102*(1+Q102)+R102+S102+T102 -> 149.55 | P102: =架空层安装工程!$P$41 -> 85 | Q102: =架空层安装工程!$Q$41 -> 0.03 | R102: =架空层安装工程!$R$41 -> 48 | S102: =架空层安装工程!$S$41 -> 12 | T102: =架空层安装工程!$T$41 -> 2 | U102: =F102*O102 -> 6817.9845
A103: 89 | B103: 30702001003 | C103: 碳钢通风管道 | D103: 1.名称：矩形风管 2.材质：镀锌薄钢板 3.厚度：1.0mm 4.长边：≤1250mm 5.其他：包括但不限于满足图纸、招标文件、规范及验收要求等一切相关费用 | E103: m2 | F103: 66.86 | G103: =R103*$R$3 -> 48 | H103: =P103*(1+Q103)*$P$3+S103*$S$3 -> 99.55 | I103: =T103*$T$3 -> 2 | J103: =(G103+H103+I103)*$J$3 -> 0 | K103: =(G103+H103+I103+J103)*$K$3 -> 0 | L103: =G103+H103+I103+J103+K103 -> 149.55 | M103: =F103*L103 -> 9998.913 | O103: =P103*(1+Q103)+R103+S103+T103 -> 149.55 | P103: =架空层安装工程!$P$42 -> 85 | Q103: =架空层安装工程!$Q$42 -> 0.03 | R103: =架空层安装工程!$R$42 -> 48 | S103: =架空层安装工程!$S$42 -> 12 | T103: =架空层安装工程!$T$42 -> 2 | U103: =F103*O103 -> 9998.913
A104: 90 | B104: 30702001004 | C104: 碳钢通风管道 | D104: 1.名称：矩形风管 2.材质：镀锌薄钢板 3.厚度：1.0mm 4.长边：≤2000mm 5.其他：包括但不限于满足图纸、招标文件、规范及验收要求等一切相关费用 | E104: m2 | F104: 279.53 | G104: =R104*$R$3 -> 48 | H104: =P104*(1+Q104)*$P$3+S104*$S$3 -> 99.55 | I104: =T104*$T$3 -> 2 | J104: =(G104+H104+I104)*$J$3 -> 0 | K104: =(G104+H104+I104+J104)*$K$3 -> 0 | L104: =G104+H104+I104+J104+K104 -> 149.55 | M104: =F104*L104 -> 41803.711 | O104: =P104*(1+Q104)+R104+S104+T104 -> 149.55 | P104: 85 | Q104: 0.03 | R104: 48 | S104: 12 | T104: 2 | U104: =F104*O104 -> 41803.711
A105: 91 | B105: 30703019001 | C105: 柔性接口 | D105: 1.名称：帆布软接口 2.材质：帆布 3.厚度：满足验收要求 4.其他：包括但不限于满足图纸、招标文件、规范及验收要求等一切相关费用 | E105: m2 | F105: 32.82 | G105: =R105*$R$3 -> 55 | H105: =P105*(1+Q105)*$P$3+S105*$S$3 -> 78.89 | I105: =T105*$T$3 -> 2.75 | J105: =(G105+H105+I105)*$J$3 -> 0 | K105: =(G105+H105+I105+J105)*$K$3 -> 0 | L105: =G105+H105+I105+J105+K105 -> 136.64 | M105: =F105*L105 -> 4484.5248 | O105: =P105*(1+Q105)+R105+S105+T105 -> 136.64 | P105: =架空层安装工程!$P$43 -> 19.49 | Q105: =架空层安装工程!$Q$43 -> 0 | R105: =架空层安装工程!$R$43 -> 55 | S105: =架空层安装工程!$S$43 -> 59.4 | T105: =架空层安装工程!$T$43 -> 2.75 | U105: =F105*O105 -> 4484.5248
A106: 92 | B106: 31301005001 | C106: 风管支架刷油 | D106: 1.名称：风管支架刷油 2.按图纸及规范要求 3.其他：包括但不限于以上内容，综合考虑按图纸、招标文件和规范要求而实施、完成这项工程的一切有关费用 | E106: kg | F106: 1884.04 | G106: =R106*$R$3 -> 5.77 | H106: =P106*(1+Q106)*$P$3+S106*$S$3 -> 6.87 | I106: =T106*$T$3 -> 1.21 | J106: =(G106+H106+I106)*$J$3 -> 0 | K106: =(G106+H106+I106+J106)*$K$3 -> 0 | L106: =G106+H106+I106+J106+K106 -> 13.85 | M106: =F106*L106 -> 26093.954 | O106: =P106*(1+Q106)+R106+S106+T106 -> 13.85 | P106: =架空层安装工程!$P$44 -> 6.87 | Q106: =架空层安装工程!$Q$44 -> 0 | R106: =架空层安装工程!$R$44 -> 5.77 | S106: =架空层安装工程!$S$44 -> 0 | T106: =架空层安装工程!$T$44 -> 1.21 | U106: =F106*O106 -> 26093.954
A107: 93 | B107: 31208003001 | C107: 通风管道绝热 | D107: 1.名称：空调风管保温 2.材质：难燃级B1级橡塑保温材料，不燃A级铝箔贴面，湿阻因子≥10000，符合国家GB8624-2012中的管状绝热材料B标准 3.厚度：20mm 4.其他：包括但不限于满足图纸、招标文件、规范及验收要求等一切相关费用 | E107: m2 | F107: 469.67 | G107: =R107*$R$3 -> 48 | H107: =P107*(1+Q107)*$P$3+S107*$S$3 -> 412 | I107: =T107*$T$3 -> 2 | J107: =(G107+H107+I107)*$J$3 -> 0 | K107: =(G107+H107+I107+J107)*$K$3 -> 0 | L107: =G107+H107+I107+J107+K107 -> 462 | M107: =F107*L107 -> 216987.54 | O107: =P107*(1+Q107)+R107+S107+T107 -> 462 | P107: =架空层安装工程!$P$45 -> 400 | Q107: =架空层安装工程!$Q$45 -> 0 | R107: =架空层安装工程!$R$45 -> 48 | S107: =架空层安装工程!$S$45 -> 12 | T107: =架空层安装工程!$T$45 -> 2 | U107: =F107*O107 -> 216987.54
A108: 94 | B108: 30704001001 | C108: 通风工程检测、调试 | D108: 1.名称：风管漏光试验、漏风试验 | E108: 系统 | F108: 1 | G108: =R108*$R$3 -> 380 | H108: =P108*(1+Q108)*$P$3+S108*$S$3 -> 600 | I108: =T108*$T$3 -> 20 | J108: =(G108+H108+I108)*$J$3 -> 0 | K108: =(G108+H108+I108+J108)*$K$3 -> 0 | L108: =G108+H108+I108+J108+K108 -> 1000 | M108: =F108*L108 -> 1000 | O108: =P108*(1+Q108)+R108+S108+T108 -> 1000 | P108: =架空层安装工程!$P$46 -> 400 | Q108: =架空层安装工程!$Q$46 -> 0 | R108: =架空层安装工程!$R$46 -> 380 | S108: =架空层安装工程!$S$46 -> 200 | T108: =架空层安装工程!$T$46 -> 20 | U108: =F108*O108 -> 1000
C109: 风管部件
...

Sheet 样板房安装工程
A1: 样板房安装工程工程量清单 | O1: 成本单价组成（投标人填写）
A2: 序号 | B2: 编码 | C2: 项目名称 | D2: 项目特征 | E2: 单位 | F2: 工程量 | G2: 人工费 | H2: 材料费 | I2: 机械费 | J2: 管理费 | K2: 利润 | L2: 不含税单价 | M2: 合价 | O2: 单价合计 | P2: 主材费 | Q2: 主材损耗率 | R2: 人工费 | S2: 辅材费 | T2: 机械费 | U2: 合计
J3: 0 | K3: 0 | P3: =架空层安装工程!$P$3 -> 1 | R3: =架空层安装工程!$R$3 -> 1 | S3: =架空层安装工程!$S$3 -> 1 | T3: =架空层安装工程!$T$3 -> 1
B4: 单位工程
C5: 109户型
C6: 电气工程
C7: 灯具、电器
A8: 1 | B8: 30413002001 | C8: R1 LED嵌入式射灯 | D8: 1.名称：R1 LED嵌入式射灯 2.规格：12W、3000K、光束角36° 3.安装方式：嵌装 4.其他：包括但不限于满足图纸、招标文件、规范及验收要求等一切相关费用 | E8: 套 | F8: 20 | G8: =R8*$R$3 -> 18 | H8: =P8*(1+Q8)*$P$3+S8*$S$3 -> 126 | I8: =T8*$T$3 -> 8 | J8: =(G8+H8+I8)*$J$3 -> 0 | K8: =(G8+H8+I8+J8)*$K$3 -> 0 | L8: =G8+H8+I8+J8+K8 -> 152 | M8: =F8*L8 -> 3040 | O8: =P8*(1+Q8)+R8+S8+T8 -> 152 | P8: 120 | Q8: 0 | R8: 18 | S8: 6 | T8: 8 | U8: =F8*O8 -> 3040
A9: 2 | B9: 30413002002 | C9: R2 LED嵌入式可调角射灯 | D9: 1.名称：R2 LED嵌入式可调角射灯 2.规格：12W、3000K、光束角24° 3.安装方式：嵌装 4.其他：包括但不限于满足图纸、招标文件、规范及验收要求等一切相关费用 | E9: 套 | F9: 4 | G9: =R9*$R$3 -> 18 | H9: =P9*(1+Q9)*$P$3+S9*$S$3 -> 126 | I9: =T9*$T$3 -> 8 | J9: =(G9+H9+I9)*$J$3 -> 0 | K9: =(G9+H9+I9+J9)*$K$3 -> 0 | L9: =G9+H9+I9+J9+K9 -> 152 | M9: =F9*L9 -> 608 | O9: =P9*(1+Q9)+R9+S9+T9 -> 152 | P9: 120 | Q9: 0 | R9: 18 | S9: 6 | T9: 8 | U9: =F9*O9 -> 608
A10: 3 | B10: 30413002003 | C10: R3 嵌入式防雾射灯 | D10: 1.名称：R3 嵌入式防雾射灯 2.规格：12W、3000K、光束角36° 3.安装方式：嵌装 4.其他：包括但不限于满足图纸、招标文件、规范及验收要求等一切相关费用 | E10: 套 | F10: 6 | G10: =R10*$R$3 -> 18 | H10: =P10*(1+Q10)*$P$3+S10*$S$3 -> 126 | I10: =T10*$T$3 -> 8 | J10: =(G10+H10+I10)*$J$3 -> 0 | K10: =(G10+H10+I10+J10)*$K$3 -> 0 | L10: =G10+H10+I10+J10+K10 -> 152 | M10: =F10*L10 -> 912 | O10: =P10*(1+Q10)+R10+S10+T10 -> 152 | P10: 120 | Q10: 0 | R10: 18 | S10: 6 | T10: 8 | U10: =F10*O10 -> 912
A11: 4 | B11: 30413002004 | C11: R4 明装双头射灯 | D11: 1.名称：R4 明装双头射灯 2.规格：12W、3000K、光束角36° 3.安装方式：嵌装 4.其他：包括但不限于满足图纸、招标文件、规范及验收要求等一切相关费用 | E11: 套 | F11: 3 | G11: =R11*$R$3 -> 18 | H11: =P11*(1+Q11)*$P$3+S11*$S$3 -> 126 | I11: =T11*$T$3 -> 8 | J11: =(G11+H11+I11)*$J$3 -> 0 | K11: =(G11+H11+I11+J11)*$K$3 -> 0 | L11: =G11+H11+I11+J11+K11 -> 152 | M11: =F11*L11 -> 456 | O11: =P11*(1+Q11)+R11+S11+T11 -> 152 | P11: 120 | Q11: 0 | R11: 18 | S11: 6 | T11: 8 | U11: =F11*O11 -> 456
A12: 5 | B12: 30413002005 | C12: R5 明装单头射灯 | D12: 1.名称：R5 明装单头射灯 2.规格：12W、3000K、光束角36° 3.安装方式：嵌装 4.其他：包括但不限于满足图纸、招标文件、规范及验收要求等一切相关费用 | E12: 套 | F12: 5 | G12: =R12*$R$3 -> 18 | H12: =P12*(1+Q12)*$P$3+S12*$S$3 -> 126 | I12: =T12*$T$3 -> 8 | J12: =(G12+H12+I12)*$J$3 -> 0 | K12: =(G12+H12+I12+J12)*$K$3 -> 0 | L12: =G12+H12+I12+J12+K12 -> 152 | M12: =F12*L12 -> 760 | O12: =P12*(1+Q12)+R12+S12+T12 -> 152 | P12: 120 | Q12: 0 | R12: 18 | S12: 6 | T12: 8 | U12: =F12*O12 -> 760
A13: 6 | B13: 30413002006 | C13: L1 LED灯条（天花） | D13: 1.名称：L1 LED灯条（天花） 2.规格：14W/米,3000K,120珠/米 3.安装方式：天花 4.其他：包括但不限于满足图纸、招标文件、规范及验收要求等一切相关费用 | E13: m | F13: 72.19 | G13: =R13*$R$3 -> 2.5 | H13: =P13*(1+Q13)*$P$3+S13*$S$3 -> 12.5 | I13: =T13*$T$3 -> 0 | J13: =(G13+H13+I13)*$J$3 -> 0 | K13: =(G13+H13+I13+J13)*$K$3 -> 0 | L13: =G13+H13+I13+J13+K13 -> 15 | M13: =F13*L13 -> 1082.85 | O13: =P13*(1+Q13)+R13+S13+T13 -> 15 | P13: 12 | Q13: 0 | R13: 2.5 | S13: 0.5 | T13: 0 | U13: =F13*O13 -> 1082.85
A14: 7 | B14: 30413002007 | C14: L2 LED灯条（墙立面） | D14: 1.名称：L2 LED灯条（墙立面） 2.规格：7W/米,3000K,120珠/米 3.安装方式：天花 4.其他：包括但不限于满足图纸、招标文件、规范及验收要求等一切相关费用 | E14: m | F14: 22.14 | G14: =R14*$R$3 -> 2.5 | H14: =P14*(1+Q14)*$P$3+S14*$S$3 -> 12.5 | I14: =T14*$T$3 -> 0 | J14: =(G14+H14+I14)*$J$3 -> 0 | K14: =(G14+H14+I14+J14)*$K$3 -> 0 | L14: =G14+H14+I14+J14+K14 -> 15 | M14: =F14*L14 -> 332.1 | O14: =P14*(1+Q14)+R14+S14+T14 -> 15 | P14: 12 | Q14: 0 | R14: 2.5 | S14: 0.5 | T14: 0 | U14: =F14*O14 -> 332.1
A15: 8 | B15: 30413002008 | C15: L3 LED灯条（柜子） | D15: 1.名称：L3 LED灯条（柜子） 2.规格：4W/米,3000K,120珠/米 3.安装方式：天花 4.其他：包括但不限于满足图纸、招标文件、规范及验收要求等一切相关费用 | E15: m | F15: 15.01 | G15: =R15*$R$3 -> 2.5 | H15: =P15*(1+Q15)*$P$3+S15*$S$3 -> 12.5 | I15: =T15*$T$3 -> 0 | J15: =(G15+H15+I15)*$J$3 -> 0 | K15: =(G15+H15+I15+J15)*$K$3 -> 0 | L15: =G15+H15+I15+J15+K15 -> 15 | M15: =F15*L15 -> 225.15 | O15: =P15*(1+Q15)+R15+S15+T15 -> 15 | P15: 12 | Q15: 0 | R15: 2.5 | S15: 0.5 | T15: 0 | U15: =F15*O15 -> 225.15
A16: 9 | B16: 30413009001 | C16: LED 灯带驱动电源 | D16: 1.名称：LED 灯带驱动电源 2.规格：60W 工作电压：220V 输出电压：24V 3.尺寸：L140*W45*H29mm 4.其他：包括但不限于满足图纸、招标文件、规范及验收要求等一切相关费用 | E16: 个 | F16: 26 | G16: =R16*$R$3 -> 3 | H16: =P16*(1+Q16)*$P$3+S16*$S$3 -> 20.5 | I16: =T16*$T$3 -> 0 | J16: =(G16+H16+I16)*$J$3 -> 0 | K16: =(G16+H16+I16+J16)*$K$3 -> 0 | L16: =G16+H16+I16+J16+K16 -> 23.5 | M16: =F16*L16 -> 611 | O16: =P16*(1+Q16)+R16+S16+T16 -> 23.5 | P16: =架空层安装工程!$P$10 -> 20 | Q16: =架空层安装工程!$Q$10 -> 0 | R16: =架空层安装工程!$R$10 -> 3 | S16: =架空层安装工程!$S$10 -> 0.5 | T16: =架空层安装工程!$T$10 -> 0 | U16: =F16*O16 -> 611
A17: 10 | B17: 30405015001 | C17: 线型凉霸及开关 | D17: 1.名称：线型凉霸及开关 2.规格：34W 3.尺寸：详见物料表 4.其他：包括但不限于满足图纸、招标文件、规范及验收要求等一切相关费用 | E17: 台 | F17: 1 | G17: =R17*$R$3 -> 25 | H17: =P17*(1+Q17)*$P$3+S17*$S$3 -> 283 | I17: =T17*$T$3 -> 0 | J17: =(G17+H17+I17)*$J$3 -> 0 | K17: =(G17+H17+I17+J17)*$K$3 -> 0 | L17: =G17+H17+I17+J17+K17 -> 308 | M17: =F17*L17 -> 308 | O17: =P17*(1+Q17)+R17+S17+T17 -> 308 | P17: 280 | Q17: 0 | R17: 25 | S17: 3 | T17: 0 | U17: =F17*O17 -> 308
A18: 11 | B18: 30405015002 | C18: 线型浴霸及开关 | D18: 1.名称：线型浴霸及开关 2.规格：40W 3.尺寸：详见物料表 4.其他：包括但不限于满足图纸、招标文件、规范及验收要求等一切相关费用 | E18: 台 | F18: 2 | G18: =R18*$R$3 -> 30 | H18: =P18*(1+Q18)*$P$3+S18*$S$3 -> 453 | I18: =T18*$T$3 -> 0 | J18: =(G18+H18+I18)*$J$3 -> 0 | K18: =(G18+H18+I18+J18)*$K$3 -> 0 | L18: =G18+H18+I18+J18+K18 -> 483 | M18: =F18*L18 -> 966 | O18: =P18*(1+Q18)+R18+S18+T18 -> 483 | P18: 450 | Q18: 0 | R18: 30 | S18: 3 | T18: 0 | U18: =F18*O18 -> 966
A19: 12 | B19: 30405017001 | C19: 洗碗机 | D19: 1.名称：洗碗机 2.规格：- 3.尺寸：详见物料表 4.其他：包括但不限于满足图纸、招标文件、规范及验收要求等一切相关费用 | E19: 台 | F19: 1 | G19: =R19*$R$3 -> 250 | H19: =P19*(1+Q19)*$P$3+S19*$S$3 -> 4235 | I19: =T19*$T$3 -> 8.5 | J19: =(G19+H19+I19)*$J$3 -> 0 | K19: =(G19+H19+I19+J19)*$K$3 -> 0 | L19: =G19+H19+I19+J19+K19 -> 4493.5 | M19: =F19*L19 -> 4493.5 | O19: =P19*(1+Q19)+R19+S19+T19 -> 4493.5 | P19: 4200 | Q19: 0 | R19: 250 | S19: 35 | T19: 8.5 | U19: =F19*O19 -> 4493.5
C20: 开关插座 | O20: =P20*(1+Q20)+R20+S20+T20 -> 0 | U20: =F20*O20 -> 0
A21: 13 | B21: 30413013001 | C21: 照明开关 | D21: 1.名称：单联单控开关 2.规格：86*86mm 3.安装方式：暗装 4.其他：包括但不限于满足图纸、招标文件、规范及验收要求等一切相关费用 | E21: 套 | F21: 2 | G21: =R21*$R$3 -> 6.31 | H21: =P21*(1+Q21)*$P$3+S21*$S$3 -> 15.74 | I21: =T21*$T$3 -> 0 | J21: =(G21+H21+I21)*$J$3 -> 0 | K21: =(G21+H21+I21+J21)*$K$3 -> 0 | L21: =G21+H21+I21+J21+K21 -> 22.05 | M21: =F21*L21 -> 44.1 | O21: =P21*(1+Q21)+R21+S21+T21 -> 22.05 | P21: =公共区域安装工程!$P$14 -> 14.62 | Q21: =公共区域安装工程!$Q$14 -> 0 | R21: =公共区域安装工程!$R$14 -> 6.31 | S21: =公共区域安装工程!$S$14 -> 1.12 | T21: =公共区域安装工程!$T$14 -> 0 | U21: =F21*O21 -> 44.1
A22: 14 | B22: 30413013002 | C22: 照明开关 | D22: 1.名称：双联单控开关 2.规格：86*86mm 3.安装方式：暗装 4.其他：包括但不限于满足图纸、招标文件、规范及验收要求等一切相关费用 | E22: 套 | F22: 1 | G22: =R22*$R$3 -> 10 | H22: =P22*(1+Q22)*$P$3+S22*$S$3 -> 19.5 | I22: =T22*$T$3 -> 0 | J22: =(G22+H22+I22)*$J$3 -> 0 | K22: =(G22+H22+I22+J22)*$K$3 -> 0 | L22: =G22+H22+I22+J22+K22 -> 29.5 | M22: =F22*L22 -> 29.5 | O22: =P22*(1+Q22)+R22+S22+T22 -> 29.5 | P22: =架空层安装工程!$P$16 -> 18 | Q22: =架空层安装工程!$Q$16 -> 0 | R22: =架空层安装工程!$R$16 -> 10 | S22: =架空层安装工程!$S$16 -> 1.5 | T22: =架空层安装工程!$T$16 -> 0 | U22: =F22*O22 -> 29.5
A23: 15 | B23: 30413013003 | C23: 照明开关 | D23: 1.名称：三联单控开关 2.规格：86*86mm 3.安装方式：暗装 4.其他：包括但不限于满足图纸、招标文件、规范及验收要求等一切相关费用 | E23: 套 | F23: 2 | G23: =R23*$R$3 -> 12 | H23: =P23*(1+Q23)*$P$3+S23*$S$3 -> 21.5 | I23: =T23*$T$3 -> 0 | J23: =(G23+H23+I23)*$J$3 -> 0 | K23: =(G23+H23+I23+J23)*$K$3 -> 0 | L23: =G23+H23+I23+J23+K23 -> 33.5 | M23: =F23*L23 -> 67 | O23: =P23*(1+Q23)+R23+S23+T23 -> 33.5 | P23: =公共区域安装工程!$P$15 -> 20 | Q23: =公共区域安装工程!$Q$15 -> 0 | R23: =公共区域安装工程!$R$15 -> 12 | S23: =公共区域安装工程!$S$15 -> 1.5 | T23: =公共区域安装工程!$T$15 -> 0 | U23: =F23*O23 -> 67
A24: 16 | B24: 30413013004 | C24: 照明开关 | D24: 1.名称：双联双控开关 2.规格：86*86mm 3.安装方式：暗装 4.其他：包括但不限于满足图纸、招标文件、规范及验收要求等一切相关费用 | E24: 套 | F24: 2 | G24: =R24*$R$3 -> 10 | H24: =P24*(1+Q24)*$P$3+S24*$S$3 -> 19.5 | I24: =T24*$T$3 -> 0 | J24: =(G24+H24+I24)*$J$3 -> 0 | K24: =(G24+H24+I24+J24)*$K$3 -> 0 | L24: =G24+H24+I24+J24+K24 -> 29.5 | M24: =F24*L24 -> 59 | O24: =P24*(1+Q24)+R24+S24+T24 -> 29.5 | P24: =户内交标安装工程!$P$21 -> 18 | Q24: =户内交标安装工程!$Q$21 -> 0 | R24: =户内交标安装工程!$R$21 -> 10 | S24: =户内交标安装工程!$S$21 -> 1.5 | T24: =户内交标安装工程!$T$21 -> 0 | U24: =F24*O24 -> 59
A25: 17 | B25: 30413013005 | C25: 照明开关 | D25: 1.名称：三联双控开关 2.规格：86*86mm 3.安装方式：暗装 4.其他：包括但不限于满足图纸、招标文件、规范及验收要求等一切相关费用 | E25: 套 | F25: 8 | G25: =R25*$R$3 -> 12 | H25: =P25*(1+Q25)*$P$3+S25*$S$3 -> 21.5 | I25: =T25*$T$3 -> 0 | J25: =(G25+H25+I25)*$J$3 -> 0 | K25: =(G25+H25+I25+J25)*$K$3 -> 0 | L25: =G25+H25+I25+J25+K25 -> 33.5 | M25: =F25*L25 -> 268 | O25: =P25*(1+Q25)+R25+S25+T25 -> 33.5 | P25: =户内交标安装工程!$P$22 -> 20 | Q25: =户内交标安装工程!$Q$22 -> 0 | R25: =户内交标安装工程!$R$22 -> 12 | S25: =户内交标安装工程!$S$22 -> 1.5 | T25: =户内交标安装工程!$T$22 -> 0 | U25: =F25*O25 -> 268
A26: 18 | B26: 30413013006 | C26: 照明开关 | D26: 1.名称：四联双控开关 2.规格：86*86mm 3.安装方式：暗装 4.其他：包括但不限于满足图纸、招标文件、规范及验收要求等一切相关费用 | E26: 套 | F26: 4 | G26: =R26*$R$3 -> 6.31 | H26: =P26*(1+Q26)*$P$3+S26*$S$3 -> 15.74 | I26: =T26*$T$3 -> 0 | J26: =(G26+H26+I26)*$J$3 -> 0 | K26: =(G26+H26+I26+J26)*$K$3 -> 0 | L26: =G26+H26+I26+J26+K26 -> 22.05 | M26: =F26*L26 -> 88.2 | O26: =P26*(1+Q26)+R26+S26+T26 -> 22.05 | P26: 14.62 | Q26: 0 | R26: 6.31 | S26: 1.12 | T26: 0 | U26: =F26*O26 -> 88.2
A27: 19 | B27: 30413014001 | C27: 插座 | D27: 1.名称：五孔插座 2.规格：86*86mm 3.安装方式：暗装 4.其他：包括但不限于满足图纸、招标文件、规范及验收要求等一切相关费用 | E27: 套 | F27: 31 | G27: =R27*$R$3 -> 6.31 | H27: =P27*(1+Q27)*$P$3+S27*$S$3 -> 15.74 | I27: =T27*$T$3 -> 0 | J27: =(G27+H27+I27)*$J$3 -> 0 | K27: =(G27+H27+I27+J27)*$K$3 -> 0 | L27: =G27+H27+I27+J27+K27 -> 22.05 | M27: =F27*L27 -> 683.55 | O27: =P27*(1+Q27)+R27+S27+T27 -> 22.05 | P27: =公共区域安装工程!$P$16 -> 14.62 | Q27: =公共区域安装工程!$Q$16 -> 0 | R27: =公共区域安装工程!$R$16 -> 6.31 | S27: =公共区域安装工程!$S$16 -> 1.12 | T27: =公共区域安装工程!$T$16 -> 0 | U27: =F27*O27 -> 683.55
A28: 20 | B28: 30413014002 | C28: 插座 | D28: 1.名称：五孔插座（带防溅盒） 2.规格：86*86mm 3.安装方式：暗装 4.其他：包括但不限于满足图纸、招标文件、规范及验收要求等一切相关费用 | E28: 套 | F28: 12 | G28: =R28*$R$3 -> 6.31 | H28: =P28*(1+Q28)*$P$3+S28*$S$3 -> 15.74 | I28: =T28*$T$3 -> 0 | J28: =(G28+H28+I28)*$J$3 -> 0 | K28: =(G28+H28+I28+J28)*$K$3 -> 0 | L28: =G28+H28+I28+J28+K28 -> 22.05 | M28: =F28*L28 -> 264.6 | O28: =P28*(1+Q28)+R28+S28+T28 -> 22.05 | P28: 14.62 | Q28: 0 | R28: 6.31 | S28: 1.12 | T28: 0 | U28: =F28*O28 -> 264.6
A29: 21 | B29: 30413014003 | C29: 插座 | D29: 1.名称：五孔插座带USB 2.规格：86*86mm 3.安装方式：暗装 4.其他：包括但不限于满足图纸、招标文件、规范及验收要求等一切相关费用 | E29: 套 | F29: 3 | G29: =R29*$R$3 -> 6.31 | H29: =P29*(1+Q29)*$P$3+S29*$S$3 -> 15.74 | I29: =T29*$T$3 -> 0 | J29: =(G29+H29+I29)*$J$3 -> 0 | K29: =(G29+H29+I29+J29)*$K$3 -> 0 | L29: =G29+H29+I29+J29+K29 -> 22.05 | M29: =F29*L29 -> 66.15 | O29: =P29*(1+Q29)+R29+S29+T29 -> 22.05 | P29: 14.62 | Q29: 0 | R29: 6.31 | S29: 1.12 | T29: 0 | U29: =F29*O29 -> 66.15
A30: 22 | B30: 30413014004 | C30: 插座 | D30: 1.名称：五孔插座带开关 2.规格：86*86mm 3.安装方式：暗装 4.其他：包括但不限于满足图纸、招标文件、规范及验收要求等一切相关费用 | E30: 套 | F30: 2 | G30: =R30*$R$3 -> 6.31 | H30: =P30*(1+Q30)*$P$3+S30*$S$3 -> 15.74 | I30: =T30*$T$3 -> 0 | J30: =(G30+H30+I30)*$J$3 -> 0 | K30: =(G30+H30+I30+J30)*$K$3 -> 0 | L30: =G30+H30+I30+J30+K30 -> 22.05 | M30: =F30*L30 -> 44.1 | O30: =P30*(1+Q30)+R30+S30+T30 -> 22.05 | P30: =户内交标安装工程!$P$25 -> 14.62 | Q30: =户内交标安装工程!$Q$25 -> 0 | R30: =户内交标安装工程!$R$25 -> 6.31 | S30: =户内交标安装工程!$S$25 -> 1.12 | T30: =户内交标安装工程!$T$25 -> 0 | U30: =F30*O30 -> 44.1
A31: 23 | B31: 30413014005 | C31: 插座 | D31: 1.名称：五孔插座带开关（带防溅盒） 2.规格：86*86mm 3.安装方式：暗装 4.其他：包括但不限于满足图纸、招标文件、规范及验收要求等一切相关费用 | E31: 套 | F31: 2 | G31: =R31*$R$3 -> 6.31 | H31: =P31*(1+Q31)*$P$3+S31*$S$3 -> 15.74 | I31: =T31*$T$3 -> 0 | J31: =(G31+H31+I31)*$J$3 -> 0 | K31: =(G31+H31+I31+J31)*$K$3 -> 0 | L31: =G31+H31+I31+J31+K31 -> 22.05 | M31: =F31*L31 -> 44.1 | O31: =P31*(1+Q31)+R31+S31+T31 -> 22.05 | P31: 14.62 | Q31: 0 | R31: 6.31 | S31: 1.12 | T31: 0 | U31: =F31*O31 -> 44.1
A32: 24 | B32: 30413014006 | C32: 插座 | D32: 1.名称：地面五孔插座 2.规格：86*86mm 3.安装方式：暗装 4.其他：包括但不限于满足图纸、招标文件、规范及验收要求等一切相关费用 | E32: 套 | F32: 2 | G32: =R32*$R$3 -> 6.31 | H32: =P32*(1+Q32)*$P$3+S32*$S$3 -> 15.74 | I32: =T32*$T$3 -> 0 | J32: =(G32+H32+I32)*$J$3 -> 0 | K32: =(G32+H32+I32+J32)*$K$3 -> 0 | L32: =G32+H32+I32+J32+K32 -> 22.05 | M32: =F32*L32 -> 44.1 | O32: =P32*(1+Q32)+R32+S32+T32 -> 22.05 | P32: =架空层安装工程!$P$19 -> 14.62 | Q32: =架空层安装工程!$Q$19 -> 0 | R32: =架空层安装工程!$R$19 -> 6.31 | S32: =架空层安装工程!$S$19 -> 1.12 | T32: =架空层安装工程!$T$19 -> 0 | U32: =F32*O32 -> 44.1
C33: 配管配线 | O33: =P33*(1+Q33)+R33+S33+T33 -> 0 | U33: =F33*O33 -> 0
A34: 25 | B34: 30412004001 | C34: 配线 | D34: 1.名称：电气配线 2.型号规格：BV-1.5 3.安装方式：管内穿线 4.其他：包括但不限于满足图纸、招标文件、规范及验收要求等一切相关费用 | E34: m | F34: 278.13 | G34: =R34*$R$3 -> 1.58 | H34: =P34*(1+Q34)*$P$3+S34*$S$3 -> 2.128 | I34: =T34*$T$3 -> 0.02 | J34: =(G34+H34+I34)*$J$3 -> 0 | K34: =(G34+H34+I34+J34)*$K$3 -> 0 | L34: =G34+H34+I34+J34+K34 -> 3.728 | M34: =F34*L34 -> 1036.8686 | O34: =P34*(1+Q34)+R34+S34+T34 -> 3.728 | P34: 1.9 | Q34: 0.02 | R34: 1.58 | S34: 0.19 | T34: 0.02 | U34: =F34*O34 -> 1036.8686
A35: 26 | B35: 30412004002 | C35: 配线 | D35: 1.名称：电气配线 2.型号规格：BV-2.5 3.安装方式：管内穿线 4.其他：包括但不限于满足图纸、招标文件、规范及验收要求等一切相关费用 | E35: m | F35: 1134.55 | G35: =R35*$R$3 -> 2.1 | H35: =P35*(1+Q35)*$P$3+S35*$S$3 -> 3.0354 | I35: =T35*$T$3 -> 0.02 | J35: =(G35+H35+I35)*$J$3 -> 0 | K35: =(G35+H35+I35+J35)*$K$3 -> 0 | L35: =G35+H35+I35+J35+K35 -> 5.1554 | M35: =F35*L35 -> 5849.0591 | O35: =P35*(1+Q35)+R35+S35+T35 -> 5.1554 | P35: =公共区域安装工程!$P$22 -> 2.77 | Q35: =公共区域安装工程!$Q$22 -> 0.02 | R35: =公共区域安装工程!$R$22 -> 2.1 | S35: =公共区域安装工程!$S$22 -> 0.21 | T35: =公共区域安装工程!$T$22 -> 0.02 | U35: =F35*O35 -> 5849.0591
A36: 27 | B36: 30412004003 | C36: 配线 | D36: 1.名称：电气配线 2.型号规格：BV-4 3.安装方式：管内穿线 4.其他：包括但不限于满足图纸、招标文件、规范及验收要求等一切相关费用 | E36: m | F36: 720.6 | G36: =R36*$R$3 -> 1.4 | H36: =P36*(1+Q36)*$P$3+S36*$S$3 -> 3.9736 | I36: =T36*$T$3 -> 0.01 | J36: =(G36+H36+I36)*$J$3 -> 0 | K36: =(G36+H36+I36+J36)*$K$3 -> 0 | L36: =G36+H36+I36+J36+K36 -> 5.3836 | M36: =F36*L36 -> 3879.4222 | O36: =P36*(1+Q36)+R36+S36+T36 -> 5.3836 | P36: =户内交标安装工程!$P$32 -> 3.68 | Q36: =户内交标安装工程!$Q$32 -> 0.02 | R36: =户内交标安装工程!$R$32 -> 1.4 | S36: =户内交标安装工程!$S$32 -> 0.22 | T36: =户内交标安装工程!$T$32 -> 0.01 | U36: =F36*O36 -> 3879.4222
A37: 28 | B37: 30412004004 | C37: 配线 | D37: 1.名称：电气配线 2.型号规格：BV-10 3.安装方式：管内穿线 4.其他：包括但不限于满足图纸、招标文件、规范及验收要求等一切相关费用 | E37: m | F37: 31.52 | G37: =R37*$R$3 -> 2 | H37: =P37*(1+Q37)*$P$3+S37*$S$3 -> 9.51 | I37: =T37*$T$3 -> 0.02 | J37: =(G37+H37+I37)*$J$3 -> 0 | K37: =(G37+H37+I37+J37)*$K$3 -> 0 | L37: =G37+H37+I37+J37+K37 -> 11.53 | M37: =F37*L37 -> 363.4256 | O37: =P37*(1+Q37)+R37+S37+T37 -> 11.53 | P37: 9 | Q37: 0.02 | R37: 2 | S37: 0.33 | T37: 0.02 | U37: =F37*O37 -> 363.4256
C38: 弱电工程 | O38: =P38*(1+Q38)+R38+S38+T38 -> 0 | U38: =F38*O38 -> 0
A39: 29 | B39: 30413014007 | C39: 插座 | D39: 1.名称：网络插座 2.规格：86*86mm 3.安装方式：暗装 4.其他：包括但不限于满足图纸、招标文件、规范及验收要求等一切相关费用 | E39: 套 | F39: 4 | G39: =R39*$R$3 -> 6.31 | H39: =P39*(1+Q39)*$P$3+S39*$S$3 -> 15.74 | I39: =T39*$T$3 -> 0 | J39: =(G39+H39+I39)*$J$3 -> 0 | K39: =(G39+H39+I39+J39)*$K$3 -> 0 | L39: =G39+H39+I39+J39+K39 -> 22.05 | M39: =F39*L39 -> 88.2 | O39: =P39*(1+Q39)+R39+S39+T39 -> 22.05 | P39: 14.62 | Q39: 0 | R39: 6.31 | S39: 1.12 | T39: 0 | U39: =F39*O39 -> 88.2
A40: 30 | B40: 30413014008 | C40: 插座 | D40: 1.名称：电视插座 2.规格：86*86mm 3.安装方式：暗装 4.其他：包括但不限于满足图纸、招标文件、规范及验收要求等一切相关费用 | E40: 套 | F40: 2 | G40: =R40*$R$3 -> 6.31 | H40: =P40*(1+Q40)*$P$3+S40*$S$3 -> 15.74 | I40: =T40*$T$3 -> 0 | J40: =(G40+H40+I40)*$J$3 -> 0 | K40: =(G40+H40+I40+J40)*$K$3 -> 0 | L40: =G40+H40+I40+J40+K40 -> 22.05 | M40: =F40*L40 -> 44.1 | O40: =P40*(1+Q40)+R40+S40+T40 -> 22.05 | P40: 14.62 | Q40: 0 | R40: 6.31 | S40: 1.12 | T40: 0 | U40: =F40*O40 -> 44.1
A41: 31 | B41: 30413013007 | C41: 紧急按钮 | D41: 1.名称：紧急按钮 2.规格：86*86mm 3.安装方式：暗装 4.其他：包括但不限于满足图纸、招标文件、规范及验收要求等一切相关费用 | E41: 套 | F41: 1 | G41: =R41*$R$3 -> 12 | H41: =P41*(1+Q41)*$P$3+S41*$S$3 -> 29 | I41: =T41*$T$3 -> 0 | J41: =(G41+H41+I41)*$J$3 -> 0 | K41: =(G41+H41+I41+J41)*$K$3 -> 0 | L41: =G41+H41+I41+J41+K41 -> 41 | M41: =F41*L41 -> 41 | O41: =P41*(1+Q41)+R41+S41+T41 -> 41 | P41: 27 | Q41: 0 | R41: 12 | S41: 2 | T41: 0 | U41: =F41*O41 -> 41
A42: 32 | B42: 30502003001 | C42: 双绞线缆 | D42: 1.名称：超六类网线 2.型号规格：CAT6e 3.敷设方式：管内穿线 4.其他：包括但不限于满足图纸、招标文件、规范及验收要求等一切相关费用 | E42: m | F42: 69.6 | G42: =R42*$R$3 -> 0.8 | H42: =P42*(1+Q42)*$P$3+S42*$S$3 -> 2.6 | I42: =T42*$T$3 -> 0.1 | J42: =(G42+H42+I42)*$J$3 -> 0 | K42: =(G42+H42+I42+J42)*$K$3 -> 0 | L42: =G42+H42+I42+J42+K42 -> 3.5 | M42: =F42*L42 -> 243.6 | O42: =P42*(1+Q42)+R42+S42+T42 -> 3.5 | P42: 2.5 | Q42: 0 | R42: 0.8 | S42: 0.1 | T42: 0.1 | U42: =F42*O42 -> 243.6
A43: 33 | B43: 30502003002 | C43: 多芯软导线 | D43: 1.名称：多芯软导线 2.型号规格：RVV-2*1.0 3.敷设方式：管内穿线 4.其他：包括但不限于满足图纸、招标文件、规范及验收要求等一切相关费用 | E43: m | F43: 14.63 | G43: =R43*$R$3 -> 1.73 | H43: =P43*(1+Q43)*$P$3+S43*$S$3 -> 3.18 | I43: =T43*$T$3 -> 0.02 | J43: =(G43+H43+I43)*$J$3 -> 0 | K43: =(G43+H43+I43+J43)*$K$3 -> 0 | L43: =G43+H43+I43+J43+K43 -> 4.93 | M43: =F43*L43 -> 72.1259 | O43: =P43*(1+Q43)+R43+S43+T43 -> 4.93 | P43: 3 | Q43: 0.02 | R43: 1.73 | S43: 0.12 | T43: 0.02 | U43: =F43*O43 -> 72.1259
C44: 给排水工程 | O44: =P44*(1+Q44)+R44+S44+T44 -> 0 | U44: =F44*O44 -> 0
C45: 排水管 | O45: =P45*(1+Q45)+R45+S45+T45 -> 0 | U45: =F45*O45 -> 0
A46: 34 | B46: 31001008007 | C46: UPVC排水管 | D46: 1.名称：UPVC排水管 2.规格：DN50 3.连接方式：粘接 4.压力试验及吹、洗要求：水压试验、管道标识等 5.其他：包括但不限于满足图纸、招标文件、规范及验收要求等一切相关费用 | E46: m | F46: 6.1 | G46: =R46*$R$3 -> 24 | H46: =P46*(1+Q46)*$P$3+S46*$S$3 -> 16.27 | I46: =T46*$T$3 -> 0.23 | J46: =(G46+H46+I46)*$J$3 -> 0 | K46: =(G46+H46+I46+J46)*$K$3 -> 0 | L46: =G46+H46+I46+J46+K46 -> 40.5 | M46: =F46*L46 -> 247.05 | O46: =P46*(1+Q46)+R46+S46+T46 -> 40.5 | P46: 15 | Q46: 0 | R46: 24 | S46: 1.27 | T46: 0.23 | U46: =F46*O46 -> 247.05
A47: 35 | B47: 31001008008 | C47: UPVC排水管 | D47: 1.名称：UPVC排水管 2.规格：DN75 3.连接方式：粘接 4.压力试验及吹、洗要求：水压试验、管道标识等 5.其他：包括但不限于满足图纸、招标文件、规范及验收要求等一切相关费用 | E47: m | F47: 1.97 | G47: =R47*$R$3 -> 55 | H47: =P47*(1+Q47)*$P$3+S47*$S$3 -> 28 | I47: =T47*$T$3 -> 3 | J47: =(G47+H47+I47)*$J$3 -> 0 | K47: =(G47+H47+I47+J47)*$K$3 -> 0 | L47: =G47+H47+I47+J47+K47 -> 86 | M47: =F47*L47 -> 169.42 | O47: =P47*(1+Q47)+R47+S47+T47 -> 86 | P47: 25 | Q47: 0 | R47: 55 | S47: 3 | T47: 3 | U47: =F47*O47 -> 169.42
A48: 36 | B48: 31001008009 | C48: UPVC排水管 | D48: 1.名称：UPVC排水管 2.规格：DN100 3.连接方式：粘接 4.压力试验及吹、洗要求：水压试验、管道标识等 5.其他：包括但不限于满足图纸、招标文件、规范及验收要求等一切相关费用 | E48: m | F48: 1.53 | G48: =R48*$R$3 -> 30 | H48: =P48*(1+Q48)*$P$3+S48*$S$3 -> 38.12 | I48: =T48*$T$3 -> 0.38 | J48: =(G48+H48+I48)*$J$3 -> 0 | K48: =(G48+H48+I48+J48)*$K$3 -> 0 | L48: =G48+H48+I48+J48+K48 -> 68.5 | M48: =F48*L48 -> 104.805 | O48: =P48*(1+Q48)+R48+S48+T48 -> 68.5 | P48: 36 | Q48: 0 | R48: 30 | S48: 2.12 | T48: 0.38 | U48: =F48*O48 -> 104.805
C49: 洁具五金 | O49: =P49*(1+Q49)+R49+S49+T49 -> 0 | U49: =F49*O49 -> 0
A50: 37 | B50: 31003006001 | C50: 大便器 | D50: 1.名称：智能坐便器-主卫 2.型号：详见物料表 3.其他：包括但不限于满足图纸、招标文件、规范及验收要求等一切相关费用 | E50: 组 | F50: 1 | G50: =R50*$R$3 -> 130 | H50: =P50*(1+Q50)*$P$3+S50*$S$3 -> 815 | I50: =T50*$T$3 -> 0.8 | J50: =(G50+H50+I50)*$J$3 -> 0 | K50: =(G50+H50+I50+J50)*$K$3 -> 0 | L50: =G50+H50+I50+J50+K50 -> 945.8 | M50: =F50*L50 -> 945.8 | O50: =P50*(1+Q50)+R50+S50+T50 -> 945.8 | P50: 800 | Q50: 0 | R50: 130 | S50: 15 | T50: 0.8 | U50: =F50*O50 -> 945.8
A51: 38 | B51: 31003006002 | C51: 大便器 | D51: 1.名称：连体坐便器-公卫 2.型号：详见物料表 3.其他：包括但不限于满足图纸、招标文件、规范及验收要求等一切相关费用 | E51: 组 | F51: 1 | G51: =R51*$R$3 -> 130 | H51: =P51*(1+Q51)*$P$3+S51*$S$3 -> 815 | I51: =T51*$T$3 -> 0.8 | J51: =(G51+H51+I51)*$J$3 -> 0 | K51: =(G51+H51+I51+J51)*$K$3 -> 0 | L51: =G51+H51+I51+J51+K51 -> 945.8 | M51: =F51*L51 -> 945.8 | O51: =P51*(1+Q51)+R51+S51+T51 -> 945.8 | P51: 800 | Q51: 0 | R51: 130 | S51: 15 | T51: 0.8 | U51: =F51*O51 -> 945.8
A52: 39 | B52: 31003010001 | C52: 淋浴器 | D52: 1.名称：淋浴花洒3-主卫 2.型号：详见物料表 3.其他：包括但不限于满足图纸、招标文件、规范及验收要求等一切相关费用 | E52: 套 | F52: 1 | G52: =R52*$R$3 -> 90 | H52: =P52*(1+Q52)*$P$3+S52*$S$3 -> 1135 | I52: =T52*$T$3 -> 0 | J52: =(G52+H52+I52)*$J$3 -> 0 | K52: =(G52+H52+I52+J52)*$K$3 -> 0 | L52: =G52+H52+I52+J52+K52 -> 1225 | M52: =F52*L52 -> 1225 | O52: =P52*(1+Q52)+R52+S52+T52 -> 1225 | P52: 1100 | Q52: 0 | R52: 90 | S52: 35 | T52: 0 | U52: =F52*O52 -> 1225
A53: 40 | B53: 31003010002 | C53: 淋浴器 | D53: 1.名称：淋浴花洒2-公卫 2.型号：详见物料表 3.其他：包括但不限于满足图纸、招标文件、规范及验收要求等一切相关费用 | E53: 套 | F53: 1 | G53: =R53*$R$3 -> 90 | H53: =P53*(1+Q53)*$P$3+S53*$S$3 -> 1135 | I53: =T53*$T$3 -> 0 | J53: =(G53+H53+I53)*$J$3 -> 0 | K53: =(G53+H53+I53+J53)*$K$3 -> 0 | L53: =G53+H53+I53+J53+K53 -> 1225 | M53: =F53*L53 -> 1225 | O53: =P53*(1+Q53)+R53+S53+T53 -> 1225 | P53: 1100 | Q53: 0 | R53: 90 | S53: 35 | T53: 0 | U53: =F53*O53 -> 1225
A54: 41 | B54: 31003003001 | C54: 台下盆及龙头 | D54: 1.名称：台下盆方形及龙头-主卫 2.型号：详见物料表 3.其他：包括但不限于满足图纸、招标文件、规范及验收要求等一切相关费用 | E54: 组 | F54: 1 | G54: =R54*$R$3 -> 90 | H54: =P54*(1+Q54)*$P$3+S54*$S$3 -> 562 | I54: =T54*$T$3 -> 0 | J54: =(G54+H54+I54)*$J$3 -> 0 | K54: =(G54+H54+I54+J54)*$K$3 -> 0 | L54: =G54+H54+I54+J54+K54 -> 652 | M54: =F54*L54 -> 652 | O54: =P54*(1+Q54)+R54+S54+T54 -> 652 | P54: 550 | Q54: 0 | R54: 90 | S54: 12 | T54: 0 | U54: =F54*O54 -> 652
A55: 42 | B55: 31003003002 | C55: 台下盆及龙头 | D55: 1.名称：台下盆方形及龙头-公卫 2.型号：详见物料表 3.其他：包括但不限于满足图纸、招标文件、规范及验收要求等一切相关费用 | E55: 组 | F55: 1 | G55: =R55*$R$3 -> 90 | H55: =P55*(1+Q55)*$P$3+S55*$S$3 -> 562 | I55: =T55*$T$3 -> 0 | J55: =(G55+H55+I55)*$J$3 -> 0 | K55: =(G55+H55+I55+J55)*$K$3 -> 0 | L55: =G55+H55+I55+J55+K55 -> 652 | M55: =F55*L55 -> 652 | O55: =P55*(1+Q55)+R55+S55+T55 -> 652 | P55: 550 | Q55: 0 | R55: 90 | S55: 12 | T55: 0 | U55: =F55*O55 -> 652
A56: 43 | B56: 31003004001 | C56: 水槽及龙头 | D56: 1.名称：厨房大单盆水槽 2.型号：详见物料表 3.其他：包括但不限于满足图纸、招标文件、规范及验收要求等一切相关费用 | E56: 组 | F56: 1 | G56: =R56*$R$3 -> 60 | H56: =P56*(1+Q56)*$P$3+S56*$S$3 -> 990 | I56: =T56*$T$3 -> 0 | J56: =(G56+H56+I56)*$J$3 -> 0 | K56: =(G56+H56+I56+J56)*$K$3 -> 0 | L56: =G56+H56+I56+J56+K56 -> 1050 | M56: =F56*L56 -> 1050 | O56: =P56*(1+Q56)+R56+S56+T56 -> 1050 | P56: 950 | Q56: 0 | R56: 60 | S56: 40 | T56: 0 | U56: =F56*O56 -> 1050
A57: 44 | B57: 31003014001 | C57: 地漏 | D57: 1.名称：隐藏式地漏-干区 2.规格：DN50 3.型号：详见物料表 4.其他：包括但不限于满足图纸、招标文件、规范及验收要求等一切相关费用 | E57: 个 | F57: 2 | G57: =R57*$R$3 -> 18 | H57: =P57*(1+Q57)*$P$3+S57*$S$3 -> 40 | I57: =T57*$T$3 -> 0 | J57: =(G57+H57+I57)*$J$3 -> 0 | K57: =(G57+H57+I57+J57)*$K$3 -> 0 | L57: =G57+H57+I57+J57+K57 -> 58 | M57: =F57*L57 -> 116 | O57: =P57*(1+Q57)+R57+S57+T57 -> 58 | P57: 35 | Q57: 0 | R57: 18 | S57: 5 | T57: 0 | U57: =F57*O57 -> 116
A58: 45 | B58: 31003014002 | C58: 地漏 | D58: 1.名称：隐形长地漏-淋浴间 2.规格：DN75 3.型号：详见物料表 4.其他：包括但不限于满足图纸、招标文件、规范及验收要求等一切相关费用 | E58: 个 | F58: 2 | G58: =R58*$R$3 -> 25 | H58: =P58*(1+Q58)*$P$3+S58*$S$3 -> 56.5 | I58: =T58*$T$3 -> 0.2 | J58: =(G58+H58+I58)*$J$3 -> 0 | K58: =(G58+H58+I58+J58)*$K$3 -> 0 | L58: =G58+H58+I58+J58+K58 -> 81.7 | M58: =F58*L58 -> 163.4 | O58: =P58*(1+Q58)+R58+S58+T58 -> 81.7 | P58: 55 | Q58: 0 | R58: 25 | S58: 1.5 | T58: 0.2 | U58: =F58*O58 -> 163.4
A59: 46 | B59: 31003014003 | C59: 地漏 | D59: 1.名称：隐藏式地漏-阳台 2.规格：DN75 3.型号：详见物料表 4.其他：包括但不限于满足图纸、招标文件、规范及验收要求等一切相关费用 | E59: 个 | F59: 2 | G59: =R59*$R$3 -> 25 | H59: =P59*(1+Q59)*$P$3+S59*$S$3 -> 56.5 | I59: =T59*$T$3 -> 0.2 | J59: =(G59+H59+I59)*$J$3 -> 0 | K59: =(G59+H59+I59+J59)*$K$3 -> 0 | L59: =G59+H59+I59+J59+K59 -> 81.7 | M59: =F59*L59 -> 163.4 | O59: =P59*(1+Q59)+R59+S59+T59 -> 81.7 | P59: 55 | Q59: 0 | R59: 25 | S59: 1.5 | T59: 0.2 | U59: =F59*O59 -> 163.4
A60: 47 | B60: 31003014004 | C60: 地漏 | D60: 1.名称：洗衣机地漏 2.规格：DN75 3.型号：详见物料表 4.其他：包括但不限于满足图纸、招标文件、规范及验收要求等一切相关费用 | E60: 个 | F60: 1 | G60: =R60*$R$3 -> 18 | H60: =P60*(1+Q60)*$P$3+S60*$S$3 -> 40 | I60: =T60*$T$3 -> 0 | J60: =(G60+H60+I60)*$J$3 -> 0 | K60: =(G60+H60+I60+J60)*$K$3 -> 0 | L60: =G60+H60+I60+J60+K60 -> 58 | M60: =F60*L60 -> 58 | O60: =P60*(1+Q60)+R60+S60+T60 -> 58 | P60: 35 | Q60: 0 | R60: 18 | S60: 5 | T60: 0 | U60: =F60*O60 -> 58
A61: 48 | B61: 31003014005 | C61: 洗衣机龙头 | D61: 1.名称：洗衣机龙头 2.规格：DN15 3.型号：详见物料表 4.其他：包括但不限于满足图纸、招标文件、规范及验收要求等一切相关费用 | E61: 个 | F61: 1 | G61: =R61*$R$3 -> 55 | H61: =P61*(1+Q61)*$P$3+S61*$S$3 -> 485 | I61: =T61*$T$3 -> 0 | J61: =(G61+H61+I61)*$J$3 -> 0 | K61: =(G61+H61+I61+J61)*$K$3 -> 0 | L61: =G61+H61+I61+J61+K61 -> 540 | M61: =F61*L61 -> 540 | O61: =P61*(1+Q61)+R61+S61+T61 -> 540 | P61: 465 | Q61: 0 | R61: 55 | S61: 20 | T61: 0 | U61: =F61*O61 -> 540
A62: 49 | B62: 31002001004 | C62: 角阀 | D62: 1.名称：角阀（热水器、洗碗机、扫地机、阳台洗手盆） 2.型号规格：DN15 3.其他：包括但不限于满足图纸、招标文件、规范及验收要求等一切相关费用 | E62: 个 | F62: 6 | G62: =R62*$R$3 -> 167.09 | H62: =P62*(1+Q62)*$P$3+S62*$S$3 -> 1504.2 | I62: =T62*$T$3 -> 12.03 | J62: =(G62+H62+I62)*$J$3 -> 0 | K62: =(G62+H62+I62+J62)*$K$3 -> 0 | L62: =G62+H62+I62+J62+K62 -> 1683.32 | M62: =F62*L62 -> 10099.92 | O62: =P62*(1+Q62)+R62+S62+T62 -> 1683.32 | P62: 1504.2 | Q62: 0 | R62: 167.09 | S62: 0 | T62: 12.03 | U62: =F62*O62 -> 10099.92
C63: 空调工程 | O63: =P63*(1+Q63)+R63+S63+T63 -> 0 | U63: =F63*O63 -> 0
C64: 设备 | O64: =P64*(1+Q64)+R64+S64+T64 -> 0 | U64: =F64*O64 -> 0
A65: 50 | B65: 30701003001 | C65: 风管机 | D65: 1.名称：超薄风管式室内机 FF25 2.规格：制冷量2.5kW 制冷功率40W 制热量3.0kW 制热功率40W 风量500m3/h 运转噪音≤29dB(A) 3.安装方式：吊装 4.其他：包括但不限于满足图纸、招标文件、规范及验收要求等一切相关费用 | E65: 台 | F65: 1 | G65: =R65*$R$3 -> 1000 | H65: =P65*(1+Q65)*$P$3+S65*$S$3 -> 4800 | I65: =T65*$T$3 -> 45 | J65: =(G65+H65+I65)*$J$3 -> 0 | K65: =(G65+H65+I65+J65)*$K$3 -> 0 | L65: =G65+H65+I65+J65+K65 -> 5845 | M65: =F65*L65 -> 5845 | O65: =P65*(1+Q65)+R65+S65+T65 -> 5845 | P65: 3600 | Q65: 0 | R65: 1000 | S65: 1200 | T65: 45 | U65: =F65*O65 -> 5845
A66: 51 | B66: 30701003002 | C66: 风管机 | D66: 1.名称：超薄风管式室内机 FF36 2.规格：制冷量3.6kW 制冷功率50W 制热量4.5kW 制热功率50W 风量550m3/h 运转噪音≤29dB(A) 3.安装方式：吊装 4.其他：包括但不限于满足图纸、招标文件、规范及验收要求等一切相关费用 | E66: 台 | F66: 2 | G66: =R66*$R$3 -> 1000 | H66: =P66*(1+Q66)*$P$3+S66*$S$3 -> 4800 | I66: =T66*$T$3 -> 45 | J66: =(G66+H66+I66)*$J$3 -> 0 | K66: =(G66+H66+I66+J66)*$K$3 -> 0 | L66: =G66+H66+I66+J66+K66 -> 5845 | M66: =F66*L66 -> 11690 | O66: =P66*(1+Q66)+R66+S66+T66 -> 5845 | P66: 3600 | Q66: 0 | R66: 1000 | S66: 1200 | T66: 45 | U66: =F66*O66 -> 11690
A67: 52 | B67: 30701003003 | C67: 风管机 | D67: 1.名称：超薄风管式室内机 FF45 2.规格：制冷量4.5kW 制冷功率60W 制热量5.0kW 制热功率60W 风量800m3/h 运转噪音≤30dB(A) 3.安装方式：吊装 4.其他：包括但不限于满足图纸、招标文件、规范及验收要求等一切相关费用 | E67: 台 | F67: 1 | G67: =R67*$R$3 -> 1000 | H67: =P67*(1+Q67)*$P$3+S67*$S$3 -> 4800 | I67: =T67*$T$3 -> 45 | J67: =(G67+H67+I67)*$J$3 -> 0 | K67: =(G67+H67+I67+J67)*$K$3 -> 0 | L67: =G67+H67+I67+J67+K67 -> 5845 | M67: =F67*L67 -> 5845 | O67: =P67*(1+Q67)+R67+S67+T67 -> 5845 | P67: 3600 | Q67: 0 | R67: 1000 | S67: 1200 | T67: 45 | U67: =F67*O67 -> 5845
A68: 53 | B68: 30701003004 | C68: 风管机 | D68: 1.名称：超薄风管式室内机 FF56 2.规格：制冷量5.6kW 制冷功率60W 制热量6.3kW 制热功率60W 风量850m3/h 运转噪音≤33dB(A) 3.安装方式：吊装 4.其他：包括但不限于满足图纸、招标文件、规范及验收要求等一切相关费用 | E68: 台 | F68: 2 | G68: =R68*$R$3 -> 1000 | H68: =P68*(1+Q68)*$P$3+S68*$S$3 -> 4800 | I68: =T68*$T$3 -> 45 | J68: =(G68+H68+I68)*$J$3 -> 0 | K68: =(G68+H68+I68+J68)*$K$3 -> 0 | L68: =G68+H68+I68+J68+K68 -> 5845 | M68: =F68*L68 -> 11690 | O68: =P68*(1+Q68)+R68+S68+T68 -> 5845 | P68: 3600 | Q68: 0 | R68: 1000 | S68: 1200 | T68: 45 | U68: =F68*O68 -> 11690
A69: 54 | B69: 30701003005 | C69: 多联式室外机 | D69: 1.名称：多联式室外机 SWJ-224 2.规格：制冷量24.4kW 制冷功率6300W 制热量24.5kW 制热功率6000W 风量9500m3/h 运转噪音≤60dB(A) 3.安装方式：落地 4.其他：包括但不限于满足图纸、招标文件、规范及验收要求等一切相关费用 | E69: 台 | F69: 1 | G69: =R69*$R$3 -> 732.5 | H69: =P69*(1+Q69)*$P$3+S69*$S$3 -> 12600 | I69: =T69*$T$3 -> 25 | J69: =(G69+H69+I69)*$J$3 -> 0 | K69: =(G69+H69+I69+J69)*$K$3 -> 0 | L69: =G69+H69+I69+J69+K69 -> 13357.5 | M69: =F69*L69 -> 13357.5 | O69: =P69*(1+Q69)+R69+S69+T69 -> 13357.5 | P69: 12000 | Q69: 0 | R69: 732.5 | S69: 600 | T69: 25 | U69: =F69*O69 -> 13357.5
A70: 55 | B70: 30413013008 | C70: 空调温控面板 | D70: 1.名称：空调温控面板 2.规格：86*86mm 3.安装方式：暗装 4.其他：包括但不限于满足图纸、招标文件、规范及验收要求等一切相关费用 | E70: 套 | F70: 6 | G70: =R70*$R$3 -> 35 | H70: =P70*(1+Q70)*$P$3+S70*$S$3 -> 103 | I70: =T70*$T$3 -> 0 | J70: =(G70+H70+I70)*$J$3 -> 0 | K70: =(G70+H70+I70+J70)*$K$3 -> 0 | L70: =G70+H70+I70+J70+K70 -> 138 | M70: =F70*L70 -> 828 | O70: =P70*(1+Q70)+R70+S70+T70 -> 138 | P70: =架空层安装工程!$P$33 -> 95 | Q70: =架空层安装工程!$Q$33 -> 0 | R70: =架空层安装工程!$R$33 -> 35 | S70: =架空层安装工程!$S$33 -> 8 | T70: =架空层安装工程!$T$33 -> 0 | U70: =F70*O70 -> 828
C71: 风管 | O71: =P71*(1+Q71)+R71+S71+T71 -> 0 | U71: =F71*O71 -> 0
A72: 56 | B72: 30702001001 | C72: 碳钢通风管道 | D72: 1.名称：矩形风管 2.材质：镀锌薄钢板 3.厚度：0.6mm 4.长边：≤1000mm 5.其他：包括但不限于满足图纸、招标文件、规范及验收要求等一切相关费用 | E72: m2 | F72: 3.71 | G72: =R72*$R$3 -> 48 | H72: =P72*(1+Q72)*$P$3+S72*$S$3 -> 99.55 | I72: =T72*$T$3 -> 2 | J72: =(G72+H72+I72)*$J$3 -> 0 | K72: =(G72+H72+I72+J72)*$K$3 -> 0 | L72: =G72+H72+I72+J72+K72 -> 149.55 | M72: =F72*L72 -> 554.8305 | O72: =P72*(1+Q72)+R72+S72+T72 -> 149.55 | P72: =架空层安装工程!$P$40 -> 85 | Q72: =架空层安装工程!$Q$40 -> 0.03 | R72: =架空层安装工程!$R$40 -> 48 | S72: =架空层安装工程!$S$40 -> 12 | T72: =架空层安装工程!$T$40 -> 2 | U72: =F72*O72 -> 554.8305
A73: 57 | B73: 30703019001 | C73: 柔性接口 | D73: 1.名称：帆布软接口 2.材质：帆布 3.厚度：满足验收要求 4.其他：包括但不限于满足图纸、招标文件、规范及验收要求等一切相关费用 | E73: m2 | F73: 1.82 | G73: =R73*$R$3 -> 55 | H73: =P73*(1+Q73)*$P$3+S73*$S$3 -> 78.89 | I73: =T73*$T$3 -> 2.75 | J73: =(G73+H73+I73)*$J$3 -> 0 | K73: =(G73+H73+I73+J73)*$K$3 -> 0 | L73: =G73+H73+I73+J73+K73 -> 136.64 | M73: =F73*L73 -> 248.6848 | O73: =P73*(1+Q73)+R73+S73+T73 -> 136.64 | P73: =架空层安装工程!$P$43 -> 19.49 | Q73: =架空层安装工程!$Q$43 -> 0 | R73: =架空层安装工程!$R$43 -> 55 | S73: =架空层安装工程!$S$43 -> 59.4 | T73: =架空层安装工程!$T$43 -> 2.75 | U73: =F73*O73 -> 248.6848
A74: 58 | B74: 31301005001 | C74: 风管支架刷油 | D74: 1.名称：风管支架刷油 2.按图纸及规范要求 3.其他：包括但不限于以上内容，综合考虑按图纸、招标文件和规范要求而实施、完成这项工程的一切有关费用 | E74: kg | F74: 13.48 | G74: =R74*$R$3 -> 5.77 | H74: =P74*(1+Q74)*$P$3+S74*$S$3 -> 6.87 | I74: =T74*$T$3 -> 1.21 | J74: =(G74+H74+I74)*$J$3 -> 0 | K74: =(G74+H74+I74+J74)*$K$3 -> 0 | L74: =G74+H74+I74+J74+K74 -> 13.85 | M74: =F74*L74 -> 186.698 | O74: =P74*(1+Q74)+R74+S74+T74 -> 13.85 | P74: =架空层安装工程!$P$44 -> 6.87 | Q74: =架空层安装工程!$Q$44 -> 0 | R74: =架空层安装工程!$R$44 -> 5.77 | S74: =架空层安装工程!$S$44 -> 0 | T74: =架空层安装工程!$T$44 -> 1.21 | U74: =F74*O74 -> 186.698
A75: 59 | B75: 31208003001 | C75: 通风管道绝热 | D75: 1.名称：空调风管保温 2.材质：难燃级B1级橡塑保温材料，不燃A级铝箔贴面，湿阻因子≥10000，符合国家GB8624-2012中的管状绝热材料B标准 3.厚度：20mm 4.其他：包括但不限于满足图纸、招标文件、规范及验收要求等一切相关费用 | E75: m2 | F75: 3.71 | G75: =R75*$R$3 -> 48 | H75: =P75*(1+Q75)*$P$3+S75*$S$3 -> 412 | I75: =T75*$T$3 -> 2 | J75: =(G75+H75+I75)*$J$3 -> 0 | K75: =(G75+H75+I75+J75)*$K$3 -> 0 | L75: =G75+H75+I75+J75+K75 -> 462 | M75: =F75*L75 -> 1714.02 | O75: =P75*(1+Q75)+R75+S75+T75 -> 462 | P75: =架空层安装工程!$P$45 -> 400 | Q75: =架空层安装工程!$Q$45 -> 0 | R75: =架空层安装工程!$R$45 -> 48 | S75: =架空层安装工程!$S$45 -> 12 | T75: =架空层安装工程!$T$45 -> 2 | U75: =F75*O75 -> 1714.02
A76: 60 | B76: 30704001001 | C76: 通风工程检测、调试 | D76: 1.名称：风管漏光试验、漏风试验 | E76: 系统 | F76: 1 | G76: =R76*$R$3 -> 380 | H76: =P76*(1+Q76)*$P$3+S76*$S$3 -> 600 | I76: =T76*$T$3 -> 20 | J76: =(G76+H76+I76)*$J$3 -> 0 | K76: =(G76+H76+I76+J76)*$K$3 -> 0 | L76: =G76+H76+I76+J76+K76 -> 1000 | M76: =F76*L76 -> 1000 | O76: =P76*(1+Q76)+R76+S76+T76 -> 1000 | P76: =架空层安装工程!$P$46 -> 400 | Q76: =架空层安装工程!$Q$46 -> 0 | R76: =架空层安装工程!$R$46 -> 380 | S76: =架空层安装工程!$S$46 -> 200 | T76: =架空层安装工程!$T$46 -> 20 | U76: =F76*O76 -> 1000
C77: 水管 | O77: =P77*(1+Q77)+R77+S77+T77 -> 0 | U77: =F77*O77 -> 0
A78: 61 | B78: 31001005001 | C78: 铜管 | D78: 1.名称：紫铜管 2.规格：φ6.4 3.厚度：0.8mm 4.连接方式：钎焊连结 5.其他：包括但不限于满足图纸、招标文件、规范及验收要求等一切相关费用 | E78: m | F78: 9.18 | G78: =R78*$R$3 -> 9.64 | H78: =P78*(1+Q78)*$P$3+S78*$S$3 -> 13.1816 | I78: =T78*$T$3 -> 0 | J78: =(G78+H78+I78)*$J$3 -> 0 | K78: =(G78+H78+I78+J78)*$K$3 -> 0 | L78: =G78+H78+I78+J78+K78 -> 22.8216 | M78: =F78*L78 -> 209.50229 | O78: =P78*(1+Q78)+R78+S78+T78 -> 22.8216 | P78: =架空层安装工程!$P$48 -> 10.72 | Q78: =架空层安装工程!$Q$48 -> 0.03 | R78: =架空层安装工程!$R$48 -> 9.64 | S78: =架空层安装工程!$S$48 -> 2.14 | T78: =架空层安装工程!$T$48 -> 0 | U78: =F78*O78 -> 209.50229
A79: 62 | B79: 31001005002 | C79: 铜管 | D79: 1.名称：紫铜管 2.规格：φ9.5 3.厚度：0.8mm 4.连接方式：钎焊连结 5.其他：包括但不限于满足图纸、招标文件、规范及验收要求等一切相关费用 | E79: m | F79: 15.88 | G79: =R79*$R$3 -> 14.29 | H79: =P79*(1+Q79)*$P$3+S79*$S$3 -> 17.7632 | I79: =T79*$T$3 -> 0 | J79: =(G79+H79+I79)*$J$3 -> 0 | K79: =(G79+H79+I79+J79)*$K$3 -> 0 | L79: =G79+H79+I79+J79+K79 -> 32.0532 | M79: =F79*L79 -> 509.00482 | O79: =P79*(1+Q79)+R79+S79+T79 -> 32.0532 | P79: =架空层安装工程!$P$49 -> 14.44 | Q79: =架空层安装工程!$Q$49 -> 0.03 | R79: =架空层安装工程!$R$49 -> 14.29 | S79: =架空层安装工程!$S$49 -> 2.89 | T79: =架空层安装工程!$T$49 -> 0 | U79: =F79*O79 -> 509.00482
A80: 63 | B80: 31001005003 | C80: 铜管 | D80: 1.名称：紫铜管 2.规格：φ12.7 3.厚度：0.8mm 4.连接方式：钎焊连结 5.其他：包括但不限于满足图纸、招标文件、规范及验收要求等一切相关费用 | E80: m | F80: 9.18 | G80: =R80*$R$3 -> 19.09 | H80: =P80*(1+Q80)*$P$3+S80*$S$3 -> 19.0138 | I80: =T80*$T$3 -> 0 | J80: =(G80+H80+I80)*$J$3 -> 0 | K80: =(G80+H80+I80+J80)*$K$3 -> 0 | L80: =G80+H80+I80+J80+K80 -> 38.1038 | M80: =F80*L80 -> 349.79288 | O80: =P80*(1+Q80)+R80+S80+T80 -> 38.1038 | P80: =架空层安装工程!$P$50 -> 15.46 | Q80: =架空层安装工程!$Q$50 -> 0.03 | R80: =架空层安装工程!$R$50 -> 19.09 | S80: =架空层安装工程!$S$50 -> 3.09 | T80: =架空层安装工程!$T$50 -> 0 | U80: =F80*O80 -> 349.79288
A81: 64 | B81: 31001005004 | C81: 铜管 | D81: 1.名称：紫铜管 2.规格：φ15.9 3.厚度：1.0mm 4.连接方式：钎焊连结 5.其他：包括但不限于满足图纸、招标文件、规范及验收要求等一切相关费用 | E81: m | F81: 15.88 | G81: =R81*$R$3 -> 23.89 | H81: =P81*(1+Q81)*$P$3+S81*$S$3 -> 26.4962 | I81: =T81*$T$3 -> 0 | J81: =(G81+H81+I81)*$J$3 -> 0 | K81: =(G81+H81+I81+J81)*$K$3 -> 0 | L81: =G81+H81+I81+J81+K81 -> 50.3862 | M81: =F81*L81 -> 800.13286 | O81: =P81*(1+Q81)+R81+S81+T81 -> 50.3862 | P81: =架空层安装工程!$P$51 -> 21.54 | Q81: =架空层安装工程!$Q$51 -> 0.03 | R81: =架空层安装工程!$R$51 -> 23.89 | S81: =架空层安装工程!$S$51 -> 4.31 | T81: =架空层安装工程!$T$51 -> 0 | U81: =F81*O81 -> 800.13286
A82: 65 | B82: 31002001001 | C82: 分歧器 | D82: 1.名称：分歧器 2.规格：公称直径20mm以内 3.其他：包括但不限于满足图纸、招标文件、规范及验收要求等一切相关费用 | E82: 个 | F82: 5 | G82: =R82*$R$3 -> 94 | H82: =P82*(1+Q82)*$P$3+S82*$S$3 -> 177 | I82: =T82*$T$3 -> 4.7 | J82: =(G82+H82+I82)*$J$3 -> 0 | K82: =(G82+H82+I82+J82)*$K$3 -> 0 | L82: =G82+H82+I82+J82+K82 -> 275.7 | M82: =F82*L82 -> 1378.5 | O82: =P82*(1+Q82)+R82+S82+T82 -> 275.7 | P82: =架空层安装工程!$P$54 -> 118 | Q82: =架空层安装工程!$Q$54 -> 0 | R82: =架空层安装工程!$R$54 -> 94 | S82: =架空层安装工程!$S$54 -> 59 | T82: =架空层安装工程!$T$54 -> 4.7 | U82: =F82*O82 -> 1378.5
A83: 66 | B83: 31001008010 | C83: 塑料管 | D83: 1.名称：UPVC管 2.规格：DN20 3.介质：冷凝水 4.连接方式：粘接 5.其他：包括但不限于满足图纸、招标文件、规范及验收要求等一切相关费用 | E83: m | F83: 15.87 | G83: =R83*$R$3 -> 18 | H83: =P83*(1+Q83)*$P$3+S83*$S$3 -> 4.76 | I83: =T83*$T$3 -> 0.04 | J83: =(G83+H83+I83)*$J$3 -> 0 | K83: =(G83+H83+I83+J83)*$K$3 -> 0 | L83: =G83+H83+I83+J83+K83 -> 22.8 | M83: =F83*L83 -> 361.836 | O83: =P83*(1+Q83)+R83+S83+T83 -> 22.8 | P83: 4.5 | Q83: 0 | R83: 18 | S83: 0.26 | T83: 0.04 | U83: =F83*O83 -> 361.836
A84: 67 | B84: 31001008011 | C84: 塑料管 | D84: 1.名称：UPVC管 2.规格：DN25 3.介质：冷凝水 4.连接方式：粘接 5.其他：包括但不限于满足图纸、招标文件、规范及验收要求等一切相关费用 | E84: m | F84: 3.81 | G84: =R84*$R$3 -> 22.09 | H84: =P84*(1+Q84)*$P$3+S84*$S$3 -> 8.76 | I84: =T84*$T$3 -> 0.04 | J84: =(G84+H84+I84)*$J$3 -> 0 | K84: =(G84+H84+I84+J84)*$K$3 -> 0 | L84: =G84+H84+I84+J84+K84 -> 30.89 | M84: =F84*L84 -> 117.6909 | O84: =P84*(1+Q84)+R84+S84+T84 -> 30.89 | P84: =架空层安装工程!$P$55 -> 8.5 | Q84: =架空层安装工程!$Q$55 -> 0 | R84: =架空层安装工程!$R$55 -> 22.09 | S84: =架空层安装工程!$S$55 -> 0.26 | T84: =架空层安装工程!$T$55 -> 0.04 | U84: =F84*O84 -> 117.6909
A85: 68 | B85: 31208002003 | C85: 其他管道绝热 | D85: 1.名称：冷媒管保温 2.材质：难燃B1级橡塑 3.厚度：20mm 4.其他：包括但不限于满足图纸、招标文件、规范及验收要求等一切相关费用 | E85: m3 | F85: 0.11 | G85: =R85*$R$3 -> 120 | H85: =P85*(1+Q85)*$P$3+S85*$S$3 -> 410 | I85: =T85*$T$3 -> 5 | J85: =(G85+H85+I85)*$J$3 -> 0 | K85: =(G85+H85+I85+J85)*$K$3 -> 0 | L85: =G85+H85+I85+J85+K85 -> 535 | M85: =F85*L85 -> 58.85 | O85: =P85*(1+Q85)+R85+S85+T85 -> 535 | P85: =架空层安装工程!$P$58 -> 400 | Q85: =架空层安装工程!$Q$58 -> 0 | R85: =架空层安装工程!$R$58 -> 120 | S85: =架空层安装工程!$S$58 -> 10 | T85: =架空层安装工程!$T$58 -> 5 | U85: =F85*O85 -> 58.85
A86: 69 | B86: 31208002004 | C86: 其他管道绝热 | D86: 1.名称：冷凝管保温 2.材质：难燃B1级橡塑 3.厚度：13mm 4.其他：包括但不限于满足图纸、招标文件、规范及验收要求等一切相关费用 | E86: m3 | F86: 0.03 | G86: =R86*$R$3 -> 120 | H86: =P86*(1+Q86)*$P$3+S86*$S$3 -> 410 | I86: =T86*$T$3 -> 5 | J86: =(G86+H86+I86)*$J$3 -> 0 | K86: =(G86+H86+I86+J86)*$K$3 -> 0 | L86: =G86+H86+I86+J86+K86 -> 535 | M86: =F86*L86 -> 16.05 | O86: =P86*(1+Q86)+R86+S86+T86 -> 535 | P86: =架空层安装工程!$P$59 -> 400 | Q86: =架空层安装工程!$Q$59 -> 0 | R86: =架空层安装工程!$R$59 -> 120 | S86: =架空层安装工程!$S$59 -> 10 | T86: =架空层安装工程!$T$59 -> 5 | U86: =F86*O86 -> 16.05
C87: 119户型 | O87: =P87*(1+Q87)+R87+S87+T87 -> 0 | U87: =F87*O87 -> 0
C88: 电气工程 | O88: =P88*(1+Q88)+R88+S88+T88 -> 0 | U88: =F88*O88 -> 0
C89: 灯具、电器 | O89: =P89*(1+Q89)+R89+S89+T89 -> 0 | U89: =F89*O89 -> 0
A90: 70 | B90: 30413002009 | C90: R1 LED嵌入式射灯 | D90: 1.名称：R1 LED嵌入式射灯 2.规格：12W、3000K、光束角36° 3.安装方式：嵌装 4.其他：包括但不限于满足图纸、招标文件、规范及验收要求等一切相关费用 | E90: 套 | F90: 24 | G90: =R90*$R$3 -> 18 | H90: =P90*(1+Q90)*$P$3+S90*$S$3 -> 126 | I90: =T90*$T$3 -> 8 | J90: =(G90+H90+I90)*$J$3 -> 0 | K90: =(G90+H90+I90+J90)*$K$3 -> 0 | L90: =G90+H90+I90+J90+K90 -> 152 | M90: =F90*L90 -> 3648 | O90: =P90*(1+Q90)+R90+S90+T90 -> 152 | P90: =$P$8 -> 120 | Q90: =$Q$8 -> 0 | R90: =$R$8 -> 18 | S90: =$S$8 -> 6 | T90: =$T$8 -> 8 | U90: =F90*O90 -> 3648
A91: 71 | B91: 30413002010 | C91: R2 LED嵌入式可调角射灯 | D91: 1.名称：R2 LED嵌入式可调角射灯 2.规格：12W、3000K、光束角24° 3.安装方式：嵌装 4.其他：包括但不限于满足图纸、招标文件、规范及验收要求等一切相关费用 | E91: 套 | F91: 26 | G91: =R91*$R$3 -> 18 | H91: =P91*(1+Q91)*$P$3+S91*$S$3 -> 126 | I91: =T91*$T$3 -> 8 | J91: =(G91+H91+I91)*$J$3 -> 0 | K91: =(G91+H91+I91+J91)*$K$3 -> 0 | L91: =G91+H91+I91+J91+K91 -> 152 | M91: =F91*L91 -> 3952 | O91: =P91*(1+Q91)+R91+S91+T91 -> 152 | P91: =$P$9 -> 120 | Q91: =$Q$9 -> 0 | R91: =$R$9 -> 18 | S91: =$S$9 -> 6 | T91: =$T$9 -> 8 | U91: =F91*O91 -> 3952
A92: 72 | B92: 30413002011 | C92: R5 明装单头射灯 | D92: 1.名称：R5 明装单头射灯 2.规格：12W、3000K、光束角36° 3.安装方式：嵌装 4.其他：包括但不限于满足图纸、招标文件、规范及验收要求等一切相关费用 | E92: 套 | F92: 5 | G92: =R92*$R$3 -> 18 | H92: =P92*(1+Q92)*$P$3+S92*$S$3 -> 126 | I92: =T92*$T$3 -> 8 | J92: =(G92+H92+I92)*$J$3 -> 0 | K92: =(G92+H92+I92+J92)*$K$3 -> 0 | L92: =G92+H92+I92+J92+K92 -> 152 | M92: =F92*L92 -> 760 | O92: =P92*(1+Q92)+R92+S92+T92 -> 152 | P92: =$P$12 -> 120 | Q92: =$Q$12 -> 0 | R92: =$R$12 -> 18 | S92: =$S$12 -> 6 | T92: =$T$12 -> 8 | U92: =F92*O92 -> 760
A93: 73 | B93: 30413002012 | C93: L1 LED灯条（天花） | D93: 1.名称：L1 LED灯条（天花） 2.规格：14W/米,3000K,120珠/米 3.安装方式：天花 4.其他：包括但不限于满足图纸、招标文件、规范及验收要求等一切相关费用 | E93: m | F93: 51.35 | G93: =R93*$R$3 -> 2.5 | H93: =P93*(1+Q93)*$P$3+S93*$S$3 -> 12.5 | I93: =T93*$T$3 -> 0 | J93: =(G93+H93+I93)*$J$3 -> 0 | K93: =(G93+H93+I93+J93)*$K$3 -> 0 | L93: =G93+H93+I93+J93+K93 -> 15 | M93: =F93*L93 -> 770.25 | O93: =P93*(1+Q93)+R93+S93+T93 -> 15 | P93: =$P$13 -> 12 | Q93: =$Q$13 -> 0 | R93: =$R$13 -> 2.5 | S93: =$S$13 -> 0.5 | T93: =$T$13 -> 0 | U93: =F93*O93 -> 770.25
A94: 74 | B94: 30413002013 | C94: L3 LED灯条（柜子） | D94: 1.名称：L3 LED灯条（柜子） 2.规格：4W/米,3000K,120珠/米 3.安装方式：天花 4.其他：包括但不限于满足图纸、招标文件、规范及验收要求等一切相关费用 | E94: m | F94: 45.73 | G94: =R94*$R$3 -> 2.5 | H94: =P94*(1+Q94)*$P$3+S94*$S$3 -> 12.5 | I94: =T94*$T$3 -> 0 | J94: =(G94+H94+I94)*$J$3 -> 0 | K94: =(G94+H94+I94+J94)*$K$3 -> 0 | L94: =G94+H94+I94+J94+K94 -> 15 | M94: =F94*L94 -> 685.95 | O94: =P94*(1+Q94)+R94+S94+T94 -> 15 | P94: =$P$15 -> 12 | Q94: =$Q$15 -> 0 | R94: =$R$15 -> 2.5 | S94: =$S$15 -> 0.5 | T94: =$T$15 -> 0 | U94: =F94*O94 -> 685.95
A95: 75 | B95: 30413009002 | C95: LED 灯带驱动电源 | D95: 1.名称：LED 灯带驱动电源 2.规格：60W 工作电压：220V 输出电压：24V 3.尺寸：L140*W45*H29mm 4.其他：包括但不限于满足图纸、招标文件、规范及验收要求等一切相关费用 | E95: 个 | F95: 19 | G95: =R95*$R$3 -> 3 | H95: =P95*(1+Q95)*$P$3+S95*$S$3 -> 20.5 | I95: =T95*$T$3 -> 0 | J95: =(G95+H95+I95)*$J$3 -> 0 | K95: =(G95+H95+I95+J95)*$K$3 -> 0 | L95: =G95+H95+I95+J95+K95 -> 23.5 | M95: =F95*L95 -> 446.5 | O95: =P95*(1+Q95)+R95+S95+T95 -> 23.5 | P95: =架空层安装工程!$P$10 -> 20 | Q95: =架空层安装工程!$Q$10 -> 0 | R95: =架空层安装工程!$R$10 -> 3 | S95: =架空层安装工程!$S$10 -> 0.5 | T95: =架空层安装工程!$T$10 -> 0 | U95: =F95*O95 -> 446.5
A96: 76 | B96: 30405015003 | C96: 线型凉霸及开关 | D96: 1.名称：线型凉霸及开关 2.规格：34W 3.尺寸：详见物料表 4.其他：包括但不限于满足图纸、招标文件、规范及验收要求等一切相关费用 | E96: 台 | F96: 1 | G96: =R96*$R$3 -> 25 | H96: =P96*(1+Q96)*$P$3+S96*$S$3 -> 283 | I96: =T96*$T$3 -> 0 | J96: =(G96+H96+I96)*$J$3 -> 0 | K96: =(G96+H96+I96+J96)*$K$3 -> 0 | L96: =G96+H96+I96+J96+K96 -> 308 | M96: =F96*L96 -> 308 | O96: =P96*(1+Q96)+R96+S96+T96 -> 308 | P96: =$P$17 -> 280 | Q96: =$Q$17 -> 0 | R96: =$R$17 -> 25 | S96: =$S$17 -> 3 | T96: =$T$17 -> 0 | U96: =F96*O96 -> 308
A97: 77 | B97: 30405015004 | C97: 暖风机及开关 | D97: 1.名称：暖风机及开关 2.规格：40W 3.尺寸：详见物料表 4.其他：包括但不限于满足图纸、招标文件、规范及验收要求等一切相关费用 | E97: 台 | F97: 3 | G97: =R97*$R$3 -> 30 | H97: =P97*(1+Q97)*$P$3+S97*$S$3 -> 553 | I97: =T97*$T$3 -> 0 | J97: =(G97+H97+I97)*$J$3 -> 0 | K97: =(G97+H97+I97+J97)*$K$3 -> 0 | L97: =G97+H97+I97+J97+K97 -> 583 | M97: =F97*L97 -> 1749 | O97: =P97*(1+Q97)+R97+S97+T97 -> 583 | P97: 550 | Q97: 0 | R97: 30 | S97: 3 | T97: 0 | U97: =F97*O97 -> 1749
A98: 78 | B98: 30405015005 | C98: 排气扇及开关 | D98: 1.名称：排气扇及开关 2.规格：- 3.尺寸：详见物料表 4.其他：包括但不限于满足图纸、招标文件、规范及验收要求等一切相关费用 | E98: 台 | F98: 3 | G98: =R98*$R$3 -> 21 | H98: =P98*(1+Q98)*$P$3+S98*$S$3 -> 157 | I98: =T98*$T$3 -> 0 | J98: =(G98+H98+I98)*$J$3 -> 0 | K98: =(G98+H98+I98+J98)*$K$3 -> 0 | L98: =G98+H98+I98+J98+K98 -> 178 | M98: =F98*L98 -> 534 | O98: =P98*(1+Q98)+R98+S98+T98 -> 178 | P98: 155 | Q98: 0 | R98: 21 | S98: 2 | T98: 0 | U98: =F98*O98 -> 534
A99: 79 | B99: 30405017002 | C99: 洗碗机 | D99: 1.名称：洗碗机 2.规格：- 3.尺寸：详见物料表 4.其他：包括但不限于满足图纸、招标文件、规范及验收要求等一切相关费用 | E99: 台 | F99: 1 | G99: =R99*$R$3 -> 250 | H99: =P99*(1+Q99)*$P$3+S99*$S$3 -> 4235 | I99: =T99*$T$3 -> 8.5 | J99: =(G99+H99+I99)*$J$3 -> 0 | K99: =(G99+H99+I99+J99)*$K$3 -> 0 | L99: =G99+H99+I99+J99+K99 -> 4493.5 | M99: =F99*L99 -> 4493.5 | O99: =P99*(1+Q99)+R99+S99+T99 -> 4493.5 | P99: =$P$19 -> 4200 | Q99: =$Q$19 -> 0 | R99: =$R$19 -> 250 | S99: =$S$19 -> 35 | T99: =$T$19 -> 8.5 | U99: =F99*O99 -> 4493.5
C100: 开关插座 | O100: =P100*(1+Q100)+R100+S100+T100 -> 0 | U100: =F100*O100 -> 0
...

Sheet 公共区域安装工程
A1: 公共区域安装工程工程量清单 | O1: 成本单价组成（投标人填写）
A2: 序号 | B2: 编码 | C2: 项目名称 | D2: 项目特征 | E2: 单位 | F2: 工程量 | G2: 人工费 | H2: 材料费 | I2: 机械费 | J2: 管理费 | K2: 利润 | L2: 不含税单价 | M2: 合价 | O2: 单价合计 | P2: 主材费 | Q2: 主材损耗率 | R2: 人工费 | S2: 辅材费 | T2: 机械费 | U2: 合计
J3: 0 | K3: 0 | P3: =架空层安装工程!$P$3 -> 1 | R3: =架空层安装工程!$R$3 -> 1 | S3: =架空层安装工程!$S$3 -> 1 | T3: =架空层安装工程!$T$3 -> 1
B4: 单位工程
C5: 批量公区
A6: 1 | B6: 30413002001 | C6: LA-01 嵌入式筒灯 | D6: 1.名称：LA-01 嵌入式筒灯 2.规格：12W 4000K 灯体尺寸Φ118*50mm 3.安装方式：嵌装 4.其他：包括但不限于满足图纸、招标文件、规范及验收要求等一切相关费用 | E6: 套 | F6: 65 | G6: =R6*$R$3 -> 20 | H6: =P6*(1+Q6)*$P$3+S6*$S$3 -> 76 | I6: =T6*$T$3 -> 0 | J6: =(G6+H6+I6)*$J$3 -> 0 | K6: =(G6+H6+I6+J6)*$K$3 -> 0 | L6: =G6+H6+I6+J6+K6 -> 96 | M6: =F6*L6 -> 6240 | O6: =P6*(1+Q6)+R6+S6+T6 -> 96 | P6: 70 | Q6: 0 | R6: 20 | S6: 6 | T6: 0 | U6: =F6*O6 -> 6240
A7: 2 | B7: 30413002002 | C7: LA-02 射灯 | D7: 1.名称：LA-02 射灯 2.规格：12W 4000K 灯体尺寸Φ118*50mm 3.安装方式：嵌装 4.其他：包括但不限于满足图纸、招标文件、规范及验收要求等一切相关费用 | E7: 套 | F7: 61 | G7: =R7*$R$3 -> 18 | H7: =P7*(1+Q7)*$P$3+S7*$S$3 -> 123.5 | I7: =T7*$T$3 -> 0.5 | J7: =(G7+H7+I7)*$J$3 -> 0 | K7: =(G7+H7+I7+J7)*$K$3 -> 0 | L7: =G7+H7+I7+J7+K7 -> 142 | M7: =F7*L7 -> 8662 | O7: =P7*(1+Q7)+R7+S7+T7 -> 142 | P7: 120 | Q7: 0 | R7: 18 | S7: 3.5 | T7: 0.5 | U7: =F7*O7 -> 8662
A8: 3 | B8: 30413002003 | C8: LA-04 红外人体感应筒灯 | D8: 1.名称：LA-04 红外人体感应筒灯 2.规格：9W 4000K 灯体尺寸Φ118*50mm 3.安装方式：嵌装 4.其他：包括但不限于满足图纸、招标文件、规范及验收要求等一切相关费用 | E8: 套 | F8: 10 | G8: =R8*$R$3 -> 20 | H8: =P8*(1+Q8)*$P$3+S8*$S$3 -> 76 | I8: =T8*$T$3 -> 0 | J8: =(G8+H8+I8)*$J$3 -> 0 | K8: =(G8+H8+I8+J8)*$K$3 -> 0 | L8: =G8+H8+I8+J8+K8 -> 96 | M8: =F8*L8 -> 960 | O8: =P8*(1+Q8)+R8+S8+T8 -> 96 | P8: 70 | Q8: 0 | R8: 20 | S8: 6 | T8: 0 | U8: =F8*O8 -> 960
A9: 4 | B9: 30413002004 | C9: LA-05 明装红外人体感应筒灯 | D9: 1.名称：LA-05 明装红外人体感应筒灯 2.规格：9W 4000K 灯体尺寸Φ150*100mm 3.安装方式：明装 4.其他：包括但不限于满足图纸、招标文件、规范及验收要求等一切相关费用 | E9: 套 | F9: 100 | G9: =R9*$R$3 -> 20 | H9: =P9*(1+Q9)*$P$3+S9*$S$3 -> 76 | I9: =T9*$T$3 -> 0 | J9: =(G9+H9+I9)*$J$3 -> 0 | K9: =(G9+H9+I9+J9)*$K$3 -> 0 | L9: =G9+H9+I9+J9+K9 -> 96 | M9: =F9*L9 -> 9600 | O9: =P9*(1+Q9)+R9+S9+T9 -> 96 | P9: 70 | Q9: 0 | R9: 20 | S9: 6 | T9: 0 | U9: =F9*O9 -> 9600
A10: 5 | B10: 30413002005 | C10: LA-06 LED明装筒灯 | D10: 1.名称：LA-06 LED明装筒灯 2.规格：9W 4000K 灯体尺寸Φ150*100mm 3.安装方式：明装 4.其他：包括但不限于满足图纸、招标文件、规范及验收要求等一切相关费用 | E10: 套 | F10: 117 | G10: =R10*$R$3 -> 20 | H10: =P10*(1+Q10)*$P$3+S10*$S$3 -> 76 | I10: =T10*$T$3 -> 0 | J10: =(G10+H10+I10)*$J$3 -> 0 | K10: =(G10+H10+I10+J10)*$K$3 -> 0 | L10: =G10+H10+I10+J10+K10 -> 96 | M10: =F10*L10 -> 11232 | O10: =P10*(1+Q10)+R10+S10+T10 -> 96 | P10: =架空层安装工程!$P$8 -> 70 | Q10: =架空层安装工程!$Q$8 -> 0 | R10: =架空层安装工程!$R$8 -> 20 | S10: =架空层安装工程!$S$8 -> 6 | T10: =架空层安装工程!$T$8 -> 0 | U10: =F10*O10 -> 11232
A11: 6 | B11: 30413002006 | C11: LA-07 LED明装筒灯(带红外感应) | D11: 1.名称：LA-07 LED明装筒灯(带红外感应) 2.规格：9W 4000K 灯体尺寸Φ150*100mm 3.安装方式：明装 4.其他：包括但不限于满足图纸、招标文件、规范及验收要求等一切相关费用 | E11: 套 | F11: 233 | G11: =R11*$R$3 -> 20 | H11: =P11*(1+Q11)*$P$3+S11*$S$3 -> 76 | I11: =T11*$T$3 -> 0 | J11: =(G11+H11+I11)*$J$3 -> 0 | K11: =(G11+H11+I11+J11)*$K$3 -> 0 | L11: =G11+H11+I11+J11+K11 -> 96 | M11: =F11*L11 -> 22368 | O11: =P11*(1+Q11)+R11+S11+T11 -> 96 | P11: 70 | Q11: 0 | R11: 20 | S11: 6 | T11: 0 | U11: =F11*O11 -> 22368
A12: 7 | B12: 30413002007 | C12: LA-03 LED灯带 | D12: 1.名称：LA-03 LED灯带 2.规格：8W/米 4000K L170*W170*H25mm 3.安装方式：天花 4.其他：包括但不限于满足图纸、招标文件、规范及验收要求等一切相关费用 | E12: m | F12: 1471 | G12: =R12*$R$3 -> 12.5 | H12: =P12*(1+Q12)*$P$3+S12*$S$3 -> 20.81 | I12: =T12*$T$3 -> 0 | J12: =(G12+H12+I12)*$J$3 -> 0 | K12: =(G12+H12+I12+J12)*$K$3 -> 0 | L12: =G12+H12+I12+J12+K12 -> 33.31 | M12: =F12*L12 -> 48999.01 | O12: =P12*(1+Q12)+R12+S12+T12 -> 33.31 | P12: 20.4 | Q12: 0 | R12: 12.5 | S12: 0.41 | T12: 0 | U12: =F12*O12 -> 48999.01
A13: 8 | B13: 30413009001 | C13: LED 灯带驱动电源 | D13: 1.名称：LED 灯带驱动电源 2.规格：60W 工作电压：220V 输出电压：24V 3.尺寸：L140*W45*H29mm 4.其他：包括但不限于满足图纸、招标文件、规范及验收要求等一切相关费用 | E13: 个 | F13: 2245 | G13: =R13*$R$3 -> 3 | H13: =P13*(1+Q13)*$P$3+S13*$S$3 -> 20.5 | I13: =T13*$T$3 -> 0 | J13: =(G13+H13+I13)*$J$3 -> 0 | K13: =(G13+H13+I13+J13)*$K$3 -> 0 | L13: =G13+H13+I13+J13+K13 -> 23.5 | M13: =F13*L13 -> 52757.5 | O13: =P13*(1+Q13)+R13+S13+T13 -> 23.5 | P13: =架空层安装工程!$P$10 -> 20 | Q13: =架空层安装工程!$Q$10 -> 0 | R13: =架空层安装工程!$R$10 -> 3 | S13: =架空层安装工程!$S$10 -> 0.5 | T13: =架空层安装工程!$T$10 -> 0 | U13: =F13*O13 -> 52757.5
A14: 9 | B14: 30413013001 | C14: 照明开关 | D14: 1.名称：单联单控开关 2.规格：86*86mm 3.安装方式：暗装 4.其他：包括但不限于满足图纸、招标文件、规范及验收要求等一切相关费用 | E14: 套 | F14: 117 | G14: =R14*$R$3 -> 6.31 | H14: =P14*(1+Q14)*$P$3+S14*$S$3 -> 15.74 | I14: =T14*$T$3 -> 0 | J14: =(G14+H14+I14)*$J$3 -> 0 | K14: =(G14+H14+I14+J14)*$K$3 -> 0 | L14: =G14+H14+I14+J14+K14 -> 22.05 | M14: =F14*L14 -> 2579.85 | O14: =P14*(1+Q14)+R14+S14+T14 -> 22.05 | P14: 14.62 | Q14: 0 | R14: 6.31 | S14: 1.12 | T14: 0 | U14: =F14*O14 -> 2579.85
A15: 10 | B15: 30413013003 | C15: 照明开关 | D15: 1.名称：三联单控开关 2.规格：86*86mm 3.安装方式：暗装 4.其他：包括但不限于满足图纸、招标文件、规范及验收要求等一切相关费用 | E15: 套 | F15: 4 | G15: =R15*$R$3 -> 12 | H15: =P15*(1+Q15)*$P$3+S15*$S$3 -> 21.5 | I15: =T15*$T$3 -> 0 | J15: =(G15+H15+I15)*$J$3 -> 0 | K15: =(G15+H15+I15+J15)*$K$3 -> 0 | L15: =G15+H15+I15+J15+K15 -> 33.5 | M15: =F15*L15 -> 134 | O15: =P15*(1+Q15)+R15+S15+T15 -> 33.5 | P15: 20 | Q15: 0 | R15: 12 | S15: 1.5 | T15: 0 | U15: =F15*O15 -> 134
A16: 11 | B16: 30413014001 | C16: 插座 | D16: 1.名称：五孔插座 2.规格：86*86mm 3.安装方式：暗装 4.其他：包括但不限于满足图纸、招标文件、规范及验收要求等一切相关费用 | E16: 套 | F16: 2 | G16: =R16*$R$3 -> 6.31 | H16: =P16*(1+Q16)*$P$3+S16*$S$3 -> 15.74 | I16: =T16*$T$3 -> 0 | J16: =(G16+H16+I16)*$J$3 -> 0 | K16: =(G16+H16+I16+J16)*$K$3 -> 0 | L16: =G16+H16+I16+J16+K16 -> 22.05 | M16: =F16*L16 -> 44.1 | O16: =P16*(1+Q16)+R16+S16+T16 -> 22.05 | P16: 14.62 | Q16: 0 | R16: 6.31 | S16: 1.12 | T16: 0 | U16: =F16*O16 -> 44.1
A17: 12 | B17: 30412004001 | C17: 配线 | D17: 1.名称：电气配线 2.型号规格：WDZC-BYJ-2.5 3.安装方式：管内穿线 4.其他：包括但不限于满足图纸、招标文件、规范及验收要求等一切相关费用 | E17: m | F17: 11412 | G17: =R17*$R$3 -> 2.2 | H17: =P17*(1+Q17)*$P$3+S17*$S$3 -> 3.1884 | I17: =T17*$T$3 -> 0.02 | J17: =(G17+H17+I17)*$J$3 -> 0 | K17: =(G17+H17+I17+J17)*$K$3 -> 0 | L17: =G17+H17+I17+J17+K17 -> 5.4084 | M17: =F17*L17 -> 61720.661 | O17: =P17*(1+Q17)+R17+S17+T17 -> 5.4084 | P17: 2.92 | Q17: 0.02 | R17: 2.2 | S17: 0.21 | T17: 0.02 | U17: =F17*O17 -> 61720.661
C18: 电梯轿厢
A19: 13 | B19: 30413002008 | C19: 嵌入式筒灯 | D19: 1.名称：嵌入式筒灯 2.规格：- 3.安装方式：嵌装 4.其他：包括但不限于满足图纸、招标文件、规范及验收要求等一切相关费用 | E19: 套 | F19: 8 | G19: =R19*$R$3 -> 20 | H19: =P19*(1+Q19)*$P$3+S19*$S$3 -> 76 | I19: =T19*$T$3 -> 0 | J19: =(G19+H19+I19)*$J$3 -> 0 | K19: =(G19+H19+I19+J19)*$K$3 -> 0 | L19: =G19+H19+I19+J19+K19 -> 96 | M19: =F19*L19 -> 768 | O19: =P19*(1+Q19)+R19+S19+T19 -> 96 | P19: 70 | Q19: 0 | R19: 20 | S19: 6 | T19: 0 | U19: =F19*O19 -> 768
A20: 14 | B20: 30413002009 | C20: LED灯带 | D20: 1.名称：LED灯带 2.规格：8W/米 4000K L170*W170*H25mm 3.安装方式：天花 4.其他：包括但不限于满足图纸、招标文件、规范及验收要求等一切相关费用 | E20: m | F20: 39.68 | G20: =R20*$R$3 -> 12.5 | H20: =P20*(1+Q20)*$P$3+S20*$S$3 -> 20.81 | I20: =T20*$T$3 -> 0 | J20: =(G20+H20+I20)*$J$3 -> 0 | K20: =(G20+H20+I20+J20)*$K$3 -> 0 | L20: =G20+H20+I20+J20+K20 -> 33.31 | M20: =F20*L20 -> 1321.7408 | O20: =P20*(1+Q20)+R20+S20+T20 -> 33.31 | P20: 20.4 | Q20: 0 | R20: 12.5 | S20: 0.41 | T20: 0 | U20: =F20*O20 -> 1321.7408
A21: 15 | B21: 30413009002 | C21: LED 灯带驱动电源 | D21: 1.名称：LED 灯带驱动电源 2.规格：60W 工作电压：220V 输出电压：24V 3.尺寸：L140*W45*H29mm 4.其他：包括但不限于满足图纸、招标文件、规范及验收要求等一切相关费用 | E21: 个 | F21: 8 | G21: =R21*$R$3 -> 3 | H21: =P21*(1+Q21)*$P$3+S21*$S$3 -> 20.5 | I21: =T21*$T$3 -> 0 | J21: =(G21+H21+I21)*$J$3 -> 0 | K21: =(G21+H21+I21+J21)*$K$3 -> 0 | L21: =G21+H21+I21+J21+K21 -> 23.5 | M21: =F21*L21 -> 188 | O21: =P21*(1+Q21)+R21+S21+T21 -> 23.5 | P21: =架空层安装工程!$P$10 -> 20 | Q21: =架空层安装工程!$Q$10 -> 0 | R21: =架空层安装工程!$R$10 -> 3 | S21: =架空层安装工程!$S$10 -> 0.5 | T21: =架空层安装工程!$T$10 -> 0 | U21: =F21*O21 -> 188
A22: 16 | B22: 30412004002 | C22: 配线 | D22: 1.名称：电气配线 2.型号规格：BV-2.5 3.安装方式：管内穿线 4.其他：包括但不限于满足图纸、招标文件、规范及验收要求等一切相关费用 | E22: m | F22: 240 | G22: =R22*$R$3 -> 2.1 | H22: =P22*(1+Q22)*$P$3+S22*$S$3 -> 3.0354 | I22: =T22*$T$3 -> 0.02 | J22: =(G22+H22+I22)*$J$3 -> 0 | K22: =(G22+H22+I22+J22)*$K$3 -> 0 | L22: =G22+H22+I22+J22+K22 -> 5.1554 | M22: =F22*L22 -> 1237.296 | O22: =P22*(1+Q22)+R22+S22+T22 -> 5.1554 | P22: 2.77 | Q22: 0.02 | R22: 2.1 | S22: 0.21 | T22: 0.02 | U22: =F22*O22 -> 1237.296
B23: 税前合价 | E23: 元 | M23: =SUM(M4:M22) -> 228812.16
B24: 税金 | E24: 元 | M24: =$M$23*0.09 -> 20593.094
B25: 含税合价 | E25: 元 | M25: =$M$23+$M$24 -> 249405.25

Sheet 户内交标安装工程
A1: 户内交标安装工程工程量清单 | O1: 成本单价组成（投标人填写）
A2: 序号 | B2: 编码 | C2: 项目名称 | D2: 项目特征 | E2: 单位 | F2: 工程量 | G2: 人工费 | H2: 材料费 | I2: 机械费 | J2: 管理费 | K2: 利润 | L2: 不含税单价 | M2: 合价 | O2: 单价合计 | P2: 主材费 | Q2: 主材损耗率 | R2: 人工费 | S2: 辅材费 | T2: 机械费 | U2: 合计
J3: 0 | K3: 0 | P3: =架空层安装工程!$P$3 -> 1 | R3: =架空层安装工程!$R$3 -> 1 | S3: =架空层安装工程!$S$3 -> 1 | T3: =架空层安装工程!$T$3 -> 1
B4: 单位工程
C5: 电气
A6: 1 | B6: 30413002001 | C6: LA-01 筒灯 | D6: 1.名称：LA-01 筒灯 2.规格：8.5W 4000K 尺寸Φ138*32mm 3.安装方式：嵌装 4.其他：包括但不限于满足图纸、招标文件、规范及验收要求等一切相关费用 | E6: 套 | F6: 730.33333 | G6: =R6*$R$3 -> 20 | H6: =P6*(1+Q6)*$P$3+S6*$S$3 -> 76 | I6: =T6*$T$3 -> 0 | J6: =(G6+H6+I6)*$J$3 -> 0 | K6: =(G6+H6+I6+J6)*$K$3 -> 0 | L6: =G6+H6+I6+J6+K6 -> 96 | M6: =F6*L6 -> 70112 | O6: =P6*(1+Q6)+R6+S6+T6 -> 96 | P6: 70 | Q6: 0 | R6: 20 | S6: 6 | T6: 0 | U6: =F6*O6 -> 70112
A7: 2 | B7: 30413002002 | C7: LA-02 LED嵌入式射灯 | D7: 1.名称：LA-02 LED嵌入式射灯 2.规格：7.5W 4000K 尺寸Φ85*57mm 3.安装方式：嵌装 4.其他：包括但不限于满足图纸、招标文件、规范及验收要求等一切相关费用 | E7: 套 | F7: 254 | G7: =R7*$R$3 -> 18 | H7: =P7*(1+Q7)*$P$3+S7*$S$3 -> 123.5 | I7: =T7*$T$3 -> 0.5 | J7: =(G7+H7+I7)*$J$3 -> 0 | K7: =(G7+H7+I7+J7)*$K$3 -> 0 | L7: =G7+H7+I7+J7+K7 -> 142 | M7: =F7*L7 -> 36068 | O7: =P7*(1+Q7)+R7+S7+T7 -> 142 | P7: 120 | Q7: 0 | R7: 18 | S7: 3.5 | T7: 0.5 | U7: =F7*O7 -> 36068
A8: 3 | B8: 30413002003 | C8: LA-03 防雾射灯 | D8: 1.名称：LA-03 防雾射灯 2.规格：7W 3500K 尺寸Φ86*86mm 3.安装方式：嵌装 4.其他：包括但不限于满足图纸、招标文件、规范及验收要求等一切相关费用 | E8: 套 | F8: 231 | G8: =R8*$R$3 -> 18 | H8: =P8*(1+Q8)*$P$3+S8*$S$3 -> 123.5 | I8: =T8*$T$3 -> 0.5 | J8: =(G8+H8+I8)*$J$3 -> 0 | K8: =(G8+H8+I8+J8)*$K$3 -> 0 | L8: =G8+H8+I8+J8+K8 -> 142 | M8: =F8*L8 -> 32802 | O8: =P8*(1+Q8)+R8+S8+T8 -> 142 | P8: 120 | Q8: 0 | R8: 18 | S8: 3.5 | T8: 0.5 | U8: =F8*O8 -> 32802
A9: 4 | B9: 30413002004 | C9: LA-05 平板灯300*600 | D9: 1.名称：LA-05 平板灯300*600 2.规格：12W 4000K 尺寸300*600mm 3.安装方式：嵌装 4.其他：包括但不限于满足图纸、招标文件、规范及验收要求等一切相关费用 | E9: 套 | F9: 403.33333 | G9: =R9*$R$3 -> 38 | H9: =P9*(1+Q9)*$P$3+S9*$S$3 -> 133 | I9: =T9*$T$3 -> 0 | J9: =(G9+H9+I9)*$J$3 -> 0 | K9: =(G9+H9+I9+J9)*$K$3 -> 0 | L9: =G9+H9+I9+J9+K9 -> 171 | M9: =F9*L9 -> 68970 | O9: =P9*(1+Q9)+R9+S9+T9 -> 171 | P9: 125 | Q9: 0 | R9: 38 | S9: 8 | T9: 0 | U9: =F9*O9 -> 68970
A10: 5 | B10: 30413001001 | C10: LA-06 吸顶灯 | D10: 1.名称：LA-06 吸顶灯 2.规格：18W 4000K 尺寸φ330*H48mm 3.安装方式：嵌装 4.其他：包括但不限于满足图纸、招标文件、规范及验收要求等一切相关费用 | E10: 套 | F10: 185 | G10: =R10*$R$3 -> 10 | H10: =P10*(1+Q10)*$P$3+S10*$S$3 -> 62 | I10: =T10*$T$3 -> 0 | J10: =(G10+H10+I10)*$J$3 -> 0 | K10: =(G10+H10+I10+J10)*$K$3 -> 0 | L10: =G10+H10+I10+J10+K10 -> 72 | M10: =F10*L10 -> 13320 | O10: =P10*(1+Q10)+R10+S10+T10 -> 72 | P10: 60 | Q10: 0 | R10: 10 | S10: 2 | T10: 0 | U10: =F10*O10 -> 13320
A11: 6 | B11: 30413001003 | C11: 普通灯具 | D11: 1.名称：LA-08 LED灯泡+灯座 2.规格：5W 4000K 86*86mm E27螺口 3.安装方式：嵌装 4.其他：包括但不限于满足图纸、招标文件、规范及验收要求等一切相关费用 | E11: 套 | F11: 756.33333 | G11: =R11*$R$3 -> 18 | H11: =P11*(1+Q11)*$P$3+S11*$S$3 -> 49.5 | I11: =T11*$T$3 -> 0.2 | J11: =(G11+H11+I11)*$J$3 -> 0 | K11: =(G11+H11+I11+J11)*$K$3 -> 0 | L11: =G11+H11+I11+J11+K11 -> 67.7 | M11: =F11*L11 -> 51203.767 | O11: =P11*(1+Q11)+R11+S11+T11 -> 67.7 | P11: 48 | Q11: 0 | R11: 18 | S11: 1.5 | T11: 0.2 | U11: =F11*O11 -> 51203.767
A12: 7 | B12: 30413002005 | C12: LA-04 线条灯 | D12: 1.名称：LA-04 线条灯 2.规格：12W/m 尺寸20*10mm 3.安装方式：吊装 4.其他：包括但不限于满足图纸、招标文件、规范及验收要求等一切相关费用 | E12: m | F12: 230.34 | G12: =R12*$R$3 -> 5 | H12: =P12*(1+Q12)*$P$3+S12*$S$3 -> 41 | I12: =T12*$T$3 -> 0 | J12: =(G12+H12+I12)*$J$3 -> 0 | K12: =(G12+H12+I12+J12)*$K$3 -> 0 | L12: =G12+H12+I12+J12+K12 -> 46 | M12: =F12*L12 -> 10595.64 | O12: =P12*(1+Q12)+R12+S12+T12 -> 46 | P12: 40 | Q12: 0 | R12: 5 | S12: 1 | T12: 0 | U12: =F12*O12 -> 10595.64
A13: 8 | B13: 30413002006 | C13: LA-07 LED灯带 | D13: 1.名称：LA-07 LED灯带 2.规格：8W/米 4000K 3.安装方式：天花 4.其他：包括但不限于满足图纸、招标文件、规范及验收要求等一切相关费用 | E13: m | F13: 818.02333 | G13: =R13*$R$3 -> 12.5 | H13: =P13*(1+Q13)*$P$3+S13*$S$3 -> 20.81 | I13: =T13*$T$3 -> 0 | J13: =(G13+H13+I13)*$J$3 -> 0 | K13: =(G13+H13+I13+J13)*$K$3 -> 0 | L13: =G13+H13+I13+J13+K13 -> 33.31 | M13: =F13*L13 -> 27248.357 | O13: =P13*(1+Q13)+R13+S13+T13 -> 33.31 | P13: 20.4 | Q13: 0 | R13: 12.5 | S13: 0.41 | T13: 0 | U13: =F13*O13 -> 27248.357
A14: 9 | B14: 30413009001 | C14: LED 灯带驱动电源 | D14: 1.名称：LED 灯带驱动电源 2.规格：60W 工作电压：220V 输出电压：24V 3.尺寸：L140*W45*H29mm 4.其他：包括但不限于满足图纸、招标文件、规范及验收要求等一切相关费用 | E14: 个 | F14: 136.33333 | G14: =R14*$R$3 -> 3 | H14: =P14*(1+Q14)*$P$3+S14*$S$3 -> 20.5 | I14: =T14*$T$3 -> 0 | J14: =(G14+H14+I14)*$J$3 -> 0 | K14: =(G14+H14+I14+J14)*$K$3 -> 0 | L14: =G14+H14+I14+J14+K14 -> 23.5 | M14: =F14*L14 -> 3203.8333 | O14: =P14*(1+Q14)+R14+S14+T14 -> 23.5 | P14: =架空层安装工程!$P$10 -> 20 | Q14: =架空层安装工程!$Q$10 -> 0 | R14: =架空层安装工程!$R$10 -> 3 | S14: =架空层安装工程!$S$10 -> 0.5 | T14: =架空层安装工程!$T$10 -> 0 | U14: =F14*O14 -> 3203.8333
A15: 10 | B15: 30405015001 | C15: 排气扇 | D15: 1.名称：排气扇 2.规格：40W 风量235m3/h 3.尺寸：详见物料表 4.其他：包括但不限于满足图纸、招标文件、规范及验收要求等一切相关费用 | E15: 台 | F15: 268 | G15: =R15*$R$3 -> 21 | H15: =P15*(1+Q15)*$P$3+S15*$S$3 -> 157 | I15: =T15*$T$3 -> 0 | J15: =(G15+H15+I15)*$J$3 -> 0 | K15: =(G15+H15+I15+J15)*$K$3 -> 0 | L15: =G15+H15+I15+J15+K15 -> 178 | M15: =F15*L15 -> 47704 | O15: =P15*(1+Q15)+R15+S15+T15 -> 178 | P15: 155 | Q15: 0 | R15: 21 | S15: 2 | T15: 0 | U15: =F15*O15 -> 47704
A16: 11 | B16: 30413013001 | C16: 照明开关 | D16: 1.名称：一键开关 2.规格：86*86mm 3.安装方式：暗装 4.其他：包括但不限于满足图纸、招标文件、规范及验收要求等一切相关费用 | E16: 套 | F16: 117.66667 | G16: =R16*$R$3 -> 6.31 | H16: =P16*(1+Q16)*$P$3+S16*$S$3 -> 15.74 | I16: =T16*$T$3 -> 0 | J16: =(G16+H16+I16)*$J$3 -> 0 | K16: =(G16+H16+I16+J16)*$K$3 -> 0 | L16: =G16+H16+I16+J16+K16 -> 22.05 | M16: =F16*L16 -> 2594.55 | O16: =P16*(1+Q16)+R16+S16+T16 -> 22.05 | P16: 14.62 | Q16: 0 | R16: 6.31 | S16: 1.12 | T16: 0 | U16: =F16*O16 -> 2594.55
A17: 12 | B17: 30413013002 | C17: 照明开关 | D17: 1.名称：单联单控开关 2.规格：86*86mm 3.安装方式：暗装 4.其他：包括但不限于满足图纸、招标文件、规范及验收要求等一切相关费用 | E17: 套 | F17: 386 | G17: =R17*$R$3 -> 6.31 | H17: =P17*(1+Q17)*$P$3+S17*$S$3 -> 15.74 | I17: =T17*$T$3 -> 0 | J17: =(G17+H17+I17)*$J$3 -> 0 | K17: =(G17+H17+I17+J17)*$K$3 -> 0 | L17: =G17+H17+I17+J17+K17 -> 22.05 | M17: =F17*L17 -> 8511.3 | O17: =P17*(1+Q17)+R17+S17+T17 -> 22.05 | P17: =公共区域安装工程!$P$14 -> 14.62 | Q17: =公共区域安装工程!$Q$14 -> 0 | R17: =公共区域安装工程!$R$14 -> 6.31 | S17: =公共区域安装工程!$S$14 -> 1.12 | T17: =公共区域安装工程!$T$14 -> 0 | U17: =F17*O17 -> 8511.3
A18: 13 | B18: 30413013003 | C18: 照明开关 | D18: 1.名称：双联单控开关 2.规格：86*86mm 3.安装方式：暗装 4.其他：包括但不限于满足图纸、招标文件、规范及验收要求等一切相关费用 | E18: 套 | F18: 234 | G18: =R18*$R$3 -> 10 | H18: =P18*(1+Q18)*$P$3+S18*$S$3 -> 19.5 | I18: =T18*$T$3 -> 0 | J18: =(G18+H18+I18)*$J$3 -> 0 | K18: =(G18+H18+I18+J18)*$K$3 -> 0 | L18: =G18+H18+I18+J18+K18 -> 29.5 | M18: =F18*L18 -> 6903 | O18: =P18*(1+Q18)+R18+S18+T18 -> 29.5 | P18: =架空层安装工程!$P$16 -> 18 | Q18: =架空层安装工程!$Q$16 -> 0 | R18: =架空层安装工程!$R$16 -> 10 | S18: =架空层安装工程!$S$16 -> 1.5 | T18: =架空层安装工程!$T$16 -> 0 | U18: =F18*O18 -> 6903
A19: 14 | B19: 30413013004 | C19: 照明开关 | D19: 1.名称：三联单控开关 2.规格：86*86mm 3.安装方式：暗装 4.其他：包括但不限于满足图纸、招标文件、规范及验收要求等一切相关费用 | E19: 套 | F19: 100.33333 | G19: =R19*$R$3 -> 12 | H19: =P19*(1+Q19)*$P$3+S19*$S$3 -> 21.5 | I19: =T19*$T$3 -> 0 | J19: =(G19+H19+I19)*$J$3 -> 0 | K19: =(G19+H19+I19+J19)*$K$3 -> 0 | L19: =G19+H19+I19+J19+K19 -> 33.5 | M19: =F19*L19 -> 3361.1667 | O19: =P19*(1+Q19)+R19+S19+T19 -> 33.5 | P19: =公共区域安装工程!$P$15 -> 20 | Q19: =公共区域安装工程!$Q$15 -> 0 | R19: =公共区域安装工程!$R$15 -> 12 | S19: =公共区域安装工程!$S$15 -> 1.5 | T19: =公共区域安装工程!$T$15 -> 0 | U19: =F19*O19 -> 3361.1667
A20: 15 | B20: 30413013005 | C20: 照明开关 | D20: 1.名称：单联双控开关 2.规格：86*86mm 3.安装方式：暗装 4.其他：包括但不限于满足图纸、招标文件、规范及验收要求等一切相关费用 | E20: 套 | F20: 708.66667 | G20: =R20*$R$3 -> 6.31 | H20: =P20*(1+Q20)*$P$3+S20*$S$3 -> 15.74 | I20: =T20*$T$3 -> 0 | J20: =(G20+H20+I20)*$J$3 -> 0 | K20: =(G20+H20+I20+J20)*$K$3 -> 0 | L20: =G20+H20+I20+J20+K20 -> 22.05 | M20: =F20*L20 -> 15626.1 | O20: =P20*(1+Q20)+R20+S20+T20 -> 22.05 | P20: 14.62 | Q20: 0 | R20: 6.31 | S20: 1.12 | T20: 0 | U20: =F20*O20 -> 15626.1
A21: 16 | B21: 30413013006 | C21: 照明开关 | D21: 1.名称：双联双控开关 2.规格：86*86mm 3.安装方式：暗装 4.其他：包括但不限于满足图纸、招标文件、规范及验收要求等一切相关费用 | E21: 套 | F21: 463.66667 | G21: =R21*$R$3 -> 10 | H21: =P21*(1+Q21)*$P$3+S21*$S$3 -> 19.5 | I21: =T21*$T$3 -> 0 | J21: =(G21+H21+I21)*$J$3 -> 0 | K21: =(G21+H21+I21+J21)*$K$3 -> 0 | L21: =G21+H21+I21+J21+K21 -> 29.5 | M21: =F21*L21 -> 13678.167 | O21: =P21*(1+Q21)+R21+S21+T21 -> 29.5 | P21: 18 | Q21: 0 | R21: 10 | S21: 1.5 | T21: 0 | U21: =F21*O21 -> 13678.167
A22: 17 | B22: 30413013007 | C22: 照明开关 | D22: 1.名称：三联双控开关 2.规格：86*86mm 3.安装方式：暗装 4.其他：包括但不限于满足图纸、招标文件、规范及验收要求等一切相关费用 | E22: 套 | F22: 169.33333 | G22: =R22*$R$3 -> 12 | H22: =P22*(1+Q22)*$P$3+S22*$S$3 -> 21.5 | I22: =T22*$T$3 -> 0 | J22: =(G22+H22+I22)*$J$3 -> 0 | K22: =(G22+H22+I22+J22)*$K$3 -> 0 | L22: =G22+H22+I22+J22+K22 -> 33.5 | M22: =F22*L22 -> 5672.6667 | O22: =P22*(1+Q22)+R22+S22+T22 -> 33.5 | P22: 20 | Q22: 0 | R22: 12 | S22: 1.5 | T22: 0 | U22: =F22*O22 -> 5672.6667
A23: 18 | B23: 30413014001 | C23: 插座 | D23: 1.名称：五孔插座 2.规格：86*86mm 3.安装方式：暗装 4.其他：包括但不限于满足图纸、招标文件、规范及验收要求等一切相关费用 | E23: 套 | F23: 2499 | G23: =R23*$R$3 -> 6.31 | H23: =P23*(1+Q23)*$P$3+S23*$S$3 -> 15.74 | I23: =T23*$T$3 -> 0 | J23: =(G23+H23+I23)*$J$3 -> 0 | K23: =(G23+H23+I23+J23)*$K$3 -> 0 | L23: =G23+H23+I23+J23+K23 -> 22.05 | M23: =F23*L23 -> 55102.95 | O23: =P23*(1+Q23)+R23+S23+T23 -> 22.05 | P23: =公共区域安装工程!$P$16 -> 14.62 | Q23: =公共区域安装工程!$Q$16 -> 0 | R23: =公共区域安装工程!$R$16 -> 6.31 | S23: =公共区域安装工程!$S$16 -> 1.12 | T23: =公共区域安装工程!$T$16 -> 0 | U23: =F23*O23 -> 55102.95
A24: 19 | B24: 30413014002 | C24: 插座 | D24: 1.名称：五孔插座（防溅） 2.规格：86*86mm 3.安装方式：暗装 4.其他：包括但不限于满足图纸、招标文件、规范及验收要求等一切相关费用 | E24: 套 | F24: 871 | G24: =R24*$R$3 -> 6.31 | H24: =P24*(1+Q24)*$P$3+S24*$S$3 -> 15.74 | I24: =T24*$T$3 -> 0 | J24: =(G24+H24+I24)*$J$3 -> 0 | K24: =(G24+H24+I24+J24)*$K$3 -> 0 | L24: =G24+H24+I24+J24+K24 -> 22.05 | M24: =F24*L24 -> 19205.55 | O24: =P24*(1+Q24)+R24+S24+T24 -> 22.05 | P24: 14.62 | Q24: 0 | R24: 6.31 | S24: 1.12 | T24: 0 | U24: =F24*O24 -> 19205.55
A25: 20 | B25: 30413014003 | C25: 插座 | D25: 1.名称：五孔插座带开关 2.规格：86*86mm 3.安装方式：暗装 4.其他：包括但不限于满足图纸、招标文件、规范及验收要求等一切相关费用 | E25: 套 | F25: 235.33333 | G25: =R25*$R$3 -> 6.31 | H25: =P25*(1+Q25)*$P$3+S25*$S$3 -> 15.74 | I25: =T25*$T$3 -> 0 | J25: =(G25+H25+I25)*$J$3 -> 0 | K25: =(G25+H25+I25+J25)*$K$3 -> 0 | L25: =G25+H25+I25+J25+K25 -> 22.05 | M25: =F25*L25 -> 5189.1 | O25: =P25*(1+Q25)+R25+S25+T25 -> 22.05 | P25: 14.62 | Q25: 0 | R25: 6.31 | S25: 1.12 | T25: 0 | U25: =F25*O25 -> 5189.1
A26: 21 | B26: 30413014004 | C26: 插座 | D26: 1.名称：五孔插座带USB接口 2.规格：86*86mm 3.安装方式：暗装 4.其他：包括但不限于满足图纸、招标文件、规范及验收要求等一切相关费用 | E26: 套 | F26: 200.33333 | G26: =R26*$R$3 -> 6.31 | H26: =P26*(1+Q26)*$P$3+S26*$S$3 -> 15.74 | I26: =T26*$T$3 -> 0 | J26: =(G26+H26+I26)*$J$3 -> 0 | K26: =(G26+H26+I26+J26)*$K$3 -> 0 | L26: =G26+H26+I26+J26+K26 -> 22.05 | M26: =F26*L26 -> 4417.35 | O26: =P26*(1+Q26)+R26+S26+T26 -> 22.05 | P26: 14.62 | Q26: 0 | R26: 6.31 | S26: 1.12 | T26: 0 | U26: =F26*O26 -> 4417.35
A27: 22 | B27: 30413014005 | C27: 插座 | D27: 1.名称：三孔插座 2.规格：86*86mm 3.安装方式：暗装 4.其他：包括但不限于满足图纸、招标文件、规范及验收要求等一切相关费用 | E27: 套 | F27: 691.66667 | G27: =R27*$R$3 -> 6.31 | H27: =P27*(1+Q27)*$P$3+S27*$S$3 -> 15.74 | I27: =T27*$T$3 -> 0 | J27: =(G27+H27+I27)*$J$3 -> 0 | K27: =(G27+H27+I27+J27)*$K$3 -> 0 | L27: =G27+H27+I27+J27+K27 -> 22.05 | M27: =F27*L27 -> 15251.25 | O27: =P27*(1+Q27)+R27+S27+T27 -> 22.05 | P27: 14.62 | Q27: 0 | R27: 6.31 | S27: 1.12 | T27: 0 | U27: =F27*O27 -> 15251.25
A28: 23 | B28: 30413014006 | C28: 插座 | D28: 1.名称：三孔插座 16A 2.规格：86*86mm 3.安装方式：暗装 4.其他：包括但不限于满足图纸、招标文件、规范及验收要求等一切相关费用 | E28: 套 | F28: 2.6666667 | G28: =R28*$R$3 -> 6.31 | H28: =P28*(1+Q28)*$P$3+S28*$S$3 -> 15.74 | I28: =T28*$T$3 -> 0 | J28: =(G28+H28+I28)*$J$3 -> 0 | K28: =(G28+H28+I28+J28)*$K$3 -> 0 | L28: =G28+H28+I28+J28+K28 -> 22.05 | M28: =F28*L28 -> 58.8 | O28: =P28*(1+Q28)+R28+S28+T28 -> 22.05 | P28: 14.62 | Q28: 0 | R28: 6.31 | S28: 1.12 | T28: 0 | U28: =F28*O28 -> 58.8
A29: 24 | B29: 30413014007 | C29: 插座 | D29: 1.名称：三孔插座带开关（防溅） 2.规格：86*86mm 3.安装方式：暗装 4.其他：包括但不限于满足图纸、招标文件、规范及验收要求等一切相关费用 | E29: 套 | F29: 117.66667 | G29: =R29*$R$3 -> 6.31 | H29: =P29*(1+Q29)*$P$3+S29*$S$3 -> 15.74 | I29: =T29*$T$3 -> 0 | J29: =(G29+H29+I29)*$J$3 -> 0 | K29: =(G29+H29+I29+J29)*$K$3 -> 0 | L29: =G29+H29+I29+J29+K29 -> 22.05 | M29: =F29*L29 -> 2594.55 | O29: =P29*(1+Q29)+R29+S29+T29 -> 22.05 | P29: 14.62 | Q29: 0 | R29: 6.31 | S29: 1.12 | T29: 0 | U29: =F29*O29 -> 2594.55
A30: 25 | B30: 30413014008 | C30: 小夜灯 | D30: 1.名称：小夜灯 2.规格：86*86mm 3.安装方式：暗装 4.其他：包括但不限于满足图纸、招标文件、规范及验收要求等一切相关费用 | E30: 套 | F30: 115.66667 | G30: =R30*$R$3 -> 5 | H30: =P30*(1+Q30)*$P$3+S30*$S$3 -> 15.5 | I30: =T30*$T$3 -> 0 | J30: =(G30+H30+I30)*$J$3 -> 0 | K30: =(G30+H30+I30+J30)*$K$3 -> 0 | L30: =G30+H30+I30+J30+K30 -> 20.5 | M30: =F30*L30 -> 2371.1667 | O30: =P30*(1+Q30)+R30+S30+T30 -> 20.5 | P30: 15 | Q30: 0 | R30: 5 | S30: 0.5 | T30: 0 | U30: =F30*O30 -> 2371.1667
A31: 26 | B31: 30412004001 | C31: 配线 | D31: 1.名称：电气配线 2.型号规格：BV-2.5 3.安装方式：管内穿线 4.其他：包括但不限于满足图纸、招标文件、规范及验收要求等一切相关费用 | E31: m | F31: 56229.66 | G31: =R31*$R$3 -> 2.1 | H31: =P31*(1+Q31)*$P$3+S31*$S$3 -> 3.0354 | I31: =T31*$T$3 -> 0.02 | J31: =(G31+H31+I31)*$J$3 -> 0 | K31: =(G31+H31+I31+J31)*$K$3 -> 0 | L31: =G31+H31+I31+J31+K31 -> 5.1554 | M31: =F31*L31 -> 289886.39 | O31: =P31*(1+Q31)+R31+S31+T31 -> 5.1554 | P31: =公共区域安装工程!$P$22 -> 2.77 | Q31: =公共区域安装工程!$Q$22 -> 0.02 | R31: =公共区域安装工程!$R$22 -> 2.1 | S31: =公共区域安装工程!$S$22 -> 0.21 | T31: =公共区域安装工程!$T$22 -> 0.02 | U31: =F31*O31 -> 289886.39
A32: 27 | B32: 30412004002 | C32: 配线 | D32: 1.名称：电气配线 2.型号规格：BV-4 3.安装方式：管内穿线 4.其他：包括但不限于满足图纸、招标文件、规范及验收要求等一切相关费用 | E32: m | F32: 76002.463 | G32: =R32*$R$3 -> 1.4 | H32: =P32*(1+Q32)*$P$3+S32*$S$3 -> 3.9736 | I32: =T32*$T$3 -> 0.01 | J32: =(G32+H32+I32)*$J$3 -> 0 | K32: =(G32+H32+I32+J32)*$K$3 -> 0 | L32: =G32+H32+I32+J32+K32 -> 5.3836 | M32: =F32*L32 -> 409166.86 | O32: =P32*(1+Q32)+R32+S32+T32 -> 5.3836 | P32: 3.68 | Q32: 0.02 | R32: 1.4 | S32: 0.22 | T32: 0.01 | U32: =F32*O32 -> 409166.86
A33: 28 | B33: 30412004006 | C33: 配线 | D33: 1.名称：电气配线 2.型号规格：RVS-4*1.0 3.安装方式：管内穿线 4.其他：包括但不限于满足图纸、招标文件、规范及验收要求等一切相关费用 | E33: m | F33: 1266.87 | G33: =R33*$R$3 -> 5.2 | H33: =P33*(1+Q33)*$P$3+S33*$S$3 -> 4.106 | I33: =T33*$T$3 -> 0.05 | J33: =(G33+H33+I33)*$J$3 -> 0 | K33: =(G33+H33+I33+J33)*$K$3 -> 0 | L33: =G33+H33+I33+J33+K33 -> 9.356 | M33: =F33*L33 -> 11852.836 | O33: =P33*(1+Q33)+R33+S33+T33 -> 9.356 | P33: =架空层安装工程!$P$23 -> 3.8 | Q33: =架空层安装工程!$Q$23 -> 0.02 | R33: =架空层安装工程!$R$23 -> 5.2 | S33: =架空层安装工程!$S$23 -> 0.23 | T33: =架空层安装工程!$T$23 -> 0.05 | U33: =F33*O33 -> 11852.836
A34: 29 | B34: 30412004004 | C34: 配线 | D34: 1.名称：电气配线 2.型号规格：BV-2.5 3.安装方式：管内穿线 4.其他：包括但不限于满足图纸、招标文件、规范及验收要求等一切相关费用 | E34: m | F34: 1100.8933 | G34: =R34*$R$3 -> 2.1 | H34: =P34*(1+Q34)*$P$3+S34*$S$3 -> 3.0354 | I34: =T34*$T$3 -> 0.02 | J34: =(G34+H34+I34)*$J$3 -> 0 | K34: =(G34+H34+I34+J34)*$K$3 -> 0 | L34: =G34+H34+I34+J34+K34 -> 5.1554 | M34: =F34*L34 -> 5675.5455 | O34: =P34*(1+Q34)+R34+S34+T34 -> 5.1554 | P34: =公共区域安装工程!$P$22 -> 2.77 | Q34: =公共区域安装工程!$Q$22 -> 0.02 | R34: =公共区域安装工程!$R$22 -> 2.1 | S34: =公共区域安装工程!$S$22 -> 0.21 | T34: =公共区域安装工程!$T$22 -> 0.02 | U34: =F34*O34 -> 5675.5455
A35: 30 | B35: 30412004005 | C35: 配线 | D35: 1.名称：电气配线 2.型号规格：BV-4 3.安装方式：管内穿线 4.其他：包括但不限于满足图纸、招标文件、规范及验收要求等一切相关费用 | E35: m | F35: 1253.5333 | G35: =R35*$R$3 -> 1.4 | H35: =P35*(1+Q35)*$P$3+S35*$S$3 -> 3.9736 | I35: =T35*$T$3 -> 0.01 | J35: =(G35+H35+I35)*$J$3 -> 0 | K35: =(G35+H35+I35+J35)*$K$3 -> 0 | L35: =G35+H35+I35+J35+K35 -> 5.3836 | M35: =F35*L35 -> 6748.5221 | O35: =P35*(1+Q35)+R35+S35+T35 -> 5.3836 | P35: =$P$32 -> 3.68 | Q35: =$Q$32 -> 0.02 | R35: =$R$32 -> 1.4 | S35: =$S$32 -> 0.22 | T35: =$T$32 -> 0.01 | U35: =F35*O35 -> 6748.5221
C36: 弱电
A37: 31 | B37: 30413014009 | C37: 插座 | D37: 1.名称：单口网络插座 2.规格：86*86mm 3.安装方式：暗装 4.其他：包括但不限于满足图纸、招标文件、规范及验收要求等一切相关费用 | E37: 套 | F37: 201 | G37: =R37*$R$3 -> 6.31 | H37: =P37*(1+Q37)*$P$3+S37*$S$3 -> 15.74 | I37: =T37*$T$3 -> 0 | J37: =(G37+H37+I37)*$J$3 -> 0 | K37: =(G37+H37+I37+J37)*$K$3 -> 0 | L37: =G37+H37+I37+J37+K37 -> 22.05 | M37: =F37*L37 -> 4432.05 | O37: =P37*(1+Q37)+R37+S37+T37 -> 22.05 | P37: 14.62 | Q37: 0 | R37: 6.31 | S37: 1.12 | T37: 0 | U37: =F37*O37 -> 4432.05
A38: 32 | B38: 30413014010 | C38: 插座 | D38: 1.名称：单口网络插座 2.规格：86*86mm 3.安装方式：暗装 4.其他：包括但不限于满足图纸、招标文件、规范及验收要求等一切相关费用 | E38: 套 | F38: 84.666667 | G38: =R38*$R$3 -> 6.31 | H38: =P38*(1+Q38)*$P$3+S38*$S$3 -> 15.74 | I38: =T38*$T$3 -> 0 | J38: =(G38+H38+I38)*$J$3 -> 0 | K38: =(G38+H38+I38+J38)*$K$3 -> 0 | L38: =G38+H38+I38+J38+K38 -> 22.05 | M38: =F38*L38 -> 1866.9 | O38: =P38*(1+Q38)+R38+S38+T38 -> 22.05 | P38: =$P$37 -> 14.62 | Q38: =$Q$37 -> 0 | R38: =$R$37 -> 6.31 | S38: =$S$37 -> 1.12 | T38: =$T$37 -> 0 | U38: =F38*O38 -> 1866.9
A39: 33 | B39: 30413014011 | C39: 插座 | D39: 1.名称：双口插座(网络+电视) 2.规格：86*86mm 3.安装方式：暗装 4.其他：包括但不限于满足图纸、招标文件、规范及验收要求等一切相关费用 | E39: 套 | F39: 117.66667 | G39: =R39*$R$3 -> 6.31 | H39: =P39*(1+Q39)*$P$3+S39*$S$3 -> 15.74 | I39: =T39*$T$3 -> 0 | J39: =(G39+H39+I39)*$J$3 -> 0 | K39: =(G39+H39+I39+J39)*$K$3 -> 0 | L39: =G39+H39+I39+J39+K39 -> 22.05 | M39: =F39*L39 -> 2594.55 | O39: =P39*(1+Q39)+R39+S39+T39 -> 22.05 | P39: 14.62 | Q39: 0 | R39: 6.31 | S39: 1.12 | T39: 0 | U39: =F39*O39 -> 2594.55
A40: 34 | B40: 30413014012 | C40: 插座 | D40: 1.名称：双口地插(网络+电话) 2.规格：86*86mm 3.安装方式：暗装 4.其他：包括但不限于满足图纸、招标文件、规范及验收要求等一切相关费用 | E40: 套 | F40: 33 | G40: =R40*$R$3 -> 6.31 | H40: =P40*(1+Q40)*$P$3+S40*$S$3 -> 15.74 | I40: =T40*$T$3 -> 0 | J40: =(G40+H40+I40)*$J$3 -> 0 | K40: =(G40+H40+I40+J40)*$K$3 -> 0 | L40: =G40+H40+I40+J40+K40 -> 22.05 | M40: =F40*L40 -> 727.65 | O40: =P40*(1+Q40)+R40+S40+T40 -> 22.05 | P40: 14.62 | Q40: 0 | R40: 6.31 | S40: 1.12 | T40: 0 | U40: =F40*O40 -> 727.65
A41: 35 | B41: 30413013008 | C41: 紧急按钮 | D41: 1.名称：紧急按钮 2.规格：86*86mm 3.安装方式：暗装 4.其他：包括但不限于满足图纸、招标文件、规范及验收要求等一切相关费用 | E41: 套 | F41: 150.66667 | G41: =R41*$R$3 -> 12 | H41: =P41*(1+Q41)*$P$3+S41*$S$3 -> 29 | I41: =T41*$T$3 -> 0 | J41: =(G41+H41+I41)*$J$3 -> 0 | K41: =(G41+H41+I41+J41)*$K$3 -> 0 | L41: =G41+H41+I41+J41+K41 -> 41 | M41: =F41*L41 -> 6177.3333 | O41: =P41*(1+Q41)+R41+S41+T41 -> 41 | P41: =样板房安装工程!P41 -> 27 | Q41: =样板房安装工程!Q41 -> 0 | R41: =样板房安装工程!R41 -> 12 | S41: =样板房安装工程!S41 -> 2 | T41: =样板房安装工程!T41 -> 0 | U41: =F41*O41 -> 6177.3333
A42: 36 | B42: 30502003001 | C42: 双绞线缆 | D42: 1.名称：超六类网线 2.型号规格：CAT6 3.敷设方式：管内穿线 4.其他：包括但不限于满足图纸、招标文件、规范及验收要求等一切相关费用 | E42: m | F42: 6817.96 | G42: =R42*$R$3 -> 0.8 | H42: =P42*(1+Q42)*$P$3+S42*$S$3 -> 2.6 | I42: =T42*$T$3 -> 0.1 | J42: =(G42+H42+I42)*$J$3 -> 0 | K42: =(G42+H42+I42+J42)*$K$3 -> 0 | L42: =G42+H42+I42+J42+K42 -> 3.5 | M42: =F42*L42 -> 23862.86 | O42: =P42*(1+Q42)+R42+S42+T42 -> 3.5 | P42: 2.5 | Q42: 0 | R42: 0.8 | S42: 0.1 | T42: 0.1 | U42: =F42*O42 -> 23862.86
A43: 37 | B43: 30502003002 | C43: 多芯软导线 | D43: 1.名称：多芯软导线 2.型号规格：RVV-2*1.0 3.敷设方式：管内穿线 4.其他：包括但不限于满足图纸、招标文件、规范及验收要求等一切相关费用 | E43: m | F43: 1970.6033 | G43: =R43*$R$3 -> 1.73 | H43: =P43*(1+Q43)*$P$3+S43*$S$3 -> 3.18 | I43: =T43*$T$3 -> 0.02 | J43: =(G43+H43+I43)*$J$3 -> 0 | K43: =(G43+H43+I43+J43)*$K$3 -> 0 | L43: =G43+H43+I43+J43+K43 -> 4.93 | M43: =F43*L43 -> 9715.0744 | O43: =P43*(1+Q43)+R43+S43+T43 -> 4.93 | P43: =样板房安装工程!P43 -> 3 | Q43: =样板房安装工程!Q43 -> 0.02 | R43: =样板房安装工程!R43 -> 1.73 | S43: =样板房安装工程!S43 -> 0.12 | T43: =样板房安装工程!T43 -> 0.02 | U43: =F43*O43 -> 9715.0744
A44: 38 | B44: 30502003003 | C44: 双绞线缆 | D44: 1.名称：超六类网线 2.型号规格：CAT6 3.敷设方式：管内穿线 4.其他：包括但不限于满足图纸、招标文件、规范及验收要求等一切相关费用 | E44: m | F44: 86.293333 | G44: =R44*$R$3 -> 0.8 | H44: =P44*(1+Q44)*$P$3+S44*$S$3 -> 2.6 | I44: =T44*$T$3 -> 0.1 | J44: =(G44+H44+I44)*$J$3 -> 0 | K44: =(G44+H44+I44+J44)*$K$3 -> 0 | L44: =G44+H44+I44+J44+K44 -> 3.5 | M44: =F44*L44 -> 302.02667 | O44: =P44*(1+Q44)+R44+S44+T44 -> 3.5 | P44: =$P$42 -> 2.5 | Q44: =$Q$42 -> 0 | R44: =$R$42 -> 0.8 | S44: =$S$42 -> 0.1 | T44: =$T$42 -> 0.1 | U44: =F44*O44 -> 302.02667
A45: 39 | B45: 30502003004 | C45: 多芯软导线 | D45: 1.名称：多芯软导线 2.型号规格：RVV-2*1.0 3.敷设方式：管内穿线 4.其他：包括但不限于满足图纸、招标文件、规范及验收要求等一切相关费用 | E45: m | F45: 23.313333 | G45: =R45*$R$3 -> 1.73 | H45: =P45*(1+Q45)*$P$3+S45*$S$3 -> 3.18 | I45: =T45*$T$3 -> 0.02 | J45: =(G45+H45+I45)*$J$3 -> 0 | K45: =(G45+H45+I45+J45)*$K$3 -> 0 | L45: =G45+H45+I45+J45+K45 -> 4.93 | M45: =F45*L45 -> 114.93473 | O45: =P45*(1+Q45)+R45+S45+T45 -> 4.93 | P45: =样板房安装工程!$P$43 -> 3 | Q45: =样板房安装工程!$Q$43 -> 0.02 | R45: =样板房安装工程!$R$43 -> 1.73 | S45: =样板房安装工程!$S$43 -> 0.12 | T45: =样板房安装工程!$T$43 -> 0.02 | U45: =F45*O45 -> 114.93473
C46: 洁具五金、排水管
A47: 40 | B47: 31003006001 | C47: 连体马桶 | D47: 1.名称：连体马桶 2.型号：详见物料表(主材甲供) 3.其他：包括但不限于满足图纸、招标文件、规范及验收要求等一切相关费用 | E47: 组 | F47: 301.33333 | G47: =R47*$R$3 -> 60 | H47: =P47*(1+Q47)*$P$3+S47*$S$3 -> 10 | I47: =T47*$T$3 -> 0 | J47: =(G47+H47+I47)*$J$3 -> 0 | K47: =(G47+H47+I47+J47)*$K$3 -> 0 | L47: =G47+H47+I47+J47+K47 -> 70 | M47: =F47*L47 -> 21093.333 | O47: =P47*(1+Q47)+R47+S47+T47 -> 70 | Q47: 0 | R47: 60 | S47: 10 | T47: 0 | U47: =F47*O47 -> 21093.333
A48: 41 | B48: 31003010001 | C48: 淋浴器 | D48: 1.名称：淋浴花洒-主卫 2.型号：详见物料表(主材甲供) 3.其他：包括但不限于满足图纸、招标文件、规范及验收要求等一切相关费用 | E48: 套 | F48: 117.66667 | G48: =R48*$R$3 -> 90 | H48: =P48*(1+Q48)*$P$3+S48*$S$3 -> 35 | I48: =T48*$T$3 -> 0 | J48: =(G48+H48+I48)*$J$3 -> 0 | K48: =(G48+H48+I48+J48)*$K$3 -> 0 | L48: =G48+H48+I48+J48+K48 -> 125 | M48: =F48*L48 -> 14708.333 | O48: =P48*(1+Q48)+R48+S48+T48 -> 125 | Q48: 0 | R48: 90 | S48: 35 | T48: 0 | U48: =F48*O48 -> 14708.333
A49: 42 | B49: 31003010002 | C49: 淋浴器 | D49: 1.名称：淋浴花洒-公卫、次卫(主材甲供) 3.其他：包括但不限于满足图纸、招标文件、规范及验收要求等一切相关费用 | E49: 套 | F49: 183.66667 | G49: =R49*$R$3 -> 90 | H49: =P49*(1+Q49)*$P$3+S49*$S$3 -> 35 | I49: =T49*$T$3 -> 0 | J49: =(G49+H49+I49)*$J$3 -> 0 | K49: =(G49+H49+I49+J49)*$K$3 -> 0 | L49: =G49+H49+I49+J49+K49 -> 125 | M49: =F49*L49 -> 22958.333 | O49: =P49*(1+Q49)+R49+S49+T49 -> 125 | Q49: 0 | R49: 90 | S49: 35 | T49: 0 | U49: =F49*O49 -> 22958.333
A50: 43 | B50: 31003003001 | C50: 台下盆及龙头 | D50: 1.名称：台下盆及龙头 2.型号：详见物料表(主材甲供) 3.其他：包括但不限于满足图纸、招标文件、规范及验收要求等一切相关费用 | E50: 组 | F50: 334.33333 | G50: =R50*$R$3 -> 90 | H50: =P50*(1+Q50)*$P$3+S50*$S$3 -> 12 | I50: =T50*$T$3 -> 0 | J50: =(G50+H50+I50)*$J$3 -> 0 | K50: =(G50+H50+I50+J50)*$K$3 -> 0 | L50: =G50+H50+I50+J50+K50 -> 102 | M50: =F50*L50 -> 34102 | O50: =P50*(1+Q50)+R50+S50+T50 -> 102 | Q50: 0 | R50: 90 | S50: 12 | T50: 0 | U50: =F50*O50 -> 34102
A51: 44 | B51: 31003004001 | C51: 水槽及龙头 | D51: 1.名称：厨房大单盆水槽及龙头 2.型号：详见物料表(主材甲供) 3.其他：包括但不限于满足图纸、招标文件、规范及验收要求等一切相关费用 | E51: 组 | F51: 117.66667 | G51: =R51*$R$3 -> 60 | H51: =P51*(1+Q51)*$P$3+S51*$S$3 -> 40 | I51: =T51*$T$3 -> 0 | J51: =(G51+H51+I51)*$J$3 -> 0 | K51: =(G51+H51+I51+J51)*$K$3 -> 0 | L51: =G51+H51+I51+J51+K51 -> 100 | M51: =F51*L51 -> 11766.667 | O51: =P51*(1+Q51)+R51+S51+T51 -> 100 | Q51: 0 | R51: 60 | S51: 40 | T51: 0 | U51: =F51*O51 -> 11766.667
A52: 45 | B52: 31003014001 | C52: 地漏 | D52: 1.名称：不锈钢地漏-干区 2.规格：DN50 3.型号：详见物料表(主材甲供) 4.其他：包括但不限于满足图纸、招标文件、规范及验收要求等一切相关费用 | E52: 个 | F52: 334.33333 | G52: =R52*$R$3 -> 18 | H52: =P52*(1+Q52)*$P$3+S52*$S$3 -> 5 | I52: =T52*$T$3 -> 0 | J52: =(G52+H52+I52)*$J$3 -> 0 | K52: =(G52+H52+I52+J52)*$K$3 -> 0 | L52: =G52+H52+I52+J52+K52 -> 23 | M52: =F52*L52 -> 7689.6667 | O52: =P52*(1+Q52)+R52+S52+T52 -> 23 | Q52: 0 | R52: 18 | S52: 5 | T52: 0 | U52: =F52*O52 -> 7689.6667
A53: 46 | B53: 31003014002 | C53: 地漏 | D53: 1.名称：不锈钢地漏-淋浴间 2.规格：DN75 3.型号：详见物料表(主材甲供) 4.其他：包括但不限于满足图纸、招标文件、规范及验收要求等一切相关费用 | E53: 个 | F53: 301.33333 | G53: =R53*$R$3 -> 25 | H53: =P53*(1+Q53)*$P$3+S53*$S$3 -> 1.5 | I53: =T53*$T$3 -> 0.2 | J53: =(G53+H53+I53)*$J$3 -> 0 | K53: =(G53+H53+I53+J53)*$K$3 -> 0 | L53: =G53+H53+I53+J53+K53 -> 26.7 | M53: =F53*L53 -> 8045.6 | O53: =P53*(1+Q53)+R53+S53+T53 -> 26.7 | Q53: 0 | R53: 25 | S53: 1.5 | T53: 0.2 | U53: =F53*O53 -> 8045.6
A54: 47 | B54: 31003014003 | C54: 地漏 | D54: 1.名称：不锈钢地漏-阳台 2.规格：DN75 3.型号：详见物料表(主材甲供) 4.其他：包括但不限于满足图纸、招标文件、规范及验收要求等一切相关费用 | E54: 个 | F54: 183.66667 | G54: =R54*$R$3 -> 25 | H54: =P54*(1+Q54)*$P$3+S54*$S$3 -> 1.5 | I54: =T54*$T$3 -> 0.2 | J54: =(G54+H54+I54)*$J$3 -> 0 | K54: =(G54+H54+I54+J54)*$K$3 -> 0 | L54: =G54+H54+I54+J54+K54 -> 26.7 | M54: =F54*L54 -> 4903.9 | O54: =P54*(1+Q54)+R54+S54+T54 -> 26.7 | Q54: 0 | R54: 25 | S54: 1.5 | T54: 0.2 | U54: =F54*O54 -> 4903.9
A55: 48 | B55: 31003014004 | C55: 地漏 | D55: 1.名称：洗衣机地漏 2.规格：DN75 3.型号：详见物料表(主材甲供) 4.其他：包括但不限于满足图纸、招标文件、规范及验收要求等一切相关费用 | E55: 个 | F55: 117.66667 | G55: =R55*$R$3 -> 18 | H55: =P55*(1+Q55)*$P$3+S55*$S$3 -> 5 | I55: =T55*$T$3 -> 0 | J55: =(G55+H55+I55)*$J$3 -> 0 | K55: =(G55+H55+I55+J55)*$K$3 -> 0 | L55: =G55+H55+I55+J55+K55 -> 23 | M55: =F55*L55 -> 2706.3333 | O55: =P55*(1+Q55)+R55+S55+T55 -> 23 | Q55: 0 | R55: 18 | S55: 5 | T55: 0 | U55: =F55*O55 -> 2706.3333
A56: 49 | B56: 31003014005 | C56: 洗衣机龙头 | D56: 1.名称：洗衣机龙头 2.规格：DN15 3.型号：详见物料表(主材甲供) 4.其他：包括但不限于满足图纸、招标文件、规范及验收要求等一切相关费用 | E56: 个 | F56: 117.66667 | G56: =R56*$R$3 -> 55 | H56: =P56*(1+Q56)*$P$3+S56*$S$3 -> 20 | I56: =T56*$T$3 -> 0 | J56: =(G56+H56+I56)*$J$3 -> 0 | K56: =(G56+H56+I56+J56)*$K$3 -> 0 | L56: =G56+H56+I56+J56+K56 -> 75 | M56: =F56*L56 -> 8825 | O56: =P56*(1+Q56)+R56+S56+T56 -> 75 | Q56: 0 | R56: 55 | S56: 20 | T56: 0 | U56: =F56*O56 -> 8825
A57: 50 | B57: 31002001001 | C57: 角阀 | D57: 1.名称：热水器角阀(主材甲供) 2.型号规格：DN15 3.其他：包括但不限于满足图纸、招标文件、规范及验收要求等一切相关费用 | E57: 个 | F57: 235.33333 | G57: =R57*$R$3 -> 167.09 | H57: =P57*(1+Q57)*$P$3+S57*$S$3 -> 0 | I57: =T57*$T$3 -> 12.03 | J57: =(G57+H57+I57)*$J$3 -> 0 | K57: =(G57+H57+I57+J57)*$K$3 -> 0 | L57: =G57+H57+I57+J57+K57 -> 179.12 | M57: =F57*L57 -> 42152.907 | O57: =P57*(1+Q57)+R57+S57+T57 -> 179.12 | Q57: 0 | R57: 167.09 | S57: 0 | T57: 12.03 | U57: =F57*O57 -> 42152.907
A58: 51 | B58: 31001008001 | C58: UPVC排水管 | D58: 1.名称：UPVC排水管 2.规格：DN50 3.连接方式：粘接 4.压力试验及吹、洗要求：水压试验、管道标识等 5.其他：包括但不限于满足图纸、招标文件、规范及验收要求等一切相关费用 | E58: m | F58: 883.64667 | G58: =R58*$R$3 -> 24 | H58: =P58*(1+Q58)*$P$3+S58*$S$3 -> 16.27 | I58: =T58*$T$3 -> 0.23 | J58: =(G58+H58+I58)*$J$3 -> 0 | K58: =(G58+H58+I58+J58)*$K$3 -> 0 | L58: =G58+H58+I58+J58+K58 -> 40.5 | M58: =F58*L58 -> 35787.69 | O58: =P58*(1+Q58)+R58+S58+T58 -> 40.5 | P58: =样板房安装工程!$P$46 -> 15 | Q58: =样板房安装工程!$Q$46 -> 0 | R58: =样板房安装工程!$R$46 -> 24 | S58: =样板房安装工程!$S$46 -> 1.27 | T58: =样板房安装工程!$T$46 -> 0.23 | U58: =F58*O58 -> 35787.69
A59: 52 | B59: 31001008002 | C59: UPVC排水管 | D59: 1.名称：UPVC排水管 2.规格：DN75 3.连接方式：粘接 4.压力试验及吹、洗要求：水压试验、管道标识等 5.其他：包括但不限于满足图纸、招标文件、规范及验收要求等一切相关费用 | E59: m | F59: 743.49 | G59: =R59*$R$3 -> 55 | H59: =P59*(1+Q59)*$P$3+S59*$S$3 -> 28 | I59: =T59*$T$3 -> 3 | J59: =(G59+H59+I59)*$J$3 -> 0 | K59: =(G59+H59+I59+J59)*$K$3 -> 0 | L59: =G59+H59+I59+J59+K59 -> 86 | M59: =F59*L59 -> 63940.14 | O59: =P59*(1+Q59)+R59+S59+T59 -> 86 | P59: =样板房安装工程!$P$47 -> 25 | Q59: =样板房安装工程!$Q$47 -> 0 | R59: =样板房安装工程!$R$47 -> 55 | S59: =样板房安装工程!$S$47 -> 3 | T59: =样板房安装工程!$T$47 -> 3 | U59: =F59*O59 -> 63940.14
A60: 53 | B60: 31001008003 | C60: UPVC排水管 | D60: 1.名称：UPVC排水管 2.规格：DN100 3.连接方式：粘接 4.压力试验及吹、洗要求：水压试验、管道标识等 5.其他：包括但不限于满足图纸、招标文件、规范及验收要求等一切相关费用 | E60: m | F60: 268.99667 | G60: =R60*$R$3 -> 30 | H60: =P60*(1+Q60)*$P$3+S60*$S$3 -> 38.12 | I60: =T60*$T$3 -> 0.38 | J60: =(G60+H60+I60)*$J$3 -> 0 | K60: =(G60+H60+I60+J60)*$K$3 -> 0 | L60: =G60+H60+I60+J60+K60 -> 68.5 | M60: =F60*L60 -> 18426.272 | O60: =P60*(1+Q60)+R60+S60+T60 -> 68.5 | P60: =样板房安装工程!$P$48 -> 36 | Q60: =样板房安装工程!$Q$48 -> 0 | R60: =样板房安装工程!$R$48 -> 30 | S60: =样板房安装工程!$S$48 -> 2.12 | T60: =样板房安装工程!$T$48 -> 0.38 | U60: =F60*O60 -> 18426.272
A61: 54 | B61: 31001008004 | C61: UPVC排水管 | D61: 1.名称：UPVC排水管 2.规格：DN50 3.连接方式：粘接 4.压力试验及吹、洗要求：水压试验、管道标识等 5.其他：包括但不限于满足图纸、招标文件、规范及验收要求等一切相关费用 | E61: m | F61: 11.98 | G61: =R61*$R$3 -> 24 | H61: =P61*(1+Q61)*$P$3+S61*$S$3 -> 16.27 | I61: =T61*$T$3 -> 0.23 | J61: =(G61+H61+I61)*$J$3 -> 0 | K61: =(G61+H61+I61+J61)*$K$3 -> 0 | L61: =G61+H61+I61+J61+K61 -> 40.5 | M61: =F61*L61 -> 485.19 | O61: =P61*(1+Q61)+R61+S61+T61 -> 40.5 | P61: =样板房安装工程!$P$46 -> 15 | Q61: =样板房安装工程!$Q$46 -> 0 | R61: =样板房安装工程!$R$46 -> 24 | S61: =样板房安装工程!$S$46 -> 1.27 | T61: =样板房安装工程!$T$46 -> 0.23 | U61: =F61*O61 -> 485.19
A62: 55 | B62: 31001008005 | C62: UPVC排水管 | D62: 1.名称：UPVC排水管 2.规格：DN75 3.连接方式：粘接 4.压力试验及吹、洗要求：水压试验、管道标识等 5.其他：包括但不限于满足图纸、招标文件、规范及验收要求等一切相关费用 | E62: m | F62: 5.7666667 | G62: =R62*$R$3 -> 55 | H62: =P62*(1+Q62)*$P$3+S62*$S$3 -> 28 | I62: =T62*$T$3 -> 3 | J62: =(G62+H62+I62)*$J$3 -> 0 | K62: =(G62+H62+I62+J62)*$K$3 -> 0 | L62: =G62+H62+I62+J62+K62 -> 86 | M62: =F62*L62 -> 495.93333 | O62: =P62*(1+Q62)+R62+S62+T62 -> 86 | P62: =样板房安装工程!$P$47 -> 25 | Q62: =样板房安装工程!$Q$47 -> 0 | R62: =样板房安装工程!$R$47 -> 55 | S62: =样板房安装工程!$S$47 -> 3 | T62: =样板房安装工程!$T$47 -> 3 | U62: =F62*O62 -> 495.93333
A63: 56 | B63: 31001008006 | C63: UPVC排水管 | D63: 1.名称：UPVC排水管 2.规格：DN100 3.连接方式：粘接 4.压力试验及吹、洗要求：水压试验、管道标识等 5.其他：包括但不限于满足图纸、招标文件、规范及验收要求等一切相关费用 | E63: m | F63: 2.6333333 | G63: =R63*$R$3 -> 30 | H63: =P63*(1+Q63)*$P$3+S63*$S$3 -> 38.12 | I63: =T63*$T$3 -> 0.38 | J63: =(G63+H63+I63)*$J$3 -> 0 | K63: =(G63+H63+I63+J63)*$K$3 -> 0 | L63: =G63+H63+I63+J63+K63 -> 68.5 | M63: =F63*L63 -> 180.38333 | O63: =P63*(1+Q63)+R63+S63+T63 -> 68.5 | P63: =样板房安装工程!$P$48 -> 36 | Q63: =样板房安装工程!$Q$48 -> 0 | R63: =样板房安装工程!$R$48 -> 30 | S63: =样板房安装工程!$S$48 -> 2.12 | T63: =样板房安装工程!$T$48 -> 0.38 | U63: =F63*O63 -> 180.38333
B64: 税前合价 | E64: 元 | M64: =SUM(M4:M63) -> 1593156.5
B65: 税金 | E65: 元 | M65: =$M$64*0.09 -> 143384.08
B66: 含税合价 | E66: 元 | M66: =$M$64+$M$65 -> 1736540.6

Sheet 会所售楼处消防电工程
A1: 会所售楼处消防电工程工程量清单 | Q1: 成本单价组成（投标人填写）
A2: 序号 | B2: 编码 | C2: 项目名称 | D2: 项目特征 | E2: 单位 | F2: 工程量 | G2: 人工费 | H2: 材料费 | I2: 机械费 | J2: 管理费 | K2: 利润 | L2: 不含税单价 | M2: 合价 | N2: 控制价 | Q2: 单价合计 | R2: 主材费 | S2: 主材损耗率 | T2: 人工费 | U2: 辅材费 | V2: 机械费 | W2: 合计
J3: 0 | K3: 0 | N3: 不含税单价 | O3: 不含税合价 | R3: =架空层安装工程!$P$3 -> 1 | T3: =架空层安装工程!$R$3 -> 1 | U3: =架空层安装工程!$S$3 -> 1 | V3: =架空层安装工程!$T$3 -> 1
B4: 单位工程
C5: 消防自动报警系统
A6: 1 | B6: 30904008001 | C6: 消防模块箱 | D6: 1、名称：消防模块箱 2、安装方式：按图纸要求综合考虑 3、其他：包括但不限于以上内容，综合考虑按图纸、招标文件和规范要求而实施、完成这项工程的一切有关费用 | E6: 台 | F6: 2 | G6: =T6*$T$3 -> 30 | H6: =R6*(1+S6)*$R$3+U6*$U$3 -> 108 | I6: =V6*$V$3 -> 0 | J6: =(G6+H6+I6)*$J$3 -> 0 | K6: =(G6+H6+I6+J6)*$K$3 -> 0 | L6: =G6+H6+I6+J6+K6 -> 138 | M6: =F6*L6 -> 276 | N6: 142.1 | O6: =N6*F6 -> 284.2 | Q6: 138 | R6: 100 | S6: 0 | T6: 30 | U6: 8 | V6: 0 | W6: =F6*Q6 -> 276
A7: 2 | B7: 30904007001 | C7: 总线短路隔离器 | D7: 1、名称：总线短路隔离器 2、安装方式：按图纸要求综合考虑 3、其他：包括但不限于以上内容，综合考虑按图纸、招标文件和规范要求而实施、完成这项工程的一切有关费用 | E7: 个 | F7: 2 | G7: =T7*$T$3 -> 15 | H7: =R7*(1+S7)*$R$3+U7*$U$3 -> 235 | I7: =V7*$V$3 -> 0 | J7: =(G7+H7+I7)*$J$3 -> 0 | K7: =(G7+H7+I7+J7)*$K$3 -> 0 | L7: =G7+H7+I7+J7+K7 -> 250 | M7: =F7*L7 -> 500 | N7: 298.04 | O7: =N7*F7 -> 596.08 | Q7: 250 | R7: 230 | S7: 0 | T7: 15 | U7: 5 | V7: 0 | W7: =F7*Q7 -> 500
A8: 3 | B8: 30904007003 | C8: 消防模块 | D8: 1、名称：编码单输入/输出模块 2、安装方式：按图纸要求综合考虑 3、其他：包括但不限于以上内容，综合考虑按图纸、招标文件和规范要求而实施、完成这项工程的一切有关费用 | E8: 个 | F8: 6 | G8: =T8*$T$3 -> 25 | H8: =R8*(1+S8)*$R$3+U8*$U$3 -> 118 | I8: =V8*$V$3 -> 0 | J8: =(G8+H8+I8)*$J$3 -> 0 | K8: =(G8+H8+I8+J8)*$K$3 -> 0 | L8: =G8+H8+I8+J8+K8 -> 143 | M8: =F8*L8 -> 858 | N8: 160.25 | O8: =N8*F8 -> 961.5 | Q8: 143 | R8: 110 | S8: 0 | T8: 25 | U8: 8 | V8: 0 | W8: =F8*Q8 -> 858
A9: 4 | B9: 30904001001 | C9: 点型探测器 | D9: 1、名称：智能型感烟探测器 2、安装方式：按图纸要求综合考虑 3、其他：包括但不限于以上内容，综合考虑按图纸、招标文件和规范要求而实施、完成这项工程的一切有关费用 | E9: 个 | F9: 26 | G9: =T9*$T$3 -> 15 | H9: =R9*(1+S9)*$R$3+U9*$U$3 -> 44 | I9: =V9*$V$3 -> 0 | J9: =(G9+H9+I9)*$J$3 -> 0 | K9: =(G9+H9+I9+J9)*$K$3 -> 0 | L9: =G9+H9+I9+J9+K9 -> 59 | M9: =F9*L9 -> 1534 | N9: 64.26 | O9: =N9*F9 -> 1670.76 | Q9: 59 | R9: 40 | S9: 0 | T9: 15 | U9: 4 | V9: 0 | W9: =F9*Q9 -> 1534
A10: 5 | B10: 30904005001 | C10: 消防报警电话插孔(电话) | D10: 1、名称：消防电话插孔 2、安装方式：按图纸要求综合考虑 3、其他：包括但不限于以上内容，综合考虑按图纸、招标文件和规范要求而实施、完成这项工程的一切有关费用 | E10: 个 | F10: 5 | G10: =T10*$T$3 -> 5 | H10: =R10*(1+S10)*$R$3+U10*$U$3 -> 16.5 | I10: =V10*$V$3 -> 0 | J10: =(G10+H10+I10)*$J$3 -> 0 | K10: =(G10+H10+I10+J10)*$K$3 -> 0 | L10: =G10+H10+I10+J10+K10 -> 21.5 | M10: =F10*L10 -> 107.5 | N10: 22.79 | O10: =N10*F10 -> 113.95 | Q10: 21.5 | R10: 15 | S10: 0 | T10: 5 | U10: 1.5 | V10: 0 | W10: =F10*Q10 -> 107.5
A11: 6 | B11: 30904003001 | C11: 按钮 | D11: 1、名称：编码型手动报警按钮 2、安装方式：按图纸要求综合考虑 3、其他：包括但不限于以上内容，综合考虑按图纸、招标文件和规范要求而实施、完成这项工程的一切有关费用 | E11: 个 | F11: 5 | G11: =T11*$T$3 -> 15 | H11: =R11*(1+S11)*$R$3+U11*$U$3 -> 65 | I11: =V11*$V$3 -> 0 | J11: =(G11+H11+I11)*$J$3 -> 0 | K11: =(G11+H11+I11+J11)*$K$3 -> 0 | L11: =G11+H11+I11+J11+K11 -> 80 | M11: =F11*L11 -> 400 | N11: 85.09 | O11: =N11*F11 -> 425.45 | Q11: 80 | R11: 60 | S11: 0 | T11: 15 | U11: 5 | V11: 0 | W11: =F11*Q11 -> 400
A12: 7 | B12: 30904003002 | C12: 按钮 | D12: 1、名称：编码型消火栓按钮 2、安装方式：按图纸要求综合考虑 3、其他：包括但不限于以上内容，综合考虑按图纸、招标文件和规范要求而实施、完成这项工程的一切有关费用 | E12: 个 | F12: 12 | G12: =T12*$T$3 -> 15 | H12: =R12*(1+S12)*$R$3+U12*$U$3 -> 65 | I12: =V12*$V$3 -> 0 | J12: =(G12+H12+I12)*$J$3 -> 0 | K12: =(G12+H12+I12+J12)*$K$3 -> 0 | L12: =G12+H12+I12+J12+K12 -> 80 | M12: =F12*L12 -> 960 | N12: 85.09 | O12: =N12*F12 -> 1021.08 | Q12: 80 | R12: 60 | S12: 0 | T12: 15 | U12: 5 | V12: 0 | W12: =F12*Q12 -> 960
A13: 8 | B13: 30904004001 | C13: 声光报警器 | D13: 1、名称：声光报警器 2、安装方式：按图纸要求综合考虑 3、其他：包括但不限于以上内容，综合考虑按图纸、招标文件和规范要求而实施、完成这项工程的一切有关费用 | E13: 个 | F13: 5 | G13: =T13*$T$3 -> 18 | H13: =R13*(1+S13)*$R$3+U13*$U$3 -> 86 | I13: =V13*$V$3 -> 0 | J13: =(G13+H13+I13)*$J$3 -> 0 | K13: =(G13+H13+I13+J13)*$K$3 -> 0 | L13: =G13+H13+I13+J13+K13 -> 104 | M13: =F13*L13 -> 520 | N13: 113.57 | O13: =N13*F13 -> 567.85 | Q13: 104 | R13: 80 | S13: 0 | T13: 18 | U13: 6 | V13: 0 | W13: =F13*Q13 -> 520
A14: 9 | B14: 30904005002 | C14: 消防电话分机 | D14: 1、名称：消防电话分机 2、安装方式：按图纸要求综合考虑 3、其他：包括但不限于以上内容，综合考虑按图纸、招标文件和规范要求而实施、完成这项工程的一切有关费用 | E14: 个 | F14: 5 | G14: =T14*$T$3 -> 10 | H14: =R14*(1+S14)*$R$3+U14*$U$3 -> 38 | I14: =V14*$V$3 -> 0 | J14: =(G14+H14+I14)*$J$3 -> 0 | K14: =(G14+H14+I14+J14)*$K$3 -> 0 | L14: =G14+H14+I14+J14+K14 -> 48 | M14: =F14*L14 -> 240 | N14: 50.49 | O14: =N14*F14 -> 252.45 | Q14: 48 | R14: 35 | S14: 0 | T14: 10 | U14: 3 | V14: 0 | W14: =F14*Q14 -> 240
A15: 10 | B15: 30904007004 | C15: 消防模块 | D15: 1、名称：广播模块 2、安装方式：按图纸要求综合考虑 3、其他：包括但不限于以上内容，综合考虑按图纸、招标文件和规范要求而实施、完成这项工程的一切有关费用 | E15: 个 | F15: 2 | G15: =T15*$T$3 -> 25 | H15: =R15*(1+S15)*$R$3+U15*$U$3 -> 118 | I15: =V15*$V$3 -> 0 | J15: =(G15+H15+I15)*$J$3 -> 0 | K15: =(G15+H15+I15+J15)*$K$3 -> 0 | L15: =G15+H15+I15+J15+K15 -> 143 | M15: =F15*L15 -> 286 | N15: 158.07 | O15: =N15*F15 -> 316.14 | Q15: 143 | R15: 110 | S15: 0 | T15: 25 | U15: 8 | V15: 0 | W15: =F15*Q15 -> 286
A16: 11 | B16: 30904006001 | C16: 吸顶式扬声器 | D16: 1、名称：吸顶式扬声器 2、安装方式：按图纸要求综合考虑 3、其他：包括但不限于以上内容，综合考虑按图纸、招标文件和规范要求而实施、完成这项工程的一切有关费用 | E16: 个 | F16: 10 | G16: =T16*$T$3 -> 8 | H16: =R16*(1+S16)*$R$3+U16*$U$3 -> 28 | I16: =V16*$V$3 -> 0 | J16: =(G16+H16+I16)*$J$3 -> 0 | K16: =(G16+H16+I16+J16)*$K$3 -> 0 | L16: =G16+H16+I16+J16+K16 -> 36 | M16: =F16*L16 -> 360 | N16: 43.04 | O16: =N16*F16 -> 430.4 | Q16: 36 | R16: 25 | S16: 0 | T16: 8 | U16: 3 | V16: 0 | W16: =F16*Q16 -> 360
A17: 12 | B17: 30412001001 | C17: 配管 | D17: 1、名称:电气配管JDG20 2、配置形式:暗配 3、厚度:按国标 4、其他：包括但不限于以上内容，综合考虑按图纸、招标文件和规范要求而实施、完成这项工程的一切有关费用 | E17: m | F17: 578.69 | G17: =T17*$T$3 -> 3.5 | H17: =R17*(1+S17)*$R$3+U17*$U$3 -> 8.01 | I17: =V17*$V$3 -> 0 | J17: =(G17+H17+I17)*$J$3 -> 0 | K17: =(G17+H17+I17+J17)*$K$3 -> 0 | L17: =G17+H17+I17+J17+K17 -> 11.51 | M17: =F17*L17 -> 6660.7219 | N17: 11.91 | O17: =N17*F17 -> 6892.1979 | Q17: 11.51 | R17: 7 | S17: 0.03 | T17: 3.5 | U17: 0.8 | V17: 0 | W17: =F17*Q17 -> 6660.7219
... A20: 15 | B20: 30412006001 | C20: 钢质接线盒 | D20: 1、名称：钢质接线盒 2、安装方式：暗装 3、其他：包括但不限于以上内容，按图纸要求综合考虑按图纸、招标文件和规范要求而实施、完成这项工程的一切有关费用 | E20: 个 | F20: 80 | G20: =T20*$T$3 -> 2.5 | H20: =R20*(1+S20)*$R$3+U20*$U$3 -> 6.5 | I20: =V20*$V$3 -> 0 | J20: =(G20+H20+I20)*$J$3 -> 0 | K20: =(G20+H20+I20+J20)*$K$3 -> 0 | L20: =G20+H20+I20+J20+K20 -> 9 | M20: =F20*L20 -> 720 | N20: 10.15 | O20: =N20*F20 -> 812 | Q20: 9 | R20: 6 | S20: 0 | T20: 2.5 | U20: 0.5 | V20: 0 | W20: =F20*Q20 -> 720
A21: 16 | B21: 30412004011 | C21: 剔槽 | D21: 1、名称：线管剔槽 2、型号及规格：70×70mm 3、配置形式、部位：综合考虑 4、其他：包括但不限于以上内容，综合考虑按图纸、招标文件和规范要求而实施、完成这项工程的一切有关费用 | E21: m | F21: 50 | G21: =T21*$T$3 -> 20 | H21: =R21*(1+S21)*$R$3+U21*$U$3 -> 0 | I21: =V21*$V$3 -> 2.5 | J21: =(G21+H21+I21)*$J$3 -> 0 | K21: =(G21+H21+I21+J21)*$K$3 -> 0 | L21: =G21+H21+I21+J21+K21 -> 22.5 | M21: =F21*L21 -> 1125 | N21: 25.5 | O21: =N21*F21 -> 1275 | Q21: =R21*(1+S21)+T21+U21+V21 -> 22.5 | R21: 0 | S21: 0 | T21: 20 | U21: 0 | V21: 2.5 | W21: =F21*Q21 -> 1125
B22: 税前合价 | E22: 元 | M22: =SUM(M4:M21) -> 18011.868 | O22: =SUM(O4:O21) -> 19891.503
B23: 税金 | E23: 元 | M23: =M22*0.09 -> 1621.0681 | O23: =O22*0.09 -> 1790.2353
B24: 含税合价 | E24: 元 | M24: =M22+M23 -> 19632.936 | O24: =O22+O23 -> 21681.738

Sheet 会所售楼处消防水工程
A1: 会所售楼处消防水工程工程量清单 | Q1: 成本单价组成（投标人填写）
A2: 序号 | B2: 编码 | C2: 项目名称 | D2: 项目特征 | E2: 单位 | F2: 工程量 | G2: 人工费 | H2: 材料费 | I2: 机械费 | J2: 管理费 | K2: 利润 | L2: 不含税单价 | M2: 合价 | N2: 控制价 | Q2: 单价合计 | R2: 主材费 | S2: 主材损耗率 | T2: 人工费 | U2: 辅材费 | V2: 机械费 | W2: 合计
J3: 0 | K3: 0 | N3: 不含税单价 | O3: 不含税合价 | R3: =架空层安装工程!$P$3 -> 1 | T3: =架空层安装工程!$R$3 -> 1 | U3: =架空层安装工程!$S$3 -> 1 | V3: =架空层安装工程!$T$3 -> 1
C4: 消防喷淋系统
A5: 2 | B5: 30901001002 | C5: 热浸镀锌钢管 | D5: 1、安装部位：室内 2、材质、规格：热浸镀锌钢管DN150 3、连接形式：按图纸要求 4、钢管镀锌设计要求：国标 5、压力试验及冲洗设计要求：液压试验，水冲洗 6、管道标识设计要求：按图纸要求 7、其他：包括但不限于以上内容，综合考虑按图纸、招标文件和规范要求而实施、完成这项工程的一切有关费用 | E5: m | F5: 11 | G5: =T5*$T$3 -> 18 | H5: =R5*(1+S5)*$R$3+U5*$U$3 -> 111 | I5: =V5*$V$3 -> 0 | J5: =(G5+H5+I5)*$J$3 -> 0 | K5: =(G5+H5+I5+J5)*$K$3 -> 0 | L5: =G5+H5+I5+J5+K5 -> 129 | M5: =F5*L5 -> 1419 | N5: 129.47 | O5: =N5*F5 -> 1424.17 | Q5: 129 | R5: 100 | S5: 0.03 | T5: 18 | U5: 8 | V5: 0 | W5: =F5*Q5 -> 1419
A6: 3 | B6: 30901001003 | C6: 热浸镀锌钢管 | D6: 1、安装部位：室内 2、材质、规格：热浸镀锌钢管DN100 3、连接形式：按图纸要求 4、钢管镀锌设计要求：国标 5、压力试验及冲洗设计要求：液压试验，水冲洗 6、管道标识设计要求：按图纸要求 7、其他：包括但不限于以上内容，综合考虑按图纸、招标文件和规范要求而实施、完成这项工程的一切有关费用 | E6: m | F6: 41 | G6: =T6*$T$3 -> 14 | H6: =R6*(1+S6)*$R$3+U6*$U$3 -> 80.16 | I6: =V6*$V$3 -> 0 | J6: =(G6+H6+I6)*$J$3 -> 0 | K6: =(G6+H6+I6+J6)*$K$3 -> 0 | L6: =G6+H6+I6+J6+K6 -> 94.16 | M6: =F6*L6 -> 3860.56 | N6: 93.12 | O6: =N6*F6 -> 3817.92 | Q6: 94.16 | R6: 72 | S6: 0.03 | T6: 14 | U6: 6 | V6: 0 | W6: =F6*Q6 -> 3860.56
A7: 4 | B7: 30901001004 | C7: 热浸镀锌钢管 | D7: 1、安装部位：室内 2、材质、规格：热浸镀锌钢管DN80 3、连接形式：按图纸要求 4、钢管镀锌设计要求：国标 5、压力试验及冲洗设计要求：液压试验，水冲洗 6、管道标识设计要求：按图纸要求 7、其他：包括但不限于以上内容，综合考虑按图纸、招标文件和规范要求而实施、完成这项工程的一切有关费用 | E7: m | F7: 54 | G7: =T7*$T$3 -> 12 | H7: =R7*(1+S7)*$R$3+U7*$U$3 -> 62.68 | I7: =V7*$V$3 -> 0 | J7: =(G7+H7+I7)*$J$3 -> 0 | K7: =(G7+H7+I7+J7)*$K$3 -> 0 | L7: =G7+H7+I7+J7+K7 -> 74.68 | M7: =F7*L7 -> 4032.72 | N7: 76.52 | O7: =N7*F7 -> 4132.08 | Q7: 74.68 | R7: 56 | S7: 0.03 | T7: 12 | U7: 5 | V7: 0 | W7: =F7*Q7 -> 4032.72
A8: 5 | B8: 30901001005 | C8: 热浸镀锌钢管 | D8: 1、安装部位：室内 2、材质、规格：热浸镀锌钢管DN65 3、连接形式：按图纸要求 4、钢管镀锌设计要求：国标 5、压力试验及冲洗设计要求：液压试验，水冲洗 6、管道标识设计要求：按图纸要求 7、其他：包括但不限于以上内容，综合考虑按图纸、招标文件和规范要求而实施、完成这项工程的一切有关费用 | E8: m | F8: 28 | G8: =T8*$T$3 -> 10 | H8: =R8*(1+S8)*$R$3+U8*$U$3 -> 51.88 | I8: =V8*$V$3 -> 0 | J8: =(G8+H8+I8)*$J$3 -> 0 | K8: =(G8+H8+I8+J8)*$K$3 -> 0 | L8: =G8+H8+I8+J8+K8 -> 61.88 | M8: =F8*L8 -> 1732.64 | N8: 62.58 | O8: =N8*F8 -> 1752.24 | Q8: 61.88 | R8: 46 | S8: 0.03 | T8: 10 | U8: 4.5 | V8: 0 | W8: =F8*Q8 -> 1732.64
A9: 6 | B9: 30901001006 | C9: 热浸镀锌钢管 | D9: 1、安装部位：室内 2、材质、规格：热浸镀锌钢管DN50 3、连接形式：按图纸要求 4、钢管镀锌设计要求：国标 5、压力试验及冲洗设计要求：液压试验，水冲洗 6、管道标识设计要求：按图纸要求 7、其他：包括但不限于以上内容，综合考虑按图纸、招标文件和规范要求而实施、完成这项工程的一切有关费用 | E9: m | F9: 83 | G9: =T9*$T$3 -> 22 | H9: =R9*(1+S9)*$R$3+U9*$U$3 -> 30.9 | I9: =V9*$V$3 -> 0.5 | J9: =(G9+H9+I9)*$J$3 -> 0 | K9: =(G9+H9+I9+J9)*$K$3 -> 0 | L9: =G9+H9+I9+J9+K9 -> 53.4 | M9: =F9*L9 -> 4432.2 | N9: 66.14 | O9: =N9*F9 -> 5489.62 | Q9: =R9*(1+S9)+T9+U9+V9 -> 53.4 | R9: 30 | S9: 0.03 | T9: 22 | U9: 0 | V9: 0.5 | W9: =F9*Q9 -> 4432.2
A10: 7 | B10: 30901001007 | C10: 热浸镀锌钢管 | D10: 1、安装部位：室内 2、材质、规格：热浸镀锌钢管DN40 3、连接形式：按图纸要求 4、钢管镀锌设计要求：国标 5、压力试验及冲洗设计要求：液压试验，水冲洗 6、管道标识设计要求：按图纸要求 7、其他：包括但不限于以上内容，综合考虑按图纸、招标文件和规范要求而实施、完成这项工程的一切有关费用 | E10: m | F10: 38 | G10: =T10*$T$3 -> 20 | H10: =R10*(1+S10)*$R$3+U10*$U$3 -> 22.66 | I10: =V10*$V$3 -> 0.5 | J10: =(G10+H10+I10)*$J$3 -> 0 | K10: =(G10+H10+I10+J10)*$K$3 -> 0 | L10: =G10+H10+I10+J10+K10 -> 43.16 | M10: =F10*L10 -> 1640.08 | N10: 54.99 | O10: =N10*F10 -> 2089.62 | Q10: =R10*(1+S10)+T10+U10+V10 -> 43.16 | R10: 22 | S10: 0.03 | T10: 20 | U10: 0 | V10: 0.5 | W10: =F10*Q10 -> 1640.08
A11: 8 | B11: 30901001008 | C11: 热浸镀锌钢管 | D11: 1、安装部位：室内 2、材质、规格：热浸镀锌钢管DN32 3、连接形式：按图纸要求 4、钢管镀锌设计要求：国标 5、压力试验及冲洗设计要求：液压试验，水冲洗 6、管道标识设计要求：按图纸要求 7、其他：包括但不限于以上内容，综合考虑按图纸、招标文件和规范要求而实施、完成这项工程的一切有关费用 | E11: m | F11: 175 | G11: =T11*$T$3 -> 18 | H11: =R11*(1+S11)*$R$3+U11*$U$3 -> 18.54 | I11: =V11*$V$3 -> 0.5 | J11: =(G11+H11+I11)*$J$3 -> 0 | K11: =(G11+H11+I11+J11)*$K$3 -> 0 | L11: =G11+H11+I11+J11+K11 -> 37.04 | M11: =F11*L11 -> 6482 | N11: 54.5 | O11: =N11*F11 -> 9537.5 | Q11: =R11*(1+S11)+T11+U11+V11 -> 37.04 | R11: 18 | S11: 0.03 | T11: 18 | U11: 0 | V11: 0.5 | W11: =F11*Q11 -> 6482
A12: 9 | B12: 30901001009 | C12: 热浸镀锌钢管 | D12: 1、安装部位：室内 2、材质、规格：热浸镀锌钢管DN25 3、连接形式：按图纸要求 4、钢管镀锌设计要求：国标 5、压力试验及冲洗设计要求：液压试验，水冲洗 6、管道标识设计要求：按图纸要求 7、其他：包括但不限于以上内容，综合考虑按图纸、招标文件和规范要求而实施、完成这项工程的一切有关费用 | E12: m | F12: 420 | G12: =T12*$T$3 -> 15 | H12: =R12*(1+S12)*$R$3+U12*$U$3 -> 14.42 | I12: =V12*$V$3 -> 0.5 | J12: =(G12+H12+I12)*$J$3 -> 0 | K12: =(G12+H12+I12+J12)*$K$3 -> 0 | L12: =G12+H12+I12+J12+K12 -> 29.92 | M12: =F12*L12 -> 12566.4 | N12: 38.89 | O12: =N12*F12 -> 16333.8 | Q12: =R12*(1+S12)+T12+U12+V12 -> 29.92 | R12: 14 | S12: 0.03 | T12: 15 | U12: 0 | V12: 0.5 | W12: =F12*Q12 -> 12566.4
A13: 10 | B13: 31301005003 | C13: 管道支架 | D13: 1、名称：管道支架 2、刷油防腐：除锈后樟丹防锈漆二道,醇酸磁漆二道 3、其他：包括但不限于以上内容，综合考虑按图纸、招标文件和规范要求而实施、完成这项工程的一切有关费用 | E13: Kg | F13: 425 | G13: =T13*$T$3 -> 5 | H13: =R13*(1+S13)*$R$3+U13*$U$3 -> 20 | I13: =V13*$V$3 -> 0 | J13: =(G13+H13+I13)*$J$3 -> 0 | K13: =(G13+H13+I13+J13)*$K$3 -> 0 | L13: =G13+H13+I13+J13+K13 -> 25 | M13: =F13*L13 -> 10625 | N13: 29.87 | O13: =N13*F13 -> 12694.75 | Q13: 25 | R13: 18 | S13: 0 | T13: 5 | U13: 2 | V13: 0 | W13: =F13*Q13 -> 10625
A14: 14 | B14: 31002001005 | C14: 铜截止阀 | D14: 1、类型：铜截止阀 2、材质：按图纸要求 3、规格、压力等级：DN25 4、其他：包括但不限于以上内容，综合考虑按图纸、招标文件和规范要求而实施、完成这项工程的一切有关费用 | E14: 个 | F14: 3 | G14: =T14*$T$3 -> 25.06 | H14: =R14*(1+S14)*$R$3+U14*$U$3 -> 46 | I14: =V14*$V$3 -> 0 | J14: =(G14+H14+I14)*$J$3 -> 0 | K14: =(G14+H14+I14+J14)*$K$3 -> 0 | L14: =G14+H14+I14+J14+K14 -> 71.06 | M14: =F14*L14 -> 213.18 | N14: 67.71 | O14: =N14*F14 -> 203.13 | Q14: =R14*(1+S14)+T14+U14+V14 -> 71.06 | R14: 34 | S14: 0 | T14: 25.06 | U14: 12 | V14: 0 | W14: =F14*Q14 -> 213.18
A15: 15 | B15: 31002001023 | C15: 截止阀 | D15: 1、名称：截止阀 2、材质：符合设计要求材质 3、型号、规格：DN50 4、连接形式：按图纸要求 5、其他：包括但不限于以上内容，综合考虑按图纸、招标文件和规范要求而实施、完成这项工程的一切有关费用 | E15: 个 | F15: 2 | G15: =T15*$T$3 -> 15 | H15: =R15*(1+S15)*$R$3+U15*$U$3 -> 116 | I15: =V15*$V$3 -> 0 | J15: =(G15+H15+I15)*$J$3 -> 0 | K15: =(G15+H15+I15+J15)*$K$3 -> 0 | L15: =G15+H15+I15+J15+K15 -> 131 | M15: =F15*L15 -> 262 | N15: 137.92 | O15: =N15*F15 -> 275.84 | Q15: 131 | R15: 110 | S15: 0 | T15: 15 | U15: 6 | V15: 0 | W15: =F15*Q15 -> 262
A16: 29 | B16: 30902007003 | C16: 直立式喷头 | D16: 1、名称：直立式喷头 2、型号、规格：公称动作温度 68°C 3、本体安装及调试 4、其他：包括但不限于以上内容，综合考虑按图纸、招标文件和规范要求而实施、完成这项工程的一切有关费用 | E16: 个 | F16: 213 | G16: =T16*$T$3 -> 6 | H16: =R16*(1+S16)*$R$3+U16*$U$3 -> 20 | I16: =V16*$V$3 -> 0 | J16: =(G16+H16+I16)*$J$3 -> 0 | K16: =(G16+H16+I16+J16)*$K$3 -> 0 | L16: =G16+H16+I16+J16+K16 -> 26 | M16: =F16*L16 -> 5538 | N16: 27.97 | O16: =N16*F16 -> 5957.61 | Q16: 26 | R16: 18 | S16: 0 | T16: 6 | U16: 2 | V16: 0 | W16: =F16*Q16 -> 5538
A17: 30 | B17: 30902007004 | C17: 直立式喷头 | D17: 1、名称：直立式喷头 2、型号、规格：公称动作温度 93°C 3、本体安装及调试 4、其他：包括但不限于以上内容，综合考虑按图纸、招标文件和规范要求而实施、完成这项工程的一切有关费用 | E17: 个 | F17: 2 | G17: =T17*$T$3 -> 6 | H17: =R17*(1+S17)*$R$3+U17*$U$3 -> 20 | I17: =V17*$V$3 -> 0 | J17: =(G17+H17+I17)*$J$3 -> 0 | K17: =(G17+H17+I17+J17)*$K$3 -> 0 | L17: =G17+H17+I17+J17+K17 -> 26 | M17: =F17*L17 -> 52 | N17: 27.97 | O17: =N17*F17 -> 55.94 | Q17: 26 | R17: 18 | S17: 0 | T17: 6 | U17: 2 | V17: 0 | W17: =F17*Q17 -> 52
B18: 税前合价 | E18: 元 | M18: =SUM(M4:M17) -> 52855.78 | O18: =SUM(O4:O17) -> 63764.22
B19: 税金 | E19: 元 | M19: =M18*0.09 -> 4757.0202 | O19: =O18*0.09 -> 5738.7798
B20: 含税合价 | E20: 元 | M20: =M18+M19 -> 57612.8 | O20: =O18+O19 -> 69503

Sheet 项目甲供清单
A1: 项目甲供材种类清单
A2: 序号 | B2: 材料名称 | C2: 供货及安装方式 | D2: 备注
A3: 1 | B3: 入户门 | C3: 供货+安装
A4: 2 | B4: 墙地砖 | C4: 仅供货
A5: 3 | B5: 户内门锁 | C5: 供货+安装
A6: 4 | B6: 户内门 | C6: 供货+安装
A7: 5 | B7: 星盆及龙头 | C7: 仅供货
A8: 6 | B8: 洁具 | C8: 仅供货
A9: 7 | B9: 龙头 | C9: 仅供货
A10: 8 | B10: 卫浴五金 | C10: 仅供货
A11: 9 | B11: 橱柜 | C11: 供货+安装
A12: 10 | B12: 镜浴柜 | C12: 供货+安装
A13: 11 | B13: 厨房电器 | C13: 供货+安装
A14: 12 | B14: 空调 | C14: 供货+安装
A15: 13 | B15: 电子门锁 | C15: 供货+安装
