Workbook
Name ___________________N81020: [1]地梁!#REF!
Name dw: #REF!
Name dw: #REF!
Name dw: #REF!
Name A: EVALUATE(SUBSTITUTE(SUBSTITUTE(#REF!,"[","*ISTEXT(""["),"]","]"")"))
Name A: EVALUATE(SUBSTITUTE(SUBSTITUTE(#REF!,"[","*ISTEXT(""["),"]","]"")"))

Sheet 编制说明
A1: 编制说明
A2: 1、工程概况：
A3: 1）、工程名称：珠海丹田海德公馆会所精装修工程
A4: 2）、建设单位：丹田海德公馆
A5: 3）、工程内容：会所、公区装修及机电
A6: 2、编制依据：
A7: 1）、按建设单位提供的《珠海海德公馆会所项目施工图20260529》及《珠海丹田海德公馆会所施工手册》、《酒窖深化图》；
A8: 3、编制范围：
A9: 1）、海德公馆大堂、电梯厅、电梯轿厢、三楼会所、健身房等室内装修工程。 包括：大堂、电梯厅、电梯轿厢、会所、健身房地面、墙面、天花等；
A10: 4、计价说明：
A11: 1）、综合单价综合考虑人工费、各类材料费（含损耗）、机械费、项目措施费（地下暗室施工费、技术措施费、安全文明施工费、临时设施费）、成品保护费、运输装卸费、材料设备场内二次运输费[在合同总工期内施工过程中因各种因素导致需二次运输作业，搬运距离，自行勘察现场]、材料检测试验费、检测费、调试费、验收费、保险费（不包含甲方已购买保险）、规费、管理费、利润、国家强制性收费、风险责任、施工水电费、克服施工现场苛刻条件及难度费用等除监理费之外的全部费用除非另有约定，结算时该综合单价不调整、税金在汇总单独计算。
A12: 5、其他说明
... A15: 3、根据图纸设计说明墙面瓷砖瓷砖大于400*800规格采用C2T等级增强型水泥基胶粘剂,由于项目中不同区域使用的瓷砖规格大小有不一,清单中统一描述为C1T等级增强型水泥基胶粘剂,最终根据项目中各区域使用的瓷砖规格选择相应规格胶粘剂；

Sheet 汇总表
A1: 报价汇总表
A2: 工程名称：珠海丹田海德公馆会所精装修工程
A3: 序号 | B3: 名称 | C3: 单层装修面积（m2） | D3: 层数 | E3: 单层造价（元） | F3: 总造价（元） | G3: 单方指标 | H3: 备注
A4: 1 | B4: 首层装修部分（北向） | C4: 274.13 | D4: 1 | E4: =+地上装修工程!K4 -> 0 | F4: =E4*D4 -> 0 | G4: =+E4/C4 -> 0
A5: 2 | B5: 首层装修部分（南向） | C5: 303.3 | D5: 1 | E5: =+地上装修工程!K168 -> 0 | F5: =E5*D5 -> 0 | G5: =+E5/C5 -> 0
A6: 3 | B6: 标准层装修部分(四~三十一层) | C6: 59.41 | D6: 28 | E6: =+地上装修工程!K336 -> 0 | F6: =E6*D6 -> 0 | G6: =+E6/C6 -> 0
A7: 4 | B7: 会所装修部分（三层） | C7: 887.57 | D7: 1 | E7: =+地上装修工程!K448 -> 0 | F7: =E7*D7 -> 0 | G7: =+E7/C7 -> 0
A8: 5 | B8: 健身房装修部分（三层） | C8: 278.86 | D8: 1 | E8: =+地上装修工程!K911 -> 0 | F8: =E8*D8 -> 0 | G8: =+E8/C8 -> 0
A9: 6 | B9: 负一层装修部分 | C9: 103.84 | D9: 1 | E9: =+地下室装修工程!K4 -> 0 | F9: =E9*D9 -> 0 | G9: =+E9/C9 -> 0
A10: 7 | B10: 负二层装修部分 | C10: 92.34 | D10: 1 | E10: =+地下室装修工程!K105 -> 0 | F10: =E10*D10 -> 0 | G10: =+E10/C10 -> 0
A11: 8 | B11: 负三层装修部分 | C11: 77.93 | D11: 1 | E11: =+地下室装修工程!K204 -> 0 | F11: =E11*D11 -> 0 | G11: =+E11/C11 -> 0
A12: 9 | B12: 电梯轿厢 | C12: =2.34*2 -> 4.68 | D12: 4 | E12: =+电梯轿厢装修工程!K44 -> 0 | F12: =E12*D12 -> 0 | G12: =+E12/C12 -> 0 | H12: 1个电梯轿厢+1个无障碍电梯轿厢
A13: 10 | B13: 安装工程 | C13: =C4+C5+C6*D6+C7+C8+C9+C10+C11+C12*D12 -> 3700.17 | D13: 1 | E13: =会所安装工程量清单!K223 -> 0 | F13: =E13*D13 -> 0 | G13: =+E13/C13 -> 0
A14: 11 | B14: 措施费 | C14: =C13 -> 3700.17 | D14: 1 | E14: =+措施费!K7 -> 0 | F14: =E14*D14 -> 0 | G14: =+E14/C14 -> 0
A15: 12 | B15: 小计 | C15: =+$C$14 -> 3700.17 | F15: =SUM(F4:F14) -> 0 | G15: =+E15/C15 -> 0
A16: 13 | B16: 税金（9%） | C16: =+$C$14 -> 3700.17 | F16: =+F15*9% -> 0 | G16: =+E16/C16 -> 0
B17: 总计 | C17: =+$C$14 -> 3700.17 | F17: =+F15+F16 -> 0 | G17: =+E17/C17 -> 0

Sheet 地上装修工程
A1: 珠海海德公馆会所项目-工程量清单
A2: 序号 | B2: 项目名称 | C2: 项目特征 | D2: 单位 | E2: 工程量 | F2: 人工 | G2: 主材 | H2: 辅材及机械费 | I2: 管理及利润取费 | J2: 综合单价 （不含税） | K2: 合价 （不含税） | L2: 备注 | M2: 检查
M3: 1 | N3: 2
A4: A | B4: 首层装修部分（北向） | K4: =SUM(K5:K167) -> 0
A5: 一 | B5: 一层电梯厅、设备间（DT1） | O5: =_xlfn.DISPIMG("ID_7F15BB9A08234B43B10CC616E0663C90",1) -> =DISPIMG("ID_7F15BB9A08234B43B10CC616E0663C90",1)
B6: 地面工程
A7: =1+N(A6) -> 1 | B7: 地面铺贴大理石ST-01 | C7: 1.地面20mm大理石ST-01、铺贴、厚度及样式按物料书为准； 2.10mm厚石材专用粘结剂； 3.70mm厚DS-M15干混砂浆找平； 4.基层清理、石材六面防护、背面刷胶封闭,同色云石胶补缝； 5.含开槽、磨边、倒角、拼接等处理； 6.包含完成该项内容所有工作及费用并满足设计图纸、规范等要求； | D7: m2 | E7: 18.57 | I7: =(F7+G7+H7)*$I$3 -> 0 | J7: =ROUND(SUM(F7:I7),2) -> 0 | K7: =ROUND(J7*E7,2) -> 0 | M7: 1
A8: =1+N(A7) -> 2 | B8: 地面铺贴大理石ST-01.02拼花 | C8: 1.地面20mm大理石拼花、参考3F-DF-01样式、ST-01、ST-02按物料书为准； 2.10mm厚石材专用粘结剂； 3.70mm厚DS-M15干混砂浆找平； 4.基层清理、石材六面防护、背面刷胶封闭,同色云石胶补缝； 5.含开槽、磨边、倒角、拼接等处理； 6.包含完成该项内容所有工作及费用并满足设计图纸、规范等要求； | D8: m2 | E8: 10.62 | I8: =(F8+G8+H8)*$I$3 -> 0 | J8: =ROUND(SUM(F8:I8),2) -> 0 | K8: =ROUND(J8*E8,2) -> 0 | M8: 1
A9: =1+N(A8) -> 3 | B9: 地面地砖 CT-06 | C9: 1.地面花砖CT-06； 2.10mm厚专用粘结剂； 3.80mm厚DS-M15干混砂浆找平； 4.基层清理； 5.含切边、倒角、拼接等处理； 6.包含完成该项内容所有工作及费用并满足设计图纸、规范等要求； | D9: m2 | E9: 2.58 | I9: =(F9+G9+H9)*$I$3 -> 0 | J9: =ROUND(SUM(F9:I9),2) -> 0 | K9: =ROUND(J9*E9,2) -> 0 | M9: 1
A10: =1+N(A9) -> 4 | B10: 实心铜条5mm宽 | C10: 1.实心铜条5mm宽； 2.包含完成该项内容所有工作及费用并满足设计图纸、规范等要求； | D10: m | E10: 12.77 | I10: =(F10+G10+H10)*$I$3 -> 0 | J10: =ROUND(SUM(F10:I10),2) -> 0 | K10: =ROUND(J10*E10,2) -> 0 | M10: 1
A11: =1+N(A10) -> 5 | B11: 地面石材晶面处理 | C11: 1.石材结晶处理(结晶水及石材保养剂,中性清洁剂)； 2.包含完成该项内容所有工作及费用并满足设计图纸、规范等要求； | D11: m2 | E11: 14.77 | I11: =(F11+G11+H11)*$I$3 -> 0 | J11: =ROUND(SUM(F11:I11),2) -> 0 | K11: =ROUND(J11*E11,2) -> 0 | M11: 1
B12: 墙柱面工程
A13: =1+N(A12) -> 1 | B13: 墙面湿贴石材ST-05 | C13: 1、墙面湿贴石材ST-05 2、8mm厚石材专用胶粘剂WC粘结层 3、界面剂拉毛处理 4、石材的开槽、磨边、倒角、粘接、形成所需之凹坑、抛光、六面防污防渗等一切处理费用均在主材费中考虑，不再另行计取 5、包含完成该项内容所有工作及费用并满足设计图纸、规范等要求 | D13: m2 | E13: 12.933 | I13: =(F13+G13+H13)*$I$3 -> 0 | J13: =ROUND(SUM(F13:I13),2) -> 0 | K13: =ROUND(J13*E13,2) -> 0 | M13: 1
A14: =1+N(A13) -> 2 | B14: 墙面干挂ST-05石材 | C14: 1、墙面干挂ST-05石材 2、不锈钢背栓挂件安装，云石胶+AB胶固定 3、镀锌角钢钢架(高度超4m、完成面超150mm采用槽钢基层加固)，钢架防锈处理 4、膨胀螺栓固定预埋铁件(轻质砖墙体需要穿墙螺栓固定) 5、石材的开槽、磨边、倒角、粘接、形成所需之凹坑、抛光、六面防污防渗等一切处理费用均在主材费中考虑，不再另行计取 6、包含完成该项内容所有工作及费用并满足设计图纸、规范等要求 | D14: m2 | E14: =58.817+0.727 -> 59.544 | I14: =(F14+G14+H14)*$I$3 -> 0 | J14: =ROUND(SUM(F14:I14),2) -> 0 | K14: =ROUND(J14*E14,2) -> 0 | M14: 1
A15: =1+N(A14) -> 3 | B15: 墙面干挂ST-05石材（波浪造型） | C15: 1、墙面干挂ST-05石材（波浪造型） 2、不锈钢背栓挂件安装，云石胶+AB胶固定 3、镀锌角钢钢架(高度超4m、完成面超150mm采用槽钢基层加固)，钢架防锈处理 4、膨胀螺栓固定预埋铁件(轻质砖墙体需要穿墙螺栓固定) 5、石材的开槽、磨边、倒角、粘接、形成所需之凹坑、抛光、六面防污防渗等一切处理费用均在主材费中考虑，不再另行计取 6、包含完成该项内容所有工作及费用并满足设计图纸、规范等要求 | D15: m2 | E15: 2.91 | I15: =(F15+G15+H15)*$I$3 -> 0 | J15: =ROUND(SUM(F15:I15),2) -> 0 | K15: =ROUND(J15*E15,2) -> 0 | M15: 1
A16: =1+N(A15) -> 4 | B16: 墙面PT-02白色防水无机涂料 | C16: 1、墙面PT-02白色防水无机涂料(底漆1遍，面漆2遍) 2、刮白胶腻子找平二遍，打磨 3、阴、阳角护角收边 4、双层9.5mm纸面石膏板 5、轻钢龙骨基层找平 6、包含完成该项内容所有工作及费用并满足设计图纸、规范等要求 | D16: m2 | E16: =16.107+1*(3-2) -> 17.107 | I16: =(F16+G16+H16)*$I$3 -> 0 | J16: =ROUND(SUM(F16:I16),2) -> 0 | K16: =ROUND(J16*E16,2) -> 0 | M16: 1
A17: =1+N(A16) -> 5 | B17: 不锈钢门套 | C17: 1、1.2mm厚 MT-01古铜不锈钢门套，结构胶固定 2、9厘玻镁板基层 3、工程量以展开面积计算 4、包含完成该项内容所有工作及费用并满足设计图纸、规范等要求 | D17: m2 | E17: =0.29*2*2+0.98*0.26 -> 1.4148 | I17: =(F17+G17+H17)*$I$3 -> 0 | J17: =ROUND(SUM(F17:I17),2) -> 0 | K17: =ROUND(J17*E17,2) -> 0 | M17: 1
A18: =1+N(A17) -> 6 | B18: 电梯不锈钢门套 | C18: 1、1.2mm厚 MT-01古铜不锈钢门套，结构胶固定 2、9厘玻镁板基层 3、工程量以展开面积计算 4、包含完成该项内容所有工作及费用并满足设计图纸、规范等要求 | D18: m2 | E18: =0.296*3*2*2 -> 3.552 | I18: =(F18+G18+H18)*$I$3 -> 0 | J18: =ROUND(SUM(F18:I18),2) -> 0 | K18: =ROUND(J18*E18,2) -> 0 | M18: 1
A19: =1+N(A18) -> 7 | B19: 电梯不锈钢门头 | C19: 1、1.2mm厚 MT-01古铜不锈钢门头，结构胶固定 2、12mm阻燃板，轻钢副龙骨@400 3、电梯门顶内置亚克力，内部面层刮白处理 4、工程量以展开面积计算 5、包含完成该项内容所有工作及费用并满足设计图纸、规范等要求 | D19: m2 | E19: =+(0.061+0.72+0.114+0.074)*0.95*2 -> 1.8411 | I19: =(F19+G19+H19)*$I$3 -> 0 | J19: =ROUND(SUM(F19:I19),2) -> 0 | K19: =ROUND(J19*E19,2) -> 0 | M19: 1
A20: =1+N(A19) -> 8 | B20: MT-01古铜不锈钢饰面（电梯按钮处） | C20: 1、1.2mm厚 MT-01古铜不锈钢饰面 2、12mm阻燃板基层，轻钢副龙骨@400 3、工程量以展开面积计算 4、包含完成该项内容所有工作及费用并满足设计图纸、规范等要求 | D20: m2 | E20: 0.252 | I20: =(F20+G20+H20)*$I$3 -> 0 | J20: =ROUND(SUM(F20:I20),2) -> 0 | K20: =ROUND(J20*E20,2) -> 0 | M20: 1
A21: =1+N(A20) -> 9 | B21: 50mm CT-06瓷砖踢脚 | C21: 1、50mm CT-06瓷砖踢脚,瓷砖填缝剂处理 2、背覆胶处理 3、C1T等级抗滑移水泥基胶粘剂 4、界面剂拉毛处理 5、包含完成该项内容所有工作及费用并满足设计图纸、规范等要求 | D21: m2 | E21: 0.273 | I21: =(F21+G21+H21)*$I$3 -> 0 | J21: =ROUND(SUM(F21:I21),2) -> 0 | K21: =ROUND(J21*E21,2) -> 0 | M21: 1
A22: =1+N(A21) -> 10 | B22: MT-01古铜不锈钢踢脚线（高20mm） | C22: 1、1.2mm厚 MT-01古铜不锈钢踢脚线（高20mm，展开面为46mm），结构胶固定 2、9厘玻镁板基层 3、包含完成该项内容所有工作及费用并满足设计图纸、规范等要求 | D22: m | E22: 25.71 | I22: =(F22+G22+H22)*$I$3 -> 0 | J22: =ROUND(SUM(F22:I22),2) -> 0 | K22: =ROUND(J22*E22,2) -> 0 | M22: 1
A23: =1+N(A22) -> 11 | B23: MT-01古铜不锈钢线条（展开面为54mm） | C23: 1、1.2mm厚 MT-01古铜不锈钢线条（展开面为54mm），结构胶固定 2、9厘玻镁板基层 3、包含完成该项内容所有工作及费用并满足设计图纸、规范等要求 | D23: m | E23: =0.17*2 -> 0.34 | I23: =(F23+G23+H23)*$I$3 -> 0 | J23: =ROUND(SUM(F23:I23),2) -> 0 | K23: =ROUND(J23*E23,2) -> 0 | M23: 1
A24: =1+N(A23) -> 12 | B24: MT-01古铜不锈钢线条（展开面为69mm） | C24: 1、1.2mm厚 MT-01古铜不锈钢线条（展开面为69mm），结构胶固定 2、9厘玻镁板基层 3、包含完成该项内容所有工作及费用并满足设计图纸、规范等要求 | D24: m | E24: 0.96 | I24: =(F24+G24+H24)*$I$3 -> 0 | J24: =ROUND(SUM(F24:I24),2) -> 0 | K24: =ROUND(J24*E24,2) -> 0 | M24: 1
A25: =1+N(A24) -> 13 | B25: MT-01古铜不锈钢线条（展开面为114mm） | C25: 1、1.2mm厚 MT-01古铜不锈钢线条（展开面为114mm），结构胶固定 2、9厘玻镁板基层 3、包含完成该项内容所有工作及费用并满足设计图纸、规范等要求 | D25: m | E25: 24.41 | I25: =(F25+G25+H25)*$I$3 -> 0 | J25: =ROUND(SUM(F25:I25),2) -> 0 | K25: =ROUND(J25*E25,2) -> 0 | M25: 1
A26: =1+N(A25) -> 14 | B26: MT-01古铜不锈钢顶部收口条（展开面为41mm） | C26: 1、1.2mm厚 MT-01古铜不锈钢顶部收口条（展开面为41mm），结构胶固定 2、9厘玻镁板基层 3、包含完成该项内容所有工作及费用并满足设计图纸、规范等要求 | D26: m | E26: 25.71 | I26: =(F26+G26+H26)*$I$3 -> 0 | J26: =ROUND(SUM(F26:I26),2) -> 0 | K26: =ROUND(J26*E26,2) -> 0 | M26: 1
B27: 天花工程
A28: =1+N(A27) -> 1 | B28: 造型石膏板吊顶 | C28: 1.60系列轻钢主龙骨@900，60系列轻钢副龙骨@400，60系列横撑龙骨@600，08螺纹吊杆@900不上人天花吊顶（投影面计算） 2.玻镁板、双层9.5厚石膏板基层，含开孔、检修口、10*10凹槽等费用； 3.含除灯槽外的侧面高差及其连接件、吊件； 4.包含完成该项内容所有工作及费用并满足设计图纸、规范等要求； | D28: m2 | E28: 31.77 | I28: =(F28+G28+H28)*$I$3 -> 0 | J28: =ROUND(SUM(F28:I28),2) -> 0 | K28: =ROUND(J28*E28,2) -> 0 | M28: 1
A29: =1+N(A28) -> 2 | B29: 灯槽（100mm*200mm） | C29: 1.灯槽（100mm*200mm）； 2.双层板：9mm玻镁板、9.5厚石膏板； 3.包含完成该项内容所有工作及费用并满足设计图纸、规范等要求； | D29: m | E29: 12.73 | I29: =(F29+G29+H29)*$I$3 -> 0 | J29: =ROUND(SUM(F29:I29),2) -> 0 | K29: =ROUND(J29*E29,2) -> 0 | M29: 1
A30: =1+N(A29) -> 3 | B30: 成品石膏线条 | C30: 1.成品石膏线条（50mm*50mm）； 2.按图纸造型； 3.包含完成该项内容所有工作及费用并满足设计图纸、规范等要求； | D30: m | E30: 12.73 | I30: =(F30+G30+H30)*$I$3 -> 0 | J30: =ROUND(SUM(F30:I30),2) -> 0 | K30: =ROUND(J30*E30,2) -> 0 | M30: 1
A31: =1+N(A30) -> 4 | B31: 条形空调风口（150mm） | C31: 1.条形空调风口（150mm）； 2.风口周边阻燃板封边加固处理； 3.包含完成该项内容所有工作及费用并满足设计图纸、规范等要求； | D31: m | E31: =1.2*2*1 -> 2.4 | I31: =(F31+G31+H31)*$I$3 -> 0 | J31: =ROUND(SUM(F31:I31),2) -> 0 | K31: =ROUND(J31*E31,2) -> 0 | M31: 1
A32: =1+N(A31) -> 5 | B32: 天花肌理无机涂料PT-01 | C32: 1.天花肌理无机涂料PT-01； 2.刮腻子二遍磨平； 3.底漆1遍，面漆2遍； 4.包含完成该项内容所有工作及费用并满足设计图纸、规范等要求； | D32: m2 | E32: =31.77+12.73*0.3 -> 35.589 | I32: =(F32+G32+H32)*$I$3 -> 0 | J32: =ROUND(SUM(F32:I32),2) -> 0 | K32: =ROUND(J32*E32,2) -> 0 | M32: 1
B33: 门窗、家具工程
A34: =1+N(A33) -> 1 | B34: 设备间暗门(不含面层) | C34: 1、40x40x5mm热镀锌方管骨架、背封铝塑板 2、含天地轴、门吸等五金配件 3、包含完成该项内容所有工作及费用并满足设计图纸、规范等要求 | D34: m2 | E34: =0.96*3 -> 2.88 | I34: =(F34+G34+H34)*$I$3 -> 0 | J34: =ROUND(SUM(F34:I34),2) -> 0 | K34: =ROUND(J34*E34,2) -> 0 | M34: 1
A35: =1+N(A34) -> 2 | B35: 电梯厅门（参DR01） | C35: 1、门扇：1.2mm厚 MT-01古铜不锈钢饰面、GL-01超白钢化玻璃、ST-08石材、L40*40*4镀锌角钢骨架 2、门套：1.2mm厚 MT-01古铜不锈钢饰面 3、定制成品套装门制安 4、含电机、暗铰链、地弹簧等五金配件 5、包含完成该项内容所有工作及费用并满足设计图纸、规范等要求 | D35: m2 | E35: =1.84*3 -> 5.52 | I35: =(F35+G35+H35)*$I$3 -> 0 | J35: =ROUND(SUM(F35:I35),2) -> 0 | K35: =ROUND(J35*E35,2) -> 0 | M35: 1
A36: =1+N(A35) -> 3 | B36: 固定玻璃隔断 | C36: 1、GL-01超白钢化玻璃饰面 2、1.2mm厚 MT-01古铜不锈钢饰面边框 3、包含完成该项内容所有工作及费用并满足设计图纸、规范等要求 | D36: m2 | E36: =1.71*3 -> 5.13 | I36: =(F36+G36+H36)*$I$3 -> 0 | J36: =ROUND(SUM(F36:I36),2) -> 0 | K36: =ROUND(J36*E36,2) -> 0 | M36: 1
A37: 二 | B37: 一层入户大堂、前室（上） | O37: =_xlfn.DISPIMG("ID_EC83A7CF2DCE420D98B785E34F0891B0",1) -> =DISPIMG("ID_EC83A7CF2DCE420D98B785E34F0891B0",1)
B38: 地面工程
A39: =1+N(A38) -> 1 | B39: 地面铺贴大理石ST-01 | C39: 1.地面20mm大理石ST-01、铺贴、厚度及样式按物料书为准； 2.10mm厚石材专用粘结剂； 3.70mm厚DS-M15干混砂浆找平； 4.基层清理、石材六面防护、背面刷胶封闭,同色云石胶补缝； 5.含开槽、磨边、倒角、拼接等处理； 6.包含完成该项内容所有工作及费用并满足设计图纸、规范等要求； | D39: m2 | E39: 30.5 | I39: =(F39+G39+H39)*$I$3 -> 0 | J39: =ROUND(SUM(F39:I39),2) -> 0 | K39: =ROUND(J39*E39,2) -> 0 | M39: 1 | O39: 29.2
A40: =1+N(A39) -> 2 | B40: 地面铺贴大理石ST-01.03拼花 | C40: 1.地面20mm大理石拼花、参考3F-DF-01样式、ST-01、ST-03按物料书为准； 2.10mm厚石材专用粘结剂； 3.70mm厚DS-M15干混砂浆找平； 4.基层清理、石材六面防护、背面刷胶封闭,同色云石胶补缝； 5.含开槽、磨边、倒角、拼接等处理； 6.包含完成该项内容所有工作及费用并满足设计图纸、规范等要求； | D40: m2 | E40: 41.2 | I40: =(F40+G40+H40)*$I$3 -> 0 | J40: =ROUND(SUM(F40:I40),2) -> 0 | K40: =ROUND(J40*E40,2) -> 0 | M40: 1
A41: =1+N(A40) -> 3 | B41: 实心铜条5mm宽 | C41: 1.实心铜条5mm宽； 2.包含完成该项内容所有工作及费用并满足设计图纸、规范等要求； | D41: m | E41: 24.98 | I41: =(F41+G41+H41)*$I$3 -> 0 | J41: =ROUND(SUM(F41:I41),2) -> 0 | K41: =ROUND(J41*E41,2) -> 0 | M41: 1
A42: =1+N(A41) -> 4 | B42: 地面石材晶面处理 | C42: 1.石材结晶处理(结晶水及石材保养剂,中性清洁剂)； 2.包含完成该项内容所有工作及费用并满足设计图纸、规范等要求； | D42: m2 | E42: 71.7 | I42: =(F42+G42+H42)*$I$3 -> 0 | J42: =ROUND(SUM(F42:I42),2) -> 0 | K42: =ROUND(J42*E42,2) -> 0 | M42: 1
B43: 墙柱面工程
A44: =1+N(A43) -> 1 | B44: 墙面湿贴石材ST-05 | C44: 1、墙面湿贴石材ST-05 2、8mm厚石材专用胶粘剂WC粘结层 3、界面剂拉毛处理 4、石材的开槽、磨边、倒角、粘接、形成所需之凹坑、抛光、六面防污防渗等一切处理费用均在主材费中考虑，不再另行计取 5、包含完成该项内容所有工作及费用并满足设计图纸、规范等要求 | D44: m2 | E44: 16.166 | I44: =(F44+G44+H44)*$I$3 -> 0 | J44: =ROUND(SUM(F44:I44),2) -> 0 | K44: =ROUND(J44*E44,2) -> 0 | M44: 1
A45: =1+N(A44) -> 2 | B45: 墙面干挂ST-05石材 | C45: 1、墙面干挂ST-05石材 2、不锈钢背栓挂件安装，云石胶+AB胶固定 3、镀锌角钢钢架(高度超4m、完成面超150mm采用槽钢基层加固)，钢架防锈处理 4、膨胀螺栓固定预埋铁件(轻质砖墙体需要穿墙螺栓固定) 5、石材的开槽、磨边、倒角、粘接、形成所需之凹坑、抛光、六面防污防渗等一切处理费用均在主材费中考虑，不再另行计取 6、包含完成该项内容所有工作及费用并满足设计图纸、规范等要求 | D45: m2 | E45: 58.195 | I45: =(F45+G45+H45)*$I$3 -> 0 | J45: =ROUND(SUM(F45:I45),2) -> 0 | K45: =ROUND(J45*E45,2) -> 0 | M45: 1
A46: =1+N(A45) -> 3 | B46: 墙面干挂ST-05石材（波浪造型） | C46: 1、墙面干挂ST-05石材（波浪造型） 2、不锈钢背栓挂件安装，云石胶+AB胶固定 3、镀锌角钢钢架(高度超4m、完成面超150mm采用槽钢基层加固)，钢架防锈处理 4、膨胀螺栓固定预埋铁件(轻质砖墙体需要穿墙螺栓固定) 5、石材的开槽、磨边、倒角、粘接、形成所需之凹坑、抛光、六面防污防渗等一切处理费用均在主材费中考虑，不再另行计取 6、包含完成该项内容所有工作及费用并满足设计图纸、规范等要求 | D46: m2 | E46: 12.33 | I46: =(F46+G46+H46)*$I$3 -> 0 | J46: =ROUND(SUM(F46:I46),2) -> 0 | K46: =ROUND(J46*E46,2) -> 0 | M46: 1
A47: =1+N(A46) -> 4 | B47: 墙面PT-02白色防水无机涂料 | C47: 1、墙面PT-02白色防水无机涂料(底漆1遍，面漆2遍) 2、刮白胶腻子找平二遍，打磨 3、阴、阳角护角收边 4、双层9.5mm纸面石膏板 5、轻钢龙骨基层找平 6、包含完成该项内容所有工作及费用并满足设计图纸、规范等要求 | D47: m2 | E47: 5.548 | I47: =(F47+G47+H47)*$I$3 -> 0 | J47: =ROUND(SUM(F47:I47),2) -> 0 | K47: =ROUND(J47*E47,2) -> 0 | M47: 1
A48: =1+N(A47) -> 5 | B48: MT-01古铜不锈钢踢脚线（高20mm） | C48: 1、1.2mm厚 MT-01古铜不锈钢踢脚线（高20mm，展开面为46mm），结构胶固定 2、9厘玻镁板基层 3、包含完成该项内容所有工作及费用并满足设计图纸、规范等要求 | D48: m | E48: 30.137 | I48: =(F48+G48+H48)*$I$3 -> 0 | J48: =ROUND(SUM(F48:I48),2) -> 0 | K48: =ROUND(J48*E48,2) -> 0 | M48: 1
A49: =1+N(A48) -> 6 | B49: MT-01古铜不锈钢线条（展开面为114mm） | C49: 1、1.2mm厚 MT-01古铜不锈钢线条（展开面为114mm），结构胶固定 2、9厘玻镁板基层 3、包含完成该项内容所有工作及费用并满足设计图纸、规范等要求 | D49: m | E49: 30.137 | I49: =(F49+G49+H49)*$I$3 -> 0 | J49: =ROUND(SUM(F49:I49),2) -> 0 | K49: =ROUND(J49*E49,2) -> 0 | M49: 1
A50: =1+N(A49) -> 7 | B50: MT-01古铜不锈钢顶部收口条（展开面为41mm） | C50: 1、1.2mm厚 MT-01古铜不锈钢顶部收口条（展开面为41mm），结构胶固定 2、9厘玻镁板基层 3、包含完成该项内容所有工作及费用并满足设计图纸、规范等要求 | D50: m | E50: 30.137 | I50: =(F50+G50+H50)*$I$3 -> 0 | J50: =ROUND(SUM(F50:I50),2) -> 0 | K50: =ROUND(J50*E50,2) -> 0 | M50: 1
B51: 天花工程
A52: =1+N(A51) -> 1 | B52: 造型石膏板吊顶 | C52: 1.60系列轻钢主龙骨@900，60系列轻钢副龙骨@400，60系列横撑龙骨@600，08螺纹吊杆@900不上人天花吊顶（投影面计算） 2.玻镁板、双层9.5厚石膏板基层，含开孔、检修口、10*10凹槽等费用； 3.含除灯槽外的侧面高差及其连接件、吊件； 4.包含完成该项内容所有工作及费用并满足设计图纸、规范等要求； | D52: m2 | E52: =71.7-34.72 -> 36.98 | I52: =(F52+G52+H52)*$I$3 -> 0 | J52: =ROUND(SUM(F52:I52),2) -> 0 | K52: =ROUND(J52*E52,2) -> 0 | M52: 1
A53: =1+N(A52) -> 2 | B53: 造型石膏板吊顶（标高7.15m) | C53: 1.60系列轻钢主龙骨@900，60系列轻钢副龙骨@400，60系列横撑龙骨@600，08螺纹吊杆@900不上人天花吊顶（标高7.15m 投影面计算） 2.玻镁板、双层9.5厚石膏板基层，含开孔、检修口、10*10凹槽等费用； 3.含除灯槽外的侧面高差及其连接件、吊件； 4.包含完成该项内容所有工作及费用并满足设计图纸、规范等要求； | D53: m2 | E53: 34.72 | I53: =(F53+G53+H53)*$I$3 -> 0 | J53: =ROUND(SUM(F53:I53),2) -> 0 | K53: =ROUND(J53*E53,2) -> 0 | M53: 1
A54: =1+N(A53) -> 3 | B54: 灯槽（100mm*200mm） | C54: 1.灯槽（100mm*200mm）； 2.双层板：9mm玻镁板、9.5厚石膏板； 3.包含完成该项内容所有工作及费用并满足设计图纸、规范等要求； | D54: m | E54: 74.1 | I54: =(F54+G54+H54)*$I$3 -> 0 | J54: =ROUND(SUM(F54:I54),2) -> 0 | K54: =ROUND(J54*E54,2) -> 0 | M54: 1
A55: =1+N(A54) -> 4 | B55: 成品石膏线条 | C55: 1.成品石膏线条（50mm*50mm）； 2.按图纸造型； 3.包含完成该项内容所有工作及费用并满足设计图纸、规范等要求； | D55: m | E55: 74.1 | I55: =(F55+G55+H55)*$I$3 -> 0 | J55: =ROUND(SUM(F55:I55),2) -> 0 | K55: =ROUND(J55*E55,2) -> 0 | M55: 1
A56: =1+N(A55) -> 5 | B56: 条形空调风口（150mm） | C56: 1.条形空调风口（150mm）； 2.风口周边阻燃板封边加固处理； 3.包含完成该项内容所有工作及费用并满足设计图纸、规范等要求； | D56: m | E56: =1.2*2*2 -> 4.8 | I56: =(F56+G56+H56)*$I$3 -> 0 | J56: =ROUND(SUM(F56:I56),2) -> 0 | K56: =ROUND(J56*E56,2) -> 0 | M56: 1
A57: =1+N(A56) -> 6 | B57: 天花肌理无机涂料PT-01 | C57: 1.天花肌理无机涂料PT-01； 2.刮腻子二遍磨平； 3.底漆1遍，面漆2遍； 4.包含完成该项内容所有工作及费用并满足设计图纸、规范等要求； | D57: m2 | E57: =71.7+74.1*0.3 -> 93.93 | I57: =(F57+G57+H57)*$I$3 -> 0 | J57: =ROUND(SUM(F57:I57),2) -> 0 | K57: =ROUND(J57*E57,2) -> 0 | M57: 1
B58: 门窗、家具工程
A59: =1+N(A58) -> 1 | B59: 强弱电井暗门(不含面层) | C59: 1、40x40x5mm热镀锌方管骨架、背封铝塑板 2、含天地轴、门吸等五金配件 3、包含完成该项内容所有工作及费用并满足设计图纸、规范等要求 | D59: m2 | E59: =0.75*3 -> 2.25 | I59: =(F59+G59+H59)*$I$3 -> 0 | J59: =ROUND(SUM(F59:I59),2) -> 0 | K59: =ROUND(J59*E59,2) -> 0 | M59: 1
A60: =1+N(A59) -> 2 | B60: 消防栓暗门(不含面层) | C60: 1、40x40x5mm热镀锌方管骨架、背封铝塑板 2、含天地轴、门吸等五金配件 3、包含完成该项内容所有工作及费用并满足设计图纸、规范等要求 | D60: m2 | E60: =0.7*3 -> 2.1 | I60: =(F60+G60+H60)*$I$3 -> 0 | J60: =ROUND(SUM(F60:I60),2) -> 0 | K60: =ROUND(J60*E60,2) -> 0 | M60: 1
A61: 三 | B61: 一层艺术过厅 | O61: =_xlfn.DISPIMG("ID_D13A3B112CB340D4857ADF47F3345CFD",1) -> =DISPIMG("ID_D13A3B112CB340D4857ADF47F3345CFD",1)
B62: 地面工程
A63: =1+N(A62) -> 1 | B63: 地面铺贴大理石ST-01 | C63: 1.地面20mm大理石ST-01、铺贴、厚度及样式按物料书为准； 2.10mm厚石材专用粘结剂； 3.70mm厚DS-M15干混砂浆找平； 4.基层清理、石材六面防护、背面刷胶封闭,同色云石胶补缝； 5.含开槽、磨边、倒角、拼接等处理； 6.包含完成该项内容所有工作及费用并满足设计图纸、规范等要求； | D63: m2 | E63: 28.2 | I63: =(F63+G63+H63)*$I$3 -> 0 | J63: =ROUND(SUM(F63:I63),2) -> 0 | K63: =ROUND(J63*E63,2) -> 0 | M63: 1
A64: =1+N(A63) -> 2 | B64: 地面石材晶面处理 | C64: 1.石材结晶处理(结晶水及石材保养剂,中性清洁剂)； 2.包含完成该项内容所有工作及费用并满足设计图纸、规范等要求； | D64: m2 | E64: 28.2 | I64: =(F64+G64+H64)*$I$3 -> 0 | J64: =ROUND(SUM(F64:I64),2) -> 0 | K64: =ROUND(J64*E64,2) -> 0 | M64: 1
B65: 墙柱面工程
A66: =1+N(A65) -> 1 | B66: 墙面湿贴石材ST-05 | C66: 1、墙面湿贴石材ST-05 2、8mm厚石材专用胶粘剂WC粘结层 3、界面剂拉毛处理 4、石材的开槽、磨边、倒角、粘接、形成所需之凹坑、抛光、六面防污防渗等一切处理费用均在主材费中考虑，不再另行计取 5、包含完成该项内容所有工作及费用并满足设计图纸、规范等要求 | D66: m2 | E66: 4.458 | I66: =(F66+G66+H66)*$I$3 -> 0 | J66: =ROUND(SUM(F66:I66),2) -> 0 | K66: =ROUND(J66*E66,2) -> 0 | M66: 1
A67: =1+N(A66) -> 2 | B67: 墙面干挂ST-05石材 | C67: 1、墙面干挂ST-05石材 2、不锈钢背栓挂件安装，云石胶+AB胶固定 3、镀锌角钢钢架(高度超4m、完成面超150mm采用槽钢基层加固)，钢架防锈处理 4、膨胀螺栓固定预埋铁件(轻质砖墙体需要穿墙螺栓固定) 5、石材的开槽、磨边、倒角、粘接、形成所需之凹坑、抛光、六面防污防渗等一切处理费用均在主材费中考虑，不再另行计取 6、包含完成该项内容所有工作及费用并满足设计图纸、规范等要求 | D67: m2 | E67: 29.706 | I67: =(F67+G67+H67)*$I$3 -> 0 | J67: =ROUND(SUM(F67:I67),2) -> 0 | K67: =ROUND(J67*E67,2) -> 0 | M67: 1
A68: =1+N(A67) -> 3 | B68: 墙面干挂ST-05石材（波浪造型） | C68: 1、墙面干挂ST-05石材（波浪造型） 2、不锈钢背栓挂件安装，云石胶+AB胶固定 3、镀锌角钢钢架(高度超4m、完成面超150mm采用槽钢基层加固)，钢架防锈处理 4、膨胀螺栓固定预埋铁件(轻质砖墙体需要穿墙螺栓固定) 5、石材的开槽、磨边、倒角、粘接、形成所需之凹坑、抛光、六面防污防渗等一切处理费用均在主材费中考虑，不再另行计取 6、包含完成该项内容所有工作及费用并满足设计图纸、规范等要求 | D68: m2 | E68: 13.642 | I68: =(F68+G68+H68)*$I$3 -> 0 | J68: =ROUND(SUM(F68:I68),2) -> 0 | K68: =ROUND(J68*E68,2) -> 0 | M68: 1
A69: =1+N(A68) -> 4 | B69: 墙面干挂SF-06红砖 | C69: 1、墙面干挂SF-06红砖(墙面刷黑处理) 2、30*30*3镀锌方通钢架，石材干挂胶固定 3、包含完成该项内容所有工作及费用并满足设计图纸、规范等要求 | D69: m2 | E69: 16.5 | I69: =(F69+G69+H69)*$I$3 -> 0 | J69: =ROUND(SUM(F69:I69),2) -> 0 | K69: =ROUND(J69*E69,2) -> 0 | M69: 1
A70: =1+N(A69) -> 5 | B70: MT-01古铜不锈钢饰面 | C70: 1、1.2mm厚 MT-01古铜不锈钢饰面，结构胶固定 2、9厘玻镁板基层 3、工程量以展开面积计算 4、包含完成该项内容所有工作及费用并满足设计图纸、规范等要求 | D70: m2 | E70: =0.18*0.565*4 -> 0.4068 | I70: =(F70+G70+H70)*$I$3 -> 0 | J70: =ROUND(SUM(F70:I70),2) -> 0 | K70: =ROUND(J70*E70,2) -> 0 | M70: 1
A71: =1+N(A70) -> 6 | B71: MT-01古铜不锈钢踢脚线（高20mm） | C71: 1、1.2mm厚 MT-01古铜不锈钢踢脚线（高20mm，展开面为46mm），结构胶固定 2、9厘玻镁板基层 3、包含完成该项内容所有工作及费用并满足设计图纸、规范等要求 | D71: m | E71: 16.2 | I71: =(F71+G71+H71)*$I$3 -> 0 | J71: =ROUND(SUM(F71:I71),2) -> 0 | K71: =ROUND(J71*E71,2) -> 0 | M71: 1
A72: =1+N(A71) -> 7 | B72: MT-01古铜不锈钢线条（展开面为114mm） | C72: 1、1.2mm厚 MT-01古铜不锈钢线条（展开面为114mm），结构胶固定 2、9厘玻镁板基层 3、包含完成该项内容所有工作及费用并满足设计图纸、规范等要求 | D72: m | E72: 16.2 | I72: =(F72+G72+H72)*$I$3 -> 0 | J72: =ROUND(SUM(F72:I72),2) -> 0 | K72: =ROUND(J72*E72,2) -> 0 | M72: 1
A73: =1+N(A72) -> 8 | B73: MT-01古铜不锈钢顶部收口条（展开面为41mm） | C73: 1、1.2mm厚 MT-01古铜不锈钢顶部收口条（展开面为41mm），结构胶固定 2、9厘玻镁板基层 3、包含完成该项内容所有工作及费用并满足设计图纸、规范等要求 | D73: m | E73: 16.2 | I73: =(F73+G73+H73)*$I$3 -> 0 | J73: =ROUND(SUM(F73:I73),2) -> 0 | K73: =ROUND(J73*E73,2) -> 0 | M73: 1
B74: 天花工程
A75: =1+N(A74) -> 1 | B75: 造型石膏板吊顶 | C75: 1.60系列轻钢主龙骨@900，60系列轻钢副龙骨@400，60系列横撑龙骨@600，08螺纹吊杆@900不上人天花吊顶（投影面计算） 2.玻镁板、双层9.5厚石膏板基层，含开孔、检修口、10*10凹槽等费用； 3.含除灯槽外的侧面高差及其连接件、吊件； 4.包含完成该项内容所有工作及费用并满足设计图纸、规范等要求； | D75: m2 | E75: =28.2-4.4 -> 23.8 | I75: =(F75+G75+H75)*$I$3 -> 0 | J75: =ROUND(SUM(F75:I75),2) -> 0 | K75: =ROUND(J75*E75,2) -> 0 | M75: 1
A76: =1+N(A75) -> 2 | B76: 透光膜天棚 | C76: 1.透光膜天棚\施工时透气孔和穿线洞口\需加装防虫网防虫措施； 2.不锈钢压边； 3.包含完成该项内容所有工作及费用并满足设计图纸、规范等要求； | D76: m2 | E76: 4.4 | I76: =(F76+G76+H76)*$I$3 -> 0 | J76: =ROUND(SUM(F76:I76),2) -> 0 | K76: =ROUND(J76*E76,2) -> 0 | M76: 1
A77: =1+N(A76) -> 3 | B77: 灯槽（100mm*200mm） | C77: 1.灯槽（100mm*200mm）； 2.双层板：9mm玻镁板、9.5厚石膏板； 3.包含完成该项内容所有工作及费用并满足设计图纸、规范等要求； | D77: m | E77: 5.5 | I77: =(F77+G77+H77)*$I$3 -> 0 | J77: =ROUND(SUM(F77:I77),2) -> 0 | K77: =ROUND(J77*E77,2) -> 0 | M77: 1
A78: =1+N(A77) -> 4 | B78: 成品石膏线条 | C78: 1.成品石膏线条（50mm*50mm）； 2.按图纸造型； 3.包含完成该项内容所有工作及费用并满足设计图纸、规范等要求； | D78: m | E78: 5.5 | I78: =(F78+G78+H78)*$I$3 -> 0 | J78: =ROUND(SUM(F78:I78),2) -> 0 | K78: =ROUND(J78*E78,2) -> 0 | M78: 1
A79: =1+N(A78) -> 5 | B79: 条形空调风口（150mm） | C79: 1.条形空调风口（150mm）； 2.风口周边阻燃板封边加固处理； 3.包含完成该项内容所有工作及费用并满足设计图纸、规范等要求； | D79: m | E79: =1.2*2*1 -> 2.4 | I79: =(F79+G79+H79)*$I$3 -> 0 | J79: =ROUND(SUM(F79:I79),2) -> 0 | K79: =ROUND(J79*E79,2) -> 0 | M79: 1
A80: =1+N(A79) -> 6 | B80: 天花肌理无机涂料PT-01 | C80: 1.天花肌理无机涂料PT-01； 2.刮腻子二遍磨平； 3.底漆1遍，面漆2遍； 4.包含完成该项内容所有工作及费用并满足设计图纸、规范等要求； | D80: m2 | E80: =23.8+4.4+5.5*0.3 -> 29.85 | I80: =(F80+G80+H80)*$I$3 -> 0 | J80: =ROUND(SUM(F80:I80),2) -> 0 | K80: =ROUND(J80*E80,2) -> 0 | M80: 1
B81: 门窗、家具工程
A82: =1+N(A81) -> 1 | B82: 电动移门(DR02) | C82: 1、门扇：GL-01超白钢化玻璃 2、门套：1.2mm厚 MT-01古铜不锈钢饰面 3、定制成品套装门制安 4、含电动移门电机(门机安装背梁)等五金配件 5、包含完成该项内容所有工作及费用并满足设计图纸、规范等要求 | D82: m2 | E82: =1.41*3 -> 4.23 | I82: =(F82+G82+H82)*$I$3 -> 0 | J82: =ROUND(SUM(F82:I82),2) -> 0 | K82: =ROUND(J82*E82,2) -> 0 | M82: 1
A83: =1+N(A82) -> 2 | B83: 装饰屏风（800mm*100mm*3200mm） | C83: 1.装饰屏风（800mm*100mm*3200mm）； 2.包括但不限于制作安装、钢结构骨架、阻燃板基层、WD-02木饰面、1.2mm厚 MT-01古铜不锈钢、MT-04手敲铜不锈钢； 3.包含完成该项内容所有工作及费用并满足设计图纸、规范等要求 | D83: m2 | E83: =3*0.8*3.2 -> 7.68 | I83: =(F83+G83+H83)*$I$3 -> 0 | J83: =ROUND(SUM(F83:I83),2) -> 0 | K83: =ROUND(J83*E83,2) -> 0 | M83: 1
A84: 四 | B84: 一层电梯厅（DT3） | O84: =_xlfn.DISPIMG("ID_248119BFBC6C45409BF72E1F8700A056",1) -> =DISPIMG("ID_248119BFBC6C45409BF72E1F8700A056",1)
B85: 地面工程
A86: =1+N(A85) -> 1 | B86: 地面铺贴大理石ST-01 | C86: 1.地面20mm大理石ST-01、铺贴、厚度及样式按物料书为准； 2.10mm厚石材专用粘结剂； 3.70mm厚DS-M15干混砂浆找平； 4.基层清理、石材六面防护、背面刷胶封闭,同色云石胶补缝； 5.含开槽、磨边、倒角、拼接等处理； 6.包含完成该项内容所有工作及费用并满足设计图纸、规范等要求； | D86: m2 | E86: 4.86 | I86: =(F86+G86+H86)*$I$3 -> 0 | J86: =ROUND(SUM(F86:I86),2) -> 0 | K86: =ROUND(J86*E86,2) -> 0 | M86: 1
A87: =1+N(A86) -> 2 | B87: 地面铺贴大理石ST-01.02拼花 | C87: 1.地面20mm大理石拼花、参考3F-DF-01样式、ST-01、ST-02按物料书为准； 2.10mm厚石材专用粘结剂； 3.70mm厚DS-M15干混砂浆找平； 4.基层清理、石材六面防护、背面刷胶封闭,同色云石胶补缝； 5.含开槽、磨边、倒角、拼接等处理； 6.包含完成该项内容所有工作及费用并满足设计图纸、规范等要求； | D87: m2 | E87: 11.36 | I87: =(F87+G87+H87)*$I$3 -> 0 | J87: =ROUND(SUM(F87:I87),2) -> 0 | K87: =ROUND(J87*E87,2) -> 0 | M87: 1
A88: =1+N(A87) -> 3 | B88: 实心铜条5mm宽 | C88: 1.实心铜条5mm宽； 2.包含完成该项内容所有工作及费用并满足设计图纸、规范等要求； | D88: m | E88: 13.36 | I88: =(F88+G88+H88)*$I$3 -> 0 | J88: =ROUND(SUM(F88:I88),2) -> 0 | K88: =ROUND(J88*E88,2) -> 0 | M88: 1
A89: =1+N(A88) -> 4 | B89: 地面石材晶面处理 | C89: 1.石材结晶处理(结晶水及石材保养剂,中性清洁剂)； 2.包含完成该项内容所有工作及费用并满足设计图纸、规范等要求； | D89: m2 | E89: 16.22 | I89: =(F89+G89+H89)*$I$3 -> 0 | J89: =ROUND(SUM(F89:I89),2) -> 0 | K89: =ROUND(J89*E89,2) -> 0 | M89: 1
B90: 墙柱面工程
A91: =1+N(A90) -> 1 | B91: 墙面湿贴石材ST-05 | C91: 1、墙面湿贴石材ST-05 2、8mm厚石材专用胶粘剂WC粘结层 3、界面剂拉毛处理 4、石材的开槽、磨边、倒角、粘接、形成所需之凹坑、抛光、六面防污防渗等一切处理费用均在主材费中考虑，不再另行计取 5、包含完成该项内容所有工作及费用并满足设计图纸、规范等要求 | D91: m2 | E91: 4.772 | I91: =(F91+G91+H91)*$I$3 -> 0 | J91: =ROUND(SUM(F91:I91),2) -> 0 | K91: =ROUND(J91*E91,2) -> 0 | M91: 1
A92: =1+N(A91) -> 2 | B92: 墙面干挂ST-05石材 | C92: 1、墙面干挂ST-05石材 2、不锈钢背栓挂件安装，云石胶+AB胶固定 3、镀锌角钢钢架(高度超4m、完成面超150mm采用槽钢基层加固)，钢架防锈处理 4、膨胀螺栓固定预埋铁件(轻质砖墙体需要穿墙螺栓固定) 5、石材的开槽、磨边、倒角、粘接、形成所需之凹坑、抛光、六面防污防渗等一切处理费用均在主材费中考虑，不再另行计取 6、包含完成该项内容所有工作及费用并满足设计图纸、规范等要求 | D92: m2 | E92: =24.446+0.727 -> 25.173 | I92: =(F92+G92+H92)*$I$3 -> 0 | J92: =ROUND(SUM(F92:I92),2) -> 0 | K92: =ROUND(J92*E92,2) -> 0 | M92: 1
A93: =1+N(A92) -> 3 | B93: 电梯不锈钢门套 | C93: 1、1.2mm厚 MT-01古铜不锈钢门套，结构胶固定 2、9厘玻镁板基层 3、工程量以展开面积计算 4、包含完成该项内容所有工作及费用并满足设计图纸、规范等要求 | D93: m2 | E93: =0.296*3*2*2 -> 3.552 | I93: =(F93+G93+H93)*$I$3 -> 0 | J93: =ROUND(SUM(F93:I93),2) -> 0 | K93: =ROUND(J93*E93,2) -> 0 | M93: 1
A94: =1+N(A93) -> 4 | B94: 电梯不锈钢门头 | C94: 1、1.2mm厚 MT-01古铜不锈钢门头，结构胶固定 2、12mm阻燃板，轻钢副龙骨@400 3、电梯门顶内置亚克力，内部面层刮白处理 4、工程量以展开面积计算 5、包含完成该项内容所有工作及费用并满足设计图纸、规范等要求 | D94: m2 | E94: =+(0.061+0.72+0.114+0.074)*0.95*2 -> 1.8411 | I94: =(F94+G94+H94)*$I$3 -> 0 | J94: =ROUND(SUM(F94:I94),2) -> 0 | K94: =ROUND(J94*E94,2) -> 0 | M94: 1
A95: =1+N(A94) -> 5 | B95: MT-01古铜不锈钢饰面（电梯按钮处） | C95: 1、1.2mm厚 MT-01古铜不锈钢饰面 2、12mm阻燃板基层，轻钢副龙骨@400 3、工程量以展开面积计算 4、包含完成该项内容所有工作及费用并满足设计图纸、规范等要求 | D95: m2 | E95: 0.252 | I95: =(F95+G95+H95)*$I$3 -> 0 | J95: =ROUND(SUM(F95:I95),2) -> 0 | K95: =ROUND(J95*E95,2) -> 0 | M95: 1
A96: =1+N(A95) -> 6 | B96: MT-01古铜不锈钢踢脚线（高20mm） | C96: 1、1.2mm厚 MT-01古铜不锈钢踢脚线（高20mm，展开面为46mm），结构胶固定 2、9厘玻镁板基层 3、包含完成该项内容所有工作及费用并满足设计图纸、规范等要求 | D96: m | E96: 10.298 | I96: =(F96+G96+H96)*$I$3 -> 0 | J96: =ROUND(SUM(F96:I96),2) -> 0 | K96: =ROUND(J96*E96,2) -> 0 | M96: 1
A97: =1+N(A96) -> 7 | B97: MT-01古铜不锈钢线条（展开面为54mm） | C97: 1、1.2mm厚 MT-01古铜不锈钢线条（展开面为54mm），结构胶固定 2、9厘玻镁板基层 3、包含完成该项内容所有工作及费用并满足设计图纸、规范等要求 | D97: m | E97: =0.17*2 -> 0.34 | I97: =(F97+G97+H97)*$I$3 -> 0 | J97: =ROUND(SUM(F97:I97),2) -> 0 | K97: =ROUND(J97*E97,2) -> 0 | M97: 1
A98: =1+N(A97) -> 8 | B98: MT-01古铜不锈钢线条（展开面为114mm） | C98: 1、1.2mm厚 MT-01古铜不锈钢线条（展开面为114mm），结构胶固定 2、9厘玻镁板基层 3、包含完成该项内容所有工作及费用并满足设计图纸、规范等要求 | D98: m | E98: 9.958 | I98: =(F98+G98+H98)*$I$3 -> 0 | J98: =ROUND(SUM(F98:I98),2) -> 0 | K98: =ROUND(J98*E98,2) -> 0 | M98: 1
A99: =1+N(A98) -> 9 | B99: MT-01古铜不锈钢顶部收口条（展开面为41mm） | C99: 1、1.2mm厚 MT-01古铜不锈钢顶部收口条（展开面为41mm），结构胶固定 2、9厘玻镁板基层 3、包含完成该项内容所有工作及费用并满足设计图纸、规范等要求 | D99: m | E99: 10.298 | I99: =(F99+G99+H99)*$I$3 -> 0 | J99: =ROUND(SUM(F99:I99),2) -> 0 | K99: =ROUND(J99*E99,2) -> 0 | M99: 1
B100: 天花工程
...

Sheet 电梯轿厢装修工程
A1: 珠海海德公馆会所项目-工程量清单
A2: 序号 | B2: 项目名称 | C2: 项目特征 | D2: 单位 | E2: 工程量 | F2: 人工 | G2: 主材 | H2: 辅材及机械费 | I2: 管理及利润取费 | J2: 综合单价 （不含税） | K2: 合价 （不含税） | L2: 备注
A4: A | B4: 电梯轿厢 | K4: =SUM(K5:K23) -> 0
B5: 地面工程
A6: =1+N(A5) -> 1 | B6: 地面铺贴大理石ST-01 | C6: 1.地面20mm大理石ST-01、铺贴、厚度及样式按物料书为准； 2.10mm厚石材专用粘结剂； 3.70mm厚DS-M15干混砂浆找平； 4.基层清理、石材六面防护、背面刷胶封闭,同色云石胶补缝； 5.含开槽、磨边、倒角、拼接等处理； 6.包含完成该项内容所有工作及费用并满足设计图纸、规范等要求； | D6: m2 | E6: 2.337 | I6: =(F6+G6+H6)*$I$3 -> 0 | J6: =ROUND(SUM(F6:I6),2) -> 0 | K6: =ROUND(J6*E6,2) -> 0
A7: =1+N(A6) -> 2 | B7: 地面石材晶面处理 | C7: 1.石材结晶处理(结晶水及石材保养剂,中性清洁剂)； 2.包含完成该项内容所有工作及费用并满足设计图纸、规范等要求； | D7: m2 | E7: 2.337 | I7: =(F7+G7+H7)*$I$3 -> 0 | J7: =ROUND(SUM(F7:I7),2) -> 0 | K7: =ROUND(J7*E7,2) -> 0
B8: 墙面工程
A9: =1+N(A8) -> 1 | B9: 墙面湿贴石材ST-04 | C9: 1、墙面湿贴石材ST-04 2、8mm厚石材专用胶粘剂WC粘结层 3、界面剂拉毛处理 4、石材的开槽、磨边、倒角、粘接、形成所需之凹坑、抛光、六面防污防渗等一切处理费用均在主材费中考虑，不再另行计取 5、包含完成该项内容所有工作及费用并满足设计图纸、规范等要求 | D9: m2 | E9: 2.738 | I9: =(F9+G9+H9)*$I$3 -> 0 | J9: =ROUND(SUM(F9:I9),2) -> 0 | K9: =ROUND(J9*E9,2) -> 0
A10: =1+N(A9) -> 2 | B10: MT-01古铜不锈钢饰面 | C10: 1、1.2mm厚 MT-01古铜不锈钢饰面(结构胶固定) 2、9厘玻镁板基层 3、包含完成该项内容所有工作及费用并满足设计图纸、规范等要求 | D10: m2 | E10: =2.415+(0.217*1.05+0.037*1.47+0.054*1.05)*2 -> 3.09288 | I10: =(F10+G10+H10)*$I$3 -> 0 | J10: =ROUND(SUM(F10:I10),2) -> 0 | K10: =ROUND(J10*E10,2) -> 0
A11: =1+N(A10) -> 3 | B11: 墙面WD-09摩素板 | C11: 1、墙面WD-09摩素板(结构胶固定) 2、12厘玻镁板基层 3、膨胀螺栓、轻钢龙骨(钢结构)基层找平 4、包含完成该项内容所有工作及费用并满足设计图纸、规范等要求 | D11: m2 | E11: 8.025 | I11: =(F11+G11+H11)*$I$3 -> 0 | J11: =ROUND(SUM(F11:I11),2) -> 0 | K11: =ROUND(J11*E11,2) -> 0
A12: =1+N(A11) -> 4 | B12: MT-01古铜不锈钢踢脚线（高50mm） | C12: 1、1.2mm厚 MT-01古铜不锈钢踢脚线（高50mm，展开面为67mm），结构胶固定 2、9厘玻镁板基层 3、包含完成该项内容所有工作及费用并满足设计图纸、规范等要求 | D12: m | E12: 4.47 | I12: =(F12+G12+H12)*$I$3 -> 0 | J12: =ROUND(SUM(F12:I12),2) -> 0 | K12: =ROUND(J12*E12,2) -> 0
A13: =1+N(A12) -> 5 | B13: MT-01古铜不锈钢线条（展开面为67mm） | C13: 1、1.2mm厚 MT-01古铜不锈钢线条（展开面为67mm），结构胶固定 2、9厘玻镁板基层 3、包含完成该项内容所有工作及费用并满足设计图纸、规范等要求 | D13: m | E13: 5.17 | I13: =(F13+G13+H13)*$I$3 -> 0 | J13: =ROUND(SUM(F13:I13),2) -> 0 | K13: =ROUND(J13*E13,2) -> 0
A14: =1+N(A13) -> 6 | B14: MT-01古铜不锈钢线条（展开面为37mm） | C14: 1、1.2mm厚 MT-01古铜不锈钢线条（展开面为37mm），结构胶固定 2、9厘玻镁板基层 3、包含完成该项内容所有工作及费用并满足设计图纸、规范等要求 | D14: m | E14: 5.17 | I14: =(F14+G14+H14)*$I$3 -> 0 | J14: =ROUND(SUM(F14:I14),2) -> 0 | K14: =ROUND(J14*E14,2) -> 0
A15: =1+N(A14) -> 7 | B15: MT-01古铜不锈钢收口条（展开面为26mm） | C15: 1、1.2mm厚 MT-01古铜不锈钢收口条（展开面为26mm），结构胶固定 2、9厘玻镁板基层 3、包含完成该项内容所有工作及费用并满足设计图纸、规范等要求 | D15: m | E15: =6.78+3.394+10.06+2.585*2 -> 25.404 | I15: =(F15+G15+H15)*$I$3 -> 0 | J15: =ROUND(SUM(F15:I15),2) -> 0 | K15: =ROUND(J15*E15,2) -> 0
B16: 天花工程
A17: =1+N(A16) -> 1 | B17: 古铜不锈钢吊顶 | C17: 1.60系列轻钢主龙骨@900，60系列轻钢副龙骨@400，60系列横撑龙骨@600，08螺纹吊杆@900不上人天花吊顶（投影面计算） 2.玻镁板、古铜不锈钢MT-01，含开孔、检修口等费用； 3.含除灯槽外的侧面高差及其连接件、吊件； 4.包含完成该项内容所有工作及费用并满足设计图纸、规范等要求； | D17: m2 | E17: 2.096 | I17: =(F17+G17+H17)*$I$3 -> 0 | J17: =ROUND(SUM(F17:I17),2) -> 0 | K17: =ROUND(J17*E17,2) -> 0
A18: =1+N(A17) -> 2 | B18: 灯槽（135mm*100mm） | C18: 1.灯槽（135mm*100mm）； 2.双层板：9mm玻镁板、9.5厚石膏板； 3.包含完成该项内容所有工作及费用并满足设计图纸、规范等要求； | D18: m | E18: 5.26 | I18: =(F18+G18+H18)*$I$3 -> 0 | J18: =ROUND(SUM(F18:I18),2) -> 0 | K18: =ROUND(J18*E18,2) -> 0
A19: =1+N(A18) -> 3 | B19: 条形空调风口（80mm） | C19: 1.条形空调风口（80mm）； 2.风口周边阻燃板封边加固处理； 3.包含完成该项内容所有工作及费用并满足设计图纸、规范等要求； | D19: m | E19: =1.25*2 -> 2.5 | I19: =(F19+G19+H19)*$I$3 -> 0 | J19: =ROUND(SUM(F19:I19),2) -> 0 | K19: =ROUND(J19*E19,2) -> 0
A20: =1+N(A19) -> 4 | B20: 天花肌理无机涂料PT-01 | C20: 1.天花肌理无机涂料PT-01； 2.刮腻子二遍磨平； 3.底漆1遍，面漆2遍； 4.包含完成该项内容所有工作及费用并满足设计图纸、规范等要求； | D20: m2 | E20: 1.146 | I20: =(F20+G20+H20)*$I$3 -> 0 | J20: =ROUND(SUM(F20:I20),2) -> 0 | K20: =ROUND(J20*E20,2) -> 0
A21: =1+N(A20) -> 5 | B21: MT-06深色不锈钢线条 | C21: 1、MT-06深色不锈钢线条（宽为40mm），结构胶固定 2、9厘玻镁板基层 3、包含完成该项内容所有工作及费用并满足设计图纸、规范等要求 | D21: m | E21: 2.46 | I21: =(F21+G21+H21)*$I$3 -> 0 | J21: =ROUND(SUM(F21:I21),2) -> 0 | K21: =ROUND(J21*E21,2) -> 0
B22: 门窗、家具工程
A23: =1+N(A22) -> 1 | B23: 电梯扶手 | C23: 1、ST-04石材、古铜不锈钢、UP-01皮革 2、定制成品扶手制安 3、包含完成该项内容所有工作及费用并满足设计图纸、规范等要求 | D23: m | E23: =1.04*2 -> 2.08 | I23: =(F23+G23+H23)*$I$3 -> 0 | J23: =ROUND(SUM(F23:I23),2) -> 0 | K23: =ROUND(J23*E23,2) -> 0
A24: B | B24: 无障碍电梯轿厢 | K24: =SUM(K25:K43) -> 0
B25: 地面工程
A26: =1+N(A25) -> 1 | B26: 地面铺贴大理石ST-01 | C26: 1.地面20mm大理石ST-01、铺贴、厚度及样式按物料书为准； 2.10mm厚石材专用粘结剂； 3.70mm厚DS-M15干混砂浆找平； 4.基层清理、石材六面防护、背面刷胶封闭,同色云石胶补缝； 5.含开槽、磨边、倒角、拼接等处理； 6.包含完成该项内容所有工作及费用并满足设计图纸、规范等要求； | D26: m2 | E26: 2.337 | I26: =(F26+G26+H26)*$I$3 -> 0 | J26: =ROUND(SUM(F26:I26),2) -> 0 | K26: =ROUND(J26*E26,2) -> 0
A27: =1+N(A26) -> 2 | B27: 地面石材晶面处理 | C27: 1.石材结晶处理(结晶水及石材保养剂,中性清洁剂)； 2.包含完成该项内容所有工作及费用并满足设计图纸、规范等要求； | D27: m2 | E27: 2.337 | I27: =(F27+G27+H27)*$I$3 -> 0 | J27: =ROUND(SUM(F27:I27),2) -> 0 | K27: =ROUND(J27*E27,2) -> 0
B28: 墙面工程
A29: =1+N(A28) -> 1 | B29: 墙面湿贴石材ST-04 | C29: 1、墙面湿贴石材ST-04 2、8mm厚石材专用胶粘剂WC粘结层 3、界面剂拉毛处理 4、石材的开槽、磨边、倒角、粘接、形成所需之凹坑、抛光、六面防污防渗等一切处理费用均在主材费中考虑，不再另行计取 5、包含完成该项内容所有工作及费用并满足设计图纸、规范等要求 | D29: m2 | E29: 2.738 | I29: =(F29+G29+H29)*$I$3 -> 0 | J29: =ROUND(SUM(F29:I29),2) -> 0 | K29: =ROUND(J29*E29,2) -> 0
A30: =1+N(A29) -> 2 | B30: MT-01古铜不锈钢饰面 | C30: 1、1.2mm厚 MT-01古铜不锈钢饰面(结构胶固定) 2、9厘玻镁板基层 3、包含完成该项内容所有工作及费用并满足设计图纸、规范等要求 | D30: m2 | E30: =2.415+(0.547*1.05+0.037*2.13+0.054*1.05)*2 -> 3.83472 | I30: =(F30+G30+H30)*$I$3 -> 0 | J30: =ROUND(SUM(F30:I30),2) -> 0 | K30: =ROUND(J30*E30,2) -> 0
A31: =1+N(A30) -> 3 | B31: 墙面WD-09摩素板 | C31: 1、墙面WD-09摩素板(结构胶固定) 2、12厘玻镁板基层 3、膨胀螺栓、轻钢龙骨(钢结构)基层找平 4、包含完成该项内容所有工作及费用并满足设计图纸、规范等要求 | D31: m2 | E31: 7.332 | I31: =(F31+G31+H31)*$I$3 -> 0 | J31: =ROUND(SUM(F31:I31),2) -> 0 | K31: =ROUND(J31*E31,2) -> 0
A32: =1+N(A31) -> 4 | B32: MT-01古铜不锈钢踢脚线（高50mm） | C32: 1、1.2mm厚 MT-01古铜不锈钢踢脚线（高50mm，展开面为67mm），结构胶固定 2、9厘玻镁板基层 3、包含完成该项内容所有工作及费用并满足设计图纸、规范等要求 | D32: m | E32: 4.47 | I32: =(F32+G32+H32)*$I$3 -> 0 | J32: =ROUND(SUM(F32:I32),2) -> 0 | K32: =ROUND(J32*E32,2) -> 0
A33: =1+N(A32) -> 5 | B33: MT-01古铜不锈钢线条（展开面为67mm） | C33: 1、1.2mm厚 MT-01古铜不锈钢线条（展开面为67mm），结构胶固定 2、9厘玻镁板基层 3、包含完成该项内容所有工作及费用并满足设计图纸、规范等要求 | D33: m | E33: 5.17 | I33: =(F33+G33+H33)*$I$3 -> 0 | J33: =ROUND(SUM(F33:I33),2) -> 0 | K33: =ROUND(J33*E33,2) -> 0
A34: =1+N(A33) -> 6 | B34: MT-01古铜不锈钢线条（展开面为37mm） | C34: 1、1.2mm厚 MT-01古铜不锈钢线条（展开面为37mm），结构胶固定 2、9厘玻镁板基层 3、包含完成该项内容所有工作及费用并满足设计图纸、规范等要求 | D34: m | E34: 5.17 | I34: =(F34+G34+H34)*$I$3 -> 0 | J34: =ROUND(SUM(F34:I34),2) -> 0 | K34: =ROUND(J34*E34,2) -> 0
A35: =1+N(A34) -> 7 | B35: MT-01古铜不锈钢收口条（展开面为26mm） | C35: 1、1.2mm厚 MT-01古铜不锈钢收口条（展开面为26mm），结构胶固定 2、9厘玻镁板基层 3、包含完成该项内容所有工作及费用并满足设计图纸、规范等要求 | D35: m | E35: =6.78+3.394+10.06+2.585*2 -> 25.404 | I35: =(F35+G35+H35)*$I$3 -> 0 | J35: =ROUND(SUM(F35:I35),2) -> 0 | K35: =ROUND(J35*E35,2) -> 0
B36: 天花工程
A37: =1+N(A36) -> 1 | B37: 古铜不锈钢吊顶 | C37: 1.60系列轻钢主龙骨@900，60系列轻钢副龙骨@400，60系列横撑龙骨@600，08螺纹吊杆@900不上人天花吊顶（投影面计算） 2.玻镁板、古铜不锈钢MT-01，含开孔、检修口等费用； 3.含除灯槽外的侧面高差及其连接件、吊件； 4.包含完成该项内容所有工作及费用并满足设计图纸、规范等要求； | D37: m2 | E37: 2.096 | I37: =(F37+G37+H37)*$I$3 -> 0 | J37: =ROUND(SUM(F37:I37),2) -> 0 | K37: =ROUND(J37*E37,2) -> 0
A38: =1+N(A37) -> 2 | B38: 灯槽（135mm*100mm） | C38: 1.灯槽（135mm*100mm）； 2.双层板：9mm玻镁板、9.5厚石膏板； 3.包含完成该项内容所有工作及费用并满足设计图纸、规范等要求； | D38: m | E38: 5.26 | I38: =(F38+G38+H38)*$I$3 -> 0 | J38: =ROUND(SUM(F38:I38),2) -> 0 | K38: =ROUND(J38*E38,2) -> 0
A39: =1+N(A38) -> 3 | B39: 条形空调风口（80mm） | C39: 1.条形空调风口（80mm）； 2.风口周边阻燃板封边加固处理； 3.包含完成该项内容所有工作及费用并满足设计图纸、规范等要求； | D39: m | E39: =1.25*2 -> 2.5 | I39: =(F39+G39+H39)*$I$3 -> 0 | J39: =ROUND(SUM(F39:I39),2) -> 0 | K39: =ROUND(J39*E39,2) -> 0
A40: =1+N(A39) -> 4 | B40: 天花肌理无机涂料PT-01 | C40: 1.天花肌理无机涂料PT-01； 2.刮腻子二遍磨平； 3.底漆1遍，面漆2遍； 4.包含完成该项内容所有工作及费用并满足设计图纸、规范等要求； | D40: m2 | E40: 1.146 | I40: =(F40+G40+H40)*$I$3 -> 0 | J40: =ROUND(SUM(F40:I40),2) -> 0 | K40: =ROUND(J40*E40,2) -> 0
A41: =1+N(A40) -> 5 | B41: MT-06深色不锈钢线条 | C41: 1、MT-06深色不锈钢线条（宽为40mm），结构胶固定 2、9厘玻镁板基层 3、包含完成该项内容所有工作及费用并满足设计图纸、规范等要求 | D41: m | E41: 2.46 | I41: =(F41+G41+H41)*$I$3 -> 0 | J41: =ROUND(SUM(F41:I41),2) -> 0 | K41: =ROUND(J41*E41,2) -> 0
B42: 门窗、家具工程
A43: =1+N(A42) -> 1 | B43: 电梯扶手 | C43: 1、ST-04石材、古铜不锈钢、UP-01皮革 2、定制成品扶手制安 3、包含完成该项内容所有工作及费用并满足设计图纸、规范等要求 | D43: m | E43: =1.04*2 -> 2.08 | I43: =(F43+G43+H43)*$I$3 -> 0 | J43: =ROUND(SUM(F43:I43),2) -> 0 | K43: =ROUND(J43*E43,2) -> 0
B44: 合计 | K44: =+K4+K24 -> 0

Sheet 地下室装修工程
A1: 珠海海德公馆会所项目-工程量清单
A2: 序号 | B2: 项目名称 | C2: 项目特征 | D2: 单位 | E2: 工程量 | F2: 人工 | G2: 主材 | H2: 辅材及机械费 | I2: 管理及利润取费 | J2: 综合单价 （不含税） | K2: 合价 （不含税） | L2: 备注
A4: A | B4: 负一层 | K4: =SUM(K5:K104) -> 0
A5: 一 | B5: 一单元合用前室
B6: 地面工程
A7: =1+N(A6) -> 1 | B7: 地面铺贴大理石ST-01 | C7: 1.地面20mm大理石ST-01、铺贴、厚度及样式按物料书为准； 2.10mm厚石材专用粘结剂； 3.70mm厚DS-M15干混砂浆找平； 4.基层清理、石材六面防护、背面刷胶封闭,同色云石胶补缝； 5.含开槽、磨边、倒角、拼接等处理； 6.包含完成该项内容所有工作及费用并满足设计图纸、规范等要求； | D7: m2 | E7: 10.765 | I7: =(F7+G7+H7)*$I$3 -> 0 | J7: =ROUND(SUM(F7:I7),2) -> 0 | K7: =ROUND(J7*E7,2) -> 0 | P7: 1
A8: =1+N(A7) -> 2 | B8: 地面铺贴大理石ST-01.02拼花 | C8: 1.地面20mm大理石拼花、参考3F-DF-01样式、ST-01、ST-02按物料书为准； 2.10mm厚石材专用粘结剂； 3.70mm厚DS-M15干混砂浆找平； 4.基层清理、石材六面防护、背面刷胶封闭,同色云石胶补缝； 5.含开槽、磨边、倒角、拼接等处理； 6.包含完成该项内容所有工作及费用并满足设计图纸、规范等要求； | D8: m2 | E8: 16.519 | I8: =(F8+G8+H8)*$I$3 -> 0 | J8: =ROUND(SUM(F8:I8),2) -> 0 | K8: =ROUND(J8*E8,2) -> 0 | P8: 1
A9: =1+N(A8) -> 3 | B9: 实心铜条5mm宽 | C9: 1.实心铜条5mm宽； 2.包含完成该项内容所有工作及费用并满足设计图纸、规范等要求； | D9: m | E9: 17.264 | I9: =(F9+G9+H9)*$I$3 -> 0 | J9: =ROUND(SUM(F9:I9),2) -> 0 | K9: =ROUND(J9*E9,2) -> 0
A10: =1+N(A9) -> 4 | B10: 地面石材晶面处理 | C10: 1.石材结晶处理(结晶水及石材保养剂,中性清洁剂)； 2.包含完成该项内容所有工作及费用并满足设计图纸、规范等要求； | D10: m2 | E10: =+E7+E8 -> 27.284 | I10: =(F10+G10+H10)*$I$3 -> 0 | J10: =ROUND(SUM(F10:I10),2) -> 0 | K10: =ROUND(J10*E10,2) -> 0
B11: 墙面工程
A12: =1+N(A11) -> 1 | B12: 墙面湿贴石材ST-05 | C12: 1、墙面湿贴石材ST-05 2、8mm厚石材专用胶粘剂WC粘结层 3、界面剂拉毛处理 4、石材的开槽、磨边、倒角、粘接、形成所需之凹坑、抛光、六面防污防渗等一切处理费用均在主材费中考虑，不再另行计取 5、包含完成该项内容所有工作及费用并满足设计图纸、规范等要求 | D12: m2 | E12: 6.099 | I12: =(F12+G12+H12)*$I$3 -> 0 | J12: =ROUND(SUM(F12:I12),2) -> 0 | K12: =ROUND(J12*E12,2) -> 0
A13: =1+N(A12) -> 2 | B13: 墙面干挂ST-05石材 | C13: 1、墙面干挂ST-05石材 2、不锈钢背栓挂件安装，云石胶+AB胶固定 3、镀锌角钢钢架(高度超4m、完成面超150mm采用槽钢基层加固)，钢架防锈处理 4、膨胀螺栓固定预埋铁件(轻质砖墙体需要穿墙螺栓固定) 5、石材的开槽、磨边、倒角、粘接、形成所需之凹坑、抛光、六面防污防渗等一切处理费用均在主材费中考虑，不再另行计取 6、包含完成该项内容所有工作及费用并满足设计图纸、规范等要求 | D13: m2 | E13: 27.664 | I13: =(F13+G13+H13)*$I$3 -> 0 | J13: =ROUND(SUM(F13:I13),2) -> 0 | K13: =ROUND(J13*E13,2) -> 0
A14: =1+N(A13) -> 3 | B14: WD-07摩素板 | C14: 1、墙面WD-08摩素板(结构胶固定) 2、12厘玻镁板基层 3、膨胀螺栓、轻钢龙骨(钢结构)基层找平 4、包含完成该项内容所有工作及费用并满足设计图纸、规范等要求 | D14: m2 | E14: 5.421 | I14: =(F14+G14+H14)*$I$3 -> 0 | J14: =ROUND(SUM(F14:I14),2) -> 0 | K14: =ROUND(J14*E14,2) -> 0
A15: =1+N(A14) -> 4 | B15: 墙面PT-01肌理无机涂料 | C15: 1、墙面PT-01肌理无机涂料(底漆1遍，面漆2遍) 2、刮白胶腻子找平二遍，打磨 3、阴、阳角护角收边 4、双层9.5mm纸面石膏板 5、轻钢龙骨基层找平 6、包含完成该项内容所有工作及费用并满足设计图纸、规范等要求 | D15: m2 | E15: 29.816 | I15: =(F15+G15+H15)*$I$3 -> 0 | J15: =ROUND(SUM(F15:I15),2) -> 0 | K15: =ROUND(J15*E15,2) -> 0
A16: =1+N(A15) -> 5 | B16: 不锈钢门套 | C16: 1、1.2mm厚 MT-01古铜不锈钢门套，结构胶固定 2、9厘玻镁板基层 3、工程量以展开面积计算 4、包含完成该项内容所有工作及费用并满足设计图纸、规范等要求 | D16: m2 | E16: =0.21*2.2*2+0.15*1.11 -> 1.0905 | I16: =(F16+G16+H16)*$I$3 -> 0 | J16: =ROUND(SUM(F16:I16),2) -> 0 | K16: =ROUND(J16*E16,2) -> 0
A17: =1+N(A16) -> 6 | B17: 电梯不锈钢门套 | C17: 1、1.2mm厚 MT-01古铜不锈钢门套，结构胶固定 2、9厘玻镁板基层 3、工程量以展开面积计算 4、包含完成该项内容所有工作及费用并满足设计图纸、规范等要求 | D17: m2 | E17: =0.34*2.75*2*2 -> 3.74 | I17: =(F17+G17+H17)*$I$3 -> 0 | J17: =ROUND(SUM(F17:I17),2) -> 0 | K17: =ROUND(J17*E17,2) -> 0
A18: =1+N(A17) -> 7 | B18: 电梯不锈钢门头 | C18: 1、1.2mm厚 MT-01古铜不锈钢门头，结构胶固定 2、12mm阻燃板，轻钢副龙骨@400 3、电梯门顶内置亚克力，内部面层刮白处理 4、工程量以展开面积计算 5、包含完成该项内容所有工作及费用并满足设计图纸、规范等要求 | D18: m2 | E18: =+(0.061+0.475+0.114+0.074)*0.95*2 -> 1.3756 | I18: =(F18+G18+H18)*$I$3 -> 0 | J18: =ROUND(SUM(F18:I18),2) -> 0 | K18: =ROUND(J18*E18,2) -> 0
A19: =1+N(A18) -> 8 | B19: MT-01古铜不锈钢饰面（电梯按钮处） | C19: 1、1.2mm厚 MT-01古铜不锈钢饰面 2、12mm阻燃板基层，轻钢副龙骨@400 3、工程量以展开面积计算 4、包含完成该项内容所有工作及费用并满足设计图纸、规范等要求 | D19: m2 | E19: 0.253 | I19: =(F19+G19+H19)*$I$3 -> 0 | J19: =ROUND(SUM(F19:I19),2) -> 0 | K19: =ROUND(J19*E19,2) -> 0
A20: =1+N(A19) -> 9 | B20: MT-01古铜不锈钢踢脚线（高20mm） | C20: 1、1.2mm厚 MT-01古铜不锈钢踢脚线（高20mm，展开面为46mm），结构胶固定 2、9厘玻镁板基层 3、包含完成该项内容所有工作及费用并满足设计图纸、规范等要求 | D20: m | E20: 24.611 | I20: =(F20+G20+H20)*$I$3 -> 0 | J20: =ROUND(SUM(F20:I20),2) -> 0 | K20: =ROUND(J20*E20,2) -> 0
A21: =1+N(A20) -> 10 | B21: MT-01古铜不锈钢线条（展开面为51mm） | C21: 1、1.2mm厚 MT-01古铜不锈钢线条（展开面为51mm），结构胶固定 2、9厘玻镁板基层 3、包含完成该项内容所有工作及费用并满足设计图纸、规范等要求 | D21: m | E21: 10.065 | I21: =(F21+G21+H21)*$I$3 -> 0 | J21: =ROUND(SUM(F21:I21),2) -> 0 | K21: =ROUND(J21*E21,2) -> 0
A22: =1+N(A21) -> 11 | B22: MT-01古铜不锈钢线条（展开面为114mm） | C22: 1、1.2mm厚 MT-01古铜不锈钢线条（展开面为114mm），结构胶固定 2、9厘玻镁板基层 3、包含完成该项内容所有工作及费用并满足设计图纸、规范等要求 | D22: m | E22: 10.795 | I22: =(F22+G22+H22)*$I$3 -> 0 | J22: =ROUND(SUM(F22:I22),2) -> 0 | K22: =ROUND(J22*E22,2) -> 0
A23: =1+N(A22) -> 12 | B23: MT-01古铜不锈钢顶部收口条（展开面为41mm） | C23: 1、1.2mm厚 MT-01古铜不锈钢顶部收口条（展开面为41mm），结构胶固定 2、9厘玻镁板基层 3、包含完成该项内容所有工作及费用并满足设计图纸、规范等要求 | D23: m | E23: 25.474 | I23: =(F23+G23+H23)*$I$3 -> 0 | J23: =ROUND(SUM(F23:I23),2) -> 0 | K23: =ROUND(J23*E23,2) -> 0
B24: 天花工程
A25: =1+N(A24) -> 1 | B25: 石膏板吊顶 | C25: 1.60系列轻钢主龙骨@900，60系列轻钢副龙骨@400，60系列横撑龙骨@600，08螺纹吊杆@900不上人天花吊顶（投影面计算） 2.玻镁板、双层9.5厚石膏板基层，含开孔、检修口、10*10凹槽等费用； 3.含除灯槽外的侧面高差及其连接件、吊件； 4.包含完成该项内容所有工作及费用并满足设计图纸、规范等要求； | D25: m2 | E25: 27.946 | I25: =(F25+G25+H25)*$I$3 -> 0 | J25: =ROUND(SUM(F25:I25),2) -> 0 | K25: =ROUND(J25*E25,2) -> 0
A26: =1+N(A25) -> 2 | B26: 灯槽（100mm*250mm） | C26: 1.灯槽（100mm*250mm）； 2.双层板：9mm玻镁板、9.5厚石膏板； 3.包含完成该项内容所有工作及费用并满足设计图纸、规范等要求； | D26: m | E26: 17.282 | I26: =(F26+G26+H26)*$I$3 -> 0 | J26: =ROUND(SUM(F26:I26),2) -> 0 | K26: =ROUND(J26*E26,2) -> 0
A27: =1+N(A26) -> 3 | B27: 成品石膏线条 | C27: 1.成品石膏线条（50mm*50mm）； 2.按图纸造型； 3.包含完成该项内容所有工作及费用并满足设计图纸、规范等要求； | D27: m | E27: 17.282 | I27: =(F27+G27+H27)*$I$3 -> 0 | J27: =ROUND(SUM(F27:I27),2) -> 0 | K27: =ROUND(J27*E27,2) -> 0
A28: =1+N(A27) -> 4 | B28: 条形空调风口（150mm） | C28: 1.条形空调风口（150mm）； 2.风口周边阻燃板封边加固处理； 3.包含完成该项内容所有工作及费用并满足设计图纸、规范等要求； | D28: m | E28: =5.12*2 -> 10.24 | I28: =(F28+G28+H28)*$I$3 -> 0 | J28: =ROUND(SUM(F28:I28),2) -> 0 | K28: =ROUND(J28*E28,2) -> 0
A29: =1+N(A28) -> 5 | B29: 天花肌理无机涂料PT-01 | C29: 1.天花肌理无机涂料PT-01； 2.刮腻子二遍磨平； 3.底漆1遍，面漆2遍； 4.包含完成该项内容所有工作及费用并满足设计图纸、规范等要求； | D29: m2 | E29: 34.76 | I29: =(F29+G29+H29)*$I$3 -> 0 | J29: =ROUND(SUM(F29:I29),2) -> 0 | K29: =ROUND(J29*E29,2) -> 0
B30: 门窗、家具工程
A31: 二 | B31: 二单元合用前室
B32: 地面工程
A33: =1+N(A32) -> 1 | B33: 地面铺贴大理石ST-01 | C33: 1.地面20mm大理石ST-01、铺贴、厚度及样式按物料书为准； 2.10mm厚石材专用粘结剂； 3.70mm厚DS-M15干混砂浆找平； 4.基层清理、石材六面防护、背面刷胶封闭,同色云石胶补缝； 5.含开槽、磨边、倒角、拼接等处理； 6.包含完成该项内容所有工作及费用并满足设计图纸、规范等要求； | D33: m2 | E33: 11.09 | I33: =(F33+G33+H33)*$I$3 -> 0 | J33: =ROUND(SUM(F33:I33),2) -> 0 | K33: =ROUND(J33*E33,2) -> 0 | P33: 1
A34: =1+N(A33) -> 2 | B34: 地面铺贴大理石ST-01.02拼花 | C34: 1.地面20mm大理石拼花、参考3F-DF-01样式、ST-01、ST-02按物料书为准； 2.10mm厚石材专用粘结剂； 3.70mm厚DS-M15干混砂浆找平； 4.基层清理、石材六面防护、背面刷胶封闭,同色云石胶补缝； 5.含开槽、磨边、倒角、拼接等处理； 6.包含完成该项内容所有工作及费用并满足设计图纸、规范等要求； | D34: m2 | E34: 19.448 | I34: =(F34+G34+H34)*$I$3 -> 0 | J34: =ROUND(SUM(F34:I34),2) -> 0 | K34: =ROUND(J34*E34,2) -> 0 | P34: 1
A35: =1+N(A34) -> 3 | B35: 实心铜条5mm宽 | C35: 1.实心铜条5mm宽； 2.包含完成该项内容所有工作及费用并满足设计图纸、规范等要求； | D35: m | E35: 19.526 | I35: =(F35+G35+H35)*$I$3 -> 0 | J35: =ROUND(SUM(F35:I35),2) -> 0 | K35: =ROUND(J35*E35,2) -> 0
A36: =1+N(A35) -> 4 | B36: 地面石材晶面处理 | C36: 1.石材结晶处理(结晶水及石材保养剂,中性清洁剂)； 2.包含完成该项内容所有工作及费用并满足设计图纸、规范等要求； | D36: m2 | E36: =+E33+E34 -> 30.538 | I36: =(F36+G36+H36)*$I$3 -> 0 | J36: =ROUND(SUM(F36:I36),2) -> 0 | K36: =ROUND(J36*E36,2) -> 0
B37: 墙面工程
A38: =1+N(A37) -> 1 | B38: 墙面湿贴石材ST-05 | C38: 1、墙面湿贴石材ST-05 2、8mm厚石材专用胶粘剂WC粘结层 3、界面剂拉毛处理 4、石材的开槽、磨边、倒角、粘接、形成所需之凹坑、抛光、六面防污防渗等一切处理费用均在主材费中考虑，不再另行计取 5、包含完成该项内容所有工作及费用并满足设计图纸、规范等要求 | D38: m2 | E38: 8.311 | I38: =(F38+G38+H38)*$I$3 -> 0 | J38: =ROUND(SUM(F38:I38),2) -> 0 | K38: =ROUND(J38*E38,2) -> 0
A39: =1+N(A38) -> 2 | B39: 墙面干挂ST-05石材 | C39: 1、墙面干挂ST-05石材 2、不锈钢背栓挂件安装，云石胶+AB胶固定 3、镀锌角钢钢架(高度超4m、完成面超150mm采用槽钢基层加固)，钢架防锈处理 4、膨胀螺栓固定预埋铁件(轻质砖墙体需要穿墙螺栓固定) 5、石材的开槽、磨边、倒角、粘接、形成所需之凹坑、抛光、六面防污防渗等一切处理费用均在主材费中考虑，不再另行计取 6、包含完成该项内容所有工作及费用并满足设计图纸、规范等要求 | D39: m2 | E39: 37.242 | I39: =(F39+G39+H39)*$I$3 -> 0 | J39: =ROUND(SUM(F39:I39),2) -> 0 | K39: =ROUND(J39*E39,2) -> 0
A40: =1+N(A39) -> 3 | B40: 墙面PT-01肌理无机涂料 | C40: 1、墙面PT-01肌理无机涂料(底漆1遍，面漆2遍) 2、刮白胶腻子找平二遍，打磨 3、阴、阳角护角收边 4、双层9.5mm纸面石膏板 5、轻钢龙骨基层找平 6、包含完成该项内容所有工作及费用并满足设计图纸、规范等要求 | D40: m2 | E40: 24.247 | I40: =(F40+G40+H40)*$I$3 -> 0 | J40: =ROUND(SUM(F40:I40),2) -> 0 | K40: =ROUND(J40*E40,2) -> 0
A41: =1+N(A40) -> 4 | B41: 不锈钢门套 | C41: 1、1.2mm厚 MT-01古铜不锈钢门套，结构胶固定 2、9厘玻镁板基层 3、工程量以展开面积计算 4、包含完成该项内容所有工作及费用并满足设计图纸、规范等要求 | D41: m2 | E41: =0.38*2.2*2+0.29*1.2 -> 2.02 | I41: =(F41+G41+H41)*$I$3 -> 0 | J41: =ROUND(SUM(F41:I41),2) -> 0 | K41: =ROUND(J41*E41,2) -> 0
A42: =1+N(A41) -> 5 | B42: 电梯不锈钢门套 | C42: 1、1.2mm厚 MT-01古铜不锈钢门套，结构胶固定 2、9厘玻镁板基层 3、工程量以展开面积计算 4、包含完成该项内容所有工作及费用并满足设计图纸、规范等要求 | D42: m2 | E42: =0.34*2.75*2*2 -> 3.74 | I42: =(F42+G42+H42)*$I$3 -> 0 | J42: =ROUND(SUM(F42:I42),2) -> 0 | K42: =ROUND(J42*E42,2) -> 0
A43: =1+N(A42) -> 6 | B43: 电梯不锈钢门头 | C43: 1、1.2mm厚 MT-01古铜不锈钢门头，结构胶固定 2、12mm阻燃板，轻钢副龙骨@400 3、电梯门顶内置亚克力，内部面层刮白处理 4、工程量以展开面积计算 5、包含完成该项内容所有工作及费用并满足设计图纸、规范等要求 | D43: m2 | E43: =+(0.061+0.475+0.114+0.074)*0.95*2 -> 1.3756 | I43: =(F43+G43+H43)*$I$3 -> 0 | J43: =ROUND(SUM(F43:I43),2) -> 0 | K43: =ROUND(J43*E43,2) -> 0
A44: =1+N(A43) -> 7 | B44: MT-01古铜不锈钢饰面（电梯按钮处） | C44: 1、1.2mm厚 MT-01古铜不锈钢饰面 2、12mm阻燃板基层，轻钢副龙骨@400 3、工程量以展开面积计算 4、包含完成该项内容所有工作及费用并满足设计图纸、规范等要求 | D44: m2 | E44: 0.253 | I44: =(F44+G44+H44)*$I$3 -> 0 | J44: =ROUND(SUM(F44:I44),2) -> 0 | K44: =ROUND(J44*E44,2) -> 0
A45: =1+N(A44) -> 8 | B45: MT-01古铜不锈钢踢脚线（高20mm） | C45: 1、1.2mm厚 MT-01古铜不锈钢踢脚线（高20mm，展开面为46mm），结构胶固定 2、9厘玻镁板基层 3、包含完成该项内容所有工作及费用并满足设计图纸、规范等要求 | D45: m | E45: 24.411 | I45: =(F45+G45+H45)*$I$3 -> 0 | J45: =ROUND(SUM(F45:I45),2) -> 0 | K45: =ROUND(J45*E45,2) -> 0
A46: =1+N(A45) -> 9 | B46: MT-01古铜不锈钢线条（展开面为51mm） | C46: 1、1.2mm厚 MT-01古铜不锈钢线条（展开面为51mm），结构胶固定 2、9厘玻镁板基层 3、包含完成该项内容所有工作及费用并满足设计图纸、规范等要求 | D46: m | E46: 7.858 | I46: =(F46+G46+H46)*$I$3 -> 0 | J46: =ROUND(SUM(F46:I46),2) -> 0 | K46: =ROUND(J46*E46,2) -> 0
A47: =1+N(A46) -> 10 | B47: MT-01古铜不锈钢线条（展开面为114mm） | C47: 1、1.2mm厚 MT-01古铜不锈钢线条（展开面为114mm），结构胶固定 2、9厘玻镁板基层 3、包含完成该项内容所有工作及费用并满足设计图纸、规范等要求 | D47: m | E47: 14.71 | I47: =(F47+G47+H47)*$I$3 -> 0 | J47: =ROUND(SUM(F47:I47),2) -> 0 | K47: =ROUND(J47*E47,2) -> 0
A48: =1+N(A47) -> 11 | B48: MT-01古铜不锈钢顶部收口条（展开面为41mm） | C48: 1、1.2mm厚 MT-01古铜不锈钢顶部收口条（展开面为41mm），结构胶固定 2、9厘玻镁板基层 3、包含完成该项内容所有工作及费用并满足设计图纸、规范等要求 | D48: m | E48: 28.792 | I48: =(F48+G48+H48)*$I$3 -> 0 | J48: =ROUND(SUM(F48:I48),2) -> 0 | K48: =ROUND(J48*E48,2) -> 0
B49: 天花工程
A50: =1+N(A49) -> 1 | B50: 石膏板吊顶 | C50: 1.60系列轻钢主龙骨@900，60系列轻钢副龙骨@400，60系列横撑龙骨@600，08螺纹吊杆@900不上人天花吊顶（投影面计算） 2.玻镁板、双层9.5厚石膏板基层，含开孔、检修口、10*10凹槽等费用； 3.含除灯槽外的侧面高差及其连接件、吊件； 4.包含完成该项内容所有工作及费用并满足设计图纸、规范等要求； | D50: m2 | E50: 31.408 | I50: =(F50+G50+H50)*$I$3 -> 0 | J50: =ROUND(SUM(F50:I50),2) -> 0 | K50: =ROUND(J50*E50,2) -> 0
A51: =1+N(A50) -> 2 | B51: 灯槽（100mm*250mm） | C51: 1.灯槽（100mm*250mm）； 2.双层板：9mm玻镁板、9.5厚石膏板； 3.包含完成该项内容所有工作及费用并满足设计图纸、规范等要求； | D51: m | E51: 19.532 | I51: =(F51+G51+H51)*$I$3 -> 0 | J51: =ROUND(SUM(F51:I51),2) -> 0 | K51: =ROUND(J51*E51,2) -> 0
A52: =1+N(A51) -> 3 | B52: 成品石膏线条 | C52: 1.成品石膏线条（50mm*50mm）； 2.按图纸造型； 3.包含完成该项内容所有工作及费用并满足设计图纸、规范等要求； | D52: m | E52: 19.532 | I52: =(F52+G52+H52)*$I$3 -> 0 | J52: =ROUND(SUM(F52:I52),2) -> 0 | K52: =ROUND(J52*E52,2) -> 0
A53: =1+N(A52) -> 4 | B53: 条形空调风口（150mm） | C53: 1.条形空调风口（150mm）； 2.风口周边阻燃板封边加固处理； 3.包含完成该项内容所有工作及费用并满足设计图纸、规范等要求； | D53: m | E53: =6.9*2 -> 13.8 | I53: =(F53+G53+H53)*$I$3 -> 0 | J53: =ROUND(SUM(F53:I53),2) -> 0 | K53: =ROUND(J53*E53,2) -> 0
A54: =1+N(A53) -> 5 | B54: 天花肌理无机涂料PT-01 | C54: 1.天花肌理无机涂料PT-01； 2.刮腻子二遍磨平； 3.底漆1遍，面漆2遍； 4.包含完成该项内容所有工作及费用并满足设计图纸、规范等要求； | D54: m2 | E54: 39.118 | I54: =(F54+G54+H54)*$I$3 -> 0 | J54: =ROUND(SUM(F54:I54),2) -> 0 | K54: =ROUND(J54*E54,2) -> 0
B55: 门窗、家具工程
A56: 三 | B56: 三单元合用前室
B57: 地面工程
A58: =1+N(A57) -> 1 | B58: 地面铺贴大理石ST-01 | C58: 1.地面20mm大理石ST-01、铺贴、厚度及样式按物料书为准； 2.10mm厚石材专用粘结剂； 3.70mm厚DS-M15干混砂浆找平； 4.基层清理、石材六面防护、背面刷胶封闭,同色云石胶补缝； 5.含开槽、磨边、倒角、拼接等处理； 6.包含完成该项内容所有工作及费用并满足设计图纸、规范等要求； | D58: m2 | E58: 14.193 | I58: =(F58+G58+H58)*$I$3 -> 0 | J58: =ROUND(SUM(F58:I58),2) -> 0 | K58: =ROUND(J58*E58,2) -> 0 | P58: 1
A59: =1+N(A58) -> 2 | B59: 地面铺贴大理石ST-01.02拼花 | C59: 1.地面20mm大理石拼花、参考3F-DF-01样式、ST-01、ST-02按物料书为准； 2.10mm厚石材专用粘结剂； 3.70mm厚DS-M15干混砂浆找平； 4.基层清理、石材六面防护、背面刷胶封闭,同色云石胶补缝； 5.含开槽、磨边、倒角、拼接等处理； 6.包含完成该项内容所有工作及费用并满足设计图纸、规范等要求； | D59: m2 | E59: 14.838 | I59: =(F59+G59+H59)*$I$3 -> 0 | J59: =ROUND(SUM(F59:I59),2) -> 0 | K59: =ROUND(J59*E59,2) -> 0 | P59: 1
A60: =1+N(A59) -> 3 | B60: 实心铜条5mm宽 | C60: 1.实心铜条5mm宽； 2.包含完成该项内容所有工作及费用并满足设计图纸、规范等要求； | D60: m | E60: 15.966 | I60: =(F60+G60+H60)*$I$3 -> 0 | J60: =ROUND(SUM(F60:I60),2) -> 0 | K60: =ROUND(J60*E60,2) -> 0
A61: =1+N(A60) -> 4 | B61: 地面石材晶面处理 | C61: 1.石材结晶处理(结晶水及石材保养剂,中性清洁剂)； 2.包含完成该项内容所有工作及费用并满足设计图纸、规范等要求； | D61: m2 | E61: =+E58+E59 -> 29.031 | I61: =(F61+G61+H61)*$I$3 -> 0 | J61: =ROUND(SUM(F61:I61),2) -> 0 | K61: =ROUND(J61*E61,2) -> 0
B62: 墙面工程
A63: =1+N(A62) -> 1 | B63: 墙面湿贴石材ST-05 | C63: 1、墙面湿贴石材ST-05 2、8mm厚石材专用胶粘剂WC粘结层 3、界面剂拉毛处理 4、石材的开槽、磨边、倒角、粘接、形成所需之凹坑、抛光、六面防污防渗等一切处理费用均在主材费中考虑，不再另行计取 5、包含完成该项内容所有工作及费用并满足设计图纸、规范等要求 | D63: m2 | E63: 5.314 | I63: =(F63+G63+H63)*$I$3 -> 0 | J63: =ROUND(SUM(F63:I63),2) -> 0 | K63: =ROUND(J63*E63,2) -> 0
A64: =1+N(A63) -> 2 | B64: 墙面干挂ST-05石材 | C64: 1、墙面干挂ST-05石材 2、不锈钢背栓挂件安装，云石胶+AB胶固定 3、镀锌角钢钢架(高度超4m、完成面超150mm采用槽钢基层加固)，钢架防锈处理 4、膨胀螺栓固定预埋铁件(轻质砖墙体需要穿墙螺栓固定) 5、石材的开槽、磨边、倒角、粘接、形成所需之凹坑、抛光、六面防污防渗等一切处理费用均在主材费中考虑，不再另行计取 6、包含完成该项内容所有工作及费用并满足设计图纸、规范等要求 | D64: m2 | E64: 25.354 | I64: =(F64+G64+H64)*$I$3 -> 0 | J64: =ROUND(SUM(F64:I64),2) -> 0 | K64: =ROUND(J64*E64,2) -> 0
A65: =1+N(A64) -> 3 | B65: WD-07摩素板 | C65: 1、墙面WD-08摩素板(结构胶固定) 2、12厘玻镁板基层 3、膨胀螺栓、轻钢龙骨(钢结构)基层找平 4、包含完成该项内容所有工作及费用并满足设计图纸、规范等要求 | D65: m2 | E65: 5.421 | I65: =(F65+G65+H65)*$I$3 -> 0 | J65: =ROUND(SUM(F65:I65),2) -> 0 | K65: =ROUND(J65*E65,2) -> 0
A66: =1+N(A65) -> 4 | B66: 墙面PT-01肌理无机涂料 | C66: 1、墙面PT-01肌理无机涂料(底漆1遍，面漆2遍) 2、刮白胶腻子找平二遍，打磨 3、阴、阳角护角收边 4、双层9.5mm纸面石膏板 5、轻钢龙骨基层找平 6、包含完成该项内容所有工作及费用并满足设计图纸、规范等要求 | D66: m2 | E66: 39.655 | I66: =(F66+G66+H66)*$I$3 -> 0 | J66: =ROUND(SUM(F66:I66),2) -> 0 | K66: =ROUND(J66*E66,2) -> 0
A67: =1+N(A66) -> 5 | B67: 不锈钢门套 | C67: 1、1.2mm厚 MT-01古铜不锈钢门套，结构胶固定 2、9厘玻镁板基层 3、工程量以展开面积计算 4、包含完成该项内容所有工作及费用并满足设计图纸、规范等要求 | D67: m2 | E67: =0.31*2.2*2+0.25*1.2 -> 1.664 | I67: =(F67+G67+H67)*$I$3 -> 0 | J67: =ROUND(SUM(F67:I67),2) -> 0 | K67: =ROUND(J67*E67,2) -> 0
A68: =1+N(A67) -> 6 | B68: 电梯不锈钢门套 | C68: 1、1.2mm厚 MT-01古铜不锈钢门套，结构胶固定 2、9厘玻镁板基层 3、工程量以展开面积计算 4、包含完成该项内容所有工作及费用并满足设计图纸、规范等要求 | D68: m2 | E68: =0.34*2.75*2*2 -> 3.74 | I68: =(F68+G68+H68)*$I$3 -> 0 | J68: =ROUND(SUM(F68:I68),2) -> 0 | K68: =ROUND(J68*E68,2) -> 0
A69: =1+N(A68) -> 7 | B69: 电梯不锈钢门头 | C69: 1、1.2mm厚 MT-01古铜不锈钢门头，结构胶固定 2、12mm阻燃板，轻钢副龙骨@400 3、电梯门顶内置亚克力，内部面层刮白处理 4、工程量以展开面积计算 5、包含完成该项内容所有工作及费用并满足设计图纸、规范等要求 | D69: m2 | E69: =+(0.061+0.475+0.114+0.074)*0.95*2 -> 1.3756 | I69: =(F69+G69+H69)*$I$3 -> 0 | J69: =ROUND(SUM(F69:I69),2) -> 0 | K69: =ROUND(J69*E69,2) -> 0
A70: =1+N(A69) -> 8 | B70: MT-01古铜不锈钢饰面（电梯按钮处） | C70: 1、1.2mm厚 MT-01古铜不锈钢饰面 2、12mm阻燃板基层，轻钢副龙骨@400 3、工程量以展开面积计算 4、包含完成该项内容所有工作及费用并满足设计图纸、规范等要求 | D70: m2 | E70: 0.253 | I70: =(F70+G70+H70)*$I$3 -> 0 | J70: =ROUND(SUM(F70:I70),2) -> 0 | K70: =ROUND(J70*E70,2) -> 0
A71: =1+N(A70) -> 9 | B71: MT-01古铜不锈钢踢脚线（高20mm） | C71: 1、1.2mm厚 MT-01古铜不锈钢踢脚线（高20mm，展开面为46mm），结构胶固定 2、9厘玻镁板基层 3、包含完成该项内容所有工作及费用并满足设计图纸、规范等要求 | D71: m | E71: 25.991 | I71: =(F71+G71+H71)*$I$3 -> 0 | J71: =ROUND(SUM(F71:I71),2) -> 0 | K71: =ROUND(J71*E71,2) -> 0
A72: =1+N(A71) -> 10 | B72: MT-01古铜不锈钢线条（展开面为51mm） | C72: 1、1.2mm厚 MT-01古铜不锈钢线条（展开面为51mm），结构胶固定 2、9厘玻镁板基层 3、包含完成该项内容所有工作及费用并满足设计图纸、规范等要求 | D72: m | E72: 12.848 | I72: =(F72+G72+H72)*$I$3 -> 0 | J72: =ROUND(SUM(F72:I72),2) -> 0 | K72: =ROUND(J72*E72,2) -> 0
A73: =1+N(A72) -> 11 | B73: MT-01古铜不锈钢线条（展开面为114mm） | C73: 1、1.2mm厚 MT-01古铜不锈钢线条（展开面为114mm），结构胶固定 2、9厘玻镁板基层 3、包含完成该项内容所有工作及费用并满足设计图纸、规范等要求 | D73: m | E73: 9.405 | I73: =(F73+G73+H73)*$I$3 -> 0 | J73: =ROUND(SUM(F73:I73),2) -> 0 | K73: =ROUND(J73*E73,2) -> 0
A74: =1+N(A73) -> 12 | B74: MT-01古铜不锈钢顶部收口条（展开面为41mm） | C74: 1、1.2mm厚 MT-01古铜不锈钢顶部收口条（展开面为41mm），结构胶固定 2、9厘玻镁板基层 3、包含完成该项内容所有工作及费用并满足设计图纸、规范等要求 | D74: m | E74: 29.322 | I74: =(F74+G74+H74)*$I$3 -> 0 | J74: =ROUND(SUM(F74:I74),2) -> 0 | K74: =ROUND(J74*E74,2) -> 0
B75: 天花工程
A76: =1+N(A75) -> 1 | B76: 石膏板吊顶 | C76: 1.60系列轻钢主龙骨@900，60系列轻钢副龙骨@400，60系列横撑龙骨@600，08螺纹吊杆@900不上人天花吊顶（投影面计算） 2.玻镁板、双层9.5厚石膏板基层，含开孔、检修口、10*10凹槽等费用； 3.含除灯槽外的侧面高差及其连接件、吊件； 4.包含完成该项内容所有工作及费用并满足设计图纸、规范等要求； | D76: m2 | E76: 29.392 | I76: =(F76+G76+H76)*$I$3 -> 0 | J76: =ROUND(SUM(F76:I76),2) -> 0 | K76: =ROUND(J76*E76,2) -> 0
A77: =1+N(A76) -> 2 | B77: 灯槽（100mm*250mm） | C77: 1.灯槽（100mm*250mm）； 2.双层板：9mm玻镁板、9.5厚石膏板； 3.包含完成该项内容所有工作及费用并满足设计图纸、规范等要求； | D77: m | E77: 15.982 | I77: =(F77+G77+H77)*$I$3 -> 0 | J77: =ROUND(SUM(F77:I77),2) -> 0 | K77: =ROUND(J77*E77,2) -> 0
A78: =1+N(A77) -> 3 | B78: 成品石膏线条 | C78: 1.成品石膏线条（50mm*50mm）； 2.按图纸造型； 3.包含完成该项内容所有工作及费用并满足设计图纸、规范等要求； | D78: m | E78: 15.982 | I78: =(F78+G78+H78)*$I$3 -> 0 | J78: =ROUND(SUM(F78:I78),2) -> 0 | K78: =ROUND(J78*E78,2) -> 0
A79: =1+N(A78) -> 4 | B79: 条形空调风口（150mm） | C79: 1.条形空调风口（150mm）； 2.风口周边阻燃板封边加固处理； 3.包含完成该项内容所有工作及费用并满足设计图纸、规范等要求； | D79: m | E79: =5.12*2 -> 10.24 | I79: =(F79+G79+H79)*$I$3 -> 0 | J79: =ROUND(SUM(F79:I79),2) -> 0 | K79: =ROUND(J79*E79,2) -> 0
A80: =1+N(A79) -> 5 | B80: 天花肌理无机涂料PT-01 | C80: 1.天花肌理无机涂料PT-01； 2.刮腻子二遍磨平； 3.底漆1遍，面漆2遍； 4.包含完成该项内容所有工作及费用并满足设计图纸、规范等要求； | D80: m2 | E80: 35.688 | I80: =(F80+G80+H80)*$I$3 -> 0 | J80: =ROUND(SUM(F80:I80),2) -> 0 | K80: =ROUND(J80*E80,2) -> 0
B81: 门窗、家具工程
A82: 四 | B82: 四单元合用前室
B83: 地面工程
A84: =1+N(A83) -> 1 | B84: 地面铺贴大理石ST-01 | C84: 1.地面20mm大理石ST-01、铺贴、厚度及样式按物料书为准； 2.10mm厚石材专用粘结剂； 3.70mm厚DS-M15干混砂浆找平； 4.基层清理、石材六面防护、背面刷胶封闭,同色云石胶补缝； 5.含开槽、磨边、倒角、拼接等处理； 6.包含完成该项内容所有工作及费用并满足设计图纸、规范等要求； | D84: m2 | E84: 3.966 | I84: =(F84+G84+H84)*$I$3 -> 0 | J84: =ROUND(SUM(F84:I84),2) -> 0 | K84: =ROUND(J84*E84,2) -> 0 | P84: 1
A85: =1+N(A84) -> 2 | B85: 地面铺贴大理石ST-01.02拼花 | C85: 1.地面20mm大理石拼花、参考3F-DF-01样式、ST-01、ST-02按物料书为准； 2.10mm厚石材专用粘结剂； 3.70mm厚DS-M15干混砂浆找平； 4.基层清理、石材六面防护、背面刷胶封闭,同色云石胶补缝； 5.含开槽、磨边、倒角、拼接等处理； 6.包含完成该项内容所有工作及费用并满足设计图纸、规范等要求； | D85: m2 | E85: 13.025 | I85: =(F85+G85+H85)*$I$3 -> 0 | J85: =ROUND(SUM(F85:I85),2) -> 0 | K85: =ROUND(J85*E85,2) -> 0 | P85: 1
A86: =1+N(A85) -> 3 | B86: 实心铜条5mm宽 | C86: 1.实心铜条5mm宽； 2.包含完成该项内容所有工作及费用并满足设计图纸、规范等要求； | D86: m | E86: 14.566 | I86: =(F86+G86+H86)*$I$3 -> 0 | J86: =ROUND(SUM(F86:I86),2) -> 0 | K86: =ROUND(J86*E86,2) -> 0
A87: =1+N(A86) -> 4 | B87: 地面石材晶面处理 | C87: 1.石材结晶处理(结晶水及石材保养剂,中性清洁剂)； 2.包含完成该项内容所有工作及费用并满足设计图纸、规范等要求； | D87: m2 | E87: =+E84+E85 -> 16.991 | I87: =(F87+G87+H87)*$I$3 -> 0 | J87: =ROUND(SUM(F87:I87),2) -> 0 | K87: =ROUND(J87*E87,2) -> 0
B88: 墙面工程
A89: =1+N(A88) -> 1 | B89: 墙面湿贴石材ST-05 | C89: 1、墙面湿贴石材ST-05 2、8mm厚石材专用胶粘剂WC粘结层 3、界面剂拉毛处理 4、石材的开槽、磨边、倒角、粘接、形成所需之凹坑、抛光、六面防污防渗等一切处理费用均在主材费中考虑，不再另行计取 5、包含完成该项内容所有工作及费用并满足设计图纸、规范等要求 | D89: m2 | E89: 5.319 | I89: =(F89+G89+H89)*$I$3 -> 0 | J89: =ROUND(SUM(F89:I89),2) -> 0 | K89: =ROUND(J89*E89,2) -> 0
A90: =1+N(A89) -> 2 | B90: 墙面干挂ST-05石材 | C90: 1、墙面干挂ST-05石材 2、不锈钢背栓挂件安装，云石胶+AB胶固定 3、镀锌角钢钢架(高度超4m、完成面超150mm采用槽钢基层加固)，钢架防锈处理 4、膨胀螺栓固定预埋铁件(轻质砖墙体需要穿墙螺栓固定) 5、石材的开槽、磨边、倒角、粘接、形成所需之凹坑、抛光、六面防污防渗等一切处理费用均在主材费中考虑，不再另行计取 6、包含完成该项内容所有工作及费用并满足设计图纸、规范等要求 | D90: m2 | E90: 25.262 | I90: =(F90+G90+H90)*$I$3 -> 0 | J90: =ROUND(SUM(F90:I90),2) -> 0 | K90: =ROUND(J90*E90,2) -> 0
A91: =1+N(A90) -> 3 | B91: WD-07摩素板 | C91: 1、墙面WD-08摩素板(结构胶固定) 2、12厘玻镁板基层 3、膨胀螺栓、轻钢龙骨(钢结构)基层找平 4、包含完成该项内容所有工作及费用并满足设计图纸、规范等要求 | D91: m2 | E91: 2.091 | I91: =(F91+G91+H91)*$I$3 -> 0 | J91: =ROUND(SUM(F91:I91),2) -> 0 | K91: =ROUND(J91*E91,2) -> 0
A92: =1+N(A91) -> 4 | B92: 电梯不锈钢门套 | C92: 1、1.2mm厚 MT-01古铜不锈钢门套，结构胶固定 2、9厘玻镁板基层 3、工程量以展开面积计算 4、包含完成该项内容所有工作及费用并满足设计图纸、规范等要求 | D92: m2 | E92: =0.34*2.75*2*2 -> 3.74 | I92: =(F92+G92+H92)*$I$3 -> 0 | J92: =ROUND(SUM(F92:I92),2) -> 0 | K92: =ROUND(J92*E92,2) -> 0
A93: =1+N(A92) -> 5 | B93: 电梯不锈钢门头 | C93: 1、1.2mm厚 MT-01古铜不锈钢门头，结构胶固定 2、12mm阻燃板，轻钢副龙骨@400 3、电梯门顶内置亚克力，内部面层刮白处理 4、工程量以展开面积计算 5、包含完成该项内容所有工作及费用并满足设计图纸、规范等要求 | D93: m2 | E93: =+(0.061+0.475+0.114+0.074)*0.95*2 -> 1.3756 | I93: =(F93+G93+H93)*$I$3 -> 0 | J93: =ROUND(SUM(F93:I93),2) -> 0 | K93: =ROUND(J93*E93,2) -> 0
A94: =1+N(A93) -> 6 | B94: MT-01古铜不锈钢饰面（电梯按钮处） | C94: 1、1.2mm厚 MT-01古铜不锈钢饰面 2、12mm阻燃板基层，轻钢副龙骨@400 3、工程量以展开面积计算 4、包含完成该项内容所有工作及费用并满足设计图纸、规范等要求 | D94: m2 | E94: 0.253 | I94: =(F94+G94+H94)*$I$3 -> 0 | J94: =ROUND(SUM(F94:I94),2) -> 0 | K94: =ROUND(J94*E94,2) -> 0
A95: =1+N(A94) -> 7 | B95: MT-01古铜不锈钢踢脚线（高20mm） | C95: 1、1.2mm厚 MT-01古铜不锈钢踢脚线（高20mm，展开面为46mm），结构胶固定 2、9厘玻镁板基层 3、包含完成该项内容所有工作及费用并满足设计图纸、规范等要求 | D95: m | E95: 11.965 | I95: =(F95+G95+H95)*$I$3 -> 0 | J95: =ROUND(SUM(F95:I95),2) -> 0 | K95: =ROUND(J95*E95,2) -> 0
A96: =1+N(A95) -> 8 | B96: MT-01古铜不锈钢线条（展开面为114mm） | C96: 1、1.2mm厚 MT-01古铜不锈钢线条（展开面为114mm），结构胶固定 2、9厘玻镁板基层 3、包含完成该项内容所有工作及费用并满足设计图纸、规范等要求 | D96: m | E96: 9.414 | I96: =(F96+G96+H96)*$I$3 -> 0 | J96: =ROUND(SUM(F96:I96),2) -> 0 | K96: =ROUND(J96*E96,2) -> 0
A97: =1+N(A96) -> 9 | B97: MT-01古铜不锈钢顶部收口条（展开面为41mm） | C97: 1、1.2mm厚 MT-01古铜不锈钢顶部收口条（展开面为41mm），结构胶固定 2、9厘玻镁板基层 3、包含完成该项内容所有工作及费用并满足设计图纸、规范等要求 | D97: m | E97: 12.798 | I97: =(F97+G97+H97)*$I$3 -> 0 | J97: =ROUND(SUM(F97:I97),2) -> 0 | K97: =ROUND(J97*E97,2) -> 0
B98: 天花工程
A99: =1+N(A98) -> 1 | B99: 石膏板吊顶 | C99: 1.60系列轻钢主龙骨@900，60系列轻钢副龙骨@400，60系列横撑龙骨@600，08螺纹吊杆@900不上人天花吊顶（投影面计算） 2.玻镁板、双层9.5厚石膏板基层，含开孔、检修口、10*10凹槽等费用； 3.含除灯槽外的侧面高差及其连接件、吊件； 4.包含完成该项内容所有工作及费用并满足设计图纸、规范等要求； | D99: m2 | E99: 17.814 | I99: =(F99+G99+H99)*$I$3 -> 0 | J99: =ROUND(SUM(F99:I99),2) -> 0 | K99: =ROUND(J99*E99,2) -> 0
A100: =1+N(A99) -> 2 | B100: 灯槽（100mm*250mm） | C100: 1.灯槽（100mm*250mm）； 2.双层板：9mm玻镁板、9.5厚石膏板； 3.包含完成该项内容所有工作及费用并满足设计图纸、规范等要求； | D100: m | E100: 14.582 | I100: =(F100+G100+H100)*$I$3 -> 0 | J100: =ROUND(SUM(F100:I100),2) -> 0 | K100: =ROUND(J100*E100,2) -> 0
A101: =1+N(A100) -> 3 | B101: 成品石膏线条 | C101: 1.成品石膏线条（50mm*50mm）； 2.按图纸造型； 3.包含完成该项内容所有工作及费用并满足设计图纸、规范等要求； | D101: m | E101: 14.582 | I101: =(F101+G101+H101)*$I$3 -> 0 | J101: =ROUND(SUM(F101:I101),2) -> 0 | K101: =ROUND(J101*E101,2) -> 0
...

Sheet 会所安装工程量清单
A1: 工程清单与计价表
A2: 序号 | B2: 项目名称 | C2: 项目特征描述 | D2: 计量 单位 | E2: 工程量 | F2: 人工 | G2: 主材 | H2: 辅材及机械费 | I2: 管理费、利润及规费 | J2: 不含税综合单价 （元） | K2: 不含税合价（元） | L2: 备注
B4: 电气工程 | K4: =+K5+K75+K79+K83 -> 0
B5: （1）会所 | K5: =SUM(K6:K74) -> 0
A6: =A5+1 -> 1 | B6: D13m 可调深藏射灯 | C6: 1.名称:D13m 可调深藏射灯 2.规格：功率：9W、流明量：756lm；63lm/W、色温：3500K、光速角：24° 3.其他:包含完成该项内容所有工作及费用并满足设计图纸、规范等要求 | D6: 套 | E6: 17 | I6: =(F6+G6+H6)*$I$3 -> 0 | J6: =F6+G6+H6+I6 -> 0 | K6: =ROUND(E6*J6,2) -> 0
A7: =A6+1 -> 2 | B7: D13f 可调深藏射灯 | C7: 1.名称:D13f 可调深藏射灯 2.规格：功率：9W、流明量：594lm；63lm/W、色温：3500K、光速角：36° 3.其他:包含完成该项内容所有工作及费用并满足设计图纸、规范等要求 | D7: 套 | E7: 124 | I7: =(F7+G7+H7)*$I$3 -> 0 | J7: =F7+G7+H7+I7 -> 0 | K7: =ROUND(E7*J7,2) -> 0
A8: =A7+1 -> 3 | B8: D14m 可调深藏射灯 | C8: 1.名称:D14m 可调深藏射灯 2.规格：功率：12W、流明量：756lm；63lm/W、色温：3500K、光速角：24° 3.其他:包含完成该项内容所有工作及费用并满足设计图纸、规范等要求 | D8: 套 | E8: 26 | I8: =(F8+G8+H8)*$I$3 -> 0 | J8: =F8+G8+H8+I8 -> 0 | K8: =ROUND(E8*J8,2) -> 0
A9: =A8+1 -> 4 | B9: D14f 可调深藏射灯 | C9: 1.名称:D14f 可调深藏射灯 2.规格：功率：12W、流明量：792lm；66lm/W、色温：3500K、光速角：36° 3.其他:包含完成该项内容所有工作及费用并满足设计图纸、规范等要求 | D9: 套 | E9: 104 | I9: =(F9+G9+H9)*$I$3 -> 0 | J9: =F9+G9+H9+I9 -> 0 | K9: =ROUND(E9*J9,2) -> 0
A10: =A9+1 -> 5 | B10: D15m 可调深藏射灯 | C10: 1.名称:D15m 可调深藏射灯 2.规格：功率：15W、流明量：951lm；65lm/W、色温：3500K、光速角：24° 3.其他:包含完成该项内容所有工作及费用并满足设计图纸、规范等要求 | D10: 套 | E10: 9 | I10: =(F10+G10+H10)*$I$3 -> 0 | J10: =F10+G10+H10+I10 -> 0 | K10: =ROUND(E10*J10,2) -> 0
A11: =A10+1 -> 6 | B11: D15f 可调深藏射灯 | C11: 1.名称:D15f 可调深藏射灯 2.规格：功率：15W、流明量：970lm；67lm/W、色温：3500K、光速角：36° 3.其他:包含完成该项内容所有工作及费用并满足设计图纸、规范等要求 | D11: 套 | E11: 96 | I11: =(F11+G11+H11)*$I$3 -> 0 | J11: =F11+G11+H11+I11 -> 0 | K11: =ROUND(E11*J11,2) -> 0
A12: =A11+1 -> 7 | B12: D17m 可调深藏射灯 | C12: 1.名称:D17m 可调深藏射灯 2.规格：功率：24W、流明量：1802lm；77lm/W、色温：3500K、光速角：24° 3.其他:包含完成该项内容所有工作及费用并满足设计图纸、规范等要求 | D12: 套 | E12: 24 | I12: =(F12+G12+H12)*$I$3 -> 0 | J12: =F12+G12+H12+I12 -> 0 | K12: =ROUND(E12*J12,2) -> 0
A13: =A12+1 -> 8 | B13: Gs15f 方形下照深藏射灯 | C13: 1.名称:Gs15f 方形下照深藏射灯 2.规格：功率：9W、流明量：603lm；67lm/W、色温：3500K、光速角：36° 3.其他:包含完成该项内容所有工作及费用并满足设计图纸、规范等要求 | D13: 套 | E13: 12 | I13: =(F13+G13+H13)*$I$3 -> 0 | J13: =F13+G13+H13+I13 -> 0 | K13: =ROUND(E13*J13,2) -> 0
A14: =A13+1 -> 9 | B14: Mr15n 下照迷你格栅灯 | C14: 1.名称:Mr15n 下照迷你格栅灯 2.规格：功率：10*2W、流明量：1400lm；70lm/W、色温：3500K、光速角：15° 3.其他:包含完成该项内容所有工作及费用并满足设计图纸、规范等要求 | D14: 套 | E14: 6 | I14: =(F14+G14+H14)*$I$3 -> 0 | J14: =F14+G14+H14+I14 -> 0 | K14: =ROUND(E14*J14,2) -> 0
A15: =A14+1 -> 10 | B15: Mr15m 下照迷你格栅灯 | C15: 1.名称:Mr15m 下照迷你格栅灯 2.规格：功率：10*2W、流明量：1360lm；68lm/W、色温：3500K、光速角：24° 3.其他:包含完成该项内容所有工作及费用并满足设计图纸、规范等要求 | D15: 套 | E15: 8 | I15: =(F15+G15+H15)*$I$3 -> 0 | J15: =F15+G15+H15+I15 -> 0 | K15: =ROUND(E15*J15,2) -> 0
A16: =A15+1 -> 11 | B16: Mr15f 下照迷你格栅灯 | C16: 1.名称:Mr15f 下照迷你格栅灯 2.规格：功率：10*2W、流明量：1360lm；68lm/W、色温：3500K、光速角：36° 3.其他:包含完成该项内容所有工作及费用并满足设计图纸、规范等要求 | D16: 套 | E16: 6 | I16: =(F16+G16+H16)*$I$3 -> 0 | J16: =F16+G16+H16+I16 -> 0 | K16: =ROUND(E16*J16,2) -> 0
A17: =A16+1 -> 12 | B17: Md15m 可调迷你格栅灯 | C17: 1.名称:Md15m 可调迷你格栅灯 2.规格：功率：10*2W、流明量：1360lm；68lm/W、色温：3500K、光速角：36° 3.其他:包含完成该项内容所有工作及费用并满足设计图纸、规范等要求 | D17: 套 | E17: 25 | I17: =(F17+G17+H17)*$I$3 -> 0 | J17: =F17+G17+H17+I17 -> 0 | K17: =ROUND(E17*J17,2) -> 0
... A74: =A73+1 -> 69 | B74: 自助售卖机 | C74: 1.名称：自助售卖机 2.规格：750*780*1830 3.包含完成该项内容所有工作及费用并满足设计图纸、规范等要求 | D74: 个 | E74: 2 | I74: =(F74+G74+H74)*$I$3 -> 0 | J74: =F74+G74+H74+I74 -> 0 | K74: =ROUND(E74*J74,2) -> 0
B75: （2）标准层电梯厅 | K75: =SUM(K76:K78) -> 0
A76: =A75+1 -> 1 | B76: D13f 可调深藏射灯 | C76: 1.名称:D13f 可调深藏射灯 2.规格：功率：9W、流明量：594lm；63lm/W、色温：3500K、光速角：36° 3.其他:包含完成该项内容所有工作及费用并满足设计图纸、规范等要求 | D76: 套 | E76: 21 | I76: =(F76+G76+H76)*$I$3 -> 0 | J76: =F76+G76+H76+I76 -> 0 | K76: =ROUND(E76*J76,2) -> 0
A77: =A76+1 -> 2 | B77: Rm10 LED透光模组灯 | C77: 1.名称:Rm10 LED透光模组灯 2.规格：功率：80W、流明量：5500lm；80lm/W、色温：3500K、光速角：170° 3.含外置电源驱动 4.其他:包含完成该项内容所有工作及费用并满足设计图纸、规范等要求 | D77: m | E77: 13.6 | I77: =(F77+G77+H77)*$I$3 -> 0 | J77: =F77+G77+H77+I77 -> 0 | K77: =ROUND(E77*J77,2) -> 0
A78: =A77+1 -> 3 | B78: Lc12-LED侧弯灯带 | C78: 1.名称:Lc12-LED侧弯灯带 2.规格：功率：14W/M、流明量：1260lm/M；90lm/W、色温：3500K、光速角：120° 3.含外置电源驱动 4.其他:包含完成该项内容所有工作及费用并满足设计图纸、规范等要求 | D78: m | E78: 36.295 | I78: =(F78+G78+H78)*$I$3 -> 0 | J78: =F78+G78+H78+I78 -> 0 | K78: =ROUND(E78*J78,2) -> 0
B79: （3）地下室大堂 | K79: =SUM(K80:K82) -> 0
A80: =A79+1 -> 1 | B80: D13f 可调深藏射灯 | C80: 1.名称:D13f 可调深藏射灯 2.规格：功率：9W、流明量：594lm；63lm/W、色温：3500K、光速角：36° 3.其他:包含完成该项内容所有工作及费用并满足设计图纸、规范等要求 | D80: 套 | E80: 78 | I80: =(F80+G80+H80)*$I$3 -> 0 | J80: =F80+G80+H80+I80 -> 0 | K80: =ROUND(E80*J80,2) -> 0
A81: =A80+1 -> 2 | B81: Rm10 LED透光模组灯 | C81: 1.名称:Rm10 LED透光模组灯 2.规格：功率：80W、流明量：5500lm；80lm/W、色温：3500K、光速角：170° 3.含外置电源驱动 4.其他:包含完成该项内容所有工作及费用并满足设计图纸、规范等要求 | D81: m | E81: 40.8 | I81: =(F81+G81+H81)*$I$3 -> 0 | J81: =F81+G81+H81+I81 -> 0 | K81: =ROUND(E81*J81,2) -> 0
A82: =A81+1 -> 3 | B82: Lc12-LED侧弯灯带 | C82: 1.名称:Lc12-LED侧弯灯带 2.规格：功率：14W/M、流明量：1260lm/M；90lm/W、色温：3500K、光速角：120° 3.含外置电源驱动 4.其他:包含完成该项内容所有工作及费用并满足设计图纸、规范等要求 | D82: m | E82: 184.32 | I82: =(F82+G82+H82)*$I$3 -> 0 | J82: =F82+G82+H82+I82 -> 0 | K82: =ROUND(E82*J82,2) -> 0
B83: （4）电梯轿厢 | K83: =SUM(K84:K86) -> 0
A84: =A83+1 -> 1 | B84: Mr15m 下照迷你格栅灯 | C84: 1.名称:Mr15m 下照迷你格栅灯 2.规格：功率：10*2W、流明量：1360lm；68lm/W、色温：3500K、光速角：24° 3.其他:包含完成该项内容所有工作及费用并满足设计图纸、规范等要求 | D84: 套 | E84: 2 | I84: =(F84+G84+H84)*$I$3 -> 0 | J84: =F84+G84+H84+I84 -> 0 | K84: =ROUND(E84*J84,2) -> 0
A85: =A84+1 -> 2 | B85: Ls12-LED硬灯条 | C85: 1.名称:Ls12-LED硬灯条 2.规格：功率：14W/M、流明量：1260lm/M；90lm/W、色温：3500K、光速角：120° 3.含外置电源驱动 4.其他:包含完成该项内容所有工作及费用并满足设计图纸、规范等要求 | D85: m | E85: 6.98 | I85: =(F85+G85+H85)*$I$3 -> 0 | J85: =F85+G85+H85+I85 -> 0 | K85: =ROUND(E85*J85,2) -> 0
A86: =A85+1 -> 3 | B86: Lc12-LED侧弯灯带 | C86: 1.名称:Lc12-LED侧弯灯带 2.规格：功率：14W/M、流明量：1260lm/M；90lm/W、色温：3500K、光速角：120° 3.含外置电源驱动 4.其他:包含完成该项内容所有工作及费用并满足设计图纸、规范等要求 | D86: m | E86: 4.78 | I86: =(F86+G86+H86)*$I$3 -> 0 | J86: =F86+G86+H86+I86 -> 0 | K86: =ROUND(E86*J86,2) -> 0
B87: 给排水工程 | K87: =SUM(K88:K111) -> 0
A88: 1 | B88: 厨用单盆水槽 | C88: 1.名称：厨用单盆水槽 2.水槽安装 3.包含完成该项内容所有工作及费用并满足设计图纸、规范等要求 | D88: 个 | E88: 3 | I88: =(F88+G88+H88)*$I$3 -> 0 | J88: =F88+G88+H88+I88 -> 0 | K88: =ROUND(E88*J88,2) -> 0
A89: =A88+1 -> 2 | B89: 厨用龙头 | C89: 1.名称：厨用龙头 2.龙头安装，包括角阀、不锈钢软管、下水管等所需材料 3.包含完成该项内容所有工作及费用并满足设计图纸、规范等要求 | D89: 个 | E89: 3 | I89: =(F89+G89+H89)*$I$3 -> 0 | J89: =F89+G89+H89+I89 -> 0 | K89: =ROUND(E89*J89,2) -> 0
A90: =A89+1 -> 3 | B90: 台下盆 | C90: 1.名称：台下盆 2.台盆安装 3.包含完成该项内容所有工作及费用并满足设计图纸、规范等要求 | D90: 个 | E90: 2 | I90: =(F90+G90+H90)*$I$3 -> 0 | J90: =F90+G90+H90+I90 -> 0 | K90: =ROUND(E90*J90,2) -> 0 | M90: 1
A91: =A90+1 -> 4 | B91: 台盆龙头 | C91: 1.名称：台盆龙头 2.台盆龙头安装，包括角阀、不锈钢软管、下水管等所需材料 3.包含完成该项内容所有工作及费用并满足设计图纸、规范等要求 | D91: 个 | E91: =+E90+E99 -> 6 | I91: =(F91+G91+H91)*$I$3 -> 0 | J91: =F91+G91+H91+I91 -> 0 | K91: =ROUND(E91*J91,2) -> 0
A92: =A91+1 -> 5 | B92: 智能马桶 | C92: 1.名称：智能马桶 2.智能马桶安装，包括角阀、不锈钢软管、马桶橡胶圈等所需材料 3.包含完成该项内容所有工作及费用并满足设计图纸、规范等要求 | D92: 个 | E92: 7 | I92: =(F92+G92+H92)*$I$3 -> 0 | J92: =F92+G92+H92+I92 -> 0 | K92: =ROUND(E92*J92,2) -> 0
A93: =A92+1 -> 6 | B93: 连体蹲便器 | C93: 1.名称：连体蹲便器 2.蹲便器、水箱安装，包括角阀、不锈钢软管、等所需材料 3.包含完成该项内容所有工作及费用并满足设计图纸、规范等要求 | D93: 个 | E93: 1 | I93: =(F93+G93+H93)*$I$3 -> 0 | J93: =F93+G93+H93+I93 -> 0 | K93: =ROUND(E93*J93,2) -> 0
A94: =A93+1 -> 7 | B94: 感应一体挂式小便器 | C94: 1.名称：感应一体挂式小便器 2.小便器、感应开关安装及其他一切等所需材料 3.包含完成该项内容所有工作及费用并满足设计图纸、规范等要求 | D94: 个 | E94: 4 | I94: =(F94+G94+H94)*$I$3 -> 0 | J94: =F94+G94+H94+I94 -> 0 | K94: =ROUND(E94*J94,2) -> 0
A95: =A94+1 -> 8 | B95: 拖把池 | C95: 1.名称：拖把池 2.拖把池安装 3.包含完成该项内容所有工作及费用并满足设计图纸、规范等要求 | D95: 个 | E95: 1 | I95: =(F95+G95+H95)*$I$3 -> 0 | J95: =F95+G95+H95+I95 -> 0 | K95: =ROUND(E95*J95,2) -> 0
A96: =A95+1 -> 9 | B96: 用水咀龙头 | C96: 1.名称：用水咀龙头 2.拖把池安装 3.包含完成该项内容所有工作及费用并满足设计图纸、规范等要求 | D96: 个 | E96: 2 | I96: =(F96+G96+H96)*$I$3 -> 0 | J96: =F96+G96+H96+I96 -> 0 | K96: =ROUND(E96*J96,2) -> 0
A97: =A96+1 -> 10 | B97: 淋浴器 | C97: 1.名称：淋浴器 2.淋浴器安装 3.包含完成该项内容所有工作及费用并满足设计图纸、规范等要求 | D97: 套 | E97: 4 | I97: =(F97+G97+H97)*$I$3 -> 0 | J97: =F97+G97+H97+I97 -> 0 | K97: =ROUND(E97*J97,2) -> 0
A98: =A97+1 -> 11 | B98: 地漏 | C98: 1.名称：地漏 2.地漏安装 3.包含完成该项内容所有工作及费用并满足设计图纸、规范等要求 | D98: 个 | E98: 14 | I98: =(F98+G98+H98)*$I$3 -> 0 | J98: =F98+G98+H98+I98 -> 0 | K98: =ROUND(E98*J98,2) -> 0
A99: =A97+1 -> 11 | B99: 三层会所卫生间台下盆 | C99: 1.名称：三层会所卫生间台下盆 2.台盆安装 3.包含完成该项内容所有工作及费用并满足设计图纸、规范等要求 | D99: 个 | E99: 4 | I99: =(F99+G99+H99)*$I$3 -> 0 | J99: =F99+G99+H99+I99 -> 0 | K99: =ROUND(E99*J99,2) -> 0
A100: =A99+1 -> 12 | B100: 冷水管PPR-DN15 | C100: 1.安装部位：室内 2.规格：DN15 3.材质：冷水用PPR(S4系列） 4.连接形式：热熔连接 5.压力试验及吹、洗设计要求：管道冲洗、消毒 | D100: m | E100: 172.166 | I100: =(F100+G100+H100)*$I$3 -> 0 | J100: =F100+G100+H100+I100 -> 0 | K100: =ROUND(E100*J100,2) -> 0
A101: =A100+1 -> 13 | B101: 冷水管PPR-DN20 | C101: 1.安装部位：室内 2.规格：DN20 3.材质：冷水用PPR(S4系列） 4.连接形式：热熔连接 5.压力试验及吹、洗设计要求：管道冲洗、消毒 | D101: m | E101: 9.865 | I101: =(F101+G101+H101)*$I$3 -> 0 | J101: =F101+G101+H101+I101 -> 0 | K101: =ROUND(E101*J101,2) -> 0
A102: =A101+1 -> 14 | B102: 冷水管PPR-DN25 | C102: 1.安装部位：室内 2.规格：DN25 3.材质：冷水用PPR(S4系列） 4.连接形式：热熔连接 5.压力试验及吹、洗设计要求：管道冲洗、消毒 | D102: m | E102: 23.265 | I102: =(F102+G102+H102)*$I$3 -> 0 | J102: =F102+G102+H102+I102 -> 0 | K102: =ROUND(E102*J102,2) -> 0
A103: =A102+1 -> 15 | B103: 冷水管PPR-DN32 | C103: 1.安装部位：室内 2.规格：DN32 3.材质：冷水用PPR(S4系列） 4.连接形式：热熔连接 5.压力试验及吹、洗设计要求：管道冲洗、消毒 | D103: m | E103: 20.711 | I103: =(F103+G103+H103)*$I$3 -> 0 | J103: =F103+G103+H103+I103 -> 0 | K103: =ROUND(E103*J103,2) -> 0
A104: =A103+1 -> 16 | B104: 冷水管PPR-DN50 | C104: 1.安装部位：室内 2.规格：DN50 3.材质：冷水用PPR(S4系列） 4.连接形式：热熔连接 5.压力试验及吹、洗设计要求：管道冲洗、消毒 | D104: m | E104: 12.595 | I104: =(F104+G104+H104)*$I$3 -> 0 | J104: =F104+G104+H104+I104 -> 0 | K104: =ROUND(E104*J104,2) -> 0
A105: =A104+1 -> 17 | B105: 热水管PPR-DN15 | C105: 1.安装部位：室内 2.规格：DN15 3.材质：热水用PPR(S3.2系列） 4.连接形式：热熔连接 5.压力试验及吹、洗设计要求：管道冲洗、消毒 | D105: m | E105: 59.619 | I105: =(F105+G105+H105)*$I$3 -> 0 | J105: =F105+G105+H105+I105 -> 0 | K105: =ROUND(E105*J105,2) -> 0
A106: =A105+1 -> 18 | B106: 热水管PPR-DN20 | C106: 1.安装部位：室内 2.规格：DN20 3.材质：热水用PPR(S3.2系列） 4.连接形式：热熔连接 5.压力试验及吹、洗设计要求：管道冲洗、消毒 | D106: m | E106: 11.64 | I106: =(F106+G106+H106)*$I$3 -> 0 | J106: =F106+G106+H106+I106 -> 0 | K106: =ROUND(E106*J106,2) -> 0
A107: =A106+1 -> 19 | B107: 热水管PPR-DN25 | C107: 1.安装部位：室内 2.规格：DN25 3.材质：热水用PPR(S3.2系列） 4.连接形式：热熔连接 5.压力试验及吹、洗设计要求：管道冲洗、消毒 | D107: m | E107: 48.66 | I107: =(F107+G107+H107)*$I$3 -> 0 | J107: =F107+G107+H107+I107 -> 0 | K107: =ROUND(E107*J107,2) -> 0
A108: =A107+1 -> 20 | B108: UPVC排水管-DN50 | C108: 1.安装部位：室内 2.规格：DN50 3.材质：UPVC排水管 4.连接形式:粘接连接 | D108: m | E108: 42.534 | I108: =(F108+G108+H108)*$I$3 -> 0 | J108: =F108+G108+H108+I108 -> 0 | K108: =ROUND(E108*J108,2) -> 0
A109: =A108+1 -> 21 | B109: UPVC排水管-DN75 | C109: 1.安装部位：室内 2.规格：DN75 3.材质：UPVC排水管 5.连接形式:粘接连接 | D109: m | E109: 13.509 | I109: =(F109+G109+H109)*$I$3 -> 0 | J109: =F109+G109+H109+I109 -> 0 | K109: =ROUND(E109*J109,2) -> 0
A110: =A109+1 -> 22 | B110: UPVC排水管-DN100 | C110: 1.安装部位：室内 2.规格：DN100 3.材质：UPVC排水管 6.连接形式:粘接连接 | D110: m | E110: 121.478 | I110: =(F110+G110+H110)*$I$3 -> 0 | J110: =F110+G110+H110+I110 -> 0 | K110: =ROUND(E110*J110,2) -> 0
A111: =A110+1 -> 23 | B111: 闸阀 DN50 | C111: 1.名称：闸阀 2.规格：DN50 3.材质：铸铁 6.连接形式:螺纹连接 | D111: 个 | E111: 1 | I111: =(F111+G111+H111)*$I$3 -> 0 | J111: =F111+G111+H111+I111 -> 0 | K111: =ROUND(E111*J111,2) -> 0
B112: 消防工程 | K112: =+K113+K123 -> 0
B113: （1）消防水工程 | K113: =SUM(K114:K122) -> 0
A114: =A113+1 -> 1 | B114: 喷淋头 | C114: 1．名称：喷淋头 2.规格：DN15 3.其他 | D114: 个 | E114: 614 | I114: =(F114+G114+H114)*$I$3 -> 0 | J114: =F114+G114+H114+I114 -> 0 | K114: =ROUND(E114*J114,2) -> 0
A115: =A114+1 -> 2 | B115: 热浸镀锌钢管 DN25 | C115: 1．安装部位：室内 2．材质、规格：热镀锌钢管DN25 3．连接形式：螺纹连接 4．钢管镀锌设计要求：内外热镀锌 5．压力试验及冲洗设计要求：水压试验，水冲洗 | D115: m | E115: 428.939 | I115: =(F115+G115+H115)*$I$3 -> 0 | J115: =F115+G115+H115+I115 -> 0 | K115: =ROUND(E115*J115,2) -> 0
A116: =A115+1 -> 3 | B116: 热浸镀锌钢管 DN32 | C116: 1．安装部位：室内 2．材质、规格：热镀锌钢管DN32 3．连接形式：螺纹连接 4．钢管镀锌设计要求：内外热镀锌 5．压力试验及冲洗设计要求：水压试验，水冲洗 | D116: m | E116: 200.256 | I116: =(F116+G116+H116)*$I$3 -> 0 | J116: =F116+G116+H116+I116 -> 0 | K116: =ROUND(E116*J116,2) -> 0
A117: =A116+1 -> 4 | B117: 热浸镀锌钢管 DN40 | C117: 1．安装部位：室内 2．材质、规格：热镀锌钢管DN40 3．连接形式：螺纹连接 4．钢管镀锌设计要求：内外热镀锌 5．压力试验及冲洗设计要求：水压试验，水冲洗 | D117: m | E117: 47.745 | I117: =(F117+G117+H117)*$I$3 -> 0 | J117: =F117+G117+H117+I117 -> 0 | K117: =ROUND(E117*J117,2) -> 0
A118: =A117+1 -> 5 | B118: 热浸镀锌钢管 DN50 | C118: 1．安装部位：室内 2．材质、规格：热镀锌钢管DN50 3．连接形式：螺纹连接 4．钢管镀锌设计要求：内外热镀锌 5．压力试验及冲洗设计要求：水压试验，水冲洗 | D118: m | E118: 84.006 | I118: =(F118+G118+H118)*$I$3 -> 0 | J118: =F118+G118+H118+I118 -> 0 | K118: =ROUND(E118*J118,2) -> 0
A119: =A118+1 -> 6 | B119: 热浸镀锌钢管 DN65 | C119: 1．安装部位：室内 2．材质、规格：热镀锌钢管DN65 3．连接形式：螺纹连接 4．钢管镀锌设计要求：内外热镀锌 5．压力试验及冲洗设计要求：水压试验，水冲洗 | D119: m | E119: 19.44 | I119: =(F119+G119+H119)*$I$3 -> 0 | J119: =F119+G119+H119+I119 -> 0 | K119: =ROUND(E119*J119,2) -> 0
A120: =A119+1 -> 7 | B120: 热浸镀锌钢管 DN80 | C120: 1．安装部位：室内 2．材质、规格：热镀锌钢管D80 3．连接形式：螺纹连接 4．钢管镀锌设计要求：内外热镀锌 5．压力试验及冲洗设计要求：水压试验，水冲洗 | D120: m | E120: 81.91 | I120: =(F120+G120+H120)*$I$3 -> 0 | J120: =F120+G120+H120+I120 -> 0 | K120: =ROUND(E120*J120,2) -> 0
A121: =A120+1 -> 8 | B121: 热浸镀锌钢管 DN100 | C121: 1．安装部位：室内 2．材质、规格：热镀锌钢管DN100 3．连接形式：螺纹连接 4．钢管镀锌设计要求：内外热镀锌 5．压力试验及冲洗设计要求：水压试验，水冲洗 | D121: m | E121: 33.003 | I121: =(F121+G121+H121)*$I$3 -> 0 | J121: =F121+G121+H121+I121 -> 0 | K121: =ROUND(E121*J121,2) -> 0
A122: =A121+1 -> 9 | B122: 热浸镀锌钢管 DN150 | C122: 1．安装部位：室内 2．材质、规格：热镀锌钢管DN150 3．连接形式：螺纹连接 4．钢管镀锌设计要求：内外热镀锌 5．压力试验及冲洗设计要求：水压试验，水冲洗 | D122: m | E122: 85.384 | I122: =(F122+G122+H122)*$I$3 -> 0 | J122: =F122+G122+H122+I122 -> 0 | K122: =ROUND(E122*J122,2) -> 0
B123: （2）消防电工程 | K123: =SUM(K124:K134) -> 0
A124: =A123+1 -> 1 | B124: 感烟火灾探测器 | C124: 1.名称：感烟探测器 2.安装：吸顶安装 | D124: 个 | E124: 95 | I124: =(F124+G124+H124)*$I$3 -> 0 | J124: =F124+G124+H124+I124 -> 0 | K124: =ROUND(E124*J124,2) -> 0
A125: =A124+1 -> 2 | B125: 火灾应急广播扬声器 | C125: 1.名称：火灾应急广播扬声器 2.包含完成该项内容所有工作及费用并满足设计图纸、规范等要求 | D125: 个 | E125: 21 | I125: =(F125+G125+H125)*$I$3 -> 0 | J125: =F125+G125+H125+I125 -> 0 | K125: =ROUND(E125*J125,2) -> 0
A126: =A125+1 -> 3 | B126: 火灾声光报警器 | C126: 1.名称：声光报警器 2.包含完成该项内容所有工作及费用并满足设计图纸、规范等要求 | D126: 个 | E126: 11 | I126: =(F126+G126+H126)*$I$3 -> 0 | J126: =F126+G126+H126+I126 -> 0 | K126: =ROUND(E126*J126,2) -> 0
A127: =A126+1 -> 4 | B127: 手动火灾报警按钮（带消防电话插孔） | C127: 1.名称：带电话插孔手动报警按钮 2.安装：壁装 3.类型：智能型 4.包含完成该项内容所有工作及费用并满足设计图纸、规范等要求 | D127: 个 | E127: 11 | I127: =(F127+G127+H127)*$I$3 -> 0 | J127: =F127+G127+H127+I127 -> 0 | K127: =ROUND(E127*J127,2) -> 0
A128: =A127+1 -> 5 | B128: 智能型消火栓箱按钮 | C128: 1.名称：消火栓按钮 2.安装：消火栓箱内安装 3.类型：智能型 | D128: 个 | E128: 14 | I128: =(F128+G128+H128)*$I$3 -> 0 | J128: =F128+G128+H128+I128 -> 0 | K128: =ROUND(E128*J128,2) -> 0
A129: =A128+1 -> 6 | B129: 火灾显示盘 | C129: 1.名称：火灾显示盘 2.包含完成该项内容所有工作及费用并满足设计图纸、规范等要求 | D129: 个 | E129: 1 | I129: =(F129+G129+H129)*$I$3 -> 0 | J129: =F129+G129+H129+I129 -> 0 | K129: =ROUND(E129*J129,2) -> 0
A130: =A129+1 -> 7 | B130: 区域型火灾报警控制器 | C130: 1.名称：区域型火灾报警控制器 2.包含完成该项内容所有工作及费用并满足设计图纸、规范等要求 | D130: 个 | E130: 2 | I130: =(F130+G130+H130)*$I$3 -> 0 | J130: =F130+G130+H130+I130 -> 0 | K130: =ROUND(E130*J130,2) -> 0
A131: =A130+1 -> 8 | B131: 消防应急广播线WDZN-RYS-B2-2X2.5mm2 | C131: 1.名称：消防应急广播线 2.型号、规格：WDZN-RYS-B2-2X2.5mm2 3.配线部位：管内敷设 | D131: m | E131: 548.815 | I131: =(F131+G131+H131)*$I$3 -> 0 | J131: =F131+G131+H131+I131 -> 0 | K131: =ROUND(E131*J131,2) -> 0
A132: =A131+1 -> 9 | B132: 报警信号二线WDZN-RYS-B2-2X2.5mm2 | C132: 1.名称：报警信号总线 2.型号、规格：WDZN-RYS-B2-2X2.5mm2 3.配线部位：管内敷设 | D132: m | E132: 1321.028 | I132: =(F132+G132+H132)*$I$3 -> 0 | J132: =F132+G132+H132+I132 -> 0 | K132: =ROUND(E132*J132,2) -> 0
A133: =A132+1 -> 10 | B133: 消防专用电话线WDZN-RYSP-B2-2X2.5mm2 | C133: 1.名称：消防专用电话线 2.型号、规格：WDZN-RYSP-B2-2X2.5mm2 3.配线部位：管内敷设 | D133: m | E133: 402.963 | I133: =(F133+G133+H133)*$I$3 -> 0 | J133: =F133+G133+H133+I133 -> 0 | K133: =ROUND(E133*J133,2) -> 0
A134: =A133+1 -> 11 | B134: 配管JDG20 | C134: 1.名称：电线保护管 2.材质： 3.规格：JDG20 | D134: m | E134: 1092.403 | I134: =(F134+G134+H134)*$I$3 -> 0 | J134: =F134+G134+H134+I134 -> 0 | K134: =ROUND(E134*J134,2) -> 0
B135: 空调工程 | K135: =+K136+K159+K176+K196+K209 -> 0
B136: （1）空调风工程 | K136: =SUM(K137:K158) -> 0
A137: =A136+1 -> 1 | B137: 多联外机-SWJ-250 | C137: 1.名称：多联外机-SWJ-250 2.规格型号：设备制冷量：26(KW)；设备制热量：28.5(KW)；设备额定风量：10200M3/H;额定功率:7.1(KW) 3.含基础、减震器 4.本体安装 | D137: 个 | E137: 1 | I137: =(F137+G137+H137)*$I$3 -> 0 | J137: =F137+G137+H137+I137 -> 0 | K137: =ROUND(E137*J137,2) -> 0
A138: =A137+1 -> 2 | B138: 多联外机-SWJ-280 | C138: 1.名称：多联外机-SWJ-280 2.规格型号：设备制冷量：28.5(KW)；设备制热量：31.5(KW)；设备额定风量：10800M3/H;额定功率:8.8(KW) 3.含基础、减震器 4.本体安装 | D138: 个 | E138: 2 | I138: =(F138+G138+H138)*$I$3 -> 0 | J138: =F138+G138+H138+I138 -> 0 | K138: =ROUND(E138*J138,2) -> 0
A139: =A138+1 -> 3 | B139: 多联外机-SWJ-335 | C139: 1.名称：多联外机-SWJ-335 2.规格型号：设备制冷量：33.5(KW)；设备制热量：36(KW)；设备额定风量：10500M3/H;额定功率:9.5 (KW) 3.含基础、减震器 4.本体安装 | D139: 个 | E139: 7 | I139: =(F139+G139+H139)*$I$3 -> 0 | J139: =F139+G139+H139+I139 -> 0 | K139: =ROUND(E139*J139,2) -> 0
A140: =A139+1 -> 4 | B140: 多联外机-SWJ-615 | C140: 1.名称：多联外机-SWJ-615 2.规格型号：设备制冷量：61.5(KW)；设备制热量：69(KW)；设备额定风量：16500M3/H;额定功率:8.8(KW) 3.含基础、减震器 4.本体安装 | D140: 个 | E140: 2 | I140: =(F140+G140+H140)*$I$3 -> 0 | J140: =F140+G140+H140+I140 -> 0 | K140: =ROUND(E140*J140,2) -> 0
A141: =A140+1 -> 5 | B141: 风管机-SNJ-10 | C141: 1.名称：风管机-SNJ-10 2.规格型号：设备制冷量：10(KW)；设备制热量：11.2;(KW)；设备额定风量：1450~780M3/H;额定功率:0.135 (KW) 3.设备支架制作、安装，手工除锈，刷红丹防锈漆2遍、调和漆2遍 4.本体安装 | D141: 个 | E141: 2 | I141: =(F141+G141+H141)*$I$3 -> 0 | J141: =F141+G141+H141+I141 -> 0 | K141: =ROUND(E141*J141,2) -> 0
A142: =A141+1 -> 6 | B142: 风管机-SNJ-112 | C142: 1.名称：风管机-SNJ-112 2.规格型号：设备制冷量：11.2(KW)；设备制热量：12.5(KW)；设备额定风量：1450~750M3/H;额定功率:0.135 (KW) 3.设备支架制作、安装，手工除锈，刷红丹防锈漆2遍、调和漆2遍 4.本体安装 | D142: 个 | E142: 4 | I142: =(F142+G142+H142)*$I$3 -> 0 | J142: =F142+G142+H142+I142 -> 0 | K142: =ROUND(E142*J142,2) -> 0
A143: =A142+1 -> 7 | B143: 风管机-SNJ-22 | C143: 1.名称：风管机-SNJ-22 2.规格型号：设备制冷量：2.2(KW)；设备制热量：2.5(KW)；设备额定风量：450~200M3/H;额定功率:0.025 (KW) 3.设备支架制作、安装，手工除锈，刷红丹防锈漆2遍、调和漆2遍 4.本体安装 | D143: 个 | E143: 1 | I143: =(F143+G143+H143)*$I$3 -> 0 | J143: =F143+G143+H143+I143 -> 0 | K143: =ROUND(E143*J143,2) -> 0
A144: =A143+1 -> 8 | B144: 风管机-SNJ-28 | C144: 1.名称：风管机-SNJ-28 2.规格型号：设备制冷量：2.8(KW)；设备制热量：3.2(KW)；设备额定风量：450~200M3/H;额定功率:0.025 (KW) 3.设备支架制作、安装，手工除锈，刷红丹防锈漆2遍、调和漆2遍 4.本体安装 | D144: 个 | E144: 2 | I144: =(F144+G144+H144)*$I$3 -> 0 | J144: =F144+G144+H144+I144 -> 0 | K144: =ROUND(E144*J144,2) -> 0
A145: =A144+1 -> 9 | B145: 风管机-SNJ-32 | C145: 1.名称：风管机-SNJ-32 2.规格型号：设备制冷量：3.2(KW)；设备制热量：3.6(KW)；设备额定风量：550~240M3/H;额定功率:0.03KW) 3.设备支架制作、安装，手工除锈，刷红丹防锈漆2遍、调和漆2遍 4.本体安装 | D145: 个 | E145: 1 | I145: =(F145+G145+H145)*$I$3 -> 0 | J145: =F145+G145+H145+I145 -> 0 | K145: =ROUND(E145*J145,2) -> 0
A146: =A145+1 -> 10 | B146: 风管机-SNJ-36 | C146: 1.名称：风管机-SNJ-36 2.规格型号：设备制冷量：3.6(KW)；设备制热量：4KW)；设备额定风量：550~240M3/H;额定功率:0.03(KW) 3.设备支架制作、安装，手工除锈，刷红丹防锈漆2遍、调和漆2遍 4.本体安装 | D146: 个 | E146: 1 | I146: =(F146+G146+H146)*$I$3 -> 0 | J146: =F146+G146+H146+I146 -> 0 | K146: =ROUND(E146*J146,2) -> 0
A147: =A146+1 -> 11 | B147: 风管机-SNJ-40 | C147: 1.名称：风管机-SNJ-40 2.规格型号：设备制冷量：4(KW)；设备制热量：4.5KW)；设备额定风量：550~460M3/H;额定功率:0.03(KW) 3.设备支架制作、安装，手工除锈，刷红丹防锈漆2遍、调和漆2遍 4.本体安装 | D147: 个 | E147: 2 | I147: =(F147+G147+H147)*$I$3 -> 0 | J147: =F147+G147+H147+I147 -> 0 | K147: =ROUND(E147*J147,2) -> 0
A148: =A147+1 -> 12 | B148: 风管机-SNJ-45 | C148: 1.名称：风管机-SNJ-45 2.规格型号：设备制冷量：4.5(KW)；设备制热量：5(KW)；设备额定风量：800~460M3/H;额定功率:0.04 (KW) 3.设备支架制作、安装，手工除锈，刷红丹防锈漆2遍、调和漆2遍 4.本体安装 | D148: 个 | E148: 6 | I148: =(F148+G148+H148)*$I$3 -> 0 | J148: =F148+G148+H148+I148 -> 0 | K148: =ROUND(E148*J148,2) -> 0
... A158: =A157+1 -> 22 | B158: 空调风管 | C158: 1.名称：镀锌薄钢板矩形风管 2.材质：镀锌钢板 3.形状：矩形 4.规格：长边长(mm) ≤2000 5.板材厚度：δ＝1mm 6.管件、法兰等附件及支架设计要求：吊架(型钢综合) 刷防锈底漆两道 风管法兰衬垫采用厚度为5mm的垫圈，法兰在连接前应除锈并刷防锈漆两遍，连接后再刷灰油漆两遍 7.接口形式：共板法兰连接，含弯头导流叶片制作安装 8.风管保温：难燃B1的橡塑绝热材料；厚度为30mm 9.系统调整费 10.本体安装 | D158: m² | E158: 449.856 | I158: =(F158+G158+H158)*$I$3 -> 0 | J158: =F158+G158+H158+I158 -> 0 | K158: =ROUND(E158*J158,2) -> 0
B159: （2）新风工程 | K159: =SUM(K160:K175) -> 0
A160: =A159+1 -> 1 | B160: 全热交换新风换气机-YCH-650 | C160: 1.名称：全热交换新风换气机-YCH-650 2.规格型号：设备额定风量：650/530/420M3/H;额定功率:0.42 (KW) 3.设备支架制作、安装，手工除锈，刷红丹防锈漆2遍、调和漆2遍 4.本体安装 | D160: 个 | E160: 1 | I160: =(F160+G160+H160)*$I$3 -> 0 | J160: =F160+G160+H160+I160 -> 0 | K160: =ROUND(E160*J160,2) -> 0
A161: =A160+1 -> 2 | B161: 全新风多联处理机-SNJ-D224 | C161: 1.名称：全新风多联处理机-SNJ-D224 2.规格型号：设备制冷量：22.4(KW)；设备制热量：13.9;(KW)；设备额定风量：1680M3/H;额定功率:0.16 (KW) 3.设备支架制作、安装，手工除锈，刷红丹防锈漆2遍、调和漆2遍 4.本体安装 | D161: 个 | E161: 1 | I161: =(F161+G161+H161)*$I$3 -> 0 | J161: =F161+G161+H161+I161 -> 0 | K161: =ROUND(E161*J161,2) -> 0
A162: =A161+1 -> 3 | B162: 全新风多联处理机-SNJ-D335 | C162: 1.名称：全新风多联处理机-SNJ-D335 2.规格型号：设备制冷量：33.5(KW)；设备制热量：20.8;(KW)；设备额定风量：2500M3/H;额定功率:0.25 (KW) 3.设备支架制作、安装，手工除锈，刷红丹防锈漆2遍、调和漆2遍 4.本体安装 | D162: 个 | E162: 1 | I162: =(F162+G162+H162)*$I$3 -> 0 | J162: =F162+G162+H162+I162 -> 0 | K162: =ROUND(E162*J162,2) -> 0
A163: =A162+1 -> 4 | B163: 新风外机-SWJ-335 | C163: 1.名称：新风外机-SWJ-335 2.规格型号：设备制冷量：33.5(KW)；设备制热量：37.5(KW)；设备额定风量：11700M3/H;额定功率:8.8(KW) 3.设备支架制作、安装，手工除锈，刷红丹防锈漆2遍、调和漆2遍 4.本体安装 | D163: 个 | E163: 1 | I163: =(F163+G163+H163)*$I$3 -> 0 | J163: =F163+G163+H163+I163 -> 0 | K163: =ROUND(E163*J163,2) -> 0
A164: =A163+1 -> 5 | B164: 新风静压箱 | C164: 1.名称：新风静压箱 2.型号、规格：1000*350*200 3.本体安装 | D164: 个 | E164: 2.24 | I164: =(F164+G164+H164)*$I$3 -> 0 | J164: =F164+G164+H164+I164 -> 0 | K164: =ROUND(E164*J164,2) -> 0
A165: =A164+1 -> 6 | B165: 塑料新风百叶带阀 | C165: 1.名称：塑料新风百叶带阀 2.型号、规格：Φ160 3.本体安装 | D165: 个 | E165: 2 | I165: =(F165+G165+H165)*$I$3 -> 0 | J165: =F165+G165+H165+I165 -> 0 | K165: =ROUND(E165*J165,2) -> 0
A166: =A165+1 -> 7 | B166: 新风百叶 | C166: 1.名称：新风百叶 2.型号、规格：1200*250 3.本体安装 | D166: 个 | E166: 1 | I166: =(F166+G166+H166)*$I$3 -> 0 | J166: =F166+G166+H166+I166 -> 0 | K166: =ROUND(E166*J166,2) -> 0
...

Sheet 措施费
A1: 丹田海德公馆公区装修工程-工程量清单
A2: 序号 | B2: 项目名称 | C2: 项目特征 | D2: 单位 | E2: 工程量 | F2: 人工 | G2: 主材 | H2: 辅材及机械费 | I2: 管理及利润取费 | J2: 综合单价 （不含税） | K2: 合价 （不含税） | L2: 备注
A4: 一 | B4: 措施费 | K4: =SUM(K5:K6) -> 0
A5: 1 | B5: 垃圾清理及卫生清洁 | C5: 卫生清理、含粗清洁、精清洁（按地面投影面积计算） | D5: m2 | E5: =汇总表!C13 -> 3700.17 | I5: =(F5+G5+H5)*$I$3 -> 0 | J5: =ROUND(SUM(F5:I5),2) -> 0 | K5: =ROUND(J5*E5,2) -> 0
A6: 2 | B6: 脚手架费用 | C6: 脚手架费用、包括活动式、满堂式、综合式、单排式（按地面投影面积计算） | D6: m2 | E6: =E5 -> 3700.17 | I6: =(F6+G6+H6)*$I$3 -> 0 | J6: =ROUND(SUM(F6:I6),2) -> 0 | K6: =ROUND(J6*E6,2) -> 0
A7: 二 | B7: 合计 | K7: =SUM(K4:K6)/2 -> 0
