Workbook

Sheet 2-报价汇总
H4: 安措 | I4: 管理 | J4: 利润
H5: 0.01 | I5: 0 | J5: 0

Sheet 2.1-装饰工程
A1: 理想汽车中心店装修工程量清单
A2: 注意：此报价清单每项不得随意更改、删减，如有任何增加项请务必在每大项最后“补充项“中列举，补充项及说明字体颜色均采用蓝色；且所有项目都需要填写。
A3: 序号 | B3: 项目名称 | C3: 项目特征 | D3: 适用范围 | E3: 工程量计算规则 | F3: 单位 | G3: 24/25年暂估工程量 | H3: 综合单价 | I3: 人工费 | J3: 材料费 | K3: 机械费 | L3: 安措费 | M3: 管理费 | N3: 利润 | O3: 24/25年暂估总价 | P3: 备注
B4: 2.1装饰工程
A5: 2.1.1 | B5: 拆除工程
A6: 2.1.1.01 | B6: 原有石膏板天花拆除 | C6: 1.拆除原有天花 2.龙骨、吊筋拆除 | D6: 室内、室外装饰装修及安装工程项目 | E6: 按拆除面积计算。垃圾清理折算系数：0.05 | F6: m2 | G6: 1123021.8 | H6: =SUM(I6:N6) -> 10.493506 | I6: 10.14961 | J6: 0 | K6: 0.24 | L6: =(I6+J6+K6)*'2-报价汇总'!$H$5 -> 0.1038961 | M6: =(I6+J6+K6+L6)*'2-报价汇总'!$I$5 -> 0 | N6: =(M6+L6+K6+J6+I6)*'2-报价汇总'!$J$5 -> 0 | O6: =G6*H6 -> 11784437
A7: 2.1.1.02 | B7: 原有矿棉板/铝扣板天花拆除 | C7: 1.拆除原有天花 2.龙骨、吊筋拆除 | D7: 室内、室外装饰装修及安装工程项目 | E7: 按拆除面积计算。垃圾清理折算系数：0.05 | F7: m2 | G7: 355016.51 | H7: =SUM(I7:N7) -> 8.7445887 | I7: 8.4580087 | J7: 0 | K7: 0.2 | L7: =(I7+J7+K7)*'2-报价汇总'!$H$5 -> 0.086580087 | M7: =(I7+J7+K7+L7)*'2-报价汇总'!$I$5 -> 0 | N7: =(M7+L7+K7+J7+I7)*'2-报价汇总'!$J$5 -> 0 | O7: =G7*H7 -> 3104473.4
A8: 2.1.1.03 | B8: 原有地砖或石材地面拆除 *拆除至不改变地面标高 | C8: 1.拆除原有地面石材&地砖 2.粘结层拆除至满足图纸地面面层做法高度 | D8: 室内、室外装饰装修及安装工程项目 | E8: 按拆除面积计算。垃圾清理折算系数：0.05 | F8: m2 | G8: 1080551.6 | H8: =SUM(I8:N8) -> 27.982684 | I8: 27.005628 | J8: 0 | K8: 0.7 | L8: =(I8+J8+K8)*'2-报价汇总'!$H$5 -> 0.27705628 | M8: =(I8+J8+K8+L8)*'2-报价汇总'!$I$5 -> 0 | N8: =(M8+L8+K8+J8+I8)*'2-报价汇总'!$J$5 -> 0 | O8: =G8*H8 -> 30236735
A9: 2.1.1.04 | B9: 混凝土地面拆除 | C9: 1.拆除原有混凝土地面，≤100mm厚 2.＞100mm厚按此项目比例折算 | D9: 室内、室外装饰装修及安装工程项目 | E9: 按拆除面积计算。垃圾清理折算系数：0.05 | F9: m2 | G9: 350000 | H9: =SUM(I9:N9) -> 52.467532 | I9: 50.978052 | J9: 0 | K9: 0.97 | L9: =(I9+J9+K9)*'2-报价汇总'!$H$5 -> 0.51948052 | M9: =(I9+J9+K9+L9)*'2-报价汇总'!$I$5 -> 0 | N9: =(M9+L9+K9+J9+I9)*'2-报价汇总'!$J$5 -> 0 | O9: =G9*H9 -> 18363636
A10: 2.1.1.05 | B10: 原有环氧树脂地面拆除（刨铣） *拆除至不改变地面标高 | C10: 1.拆除原有环氧树脂自流平 2.地面打磨平整并不改变地面标高 | D10: 室内、室外装饰装修及安装工程项目 | E10: 按拆除面积计算。垃圾清理折算系数：0.005 | F10: m2 | G10: 300000 | H10: =SUM(I10:N10) -> 10.493506 | I10: 9.8096104 | J10: 0 | K10: 0.58 | L10: =(I10+J10+K10)*'2-报价汇总'!$H$5 -> 0.1038961 | M10: =(I10+J10+K10+L10)*'2-报价汇总'!$I$5 -> 0 | N10: =(M10+L10+K10+J10+I10)*'2-报价汇总'!$J$5 -> 0 | O10: =G10*H10 -> 3148051.9
A11: 2.1.1.06 | B11: 原有地毯或胶地板地面拆除 | C11: 1.拆除原有地面地毯、胶地板、木地板 | D11: 室内、室外装饰装修及安装工程项目 | E11: 按拆除面积计算。垃圾清理折算系数：0.01 | F11: m2 | G11: 50000 | H11: =SUM(I11:N11) -> 5.2467532 | I11: 4.9748052 | J11: 0 | K11: 0.22 | L11: =(I11+J11+K11)*'2-报价汇总'!$H$5 -> 0.051948052 | M11: =(I11+J11+K11+L11)*'2-报价汇总'!$I$5 -> 0 | N11: =(M11+L11+K11+J11+I11)*'2-报价汇总'!$J$5 -> 0 | O11: =G11*H11 -> 262337.66
A12: 2.1.1.07 | B12: 原有砌筑墙体（连门）拆除 | C12: 1.拆除原有砌体墙连墙体内砼柱破碎 2.装袋清理 | D12: 室内、室外装饰装修及安装工程项目 | E12: 以 m3计量，按拆除的体积计算。垃圾清理折算系数：1 | F12: m3 | G12: 283578.53 | H12: =SUM(I12:N12) -> 174.89177 | I12: 171.02017 | J12: 0 | K12: 2.14 | L12: =(I12+J12+K12)*'2-报价汇总'!$H$5 -> 1.7316017 | M12: =(I12+J12+K12+L12)*'2-报价汇总'!$I$5 -> 0 | N12: =(M12+L12+K12+J12+I12)*'2-报价汇总'!$J$5 -> 0 | O12: =G12*H12 -> 49595553
A13: 2.1.1.08 | B13: 原有玻璃隔墙（连门）拆除 | C13: 1.拆除原有玻璃隔断及框 2.装袋清理 | D13: 室内、室外装饰装修及安装工程项目 | E13: 按拆除的面积计算。垃圾清理折算系数：0.05 | F13: m2 | G13: 145436.63 | H13: =SUM(I13:N13) -> 17.489177 | I13: 17.116017 | J13: 0 | K13: 0.2 | L13: =(I13+J13+K13)*'2-报价汇总'!$H$5 -> 0.17316017 | M13: =(I13+J13+K13+L13)*'2-报价汇总'!$I$5 -> 0 | N13: =(M13+L13+K13+J13+I13)*'2-报价汇总'!$J$5 -> 0 | O13: =G13*H13 -> 2543567.1
A14: 2.1.1.09 | B14: 原有石膏板/水泥压力板隔墙（连门）拆除 | C14: 1.拆除原有龙骨式隔墙 2.装袋清理 | D14: 室内、室外装饰装修及安装工程项目 | E14: 按拆除面积计算。垃圾清理折算系数：0.15 | F14: m2 | G14: 494719.99 | H14: =SUM(I14:N14) -> 19.233898 | I14: 18.083463 | J14: 0 | K14: 0.96 | L14: =(I14+J14+K14)*'2-报价汇总'!$H$5 -> 0.19043463 | M14: =(I14+J14+K14+L14)*'2-报价汇总'!$I$5 -> 0 | N14: =(M14+L14+K14+J14+I14)*'2-报价汇总'!$J$5 -> 0 | O14: =G14*H14 -> 9515393.8
A15: 2.1.1.10 | B15: 拆除墙面石材、墙砖 | C15: 1.拆除原有墙面石材&瓷砖 2.粘结层拆除至满足图纸墙面面层做法厚度 | D15: 室内、室外装饰装修及安装工程项目 | E15: 按拆除面积计算。垃圾清理折算系数：0.05 | F15: m2 | G15: 45876.504 | H15: =SUM(I15:N15) -> 27.982684 | I15: 26.925628 | J15: 0 | K15: 0.78 | L15: =(I15+J15+K15)*'2-报价汇总'!$H$5 -> 0.27705628 | M15: =(I15+J15+K15+L15)*'2-报价汇总'!$I$5 -> 0 | N15: =(M15+L15+K15+J15+I15)*'2-报价汇总'!$J$5 -> 0 | O15: =G15*H15 -> 1283747.7
A16: 2.1.1.11 | B16: 乳胶漆铲除 | C16: 1.铲除原有墙面/顶面乳胶漆及腻子 | D16: 室内、室外装饰装修及安装工程项目 | E16: 按拆除部位的面积计算。垃圾清理折算系数：0.001 | F16: m2 | G16: 2000 | H16: =SUM(I16:N16) -> 4.3722944 | I16: 4.2690043 | J16: 0 | K16: 0.06 | L16: =(I16+J16+K16)*'2-报价汇总'!$H$5 -> 0.043290043 | M16: =(I16+J16+K16+L16)*'2-报价汇总'!$I$5 -> 0 | N16: =(M16+L16+K16+J16+I16)*'2-报价汇总'!$J$5 -> 0 | O16: =G16*H16 -> 8744.5887
A17: 2.1.1.12 | B17: 拆除外窗 | C17: 1.拆除原有外窗 2.装袋清理 | D17: 室内、室外装饰装修及安装工程项目 | E17: 按拆除部位的面积计算。垃圾清理折算系数：0.02 | F17: m2 | G17: 64681.04 | H17: =SUM(I17:N17) -> 11.367965 | I17: 10.535411 | J17: 0 | K17: 0.72 | L17: =(I17+J17+K17)*'2-报价汇总'!$H$5 -> 0.11255411 | M17: =(I17+J17+K17+L17)*'2-报价汇总'!$I$5 -> 0 | N17: =(M17+L17+K17+J17+I17)*'2-报价汇总'!$J$5 -> 0 | O17: =G17*H17 -> 735291.82
... A38: 2.1.1.33 | B38: 幕墙钢框保护利旧及拆除幕墙玻璃 | C38: 1.原有幕墙玻璃拆除 2.原幕墙结构保护 3.垃圾清理及垃圾外运 | D38: 室内、室外装饰装修及安装工程项目 | E38: 按拆除面积计算 | F38: m2 | G38: 5000 | H38: =SUM(I38:N38) -> 43.719971 | I38: 42.2871 | J38: 0 | K38: 1 | L38: =(I38+J38+K38)*'2-报价汇总'!$H$5 -> 0.432871 | M38: =(I38+J38+K38+L38)*'2-报价汇总'!$I$5 -> 0 | N38: =(M38+L38+K38+J38+I38)*'2-报价汇总'!$J$5 -> 0 | O38: =G38*H38 -> 218599.85
A39: 2.1.1.34 | B39: 拆除垃圾清理、清运（规格：5立方） | D39: 室内、室外装饰装修及安装工程项目 | E39: 分项工程垃圾清理折算系数*面积之和/5 | F39: 车 | G39: 30000 | H39: =SUM(I39:N39) -> 546.5368 | I39: 181.12554 | J39: 0 | K39: 360 | L39: =(I39+J39+K39)*'2-报价汇总'!$H$5 -> 5.4112554 | M39: =(I39+J39+K39+L39)*'2-报价汇总'!$I$5 -> 0 | N39: =(M39+L39+K39+J39+I39)*'2-报价汇总'!$J$5 -> 0 | O39: =G39*H39 -> 16396104
A40: 2.1.1.35 | B40: 拆除垃圾清理、清运（规格：7立方） | D40: 室内、室外装饰装修及安装工程项目 | E40: 分项工程垃圾清理折算系数*面积之和/7 | F40: 车 | G40: 35655.67 | H40: =SUM(I40:N40) -> 765.15152 | I40: 257.57576 | J40: 0 | K40: 500 | L40: =(I40+J40+K40)*'2-报价汇总'!$H$5 -> 7.5757576 | M40: =(I40+J40+K40+L40)*'2-报价汇总'!$I$5 -> 0 | N40: =(M40+L40+K40+J40+I40)*'2-报价汇总'!$J$5 -> 0 | O40: =G40*H40 -> 27281990
B41: 补充项
B42: 小 计
A43: 2.1.2 | B43: 隔断工程
A44: 2.1.2.01 | B44: 120mm厚双面双层石膏板隔墙 | C44: 1.75轻钢龙骨 间距400 2.双面双层9厘石膏板 防锈螺钉固定 3.内填50mm隔音岩棉，容重65kg/m3 | D44: 室内、室外装饰装修项目 | E44: 按设计图示尺寸以面积计算 | F44: m2 | G44: 139029.87 | H44: =SUM(I44:N44) -> 197.455 | I44: 94.3 | J44: 100 | K44: 1.2 | L44: =(I44+J44+K44)*'2-报价汇总'!$H$5 -> 1.955 | M44: =(I44+J44+K44+L44)*'2-报价汇总'!$I$5 -> 0 | N44: =(M44+L44+K44+J44+I44)*'2-报价汇总'!$J$5 -> 0 | O44: =G44*H44 -> 27452143
A45: 2.1.2.02 | B45: 120mm厚双面双层防水石膏板隔墙 | C45: 1.75轻钢龙骨 间距400 2.双面双层9厘防水石膏板 防锈螺钉固定 3.内填50mm隔音岩棉，容重65kg/m3 | D45: 室内、室外装饰装修项目 | E45: 按设计图示尺寸面积计算 | F45: m2 | G45: 80000 | H45: =SUM(I45:N45) -> 217.655 | I45: 94.3 | J45: 120 | K45: 1.2 | L45: =(I45+J45+K45)*'2-报价汇总'!$H$5 -> 2.155 | M45: =(I45+J45+K45+L45)*'2-报价汇总'!$I$5 -> 0 | N45: =(M45+L45+K45+J45+I45)*'2-报价汇总'!$J$5 -> 0 | O45: =G45*H45 -> 17412400
A46: 2.1.2.03 | B46: 100mm厚单面双层石膏板隔墙包管道或墙体，假天花标高：（管道、消防栓） | C46: 1.75轻钢龙骨 间距400 2单面双层9厘石膏板 防锈螺钉固定 3.内填50mm隔音岩棉，容重65kg/m3 | D46: 室内、室外装饰装修项目 | E46: 按设计图示尺寸面积计算 | F46: m2 | G46: 499161.28 | H46: =SUM(I46:N46) -> 144.632 | I46: 62 | J46: 80 | K46: 1.2 | L46: =(I46+J46+K46)*'2-报价汇总'!$H$5 -> 1.432 | M46: =(I46+J46+K46+L46)*'2-报价汇总'!$I$5 -> 0 | N46: =(M46+L46+K46+J46+I46)*'2-报价汇总'!$J$5 -> 0 | O46: =G46*H46 -> 72194694
A47: 2.1.2.04 | B47: 100mm厚单面双层防水石膏板隔墙包管道或墙体，假天花标高：（管道、消防栓） | C47: 1.75轻钢龙骨 间距400 2单面双层9厘防水石膏板 防锈螺钉固定 3.内填50mm隔音岩棉，容重65kg/m3 | D47: 室内、室外装饰装修项目 | E47: 按设计图示尺寸面积计算 | F47: m2 | G47: 499161.28 | H47: =SUM(I47:N47) -> 154.732 | I47: 62 | J47: 90 | K47: 1.2 | L47: =(I47+J47+K47)*'2-报价汇总'!$H$5 -> 1.532 | M47: =(I47+J47+K47+L47)*'2-报价汇总'!$I$5 -> 0 | N47: =(M47+L47+K47+J47+I47)*'2-报价汇总'!$J$5 -> 0 | O47: =G47*H47 -> 77236223
A48: 2.1.2.05 | B48: 100mm厚双面单层水泥压力板隔墙 | C48: 1.75轻钢龙骨 间距400 2.双面单层12厘水泥压力板 防锈螺钉固定 3.内填50mm隔音岩棉，容重65kg/m3 | D48: 室内、室外装饰装修项目 | E48: 按设计图示尺寸面积计算 | F48: m2 | G48: 69708.456 | H48: =SUM(I48:N48) -> 156.752 | I48: 62 | J48: 92 | K48: 1.2 | L48: =(I48+J48+K48)*'2-报价汇总'!$H$5 -> 1.552 | M48: =(I48+J48+K48+L48)*'2-报价汇总'!$I$5 -> 0 | N48: =(M48+L48+K48+J48+I48)*'2-报价汇总'!$J$5 -> 0 | O48: =G48*H48 -> 10926940
A49: 2.1.2.06 | B49: 100mm厚单面单层水泥压力板板隔墙包管道或墙体，假天花标高：（管道、消防栓） | C49: 1.75轻钢龙骨 间距400 2.单面单层12厘水泥压力板 防锈螺钉固定 3.内填50mm隔音岩棉，容重65kg/m3 | D49: 室内、室外装饰装修项目 | E49: 按设计图示尺寸面积计算 | F49: m2 | G49: 69708.456 | H49: =SUM(I49:N49) -> 133.32 | I49: 56 | J49: 75 | K49: 1 | L49: =(I49+J49+K49)*'2-报价汇总'!$H$5 -> 1.32 | M49: =(I49+J49+K49+L49)*'2-报价汇总'!$I$5 -> 0 | N49: =(M49+L49+K49+J49+I49)*'2-报价汇总'!$J$5 -> 0 | O49: =G49*H49 -> 9293531.3
A50: 2.1.2.07 | B50: 120mm厚单面双层石膏板+单面双层水泥板隔墙 | C50: 1.75轻钢龙骨 间距400 2.单面双层9厘石膏板+单面双层9厘水泥板 防锈螺钉固定 3.内填50mm隔音岩棉，容重65kg/m3 | D50: 室内、室外装饰装修项目（无特殊原因不采用此项目，砌块墙优先选择） | E50: 按设计图示尺寸面积计算 | F50: m2 | G50: 10000 | H50: =SUM(I50:N50) -> 248.2681 | I50: 120 | J50: 120 | K50: 5.81 | L50: =(I50+J50+K50)*'2-报价汇总'!$H$5 -> 2.4581 | M50: =(I50+J50+K50+L50)*'2-报价汇总'!$I$5 -> 0 | N50: =(M50+L50+K50+J50+I50)*'2-报价汇总'!$J$5 -> 0 | O50: =G50*H50 -> 2482681
A51: 2.1.2.08 | B51: 120mm厚双面双层水泥压力板隔墙 | C51: 1.75轻钢龙骨 间距400 2.双面双层9厘水泥压力板 防锈螺钉固定 3.内填50mm隔音岩棉，容重65kg/m3 | D51: 室内、室外装饰装修项目（无特殊原因不采用此项目，砌块墙优先选择） | E51: 按设计图示尺寸面积计算 | F51: m2 | G51: 10000 | H51: =SUM(I51:N51) -> 183.63636 | I51: 45.838182 | J51: 130 | K51: 5.98 | L51: =(I51+J51+K51)*'2-报价汇总'!$H$5 -> 1.8181818 | M51: =(I51+J51+K51+L51)*'2-报价汇总'!$I$5 -> 0 | N51: =(M51+L51+K51+J51+I51)*'2-报价汇总'!$J$5 -> 0 | O51: =G51*H51 -> 1836363.6
A52: 2.1.2.09 | B52: 100mm厚单面双层水泥压力板板隔墙包管道或墙体（管道、消防栓） | C52: 1.75轻钢龙骨 间距400 2.单面双层9厘水泥压力板 防锈螺钉固定 3.内填50mm隔音岩棉，容重65kg/m3 | D52: 室内、室外装饰装修项目（无特殊原因不采用此项目，砌块墙优先选择） | E52: 按设计图示尺寸面积计算 | F52: m2 | G52: 10000 | H52: =SUM(I52:N52) -> 139.91342 | I52: 64.958139 | J52: 70 | K52: 3.57 | L52: =(I52+J52+K52)*'2-报价汇总'!$H$5 -> 1.3852814 | M52: =(I52+J52+K52+L52)*'2-报价汇总'!$I$5 -> 0 | N52: =(M52+L52+K52+J52+I52)*'2-报价汇总'!$J$5 -> 0 | O52: =G52*H52 -> 1399134.2
A53: 2.1.2.10 | B53: 在原有墙面 贴2层纸面石膏板 单面双层9mm厚石膏板 防锈螺钉固定 | C53: 1.原墙面修补双层纸面石膏板 2.防锈螺钉固定 | D53: 室内、室外装饰装修项目 | E53: 按设计图示尺寸面积计算 | F53: m2 | G53: 10000 | H53: =SUM(I53:N53) -> 56.839827 | I53: 25.647056 | J53: 30 | K53: 0.63 | L53: =(I53+J53+K53)*'2-报价汇总'!$H$5 -> 0.56277056 | M53: =(I53+J53+K53+L53)*'2-报价汇总'!$I$5 -> 0 | N53: =(M53+L53+K53+J53+I53)*'2-报价汇总'!$J$5 -> 0 | O53: =G53*H53 -> 568398.27
A54: 2.1.2.11 | B54: 20*40方钢管双层防水纸面石膏板 | C54: 1.20*40方钢龙骨 2.双面双层9厘防水石膏板，防锈螺钉固定 3.内填50mm隔音岩棉，容重65kg/m3 | D54: 室内、室外装饰装修项目 | E54: 按设计图示尺寸面积计算 | F54: m2 | G54: 10000 | H54: =SUM(I54:N54) -> 214.24242 | I54: 65.931212 | J54: 140 | K54: 6.19 | L54: =(I54+J54+K54)*'2-报价汇总'!$H$5 -> 2.1212121 | M54: =(I54+J54+K54+L54)*'2-报价汇总'!$I$5 -> 0 | N54: =(M54+L54+K54+J54+I54)*'2-报价汇总'!$J$5 -> 0 | O54: =G54*H54 -> 2142424.2
A55: 2.1.2.12 | B55: 在原有墙面 贴2层水泥板 单面双层12mm厚水泥压力板 防锈螺钉固定 | C55: 1.原墙面修补双层水泥压力板 2.防锈螺钉固定 | D55: 室内、室外装饰装修项目 | E55: 按设计图示尺寸面积计算 | F55: m2 | G55: 35540.846 | H55: =SUM(I55:N55) -> 65.584416 | I55: 24.135065 | J55: 40 | K55: 0.8 | L55: =(I55+J55+K55)*'2-报价汇总'!$H$5 -> 0.64935065 | M55: =(I55+J55+K55+L55)*'2-报价汇总'!$I$5 -> 0 | N55: =(M55+L55+K55+J55+I55)*'2-报价汇总'!$J$5 -> 0 | O55: =G55*H55 -> 2330925.6
... A74: 2.1.2.31 | B74: 单面单层阻燃板隔墙 | C74: 1.75轻钢龙骨 2.单层15厘阻燃板 防锈螺钉固定 3.内填50mm隔音岩棉，容重65kg/m3 | D74: 室内装饰装修项目 | E74: 按设计图示尺寸以以面积计算 | F74: m2 | G74: 5000 | H74: =SUM(I74:N74) -> 149.682 | I74: 45 | J74: 102 | K74: 1.2 | L74: =(I74+J74+K74)*'2-报价汇总'!$H$5 -> 1.482 | M74: =(I74+J74+K74+L74)*'2-报价汇总'!$I$5 -> 0 | N74: =(M74+L74+K74+J74+I74)*'2-报价汇总'!$J$5 -> 0 | O74: =G74*H74 -> 748410
A75: 2.1.2.32 | B75: 100mm厚单面单层石膏板隔墙 | C75: 1.75轻钢龙骨间距400 2.单面单层9厘石膏板 防锈螺钉固定 3.内填50mm隔音岩棉，容重65kg/m3 | D75: 室内、室外装饰装修项目 | E75: 按设计图示尺寸以面积计算 | F75: m2 | G75: 5000 | H75: =SUM(I75:N75) -> 118.877 | I75: 45 | J75: =100-9.5*3 -> 71.5 | K75: 1.2 | L75: =(I75+J75+K75)*'2-报价汇总'!$H$5 -> 1.177 | M75: =(I75+J75+K75+L75)*'2-报价汇总'!$I$5 -> 0 | N75: =(M75+L75+K75+J75+I75)*'2-报价汇总'!$J$5 -> 0 | O75: =G75*H75 -> 594385
A76: 2.1.2.33 | B76: 隔墙圆弧角加工制作（阴角弧长785mm） | C76: 1.75轻钢龙骨 间距400 2.双面双层9厘石膏板 防锈螺钉固定 3.内填50mm隔音岩棉，容重65kg/m3 | E76: 按设计图示尺寸以长度计算（从地面算至天花） | F76: m | G76: 14401.923 | H76: =SUM(I76:N76) -> 44.036 | I76: 12 | J76: =7.6*4 -> 30.4 | K76: 1.2 | L76: =(I76+J76+K76)*'2-报价汇总'!$H$5 -> 0.436 | M76: =(I76+J76+K76+L76)*'2-报价汇总'!$I$5 -> 0 | N76: =(M76+L76+K76+J76+I76)*'2-报价汇总'!$J$5 -> 0 | O76: =G76*H76 -> 634203.07
A77: 2.1.2.34 | B77: 隔墙圆弧角加工制作（阳角弧长314mm） | C77: 1.75轻钢龙骨 间距400 2.双面双层9厘石膏板 防锈螺钉固定 3.内填50mm隔音岩棉，容重65kg/m3 | E77: 按设计图示尺寸以长度计算（从地面算至天花） | F77: m | G77: 5469.0846 | H77: =SUM(I77:N77) -> 22.018 | I77: 6 | J77: =J76/2 -> 15.2 | K77: 0.6 | L77: =(I77+J77+K77)*'2-报价汇总'!$H$5 -> 0.218 | M77: =(I77+J77+K77+L77)*'2-报价汇总'!$I$5 -> 0 | N77: =(M77+L77+K77+J77+I77)*'2-报价汇总'!$J$5 -> 0 | O77: =G77*H77 -> 120418.3 | P77: =SUM(#REF!) -> #REF!
B78: 补充项
B79: 小 计
A80: 2.1.3 | B80: 地面工程
A81: 2.1.3.01 | B81: 车间排水沟&排水篦子 | C81: 1.C20混凝土基础，含L型角铁 2.树脂篦子，小孔 3.地面开挖及回填 4.基础宽1400mm，篦子宽300mm | D81: 室内、室外车间及洗车区 | E81: 按设计图示尺寸延长米计算 | F81: m | G81: 88972.891 | H81: =SUM(I81:N81) -> 314.80519 | I81: 106.54831 | J81: 200 | K81: 5.14 | L81: =(I81+J81+K81)*'2-报价汇总'!$H$5 -> 3.1168831 | M81: =(I81+J81+K81+L81)*'2-报价汇总'!$I$5 -> 0 | N81: =(M81+L81+K81+J81+I81)*'2-报价汇总'!$J$5 -> 0 | O81: =G81*H81 -> 28009128 | P81: 位置：车间
A82: 2.1.3.02 | B82: 洗车工位活动盖板 | C82: 1.C20混凝土网格基础，含L型角铁 2.土方开挖及回填外运 3.树脂盖板，小孔 | D82: 室内、室外装饰装修项目 | E82: 按设计图示尺寸面积计算 | F82: m2 | G82: 5000 | H82: =SUM(I82:N82) -> 393.50649 | I82: 39.46039 | J82: 350 | K82: 0.15 | L82: =(I82+J82+K82)*'2-报价汇总'!$H$5 -> 3.8961039 | M82: =(I82+J82+K82+L82)*'2-报价汇总'!$I$5 -> 0 | N82: =(M82+L82+K82+J82+I82)*'2-报价汇总'!$J$5 -> 0 | O82: =G82*H82 -> 1967532.5
A83: 2.1.3.03 | B83: 混凝土地面垫层 | C83: 1.地面清理 2.C20混凝土找平 3.包括一切所需的材料及工作 | D83: 室内装饰装修工程 | E83: 按设计图示尺寸面积计算 | F83: m3 | G83: 22017.441 | H83: =SUM(I83:N83) -> 524.67532 | I83: 106.28052 | J83: 403 | K83: 10.2 | L83: =(I83+J83+K83)*'2-报价汇总'!$H$5 -> 5.1948052 | M83: =(I83+J83+K83+L83)*'2-报价汇总'!$I$5 -> 0 | N83: =(M83+L83+K83+J83+I83)*'2-报价汇总'!$J$5 -> 0 | O83: =G83*H83 -> 11552008
A84: 2.1.3.04 | B84: 陶粒混凝土地面垫层 | C84: 1.陶粒水泥砂浆找平 2.陶粒层及30mm厚水泥砂浆找平层 3.具体尺寸以现场实际高度为准,包括到综合单价内 4.包括一切所需的材料及工作 | D84: 室内装饰装修工程 | E84: 按设计图示尺寸面积计算 | F84: m3 | G84: 5000 | H84: =SUM(I84:N84) -> 524.67532 | I84: 117.94052 | J84: 400 | K84: 1.54 | L84: =(I84+J84+K84)*'2-报价汇总'!$H$5 -> 5.1948052 | M84: =(I84+J84+K84+L84)*'2-报价汇总'!$I$5 -> 0 | N84: =(M84+L84+K84+J84+I84)*'2-报价汇总'!$J$5 -> 0 | O84: =G84*H84 -> 2623376.6
A85: 2.1.3.05 | B85: 600x600地砖 | C85: 1.600*600地面瓷砖铺装（含切割、磨边、勾缝） 2.基层处理，粘结层 3.素水泥砂浆一道(内掺建筑胶） 4.1：2.5水泥砂浆找平层 5.原有地面机械刨铣，深度大于3公分 *包含消耗量，品牌：以品牌清单要求为准 | D85: 室内、室外装饰装修项目 | E85: 按设计图示尺寸面积计算 | F85: m2 | G85: 563142.52 | H85: =SUM(I85:N85) -> 170.185 | I85: 65 | J85: 102 | K85: 1.5 | L85: =(I85+J85+K85)*'2-报价汇总'!$H$5 -> 1.685 | M85: =(I85+J85+K85+L85)*'2-报价汇总'!$I$5 -> 0 | N85: =(M85+L85+K85+J85+I85)*'2-报价汇总'!$J$5 -> 0 | O85: =G85*H85 -> 95838410 | P85: 主材现按86元/㎡组价
A86: 2.1.3.06 | B86: 200x200地砖 | C86: 1.200*200地面瓷砖铺装（含切割、磨边、勾缝） 2.基层处理，粘结层 3.素水泥砂浆一道(内掺建筑胶） 4.1：2.5水泥砂浆找平层 5.原有地面机械刨铣，深度大于3公分 *包含消耗量，品牌：以品牌清单要求为准 | D86: 室内、室外装饰装修项目 | E86: 按设计图示尺寸面积计算 | F86: m2 | G86: 1057101.1 | H86: =SUM(I86:N86) -> 173.922 | I86: 78 | J86: 92.7 | K86: 1.5 | L86: =(I86+J86+K86)*'2-报价汇总'!$H$5 -> 1.722 | M86: =(I86+J86+K86+L86)*'2-报价汇总'!$I$5 -> 0 | N86: =(M86+L86+K86+J86+I86)*'2-报价汇总'!$J$5 -> 0 | O86: =G86*H86 -> 1.8385314e+08 | P86: 主材现按76元/㎡组价
A87: 2.1.3.07 | B87: 800*800地砖 | C87: 1.800*800地面瓷砖铺装（含切割、磨边、勾缝） 2.基层处理，粘结层 3.素水泥砂浆一道(内掺建筑胶） 4.1：2.5水泥砂浆找平层 5.原有地面机械刨铣，深度大于3公分 *包含消耗量，品牌：以品牌清单要求为准 | D87: 室内、室外装饰装修项目 | E87: 按设计图示尺寸面积计算 | F87: m2 | G87: 1042617.2 | H87: =SUM(I87:N87) -> 141.4 | I87: 65.5 | J87: 72 | K87: 2.5 | L87: =(I87+J87+K87)*'2-报价汇总'!$H$5 -> 1.4 | M87: =(I87+J87+K87+L87)*'2-报价汇总'!$I$5 -> 0 | N87: =(M87+L87+K87+J87+I87)*'2-报价汇总'!$J$5 -> 0 | O87: =G87*H87 -> 1.4742607e+08 | P87: 主材现按55.8元/㎡组价
A88: 2.1.3.08 | B88: 300x300地砖 | C88: 1.300*300地面瓷砖铺装（含切割、磨边、勾缝） 2.基层处理，粘结层 3.素水泥砂浆一道(内掺建筑胶） 4.1：2.5水泥砂浆找平层 5.原有地面机械刨铣，深度大于3公分 *包含消耗量，品牌：以品牌清单要求为准 | D88: 室内、室外装饰装修项目 | E88: 按设计图示尺寸面积计算 | F88: m2 | G88: 47900.066 | H88: =SUM(I88:N88) -> 159.15152 | I88: 76.075758 | J88: 80 | K88: 1.5 | L88: =(I88+J88+K88)*'2-报价汇总'!$H$5 -> 1.5757576 | M88: =(I88+J88+K88+L88)*'2-报价汇总'!$I$5 -> 0 | N88: =(M88+L88+K88+J88+I88)*'2-报价汇总'!$J$5 -> 0 | O88: =G88*H88 -> 7623368
A89: 2.1.3.09 | B89: 900*900地砖 | C89: 1.900*900地面瓷砖铺装（含切割、磨边、勾缝） 2.基层处理，粘结层 3.素水泥砂浆一道(内掺建筑胶） 4.1：2.5水泥砂浆找平层 5.原有地面机械刨铣，深度大于3公分 *包含消耗量，品牌：以品牌清单要求为准 | D89: 室内、室外装饰装修项目 | E89: 按设计图示尺寸面积计算 | F89: m2 | G89: 5000 | H89: =SUM(I89:N89) -> 222.503 | I89: 67.8 | J89: 150 | K89: 2.5 | L89: =(I89+J89+K89)*'2-报价汇总'!$H$5 -> 2.203 | M89: =(I89+J89+K89+L89)*'2-报价汇总'!$I$5 -> 0 | N89: =(M89+L89+K89+J89+I89)*'2-报价汇总'!$J$5 -> 0 | O89: =G89*H89 -> 1112515
A90: 2.1.3.10 | B90: 瓷砖美缝 | C90: 1.地面瓷砖缝清理 2.美缝剂 3.面层清理 | D90: 室内、室外装饰装修项目 | E90: 按设计图示尺寸面积计算 | F90: m2 | G90: 1462442.3 | H90: =SUM(I90:N90) -> 17.489177 | I90: 2.1160173 | J90: 15 | K90: 0.2 | L90: =(I90+J90+K90)*'2-报价汇总'!$H$5 -> 0.17316017 | M90: =(I90+J90+K90+L90)*'2-报价汇总'!$I$5 -> 0 | N90: =(M90+L90+K90+J90+I90)*'2-报价汇总'!$J$5 -> 0 | O90: =G90*H90 -> 25576913
A91: 2.1.3.11 | B91: 楼梯地砖 | C91: 1.地面瓷砖铺装（含切割、磨边、勾缝） 2.基层处理，粘结层 3.素水泥砂浆一道(内掺建筑胶） 4.1：2.5水泥砂浆找平层 5.原有地面机械刨铣，深度大于3公分 6.含成品金属止滑条 *包含消耗量，品牌：以品牌清单要求为准 | D91: 室内、室外楼梯间 | E91: 按设计图示尺寸面积计算 | F91: m2 | G91: 31583.963 | H91: =SUM(I91:N91) -> 284.19913 | I91: 96.935281 | J91: 180 | K91: 4.45 | L91: =(I91+J91+K91)*'2-报价汇总'!$H$5 -> 2.8138528 | M91: =(I91+J91+K91+L91)*'2-报价汇总'!$I$5 -> 0 | N91: =(M91+L91+K91+J91+I91)*'2-报价汇总'!$J$5 -> 0 | O91: =G91*H91 -> 8976135
A92: 2.1.3.12 | B92: 地面3mm环氧自流平连混凝土基层处理 | C92: 1.界面剂一道 2.20mm厚C20细石混凝土垫层，双向Φ6钢筋@150 3.10mm厚1：3水泥砂浆保护层 4.1.5mm厚聚氨酯防水涂膜 5.自流平界面剂 6.水泥基自流平砂浆层 7.底涂层+3mm厚环氧树脂深灰色自流平+超耐磨面层；半哑光无高亮反光；保证完成后地面不会与轮胎产生化学反应印记；不开裂；不脱层； | D92: 室内装饰装修工程 | E92: 按设计图示尺寸面积计算 | F92: m2 | G92: 5000 | H92: =SUM(I92:N92) -> 227.35931 | I92: 43.498225 | J92: 180 | K92: 1.61 | L92: =(I92+J92+K92)*'2-报价汇总'!$H$5 -> 2.2510823 | M92: =(I92+J92+K92+L92)*'2-报价汇总'!$I$5 -> 0 | N92: =(M92+L92+K92+J92+I92)*'2-报价汇总'!$J$5 -> 0 | O92: =G92*H92 -> 1136796.5
A93: 2.1.3.13 | B93: 地面3mm环氧自流平 | C93: 1.自流平界面剂 2水泥基自流平砂浆层 3.底涂层+3mm厚环氧树脂深灰色自流平+超耐磨面层； 4.半哑光无高亮反光； 5.保证完成后地面不会与轮胎产生化学反应印记； 6.不开裂；不脱层； | D93: 室内装饰装修工程 | E93: 按设计图示尺寸面积计算 | F93: m2 | G93: 11637.3 | H93: =SUM(I93:N93) -> 131.16883 | I93: 29.16013 | J93: 100 | K93: 0.71 | L93: =(I93+J93+K93)*'2-报价汇总'!$H$5 -> 1.2987013 | M93: =(I93+J93+K93+L93)*'2-报价汇总'!$I$5 -> 0 | N93: =(M93+L93+K93+J93+I93)*'2-报价汇总'!$J$5 -> 0 | O93: =G93*H93 -> 1526451.1
A94: 2.1.3.14 | B94: 地面3mm环氧自流平 | C94: 1.原地面打磨找平 2.地面清理修补 3.底涂层+3mm厚环氧树脂深灰色自流平 4.半哑光无高亮反光 5.保证完成后地面不会与轮胎产生化学反应印记 6.不开裂；不脱层；（含超耐磨面层） | D94: 室内、室外装饰装修项目 | E94: 按设计图示尺寸面积计算 | F94: m2 | G94: 5000 | H94: =SUM(I94:N94) -> 118.05195 | I94: 15.683117 | J94: 100 | K94: 1.2 | L94: =(I94+J94+K94)*'2-报价汇总'!$H$5 -> 1.1688312 | M94: =(I94+J94+K94+L94)*'2-报价汇总'!$I$5 -> 0 | N94: =(M94+L94+K94+J94+I94)*'2-报价汇总'!$J$5 -> 0 | O94: =G94*H94 -> 590259.74
A95: 2.1.3.15 | B95: 机房防静电架空地板 | C95: 1.基层处理 2.地面防尘漆 3.防静电架空地板 | D95: IT机房 | E95: 按设计图示尺寸面积计算 | F95: m2 | G95: 6836.3557 | H95: =SUM(I95:N95) -> 257.96537 | I95: 52.861255 | J95: 200 | K95: 2.55 | L95: =(I95+J95+K95)*'2-报价汇总'!$H$5 -> 2.5541126 | M95: =(I95+J95+K95+L95)*'2-报价汇总'!$I$5 -> 0 | N95: =(M95+L95+K95+J95+I95)*'2-报价汇总'!$J$5 -> 0 | O95: =G95*H95 -> 1763543
A96: 2.1.3.16 | B96: 地面铺贴500*500地毯 | C96: 1.地面基层处理 2.地面涂刷界面剂 3.铺贴胶片 4.500*500地毯 | D96: 室内装饰装修项目 | E96: 按设计图示尺寸面积计算 | F96: m2 | G96: 5000 | H96: =SUM(I96:N96) -> 122.42424 | I96: 39.692121 | J96: 80 | K96: 1.52 | L96: =(I96+J96+K96)*'2-报价汇总'!$H$5 -> 1.2121212 | M96: =(I96+J96+K96+L96)*'2-报价汇总'!$I$5 -> 0 | N96: =(M96+L96+K96+J96+I96)*'2-报价汇总'!$J$5 -> 0 | O96: =G96*H96 -> 612121.21
A97: 2.1.3.17 | B97: 楼梯地毯 | C97: 1.500*500地面地毯铺装（含收边处理、胶垫、成品防滑条） *包含消耗量，品牌：以品牌清单要求为准 | D97: 室内、室外楼梯间 | E97: 按设计图示尺寸面积计算 | F97: m2 | G97: 5000 | H97: =SUM(I97:N97) -> 122.42424 | I97: 56.992121 | J97: 60 | K97: 4.22 | L97: =(I97+J97+K97)*'2-报价汇总'!$H$5 -> 1.2121212 | M97: =(I97+J97+K97+L97)*'2-报价汇总'!$I$5 -> 0 | N97: =(M97+L97+K97+J97+I97)*'2-报价汇总'!$J$5 -> 0 | O97: =G97*H97 -> 612121.21
A98: 2.1.3.18 | B98: 楼梯防滑条 | C98: 1.成品防滑条 | D98: 室内、室外楼梯间 | E98: 按设计图示尺寸延长米计算 | F98: m | G98: 5000 | H98: =SUM(I98:N98) -> 27.982684 | I98: 7.3956277 | J98: 20 | K98: 0.31 | L98: =(I98+J98+K98)*'2-报价汇总'!$H$5 -> 0.27705628 | M98: =(I98+J98+K98+L98)*'2-报价汇总'!$I$5 -> 0 | N98: =(M98+L98+K98+J98+I98)*'2-报价汇总'!$J$5 -> 0 | O98: =G98*H98 -> 139913.42
A99: 2.1.3.19 | B99: 地面防水 | C99: 1.从门口处至地漏找1％的坡，随打随抹平（防水找平层） 2.1.5厚聚氨酯防水涂膜 3.聚合物水泥砂浆两道防水保护层 4.24H闭水试验 | D99: 卫生间、淋浴室、洗车房、车间排水沟 | E99: 按设计图示尺寸面积计算 | F99: m2 | G99: 152467.14 | H99: =SUM(I99:N99) -> 56.839827 | I99: 15.727056 | J99: 40 | K99: 0.55 | L99: =(I99+J99+K99)*'2-报价汇总'!$H$5 -> 0.56277056 | M99: =(I99+J99+K99+L99)*'2-报价汇总'!$I$5 -> 0 | N99: =(M99+L99+K99+J99+I99)*'2-报价汇总'!$J$5 -> 0 | O99: =G99*H99 -> 8666205.8
... A102: 2.1.3.22 | B102: 室外坡道 | C102: 1.混凝土面层（含防滑处理） 2.150厚C25钢筋混凝土基层（含基层开挖） | D102: 室外装饰装修项目 | E102: 按设计图示尺寸面积计算 | F102: m2 | G102: 5000 | H102: =SUM(I102:N102) -> 191.55022 | I102: 68.51368 | J102: 120 | K102: 1.14 | L102: =(I102+J102+K102)*'2-报价汇总'!$H$5 -> 1.8965368 | M102: =(I102+J102+K102+L102)*'2-报价汇总'!$I$5 -> 0 | N102: =(M102+L102+K102+J102+I102)*'2-报价汇总'!$J$5 -> 0 | O102: =G102*H102 -> 957751.08
A103: 2.1.3.23 | B103: 室外坡道 | C103: 1.面层3cm厚毛面花岗岩 2.150厚C25钢筋混凝土基层（含基层开挖） | E103: 按设计图示尺寸面积计算 | F103: m2 | G103: 16261.411 | H103: =SUM(I103:N103) -> 327.92208 | I103: 89.385325 | J103: 231.26 | K103: 4.03 | L103: =(I103+J103+K103)*'2-报价汇总'!$H$5 -> 3.2467532 | M103: =(I103+J103+K103+L103)*'2-报价汇总'!$I$5 -> 0 | N103: =(M103+L103+K103+J103+I103)*'2-报价汇总'!$J$5 -> 0 | O103: =G103*H103 -> 5332475.8
A104: 2.1.3.24 | B104: 入口处蹭脚垫 | C104: 1.嵌入式铝合金地垫； 2.3mm宽金属收边条，尼龙+铝合金） 3.混凝土基础 4.含不锈钢边、护角 | D104: 室内、室外装饰装修项目 | E104: 按设计图示尺寸面积计算 | F104: m2 | G104: 4812.7944 | H104: =SUM(I104:N104) -> 743.29004 | I104: 233.27074 | J104: 500 | K104: 2.66 | L104: =(I104+J104+K104)*'2-报价汇总'!$H$5 -> 7.3593074 | M104: =(I104+J104+K104+L104)*'2-报价汇总'!$I$5 -> 0 | N104: =(M104+L104+K104+J104+I104)*'2-报价汇总'!$J$5 -> 0 | O104: =G104*H104 -> 3577302.2
A105: 2.1.3.25 | B105: 卫生间混凝土砌筑高台250高 | C105: 1.基层处理 2.陶粒混凝土250厚 3.水泥砂浆找平 | D105: 室外装饰装修项目 | E105: 按设计图示尺寸面积计算 | F105: m2 | G105: 5000 | H105: =SUM(I105:N105) -> 129.41991 | I105: 37.088528 | J105: 90 | K105: 1.05 | L105: =(I105+J105+K105)*'2-报价汇总'!$H$5 -> 1.2813853 | M105: =(I105+J105+K105+L105)*'2-报价汇总'!$I$5 -> 0 | N105: =(M105+L105+K105+J105+I105)*'2-报价汇总'!$J$5 -> 0 | O105: =G105*H105 -> 647099.57
A106: 2.1.3.26 | B106: 卫生间地面开挖，深度：300高 | E106: 按设计图示尺寸面积计算 | F106: m2 | G106: 5000 | H106: =SUM(I106:N106) -> 62.418874 | I106: 58.900866 | J106: 0 | K106: 2.9 | L106: =(I106+J106+K106)*'2-报价汇总'!$H$5 -> 0.61800866 | M106: =(I106+J106+K106+L106)*'2-报价汇总'!$I$5 -> 0 | N106: =(M106+L106+K106+J106+I106)*'2-报价汇总'!$J$5 -> 0 | O106: =G106*H106 -> 312094.37
A107: 2.1.3.27 | B107: 淋浴间挡水台 | C107: 1.基层处理 2.混凝土基层 3.聚氨酯防水 3.同淋浴间地面瓷砖 | D107: 淋浴间、卫生间 | E107: 按设计图示尺寸延长米计算 | F107: m | G107: 5000 | H107: =SUM(I107:N107) -> 48.095238 | I107: 12.079048 | J107: 35 | K107: 0.54 | L107: =(I107+J107+K107)*'2-报价汇总'!$H$5 -> 0.47619048 | M107: =(I107+J107+K107+L107)*'2-报价汇总'!$I$5 -> 0 | N107: =(M107+L107+K107+J107+I107)*'2-报价汇总'!$J$5 -> 0 | O107: =G107*H107 -> 240476.19
A108: 2.1.3.28 | B108: 过门石 | C108: 1.地面瓷砖铺装（含切割、磨边、勾缝） 2.基层处理，2cm厚粘结层 3.素水泥砂浆一道(内掺建筑胶） 4.2cm厚1：2.5水泥砂浆找平层 5.原有地面机械刨铣，深度大于3公分，整体做法5公分 *包含消耗量，品牌：以品牌清单要求为准 | D108: 室内、室外装饰装修项目 | E108: 按设计图示尺寸面积计算 | F108: m2 | G108: 5000 | H108: =SUM(I108:N108) -> 163.59377 | I108: 50.314026 | J108: 110 | K108: 1.66 | L108: =(I108+J108+K108)*'2-报价汇总'!$H$5 -> 1.6197403 | M108: =(I108+J108+K108+L108)*'2-报价汇总'!$I$5 -> 0 | N108: =(M108+L108+K108+J108+I108)*'2-报价汇总'!$J$5 -> 0 | O108: =G108*H108 -> 817968.83
A109: 2.1.3.29 | B109: PDI工位地沟防护网 | E109: 按设计图示尺寸面积计算 | F109: m2 | G109: 5000 | H109: =SUM(I109:N109) -> 34.978355 | I109: 4.1320346 | J109: 30 | K109: 0.5 | L109: =(I109+J109+K109)*'2-报价汇总'!$H$5 -> 0.34632035 | M109: =(I109+J109+K109+L109)*'2-报价汇总'!$I$5 -> 0 | N109: =(M109+L109+K109+J109+I109)*'2-报价汇总'!$J$5 -> 0 | O109: =G109*H109 -> 174891.77
A110: 2.1.3.30 | B110: 交付大厅地面工位划线（白色热融漆划线） （1）地面白色车位线200mm宽 | E110: 按设计图示尺寸延长米计算 | F110: m | G110: 5000 | H110: =SUM(I110:N110) -> 13.116883 | I110: 2.487013 | J110: 10 | K110: 0.5 | L110: =(I110+J110+K110)*'2-报价汇总'!$H$5 -> 0.12987013 | M110: =(I110+J110+K110+L110)*'2-报价汇总'!$I$5 -> 0 | N110: =(M110+L110+K110+J110+I110)*'2-报价汇总'!$J$5 -> 0 | O110: =G110*H110 -> 65584.416
A111: 2.1.3.31 | B111: 地面基层竹胶板（钢结构基层上铺设） | C111: 1.地面清理 2.地面满铺竹胶板 | E111: 按设计图示尺寸面积计算 | F111: m2 | G111: 5000 | H111: =SUM(I111:N111) -> 94.441558 | I111: 7.4064935 | J111: 85 | K111: 1.1 | L111: =(I111+J111+K111)*'2-报价汇总'!$H$5 -> 0.93506494 | M111: =(I111+J111+K111+L111)*'2-报价汇总'!$I$5 -> 0 | N111: =(M111+L111+K111+J111+I111)*'2-报价汇总'!$J$5 -> 0 | O111: =G111*H111 -> 472207.79
A112: 2.1.3.32 | B112: 地面实心不锈钢条收口（3mm厚） | D112: 室内、室外装饰装修项目 | E112: 按设计图示尺寸延长米计算 | F112: m | G112: 55237.754 | H112: =SUM(I112:N112) -> 43.719971 | I112: 5.0570996 | J112: 38 | K112: 0.23 | L112: =(I112+J112+K112)*'2-报价汇总'!$H$5 -> 0.432871 | M112: =(I112+J112+K112+L112)*'2-报价汇总'!$I$5 -> 0 | N112: =(M112+L112+K112+J112+I112)*'2-报价汇总'!$J$5 -> 0 | O112: =G112*H112 -> 2414993
A113: 2.1.3.33 | B113: 换排水沟上树脂篦子（小孔）盖板 | C113: 1.原有排水沟修整清理 2.拆除原有排水篦子盖板 3.提供安装树脂篦子（小孔） | D113: 室内、室外装饰装修项目 | E113: 按设计图示尺寸延长米计算 | F113: m | G113: 117890.68 | H113: =SUM(I113:N113) -> 78.700074 | I113: 10.440866 | J113: 65 | K113: 2.48 | L113: =(I113+J113+K113)*'2-报价汇总'!$H$5 -> 0.77920866 | M113: =(I113+J113+K113+L113)*'2-报价汇总'!$I$5 -> 0 | N113: =(M113+L113+K113+J113+I113)*'2-报价汇总'!$J$5 -> 0 | O113: =G113*H113 -> 9278004.9
A114: 2.1.3.34 | B114: 3：7灰土回填 1、夯实系数≥95 | C114: 1.3:7灰土回填 2.夯实系数≥95 | D114: 室内、室外装饰装修项目 | E114: 按设计图示尺寸体积计算 | F114: m3 | G114: 5000 | H114: =SUM(I114:N114) -> 147.7832 | I114: 72.67 | J114: 72 | K114: 1.65 | L114: =(I114+J114+K114)*'2-报价汇总'!$H$5 -> 1.4632 | M114: =(I114+J114+K114+L114)*'2-报价汇总'!$I$5 -> 0 | N114: =(M114+L114+K114+J114+I114)*'2-报价汇总'!$J$5 -> 0 | O114: =G114*H114 -> 738916
A115: 2.1.3.35 | B115: 素土回填 1、夯实系数≥95 | C115: 1.素土回填 2.夯实系数≥95 | D115: 室内、室外装饰装修项目 | E115: 按设计图示尺寸体积计算 | F115: m3 | G115: 5000 | H115: =SUM(I115:N115) -> 100.56277 | I115: 77.5671 | J115: 20 | K115: 2 | L115: =(I115+J115+K115)*'2-报价汇总'!$H$5 -> 0.995671 | M115: =(I115+J115+K115+L115)*'2-报价汇总'!$I$5 -> 0 | N115: =(M115+L115+K115+J115+I115)*'2-报价汇总'!$J$5 -> 0 | O115: =G115*H115 -> 502813.85
A116: 2.1.3.36 | B116: 胶地板地面 | C116: 1、自流平找平 2、防滑胶地板 3、耐磨层厚度：卷材0.35mm，片材0.25mm | D116: 室内、室外装饰装修项目 | E116: 按设计图示尺寸面积计算 | F116: m2 | G116: 5000 | H116: =SUM(I116:N116) -> 87.445887 | I116: 25.740087 | J116: 60 | K116: 0.84 | L116: =(I116+J116+K116)*'2-报价汇总'!$H$5 -> 0.86580087 | M116: =(I116+J116+K116+L116)*'2-报价汇总'!$I$5 -> 0 | N116: =(M116+L116+K116+J116+I116)*'2-报价汇总'!$J$5 -> 0 | O116: =G116*H116 -> 437229.44
A117: 2.1.3.37 | B117: 原洗车房地垫（原有地面找平后铺贴） (1)树脂盖板，小孔 | C117: 1.原洗车房地垫拆除 2.原有基础修补找平 3.树脂篦子（小孔）供应安装 | D117: 室内、室外装饰装修项目 | E117: 按设计图示尺寸面积计算 | F117: m2 | G117: 5000 | H117: =SUM(I117:N117) -> 113.67965 | I117: 10.074113 | J117: 100 | K117: 2.48 | L117: =(I117+J117+K117)*'2-报价汇总'!$H$5 -> 1.1255411 | M117: =(I117+J117+K117+L117)*'2-报价汇总'!$I$5 -> 0 | N117: =(M117+L117+K117+J117+I117)*'2-报价汇总'!$J$5 -> 0 | O117: =G117*H117 -> 568398.27
A118: 2.1.3.38 | B118: 危险品库房地面导油槽 | C118: 1.混凝土地面导油槽 | D118: 室内、室外装饰装修项目 | E118: 按设计图示尺寸延长米计算 | F118: m | G118: 7232.8643 | H118: =SUM(I118:N118) -> 52.467532 | I118: 20.348052 | J118: 30 | K118: 1.6 | L118: =(I118+J118+K118)*'2-报价汇总'!$H$5 -> 0.51948052 | M118: =(I118+J118+K118+L118)*'2-报价汇总'!$I$5 -> 0 | N118: =(M118+L118+K118+J118+I118)*'2-报价汇总'!$J$5 -> 0 | O118: =G118*H118 -> 379490.54
A119: 2.1.3.39 | B119: 原有排水篦子盖板拆除 | C119: 1.拆除原有排水篦子 2.垃圾清理及垃圾外运 | D119: 室内、室外装饰装修项目 | E119: 按设计图示尺寸延长米计算 | F119: m | G119: 5000 | H119: =SUM(I119:N119) -> 4.3722944 | I119: 4.3290043 | J119: 0 | K119: 0 | L119: =(I119+J119+K119)*'2-报价汇总'!$H$5 -> 0.043290043 | M119: =(I119+J119+K119+L119)*'2-报价汇总'!$I$5 -> 0 | N119: =(M119+L119+K119+J119+I119)*'2-报价汇总'!$J$5 -> 0 | O119: =G119*H119 -> 21861.472
A120: 2.1.3.40 | B120: 局部地面瓷砖修补 | C120: 1.局部地面瓷砖拆除 2.瓷砖专用粘结剂 3.修补瓷砖面层 4.切割、磨边、勾缝 5.垃圾清理及垃圾外运 | D120: 室内、室外装饰装修项目 | E120: 按设计图示尺寸面积计算 | F120: m2 | G120: 5000 | H120: =SUM(I120:N120) -> 218.61472 | I120: 93.290216 | J120: 120 | K120: 3.16 | L120: =(I120+J120+K120)*'2-报价汇总'!$H$5 -> 2.1645022 | M120: =(I120+J120+K120+L120)*'2-报价汇总'!$I$5 -> 0 | N120: =(M120+L120+K120+J120+I120)*'2-报价汇总'!$J$5 -> 0 | O120: =G120*H120 -> 1093073.6
A121: 2.1.3.41 | B121: 交付大厅地砖 | C121: 1.600*600地面瓷砖铺装（含切割、磨边、勾缝） 2.基层处理，粘结层 3.素水泥砂浆一道(内掺建筑胶） 4.1：2.5水泥砂浆找平层 5.原有地面机械刨铣，深度大于3公分 *包含消耗量，品牌：以品牌清单要求为准 | E121: 按设计图示尺寸以面积计算 | F121: m2 | G121: 5000 | H121: =SUM(I121:N121) -> 144.00152 | I121: 56.075758 | J121: 85 | K121: 1.5 | L121: =(I121+J121+K121)*'2-报价汇总'!$H$5 -> 1.4257576 | M121: =(I121+J121+K121+L121)*'2-报价汇总'!$I$5 -> 0 | N121: =(M121+L121+K121+J121+I121)*'2-报价汇总'!$J$5 -> 0 | O121: =G121*H121 -> 720007.58
A122: 2.1.3.42 | B122: 灰色过门石连基层处理 | C122: 1.灰色过门石铺装（含切割、磨边、勾缝） 2.素水泥砂浆一道(内掺建筑胶） 3.水泥砂浆粘结层 4.包含消耗量 | E122: 按设计图示尺寸以面积计算 | F122: m2 | G122: 5000 | H122: =SUM(I122:N122) -> 121.67877 | I122: 50.314026 | J122: 68.5 | K122: 1.66 | L122: =(I122+J122+K122)*'2-报价汇总'!$H$5 -> 1.2047403 | M122: =(I122+J122+K122+L122)*'2-报价汇总'!$I$5 -> 0 | N122: =(M122+L122+K122+J122+I122)*'2-报价汇总'!$J$5 -> 0 | O122: =G122*H122 -> 608393.83
A123: 2.1.3.43 | B123: 原地面打磨，面刷两遍透明地固 | E123: 按设计图示尺寸以面积计算 | F123: m2 | G123: 5000 | H123: =SUM(I123:N123) -> 10.15555 | I123: 4 | J123: 5 | K123: 1.055 | L123: =(I123+J123+K123)*'2-报价汇总'!$H$5 -> 0.10055 | M123: =(I123+J123+K123+L123)*'2-报价汇总'!$I$5 -> 0 | N123: =(M123+L123+K123+J123+I123)*'2-报价汇总'!$J$5 -> 0 | O123: =G123*H123 -> 50777.75
A124: 2.1.3.44 | B124: 车间排水沟&排水篦子 | C124: 1.C20混凝土基础，含L型角铁 2.树脂篦子，小孔 3.地面开挖及回填 4.基础宽800mm，篦子宽200mm | E124: 按设计图示尺寸延长米计算 | F124: m | G124: 5000 | H124: =SUM(I124:N124) -> 255.41719 | I124: =106.548311688312-13.8 -> 92.748312 | J124: 155 | K124: 5.14 | L124: =(I124+J124+K124)*'2-报价汇总'!$H$5 -> 2.5288831 | M124: =(I124+J124+K124+L124)*'2-报价汇总'!$I$5 -> 0 | N124: =(M124+L124+K124+J124+I124)*'2-报价汇总'!$J$5 -> 0 | O124: =G124*H124 -> 1277086 | P124: 位置：车间
A125: 2.1.3.45 | B125: 车间排水沟&排水篦子 | C125: 1.C20混凝土基础，含L型角铁 2.树脂篦子，小孔 3.地面开挖及回填 4.基础宽800mm，篦子宽300mm | E125: 按设计图示尺寸延长米计算 | F125: m | G125: 5000 | H125: =SUM(I125:N125) -> 270.56719 | I125: =106.548311688312-13.8 -> 92.748312 | J125: 170 | K125: 5.14 | L125: =(I125+J125+K125)*'2-报价汇总'!$H$5 -> 2.6788831 | M125: =(I125+J125+K125+L125)*'2-报价汇总'!$I$5 -> 0 | N125: =(M125+L125+K125+J125+I125)*'2-报价汇总'!$J$5 -> 0 | O125: =G125*H125 -> 1352836 | P125: 位置：洗车区
B126: 补充项
B127: 小 计
A128: 2.1.4 | B128: 天花工程
A129: 2.1.4.01 | B129: 裸顶喷涂料 | C129: 1.白色乳胶漆，找补腻子 2.管线、设备表面全部喷涂 3.原基础层修补 | D129: 室内装饰装修项目 | E129: 按投影面积计算 | F129: m2 | G129: 671890.31 | H129: =SUM(I129:N129) -> 24.484848 | I129: 23.462424 | J129: 0.23 | K129: 0.55 | L129: =(I129+J129+K129)*'2-报价汇总'!$H$5 -> 0.24242424 | M129: =(I129+J129+K129+L129)*'2-报价汇总'!$I$5 -> 0 | N129: =(M129+L129+K129+J129+I129)*'2-报价汇总'!$J$5 -> 0 | O129: =G129*H129 -> 16451132
A130: 2.1.4.02 | B130: 裸顶喷涂料 | C130: 1.黑/灰色乳胶漆，找补腻子 2.管线、设备表面全部喷涂 3.原基础层修补 | D130: 室内装饰装修项目 | E130: 按投影面积计算 | F130: m2 | G130: 671890.31 | H130: =SUM(I130:N130) -> 24.484848 | I130: 23.462424 | J130: 0.23 | K130: 0.55 | L130: =(I130+J130+K130)*'2-报价汇总'!$H$5 -> 0.24242424 | M130: =(I130+J130+K130+L130)*'2-报价汇总'!$I$5 -> 0 | N130: =(M130+L130+K130+J130+I130)*'2-报价汇总'!$J$5 -> 0 | O130: =G130*H130 -> 16451132
A131: 2.1.4.03 | B131: 轻钢龙骨双层石膏板吊顶 | C131: 1.直径8钢筋吊杆，中距横向≤1200，纵向≤1100 2.U型轻钢主龙骨CB50*20，中距≤1200 3.9.5mm双层石膏板，表面刮腻子、刷白色防水乳胶漆 | D131: 室内装饰装修项目 | E131: 按设计图示尺寸面积计算 | F131: m2 | G131: 1014773.6 | H131: =SUM(I131:N131) -> 148.65801 | I131: 57.076147 | J131: 85 | K131: 5.11 | L131: =(I131+J131+K131)*'2-报价汇总'!$H$5 -> 1.4718615 | M131: =(I131+J131+K131+L131)*'2-报价汇总'!$I$5 -> 0 | N131: =(M131+L131+K131+J131+I131)*'2-报价汇总'!$J$5 -> 0 | O131: =G131*H131 -> 1.5085422e+08
A132: 2.1.4.04 | B132: 轻钢龙骨双层防水石膏板吊顶 | C132: 1.直径8钢筋吊杆，中距横向≤1200，纵向≤1100 2.U型轻钢主龙骨CB50*20，中距≤1200 3.9.5mm双层防水石膏板，表面刮腻子、刷白色防水乳胶漆 | D132: 卫生间 | E132: 按设计图示尺寸面积计算 | F132: m2 | G132: 59476.295 | H132: =SUM(I132:N132) -> 157.4026 | I132: 55.734156 | J132: 95 | K132: 5.11 | L132: =(I132+J132+K132)*'2-报价汇总'!$H$5 -> 1.5584416 | M132: =(I132+J132+K132+L132)*'2-报价汇总'!$I$5 -> 0 | N132: =(M132+L132+K132+J132+I132)*'2-报价汇总'!$J$5 -> 0 | O132: =G132*H132 -> 9361723.3
A133: 2.1.4.05 | B133: 轻钢龙骨矿棉板吊顶 | C133: 1.直径8钢筋吊杆，中距横向≤1200，纵向≤1100 2.U型轻钢主龙骨CB50*20，中距≤1200 3.矿棉板与龙骨固定 | D133: 办公区、辅房 | E133: 按设计图示尺寸面积计算 | F133: m2 | G133: 399962.36 | H133: =SUM(I133:N133) -> 100.56277 | I133: 24.7671 | J133: 70 | K133: 4.8 | L133: =(I133+J133+K133)*'2-报价汇总'!$H$5 -> 0.995671 | M133: =(I133+J133+K133+L133)*'2-报价汇总'!$I$5 -> 0 | N133: =(M133+L133+K133+J133+I133)*'2-报价汇总'!$J$5 -> 0 | O133: =G133*H133 -> 40221323
A134: 2.1.4.06 | B134: 天花铝扣板300mm*300mm | C134: 1.10厚镀锌低碳钢丝吊杆，双向中距≤1200，吊杆上部与檩条固定 2.与暗架式配套的专用上层主龙骨。间距≤1200，用吊件与钢筋吊杆连接后找平 3.与铝合金方板配套的专用下层副龙骨连接，间距≤600 4.铝扣板与配套专用龙骨固定 | D134: 淋浴室、卫生间 | E134: 按设计图示尺寸面积计算 | F134: m2 | G134: 58236.635 | H134: =SUM(I134:N134) -> 110.60156 | I134: 25.496494 | J134: 80 | K134: 4.01 | L134: =(I134+J134+K134)*'2-报价汇总'!$H$5 -> 1.0950649 | M134: =(I134+J134+K134+L134)*'2-报价汇总'!$I$5 -> 0 | N134: =(M134+L134+K134+J134+I134)*'2-报价汇总'!$J$5 -> 0 | O134: =G134*H134 -> 6441062.6
A135: 2.1.4.07 | B135: 石膏板暗藏式检修口 | C135: 1.规格：600mm*600mm | D135: 室内装饰装修项目 | E135: 按设计图示数量计算 | F135: 个 | G135: 10938.169 | H135: =SUM(I135:N135) -> 131.16883 | I135: 67.87013 | J135: 60 | K135: 2 | L135: =(I135+J135+K135)*'2-报价汇总'!$H$5 -> 1.2987013 | M135: =(I135+J135+K135+L135)*'2-报价汇总'!$I$5 -> 0 | N135: =(M135+L135+K135+J135+I135)*'2-报价汇总'!$J$5 -> 0 | O135: =G135*H135 -> 1434746.9
A136: 2.1.4.08 | B136: 条形灯上方镀锌方管灯架 | C136: 1.方钢规格50mm*50mm 2.方钢厚度3mm 3.所有电线走方钢管内 4.镀锌方钢同天花颜色 | D136: 室内装饰装修项目 | E136: 按设计图示尺寸延长米计算 | F136: m | G136: 673499.53 | H136: =SUM(I136:N136) -> 48.095238 | I136: 17.419048 | J136: 30 | K136: 0.2 | L136: =(I136+J136+K136)*'2-报价汇总'!$H$5 -> 0.47619048 | M136: =(I136+J136+K136+L136)*'2-报价汇总'!$I$5 -> 0 | N136: =(M136+L136+K136+J136+I136)*'2-报价汇总'!$J$5 -> 0 | O136: =G136*H136 -> 32392120
A137: 2.1.4.09 | B137: 天花反支撑 | D137: 室内装饰装修项目 | E137: 板底至吊顶高度≥1.5m＜2m 按设计图示尺寸面积计算 | F137: m2 | G137: 673499.53 | H137: =SUM(I137:N137) -> 34.978355 | I137: 6.2020346 | J137: 28.03 | K137: 0.4 | L137: =(I137+J137+K137)*'2-报价汇总'!$H$5 -> 0.34632035 | M137: =(I137+J137+K137+L137)*'2-报价汇总'!$I$5 -> 0 | N137: =(M137+L137+K137+J137+I137)*'2-报价汇总'!$J$5 -> 0 | O137: =G137*H137 -> 23557906
A138: 2.1.4.10 | B138: 天花钢结构转换层 | C138: 1.型材规格50*50角钢 | D138: 室内装饰装修项目 | E138: 板底至吊顶高度＞2m 按设计图示尺寸面积计算 | F138: m2 | G138: 677036.21 | H138: =SUM(I138:N138) -> 90.799 | I138: 51 | J138: 38 | K138: 0.9 | L138: =(I138+J138+K138)*'2-报价汇总'!$H$5 -> 0.899 | M138: =(I138+J138+K138+L138)*'2-报价汇总'!$I$5 -> 0 | N138: =(M138+L138+K138+J138+I138)*'2-报价汇总'!$J$5 -> 0 | O138: =G138*H138 -> 61474211
A139: 2.1.4.11 | B139: 窗帘盒 | C139: 1.窗帘盒材质、规格:18mm厚防火阻燃板，9.5mm厚纸面石膏板 2.防护材料种类:木基层作三防处理，石膏板表面刷白色防水乳胶漆 3.其他:满足设计要求及施工规范 | D139: 室内装饰装修项目 | E139: 按设计图示尺寸延长米计算 | F139: m | G139: 5000 | H139: =SUM(I139:N139) -> 73.88303 | I139: 22.051515 | J139: 50 | K139: 1.1 | L139: =(I139+J139+K139)*'2-报价汇总'!$H$5 -> 0.73151515 | M139: =(I139+J139+K139+L139)*'2-报价汇总'!$I$5 -> 0 | N139: =(M139+L139+K139+J139+I139)*'2-报价汇总'!$J$5 -> 0 | O139: =G139*H139 -> 369415.15
A140: 2.1.4.12 | B140: 供应及安装半遮光卷帘 | C140: 1.成品半遮光卷帘供应及安装 | E140: 按设计图示尺寸面积计算 | F140: m2 | G140: 5000 | H140: =SUM(I140:N140) -> 43.722944 | I140: 8.0900433 | J140: 35 | K140: 0.2 | L140: =(I140+J140+K140)*'2-报价汇总'!$H$5 -> 0.43290043 | M140: =(I140+J140+K140+L140)*'2-报价汇总'!$I$5 -> 0 | N140: =(M140+L140+K140+J140+I140)*'2-报价汇总'!$J$5 -> 0 | O140: =G140*H140 -> 218614.72
...

Sheet 2.2-电气工程
A1: 理想汽车中心店电气工程量清单
A2: ='2.1-装饰工程'!A2 -> 注意：此报价清单每项不得随意更改、删减，如有任何增加项请务必在每大项最后“补充项“中列举，补充项及说明字体颜色均采用蓝色；且所有项目都需要填写。
A3: 序号 | B3: 名 称 | C3: 项目特征 | D3: 适用范围 | E3: 工程量计算规则 | F3: 单位 | G3: 24/25年暂估工程量 | H3: 综合单价 | I3: 人工费 | J3: 材料费 | K3: 机械费 | L3: 安措费 | M3: 管理费 | N3: 利润 | O3: 24/25年暂估总价 | P3: 备注
B4: 2.2电气工程
A5: 2.2.1 | B5: 配电部分
B6: 新增配电箱（除空开外一切配套附件）
A7: 2.2.1.01 | B7: 移位配电箱 | C7: 1.拆除原有配电箱 2.安装利旧原有配电箱 3.元配电箱元器件检测 | D7: 室内、室外装饰装修项目 | E7: 按设计图示数量计算 | F7: 个 | G7: 100 | H7: =SUM(I7:N7) -> 507.18615 | I7: 408.2645 | J7: 88.89 | K7: 5.01 | L7: =(I7+J7+K7)*'2-报价汇总'!$H$5 -> 5.021645 | M7: =(I7+J7+K7+L7)*'2-报价汇总'!$I$5 -> 0 | N7: =(M7+L7+K7+J7+I7)*'2-报价汇总'!$J$5 -> 0 | O7: =G7*H7 -> 50718.615
A8: 2.2.1.02 | B8: 总配电箱箱体 | C8: 1000*1200以上规格 | D8: 室内、室外装饰装修项目 | E8: 按设计图示数量计算 包含配套铜排及落地安装基础、接地等 | F8: 个 | G8: 800 | H8: =SUM(I8:N8) -> 2273.5931 | I8: 598.35498 | J8: 1600 | K8: 52.727273 | L8: =(I8+J8+K8)*'2-报价汇总'!$H$5 -> 22.510823 | M8: =(I8+J8+K8+L8)*'2-报价汇总'!$I$5 -> 0 | N8: =(M8+L8+K8+J8+I8)*'2-报价汇总'!$J$5 -> 0 | O8: =G8*H8 -> 1818874.5
A9: 2.2.1.03 | B9: 一级配电箱 | C9: 800*1000以上规格 | D9: 室内、室外装饰装修项目 | F9: 个 | G9: 1823.0282 | H9: =SUM(I9:N9) -> 1748.9177 | I9: 525.10173 | J9: 1200 | K9: 6.5 | L9: =(I9+J9+K9)*'2-报价汇总'!$H$5 -> 17.316017 | M9: =(I9+J9+K9+L9)*'2-报价汇总'!$I$5 -> 0 | N9: =(M9+L9+K9+J9+I9)*'2-报价汇总'!$J$5 -> 0 | O9: =G9*H9 -> 3188326.4
A10: 2.2.1.04 | B10: 二级配电箱 | D10: 室内、室外装饰装修项目 | E10: 按设计图示数量计算 | F10: 个 | G10: 4557.5705 | H10: =SUM(I10:N10) -> 664.58874 | I10: 193.14866 | J10: 461.08 | K10: 3.78 | L10: =(I10+J10+K10)*'2-报价汇总'!$H$5 -> 6.5800866 | M10: =(I10+J10+K10+L10)*'2-报价汇总'!$I$5 -> 0 | N10: =(M10+L10+K10+J10+I10)*'2-报价汇总'!$J$5 -> 0 | O10: =G10*H10 -> 3028910
A11: 2.2.1.05 | B11: 设备终端箱 | D11: 室内、室外装饰装修项目 | E11: 按设计图示数量计算 | F11: 个 | G11: 20053.31 | H11: =SUM(I11:N11) -> 524.67532 | I11: 56.950519 | J11: 459.19 | K11: 3.34 | L11: =(I11+J11+K11)*'2-报价汇总'!$H$5 -> 5.1948052 | M11: =(I11+J11+K11+L11)*'2-报价汇总'!$I$5 -> 0 | N11: =(M11+L11+K11+J11+I11)*'2-报价汇总'!$J$5 -> 0 | O11: =G11*H11 -> 10521477
A12: 2.2.1.06 | B12: 供应及安装成套配电箱，包括开箱检查、本体安装固定、箱内辅材、连接线缆、接地、调试等，一切如图纸及规范所述。 | D12: 室内、室外装饰装修项目 | E12: 按设计图示数量计算 | F12: 个 | G12: 27345.423 | H12: =SUM(I12:N12) -> 206.98442 | I12: 204.93506 | L12: =(I12+J12+K12)*'2-报价汇总'!$H$5 -> 2.0493506 | M12: =(I12+J12+K12+L12)*'2-报价汇总'!$I$5 -> 0 | N12: =(M12+L12+K12+J12+I12)*'2-报价汇总'!$J$5 -> 0 | O12: =G12*H12 -> 5660076.4
A13: 2.2.1.07 | B13: NB3-63 C16/1P | C13: 1.电气元器件及附件供应安装 2.接线、调试 | D13: 配电箱内 | E13: 按设计图示数量计算 | F13: 个 | G13: 41929.648 | H13: =SUM(I13:N13) -> 14.603463 | I13: 2.7588745 | J13: 11.37 | K13: 0.33 | L13: =(I13+J13+K13)*'2-报价汇总'!$H$5 -> 0.14458874 | M13: =(I13+J13+K13+L13)*'2-报价汇总'!$I$5 -> 0 | N13: =(M13+L13+K13+J13+I13)*'2-报价汇总'!$J$5 -> 0 | O13: =G13*H13 -> 612318.08
A14: 2.2.1.08 | B14: NB3-63 C16/2P | C14: 1.电气元器件及附件供应安装 2.接线、调试 | D14: 配电箱内 | E14: 按设计图示数量计算 | F14: 个 | G14: 76567.184 | H14: =SUM(I14:N14) -> 25.709091 | I14: 11.464545 | J14: 13.55 | K14: 0.44 | L14: =(I14+J14+K14)*'2-报价汇总'!$H$5 -> 0.25454545 | M14: =(I14+J14+K14+L14)*'2-报价汇总'!$I$5 -> 0 | N14: =(M14+L14+K14+J14+I14)*'2-报价汇总'!$J$5 -> 0 | O14: =G14*H14 -> 1968472.7
A15: 2.2.1.09 | B15: NB3-63 C16/3P | C15: 1.电气元器件及附件供应安装 2.接线、调试 | D15: 配电箱内 | E15: 按设计图示数量计算 | F15: 个 | G15: 15000 | H15: =SUM(I15:N15) -> 33.404329 | I15: 12.573593 | J15: 20.06 | K15: 0.44 | L15: =(I15+J15+K15)*'2-报价汇总'!$H$5 -> 0.33073593 | M15: =(I15+J15+K15+L15)*'2-报价汇总'!$I$5 -> 0 | N15: =(M15+L15+K15+J15+I15)*'2-报价汇总'!$J$5 -> 0 | O15: =G15*H15 -> 501064.94
A16: 2.2.1.10 | B16: NXB-63 D16/1P | C16: 1.电气元器件及附件供应安装 2.接线、调试 | D16: 配电箱内 | E16: 按设计图示数量计算 | F16: 个 | G16: 500 | H16: =SUM(I16:N16) -> 10.7471 | I16: 3.9406926 | J16: 6.37 | K16: 0.33 | L16: =(I16+J16+K16)*'2-报价汇总'!$H$5 -> 0.10640693 | M16: =(I16+J16+K16+L16)*'2-报价汇总'!$I$5 -> 0 | N16: =(M16+L16+K16+J16+I16)*'2-报价汇总'!$J$5 -> 0 | O16: =G16*H16 -> 5373.5498
A17: 2.2.1.11 | B17: NXB-63 D16/2P | C17: 1.电气元器件及附件供应安装 2.接线、调试 | D17: 配电箱内 | E17: 按设计图示数量计算 | F17: 个 | G17: 2000 | H17: =SUM(I17:N17) -> 24.047619 | I17: 9.8195238 | J17: 13.55 | K17: 0.44 | L17: =(I17+J17+K17)*'2-报价汇总'!$H$5 -> 0.23809524 | M17: =(I17+J17+K17+L17)*'2-报价汇总'!$I$5 -> 0 | N17: =(M17+L17+K17+J17+I17)*'2-报价汇总'!$J$5 -> 0 | O17: =G17*H17 -> 48095.238
A18: 2.2.1.12 | B18: NXB-63 D16/3P | C18: 1.电气元器件及附件供应安装 2.接线、调试 | D18: 配电箱内 | E18: 按设计图示数量计算 | F18: 个 | G18: 2000 | H18: =SUM(I18:N18) -> 33.404329 | I18: 12.573593 | J18: 20.06 | K18: 0.44 | L18: =(I18+J18+K18)*'2-报价汇总'!$H$5 -> 0.33073593 | M18: =(I18+J18+K18+L18)*'2-报价汇总'!$I$5 -> 0 | N18: =(M18+L18+K18+J18+I18)*'2-报价汇总'!$J$5 -> 0 | O18: =G18*H18 -> 66808.658
A19: 2.2.1.13 | B19: NXBLE-32 D16/4P(30mA) | C19: 1.电气元器件及附件供应安装 2.接线、调试 | D19: 配电箱内 | E19: 按设计图示数量计算 | F19: 个 | G19: 2000 | H19: =SUM(I19:N19) -> 84.997403 | I19: 35.215844 | J19: 48.5 | K19: 0.44 | L19: =(I19+J19+K19)*'2-报价汇总'!$H$5 -> 0.84155844 | M19: =(I19+J19+K19+L19)*'2-报价汇总'!$I$5 -> 0 | N19: =(M19+L19+K19+J19+I19)*'2-报价汇总'!$J$5 -> 0 | O19: =G19*H19 -> 169994.81
A20: 2.2.1.14 | B20: NB3-63 C20/1P | C20: 1.电气元器件及附件供应安装 2.接线、调试 | D20: 配电箱内 | E20: 按设计图示数量计算 | F20: 个 | G20: 2000 | H20: =SUM(I20:N20) -> 14.603463 | I20: 6.2188745 | J20: 7.8 | K20: 0.44 | L20: =(I20+J20+K20)*'2-报价汇总'!$H$5 -> 0.14458874 | M20: =(I20+J20+K20+L20)*'2-报价汇总'!$I$5 -> 0 | N20: =(M20+L20+K20+J20+I20)*'2-报价汇总'!$J$5 -> 0 | O20: =G20*H20 -> 29206.926
A21: 2.2.1.15 | B21: NB3-63 C20/2P | C21: 1.电气元器件及附件供应安装 2.接线、调试 | D21: 配电箱内 | E21: 按设计图示数量计算 | F21: 个 | G21: 4500 | H21: =SUM(I21:N21) -> 25.709091 | I21: 11.464545 | J21: 13.55 | K21: 0.44 | L21: =(I21+J21+K21)*'2-报价汇总'!$H$5 -> 0.25454545 | M21: =(I21+J21+K21+L21)*'2-报价汇总'!$I$5 -> 0 | N21: =(M21+L21+K21+J21+I21)*'2-报价汇总'!$J$5 -> 0 | O21: =G21*H21 -> 115690.91
A22: 2.2.1.16 | B22: NB3-63 C20/3P | C22: 1.电气元器件及附件供应安装 2.接线、调试 | D22: 配电箱内 | E22: 按设计图示数量计算 | F22: 个 | G22: 4500 | H22: =SUM(I22:N22) -> 33.780346 | I22: 16.505887 | J22: 16.5 | K22: 0.44 | L22: =(I22+J22+K22)*'2-报价汇总'!$H$5 -> 0.33445887 | M22: =(I22+J22+K22+L22)*'2-报价汇总'!$I$5 -> 0 | N22: =(M22+L22+K22+J22+I22)*'2-报价汇总'!$J$5 -> 0 | O22: =G22*H22 -> 152011.56
A23: 2.2.1.17 | B23: NXBLE-63 C20/2P（30mA） | C23: 1.电气元器件及附件供应安装 2.接线、调试 | D23: 配电箱内 | E23: 按设计图示数量计算 | F23: 个 | G23: 4500 | H23: =SUM(I23:N23) -> 54.741126 | I23: 11.929134 | J23: 41.83 | K23: 0.44 | L23: =(I23+J23+K23)*'2-报价汇总'!$H$5 -> 0.54199134 | M23: =(I23+J23+K23+L23)*'2-报价汇总'!$I$5 -> 0 | N23: =(M23+L23+K23+J23+I23)*'2-报价汇总'!$J$5 -> 0 | O23: =G23*H23 -> 246335.06
A24: 2.2.1.18 | B24: NXB-63 D20/1P | C24: 1.电气元器件及附件供应安装 2.接线、调试 | D24: 配电箱内 | E24: 按设计图示数量计算 | F24: 个 | G24: 4500 | H24: =SUM(I24:N24) -> 12.478528 | I24: 4.3149784 | J24: 7.6 | K24: 0.44 | L24: =(I24+J24+K24)*'2-报价汇总'!$H$5 -> 0.12354978 | M24: =(I24+J24+K24+L24)*'2-报价汇总'!$I$5 -> 0 | N24: =(M24+L24+K24+J24+I24)*'2-报价汇总'!$J$5 -> 0 | O24: =G24*H24 -> 56153.377
... A62: 2.2.1.56 | B62: NB6LE-63 C40/3P（30mA） | C62: 1.电气元器件及附件供应安装 2.接线、调试 | D62: 配电箱内 | E62: 按设计图示数量计算 | F62: 个 | G62: 300 | H62: =SUM(I62:N62) -> 89.3042 | I62: 15.49 | J62: 71.92 | K62: 1.01 | L62: =(I62+J62+K62)*'2-报价汇总'!$H$5 -> 0.8842 | M62: =(I62+J62+K62+L62)*'2-报价汇总'!$I$5 -> 0 | N62: =(M62+L62+K62+J62+I62)*'2-报价汇总'!$J$5 -> 0 | O62: =G62*H62 -> 26791.26
A63: 2.2.1.57 | B63: NXB-63/C25/4P、NXM-63/25A/4P | C63: 1.电气元器件及附件供应安装 2.接线、调试 | D63: 配电箱内 | E63: 按设计图示数量计算 | F63: 个 | G63: 6000 | H63: =SUM(I63:N63) -> 36.0873 | I63: 11.89 | J63: 23.4 | K63: 0.44 | L63: =(I63+J63+K63)*'2-报价汇总'!$H$5 -> 0.3573 | M63: =(I63+J63+K63+L63)*'2-报价汇总'!$I$5 -> 0 | N63: =(M63+L63+K63+J63+I63)*'2-报价汇总'!$J$5 -> 0 | O63: =G63*H63 -> 216523.8 | P63: 41.68
A64: 2.2.1.58 | B64: NXB-63/D20/4P | C64: 1.电气元器件及附件供应安装 2.接线、调试 | D64: 配电箱内 | E64: 按设计图示数量计算 | F64: 个 | G64: 6000 | H64: =SUM(I64:N64) -> 42.9452 | I64: 12.08 | J64: 30 | K64: 0.44 | L64: =(I64+J64+K64)*'2-报价汇总'!$H$5 -> 0.4252 | M64: =(I64+J64+K64+L64)*'2-报价汇总'!$I$5 -> 0 | N64: =(M64+L64+K64+J64+I64)*'2-报价汇总'!$J$5 -> 0 | O64: =G64*H64 -> 257671.2 | P64: 49.6
A65: 2.2.1.59 | B65: NXMLE-125/D63/3P（30mA） | C65: 1.电气元器件及附件供应安装 2.接线、调试 | D65: 配电箱内 | E65: 按设计图示数量计算 | F65: 个 | G65: 6000 | H65: =SUM(I65:N65) -> 135.5117 | I65: 26.71 | J65: 106.45 | K65: 1.01 | L65: =(I65+J65+K65)*'2-报价汇总'!$H$5 -> 1.3417 | M65: =(I65+J65+K65+L65)*'2-报价汇总'!$I$5 -> 0 | N65: =(M65+L65+K65+J65+I65)*'2-报价汇总'!$J$5 -> 0 | O65: =G65*H65 -> 813070.2 | P65: 156.52
A66: 2.2.1.60 | B66: ESC227P | C66: 1.电气元器件及附件供应安装 2.接线、调试 | D66: 配电箱内 | E66: 按设计图示数量计算 | F66: 个 | G66: 6000 | H66: =SUM(I66:N66) -> 301.1921 | I66: 128.58 | J66: 169.19 | K66: 0.44 | L66: =(I66+J66+K66)*'2-报价汇总'!$H$5 -> 2.9821 | M66: =(I66+J66+K66+L66)*'2-报价汇总'!$I$5 -> 0 | N66: =(M66+L66+K66+J66+I66)*'2-报价汇总'!$J$5 -> 0 | O66: =G66*H66 -> 1807152.6 | P66: 347.88
A67: 2.2.1.61 | B67: NXMLE-400/3P 250A（30mA） | C67: 1.电气元器件及附件供应安装 2.接线、调试 | D67: 配电箱内 | E67: 按设计图示数量计算 | F67: 个 | G67: 6000 | H67: =SUM(I67:N67) -> 378.0738 | I67: 100.32 | J67: 272.9105 | K67: 1.1 | L67: =(I67+J67+K67)*'2-报价汇总'!$H$5 -> 3.743305 | M67: =(I67+J67+K67+L67)*'2-报价汇总'!$I$5 -> 0 | N67: =(M67+L67+K67+J67+I67)*'2-报价汇总'!$J$5 -> 0 | O67: =G67*H67 -> 2268442.8 | P67: 436.68
A68: 2.2.1.62 | B68: NXBLE-63/C25 3P（30mA） | C68: 1.电气元器件及附件供应安装 2.接线、调试 | D68: 配电箱内 | E68: 按设计图示数量计算 | F68: 个 | G68: 6000 | H68: =SUM(I68:N68) -> 120.5839 | I68: 14.69 | J68: 103.6 | K68: 1.1 | L68: =(I68+J68+K68)*'2-报价汇总'!$H$5 -> 1.1939 | M68: =(I68+J68+K68+L68)*'2-报价汇总'!$I$5 -> 0 | N68: =(M68+L68+K68+J68+I68)*'2-报价汇总'!$J$5 -> 0 | O68: =G68*H68 -> 723503.4 | P68: 139.27
A69: 2.2.1.63 | B69: NM1-6300S/4300 630A 4极 | C69: 1.电气元器件及附件供应安装 2.接线、调试 | D69: 配电箱内 | E69: 按设计图示数量计算 | F69: 个 | G69: 6000 | H69: =SUM(I69:N69) -> 904.3237 | I69: 162.63 | J69: 731.73 | K69: 1.01 | L69: =(I69+J69+K69)*'2-报价汇总'!$H$5 -> 8.9537 | M69: =(I69+J69+K69+L69)*'2-报价汇总'!$I$5 -> 0 | N69: =(M69+L69+K69+J69+I69)*'2-报价汇总'!$J$5 -> 0 | O69: =G69*H69 -> 5425942.2 | P69: 1044.49
A70: 2.2.1.64 | B70: NM1-1250S/3300 1250A | C70: 1.电气元器件及附件供应安装 2.接线、调试 | D70: 配电箱内 | E70: 按设计图示数量计算 | F70: 个 | G70: 6000 | H70: =SUM(I70:N70) -> 2205.4158 | I70: 300.17 | J70: 1882.4 | K70: 1.01 | L70: =(I70+J70+K70)*'2-报价汇总'!$H$5 -> 21.8358 | M70: =(I70+J70+K70+L70)*'2-报价汇总'!$I$5 -> 0 | N70: =(M70+L70+K70+J70+I70)*'2-报价汇总'!$J$5 -> 0 | O70: =G70*H70 -> 13232495 | P70: 2547.26
A71: 2.2.1.65 | B71: NM1-630S/3300 500A | C71: 1.电气元器件及附件供应安装 2.接线、调试 | D71: 配电箱内 | E71: 按设计图示数量计算 | F71: 个 | G71: 6000 | H71: =SUM(I71:N71) -> 791.9309 | I71: 297.02 | J71: 486.06 | K71: 1.01 | L71: =(I71+J71+K71)*'2-报价汇总'!$H$5 -> 7.8409 | M71: =(I71+J71+K71+L71)*'2-报价汇总'!$I$5 -> 0 | N71: =(M71+L71+K71+J71+I71)*'2-报价汇总'!$J$5 -> 0 | O71: =G71*H71 -> 4751585.4 | P71: 914.68
A72: 2.2.1.66 | B72: NM1LE-400S/3300 315A 4极（30mA） | C72: 1.电气元器件及附件供应安装 2.接线、调试 | D72: 配电箱内 | E72: 按设计图示数量计算 | F72: 个 | G72: 6000 | H72: =SUM(I72:N72) -> 588.74415 | I72: 168.63 | J72: 413.275 | K72: 1.01 | L72: =(I72+J72+K72)*'2-报价汇总'!$H$5 -> 5.82915 | M72: =(I72+J72+K72+L72)*'2-报价汇总'!$I$5 -> 0 | N72: =(M72+L72+K72+J72+I72)*'2-报价汇总'!$J$5 -> 0 | O72: =G72*H72 -> 3532464.9 | P72: 680
A73: 2.2.1.67 | B73: ARD-80/4P/Ⅰ级 | C73: 1.电气元器件及附件供应安装 2.接线、调试 | D73: 配电箱内 | E73: 按设计图示数量计算 | F73: 个 | G73: 5000 | H73: =SUM(I73:N73) -> 744.5922 | I73: 145.67 | J73: 590.54 | K73: 1.01 | L73: =(I73+J73+K73)*'2-报价汇总'!$H$5 -> 7.3722 | M73: =(I73+J73+K73+L73)*'2-报价汇总'!$I$5 -> 0 | N73: =(M73+L73+K73+J73+I73)*'2-报价汇总'!$J$5 -> 0 | O73: =G73*H73 -> 3722961 | P73: 860
A74: 2.2.1.68 | B74: NM1-100S/3300 100A（30mA） | C74: 1.电气元器件及附件供应安装 2.接线、调试 | D74: 配电箱内 | E74: 按设计图示数量计算 | F74: 个 | G74: 5000 | H74: =SUM(I74:N74) -> 242.4202 | I74: 69 | J74: 170.01 | K74: 1.01 | L74: =(I74+J74+K74)*'2-报价汇总'!$H$5 -> 2.4002 | M74: =(I74+J74+K74+L74)*'2-报价汇总'!$I$5 -> 0 | N74: =(M74+L74+K74+J74+I74)*'2-报价汇总'!$J$5 -> 0 | O74: =G74*H74 -> 1212101 | P74: 280
... A81: 2.2.1.75 | B81: NXBLE-63 3P C16（30mA） | C81: 1.电气元器件及附件供应安装 2.接线、调试 | D81: 配电箱内 | E81: 按设计图示数量计算 | F81: 个 | G81: 5000 | H81: =SUM(I81:N81) -> 135.14305 | I81: 16.025 | J81: 117.34 | K81: 0.44 | L81: =(I81+J81+K81)*'2-报价汇总'!$H$5 -> 1.33805 | M81: =(I81+J81+K81+L81)*'2-报价汇总'!$I$5 -> 0 | N81: =(M81+L81+K81+J81+I81)*'2-报价汇总'!$J$5 -> 0 | O81: =G81*H81 -> 675715.25 | P81: 156.09
A82: 2.2.1.76 | B82: 定式控制器 NKG1 | C82: 1.电气元器件及附件供应安装 2.接线、调试 | D82: 配电箱内 | E82: 按设计图示数量计算 | F82: 个 | G82: 300 | H82: =SUM(I82:N82) -> 68.347706 | I82: 28.810996 | J82: 37.87 | K82: 0.99 | L82: =(I82+J82+K82)*'2-报价汇总'!$H$5 -> 0.67670996 | M82: =(I82+J82+K82+L82)*'2-报价汇总'!$I$5 -> 0 | N82: =(M82+L82+K82+J82+I82)*'2-报价汇总'!$J$5 -> 0 | O82: =G82*H82 -> 20504.312
A83: 2.2.1.77 | B83: 交流接触器 CJX2-1210 | C83: 1.电气元器件及附件供应安装 2.接线、调试 | D83: 配电箱内 | E83: 按设计图示数量计算 | F83: 个 | G83: 3646.0564 | H83: =SUM(I83:N83) -> 51.35697 | I83: 14.548485 | J83: 35.86 | K83: 0.44 | L83: =(I83+J83+K83)*'2-报价汇总'!$H$5 -> 0.50848485 | M83: =(I83+J83+K83+L83)*'2-报价汇总'!$I$5 -> 0 | N83: =(M83+L83+K83+J83+I83)*'2-报价汇总'!$J$5 -> 0 | O83: =G83*H83 -> 187250.41
A84: 2.2.1.78 | B84: 电容互感器 LMZJ1-50I-200-5A | C84: 1.电气元器件及附件供应安装 2.接线、调试 | D84: 配电箱内 | E84: 按设计图示数量计算 | F84: 个 | G84: 911.51409 | H84: =SUM(I84:N84) -> 26.601039 | I84: 7.7176623 | J84: 18.18 | K84: 0.44 | L84: =(I84+J84+K84)*'2-报价汇总'!$H$5 -> 0.26337662 | M84: =(I84+J84+K84+L84)*'2-报价汇总'!$I$5 -> 0 | N84: =(M84+L84+K84+J84+I84)*'2-报价汇总'!$J$5 -> 0 | O84: =G84*H84 -> 24247.222
A85: 2.2.1.79 | B85: 电容互感器 LMZJ1-50I-400-5A | C85: 1.电气元器件及附件供应安装 2.接线、调试 | D85: 配电箱内 | E85: 按设计图示数量计算 | F85: 个 | G85: 5469.0846 | H85: =SUM(I85:N85) -> 30.18632 | I85: 6.5274459 | J85: 22.35 | K85: 1.01 | L85: =(I85+J85+K85)*'2-报价汇总'!$H$5 -> 0.29887446 | M85: =(I85+J85+K85+L85)*'2-报价汇总'!$I$5 -> 0 | N85: =(M85+L85+K85+J85+I85)*'2-报价汇总'!$J$5 -> 0 | O85: =G85*H85 -> 165091.54
A86: 2.2.1.80 | B86: 电容互感器 LMZJ1-50I-600-5A | C86: 1.电气元器件及附件供应安装 2.接线、调试 | D86: 配电箱内 | E86: 按设计图示数量计算 | F86: 个 | G86: 2734.5423 | H86: =SUM(I86:N86) -> 30.999567 | I86: 6.3326407 | J86: 23.21 | K86: 1.15 | L86: =(I86+J86+K86)*'2-报价汇总'!$H$5 -> 0.30692641 | M86: =(I86+J86+K86+L86)*'2-报价汇总'!$I$5 -> 0 | N86: =(M86+L86+K86+J86+I86)*'2-报价汇总'!$J$5 -> 0 | O86: =G86*H86 -> 84769.627
A87: 2.2.1.81 | B87: 电容互感器 LMZJ1-100I-1000-5A | C87: 1.电气元器件及附件供应安装 2.接线、调试 | D87: 配电箱内 | E87: 按设计图示数量计算 | F87: 个 | G87: 2734.5423 | H87: =SUM(I87:N87) -> 61.387013 | I87: 23.169221 | J87: 36.53 | K87: 1.08 | L87: =(I87+J87+K87)*'2-报价汇总'!$H$5 -> 0.60779221 | M87: =(I87+J87+K87+L87)*'2-报价汇总'!$I$5 -> 0 | N87: =(M87+L87+K87+J87+I87)*'2-报价汇总'!$J$5 -> 0 | O87: =G87*H87 -> 167865.38
A88: 2.2.1.82 | B88: 电容互感器 LMZJ1-100I-1200-5A | C88: 1.电气元器件及附件供应安装 2.接线、调试 | D88: 配电箱内 | E88: 按设计图示数量计算 | F88: 个 | G88: 2734.5423 | H88: =SUM(I88:N88) -> 58.212727 | I88: 18.146364 | J88: 38.41 | K88: 1.08 | L88: =(I88+J88+K88)*'2-报价汇总'!$H$5 -> 0.57636364 | M88: =(I88+J88+K88+L88)*'2-报价汇总'!$I$5 -> 0 | N88: =(M88+L88+K88+J88+I88)*'2-报价汇总'!$J$5 -> 0 | O88: =G88*H88 -> 159185.16
A89: 2.2.1.83 | B89: 分励脱扣器 NM1-63 AC230 | C89: 1.电气元器件及附件供应安装 2.接线、调试 | D89: 配电箱内 | E89: 按设计图示数量计算 | F89: 个 | G89: 450 | H89: =SUM(I89:N89) -> 30.693506 | I89: 10.14961 | J89: 19.16 | K89: 1.08 | L89: =(I89+J89+K89)*'2-报价汇总'!$H$5 -> 0.3038961 | M89: =(I89+J89+K89+L89)*'2-报价汇总'!$I$5 -> 0 | N89: =(M89+L89+K89+J89+I89)*'2-报价汇总'!$J$5 -> 0 | O89: =G89*H89 -> 13812.078
A90: 2.2.1.84 | B90: 分励脱扣器 NM1-125 AC230 | C90: 1.电气元器件及附件供应安装 2.接线、调试 | D90: 配电箱内 | E90: 按设计图示数量计算 | F90: 个 | G90: 450 | H90: =SUM(I90:N90) -> 30.693506 | I90: 9.1596104 | J90: 20.15 | K90: 1.08 | L90: =(I90+J90+K90)*'2-报价汇总'!$H$5 -> 0.3038961 | M90: =(I90+J90+K90+L90)*'2-报价汇总'!$I$5 -> 0 | N90: =(M90+L90+K90+J90+I90)*'2-报价汇总'!$J$5 -> 0 | O90: =G90*H90 -> 13812.078
A91: 2.2.1.85 | B91: 分励脱扣器 NM1-250 AC230 | C91: 1.电气元器件及附件供应安装 2.接线、调试 | D91: 配电箱内 | E91: 按设计图示数量计算 | F91: 个 | G91: 600 | H91: =SUM(I91:N91) -> 30.693506 | I91: 8.1596104 | J91: 21.15 | K91: 1.08 | L91: =(I91+J91+K91)*'2-报价汇总'!$H$5 -> 0.3038961 | M91: =(I91+J91+K91+L91)*'2-报价汇总'!$I$5 -> 0 | N91: =(M91+L91+K91+J91+I91)*'2-报价汇总'!$J$5 -> 0 | O91: =G91*H91 -> 18416.104
A92: 2.2.1.86 | B92: 分励脱扣器 NM1-400S.H.R AC230 | C92: 1.电气元器件及附件供应安装 2.接线、调试 | D92: 配电箱内 | E92: 按设计图示数量计算 | F92: 个 | G92: 600 | H92: =SUM(I92:N92) -> 69.571948 | I92: 14.243117 | J92: 53.56 | K92: 1.08 | L92: =(I92+J92+K92)*'2-报价汇总'!$H$5 -> 0.68883117 | M92: =(I92+J92+K92+L92)*'2-报价汇总'!$I$5 -> 0 | N92: =(M92+L92+K92+J92+I92)*'2-报价汇总'!$J$5 -> 0 | O92: =G92*H92 -> 41743.169
A93: 2.2.1.87 | B93: 限流防火保护器ASCP-200 | C93: 1.电气元器件及附件供应安装 2.接线、调试 | D93: 配电箱内 | E93: 按设计图示数量计算 | F93: 个 | G93: 5000 | H93: =SUM(I93:N93) -> 1369.6963 | I93: 154.055 | J93: 1201 | K93: 1.08 | L93: =(I93+J93+K93)*'2-报价汇总'!$H$5 -> 13.56135 | M93: =(I93+J93+K93+L93)*'2-报价汇总'!$I$5 -> 0 | N93: =(M93+L93+K93+J93+I93)*'2-报价汇总'!$J$5 -> 0 | O93: =G93*H93 -> 6848481.8 | P93: 1582
A94: 2.2.1.88 | B94: 浪涌保护器 NXU-ⅡG-65kA/385V-3P | C94: 1.电气元器件及附件供应安装 2.接线、调试 | D94: 配电箱内 | E94: 按设计图示数量计算 | F94: 个 | G94: 600 | H94: =SUM(I94:N94) -> 181.0223 | I94: 18.15 | J94: =160 -> 160 | K94: 1.08 | L94: =(I94+J94+K94)*'2-报价汇总'!$H$5 -> 1.7923 | M94: =(I94+J94+K94+L94)*'2-报价汇总'!$I$5 -> 0 | N94: =(M94+L94+K94+J94+I94)*'2-报价汇总'!$J$5 -> 0 | O94: =G94*H94 -> 108613.38
A95: 2.2.1.89 | B95: 镀锌桥架 50*50*1.0 | C95: 1.桥架及弯头、三通、盖板等所有附件，防雷接地连接。 2.预留洞口及防火封堵。 3.支、吊架制作安装。 | D95: 室内、室外装饰装修及安装工程项目 | E95: 按设计图示长度计算 | F95: m | G95: 50000 | H95: =SUM(I95:N95) -> 42.848485 | I95: 25.254242 | J95: 16.61 | K95: 0.56 | L95: =(I95+J95+K95)*'2-报价汇总'!$H$5 -> 0.42424242 | M95: =(I95+J95+K95+L95)*'2-报价汇总'!$I$5 -> 0 | N95: =(M95+L95+K95+J95+I95)*'2-报价汇总'!$J$5 -> 0 | O95: =G95*H95 -> 2142424.2
A96: 2.2.1.90 | B96: 镀锌桥架 100*50*1.0 | C96: 1.桥架及弯头、三通、盖板等所有附件，防雷接地连接。 2.预留洞口及防火封堵。 3.支、吊架制作安装。 | D96: 室内、室外装饰装修及安装工程项目 | E96: 按设计图示长度计算 | F96: m | G96: 50000 | H96: =SUM(I96:N96) -> 48.969697 | I96: 23.334848 | J96: 24.59 | K96: 0.56 | L96: =(I96+J96+K96)*'2-报价汇总'!$H$5 -> 0.48484848 | M96: =(I96+J96+K96+L96)*'2-报价汇总'!$I$5 -> 0 | N96: =(M96+L96+K96+J96+I96)*'2-报价汇总'!$J$5 -> 0 | O96: =G96*H96 -> 2448484.8
A97: 2.2.1.91 | B97: 镀锌桥架 100*100*1.5 | C97: 1.桥架及弯头、三通、盖板等所有附件，防雷接地连接。 2.预留洞口及防火封堵。 3.支、吊架制作安装。 | D97: 室内、室外装饰装修及安装工程项目 | E97: 按设计图示长度计算 | F97: m | G97: 50000 | H97: =SUM(I97:N97) -> 59.463203 | I97: 24.974459 | J97: 32.78 | K97: 1.12 | L97: =(I97+J97+K97)*'2-报价汇总'!$H$5 -> 0.58874459 | M97: =(I97+J97+K97+L97)*'2-报价汇总'!$I$5 -> 0 | N97: =(M97+L97+K97+J97+I97)*'2-报价汇总'!$J$5 -> 0 | O97: =G97*H97 -> 2973160.2
A98: 2.2.1.92 | B98: 镀锌桥架 150*100*1.5 | C98: 1.桥架及弯头、三通、盖板等所有附件，防雷接地连接。 2.预留洞口及防火封堵。 3.支、吊架制作安装。 | D98: 室内、室外装饰装修及安装工程项目 | E98: 按设计图示长度计算 | F98: m | G98: 50000 | H98: =SUM(I98:N98) -> 78.701299 | I98: 38.392078 | J98: 37.9 | K98: 1.63 | L98: =(I98+J98+K98)*'2-报价汇总'!$H$5 -> 0.77922078 | M98: =(I98+J98+K98+L98)*'2-报价汇总'!$I$5 -> 0 | N98: =(M98+L98+K98+J98+I98)*'2-报价汇总'!$J$5 -> 0 | O98: =G98*H98 -> 3935064.9
A99: 2.2.1.93 | B99: 镀锌桥架 200*100*1.5 | C99: 1.桥架及弯头、三通、盖板等所有附件，防雷接地连接。 2.预留洞口及防火封堵。 3.支、吊架制作安装。 | D99: 室内、室外装饰装修及安装工程项目 | E99: 按设计图示长度计算 | F99: m | G99: 100000 | H99: =SUM(I99:N99) -> 83.948052 | I99: 34.586883 | J99: 46.9 | K99: 1.63 | L99: =(I99+J99+K99)*'2-报价汇总'!$H$5 -> 0.83116883 | M99: =(I99+J99+K99+L99)*'2-报价汇总'!$I$5 -> 0 | N99: =(M99+L99+K99+J99+I99)*'2-报价汇总'!$J$5 -> 0 | O99: =G99*H99 -> 8394805.2
A100: 2.2.1.94 | B100: 镀锌桥架 200*150*1.5 | C100: 1.桥架及弯头、三通、盖板等所有附件，防雷接地连接。 2.预留洞口及防火封堵。 3.支、吊架制作安装。 | D100: 室内、室外装饰装修及安装工程项目 | E100: 按设计图示长度计算 | F100: m | G100: 100000 | H100: =SUM(I100:N100) -> 101.43723 | I100: 44.7629 | J100: 54.21 | K100: 1.46 | L100: =(I100+J100+K100)*'2-报价汇总'!$H$5 -> 1.004329 | M100: =(I100+J100+K100+L100)*'2-报价汇总'!$I$5 -> 0 | N100: =(M100+L100+K100+J100+I100)*'2-报价汇总'!$J$5 -> 0 | O100: =G100*H100 -> 10143723
A101: 2.2.1.95 | B101: 镀锌桥架 300*100*1.5 | C101: 1.桥架及弯头、三通、盖板等所有附件，防雷接地连接。 2.预留洞口及防火封堵。 3.支、吊架制作安装。 | D101: 室内、室外装饰装修及安装工程项目 | E101: 按设计图示长度计算 | F101: m | G101: 2000 | H101: =SUM(I101:N101) -> 99.688312 | I101: 32.811299 | J101: 64.43 | K101: 1.46 | L101: =(I101+J101+K101)*'2-报价汇总'!$H$5 -> 0.98701299 | M101: =(I101+J101+K101+L101)*'2-报价汇总'!$I$5 -> 0 | N101: =(M101+L101+K101+J101+I101)*'2-报价汇总'!$J$5 -> 0 | O101: =G101*H101 -> 199376.62
A102: 2.2.1.96 | B102: 镀锌桥架 300*150*1.5 | C102: 1.桥架及弯头、三通、盖板等所有附件，防雷接地连接。 2.预留洞口及防火封堵。 3.支、吊架制作安装。 | D102: 室内、室外装饰装修及安装工程项目 | E102: 按设计图示长度计算 | F102: m | G102: 2000 | H102: =SUM(I102:N102) -> 121.54978 | I102: 51.44632 | J102: 66.93 | K102: 1.97 | L102: =(I102+J102+K102)*'2-报价汇总'!$H$5 -> 1.2034632 | M102: =(I102+J102+K102+L102)*'2-报价汇总'!$I$5 -> 0 | N102: =(M102+L102+K102+J102+I102)*'2-报价汇总'!$J$5 -> 0 | O102: =G102*H102 -> 243099.57
A103: 2.2.1.97 | B103: 镀锌桥架 400*150*2.0 | C103: 1.桥架及弯头、三通、盖板等所有附件，防雷接地连接。 2.预留洞口及防火封堵。 3.支、吊架制作安装。 | D103: 室内、室外装饰装修及安装工程项目 | E103: 按设计图示长度计算 | F103: m | G103: 2000 | H103: =SUM(I103:N103) -> 136.41558 | I103: 58.354935 | J103: 74.35 | K103: 2.36 | L103: =(I103+J103+K103)*'2-报价汇总'!$H$5 -> 1.3506494 | M103: =(I103+J103+K103+L103)*'2-报价汇总'!$I$5 -> 0 | N103: =(M103+L103+K103+J103+I103)*'2-报价汇总'!$J$5 -> 0 | O103: =G103*H103 -> 272831.17
A104: 2.2.1.98 | B104: 镀锌桥架 500*200*1.5 | C104: 1.桥架及弯头、三通、盖板等所有附件，防雷接地连接。 2.预留洞口及防火封堵。 3.支、吊架制作安装。 | D104: 室内、室外装饰装修及安装工程项目 | E104: 按设计图示长度计算 | F104: m | G104: 2000 | H104: =SUM(I104:N104) -> 181.88745 | I104: 89.78658 | J104: 86.52 | K104: 3.78 | L104: =(I104+J104+K104)*'2-报价汇总'!$H$5 -> 1.8008658 | M104: =(I104+J104+K104+L104)*'2-报价汇总'!$I$5 -> 0 | N104: =(M104+L104+K104+J104+I104)*'2-报价汇总'!$J$5 -> 0 | O104: =G104*H104 -> 363774.89
A105: 2.2.1.99 | B105: 镀锌桥架 500*200*2.0 | C105: 1.桥架及弯头、三通、盖板等所有附件，防雷接地连接。 2.预留洞口及防火封堵。 3.支、吊架制作安装。 | D105: 室内、室外装饰装修及安装工程项目 | E105: 按设计图示长度计算 | F105: m | G105: 2000 | H105: =SUM(I105:N105) -> 197.62771 | I105: 100.281 | J105: 91.61 | K105: 3.78 | L105: =(I105+J105+K105)*'2-报价汇总'!$H$5 -> 1.95671 | M105: =(I105+J105+K105+L105)*'2-报价汇总'!$I$5 -> 0 | N105: =(M105+L105+K105+J105+I105)*'2-报价汇总'!$J$5 -> 0 | O105: =G105*H105 -> 395255.41
A106: 2.2.1.100 | B106: 镀锌桥架 100*100*1.2 | C106: 1.桥架及弯头、三通、盖板等所有附件，防雷接地连接。 2.预留洞口及防火封堵。 3.支、吊架制作安装。 | D106: 室内、室外装饰装修及安装工程项目 | E106: 按设计图示长度计算 | F106: m | G106: 2000 | H106: =SUM(I106:N106) -> 55.493903 | I106: 24.974459 | J106: 28.85 | K106: 1.12 | L106: =(I106+J106+K106)*'2-报价汇总'!$H$5 -> 0.54944459 | M106: =(I106+J106+K106+L106)*'2-报价汇总'!$I$5 -> 0 | N106: =(M106+L106+K106+J106+I106)*'2-报价汇总'!$J$5 -> 0 | O106: =G106*H106 -> 110987.81
A107: 2.2.1.101 | B107: 镀锌桥架 150*100*1.2 | C107: 1.桥架及弯头、三通、盖板等所有附件，防雷接地连接。 2.预留洞口及防火封堵。 3.支、吊架制作安装。 | D107: 室内、室外装饰装修及安装工程项目 | E107: 按设计图示长度计算 | F107: m | G107: 2000 | H107: =SUM(I107:N107) -> 74.105799 | I107: 38.392078 | J107: 33.35 | K107: 1.63 | L107: =(I107+J107+K107)*'2-报价汇总'!$H$5 -> 0.73372078 | M107: =(I107+J107+K107+L107)*'2-报价汇总'!$I$5 -> 0 | N107: =(M107+L107+K107+J107+I107)*'2-报价汇总'!$J$5 -> 0 | O107: =G107*H107 -> 148211.6
A108: 2.2.1.102 | B108: 桥架600*100*2.0 | C108: 1.桥架及弯头、三通、盖板等所有附件，防雷接地连接。 2.预留洞口及防火封堵。 10.支、吊架制作安装。 | D108: 室内、室外装饰装修及安装工程项目 | E108: 按设计图示长度计算 | F108: m | G108: 2000 | H108: =SUM(I108:N108) -> 242.9151 | I108: 100.28 | J108: 136.45 | K108: 3.78 | L108: =(I108+J108+K108)*'2-报价汇总'!$H$5 -> 2.4051 | M108: =(I108+J108+K108+L108)*'2-报价汇总'!$I$5 -> 0 | N108: =(M108+L108+K108+J108+I108)*'2-报价汇总'!$J$5 -> 0 | O108: =G108*H108 -> 485830.2 | P108: 280.57
A109: 2.2.1.103 | B109: 桥架400*200*2.0 | C109: 1.桥架及弯头、三通、盖板等所有附件，防雷接地连接。 2.预留洞口及防火封堵。 10.支、吊架制作安装。 | D109: 室内、室外装饰装修及安装工程项目 | E109: 按设计图示长度计算 | F109: m | G109: 2000 | H109: =SUM(I109:N109) -> 232.8656 | I109: 100.33 | J109: 126.45 | K109: 3.78 | L109: =(I109+J109+K109)*'2-报价汇总'!$H$5 -> 2.3056 | M109: =(I109+J109+K109+L109)*'2-报价汇总'!$I$5 -> 0 | N109: =(M109+L109+K109+J109+I109)*'2-报价汇总'!$J$5 -> 0 | O109: =G109*H109 -> 465731.2 | P109: 268.96
A110: 2.2.1.104 | B110: 带铠电缆YJV-4x240+1x120mm2铜芯 | C110: 1.包括接驳费用 2.含电缆头制作安装 3.含安装和附件 | D110: 室内、室外装饰装修及安装工程项目 | E110: 按设计图示尺寸净长度计算加箱体半周长计量，设备端预留一米长度计量，含电缆套管， | F110: m | G110: 2000 | H110: =SUM(I110:N110) -> 865.71429 | I110: 49.322857 | J110: 803.66 | K110: 4.16 | L110: =(I110+J110+K110)*'2-报价汇总'!$H$5 -> 8.5714286 | M110: =(I110+J110+K110+L110)*'2-报价汇总'!$I$5 -> 0 | N110: =(M110+L110+K110+J110+I110)*'2-报价汇总'!$J$5 -> 0 | O110: =G110*H110 -> 1731428.6
A111: 2.2.1.105 | B111: 带铠电缆YJLV-4x240+1x120mm2铝芯 | C111: 1.包括接驳费用 2.含电缆头制作安装 3.含安装和附件 | D111: 室内、室外装饰装修及安装工程项目 | E111: 按设计图示尺寸净长度计算加箱体半周长计量，设备端预留一米长度计量，含电缆套管， | F111: m | G111: 365972.91 | H111: =SUM(I111:N111) -> 168.973 | I111: 49.32 | J111: 113.82 | K111: 4.16 | L111: =(I111+J111+K111)*'2-报价汇总'!$H$5 -> 1.673 | M111: =(I111+J111+K111+L111)*'2-报价汇总'!$I$5 -> 0 | N111: =(M111+L111+K111+J111+I111)*'2-报价汇总'!$J$5 -> 0 | O111: =G111*H111 -> 61839540
A112: 2.2.1.106 | B112: 带铠电缆YJV-4x185+1x95mm2铜芯 | C112: 1.包括接驳费用 2.含电缆头制作安装 3.含安装和附件 | D112: 室内、室外装饰装修及安装工程项目 | E112: 按设计图示尺寸净长度计算加箱体半周长计量，设备端预留一米长度计量，含电缆套管， | F112: m | G112: 10000 | H112: =SUM(I112:N112) -> 579.16286 | I112: 38.858571 | J112: 531.02 | K112: 3.55 | L112: =(I112+J112+K112)*'2-报价汇总'!$H$5 -> 5.7342857 | M112: =(I112+J112+K112+L112)*'2-报价汇总'!$I$5 -> 0 | N112: =(M112+L112+K112+J112+I112)*'2-报价汇总'!$J$5 -> 0 | O112: =G112*H112 -> 5791628.6
A113: 2.2.1.107 | B113: 带铠电缆YJLV-4x185+1x95mm2铝芯 | C113: 1.包括接驳费用 2.含电缆头制作安装 3.含安装和附件 | D113: 室内、室外装饰装修及安装工程项目 | E113: 按设计图示尺寸净长度计算加箱体半周长计量，设备端预留一米长度计量，含电缆套管， | F113: m | G113: 10000 | H113: =SUM(I113:N113) -> 136.3904 | I113: 38.86 | J113: 92.63 | K113: 3.55 | L113: =(I113+J113+K113)*'2-报价汇总'!$H$5 -> 1.3504 | M113: =(I113+J113+K113+L113)*'2-报价汇总'!$I$5 -> 0 | N113: =(M113+L113+K113+J113+I113)*'2-报价汇总'!$J$5 -> 0 | O113: =G113*H113 -> 1363904
A114: 2.2.1.108 | B114: 带铠电缆YJV-4x150+1x70mm2铜芯 | C114: 1.包括接驳费用 2.含电缆头制作安装 3.含安装和附件 | D114: 室内、室外装饰装修及安装工程项目 | E114: 按设计图示尺寸净长度计算加箱体半周长计量，设备端预留一米长度计量，含电缆套管， | F114: m | G114: 10000 | H114: =SUM(I114:N114) -> 505 | I114: 36.52 | J114: 459.93 | K114: 3.55 | L114: =(I114+J114+K114)*'2-报价汇总'!$H$5 -> 5 | M114: =(I114+J114+K114+L114)*'2-报价汇总'!$I$5 -> 0 | N114: =(M114+L114+K114+J114+I114)*'2-报价汇总'!$J$5 -> 0 | O114: =G114*H114 -> 5050000
A115: 2.2.1.109 | B115: 带铠电缆YJLV-4x150+1x70mm2铝芯 | C115: 1.包括接驳费用 2.含电缆头制作安装 3.含安装和附件 | D115: 室内、室外装饰装修及安装工程项目 | E115: 按设计图示尺寸净长度计算加箱体半周长计量，设备端预留一米长度计量，含电缆套管， | F115: m | G115: 10000 | H115: =SUM(I115:N115) -> 122.8059 | I115: 36.52 | J115: 81.52 | K115: 3.55 | L115: =(I115+J115+K115)*'2-报价汇总'!$H$5 -> 1.2159 | M115: =(I115+J115+K115+L115)*'2-报价汇总'!$I$5 -> 0 | N115: =(M115+L115+K115+J115+I115)*'2-报价汇总'!$J$5 -> 0 | O115: =G115*H115 -> 1228059
A116: 2.2.1.110 | B116: 电缆YJV-4x120+1x70mm2铜芯 | C116: 1.包括接驳费用 2.含电缆头制作安装 3.含安装和附件 | D116: 室内、室外装饰装修及安装工程项目 | E116: 按设计图示尺寸长度计算加箱体半周长计量，设备端预留一米长度计量 | F116: m | G116: 10000 | H116: =SUM(I116:N116) -> 416.50476 | I116: 31.990952 | J116: 378.65 | K116: 1.74 | L116: =(I116+J116+K116)*'2-报价汇总'!$H$5 -> 4.1238095 | M116: =(I116+J116+K116+L116)*'2-报价汇总'!$I$5 -> 0 | N116: =(M116+L116+K116+J116+I116)*'2-报价汇总'!$J$5 -> 0 | O116: =G116*H116 -> 4165047.6
A117: 2.2.1.111 | B117: 电缆YJLV-4x120+1x70mm2铝芯 | C117: 1.包括接驳费用 2.含电缆头制作安装 3.含安装和附件 | D117: 室内、室外装饰装修及安装工程项目 | E117: 按设计图示尺寸长度计算加箱体半周长计量，设备端预留一米长度计量 | F117: m | G117: 7292.1128 | H117: =SUM(I117:N117) -> 100.6061 | I117: 31.99 | J117: 65.88 | K117: 1.74 | L117: =(I117+J117+K117)*'2-报价汇总'!$H$5 -> 0.9961 | M117: =(I117+J117+K117+L117)*'2-报价汇总'!$I$5 -> 0 | N117: =(M117+L117+K117+J117+I117)*'2-报价汇总'!$J$5 -> 0 | O117: =G117*H117 -> 733631.02
A118: 2.2.1.112 | B118: 电缆-YJV-4*95+1*50mm2铜芯 | C118: 1.包括接驳费用 2.含电缆头制作安装 3.含安装和附件 | D118: 室内、室外装饰装修及安装工程项目 | E118: 按设计图示尺寸长度计算加箱体半周长计量，设备端预留一米长度计量 | F118: m | G118: 20782.521 | H118: =SUM(I118:N118) -> 286.16667 | I118: 30.903333 | J118: 250.69 | K118: 1.74 | L118: =(I118+J118+K118)*'2-报价汇总'!$H$5 -> 2.8333333 | M118: =(I118+J118+K118+L118)*'2-报价汇总'!$I$5 -> 0 | N118: =(M118+L118+K118+J118+I118)*'2-报价汇总'!$J$5 -> 0 | O118: =G118*H118 -> 5947264.9
A119: 2.2.1.113 | B119: 电缆-YJLV-4*95+1*50mm2铝芯 | C119: 1.包括接驳费用 2.含电缆头制作安装 3.含安装和附件 | D119: 室内、室外装饰装修及安装工程项目 | E119: 按设计图示尺寸长度计算加箱体半周长计量，设备端预留一米长度计量 | F119: m | G119: 184672.76 | H119: =SUM(I119:N119) -> 90.3243 | I119: 30.9 | J119: 56.79 | K119: 1.74 | L119: =(I119+J119+K119)*'2-报价汇总'!$H$5 -> 0.8943 | M119: =(I119+J119+K119+L119)*'2-报价汇总'!$I$5 -> 0 | N119: =(M119+L119+K119+J119+I119)*'2-报价汇总'!$J$5 -> 0 | O119: =G119*H119 -> 16680437
A120: 2.2.1.114 | B120: 电缆-YJV-4*70+1*35mm2铜芯 | C120: 1.包括接驳费用 2.含电缆头制作安装 3.含安装和附件 | D120: 室内、室外装饰装修及安装工程项目 | E120: 按设计图示尺寸长度计算加箱体半周长计量，设备端预留一米长度计量 | F120: m | G120: 12000 | H120: =SUM(I120:N120) -> 204.9819 | I120: 26.092381 | J120: 175.35 | K120: 1.51 | L120: =(I120+J120+K120)*'2-报价汇总'!$H$5 -> 2.0295238 | M120: =(I120+J120+K120+L120)*'2-报价汇总'!$I$5 -> 0 | N120: =(M120+L120+K120+J120+I120)*'2-报价汇总'!$J$5 -> 0 | O120: =G120*H120 -> 2459782.9
A121: 2.2.1.115 | B121: 电缆-YJLV-4*70+1*35mm2铝芯 | C121: 1.包括接驳费用 2.含电缆头制作安装 3.含安装和附件 | D121: 室内、室外装饰装修及安装工程项目 | E121: 按设计图示尺寸长度计算加箱体半周长计量，设备端预留一米长度计量 | F121: m | G121: 12000 | H121: =SUM(I121:N121) -> 85.2339 | I121: 26.09 | J121: 56.79 | K121: 1.51 | L121: =(I121+J121+K121)*'2-报价汇总'!$H$5 -> 0.8439 | M121: =(I121+J121+K121+L121)*'2-报价汇总'!$I$5 -> 0 | N121: =(M121+L121+K121+J121+I121)*'2-报价汇总'!$J$5 -> 0 | O121: =G121*H121 -> 1022806.8
... A135: 2.2.1.129 | B135: 电缆YJV-3*25+2*16mm2 | C135: 1.包括接驳费用 2.含电缆头制作安装 3.含安装和附件 | D135: 室内、室外装饰装修及安装工程项目 | E135: 按设计图示尺寸长度计算加箱体半周长计量，设备端预留一米长度计量 | F135: m | G135: 150000 | H135: =SUM(I135:N135) -> 85.032381 | I135: 11.590476 | J135: 72.46 | K135: 0.14 | L135: =(I135+J135+K135)*'2-报价汇总'!$H$5 -> 0.84190476 | M135: =(I135+J135+K135+L135)*'2-报价汇总'!$I$5 -> 0 | N135: =(M135+L135+K135+J135+I135)*'2-报价汇总'!$J$5 -> 0 | O135: =G135*H135 -> 12754857
A136: 2.2.1.130 | B136: 电缆-YJV-3*70+2*35mm2铜芯 | C136: 1.包括接驳费用 2.含电缆头制作安装 3.含安装和附件 | D136: 室内、室外装饰装修及安装工程项目 | E136: 按设计图示尺寸长度计算加箱体半周长计量，设备端预留一米长度计量 | F136: m | G136: 5000 | H136: =SUM(I136:N136) -> 190.4759 | I136: 22.07 | J136: 165.01 | K136: 1.51 | L136: =(I136+J136+K136)*'2-报价汇总'!$H$5 -> 1.8859 | M136: =(I136+J136+K136+L136)*'2-报价汇总'!$I$5 -> 0 | N136: =(M136+L136+K136+J136+I136)*'2-报价汇总'!$J$5 -> 0 | O136: =G136*H136 -> 952379.5 | P136: 220
A137: 2.2.1.131 | B137: 消防电缆BTTZ4*70+1*35 | C137: 1.包括接驳费用 2.含电缆头制作安装 3.含安装和附件 | D137: 室内、室外装饰装修及安装工程项目 | E137: 按设计图示尺寸长度计算加箱体半周长计量，设备端预留一米长度计量 | F137: m | G137: 2000 | H137: =SUM(I137:N137) -> 285.44427 | I137: 27.08 | J137: 254.02809 | K137: 1.51 | L137: =(I137+J137+K137)*'2-报价汇总'!$H$5 -> 2.8261809 | M137: =(I137+J137+K137+L137)*'2-报价汇总'!$I$5 -> 0 | N137: =(M137+L137+K137+J137+I137)*'2-报价汇总'!$J$5 -> 0 | O137: =G137*H137 -> 570888.55 | P137: 329.69
A138: 2.2.1.132 | B138: 智能三项电表正泰LCD DTS634 | C138: 1.本体及附件供应安装 | D138: 配电箱内 | E138: 按设计图示数量计算 | F138: 个 | G138: 1200 | H138: =SUM(I138:N138) -> 419.74026 | I138: 28.994416 | J138: 384.67 | K138: 1.92 | L138: =(I138+J138+K138)*'2-报价汇总'!$H$5 -> 4.1558442 | M138: =(I138+J138+K138+L138)*'2-报价汇总'!$I$5 -> 0 | N138: =(M138+L138+K138+J138+I138)*'2-报价汇总'!$J$5 -> 0 | O138: =G138*H138 -> 503688.31
A139: 2.2.1.133 | B139: 焊接钢管SC100 | C139: 1.线管铺设 2.包含支架、卡扣、吊筋等其他辅材 | D139: 室内、室外装饰装修及安装工程项目 | E139: 按设计图示长度计算 | F139: m | G139: 1200 | H139: =SUM(I139:N139) -> 112.45541 | I139: 60.621991 | J139: 48.85 | K139: 1.87 | L139: =(I139+J139+K139)*'2-报价汇总'!$H$5 -> 1.1134199 | M139: =(I139+J139+K139+L139)*'2-报价汇总'!$I$5 -> 0 | N139: =(M139+L139+K139+J139+I139)*'2-报价汇总'!$J$5 -> 0 | O139: =G139*H139 -> 134946.49
A140: 2.2.1.134 | B140: 焊接钢管SC80 | C140: 1.线管铺设 3.包含支架、卡扣、吊筋等其他辅材 | D140: 室内、室外装饰装修及安装工程项目 | E140: 按设计图示长度计算 | F140: m | G140: 1200 | H140: =SUM(I140:N140) -> 104.35792 | I140: 64.584675 | J140: 37.24 | K140: 1.5 | L140: =(I140+J140+K140)*'2-报价汇总'!$H$5 -> 1.0332468 | M140: =(I140+J140+K140+L140)*'2-报价汇总'!$I$5 -> 0 | N140: =(M140+L140+K140+J140+I140)*'2-报价汇总'!$J$5 -> 0 | O140: =G140*H140 -> 125229.51
A141: 2.2.1.135 | B141: 焊接钢管SC70 | C141: 1.线管铺设 3.包含支架、卡扣、吊筋等其他辅材 | D141: 室内、室外装饰装修及安装工程项目 | E141: 按设计图示长度计算 | F141: m | G141: 1200 | H141: =SUM(I141:N141) -> 98.201732 | I141: 66.419437 | J141: 29.69 | K141: 1.12 | L141: =(I141+J141+K141)*'2-报价汇总'!$H$5 -> 0.97229437 | M141: =(I141+J141+K141+L141)*'2-报价汇总'!$I$5 -> 0 | N141: =(M141+L141+K141+J141+I141)*'2-报价汇总'!$J$5 -> 0 | O141: =G141*H141 -> 117842.08
A142: 2.2.1.136 | B142: 焊接钢管SC50 | C142: 1.线管铺设 4.包含支架、卡扣、吊筋等其他辅材 | D142: 室内、室外装饰装修及安装工程项目 | E142: 按设计图示长度计算 | F142: m | G142: 7491.9555 | H142: =SUM(I142:N142) -> 48.086494 | I142: 25.13039 | J142: 21.72 | K142: 0.76 | L142: =(I142+J142+K142)*'2-报价汇总'!$H$5 -> 0.4761039 | M142: =(I142+J142+K142+L142)*'2-报价汇总'!$I$5 -> 0 | N142: =(M142+L142+K142+J142+I142)*'2-报价汇总'!$J$5 -> 0 | O142: =G142*H142 -> 360261.87
A143: 2.2.1.137 | B143: 镀锌钢管JDG50 | C143: 1.线管铺设 5.包含支架、卡扣、吊筋等其他辅材 | D143: 室内、室外装饰装修及安装工程项目 | E143: 按设计图示长度计算 | F143: m | G143: 10000 | H143: =SUM(I143:N143) -> 44.488943 | I143: 30.028458 | J143: 13.73 | K143: 0.29 | L143: =(I143+J143+K143)*'2-报价汇总'!$H$5 -> 0.44048458 | M143: =(I143+J143+K143+L143)*'2-报价汇总'!$I$5 -> 0 | N143: =(M143+L143+K143+J143+I143)*'2-报价汇总'!$J$5 -> 0 | O143: =G143*H143 -> 444889.43
A144: 2.2.1.138 | B144: 镀锌钢管JDG40 | C144: 1.线管铺设 6.包含支架、卡扣、吊筋等其他辅材 | D144: 室内、室外装饰装修及安装工程项目 | E144: 按设计图示长度计算 | F144: m | G144: 32465.37 | H144: =SUM(I144:N144) -> 36.362187 | I144: 26.222166 | J144: 9.5 | K144: 0.28 | L144: =(I144+J144+K144)*'2-报价汇总'!$H$5 -> 0.36002166 | M144: =(I144+J144+K144+L144)*'2-报价汇总'!$I$5 -> 0 | N144: =(M144+L144+K144+J144+I144)*'2-报价汇总'!$J$5 -> 0 | O144: =G144*H144 -> 1180511.9
A145: 2.2.1.139 | B145: 镀锌钢管JDG32 | C145: 1.线管铺设 6.包含支架、卡扣、吊筋等其他辅材 | D145: 室内、室外装饰装修及安装工程项目 | E145: 按设计图示长度计算 | F145: m | G145: 40000 | H145: =SUM(I145:N145) -> 26.233766 | I145: 17.114026 | J145: 8.61 | K145: 0.25 | L145: =(I145+J145+K145)*'2-报价汇总'!$H$5 -> 0.25974026 | M145: =(I145+J145+K145+L145)*'2-报价汇总'!$I$5 -> 0 | N145: =(M145+L145+K145+J145+I145)*'2-报价汇总'!$J$5 -> 0 | O145: =G145*H145 -> 1049350.6
A146: 2.2.1.140 | B146: 镀锌钢管JDG25 | C146: 1.线管铺设 7.包含支架、卡扣、吊筋等其他辅材 | D146: 室内、室外装饰装修及安装工程项目 | E146: 按设计图示长度计算 | F146: m | G146: 32465.37 | H146: =SUM(I146:N146) -> 21.861472 | I146: 13.495022 | J146: 7.93 | K146: 0.22 | L146: =(I146+J146+K146)*'2-报价汇总'!$H$5 -> 0.21645022 | M146: =(I146+J146+K146+L146)*'2-报价汇总'!$I$5 -> 0 | N146: =(M146+L146+K146+J146+I146)*'2-报价汇总'!$J$5 -> 0 | O146: =G146*H146 -> 709740.78
A147: 2.2.1.141 | B147: 镀锌钢管JDG20 | C147: 1.线管铺设 8.包含支架、卡扣、吊筋等其他辅材 | D147: 室内、室外装饰装修及安装工程项目 | E147: 按设计图示长度计算 | F147: m | G147: 40000 | H147: =SUM(I147:N147) -> 17.314286 | I147: 10.042857 | J147: 6.9 | K147: 0.2 | L147: =(I147+J147+K147)*'2-报价汇总'!$H$5 -> 0.17142857 | M147: =(I147+J147+K147+L147)*'2-报价汇总'!$I$5 -> 0 | N147: =(M147+L147+K147+J147+I147)*'2-报价汇总'!$J$5 -> 0 | O147: =G147*H147 -> 692571.43
A148: 2.2.1.142 | B148: 镀锌钢管JDG125 | C148: 1.线管铺设 5.包含支架、卡扣、吊筋等其他辅材 | D148: 室内、室外装饰装修及安装工程项目 | E148: 按设计图示长度计算 | F148: m | G148: 40000 | H148: =SUM(I148:N148) -> 123.119 | I148: =44.5+25 -> 69.5 | J148: 52.11 | K148: 0.29 | L148: =(I148+J148+K148)*'2-报价汇总'!$H$5 -> 1.219 | M148: =(I148+J148+K148+L148)*'2-报价汇总'!$I$5 -> 0 | N148: =(M148+L148+K148+J148+I148)*'2-报价汇总'!$J$5 -> 0 | O148: =G148*H148 -> 4924760
A149: 2.2.1.143 | B149: 镀锌钢管JDG100 | C149: 1.线管铺设 5.包含支架、卡扣、吊筋等其他辅材 | D149: 室内、室外装饰装修及安装工程项目 | E149: 按设计图示长度计算 | F149: m | G149: 40000 | H149: =SUM(I149:N149) -> 94.0613 | I149: =44.5+12 -> 56.5 | J149: 36.25 | K149: 0.38 | L149: =(I149+J149+K149)*'2-报价汇总'!$H$5 -> 0.9313 | M149: =(I149+J149+K149+L149)*'2-报价汇总'!$I$5 -> 0 | N149: =(M149+L149+K149+J149+I149)*'2-报价汇总'!$J$5 -> 0 | O149: =G149*H149 -> 3762452
A150: 2.2.1.144 | B150: 镀锌钢管JDG70 | C150: 1.线管铺设 5.包含支架、卡扣、吊筋等其他辅材 | D150: 室内、室外装饰装修及安装工程项目 | E150: 按设计图示长度计算 | F150: m | G150: 40000 | H150: =SUM(I150:N150) -> 66.2964 | I150: =38.25+4 -> 42.25 | J150: 23.07 | K150: 0.32 | L150: =(I150+J150+K150)*'2-报价汇总'!$H$5 -> 0.6564 | M150: =(I150+J150+K150+L150)*'2-报价汇总'!$I$5 -> 0 | N150: =(M150+L150+K150+J150+I150)*'2-报价汇总'!$J$5 -> 0 | O150: =G150*H150 -> 2651856
A151: 2.2.1.145 | B151: 镀锌钢管JDG150 | F151: m | G151: 6000 | H151: =SUM(I151:N151) -> 177.4873 | I151: 92.03 | J151: 83.41 | K151: 0.29 | L151: =(I151+J151+K151)*'2-报价汇总'!$H$5 -> 1.7573 | M151: =(I151+J151+K151+L151)*'2-报价汇总'!$I$5 -> 0 | N151: =(M151+L151+K151+J151+I151)*'2-报价汇总'!$J$5 -> 0 | O151: =G151*H151 -> 1064923.8 | P151: 205
A152: 2.2.1.146 | B152: 焊接钢管SC150 | F152: m | G152: 6000 | H152: =SUM(I152:N152) -> 186.143 | I152: 95.62 | J152: 86.81 | K152: 1.87 | L152: =(I152+J152+K152)*'2-报价汇总'!$H$5 -> 1.843 | M152: =(I152+J152+K152+L152)*'2-报价汇总'!$I$5 -> 0 | N152: =(M152+L152+K152+J152+I152)*'2-报价汇总'!$J$5 -> 0 | O152: =G152*H152 -> 1116858 | P152: 215
A153: 2.2.1.147 | B153: 室外道闸、立招电、岗亭电源等 | C153: 1.含配管、配线 2.底盒安装 | D153: 室外装饰装修及安装工程项目 | E153: 按设计图示长度计算 | F153: m | G153: 42932.314 | H153: =SUM(I153:N153) -> 56.481299 | I153: 32.922078 | J153: =1.8*5+13.5 -> 22.5 | K153: 0.5 | L153: =(I153+J153+K153)*'2-报价汇总'!$H$5 -> 0.55922078 | M153: =(I153+J153+K153+L153)*'2-报价汇总'!$I$5 -> 0 | N153: =(M153+L153+K153+J153+I153)*'2-报价汇总'!$J$5 -> 0 | O153: =G153*H153 -> 2424872.8
A154: 2.2.1.148 | B154: 入户电缆、室外充电桩电缆、室外道闸机等管沟挖沟回填（深挖800-1000mm，路面恢复） | F154: m | G154: 6000 | H154: =SUM(I154:N154) -> 213.36797 | I154: 209.25541 | K154: 2 | L154: =(I154+J154+K154)*'2-报价汇总'!$H$5 -> 2.1125541 | M154: =(I154+J154+K154+L154)*'2-报价汇总'!$I$5 -> 0 | N154: =(M154+L154+K154+J154+I154)*'2-报价汇总'!$J$5 -> 0 | O154: =G154*H154 -> 1280207.8
B155: 补充项 | G155: 0
B156: 小计 | G156: 0
...

Sheet 2.3-给排水工程
A1: 理想汽车中心店给排水工程量清单
A2: ='2.1-装饰工程'!A2 -> 注意：此报价清单每项不得随意更改、删减，如有任何增加项请务必在每大项最后“补充项“中列举，补充项及说明字体颜色均采用蓝色；且所有项目都需要填写。
A3: 序号 | B3: 项目名称 | C3: 项目特征 | D3: 适用范围 | E3: 工程量计算规则 | F3: 单位 | G3: 24/25年暂估工程量 | H3: 综合单价 | I3: 人工费 | J3: 材料费 | K3: 机械费 | L3: 安措费 | M3: 管理费 | N3: 利润 | O3: 24/25年暂估总价 | P3: 备注
B4: 2.3给排水工程
A5: 2.3.1 | B5: 卫生间工程
A6: 2.3.1.01 | B6: 坐便器采购及安装 | C6: 1.本体及辅料（软管、阀门等）安装 | D6: 卫生间、淋浴间、清扫间 | E6: 按设计图示数量计算 | F6: 套 | G6: 15495.74 | H6: =SUM(I6:N6) -> 2271.7728 | I6: 205 | J6: 2042.36 | K6: 1.92 | L6: =(I6+J6+K6)*'2-报价汇总'!$H$5 -> 22.4928 | M6: =(I6+J6+K6+L6)*'2-报价汇总'!$I$5 -> 0 | N6: =(M6+L6+K6+J6+I6)*'2-报价汇总'!$J$5 -> 0 | O6: =G6*H6 -> 35202800 | S6: 15495.74
A7: 2.3.1.02 | B7: 小便斗及感应器采购及安装 | C7: 1.本体及辅料（软管、阀门等）安装 | D7: 卫生间、淋浴间、清扫间 | E7: 按设计图示数量计算 | F7: 套 | G7: 7292.1128 | H7: =SUM(I7:N7) -> 2152.714 | I7: 150 | J7: 1980.64 | K7: 0.76 | L7: =(I7+J7+K7)*'2-报价汇总'!$H$5 -> 21.314 | M7: =(I7+J7+K7+L7)*'2-报价汇总'!$I$5 -> 0 | N7: =(M7+L7+K7+J7+I7)*'2-报价汇总'!$J$5 -> 0 | O7: =G7*H7 -> 15697833 | S7: 7292.1128
A8: 2.3.1.03 | B8: 洗手盆及龙头采购及安装 | C8: 1.本体及辅料（软管、阀门等）安装 | D8: 卫生间、淋浴间、清扫间 | E8: 按设计图示数量计算 | F8: 套 | G8: 5000 | H8: =SUM(I8:N8) -> 1914.6883 | I8: 143.88095 | J8: 1750.77 | K8: 1.08 | L8: =(I8+J8+K8)*'2-报价汇总'!$H$5 -> 18.95731 | M8: =(I8+J8+K8+L8)*'2-报价汇总'!$I$5 -> 0 | N8: =(M8+L8+K8+J8+I8)*'2-报价汇总'!$J$5 -> 0 | O8: =G8*H8 -> 9573441.3 | S8: 10938.169
A9: 2.3.1.04 | B9: 坐便器采购及安装（箭牌AB1287-400） | C9: 1.本体及辅料（软管、阀门等）安装 | D9: 员工区 | E9: 按设计图示数量计算 | F9: 套 | G9: 5000 | H9: =SUM(I9:N9) -> 1049.3506 | I9: 258.37104 | J9: 778.67 | K9: 1.92 | L9: =(I9+J9+K9)*'2-报价汇总'!$H$5 -> 10.38961 | M9: =(I9+J9+K9+L9)*'2-报价汇总'!$I$5 -> 0 | N9: =(M9+L9+K9+J9+I9)*'2-报价汇总'!$J$5 -> 0 | O9: =G9*H9 -> 5246753.2 | S9: 0
A10: 2.3.1.05 | B10: 小便斗及感应器采购及安装（箭牌AN633+感应器AGY108-3A（交流）） | C10: 1.本体及辅料（软管、阀门等）安装 | D10: 员工区 | E10: 按设计图示数量计算 | F10: 套 | G10: 5000 | H10: =SUM(I10:N10) -> 1281.0823 | I10: 223.39827 | J10: 1044.24 | K10: 0.76 | L10: =(I10+J10+K10)*'2-报价汇总'!$H$5 -> 12.683983 | M10: =(I10+J10+K10+L10)*'2-报价汇总'!$I$5 -> 0 | N10: =(M10+L10+K10+J10+I10)*'2-报价汇总'!$J$5 -> 0 | O10: =G10*H10 -> 6405411.3 | S10: 0
A11: 2.3.1.06 | B11: 工位不锈钢洗手盆及龙头采购及安装 | C11: 1.本体及辅料（软管、阀门等）安装 | D11: 卫生间、淋浴间、清扫间 | E11: 按设计图示数量计算 | F11: 套 | G11: 500 | H11: =SUM(I11:N11) -> 699.5671 | I11: 135.82069 | J11: 555.39 | K11: 1.43 | L11: =(I11+J11+K11)*'2-报价汇总'!$H$5 -> 6.9264069 | M11: =(I11+J11+K11+L11)*'2-报价汇总'!$I$5 -> 0 | N11: =(M11+L11+K11+J11+I11)*'2-报价汇总'!$J$5 -> 0 | O11: =G11*H11 -> 349783.55 | S11: 0
A12: 2.3.1.07 | B12: 皂液器采购及安装 | C12: 1.本体及配件辅料安装 | D12: 卫生间、淋浴间、清扫间 | E12: 按设计图示数量计算 | F12: 套 | G12: 500 | H12: =SUM(I12:N12) -> 131.16883 | I12: 31.68013 | J12: 97.9 | K12: 0.29 | L12: =(I12+J12+K12)*'2-报价汇总'!$H$5 -> 1.2987013 | M12: =(I12+J12+K12+L12)*'2-报价汇总'!$I$5 -> 0 | N12: =(M12+L12+K12+J12+I12)*'2-报价汇总'!$J$5 -> 0 | O12: =G12*H12 -> 65584.416 | S12: 0
A13: 2.3.1.08 | B13: 手纸盒（小）采购及安装，卫生间隔间内 | C13: 1.本体及配件辅料安装 | D13: 卫生间、淋浴间、清扫间 | E13: 按设计图示数量计算 | F13: 套 | G13: 500 | H13: =SUM(I13:N13) -> 306.06061 | I13: 136.0303 | J13: 166.67 | K13: 0.33 | L13: =(I13+J13+K13)*'2-报价汇总'!$H$5 -> 3.030303 | M13: =(I13+J13+K13+L13)*'2-报价汇总'!$I$5 -> 0 | N13: =(M13+L13+K13+J13+I13)*'2-报价汇总'!$J$5 -> 0 | O13: =G13*H13 -> 153030.3 | S13: 15495.74
A14: 2.3.1.09 | B14: 洗手池：抽纸不锈钢纸盒采购及安装 | C14: 1.本体及配件辅料安装 | D14: 卫生间、淋浴间、清扫间 | E14: 按设计图示数量计算 | F14: 套 | G14: 500 | H14: =SUM(I14:N14) -> 104.93506 | I14: 36.896104 | J14: 66.67 | K14: 0.33 | L14: =(I14+J14+K14)*'2-报价汇总'!$H$5 -> 1.038961 | M14: =(I14+J14+K14+L14)*'2-报价汇总'!$I$5 -> 0 | N14: =(M14+L14+K14+J14+I14)*'2-报价汇总'!$J$5 -> 0 | O14: =G14*H14 -> 52467.532 | S14: 6380.5987
A15: 2.3.1.10 | B15: 厕板纸纸盒采购及安装，卫生间隔间内 | C15: 1.本体及配件辅料安装 | D15: 卫生间、淋浴间、清扫间 | E15: 按设计图示数量计算 | F15: 套 | G15: 500 | H15: =SUM(I15:N15) -> 113.67965 | I15: 45.554113 | J15: 66.67 | K15: 0.33 | L15: =(I15+J15+K15)*'2-报价汇总'!$H$5 -> 1.1255411 | M15: =(I15+J15+K15+L15)*'2-报价汇总'!$I$5 -> 0 | N15: =(M15+L15+K15+J15+I15)*'2-报价汇总'!$J$5 -> 0 | O15: =G15*H15 -> 56839.827 | S15: 15495.74
A16: 2.3.1.11 | B16: 墩布池及龙头采购及安装 | C16: 1.本体及辅料（软管、阀门等）安装 | D16: 卫生间、淋浴间、清扫间 | E16: 按设计图示数量计算 | F16: 套 | G16: 500 | H16: =SUM(I16:N16) -> 1049.3506 | I16: 325.17104 | J16: 713.03 | K16: 0.76 | L16: =(I16+J16+K16)*'2-报价汇总'!$H$5 -> 10.38961 | M16: =(I16+J16+K16+L16)*'2-报价汇总'!$I$5 -> 0 | N16: =(M16+L16+K16+J16+I16)*'2-报价汇总'!$J$5 -> 0 | O16: =G16*H16 -> 524675.32 | S16: 1823.0282
A17: 2.3.1.12 | B17: 花洒采购及安装 | C17: 1.本体及辅料（软管、阀门等）安装 | D17: 卫生间、淋浴间、清扫间 | E17: 按设计图示数量计算 | F17: 套 | G17: 500 | H17: =SUM(I17:N17) -> 1168.4185 | I17: 50 | J17: 1104 | K17: 2.85 | L17: =(I17+J17+K17)*'2-报价汇总'!$H$5 -> 11.5685 | M17: =(I17+J17+K17+L17)*'2-报价汇总'!$I$5 -> 0 | N17: =(M17+L17+K17+J17+I17)*'2-报价汇总'!$J$5 -> 0 | O17: =G17*H17 -> 584209.25 | S17: 0
... A46: 2.3.1.41 | B46: 电热水器 60L 采购及安装 | C46: 1.设备供应安装 2.包含墙面加固、安装支架等其他辅助工作 3.设备调试 | D46: 卫生间、淋浴间、清扫间 | E46: 按设计图示数量计算 | F46: 套 | G46: 1000 | H46: =SUM(I46:N46) -> 1661.4719 | I46: 126.29165 | J46: 1504.2 | K46: 14.53 | L46: =(I46+J46+K46)*'2-报价汇总'!$H$5 -> 16.450216 | M46: =(I46+J46+K46+L46)*'2-报价汇总'!$I$5 -> 0 | N46: =(M46+L46+K46+J46+I46)*'2-报价汇总'!$J$5 -> 0 | O46: =G46*H46 -> 1661471.9 | S46: 0
A47: 2.3.1.42 | B47: 工业太阳能热水器 | C47: 1.管件及接线供应安装，清华紫光，容积：4立方 2.本体及附件，配线及管道等安装工作 3.含控制柜及水泵等安装工作 | D47: 卫生间、淋浴间、清扫间 | E47: 按设计图示数量计算 | F47: 项 | G47: 1000 | H47: =SUM(I47:N47) -> 45471.861 | I47: 32521.645 | J47: 12500 | L47: =(I47+J47+K47)*'2-报价汇总'!$H$5 -> 450.21645 | M47: =(I47+J47+K47+L47)*'2-报价汇总'!$I$5 -> 0 | N47: =(M47+L47+K47+J47+I47)*'2-报价汇总'!$J$5 -> 0 | O47: =G47*H47 -> 45471861 | S47: 0
A48: 2.3.1.43 | B48: 主给水管改造，增加控制阀门、水表 | C48: 1.原管道拆除调整 2.相关管件安装 3.阀门、水表提供及安装 | D48: 室内、室外装饰装修及安装工程项目 | E48: 按设计图示数量计算 | F48: 处 | G48: 1823.0282 | H48: =SUM(I48:N48) -> 437.22944 | I48: 432.90043 | L48: =(I48+J48+K48)*'2-报价汇总'!$H$5 -> 4.3290043 | M48: =(I48+J48+K48+L48)*'2-报价汇总'!$I$5 -> 0 | N48: =(M48+L48+K48+J48+I48)*'2-报价汇总'!$J$5 -> 0 | O48: =G48*H48 -> 797081.59 | S48: 1823.0282
A49: 2.3.1.44 | B49: 室外给水主管道增压泵 | C49: 1.1.5kw，扬程20m，口径50mm，不锈钢离心泵 2.品牌：利欧、人民 | D49: 室内、室外装饰装修及安装工程项目 | E49: 按设计图示数量计算 | F49: 套 | G49: 1000 | H49: =SUM(I49:N49) -> 1923.8095 | I49: 435.2719 | J49: 1433.67 | K49: 35.82 | L49: =(I49+J49+K49)*'2-报价汇总'!$H$5 -> 19.047619 | M49: =(I49+J49+K49+L49)*'2-报价汇总'!$I$5 -> 0 | N49: =(M49+L49+K49+J49+I49)*'2-报价汇总'!$J$5 -> 0 | O49: =G49*H49 -> 1923809.5 | S49: 0
A50: 2.3.1.45 | B50: 不锈钢拖把池 | C50: 1.成品不锈钢拖把池 2.规格1200*410*550 | E50: 按设计图示数量计算 | F50: 套 | G50: 1000 | H50: =SUM(I50:N50) -> 743.29004 | I50: 22.320736 | J50: 712.85 | K50: 0.76 | L50: =(I50+J50+K50)*'2-报价汇总'!$H$5 -> 7.3593074 | M50: =(I50+J50+K50+L50)*'2-报价汇总'!$I$5 -> 0 | N50: =(M50+L50+K50+J50+I50)*'2-报价汇总'!$J$5 -> 0 | O50: =G50*H50 -> 743290.04 | S50: 0
A51: 2.3.1.46 | B51: 混凝土地面开挖排水管槽及修补 1.测位、划线、刨沟、垃圾清理、填补 | F51: m | G51: 1000 | H51: =SUM(I51:N51) -> 157.4026 | I51: 153.84416 | K51: 2 | L51: =(I51+J51+K51)*'2-报价汇总'!$H$5 -> 1.5584416 | M51: =(I51+J51+K51+L51)*'2-报价汇总'!$I$5 -> 0 | N51: =(M51+L51+K51+J51+I51)*'2-报价汇总'!$J$5 -> 0 | O51: =G51*H51 -> 157402.6 | S51: 0
A52: 2.3.1.47 | B52: 提供及安装排水管UPVC200 | F52: m | G52: 1000 | H52: =SUM(I52:N52) -> 69.2658 | I52: 9.06 | J52: 57.76 | K52: 1.76 | L52: =(I52+J52+K52)*'2-报价汇总'!$H$5 -> 0.6858 | M52: =(I52+J52+K52+L52)*'2-报价汇总'!$I$5 -> 0 | N52: =(M52+L52+K52+J52+I52)*'2-报价汇总'!$J$5 -> 0
B53: 补充项
B54: 给排水工程合计： | O54: =SUM(O6:O51) -> 1.6278697e+08

Sheet 2.4-外立面工程
A1: 理想汽车中心店外立面工程量清单
A2: ='2.1-装饰工程'!A2 -> 注意：此报价清单每项不得随意更改、删减，如有任何增加项请务必在每大项最后“补充项“中列举，补充项及说明字体颜色均采用蓝色；且所有项目都需要填写。
A3: 序号 | B3: 项目名称 | C3: 项目特征 | D3: 适用范围 | E3: 工程量计算规则 | F3: 单位 | G3: 24/25年暂估工程量 | H3: 综合单价 | I3: 人工费 | J3: 材料费 | K3: 机械费 | L3: 安措费 | M3: 管理费 | N3: 利润 | O3: 24/25年暂估总价 | P3: 备注
B4: 2.4外立面工程
A5: 2.4.1 | B5: 外幕墙准备工作
A6: 2.4.1.01 | B6: 外幕墙拆除（玻璃、石材、外墙砖、铝板等） *包括原幕墙固定结构拆除 | C6: 1.拆除原有外幕墙 2.包括玻璃、石材、外墙砖、铝板等幕墙 3.幕墙固定结构拆除 | D6: 室外装饰装修及安装工程项目 | E6: 按设计图示尺寸面积计算 垃圾清运折算系数0.05 | F6: m2 | G6: 50000 | H6: =SUM(I6:N6) -> 34.978355 | I6: 33.672035 | J6: 0 | K6: 0.96 | L6: =(I6+J6+K6)*'2-报价汇总'!$H$5 -> 0.34632035 | M6: =(I6+J6+K6+L6)*'2-报价汇总'!$I$5 -> 0 | N6: =(M6+L6+K6+J6+I6)*'2-报价汇总'!$J$5 -> 0 | O6: =G6*H6 -> 1748917.7
A7: 2.4.1.02 | B7: 外墙涂料拆除 | C7: 1.外墙涂料拆除 2.垃圾清理 | D7: 室外装饰装修及安装工程项目 | E7: 按设计图示尺寸面积计算 垃圾清运折算系数0.001 | F7: m2 | G7: 50000 | H7: =SUM(I7:N7) -> 4.3722944 | I7: 4.2690043 | J7: 0 | K7: 0.06 | L7: =(I7+J7+K7)*'2-报价汇总'!$H$5 -> 0.043290043 | M7: =(I7+J7+K7+L7)*'2-报价汇总'!$I$5 -> 0 | N7: =(M7+L7+K7+J7+I7)*'2-报价汇总'!$J$5 -> 0 | O7: =G7*H7 -> 218614.72
A8: 2.4.1.03 | B8: 外墙开洞及修补 | C8: 1.外墙涂料拆除 2.垃圾清理 | D8: 室外装饰装修及安装工程项目 | E8: 按设计图示尺寸面积计算 | F8: m2 | G8: 6316.7927 | H8: =SUM(I8:N8) -> 122.42424 | I8: 16.212121 | J8: 5 | K8: 100 | L8: =(I8+J8+K8)*'2-报价汇总'!$H$5 -> 1.2121212 | M8: =(I8+J8+K8+L8)*'2-报价汇总'!$I$5 -> 0 | N8: =(M8+L8+K8+J8+I8)*'2-报价汇总'!$J$5 -> 0 | O8: =G8*H8 -> 773328.56
A9: 2.4.1.04 | B9: 拆除垃圾清理、清运（7立方） | E9: 分项工程垃圾清理折算系数*面积之和/7 | F9: 车 | G9: 911.51409 | H9: =SUM(I9:N9) -> 765.15152 | I9: 257.57576 | J9: 0 | K9: 500 | L9: =(I9+J9+K9)*'2-报价汇总'!$H$5 -> 7.5757576 | M9: =(I9+J9+K9+L9)*'2-报价汇总'!$I$5 -> 0 | N9: =(M9+L9+K9+J9+I9)*'2-报价汇总'!$J$5 -> 0 | O9: =G9*H9 -> 697446.39
A10: 2.4.1.05 | B10: 室外搭建围挡2m高 | C10: (材质：蓝色金属板含金属骨架) | D10: 室内、室外各个功能区域 | E10: 正投影面积计算 | F10: ㎡ | G10: 95565.349 | H10: =SUM(I10:N10) -> 112.5544 | I10: 49.9 | J10: 55.94 | K10: 5.6 | L10: =(I10+J10+K10)*'2-报价汇总'!$H$5 -> 1.1144 | M10: =(I10+J10+K10+L10)*'2-报价汇总'!$I$5 -> 0 | N10: =(M10+L10+K10+J10+I10)*'2-报价汇总'!$J$5 -> 0 | O10: =G10*H10 -> 10756300
A11: 2.4.1.06 | B11: 室外搭建围挡2m高 | C11: 龙骨：方钢龙骨 饰面：彩条布或宝丽布 | D11: 室内、室外各个功能区域 | E11: 正投影面积计算 | F11: ㎡ | G11: 95565.349 | H11: =SUM(I11:N11) -> 51.9443 | I11: 23.03 | J11: 25 | K11: 3.4 | L11: =(I11+J11+K11)*'2-报价汇总'!$H$5 -> 0.5143 | M11: =(I11+J11+K11+L11)*'2-报价汇总'!$I$5 -> 0 | N11: =(M11+L11+K11+J11+I11)*'2-报价汇总'!$J$5 -> 0 | O11: =G11*H11 -> 4964075.1
A12: 2.4.1.07 | B12: 室外墙面脚手架 | C12: 租赁、搭拆脚手架费用及相关运输费用 | D12: 室外结构标高超过4.5m计取此部分费用 | E12: 墙面投影面积 | F12: m2 | G12: 2033697.3 | H12: =SUM(I12:N12) -> 21.6443 | I12: 10.39 | J12: 10 | K12: 1.04 | L12: =(I12+J12+K12)*'2-报价汇总'!$H$5 -> 0.2143 | M12: =(I12+J12+K12+L12)*'2-报价汇总'!$I$5 -> 0 | N12: =(M12+L12+K12+J12+I12)*'2-报价汇总'!$J$5 -> 0 | O12: =G12*H12 -> 44017955
B13: 补充项
B14: 小计
A15: 2.4.2 | B15: 外墙涂料
A16: 2.4.2.01 | B16: 外墙涂料，基层处理（平涂） | C16: 1.基层清理 2.外墙防水腻子2遍，打磨 3.外墙涂料2遍底漆3遍面漆（平涂） | D16: 室外装饰装修及安装工程项目 | E16: 按设计图示尺寸面积计算 | F16: m2 | G16: 5000 | H16: =SUM(I16:N16) -> 54.21645 | I16: 23.409654 | J16: 29.93 | K16: 0.34 | L16: =(I16+J16+K16)*'2-报价汇总'!$H$5 -> 0.53679654 | M16: =(I16+J16+K16+L16)*'2-报价汇总'!$I$5 -> 0 | N16: =(M16+L16+K16+J16+I16)*'2-报价汇总'!$J$5 -> 0 | O16: =G16*H16 -> 271082.25
A17: 2.4.2.02 | B17: 外墙涂料，基层处理（弹涂） | C17: 1.基层清理 2.外墙防水腻子2遍，打磨 3.外墙涂料2遍底漆3遍面漆（弹涂） 4.弹涂：真石漆、肌理漆、水包水等 | D17: 室外装饰装修及安装工程项目 | E17: 按设计图示尺寸面积计算 | F17: m2 | G17: 5000 | H17: =SUM(I17:N17) -> 74.329004 | I17: 36.203074 | J17: 37 | K17: 0.39 | L17: =(I17+J17+K17)*'2-报价汇总'!$H$5 -> 0.73593074 | M17: =(I17+J17+K17+L17)*'2-报价汇总'!$I$5 -> 0 | N17: =(M17+L17+K17+J17+I17)*'2-报价汇总'!$J$5 -> 0 | O17: =G17*H17 -> 371645.02
A18: 2.4.2.03 | B18: 外墙氟碳漆，基层处理 | C18: 1.基层清理 2.外墙防水腻子2遍，打磨 3.氟碳喷涂 | D18: 室外装饰装修及安装工程项目 | E18: 按设计图示尺寸面积计算 | F18: m2 | G18: 5000 | H18: =SUM(I18:N18) -> 100.56277 | I18: 29.1571 | J18: 70 | K18: 0.41 | L18: =(I18+J18+K18)*'2-报价汇总'!$H$5 -> 0.995671 | M18: =(I18+J18+K18+L18)*'2-报价汇总'!$I$5 -> 0 | N18: =(M18+L18+K18+J18+I18)*'2-报价汇总'!$J$5 -> 0 | O18: =G18*H18 -> 502813.85
A19: 2.4.2.04 | B19: 外墙面国产花岗岩石材 | C19: 1.基层清理 2.钢龙骨自作安装 3.石材六面防护 4.干挂石材供应安装 | D19: 室外装饰装修及安装工程项目 | E19: 按设计图示尺寸面积计算 | F19: m2 | G19: 5000 | H19: =SUM(I19:N19) -> 480.95238 | I19: 186.89048 | J19: 280 | K19: 9.3 | L19: =(I19+J19+K19)*'2-报价汇总'!$H$5 -> 4.7619048 | M19: =(I19+J19+K19+L19)*'2-报价汇总'!$I$5 -> 0 | N19: =(M19+L19+K19+J19+I19)*'2-报价汇总'!$J$5 -> 0 | O19: =G19*H19 -> 2404761.9
B20: 补充项
B21: 小计
A22: 2.4.3 | B22: 外幕墙玻璃
A23: 2.4.3.01 | B23: 外玻璃幕墙 | C23: 1.钢结构骨架自作安装及相关结构改造施工 2.8+6+8mm中空钢化玻璃（普白） 3.氟碳喷涂铝框 | D23: 适用于外立面＞3米高外玻璃幕墙，≤3米高幕墙套用装饰内项目 | E23: 按图示尺寸以投影面积计算 | F23: m2 | G23: 5000 | H23: =SUM(I23:N23) -> 1202.381 | I23: 262.33619 | J23: 900 | K23: 28.14 | L23: =(I23+J23+K23)*'2-报价汇总'!$H$5 -> 11.904762 | M23: =(I23+J23+K23+L23)*'2-报价汇总'!$I$5 -> 0 | N23: =(M23+L23+K23+J23+I23)*'2-报价汇总'!$J$5 -> 0 | O23: =G23*H23 -> 6011904.8
A24: 2.4.3.02 | B24: 主入口玻璃门 | C24: 1.8+6+8mm钢化玻璃 2.氟碳喷涂门拉手，配套五金 3.金属边框氟碳喷涂 *多玛重力地弹簧、上夹、下夹、锁夹 | D24: 室外装饰装修及安装工程项目 | E24: 按图示尺寸以投影面积计算 | F24: m2 | G24: 5000 | H24: =SUM(I24:N24) -> 1049.3506 | I24: 233.96104 | J24: 800 | K24: 5 | L24: =(I24+J24+K24)*'2-报价汇总'!$H$5 -> 10.38961 | M24: =(I24+J24+K24+L24)*'2-报价汇总'!$I$5 -> 0 | N24: =(M24+L24+K24+J24+I24)*'2-报价汇总'!$J$5 -> 0 | O24: =G24*H24 -> 5246753.2
A25: 2.4.3.03 | B25: 外玻璃幕墙，15mm超白钢化玻璃 | C25: 1.钢结构骨架自作安装及相关结构改造施工 2.15mm钢化玻璃（超白） 3.氟碳喷涂铝框 | D25: 适用于外立面＞3米高外玻璃幕墙，≤3米高幕墙套用装饰内项目 | E25: 按图示尺寸以投影面积计算 | F25: m2 | G25: 5000 | H25: =SUM(I25:N25) -> 839.48052 | I25: 253.02883 | J25: 550 | K25: 28.14 | L25: =(I25+J25+K25)*'2-报价汇总'!$H$5 -> 8.3116883 | M25: =(I25+J25+K25+L25)*'2-报价汇总'!$I$5 -> 0 | N25: =(M25+L25+K25+J25+I25)*'2-报价汇总'!$J$5 -> 0 | O25: =G25*H25 -> 4197402.6
A26: 2.4.3.04 | B26: 外玻璃幕墙（明框或隐框） | C26: 1.钢结构骨架自作安装及相关结构改造施工 2.8+8夹胶玻璃钢化玻璃（普白） 3.氟碳喷涂铝框 | D26: 适用于外立面＞3米高外玻璃幕墙，≤3米高幕墙套用装饰内项目 | E26: 按图示尺寸以投影面积计算 | F26: m2 | G26: 5000 | H26: =SUM(I26:N26) -> 1202.381 | I26: 211.47619 | J26: 950 | K26: 29 | L26: =(I26+J26+K26)*'2-报价汇总'!$H$5 -> 11.904762 | M26: =(I26+J26+K26+L26)*'2-报价汇总'!$I$5 -> 0 | N26: =(M26+L26+K26+J26+I26)*'2-报价汇总'!$J$5 -> 0 | O26: =G26*H26 -> 6011904.8
A27: 2.4.3.05 | B27: 新做消防排烟平开窗（含电动装置） | C27: 1.成品电动排烟窗 2.电机、控制器、控制主板 3.设备调试安装 | D27: 室外装饰装修及安装工程项目 | E27: 按图示尺寸以投影面积计算 | F27: m2 | G27: 500 | H27: =SUM(I27:N27) -> 1311.6883 | I27: 263.7013 | J27: 1000 | K27: 35 | L27: =(I27+J27+K27)*'2-报价汇总'!$H$5 -> 12.987013 | M27: =(I27+J27+K27+L27)*'2-报价汇总'!$I$5 -> 0 | N27: =(M27+L27+K27+J27+I27)*'2-报价汇总'!$J$5 -> 0 | O27: =G27*H27 -> 655844.16
A28: 2.4.3.06 | B28: 双扇玻璃门： 1500*2200 | C28: 1.15钢化玻璃 2.氟碳喷涂门拉手，配套五金 3.金属边框氟碳喷涂 *多玛重力地弹簧、上夹、下夹、锁夹 | D28: 室外装饰装修及安装工程项目 | E28: 按图示尺寸以投影面积计算 | F28: 樘 | G28: 400 | H28: =SUM(I28:N28) -> 5211.7749 | I28: 944.30316 | J28: 4200 | K28: 15.87 | L28: =(I28+J28+K28)*'2-报价汇总'!$H$5 -> 51.601732 | M28: =(I28+J28+K28+L28)*'2-报价汇总'!$I$5 -> 0 | N28: =(M28+L28+K28+J28+I28)*'2-报价汇总'!$J$5 -> 0 | O28: =G28*H28 -> 2084710
A29: 2.4.3.07 | B29: 双扇玻璃门： L2500*H2400 | C29: 1.15mm钢化玻璃 2.氟碳喷涂门拉手，配套五金 3.金属边框氟碳喷涂 *多玛重力地弹簧、上夹、下夹、锁夹 | D29: 室外装饰装修及安装工程项目 | E29: 按设计图示数量计算 | F29: 樘 | G29: 400 | H29: =SUM(I29:N29) -> 6392.2944 | I29: 1100.1443 | J29: 5200 | K29: 28.86 | L29: =(I29+J29+K29)*'2-报价汇总'!$H$5 -> 63.290043 | M29: =(I29+J29+K29+L29)*'2-报价汇总'!$I$5 -> 0 | N29: =(M29+L29+K29+J29+I29)*'2-报价汇总'!$J$5 -> 0 | O29: =G29*H29 -> 2556917.7
A30: 2.4.3.08 | B30: 外窗、外墙彩钢板孔洞修补 | C30: 1.修补外窗玻璃&彩钢板 2.龙骨加固 | D30: 室外装饰装修及安装工程项目 | E30: 按设计图示数量计算 | F30: m2 | G30: 500 | H30: =SUM(I30:N30) -> 174.89177 | I30: 92.060173 | J30: 80 | K30: 1.1 | L30: =(I30+J30+K30)*'2-报价汇总'!$H$5 -> 1.7316017 | M30: =(I30+J30+K30+L30)*'2-报价汇总'!$I$5 -> 0 | N30: =(M30+L30+K30+J30+I30)*'2-报价汇总'!$J$5 -> 0 | O30: =G30*H30 -> 87445.887
B31: 补充项
B32: 小计
A33: 2.4.4 | B33: 雨棚
A34: 2.4.4.01 | B34: 外幕墙铝塑板雨棚 | C34: 1.铝塑板面层 2.铝方型材龙骨，用于固定铝板 3.方钢龙骨，固定于墙面 | D34: 室外装饰装修及安装工程项目 | E34: 1、按展开面积计算 2、雨棚跨度＞3.5米，雨棚所用型钢骨架及饰面材料骨架套用钢结构项目以吨计量，饰面材料单独计算。 | F34: m2 | G34: 43548.263 | H34: =SUM(I34:N34) -> 345.58615 | I34: 116.7945 | J34: 220 | K34: 5.37 | L34: =(I34+J34+K34)*'2-报价汇总'!$H$5 -> 3.421645 | M34: =(I34+J34+K34+L34)*'2-报价汇总'!$I$5 -> 0 | N34: =(M34+L34+K34+J34+I34)*'2-报价汇总'!$J$5 -> 0 | O34: =G34*H34 -> 15049676
A35: 2.4.4.02 | B35: 外幕墙钢化夹胶玻璃雨棚 | C35: 1.6+1.2+6钢化夹胶玻璃 2.镀锌方管龙骨，含结构链接 3.氟碳漆 | D35: 室外装饰装修及安装工程项目 | E35: 按水平投影面积计算 | F35: m2 | G35: 43548.263 | H35: =SUM(I35:N35) -> 559.65368 | I35: 95.972554 | J35: 450 | K35: 8.14 | L35: =(I35+J35+K35)*'2-报价汇总'!$H$5 -> 5.5411255 | M35: =(I35+J35+K35+L35)*'2-报价汇总'!$I$5 -> 0 | N35: =(M35+L35+K35+J35+I35)*'2-报价汇总'!$J$5 -> 0 | O35: =G35*H35 -> 24371946
B36: 补充项
B37: 小计
A38: 2.4.5 | B38: 门头
A39: 2.4.5.01 | B39: 外墙铝塑板，含基层处理 | C39: 1.铝塑板面层 2.镀锌方钢龙骨，用于固定铝塑板 3.含结构胶勾缝 | D39: 室外装饰装修及安装工程项目 | E39: 按设计图示尺寸面积计算 | F39: m2 | G39: 690830.51 | H39: =SUM(I39:N39) -> 402.25108 | I39: 138.2684 | J39: 240 | K39: 20 | L39: =(I39+J39+K39)*'2-报价汇总'!$H$5 -> 3.982684 | M39: =(I39+J39+K39+L39)*'2-报价汇总'!$I$5 -> 0 | N39: =(M39+L39+K39+J39+I39)*'2-报价汇总'!$J$5 -> 0 | O39: =G39*H39 -> 2.7788732e+08
A40: 2.4.5.02 | B40: 外墙LOGO安装位置角钢加固 | C40: 1.外墙龙骨加密 | D40: 室外装饰装修及安装工程项目 | E40: 按设计图示数量计算 | F40: 项 | G40: 911.51409 | H40: =SUM(I40:N40) -> 743.29004 | I40: 130.93074 | J40: 590 | K40: 15 | L40: =(I40+J40+K40)*'2-报价汇总'!$H$5 -> 7.3593074 | M40: =(I40+J40+K40+L40)*'2-报价汇总'!$I$5 -> 0 | N40: =(M40+L40+K40+J40+I40)*'2-报价汇总'!$J$5 -> 0 | O40: =G40*H40 -> 677519.35
A41: 2.4.5.03 | B41: 外墙铝板（蓝色），含基层处理 | C41: 1.蓝色铝板面层 2.镀锌方钢龙骨，用于固定铝塑板 3.含结构胶勾缝 4、铝板厚度：2mm | D41: 室外装饰装修及安装工程项目 | E41: 按设计图示尺寸面积计算 | F41: m2 | G41: 29299.213 | H41: =SUM(I41:N41) -> 629.61039 | I41: 103.37662 | J41: 500 | K41: 20 | L41: =(I41+J41+K41)*'2-报价汇总'!$H$5 -> 6.2337662 | M41: =(I41+J41+K41+L41)*'2-报价汇总'!$I$5 -> 0 | N41: =(M41+L41+K41+J41+I41)*'2-报价汇总'!$J$5 -> 0 | O41: =G41*H41 -> 18447089
A42: 2.4.5.04 | B42: 外墙铝塑板，含基层处理 | C42: 1.铝塑板面层 2.含结构胶勾缝 3.原基层打磨调平 | D42: 室外装饰装修及安装工程项目 | E42: 按设计图示尺寸面积计算 | F42: m2 | G42: 8000 | H42: =SUM(I42:N42) -> 149.95221 | I42: 76.467532 | J42: 60 | K42: 12 | L42: =(I42+J42+K42)*'2-报价汇总'!$H$5 -> 1.4846753 | M42: =(I42+J42+K42+L42)*'2-报价汇总'!$I$5 -> 0 | N42: =(M42+L42+K42+J42+I42)*'2-报价汇总'!$J$5 -> 0 | O42: =G42*H42 -> 1199617.7
A43: 2.4.5.05 | B43: 提供及安装外幕墙烤漆铝板 | C43: 包括结构、折边、防水等费用 *2mm厚 *金属龙骨基础；干挂铝板；铝板密拼且无需打胶；包含刨槽折边 | E43: 按展开面积计算 | F43: m2 | G43: 10000 | H43: =SUM(I43:N43) -> 679.19136 | I43: 104.11688 | J43: 542.34981 | K43: 26 | L43: =(I43+J43+K43)*'2-报价汇总'!$H$5 -> 6.7246669 | M43: =(I43+J43+K43+L43)*'2-报价汇总'!$I$5 -> 0 | N43: =(M43+L43+K43+J43+I43)*'2-报价汇总'!$J$5 -> 0 | O43: =G43*H43 -> 6791913.6
A44: 2.4.5.06 | B44: 提供及安装外幕墙烤漆铝板 | C44: 包括结构、折边、防水等费用 *3mm厚 *金属龙骨基础；干挂铝板；铝板密拼且无需打胶；包含刨槽折边 | D44: 50㎡以内 | E44: 按展开面积计算 | F44: ㎡ | G44: 10000 | H44: =SUM(I44:N44) -> 891.94805 | I44: 104.11688 | J44: 750 | K44: 29 | L44: =(I44+J44+K44)*'2-报价汇总'!$H$5 -> 8.8311688 | M44: =(I44+J44+K44+L44)*'2-报价汇总'!$I$5 -> 0 | N44: =(M44+L44+K44+J44+I44)*'2-报价汇总'!$J$5 -> 0 | O44: =G44*H44 -> 8919480.5
A45: 2.4.5.07 | B45: 提供及安装外幕墙烤漆铝板 | C45: 包括结构、折边、防水等费用 *3mm厚 *金属龙骨基础；干挂铝板；铝板密拼且无需打胶；包含刨槽折边 | D45: 50㎡以外 | E45: 按展开面积计算 | F45: ㎡ | G45: 10000 | H45: =SUM(I45:N45) -> 856.9697 | I45: 120.34485 | J45: 700 | K45: 28.14 | L45: =(I45+J45+K45)*'2-报价汇总'!$H$5 -> 8.4848485 | M45: =(I45+J45+K45+L45)*'2-报价汇总'!$I$5 -> 0 | N45: =(M45+L45+K45+J45+I45)*'2-报价汇总'!$J$5 -> 0 | O45: =G45*H45 -> 8569697
A46: 2.4.5.08 | B46: 木纹贴皮门头： 大门门头内框 | C46: (1)基层：钢架+铝塑板基层 (2)面层：防燃饰面，密缝拼装 | D46: 50㎡以内 | E46: 按展开面积计算 | F46: ㎡ | G46: 1000 | H46: =SUM(I46:N46) -> 814.12121 | I46: 277.06061 | J46: 500 | K46: 29 | L46: =(I46+J46+K46)*'2-报价汇总'!$H$5 -> 8.0606061 | M46: =(I46+J46+K46+L46)*'2-报价汇总'!$I$5 -> 0 | N46: =(M46+L46+K46+J46+I46)*'2-报价汇总'!$J$5 -> 0 | O46: =G46*H46 -> 814121.21
A47: 2.4.5.09 | B47: 木纹贴皮门头： 大门门头内框 | C47: (1)基层：钢架+铝塑板基层 (2)面层：防燃饰面，密缝拼装 | D47: 50㎡以外 | E47: 按展开面积计算 | F47: ㎡ | G47: 1000 | H47: =SUM(I47:N47) -> 773.02165 | I47: 236.36797 | J47: 500 | K47: 29 | L47: =(I47+J47+K47)*'2-报价汇总'!$H$5 -> 7.6536797 | M47: =(I47+J47+K47+L47)*'2-报价汇总'!$I$5 -> 0 | N47: =(M47+L47+K47+J47+I47)*'2-报价汇总'!$J$5 -> 0 | O47: =G47*H47 -> 773021.65
A48: 2.4.5.10 | B48: 木纹转印铝板 | C48: 1.干挂3mm厚铝板；铝板密拼且无需打胶；包含刨槽折边 2.60x60x4铝方型材龙骨，横向间距同金属板材宽度，纵向间距同金属板材长度，用螺栓与角钢连接，角钢用膨胀螺栓固定于墙体上包括结构、折边、防水等费用 | D48: 50㎡以内 | E48: 按展开面积计算 | F48: m2 | G48: 1000 | H48: =SUM(I48:N48) -> 800.72416 | I48: 120.34485 | J48: 644.31135 | K48: 28.14 | L48: =(I48+J48+K48)*'2-报价汇总'!$H$5 -> 7.927962 | M48: =(I48+J48+K48+L48)*'2-报价汇总'!$I$5 -> 0 | N48: =(M48+L48+K48+J48+I48)*'2-报价汇总'!$J$5 -> 0 | O48: =G48*H48 -> 800724.16
A49: 2.4.5.11 | B49: 木纹转印铝板 | C49: 1.干挂3mm厚铝板；铝板密拼且无需打胶；包含刨槽折边 2..60x60x4铝方型材龙骨，横向间距同金属板材宽度，纵向间距同金属板材长度，用螺栓与角钢连接，角钢用膨胀螺栓固定于墙体上包括结构、折边、防水等费用 | D49: 50㎡以外 | E49: 按展开面积计算 | F49: m2 | G49: 1000 | H49: =SUM(I49:N49) -> 792.36162 | I49: 120.34485 | J49: 636.03161 | K49: 28.14 | L49: =(I49+J49+K49)*'2-报价汇总'!$H$5 -> 7.8451645 | M49: =(I49+J49+K49+L49)*'2-报价汇总'!$I$5 -> 0 | N49: =(M49+L49+K49+J49+I49)*'2-报价汇总'!$J$5 -> 0 | O49: =G49*H49 -> 792361.62
A50: 2.4.5.12 | B50: 波纹铝板 | C50: 1.干挂3mm厚铝板；铝板密拼且无需打胶；包含刨槽折边 2..60x60x4铝方型材龙骨，横向间距同金属板材宽度，纵向间距同金属板材长度，用螺栓与角钢连接，角钢用膨胀螺栓固定于墙体上 | D50: 50㎡以内 | E50: 按展开面积计算 | F50: m2 | G50: 10000 | H50: =SUM(I50:N50) -> 1018.787 | I50: 167.70004 | J50: 820 | K50: 21 | L50: =(I50+J50+K50)*'2-报价汇总'!$H$5 -> 10.087 | M50: =(I50+J50+K50+L50)*'2-报价汇总'!$I$5 -> 0 | N50: =(M50+L50+K50+J50+I50)*'2-报价汇总'!$J$5 -> 0 | O50: =G50*H50 -> 10187870
A51: 2.4.5.13 | B51: 波纹铝板 | C51: 1.干挂3mm厚铝板；铝板密拼且无需打胶；包含刨槽折边 2..60x60x4铝方型材龙骨，横向间距同金属板材宽度，纵向间距同金属板材长度，用螺栓与角钢连接，角钢用膨胀螺栓固定于墙体上 | D51: 50㎡以外 | E51: 按展开面积计算 | F51: m2 | G51: 20000 | H51: =SUM(I51:N51) -> 933.88812 | I51: 167.70004 | J51: 735.94166 | K51: 21 | L51: =(I51+J51+K51)*'2-报价汇总'!$H$5 -> 9.246417 | M51: =(I51+J51+K51+L51)*'2-报价汇总'!$I$5 -> 0 | N51: =(M51+L51+K51+J51+I51)*'2-报价汇总'!$J$5 -> 0 | O51: =G51*H51 -> 18677762
A52: 2.4.5.14 | B52: 穿孔铝板 | C52: 3mm铝板冲孔，氟碳喷涂，20%哑光度 1.干挂3mm厚铝板；铝板密拼且无需打胶；包含刨槽折边 2.60x60x4铝方型材龙骨，横向间距同金属板材宽度，纵向间距同金属板材长度，用螺栓与角钢连接，角钢用膨胀螺栓固定于墙体上 | D52: 50㎡以内 | E52: 按展开面积计算 | F52: m2 | G52: 20000 | H52: =SUM(I52:N52) -> 925.39823 | I52: 165 | J52: 699.23587 | K52: 52 | L52: =(I52+J52+K52)*'2-报价汇总'!$H$5 -> 9.1623587 | M52: =(I52+J52+K52+L52)*'2-报价汇总'!$I$5 -> 0 | N52: =(M52+L52+K52+J52+I52)*'2-报价汇总'!$J$5 -> 0 | O52: =G52*H52 -> 18507965
A53: 2.4.5.15 | B53: 穿孔铝板 | C53: 3mm铝板冲孔，氟碳喷涂，20%哑光度 1.干挂3mm厚铝板；铝板密拼且无需打胶；包含刨槽折边 2.60x60x4铝方型材龙骨，横向间距同金属板材宽度，纵向间距同金属板材长度，用螺栓与角钢连接，角钢用膨胀螺栓固定于墙体上 | D53: 50㎡以外 | E53: 按展开面积计算 | F53: m2 | G53: 10000 | H53: =SUM(I53:N53) -> 865.96898 | I53: 165 | J53: 652.39503 | K53: 40 | L53: =(I53+J53+K53)*'2-报价汇总'!$H$5 -> 8.5739503 | M53: =(I53+J53+K53+L53)*'2-报价汇总'!$I$5 -> 0 | N53: =(M53+L53+K53+J53+I53)*'2-报价汇总'!$J$5 -> 0 | O53: =G53*H53 -> 8659689.8
A54: 2.4.5.16 | B54: 铝方管 40*60*3mm铝管 | C54: 1.铝方管规格：40*60*3mm 2.表面处理：氟碳喷涂，潘通Black U，5%闪银，10%哑光度 3.固定方式：螺栓、L50*4铝角码（氟碳喷涂）固定在竖向方钢管 | E54: 按延长米计算 | F54: m | G54: 1000 | H54: =SUM(I54:N54) -> 101.23765 | I54: 30.325294 | J54: 69.34 | K54: 0.57 | L54: =(I54+J54+K54)*'2-报价汇总'!$H$5 -> 1.0023529 | M54: =(I54+J54+K54+L54)*'2-报价汇总'!$I$5 -> 0 | N54: =(M54+L54+K54+J54+I54)*'2-报价汇总'!$J$5 -> 0 | O54: =G54*H54 -> 101237.65
A55: 2.4.5.17 | B55: 铝方管 50*100*2mm铝管 | C55: 1.铝方管规格：50*100*2mm 2.表面处理：氟碳喷涂，潘通Black U，5%闪银，10%哑光度 3.固定方式：螺栓、L50*4铝角码（氟碳喷涂）固定在竖向方钢管 | E55: 按延长米计算 | F55: m | G55: 1000 | H55: =SUM(I55:N55) -> 103.2916 | I55: 30.258908 | J55: 71.44 | K55: 0.57 | L55: =(I55+J55+K55)*'2-报价汇总'!$H$5 -> 1.0226891 | M55: =(I55+J55+K55+L55)*'2-报价汇总'!$I$5 -> 0 | N55: =(M55+L55+K55+J55+I55)*'2-报价汇总'!$J$5 -> 0 | O55: =G55*H55 -> 103291.6
A56: 2.4.5.18 | B56: 铝方管 50*150*2mm铝管 | C56: 1.铝方管规格：50*150*2mm 2.表面处理：氟碳喷涂，潘通Black U，5%闪银，10%哑光度 3.固定方式：螺栓、L50*4铝角码（氟碳喷涂）固定在竖向方钢管 | E56: 按延长米计算 | F56: m | G56: 1000 | H56: =SUM(I56:N56) -> 115.58983 | I56: 29.895378 | J56: 83.98 | K56: 0.57 | L56: =(I56+J56+K56)*'2-报价汇总'!$H$5 -> 1.1444538 | M56: =(I56+J56+K56+L56)*'2-报价汇总'!$I$5 -> 0 | N56: =(M56+L56+K56+J56+I56)*'2-报价汇总'!$J$5 -> 0 | O56: =G56*H56 -> 115589.83
A57: 2.4.5.19 | B57: 铝方管 50*200*2mm铝管 | C57: 1.铝方管规格：50*200*2mm 2.表面处理：氟碳喷涂，20%哑光度 3.固定方式：螺栓、L50*4铝角码（氟碳喷涂）固定在竖向方钢管 | E57: 按延长米计算 | F57: m | G57: 1000 | H57: =SUM(I57:N57) -> 144.65067 | I57: 35.558487 | J57: 106.98 | K57: 0.68 | L57: =(I57+J57+K57)*'2-报价汇总'!$H$5 -> 1.4321849 | M57: =(I57+J57+K57+L57)*'2-报价汇总'!$I$5 -> 0 | N57: =(M57+L57+K57+J57+I57)*'2-报价汇总'!$J$5 -> 0 | O57: =G57*H57 -> 144650.67
A58: 2.4.5.20 | B58: 铝方管 30*200*2mm铝管 | C58: 1.铝方管规格：30*200*2mm 2.表面处理：氟碳喷涂，20%哑光度 3.固定方式：螺栓、L50*4铝角码（氟碳喷涂）固定在竖向方钢管 | E58: 按延长米计算 | F58: m | G58: 1000 | H58: =SUM(I58:N58) -> 139.52429 | I58: 35.712857 | J58: 101.75 | K58: 0.68 | L58: =(I58+J58+K58)*'2-报价汇总'!$H$5 -> 1.3814286 | M58: =(I58+J58+K58+L58)*'2-报价汇总'!$I$5 -> 0 | N58: =(M58+L58+K58+J58+I58)*'2-报价汇总'!$J$5 -> 0 | O58: =G58*H58 -> 139524.29
A59: 2.4.5.21 | B59: 镀钛金属板（包边） | F59: m2 | G59: 1000 | H59: =SUM(I59:N59) -> 193.00071 | I59: 87.089816 | J59: 102 | K59: 2 | L59: =(I59+J59+K59)*'2-报价汇总'!$H$5 -> 1.9108982 | M59: =(I59+J59+K59+L59)*'2-报价汇总'!$I$5 -> 0 | N59: =(M59+L59+K59+J59+I59)*'2-报价汇总'!$J$5 -> 0 | O59: =G59*H59 -> 193000.71
A60: 2.4.5.22 | B60: 门头铝板弧形加工补差 | E60: 按展开面积计算 | F60: ㎡ | G60: 1000 | H60: =SUM(I60:N60) -> 174.89177 | I60: 76.160173 | J60: 95 | K60: 2 | L60: =(I60+J60+K60)*'2-报价汇总'!$H$5 -> 1.7316017 | M60: =(I60+J60+K60+L60)*'2-报价汇总'!$I$5 -> 0 | N60: =(M60+L60+K60+J60+I60)*'2-报价汇总'!$J$5 -> 0 | O60: =G60*H60 -> 174891.77
A61: 2.4.5.23 | B61: 大理石石材墙面 | C61: 1.30厚石材板 2.L50x50x5横向角钢龙骨(根据石板大小调整角钢尺寸)中距为石板高度+缝宽 3.L60x60x6(或由设计人定)竖向角钢龙骨(根据石板大小调整角钢尺寸)中距为石板宽度+缝宽 4.角钢龙骨焊于墙内预埋伸出的角钢头上或在墙内预埋钢板，然后用角钢焊连竖向角钢龙骨 | D61: 50㎡以内 | E61: 按展开面积计算 | F61: m2 | G61: 1000 | H61: =SUM(I61:N61) -> 509.39352 | I61: 56 | J61: 430.35002 | K61: 18 | L61: =(I61+J61+K61)*'2-报价汇总'!$H$5 -> 5.0435002 | M61: =(I61+J61+K61+L61)*'2-报价汇总'!$I$5 -> 0 | N61: =(M61+L61+K61+J61+I61)*'2-报价汇总'!$J$5 -> 0 | O61: =G61*H61 -> 509393.52
A62: 2.4.5.24 | B62: 大理石石材墙面 | C62: 1.30厚石材板 2.L50x50x5横向角钢龙骨(根据石板大小调整角钢尺寸)中距为石板高度+缝宽 3.L60x60x6(或由设计人定)竖向角钢龙骨(根据石板大小调整角钢尺寸)中距为石板宽度+缝宽 4.角钢龙骨焊于墙内预埋伸出的角钢头上或在墙内预埋钢板，然后用角钢焊连竖向角钢龙骨 | D62: 50㎡以外 | E62: 按展开面积计算 | F62: m2 | G62: 1000 | H62: =SUM(I62:N62) -> 475.43395 | I62: 52 | J62: 402.72668 | K62: 16 | L62: =(I62+J62+K62)*'2-报价汇总'!$H$5 -> 4.7072668 | M62: =(I62+J62+K62+L62)*'2-报价汇总'!$I$5 -> 0 | N62: =(M62+L62+K62+J62+I62)*'2-报价汇总'!$J$5 -> 0 | O62: =G62*H62 -> 475433.95
A63: 2.4.5.25 | B63: 花岗岩石材 | C63: 1.基层清理 2.钢龙骨制作安装 3.石材六面防护 4.干挂石材供应安装 5.30厚石材板 | E63: 按展开面积计算 | F63: m2 | G63: 1000 | H63: =SUM(I63:N63) -> 413.393 | I63: 120 | J63: 280 | K63: 9.3 | L63: =(I63+J63+K63)*'2-报价汇总'!$H$5 -> 4.093 | M63: =(I63+J63+K63+L63)*'2-报价汇总'!$I$5 -> 0 | N63: =(M63+L63+K63+J63+I63)*'2-报价汇总'!$J$5 -> 0 | O63: =G63*H63 -> 413393
A64: 2.4.5.26 | B64: 外幕墙烤漆铝框 | E64: 按延长米计算 | F64: m | G64: 1000 | H64: =SUM(I64:N64) -> 348.90909 | I64: 145.45455 | J64: 180 | K64: 20 | L64: =(I64+J64+K64)*'2-报价汇总'!$H$5 -> 3.4545455 | M64: =(I64+J64+K64+L64)*'2-报价汇总'!$I$5 -> 0 | N64: =(M64+L64+K64+J64+I64)*'2-报价汇总'!$J$5 -> 0 | O64: =G64*H64 -> 348909.09
A65: 2.4.5.27 | B65: 铝板漆面修复 | E65: 净长*高度计算 | F65: ㎡ | G65: 1000 | H65: =SUM(I65:N65) -> 96.190476 | I65: 53.238095 | J65: 40 | K65: 2 | L65: =(I65+J65+K65)*'2-报价汇总'!$H$5 -> 0.95238095 | M65: =(I65+J65+K65+L65)*'2-报价汇总'!$I$5 -> 0 | N65: =(M65+L65+K65+J65+I65)*'2-报价汇总'!$J$5 -> 0 | O65: =G65*H65 -> 96190.476
A66: 2.4.5.28 | B66: 中文标识内嵌正发光 | C66: 1.灯箱背板：白色铝塑板框体 2.内置5500K防水LED 3.镶嵌乳白色亚克力3mm+5mm 4.文字处面板镂空 | E66: 按图示面积计算 | F66: m2 | G66: 1000 | H66: =SUM(I66:N66) -> 1486.3593 | I66: 259.64292 | J66: 1180 | K66: 32 | L66: =(I66+J66+K66)*'2-报价汇总'!$H$5 -> 14.716429 | M66: =(I66+J66+K66+L66)*'2-报价汇总'!$I$5 -> 0 | N66: =(M66+L66+K66+J66+I66)*'2-报价汇总'!$J$5 -> 0 | O66: =G66*H66 -> 1486359.3
B67: 补充项
B68: 小计
B69: 外立面工程合计： | O69: =SUM(O6:O66) -> 5.1900947e+08

Sheet 2.5-室外工程
A1: 理想汽车中心店室外工程量清单
A2: ='2.1-装饰工程'!A2 -> 注意：此报价清单每项不得随意更改、删减，如有任何增加项请务必在每大项最后“补充项“中列举，补充项及说明字体颜色均采用蓝色；且所有项目都需要填写。
A3: 序号 | B3: 项目名称 | C3: 项目特征 | D3: 适用范围 | E3: 工程量计算规则 | F3: 单位 | G3: 24/25年暂估工程量 | H3: 综合单价 | I3: 人工费 | J3: 材料费 | K3: 机械费 | L3: 安措费 | M3: 管理费 | N3: 利润 | O3: 24/25年暂估总价 | P3: 备注
B4: 2.5室外工程
A5: 2.5.1 | B5: 沥青地面，含场地平整
A6: 2.5.1.1 | B6: 30mm厚细沥青混凝土 | C6: 1.地面清理、平整 2.30mm后沥青混凝土 3.面层压平 | D6: 室外装饰装修及安装工程项目 | E6: 按设计图示尺寸面积计算 | F6: m2 | G6: 1025476.1 | H6: =SUM(I6:N6) -> 45.471861 | I6: 2.511645 | J6: 34.54 | K6: 7.97 | L6: =(I6+J6+K6)*'2-报价汇总'!$H$5 -> 0.45021645 | M6: =(I6+J6+K6+L6)*'2-报价汇总'!$I$5 -> 0 | N6: =(M6+L6+K6+J6+I6)*'2-报价汇总'!$J$5 -> 0 | O6: =G6*H6 -> 46630308
A7: 2.5.1.2 | B7: 50mm厚粗沥青混凝土 | C7: 1.地面清理、平整 2.50mm后沥青混凝土 3.面层压平 | D7: 室外装饰装修及安装工程项目 | E7: 按设计图示尺寸面积计算 | F7: m2 | G7: 725476.13 | H7: =SUM(I7:N7) -> 64.709957 | I7: 2.1992641 | J7: 53.8 | K7: 8.07 | L7: =(I7+J7+K7)*'2-报价汇总'!$H$5 -> 0.64069264 | M7: =(I7+J7+K7+L7)*'2-报价汇总'!$I$5 -> 0 | N7: =(M7+L7+K7+J7+I7)*'2-报价汇总'!$J$5 -> 0 | O7: =G7*H7 -> 46945529
A8: 2.5.1.3 | B8: 拆除原有沥青路面 | C8: 1.拆除原有沥青地面 2.垃圾清理及垃圾外运 | D8: 室外装饰装修及安装工程项目 | E8: 按设计图示尺寸面积计算 | F8: m2 | G8: 2000 | H8: =SUM(I8:N8) -> 27.982684 | I8: 27.225628 | J8: 0 | K8: 0.48 | L8: =(I8+J8+K8)*'2-报价汇总'!$H$5 -> 0.27705628 | M8: =(I8+J8+K8+L8)*'2-报价汇总'!$I$5 -> 0 | N8: =(M8+L8+K8+J8+I8)*'2-报价汇总'!$J$5 -> 0 | O8: =G8*H8 -> 55965.368
A9: 2.5.1.4 | B9: 150mm素混凝土基层 | C9: 1.地面清理、平整 2.150mm素混凝土基层 3.面层压光 4.防滑处理 | D9: 室外装饰装修及安装工程项目 | E9: 按设计图示尺寸面积计算 | F9: m2 | G9: 73406.441 | H9: =SUM(I9:N9) -> 83.073593 | I9: 5.2810823 | J9: 76.83 | K9: 0.14 | L9: =(I9+J9+K9)*'2-报价汇总'!$H$5 -> 0.82251082 | M9: =(I9+J9+K9+L9)*'2-报价汇总'!$I$5 -> 0 | N9: =(M9+L9+K9+J9+I9)*'2-报价汇总'!$J$5 -> 0 | O9: =G9*H9 -> 6098136.8
A10: 2.5.1.5 | B10: 150mm碎石垫层基层 | C10: 1.地面清理、平整 2.150mm碎石垫层基层 | D10: 室外装饰装修及安装工程项目 | E10: 按设计图示尺寸面积计算 | F10: m2 | G10: 73406.441 | H10: =SUM(I10:N10) -> 40.225108 | I10: 10.28684 | J10: 26 | K10: 3.54 | L10: =(I10+J10+K10)*'2-报价汇总'!$H$5 -> 0.3982684 | M10: =(I10+J10+K10+L10)*'2-报价汇总'!$I$5 -> 0 | N10: =(M10+L10+K10+J10+I10)*'2-报价汇总'!$J$5 -> 0 | O10: =G10*H10 -> 2952782
A11: 2.5.1.6 | B11: 厚100mm混凝土地面 | C11: 1.地面清理、场地平整 2.100mm混凝土地面 3.满铺钢筋网片 4.面层压光，防滑处理 | D11: 室外装饰装修及安装工程项目 | E11: 按设计图示尺寸面积计算 | F11: m2 | G11: 73406.441 | H11: =SUM(I11:N11) -> 94.441558 | I11: 28.396494 | J11: 63.2 | K11: 1.91 | L11: =(I11+J11+K11)*'2-报价汇总'!$H$5 -> 0.93506494 | M11: =(I11+J11+K11+L11)*'2-报价汇总'!$I$5 -> 0 | N11: =(M11+L11+K11+J11+I11)*'2-报价汇总'!$J$5 -> 0 | O11: =G11*H11 -> 6932618.7
A12: 2.5.1.7 | B12: 厚100mm混凝土地面 | C12: 1.地面清理、场地平整 2.100mm混凝土地面 3.面层压光，防滑处理 | D12: 室外装饰装修及安装工程项目 | E12: 按设计图示尺寸面积计算 | F12: m2 | G12: 73406.441 | H12: =SUM(I12:N12) -> 52.467532 | I12: 4.8480519 | J12: 46.41 | K12: 0.69 | L12: =(I12+J12+K12)*'2-报价汇总'!$H$5 -> 0.51948052 | M12: =(I12+J12+K12+L12)*'2-报价汇总'!$I$5 -> 0 | N12: =(M12+L12+K12+J12+I12)*'2-报价汇总'!$J$5 -> 0 | O12: =G12*H12 -> 3851454.8
A13: 2.5.1.8 | B13: 草坪砖地面供应及安装 | C13: 1.地面清理、场地平整 2.草坪砖地面供应及安装 | D13: 室外装饰装修及安装工程项目 | E13: 按设计图示尺寸面积计算 | F13: m2 | G13: 5000 | H13: =SUM(I13:N13) -> 78.701299 | I13: 27.162078 | J13: 50 | K13: 0.76 | L13: =(I13+J13+K13)*'2-报价汇总'!$H$5 -> 0.77922078 | M13: =(I13+J13+K13+L13)*'2-报价汇总'!$I$5 -> 0 | N13: =(M13+L13+K13+J13+I13)*'2-报价汇总'!$J$5 -> 0 | O13: =G13*H13 -> 393506.49
A14: 2.5.1.9 | B14: 广场砖地面供应及安装 | C14: 1.地面清理、场地平整 2.广场砖地面供应及安装 | D14: 室外装饰装修及安装工程项目 | E14: 按设计图示尺寸面积计算 | F14: m2 | G14: 5000 | H14: =SUM(I14:N14) -> 78.701299 | I14: 31.862078 | J14: 45 | K14: 1.06 | L14: =(I14+J14+K14)*'2-报价汇总'!$H$5 -> 0.77922078 | M14: =(I14+J14+K14+L14)*'2-报价汇总'!$I$5 -> 0 | N14: =(M14+L14+K14+J14+I14)*'2-报价汇总'!$J$5 -> 0 | O14: =G14*H14 -> 393506.49
A15: 2.5.1.10 | B15: 道牙新做 | C15: 1.地面清理、场地平整 2.地面开挖、回填 3.道牙石供应及安装 | D15: 室外装饰装修及安装工程项目 | F15: m | G15: 97349.705 | H15: =SUM(I15:N15) -> 48.095238 | I15: 12.109048 | J15: 35 | K15: 0.51 | L15: =(I15+J15+K15)*'2-报价汇总'!$H$5 -> 0.47619048 | M15: =(I15+J15+K15+L15)*'2-报价汇总'!$I$5 -> 0 | N15: =(M15+L15+K15+J15+I15)*'2-报价汇总'!$J$5 -> 0 | O15: =G15*H15 -> 4682057.3
A16: 2.5.1.11 | B16: 新做方钢栏杆 | C16: 1.方钢栏杆（1800mm高）含地面基础 2.表面防锈处理 3.满刷油漆面层 | D16: 室外装饰装修及安装工程项目 | F16: m | G16: 3000 | H16: =SUM(I16:N16) -> 218.61472 | I16: 92.540216 | J16: 120 | K16: 3.91 | L16: =(I16+J16+K16)*'2-报价汇总'!$H$5 -> 2.1645022 | M16: =(I16+J16+K16+L16)*'2-报价汇总'!$I$5 -> 0 | N16: =(M16+L16+K16+J16+I16)*'2-报价汇总'!$J$5 -> 0 | O16: =G16*H16 -> 655844.16
A17: 2.5.1.12 | B17: 钢塑围栏，高度:1500mm高 | C17: 1.成品钢塑围栏 2.高度1500mm高 3.含地面基础制作 | D17: 室外装饰装修及安装工程项目 | F17: m | G17: 2000 | H17: =SUM(I17:N17) -> 262.33766 | I17: 27.10026 | J17: 230 | K17: 2.64 | L17: =(I17+J17+K17)*'2-报价汇总'!$H$5 -> 2.5974026 | M17: =(I17+J17+K17+L17)*'2-报价汇总'!$I$5 -> 0 | N17: =(M17+L17+K17+J17+I17)*'2-报价汇总'!$J$5 -> 0 | O17: =G17*H17 -> 524675.32
A18: 2.5.1.13 | B18: 金属小围栏，含铁链 | C18: 1.成品金属小围栏，含铁链（1800mm高）含地面基础 | D18: 室外装饰装修及安装工程项目 | E18: 按设计图示数量计算 | F18: 根 | G18: 1000 | H18: =SUM(I18:N18) -> 87.445887 | I18: 5.9800866 | J18: 80 | K18: 0.6 | L18: =(I18+J18+K18)*'2-报价汇总'!$H$5 -> 0.86580087 | M18: =(I18+J18+K18+L18)*'2-报价汇总'!$I$5 -> 0 | N18: =(M18+L18+K18+J18+I18)*'2-报价汇总'!$J$5 -> 0 | O18: =G18*H18 -> 87445.887
A19: 2.5.1.14 | B19: 外围墙围栏翻新处理 | C19: 1.面层打磨 2.表面防锈处理 3.满刷油漆面层 | D19: 室外装饰装修及安装工程项目 | F19: m | G19: 1000 | H19: =SUM(I19:N19) -> 76.952381 | I19: 57.830476 | J19: 17 | K19: 1.36 | L19: =(I19+J19+K19)*'2-报价汇总'!$H$5 -> 0.76190476 | M19: =(I19+J19+K19+L19)*'2-报价汇总'!$I$5 -> 0 | N19: =(M19+L19+K19+J19+I19)*'2-报价汇总'!$J$5 -> 0 | O19: =G19*H19 -> 76952.381
A20: 2.5.1.15 | B20: 室外停车场划线、喷字 | C20: 1.基层清理 2.150mm宽白色热融漆划线； 3.含白色数字编号、标识等，按公司规范字体； | D20: 室外装饰装修及安装工程项目 | E20: 按设计图示数量计算 | F20: 车位 | G20: 37372.078 | H20: =SUM(I20:N20) -> 139.91342 | I20: 36.528139 | J20: 100 | K20: 2 | L20: =(I20+J20+K20)*'2-报价汇总'!$H$5 -> 1.3852814 | M20: =(I20+J20+K20+L20)*'2-报价汇总'!$I$5 -> 0 | N20: =(M20+L20+K20+J20+I20)*'2-报价汇总'!$J$5 -> 0 | O20: =G20*H20 -> 5228855.2
A21: 2.5.1.16 | B21: 室外停车位车档供应及安装 | C21: 1.成品车档制作安装 | D21: 室外装饰装修及安装工程项目 | E21: 按设计图示数量计算 | F21: 对 | G21: 51956.303 | H21: =SUM(I21:N21) -> 139.91342 | I21: 27.028139 | J21: 110 | K21: 1.5 | L21: =(I21+J21+K21)*'2-报价汇总'!$H$5 -> 1.3852814 | M21: =(I21+J21+K21+L21)*'2-报价汇总'!$I$5 -> 0 | N21: =(M21+L21+K21+J21+I21)*'2-报价汇总'!$J$5 -> 0 | O21: =G21*H21 -> 7269384.1
A22: 2.5.1.17 | B22: 室外原围墙间结构柱刷外墙涂料，含基层处理 | C22: 1.基层清理 2.外墙防水腻子2遍，打磨 3.外墙涂料2遍底漆3遍面漆（平涂） | D22: 室外装饰装修及安装工程项目 | E22: 按设计图示尺寸面积计算 | F22: m2 | G22: 1000 | H22: =SUM(I22:N22) -> 50.718615 | I22: 13.79645 | J22: 36 | K22: 0.42 | L22: =(I22+J22+K22)*'2-报价汇总'!$H$5 -> 0.5021645 | M22: =(I22+J22+K22+L22)*'2-报价汇总'!$I$5 -> 0 | N22: =(M22+L22+K22+J22+I22)*'2-报价汇总'!$J$5 -> 0 | O22: =G22*H22 -> 50718.615
A23: 2.5.1.18 | B23: 室外成品岗亭提供及安装，含地面基础 | C23: 1.室外成品岗亭 | D23: 室外装饰装修及安装工程项目 | F23: 项 | G23: 300 | H23: =SUM(I23:N23) -> 14865.801 | I23: 2518.6147 | J23: 12000 | K23: 200 | L23: =(I23+J23+K23)*'2-报价汇总'!$H$5 -> 147.18615 | M23: =(I23+J23+K23+L23)*'2-报价汇总'!$I$5 -> 0 | N23: =(M23+L23+K23+J23+I23)*'2-报价汇总'!$J$5 -> 0 | O23: =G23*H23 -> 4459740.3
A24: 2.5.1.19 | B24: 提供及安装立招基础、立招电源 | C24: 1.室外地面开挖 2.混凝土基础（含模板、钢筋等） 3.预留室外电源 | D24: 室外装饰装修及安装工程项目 | F24: 项 | G24: 300 | H24: =SUM(I24:N24) -> 11805.195 | I24: 1638.3117 | J24: 10000 | K24: 50 | L24: =(I24+J24+K24)*'2-报价汇总'!$H$5 -> 116.88312 | M24: =(I24+J24+K24+L24)*'2-报价汇总'!$I$5 -> 0 | N24: =(M24+L24+K24+J24+I24)*'2-报价汇总'!$J$5 -> 0 | O24: =G24*H24 -> 3541558.4
A25: 2.5.1.20 | B25: 厂区大门新做 (1)铁艺大门新做，含轨道 | C25: 1.大门地面轨道制作 2.定制厂区大门提供及安装 | D25: 室外装饰装修及安装工程项目 | E25: 按设计图示尺寸面积计算 | F25: m2 | G25: 50 | H25: =SUM(I25:N25) -> 830.73593 | I25: 21.880823 | J25: 800 | K25: 0.63 | L25: =(I25+J25+K25)*'2-报价汇总'!$H$5 -> 8.2251082 | M25: =(I25+J25+K25+L25)*'2-报价汇总'!$I$5 -> 0 | N25: =(M25+L25+K25+J25+I25)*'2-报价汇总'!$J$5 -> 0 | O25: =G25*H25 -> 41536.797
A26: 2.5.1.21 | B26: 电动伸缩门，含轨道 | C26: 1.本体、配管配线、安装 | D26: 室外装饰装修及安装工程项目 | E26: 按设计图示数量计算 | F26: 套 | G26: 50 | H26: =SUM(I26:N26) -> 4022.5108 | I26: 469.68398 | J26: 3500 | K26: 13 | L26: =(I26+J26+K26)*'2-报价汇总'!$H$5 -> 39.82684 | M26: =(I26+J26+K26+L26)*'2-报价汇总'!$I$5 -> 0 | N26: =(M26+L26+K26+J26+I26)*'2-报价汇总'!$J$5 -> 0 | O26: =G26*H26 -> 201125.54
A27: 2.5.1.22 | B27: 遥控挡车杆 | C27: 2.本体、配管配线、安装 | D27: 室外装饰装修及安装工程项目 | E27: 按设计图示数量计算 | F27: 套 | G27: 1823.0282 | H27: =SUM(I27:N27) -> 2098.7013 | I27: 262.92208 | J27: 1800 | K27: 15 | L27: =(I27+J27+K27)*'2-报价汇总'!$H$5 -> 20.779221 | M27: =(I27+J27+K27+L27)*'2-报价汇总'!$I$5 -> 0 | N27: =(M27+L27+K27+J27+I27)*'2-报价汇总'!$J$5 -> 0 | O27: =G27*H27 -> 3825991.6
A28: 2.5.1.23 | B28: 承重井盖（能承重车） | C28: 1.球墨铸铁承重井盖 | D28: 室外装饰装修及安装工程项目 | E28: 按设计图示数量计算 | F28: 个 | G28: 5469.0846 | H28: =SUM(I28:N28) -> 466.08658 | I28: 106.47186 | J28: 350 | K28: 5 | L28: =(I28+J28+K28)*'2-报价汇总'!$H$5 -> 4.6147186 | M28: =(I28+J28+K28+L28)*'2-报价汇总'!$I$5 -> 0 | N28: =(M28+L28+K28+J28+I28)*'2-报价汇总'!$J$5 -> 0 | O28: =G28*H28 -> 2549066.9
A29: 2.5.1.24 | B29: 室外路灯，含相关电路 | C29: 1.本体及配管配线等工作 2.挖土、回填、基础制作等工作 | D29: 室外装饰装修及安装工程项目 | E29: 按设计图示数量计算 | F29: 个 | G29: 500 | H29: =SUM(I29:N29) -> 1224.2424 | I29: 192.12121 | J29: 1000 | K29: 20 | L29: =(I29+J29+K29)*'2-报价汇总'!$H$5 -> 12.121212 | M29: =(I29+J29+K29+L29)*'2-报价汇总'!$I$5 -> 0 | N29: =(M29+L29+K29+J29+I29)*'2-报价汇总'!$J$5 -> 0 | O29: =G29*H29 -> 612121.21
A30: 2.5.1.25 | B30: 室外高光灯，含相关电路 | C30: 1.本体及配管配线等工作 3.挖土、回填、基础制作等工作 | D30: 室外装饰装修及安装工程项目 | E30: 按设计图示数量计算 | F30: 个 | G30: 500 | H30: =SUM(I30:N30) -> 699.5671 | I30: 172.64069 | J30: 500 | K30: 20 | L30: =(I30+J30+K30)*'2-报价汇总'!$H$5 -> 6.9264069 | M30: =(I30+J30+K30+L30)*'2-报价汇总'!$I$5 -> 0 | N30: =(M30+L30+K30+J30+I30)*'2-报价汇总'!$J$5 -> 0 | O30: =G30*H30 -> 349783.55
A31: 2.5.1.26 | B31: 室外金属篦子 | C31: 1.球墨铸铁金属篦子 | D31: 室外装饰装修及安装工程项目 | E31: 按设计图示数量计算 | F31: 个 | G31: 500 | H31: =SUM(I31:N31) -> 87.445887 | I31: 4.5800866 | J31: 80 | K31: 2 | L31: =(I31+J31+K31)*'2-报价汇总'!$H$5 -> 0.86580087 | M31: =(I31+J31+K31+L31)*'2-报价汇总'!$I$5 -> 0 | N31: =(M31+L31+K31+J31+I31)*'2-报价汇总'!$J$5 -> 0 | O31: =G31*H31 -> 43722.944
A32: 2.5.1.27 | B32: 给排水接入市政管线DN100 | C32: 1.PE管道及管件供应安装 2.管沟开挖、回填 | D32: 室外装饰装修及安装工程项目 | F32: m | G32: 500 | H32: =SUM(I32:N32) -> 121.2 | I32: 29.5 | J32: 90 | K32: 0.5 | L32: =(I32+J32+K32)*'2-报价汇总'!$H$5 -> 1.2 | M32: =(I32+J32+K32+L32)*'2-报价汇总'!$I$5 -> 0 | N32: =(M32+L32+K32+J32+I32)*'2-报价汇总'!$J$5 -> 0 | O32: =G32*H32 -> 60600
A33: 2.5.1.28 | B33: 给排水接入市政管线DN150 | C33: 1.PE管道及管件供应安装 2.管沟开挖、回填 | D33: 室外装饰装修及安装工程项目 | F33: m | G33: 500 | H33: =SUM(I33:N33) -> 154.60433 | I33: 52.573593 | J33: 100 | K33: 0.5 | L33: =(I33+J33+K33)*'2-报价汇总'!$H$5 -> 1.5307359 | M33: =(I33+J33+K33+L33)*'2-报价汇总'!$I$5 -> 0 | N33: =(M33+L33+K33+J33+I33)*'2-报价汇总'!$J$5 -> 0 | O33: =G33*H33 -> 77302.165
A34: 2.5.1.29 | B34: 给排水接入市政管线DN200 | C34: 1.PE管道及管件供应安装 2.管沟开挖、回填 | D34: 室外装饰装修及安装工程项目 | F34: m | G34: 500 | H34: =SUM(I34:N34) -> 168.24589 | I34: 56.080087 | J34: 110 | K34: 0.5 | L34: =(I34+J34+K34)*'2-报价汇总'!$H$5 -> 1.6658009 | M34: =(I34+J34+K34+L34)*'2-报价汇总'!$I$5 -> 0 | N34: =(M34+L34+K34+J34+I34)*'2-报价汇总'!$J$5 -> 0 | O34: =G34*H34 -> 84122.944
A35: 2.5.1.30 | B35: 空调室外机基座 | C35: 1.挖土、回填等工作 2.混凝土基础 | D35: 室外装饰装修及安装工程项目 | E35: 按设计图示数量计算 | F35: 个 | G35: 500 | H35: =SUM(I35:N35) -> 874.45887 | I35: 265.42087 | J35: 600 | K35: 0.38 | L35: =(I35+J35+K35)*'2-报价汇总'!$H$5 -> 8.6580087 | M35: =(I35+J35+K35+L35)*'2-报价汇总'!$I$5 -> 0 | N35: =(M35+L35+K35+J35+I35)*'2-报价汇总'!$J$5 -> 0 | O35: =G35*H35 -> 437229.44
A36: 2.5.1.31 | B36: 化粪池 | C36: 1.地面开挖及回填等工作 2.钢筋混凝土化粪池制作（含模板） 3.内外防水处理 | D36: 室外装饰装修及安装工程项目 | E36: 按设计图示尺寸以混凝土体积计算 | F36: m3 | G36: 1000 | H36: =SUM(I36:N36) -> 3935.0649 | I36: 661.1039 | J36: 3200 | K36: 35 | L36: =(I36+J36+K36)*'2-报价汇总'!$H$5 -> 38.961039 | M36: =(I36+J36+K36+L36)*'2-报价汇总'!$I$5 -> 0 | N36: =(M36+L36+K36+J36+I36)*'2-报价汇总'!$J$5 -> 0 | O36: =G36*H36 -> 3935064.9
A37: 2.5.1.32 | B37: 雨水井 | C37: 1.地面开挖及回填等工作 2.预制混凝土井道及井圈 3.球磨铸铁承重井盖 | D37: 室外装饰装修及安装工程项目 | E37: 按设计图示数量计算 | F37: 个 | G37: 200 | H37: =SUM(I37:N37) -> 3397.2727 | I37: 513.63636 | J37: 2800 | K37: 50 | L37: =(I37+J37+K37)*'2-报价汇总'!$H$5 -> 33.636364 | M37: =(I37+J37+K37+L37)*'2-报价汇总'!$I$5 -> 0 | N37: =(M37+L37+K37+J37+I37)*'2-报价汇总'!$J$5 -> 0 | O37: =G37*H37 -> 679454.55
A38: 2.5.1.33 | B38: 200mm厚混凝土地面 | C38: 1.地面清理、场地平整 2.200mmC20混凝土地面 3.满铺钢筋网片φ6，横纵向间距200mm 4.面层压光，防滑处理 | D38: 室外装饰装修及安装工程项目 | E38: 按设计图示尺寸面积计算 | F38: m2 | G38: 500 | H38: =SUM(I38:N38) -> 166.14719 | I38: 114.50216 | J38: 40 | K38: 10 | L38: =(I38+J38+K38)*'2-报价汇总'!$H$5 -> 1.6450216 | M38: =(I38+J38+K38+L38)*'2-报价汇总'!$I$5 -> 0 | N38: =(M38+L38+K38+J38+I38)*'2-报价汇总'!$J$5 -> 0 | O38: =G38*H38 -> 83073.593
A39: 2.5.1.34 | B39: 排水管道土方开挖 | C39: 1.土方开挖 | D39: 室外装饰装修及安装工程项目 | E39: 按设计图示尺寸体积计算 | F39: m3 | G39: 500 | H39: =SUM(I39:N39) -> 69.95671 | I39: 62.794069 | J39: 3.8 | K39: 2.67 | L39: =(I39+J39+K39)*'2-报价汇总'!$H$5 -> 0.69264069 | M39: =(I39+J39+K39+L39)*'2-报价汇总'!$I$5 -> 0 | N39: =(M39+L39+K39+J39+I39)*'2-报价汇总'!$J$5 -> 0 | O39: =G39*H39 -> 34978.355
A40: 2.5.1.35 | B40: 排水管道土方回填 | C40: 1.土方回填 2.余土清理 | D40: 室内、室外装饰装修及安装工程项目 | E40: 按设计图示尺寸体积计算 | F40: m3 | G40: 500 | H40: =SUM(I40:N40) -> 87.445887 | I40: 77.240087 | J40: 7 | K40: 2.34 | L40: =(I40+J40+K40)*'2-报价汇总'!$H$5 -> 0.86580087 | M40: =(I40+J40+K40+L40)*'2-报价汇总'!$I$5 -> 0 | N40: =(M40+L40+K40+J40+I40)*'2-报价汇总'!$J$5 -> 0 | O40: =G40*H40 -> 43722.944
A41: 2.5.1.36 | B41: 户外地面橡胶减速带 | C41: 1.成品橡胶减速带提供及安装 | D41: 室外装饰装修及安装工程项目 | F41: m | G41: 5683.5115 | H41: =SUM(I41:N41) -> 87.445887 | I41: 6.5800866 | J41: 75 | K41: 5 | L41: =(I41+J41+K41)*'2-报价汇总'!$H$5 -> 0.86580087 | M41: =(I41+J41+K41+L41)*'2-报价汇总'!$I$5 -> 0 | N41: =(M41+L41+K41+J41+I41)*'2-报价汇总'!$J$5 -> 0 | O41: =G41*H41 -> 496999.71
A42: 2.5.1.37 | B42: 室外金属围栏，H:1500 | C42: 1.成品金属围栏 2.高度1500mm高 3.含地面基础制作 | D42: 室外装饰装修及安装工程项目 | F42: m | G42: 25155.443 | H42: =SUM(I42:N42) -> 262.33766 | I42: 27.10026 | J42: 230 | K42: 2.64 | L42: =(I42+J42+K42)*'2-报价汇总'!$H$5 -> 2.5974026 | M42: =(I42+J42+K42+L42)*'2-报价汇总'!$I$5 -> 0 | N42: =(M42+L42+K42+J42+I42)*'2-报价汇总'!$J$5 -> 0 | O42: =G42*H42 -> 6599220
A43: 2.5.1.38 | B43: 室外金属围栏，H:400 | C43: 1.成品金属围栏 2.高度400mm高 3.含地面基础制作 | D43: 室外装饰装修及安装工程项目 | F43: m | G43: 25155.443 | H43: =SUM(I43:N43) -> 133.35498 | I43: 20.854632 | J43: 110 | K43: 1.18 | L43: =(I43+J43+K43)*'2-报价汇总'!$H$5 -> 1.3203463 | M43: =(I43+J43+K43+L43)*'2-报价汇总'!$I$5 -> 0 | N43: =(M43+L43+K43+J43+I43)*'2-报价汇总'!$J$5 -> 0 | O43: =G43*H43 -> 3354603.5
A44: 2.5.1.39 | B44: 室外工程垃圾清运 | D44: 室外装饰装修及安装工程项目 | F44: 车 | G44: 50 | H44: =SUM(I44:N44) -> 765.15152 | I44: 37.575758 | J44: 450 | K44: 270 | L44: =(I44+J44+K44)*'2-报价汇总'!$H$5 -> 7.5757576 | M44: =(I44+J44+K44+L44)*'2-报价汇总'!$I$5 -> 0 | N44: =(M44+L44+K44+J44+I44)*'2-报价汇总'!$J$5 -> 0 | O44: =G44*H44 -> 38257.576
A45: 2.5.1.40 | B45: 室外杂草清理 | C45: 1.室外杂草、低矮灌木清理 2.垃圾清运及垃圾外运 | D45: 室外装饰装修及安装工程项目 | E45: 按设计图示尺寸面积计算 | F45: m2 | G45: 656089.61 | H45: =SUM(I45:N45) -> 4.3722944 | I45: 4.2090043 | J45: 0 | K45: 0.12 | L45: =(I45+J45+K45)*'2-报价汇总'!$H$5 -> 0.043290043 | M45: =(I45+J45+K45+L45)*'2-报价汇总'!$I$5 -> 0 | N45: =(M45+L45+K45+J45+I45)*'2-报价汇总'!$J$5 -> 0 | O45: =G45*H45 -> 2868616.9
A46: 2.5.1.41 | B46: 室外独立立招 定制铝塑板及方钢龙骨 | C46: 1.铝塑板面层 2.镀锌方钢龙骨，用于固定铝塑板 3.含结构胶勾缝 | D46: 室外装饰装修及安装工程项目 | E46: 按设计图示尺寸面积计算 | F46: m2 | G46: 35804.274 | H46: =SUM(I46:N46) -> 402.25108 | I46: 82.468398 | J46: 310 | K46: 5.8 | L46: =(I46+J46+K46)*'2-报价汇总'!$H$5 -> 3.982684 | M46: =(I46+J46+K46+L46)*'2-报价汇总'!$I$5 -> 0 | N46: =(M46+L46+K46+J46+I46)*'2-报价汇总'!$J$5 -> 0 | O46: =G46*H46 -> 14402308 | P46: 计算方式需按双面来
A47: 2.5.1.42 | B47: 成品化粪池（玻璃钢） | C47: 1、土方开挖 2、设备供应及安装 3、土方回填 | F47: m3 | G47: 200 | H47: =SUM(I47:N47) -> 649.3492 | I47: 87.12 | J47: 550 | K47: 5.8 | L47: =(I47+J47+K47)*'2-报价汇总'!$H$5 -> 6.4292 | M47: =(I47+J47+K47+L47)*'2-报价汇总'!$I$5 -> 0 | N47: =(M47+L47+K47+J47+I47)*'2-报价汇总'!$J$5 -> 0
B48: 补充项
B49: 室外工程合计： | O49: =SUM(O6:O46) -> 1.8164994e+08

Sheet 2.6-消防工程
A1: 理想汽车中心店消防工程量清单
A2: ='2.1-装饰工程'!A2 -> 注意：此报价清单每项不得随意更改、删减，如有任何增加项请务必在每大项最后“补充项“中列举，补充项及说明字体颜色均采用蓝色；且所有项目都需要填写。
A3: 序号 | B3: 名 称 | C3: 型号及规格 | D3: 单位 | E3: 24/25年暂估工程量 | F3: 综合单价 | G3: 人工费 | H3: 材料费 | I3: 机械费 | J3: 安措费 | K3: 管理费 | L3: 利润 | M3: 24/25年暂估总价 | N3: 备注
B4: 2.6消防工程
A5: 2.6.1 | B5: 消防电系统
A6: 2.6.1.01 | B6: 新增烟感 1.含本体、管线、安装 2.底盒安装 | C6: 含管、线及辅料 | D6: 个 | F6: =SUM(G6:L6) -> 279.82684 | G6: 114.50628 | H6: 155.19 | I6: 7.36 | J6: =(G6+H6+I6)*'2-报价汇总'!$H$5 -> 2.7705628 | K6: =(G6+H6+I6+J6)*'2-报价汇总'!$I$5 -> 0 | L6: =(K6+J6+I6+H6+G6)*'2-报价汇总'!$J$5 -> 0 | M6: =E6*F6 -> 0
A7: 2.6.1.02 | B7: 移位及安装烟感 1.含拆除、移位、管线、重新安装 2.底盒安装 | C7: 含管、线及辅料 | D7: 个 | E7: 0 | F7: =SUM(G7:L7) -> 227.35931 | G7: 225.10823 | J7: =(G7+H7+I7)*'2-报价汇总'!$H$5 -> 2.2510823 | K7: =(G7+H7+I7+J7)*'2-报价汇总'!$I$5 -> 0 | L7: =(K7+J7+I7+H7+G7)*'2-报价汇总'!$J$5 -> 0 | M7: =E7*F7 -> 0
A8: 2.6.1.03 | B8: 新增火灾声光警报器 1.含本体、管线、安装 2.底盒安装 | C8: 含管、线及辅料 | D8: 个 | E8: 0 | F8: =SUM(G8:L8) -> 507.18615 | G8: 146.2445 | H8: 355.17 | I8: 0.75 | J8: =(G8+H8+I8)*'2-报价汇总'!$H$5 -> 5.021645 | K8: =(G8+H8+I8+J8)*'2-报价汇总'!$I$5 -> 0 | L8: =(K8+J8+I8+H8+G8)*'2-报价汇总'!$J$5 -> 0 | M8: =E8*F8 -> 0
A9: 2.6.1.04 | B9: 新增手动火灾警报装置 1.含本体、管线、安装 2.底盒安装 | C9: 含管、线及辅料 | D9: 个 | E9: 0 | F9: =SUM(G9:L9) -> 148.65801 | G9: 73.856147 | H9: 71.61 | I9: 1.72 | J9: =(G9+H9+I9)*'2-报价汇总'!$H$5 -> 1.4718615 | K9: =(G9+H9+I9+J9)*'2-报价汇总'!$I$5 -> 0 | L9: =(K9+J9+I9+H9+G9)*'2-报价汇总'!$J$5 -> 0 | M9: =E9*F9 -> 0
A10: 2.6.1.05 | B10: 新增消火栓起泵按钮 1.含本体、管线、安装 2.底盒安装 | C10: 含管、线及辅料 | D10: 个 | E10: 0 | F10: =SUM(G10:L10) -> 96.190476 | G10: 89.418095 | H10: 4.94 | I10: 0.88 | J10: =(G10+H10+I10)*'2-报价汇总'!$H$5 -> 0.95238095 | K10: =(G10+H10+I10+J10)*'2-报价汇总'!$I$5 -> 0 | L10: =(K10+J10+I10+H10+G10)*'2-报价汇总'!$J$5 -> 0 | M10: =E10*F10 -> 0
A11: 2.6.1.06 | B11: 移动及安装带电话插孔的手动报警按钮 1.含本体、管线、安装 2.底盒安装 | C11: 含管、线及辅料 | D11: 个 | E11: 0 | F11: =SUM(G11:L11) -> 183.63636 | G11: 45.828182 | H11: 134.43 | I11: 1.56 | J11: =(G11+H11+I11)*'2-报价汇总'!$H$5 -> 1.8181818 | K11: =(G11+H11+I11+J11)*'2-报价汇总'!$I$5 -> 0 | L11: =(K11+J11+I11+H11+G11)*'2-报价汇总'!$J$5 -> 0 | M11: =E11*F11 -> 0
A12: 2.6.1.07 | B12: 提供及安装短路隔离器 1.含本体、管线、安装 2.底盒安装 | C12: 含管、线及辅料 | D12: 个 | E12: 0 | F12: =SUM(G12:L12) -> 253.59307 | G12: 27.692251 | H12: 222.19 | I12: 1.2 | J12: =(G12+H12+I12)*'2-报价汇总'!$H$5 -> 2.5108225 | K12: =(G12+H12+I12+J12)*'2-报价汇总'!$I$5 -> 0 | L12: =(K12+J12+I12+H12+G12)*'2-报价汇总'!$J$5 -> 0 | M12: =E12*F12 -> 0
A13: 2.6.1.08 | B13: 新增消防广播 1.含本体、管线、安装 2.底盒安装 | C13: 含管、线及辅料 | D13: 个 | E13: 0 | F13: =SUM(G13:L13) -> 338.41558 | G13: 86.684935 | H13: 247.2 | I13: 1.18 | J13: =(G13+H13+I13)*'2-报价汇总'!$H$5 -> 3.3506494 | K13: =(G13+H13+I13+J13)*'2-报价汇总'!$I$5 -> 0 | L13: =(K13+J13+I13+H13+G13)*'2-报价汇总'!$J$5 -> 0 | M13: =E13*F13 -> 0
A14: 2.6.1.09 | B14: 移位消防广播 1.含本体、管线、安装 2.底盒安装 | C14: 含管、线及辅料 | D14: 个 | E14: 0 | F14: =SUM(G14:L14) -> 244.84848 | G14: 173.36987 | H14: 67.874372 | I14: 1.18 | J14: =(G14+H14+I14)*'2-报价汇总'!$H$5 -> 2.4242424 | K14: =(G14+H14+I14+J14)*'2-报价汇总'!$I$5 -> 0 | L14: =(K14+J14+I14+H14+G14)*'2-报价汇总'!$J$5 -> 0 | M14: =E14*F14 -> 0
A15: 2.6.1.10 | B15: 系统的调试 | D15: m2 | E15: 0 | F15: =SUM(G15:L15) -> 2.6233766 | G15: 2.5974026 | J15: =(G15+H15+I15)*'2-报价汇总'!$H$5 -> 0.025974026 | K15: =(G15+H15+I15+J15)*'2-报价汇总'!$I$5 -> 0 | L15: =(K15+J15+I15+H15+G15)*'2-报价汇总'!$J$5 -> 0 | M15: =E15*F15 -> 0
B16: 补充项 | E16: 0 | G16: 0 | J16: =(G16+H16+I16)*'2-报价汇总'!$H$5 -> 0 | K16: =(G16+H16+I16+J16)*'2-报价汇总'!$I$5 -> 0 | L16: =(K16+J16+I16+H16+G16)*'2-报价汇总'!$J$5 -> 0 | M16: =E16*F16 -> 0
B17: 小计 | E17: 0 | G17: 0 | J17: =(G17+H17+I17)*'2-报价汇总'!$H$5 -> 0 | K17: =(G17+H17+I17+J17)*'2-报价汇总'!$I$5 -> 0 | L17: =(K17+J17+I17+H17+G17)*'2-报价汇总'!$J$5 -> 0 | M17: =E17*F17 -> 0
A18: 2.6.2 | B18: 消防水系统 | E18: 0 | G18: 0 | J18: =(G18+H18+I18)*'2-报价汇总'!$H$5 -> 0 | K18: =(G18+H18+I18+J18)*'2-报价汇总'!$I$5 -> 0 | L18: =(K18+J18+I18+H18+G18)*'2-报价汇总'!$J$5 -> 0 | M18: =E18*F18 -> 0
A19: 2.6.2.01 | B19: 提供及安装明装喷淋 1.含本体、管道、构件、阀门等安装 2.支、吊架制作安装 | C19: 含管路及辅料 | D19: 个 | E19: 0 | F19: =SUM(G19:L19) -> 104.93506 | G19: 15.006104 | H19: 88.24 | I19: 0.65 | J19: =(G19+H19+I19)*'2-报价汇总'!$H$5 -> 1.038961 | K19: =(G19+H19+I19+J19)*'2-报价汇总'!$I$5 -> 0 | L19: =(K19+J19+I19+H19+G19)*'2-报价汇总'!$J$5 -> 0 | M19: =E19*F19 -> 0
A20: 2.6.2.02 | B20: 提供及安装暗装喷淋 1.含本体、管道、构件、阀门等安装 2.支、吊架制作安装 | C20: 含管路及辅料 | D20: 个 | E20: 0 | F20: =SUM(G20:L20) -> 104.93506 | G20: 15.006104 | H20: 88.24 | I20: 0.65 | J20: =(G20+H20+I20)*'2-报价汇总'!$H$5 -> 1.038961 | K20: =(G20+H20+I20+J20)*'2-报价汇总'!$I$5 -> 0 | L20: =(K20+J20+I20+H20+G20)*'2-报价汇总'!$J$5 -> 0 | M20: =E20*F20 -> 0
A21: 2.6.2.03 | B21: 移动原有喷淋 1.含拆除本体、管道、构件、阀门等重新安装 2.支、吊架制作安装 | C21: 含管路及辅料 | D21: 个 | E21: 0 | F21: =SUM(G21:L21) -> 69.95671 | G21: 69.264069 | J21: =(G21+H21+I21)*'2-报价汇总'!$H$5 -> 0.69264069 | K21: =(G21+H21+I21+J21)*'2-报价汇总'!$I$5 -> 0 | L21: =(K21+J21+I21+H21+G21)*'2-报价汇总'!$J$5 -> 0 | M21: =E21*F21 -> 0
A22: 2.6.2.04 | B22: 新做及安装消防水系统 1.管道、构件、阀门等安装 2.支、吊架制作安装 | D22: m² | E22: 0 | F22: =SUM(G22:L22) -> 34.978355 | G22: 34.632035 | J22: =(G22+H22+I22)*'2-报价汇总'!$H$5 -> 0.34632035 | K22: =(G22+H22+I22+J22)*'2-报价汇总'!$I$5 -> 0 | L22: =(K22+J22+I22+H22+G22)*'2-报价汇总'!$J$5 -> 0 | M22: =E22*F22 -> 0
B23: 补充项 | E23: 0 | M23: =E23*F23 -> 0
B24: 小计 | E24: 0 | M24: =E24*F24 -> 0
A25: 2.6.3 | B25: 消火栓箱 | E25: 0 | M25: =E25*F25 -> 0
A26: 2.6.3.01 | B26: 新做及安装消火栓箱，含配套灭火器、消防水带等 | C26: 含管道及辅料 | D26: 个 | E26: 0 | F26: =SUM(G26:L26) -> 1923.8095 | G26: 293.9619 | H26: 1606.7 | I26: 4.1 | J26: =(G26+H26+I26)*'2-报价汇总'!$H$5 -> 19.047619 | K26: =(G26+H26+I26+J26)*'2-报价汇总'!$I$5 -> 0 | L26: =(K26+J26+I26+H26+G26)*'2-报价汇总'!$J$5 -> 0 | M26: =E26*F26 -> 0
A27: 2.6.3.02 | B27: 移位及安装消火栓箱，含配套灭火器、消防水带等 | C27: 含管道及辅料 | D27: 个 | E27: 0 | F27: =SUM(G27:L27) -> 480.95238 | G27: 459.99048 | H27: 10.05 | I27: 6.15 | J27: =(G27+H27+I27)*'2-报价汇总'!$H$5 -> 4.7619048 | K27: =(G27+H27+I27+J27)*'2-报价汇总'!$I$5 -> 0 | L27: =(K27+J27+I27+H27+G27)*'2-报价汇总'!$J$5 -> 0 | M27: =E27*F27 -> 0
A28: 2.6.3.03 | B28: 5kgABC干粉灭火器（一组两只，含金属箱体） | D28: 组 | E28: 0 | F28: =SUM(G28:L28) -> 174.89177 | G28: 173.16017 | J28: =(G28+H28+I28)*'2-报价汇总'!$H$5 -> 1.7316017 | K28: =(G28+H28+I28+J28)*'2-报价汇总'!$I$5 -> 0 | L28: =(K28+J28+I28+H28+G28)*'2-报价汇总'!$J$5 -> 0 | M28: =E28*F28 -> 0
A29: 2.6.3.04 | B29: 201不锈钢灭火器箱（圆型）可放2-5KG灭火器 | C29: 成品灭火器箱 | D29: 个 | E29: 7000 | F29: =SUM(G29:L29) -> 262.33766 | G29: 259.74026 | J29: =(G29+H29+I29)*'2-报价汇总'!$H$5 -> 2.5974026 | K29: =(G29+H29+I29+J29)*'2-报价汇总'!$I$5 -> 0 | L29: =(K29+J29+I29+H29+G29)*'2-报价汇总'!$J$5 -> 0 | M29: =E29*F29 -> 1836363.6
B30: 补充项 | K30: =(G30+H30+I30)*0.05 -> 0 | L30: =(H30+I30+K30+G30)*0.1 -> 0 | M30: =E30*F30 -> 0
B31: 小计 | K31: =(G31+H31+I31)*0.05 -> 0 | L31: =(H31+I31+K31+G31)*0.1 -> 0 | M31: =E31*F31 -> 0
A32: 2.6.4 | B32: 消防零星工程 | K32: =(G32+H32+I32)*0.05 -> 0 | L32: =(H32+I32+K32+G32)*0.1 -> 0 | M32: =E32*F32 -> 0
A33: 2.6.4.01 | B33: 消防管道挖沟回填 | D33: m | E33: 0 | F33: =SUM(G33:L33) -> 262.33766 | G33: 259.74026 | J33: =(G33+H33+I33)*'2-报价汇总'!$H$5 -> 2.5974026 | K33: =(G33+H33+I33+J33)*'2-报价汇总'!$I$5 -> 0 | L33: =(K33+J33+I33+H33+G33)*'2-报价汇总'!$J$5 -> 0 | M33: =E33*F33 -> 0
A34: 2.6.4.02 | B34: 新做消防镀锌钢管DN100 | C34: 含管道构件 | D34: m | E34: 0 | F34: =SUM(G34:L34) -> 139.91342 | G34: 73.298139 | H34: 64.43 | I34: 0.8 | J34: =(G34+H34+I34)*'2-报价汇总'!$H$5 -> 1.3852814 | K34: =(G34+H34+I34+J34)*'2-报价汇总'!$I$5 -> 0 | L34: =(K34+J34+I34+H34+G34)*'2-报价汇总'!$J$5 -> 0 | M34: =E34*F34 -> 0
A35: 2.6.4.03 | B35: 新做消防镀锌钢管DN65 | C35: 含管道构件 | D35: m | E35: 0 | F35: =SUM(G35:L35) -> 104.93506 | G35: 69.296104 | H35: 33.93 | I35: 0.67 | J35: =(G35+H35+I35)*'2-报价汇总'!$H$5 -> 1.038961 | K35: =(G35+H35+I35+J35)*'2-报价汇总'!$I$5 -> 0 | L35: =(K35+J35+I35+H35+G35)*'2-报价汇总'!$J$5 -> 0 | M35: =E35*F35 -> 0
A36: 2.6.4.04 | B36: 管道支架、刷油 | D36: kg | E36: 0 | F36: =SUM(G36:L36) -> 13.991342 | G36: 5.7728139 | H36: 6.87 | I36: 1.21 | J36: =(G36+H36+I36)*'2-报价汇总'!$H$5 -> 0.13852814 | K36: =(G36+H36+I36+J36)*'2-报价汇总'!$I$5 -> 0 | L36: =(K36+J36+I36+H36+G36)*'2-报价汇总'!$J$5 -> 0 | M36: =E36*F36 -> 0
A37: 2.6.4.05 | B37: 消火栓系统调试 | D37: m | E37: 0 | F37: =SUM(G37:L37) -> 8.7445887 | G37: 8.6580087 | J37: =(G37+H37+I37)*'2-报价汇总'!$H$5 -> 0.086580087 | K37: =(G37+H37+I37+J37)*'2-报价汇总'!$I$5 -> 0 | L37: =(K37+J37+I37+H37+G37)*'2-报价汇总'!$J$5 -> 0 | M37: =E37*F37 -> 0
A38: 2.6.4.06 | B38: 原消防管道重新油漆 | D38: m2 | E38: 0 | F38: =SUM(G38:L38) -> 18.162511 | G38: 8.452684 | H38: 9.44 | I38: 0.09 | J38: =(G38+H38+I38)*'2-报价汇总'!$H$5 -> 0.17982684 | K38: =(G38+H38+I38+J38)*'2-报价汇总'!$I$5 -> 0 | L38: =(K38+J38+I38+H38+G38)*'2-报价汇总'!$J$5 -> 0 | M38: =E38*F38 -> 0
A39: 2.6.4.07 | B39: 火灾报警控制器 1.型号:JBF-11SF 2.落地安装 | D39: 台 | E39: 0 | F39: =SUM(G39:L39) -> 12839.68 | G39: 355.35411 | H39: 12297.69 | I39: 59.51 | J39: =(G39+H39+I39)*'2-报价汇总'!$H$5 -> 127.12554 | K39: =(G39+H39+I39+J39)*'2-报价汇总'!$I$5 -> 0 | L39: =(K39+J39+I39+H39+G39)*'2-报价汇总'!$J$5 -> 0 | M39: =E39*F39 -> 0
A40: 2.6.4.08 | B40: 广播控制盘 型号:MP3/JBF-11SF-KZ | D40: 台 | E40: 0 | F40: =SUM(G40:L40) -> 4736.9437 | G40: 348.09329 | H40: 4285.06 | I40: 56.89 | J40: =(G40+H40+I40)*'2-报价汇总'!$H$5 -> 46.900433 | K40: =(G40+H40+I40+J40)*'2-报价汇总'!$I$5 -> 0 | L40: =(K40+J40+I40+H40+G40)*'2-报价汇总'!$J$5 -> 0 | M40: =E40*F40 -> 0
A41: 2.6.4.09 | B41: 功率放大器 型号:JBF/11SF-P350W | D41: 台 | E41: 0 | F41: =SUM(G41:L41) -> 3171.6623 | G41: 495.90974 | H41: 2642.56 | I41: 1.79 | J41: =(G41+H41+I41)*'2-报价汇总'!$H$5 -> 31.402597 | K41: =(G41+H41+I41+J41)*'2-报价汇总'!$I$5 -> 0 | L41: =(K41+J41+I41+H41+G41)*'2-报价汇总'!$J$5 -> 0 | M41: =E41*F41 -> 0
A42: 2.6.4.10 | B42: 消防电话系统 型号:HDM2101 | D42: 台 | E42: 0 | F42: =SUM(G42:L42) -> 4910.961 | G42: 437.56766 | H42: 4424 | I42: 0.77 | J42: =(G42+H42+I42)*'2-报价汇总'!$H$5 -> 48.623377 | K42: =(G42+H42+I42+J42)*'2-报价汇总'!$I$5 -> 0 | L42: =(K42+J42+I42+H42+G42)*'2-报价汇总'!$J$5 -> 0 | M42: =E42*F42 -> 0
A43: 2.6.4.11 | B43: 消防联动电源 型号:BYF-PC20M | D43: 台 | E43: 0 | F43: =SUM(G43:L43) -> 3380.658 | G43: 201.37615 | H43: 3085.4 | I43: 60.41 | J43: =(G43+H43+I43)*'2-报价汇总'!$H$5 -> 33.471861 | K43: =(G43+H43+I43+J43)*'2-报价汇总'!$I$5 -> 0 | L43: =(K43+J43+I43+H43+G43)*'2-报价汇总'!$J$5 -> 0 | M43: =E43*F43 -> 0
A44: 2.6.4.12 | B44: 模块 输入/输出模块 | D44: 个 | E44: 0 | F44: =SUM(G44:L44) -> 501.93939 | G44: 99.539697 | H44: 393.25 | I44: 4.18 | J44: =(G44+H44+I44)*'2-报价汇总'!$H$5 -> 4.969697 | K44: =(G44+H44+I44+J44)*'2-报价汇总'!$I$5 -> 0 | L44: =(K44+J44+I44+H44+G44)*'2-报价汇总'!$J$5 -> 0 | M44: =E44*F44 -> 0
A45: 2.6.4.13 | B45: 消防区域报警主机（联动型）：火灾广播功放盘，分路控制盘；火灾报警控制器；消防联动台；消防电话主机；DC24V电源 | D45: 台 | E45: 0 | F45: =SUM(G45:L45) -> 19063.203 | G45: 776.42887 | H45: 17975.33 | I45: 122.7 | J45: =(G45+H45+I45)*'2-报价汇总'!$H$5 -> 188.74459 | K45: =(G45+H45+I45+J45)*'2-报价汇总'!$I$5 -> 0 | L45: =(K45+J45+I45+H45+G45)*'2-报价汇总'!$J$5 -> 0 | M45: =E45*F45 -> 0
A46: 2.6.4.14 | B46: 控制模块 | D46: 个 | E46: 0 | F46: =SUM(G46:L46) -> 614.74459 | G46: 111.22801 | H46: 493.25 | I46: 4.18 | J46: =(G46+H46+I46)*'2-报价汇总'!$H$5 -> 6.0865801 | K46: =(G46+H46+I46+J46)*'2-报价汇总'!$I$5 -> 0 | L46: =(K46+J46+I46+H46+G46)*'2-报价汇总'!$J$5 -> 0 | M46: =E46*F46 -> 0
A47: 2.6.4.15 | B47: 输入模块 | D47: 个 | E47: 0 | F47: =SUM(G47:L47) -> 471.33333 | G47: 139.23667 | H47: 323.25 | I47: 4.18 | J47: =(G47+H47+I47)*'2-报价汇总'!$H$5 -> 4.6666667 | K47: =(G47+H47+I47+J47)*'2-报价汇总'!$I$5 -> 0 | L47: =(K47+J47+I47+H47+G47)*'2-报价汇总'!$J$5 -> 0 | M47: =E47*F47 -> 0
A48: 2.6.4.16 | B48: 信号报警阀 | D48: 个 | E48: 0 | F48: =SUM(G48:L48) -> 3786.4069 | G48: 301.87775 | H48: 3401.53 | I48: 45.51 | J48: =(G48+H48+I48)*'2-报价汇总'!$H$5 -> 37.489177 | K48: =(G48+H48+I48+J48)*'2-报价汇总'!$I$5 -> 0 | L48: =(K48+J48+I48+H48+G48)*'2-报价汇总'!$J$5 -> 0 | M48: =E48*F48 -> 0
A49: 2.6.4.17 | B49: 应急广播控制模块箱300*300*150 | D49: 个 | E49: 0 | F49: =SUM(G49:L49) -> 314.80519 | G49: 1.2483117 | H49: 307.56 | I49: 2.88 | J49: =(G49+H49+I49)*'2-报价汇总'!$H$5 -> 3.1168831 | K49: =(G49+H49+I49+J49)*'2-报价汇总'!$I$5 -> 0 | L49: =(K49+J49+I49+H49+G49)*'2-报价汇总'!$J$5 -> 0 | M49: =E49*F49 -> 0
... A53: 2.6.4.21 | B53: 挂装6kg球形灭火弹 | D53: 个 | E53: 0 | F53: =SUM(G53:L53) -> 207.79437 | G53: 18.53 | H53: 184.067 | I53: 3.14 | J53: =(G53+H53+I53)*'2-报价汇总'!$H$5 -> 2.05737 | K53: =(G53+H53+I53+J53)*'2-报价汇总'!$I$5 -> 0 | L53: =(K53+J53+I53+H53+G53)*'2-报价汇总'!$J$5 -> 0 | M53: =E53*F53 -> 0
A54: 2.6.4.22 | B54: 指定消防公司施工
A55: 2.6.4.23 | B55: 基于图纸的原消防系统改造工程（含所有消防验收三证的费用） | D55: 项 | F55: 811312.52 | M55: =E55*F55 -> 0
A56: 2.6.4.24 | B56: 基于图纸的原消防系统改造工程总包管理费用 | D56: 项 | F56: =F55*0.05 -> 40565.626 | M56: =E56*F56 -> 0
B57: 补充项
B58: 小计
B59: 消防工程合计 | M59: =SUM(M4:M57) -> 4225983.2

Sheet 2.7-屋面工程
A1: 理想汽车中心店屋面工程量清单
A2: ='2.1-装饰工程'!A2 -> 注意：此报价清单每项不得随意更改、删减，如有任何增加项请务必在每大项最后“补充项“中列举，补充项及说明字体颜色均采用蓝色；且所有项目都需要填写。
A3: 序号 | B3: 名 称 | C3: 项目特征 | D3: 适用范围 | E3: 单位 | F3: 24/25年暂估工程量 | G3: 综合单价 | H3: 人工费 | I3: 材料费 | J3: 机械费 | K3: 安措费 | L3: 管理费 | M3: 利润 | N3: 24/25年暂估总价 | O3: 备注
B4: 2.7屋面工程
A5: 2.7.1 | B5: 屋面保温层 | C5: 1.屋面清理 2.复合岩棉板，容重：50kg/m3，厚度100mm制作安装 | D5: 室内、室外装饰装修及安装工程项目 | E5: m2 | F5: 274258.51 | G5: =SUM(H5:M5) -> 74.329004 | H5: 8.4130736 | I5: 65 | J5: 0.18 | K5: =(H5+I5+J5)*'2-报价汇总'!$H$5 -> 0.73593074 | L5: =(H5+I5+J5+K5)*'2-报价汇总'!$I$5 -> 0 | M5: =(L5+K5+J5+I5+H5)*'2-报价汇总'!$J$5 -> 0 | N5: =F5*G5 -> 20385362
A6: 2.7.2 | B6: SBS 3+3屋面防水层 | C6: 1.基层清理 2.涂刷底油 3.3mm厚SBS防水卷材2层 | D6: 室内、室外装饰装修及安装工程项目 | E6: m2 | F6: 274258.51 | G6: =SUM(H6:M6) -> 100.12554 | H6: 23.774199 | I6: 75 | J6: 0.36 | K6: =(H6+I6+J6)*'2-报价汇总'!$H$5 -> 0.99134199 | L6: =(H6+I6+J6+K6)*'2-报价汇总'!$I$5 -> 0 | M6: =(L6+K6+J6+I6+H6)*'2-报价汇总'!$J$5 -> 0 | N6: =F6*G6 -> 27460281
A7: 2.7.3 | B7: 屋面修补漏水铺设单层彩钢板 | C7: 1.拆除原有破损彩钢板 2.修补单层彩钢版 3.型钢龙骨修补 | D7: 室内、室外装饰装修及安装工程项目 | E7: m2 | F7: 274258.51 | G7: =SUM(H7:M7) -> 83.948052 | H7: 21.616883 | I7: 60 | J7: 1.5 | K7: =(H7+I7+J7)*'2-报价汇总'!$H$5 -> 0.83116883 | L7: =(H7+I7+J7+K7)*'2-报价汇总'!$I$5 -> 0 | M7: =(L7+K7+J7+I7+H7)*'2-报价汇总'!$J$5 -> 0 | N7: =F7*G7 -> 23023467
B8: 补充项
B9: 屋面工程合计： | N9: =SUM(N5:N7) -> 70869110

Sheet 2.8-结构工程
A1: 理想汽车中心店结构工程量清单
A2: ='2.1-装饰工程'!A2 -> 注意：此报价清单每项不得随意更改、删减，如有任何增加项请务必在每大项最后“补充项“中列举，补充项及说明字体颜色均采用蓝色；且所有项目都需要填写。
A3: 序号 | B3: 项目名称 | C3: 项目特征 | D3: 适用范围 | E3: 工程量计算规则 | F3: 单位 | G3: 24/25年暂估工程量 | H3: 综合单价 | I3: 人工费 | J3: 材料费 | K3: 机械费 | L3: 安措费 | M3: 管理费 | N3: 利润 | O3: 24/25年暂估总价 | P3: 备注
B4: 2.8钢结构工程
A5: 2.8.01 | B5: 拆除原钢筋混凝土结构楼板，厚度：250mm以内 | C5: 1.拆除原有混凝土楼板，厚度≤250mm 2.垃圾清理、外运 | D5: 室内、室外装饰装修项目 | E5: 按设计图示尺寸面积计算 | F5: m2 | G5: 26809.24 | H5: =SUM(I5:N5) -> 174.89177 | I5: 163.16017 | J5: 0 | K5: 10 | L5: =(I5+J5+K5)*'2-报价汇总'!$H$5 -> 1.7316017 | M5: =(I5+J5+K5+L5)*'2-报价汇总'!$I$5 -> 0 | N5: =(M5+L5+K5+J5+I5)*'2-报价汇总'!$J$5 -> 0 | O5: =G5*H5 -> 4688715.6
A6: 2.8.02 | B6: 结构楼板加固，需达到500kg/m2 | C6: 1.原结构楼板加固 2.包含混凝土结构、钢结构等加固方式 | D6: 室内、室外装饰装修项目 | E6: 按设计图示尺寸面积计算 | F6: m2 | G6: 6000 | H6: =SUM(I6:N6) -> 480.95238 | I6: 74.690476 | J6: 400 | K6: 1.5 | L6: =(I6+J6+K6)*'2-报价汇总'!$H$5 -> 4.7619048 | M6: =(I6+J6+K6+L6)*'2-报价汇总'!$I$5 -> 0 | N6: =(M6+L6+K6+J6+I6)*'2-报价汇总'!$J$5 -> 0 | O6: =G6*H6 -> 2885714.3
A7: 2.8.03 | B7: 新增钢结构 | C7: 1.新建钢结构夹层、楼梯、结构加固等全部钢结构工程 2.包含钢结构内涉及到的型钢龙骨、钢板、化学螺栓等全部材料及工作内容 3.钢结构表面灰色防锈漆处理 | D7: 室内、室外装饰装修项目 | F7: t | G7: 480.66 | H7: =SUM(I7:N7) -> 8744.5887 | I7: 2013.0087 | J7: 6500 | K7: 145 | L7: =(I7+J7+K7)*'2-报价汇总'!$H$5 -> 86.580087 | M7: =(I7+J7+K7+L7)*'2-报价汇总'!$I$5 -> 0 | N7: =(M7+L7+K7+J7+I7)*'2-报价汇总'!$J$5 -> 0 | O7: =G7*H7 -> 4203174
A8: 2.8.04 | B8: 新增钢结构楼梯 | C8: 1.新建钢结构楼梯 2.包含钢结构内涉及到的型钢龙骨、钢板、化学螺栓等全部材料及工作内容 3.钢结构表面灰色防锈漆处理 | D8: 室内、室外装饰装修项目 | F8: t | G8: 3000 | H8: =SUM(I8:N8) -> 8744.5887 | I8: 2013.0087 | J8: 6500 | K8: 145 | L8: =(I8+J8+K8)*'2-报价汇总'!$H$5 -> 86.580087 | M8: =(I8+J8+K8+L8)*'2-报价汇总'!$I$5 -> 0 | N8: =(M8+L8+K8+J8+I8)*'2-报价汇总'!$J$5 -> 0 | O8: =G8*H8 -> 26233766
A9: 2.8.05 | B9: 新增混凝土基础 | C9: 1.土方开挖回填 2.C30钢筋混凝土浇筑，预埋件敷设 3.模板拆装及租赁 | D9: 室内、室外装饰装修项目 | E9: 按设计图示尺寸体积计算 | F9: m3 | G9: 2533.47 | H9: =SUM(I9:N9) -> 1049.3506 | I9: 207.78104 | J9: 830 | K9: 1.18 | L9: =(I9+J9+K9)*'2-报价汇总'!$H$5 -> 10.38961 | M9: =(I9+J9+K9+L9)*'2-报价汇总'!$I$5 -> 0 | N9: =(M9+L9+K9+J9+I9)*'2-报价汇总'!$J$5 -> 0 | O9: =G9*H9 -> 2658498.4
A10: 2.8.06 | B10: 新做混凝土工程 | C10: 1.新做钢筋混凝土梁、板、柱 2.C30钢筋混凝土浇筑，预埋件敷设 3.模板拆装及租赁 | D10: 室内、室外装饰装修项目 | E10: 按设计图示尺寸体积计算 | F10: m3 | G10: 2533.47 | H10: =SUM(I10:N10) -> 1311.6883 | I10: 296.5213 | J10: 1000 | K10: 2.18 | L10: =(I10+J10+K10)*'2-报价汇总'!$H$5 -> 12.987013 | M10: =(I10+J10+K10+L10)*'2-报价汇总'!$I$5 -> 0 | N10: =(M10+L10+K10+J10+I10)*'2-报价汇总'!$J$5 -> 0 | O10: =G10*H10 -> 3323123
A11: 2.8.07 | B11: 新做混凝土小构配件工程 | C11: 1.新做钢筋混凝土小构配件 2.C30钢筋混凝土浇筑，预埋件敷设 3.模板拆装及租赁 | D11: 结构增加牛腿、悬挑梁等单体浇筑物≤0.1立方钢筋混凝土结构 | E11: 按设计图示尺寸体积计算 | F11: m3 | G11: 579.08 | H11: =SUM(I11:N11) -> 2885.7143 | I11: 307.14286 | J11: 2550 | K11: 0 | L11: =(I11+J11+K11)*'2-报价汇总'!$H$5 -> 28.571429 | M11: =(I11+J11+K11+L11)*'2-报价汇总'!$I$5 -> 0 | N11: =(M11+L11+K11+J11+I11)*'2-报价汇总'!$J$5 -> 0 | O11: =G11*H11 -> 1671059.4
A12: 2.8.08 | B12: 结构加固深化设计，含盖设计院章 | C12: 1.取得符合资质要求的设计院盖章计算书 2.全套设计图纸及盖章蓝图 | D12: 室内、室外装饰装修项目 | E12: 按设计图示尺寸面积计算 | F12: m2 | G12: 0 | H12: =SUM(I12:N12) -> 43.722944 | I12: 43.290043 | J12: 0 | K12: 0 | L12: =(I12+J12+K12)*'2-报价汇总'!$H$5 -> 0.43290043 | M12: =(I12+J12+K12+L12)*'2-报价汇总'!$I$5 -> 0 | N12: =(M12+L12+K12+J12+I12)*'2-报价汇总'!$J$5 -> 0 | O12: =G12*H12 -> 0
A13: 2.8.09 | B13: 土方开挖 | C13: 1.土方开挖 | D13: 室内装饰装修项目 | E13: 按设计图示尺寸体积计算 | F13: m3 | G13: 54225.71 | H13: =SUM(I13:N13) -> 34.978355 | I13: 26.632035 | J13: 0 | K13: 8 | L13: =(I13+J13+K13)*'2-报价汇总'!$H$5 -> 0.34632035 | M13: =(I13+J13+K13+L13)*'2-报价汇总'!$I$5 -> 0 | N13: =(M13+L13+K13+J13+I13)*'2-报价汇总'!$J$5 -> 0 | O13: =G13*H13 -> 1896726.1
A14: 2.8.10 | B14: 储水池外防水（隔油池） | C14: 1.2mm厚JS防水 | D14: 室内、室外装饰装修项目 | E14: 按设计图示尺寸面积计算 | F14: m2 | G14: 32000.85 | H14: =SUM(I14:N14) -> 65.584416 | I14: 24.785065 | J14: 40 | K14: 0.15 | L14: =(I14+J14+K14)*'2-报价汇总'!$H$5 -> 0.64935065 | M14: =(I14+J14+K14+L14)*'2-报价汇总'!$I$5 -> 0 | N14: =(M14+L14+K14+J14+I14)*'2-报价汇总'!$J$5 -> 0 | O14: =G14*H14 -> 2098757
A15: 2.8.11 | B15: 钢筋混凝土储水池（隔油池） | C15: 1.按厂家规范要求尺寸做法完成 | D15: 室内、室外装饰装修项目 | E15: 按设计图示尺寸体积计算 | F15: m3 | G15: 3418.18 | H15: =SUM(I15:N15) -> 2186.1472 | I15: 142.00216 | J15: 2000 | K15: 22.5 | L15: =(I15+J15+K15)*'2-报价汇总'!$H$5 -> 21.645022 | M15: =(I15+J15+K15+L15)*'2-报价汇总'!$I$5 -> 0 | N15: =(M15+L15+K15+J15+I15)*'2-报价汇总'!$J$5 -> 0 | O15: =G15*H15 -> 7472644.6
A16: 2.8.12 | B16: 钢筋混凝土盖板（隔油池） | C16: 1.按厂家规范要求尺寸做法完成 | D16: 室内、室外装饰装修项目 | E16: 按设计图示尺寸面积计算 | F16: m2 | G16: 24128.31 | H16: =SUM(I16:N16) -> 174.89177 | I16: 87.360173 | J16: 80 | K16: 5.8 | L16: =(I16+J16+K16)*'2-报价汇总'!$H$5 -> 1.7316017 | M16: =(I16+J16+K16+L16)*'2-报价汇总'!$I$5 -> 0 | N16: =(M16+L16+K16+J16+I16)*'2-报价汇总'!$J$5 -> 0 | O16: =G16*H16 -> 4219843
A17: 2.8.13 | B17: 混凝土地面开挖（隔油池） | C17: 1.拆除原有混凝土地面 | D17: 室内、室外装饰装修项目 | E17: 按设计图示尺寸面积计算 | F17: m2 | G17: 6615.18 | H17: =SUM(I17:N17) -> 52.467532 | I17: 46.148052 | J17: 0 | K17: 5.8 | L17: =(I17+J17+K17)*'2-报价汇总'!$H$5 -> 0.51948052 | M17: =(I17+J17+K17+L17)*'2-报价汇总'!$I$5 -> 0 | N17: =(M17+L17+K17+J17+I17)*'2-报价汇总'!$J$5 -> 0 | O17: =G17*H17 -> 347082.17
A18: 2.8.14 | B18: 双柱举升机基础：含现有地面拆除新做400厚钢筋混凝土带型基础 | C18: 1.土方开挖及回填（包含原地面拆除） 2.400mm厚C30钢筋混凝土带型基础 3.模板拆装及租赁 | D18: 室内、室外装饰装修项目 | E18: 按设计图示数量计算 | F18: 个 | G18: 5000 | H18: =SUM(I18:N18) -> 1705.1948 | I18: 176.31169 | J18: 1500 | K18: 12 | L18: =(I18+J18+K18)*'2-报价汇总'!$H$5 -> 16.883117 | M18: =(I18+J18+K18+L18)*'2-报价汇总'!$I$5 -> 0 | N18: =(M18+L18+K18+J18+I18)*'2-报价汇总'!$J$5 -> 0 | O18: =G18*H18 -> 8525974
A19: 2.8.15 | B19: 剪式举升机基础 | C19: 1.土方开挖及回填（包含原地面拆除） 2.C30钢筋混凝土基础（按设备厂家要求尺寸） 3.模板拆装及租赁 | D19: 室内、室外装饰装修项目 | E19: 按设计图示数量计算 | F19: 个 | G19: 670.23 | H19: =SUM(I19:N19) -> 3497.8355 | I19: 453.00346 | J19: 3000 | K19: 10.2 | L19: =(I19+J19+K19)*'2-报价汇总'!$H$5 -> 34.632035 | M19: =(I19+J19+K19+L19)*'2-报价汇总'!$I$5 -> 0 | N19: =(M19+L19+K19+J19+I19)*'2-报价汇总'!$J$5 -> 0 | O19: =G19*H19 -> 2344354.3
A20: 2.8.16 | B20: 排水沟 | C20: 1.C20混凝土基础 2.地面开挖及回填 | D20: 室外雨水排水沟项目 | E20: 按设计图示长度计算 | F20: m | G20: 16621.73 | H20: =SUM(I20:N20) -> 214.24242 | I20: 120.92121 | J20: 90 | K20: 1.2 | L20: =(I20+J20+K20)*'2-报价汇总'!$H$5 -> 2.1212121 | M20: =(I20+J20+K20+L20)*'2-报价汇总'!$I$5 -> 0 | N20: =(M20+L20+K20+J20+I20)*'2-报价汇总'!$J$5 -> 0 | O20: =G20*H20 -> 3561079.7
... A28: 2.8.24 | B28: 四轮定位基础：含现有地面拆除新做300厚混凝土带型基础 | C28: 1.土方开挖及回填（包含原地面拆除） 2.300mm厚C30钢筋混凝土带型基础 3.模板拆装及租赁 | D28: 室内、室外装饰装修项目 | E28: 按设计图示数量计算 | F28: 个 | G28: 670.23 | H28: =SUM(I28:N28) -> 1923.8095 | I28: 94.761905 | J28: 1800 | K28: 10 | L28: =(I28+J28+K28)*'2-报价汇总'!$H$5 -> 19.047619 | M28: =(I28+J28+K28+L28)*'2-报价汇总'!$I$5 -> 0 | N28: =(M28+L28+K28+J28+I28)*'2-报价汇总'!$J$5 -> 0 | O28: =G28*H28 -> 1289394.9
A29: 2.8.25 | B29: 土方清运（7立方） | F29: 车 | G29: 12734.39 | H29: =SUM(I29:N29) -> 765.15152 | I29: 37.575758 | J29: 450 | K29: 270 | L29: =(I29+J29+K29)*'2-报价汇总'!$H$5 -> 7.5757576 | M29: =(I29+J29+K29+L29)*'2-报价汇总'!$I$5 -> 0 | N29: =(M29+L29+K29+J29+I29)*'2-报价汇总'!$J$5 -> 0 | O29: =G29*H29 -> 9743737.8
A30: 2.8.26 | B30: 成品隔油池（玻璃钢） | C30: 1、土方开挖 2、设备供应及安装 3、土方回填 | F30: m3 | G30: 2010.69 | H30: 750 | O30: =G30*H30 -> 1508017.5
A31: 2.8.27 | B31: 结构检测/鉴定（有结构图纸） | C31: 1、现场踏勘，复核图纸准确性 2、依据结构图纸计算承载力是否符合要求 3、包含不限于检测内容如下 1）构件截面尺寸检测； 2）材料强度检测； 3）钢结构防腐涂层厚度检测； 4）结构外观质量检查； 5）结构体系核查； 6）结构顶点侧向水平位移检测； 7）结构安全性鉴定； 8）结构抗震鉴定； 4、处理意见 5、出具专业机构盖章确认的结构检测报告 | E31: 按使用面积记取（以石膏板隔墙外边为边界、未利用空间不算建筑面积） | F31: ㎡ | G31: 448540 | H31: 12 | O31: =G31*H31 -> 5382480
A32: 2.8.28 | B32: 结构检测/鉴定（无结构图纸） | C32: 1、现场踏勘，复核现场结构情况 2、依据现场实际情况计算承载力是否符合要求 3、包含不限于检测内容如下 1）构件截面尺寸检测； 2）材料强度检测； 3）钢结构防腐涂层厚度检测； 4）结构外观质量检查； 5）结构体系核查； 6）结构顶点侧向水平位移检测； 7）结构安全性鉴定； 8）结构抗震鉴定； 4、处理意见 5、出具专业机构盖章确认的结构检测报告 | E32: 按使用面积记取（以石膏板隔墙外边为边界、未利用空间不算建筑面积） | F32: ㎡ | G32: 448540 | H32: 15 | O32: =G32*H32 -> 6728100
B33: 补充项
B34: 小计
B35: 结构工程合计： | O35: =SUM(O5:O34) -> 1.3123692e+08

Sheet 2.9-空调工程
A1: 理想汽车中心店空调工程量清单
A2: ='2.1-装饰工程'!A2 -> 注意：此报价清单每项不得随意更改、删减，如有任何增加项请务必在每大项最后“补充项“中列举，补充项及说明字体颜色均采用蓝色；且所有项目都需要填写。
A3: 编号 | B3: 项目名称 | C3: 项目特征 | D3: 规格 | E3: 工程量计算规则 | F3: 单位 | G3: 24/25年暂估工程量 | H3: 综合单价 | I3: 人工费 | J3: 材料费 | K3: 机械费 | L3: 安措费 | M3: 管理费 | N3: 利润 | O3: 24/25年暂估总价 | P3: 备注
A4: 2.9.1 | B4: 通风设备（卫生间、淋浴间）
A5: 2.9.1.01 | B5: 排风扇（风量V-250） | C5: 1、包含线管、控制线、电源线等材料 2、包含设备及辅材安装费 3、品牌：以材料清单为准 | D5: 松下、绿岛风或同等以上品牌 | E5: 按图示数量 | F5: 台 | G5: 13404.619 | H5: 337.14 | O5: =G5*H5 -> 4519233.3
A6: 2.9.1.02 | B6: 排风扇（风量V-500） | D6: 松下、绿岛风或同等以上品牌 | E6: 按图示数量 | F6: 台 | G6: 13404.619 | H6: 514.8 | O6: =G6*H6 -> 6900697.9
A7: 2.9.1.03 | B7: 轴流风机，φ300含电源 | E7: 按图示数量 | F7: 个 | G7: 13404.619 | H7: 822.69 | O7: =G7*H7 -> 11027846
A8: 2.9.1.04 | B8: 工业风扇，φ600，含开关及电源 | E8: 按图示数量 | F8: 个 | G8: 6702.31 | H8: 544.77 | O8: =G8*H8 -> 3651217.4
A9: 2.9.1.05 | B9: 风幕机 （绿岛风FM4512H） | E9: 按图示数量 | F9: 台 | G9: 100 | H9: 1590.93 | O9: =G9*H9 -> 159093
A10: 2.9.1.06 | B10: 风幕机（电加热） | D10: 长度900 | E10: 按图示数量 | F10: 台 | G10: 100 | H10: 1826 | O10: =G10*H10 -> 182600
A11: 2.9.1.07 | B11: 风幕机（电加热） | D11: 长度1500 | E11: 按图示数量 | F11: 台 | G11: 100 | H11: 2321 | O11: =G11*H11 -> 232100
A12: 2.9.1.08 | B12: 壁挂机冷凝水提升泵 | E12: 按图示数量 | F12: 个 | G12: 50 | H12: 192.5 | O12: =G12*H12 -> 9625
A13: 2.9.1.09 | B13: 室内机冷凝水提升泵 | E13: 按图示数量 | F13: 个 | G13: 50 | H13: 192.5 | O13: =G13*H13 -> 9625
A14: 2.9.2 | B14: 原有空调移位安装 | O14: =G14*H14 -> 0
A15: 2.9.2.01 | B15: 多联机空调室外机安装 | C15: 1、包含线管、控制线、电源线等材料 2、包含设备及辅材安装费 4、包含电源线接驳 3、品牌：以材料清单为准 | E15: 按图示数量 | F15: 台 | G15: 600 | H15: 1538.46 | O15: =G15*H15 -> 923076
A16: 2.9.2.02 | B16: 多联机空调室内机安装 | E16: 按图示数量 | F16: 台 | G16: 600 | H16: 834.57 | O16: =G16*H16 -> 500742
A17: 2.9.2.03 | B17: 壁挂机（室内外）安装 | E17: 按图示数量 | F17: 套 | G17: 600 | H17: 297 | O17: =G17*H17 -> 178200
A18: 2.9.2.04 | B18: 柜机（室内外）安装 | E18: 按图示数量 | F18: 套 | G18: 600 | H18: 445.5 | O18: =G18*H18 -> 267300
A19: 2.9.2.05 | B19: 原有空调拆除 | E19: 按图示数量 | F19: 套 | G19: 1200 | H19: 293.04 | O19: =G19*H19 -> 351648
A20: 2.9.2.06 | B20: 风盘移位 | C20: 室内机、风机盘管等拆除、移位安装 | E20: 按图示数量 | F20: 个 | G20: 1200 | H20: 550 | O20: =G20*H20 -> 660000
A21: 2.9.2.07 | B21: 风盘清洗 | E21: 按图示数量 | F21: 个 | G21: 1200 | H21: 165 | O21: =G21*H21 -> 198000
A22: 2.9.3 | B22: 紫铜管（含橡塑保温管） | O22: =G22*H22 -> 0
A23: 2.9.3.01 | B23: 冷媒铜管（含橡塑保温20mm）Φ6.35*0.75 | C23: 场内搬运、检查及清扫管件、切管、调直、管道及管件安装、水压试验、水冲洗 | D23: Φ6.35 | F23: m | G23: 20000 | H23: 29.7 | O23: =G23*H23 -> 594000
A24: 2.9.3.02 | B24: 冷媒铜管（含橡塑保温20mm）Φ9.52*0.75 | D24: Φ9.5 | F24: m | G24: 20000 | H24: 38.5 | O24: =G24*H24 -> 770000
A25: 2.9.3.03 | B25: 冷媒铜管（含橡塑保温20mm）Φ12.7*1.0 | D25: Φ12.7 | F25: m | G25: 20000 | H25: 49.5 | O25: =G25*H25 -> 990000
A26: 2.9.3.04 | B26: 冷媒铜管（含橡塑保温20mm）Φ15.9*1.0 | D26: Φ15.9 | F26: m | G26: 20000 | H26: 60.5 | O26: =G26*H26 -> 1210000
A27: 2.9.3.05 | B27: 冷媒铜管（含橡塑保温20mm）Φ19.05*1.5 | D27: Φ19.1 | F27: m | G27: 20000 | H27: 71.5 | O27: =G27*H27 -> 1430000
A28: 2.9.3.06 | B28: 冷媒铜管（含橡塑保温20mm）Φ22.2*1.2 | D28: Φ22.2 | F28: m | G28: 20000 | H28: 93.5 | O28: =G28*H28 -> 1870000
A29: 2.9.3.07 | B29: 冷媒铜管（含橡塑保温20mm）Φ25.4*1.2 | D29: Φ25.4 | F29: m | G29: 20000 | H29: 104.5 | O29: =G29*H29 -> 2090000
A30: 2.9.3.08 | B30: 冷媒铜管（含橡塑保温20mm）Φ28.6*1.2 | D30: Φ28.6 | F30: m | G30: 20000 | H30: 115.5 | O30: =G30*H30 -> 2310000
A31: 2.9.3.09 | B31: 冷媒铜管（含橡塑保温20mm）Φ31.8*1.2 | D31: Φ31.8 | F31: m | G31: 20000 | H31: 126.5 | O31: =G31*H31 -> 2530000
A32: 2.9.3.10 | B32: 冷媒铜管（含橡塑保温20mm）Φ34.92*1.5 | D32: Φ34.9 | F32: m | G32: 20000 | H32: 137.5 | O32: =G32*H32 -> 2750000
A33: 2.9.3.11 | B33: 冷媒铜管（含橡塑保温20mm）Φ38*1.5 | D33: Φ38 | F33: m | G33: 20000 | H33: 148.5 | O33: =G33*H33 -> 2970000
A34: 2.9.3.12 | B34: 冷媒铜管（含橡塑保温20mm）Φ42*1.5 | D34: φ41.3 | F34: m | G34: 20000 | H34: 165 | O34: =G34*H34 -> 3300000
A35: 2.9.3.13 | B35: 冷媒铜管（含橡塑保温20mm）Φ54*1.8 | D35: Φ54 | F35: m | G35: 20000 | H35: 203.5 | O35: =G35*H35 -> 4070000
A36: 2.9.3.14 | B36: R410冷媒分歧器 FQ01A | E36: 按图示数量 | F36: 个 | G36: 400 | H36: 59.98 | O36: =G36*H36 -> 23992
A37: 2.9.3.15 | B37: R410冷媒分歧器 FQ01B | E37: 按图示数量 | F37: 个 | G37: 400 | H37: 59.98 | O37: =G37*H37 -> 23992
A38: 2.9.3.16 | B38: R410冷媒分歧器 FQ02 | E38: 按图示数量 | F38: 个 | G38: 400 | H38: 75.75 | O38: =G38*H38 -> 30300
A39: 2.9.3.17 | B39: R410冷媒分歧器 FQ03 | E39: 按图示数量 | F39: 个 | G39: 400 | H39: 151.02 | O39: =G39*H39 -> 60408
A40: 2.9.3.18 | B40: R410冷媒分歧器 FQ04 | E40: 按图示数量 | F40: 个 | G40: 400 | H40: 235.26 | O40: =G40*H40 -> 94104
A41: 2.9.4 | B41: 冷凝水管及冷冻水管 | O41: =G41*H41 -> 0
A42: 2.9.4.01 | B42: 冷冻水管（镀锌钢管含橡塑保温20mm）DN20*2.75 | C42: 水管的连接、保温与固定 | D42: DN20 | F42: m | G42: 20000 | H42: 57.2 | O42: =G42*H42 -> 1144000
A43: 2.9.4.02 | B43: 冷冻水管（镀锌钢管含橡塑保温20mm）DN25*3.25 | D43: DN25 | F43: m | G43: 20000 | H43: 69.3 | O43: =G43*H43 -> 1386000
A44: 2.9.4.03 | B44: 冷冻水管（镀锌钢管含橡塑保温20mm）DN32*3.25 | D44: DN32 | F44: m | G44: 20000 | H44: 79.2 | O44: =G44*H44 -> 1584000
A45: 2.9.4.04 | B45: 冷冻水管（镀锌钢管含橡塑保温30mm）DN40*3.5 | D45: DN40 | F45: m | G45: 20000 | H45: 92.4 | O45: =G45*H45 -> 1848000
A46: 2.9.4.05 | B46: 冷冻水管（镀锌钢管含橡塑保温30mm）DN50*3.5 | D46: DN50 | F46: m | G46: 20000 | H46: 111.1 | O46: =G46*H46 -> 2222000
A47: 2.9.4.06 | B47: 冷冻水管（镀锌铁管含橡塑保温30mm）DN65*3.75 | D47: DN65 | F47: m | G47: 20000 | H47: 137.5 | O47: =G47*H47 -> 2750000
A48: 2.9.4.07 | B48: 冷冻水管（镀锌钢管含橡塑保温30mm）DN80*4 | D48: DN80 | F48: m | G48: 20000 | H48: 162.8 | O48: =G48*H48 -> 3256000
A49: 2.9.4.08 | B49: 冷冻水管（镀锌钢管含橡塑保温30mm）DN100*4 | D49: DN100 | F49: m | G49: 20000 | H49: 193.6 | O49: =G49*H49 -> 3872000
A50: 2.9.4.09 | B50: 冷凝水管（PVC）DN63*3.7 （含橡塑保温10mm） | D50: DN63 | F50: m | G50: 20000 | H50: 77.07 | O50: =G50*H50 -> 1541400
A51: 2.9.4.10 | B51: 冷凝水管（PVC）DN50*3.7 （含橡塑保温10mm） | D51: DN50 | F51: m | G51: 20000 | H51: 46.69 | O51: =G51*H51 -> 933800
A52: 2.9.4.11 | B52: 冷凝水管（PVC）DN40*3 （含橡塑保温10mm） | D52: DN40 | F52: m | G52: 20000 | H52: 42.57 | O52: =G52*H52 -> 851400
A53: 2.9.4.12 | B53: 冷凝水管（PVC）DN32*2.4 （含橡塑保温10mm） | D53: DN32 | F53: m | G53: 20000 | H53: 33.33 | O53: =G53*H53 -> 666600
A54: 2.9.4.13 | B54: 冷凝水管（PVC）DN25*2 （含橡塑保温10mm） | D54: DN25 | F54: m | G54: 20000 | H54: 37.82 | O54: =G54*H54 -> 756400
A55: 2.9.5 | B55: 风管（含橡塑保温20mm） | O55: =G55*H55 -> 0
A56: 2.9.5.01 | B56: 镀锌铁皮风管（0.5mm） （含法兰、支架、预埋件等辅材） | C56: 风管的制作与安装；法兰、支架的制作、防锈与安装固定；含橡塑保温20mm； | D56: 钢板厚度0.5 | F56: m2 | G56: 30000 | H56: 176 | O56: =G56*H56 -> 5280000
A57: 2.9.5.02 | B57: 镀锌铁皮风管（0.6mm） （含法兰、支架、预埋件等辅材） | D57: 钢板厚度0.6 | F57: m2 | G57: 30000 | H57: 187 | O57: =G57*H57 -> 5610000
A58: 2.9.5.03 | B58: 镀锌铁皮风管（0.75mm） （含法兰、支架、预埋件等辅材） | D58: 钢板厚度0.75 | F58: m2 | G58: 30000 | H58: 192.5 | O58: =G58*H58 -> 5775000
A59: 2.9.5.04 | B59: 镀锌铁皮风管（1mm） （含法兰、支架、预埋件等辅材） | D59: 钢板厚度1.0 | F59: m2 | G59: 30000 | H59: 203.5 | O59: =G59*H59 -> 6105000
A60: 2.9.5.05 | B60: 镀锌铁皮风管（1.2mm） （含法兰、支架、预埋件等辅材） | D60: 钢板厚度1.2 | F60: m2 | G60: 30000 | H60: 215.6 | O60: =G60*H60 -> 6468000
A61: 2.9.5.06 | B61: 镀锌铁皮风管（1.5mm） （含法兰、支架、预埋件等辅材） | D61: 钢板厚度1.5 | F61: m2 | G61: 30000 | H61: 243.73 | O61: =G61*H61 -> 7311900
A62: 2.9.5.07 | B62: 排风管道（镀锌铁皮） | C62: 直径300 | F62: m2 | G62: 60000 | H62: 280.5 | O62: =G62*H62 -> 16830000
A63: 2.9.5.08 | B63: 排风管道（PVC） | C63: 直径200 | F63: m | G63: 20000 | H63: 176 | O63: =G63*H63 -> 3520000
A64: 2.9.5.09 | B64: 排风管道（PVC） | C64: 直径110 | F64: m | G64: 20000 | H64: 99 | O64: =G64*H64 -> 1980000
A65: 2.9.5.10 | B65: 金属伸缩保温软管（300Φ） | C65: 管道制作及安装 | F65: m | G65: 15000 | H65: 53.16 | O65: =G65*H65 -> 797400
A66: 2.9.5.11 | B66: 金属伸缩保温软管（250Φ） | F66: m | G66: 15000 | H66: 46.48 | O66: =G66*H66 -> 697200
A67: 2.9.5.12 | B67: 金属伸缩保温软管（200Φ） | F67: m | G67: 15000 | H67: 40.19 | O67: =G67*H67 -> 602850
A68: 2.9.5.13 | B68: 金属伸缩保温软管（150Φ） | F68: m | G68: 15000 | H68: 32.95 | O68: =G68*H68 -> 494250
A69: 2.9.5.14 | B69: 金属伸缩保温软管（100Φ） | F69: m | G69: 15000 | H69: 28.33 | O69: =G69*H69 -> 424950
A70: 2.9.5.15 | B70: 金属伸缩软管（250Φ） | F70: m | G70: 15000 | H70: 39.09 | O70: =G70*H70 -> 586350
A71: 2.9.5.16 | B71: 金属伸缩软管（200Φ） | F71: m | G71: 15000 | H71: 34.45 | O71: =G71*H71 -> 516750
A72: 2.9.5.17 | B72: 金属伸缩软管（150Φ） | F72: m | G72: 15000 | H72: 27.31 | O72: =G72*H72 -> 409650
A73: 2.9.5.18 | B73: 金属伸缩软管（100Φ） | F73: m | G73: 15000 | H73: 23.76 | O73: =G73*H73 -> 356400
A74: 2.9.5.19 | B74: 帆布软连接 | C74: PVC涂塑帆布 | F74: m2 | G74: 1200 | H74: 81.94 | O74: =G74*H74 -> 98328
A75: 2.9.5.20 | B75: JDG20 | C75: 壁厚1.2mm | F75: m | G75: 1200 | H75: 18.08 | O75: =G75*H75 -> 21696
A76: 2.9.5.21 | B76: JDG25 | C76: 壁厚1.2mm | F76: m | G76: 1200 | H76: 22.83 | O76: =G76*H76 -> 27396
A77: 2.9.5.22 | B77: JDG32 | C77: 壁厚1.2mm | F77: m | G77: 1200 | H77: 27.39 | O77: =G77*H77 -> 32868
A78: 2.9.5.23 | B78: 桥架(厚度1.2mm）50*100 | C78: 镀锌铁皮（墙面、顶面、地面） | F78: m | G78: 400 | H78: 51.13 | O78: =G78*H78 -> 20452
A79: 2.9.5.24 | B79: 桥架(厚度1.5mm）100*100 | F79: m | G79: 400 | H79: 62.09 | O79: =G79*H79 -> 24836
A80: 2.9.5.25 | B80: 桥架(厚度1.5mm）200*100 | F80: m | G80: 400 | H80: 87.66 | O80: =G80*H80 -> 35064
A81: 2.9.5.26 | B81: 桥架(厚度1.5mm）200*300 | F81: m | G81: 400 | H81: 104.1 | O81: =G81*H81 -> 41640
A82: 2.9.6 | B82: 风口 | O82: =G82*H82 -> 0
A83: 2.9.6.01 | B83: 风口 | C83: 1、提供及安装风口主体及辅料 | D83: 200*200 | E83: 按图示数量 | F83: 个 | G83: 600 | H83: 82.95 | O83: =G83*H83 -> 49770
A84: 2.9.6.02 | B84: 风口 | D84: 240*240 | E84: 按图示数量 | F84: 个 | G84: 600 | H84: 88.5 | O84: =G84*H84 -> 53100
A85: 2.9.6.03 | B85: 风口 | D85: 320*320 | E85: 按图示数量 | F85: 个 | G85: 600 | H85: 100.57 | O85: =G85*H85 -> 60342
A86: 2.9.6.04 | B86: 风口 | D86: 360*360 | E86: 按图示数量 | F86: 个 | G86: 600 | H86: 98.01 | O86: =G86*H86 -> 58806
A87: 2.9.6.05 | B87: 风口 | D87: 420*420 | E87: 按图示数量 | F87: 个 | G87: 600 | H87: 116.82 | O87: =G87*H87 -> 70092
A88: 2.9.6.06 | B88: 风口 | D88: 480*480 | E88: 按图示数量 | F88: 个 | G88: 600 | H88: 122.76 | O88: =G88*H88 -> 73656
A89: 2.9.6.07 | B89: 风口 | D89: 1000*200 | E89: 按图示数量 | F89: 个 | G89: 600 | H89: 138.6 | O89: =G89*H89 -> 83160
A90: 2.9.6.08 | B90: 风口 | D90: 400*400 | E90: 按图示数量 | F90: 个 | G90: 600 | H90: 111.87 | O90: =G90*H90 -> 67122
A91: 2.9.6.09 | B91: 风口 | D91: 1200*200 | E91: 按图示数量 | F91: 个 | G91: 600 | H91: 154.44 | O91: =G91*H91 -> 92664
A92: 2.9.6.10 | B92: 风口 | D92: 300*300 | E92: 按图示数量 | F92: 个 | G92: 600 | H92: 89.1 | O92: =G92*H92 -> 53460
A93: 2.9.6.11 | B93: 风口 | D93: 400*400 | E93: 按图示数量 | F93: 个 | G93: 600 | H93: 105.93 | O93: =G93*H93 -> 63558
A94: 2.9.6.12 | B94: 风口 | D94: 450*450 | E94: 按图示数量 | F94: 个 | G94: 600 | H94: 111.87 | O94: =G94*H94 -> 67122
A95: 2.9.6.13 | B95: 风口 | D95: 500*500 | E95: 按图示数量 | F95: 个 | G95: 600 | H95: 124.74 | O95: =G95*H95 -> 74844
... A105: 2.9.6.23 | B105: 送回风口 | D105: 1200*600 | E105: 按图示数量 | F105: 个 | G105: 600 | H105: 231 | O105: =G105*H105 -> 138600
A106: 2.9.6.24 | B106: 防雨百叶 | F106: m2 | G106: 1000 | H106: 550.44 | O106: =G106*H106 -> 550440
A107: 2.9.7 | B107: 空调安装费 | O107: =G107*H107 -> 0
A108: 2.9.7.01 | B108: 分体空调安装费（室内外机全包含） | E108: 按图示数量 | F108: 套 | G108: 500 | H108: 297 | O108: =G108*H108 -> 148500
A109: 2.9.7.02 | B109: 柜机安装费（室内外机全包含） | E109: 按图示数量 | F109: 套 | G109: 500 | H109: 445.5 | O109: =G109*H109 -> 222750
...

Sheet 2.10-采暖工程
A1: 理想汽车中心店采暖工程量清单
A2: ='2.1-装饰工程'!A2 -> 注意：此报价清单每项不得随意更改、删减，如有任何增加项请务必在每大项最后“补充项“中列举，补充项及说明字体颜色均采用蓝色；且所有项目都需要填写。
A3: 序号 | B3: 项目名称 | C3: 项目特征 | D3: 适用范围 | E3: 单位 | F3: 24/25年暂估工程量 | G3: 综合单价 | H3: 人工费 | I3: 材料费 | J3: 机械费 | K3: 安措费 | L3: 管理费 | M3: 利润 | N3: 24/25年暂估总价 | O3: 备注
A4: 2.10.1 | B4: 暖气片系统
A5: 2.10.1.01 | B5: 暖气片H=600mm | C5: 1.暖气片主材费及辅材支架等 | D5: 室内装饰装修及安装工程项目 | E5: 片 | F5: 900 | G5: 60 | N5: =F5*G5 -> 54000
A6: 2.10.1.02 | B6: 暖气片H=1200mm | C6: 1.暖气片主材费及辅材支架等 | D6: 室内装饰装修及安装工程项目 | E6: 片 | F6: 900 | G6: 110 | N6: =F6*G6 -> 99000
A7: 2.10.1.03 | B7: 暖气片H=1500mm | C7: 1.暖气片主材费及辅材支架等 | D7: 室内装饰装修及安装工程项目 | E7: 片 | F7: 900 | G7: 145 | N7: =F7*G7 -> 130500
A8: 2.10.1.04 | B8: 暖气片安装费（每组安装费15KG以内） | C8: 1.暖气片安装费 | D8: 室内装饰装修及安装工程项目 | E8: 组 | F8: 1350 | G8: =SUM(H8:M8) -> 244.84848 | H8: 218.67424 | I8: 22.67 | J8: 1.08 | K8: =(H8+I8+J8)*'2-报价汇总'!$H$5 -> 2.4242424 | L8: =(H8+I8+J8+K8)*'2-报价汇总'!$I$5 -> 0 | M8: =(L8+K8+J8+I8+H8)*'2-报价汇总'!$J$5 -> 0 | N8: =F8*G8 -> 330545.45
A9: 2.10.1.05 | B9: 暖气片安装费（每组安装费15KG以外） | C9: 1.暖气片安装费 | D9: 室内装饰装修及安装工程项目 | E9: 组 | F9: 1350 | G9: =SUM(H9:M9) -> 279.82684 | H9: 257.42628 | I9: 18.13 | J9: 1.5 | K9: =(H9+I9+J9)*'2-报价汇总'!$H$5 -> 2.7705628 | L9: =(H9+I9+J9+K9)*'2-报价汇总'!$I$5 -> 0 | M9: =(L9+K9+J9+I9+H9)*'2-报价汇总'!$J$5 -> 0 | N9: =F9*G9 -> 377766.23
A10: 2.10.1.06 | B10: 入口处风幕机 | C10: 1.L=1200*220*330： 2.品牌：绿岛风 3.型号：RM3512-3D/Y-D ,电机功率：350W，风量2300m3/h | D10: 室内、室外装饰装修及安装工程项目 | E10: 套 | F10: 459 | G10: =SUM(H10:M10) -> 2929.4372 | H10: 560.5929 | I10: 2306.5 | J10: 33.34 | K10: =(H10+I10+J10)*'2-报价汇总'!$H$5 -> 29.004329 | L10: =(H10+I10+J10+K10)*'2-报价汇总'!$I$5 -> 0 | M10: =(L10+K10+J10+I10+H10)*'2-报价汇总'!$J$5 -> 0 | N10: =F10*G10 -> 1344611.7
A11: 2.10.1.07 | B11: 热镀锌钢管DN70 | C11: 1.管道及配套管件供应安装 2.管道保温 3.管道清洗 4.管道打压测试 5.管道支架等 | D11: 室内、室外装饰装修及安装工程项目 | E11: m | F11: 500 | G11: =SUM(H11:M11) -> 73.192208 | H11: 30.707532 | I11: 39.7 | J11: 2.06 | K11: =(H11+I11+J11)*'2-报价汇总'!$H$5 -> 0.72467532 | L11: =(H11+I11+J11+K11)*'2-报价汇总'!$I$5 -> 0 | M11: =(L11+K11+J11+I11+H11)*'2-报价汇总'!$J$5 -> 0 | N11: =F11*G11 -> 36596.104
A12: 2.10.1.08 | B12: 热镀锌钢管DN50 | C12: 1.管道及配套管件供应安装 2.管道保温 3.管道清洗 4.管道打压测试 5.管道支架等 | D12: 室内、室外装饰装修及安装工程项目 | E12: m | F12: 500 | G12: =SUM(H12:M12) -> 51.942857 | H12: 18.448571 | I12: 30.87 | J12: 2.11 | K12: =(H12+I12+J12)*'2-报价汇总'!$H$5 -> 0.51428571 | L12: =(H12+I12+J12+K12)*'2-报价汇总'!$I$5 -> 0 | M12: =(L12+K12+J12+I12+H12)*'2-报价汇总'!$J$5 -> 0 | N12: =F12*G12 -> 25971.429
A13: 2.10.1.09 | B13: 热镀锌钢管DN40 | C13: 1.管道及配套管件供应安装 2.管道保温 3.管道清洗 4.管道打压测试 5.管道支架等 | D13: 室内、室外装饰装修及安装工程项目 | E13: m | F13: 500 | G13: =SUM(H13:M13) -> 46.258874 | H13: 18.670866 | I13: 25.06 | J13: 2.07 | K13: =(H13+I13+J13)*'2-报价汇总'!$H$5 -> 0.45800866 | L13: =(H13+I13+J13+K13)*'2-报价汇总'!$I$5 -> 0 | M13: =(L13+K13+J13+I13+H13)*'2-报价汇总'!$J$5 -> 0 | N13: =F13*G13 -> 23129.437
A14: 2.10.1.10 | B14: 热镀锌钢管DN32 | C14: 1.管道及配套管件供应安装 2.管道保温 3.管道清洗 4.管道打压测试 5.管道支架等 | D14: 室内、室外装饰装修及安装工程项目 | E14: m | F14: 500 | G14: =SUM(H14:M14) -> 41.536797 | H14: 17.005541 | I14: 22.2 | J14: 1.92 | K14: =(H14+I14+J14)*'2-报价汇总'!$H$5 -> 0.41125541 | L14: =(H14+I14+J14+K14)*'2-报价汇总'!$I$5 -> 0 | M14: =(L14+K14+J14+I14+H14)*'2-报价汇总'!$J$5 -> 0 | N14: =F14*G14 -> 20768.398
A15: 2.10.1.11 | B15: 热镀锌钢管DN25 | C15: 1.管道及配套管件供应安装 2.管道保温 3.管道清洗 4.管道打压测试 5.管道支架等 | D15: 室内、室外装饰装修及安装工程项目 | E15: m | F15: 500 | G15: =SUM(H15:M15) -> 33.491775 | H15: 18.270173 | I15: 13.65 | J15: 1.24 | K15: =(H15+I15+J15)*'2-报价汇总'!$H$5 -> 0.33160173 | L15: =(H15+I15+J15+K15)*'2-报价汇总'!$I$5 -> 0 | M15: =(L15+K15+J15+I15+H15)*'2-报价汇总'!$J$5 -> 0 | N15: =F15*G15 -> 16745.887
A16: 2.10.1.12 | B16: 热镀锌钢管DN20 | C16: 1.管道及配套管件供应安装 2.管道保温 3.管道清洗 4.管道打压测试 5.管道支架等 | D16: 室内、室外装饰装修及安装工程项目 | E16: m | F16: 500 | G16: =SUM(H16:M16) -> 25.009524 | H16: 13.671905 | I16: 9.97 | J16: 1.12 | K16: =(H16+I16+J16)*'2-报价汇总'!$H$5 -> 0.24761905 | L16: =(H16+I16+J16+K16)*'2-报价汇总'!$I$5 -> 0 | M16: =(L16+K16+J16+I16+H16)*'2-报价汇总'!$J$5 -> 0 | N16: =F16*G16 -> 12504.762
A17: 2.10.1.13 | B17: 金属软接头DN20 | C17: 1.供应安装 2.管道清洗 3.管道打压测试 | D17: 主管道改造 | E17: 个 | F17: 300 | G17: =SUM(H17:M17) -> 33.229437 | H17: 8.7504329 | I17: 23.72 | J17: 0.43 | K17: =(H17+I17+J17)*'2-报价汇总'!$H$5 -> 0.32900433 | L17: =(H17+I17+J17+K17)*'2-报价汇总'!$I$5 -> 0 | M17: =(L17+K17+J17+I17+H17)*'2-报价汇总'!$J$5 -> 0 | N17: =F17*G17 -> 9968.8312
A18: 2.10.1.14 | B18: Y型过滤器DN20 | C18: 1.供应安装 2.管道清洗 3.管道打压测试 | D18: 室内装饰装修及安装工程项目 | E18: 个 | F18: 300 | G18: =SUM(H18:M18) -> 44.492468 | H18: 7.7819481 | I18: 35.84 | J18: 0.43 | K18: =(H18+I18+J18)*'2-报价汇总'!$H$5 -> 0.44051948 | L18: =(H18+I18+J18+K18)*'2-报价汇总'!$I$5 -> 0 | M18: =(L18+K18+J18+I18+H18)*'2-报价汇总'!$J$5 -> 0 | N18: =F18*G18 -> 13347.74
A19: 2.10.1.15 | B19: 铜球阀DN20 | C19: 1.供应安装 2.管道清洗 3.管道打压测试 | D19: 室内装饰装修及安装工程项目 | E19: 个 | F19: 300 | G19: =SUM(H19:M19) -> 38.773506 | H19: 4.1396104 | I19: 33.82 | J19: 0.43 | K19: =(H19+I19+J19)*'2-报价汇总'!$H$5 -> 0.3838961 | L19: =(H19+I19+J19+K19)*'2-报价汇总'!$I$5 -> 0 | M19: =(L19+K19+J19+I19+H19)*'2-报价汇总'!$J$5 -> 0 | N19: =F19*G19 -> 11632.052
... A31: 2.10.1.27 | B31: 闸阀DN50 | C31: 1.供应安装 2.管道清洗 3.管道打压测试 | D31: 室内装饰装修及安装工程项目 | E31: 个 | F31: 800 | G31: =SUM(H31:M31) -> 95.928139 | H31: 1.098355 | I31: 92.88 | J31: 1 | K31: =(H31+I31+J31)*'2-报价汇总'!$H$5 -> 0.94978355 | L31: =(H31+I31+J31+K31)*'2-报价汇总'!$I$5 -> 0 | M31: =(L31+K31+J31+I31+H31)*'2-报价汇总'!$J$5 -> 0 | N31: =F31*G31 -> 76742.511
A32: 2.10.1.28 | B32: 水压试验、系统调试 | C32: 1.打压试验 | D32: 无暖气改造，测试原有采暖设备是否可以正常使用 | E32: 系统 | F32: 300 | G32: 2000 | N32: =F32*G32 -> 600000
A33: 2.10.1.29 | B33: 暖气片移动位置（包含10米内管道） | C33: 1.拆除原有暖气片 2.安装暖气片 3.包含10米管道，超出部分单独计算 | D33: 室内装饰装修及安装工程项目 | E33: 组 | F33: 1200 | G33: 570 | N33: =F33*G33 -> 684000
B34: 小计
A35: 2.10.2 | B35: 地暖系统
A36: 2.10.2.01 | B36: 分集水器 | C36: 1.分集水器供应安装 2.调试测试 | D36: 室内装饰装修及安装工程项目 | E36: 路 | F36: 300 | G36: =SUM(H36:M36) -> 131.16883 | H36: 28.96013 | I36: 97.04 | J36: 3.87 | K36: =(H36+I36+J36)*'2-报价汇总'!$H$5 -> 1.2987013 | L36: =(H36+I36+J36+K36)*'2-报价汇总'!$I$5 -> 0 | M36: =(L36+K36+J36+I36+H36)*'2-报价汇总'!$J$5 -> 0 | N36: =F36*G36 -> 39350.649
A37: 2.10.2.02 | B37: 地暖采暖管铺设 | C37: 1.聚苯乙烯泡沫塑料板，地暖反射膜 2.地板辐射PERT塑料管DN25，地板采暖固定卡，铅丝网铺设 3.地暖保护层 | D37: 室内装饰装修及安装工程项目 | E37: m2 | F37: 300000 | G37: =SUM(H37:M37) -> 91.818182 | H37: 8.7790909 | I37: 81.37 | J37: 0.76 | K37: =(H37+I37+J37)*'2-报价汇总'!$H$5 -> 0.90909091 | L37: =(H37+I37+J37+K37)*'2-报价汇总'!$I$5 -> 0 | M37: =(L37+K37+J37+I37+H37)*'2-报价汇总'!$J$5 -> 0 | N37: =F37*G37 -> 27545455
A38: 2.10.2.03 | B38: 热镀锌钢管DN70 | C38: 1.管道及配套管件供应安装 2.管道保温 3.管道清洗 4.管道打压测试 5.管道支架等 | D38: 室内、室外装饰装修及安装工程项目 | E38: m | F38: 3000 | G38: 83.7 | N38: =F38*G38 -> 251100
A39: 2.10.2.04 | B39: 热镀锌钢管DN50 | C39: 1.管道及配套管件供应安装 2.管道保温 3.管道清洗 4.管道打压测试 5.管道支架等 | D39: 室内、室外装饰装修及安装工程项目 | E39: m | F39: 3000 | G39: 59.4 | N39: =F39*G39 -> 178200
A40: 2.10.2.05 | B40: 热镀锌钢管DN40 | C40: 1.管道及配套管件供应安装 2.管道保温 3.管道清洗 4.管道打压测试 5.管道支架等 | D40: 室内、室外装饰装修及安装工程项目 | E40: m | F40: 3000 | G40: 52.9 | N40: =F40*G40 -> 158700
A41: 2.10.2.06 | B41: 热镀锌钢管DN32 | C41: 1.管道及配套管件供应安装 2.管道保温 3.管道清洗 4.管道打压测试 5.管道支架等 | D41: 室内、室外装饰装修及安装工程项目 | E41: m | F41: 3000 | G41: 47.5 | N41: =F41*G41 -> 142500
A42: 2.10.2.07 | B42: 热镀锌钢管DN25 | C42: 1.管道及配套管件供应安装 2.管道保温 3.管道清洗 4.管道打压测试 5.管道支架等 | D42: 室内、室外装饰装修及安装工程项目 | E42: m | F42: 3000 | G42: 38.3 | N42: =F42*G42 -> 114900
A43: 2.10.2.08 | B43: 热镀锌钢管DN20 | C43: 1.管道及配套管件供应安装 2.管道保温 3.管道清洗 4.管道打压测试 5.管道支架等 | D43: 室内、室外装饰装修及安装工程项目 | E43: m | F43: 3000 | G43: 28.6 | N43: =F43*G43 -> 85800
A44: 2.10.2.09 | B44: 自动排气阀DN32 | C44: 1.供应安装 2.管道清洗 3.管道打压测试 | D44: 室内装饰装修及安装工程项目 | E44: 个 | F44: 1200 | G44: 98.6 | N44: =F44*G44 -> 118320
A45: 2.10.2.10 | B45: 自动排气阀DN20 | C45: 1.供应安装 2.管道清洗 3.管道打压测试 | D45: 室内装饰装修及安装工程项目 | E45: 个 | F45: 1200 | G45: 73.7 | N45: =F45*G45 -> 88440
A46: 2.10.2.11 | B46: 自动排气阀DN15 | C46: 1.供应安装 2.管道清洗 3.管道打压测试 | D46: 室内装饰装修及安装工程项目 | E46: 个 | F46: 1200 | G46: 63.2 | N46: =F46*G46 -> 75840
A47: 2.10.2.12 | B47: 球阀DN32 | C47: 1.供应安装 2.管道清洗 3.管道打压测试 | D47: 室内装饰装修及安装工程项目 | E47: 个 | F47: 1200 | G47: =SUM(H47:M47) -> 59.769264 | H47: 10.087489 | I47: 48.5 | J47: 0.59 | K47: =(H47+I47+J47)*'2-报价汇总'!$H$5 -> 0.59177489 | L47: =(H47+I47+J47+K47)*'2-报价汇总'!$I$5 -> 0 | M47: =(L47+K47+J47+I47+H47)*'2-报价汇总'!$J$5 -> 0 | N47: =F47*G47 -> 71723.117
A48: 2.10.2.13 | B48: 过滤器DN32 | C48: 1.供应安装 2.管道清洗 3.管道打压测试 | D48: 室内装饰装修及安装工程项目 | E48: 个 | F48: 300 | G48: =SUM(H48:M48) -> 44.492468 | H48: 4.9419481 | I48: 38.7 | J48: 0.41 | K48: =(H48+I48+J48)*'2-报价汇总'!$H$5 -> 0.44051948 | L48: =(H48+I48+J48+K48)*'2-报价汇总'!$I$5 -> 0 | M48: =(L48+K48+J48+I48+H48)*'2-报价汇总'!$J$5 -> 0 | N48: =F48*G48 -> 13347.74
A49: 2.10.2.14 | B49: 泄水阀DN32 | C49: 1.供应安装 2.管道清洗 3.管道打压测试 | D49: 室内装饰装修及安装工程项目 | E49: 个 | F49: 1200 | G49: =SUM(H49:M49) -> 68.207792 | H49: 11.652468 | I49: 55.29 | J49: 0.59 | K49: =(H49+I49+J49)*'2-报价汇总'!$H$5 -> 0.67532468 | L49: =(H49+I49+J49+K49)*'2-报价汇总'!$I$5 -> 0 | M49: =(L49+K49+J49+I49+H49)*'2-报价汇总'!$J$5 -> 0 | N49: =F49*G49 -> 81849.351
A50: 2.10.2.15 | B50: 水压试验、系统调试 | C50: 1.打压试验 | D50: 无暖气改造，测试原有采暖设备是否可以正常使用 | E50: 系统 | F50: 300 | G50: 2000 | N50: =F50*G50 -> 600000
B51: 小计
B52: 采暖工程合计： | N52: =SUM(N5:N51) -> 33921677

Sheet 2.11-施工图纸
A1: 理想汽车中心店施工图纸报价清单
A2: ='2.1-装饰工程'!A2 -> 注意：此报价清单每项不得随意更改、删减，如有任何增加项请务必在每大项最后“补充项“中列举，补充项及说明字体颜色均采用蓝色；且所有项目都需要填写。
A3: 序号 | B3: 内容 | C3: 适用范围 | D3: 单位 | E3: 24/25年暂估工程量 | F3: 综合单价 | G3: 24/25年暂估总价 | H3: 计算规则 | I3: 备注
B4: 2.11施工图纸
A5: 2.11.1 | B5: 装饰设计部分
A6: 2.11.1.01 | B6: 室内装饰 | C6: 室内装饰工程 | D6: ㎡ | E6: 3147637.1 | F6: 25 | G6: =E6*F6 -> 78690928 | H6: 装修改造区域面积 | I6: 含施工图及竣工图
A7: 2.11.2 | B7: 建筑改造部分
A8: 2.11.2.01 | B8: 建筑结构 | C8: 主体结构改造（搭建夹层、钢结构楼梯等主结构变化项目）不包含二次砌筑结构 | D8: ㎡ | E8: 0 | F8: 35 | G8: =E8*F8 -> 0 | H8: 涉及结构工程位置水平投影面积
A9: 2.11.2.02 | B9: 外墙场地 | C9: 室外场地实际改造及外立面改造部分（室外停车划线、雨水井、污水井、化粪池不包含） | D9: ㎡ | E9: 60053.122 | F9: 20 | G9: =E9*F9 -> 1201062.4 | H9: 需要改造的室外场地及外立面投影面积
A10: 2.11.3 | B10: 机电设计部分
A11: 2.11.3.01 | B11: 强电 | C11: 机电改造工程 | D11: ㎡ | E11: 3147637.1 | F11: 4 | G11: =E11*F11 -> 12590548 | H11: 机电改造区域面积
A12: 2.11.3.02 | B12: 弱电 | C12: 弱电改造工程 | D12: ㎡ | E12: 948689.12 | F12: 3 | G12: =E12*F12 -> 2846067.4 | H12: 弱电改造区域面积
A13: 2.11.3.03 | B13: 给排水 | C13: 给排水工程 | D13: ㎡ | E13: 187397.78 | F13: 35 | G13: =E13*F13 -> 6558922.3 | H13: 给排水改造区域面积
A14: 2.11.3.04 | B14: 空调、暖通 | C14: 空调、暖通工程 | D14: ㎡ | E14: 0 | F14: 3 | G14: =E14*F14 -> 0 | H14: 空调改造区域面积
A15: 2.11.3.05 | B15: 消防 | C15: 消防改造工程 | D15: ㎡ | E15: 0 | F15: 2 | G15: =E15*F15 -> 0 | H15: 消防改造区域面积
A16: 2.11.4 | B16: 效果图 | E16: 6475 | F16: 550 | G16: =E16*F16 -> 3561250 | H16: 单位：元/张
A17: 2.11.5 | B17: 平面方案设计 | E17: 0 | F17: 10 | G17: =E17*F17 -> 0 | H17: 单位：元/㎡
B18: 合计 | G18: =SUM(G6:G17) -> 1.0544878e+08
A19: 说明：1、含施工图敲章，不包含结构设计、消防设计图敲章，包含消防及施工图报审配合，结构计算书，原一次动力电改造设计
G21: =G16/#REF! -> #REF!

Sheet 2.12-其他措施费
A1: 理想汽车中心店其他措施工程量清单
A2: ='2.1-装饰工程'!A2 -> 注意：此报价清单每项不得随意更改、删减，如有任何增加项请务必在每大项最后“补充项“中列举，补充项及说明字体颜色均采用蓝色；且所有项目都需要填写。
A3: 序号 | B3: 项目名称 | C3: 项目特征 | D3: 适用范围 | E3: 工程量计算规则 | F3: 单位 | G3: 24/25年暂估工程量 | H3: 综合单价 | I3: 24/25年暂估总价 | J3: 备注
B4: 2.12其他措施费
A5: 2.12.01 | B5: 室内脚手架 | C5: 租赁、搭拆脚手架费用及相关运输费用 | D5: 室内结构标高超过4.5m计取此部分费用 | E5: 室内使用面积 | F5: m2 | G5: 2076498 | H5: 8 | I5: =G5*H5 -> 16611984
A6: 2.12.02 | B6: 工程保险费 | C6: 建筑工程一切险以合同额提保； 第三者责任险500万； *开工前务必提供保单 | D6: 室内、室外装饰装修及安装工程项目 | E6: 提供保险单据,以实际发生+5%管理费为准 | F6: 项 | G6: 0 | I6: =G6*H6 -> 0
A7: 2.12.03 | B7: 装修用电费 | C7: 竣工验收合格前产生的全部电费 | D7: 室内、室外装饰装修及安装工程项目 | E7: 以实际缴纳凭证为准，注：业主指定购买不扣降幅 | F7: 项 | G7: 2198948 | I7: =G7*H7 -> 0
A8: 2.12.04 | B8: 装修用水费 | C8: 竣工验收合格前产生的全部水费 | D8: 室内、室外装饰装修及安装工程项目 | E8: 以实际缴纳凭证为准，注：业主指定购买不扣降幅 | F8: 项 | G8: 2198948 | I8: =G8*H8 -> 0
A9: 2.12.05 | B9: 支付政府管理部门各项费用： | E9: 以理想汽车项目经理确认为准 | F9: 项 | G9: 0 | I9: =G9*H9 -> 0
A10: 2.12.06 | B10: 装修材料复检费（材料见证取样费，若发生） | E10: 以实际缴纳凭证为准 | F10: 项 | G10: 0 | I10: =G10*H10 -> 0
A11: 2.12.07 | B11: 空气检测 | C11: 竣工验收前检测项目室内甲醛、苯、甲苯、二甲苯、TVOC相关内容并达到国家规范标准出具CMA认证检测报告 | D11: 客休区、办公室 | E11: 标准检测位置：办公室、客休区、领料室、卫生间 | F11: 点 | G11: 9249.1871 | H11: 400 | I11: =G11*H11 -> 3699674.9
A12: 2.12.08 | B12: 冬季施工措施费（含施工保温及取暖费用） | C12: 1.室内场地施工期间取暖费 2.局部功能区取暖装置 3.施工保温 4.提供冬季施工方案并严格按照方案执行 | D12: 室外日平均气温低于-5°C之下的施工项目 | E12: 室内使用面积 | F12: m2 | G12: 0 | H12: 12 | I12: =G12*H12 -> 0
B13: 补充项
B14: 注意：由于乙方原因发生的抢工费用，由乙方支付。
B15: 其他措施费合计： | I15: =SUM(I5:I12) -> 20311659

Sheet 3-材料品牌表
A1: 材料品牌表
A2: 序号 | B2: 材料名称 | C2: 使用区域 | D2: 品牌 | E2: 颜色 | F2: 规格 | G2: 备注
A3: 1 | B3: 涂料
A4: 1.01 | B4: 乳胶漆 | C4: 零售办公室/交付客休区天花 交付工位天花 车间区域的墙面（1200mm以上，标高线以下）功能房间 | D4: 立邦净味120 多乐士 静味五合一 | E4: 白色 | F4: 立邦 OW041-4多乐±83YY 88/033clinic white
A5: 1.02 | B5: 防水乳胶漆 | C5: 男、女卫生间天花 | D5: 立邦-美得丽户外防水 | E5: 白色 | F5: -
A6: 1.03 | B6: 米色乳胶漆 | C6: 零售展厅佼付客休区/洽谈室佼车大厅 | D6: 立邦净味120 多乐士 静味五合一 | E6: 米色 | F6: 立邦 云端漫步OW082-4 多乐士 Cielo Blanco43YY 81/051
A7: 1.04 | B7: 灰色乳胶漆 | C7: 车间区域标高线以上的墻面及顶面（裸顶顶面） | D7: 立邦 多乐士 静味五合一 | E7: 深灰色 | F7: 立邦NN6500-1魔力黑多乐士60RR 07/002
A8: 1.05 | B8: 外墙漆 | C8: 室外立面 | D8: 立邦室外漆多乐士室外漆 | E8: 浅灰色 | F8: 立邦NN1380-2山雨欲来 多乐士16BB 25/001
A9: 1.06 | B9: 深灰色环氧树脂漆 | C9: 交付工位 | D9: 耐石固MARKFRLFD/玛珂立 | E9: 灰色 | F9: 哑光漆 参照潘通色：401U
A10: 1.07 | B10: 白色地坪漆线 | C10: 车位线、车位编号 | D10: 环氧地坪漆地面采用以下品牌：耐石固MARKFRLFD/玛珂立普通地面无品牌要求 | E10: 白色 | F10: 宽度：100mm企业标准字体5个车位以下工艺：冷喷
A11: 1.08 | B11: 白色地坪漆线 | C11: 沥青路面 | D11: 热熔 | F11: 5个车位以上使用工艺：热熔
A12: 2 | B12: 金属
A13: 2.01 | B13: 米色铝板 | C13: 零售外立面 | D13: 总包定制 | E13: 劳尔色卡色号：RAL9001TS75 | F13: 米白色厚度3mm40%哑光
A14: 2.02 | B14: 灰色铝板 | C14: 零售中心商场店室内门头 | D14: 总包定制 | E14: JX815珍珠灰 | F14: 1200*2400mm(常规尺寸)厚度:3mm(胶粘工艺)
A15: 2.03 | B15: 铝板木皮饰面 | C15: 零售外立面 | D15: 总包定制甲指木皮 | E15: 直纹 | F15: 铝板贴木纹厚度3mm
A16: 2.04 | B16: 波浪板 | C16: 外立面 | D16: 总包定制 | E16: 劳尔色卡:闪银9022吉祥铝塑板色卡:鼠灰银JX816 | F16: 厚度3mm,哑光度40%
A17: 2.05 | B17: 深灰色铝板 | C17: 外立面-波浪板边框 | D17: 总包定制 | E17: 劳尔色卡:闪银9022吉祥铝塑板色卡:鼠灰银JX816 | F17: 1200*2400mm厚度:宽度1m内2mm宽度大于1m用3mm
A18: 2.06 | B18: 白色穿孔铝板 | C18: 冲孔板外立面 | D18: 总包定制 | E18: 氟碳喷涂,参考多乐士色卡93YY89/01220%哑光 | F18: 1200*2400mm厚度:3mm
A19: 2.07 | B19: 理想绿色铝板 | C19: 冲孔板外立面入口pylon横格栅外立面入口塔牌 | D19: 总包定制 | E19: 氟碳喷涂,潘通330C+10%哑光 | F19: 1200*2400mm厚度:3mm
A20: 2.08 | B20: 深灰色金属铝型材 | C20: 格栅门头上下沿 | D20: 总包定制 | E20: 氟碳喷涂,潘通BlackU+5%闪银+10%哑光度(追横格栅颜色) | F20: 大尺寸干挂形式建议3mm厚不变,小尺寸可用2mm厚
A21: 2.09 | B21: 灰色铝方管 | C21: 门头 | D21: 总包定制 | E21: 氟碳喷涂,潘通BlackU+5%闪银+10%哑光度 | F21: 50*100mm(横截面尺寸)厚度2mm
A22: 2.1 | B22: 白色金属铝型材 | C22: 冲孔板门头上下沿 | D22: 总包定制 | E22: 氟碳喷涂,参考多乐士色卡93YY89/012,20%哑光(追冲孔板颜色) | F22: 宽度1m内2mm宽度大于1m用3mm
A23: 2.11 | B23: 木纹转印铝方管 | C23: 部分售后或交付外立面 | D23: 总包定制 | E23: 木纹纹样:追样兔宝宝科技木-双子木982颜色:追2.1木作色 | F23: 30*200mm(横截面尺寸),厚度:2mm
A24: 2.12 | B24: 铝塑板 | C24: 冲孔板背板绿色pylon凹槽横格栅背板 | D24: 吉祥系列 | E24: 铝塑板-JX814白银灰 | F24: 1200*2400mm(常规尺寸)厚度:4mm21丝以上
... A29: 2.17 | B29: 白色金属踢脚线明装 | C29: 交付中心、零售展厅办公室 | D29: 总包定制 | E29: 铝合金踢脚哑光度40%颜色同乳胶漆 | F29: 50mm 高
A30: 2.18 | B30: 白色铝板 | C30: 零售展厅一体展示墙充电桩区域 | E30: 白色哑光 | F30: 厚度2mm
A31: 2.19 | B31: 深灰色铝塑板 | C31: 外立面、窗台板 | D31: 吉祥系列 | E31: jx816鼠灰银 | F31: 厚度：4mm； 窗台21丝，外立面30丝及以上
A32: 2.2 | B32: 40%雾面不锈钢 | C32: 电视后背板/木作嵌条 | D32: 总包定制 | E32: 黑色 | F32: 厚度：1.5mm
A33: 2.21 | B33: 墙砖金属折边 | C33: 维修车间/PDI/洗车墙砖收边 | D33: 成品 | E33: 深灰色哑光烤漆PT419u | F33: 1cm*1.5cm
A34: 2.22 | B34: 金属门框 | C34: 玻璃门门框 | D34: 总包定制 | E34: 深灰色哑光氟碳漆PT419u | F34: 厚度：1mm
A35: 3 | B35: 瓷砖
A36: 3.01 | B36: 深灰色地砖 | C36: 零售展厅-主展车 | D36: 一拓:LX101 | E36: 深灰色 | F36: 800*800*9mm
A37: 3.02 | B37: 浅灰色地砖 | C37: 零售展厅 | D37: 一拓:LX10160-22 | E37: 浅灰色 | F37: 800*800*9mm
A38: 3.03 | B38: 木纹地砖 | C38: 家庭区、洽谈室、儿童区 | D38: 一拓:WLX301 | E38: - | F38: 200*1200*10mm
A39: 3.04 | B39: 地砖 | C39: 车间的办公室及功能间客户卫生间、员工卫生间 | D39: 甲指 | E39: 灰色 | F39: 600x600mm
A40: 3.05 | B40: 地砖 | C40: 客户、员工卫生间墙面淋浴间墙面 | D40: 甲指 | E40: 灰色 | F40: 地面:600x600mm墙面:300x600mm
A41: 3.06 | B41: 地砖 | C41: 车间区域 | D41: 马可波罗：车间地面产品STD-K923灰色或诺贝尔同款 | E41: 深灰色 | F41: 200x200mm厚度12mm
A42: 3.07 | B42: 地砖 | C42: 车间区域 | D42: 马可波罗：工位线STD-K801白色 或诺贝尔同款 | E42: 白色 | F42: 200x200mm
A43: 3.08 | B43: 墙砖 | C43: 车间区域1200mm、洗车3000mm | D43: 马可波罗墙砖： STD-K923-10 灰色 或诺贝尔同款 | E43: 灰色 | F43: 200x200x10(mm)砖缝5mm
A44: 4 | B44: 石材
A45: 4.01 | B45: 人造石 | C45: 男、女卫生间洗手台面 | D45: 总包定制,设计师确认 | E45: 哑光白 | F45: 设计师确认
A46: 4.02 | B46: 花岗岩（芝麻灰） | C46: 室外坡道 | D46: 总包定制 | E46: 烧面灰麻石 | F46: 30mm厚
A47: 4.03 | B47: 花岗岩（芝麻灰） | C47: 室外台阶 | D47: 总包定制 | E47: 灰麻花岗岩，荔枝面或烧面灰麻石 | F47: 20mm厚
A48: 4.04 | B48: 过门石（芝麻灰） | C48: 地面 | D48: 总包定制 | E48: 哑光面原板面 | F48: 15mm厚
A49: 5 | B49: 玻璃
A50: 5.01 | B50: 钢化玻璃 | C50: 洽谈室、财务室 | D50: 总包定制 | E50: 零售:超白交付:普白 | F50: 12mm以上钢化
A51: 5.02 | B51: 钢化玻璃 | C51: 外立面主入口 | D51: 总包定制 | E51: 零售:超白交付:超白 | F51: 3米以下:15mm3米以上:19mm
A52: 5.03 | B52: 钢化夹胶玻璃 | C52: 楼梯扶手 | D52: 总包定制 | E52: 零售:超白交付:超白 | F52: 6+6夹胶
A53: 5.04 | B53: 中空玻璃 | C53: 玻璃幕墙 | D53: 总包定制 | E53: 零售:超白交付:超白 | F53: 8+12A+8中空
A54: 5.05 | B54: 带框银镜边框色PT419U | C54: 客户卫生间、员工卫生间 | D54: 总包定制 | E54: 颜色：边框为深灰色金属烤漆；安装：底边距洗手池台面200mm | F54: 定制
A55: 6 | B55: 石膏板
A56: 6.01 | B56: 矿棉吸音板 | C56: 零售、交付办公室、功能间 | D56: 阿姆斯壮长城 | E56: 雅丽、雅韵防潮RH99 | F56: 600x600mm
A57: 6.02 | B57: 纸面石膏板 | C57: 交付大厅、交付工位、保洁间 | D57: 龙牌、泰山、拉法基 | F57: 天花9.5mm墙身12mm
A58: 6.03 | B58: 防火石膏板 | C58: 交付大厅 | D58: 龙牌、泰山、拉法基 | F58: 天花9.5mm墙身12mm
A59: 6.04 | B59: 铝扣板 | C59: 员工卫生间/更衣室/淋浴间 | D59: 总包定制 | E59: 白色 | F59: 300X300mm厚度0.6mm
A60: 6.05 | B60: 防水纸面石膏板 | C60: 客户/员工卫生间/更衣室/淋浴间 | D60: 龙牌、泰山、拉法基 | F60: 天花9.5mm墙身12mm
A61: 6.06 | B61: 水泥压力板 | C61: 防水部位 | F61: 厚度9.5mm、12mm
A62: 7 | B62: 辅材
A63: 7.01 | B63: 胶地板 | C63: 儿童区 | E63: 原木色
A64: 7.02 | B64: 防静电高架地板 | C64: 弱电室 | D64: 科华、红日 | F64: 600x600
A65: 7.03 | B65: 空调风口百叶 | C65: 功能房间 | E65: 哑光白色(同周边涂料颜色) | F65: 送风600*600散流器回风单层百叶
A66: 7.04 | B66: 美缝剂 | C66: 交付中心、零售展厅、卫生间 | D66: 家美士、德高 | E66: 灰色 | F66: 家美士:罗马灰
A67: 7.05 | B67: 水篦子 | C67: 维修车间 | E67: 灰色 | F67: 小孔4#国标/3.8m高280x220mm 高分子树脂水篦子
A68: 7.06 | B68: 磨砂贴膜 | C68: 接待室、洽谈室、财务室 | F68: 定制
A69: 7.07 | B69: 聚酯纤维板 | C69: 办公室 | E69: 月光灰 | F69: 定制
A70: 7.08 | B70: 聚酯纤维板 | C70: 车务保险区 | E70: 米白色 | F70: 定制
A71: 7.09 | B71: 阻燃胶合板 | D71: 千年舟、金秋、莫干山 | F71: 环保:E0级防火:B1级厚度：18mm
A72: 7.1 | B72: 轻钢龙骨 | C72: 轻钢龙骨到顶的区域:卫生间，办公室，机房 | D72: 龙牌、泰山、拉法基 | F72: 3m以上厚度不低于0.6mm
A73: 7.11 | B73: 岩棉 | F73: 厚度 50mm容重65kg/m3防火与隔音作用同时满足
A74: 7.12 | B74: 橡塑保温棉 | F74: 厚度20mm
A75: 7.13 | B75: 防火板-抗倍特 | C75: 男、女卫生间 | D75: 瑞权麦象 | E75: 白橡直纹 | F75: 厚度18mm
A76: 7.14 | B76: 排水管 | D76: 联塑、日新、日丰
A77: 7.15 | B77: 给水管 | D77: 联塑、日新、日丰
A78: 8 | B78: 其它建材
A79: 8.01 | B79: 墙布 | C79: 照片墙背板 | D79: 雅悦TM140-202 CLOTH HUAN PAGE26
A80: 8.02 | B80: 灰色墙布 | C80: 零售洽谈室 | D80: 繁华墙布炼色FH14-10 完美世家MSJ096-26
A81: 8.03 | B81: 科技木皮 | C81: 儿童区墙面 | D81: 总包定制 | E81: 木纹纹样:追样兔宝宝科技木-双子木982 颜色:追2.1木作色 | F81: 1200*2400mm(常规尺寸)
A82: 8.04 | B82: 木纹转印 | C82: 儿童区墙面 | D82: 总包定制 | E82: 木纹纹样:追样兔宝宝科技木-双子木982 颜色:追2.1木作色 | F82: 1200*2400mm(常规尺寸)
A83: 8.05 | B83: 木饰面-科技木皮 | C83: 木作道具、家具道具 | D83: 甲指 | E83: 白橡直纹 | F83: 开放清漆
A84: 8.06 | B84: 矿棉板 | C84: 零售、交付办公室、功能间 | D84: 阿姆斯壮 长城 | E84: 雅丽 防潮RH99 | F84: 600mm*600mm
A85: 9 | B85: 电气材料
A86: 9.01 | B86: 电线 | C86: 全店铺用电区域 | D86: 起帆、上上、珠江、江南、远东 | F86: ZRBV 铜芯，商场店有特殊需求的可用WDZB 铜芯
A87: 9.02 | B87: 电缆 | C87: 全店铺用电区域 | D87: 起帆、上上、远东、珠江、江南、民兴、南牌、金龙羽、花城、宝胜、津猫、鲁能泰山、熊猫、津达、塔牌、川缆、三峡、鸽牌、瑞强 | F87: 50平方以上，150m以下的用铝芯，其余用铜芯ZRBV，商场店有特殊需求的可用WDZB 铜芯
A88: 9.03 | B88: 线管 | C88: 全店铺用电区域 | D88: 总包定制 | F88: KBG或JDG金属管 壁厚不得小于1mm
A89: 9.04 | B89: 空调铜管 | D89: 总包定制 | F89: 直径9.52mm以下 壁厚0.8mm直径12-28.6mm 壁厚1mm直径31.8mm 壁厚1.25mm直径34.9mm 壁厚1.5mm（外径允许偏差±0.05）（壁厚允许偏差±0.06）
A90: 9.05 | B90: 空开 | D90: 正泰、德力西 （商场店业主有特殊需求采用施耐德）
A91: 9.06 | B91: 电表 | D91: 正泰
A92: 9.07 | B92: 电箱 | D92: 总包定制
A93: 9.08 | B93: 桥架 | D93: 总包定制 | F93: 尺寸：50*50/100厚度1.0mm尺寸：100*100及以上厚度1.5mm
A94: 9.09 | B94: 单联单控开关 | C94: 客休区、车间区域 | D94: 施耐德/绎尚 西门子/远景 | E94: 白色、灰色（灰色墙裙采用灰色面板）原则同墙面统一 | F94: 施耐德250V 10A100*100
A95: 9.1 | B95: 单联双控开关 | C95: 客休区、车间区域 | D95: 施耐德/绎尚西门子/远景 | E95: 白色、灰色（灰色墙裙采用灰色面板）原则同墙面统一 | F95: 施耐德250V 10A100*100
A96: 9.11 | B96: 双联单控开关 | C96: 客休区 | D96: 施耐德/绎尚西门子/远景 | E96: 白色、灰色（灰色墙裙采用灰色面板）原则同墙面统一 | F96: 施耐德250V 10A100*100
A97: 9.12 | B97: 三联单控开关 | C97: 客休区、车间区域 | D97: 施耐德/绎尚 西门子/远景 | E97: 白色、灰色（灰色墙裙采用灰色面板）原则同墙面统一 | F97: 施耐德250V 10A100*100
A98: 9.13 | B98: 四联单控开关 | C98: 客休区、车间区域 | D98: 施耐德/绎尚 西门子/远景 | E98: 白色、灰色（灰色墙裙采用灰色面板）原则同墙面统一 | F98: 施耐德250V 10A100*100
A99: 9.14 | B99: 时控开关 | C99: 客休区 | D99: ABB 德力西 | E99: 白色、灰色（灰色墙裙采用灰色面板）原则同墙面统一 | F99: 100*100
A100: 9.15 | B100: 三孔插座 | C100: 客休区、车间区域 | D100: 施耐德/绎尚 西门子/远景 | E100: 白色、灰色（灰色墙裙采用灰色面板）原则同墙面统一 | F100: 施耐德250V 16A100*100
A101: 9.16 | B101: 安全型二三孔插座 | C101: 客休区、车间区域 | D101: 施耐德/绎尚 西门子/远景 | E101: 白色、灰色（灰色墙裙采用灰色面板）原则同墙面统一 | F101: 施耐德250V 10A100*100、定制松本五孔16A100*100
A102: 9.17 | B102: 设备三相四孔插座 | D102: 施耐德/绎尚 西门子/远景 | E102: 白色、灰色（灰色墙裙采用灰色面板）、香槟金色（追木作色），原则同墙面统一 | F102: 施耐德250V 22A100*100
A103: 9.18 | B103: 光感开关 | D103: 施耐德/绎尚 西门子/远景 | E103: 白色、灰色（灰色墙裙采用灰色面板）原则同墙面统一
A104: 9.19 | B104: 五孔USB+type c接口 | C104: 家具插座 | D104: 西门子/德力西 | E104: 白色、灰色（灰色墙裙采用灰色面板）原则同墙面统一 | F104: 5UB25753NC01
...
