Workbook
Name ___________________N81020: [1]地梁!#REF!
Name dw: #REF!

Sheet 编制说明
A1: 编制说明
A2: 1、工程概况：
A3: 1）、工程名称：珠海丹田海德地库项目装修工程
A4: 2）、建设单位：丹田海德公馆
A5: 3）、工程内容：地库装修及机电
A6: 2、编制依据：
A7: 1）、按建设单位提供的《珠海丹田海德地库施工图2025.12.08》及《珠海丹田海德地库物料书》；
A8: 3、编制范围：
A9: 1）、海德公馆地下室-1F~-3F室内装修工程。 包括：一层主入口、次出口、次出口天花、地面、墙面;地下一层、地下二层、地下三层天花、地面、墙面；
A10: 4、计价说明：
A11: 1）、综合单价综合考虑人工费、各类材料费（含损耗）、机械费、项目措施费（地下暗室施工费、技术措施费、安全文明施工费、临时设施费）、成品保护费、运输装卸费、材料设备场内二次运输费[在合同总工期内施工过程中因各种因素导致需二次运输作业，搬运距离，自行勘察现场]、材料检测试验费、检测费、调试费、验收费、保险费（不包含甲方已购买保险）、规费、管理费、利润、国家强制性收费、风险责任、施工水电费、克服施工现场苛刻条件及难度费用等除监理费之外的全部费用除非另有约定，结算时该综合单价不调整、税金在汇总单独计算。
A12: 5、其他说明
... A21: 9）、根据图纸，有疑问处已列入联系单提疑；

Sheet 汇总表
A1: 报价汇总表
A2: 工程名称：珠海丹田海德地库项目装修工程
A3: 序号 | B3: 户型 | C3: 建筑面积（m2） | D3: 套数 | E3: 造价 （元） | F3: 合价(元)
A4: 1 | B4: 坡道装饰 | C4: 1096.9144 | D4: 1 | E4: =坡道装饰工程量清单!N33 -> 546442.36 | F4: =D4*E4 -> 546442.36
A5: 2 | B5: 地库装饰 | C5: 9925.16 | D5: 1 | E5: =地库装饰工程量清单!N40 -> 2344307.6 | F5: =D5*E5 -> 2344307.6
A6: 3 | B6: 坡道安装 | C6: =C4 -> 1096.9144 | D6: 1 | E6: =坡道安装工程!K9 -> 35729.65 | F6: =D6*E6 -> 35729.65
A7: 4 | B7: 地库安装 | C7: =C5 -> 9925.16 | D7: 1 | E7: =地库安装工程!N19 -> 211932.54 | F7: =D7*E7 -> 211932.54
A8: 5 | B8: 小计 | E8: =SUM(E4:E7) -> 3138412.1 | F8: =SUM(F4:F7) -> 3138412.1
A9: 6 | B9: 税金（9%） | E9: =E8*0.09 -> 282457.09 | F9: =F8*9% -> 282457.09
B10: 总计 | C10: =C4+C5 -> 11022.074 | E10: =E9+E8 -> 3420869.2 | F10: =F8+F9 -> 3420869.2 | H10: =F10/C10 -> 310.36528

Sheet 坡道装饰工程量清单
A1: 珠海丹田海德地库项目装修工程量清单 | S1: 1 | U1: 1 | V1: 1
A2: 序号 | B2: 项目名称 | C2: 项目特征 | D2: 单位 | E2: -1层工程量 | F2: -2层工程量 | G2: -3层工程量 | H2: 合计工程量 | I2: 人工 | J2: 主材 | K2: 辅材及机械费 | L2: 管理及利润取费 | M2: 综合单价（不含税） | N2: 合价（不含税） | O2: 备注 | R2: 成本单价 | S2: 主材 | T2: 损耗率 | U2: 人工 | V2: 辅材 | W2: 机械 | X2: 合价
I3: A | J3: B | K3: C | L3: 0.1 | M3: E=A+B+C+D | N3: F=E*工程量
L4: D=(A+B+C)*费率
A5: 一 | B5: 坡道 | N5: =N6+N15 -> 546442.36
B6: 墙柱面工程 | N6: =SUM(N7:N14) -> 219995.54
A7: 1 | B7: PT-01 涂料 | C7: 1.PT-01 涂料一道; 2.内墙涂料一道; 3.封闭底涂料一道; 4.刮腻子两遍; 5.包含完成该项内容所有工作及费用并满足设计图纸、规范等要求; | D7: m2 | E7: 69.06 | F7: 234.24842 | G7: 101.07512 | H7: =E7+F7+G7 -> 404.38354 | I7: =U7*$U$1 -> 22.5 | J7: =S7*(1+T7)*$S$1 -> 5.555 | K7: =(V7+W7)*$V$1 -> 6.18 | L7: =+SUM(I7:K7)*$L$3 -> 3.4235 | M7: =SUM(I7:L7) -> 37.6585 | N7: =H7*M7 -> 15228.478 | R7: =S7+S7*T7+U7+V7+W7 -> 34.235 | S7: 5.5 | T7: 0.01 | U7: 22.5 | V7: 5.98 | W7: 0.2 | X7: =R7*H7 -> 13844.07
A8: =A7+1 -> 2 | B8: PT-02 涂料 | C8: 1.PT-01 涂料一道; 2.内墙涂料一道; 3.封闭底涂料一道; 4.刮腻子两遍; 5.含成品U型收口条 6.包含完成该项内容所有工作及费用并满足设计图纸、规范等要求; | D8: m2 | E8: 451.5889 | F8: 334.6406 | G8: 334.6406 | H8: =E8+F8+G8 -> 1120.8701 | I8: =U8*$U$1 -> 22.5 | J8: =S8*(1+T8)*$S$1 -> 5.555 | K8: =(V8+W8)*$V$1 -> 6.18 | L8: =+SUM(I8:K8)*$L$3 -> 3.4235 | M8: =SUM(I8:L8) -> 37.6585 | N8: =H8*M8 -> 42210.287 | R8: =S8+S8*T8+U8+V8+W8 -> 34.235 | S8: 5.5 | T8: 0.01 | U8: 22.5 | V8: 5.98 | W8: 0.2 | X8: =R8*H8 -> 38372.988
A9: =A8+1 -> 3 | B9: PT-05 涂料 | C9: 1.PT-05 涂料(包含PT-01线条); 2.一底两面无机涂料饰面层(颜色以图纸标注为准）; 3.2mm厚无机涂料配套的腻子粉调浆满批并打磨平整; 4.包含完成该项内容所有工作及费用并满足设计图纸、规范等要求; | D9: m2 | E9: 277.8103 | F9: 0 | G9: 0 | H9: =E9+F9+G9 -> 277.8103 | I9: =U9*$U$1 -> 22.5 | J9: =S9*(1+T9)*$S$1 -> 5.555 | K9: =(V9+W9)*$V$1 -> 6.18 | L9: =+SUM(I9:K9)*$L$3 -> 3.4235 | M9: =SUM(I9:L9) -> 37.6585 | N9: =H9*M9 -> 10461.919 | R9: =S9+S9*T9+U9+V9+W9 -> 34.235 | S9: 5.5 | T9: 0.01 | U9: 22.5 | V9: 5.98 | W9: 0.2 | X9: =R9*H9 -> 9510.8356
A10: =A9+1 -> 4 | B10: CH-03a 地坪漆踢脚线：H100mm | C10: 1.CH-03a 地坪漆踢脚线：H100mm; 2.包含完成该项内容所有工作及费用并满足设计图纸、规范等要求; | D10: m | E10: 11.18 | F10: 0 | G10: 0 | H10: =E10+F10+G10 -> 11.18 | I10: =U10*$U$1 -> 12 | J10: =S10*(1+T10)*$S$1 -> 4.545 | K10: =(V10+W10)*$V$1 -> 1.3 | L10: =+SUM(I10:K10)*$L$3 -> 1.7845 | M10: =SUM(I10:L10) -> 19.6295 | N10: =H10*M10 -> 219.45781 | R10: =S10+S10*T10+U10+V10+W10 -> 17.845 | S10: 4.5 | T10: 0.01 | U10: 12 | V10: 1.2 | W10: 0.1 | X10: =R10*H10 -> 199.5071
A11: =A10+1 -> 5 | B11: CH-03a 地坪漆踢脚线：H50mm | C11: 1.CH-03a 地坪漆踢脚线：H50mm; 2.包含完成该项内容所有工作及费用并满足设计图纸、规范等要求; | D11: m | E11: 96.765 | F11: 136.588 | G11: 136.588 | H11: =E11+F11+G11 -> 369.941 | I11: =U11*$U$1 -> 10 | J11: =S11*(1+T11)*$S$1 -> 2.525 | K11: =(V11+W11)*$V$1 -> 1.3 | L11: =+SUM(I11:K11)*$L$3 -> 1.3825 | M11: =SUM(I11:L11) -> 15.2075 | N11: =H11*M11 -> 5625.8778 | R11: =S11+S11*T11+U11+V11+W11 -> 13.825 | S11: 2.5 | T11: 0.01 | U11: 10 | V11: 1.2 | W11: 0.1 | X11: =R11*H11 -> 5114.4343
A12: =A11+1 -> 6 | B12: MT-02 金属饰面 | C12: 1.MT-02 金属饰面 1.2mm厚拉丝不锈钢（防指纹处理）; 2.10mm玻镁板、50*50*5mm镀锌方通; 3.包含完成该项内容所有工作及费用并满足设计图纸、规范等要求; | D12: m2 | E12: 29.826685 | F12: 0 | G12: 0 | H12: =E12+F12+G12 -> 29.826685 | I12: =U12*$U$1 -> 85 | J12: =S12*(1+T12)*$S$1 -> 454.5 | K12: =(V12+W12)*$V$1 -> 72.2 | L12: =+SUM(I12:K12)*$L$3 -> 61.17 | M12: =SUM(I12:L12) -> 672.87 | N12: =H12*M12 -> 20069.482 | R12: =S12+S12*T12+U12+V12+W12 -> 611.7 | S12: 450 | T12: 0.01 | U12: =20+65 -> 85 | V12: =12.5+25*2+8.5 -> 71 | W12: 1.2 | X12: =R12*H12 -> 18244.983
A13: =A12+1 -> 7 | B13: 玻镁板封墙 | C13: 1.玻镁板封墙 2.10mm玻镁板、50*50*5mm镀锌方通; 3.包含完成该项内容所有工作及费用并满足设计图纸、规范等要求; | D13: m2 | E13: 129.108 | F13: 0 | G13: 0 | H13: =E13+F13+G13 -> 129.108 | I13: =U13*$U$1 -> 75 | J13: =S13*(1+T13)*$S$1 -> 50.5 | K13: =(V13+W13)*$V$1 -> 122.75 | L13: =+SUM(I13:K13)*$L$3 -> 24.825 | M13: =SUM(I13:L13) -> 273.075 | N13: =H13*M13 -> 35256.167 | Q13: =39.25*0.2 -> 7.85 | R13: =S13+S13*T13+U13+V13+W13 -> 248.25 | S13: =25*2 -> 50 | T13: 0.01 | U13: =35+20*2 -> 75 | V13: =5.5*20.5+8.5 -> 121.25 | W13: 1.5 | X13: =R13*H13 -> 32051.061
A14: =A13+1 -> 8 | B14: AM-01a 铝格栅 | C14: 1.AM-01a 铝格栅 2.5mm厚; 2.铝格栅规格：30*120*2.5@130mm; 3.阳极氧化处理; 4.按要求做加固处理，含必要的骨架; 5.包含完成该项内容所有工作及费用并满足设计图纸、规范等要求; | D14: m2 | E14: 95.1 | F14: 0 | G14: 0 | H14: =E14+F14+G14 -> 95.1 | I14: =U14*$U$1 -> 96 | J14: =S14*(1+T14)*$S$1 -> 714.07 | K14: =(V14+W14)*$V$1 -> 59.1 | L14: =+SUM(I14:K14)*$L$3 -> 86.917 | M14: =SUM(I14:L14) -> 956.087 | N14: =H14*M14 -> 90923.874 | P14: =1000/130 -> 7.6923077 | Q14: =0.36*255*7.7 -> 706.86 | R14: =S14+S14*T14+U14+V14+W14 -> 869.17 | S14: 707 | T14: 0.01 | U14: =12*8 -> 96 | V14: =1.8*4*8 -> 57.6 | W14: 1.5 | X14: =R14*H14 -> 82658.067
B15: 天花工程 | N15: =SUM(N16:N32) -> 326446.81 | X15: =R15*H15 -> 0
A16: 1 | B16: 玻镁板吊顶（含刷白） | C16: 1.双层10mm玻镁板刷白(按投影面积计算); 2.50*50*5镀锌方通基层、150*150*10mm镀锌钢板; 3.包含完成该项内容所有工作及费用并满足设计图纸、规范等要求; | D16: ㎡ | E16: 24.92 | F16: 0 | G16: 0 | H16: =E16+F16+G16 -> 24.92 | I16: =U16*$U$1 -> 109.5 | J16: =S16*(1+T16)*$S$1 -> 5.05 | K16: =(V16+W16)*$V$1 -> 197.73 | L16: =+SUM(I16:K16)*$L$3 -> 31.228 | M16: =SUM(I16:L16) -> 343.508 | N16: =H16*M16 -> 8560.2194 | R16: =S16+S16*T16+U16+V16+W16 -> 312.28 | S16: 5 | T16: 0.01 | U16: =50+20*2+19.5 -> 109.5 | V16: =5.5*25.5+25*2+5.98 -> 196.23 | W16: 1.5 | X16: =R16*H16 -> 7782.0176
A17: =A16+1 -> 2 | B17: 玻镁板吊顶 | C17: 1.双层10mm玻镁板吊顶(按投影面积计算); 2.50*50*5镀锌方通基层; 3.包含完成该项内容所有工作及费用并满足设计图纸、规范等要求; | D17: ㎡ | E17: 6.8297 | F17: 0 | G17: 0 | H17: =E17+F17+G17 -> 6.8297 | I17: =U17*$U$1 -> 109.5 | J17: =S17*(1+T17)*$S$1 -> 5.05 | K17: =(V17+W17)*$V$1 -> 170.23 | L17: =+SUM(I17:K17)*$L$3 -> 28.478 | M17: =SUM(I17:L17) -> 313.258 | N17: =H17*M17 -> 2139.4582 | R17: =S17+S17*T17+U17+V17+W17 -> 284.78 | S17: 5 | T17: 0.01 | U17: =50+20*2+19.5 -> 109.5 | V17: =5.5*20.5+25*2+5.98 -> 168.73 | W17: 1.5 | X17: =R17*H17 -> 1944.962
A18: =A17+1 -> 3 | B18: MT-02金属凹槽 100mm宽 | C18: 1.100mm宽金属凹槽 1.2mm厚拉丝不锈钢（防指纹处理）; 2.镀锌方通规格：50*50*5mm; 3.双层10mm玻镁板; 4.展开面：400mm; 5.包含完成该项内容所有工作及费用并满足设计图纸、规范等要求; | D18: m | E18: 12.57 | F18: 0 | G18: 0 | H18: =E18+F18+G18 -> 12.57 | I18: =U18*$U$1 -> 100 | J18: =S18*(1+T18)*$S$1 -> 189.072 | K18: =(V18+W18)*$V$1 -> 148.525 | L18: =+SUM(I18:K18)*$L$3 -> 43.7597 | M18: =SUM(I18:L18) -> 481.3567 | N18: =H18*M18 -> 6050.6537 | R18: =S18+S18*T18+U18+V18+W18 -> 437.597 | S18: =450*0.4+1.2*6 -> 187.2 | T18: 0.01 | U18: 100 | V18: =7.85*3*5.5+3.5+25*2*0.3 -> 148.025 | W18: 0.5 | X18: =R18*H18 -> 5500.5943
A19: =A18+1 -> 4 | B19: MT-02 金属饰面 | C19: 1.MT-02金属饰面 1.2mm厚拉丝不锈钢（防指纹处理）; 2.50*50*5镀锌方通、30*13*3镀锌方通、10mm玻镁板; 3.包含完成该项内容所有工作及费用并满足设计图纸、规范等要求; | D19: ㎡ | E19: 53.50305 | F19: 0 | G19: 0 | H19: =E19+F19+G19 -> 53.50305 | I19: =U19*$U$1 -> 110 | J19: =S19*(1+T19)*$S$1 -> 454.5 | K19: =(V19+W19)*$V$1 -> 183.525 | L19: =+SUM(I19:K19)*$L$3 -> 74.8025 | M19: =SUM(I19:L19) -> 822.8275 | N19: =H19*M19 -> 44023.781 | R19: =S19+S19*T19+U19+V19+W19 -> 748.025 | S19: 450 | T19: 0.01 | U19: 110 | V19: =7.85*3*5.5+3.5+25*2 -> 183.025 | W19: 0.5 | X19: =R19*H19 -> 40021.619
A20: =A19+1 -> 5 | B20: AM-01a 铝格栅吊顶 | C20: 1.AM-01a 铝格栅吊顶 2.5mm厚 2.包含但不限于钢龙骨; 3.铝格栅专用龙骨，Ø8钢筋吊杆，双向吊点中距900，与角钢焊接; 4.铝格栅规格：30*120*2.5@130mm; 5.阳极氧化处理; 6.包含完成该项内容所有工作及费用并满足设计图纸、规范等要求; | D20: ㎡ | E20: 24.92 | F20: 0 | G20: 0 | H20: =E20+F20+G20 -> 24.92 | I20: =U20*$U$1 -> 120 | J20: =S20*(1+T20)*$S$1 -> 714.07 | K20: =(V20+W20)*$V$1 -> 59.1 | L20: =+SUM(I20:K20)*$L$3 -> 89.317 | M20: =SUM(I20:L20) -> 982.487 | N20: =H20*M20 -> 24483.576 | P20: =1000/130 -> 7.6923077 | Q20: =0.36*255*7.7 -> 706.86 | R20: =S20+S20*T20+U20+V20+W20 -> 893.17 | S20: 707 | T20: 0.01 | U20: =15*8 -> 120 | V20: =1.8*4*8 -> 57.6 | W20: 1.5 | X20: =R20*H20 -> 22257.796
A21: =A20+1 -> 6 | B21: AM-01 铝格栅吊顶 | C21: 1.AM-01 铝格栅吊顶 2.0mm厚 2.铝格栅规格：20*30*2.0@60mm; 3.阳极氧化处理; 4.包含完成该项内容所有工作及费用并满足设计图纸、规范等要求; | D21: ㎡ | E21: 47.1025 | F21: 0 | G21: 0 | H21: =E21+F21+G21 -> 47.1025 | I21: =U21*$U$1 -> 135 | J21: =S21*(1+T21)*$S$1 -> 412.08 | K21: =(V21+W21)*$V$1 -> 80.7 | L21: =+SUM(I21:K21)*$L$3 -> 62.778 | M21: =SUM(I21:L21) -> 690.558 | N21: =H21*M21 -> 32527.008 | P21: =1000/80 -> 12.5 | Q21: =0.1*255*16 -> 408 | R21: =S21+S21*T21+U21+V21+W21 -> 627.78 | S21: 408 | T21: 0.01 | U21: 135 | V21: =1.8*4*11 -> 79.2 | W21: 1.5 | X21: =R21*H21 -> 29570.007
A22: =A21+1 -> 7 | B22: AM-01b 造型铝板 | C22: 1.AM-01b 铝板造型天花 2.0mm厚; 2.50*50*5镀锌方通基层、10mm玻镁板 3.氟碳喷涂处理; 4.按投影面积计算、包含完成该项内容所有工作及费用并满足设计图纸、规范等要求; | D22: ㎡ | E22: 3.075 | F22: 0 | G22: 0 | H22: =E22+F22+G22 -> 3.075 | I22: =U22*$U$1 -> 135 | J22: =S22*(1+T22)*$S$1 -> 257.55 | K22: =(V22+W22)*$V$1 -> 183.525 | L22: =+SUM(I22:K22)*$L$3 -> 57.6075 | M22: =SUM(I22:L22) -> 633.6825 | N22: =H22*M22 -> 1948.5737 | R22: =S22+S22*T22+U22+V22+W22 -> 576.075 | S22: 255 | T22: 0.01 | U22: 135 | V22: =7.85*3*5.5+3.5+25*2 -> 183.025 | W22: 0.5 | X22: =R22*H22 -> 1771.4306
A23: =A22+1 -> 8 | B23: AM-01b 铝板 | C23: 1.AM-01b 铝板天花 2.0mm厚铝板; 2.50*50*5镀锌方通基层、10mm玻镁板 3.氟碳喷涂处理; 4.按投影面积计算、包含完成该项内容所有工作及费用并满足设计图纸、规范等要求; | D23: ㎡ | E23: 27.74575 | F23: 0 | G23: 0 | H23: =E23+F23+G23 -> 27.74575 | I23: =U23*$U$1 -> 135 | J23: =S23*(1+T23)*$S$1 -> 257.55 | K23: =(V23+W23)*$V$1 -> 183.525 | L23: =+SUM(I23:K23)*$L$3 -> 57.6075 | M23: =SUM(I23:L23) -> 633.6825 | N23: =H23*M23 -> 17581.996 | R23: =S23+S23*T23+U23+V23+W23 -> 576.075 | S23: 255 | T23: 0.01 | U23: 135 | V23: =7.85*3*5.5+3.5+25*2 -> 183.025 | W23: 0.5 | X23: =R23*H23 -> 15983.633
A24: =A23+1 -> 9 | B24: AM-02 铝板 | C24: 1.AM-02 铝板天花 2.0mm厚; 2.50*50*5镀锌方通基层、10mm玻镁板 3.氟碳喷涂处理; 4.按投影面积计算、包含完成该项内容所有工作及费用并满足设计图纸、规范等要求; | D24: ㎡ | E24: 0.89 | F24: 0 | G24: 0 | H24: =E24+F24+G24 -> 0.89 | I24: =U24*$U$1 -> 135 | J24: =S24*(1+T24)*$S$1 -> 257.55 | K24: =(V24+W24)*$V$1 -> 183.525 | L24: =+SUM(I24:K24)*$L$3 -> 57.6075 | M24: =SUM(I24:L24) -> 633.6825 | N24: =H24*M24 -> 563.97743 | R24: =S24+S24*T24+U24+V24+W24 -> 576.075 | S24: 255 | T24: 0.01 | U24: 135 | V24: =7.85*3*5.5+3.5+25*2 -> 183.025 | W24: 0.5 | X24: =R24*H24 -> 512.70675
A25: =A24+1 -> 10 | B25: UP-01 防火软膜 | C25: 1.UP-01 防火软膜; 2.按投影面积计算; 3.包含完成该项内容所有工作及费用并满足设计图纸、规范等要求; | D25: ㎡ | E25: 45.4425 | F25: 0 | G25: 0 | H25: =E25+F25+G25 -> 45.4425 | I25: =U25*$U$1 -> 80 | J25: =S25*(1+T25)*$S$1 -> 222.2 | K25: =(V25+W25)*$V$1 -> 37.3 | L25: =+SUM(I25:K25)*$L$3 -> 33.95 | M25: =SUM(I25:L25) -> 373.45 | N25: =H25*M25 -> 16970.502 | Q25: =_xlfn.DISPIMG("ID_5A9B51545E5149F599533FEFAF59B259",1) -> =DISPIMG("ID_5A9B51545E5149F599533FEFAF59B259",1) | R25: =S25+S25*T25+U25+V25+W25 -> 339.5 | S25: 220 | T25: 0.01 | U25: 80 | V25: =28.5+8.5 -> 37 | W25: 0.3 | X25: =R25*H25 -> 15427.729
A26: =A25+1 -> 11 | B26: 超白磨砂亚克力 | C26: 1.5mm超白磨砂亚克力; 2.包含完成该项内容所有工作及费用并满足设计图纸、规范等要求; | D26: ㎡ | E26: 2.0916 | F26: 0 | G26: 0 | H26: =E26+F26+G26 -> 2.0916 | I26: =U26*$U$1 -> 65 | J26: =S26*(1+T26)*$S$1 -> 186.85 | K26: =(V26+W26)*$V$1 -> 15.5 | L26: =+SUM(I26:K26)*$L$3 -> 26.735 | M26: =SUM(I26:L26) -> 294.085 | N26: =H26*M26 -> 615.10819 | R26: =S26+S26*T26+U26+V26+W26 -> 267.35 | S26: 185 | T26: 0.01 | U26: 65 | V26: 15 | W26: 0.5 | X26: =R26*H26 -> 559.18926
A27: =A26+1 -> 12 | B27: PT-01 原顶涂料 | C27: 1.PT-01 原顶涂料 2.一底两面无机涂料饰面层(颜色以图纸标注为准）; 3.2mm厚无机涂料配套的腻子粉调浆满批并打磨平整; 4.包含完成该项内容所有工作及费用并满足设计图纸、规范等要求; | D27: ㎡ | E27: 452.38495 | F27: 312.14345 | G27: 312.14345 | H27: =E27+F27+G27 -> 1076.6718 | I27: =U27*$U$1 -> 22.5 | J27: =S27*(1+T27)*$S$1 -> 5.555 | K27: =(V27+W27)*$V$1 -> 6.18 | L27: =+SUM(I27:K27)*$L$3 -> 3.4235 | M27: =SUM(I27:L27) -> 37.6585 | N27: =H27*M27 -> 40545.847 | R27: =S27+S27*T27+U27+V27+W27 -> 34.235 | S27: 5.5 | T27: 0.01 | U27: 22.5 | V27: 5.98 | W27: 0.2 | X27: =R27*H27 -> 36859.861
A28: =A27+1 -> 13 | B28: PT-05 涂料 | C28: 1.PT-05 涂料（包含PT-01线条）; 2.一底两面无机涂料饰面层(颜色以图纸标注为准）; 3.2mm厚无机涂料配套的腻子粉调浆满批并打磨平整; 4.包含完成该项内容所有工作及费用并满足设计图纸、规范等要求; | D28: ㎡ | E28: 2.933 | F28: 0 | G28: 0 | H28: =E28+F28+G28 -> 2.933 | I28: =U28*$U$1 -> 22.5 | J28: =S28*(1+T28)*$S$1 -> 5.555 | K28: =(V28+W28)*$V$1 -> 6.18 | L28: =+SUM(I28:K28)*$L$3 -> 3.4235 | M28: =SUM(I28:L28) -> 37.6585 | N28: =H28*M28 -> 110.45238 | R28: =S28+S28*T28+U28+V28+W28 -> 34.235 | S28: 5.5 | T28: 0.01 | U28: 22.5 | V28: 5.98 | W28: 0.2 | X28: =R28*H28 -> 100.41125
A29: =A28+1 -> 14 | B29: AM-02 L型铝板灯槽(450宽) | C29: 1.L型铝板灯槽 2.0mm厚（展开面：1500mm）; 2.氟碳喷涂处理; 3.双层10mm玻镁板基底; 4.镀锌方通规格：50*50*5mm; 5.包含完成该项内容所有工作及费用并满足设计图纸、规范等要求; | D29: m2 | E29: 38.86 | F29: 0 | G29: 0 | H29: =E29+F29+G29 -> 38.86 | I29: =U29*$U$1 -> 135 | J29: =S29*(1+T29)*$S$1 -> 257.55 | K29: =(V29+W29)*$V$1 -> 183.525 | L29: =+SUM(I29:K29)*$L$3 -> 57.6075 | M29: =SUM(I29:L29) -> 633.6825 | N29: =H29*M29 -> 24624.902 | R29: =S29+S29*T29+U29+V29+W29 -> 576.075 | S29: 255 | T29: 0.01 | U29: 135 | V29: =7.85*3*5.5+3.5+25*2 -> 183.025 | W29: 0.5 | X29: =R29*H29 -> 22386.274
A30: =A29+1 -> 15 | B30: AM-02 L型铝板灯槽(650宽) | C30: 1.L型铝板灯槽 2.0mm厚（展开面：1900mm）; 2.氟碳喷涂处理; 3.双层10mm玻镁板基底; 4.镀锌方通规格：50*50*5mm; 5.包含完成该项内容所有工作及费用并满足设计图纸、规范等要求; | D30: m2 | E30: 4.459 | F30: 0 | G30: 0 | H30: =E30+F30+G30 -> 4.459 | I30: =U30*$U$1 -> 135 | J30: =S30*(1+T30)*$S$1 -> 257.55 | K30: =(V30+W30)*$V$1 -> 183.525 | L30: =+SUM(I30:K30)*$L$3 -> 57.6075 | M30: =SUM(I30:L30) -> 633.6825 | N30: =H30*M30 -> 2825.5903 | R30: =S30+S30*T30+U30+V30+W30 -> 576.075 | S30: 255 | T30: 0.01 | U30: 135 | V30: =7.85*3*5.5+3.5+25*2 -> 183.025 | W30: 0.5 | X30: =R30*H30 -> 2568.7184
A31: =A30+1 -> 16 | B31: AM-02 L型铝板灯槽(850宽) | C31: 1.L型铝板灯槽 2.0mm厚（展开面：2300mm）; 2.氟碳喷涂处理; 3.双层10mm玻镁板基底; 4.镀锌方通规格：50*50*5mm; 5.包含完成该项内容所有工作及费用并满足设计图纸、规范等要求; | D31: m2 | E31: 5.831 | F31: 0 | G31: 0 | H31: =E31+F31+G31 -> 5.831 | I31: =U31*$U$1 -> 135 | J31: =S31*(1+T31)*$S$1 -> 257.55 | K31: =(V31+W31)*$V$1 -> 183.525 | L31: =+SUM(I31:K31)*$L$3 -> 57.6075 | M31: =SUM(I31:L31) -> 633.6825 | N31: =H31*M31 -> 3695.0027 | R31: =S31+S31*T31+U31+V31+W31 -> 576.075 | S31: 255 | T31: 0.01 | U31: 135 | V31: =7.85*3*5.5+3.5+25*2 -> 183.025 | W31: 0.5 | X31: =R31*H31 -> 3359.0933
A32: =A31+1 -> 17 | B32: AM-02 铝板灯槽 | C32: 1.AM-02 铝板灯槽 2.0mm厚（高250mm*宽80mm）; 2.氟碳喷涂处理; 3.5mm超白亚克力 4.吊件、10mm丝杆、20*40*3镀锌方通、50*50*5镀锌角钢 5.吊件具体高度及距离以现场为准 6.包含完成该项内容所有工作及费用并满足设计图纸、规范等要求; | D32: m | E32: 0 | F32: 136.588 | G32: 136.588 | H32: =E32+F32+G32 -> 273.176 | I32: =U32*$U$1 -> 55 | J32: =S32*(1+T32)*$S$1 -> 167.4075 | K32: =(V32+W32)*$V$1 -> 107.65 | L32: =+SUM(I32:K32)*$L$3 -> 33.00575 | M32: =SUM(I32:L32) -> 363.06325 | N32: =H32*M32 -> 99180.166 | Q32: =_xlfn.DISPIMG("ID_804D414A39A44E389CF75EFDA0C8509A",1) -> =DISPIMG("ID_804D414A39A44E389CF75EFDA0C8509A",1) | R32: =S32+S32*T32+U32+V32+W32 -> 330.0575 | S32: =255*0.65 -> 165.75 | T32: 0.01 | U32: 55 | V32: =5.5*7.85*2+5.5+15 -> 106.85 | W32: 0.8 | X32: =R32*H32 -> 90163.788
A33: 二 | B33: 合计 | N33: =N5 -> 546442.36

Sheet 地库装饰工程量清单
A1: 珠海丹田海德地库项目装修工程量清单 | S1: 1 | U1: 1 | V1: 1
A2: 序号 | B2: 项目名称 | C2: 项目特征 | D2: 单位 | E2: -1层工程量 | F2: -2层工程量 | G2: -3层工程量 | H2: 合计工程量 | I2: 人工 | J2: 主材 | K2: 辅材及机械费 | L2: 管理及利润取费 | M2: 综合单价（不含税） | N2: 合价（不含税） | O2: 备注 | R2: 成本单价 | S2: 主材 | T2: 损耗率 | U2: 人工 | V2: 辅材 | W2: 机械 | X2: 合价
I3: A | J3: B | K3: C | L3: =坡道装饰工程量清单!$L$3 -> 0.1 | M3: E=A+B+C+D | N3: F=E*工程量
L4: D=(A+B+C)*费率
A5: 一 | B5: 地库 | N5: =+N6+N22+N29 -> 2344307.6
B6: 墙柱面工程 | N6: =SUM(N7:N21) -> 718486.24
A7: 1 | B7: PT-01 涂料 | C7: 1.PT-01 涂料一道; 2.内墙涂料一道; 3.封闭底涂料一道; 4.刮腻子两遍; 5.包含完成该项内容所有工作及费用并满足设计图纸、规范等要求; | D7: ㎡ | E7: 756.449 | F7: 802.275 | G7: 850.308 | H7: =E7+F7+G7 -> 2409.032 | I7: =坡道装饰工程量清单!$I$7 -> 22.5 | J7: =坡道装饰工程量清单!$J$7 -> 5.555 | K7: =坡道装饰工程量清单!$K$7 -> 6.18 | L7: =+SUM(I7:K7)*$L$3 -> 3.4235 | M7: =SUM(I7:L7) -> 37.6585 | N7: =H7*M7 -> 90720.532 | R7: =S7+S7*T7+U7+V7+W7 -> 0 | X7: =R7*H7 -> 0
A8: =A7+1 -> 2 | B8: PT-02 涂料 | C8: 1.PT-01 涂料一道; 2.内墙涂料一道; 3.封闭底涂料一道; 4.刮腻子两遍; 5.含成品U型收口条 6.包含完成该项内容所有工作及费用并满足设计图纸、规范等要求; | D8: ㎡ | E8: =1848.398-E9 -> 1727.438 | F8: 1994.297 | G8: 2180.445 | H8: =E8+F8+G8 -> 5902.18 | I8: =坡道装饰工程量清单!$I$7 -> 22.5 | J8: =坡道装饰工程量清单!$J$7 -> 5.555 | K8: =坡道装饰工程量清单!$K$7 -> 6.18 | L8: =+SUM(I8:K8)*$L$3 -> 3.4235 | M8: =SUM(I8:L8) -> 37.6585 | N8: =H8*M8 -> 222267.25 | R8: =S8+S8*T8+U8+V8+W8 -> 0 | X8: =R8*H8 -> 0
A9: =A8+1 -> 3 | B9: PT-07 涂料 | C9: 1.PT-07 涂料一道; 2.内墙涂料一道; 3.封闭底涂料一道; 4.刮腻子两遍; 5.包含完成该项内容所有工作及费用并满足设计图纸、规范等要求; | D9: ㎡ | E9: =84*0.6*2.4 -> 120.96 | F9: 0 | G9: 0 | H9: =E9+F9+G9 -> 120.96 | I9: =坡道装饰工程量清单!$I$7 -> 22.5 | J9: =坡道装饰工程量清单!$J$7 -> 5.555 | K9: =坡道装饰工程量清单!$K$7 -> 6.18 | L9: =+SUM(I9:K9)*$L$3 -> 3.4235 | M9: =SUM(I9:L9) -> 37.6585 | N9: =H9*M9 -> 4555.1722 | R9: =S9+S9*T9+U9+V9+W9 -> 0 | X9: =R9*H9 -> 0
A10: =A8+1 -> 3 | B10: 玻镁板墙面 | C10: 1.玻镁板墙面; 2.9mm阻燃夹板+10mm玻镁板; 3.镀锌方通50*50*5mm; 4.包含完成该项内容所有工作及费用并满足设计图纸、规范等要求; | D10: ㎡ | E10: 25.014 | F10: 24.98 | G10: 39.129 | H10: =E10+F10+G10 -> 89.123 | I10: =U10*$U$1 -> 75 | J10: =S10*(1+T10)*$S$1 -> 50.5 | K10: =(V10+W10)*$V$1 -> 122.75 | L10: =+SUM(I10:K10)*$L$3 -> 24.825 | M10: =SUM(I10:L10) -> 273.075 | N10: =H10*M10 -> 24337.263 | R10: =S10+S10*T10+U10+V10+W10 -> 248.25 | S10: =25*2 -> 50 | T10: 0.01 | U10: =35+20*2 -> 75 | V10: =5.5*20.5+8.5 -> 121.25 | W10: 1.5 | X10: =R10*H10 -> 22124.785
A11: =A10+1 -> 4 | B11: ST-04 石材湿贴 | C11: 1.ST-04 石材湿贴 25厚; 2.石材专用胶、双层10mm玻镁板; 3.50*50*5镀锌方通 4.石材六面防水、防污处理、背筋; 5.包含完成该项内容所有工作及费用并满足设计图纸、规范等要求; | D11: ㎡ | E11: =97.137-E13 -> 60.09 | F11: =89.643-F13 -> 51.019 | G11: =114.003-G13 -> 76.944 | H11: =E11+F11+G11 -> 188.053 | I11: =U11*$U$1 -> 125 | J11: =S11*(1+T11)*$S$1 -> 454.5 | K11: =(V11+W11)*$V$1 -> 80.3 | L11: =+SUM(I11:K11)*$L$3 -> 65.98 | M11: =SUM(I11:L11) -> 725.78 | N11: =H11*M11 -> 136485.11 | R11: =S11+S11*T11+U11+V11+W11 -> 659.8 | S11: 450 | T11: 0.01 | U11: =20*2+85 -> 125 | V11: =25*2+1.5*8+16.8 -> 78.8 | W11: 1.5 | X11: =R11*H11 -> 124077.37
A12: =A11+1 -> 5 | B12: ST-04a 石材湿贴 | C12: 1.ST-04a 石材湿贴 25厚（毛面）; 2.石材专用胶、双层10mm玻镁板; 3.50*50*5镀锌方通 4.石材六面防水、防污处理、背筋; 5.包含完成该项内容所有工作及费用并满足设计图纸、规范等要求; | D12: ㎡ | E12: =28.34-E14 -> 17.001 | F12: =25.762-F14 -> 14.427 | G12: =33.071-G14 -> 21.735 | H12: =E12+F12+G12 -> 53.163 | I12: =U12*$U$1 -> 125 | J12: =S12*(1+T12)*$S$1 -> 585.8 | K12: =(V12+W12)*$V$1 -> 80.3 | L12: =+SUM(I12:K12)*$L$3 -> 79.11 | M12: =SUM(I12:L12) -> 870.21 | N12: =H12*M12 -> 46262.974 | R12: =S12+S12*T12+U12+V12+W12 -> 791.1 | S12: 580 | T12: 0.01 | U12: =20*2+85 -> 125 | V12: =25*2+1.5*8+16.8 -> 78.8 | W12: 1.5 | X12: =R12*H12 -> 42057.249
A13: =A12+1 -> 6 | B13: ST-04 石材干挂 | C13: 1.ST-04 石材干挂 25厚; 2.不锈钢石材挂件; 3.30*30*3镀锌方通 4.石材六面防水、防污处理、背筋; 5.包含完成该项内容所有工作及费用并满足设计图纸、规范等要求; | D13: ㎡ | E13: 37.047 | F13: 38.624 | G13: 37.059 | H13: =E13+F13+G13 -> 112.73 | I13: =U13*$U$1 -> 150 | J13: =S13*(1+T13)*$S$1 -> 472.5 | K13: =(V13+W13)*$V$1 -> 113.55 | L13: =+SUM(I13:K13)*$L$3 -> 73.605 | M13: =SUM(I13:L13) -> 809.655 | N13: =H13*M13 -> 91272.408 | R13: =S13+S13*T13+U13+V13+W13 -> 736.05 | S13: 450 | T13: 0.05 | U13: 150 | V13: =15.5*5.5+4*3.5+4*1+8.5 -> 111.75 | W13: 1.8 | X13: =R13*H13 -> 82974.917
A14: =A13+1 -> 7 | B14: ST-04a 石材干挂 | C14: 1.ST-04a 石材湿贴 25厚（毛面）; 2.不锈钢石材挂件; 3.30*30*3镀锌方通; 4.石材拉槽、六面防水、防污处理、背筋; 5.包含完成该项内容所有工作及费用并满足设计图纸、规范等要求; | D14: ㎡ | E14: 11.339 | F14: 11.335 | G14: 11.336 | H14: =E14+F14+G14 -> 34.01 | I14: =U14*$U$1 -> 150 | J14: =S14*(1+T14)*$S$1 -> 609 | K14: =(V14+W14)*$V$1 -> 113.55 | L14: =+SUM(I14:K14)*$L$3 -> 87.255 | M14: =SUM(I14:L14) -> 959.805 | N14: =H14*M14 -> 32642.968 | Q14: =_xlfn.DISPIMG("ID_775DD9E8F501476888EF6E21280FECA3",1) -> =DISPIMG("ID_775DD9E8F501476888EF6E21280FECA3",1) | R14: =S14+S14*T14+U14+V14+W14 -> 872.55 | S14: 580 | T14: 0.05 | U14: 150 | V14: =15.5*5.5+4*3.5+4*1+8.5 -> 111.75 | W14: 1.8 | X14: =R14*H14 -> 29675.426
A15: =A14+1 -> 8 | B15: CT-03 瓷砖600*600mm | C15: 1.CT-03 瓷砖600*600mm; 2.瓷砖专用胶; 3.水泥砂浆找平层; 4.包含完成该项内容所有工作及费用并满足设计图纸、规范等要求; | D15: ㎡ | E15: 27.155 | F15: 0 | G15: 0 | H15: =E15+F15+G15 -> 27.155 | I15: =U15*$U$1 -> 45 | J15: =S15*(1+T15)*$S$1 -> 45 | K15: =(V15+W15)*$V$1 -> 17 | L15: =+SUM(I15:K15)*$L$3 -> 10.7 | M15: =SUM(I15:L15) -> 117.7 | N15: =H15*M15 -> 3196.1435 | R15: =S15+S15*T15+U15+V15+W15 -> 107 | S15: 45 | T15: 0 | U15: =45 -> 45 | V15: =16.5 -> 16.5 | W15: 0.5 | X15: =R15*H15 -> 2905.585
A16: =A15+1 -> 9 | B16: MT-02 50宽金属线条（展开面：120mm） | C16: 1.MT-02 50宽金属线条 1.2mm厚拉丝不锈钢（防指纹处理） 2.展开面：120mm; 3.包含完成该项内容所有工作及费用并满足设计图纸、规范等要求; | D16: m | E16: =1.85*6 -> 11.1 | F16: =1.85*6 -> 11.1 | G16: =1.85*6 -> 11.1 | H16: =E16+F16+G16 -> 33.3 | I16: =U16*$U$1 -> 15 | J16: =S16*(1+T16)*$S$1 -> 58.195 | K16: =(V16+W16)*$V$1 -> 3.8 | L16: =+SUM(I16:K16)*$L$3 -> 7.6995 | M16: =SUM(I16:L16) -> 84.6945 | N16: =H16*M16 -> 2820.3268 | R16: =S16+S16*T16+U16+V16+W16 -> 76.995 | S16: =450*0.12+2.5 -> 56.5 | T16: 0.03 | U16: 15 | V16: 3.5 | W16: 0.3 | X16: =R16*H16 -> 2563.9335
A17: =A16+1 -> 10 | B17: MT-02 10宽金属线条（展开面：65mm） | C17: 1.MT-02 10宽金属线条 1.2mm厚拉丝不锈钢（防指纹处理）; 2.展开面：65mm 3.包含完成该项内容所有工作及费用并满足设计图纸、规范等要求; | D17: m | E17: =E21-((515+1505)*3+515+1071)*0.001 -> 51.032 | F17: =F21-((515+1505)*2+(515+1071)*2)*0.001 -> 47.079 | G17: =G21-((515+1505)*3+515+1071)*0.001 -> 59.426 | H17: =E17+F17+G17 -> 157.537 | I17: =U17*$U$1 -> 15 | J17: =S17*(1+T17)*$S$1 -> 32.7025 | K17: =(V17+W17)*$V$1 -> 3.8 | L17: =+SUM(I17:K17)*$L$3 -> 5.15025 | M17: =SUM(I17:L17) -> 56.65275 | N17: =H17*M17 -> 8924.9043 | R17: =S17+S17*T17+U17+V17+W17 -> 51.5025 | S17: =450*0.065+2.5 -> 31.75 | T17: 0.03 | U17: 15 | V17: 3.5 | W17: 0.3 | X17: =R17*H17 -> 8113.5493
A18: =A17+1 -> 11 | B18: MT-02 瓷砖位金属收口线条（展开面：55mm） | C18: 1.MT-02 瓷砖位金属收口线条 1.2mm厚拉丝不锈钢（防指纹处理）; 2.展开面：55mm 3.包含完成该项内容所有工作及费用并满足设计图纸、规范等要求; | D18: m | E18: =2.45*4+(1.025+0.1+2.675+2.025+0.1+0.4+1.76+0.9+0.36+1.525) -> 20.67 | F18: 0 | G18: 0 | H18: =E18+F18+G18 -> 20.67 | I18: =U18*$U$1 -> 15 | J18: =S18*(1+T18)*$S$1 -> 28.0675 | K18: =(V18+W18)*$V$1 -> 3.8 | L18: =+SUM(I18:K18)*$L$3 -> 4.68675 | M18: =SUM(I18:L18) -> 51.55425 | N18: =H18*M18 -> 1065.6263 | R18: =S18+S18*T18+U18+V18+W18 -> 46.8675 | S18: =450*0.055+2.5 -> 27.25 | T18: 0.03 | U18: 15 | V18: 3.5 | W18: 0.3 | X18: =R18*H18 -> 968.75122
A19: =A18+1 -> 12 | B19: MT-02 金属饰面 | C19: 1.MT-02 金属饰面 1.2mm厚拉丝不锈钢（防指纹处理）; 2.30*30*3镀锌方通支架; 3.双层10mm玻镁板基底; 4.包含完成该项内容所有工作及费用并满足设计图纸、规范等要求; | D19: ㎡ | E19: 2.267 | F19: 2.134 | G19: 2.265 | H19: =E19+F19+G19 -> 6.666 | I19: =坡道装饰工程量清单!I12 -> 85 | J19: =坡道装饰工程量清单!J12 -> 454.5 | K19: =坡道装饰工程量清单!K12 -> 72.2 | L19: =+SUM(I19:K19)*$L$3 -> 61.17 | M19: =SUM(I19:L19) -> 672.87 | N19: =H19*M19 -> 4485.3514 | R19: =S19+S19*T19+U19+V19+W19 -> 0 | X19: =R19*H19 -> 0
A20: =A19+1 -> 13 | B20: CH-03a 地坪漆踢脚线：H50mm | C20: 1.CH-03a 地坪漆踢脚线：H50mm; 2.包含完成该项内容所有工作及费用并满足设计图纸、规范等要求; | D20: m | E20: 773.011 | F20: 825.66 | G20: 891.777 | H20: =E20+F20+G20 -> 2490.448 | I20: =坡道装饰工程量清单!I11 -> 10 | J20: =坡道装饰工程量清单!J11 -> 2.525 | K20: =坡道装饰工程量清单!K11 -> 1.3 | L20: =+SUM(I20:K20)*$L$3 -> 1.3825 | M20: =SUM(I20:L20) -> 15.2075 | N20: =H20*M20 -> 37873.488 | R20: =S20+S20*T20+U20+V20+W20 -> 0 | X20: =R20*H20 -> 0
A21: =A20+1 -> 14 | B21: MT-01 暗装金属踢脚 | C21: 1.MT-01 暗装金属踢脚 H50mm（展开面：80mm） 2.10mm玻镁板 3.包含完成该项内容所有工作及费用并满足设计图纸、规范等要求; | D21: m | E21: 58.678 | F21: 54.291 | G21: 67.072 | H21: =E21+F21+G21 -> 180.041 | I21: =U21*$U$1 -> 15 | J21: =S21*(1+T21)*$S$1 -> 39.655 | K21: =(V21+W21)*$V$1 -> 3.8 | L21: =+SUM(I21:K21)*$L$3 -> 5.8455 | M21: =SUM(I21:L21) -> 64.3005 | N21: =H21*M21 -> 11576.726 | R21: =S21+S21*T21+U21+V21+W21 -> 58.455 | S21: =450*0.08+2.5 -> 38.5 | T21: 0.03 | U21: 15 | V21: 3.5 | W21: 0.3 | X21: =R21*H21 -> 10524.297
B22: 天花工程 | N22: =SUM(N23:N28) -> 1543983.6
A23: 1 | B23: AM-03 铝板造型天花 | C23: 1.AM-03 铝板造型天花 2.5mm厚; 2.50*50*5镀锌方通基层、10mm玻镁板 3.氟碳喷涂处理; 4.按投影面积计算、包含完成该项内容所有工作及费用并满足设计图纸、规范等要求; | D23: m2 | E23: 114.15 | F23: 109.094 | G23: 113.278 | H23: =E23+F23+G23 -> 336.522 | I23: =U23*$U$1 -> 135 | J23: =S23*(1+T23)*$S$1 -> 296.1825 | K23: =(V23+W23)*$V$1 -> 183.525 | L23: =+SUM(I23:K23)*$L$3 -> 61.47075 | M23: =SUM(I23:L23) -> 676.17825 | N23: =H23*M23 -> 227548.86 | P23: =_xlfn.DISPIMG("ID_694C49779BC14336B1D5102133D742CD",1) -> =DISPIMG("ID_694C49779BC14336B1D5102133D742CD",1) | R23: =S23+S23*T23+U23+V23+W23 -> 614.7075 | S23: =255*1.15 -> 293.25 | T23: 0.01 | U23: 135 | V23: =7.85*3*5.5+3.5+25*2 -> 183.025 | W23: 0.5 | X23: =R23*H23 -> 206862.6
A24: 2 | B24: 玻镁板侧板 | C24: 1.双层玻镁板侧板; 2.按投影面积计算、包含完成该项内容所有工作及费用并满足设计图纸、规范等要求; | D24: m2 | E24: =1.32*(4.6*2+8.1+4.6*2+7.66+3.7*2+6.91+3.7*2+7.81) -> 84.0576 | F24: =0.93*(4.6*2+8.1+4.6*2+7.66+3.34*2+6.1+3.7*2+7.81) -> 57.7995 | G24: =1.03*(4.585*2+8.1+4.585*2+7.638+4.34*2+6.13+3.69*2+7.785) -> 65.97459 | H24: =E24+F24+G24 -> 207.83169 | I24: =U24*$U$1 -> 75 | J24: =S24*(1+T24)*$S$1 -> 0 | K24: =(V24+W24)*$V$1 -> 189.525 | L24: =+SUM(I24:K24)*$L$3 -> 26.4525 | M24: =SUM(I24:L24) -> 290.9775 | N24: =H24*M24 -> 60474.346 | R24: =S24+S24*T24+U24+V24+W24 -> 264.525 | S24: 0 | T24: 0 | U24: =35+20*2 -> 75 | V24: =7.85*3*5.5+25*2+8.5 -> 188.025 | W24: 1.5 | X24: =R24*H24 -> 54976.678
A25: 3 | B25: AM-03 铝板天花 | C25: 1.AM-03 铝板天花 2.0mm厚; 2.10mm玻镁板; 3.60系轻钢龙骨、Ø8全螺吊杆; 4.氟碳喷涂处理; 5.按投影面积计算、包含完成该项内容所有工作及费用并满足设计图纸、规范等要求; | D25: m2 | E25: 177.723 | F25: 152.639 | G25: 171.45 | H25: =E25+F25+G25 -> 501.812 | I25: =U25*$U$1 -> 135 | J25: =S25*(1+T25)*$S$1 -> 257.55 | K25: =(V25+W25)*$V$1 -> 158.525 | L25: =+SUM(I25:K25)*$L$3 -> 55.1075 | M25: =SUM(I25:L25) -> 606.1825 | N25: =H25*M25 -> 304189.65 | R25: =S25+S25*T25+U25+V25+W25 -> 551.075 | S25: 255 | T25: 0.01 | U25: 135 | V25: =7.85*3*5.5+3.5+25 -> 158.025 | W25: 0.5 | X25: =R25*H25 -> 276536.05
A26: 4 | B26: AM-02 铝板天花（防火卷帘收口） | C26: 1.AM-02 铝板天花 2.0mm厚（防火卷帘收口）; 2.氟碳喷涂处理; 3.30*30*3镀锌方通、10mm玻镁板; 4.包含完成该项内容所有工作及费用并满足设计图纸、规范等要求; | D26: m2 | E26: =(0.5+0.1)*2*(5.1+5.1+4.6+3.6+4.6+5.1+5.1) -> 39.84 | F26: =(0.5+0.1)*2*(5.1+5.1+4.6+4.1+3.6+4.6+5.1+4.1+5.1) -> 49.68 | G26: =(0.5+0.1)*2*(4.6+5.1+4.6+4.1+3.6+5.1+4.6+4.6+5.1+5.1+3.6) -> 60.12 | H26: =E26+F26+G26 -> 149.64 | I26: =U26*$U$1 -> 135 | J26: =S26*(1+T26)*$S$1 -> 257.55 | K26: =(V26+W26)*$V$1 -> 158.525 | L26: =+SUM(I26:K26)*$L$3 -> 55.1075 | M26: =SUM(I26:L26) -> 606.1825 | N26: =H26*M26 -> 90709.149 | R26: =S26+S26*T26+U26+V26+W26 -> 551.075 | S26: 255 | T26: 0.01 | U26: 135 | V26: =7.85*3*5.5+3.5+25 -> 158.025 | W26: 0.5 | X26: =R26*H26 -> 82462.863
A27: 5 | B27: AM-02 铝板灯槽 | C27: 1.AM-02 铝板灯槽 2.0mm厚（高250mm*宽80mm）; 2.氟碳喷涂处理; 3.5mm超白亚克力 4.吊件、10mm丝杆、20*40*3镀锌方通、50*50*5镀锌角钢 5.吊件具体高度及距离以现场为准 6.包含完成该项内容所有工作及费用并满足设计图纸、规范等要求; | D27: m | E27: 453.839 | F27: 460.958 | G27: 492.778 | H27: =E27+F27+G27 -> 1407.575 | I27: =坡道装饰工程量清单!I32 -> 55 | J27: =坡道装饰工程量清单!J32 -> 167.4075 | K27: =坡道装饰工程量清单!K32 -> 107.65 | L27: =+SUM(I27:K27)*$L$3 -> 33.00575 | M27: =SUM(I27:L27) -> 363.06325 | N27: =H27*M27 -> 511038.75 | Q27: =_xlfn.DISPIMG("ID_804D414A39A44E389CF75EFDA0C8509A",1) -> =DISPIMG("ID_804D414A39A44E389CF75EFDA0C8509A",1) | R27: =S27+S27*T27+U27+V27+W27 -> 0 | X27: =R27*H27 -> 0
A28: 6 | B28: PT-01 原顶涂料（投影面计算） | C28: 1.PT-01 原顶涂料（投影面计算）; 2.一底两面无机涂料饰面层(颜色以图纸标注为准）; 3.2mm厚无机涂料配套的腻子粉调浆满批并打磨平整; 4.包含完成该项内容所有工作及费用并满足设计图纸、规范等要求; | D28: m2 | E28: =3172.22-E23-E25+E24 -> 2964.4046 | F28: =3171.825-F23-F25+F24 -> 2967.8915 | G28: =3581.113-G23-G25+G24 -> 3362.3596 | H28: =E28+F28+G28 -> 9294.6557 | I28: =坡道装饰工程量清单!I27 -> 22.5 | J28: =坡道装饰工程量清单!J27 -> 5.555 | K28: =坡道装饰工程量清单!K27 -> 6.18 | L28: =+SUM(I28:K28)*$L$3 -> 3.4235 | M28: =SUM(I28:L28) -> 37.6585 | N28: =H28*M28 -> 350022.79 | R28: =S28+S28*T28+U28+V28+W28 -> 0 | X28: =R28*H28 -> 0
B29: 其它工程 | N29: =SUM(N30:N39) -> 81837.788 | R29: =S29+S29*T29+U29+V29+W29 -> 0 | X29: =R29*H29 -> 0
A30: 1 | B30: 消防栓暗门：800*2210mm | C30: 1.消防栓暗门：800*2210mm; 2.10mm玻镁板基底; 3.包含一切安装所需的配件及辅材，不包含涂料; | D30: 樘 | E30: 1 | F30: 1 | G30: 1 | H30: =E30+F30+G30 -> 3 | I30: =U30*$U$1 -> 291.72 | J30: =S30*(1+T30)*$S$1 -> 0 | K30: =(V30+W30)*$V$1 -> 626.79639 | L30: =+SUM(I30:K30)*$L$3 -> 91.851639 | M30: =SUM(I30:L30) -> 1010.368 | N30: =H30*M30 -> 3031.1041 | R30: =S30+S30*T30+U30+V30+W30 -> 918.51639 | S30: 0 | T30: 0 | U30: =165*0.8*2.21 -> 291.72 | V30: =((27.3*5+30*2+25+25+16.5)/(0.87*1.14)+33.5+55)*0.8*2.21 -> 625.29639 | W30: 1.5 | X30: =R30*H30 -> 2755.5492
A31: =A30+1 -> 2 | B31: 消防栓石材暗门：700*2150mm | C31: 1.消防栓石材暗门：700*2150mm; 2.大理石石材ST-04/ST-04a干挂; 3.石材加工; 4.包含一切安装所需的配件及辅材; | D31: 樘 | E31: 1 | F31: 1 | G31: 0 | H31: =E31+F31+G31 -> 2 | I31: =U31*$U$1 -> 376.25 | J31: =S31*(1+T31)*$S$1 -> 722.4 | K31: =(V31+W31)*$V$1 -> 533.78002 | L31: =+SUM(I31:K31)*$L$3 -> 163.243 | M31: =SUM(I31:L31) -> 1795.673 | N31: =H31*M31 -> 3591.346 | R31: =S31+S31*T31+U31+V31+W31 -> 1632.43 | S31: =480*0.7*2.15 -> 722.4 | T31: 0 | U31: =250*0.7*2.15 -> 376.25 | V31: =((27.3*5+30*2+25+25+16.5)/(0.87*1.14)+33.5+55)*0.7*2.15 -> 532.28002 | W31: 1.5 | X31: =R31*H31 -> 3264.86
A32: =A31+1 -> 3 | B32: 消防栓石材暗门：800*2210mm | C32: 1.消防栓石材暗门：800*2210mm; 2.大理石石材ST-04/ST-04a干挂; 3.石材加工; 4.包含一切安装所需的配件及辅材; | D32: 樘 | E32: 3 | F32: 3 | G32: 1 | H32: =E32+F32+G32 -> 7 | I32: =U32*$U$1 -> 442 | J32: =S32*(1+T32)*$S$1 -> 848.64 | K32: =(V32+W32)*$V$1 -> 626.79639 | L32: =+SUM(I32:K32)*$L$3 -> 191.74364 | M32: =SUM(I32:L32) -> 2109.18 | N32: =H32*M32 -> 14764.26 | R32: =S32+S32*T32+U32+V32+W32 -> 1917.4364 | S32: =480*0.8*2.21 -> 848.64 | T32: 0 | U32: =250*0.8*2.21 -> 442 | V32: =((27.3*5+30*2+25+25+16.5)/(0.87*1.14)+33.5+55)*0.8*2.21 -> 625.29639 | W32: 1.5 | X32: =R32*H32 -> 13422.055
A33: =A32+1 -> 4 | B33: 工具间石材暗门：1300*2200mm | C33: 1.工具间石材暗门：1300*2200mm; 2.大理石石材ST-04/ST-04a干挂; 3.石材加工; 4.包含一切安装所需的配件及辅材; | D33: 樘 | E33: 0 | F33: 2 | G33: 0 | H33: =E33+F33+G33 -> 2 | I33: =U33*$U$1 -> 715 | J33: =S33*(1+T33)*$S$1 -> 1372.8 | K33: =(V33+W33)*$V$1 -> 1013.0089 | L33: =+SUM(I33:K33)*$L$3 -> 310.08089 | M33: =SUM(I33:L33) -> 3410.8898 | N33: =H33*M33 -> 6821.7795 | R33: =S33+S33*T33+U33+V33+W33 -> 3100.8089 | S33: =480*1.3*2.2 -> 1372.8 | T33: 0 | U33: =250*1.3*2.2 -> 715 | V33: =((27.3*5+30*2+25+25+16.5)/(0.87*1.14)+33.5+55)*1.3*2.2 -> 1011.5089 | W33: 1.5 | X33: =R33*H33 -> 6201.6177
A34: =A33+1 -> 5 | B34: 电井门石材暗门：900*2210mm | C34: 1.电井门石材暗门：900*2210mm; 2.大理石石材ST-04/ST-04a干挂; 3.石材加工; 4.包含一切安装所需的配件及辅材; | D34: 樘 | E34: 2 | F34: 2 | G34: 1 | H34: =E34+F34+G34 -> 5 | I34: =U34*$U$1 -> 497.25 | J34: =S34*(1+T34)*$S$1 -> 954.72 | K34: =(V34+W34)*$V$1 -> 704.95844 | L34: =+SUM(I34:K34)*$L$3 -> 215.69284 | M34: =SUM(I34:L34) -> 2372.6213 | N34: =H34*M34 -> 11863.106 | R34: =S34+S34*T34+U34+V34+W34 -> 2156.9284 | S34: =480*0.9*2.21 -> 954.72 | T34: 0 | U34: =250*0.9*2.21 -> 497.25 | V34: =((27.3*5+30*2+25+25+16.5)/(0.87*1.14)+33.5+55)*0.9*2.21 -> 703.45844 | W34: 1.5 | X34: =R34*H34 -> 10784.642
A35: =A34+1 -> 6 | B35: 电井门石材暗门：1000*2210mm | C35: 1.电井门石材暗门：1000*2210mm； 2.大理石石材ST-04/ST-04a干挂； 3.石材加工； 4.包含一切安装所需的配件及辅材； | D35: 樘 | E35: 1 | F35: 0 | G35: 0 | H35: =E35+F35+G35 -> 1 | I35: =U35*$U$1 -> 552.5 | J35: =S35*(1+T35)*$S$1 -> 1060.8 | K35: =(V35+W35)*$V$1 -> 783.12049 | L35: =+SUM(I35:K35)*$L$3 -> 239.64205 | M35: =SUM(I35:L35) -> 2636.0625 | N35: =H35*M35 -> 2636.0625 | R35: =S35+S35*T35+U35+V35+W35 -> 2396.4205 | S35: =480*1*2.21 -> 1060.8 | T35: 0 | U35: =250*1*2.21 -> 552.5 | V35: =((27.3*5+30*2+25+25+16.5)/(0.87*1.14)+33.5+55)*1*2.21 -> 781.62049 | W35: 1.5 | X35: =R35*H35 -> 2396.4205
A36: =A35+1 -> 7 | B36: 双开电井暗门：1300*2210mm | C36: 1.双开电井暗门：1300*2210mm； 2.10mm玻镁板基底; 3.包含一切安装所需的配件及辅材，不包含涂料； | D36: 樘 | E36: 0 | F36: 0 | G36: 1 | H36: =E36+F36+G36 -> 1 | I36: =U36*$U$1 -> 474.045 | J36: =S36*(1+T36)*$S$1 -> 0 | K36: =(V36+W36)*$V$1 -> 1017.6066 | L36: =+SUM(I36:K36)*$L$3 -> 149.16516 | M36: =SUM(I36:L36) -> 1640.8168 | N36: =H36*M36 -> 1640.8168 | R36: =S36+S36*T36+U36+V36+W36 -> 1491.6516 | S36: 0 | T36: 0 | U36: =165*1.3*2.21 -> 474.045 | V36: =((27.3*5+30*2+25+25+16.5)/(0.87*1.14)+33.5+55)*1.3*2.21 -> 1016.1066 | W36: 1.5 | X36: =R36*H36 -> 1491.6516
A37: =A36+1 -> 8 | B37: 双开电井石材暗门：1300*2210mm | C37: 1.双开电井石材暗门：1300*2210mm； 2.大理石石材ST-04/ST-04a干挂； 3.石材加工； 4.包含一切安装所需的配件及辅材； | D37: 樘 | E37: 2 | F37: 0 | G37: 0 | H37: =E37+F37+G37 -> 2 | I37: =U37*$U$1 -> 718.25 | J37: =S37*(1+T37)*$S$1 -> 1379.04 | K37: =(V37+W37)*$V$1 -> 1017.6066 | L37: =+SUM(I37:K37)*$L$3 -> 311.48966 | M37: =SUM(I37:L37) -> 3426.3863 | N37: =H37*M37 -> 6852.7726 | R37: =S37+S37*T37+U37+V37+W37 -> 3114.8966 | S37: =480*1.3*2.21 -> 1379.04 | T37: 0 | U37: =250*1.3*2.21 -> 718.25 | V37: =((27.3*5+30*2+25+25+16.5)/(0.87*1.14)+33.5+55)*1.3*2.21 -> 1016.1066 | W37: 1.5 | X37: =R37*H37 -> 6229.7933
A38: =A37+1 -> 9 | B38: 护角：H900mm | C38: 1.护角：H900mm 2.包含完成该项内容所有工作及费用并满足设计图纸、规范等要求; | D38: 套 | E38: 96 | F38: 114 | G38: 129 | H38: =E38+F38+G38 -> 339 | I38: =U38*$U$1 -> 8 | J38: =S38*(1+T38)*$S$1 -> 32 | K38: =(V38+W38)*$V$1 -> 0.2 | L38: =+SUM(I38:K38)*$L$3 -> 4.02 | M38: =SUM(I38:L38) -> 44.22 | N38: =H38*M38 -> 14990.58 | R38: =S38+S38*T38+U38+V38+W38 -> 40.2 | S38: 32 | T38: 0 | U38: 8 | V38: 0.2 | W38: 0 | X38: =R38*H38 -> 13627.8
A39: =A38+1 -> 10 | B39: 防撞杆 | C39: 1.防撞杆 2.MT-02a 金属饰面 3.包含完成该项内容所有工作及费用并满足设计图纸、规范等要求; | D39: 套 | E39: 29 | F39: 39 | G39: 40 | H39: =E39+F39+G39 -> 108 | I39: =U39*$U$1 -> 35 | J39: =S39*(1+T39)*$S$1 -> 95 | K39: =(V39+W39)*$V$1 -> 1.7 | L39: =+SUM(I39:K39)*$L$3 -> 13.17 | M39: =SUM(I39:L39) -> 144.87 | N39: =H39*M39 -> 15645.96 | R39: =S39+S39*T39+U39+V39+W39 -> 131.7 | S39: 95 | T39: 0 | U39: 35 | V39: 1.5 | W39: 0.2 | X39: =R39*H39 -> 14223.6
A40: 二 | B40: 合计 | N40: =N5 -> 2344307.6

Sheet 划线及标识工程量清单
A1: 珠海丹田海德地库项目装修工程量清单
A2: 序号 | B2: 项目名称 | C2: 项目特征 | D2: 单位 | E2: -1层工程量 | F2: -2层工程量 | G2: -3层工程量 | H2: 合计工程量 | I2: 人工 | J2: 主材 | K2: 辅材及机械费 | L2: 管理及利润取费 | M2: 综合单价（不含税） | N2: 合价（不含税） | O2: 备注 | Q2: 计算方式
A3: 一 | B3: 地面划线 | N3: =N4 -> 34876.879
B4: 地面 | N4: =SUM(N5:N17) -> 34876.879
A5: 1 | B5: 车位划线 | C5: 1.车位划线; 2.包含完成该项内容所有工作及费用并满足设计图纸、规范等要求; | D5: m2 | E5: 217.082 | F5: 228.853 | G5: 253.202 | H5: =E5+F5+G5 -> 699.137 | I5: 4 | J5: 10 | K5: =16.65-I5-J5 -> 2.65 | L5: =(I5+J5+K5)*10% -> 1.665 | M5: =SUM(I5:L5) -> 18.315 | N5: =H5*M5 -> 12804.694 | O5: 参考市场价 | Q5: 模型
A6: 2 | B6: 车位编号 | C6: 1.车位编号; 2.包含完成该项内容所有工作及费用并满足设计图纸、规范等要求; | D6: 个 | E6: 88 | F6: 94 | G6: 102 | H6: =E6+F6+G6 -> 284 | I6: 1.326 | J6: 2.652 | K6: 0.782 | L6: =(I6+J6+K6)*10% -> 0.476 | M6: =SUM(I6:L6) -> 5.236 | N6: =H6*M6 -> 1487.024 | O6: 参考市场价 | Q6: 模型
A7: 3 | B7: 坡道箭头 | C7: 1.坡道箭头; 2.包含完成该项内容所有工作及费用并满足设计图纸、规范等要求; | D7: 个 | E7: 7 | F7: 5 | G7: 4 | H7: =E7+F7+G7 -> 16 | I7: 8.505 | J7: 17.01 | K7: 2.835 | L7: =(I7+J7+K7)*10% -> 2.835 | M7: =SUM(I7:L7) -> 31.185 | N7: =H7*M7 -> 498.96 | O7: 参考市场价 | Q7: 模型
A8: 4 | B8: 直行箭头 | C8: 1.直行箭头; 2.包含完成该项内容所有工作及费用并满足设计图纸、规范等要求; | D8: 个 | E8: 19 | F8: 13 | G8: 14 | H8: =E8+F8+G8 -> 46 | I8: 8.505 | J8: 17.01 | K8: 2.835 | L8: =(I8+J8+K8)*10% -> 2.835 | M8: =SUM(I8:L8) -> 31.185 | N8: =H8*M8 -> 1434.51 | O8: 参考市场价 | Q8: 模型
A9: 5 | B9: 左（右）转箭头 | C9: 1.左转箭头; 2.包含完成该项内容所有工作及费用并满足设计图纸、规范等要求; | D9: 个 | E9: 10 | F9: 13 | G9: 9 | H9: =E9+F9+G9 -> 32 | I9: 8.505 | J9: 17.01 | K9: 2.835 | L9: =(I9+J9+K9)*10% -> 2.835 | M9: =SUM(I9:L9) -> 31.185 | N9: =H9*M9 -> 997.92 | O9: 参考市场价 | Q9: 模型
A10: 6 | B10: 直行左（右）转箭头 | C10: 1.直行左转箭头; 2.包含完成该项内容所有工作及费用并满足设计图纸、规范等要求; | D10: 个 | E10: 2 | F10: 0 | G10: 1 | H10: =E10+F10+G10 -> 3 | I10: 8.505 | J10: 17.01 | K10: 2.835 | L10: =(I10+J10+K10)*10% -> 2.835 | M10: =SUM(I10:L10) -> 31.185 | N10: =H10*M10 -> 93.555 | O10: 参考市场价 | Q10: 模型
A11: 7 | B11: 双向箭头 | C11: 1.双向箭头; 2.包含完成该项内容所有工作及费用并满足设计图纸、规范等要求; | D11: 个 | E11: 0 | F11: 0 | G11: 2 | H11: =E11+F11+G11 -> 2 | I11: 8.505 | J11: 17.01 | K11: 2.835 | L11: =(I11+J11+K11)*10% -> 2.835 | M11: =SUM(I11:L11) -> 31.185 | N11: =H11*M11 -> 62.37 | O11: 参考市场价 | Q11: 模型
A12: 8 | B12: 掉头箭头 | C12: 1.掉头箭头; 2.包含完成该项内容所有工作及费用并满足设计图纸、规范等要求; | D12: 个 | E12: 1 | F12: 1 | G12: 1 | H12: =E12+F12+G12 -> 3 | I12: 8.505 | J12: 17.01 | K12: 2.835 | L12: =(I12+J12+K12)*10% -> 2.835 | M12: =SUM(I12:L12) -> 31.185 | N12: =H12*M12 -> 93.555 | O12: 参考市场价 | Q12: 模型
A13: 9 | B13: 斑马线 | C13: 1.斑马线; 2.包含完成该项内容所有工作及费用并满足设计图纸、规范等要求; | D13: m | E13: 42 | F13: 63 | G13: 60 | H13: =E13+F13+G13 -> 165 | I13: 2.66 | J13: 5.304 | K13: 0.886 | L13: =(I13+J13+K13)*10% -> 0.885 | M13: =SUM(I13:L13) -> 9.735 | N13: =H13*M13 -> 1606.275 | O13: 参考市场价 | Q13: 模型
A14: 10 | B14: 通道线（中心线） | C14: 1.通道线（中心线）; 2.包含完成该项内容所有工作及费用并满足设计图纸、规范等要求; | D14: m | E14: 76.2 | F14: 73.8 | G14: 36 | H14: =E14+F14+G14 -> 186 | I14: 1.326 | J14: 2.652 | K14: 0.442 | L14: =(I14+J14+K14)*10% -> 0.442 | M14: =SUM(I14:L14) -> 4.862 | N14: =H14*M14 -> 904.332 | O14: 参考市场价 | Q14: 模型
A15: 11 | B15: 通道边线 | C15: 1.通道边线; 2.包含完成该项内容所有工作及费用并满足设计图纸、规范等要求; | D15: m | E15: 643.643 | F15: 626.506 | G15: 626.278 | H15: =E15+F15+G15 -> 1896.427 | I15: 1.326 | J15: 2.652 | K15: 0.442 | L15: =(I15+J15+K15)*10% -> 0.442 | M15: =SUM(I15:L15) -> 4.862 | N15: =H15*M15 -> 9220.4281 | O15: 参考市场价 | Q15: 模型
A16: 12 | B16: 减速带 | C16: 1.减速带; 2.包含完成该项内容所有工作及费用并满足设计图纸、规范等要求; | D16: m | E16: 15.5 | F16: 16 | G16: 8 | H16: =E16+F16+G16 -> 39.5 | I16: 20 | J16: 60 | K16: 20.19 | L16: =(I16+J16+K16)*10% -> 10.019 | M16: =SUM(I16:L16) -> 110.209 | N16: =H16*M16 -> 4353.2555 | O16: 参考市场价 | Q16: 模型 | R16: =_xlfn.DISPIMG("ID_48D9FBAC357141EAA6DC4F0A56455221",1) -> =DISPIMG("ID_48D9FBAC357141EAA6DC4F0A56455221",1)
A17: 13 | B17: 落客区地面LOGO标识 | C17: 1.落客区地面LOGO标识; 2.包含完成该项内容所有工作及费用并满足设计图纸、规范等要求; | D17: m2 | E17: 4 | F17: 4 | G17: 4 | H17: =E17+F17+G17 -> 12 | I17: 30 | J17: 60 | K17: 10 | L17: =(I17+J17+K17)*10% -> 10 | M17: =SUM(I17:L17) -> 110 | N17: =H17*M17 -> 1320 | O17: 参考市场价 | Q17: 模型
A18: 二 | B18: 合计 | N18: =N3 -> 34876.879

Sheet 坡道安装工程
A1: 珠海丹田海德地库项目装修工程量清单 | P1: 1 | R1: 1 | S1: 1
A2: 序号 | B2: 项目名称 | C2: 项目特征 | D2: 单位 | E2: 工程量合计 | F2: 人工 | G2: 主材 | H2: 辅材及机械费 | I2: 管理及利润取费 | J2: 综合单价（不含税） | K2: 合价（不含税） | L2: 备注 | O2: 成本单价 | P2: 主材 | Q2: 损耗率 | R2: 人工 | S2: 辅材 | T2: 机械 | U2: 合价
F3: A | G3: B | H3: C | I3: =坡道装饰工程量清单!$L$3 -> 0.1 | J3: E=A+B+C+D | K3: F=E*工程量
I4: D=(A+B+C)*费率
A5: 一 | B5: 坡道
A6: 1 | B6: LT.1 明装LED线形灯 | C6: 1、名称：明装LED线形灯 2、规格型号：型号：CEB0512B-B/J、色温：4000K、功率：26W、显指：Ra＞90 3、包含完成该项内容所有工作及费用并满足设计图纸、规范等要求; | D6: 套 | E6: =102+34+14 -> 150 | F6: =R6*$R$1 -> 18 | G6: =P6*(1+Q6)*$P$1 -> 125 | H6: =(S6+T6)*$S$1 -> 1.5 | I6: =(F6+G6+H6)*$I$3 -> 14.45 | J6: =SUM(F6:I6) -> 158.95 | K6: =J6*E6 -> 23842.5 | O6: =P6+P6*Q6+R6+S6+T6 -> 144.5 | P6: 125 | R6: 18 | S6: 1.5 | U6: =O6*E6 -> 21675
A7: 2 | B7: LT.3b 天花嵌入式射灯 | C7: 1、名称：天花嵌入式射灯 2、规格型号：型号：PAK564151、名称：色温：4000K、功率：20W、显指：Ra＞90 3、包含完成该项内容所有工作及费用并满足设计图纸、规范等要求; | D7: 套 | E7: 14 | F7: =R7*$R$1 -> 18 | G7: =P7*(1+Q7)*$P$1 -> 135 | H7: =(S7+T7)*$S$1 -> 1.5 | I7: =(F7+G7+H7)*$I$3 -> 15.45 | J7: =SUM(F7:I7) -> 169.95 | K7: =J7*E7 -> 2379.3 | O7: =P7+P7*Q7+R7+S7+T7 -> 154.5 | P7: 135 | R7: 18 | S7: 1.5 | U7: =O7*E7 -> 2163
A8: 3 | B8: T.8 地灯 | C8: 1、名称：地灯 2、规格型号：型号：PAK520036、色温：4000K、功率：3W、显指：Ra＞90 3、包含完成该项内容所有工作及费用并满足设计图纸、规范等要求; | D8: 套 | E8: 59 | F8: =R8*$R$1 -> 35 | G8: =P8*(1+Q8)*$P$1 -> 110 | H8: =(S8+T8)*$S$1 -> 1.5 | I8: =(F8+G8+H8)*$I$3 -> 14.65 | J8: =SUM(F8:I8) -> 161.15 | K8: =J8*E8 -> 9507.85 | N8: =_xlfn.DISPIMG("ID_1BC2F87A82AD473B9EC09261F010DD27",1) -> =DISPIMG("ID_1BC2F87A82AD473B9EC09261F010DD27",1) | O8: =P8+P8*Q8+R8+S8+T8 -> 146.5 | P8: 110 | R8: 35 | S8: 1.5 | U8: =O8*E8 -> 8643.5
B9: 合计 | K9: =SUM(K6:K8) -> 35729.65

Sheet 地库安装工程
A1: 珠海丹田海德地库项目装修工程量清单 | S1: 1 | U1: 1 | V1: 1
A2: 序号 | B2: 项目名称 | C2: 项目特征 | D2: 单位 | E2: -1层工程量 | F2: -2层工程量 | G2: -3层工程量 | H2: 合计工程量 | I2: 人工 | J2: 主材 | K2: 辅材及机械费 | L2: 管理及利润取费 | M2: 综合单价（不含税） | N2: 合价（不含税） | O2: 备注 | R2: 成本单价 | S2: 主材 | T2: 损耗率 | U2: 人工 | V2: 辅材 | W2: 机械 | X2: 合价
I3: A | J3: B | K3: C | L3: =坡道装饰工程量清单!$L$3 -> 0.1 | M3: E=A+B+C+D | N3: F=E*工程量
L4: D=(A+B+C)*费率
A5: 一 | B5: 地库电气工程 | N5: =SUM(N6:N15) -> 209328.29
A6: 1 | B6: LT.1 明装LED线形灯 | C6: 1、名称：明装LED线形灯 2、规格型号：型号：CEB0512B-B/J、色温：4000K、功率：26W、显指：Ra＞90 3、包含完成该项内容所有工作及费用并满足设计图纸、规范等要求; | D6: 套 | E6: 168 | F6: 160 | G6: 182 | H6: =SUM(E6:G6) -> 510 | I6: =坡道安装工程!F6 -> 18 | J6: =坡道安装工程!G6 -> 125 | K6: =坡道安装工程!H6 -> 1.5 | L6: =(I6+J6+K6)*$L$3 -> 14.45 | M6: =SUM(I6:L6) -> 158.95 | N6: =M6*H6 -> 81064.5 | R6: =S6+S6*T6+U6+V6+W6 -> 0 | X6: =R6*H6 -> 0
A7: 2 | B7: LT.2 吊装筒灯（含吊杆） | C7: 1、名称：吊装筒灯（含吊杆） 2、规格型号：型号：CEAM316-A、色温：4000K、功率：15W、显指：Ra≥90 3、包含完成该项内容所有工作及费用并满足设计图纸、规范等要求; | D7: 套 | E7: 99 | F7: 98 | G7: 109 | H7: =SUM(E7:G7) -> 306 | I7: =U7*$U$1 -> 18 | J7: =S7*(1+T7)*$S$1 -> 85 | K7: =(V7+W7)*$V$1 -> 1.5 | L7: =(I7+J7+K7)*$L$3 -> 10.45 | M7: =SUM(I7:L7) -> 114.95 | N7: =M7*H7 -> 35174.7 | R7: =S7+S7*T7+U7+V7+W7 -> 104.5 | S7: 85 | U7: 18 | V7: 1.5 | X7: =R7*H7 -> 31977
A8: 3 | B8: LT.3 轨道射灯 | C8: 1、名称：轨道射灯 2、规格型号：型号：PAK564151、名称：色温：4000K、功率：10W、显指：Ra＞90 3、包含轨道、驱动及完成该项内容所有工作及费用并满足设计图纸、规范等要求; | D8: 套 | E8: 73 | F8: 67 | G8: 72 | H8: =SUM(E8:G8) -> 212 | I8: =U8*$U$1 -> 18 | J8: =S8*(1+T8)*$S$1 -> 135 | K8: =(V8+W8)*$V$1 -> 1.5 | L8: =(I8+J8+K8)*$L$3 -> 15.45 | M8: =SUM(I8:L8) -> 169.95 | N8: =M8*H8 -> 36029.4 | R8: =S8+S8*T8+U8+V8+W8 -> 154.5 | S8: 135 | U8: 18 | V8: 1.5 | X8: =R8*H8 -> 32754
A9: 4 | B9: LT.4 嵌入式筒灯 | C9: 1、名称：嵌入式筒灯 2、规格型号：型号：CEJ61075F01 、色温：3000K、功率：9W、光束角：50° 3、包含完成该项内容所有工作及费用并满足设计图纸、规范等要求; | D9: 套 | F9: 4 | H9: =SUM(E9:G9) -> 4 | I9: =U9*$U$1 -> 18 | J9: =S9*(1+T9)*$S$1 -> 85 | K9: =(V9+W9)*$V$1 -> 1.5 | L9: =(I9+J9+K9)*$L$3 -> 10.45 | M9: =SUM(I9:L9) -> 114.95 | N9: =M9*H9 -> 459.8 | R9: =S9+S9*T9+U9+V9+W9 -> 104.5 | S9: 85 | U9: 18 | V9: 1.5 | X9: =R9*H9 -> 418
A10: 5 | B10: LT.6 洗墙灯 | C10: 1、名称：洗墙灯 2、规格型号：、色温：4000K、功率：4W、输入电压：DC24V、光效：85 lm/W 3、包含完成该项内容所有工作及费用并满足设计图纸、规范等要求; | D10: m | E10: 53.521 | F10: 48.987 | G10: 52.718 | H10: =SUM(E10:G10) -> 155.226 | I10: =U10*$U$1 -> 18 | J10: =S10*(1+T10)*$S$1 -> 115 | K10: =(V10+W10)*$V$1 -> 1.5 | L10: =(I10+J10+K10)*$L$3 -> 13.45 | M10: =SUM(I10:L10) -> 147.95 | N10: =M10*H10 -> 22965.687 | R10: =S10+S10*T10+U10+V10+W10 -> 134.5 | S10: 115 | U10: 18 | V10: 1.5 | X10: =R10*H10 -> 20877.897
A11: 6 | B11: LT.7 壁灯 | C11: 1、名称：壁灯 2、规格型号：色温：4000K、功率：7W、显指：Ra＞90 3、包含完成该项内容所有工作及费用并满足设计图纸、规范等要求; | D11: 套 | E11: 4 | F11: 4 | G11: 4 | H11: =SUM(E11:G11) -> 12 | I11: =U11*$U$1 -> 18 | J11: =S11*(1+T11)*$S$1 -> 80 | K11: =(V11+W11)*$V$1 -> 1.5 | L11: =(I11+J11+K11)*$L$3 -> 9.95 | M11: =SUM(I11:L11) -> 109.45 | N11: =M11*H11 -> 1313.4 | R11: =S11+S11*T11+U11+V11+W11 -> 99.5 | S11: 80 | U11: 18 | V11: 1.5 | X11: =R11*H11 -> 1194
A12: 7 | B12: T.1 LED软灯带 | C12: 1、名称：LED软灯带 2、规格型号：型号：PAK544189、色温：4000K、功率：3W、光束角：120° 3.其他:含驱动电源、灯具安装 4.包含完成该项内容所有工作及费用并满足设计图纸、规范等要求; | D12: m | E12: 88.919 | F12: 86.52 | G12: 87.639 | H12: =SUM(E12:G12) -> 263.078 | I12: =U12*$U$1 -> 8 | J12: =S12*(1+T12)*$S$1 -> 23.5 | K12: =(V12+W12)*$V$1 -> 0.5 | L12: =(I12+J12+K12)*$L$3 -> 3.2 | M12: =SUM(I12:L12) -> 35.2 | N12: =M12*H12 -> 9260.3456 | R12: =S12+S12*T12+U12+V12+W12 -> 32 | S12: 23.5 | U12: 8 | V12: 0.5 | X12: =R12*H12 -> 8418.496
A13: 8 | B13: T.2 LED硬灯条 | C13: 1、名称：LED硬灯条 2、规格型号：型号：PAK544351、名称：色温：4000K、功率：7.2W、光束角：120° 3.其他:含驱动电源、灯具安装 4.包含完成该项内容所有工作及费用并满足设计图纸、规范等要求; | D13: m | E13: 144.283 | F13: 140.924 | G13: 199.516 | H13: =SUM(E13:G13) -> 484.723 | I13: =U13*$U$1 -> 8 | J13: =S13*(1+T13)*$S$1 -> 22 | K13: =(V13+W13)*$V$1 -> 0.5 | L13: =(I13+J13+K13)*$L$3 -> 3.05 | M13: =SUM(I13:L13) -> 33.55 | N13: =M13*H13 -> 16262.457 | R13: =S13+S13*T13+U13+V13+W13 -> 30.5 | S13: 22 | U13: 8 | V13: 0.5 | X13: =R13*H13 -> 14784.051
A14: 9 | B14: 感应开关 | C14: 1、名称：感应开关 2、包含完成该项内容所有工作及费用并满足设计图纸、规范等要求; | D14: 个 | E14: 45 | F14: 47 | G14: 50 | H14: =SUM(E14:G14) -> 142 | I14: =U14*$U$1 -> 15 | J14: =S14*(1+T14)*$S$1 -> 22 | K14: =(V14+W14)*$V$1 -> 0.5 | L14: =(I14+J14+K14)*$L$3 -> 3.75 | M14: =SUM(I14:L14) -> 41.25 | N14: =M14*H14 -> 5857.5 | R14: =S14+S14*T14+U14+V14+W14 -> 37.5 | S14: 22 | U14: 15 | V14: 0.5 | X14: =R14*H14 -> 5325
A15: 10 | B15: 五孔单相暗插座 | C15: 1、名称：五孔单相暗插座 2、包含完成该项内容所有工作及费用并满足设计图纸、规范等要求; | D15: 个 | E15: 13 | F15: 13 | G15: 12 | H15: =SUM(E15:G15) -> 38 | I15: =U15*$U$1 -> 10 | J15: =S15*(1+T15)*$S$1 -> 12 | K15: =(V15+W15)*$V$1 -> 0.5 | L15: =(I15+J15+K15)*$L$3 -> 2.25 | M15: =SUM(I15:L15) -> 24.75 | N15: =M15*H15 -> 940.5 | R15: =S15+S15*T15+U15+V15+W15 -> 22.5 | S15: 12 | U15: 10 | V15: 0.5 | X15: =R15*H15 -> 855
A16: 一 | B16: 地库给排水工程 | N16: =SUM(N17:N18) -> 2604.25
A17: 1 | B17: 洗手盆及龙头 | C17: 1、名称：洗手盆及龙头 2、洗手盆、龙头安装，包括角阀、不锈钢软管、下水管等所需材料 3、规格型号：洗手盆：和成：LF3530S/LF616K、龙头：和成：AF6013H、角阀：和成：FE0014 4、包含完成该项内容所有工作及费用并满足设计图纸、规范等要求; | D17: 套 | E17: 2 | F17: 0 | G17: 0 | H17: =SUM(E17:G17) -> 2 | I17: =U17*$U$1 -> 85 | J17: =S17*(1+T17)*$S$1 -> 921 | K17: =(V17+W17)*$V$1 -> 137 | L17: =(I17+J17+K17)*$L$3 -> 114.3 | M17: =SUM(I17:L17) -> 1257.3 | N17: =M17*H17 -> 2514.6 | R17: =S17+S17*T17+U17+V17+W17 -> 1143 | S17: =136+785 -> 921 | U17: 85 | V17: =93+22*2 -> 137 | X17: =R17*H17 -> 2286
A18: 2 | B18: 地漏 | C18: 1、名称：地漏 2、规格型号：和成：BA30086 3、包含完成该项内容所有工作及费用并满足设计图纸、规范等要求; | D18: 套 | E18: 1 | F18: 0 | G18: 0 | H18: =SUM(E18:G18) -> 1 | I18: =U18*$U$1 -> 25 | J18: =S18*(1+T18)*$S$1 -> 55 | K18: =(V18+W18)*$V$1 -> 1.5 | L18: =(I18+J18+K18)*$L$3 -> 8.15 | M18: =SUM(I18:L18) -> 89.65 | N18: =M18*H18 -> 89.65 | R18: =S18+S18*T18+U18+V18+W18 -> 81.5 | S18: 55 | U18: 25 | V18: 1.5 | X18: =R18*H18 -> 81.5
B19: 合计 | N19: =+N16+N5 -> 211932.54
