Workbook
Name _04房1300_1500浴缸: #REF!
Name _1500×1000浴缸及龙头花洒: #REF!

Sheet 南川一标段
A1: 重庆站房2标装饰装修一标段南川北站一标分包工程招标控制价审核表
A2: 项目名称：中铁建工集团有限公司重庆至黔江铁路站房工程2标项目经理部 | M2: 单位：元 | N2: 成本分析
A3: 序号 | B3: 项目名称 | C3: 项目特征 | D3: 工作内容 | E3: 单位 | F3: 工程量 | G3: 控制价 | I3: 上报金额 | K3: 工程量计算规则 | L3: 费用组成 | M3: 备注 | N3: 主材 | O3: 辅材 | P3: 人工 | Q3: 单价 | R3: 取费
G4: 不含税单价（元） | H4: 不含税合价（元） | I4: 不含税单价（元） | J4: 不含税合价（元） | R4: 1.2
A5: 一 | B5: 南川北站
A6: （一） | B6: 站房区域 | O6: =400*1.6*1.05*0.05 -> 33.6
A7: 1 | B7: 花岗石地面 | C7: 1、铺25厚磨光花岗石板(六面涂刷石材保护剂),同色稀水泥浆擦 2、50厚1:3干硬性水泥粘结层,撒素水泥粉 3、水泥浆一道(内掺建筑胶) 4、嵌缝材料种类：按甲方要求嵌缝、打胶； 5、防护层材料：防护剂六面处理，满足设计和相关规范要求； 6、酸洗、打蜡要求：满足设计和相关规范要求； 7、楼地面伸缩缝、变形缝的处理； 8、其他：该项包含本项工作所有工作内容含垂直运输机械等，未详尽列举特征，详见施工图纸、设计规范、施工方案事项均包含在综合单价中。(石材规格800*800) | D7: 1、基层清理、打磨；2、砂浆的制作、运输、找平、压实；3、面层的铺贴；4、水泥砂浆擦缝；5、局部部位花岗石切割、打磨，未详尽列举的图纸、方案事项均包含在综合单价中；6.该项包含本项工作所有工作内容含垂直运输机械等，未详尽列举特征，详见施工图纸、设计规范、施工方案事项均包含在综合单价中。 | E7: m2 | F7: =3735.87-F8 -> 3695.99 | G7: 85 | H7: =ROUND(F7*G7,2) -> 314159.15 | I7: =R7 -> 118.32 | J7: =F7*I7 -> 437309.54 | K7: 按设计图示尺寸以面积计算 | L7: 1、除甲供材外全费用综合单价； 2、甲供材：石材 | N7: 0 | O7: =400*1.6*1.05*0.05 -> 33.6 | P7: 65 | Q7: =N7+O7+P7 -> 98.6 | R7: =Q7*$R$4 -> 118.32 | T7: 118.32 | U7: =T7-I7 -> 0
A8: 2 | B8: 花岗石梯面 | C8: 1、铺25厚磨光花岗石板(六面涂刷石材保护剂),同色稀水泥浆擦 2、50厚1:3干硬性水泥粘结层,撒素水泥粉 3、水泥浆一道(内掺建筑胶) 4、嵌缝材料种类：按甲方要求嵌缝、打胶，挡水条制作； 5、防护层材料：防护剂六面处理，满足设计和相关规范要求； 6、酸洗、打蜡要求：满足设计和相关规范要求； 7、楼地面伸缩缝、变形缝的处理； 8、其他：该项包含本项工作所有工作内容含垂直运输机械等，未详尽列举特征，详见施工图纸、设计规范、施工方案事项均包含在综合单价中。 (石材规格800*800) | D8: 1、基层清理、打磨；2、砂浆的制作、运输、找平、压实；3、面层的铺贴，挡水条制作；4、水泥砂浆擦缝；5、局部部位花岗石切割、打磨，未详尽列举的图纸、方案事项均包含在综合单价中；6.该项包含本项工作所有工作内容含垂直运输机械等，未详尽列举特征，详见施工图纸、设计规范、施工方案事项均包含在综合单价中。 | E8: m2 | F8: 39.88 | G8: 110 | H8: =ROUND(F8*G8,2) -> 4386.8 | I8: =R8 -> 160.32 | J8: =F8*I8 -> 6393.56 | K8: 按设计图示尺寸以展开面积计算 | L8: 1、除甲供材外全费用综合单价； 2、甲供材：石材 | N8: 0 | O8: =400*1.6*1.05*0.05 -> 33.6 | P8: 100 | Q8: =N8+O8+P8 -> 133.6 | R8: =Q8*$R$4 -> 160.32 | T8: 160.32 | U8: =T8-I8 -> 0
A9: 3 | B9: 地砖地面 | C9: 1、面层：10厚玻化砖(防滑),同色水泥浆擦缝 2、30厚1:3干硬性水泥砂浆,表面撒水泥粉 3、嵌缝材料种类：按甲方要求嵌缝、打胶； 4、防护层材料：满足设计和相关规范要求； 5、酸洗、打蜡要求：满足设计和相关规范要求； 6、楼地面伸缩缝、变形缝的处理； 7、其他：该项包含本项工作所有工作内容含垂直运输机械等，未详尽列举特征，详见施工图纸、设计规范、施工方案事项均包含在综合单价中。 (地砖规格600*600) | D9: 1、基层清理、打磨；2、砂浆的制作、运输、找平、压实；3、面层的铺贴；4、水泥砂浆擦缝；5、局部部位防滑地砖切割、打磨，未详尽列举的图纸、方案事项均包含在综合单价中；6.该项包含本项工作所有工作内容含垂直运输机械等，未详尽列举特征，详见施工图纸、设计规范、施工方案事项均包含在综合单价中。 | E9: m2 | F9: 403.66 | G9: 120 | H9: =ROUND(F9*G9,2) -> 48439.2 | I9: =R9 -> 165.22 | J9: =F9*I9 -> 66692.71 | K9: 按设计图示尺寸以面积计算 | L9: 全费用综合单价 | N9: =主材表!L5 -> 57.52 | O9: =400*1.6*1.05*0.03 -> 20.16 | P9: 60 | Q9: =N9+O9+P9 -> 137.68 | R9: =Q9*$R$4 -> 165.22 | T9: 165.22 | U9: =T9-I9 -> 0
A10: 4 | B10: 防滑地砖地面(防水) | C10: 1、面层：10厚玻化砖(防滑),同色水泥浆擦缝 2、30厚1:3干硬性水泥砂浆,表面撒水泥粉 3、嵌缝材料种类：按甲方要求嵌缝、打胶； 4、防护层材料：满足设计和相关规范要求； 5、酸洗、打蜡要求：满足设计和相关规范要求； 6、楼地面伸缩缝、变形缝的处理； 7、其他：该项包含本项工作所有工作内容含垂直运输机械等，未详尽列举特征，详见施工图纸、设计规范、施工方案事项均包含在综合单价中。 (地砖规格600*600) | D10: 1、基层清理、打磨；2、砂浆的制作、运输、找平、压实；3、面层的铺贴；4、水泥砂浆擦缝；5、局部部位防滑地砖切割、打磨，未详尽列举的图纸、方案事项均包含在综合单价中 | E10: m2 | F10: 619.6 | G10: 120 | H10: =ROUND(F10*G10,2) -> 74352 | I10: =R10 -> 165.22 | J10: =F10*I10 -> 102370.31 | K10: 按设计图示尺寸以面积计算 | L10: 全费用综合单价 | N10: =主材表!$L$6 -> 57.52 | O10: =400*1.6*1.05*0.03 -> 20.16 | P10: =$P$9 -> 60 | Q10: =N10+O10+P10 -> 137.68 | R10: =Q10*$R$4 -> 165.22 | T10: 165.22 | U10: =T10-I10 -> 0
A11: 5 | B11: 地砖梯面 | C11: 1、面层：10厚玻化砖(防滑),同色水泥浆擦缝 2、30厚1:3干硬性水泥砂浆,表面撒水泥粉 3、嵌缝材料种类：按甲方要求嵌缝、打胶； 4、防护层材料：满足设计和相关规范要求； 5、酸洗、打蜡要求：满足设计和相关规范要求； 6、楼地面伸缩缝、变形缝的处理； 7、其他：该项包含本项工作所有工作内容含垂直运输机械等，未详尽列举特征，详见施工图纸、设计规范、施工方案事项均包含在综合单价中。 (地砖规格600*600) | D11: 1、基层清理、打磨；2、砂浆的制作、运输、找平、压实；3、面层的铺贴，挡水条制作；4、水泥砂浆擦缝；5、局部部位防滑地砖切割、打磨，未详尽列举的图纸、方案事项均包含在综合单价中；6.该项包含本项工作所有工作内容含垂直运输机械等，未详尽列举特征，详见施工图纸、设计规范、施工方案事项均包含在综合单价中。 | E11: m2 | F11: 1090.99 | G11: 135 | H11: =ROUND(F11*G11,2) -> 147283.65 | I11: =R11 -> 175.84 | J11: =F11*I11 -> 191839.68 | K11: 按设计图示尺寸以展开面积计算 | L11: 全费用综合单价 | N11: =主材表!L7 -> 66.37 | O11: =400*1.6*1.05*0.03 -> 20.16 | P11: =$P$9 -> 60 | Q11: =N11+O11+P11 -> 146.53 | R11: =Q11*$R$4 -> 175.84 | T11: 175.84 | U11: =T11-I11 -> 0
A12: 6 | B12: 地砖楼面 | C12: 1、面层：10厚玻化砖(防滑),同色水泥浆擦缝 2、30厚1:3干硬性水泥砂浆,表面撒水泥粉 3、嵌缝材料种类：按甲方要求嵌缝、打胶； 4、防护层材料：满足设计和相关规范要求； 5、酸洗、打蜡要求：满足设计和相关规范要求； 6、楼地面伸缩缝、变形缝的处理； 7、其他：该项包含本项工作所有工作内容含垂直运输机械等，未详尽列举特征，详见施工图纸、设计规范、施工方案事项均包含在综合单价中。 (地砖规格600*600) | D12: 1、基层清理、打磨；2、砂浆的制作、运输、找平、压实；3、面层的铺贴；4、水泥砂浆擦缝；5、局部部位防滑地砖切割、打磨，未详尽列举的图纸、方案事项均包含在综合单价中；6.该项包含本项工作所有工作内容含垂直运输机械等，未详尽列举特征，详见施工图纸、设计规范、施工方案事项均包含在综合单价中。 | E12: m2 | F12: 1090.99 | G12: 120 | H12: =ROUND(F12*G12,2) -> 130918.8 | I12: =R12 -> 165.22 | J12: =F12*I12 -> 180253.37 | K12: 按设计图示尺寸以面积计算 | L12: 全费用综合单价 | N12: =主材表!L8 -> 57.52 | O12: =400*1.6*1.05*0.03 -> 20.16 | P12: =$P$9 -> 60 | Q12: =N12+O12+P12 -> 137.68 | R12: =Q12*$R$4 -> 165.22 | T12: 165.22 | U12: =T12-I12 -> 0
A13: 7 | B13: 水泥自流平防水地面 | C13: 1、5厚水泥基自流平面层 2、涂刷自流平界面剂 3、其他：该项包含本项工作所有工作内容含垂直运输机械等，未详尽列举特征，详见施工图纸、设计规范、施工方案事项均包含在综合单价中。 | D13: 1.基层处理；2.涂界面剂；3.拌合自流平浆料；4.铺自流平面层；5、未详尽列举的图纸、方案事项均包含在综合单价中；6.该项包含本项工作所有工作内容含垂直运输机械等，未详尽列举特征，详见施工图纸、设计规范、施工方案事项均包含在综合单价中。 | E13: m2 | F13: 277.7 | G13: 47.92 | H13: =ROUND(F13*G13,2) -> 13307.38 | I13: =R13 -> 28.8 | J13: =F13*I13 -> 7997.76 | K13: 按设计图示尺寸以面积计算 | L13: 全费用综合单价 | M13: 图纸未找到 | N13: 12 | P13: 12 | Q13: =N13+O13+P13 -> 24 | R13: =Q13*$R$4 -> 28.8 | T13: 28.8 | U13: =T13-I13 -> 0
A14: 8 | B14: 防静电架空地面 | C14: 1、10厚玻化砖,同色水泥浆擦缝 2、30厚1:3干硬性水泥砂浆,表面撒水泥粉 3、水泥浆一道(内掺建筑胶) 4、其他：该项包含本项工作所有工作内容含垂直运输机械等，未详尽列举特征，详见施工图纸、设计规范、施工方案事项均包含在综合单价中。 | D14: 1、基层清理、打磨；2、水泥浆一道，内掺建筑胶；3、砂浆的制作、运输、找平、压实；4、面砖的铺贴；5、成套支架安装；6、安装陶瓷防静电架空地板；6、该项包含防静电架空地板的所有工作内容，含垂直运输机械等，未详尽列举的图纸、方案事项均包含在综合单价中 | E14: m2 | F14: 77.79 | G14: 316.06 | H14: =ROUND(F14*G14,2) -> 24586.31 | I14: =R14 -> 391.2 | J14: =F14*I14 -> 30431.45 | K14: 按设计图示尺寸以面积计算 | L14: 全费用综合单价 | M14: 图纸未找到 | N14: 225 | O14: 26 | P14: 75 | Q14: =N14+O14+P14 -> 326 | R14: =Q14*$R$4 -> 391.2 | T14: 391.2 | U14: =T14-I14 -> 0
A15: 9 | B15: 防静电活动楼面 | C15: 1、10厚玻化砖,同色水泥浆擦缝 2、30厚1:3干硬性水泥砂浆,表面撒水泥粉 3、水泥浆一道(内掺建筑胶) 4、其他：该项包含本项工作所有工作内容含垂直运输机械等，未详尽列举特征，详见施工图纸、设计规范、施工方案事项均包含在综合单价中。 | D15: 1、基层清理、打磨；2、水泥浆一道，内掺建筑胶；3、砂浆的制作、运输、找平、压实；4、面砖的铺贴；5、成套支架安装；6、安装陶瓷防静电架空地板；6、该项包含防静电架空地板的所有工作内容，含垂直运输机械等，未详尽列举的图纸、方案事项均包含在综合单价中 | E15: m2 | F15: 147.29 | G15: 316.06 | H15: =ROUND(F15*G15,2) -> 46552.48 | I15: =I14 -> 391.2 | J15: =F15*I15 -> 57619.85 | K15: 按设计图示尺寸以面积计算 | L15: 全费用综合单价 | M15: 图纸未找到 | T15: 391.2 | U15: =T15-I15 -> 0
A16: 10 | B16: 25MM 厚深灰麻过门石 | C16: 1、铺25厚磨光花岗石板(六面涂刷石材保护剂),同色稀水泥浆擦 2、50厚1:3干硬性水泥粘结层,撒素水泥粉 3、水泥浆一道(内掺建筑胶) 4、嵌缝材料种类：按甲方要求嵌缝、打胶； 5、防护层材料：防护剂六面处理，满足设计和相关规范要求； 6、酸洗、打蜡要求：满足设计和相关规范要求； 7、楼地面伸缩缝、变形缝的处理； 8、其他：该项包含本项工作所有工作内容含垂直运输机械等，未详尽列举特征，详见施工图纸、设计规范、施工方案事项均包含在综合单价中。 (石材规格800*800) | D16: 1、基层清理、打磨；2、砂浆的制作、运输、找平、压实；3、面层的铺贴；4、水泥砂浆擦缝；5、局部部位过门石切割、打磨，未详尽列举的图纸、方案事项均包含在综合单价中；5该项包含本项工作所有工作内容含垂直运输机械等，未详尽列举特征，详见施工图纸、设计规范、施工方案事项均包含在综合单价中。 | E16: m2 | F16: 31.88 | G16: 80 | H16: =ROUND(F16*G16,2) -> 2550.4 | I16: =R16 -> 156 | J16: =F16*I16 -> 4973.28 | K16: 按设计图示尺寸以面积计算 | L16: 1、除甲供材外全费用综合单价； 2、甲供材：石材 | N16: 0 | O16: 20 | P16: 110 | Q16: =N16+O16+P16 -> 130 | R16: =Q16*$R$4 -> 156 | T16: 156 | U16: =T16-I16 -> 0
A17: 11 | B17: 水泥踢脚 | C17: 1、6厚1:2.5水泥砂浆抹面压实赶光 2、刷素水泥浆一道 3、7厚1:1:6水泥石灰膏砂浆打底骚猫或划出纹道 4、3厚外加剂专用砂浆抹基底刮糙(抹前用水喷湿墙面) | D17: 1、清理基层，抹灰，材料制备，成品保护等，2、其他详见设计图纸未详尽列举的图纸、方案事项均包含在综合单价中；3.该项包含本项工作所有工作内容含垂直运输机械等，未详尽列举特征，详见施工图纸、设计规范、施工方案事项均包含在综合单价中。 | E17: m2 | F17: 42.11 | G17: 35 | H17: =ROUND(F17*G17,2) -> 1473.85 | I17: =R17 -> 174.1 | J17: =F17*I17 -> 7331.35 | K17: 以平方米计量，按设计图示长度乘高度以面积计算 | L17: 全费用综合单价 | O17: =400*1.6*1.05*0.015+15 -> 25.08 | P17: =12*10 -> 120 | Q17: =N17+O17+P17 -> 145.08 | R17: =Q17*$R$4 -> 174.1 | T17: 174.1 | U17: =T17-I17 -> 0
A18: 12 | B18: 地砖踢脚 | C18: 1、粘贴10厚地砖,专用勾缝剂勾缝 2、9厚1:2水泥砂浆(内掺3%超密聚合物防水剂)粘结层 3、素水泥浆一道(内掺建筑胶) | D18: 1、清理基层、面层铺贴、成品保护及半成品保护，材料运输，养护抛光等。2、部位：水磨石楼地面含水磨石踢脚3、其它:该项包含本项工作所有工作内容含垂直运输机械等，未详尽列举特征，详见施工图纸、设计规范、施工方案事项均包含在综合单价中。 | E18: m2 | F18: 150.88 | G18: 130 | H18: =ROUND(F18*G18,2) -> 19614.4 | I18: =R18 -> 233.83 | J18: =F18*I18 -> 35280.27 | K18: 以平方米计量，按设计图示长度乘高度以面积计算 | L18: 全费用综合单价 | N18: =主材表!L9 -> 68.14 | O18: =400*1.6*1.05*0.01 -> 6.72 | P18: =12*10 -> 120 | Q18: =N18+O18+P18 -> 194.86 | R18: =Q18*$R$4 -> 233.83 | T18: 233.83 | U18: =T18-I18 -> 0
A19: 13 | B19: 金属踢脚(高100) | C19: 1、1.0厚不锈钢金属踢脚板,下端用水泥钉钉入地面垫层,中距300 2、10厚1:3水泥砂浆压实抹平 3、素水泥浆一道(内掺建筑胶)(用于混凝土空心砌块墙);3厚外加剂专用砂浆抹基底刮糙(抹灰前用水喷湿墙面)(用于蒸 压加气混凝土砌块墙) 4、水泥钉固定踢脚上端,中距300 | D19: 1.粘贴层厚度、材料种类:铝合金踢脚卡，水泥钉固定在墙内防腐耐火砖上； 2.面层材料品种、规格、颜色:详见设计图纸 3.其它:该项包含本项工作所有工作内容含垂直运输机械等，未详尽列举特征，详见施工图纸、设计规范、施工方案事项均包含在综合单价中。 | E19: m2 | F19: 99.99 | G19: 272.98 | H19: =ROUND(F19*G19,2) -> 27295.27 | I19: =R19 -> 519.74 | J19: =F19*I19 -> 51968.8 | K19: 以平方米计量，按设计图示长度乘高度以面积计算 | L19: 全费用综合单价 | N19: =主材表!L25 -> 301.62 | O19: =8+3.5 -> 11.5 | P19: =20+100 -> 120 | Q19: =N19+O19+P19 -> 433.12 | R19: =Q19*$R$4 -> 519.74 | T19: 519.74 | U19: =T19-I19 -> 0
A20: 14 | B20: 无机涂料墙面 | C20: 1、喷(刷、辊)无机内墙薄涂涂料2道 2、满刮2厚腻子砂磨平 3、其他：该项包含本项工作所有工作内容含垂直运输机械等，未详尽列举特征，详见施工图纸、设计规范、施工方案事项均包含在综合单价中。 | D20: 1、墙体基层处理；2、刮腻子；3、涂料的制作、运输；4、喷面浆或涂料；5、该项包含涂料墙面的所有工作内容，含垂直运输机械等，未详尽列举特征，详见施工图纸、设计规范、施工方案事项均包含在综合单价中。 | E20: m2 | F20: 4198.38 | G20: 27 | H20: =ROUND(F20*G20,2) -> 113356.26 | I20: =R20 -> 44.4 | J20: =F20*I20 -> 186408.07 | K20: 按设计图示尺寸以面积计算（有吊顶房间算至吊顶底，无吊顶房间算至梁底或者板底） | L20: 全费用综合单价 | N20: 7.5 | O20: 4.5 | P20: 25 | Q20: =N20+O20+P20 -> 37 | R20: =Q20*$R$4 -> 44.4 | T20: 44.4 | U20: =T20-I20 -> 0
A21: 15 | B21: 防水面砖墙面 | C21: 1、同色水泥擦缝 2、8-10厚墙面砖(粘贴前墙砖充分浸湿) 3、8厚1:2水泥砂浆粘结层(内掺建筑胶) 4、缝宽、嵌缝材料：按甲方要求嵌缝、打胶； 5、酸洗、打蜡要求：满足设计和相关规范要求； 6、墙面伸缩缝、变形缝的处理； 7、根据安装需要开孔 8、其他：该项包含本项工作所有工作内容含垂直运输机械等，未详尽列举特征，详见施工图纸、设计规范、施工方案事项均包含在综合单价中。； | D21: 1、墙体基层处理；2、水泥砂浆的制作、运输；3、粘贴墙面砖；4、局部部位面砖切割、打磨；5、水泥擦缝；6、该项包含玻化砖墙面的所有工作内容，含垂直运输机械等，未详尽列举特征，详见施工图纸、设计规范、施工方案事项均包含在综合单价中。 | E21: m2 | F21: 1750.02 | G21: 120 | H21: =ROUND(F21*G21,2) -> 210002.4 | I21: =R21 -> 153.02 | J21: =F21*I21 -> 267788.06 | K21: 按设计图示尺寸以面积计算（有吊顶房间算至吊顶底） | L21: 全费用综合单价 | N21: =主材表!L10 -> 57.52 | O21: 10 | P21: 60 | Q21: =N21+O21+P21 -> 127.52 | R21: =Q21*$R$4 -> 153.02 | T21: 153.02 | U21: =T21-I21 -> 0
A22: 16 | B22: 干挂铝板墙面（含消防暗门） | C22: 1、2.5厚铝合金饰面面层,接缝处密缝(或10*10MM凹槽);(3 米以下加肋,衬6mm厚硅酸钙板)。 2、金属板材用抽芯铆钉或自攻螺钉固定于铝方型材纵横方向龙骨上,板材带折边采用搭接式,带挂耳采用对接式; 3、60X40X4铝方型材龙骨,横向间距同金属板材宽度,纵向间距同金属板材长度,用螺栓与角钢连接。 4、8#槽钢竖向龙骨连接件螺栓连接, 5、连接件与预埋板焊接 6、预埋件 7、墙面伸缩缝、变形缝； 其他：该项包含本项工作所有工作内容含垂直运输机械等，未详尽列举特征，详见施工图纸、设计规范、施工方案事项均包含在综合单价中。； | D22: 1、铝板下料；2、铝单板干挂；3、铝单板上铝格栅粘贴；4、与石材楼面接缝的处理；5、该项包含本项工作所有工作内容含垂直运输机械等，未详尽列举特征，详见施工图纸、设计规范、施工方案事项均包含在综合单价中。 | E22: m2 | F22: 5752.72 | G22: 120 | H22: =ROUND(F22*G22,2) -> 690326.4 | I22: =R22 -> 177 | J22: =F22*I22 -> 1018231.4 | K22: 按设计图示尺寸以面积计算 | L22: 1、除型钢龙骨及甲供材外全费用综合单价； 2、甲供材：铝板 | M22: 甲供材料：铝板 | N22: 0 | O22: =22+5.5 -> 27.5 | P22: 120 | Q22: =N22+O22+P22 -> 147.5 | R22: =Q22*$R$4 -> 177 | S22: =(5.45*1.3+8.045*0.55)/(1.2*0.55) -> 17.44 | T22: 177 | U22: =T22-I22 -> 0
A23: 17 | B23: 耐擦洗涂料墙面 | C23: 1、防火型无机耐擦洗涂料两道饰面(白色) 2、满刮2厚耐水腻子找平 3、其他：该项包含本项工作所有工作内容含垂直运输机械等，未详尽列举特征，详见施工图纸、设计规范、施工方案事项均包含在综合单价中。； | D23: 1、墙体基层处理；2、刮腻子；3、涂料的制作、运输；4、喷面浆或涂料；5、该项包含涂料墙面的所有工作内容，含垂直运输机械等，未详尽列举特征，详见施工图纸、设计规范、施工方案事项均包含在综合单价中。 | E23: m2 | F23: 1745.67 | G23: 30 | H23: =ROUND(F23*G23,2) -> 52370.1 | I23: =R23 -> 44.4 | J23: =F23*I23 -> 77507.75 | K23: 按设计图示尺寸以面积计算（有吊顶房间算至吊顶底，无吊顶房间算至梁底或者板底） | L23: 全费用综合单价 | N23: =$N$20 -> 7.5 | O23: 4.5 | P23: =$P$20 -> 25 | Q23: =N23+O23+P23 -> 37 | R23: =Q23*$R$4 -> 44.4 | T23: 44.4 | U23: =T23-I23 -> 0
A24: 18 | B24: 穿孔吸声板墙面 | C24: 1、10厚穿孔板用螺钉固定于龙骨上 2、玻璃布一层绷紧固定于龙骨表面 3、40厚岩棉(或玻璃棉)毡,建筑胶粘济粘贴于龙骨档内 4、75X50X0.7轻钢龙骨用膨胀螺栓宇墙面固定,中距按板规格设计 5、1.5厚聚合物水泥防水涂膜 6、在混凝土梁、柱或现浇混凝土条带、砌块上钻孔打入M6X75膨胀螺栓,中距按穿孔板规格设计 7、6~9厚DP-HR砂浆修补墙面抹平 8、3厚外加剂专用砂浆抹基底,抹前喷湿墙面(用于加气混凝土砌块墙) 9、墙面伸缩缝、变形缝； 其他：该项包含本项工作所有工作内容含垂直运输机械等，未详尽列举特征，详见施工图纸、设计规范、施工方案事项均包含在综合单价中。 | D24: 1、天棚基层处理；2、后置件、骨架的制作、运输、安装；3、硅酸钙板安装；4、表面涂刷乳胶漆，压条安装；5、该项包含硅酸钙板吊顶的所有工作内容，含垂直运输机械等，未详尽列举特征，详见施工图纸、设计规范、施工方案事项均包含在综合单价中。 | E24: m2 | F24: 386.43 | G24: 136.53 | H24: =ROUND(F24*G24,2) -> 52759.29 | I24: =R24 -> 294.36 | J24: =F24*I24 -> 113749.53 | K24: 按设计图示尺寸以硅酸钙板吊顶水平投影面积计算 | L24: 全费用综合单价 | N24: =主材表!L27 -> 70.8 | O24: =16+28+18+5.5 -> 67.5 | P24: =6+30+6+65 -> 107 | Q24: =N24+O24+P24 -> 245.3 | R24: =Q24*$R$4 -> 294.36 | T24: 294.36 | U24: =T24-I24 -> 0
A25: 19 | B25: 穿孔山水纹样铝单板墙面（含消防暗门） | C25: 1、穿孔山水纹样铝单板 2、金属板材用抽芯铆钉或自攻螺钉固定于铝方型材纵横方向龙骨上,板材带折边采用搭接式,带挂耳采用对接式; 3、60X40X4铝方型材龙骨,横向间距同金属板材宽度,纵向间距同金属板材长度,用螺栓与角钢连接。 4、8#槽钢竖向龙骨连接件螺栓连接, 5、连接件与预埋板焊接 6、预埋件 7、墙面伸缩缝、变形缝； 其他：该项包含本项工作所有工作内容含垂直运输机械等，未详尽列举特征，详见施工图纸、设计规范、施工方案事项均包含在综合单价中。； | D25: 1、后置件、骨架的制作、运输、安装；2、铝板下料；3、铝单板干挂；4、铝单板上铝格栅粘贴；5、与石材楼面接缝的处理；6、该项包含本项工作所有工作内容含垂直运输机械等，未详尽列举特征，详见施工图纸、设计规范、施工方案事项均包含在综合单价中。 | E25: m2 | F25: 457.25 | G25: 120 | H25: =ROUND(F25*G25,2) -> 54870 | I25: =R25 -> 181.8 | J25: =F25*I25 -> 83128.05 | K25: 按设计图示尺寸以室外可视铝板面积计算，其中：铝板梁面和铝单板吊顶分界线为最内侧的垂直方向的铝单板边线 | L25: 1、除型钢龙骨及甲供材外全费用综合单价； 2、甲供材：铝板 | O25: =26+5.5 -> 31.5 | P25: =$P$22 -> 120 | Q25: =N25+O25+P25 -> 151.5 | R25: =Q25*$R$4 -> 181.8 | S25: =_xlfn.DISPIMG("ID_4771296B097B4BBBA094ED4C648C6B3B",1) -> =DISPIMG("ID_4771296B097B4BBBA094ED4C648C6B3B",1) | T25: 181.8 | U25: =T25-I25 -> 0
A26: 20 | B26: 鱼骨纹木色铝板墙面（含消防暗门） | C26: 1、鱼骨纹木色铝板 2、金属板材用抽芯铆钉或自攻螺钉固定于铝方型材纵横方向龙骨上,板材带折边采用搭接式,带挂耳采用对接式; 3、60X40X4铝方型材龙骨,横向间距同金属板材宽度,纵向间距同金属板材长度,用螺栓与角钢连接。 4、8#槽钢竖向龙骨连接件螺栓连接, 5、连接件与预埋板焊接 6、预埋件 7、墙面伸缩缝、变形缝； 其他：该项包含本项工作所有工作内容含垂直运输机械等，未详尽列举特征，详见施工图纸、设计规范、施工方案事项均包含在综合单价中。； | D26: 1、后置件、骨架的制作、运输、安装；2、铝板下料；3、铝单板干挂；4、铝单板上铝格栅粘贴；5、与石材楼面接缝的处理；6、该项包含本项工作所有工作内容含垂直运输机械等，未详尽列举特征，详见施工图纸、设计规范、施工方案事项均包含在综合单价中。 | E26: m2 | F26: 28.16 | G26: 120 | H26: =ROUND(F26*G26,2) -> 3379.2 | I26: =$I$22 -> 177 | J26: =F26*I26 -> 4984.32 | K26: 按设计图示尺寸以室外可视铝板面积计算，其中：铝板梁面和铝单板吊顶分界线为最内侧的垂直方向的铝单板边线 | L26: 1、除型钢龙骨及甲供材外全费用综合单价； 2、甲供材：铝板 | S26: =_xlfn.DISPIMG("ID_8AFDA53BCB7C4881B934B1C0D89D3540",1) -> =DISPIMG("ID_8AFDA53BCB7C4881B934B1C0D89D3540",1) | T26: 177 | U26: =T26-I26 -> 0
A27: 21 | B27: 无机涂料吸音顶棚 | C27: 1、无机涂料 2、20厚矿物纤维吸声涂层 3、其他：该项包含本项工作所有工作内容含垂直运输机械等，未详尽列举特征，详见施工图纸、设计规范、施工方案事项均包含在综合单价中。 | D27: 1、墙体基层处理；2、刮腻子；3、涂料的制作、运输；4、矿物纤维吸声喷涂、喷面浆或涂料；5、该项包含涂料墙面的所有工作内容，含垂直运输机械等，未详尽列举特征，详见施工图纸、设计规范、施工方案事项均包含在综合单价中。 | E27: m2 | F27: 457.93 | G27: 32 | H27: =ROUND(F27*G27,2) -> 14653.76 | I27: =R27 -> 44.4 | J27: =F27*I27 -> 20332.09 | K27: 按设计图示尺寸以水平投影面积计算 | L27: 全费用综合单价 | N27: =$N$20 -> 7.5 | O27: 4.5 | P27: =$P$20 -> 25 | Q27: =N27+O27+P27 -> 37 | R27: =Q27*$R$4 -> 44.4 | T27: 44.4 | U27: =T27-I27 -> 0
A28: 22 | B28: 无机涂料顶棚 | C28: 1、防火型无机耐擦洗涂料两道饰面(白色) 2、2厚面层耐水腻子刮平 3、其他：该项包含本项工作所有工作内容含垂直运输机械等，未详尽列举特征，详见施工图纸、设计规范、施工方案事项均包含在综合单价中。 | D28: 1、墙体基层处理；2、刮腻子；3、涂料的制作、运输；4、喷面浆或涂料；5、该项包含涂料墙面的所有工作内容，含垂直运输机械等，未详尽列举特征，详见施工图纸、设计规范、施工方案事项均包含在综合单价中。 | E28: m2 | F28: 705.44 | G28: 32 | H28: =ROUND(F28*G28,2) -> 22574.08 | I28: =$I$27 -> 44.4 | J28: =F28*I28 -> 31321.54 | K28: 按设计图示尺寸以水平投影面积计算 | L28: 全费用综合单价 | T28: 44.4 | U28: =T28-I28 -> 0
A29: 23 | B29: 铝合金扣板顶棚 | C29: 1、600*600*1.0铝合金扣板(折边20) 2、与铝合金扣板配套的专用暗架龙骨,间距≤300,通过十字连扣连接件与承载龙骨连接 3、D38承载龙骨,间距≤1200,用吊杆与钢筋吊杆联结后找平 4、10厚镀锌低碳钢丝(或%%C8钢筋)吊杆,双向中距≤1200,吊杆上部与板底(或钢结构)预留吊环(勾)固定 5、结构层预埋%%C10(或钢结构预留)钢筋吊环(勾),双向中距≤1200 6、天棚伸缩缝、变形缝； 其他：该项包含本项工作所有工作内容含垂直运输机械等，未详尽列举特征，详见施工图纸、设计规范、施工方案事项均包含在综合单价中。 | D29: 1、吊杆的制作、运输、安装；2、铝板下料； 3、铝扣板安装以及与墙柱面接缝处理； 4、未详尽列举的图纸、方案事项均包含在综合单价中 5.该项包含本项工作所有工作内容含垂直运输机械等，未详尽列举特征，详见施工图纸、设计规范、施工方案事项均包含在综合单价中。 | E29: m2 | F29: 602.16 | G29: 136.14 | H29: =ROUND(F29*G29,2) -> 81978.06 | I29: =R29 -> 160.04 | J29: =F29*I29 -> 96369.69 | K29: 按设计图示尺寸以投影面积计算 | L29: 除型钢龙骨、转换层外的全费用综合单价 | N29: =主材表!L29 -> 66.37 | O29: 22 | P29: 45 | Q29: =N29+O29+P29 -> 133.37 | R29: =Q29*$R$4 -> 160.04 | T29: 160.04 | U29: =T29-I29 -> 0
A30: 24 | B30: 硅酸钙板面层板吊顶 | C30: 1、喷(刷、辊)涂料面层两遍(每道间隔2小时) 2、封底漆一道(干燥后再做面层) 3、满刮2厚面层耐水腻子找平,板面接缝处贴嵌缝带,刮腻子抹平 4、错缝粘贴第二层9.5厚耐水耐火纸面石膏板 5、双层6mm厚硅酸钙板用自攻螺丝与龙骨固定,中距≤200,螺丝距板长边≥10,短边≥15 6、U型轻钢覆面横撑龙骨CB60x27,间距1200,用挂插件与次龙骨联结 7、U型轻钢覆面次龙骨CB60x27,间距400,用挂件与承接龙骨联结 8、U型轻钢承接龙骨CS50x15,间距≤1200,用吊杆与钢筋吊杆联结后找平 9、%%C8钢筋吊杆并加反支撑,双向中距≤1200,吊杆上部与预留钢筋吊环固定 10、现浇钢筋混凝土板底预埋%%C10钢筋吊环(勾),双向中距≤1200(转换层另列） 11、天棚伸缩缝、变形缝； 其他：该项包含本项工作所有工作内容含垂直运输机械等，未详尽列举特征，详见施工图纸、设计规范、施工方案事项均包含在综合单价中。 | D30: 1、天棚基层处理；2、后置件、骨架的制作、运输、安装；3、硅酸钙板安装；4、表面涂刷乳胶漆，压条安装；5、该项包含硅酸钙板吊顶的所有工作内容，含垂直运输机械等，未详尽列举特征，详见施工图纸、设计规范、施工方案事项均包含在综合单价中。 | E30: m2 | F30: 1343.7 | G30: 185.86 | H30: =ROUND(F30*G30,2) -> 249740.08 | I30: =R30 -> 348 | J30: =F30*I30 -> 467607.6 | K30: 按设计图示尺寸以硅酸钙板吊顶水平投影面积计算 | L30: 全费用综合单价 | N30: 7.5 | O30: =65+28+26+10+4.5 -> 133.5 | P30: =55+30+20+18+26 -> 149 | Q30: =N30+O30+P30 -> 290 | R30: =Q30*$R$4 -> 348 | T30: 348 | U30: =T30-I30 -> 0
A31: 25 | B31: 铝合金单板(穿孔铝板2.5厚)装饰吊顶（候车大厅） | C31: 1、2.5厚铝合金单板与配套专用龙骨固定 2、与铝合金单板配套的专用下层副龙骨联结,间距≤600 3、与安装型式配套的专用上层主龙骨,间距≤1200,用吊件与钢筋吊杆联结后找平 4、10号镀锌低碳钢丝(或%%C8钢筋)吊杆,双向中距≤1200,吊杆上部与板底预留吊环固定 5、现浇钢筋混凝土板底预留%%C10钢筋吊环,双向中距≤1200 6、天棚伸缩缝、变形缝； 其他：该项包含本项工作所有工作内容含垂直运输机械等，未详尽列举特征，详见施工图纸、设计规范、施工方案事项均包含在综合单价中。 | D31: 1、钢结构转换层制作、安装；2、安装龙骨；3、铝单板片面层安装；4、该项包含本项工作所有工作内容含垂直运输机械等，未详尽列举特征，详见施工图纸、设计规范、施工方案事项均包含在综合单价中。 | E31: m2 | F31: 1195.5 | G31: 135 | H31: =ROUND(F31*G31,2) -> 161392.5 | I31: =R31 -> 182.4 | J31: =F31*I31 -> 218059.2 | K31: 按铝单板吊顶的水平投影面积计算 | L31: 1、除型钢龙骨及甲供材外全费用综合单价； 2、甲供材：铝板 | N31: 0 | O31: 22 | P31: 130 | Q31: =N31+O31+P31 -> 152 | R31: =Q31*$R$4 -> 182.4 | T31: 182.4 | U31: =T31-I31 -> 0
A32: 26 | B32: 铝合金单板(穿孔铝板3厚)装饰吊顶（候车大厅） | C32: 1、3厚铝合金单板与配套专用龙骨固定 2、与铝合金单板配套的专用下层副龙骨联结,间距≤600 3、与安装型式配套的专用上层主龙骨,间距≤1200,用吊件与钢筋吊杆联结后找平 4、10号镀锌低碳钢丝(或%%C8钢筋)吊杆,双向中距≤1200,吊杆上部与板底预留吊环固定 5、现浇钢筋混凝土板底预留%%C10钢筋吊环,双向中距≤1200 6、天棚伸缩缝、变形缝； 其他：该项包含本项工作所有工作内容含垂直运输机械等，未详尽列举特征，详见施工图纸、设计规范、施工方案事项均包含在综合单价中。 | D32: 1、钢结构转换层制作、安装；2、安装龙骨；3、铝单板片面层安装；4、该项包含本项工作所有工作内容含垂直运输机械等，未详尽列举特征，详见施工图纸、设计规范、施工方案事项均包含在综合单价中。 | E32: m2 | F32: 2722.94 | G32: 135 | H32: =ROUND(F32*G32,2) -> 367596.9 | I32: =$I$31 -> 182.4 | J32: =F32*I32 -> 496664.26 | K32: 按铝单板吊顶的水平投影面积计算 | L32: 1、除型钢龙骨及甲供材外全费用综合单价； 2、甲供材：铝板 | T32: 182.4 | U32: =T32-I32 -> 0
A33: 27 | B33: 铝合金条板(锤片)吊顶（候车大厅） | C33: 1、铝合金条板与配套专用龙骨固定(宽150mm,缝75mm,厚1mm) 2、与铝合金方通配套的专用龙骨,间距≤1200,用吊件与钢筋吊杆连接后找平 3、10号镀锌低碳钢丝(或%%C6钢筋)吊杆,双向中距≤1200,吊杆上部与板底预留吊环(勾)固定 4、现浇钢筋混凝土板底预留%%C10钢筋吊环(勾),双向中距≤1200(吊杆长度超过1.5米后需要做反支撑,吊杆长度超过2.5米需做转换层,做法详见二次结构施工安装详图)(转换层另列） 5、天棚伸缩缝、变形缝； 其他：该项包含本项工作所有工作内容含垂直运输机械等，未详尽列举特征，详见施工图纸、设计规范、施工方案事项均包含在综合单价中。； | D33: 基层清理；吊杆制作；吊杆、龙骨安装；面板固定、安装；洞口、检查孔、灯槽等留置、处理及收边收口，按照图纸要求吊顶四周设置圆形收边条、顶棚喷黑处理；材料场内运输；脚手架搭拆，成品保护等。该项包含本项工作所有工作内容含垂直运输机械等，未详尽列举特征，详见施工图纸、设计规范、施工方案事项均包含在综合单价中。 | E33: m2 | F33: 27.2 | G33: 125 | H33: =ROUND(F33*G33,2) -> 3400 | I33: =R33 -> 182.4 | J33: =F33*I33 -> 4961.28 | K33: 按设计图示尺寸以水平投影面积计算 | L33: 1、除型钢龙骨及甲供材外全费用综合单价； 2、甲供材：铝合金条板 | N33: 0 | O33: 22 | P33: 130 | Q33: =N33+O33+P33 -> 152 | R33: =Q33*$R$4 -> 182.4 | T33: 182.4 | U33: =T33-I33 -> 0
A34: 28 | B34: 天棚喷刷深灰色涂料 | C34: 1、基层类型：砼天棚；2、深灰A级无机涂料喷涂，厚度、装饰效果满足设计要求3、超高增加的措施费用 | D34: [工作内容] 1.基层清理 2.刮腻子 3.刷、喷涂料 | E34: m2 | F34: 922.73 | G34: 12.89 | H34: =ROUND(F34*G34,2) -> 11893.99 | I34: =R34 -> 24.6 | J34: =F34*I34 -> 22699.16 | K34: 按GB 50854-2013工程量计算规范计算 | L34: 此项工作的全费用综合单价 | N34: 8.5 | P34: 12 | Q34: =N34+O34+P34 -> 20.5 | R34: =Q34*$R$4 -> 24.6 | T34: 24.6 | U34: =T34-I34 -> 0
A35: 29 | B35: 洗漱台 | C35: 1、部位：具体详设计图纸要求； 2、石材规格：综合详见图纸； 3、2.5mm铝单板挡板 4、台面、挡水 5、其它：满足设计规范及图纸要求。 | D35: 1.洗漱台面层石材制作、运输、铺贴 2.铝板安装、收边收口 3.材料的运输、摆放、清运及场内多次搬运； 4.对已施工完成的成品及其他专业已完成的成品进行保护工作，无论是否由该单位导致的损坏，该单位都应履行修复处理责任； 5.对施工需要拆除或移动的材料，待施工完毕后，恢复原状； 6.完成工作区域的安全文明施工,清理施工遗留下的垃圾； 7、该项包含本项工作所有工作内容含垂直运输机械等，未详尽列举特征，详见施工图纸、设计规范、施工方案事项均包含在综合单价中。 | E35: m | F35: 41.85 | G35: 420.78 | H35: =ROUND(F35*G35,2) -> 17609.64 | I35: =R35 -> 639.9 | J35: =F35*I35 -> 26779.82 | K35: 按设计图示以米计算 | L35: 除基层龙骨外，此项工作的全费用综合单价 | N35: =350*0.64+主材表!L26*0.55 -> 343.25 | O35: =10 -> 10 | P35: 180 | Q35: =N35+O35+P35 -> 533.25 | R35: =Q35*$R$4 -> 639.9 | S35: =_xlfn.DISPIMG("ID_D9027A23E9374EC3A029BBD590E7A70F",1) -> =DISPIMG("ID_D9027A23E9374EC3A029BBD590E7A70F",1) | T35: 639.9 | U35: =T35-I35 -> 0
A36: 30 | B36: 镜面玻璃 | C36: 1.30*30mm方管龙骨（刷防火、防腐） 2.6mm厚双层硅酸钙板基层（涂刷防腐） 3.5mm厚银镜及安装。 4.顶部及底部LED贴片灯带、灯槽制作安装 5.不锈钢边框包边；6.完成该项工作所需的全部工作内容 | D36: [工作内容] 1.基层安装 2.玻璃及框制作、运输、安装 3.该项包含本项工作所有工作内容含垂直运输机械等，未详尽列举特征，详见施工图纸、设计规范、施工方案事项均包含在综合单价中。 | E36: m2 | F36: 54.84 | G36: 220 | H36: =ROUND(F36*G36,2) -> 12064.8 | I36: =R36 -> 526.8 | J36: =F36*I36 -> 28889.71 | K36: 按设计图示尺寸以面积计算 | L36: 除基层龙骨外，此项工作的全费用综合单价 | N36: =5.5*35+75 -> 267.5 | O36: =30+26+5.5 -> 61.5 | P36: =35+20+55 -> 110 | Q36: =N36+O36+P36 -> 439 | R36: =Q36*$R$4 -> 526.8 | S36: =(1.2*2+1.3*2)/1.2*1.3 -> 5.42 | T36: 526.8 | U36: =T36-I36 -> 0
A37: 31 | B37: 蹲位隔断 | C37: 1.50*4不锈钢角码固定隔板，膨胀螺丝与墙面固定 2.20mm厚金属复合板制作安装，含不锈钢挂衣钩固定安装； 3.复合板面不锈钢把手、不锈钢锁（红绿）隔门不锈钢合页安装； 4.隔板交接处50*4不锈钢角码纵向安装，专用平头螺丝固定，隔板与地面交接位置装100mm高不锈钢踢脚，防水胶嵌缝，2mm厚不锈钢U形抵扣封边； 5.未尽部分详见图纸； 6.完成该项工作所需的全部工作内容，完成工作区域的安全文明施工,清理施工遗留下的垃圾。 | D37: [工作内容] 1.隔断运输、安装 2.嵌缝、塞口 3.该项包含本项工作所有工作内容含垂直运输机械等，未详尽列举特征，详见施工图纸、设计规范、施工方案事项均包含在综合单价中。 | E37: 间 | F37: 66 | G37: 1250 | H37: =ROUND(F37*G37,2) -> 82500 | I37: =R37 -> 3490.32 | J37: =F37*I37 -> 230361.12 | K37: 以间计量，按设计间的数量计算。 | L37: 除基层龙骨外，此项工作的全费用综合单价 | M37: 市场不含税成本单价385元一平米，平均每个蹲位7.46㎡， | N37: =主材表!L19*7.46 -> 2872.1 | O37: 1.5 | P37: 35 | Q37: =N37+O37+P37 -> 2908.6 | R37: =Q37*$R$4 -> 3490.32 | S37: =2.8*3 -> 8.4 | T37: 3490.32 | U37: =T37-I37 -> 0
A38: 32 | B38: 小便斗隔板 | C38: 1.50*4不锈钢角码固定隔板，膨胀螺丝与墙面固定 2.20mm厚金属复合板制作安装 3.完成该项工作所需的全部工作内容，完成工作区域的安全文明施工,清理施工遗留下的垃圾。 | D38: [工作内容] 1.隔断运输、安装 2.嵌缝、塞口 3.该项包含本项工作所有工作内容含垂直运输机械等，未详尽列举特征，详见施工图纸、设计规范、施工方案事项均包含在综合单价中。 | E38: 间 | F38: 26 | G38: 265 | H38: =ROUND(F38*G38,2) -> 6890 | I38: =R38 -> 254.09 | J38: =F38*I38 -> 6606.34 | K38: 以间计量，按设计间的数量计算。 | L38: 全费用综合单价 | N38: =385*1.06*0.4 -> 163.24 | O38: 3.5 | P38: 45 | Q38: =N38+O38+P38 -> 211.74 | R38: =Q38*$R$4 -> 254.09 | T38: 254.09 | U38: =T38-I38 -> 0
A39: 33 | B39: 卫生纸盒 | C39: 1、成品304#不锈钢嵌入纸巾盒（抽纸盒垃圾箱一体）2、完成该项工作所需的全部工作内容，完成工作区域的安全文明施工,清理施工遗留下的垃圾。 | D39: [工作内容] 1.台面及支架制作、运输、安装 2.杆、环、盒、螺栓等配件安装 3.刷油漆 4.该项包含本项工作所有工作内容含垂直运输机械等，未详尽列举特征，详见施工图纸、设计规范、施工方案事项均包含在综合单价中。 | E39: 个 | F39: 59 | G39: 12.6 | H39: =ROUND(F39*G39,2) -> 743.4 | I39: =R39 -> 72.6 | J39: =F39*I39 -> 4283.4 | K39: 按设计图示个数以个计算 | L39: 全费用综合单价 | N39: 42 | O39: 0.5 | P39: 18 | Q39: =N39+O39+P39 -> 60.5 | R39: =Q39*$R$4 -> 72.6 | T39: 72.6 | U39: =T39-I39 -> 0
A40: 34 | B40: 烘手器 | C40: 1、成品烘手器安装；2.完成该项工作所需的全部工作内容，完成工作区域的安全文明施工,清理施工遗留下的垃圾。 | D40: [工作内容] 1.台面及支架制作、运输、安装 2.杆、环、盒、配件安装 3.刷油漆 4.该项包含本项工作所有工作内容含垂直运输机械等，未详尽列举特征，详见施工图纸、设计规范、施工方案事项均包含在综合单价中。 | E40: 副 | F40: 16 | G40: 417.6 | H40: =ROUND(F40*G40,2) -> 6681.6 | I40: =R40 -> 369 | J40: =F40*I40 -> 5904 | K40: 按设计图示以数量计算 | L40: 全费用综合单价 | N40: 288 | O40: 1.5 | P40: 18 | Q40: =N40+O40+P40 -> 307.5 | R40: =Q40*$R$4 -> 369 | T40: 369 | U40: =T40-I40 -> 0
A41: 35 | B41: 小便池石材台面 | C41: 1.30*30*3镀锌方管龙骨（刷防火、防腐） 2.人造石台面及侧台面安装，接缝处防水处理；3.完成该项工作所需的全部工作内容，完成工作区域的安全文明施工,清理施工遗留下的垃圾。 | D41: [工作内容] 1.基层清理 2.抹找平层 3.窗台板制作、安装 4.该项包含本项工作所有工作内容含垂直运输机械等，未详尽列举特征，详见施工图纸、设计规范、施工方案事项均包含在综合单价中。 | E41: m2 | F41: 1.84 | G41: 517.56 | H41: =ROUND(F41*G41,2) -> 952.31 | I41: =R41 -> 660 | J41: =F41*I41 -> 1214.4 | K41: 按设计图示尺寸以面积计算 | L41: 除基层龙骨外，此项工作的全费用综合单价 | N41: =(主材表!L16*0.25+2.5)*4 -> 360 | O41: 10 | P41: =45*4 -> 180 | Q41: =N41+O41+P41 -> 550 | R41: =Q41*$R$4 -> 660 | T41: 660 | U41: =T41-I41 -> 0
A42: 36 | B42: 1.1 米高玻璃栏板 | C42: 1、1.1米高玻璃栏板 2、玻璃栏板不锈钢方管立柱63*25*5mm拉丝不锈钢管 3、玻璃栏板扶手φ63*3mm异形拉丝不锈钢圆管 4、玻璃栏板防撞栏杆φ51*1.5不锈钢圆管 5、其他：该项包含本项工作所有工作内容含垂直运输机械等，未详尽列举特征，详见施工图纸、设计规范、施工方案事项均包含在综合单价中。 | D42: 1.预埋件制作、运输、埋设安装； 2.玻璃栏板制作、运输、安装、防护，安装驳接爪； 3.综合单价含栏板送样的材料费用、检验、试验等费用; 4.材料的运输、摆放、清运及场内多次搬运； 5.对已施工完成的成品及其他专业已完成的成品进行保护工作，无论是否由该单位导致的损坏，该单位都应履行修复处理责任； 6.对施工需要拆除或移动的材料，待施工完毕后，恢复原状； 7.完成工作区域的安全文明施工,清理施工遗留下的垃圾； 8.该项包含本项工作所有工作内容含垂直运输机械等，未详尽列举特征，详见施工图纸、设计规范、施工方案事项均包含在综合单价中。 | E42: m | F42: 14.81 | G42: 692.73 | H42: =ROUND(F42*G42,2) -> 10259.33 | I42: =R42 -> 986.77 | J42: =F42*I42 -> 14614.06 | K42: 按设计图示尺寸以长度计算 | L42: 全费用综合单价 | N42: =主材表!$L$46*1.1+主材表!$L$31+主材表!$L$32+主材表!$L$30*1.1 -> 632.31 | O42: 35 | P42: 155 | Q42: =N42+O42+P42 -> 822.31 | R42: =Q42*$R$4 -> 986.77 | S42: =_xlfn.DISPIMG("ID_E3E90E5D0A884FEDA3B1E66253FDD729",1) -> =DISPIMG("ID_E3E90E5D0A884FEDA3B1E66253FDD729",1) | T42: 986.77 | U42: =T42-I42 -> 0
A43: 37 | B43: 2.2 米高玻璃栏板 | C43: 1、2.2米高玻璃栏板 2、玻璃栏板不锈钢型材立柱125*55 3、玻璃栏板8+1.14PVB+8夹胶钢化玻璃 4、50*4防撞栏杆 5、其他：该项包含本项工作所有工作内容含垂直运输机械等，未详尽列举特征，详见施工图纸、设计规范、施工方案事项均包含在综合单价中。 | D43: 1.预埋件制作、运输、埋设安装； 2.玻璃栏板制作、运输、安装、防护，安装驳接爪； 3.综合单价含栏板送样的材料费用、检验、试验等费用; 4.材料的运输、摆放、清运及场内多次搬运； 5.对已施工完成的成品及其他专业已完成的成品进行保护工作，无论是否由该单位导致的损坏，该单位都应履行修复处理责任； 6.对施工需要拆除或移动的材料，待施工完毕后，恢复原状； 7.完成工作区域的安全文明施工,清理施工遗留下的垃圾； 8.该项包含本项工作所有工作内容含垂直运输机械等，未详尽列举特征，详见施工图纸、设计规范、施工方案事项均包含在综合单价中。 | E43: m | F43: 28.75 | G43: 1377.88 | H43: =ROUND(F43*G43,2) -> 39614.05 | I43: =R43 -> 1879.54 | J43: =F43*I43 -> 54036.78 | K43: 按设计图示尺寸以长度计算 | L43: 全费用综合单价 | N43: =主材表!$L$46*2.2+主材表!$L$33*2.2+主材表!$L$32 -> 1336.28 | O43: 45 | P43: 185 | Q43: =N43+O43+P43 -> 1566.28 | R43: =Q43*$R$4 -> 1879.54 | S43: =_xlfn.DISPIMG("ID_D3849F2A30AC49BF9607D10CBD436EBE",1) -> =DISPIMG("ID_D3849F2A30AC49BF9607D10CBD436EBE",1) | T43: 1879.54 | U43: =T43-I43 -> 0
A44: 38 | B44: 玻璃幕墙防撞杆 | C44: 1.直径50*2厚不锈钢防撞杆；2.成品不锈钢支撑；3.5mm不锈钢镀锌钢板安装；4.不锈钢法兰盘固定安装；5.预埋件制作安装；6.材料的水平及垂直转运；7.完成该项工作所需的全部工作内容，完成工作区域的安全文明施工,清理施工遗留下的垃圾。 | D44: [工作内容] 1.预埋件运输、安装 2.杆件、支撑件焊接安装 3.横杆，立杆固定安装 4.刷油漆 5.该项包含本项工作所有工作内容含垂直运输机械等，未详尽列举特征，详见施工图纸、设计规范、施工方案事项均包含在综合单价中。 | E44: m | F44: 306.04 | G44: 71.24 | H44: =ROUND(F44*G44,2) -> 21802.29 | I44: =R44 -> 109.6 | J44: =F44*I44 -> 33541.98 | K44: 按设计图示尺寸以长度计算 | L44: 全费用综合单价 | N44: =主材表!L32 -> 51.33 | O44: 15 | P44: 25 | Q44: =N44+O44+P44 -> 91.33 | R44: =Q44*$R$4 -> 109.6 | S44: =_xlfn.DISPIMG("ID_08154CC2FE7C47388BACBB5121277FEC",1) -> =DISPIMG("ID_08154CC2FE7C47388BACBB5121277FEC",1) | T44: 109.6 | U44: =T44-I44 -> 0
A45: 39 | B45: 防火玻璃隔断（旅客服务房间） | C45: 1、施工部位：旅客服务室外围隔断； 2、面层材料：8HS+1.52PVB+8HS（low-e）+12Ar+27mm全超白中空夹胶防火玻璃（A类，1小时防火），具体施工要求与细部分格等详见图纸及方案，包含通长支座、副框、扣盖、压板、压块、垫块、连接件等，不同规格的钢板等； 3、底部塞防火岩棉、外包1.5mm厚镀锌钢板； 4、底部及顶部采用通长钢U槽连接； 5、接缝、嵌缝及塞口材料：泡沫棒、结构密封胶、耐候密封胶、EPDM胶条、防火胶条等详图纸及方案要求； 6、所有保温防火封堵、不锈钢自攻钉、不锈钢销钉、不锈钢螺栓、断热条、防脱螺钉、硬质玻璃垫块、钢托板、φ12压力间隔套等其他所有辅材需满足图纸及方案要求，其施工费及材料费等均已含在综合单价中； 7、与其他装饰面收口打胶； | D45: 1、防火岩棉及镀锌钢板的制作、运输、安装；2、型材的制作、运输、安装；3、玻璃安装；4、嵌缝、塞口；5、清洗；6、施工区域的安全文明施工；7、该项包含本项工作所有工作内容，未详尽列举的图纸、方案事项均包含在综合单价中 | E45: m2 | F45: 45 | G45: 1429.33 | H45: =ROUND(F45*G45,2) -> 64319.85 | I45: =R45 -> 1243.27 | J45: =F45*I45 -> 55947.15 | K45: 按设计图示尺寸以面积计算 | L45: 全费用综合单价 | N45: =主材表!L47 -> 761.06 | O45: 95 | P45: 180 | Q45: =N45+O45+P45 -> 1036.06 | R45: =Q45*$R$4 -> 1243.27 | S45: =_xlfn.DISPIMG("ID_36D3645EC0554699AB80185D6D5961F6",1) -> =DISPIMG("ID_36D3645EC0554699AB80185D6D5961F6",1) | T45: 1243.27 | U45: =T45-I45 -> 0
A46: 40 | B46: 铝单板门套 | C46: 1、部位：综合考虑，有门、无门部位均按此项计算 2、墙体类型：砼、砖墙综合考虑； 3、骨架种类、规格：型材，规格详见设计图纸，间距应满足施工要求并由投标人综合考虑； 4、面层材料种类、规格：不锈钢； 5、嵌缝、打胶； 6、具体要求详设计图纸 7、根据安装需要开孔 | D46: 1、后置件、骨架的制作、运输、安装；2、铝板下料，安装；3、嵌缝、打胶；4、该项包含不锈钢门套线的所有工作内容，含垂直运输机械等，未详尽列举特征，详见施工图纸、设计规范、施工方案事项均包含在综合单价中。 | E46: m2 | F46: 172.8 | G46: 110 | H46: =ROUND(F46*G46,2) -> 19008 | I46: =R46 -> 226.2 | J46: =F46*I46 -> 39087.36 | K46: 按设计图示尺寸以室外可视铝板面积进行计算 | L46: 除基层龙骨及甲供材外，此项工作的全费用综合单价 | M46: 甲供材：铝板 | O46: 8.5 | P46: 180 | Q46: =N46+O46+P46 -> 188.5 | R46: =Q46*$R$4 -> 226.2 | T46: 226.2 | U46: =T46-I46 -> 0
A47: 41 | B47: 镀锌方管转换层 | C47: 主次龙骨50*50*5镀锌方管、埋板等 | D47: 1.镀锌型钢龙骨转换层、骨架的制作、运输、安装、刷漆 2.该项包含本项工作所有工作内容，含垂直运输机械等，未详尽列举特征，详见施工图纸、设计规范、施工方案事项均包含在综合单价中。 | E47: t | F47: 55.317 | G47: 8726.4 | H47: =ROUND(F47*G47,2) -> 482718.27 | I47: =R47 -> 10536 | J47: =F47*I47 -> 582819.91 | K47: 按设计图示尺寸以实际安装根数以重量计算 | L47: 此项工作的全费用综合单价 | O47: 5500 | P47: 3280 | Q47: =N47+O47+P47 -> 8780 | R47: =Q47*$R$4 -> 10536 | T47: 10536 | U47: =T47-I47 -> 0
A48: 42 | B48: 干挂型钢龙骨 | C48: 1、石材、铝板墙面龙骨、埋板等； 2、骨架种类、规格：具体规格、尺寸、连接方式详见图纸； | D48: 1.镀锌型钢龙骨转换层、骨架的制作、运输、安装、刷漆 2.该项包含本项工作所有工作内容，含垂直运输机械等，未详尽列举特征，详见施工图纸、设计规范、施工方案事项均包含在综合单价中。 | E48: t | F48: 224.74 | G48: 8726.4 | H48: =ROUND(F48*G48,2) -> 1961171.1 | I48: =R48 -> 10536 | J48: =F48*I48 -> 2367860.6 | K48: 按设计图示尺寸以实际安装根数以重量计算 | L48: 此项工作的全费用综合单价 | O48: 5500 | P48: 3280 | Q48: =N48+O48+P48 -> 8780 | R48: =Q48*$R$4 -> 10536 | T48: 10536 | U48: =T48-I48 -> 0
A49: 43 | B49: 残疾人扶手 | C49: 残疾人扶手 | D49: 1.台面及支架运输、安装 2.杆、环、盒、配件安装 3.刷油漆 | E49: 副 | F49: 3 | G49: 123.99 | H49: =ROUND(F49*G49,2) -> 371.97 | I49: =R49 -> 270.6 | J49: =F49*I49 -> 811.8 | K49: 按设计图示尺寸以副计算 | L49: 全费用综合单价 | N49: 190 | O49: 0.5 | P49: 35 | Q49: =N49+O49+P49 -> 225.5 | R49: =Q49*$R$4 -> 270.6 | T49: 270.6 | U49: =T49-I49 -> 0
A50: 44 | B50: 服务台 | C50: 服务台 | D50: 1.部位:综合服务中心 2.材料品种、规格、颜色:人造石台面、人造石立面、镀锌方钢龙骨及阻燃板 3.工作内容：镀锌方钢等龙骨加工制作及安装；基层阻燃板安装固定；人造石台面及立面加工及安装；灯带固定及安装；材料运输，成品及半成品保护等。 4.该项包含本项工作所有工作内容含垂直运输机械等，未详尽列举特征，详见施工图纸、设计规范、施工方案事项均包含在综合单价中。 | E50: m | F50: 16.3 | G50: 4522.11 | H50: =ROUND(F50*G50,2) -> 73710.39 | I50: =R50 -> 2109 | J50: =F50*I50 -> 34376.7 | K50: 按设计图示以中心线长度计算 | L50: 全费用综合单价 | N50: =350*2.5+270 -> 1145 | O50: =65*2.5 -> 162.5 | P50: =180*2.5 -> 450 | Q50: =N50+O50+P50 -> 1757.5 | R50: =Q50*$R$4 -> 2109 | T50: 2109 | U50: =T50-I50 -> 0
A51: 45 | B51: 母婴设施 | C51: 成品母婴设备安装，完成该项工作所需的全部工作内容，完成工作区域的安全文明施工,清理施工遗留下的垃圾。 | D51: [工作内容] 1.台面及支架运输、安装 2.杆、环、盒、配件安装 3.刷油漆 | E51: 套 | F51: 1 | G51: 16920 | H51: =ROUND(F51*G51,2) -> 16920 | I51: =R51 -> 20304 | J51: =F51*I51 -> 20304 | K51: 按设计图示个数以套计算 | L51: 全费用综合单价 | N51: 16920 | Q51: =N51+O51+P51 -> 16920 | R51: =Q51*$R$4 -> 20304 | T51: 20304 | U51: =T51-I51 -> 0
A52: 46 | B52: 置物台 | C52: 1、30*30*3镀锌方管龙骨（刷防火、防腐）2、人造石台面及侧台面安装，接缝处防水处理；3、完成该项工作所需的全部工作内容，完成工作区域的安全文明施工,清理施工遗留下的垃圾。 | D52: [工作内容] 1.基层清理 2.抹找平层 3.窗台板制作、安装 | E52: 个 | F52: 1 | G52: 517.56 | H52: =ROUND(F52*G52,2) -> 517.56 | I52: =R52 -> 726.6 | J52: =F52*I52 -> 726.6 | K52: 按设计图示个数计算 | L52: 全费用综合单价 | N52: =主材表!L15+50 -> 400 | O52: =35+5.5 -> 40.5 | P52: =45+120 -> 165 | Q52: =N52+O52+P52 -> 605.5 | R52: =Q52*$R$4 -> 726.6 | T52: 726.6 | U52: =T52-I52 -> 0
A53: 47 | B53: 软膜灯棚(白色) | C53: 软膜灯带安装 | D53: 1、基层清理，弹线定位。 2、基层龙骨，基层板安装 3、安装透光灯膜 | E53: m2 | F53: 15.67 | G53: 220 | H53: =ROUND(F53*G53,2) -> 3447.4 | I53: =R53 -> 360 | J53: =F53*I53 -> 5641.2 | K53: 按设计图示尺寸以水平投影面积计算。 | L53: 此项工作的全费用综合单价 | N53: 155 | O53: 35 | P53: 110 | Q53: =N53+O53+P53 -> 300 | R53: =Q53*$R$4 -> 360 | S53: =_xlfn.DISPIMG("ID_10D84EC8A17A4709A9059487CDD72CC7",1) -> =DISPIMG("ID_10D84EC8A17A4709A9059487CDD72CC7",1) | T53: 360 | U53: =T53-I53 -> 0
A54: 48 | B54: 2.5mm木色铝单板灯带 | C54: 1、2.5厚木色铝合金单板与配套专用龙骨固定 2、与铝合金单板配套的专用下层副龙骨联结,间距≤600 3、与安装型式配套的专用上层主龙骨,间距≤1200,用吊件与钢筋吊杆联结后找平 4、10号镀锌低碳钢丝(或%%C8钢筋)吊杆,双向中距≤1200,吊杆上部与板底预留吊环固定 5、现浇钢筋混凝土板底预留%%C10钢筋吊环,双向中距≤1200 6、顶棚伸缩缝、变形缝； 其他：该项包含本项工作所有工作内容含垂直运输机械等，未详尽列举特征，详见施工图纸、设计规范、施工方案事项均包含在综合单价中。 | D54: 1.基层处理； 2.龙骨、吊杆安装； 4.铝合金条板面层安装； 5.材料的运输、堆码、清运及场内多次搬运； 6.单价已包括送样的材料费用、检验、试验等工作; 7.配合安装队伍进行多次预留预埋及相关开槽、开洞的修补工作； 8.对已施工完成的成品及其他专业已完成的成品进行保护工作，无论是否由该单位导致的损坏，该单位都应履行修复处理责任； 9.对施工需要拆除或移动的材料，待施工完毕后，恢复原状； 10.完成工作区域的安全文明施工,清理施工遗留下的垃圾。 11.该项包含本项工作所有工作内容，含垂直运输机械等，未详尽列举特征，详见施工图纸、设计规范、施工方案事项均包含在综合单价中。 | E54: m2 | F54: 115.2 | G54: 125 | H54: =ROUND(F54*G54,2) -> 14400 | I54: =R54 -> 242.4 | J54: =F54*I54 -> 27924.48 | K54: 按设计图示尺寸以水平投影面积计算。 | L54: 除型钢龙骨及甲供材外，此项工作的全费用综合单价 | M54: 甲供材：铝单板 | N54: 0 | O54: 22 | P54: 180 | Q54: =N54+O54+P54 -> 202 | R54: =Q54*$R$4 -> 242.4 | T54: 242.4 | U54: =T54-I54 -> 0
A55: 49 | B55: 线性灯槽 | C55: LED灯带制作安装 | D55: [工作内容] 1、LED灯带制作、安装 2、该项包含本项工作所有工作内容含垂直运输机械等，未详尽列举特征，详见施工图纸、设计规范、施工方案事项均包含在综合单价中。 | E55: m | F55: 278.24 | G55: 20 | H55: =ROUND(F55*G55,2) -> 5564.8 | I55: =R55 -> 65.04 | J55: =F55*I55 -> 18096.73 | K55: 按设计图示尺寸以米计算。 | L55: 全费用综合单价 | O55: =(28+10*2)*0.4 -> 19.2 | P55: 35 | Q55: =N55+O55+P55 -> 54.2 | R55: =Q55*$R$4 -> 65.04 | T55: 65.04 | U55: =T55-I55 -> 0
A56: 50 | B56: 电缆沟盖板 | C56: 施工部位：变电所 6mm花纹钢板 | D56: [工作内容] 1.盖板制作、运输、安装 | E56: m2 | F56: 15.6 | G56: 300 | H56: =ROUND(F56*G56,2) -> 4680 | I56: =R56 -> 346.13 | J56: =F56*I56 -> 5399.63 | K56: 按设计图纸尺寸以面积计算 | L56: 此项工作的全费用综合单价 | N56: =47.1*4.85 -> 228.44 | O56: 15 | P56: 45 | Q56: =N56+O56+P56 -> 288.44 | R56: =Q56*$R$4 -> 346.13 | T56: 346.13 | U56: =T56-I56 -> 0
A57: 51 | B57: 集水坑盖板 | C57: 1、M1-150钢板预埋 2、口60*60*5方钢 3、L60*6角钢 4、5mm钢板制作安装 5、20mm厚橡胶胶垫 6、花岗石水篦子铺面 | D57: [工作内容] 1、预埋板制作、安装 2、集水井骨架制作安装 3、20mm橡胶垫安装 4、石材水篦子面板安装 5、该项包含本项工作所有工作内容含垂直运输机械等，未详尽列举特征，详见施工图纸、设计规范、施工方案事项均包含在综合单价中。 | E57: 个 | F57: 5 | G57: 55 | H57: =ROUND(F57*G57,2) -> 275 | I57: =R57 -> 84 | J57: =F57*I57 -> 420 | K57: 按设计图示尺寸以个计算。 | L57: 除基层龙骨、钢材及甲供材外，此项工作的全费用综合单价 甲供材：花岗石 | O57: 5 | P57: 65 | Q57: =N57+O57+P57 -> 70 | R57: =Q57*$R$4 -> 84 | T57: 84 | U57: =T57-I57 -> 0
A58: 52 | B58: 电缆盖板 | C58: 1、5mm厚钢板预埋 2、20mm厚橡胶胶垫 3、花岗石水篦子铺面 | D58: [工作内容] 1、预埋板制作、安装 2、胶垫安装嵌缝、塞口 3、石材水篦子面板安装 4、该项包含本项工作所有工作内容含垂直运输机械等，未详尽列举特征，详见施工图纸、设计规范、施工方案事项均包含在综合单价中。 | E58: m | F58: 88 | G58: 71 | H58: =ROUND(F58*G58,2) -> 6248 | I58: =R58 -> 78 | J58: =F58*I58 -> 6864 | K58: 按设计图示尺寸以米计算。 | L58: 除甲供材外，此项工作的全费用综合单价 甲供材：花岗石 | O58: 15 | P58: 50 | Q58: =N58+O58+P58 -> 65 | R58: =Q58*$R$4 -> 78 | T58: 78 | U58: =T58-I58 -> 0
A59: 53 | B59: 风口百叶 | C59: （1）面板：铝合金百叶； （2）龙骨及连接件：详见施工方案及图纸要求； （3）密封胶：详见施工方案及图纸要求； （4）完成本项目的所需的材料及相应的工序(包括但不限于加工制作、储运、安装、嵌缝、塞口、清洗、试验检测等内容） （5）未详尽列举特征，详见设计图纸、设计规范、施工方案。 | D59: （1）百叶窗安装、防虫网安装，百叶喷涂氟碳漆 （2）包含基层处理（打磨找补清理）、成品保护、负责工作区域的安全文明施工,施工遗留垃圾的清理及外运等； （3）含材料费管理费、措施费、夜间施工费、赶工措施费、安全文明施工费、规费、税金、临近既有线施工费用以及可能出现的人员窝工及机械停滞费用等施工所发生的一切费用 （4）其他未尽事宜详见招标文件技术要求及图纸 | E59: m2 | F59: 9 | G59: 367.83 | H59: =ROUND(F59*G59,2) -> 3310.47 | I59: =R59 -> 510 | J59: =F59*I59 -> 4590 | K59: 按百叶窗的垂直投影面积进行计算 | L59: 全费用综合单价 | N59: 260 | O59: 15 | P59: 150 | Q59: =N59+O59+P59 -> 425 | R59: =Q59*$R$4 -> 510 | T59: 510 | U59: =T59-I59 -> 0
A60: （二） | B60: 进出站通道 | U60: =T60-I60 -> 0
A61: 1 | B61: 花岗石地面 | C61: 1、25厚磨光花岗石,水泥浆擦缝; 2、30厚1:3干硬性水泥砂浆,表面撒水泥粉; 3、地面伸缩缝、变形缝的处理； 其他：该项包含本项工作所有工作内容含垂直运输机械等，未详尽列举特征，详见施工图纸、设计规范、施工方案事项均包含在综合单价中。 | D61: 1、基层清理、打磨；2、砂浆的制作、运输、找平、压实；3、面层的铺贴；4、水泥砂浆擦缝；5、局部部位花岗石切割、打磨； 6、该项包含本项工作所有工作内容含垂直运输机械等，未详尽列举特征，详见施工图纸、设计规范、施工方案事项均包含在综合单价中。 | E61: m2 | F61: 384.65 | G61: 85 | H61: =ROUND(F61*G61,2) -> 32695.25 | I61: =$I$7 -> 118.32 | J61: =F61*I61 -> 45511.79 | K61: 按设计图示尺寸以面积计算 | L61: 1、除甲供材外全费用综合单价； 2、甲供材：石材 | T61: 118.32 | U61: =T61-I61 -> 0
A62: 2 | B62: 25MM 厚深灰麻过门石 | C62: 1、铺25厚磨光花岗石板(六面涂刷石材保护剂),同色稀水泥浆擦 2、50厚1:3干硬性水泥粘结层,撒素水泥粉 3、水泥浆一道(内掺建筑胶) 4、嵌缝材料种类：按甲方要求嵌缝、打胶； 5、防护层材料：防护剂六面处理，满足设计和相关规范要求； 6、酸洗、打蜡要求：满足设计和相关规范要求； 7、楼地面伸缩缝、变形缝的处理； 8、其他：该项包含本项工作所有工作内容含垂直运输机械等，未详尽列举特征，详见施工图纸、设计规范、施工方案事项均包含在综合单价中。 (石材规格800*800) | D62: 1、基层清理、打磨；2、砂浆的制作、运输、找平、压实；3、面层的铺贴；4、水泥砂浆擦缝；5、局部部位过门石切割、打磨； 6、该项包含本项工作所有工作内容含垂直运输机械等，未详尽列举特征，详见施工图纸、设计规范、施工方案事项均包含在综合单价中。 | E62: m2 | F62: 6.14 | G62: 80 | H62: =ROUND(F62*G62,2) -> 491.2 | I62: =$I$16 -> 156 | J62: =F62*I62 -> 957.84 | K62: 按设计图示尺寸以面积计算 | L62: 1、除甲供材外全费用综合单价； 2、甲供材：石材 | T62: 156 | U62: =T62-I62 -> 0
A63: 3 | B63: 石材踢脚 | C63: 1、粘贴10厚石材(板材满涂防污济)专用勾缝剂勾缝 2、12厚1:2水泥砂浆(内掺建筑胶)粘结层 3、素水泥浆一道(内掺建筑胶)(用于混凝土空心砌块墙);界面剂一道(甩前用水喷湿墙面)(用于蒸压加气混凝土砌块墙) | D63: 1、墙体基层处理；2、砂浆的制作、运输、安装；3、石材踢脚卡件固定及不锈钢板面的安装；4、该项包含石材踢脚的所有工作内容，含垂直运输机械等，未详尽列举特征，详见施工图纸、设计规范、施工方案事项均包含在综合单价中。 | E63: m2 | F63: 8.74 | G63: 88 | H63: =ROUND(F63*G63,2) -> 769.12 | I63: =R63 -> 156 | J63: =F63*I63 -> 1363.44 | K63: 按设计图示尺寸以面积计算 | L63: 1、除甲供材外全费用综合单价； 2、甲供材：石材 | N63: 0 | O63: 10 | P63: 120 | Q63: =N63+O63+P63 -> 130 | R63: =Q63*$R$4 -> 156 | T63: 156 | U63: =T63-I63 -> 0
A64: 4 | B64: 干挂花岗岩墙面（含消防暗门） | C64: 1、干挂25mm厚石材墙面（含消防暗门） 2、石材背栓挂件,L50*5角钢连接件与横向龙骨(L50*5角钢)螺栓连接 3、L50*5角钢横向龙骨,与竖向槽钢(8#槽钢)焊接 4、8#槽钢,与连接件焊接, 5、连接件,与预埋件M3焊接 6、预埋件M3 7、墙面伸缩缝、变形缝的处理； 8、根据安装需要开孔 9、其他：该项包含本项工作所有工作内容含垂直运输机械等，未详尽列举特征，详见施工图纸、设计规范、施工方案事项均包含在综合单价中。； | D64: 2.安装方式：干挂 3.面层材料品种、规格、颜色：干挂花岗石石材,表面作晶面处理 4.龙骨材料：竖向主龙骨贯通,固定在墙体上下端(梁或楼板),龙骨截面尺寸根据墙体高度确定,次龙骨在主龙骨之间,龙骨间距依据面材分格尺寸,龙骨刷黑漆 5、该项包含本项工作所有工作内容含垂直运输机械等，未详尽列举特征，详见施工图纸、设计规范、施工方案事项均包含在综合单价中。 | E64: m2 | F64: 239.43 | G64: 150 | H64: =ROUND(F64*G64,2) -> 35914.5 | I64: =R64 -> 255.6 | J64: =F64*I64 -> 61198.31 | K64: 按设计图示尺寸以面积计算（有吊顶房间算至吊顶底，无吊顶房间算至梁底或者板底） | L64: 1、除型钢龙骨甲供材外全费用综合单价； 2、甲供材：花岗石 | N64: 0 | O64: =48+15 -> 63 | P64: 150 | Q64: =N64+O64+P64 -> 213 | R64: =Q64*$R$4 -> 255.6 | S64: =(0.08*4+0.04*2*4.5)*7.85/1.2*1.1 -> 4.89 | T64: 255.6 | U64: =T64-I64 -> 0
A65: 5 | B65: 铝合金单板(穿孔铝板)装饰吊顶 | C65: 1、2.5厚铝合金单板与配套专用龙骨固定 2、与铝合金单板配套的专用下层副龙骨联结,间距≤600 3、与安装型式配套的专用上层主龙骨,间距≤1200,用吊件与钢筋吊杆联结后找平 4、10号镀锌低碳钢丝(或%%C8钢筋)吊杆,双向中距≤1200,吊杆上部与板底预留吊环固定 5、现浇钢筋混凝土板底预留%%C10钢筋吊环,双向中距≤1200 6、天棚伸缩缝、变形缝的处理； 7、根据安装需要开孔 8、其他：该项包含本项工作所有工作内容含垂直运输机械等，未详尽列举特征，详见施工图纸、设计规范、施工方案事项均包含在综合单价中。； | D65: 1、钢结构转换层制作、安装；2、安装龙骨；3、铝单板片面层安装；4、该项包含本项工作所有工作内容含垂直运输机械等，未详尽列举特征，详见施工图纸、设计规范、施工方案事项均包含在综合单价中。 | E65: m2 | F65: 239.86 | G65: 120 | H65: =ROUND(F65*G65,2) -> 28783.2 | I65: =R65 -> 182.4 | J65: =F65*I65 -> 43750.46 | K65: 按铝单板吊顶的水平投影面积计算 | L65: 1、除型钢龙骨及甲供材外全费用综合单价； 2、甲供材：铝板 | N65: 0 | O65: 22 | P65: 130 | Q65: =N65+O65+P65 -> 152 | R65: =Q65*$R$4 -> 182.4 | T65: 182.4 | U65: =T65-I65 -> 0
A66: 6 | B66: 无机涂料吊顶 | C66: 1、防火型无机耐擦洗涂料两道饰面(白色) 2、2厚面层耐水腻子刮平 3、其他：该项包含本项工作所有工作内容含垂直运输机械等，未详尽列举特征，详见施工图纸、设计规范、施工方案事项均包含在综合单价中。 | D66: 1、天棚基层处理；2、满刮腻子一遍，砂抹平；3、涂料的制作、运输、喷涂；4、该项包含无机涂料天棚的所有工作内容，含垂直运输机械等，未详尽列举特征，详见施工图纸、设计规范、施工方案事项均包含在综合单价中。 | E66: m2 | F66: 219.96 | G66: 32 | H66: =ROUND(F66*G66,2) -> 7038.72 | I66: =$I$27 -> 44.4 | J66: =F66*I66 -> 9766.22 | K66: 按设计图示尺寸以面积计算（梁侧并入此项计算） | L66: 此项工作的全费用综合单价 | T66: 44.4 | U66: =T66-I66 -> 0
A67: 7 | B67: 线性灯槽 | C67: LED灯带制作安装 | D67: [工作内容] 1、LED灯带制作、安装 2、该项包含本项工作所有工作内容含垂直运输机械等，未详尽列举特征，详见施工图纸、设计规范、施工方案事项均包含在综合单价中。 | E67: m | F67: 143.2 | G67: 20 | H67: =ROUND(F67*G67,2) -> 2864 | I67: =$I$55 -> 65.04 | J67: =F67*I67 -> 9313.73 | K67: 按设计图示尺寸以米计算。 | L67: 全费用综合单价 | T67: 65.04 | U67: =T67-I67 -> 0
A68: （三） | B68: 出站厅区域 | U68: =T68-I68 -> 0
A69: 1 | B69: 花岗石地面 | C69: 1、铺25厚磨光花岗石板(六面涂刷石材保护剂),同色稀水泥浆擦 2、50厚1:3干硬性水泥粘结层,撒素水泥粉 3、水泥浆一道(内掺建筑胶) 4、地面伸缩缝、变形缝的处理； 其他：该项包含本项工作所有工作内容含垂直运输机械等，未详尽列举特征，详见施工图纸、设计规范、施工方案事项均包含在综合单价中。 | D69: 1、基层清理、打磨；2、砂浆的制作、运输、找平、压实；3、面层的铺贴；4、水泥砂浆擦缝；5、局部部位花岗石切割、打磨； 6、该项包含本项工作所有工作内容含垂直运输机械等，未详尽列举特征，详见施工图纸、设计规范、施工方案事项均包含在综合单价中。 | E69: m2 | F69: 447.39 | G69: 85 | H69: =ROUND(F69*G69,2) -> 38028.15 | I69: =$I$7 -> 118.32 | J69: =F69*I69 -> 52935.18 | K69: 按设计图示尺寸以面积计算 | L69: 1、除甲供材外全费用综合单价； 2、甲供材：石材 | T69: 118.32 | U69: =T69-I69 -> 0
A70: 2 | B70: 25MM 厚深灰麻过门石 | C70: 1、铺25厚磨光花岗石板(六面涂刷石材保护剂),同色稀水泥浆擦 2、50厚1:3干硬性水泥粘结层,撒素水泥粉 3、水泥浆一道(内掺建筑胶) 4、嵌缝材料种类：按甲方要求嵌缝、打胶； 5、防护层材料：防护剂六面处理，满足设计和相关规范要求； 6、酸洗、打蜡要求：满足设计和相关规范要求； 7、楼地面伸缩缝、变形缝的处理； 8、其他：该项包含本项工作所有工作内容含垂直运输机械等，未详尽列举特征，详见施工图纸、设计规范、施工方案事项均包含在综合单价中。 (石材规格800*800) | D70: 1、基层清理、打磨；2、砂浆的制作、运输、找平、压实；3、面层的铺贴；4、水泥砂浆擦缝；5、局部部位过门石切割、打磨； 6、该项包含本项工作所有工作内容含垂直运输机械等，未详尽列举特征，详见施工图纸、设计规范、施工方案事项均包含在综合单价中。 | E70: m2 | F70: 11.77 | G70: 80 | H70: =ROUND(F70*G70,2) -> 941.6 | I70: =$I$16 -> 156 | J70: =F70*I70 -> 1836.12 | K70: 按设计图示尺寸以面积计算 | L70: 1、除甲供材外全费用综合单价； 2、甲供材：石材 | T70: 156 | U70: =T70-I70 -> 0
A71: 3 | B71: 金属踢脚(高100) | C71: 1、1.0厚不锈钢金属踢脚板,下端用水泥钉钉入地面垫层,中距300 2、10厚1:3水泥砂浆压实抹平 3、素水泥浆一道(内掺建筑胶)(用于混凝土空心砌块墙);3厚外加剂专用砂浆抹基底刮糙(抹灰前用水喷湿墙面)(用于蒸 压加气混凝土砌块墙) 4、水泥钉固定踢脚上端,中距300 | D71: 1、墙体基层处理；2、砂浆的制作、运输、安装；3、金属踢脚卡件固定及不锈钢板面的安装；4、该项包含不锈钢踢脚的所有工作内容；含垂直运输机械等，未详尽列举特征，详见施工图纸、设计规范、施工方案事项均包含在综合单价中。 | E71: m2 | F71: 9.93 | G71: 272.98 | H71: =ROUND(F71*G71,2) -> 2710.69 | I71: =$I$19 -> 519.74 | J71: =F71*I71 -> 5161.02 | K71: 按设计图示尺寸以面积计算 | L71: 全费用综合单价 | T71: 519.74 | U71: =T71-I71 -> 0
A72: 4 | B72: 干挂铝板墙面（含消防暗门） | C72: 1、2.5厚铝合金饰面面层,接缝处密缝(或10*10MM凹槽);(3 米以下加肋,衬6mm厚硅酸钙板)。 2、金属板材用抽芯铆钉或自攻螺钉固定于铝方型材纵横方向龙骨上,板材带折边采用搭接式,带挂耳采用对接式; 3、60X40X4铝方型材龙骨,横向间距同金属板材宽度,纵向间距同金属板材长度,用螺栓与角钢连接。 4、8#槽钢竖向龙骨连接件螺栓连接, 5、连接件与预埋板焊接 6、预埋件 7、墙面伸缩缝、变形缝； 其他：该项包含本项工作所有工作内容含垂直运输机械等，未详尽列举特征，详见施工图纸、设计规范、施工方案事项均包含在综合单价中。 候车大厅、商务候车、出站厅等 | D72: 1.后置件 2.钢骨架 3.用石材胶粘贴石材 4.石材 5.六面刷界面处理剂，水泥浆檫缝 6.该项包含本项工作所有工作内容含垂直运输机械等，未详尽列举特征，详见施工图纸、设计规范、施工方案事项均包含在综合单价中。 | E72: m2 | F72: 642.45 | G72: 120 | H72: =ROUND(F72*G72,2) -> 77094 | I72: =$I$22 -> 177 | J72: =F72*I72 -> 113713.65 | K72: 按设计图示尺寸以面积计算 | L72: 1、除型钢龙骨及甲供材外全费用综合单价； 2、甲供材：铝板 | T72: 177 | U72: =T72-I72 -> 0
A73: 5 | B73: 铝合金单板(穿孔铝板)装饰吊顶 | C73: 1、2.5厚铝合金单板与配套专用龙骨固定 2、与铝合金单板配套的专用下层副龙骨联结,间距≤600 3、与安装型式配套的专用上层主龙骨,间距≤1200,用吊件与钢筋吊杆联结后找平 4、10号镀锌低碳钢丝(或%%C8钢筋)吊杆,双向中距≤1200,吊杆上部与板底预留吊环固定 5、现浇钢筋混凝土板底预留%%C10钢筋吊环,双向中距≤1200 6、天棚伸缩缝、变形缝的处理； 7、根据安装需要开孔 8、其他：该项包含本项工作所有工作内容含垂直运输机械等，未详尽列举特征，详见施工图纸、设计规范、施工方案事项均包含在综合单价中。； | D73: 基层清理；吊杆制作；吊杆、龙骨安装；面板固定、安装；洞口、检查孔、灯槽等留置、处理及收边收口，按照图纸要求吊顶四周设置圆形收边条、顶棚喷黑处理；材料场内运输；脚手架搭拆，成品保护等。该项包含本项工作所有工作内容含垂直运输机械等，未详尽列举特征，详见施工图纸、设计规范、施工方案事项均包含在综合单价中。 | E73: m2 | F73: 263.03 | G73: 120 | H73: =ROUND(F73*G73,2) -> 31563.6 | I73: =$I$65 -> 182.4 | J73: =F73*I73 -> 47976.67 | K73: 按设计图示尺寸以水平投影面积计算 | L73: 1、除型钢龙骨及甲供材外全费用综合单价； 2、甲供材：铝板 | T73: 182.4 | U73: =T73-I73 -> 0
A74: 6 | B74: 铝合金条板(锤片)吊顶 | C74: 1、1.5铝合金条板与配套专用龙骨固定(宽150mm,缝75mm,厚1mm) 2、与铝合金方通配套的专用龙骨,间距≤1200,用吊件与钢筋吊杆连接后找平 3、10号镀锌低碳钢丝(或%%C6钢筋)吊杆,双向中距≤1200,吊杆上部与板底预留吊环(勾)固定 4、现浇钢筋混凝土板底预留%%C10钢筋吊环(勾),双向中距≤1200(吊杆长度超过1.5米后需要做反支撑,吊杆长度超过2.5米需做转换层,做法详见二次结构施工安装详图)(转换层另列） 5、天棚伸缩缝、变形缝的处理； 6、根据安装需要开孔 7、其他：该项包含本项工作所有工作内容含垂直运输机械等，未详尽列举特征，详见施工图纸、设计规范、施工方案事项均包含在综合单价中。； | D74: 基层清理；吊杆制作；吊杆、龙骨安装；面板固定、安装；洞口、检查孔、灯槽等留置、处理及收边收口，按照图纸要求吊顶四周设置圆形收边条、顶棚喷黑处理；材料场内运输；脚手架搭拆，成品保护等。该项包含本项工作所有工作内容含垂直运输机械等，未详尽列举特征，详见施工图纸、设计规范、施工方案事项均包含在综合单价中。 | E74: m2 | F74: 311.39 | G74: 110 | H74: =ROUND(F74*G74,2) -> 34252.9 | I74: =$I$65 -> 182.4 | J74: =F74*I74 -> 56797.54 | K74: 按设计图示尺寸以水平投影面积计算 | L74: 1、除型钢龙骨及甲供材外全费用综合单价； 2、甲供材：铝合金条板 | T74: 182.4 | U74: =T74-I74 -> 0
A75: 7 | B75: 1.1 米高玻璃栏板 | C75: 1、1.1米高玻璃栏板 2、玻璃栏板不锈钢方管立柱63*25*5mm拉丝不锈钢管 3、玻璃栏板扶手φ63*3mm异形拉丝不锈钢圆管 4、玻璃栏板防撞栏杆φ51*1.5不锈钢圆管 玻璃：8+1.14PVB+8钢化夹胶玻璃 5、其他：该项包含本项工作所有工作内容含垂直运输机械等，未详尽列举特征，详见施工图纸、设计规范、施工方案事项均包含在综合单价中。 | D75: 1.预埋件制作、运输、埋设安装； 2.玻璃栏板制作、运输、安装、防护，安装驳接爪； 3.综合单价含栏板送样的材料费用、检验、试验等费用; 4.材料的运输、摆放、清运及场内多次搬运； 5.对已施工完成的成品及其他专业已完成的成品进行保护工作，无论是否由该单位导致的损坏，该单位都应履行修复处理责任； 6.对施工需要拆除或移动的材料，待施工完毕后，恢复原状； 7.完成工作区域的安全文明施工,清理施工遗留下的垃圾； 8.该项包含本项工作所有工作内容含垂直运输机械等，未详尽列举特征，详见施工图纸、设计规范、施工方案事项均包含在综合单价中。 | E75: m | F75: 35.33 | G75: 692.73 | H75: =ROUND(F75*G75,2) -> 24474.15 | I75: =$I$42 -> 986.77 | J75: =F75*I75 -> 34862.58 | K75: 按设计图示尺寸以长度计算 | L75: 全费用综合单价 | T75: 986.77 | U75: =T75-I75 -> 0
A76: （四） | B76: 外挂楼梯区域 | U76: =T76-I76 -> 0
A77: 1 | B77: 烧毛花岗岩铺面 | C77: 1、25厚磨光花岗石,水泥浆擦缝; 2、30厚1:3干硬性水泥砂浆,表面撒水泥粉; 3、地面伸缩缝、变形缝的处理； 其他：该项包含本项工作所有工作内容含垂直运输机械等，未详尽列举特征，详见施工图纸、设计规范、施工方案事项均包含在综合单价中。 | D77: 1、基层清理、打磨；2、砂浆的制作、运输、找平、压实；3、面层的铺贴；4、水泥砂浆擦缝；5、局部部位花岗石切割、打磨；6.该项包含本项工作所有工作内容含垂直运输机械等，未详尽列举特征，详见施工图纸、设计规范、施工方案事项均包含在综合单价中。 | E77: m2 | F77: =261.01-F78 -> 182.39 | G77: 85 | H77: =ROUND(F77*G77,2) -> 15503.15 | I77: =$I$7 -> 118.32 | J77: =F77*I77 -> 21580.38 | K77: 按设计图示尺寸以面积计算 | L77: 1、除甲供材外全费用综合单价； 2、甲供材：花岗石 | T77: 118.32 | U77: =T77-I77 -> 0
A78: 2 | B78: 烧毛花岗岩梯面 | C78: 1、25厚磨光花岗石,水泥浆擦缝; 2、30厚1:3干硬性水泥砂浆,表面撒水泥粉，挡水条制作 3、地面伸缩缝、变形缝的处理； 其他：该项包含本项工作所有工作内容含垂直运输机械等，未详尽列举特征，详见施工图纸、设计规范、施工方案事项均包含在综合单价中。 | D78: 1、基层清理、打磨；2、砂浆的制作、运输、找平、压实；3、面层的铺贴，挡水条制作；4、水泥砂浆擦缝；5、局部部位花岗石切割、打磨；6.该项包含本项工作所有工作内容含垂直运输机械等，未详尽列举特征，详见施工图纸、设计规范、施工方案事项均包含在综合单价中。 | E78: m2 | F78: 78.62 | G78: 110 | H78: =ROUND(F78*G78,2) -> 8648.2 | I78: =$I$8 -> 160.32 | J78: =F78*I78 -> 12604.36 | K78: 按设计图示尺寸以面积计算 | L78: 1、除甲供材外全费用综合单价； 2、甲供材：花岗石 | T78: 160.32 | U78: =T78-I78 -> 0
A79: 3 | B79: 石材踢脚 | C79: 1、粘贴10厚石材(板材满涂防污济)专用勾缝剂勾缝 2、12厚1:2水泥砂浆(内掺建筑胶)粘结层 3、素水泥浆一道(内掺建筑胶)(用于混凝土空心砌块墙);界面剂一道(甩前用水喷湿墙面)(用于蒸压加气混凝土砌块墙) | D79: 1、墙体基层处理；2、砂浆的制作、运输、安装；3、石材踢脚卡件固定及不锈钢板面的安装；4、该项包含石材踢脚的所有工作内容，含垂直运输机械等，未详尽列举特征，详见施工图纸、设计规范、施工方案事项均包含在综合单价中。 | E79: m2 | F79: 12.62 | G79: 88 | H79: =ROUND(F79*G79,2) -> 1110.56 | I79: =$I$63 -> 156 | J79: =F79*I79 -> 1968.72 | K79: 按设计图示尺寸以面积计算 | L79: 1、除甲供材外全费用综合单价； 2、甲供材：石材 | T79: 156 | U79: =T79-I79 -> 0
A80: 4 | B80: 石材止灰带 | C80: 石材止灰带 | D80: 1.后置件 2.钢骨架 3.用石材胶粘贴石材 4.石材 5.六面刷界面处理剂，水泥浆檫缝 6.其它:该项包含本项工作所有工作内容含垂直运输机械等，未详尽列举特征，详见施工图纸、设计规范、施工方案事项均包含在综合单价中。 | E80: m2 | F80: 61.63 | G80: 125 | H80: =ROUND(F80*G80,2) -> 7703.75 | I80: =R80 -> 228 | J80: =F80*I80 -> 14051.64 | K80: 按设计图示尺寸以展开面积计算 | L80: 1、除甲供材外全费用综合单价； 2、甲供材：石材 | O80: 10 | P80: 180 | Q80: =N80+O80+P80 -> 190 | R80: =Q80*$R$4 -> 228 | S80: =_xlfn.DISPIMG("ID_18CD2721379349E9981336DA0C1F8611",1) -> =DISPIMG("ID_18CD2721379349E9981336DA0C1F8611",1) | T80: 228 | U80: =T80-I80 -> 0
A81: 5 | B81: 干挂花岗岩墙面（含消防暗门） | C81: 1、干挂25mm厚石材墙面（含消防暗门） 2、石材背栓挂件,L50*5角钢连接件与横向龙骨(L50*5角钢)螺栓连接 3、L50*5角钢横向龙骨,与竖向槽钢(8#槽钢)焊接 4、8#槽钢,与连接件焊接, 5、连接件,与预埋件M3焊接 6、预埋件M3 7、墙面伸缩缝、变形缝的处理； 8、根据安装需要开孔 9、其他：该项包含本项工作所有工作内容含垂直运输机械等，未详尽列举特征，详见施工图纸、设计规范、施工方案事项均包含在综合单价中。； | D81: 2.安装方式：干挂 3.面层材料品种、规格、颜色：干挂花岗石石材,表面作晶面处理 4.龙骨材料：竖向主龙骨贯通,固定在墙体上下端(梁或楼板),龙骨截面尺寸根据墙体高度确定,次龙骨在主龙骨之间,龙骨间距依据面材分格尺寸,龙骨刷黑漆 5、该项包含本项工作所有工作内容含垂直运输机械等，未详尽列举特征，详见施工图纸、设计规范、施工方案事项均包含在综合单价中。 | E81: m2 | F81: 926.87 | G81: 150 | H81: =ROUND(F81*G81,2) -> 139030.5 | I81: =$I$64 -> 255.6 | J81: =F81*I81 -> 236907.97 | K81: 按设计图示尺寸以面积计算（有吊顶房间算至吊顶底，无吊顶房间算至梁底或者板底） | L81: 1、除型钢龙骨甲供材外全费用综合单价； 2、甲供材：花岗石 | T81: 255.6 | U81: =T81-I81 -> 0
A82: 6 | B82: 干挂铝板墙面（含消防暗门） | C82: 1、2.5厚铝合金饰面面层,接缝处密缝(或10*10MM凹槽);(3 米以下加肋,衬6mm厚硅酸钙板)。 2、金属板材用抽芯铆钉或自攻螺钉固定于铝方型材纵横方向龙骨上,板材带折边采用搭接式,带挂耳采用对接式; 3、60X40X4铝方型材龙骨,横向间距同金属板材宽度,纵向间距同金属板材长度,用螺栓与角钢连接。 4、8#槽钢竖向龙骨连接件螺栓连接, 5、连接件与预埋板焊接 6、预埋件 7、墙面伸缩缝、变形缝； 其他：该项包含本项工作所有工作内容含垂直运输机械等，未详尽列举特征，详见施工图纸、设计规范、施工方案事项均包含在综合单价中。 候车大厅、商务候车、出站厅等 | D82: 1、铝板下料；2、铝单板干挂；3、铝单板上铝格栅粘贴；4、与石材楼面接缝的处理；5、该项包含本项工作所有工作内容含垂直运输机械等，未详尽列举特征，详见施工图纸、设计规范、施工方案事项均包含在综合单价中。 | E82: m2 | F82: 610.76 | G82: 120 | H82: =ROUND(F82*G82,2) -> 73291.2 | I82: =$I$22 -> 177 | J82: =F82*I82 -> 108104.52 | K82: 按设计图示尺寸以面积计算 | L82: 1、除型钢龙骨及甲供材外全费用综合单价； 2、甲供材：铝板 | T82: 177 | U82: =T82-I82 -> 0
A83: 7 | B83: 铝合金单板(穿孔铝板)装饰吊顶 | C83: 1、2.5厚铝合金单板与配套专用龙骨固定 2、与铝合金单板配套的专用下层副龙骨联结,间距≤600 3、与安装型式配套的专用上层主龙骨,间距≤1200,用吊件与钢筋吊杆联结后找平 4、10号镀锌低碳钢丝(或%%C8钢筋)吊杆,双向中距≤1200,吊杆上部与板底预留吊环固定 5、现浇钢筋混凝土板底预留%%C10钢筋吊环,双向中距≤1200 6、天棚伸缩缝、变形缝的处理； 7、根据安装需要开孔 8、其他：该项包含本项工作所有工作内容含垂直运输机械等，未详尽列举特征，详见施工图纸、设计规范、施工方案事项均包含在综合单价中。； | D83: 1、钢结构转换层制作、安装；2、安装龙骨；3、铝单板片面层安装；4、该项包含本项工作所有工作内容含垂直运输机械等，未详尽列举特征，详见施工图纸、设计规范、施工方案事项均包含在综合单价中。 | E83: m2 | F83: 123.52 | G83: 120 | H83: =ROUND(F83*G83,2) -> 14822.4 | I83: =$I$65 -> 182.4 | J83: =F83*I83 -> 22530.05 | K83: 按铝单板吊顶的水平投影面积计算 | L83: 1、除型钢龙骨及甲供材外全费用综合单价； 2、甲供材：铝板 | T83: 182.4 | U83: =T83-I83 -> 0
A84: 8 | B84: 铝合金条板(锤片)吊顶 | C84: 1、1.5铝合金条板与配套专用龙骨固定(宽150mm,缝75mm,厚1mm) 2、与铝合金方通配套的专用龙骨,间距≤1200,用吊件与钢筋吊杆连接后找平 3、10号镀锌低碳钢丝(或%%C6钢筋)吊杆,双向中距≤1200,吊杆上部与板底预留吊环(勾)固定 4、现浇钢筋混凝土板底预留%%C10钢筋吊环(勾),双向中距≤1200(吊杆长度超过1.5米后需要做反支撑,吊杆长度超过2.5米需做转换层,做法详见二次结构施工安装详图)(转换层另列） 5、天棚伸缩缝、变形缝的处理； 6、根据安装需要开孔 7、其他：该项包含本项工作所有工作内容含垂直运输机械等，未详尽列举特征，详见施工图纸、设计规范、施工方案事项均包含在综合单价中。； | D84: 1.基层清理；吊杆制作；吊杆、龙骨安装；面板固定、安装；2.洞口、检查孔、灯槽等留置、处理及收边收口，按照图纸要求吊顶四周设置圆形收边条、顶棚喷黑处理；材料场内运输；脚手架搭拆，成品保护等。3.该项包含本项工作所有工作内容含垂直运输机械等，未详尽列举特征，详见施工图纸、设计规范、施工方案事项均包含在综合单价中。 | E84: m2 | F84: 338.32 | G84: 110 | H84: =ROUND(F84*G84,2) -> 37215.2 | I84: =$I$65 -> 182.4 | J84: =F84*I84 -> 61709.57 | K84: 按设计图示尺寸以水平投影面积计算 | L84: 1、除型钢龙骨及甲供材外全费用综合单价； 2、甲供材：铝合金条板 | T84: 182.4 | U84: =T84-I84 -> 0
A85: 8 | B85: 金属扶手、栏杆、栏板-1.3米高不锈钢栏杆 | C85: 1、1.3米高玻璃栏板 2、玻璃栏板拉丝不锈钢矩管（渐变）80~63*40*4mm 3、玻璃栏板扶手φ63*3mm异形拉丝不锈钢圆管 4、玻璃栏板防撞栏杆φ51*3不锈钢圆管 5、玻璃栏板8+1.14PVB+8夹胶钢化玻璃 其他：该项包含本项工作所有工作内容含垂直运输机械等，未详尽列举特征，详见施工图纸、设计规范、施工方案事项均包含在综合单价中。 | D85: 1.预埋件制作、运输、埋设安装； 2.玻璃栏板制作、运输、安装、防护，安装驳接爪； 3.综合单价含栏板送样的材料费用、检验、试验等费用; 4.材料的运输、摆放、清运及场内多次搬运； 5.对已施工完成的成品及其他专业已完成的成品进行保护工作，无论是否由该单位导致的损坏，该单位都应履行修复处理责任； 6.对施工需要拆除或移动的材料，待施工完毕后，恢复原状； 7.完成工作区域的安全文明施工,清理施工遗留下的垃圾； 8.该项包含本项工作所有工作内容含垂直运输机械等，未详尽列举特征，详见施工图纸、设计规范、施工方案事项均包含在综合单价中。 | E85: m | F85: 24.85 | G85: 795.1 | H85: =ROUND(F85*G85,2) -> 19758.24 | I85: =R85 -> 1085.53 | J85: =F85*I85 -> 26975.42 | K85: 按设计图示尺寸以长度计算 | L85: 全费用综合单价 | N85: =主材表!$L$46*1.3+主材表!$L$31+主材表!$L$32+主材表!$L$30*1.3 -> 714.61 | O85: 35 | P85: 155 | Q85: =N85+O85+P85 -> 904.61 | R85: =Q85*$R$4 -> 1085.53 | T85: 1085.53 | U85: =T85-I85 -> 0
A86: 9 | B86: 1.1 米高玻璃栏板 | C86: 1、1.1米高玻璃栏板 2、玻璃栏板不锈钢方管立柱63*25*5mm拉丝不锈钢管 3、玻璃栏板扶手φ63*3mm异形拉丝不锈钢圆管 4、玻璃栏板防撞栏杆φ51*1.5不锈钢圆管 5、其他：该项包含本项工作所有工作内容含垂直运输机械等，未详尽列举特征，详见施工图纸、设计规范、施工方案事项均包含在综合单价中。 | D86: 1.预埋件制作、运输、埋设安装； 2.玻璃栏板制作、运输、安装、防护，安装驳接爪； 3.综合单价含栏板送样的材料费用、检验、试验等费用; 4.材料的运输、摆放、清运及场内多次搬运； 5.对已施工完成的成品及其他专业已完成的成品进行保护工作，无论是否由该单位导致的损坏，该单位都应履行修复处理责任； 6.对施工需要拆除或移动的材料，待施工完毕后，恢复原状； 7.完成工作区域的安全文明施工,清理施工遗留下的垃圾； 8.该项包含本项工作所有工作内容含垂直运输机械等，未详尽列举特征，详见施工图纸、设计规范、施工方案事项均包含在综合单价中。 | E86: m | F86: 102.72 | G86: 692.73 | H86: =ROUND(F86*G86,2) -> 71157.23 | I86: =$I$42 -> 986.77 | J86: =F86*I86 -> 101361.01 | K86: 按设计图示尺寸以长度计算 | L86: 全费用综合单价 | T86: 986.77 | U86: =T86-I86 -> 0
A87: （五） | B87: 雨棚区域 | U87: =T87-I87 -> 0
A88: 1 | B88: 混凝土冲劲带 | C88: 1、站台外侧混凝土冲劲带浇筑； 2、冲劲带宽度200mm，高度110mm,具体详见图纸； 3、地面伸缩缝、变形缝的处理； 其它：垂直运输费用已包含在综合单价中，满足设计规范及图纸要求;未详尽列举特征，详见施工图纸、设计规范、施工方案 | D88: 1.清理基层清理净面等全部操作过程； 2.混凝土浇筑施工、养护、搓平，平整顺直； 3.材料的运输、堆码、清运及场内多次搬运； 4.综合单价包含送样的材料费用、检验、试验等工作费用，还包括地砖铺贴前排版图设计工作; 5.配合安装队伍进行多次预留预埋及相关开槽、开洞的修补工作； 6.对已施工完成的成品及其他专业已完成的成品进行保护工作，无论是否由该单位导致的损坏，该单位都应履行修复处理责任； 7.对施工需要拆除或移动的材料，待施工完毕后，恢复原状； 8.完成工作区域的安全文明施工,清理施工遗留下的垃圾； 9.该项包含本项工作所有工作内容含垂直运输机械等，未详尽列举特征，详见施工图纸、设计规范、施工方案事项均包含在综合单价中。 | E88: m | F88: =450*2 -> 900 | G88: 20 | H88: =ROUND(F88*G88,2) -> 18000 | I88: =R88 -> 71.88 | J88: =F88*I88 -> 64692 | K88: 按设计图示尺寸以延长米计算。 | L88: 除甲供材外，此项工作的全费用综合单价 甲供材：混凝土 | N88: =450*0.2*0.11+15 -> 24.9 | P88: 35 | Q88: =N88+O88+P88 -> 59.9 | R88: =Q88*$R$4 -> 71.88 | S88: =_xlfn.DISPIMG("ID_7639934494D145B4B11E9690446999EE",1) -> =DISPIMG("ID_7639934494D145B4B11E9690446999EE",1) | T88: 71.88 | U88: =T88-I88 -> 0
A89: 2 | B89: 烧毛花岗岩铺面 | C89: 1、25厚磨光花岗石,水泥浆擦缝; 2、30厚1:3干硬性水泥砂浆,表面撒水泥粉; 3、地面伸缩缝、变形缝的处理； 其它：垂直运输费用已包含在综合单价中，满足设计规范及图纸要求;未详尽列举特征，详见施工图纸、设计规范、施工方案 | D89: 1.位置：站台其他铺面、旅客活动平台； 2.工作内容：下料、清理基层、局部涂刷石材防护剂、面层铺设、嵌缝；砂浆制备；开孔、套边处理、成品保护及半成品保护等； 3.该项包含本项工作所有工作内容含垂直运输机械等，未详尽列举特征，详见施工图纸、设计规范、施工方案事项均包含在综合单价中。 | E89: m2 | F89: 405.06 | G89: 80 | H89: =ROUND(F89*G89,2) -> 32404.8 | I89: =$I$7 -> 118.32 | J89: =F89*I89 -> 47926.7 | K89: 按设计图示尺寸以面积计算 | L89: 1、除甲供材外全费用综合单价； 2、甲供材：花岗石 | M89: 同站房单价 | T89: 118.32 | U89: =T89-I89 -> 0
A90: 3 | B90: 地砖地面 | C90: 1、面层：10厚玻化砖(防滑),同色水泥浆擦缝 2、30厚1:3干硬性水泥砂浆,表面撒水泥粉 3、嵌缝材料种类：按甲方要求嵌缝、打胶； 4、防护层材料：满足设计和相关规范要求； 5、酸洗、打蜡要求：满足设计和相关规范要求； 6、楼地面伸缩缝、变形缝的处理； 7、其他：该项包含本项工作所有工作内容含垂直运输机械等，未详尽列举特征，详见施工图纸、设计规范、施工方案事项均包含在综合单价中。 (地砖规格600*600) | D90: 1、基层清理、打磨；2、砂浆的制作、运输、找平、压实；3、面层的铺贴；4、水泥砂浆擦缝；5、局部部位防滑地砖切割、打磨，含垂直运输机械等，未详尽列举特征，详见施工图纸、设计规范、施工方案事项均包含在综合单价中。 | E90: m2 | F90: 138.51 | G90: 108.2 | H90: =ROUND(F90*G90,2) -> 14986.78 | I90: =$I$9 -> 165.22 | J90: =F90*I90 -> 22884.62 | K90: 按设计图示尺寸以面积计算 | L90: 全费用综合单价 | M90: 同站房单价 | T90: 165.22 | U90: =T90-I90 -> 0
A91: 4 | B91: 防滑地砖地面(防水) | C91: 1、面层：10厚玻化砖(防滑),同色水泥浆擦缝 2、30厚1:3干硬性水泥砂浆,表面撒水泥粉 3、嵌缝材料种类：按甲方要求嵌缝、打胶； 4、防护层材料：满足设计和相关规范要求； 5、酸洗、打蜡要求：满足设计和相关规范要求； 6、楼地面伸缩缝、变形缝的处理； 7、其他：该项包含本项工作所有工作内容含垂直运输机械等，未详尽列举特征，详见施工图纸、设计规范、施工方案事项均包含在综合单价中。 (地砖规格600*600) | D91: 1、基层清理、打磨；2、砂浆的制作、运输、找平、压实；3、面层的铺贴；4、水泥砂浆擦缝；5、局部部位防滑地砖切割、打磨，该项包含本项工作所有工作内容含垂直运输机械等，未详尽列举特征，详见施工图纸、设计规范、施工方案事项均包含在综合单价中。 | E91: m2 | F91: 28.16 | G91: 108.2 | H91: =ROUND(F91*G91,2) -> 3046.91 | I91: =$I$10 -> 165.22 | J91: =F91*I91 -> 4652.6 | K91: 按设计图示尺寸以面积计算 | L91: 全费用综合单价 | M91: 同站房单价 | T91: 165.22 | U91: =T91-I91 -> 0
A92: 5 | B92: 地砖踢脚 | C92: 1、粘贴10厚地砖,专用勾缝剂勾缝 2、9厚1:2水泥砂浆(内掺3%超密聚合物防水剂)粘结层 3、素水泥浆一道(内掺建筑胶) 4、基层墙体 5、其它：垂直运输费用已包含在综合单价中，满足设计规范及图纸要求;未详尽列举特征，详见施工图纸、设计规范、施工方案 | D92: 1、清理基层、面层铺贴、成品保护及半成品保护，材料运输，养护抛光等。2、其它:该项包含本项工作所有工作内容含垂直运输机械等，未详尽列举特征，详见施工图纸、设计规范、施工方案事项均包含在综合单价中。 | E92: m2 | F92: 11.31 | G92: 113.61 | H92: =ROUND(F92*G92,2) -> 1284.93 | I92: =$I$18 -> 233.83 | J92: =F92*I92 -> 2644.62 | K92: 以平方米计量，按设计图示长度乘高度以面积计算 | L92: 全费用综合单价 | T92: 233.83 | U92: =T92-I92 -> 0
A93: 6 | B93: 石材踢脚 | C93: 1、粘贴10厚石材(板材满涂防污济)专用勾缝剂勾缝 2、12厚1:2水泥砂浆(内掺建筑胶)粘结层 3、素水泥浆一道(内掺建筑胶) 4、其它：垂直运输费用已包含在综合单价中，满足设计规范及图纸要求;未详尽列举特征，详见施工图纸、设计规范、施工方案 | D93: 1、清理基层、面层铺贴、成品保护及半成品保护，材料运输，养护抛光等。2、其它:该项包含本项工作所有工作内容含垂直运输机械等，未详尽列举特征，详见施工图纸、设计规范、施工方案事项均包含在综合单价中。 | E93: m2 | F93: 36.69 | G93: 88 | H93: =ROUND(F93*G93,2) -> 3228.72 | I93: =$I$63 -> 156 | J93: =F93*I93 -> 5723.64 | K93: 以平方米计量，按设计图示长度乘高度以面积计算 | L93: 1、除甲供材外全费用综合单价； 2、甲供材：石材 | T93: 156 | U93: =T93-I93 -> 0
A94: 7 | B94: 石材止灰带 | C94: 石材止灰带 | D94: 1.后置件 2.钢骨架 3.用石材胶粘贴石材 4.石材 5.六面刷界面处理剂，水泥浆檫缝； 6.其它:该项包含本项工作所有工作内容含垂直运输机械等，未详尽列举特征，详见施工图纸、设计规范、施工方案事项均包含在综合单价中。 | E94: m2 | F94: 32.5 | G94: 125 | H94: =ROUND(F94*G94,2) -> 4062.5 | I94: =$I$80 -> 228 | J94: =F94*I94 -> 7410 | K94: 按设计图示尺寸以展开面积计算 | L94: 1、除甲供材外全费用综合单价； 2、甲供材：石材 | S94: =_xlfn.DISPIMG("ID_5C6DEC2FA63946439A4588352BD181C4",1) -> =DISPIMG("ID_5C6DEC2FA63946439A4588352BD181C4",1) | T94: 228 | U94: =T94-I94 -> 0
A95: 8 | B95: 站台盲道砖 | C95: 1、玻化砖安全线盲道砖面层; 2、5厚坐浆层; 3、45厚1:3干硬性水泥砂浆粘结层; 4、地面伸缩缝、变形缝的处理； 其它：垂直运输费用已包含在综合单价中，满足设计规范及图纸要求;未详尽列举特征，详见施工图纸、设计规范、施工方案 | D95: 1.位置：站台 2.面层材料：20mm站台盲道砖300*300mm； 3.面层处理：石材养护剂； 贴结层：素水泥浆1道，内掺建筑胶； 4.结合层：45厚1:3干硬性水泥砂浆粘结层； 5.勾缝：水泥砂浆勾缝； 6.该项包含本项工作所有工作内容含垂直运输机械等，未详尽列举特征，详见施工图纸、设计规范、施工方案事项均包含在综合单价中。 | E95: m2 | F95: 540 | G95: 80 | H95: =ROUND(F95*G95,2) -> 43200 | I95: =R95 -> 96 | J95: =F95*I95 -> 51840 | K95: 按设计图示尺寸以面积计算 | L95: 1、除甲供材外全费用综合单价； 2、甲供材：盲道砖 | M95: 同站房单价 | N95: 0 | O95: =8/2*5 -> 20 | P95: 60 | Q95: =N95+O95+P95 -> 80 | R95: =Q95*$R$4 -> 96 | T95: 96 | U95: =T95-I95 -> 0
A96: 9 | B96: 站台安全线 | C96: 1、玻化砖安全线盲道砖面层; 2、5厚坐浆层; 3、45厚1:3干硬性水泥砂浆粘结层; 4、地面伸缩缝、变形缝的处理； 其它：垂直运输费用已包含在综合单价中，满足设计规范及图纸要求;未详尽列举特征，详见施工图纸、设计规范、施工方案 | D96: 1.下料、清理基层、局部涂刷石材防护剂、面层铺设、嵌缝；砂浆制备；开孔、套边处理、成品保护及半成品保护等； 2.该项包含本项工作所有工作内容含垂直运输机械等，未详尽列举特征，详见施工图纸、设计规范、施工方案事项均包含在综合单价中。 | E96: m2 | F96: 90 | G96: 80 | H96: =ROUND(F96*G96,2) -> 7200 | I96: =$I$95 -> 96 | J96: =F96*I96 -> 8640 | K96: 按设计图示尺寸以面积计算 | L96: 1、除甲供材外全费用综合单价； 2、甲供材：地砖 | M96: 同站房单价 | T96: 96 | U96: =T96-I96 -> 0
A97: 10 | B97: 站台帽石 | C97: 1、50厚红色花岗岩(磨光机刨6面满涂防护剂); 2、5厚坐浆层; 3、30厚1:3干硬性水泥砂浆粘结层; 4、地面伸缩缝、变形缝的处理； 其它：垂直运输费用已包含在综合单价中，满足设计规范及图纸要求;未详尽列举特征，详见施工图纸、设计规范、施工方案 | D97: 1.下料、清理基层、局部涂刷石材防护剂、面层铺设、嵌缝；砂浆制备；开孔、套边处理、成品保护及半成品保护等； 2.该项包含本项工作所有工作内容含垂直运输机械等，未详尽列举特征，详见施工图纸、设计规范、施工方案事项均包含在综合单价中。 | E97: m2 | F97: 900 | G97: 95 | H97: =ROUND(F97*G97,2) -> 85500 | I97: =R97 -> 126 | J97: =F97*I97 -> 113400 | K97: 按设计图示尺寸以面积计算 | L97: 1、除甲供材外全费用综合单价； 2、甲供材：石材 | N97: 0 | O97: 20 | P97: 85 | Q97: =N97+O97+P97 -> 105 | R97: =Q97*$R$4 -> 126 | T97: 126 | U97: =T97-I97 -> 0
A98: 11 | B98: 站台石材铺面 | C98: 1、600x900 30厚白麻花岗岩(火烧6面满涂防护剂) 2、5厚坐浆层; 3、30厚1:3干硬性水泥砂浆粘结层; 4、地面伸缩缝、变形缝的处理； 其它：垂直运输费用已包含在综合单价中，满足设计规范及图纸要求;未详尽列举特征，详见施工图纸、设计规范、施工方案 | D98: 1.位置：站台其他铺面、旅客活动平台； 2.工作内容：下料、清理基层、局部涂刷石材防护剂、面层铺设、嵌缝；砂浆制备；开孔、套边处理、成品保护及半成品保护等； 3.该项包含本项工作所有工作内容含垂直运输机械等，未详尽列举特征，详见施工图纸、设计规范、施工方案事项均包含在综合单价中。 | E98: m2 | F98: 5596.71 | G98: 80 | H98: =ROUND(F98*G98,2) -> 447736.8 | I98: =$I$7 -> 118.32 | J98: =F98*I98 -> 662202.73 | K98: 按设计图示尺寸以面积计算 | L98: 1、除甲供材外全费用综合单价； 2、甲供材：石材 | M98: 同站房单价 | T98: 118.32 | U98: =T98-I98 -> 0
A99: 12 | B99: 灰色氟碳漆踢脚 | C99: 1、清理基面:清理钢筋混凝土基面 2、基层处理:专用腻子找平、修复,厚度不大于5mm 3、灰色涂料底漆涂装:涂刷一遍 4、灰色涂料中涂涂装:涂刷一遍 5、面漆涂装:涂刷两遍 6、其它：垂直运输费用已包含在综合单价中，满足设计规范及图纸要求;未详尽列举特征，详见施工图纸、设计规范、施工方案 | D99: 1.墙体基层处理、找平抹灰、压实； 2.踢脚线制作、运输、安装，面砖背面涂专用粘接剂，用专用勾缝剂勾缝； 3.材料的运输、堆码、清运及场内多次搬运； 4.单价已包括送样的材料费用、检验、试验等工作; 5.配合安装队伍进行多次预留预埋及相关开槽、开洞的修补工作； 6.对已施工完成的成品及其他专业已完成的成品进行保护工作，无论是否由该单位导致的损坏，该单位都应履行修复处理责任； 7.对施工需要拆除或移动的材料，待施工完毕后，恢复原状； 8.完成工作区域的安全文明施工,清理施工遗留下的垃圾； 9.该项包含本项工作所有工作内容含垂直运输机械等，未详尽列举特征，详见施工图纸、设计规范、施工方案事项均包含在综合单价中。 | E99: m2 | F99: 86.75 | G99: 23.5 | H99: =ROUND(F99*G99,2) -> 2038.63 | I99: =R99 -> 251.4 | J99: =F99*I99 -> 21808.95 | K99: 以平方米计量，按设计图示长度乘高度以面积计算 | L99: 全费用综合单价 | N99: 85 | O99: 4.5 | P99: 120 | Q99: =N99+O99+P99 -> 209.5 | R99: =Q99*$R$4 -> 251.4 | T99: 251.4 | U99: =T99-I99 -> 0
A100: 13 | B100: 耐擦洗涂料墙面 | C100: 1、防火型无机耐擦洗涂料两道饰面(白色) 2、满刮2厚耐水腻子找平 3、其他：该项包含本项工作所有工作内容含垂直运输机械等，未详尽列举特征，详见施工图纸、设计规范、施工方案事项均包含在综合单价中。 | D100: 1、墙体基层处理；2、刮腻子；3、涂料的制作、运输；4、喷面浆或涂料；5、该项包含涂料墙面的所有工作内容，该项包含本项工作所有工作内容含垂直运输机械等，未详尽列举特征，详见施工图纸、设计规范、施工方案事项均包含在综合单价中。 | E100: m2 | F100: 68.21 | G100: 30 | H100: =ROUND(F100*G100,2) -> 2046.3 | I100: =$I$23 -> 44.4 | J100: =F100*I100 -> 3028.52 | K100: 按设计图示尺寸以面积计算（有吊顶房间算至吊顶底，无吊顶房间算至梁底或者板底） | L100: 全费用综合单价 | T100: 44.4 | U100: =T100-I100 -> 0
...

Sheet 彭水二标段
A1: 彭水二标
A2: 项目名称：中铁建工集团有限公司重庆至黔江铁路站房工程2标项目经理部 | M2: 单位：元
A3: 序号 | B3: 项目名称 | C3: 项目特征 | D3: 工作内容 | E3: 单位 | F3: 工程量 | G3: 控制价 | I3: 上报金额 | K3: 工程量计算规则 | L3: 费用组成 | M3: 备注 | N3: 主材 | O3: 辅材 | P3: 人工 | Q3: 单价 | R3: 取费
G4: 不含税单价（元） | H4: 不含税合价（元） | I4: 不含税单价（元） | J4: 不含税合价（元） | R4: =南川一标段!$R$4 -> 1.2
A5: （一） | B5: 彭水南站
A6: （一） | B6: 站房区域
A7: 1 | B7: 花岗石地面 | C7: 1、铺25厚磨光花岗石板(六面涂刷石材保护剂),同色稀水泥浆擦 2、50厚1:3干硬性水泥粘结层,撒素水泥粉 3、水泥浆一道(内掺建筑胶) 4、嵌缝材料种类：按甲方要求嵌缝、打胶； 5、防护层材料：防护剂六面处理，满足设计和相关规范要求； 6、酸洗、打蜡要求：满足设计和相关规范要求； 7、楼地面伸缩缝、变形缝的处理； 8、其他：该项包含本项工作所有工作内容含垂直运输机械等，未详尽列举特征，详见施工图纸、设计规范、施工方案事项均包含在综合单价中。 (石材规格800*800) | D7: 1、基层清理、打磨；2、砂浆的制作、运输、找平、压实；3、面层的铺贴；4、水泥砂浆擦缝；5、局部部位花岗石切割、打磨，所有工作内容含垂直运输机械等，未详尽列举特征，详见施工图纸、设计规范、施工方案事项均包含在综合单价中 | E7: m2 | F7: 6650.56 | G7: 85 | H7: =F7*G7 -> 565297.6 | I7: =南川一标段!$I$7 -> 118.32 | J7: =F7*I7 -> 786894.26 | K7: 按设计图示尺寸以面积计算 | L7: 1、除甲供材外全费用综合单价； 2、甲供材：花岗石 | Q7: =N7+O7+P7 -> 0 | R7: =Q7*$R$4 -> 0 | S7: =_xlfn.DISPIMG("ID_7371E3C92DDC4979A83E0D9C73E49416",1) -> =DISPIMG("ID_7371E3C92DDC4979A83E0D9C73E49416",1)
A8: 2 | B8: 25MM厚深灰麻过门石 | C8: 1、铺25厚磨光花岗石板(六面涂刷石材保护剂),同色稀水泥浆擦 2、50厚1:3干硬性水泥粘结层,撒素水泥粉 3、水泥浆一道(内掺建筑胶) 4、嵌缝材料种类：按甲方要求嵌缝、打胶； 5、防护层材料：防护剂六面处理，满足设计和相关规范要求； 6、酸洗、打蜡要求：满足设计和相关规范要求； 7、楼地面伸缩缝、变形缝的处理； 8、其他：该项包含本项工作所有工作内容含垂直运输机械等，未详尽列举特征，详见施工图纸、设计规范、施工方案事项均包含在综合单价中。 (石材规格800*800) | D8: 1、基层清理、打磨；2、砂浆的制作、运输、找平、压实；3、面层的铺贴；4、水泥砂浆擦缝；5、局部部位过门石切割、打磨，所有工作内容含垂直运输机械等，未详尽列举特征，详见施工图纸、设计规范、施工方案事项均包含在综合单价中 | E8: m2 | F8: 20.58 | G8: 80 | H8: =F8*G8 -> 1646.4 | I8: =南川一标段!$I$16 -> 156 | J8: =F8*I8 -> 3210.48 | K8: 按设计图示尺寸以面积计算 | L8: 1、除甲供材外全费用综合单价； 2、甲供材：深灰麻过门石 | Q8: =N8+O8+P8 -> 0 | R8: =Q8*$R$4 -> 0
A9: 3 | B9: 防滑地砖地面(防水)架空 | C9: 1、面层：10厚玻化砖(防滑),同色水泥浆擦缝 2、30厚1:3干硬性水泥砂浆,表面撒水泥粉 3、嵌缝材料种类：按甲方要求嵌缝、打胶； 4、防护层材料：满足设计和相关规范要求； 5、酸洗、打蜡要求：满足设计和相关规范要求； 6、楼地面伸缩缝、变形缝的处理； 7、其他：该项包含本项工作所有工作内容含垂直运输机械等，未详尽列举特征，详见施工图纸、设计规范、施工方案事项均包含在综合单价中。 (地砖规格600*600) | D9: 1、基层清理、打磨；2、砂浆的制作、运输、找平、压实；3、面层的铺贴；4、水泥砂浆擦缝；5、局部部位防滑地砖切割、打磨，所有工作内容含垂直运输机械等，未详尽列举特征，详见施工图纸、设计规范、施工方案事项均包含在综合单价中 | E9: m2 | F9: 772.33 | G9: 120 | H9: =F9*G9 -> 92679.6 | I9: =南川一标段!$I$10 -> 165.22 | J9: =F9*I9 -> 127604.36 | K9: 按设计图示尺寸以面积计算 | L9: 全费用综合单价 | Q9: =N9+O9+P9 -> 0 | R9: =Q9*$R$4 -> 0
A10: 4 | B10: 水泥自流平楼面（非架空） | C10: 1、10-12厚水泥基自流平面层 2、涂刷自流平界面剂两道 3、40厚C20细石混凝土,随打随抹平,表面打磨或喷砂处理 4.水泥浆水灰比0.4~0.5结合层一道 | D10: 1.基层处理；2.涂界面剂；3.拌合自流平浆料；4.铺自流平面层；5、该项包含本项工作所有工作内容含垂直运输机械等，未详尽列举特征，详见施工图纸、设计规范、施工方案事项均包含在综合单价中 | E10: m2 | F10: 19.44 | G10: 47.92 | H10: =F10*G10 -> 931.56 | I10: =南川一标段!$I$13 -> 28.8 | J10: =F10*I10 -> 559.87 | K10: 按设计图示尺寸以面积计算 | L10: 全费用综合单价 | Q10: =N10+O10+P10 -> 0 | R10: =Q10*$R$4 -> 0
A11: 5 | B11: 防静电架空地面 | C11: 1、250高防静电活动地板,耐压强度10kN/㎡,配成套支架 2、10厚地砖(色另定) 3、20厚1:3干硬性砂浆,表面撒水泥粉 4、20厚1:3水泥砂浆 5、水泥浆一道(内掺建筑胶) 6、楼地面伸缩缝、变形缝的处理； | D11: 1、基层清理、打磨；2、水泥浆一道，内掺建筑胶；3、砂浆的制作、运输、找平、压实；4、面砖的铺贴；5、成套支架安装；6、安装陶瓷防静电架空地板；6、该项包含防静电架空地板的所有工作内容，所有工作内容含垂直运输机械等，未详尽列举特征，详见施工图纸、设计规范、施工方案事项均包含在综合单价中 | E11: m2 | F11: 266.08 | G11: 316.06 | H11: =F11*G11 -> 84097.24 | I11: =南川一标段!$I$14 -> 391.2 | J11: =F11*I11 -> 104090.5 | K11: 按设计图示尺寸以面积计算 | L11: 全费用综合单价 | Q11: =N11+O11+P11 -> 0 | R11: =Q11*$R$4 -> 0
A12: 6 | B12: 地砖地面（架空） | C12: 1、15防滑地砖，干水泥擦缝 2、30厚1:3干硬性水泥砂浆结合层，表面撒水泥粉 3、水泥砂浆一道（内掺建筑胶） 4、楼地面伸缩缝、变形缝的处理； | D12: 1、基层清理、打磨；2、砂浆的制作、运输、找平、压实；3、面层的铺贴；4、水泥砂浆擦缝；5、局部部位防滑地砖切割、打磨，所有工作内容含垂直运输机械等，未详尽列举特征，详见施工图纸、设计规范、施工方案事项均包含在综合单价中 | E12: m2 | F12: 1145.38 | G12: 120 | H12: =F12*G12 -> 137445.6 | I12: =南川一标段!$I$9 -> 165.22 | J12: =F12*I12 -> 189239.68 | K12: 按设计图示尺寸以面积计算 | L12: 全费用综合单价 | Q12: =N12+O12+P12 -> 0 | R12: =Q12*$R$4 -> 0
A13: 7 | B13: 防滑地砖地面(防水)架空 | C13: 1、面层：10厚玻化砖(防滑),同色水泥浆擦缝 2、30厚1:3干硬性水泥砂浆,表面撒水泥粉 3、嵌缝材料种类：按甲方要求嵌缝、打胶； 4、防护层材料：满足设计和相关规范要求； 5、酸洗、打蜡要求：满足设计和相关规范要求； 6、楼地面伸缩缝、变形缝的处理； 7、其他：该项包含本项工作所有工作内容含垂直运输机械等，未详尽列举特征，详见施工图纸、设计规范、施工方案事项均包含在综合单价中。 (地砖规格600*600) | D13: 1、基层清理、打磨；2、砂浆的制作、运输、找平、压实；3、面层的铺贴；4、水泥砂浆擦缝；5、局部部位防滑地砖切割、打磨，所有工作内容含垂直运输机械等，未详尽列举特征，详见施工图纸、设计规范、施工方案事项均包含在综合单价中 | E13: m2 | F13: 76.55 | G13: 120 | H13: =F13*G13 -> 9186 | I13: =南川一标段!$I$10 -> 165.22 | J13: =F13*I13 -> 12647.59 | K13: 按设计图示尺寸以面积计算 | L13: 全费用综合单价 | Q13: =N13+O13+P13 -> 0 | R13: =Q13*$R$4 -> 0
A14: 8 | B14: 防滑玻化砖梯面 | C14: 1、面层：10厚玻化砖(防滑),同色水泥浆擦缝 2、30厚1:3干硬性水泥砂浆,表面撒水泥粉 3、嵌缝材料种类：按甲方要求嵌缝、打胶，挡水条制作； 4、防护层材料：满足设计和相关规范要求； 5、酸洗、打蜡要求：满足设计和相关规范要求； 6、楼地面伸缩缝、变形缝的处理； 7、其他：该项包含本项工作所有工作内容含垂直运输机械等，未详尽列举特征，详见施工图纸、设计规范、施工方案事项均包含在综合单价中。 (地砖规格600*600) | D14: 1.基层清理、找平、打磨、甩浆、弹线、定位； 2.结合层施工； 3.防滑地砖铺贴，干水泥擦缝，挡水条制作； 4.材料的运输、堆码、清运及场内多次搬运； 5.单价已包括送样的材料费用、检验、试验等工作，还包括地砖铺贴前排版图设计工作; 6.配合安装队伍进行多次预留预埋及相关开槽、开洞的修补工作； 7.对已施工完成的成品及其他专业已完成的成品进行保护工作，无论是否由该单位导致的损坏，该单位都应履行修复处理责任； 8.对施工需要拆除或移动的材料，待施工完毕后，恢复原状； 9.完成工作区域的安全文明施工,清理施工遗留下的垃圾； 10.该项包含本项工作所有工作内容含垂直运输机械等，未详尽列举特征，详见施工图纸、设计规范、施工方案事项均包含在综合单价中。 | E14: m2 | F14: 105.08 | G14: 135 | H14: =F14*G14 -> 14185.8 | I14: =南川一标段!$I$11 -> 175.84 | J14: =F14*I14 -> 18477.27 | K14: 按设计图示尺寸以展开面积计算 | L14: 全费用综合单价 | Q14: =N14+O14+P14 -> 0 | R14: =Q14*$R$4 -> 0
A15: 9 | B15: 不锈钢踢脚 | C15: 1、板缝处理 2、1.0厚不锈钢板与卡件安装 3、金属踢脚卡件固定,间距500mm 4、基层墙面 | D15: 1、墙体基层处理；2、砂浆的制作、运输、安装；3、金属踢脚卡件固定及不锈钢板面的安装；4、该项包含不锈钢踢脚的所有工作内容，所有工作内容含垂直运输机械等，未详尽列举特征，详见施工图纸、设计规范、施工方案事项均包含在综合单价中 | E15: m2 | F15: 1.47 | G15: 272.98 | H15: =F15*G15 -> 401.28 | I15: =南川一标段!$I$71 -> 519.74 | J15: =F15*I15 -> 764.02 | K15: 按设计图示尺寸以面积计算 | L15: 全费用综合单价 | Q15: =N15+O15+P15 -> 0 | R15: =Q15*$R$4 -> 0
A16: 10 | B16: 干挂铝板墙面（含消防暗门） | C16: 1、2.5厚铝合金饰面面层,接缝处密缝(或10*10MM凹槽);(3 米以下加肋,衬6mm厚硅酸钙板)。 2、金属板材用抽芯铆钉或自攻螺钉固定于铝方型材纵横方向龙骨上,板材带折边采用搭接式,带挂耳采用对接式; 3、60X40X4铝方型材龙骨,横向间距同金属板材宽度,纵向间距同金属板材长度,用螺栓与角钢连接。 4、8#槽钢竖向龙骨连接件螺栓连接, 5、连接件与预埋板焊接 6、预埋件 7、墙面伸缩缝、变形缝； 其他：该项包含本项工作所有工作内容含垂直运输机械等，未详尽列举特征，详见施工图纸、设计规范、施工方案事项均包含在综合单价中。； | D16: 1、铝板下料；2、铝单板干挂；3、铝单板上铝格栅粘贴；4、与石材楼面接缝的处理；5、所有工作内容含垂直运输机械等，未详尽列举特征，详见施工图纸、设计规范、施工方案事项均包含在综合单价中 | E16: m2 | F16: 760.71 | G16: 120 | H16: =F16*G16 -> 91285.2 | I16: =南川一标段!$I$22 -> 177 | J16: =F16*I16 -> 134645.67 | K16: 按设计图示尺寸以面积计算 | L16: 1、除型钢龙骨及甲供材外全费用综合单价； 2、甲供材：铝板 | Q16: =N16+O16+P16 -> 0 | R16: =Q16*$R$4 -> 0
A17: 11 | B17: 柱面CA07木纹色铝单板 | C17: 1、2.5厚铝合金饰面面层,接缝处密缝(或10*10MM凹槽);(3 米以下加肋,衬6mm厚硅酸钙板)。 2、金属板材用抽芯铆钉或自攻螺钉固定于铝方型材纵横方向龙骨上,板材带折边采用搭接式,带挂耳采用对接式; 3、60X40X4铝方型材龙骨,横向间距同金属板材宽度,纵向间距同金属板材长度,用螺栓与角钢连接。 4、8#槽钢竖向龙骨连接件螺栓连接, 5、连接件与预埋板焊接 6、预埋件 7、墙面伸缩缝、变形缝； 其他：该项包含本项工作所有工作内容含垂直运输机械等，未详尽列举特征，详见施工图纸、设计规范、施工方案事项均包含在综合单价中。； | D17: 1、铝板下料；2、铝单板干挂；3、铝单板上铝格栅粘贴；4、与石材楼面接缝的处理；5、所有工作内容含垂直运输机械等，未详尽列举特征，详见施工图纸、设计规范、施工方案事项均包含在综合单价中 | E17: m2 | F17: 49.41 | G17: 120 | H17: =F17*G17 -> 5929.2 | I17: =南川一标段!$I$22 -> 177 | J17: =F17*I17 -> 8745.57 | K17: 按设计图示尺寸以面积计算 | L17: 1、除型钢龙骨及甲供材外全费用综合单价； 2、甲供材：铝板 | Q17: =N17+O17+P17 -> 0 | R17: =Q17*$R$4 -> 0
A18: 12 | B18: 候车厅方通背景墙 | C18: 候车厅铝方通背景墙 | D18: 1.基层材料种类、规格：12mm厚多层阻燃板基层+隔音棉 2.面层材料品种、规格、颜色：成品白色皮纹板块（12mm中纤板基层+胶粘+真空吸附+翻边钉扣），设计选样， 3.压条材料种类、规格：综合 4.成品保护、压条、嵌缝、各种螺栓、螺钉、射钉、固定配件等费用包含在综合单价中 5.其他：满足设计、施工验收规范及招标技术要求 6.所有工作内容含垂直运输机械等，未详尽列举特征，详见施工图纸、设计规范、施工方案事项均包含在综合单价中 | E18: m2 | F18: 516.8 | G18: 403.26 | H18: =F18*G18 -> 208404.77 | I18: =R18 -> 658.78 | J18: =F18*I18 -> 340457.5 | K18: 按设计图示尺寸以面积计算 | L18: 全费用综合单价 | N18: =主材表!L37 -> 353.98 | O18: 65 | P18: 130 | Q18: =N18+O18+P18 -> 548.98 | R18: =Q18*$R$4 -> 658.78 | S18: =_xlfn.DISPIMG("ID_4B889F83850B41C88BEAC61337EDA281",1) -> =DISPIMG("ID_4B889F83850B41C88BEAC61337EDA281",1)
A19: 13 | B19: 商务ME06印花不锈钢 | C19: 1、1.2mm印花不锈钢 2、双层18mm阻燃版基层板 | D19: 1.龙骨材料种类、规格、中距：轻钢龙骨，规格间距综合 2.防护材料种类：以型材及型材间需要焊接位置都镀锌处理满足防锈及防火要求为止3.基层材料品种、规格：双层18mm阻燃版基层板 4.面层材料品种、规格、颜色：不锈钢面层 5.压条材料种类、规格：综合 6.成品保护、压条、嵌缝、各种螺栓、螺钉、射钉、固定配件及面层开孔（开孔符合安装要求）等费用包含在综合单价中 7.其他：所有工作内容含垂直运输机械等，未详尽列举特征，详见施工图纸、设计规范、施工方案事项均包含在综合单价中 | E19: m2 | F19: 75.35 | G19: 412.27 | H19: =F19*G19 -> 31064.54 | I19: =R19 -> 978.6 | J19: =F19*I19 -> 73737.51 | K19: 按设计图示尺寸以面积计算 | L19: 全费用综合单价 | N19: =主材表!O36 -> 580 | O19: =30+35*2+5.5 -> 105.5 | P19: 130 | Q19: =N19+O19+P19 -> 815.5 | R19: =Q19*$R$4 -> 978.6 | S19: =_xlfn.DISPIMG("ID_872B2FD62EDA4309BD1AE6E0417C0DF4",1) -> =DISPIMG("ID_872B2FD62EDA4309BD1AE6E0417C0DF4",1)
A20: 14 | B20: 干挂花岗岩墙面（含消防暗门） | C20: 1、干挂25mm厚石材墙面（含消防暗门） 2、石材背栓挂件,L50*5角钢连接件与横向龙骨(L50*5角钢)螺栓连接 3、L50*5角钢横向龙骨,与竖向槽钢(8#槽钢)焊接 4、8#槽钢,与连接件焊接, 5、连接件,与预埋件M3焊接 6、预埋件M3 7、墙面伸缩缝、变形缝的处理； 8、根据安装需要开孔 9、其他：该项包含本项工作所有工作内容含垂直运输机械等，未详尽列举特征，详见施工图纸、设计规范、施工方案事项均包含在综合单价中。； | D20: 2.安装方式：干挂 3.面层材料品种、规格、颜色：干挂花岗石石材,表面作晶面处理 4.龙骨材料：竖向主龙骨贯通,固定在墙体上下端(梁或楼板),龙骨截面尺寸根据墙体高度确定,次龙骨在主龙骨之间,龙骨间距依据面材分格尺寸,龙骨刷黑漆 5、所有工作内容含垂直运输机械等，未详尽列举特征，详见施工图纸、设计规范、施工方案事项均包含在综合单价中 | E20: m2 | F20: 2193.59 | G20: 150 | H20: =F20*G20 -> 329038.5 | I20: =南川一标段!$I$103 -> 255.6 | J20: =F20*I20 -> 560681.6 | K20: 按设计图示尺寸以面积计算（有吊顶房间算至吊顶底，无吊顶房间算至梁底或者板底） | L20: 1、除型钢龙骨及甲供材外全费用综合单价； 2、甲供材：花岗石 | Q20: =N20+O20+P20 -> 0 | R20: =Q20*$R$4 -> 0
A21: 15 | B21: 白色无机涂料墙面(A级) | C21: 1、喷(刷、辊)无机内墙薄涂涂料2道 2、满刮2厚腻子砂磨平 3、其他：该项包含本项工作所有工作内容含垂直运输机械等，未详尽列举特征，详见施工图纸、设计规范、施工方案事项均包含在综合单价中。 | D21: 1、墙体基层处理；2、刮腻子；3、涂料的制作、运输；4、喷面浆或涂料；5、该项包含涂料墙面的所有工作内容，所有工作内容含垂直运输机械等，未详尽列举特征，详见施工图纸、设计规范、施工方案事项均包含在综合单价中 | E21: m2 | F21: 4422.81 | G21: 27 | H21: =F21*G21 -> 119415.87 | I21: =南川一标段!$I$20 -> 44.4 | J21: =F21*I21 -> 196372.76 | K21: 按设计图示尺寸以面积计算（有吊顶房间算至吊顶底，无吊顶房间算至梁底或者板底） | L21: 全费用综合单价 | Q21: =N21+O21+P21 -> 0 | R21: =Q21*$R$4 -> 0
A22: 16 | B22: 白色无机涂料吸音墙面(A级) | C22: 1.无机涂料 2.20厚矿物纤维吸声喷涂层 3.6厚1:3水泥砂浆找平 4.7厚1:3水泥砂浆打底扫毛（内掺建筑胶） 5.基层清理 | D22: 1、墙体基层处理；2、刮腻子；3、涂料的制作、运输；4、矿物纤维吸声喷涂、喷面浆或涂料；5、该项包含涂料墙面的所有工作内容，所有工作内容含垂直运输机械等，未详尽列举特征，详见施工图纸、设计规范、施工方案事项均包含在综合单价中 | E22: m2 | F22: 3113.59 | G22: 32 | H22: =F22*G22 -> 99634.88 | I22: =南川一标段!$I$27 -> 44.4 | J22: =F22*I22 -> 138243.4 | K22: 按设计图示尺寸以面积计算（有吊顶房间算至吊顶底，无吊顶房间算至梁底或者板底） | L22: 全费用综合单价 | Q22: =N22+O22+P22 -> 0 | R22: =Q22*$R$4 -> 0
A23: 17 | B23: 防水面砖墙面 | C23: 1、同色水泥擦缝 2、8-10厚墙面砖(粘贴前墙砖充分浸湿) 3、8厚1:2水泥砂浆粘结层(内掺建筑胶) 4、缝宽、嵌缝材料：按甲方要求嵌缝、打胶； 5、酸洗、打蜡要求：满足设计和相关规范要求； 6、墙面伸缩缝、变形缝的处理； 7、根据安装需要开孔 8、其他：该项包含本项工作所有工作内容含垂直运输机械等，未详尽列举特征，详见施工图纸、设计规范、施工方案事项均包含在综合单价中。 (600×300墙砖) | D23: 1、墙体基层处理；2、水泥砂浆的制作、运输；3、粘贴墙面砖；4、局部部位面砖切割、打磨；5、水泥擦缝；6、该项包含玻化砖墙面的所有工作内容，所有工作内容含垂直运输机械等，未详尽列举特征，详见施工图纸、设计规范、施工方案事项均包含在综合单价中 | E23: m2 | F23: 2340.9 | G23: 120 | H23: =F23*G23 -> 280908 | I23: =南川一标段!$I$21 -> 153.02 | J23: =F23*I23 -> 358204.52 | K23: 按设计图示尺寸以面积计算（有吊顶房间算至吊顶底） | L23: 全费用综合单价 | Q23: =N23+O23+P23 -> 0 | R23: =Q23*$R$4 -> 0
A24: 18 | B24: 防火玻璃隔断（旅客服务房间） | C24: 1、施工部位：旅客服务室外围隔断； 2、面层材料：8HS+1.52PVB+8HS（low-e）+12Ar+27mm全超白中空夹胶防火玻璃（A类，1小时防火），具体施工要求与细部分格等详见图纸及方案，包含通长支座、副框、扣盖、压板、压块、垫块、连接件等，不同规格的钢板等； 3、底部塞防火岩棉、外包1.5mm厚镀锌钢板； 4、底部及顶部采用通长钢U槽连接； 5、接缝、嵌缝及塞口材料：泡沫棒、结构密封胶、耐候密封胶、EPDM胶条、防火胶条等详图纸及方案要求； 6、所有保温防火封堵、不锈钢自攻钉、不锈钢销钉、不锈钢螺栓、断热条、防脱螺钉、硬质玻璃垫块、钢托板、φ12压力间隔套等其他所有辅材需满足图纸及方案要求，其施工费及材料费等均已含在综合单价中； 7、与其他装饰面收口打胶； | D24: 1、防火岩棉及镀锌钢板的制作、运输、安装；2、型材的制作、运输、安装；3、玻璃安装；4、嵌缝、塞口；5、清洗；6、施工区域的安全文明施工；7、该项包含本项工作所有工作内容，未详尽列举的图纸、方案事项均包含在综合单价中 | E24: m2 | F24: 153.68 | G24: 1429.33 | H24: =F24*G24 -> 219659.43 | I24: =南川一标段!$I$45 -> 1243.27 | J24: =F24*I24 -> 191065.73 | K24: 按设计图示尺寸以面积计算 | L24: 全费用综合单价 | Q24: =N24+O24+P24 -> 0 | R24: =Q24*$R$4 -> 0
A25: 19 | B25: 铝合金条板(锤片)吊顶（候车大厅） | C25: 1、铝合金条板与配套专用龙骨固定(宽150mm,缝90mm,厚1.5mm) 2、与铝合金方通配套的专用龙骨,间距≤1200,用吊件与钢筋吊杆连接后找平 3、10号镀锌低碳钢丝(或%%C6钢筋)吊杆,双向中距≤1200,吊杆上部与板底预留吊环(勾)固定 4、现浇钢筋混凝土板底预留%%C10钢筋吊环(勾),双向中距≤1200(吊杆长度超过1.5米后需要做反支撑,吊杆长度超过2.5米需做转换层,做法详见二次结构施工安装详图)(转换层另列） 5、天棚伸缩缝、变形缝； 其他：该项包含本项工作所有工作内容含垂直运输机械等，未详尽列举特征，详见施工图纸、设计规范、施工方案事项均包含在综合单价中。； | D25: 1、钢结构转换层制作、安装；2、安装龙骨；3、铝条板面层安装；4、所有工作内容含垂直运输机械等，未详尽列举特征，详见施工图纸、设计规范、施工方案事项均包含在综合单价中 | E25: m2 | F25: 3810.7 | G25: 125 | H25: =F25*G25 -> 476337.5 | I25: =南川一标段!$I$33 -> 182.4 | J25: =F25*I25 -> 695071.68 | K25: 按设计图示尺寸以铝条板吊顶水平投影面积计算，其中筒灯所在的位置的宽度对应的面积不计算 | L25: 1、除型钢龙骨及甲供材外全费用综合单价； 2、甲供材：铝板 | Q25: =N25+O25+P25 -> 0 | R25: =Q25*$R$4 -> 0
A26: 20 | B26: 铝合金单板装饰吊顶（候车大厅） | C26: 1、2.5厚铝合金单板与配套专用龙骨固定 2、与铝合金单板配套的专用下层副龙骨联结,间距≤600 3、与安装型式配套的专用上层主龙骨,间距≤1200,用吊件与钢筋吊杆联结后找平 4、10号镀锌低碳钢丝(或%%C8钢筋)吊杆,双向中距≤1200,吊杆上部与板底预留吊环固定 5、现浇钢筋混凝土板底预留%%C10钢筋吊环,双向中距≤1200 6、天棚伸缩缝、变形缝； 其他：该项包含本项工作所有工作内容含垂直运输机械等，未详尽列举特征，详见施工图纸、设计规范、施工方案事项均包含在综合单价中。 | D26: 1、钢结构转换层制作、安装；2、安装龙骨；3、铝单板片面层安装；4、所有工作内容含垂直运输机械等，未详尽列举特征，详见施工图纸、设计规范、施工方案事项均包含在综合单价中 | E26: m2 | F26: 5230.12 | G26: 135 | H26: =F26*G26 -> 706066.2 | I26: =南川一标段!$I$31 -> 182.4 | J26: =F26*I26 -> 953973.89 | K26: 按铝单板吊顶的水平投影面积计算 | L26: 1、除型钢龙骨及甲供材外全费用综合单价； 2、甲供材：铝板 | Q26: =N26+O26+P26 -> 0 | R26: =Q26*$R$4 -> 0
A27: 21 | B27: CA02铝单板（印花）吊顶 | C27: 1、2.5厚铝单板印花与配套专用龙骨固定 2、与铝合金单板配套的专用下层副龙骨联结,间距≤600 3、与安装型式配套的专用上层主龙骨,间距≤1200,用吊件与钢筋吊杆联结后找平 4、10号镀锌低碳钢丝(或%%C8钢筋)吊杆,双向中距≤1200,吊杆上部与板底预留吊环固定 5、现浇钢筋混凝土板底预留%%C10钢筋吊环,双向中距≤1200 6、天棚伸缩缝、变形缝； 其他：该项包含本项工作所有工作内容含垂直运输机械等，未详尽列举特征，详见施工图纸、设计规范、施工方案事项均包含在综合单价中。 | D27: 1、后置件、骨架的制作、运输、安装；2、铝板下料；3、铝单板干挂；4、铝单板上铝格栅粘贴；5、与石材楼面接缝的处理；6、所有工作内容含垂直运输机械等，未详尽列举特征，详见施工图纸、设计规范、施工方案事项均包含在综合单价中 | E27: m2 | F27: 125.08 | G27: 135 | H27: =F27*G27 -> 16885.8 | I27: =南川一标段!$I$31 -> 182.4 | J27: =F27*I27 -> 22814.59 | K27: 按设计图示尺寸以室外可视铝板面积计算，其中：铝板梁面和铝单板吊顶分界线为最内侧的垂直方向的铝单板边线 | L27: 1、除型钢龙骨及甲供材外全费用综合单价； 2、甲供材：铝板 | Q27: =N27+O27+P27 -> 0 | R27: =Q27*$R$4 -> 0
A28: 22 | B28: 铝合金扣板顶棚 | C28: 1、600*600*1.0铝合金扣板(折边20) 2、与铝合金扣板配套的专用暗架龙骨,间距≤300,通过十字连扣连接件与承载龙骨连接 3、D38承载龙骨,间距≤1200,用吊杆与钢筋吊杆联结后找平 4、10厚镀锌低碳钢丝(或%%C8钢筋)吊杆,双向中距≤1200,吊杆上部与板底(或钢结构)预留吊环(勾)固定 5、结构层预埋%%C10(或钢结构预留)钢筋吊环(勾),双向中距≤1200 6、天棚伸缩缝、变形缝； 其他：该项包含本项工作所有工作内容含垂直运输机械等，未详尽列举特征，详见施工图纸、设计规范、施工方案事项均包含在综合单价中。 | D28: 1、吊杆的制作、运输、安装；2、铝板下料； 3、铝扣板安装以及与墙柱面接缝处理； 4、所有工作内容含垂直运输机械等，未详尽列举特征，详见施工图纸、设计规范、施工方案事项均包含在综合单价中 | E28: m2 | F28: 693.33 | G28: 136.14 | H28: =F28*G28 -> 94389.95 | I28: =南川一标段!$I$29 -> 160.04 | J28: =F28*I28 -> 110960.53 | K28: 按设计图示尺寸以面积计算 | L28: 除型钢龙骨外的全费用综合单价 | Q28: =N28+O28+P28 -> 0 | R28: =Q28*$R$4 -> 0
A29: 23 | B29: 9.5mm双层石膏板轻钢龙骨涂料跌级 | C29: 1、9.5mm厚双层石膏面层板面层,规格592x592 2、T型次龙骨TB24x30,间距600,与主龙骨插接 3、T型主龙骨TB24X30,间距600,通过D-T挂件与承载龙骨连接 4、D38承载龙骨,间距1200,用吊件与钢筋吊杆联结后找平 5、%C8螺纹吊杆,双向中距≤1200,吊杆上部与吊顶转换层固定 7、50*5镀锌角钢吊顶转换层,井字型网格间距≤2400*1200(转换层另列） 8、天棚伸缩缝、变形缝； 其他：该项包含本项工作所有工作内容含垂直运输机械等，未详尽列举特征，详见施工图纸、设计规范、施工方案事项均包含在综合单价中。 | D29: 1.吊顶形式、吊杆规格、高度：跌级，Φ8吊杆楼板固定，间距综合 2.龙骨材料种类、规格、中距：主次轻钢龙骨，间距综合；横撑轻钢龙骨，间距综合 3.面层材料品种、规格：双层9.5mm厚纸面石膏板，固定方式综合 4.防护材料种类：需要焊接位置都镀锌处理满足防锈及防火要求 5.压条、嵌缝、防护、收边线、灯槽、配套螺栓、螺钉、紧固件、弹线、窗帘盒，根据安装专业要求所开洞口（喷淋孔、灯孔、检修口、通风口）等费用均包含在综合单价中 6.清单工程量按面层水平投影面积计算,造型，石膏板立面等增加的工料包含在综合单价中考虑 7.其他：所有工作内容含垂直运输机械等，未详尽列举特征，详见施工图纸、设计规范、施工方案事项均包含在综合单价中 | E29: m2 | F29: 298.89 | G29: 166.94 | H29: =F29*G29 -> 49896.7 | I29: =R29 -> 177.6 | J29: =F29*I29 -> 53082.86 | K29: 按设计图示以水平投影面积计算 | L29: 全费用综合单价 | N29: =4.5 -> 4.5 | O29: =26+10*2+4.5 -> 50.5 | P29: =35+18*2+22 -> 93 | Q29: =N29+O29+P29 -> 148 | R29: =Q29*$R$4 -> 177.6
A30: 24 | B30: 石膏线100*100 | C30: 石膏装饰线条 100*100mm | D30: [工作内容] 1.基层清理 2.刮腻子 3.刷防护材料、油漆 | E30: m | F30: 143.06 | G30: 15 | H30: =F30*G30 -> 2145.9 | I30: =R30 -> 43.2 | J30: =F30*I30 -> 6180.19 | K30: 按设计图示尺寸以长度计算 | L30: 全费用综合单价 | N30: 12.5 | O30: 3.5 | P30: 20 | Q30: =N30+O30+P30 -> 36 | R30: =Q30*$R$4 -> 43.2
A31: 25 | B31: 硅酸钙板(防潮石膏板)涂料顶棚(防水) | C31: 1、喷(刷、辊)涂料面层两遍(每道间隔2小时) 2、封底漆一道(干燥后再做面层) 3、满刮2厚面层耐水腻子找平,板面接缝处贴嵌缝带,刮腻子抹平 4、错缝粘贴第二层9.5厚耐水耐火纸面石膏板 5、9.5厚耐水耐火纸面石膏板用自攻螺丝与龙骨固定,中距≤200,螺丝距板长边≥10,短边≥15 6、U型轻钢覆面横撑龙骨CB60x27,间距1200,用挂插件与次龙骨联结 7、U型轻钢覆面次龙骨CB60x27,间距400,用挂件与承接龙骨联结 8、U型轻钢承接龙骨CS50x15,间距≤1200,用吊杆与钢筋吊杆联结后找平 9、%%C8钢筋吊杆并加反支撑,双向中距≤1200,吊杆上部与预留钢筋吊环固定 10、现浇钢筋混凝土板底预埋%%C10钢筋吊环(勾),双向中距≤1200 11、天棚伸缩缝、变形缝； 其他：该项包含本项工作所有工作内容含垂直运输机械等，未详尽列举特征，详见施工图纸、设计规范、施工方案事项均包含在综合单价中。 | D31: 1、天棚基层处理；2、后置件、骨架的制作、运输、安装；3、硅酸钙板安装；4、表面涂刷乳胶漆，压条安装；5、该项包含硅酸钙板吊顶的所有工作内容，所有工作内容含垂直运输机械等，未详尽列举特征，详见施工图纸、设计规范、施工方案事项均包含在综合单价中 | E31: m2 | F31: 90.63 | G31: 166.94 | H31: =F31*G31 -> 15129.77 | I31: =$I$29 -> 177.6 | J31: =F31*I31 -> 16095.89 | K31: 按设计图示尺寸以硅酸钙板吊顶水平投影面积计算 | L31: 全费用综合单价 | Q31: =N31+O31+P31 -> 0 | R31: =Q31*$R$4 -> 0
A32: 26 | B32: 石膏板吊顶(轻钢龙骨)(A级)[办公用房、走道 | C32: 1、12厚石膏面层板面层,规格592x592 2、T型次龙骨TB24x30,间距600,与主龙骨插接 3、T型主龙骨TB24X30,间距600,通过D-T挂件与承载龙骨连接 4、D38承载龙骨,间距1200,用吊件与钢筋吊杆联结后找平 5、%%C8螺纹吊杆,双向中距≤1200,吊杆上部与吊顶转换层固定 7、50*5镀锌角钢吊顶转换层,井字型网格间距≤2400*1200(转换层另列） | D32: 1、天棚基层处理；2、后置件、骨架的制作、运输、安装；3、轻钢龙骨石膏板安装；4、该项包含轻钢龙骨石膏板吊顶的所有工作内容，所有工作内容含垂直运输机械等，未详尽列举特征，详见施工图纸、设计规范、施工方案事项均包含在综合单价中 | E32: m2 | F32: 1251.43 | G32: 108.1 | H32: =F32*G32 -> 135279.58 | I32: =R32 -> 108.6 | J32: =F32*I32 -> 135905.3 | K32: 按设计图示尺寸以轻钢龙骨石膏板吊顶水平投影面积计算 | L32: 全费用综合单价 | O32: =11.5+26 -> 37.5 | P32: =35+18 -> 53 | Q32: =N32+O32+P32 -> 90.5 | R32: =Q32*$R$4 -> 108.6
A33: 27 | B33: 白色无机涂料顶棚(A级） | C33: 1、防火型无机耐擦洗涂料两道饰面(白色) 2、2厚面层耐水腻子刮平 3、其他：该项包含本项工作所有工作内容含垂直运输机械等，未详尽列举特征，详见施工图纸、设计规范、施工方案事项均包含在综合单价中。 | D33: 1、天棚基层处理；2、满刮腻子一遍，砂抹平；3、涂料的制作、运输、喷涂；4、该项包含无机涂料天棚的所有工作内容，所有工作内容含垂直运输机械等，未详尽列举特征，详见施工图纸、设计规范、施工方案事项均包含在综合单价中 | E33: m2 | F33: 428.03 | G33: 32 | H33: =F33*G33 -> 13696.96 | I33: =南川一标段!$I$28 -> 44.4 | J33: =F33*I33 -> 19004.53 | K33: 按设计图示尺寸以面积计算（梁侧并入此项计算） | L33: 全费用综合单价 | Q33: =N33+O33+P33 -> 0 | R33: =Q33*$R$4 -> 0
A34: 28 | B34: 白色无机涂料吸音顶棚(A级) | C34: 1、白色无机涂料 2、20厚矿物纤维吸声喷涂层 3、其他：该项包含本项工作所有工作内容含垂直运输机械等，未详尽列举特征，详见施工图纸、设计规范、施工方案事项均包含在综合单价中。 | D34: 1、天棚基层处理；2、满刮腻子一遍，砂抹平；3、矿物纤维吸声喷涂、涂料的制作、运输、喷涂；4、该项包含无机涂料天棚的所有工作内容，所有工作内容含垂直运输机械等，未详尽列举特征，详见施工图纸、设计规范、施工方案事项均包含在综合单价中 | E34: m2 | F34: 79.5 | G34: 32 | H34: =F34*G34 -> 2544 | I34: =南川一标段!$I$27 -> 44.4 | J34: =F34*I34 -> 3529.8 | K34: 按设计图示尺寸以面积计算（梁侧并入此项计算） | L34: 全费用综合单价 | Q34: =N34+O34+P34 -> 0 | R34: =Q34*$R$4 -> 0
A35: 29 | B35: 吊顶转换层 | C35: 主次龙骨50*50*5镀锌方管、埋板等 | D35: 1、包含完成本项目所需要的材料费，转换层钢龙骨/铝板龙骨制作安装、材料运输、装卸、场内外多次倒运、试验检测等所有费用 2、包工作面清理、成品保护、负责工作区域的安全文明施工,施工遗留垃圾的清理及外运等； 3、含材料费管理费、措施费、夜间施工费、赶工措施费、安全文明施工费、规费、税金、临近既有线施工费用以及可能出现的人员窝工及机械停滞费用等施工所发生的一切费用 所有工作内容含垂直运输机械等，未详尽列举特征，详见施工图纸、设计规范、施工方案事项均包含在综合单价中 | E35: t | F35: 122 | G35: 8726.4 | H35: =F35*G35 -> 1064620.8 | I35: =南川一标段!$I$47 -> 10536 | J35: =F35*I35 -> 1285392 | K35: 按照设计图示尺寸以重量进行计算 | L35: 全费用综合单价 | Q35: =N35+O35+P35 -> 0 | R35: =Q35*$R$4 -> 0
A36: 30 | B36: 干挂型钢龙骨 | C36: 1、石材、铝板墙面龙骨、埋板等； 2、骨架种类、规格：具体规格、尺寸、连接方式详见图纸； | D36: 1.镀锌型钢龙骨转换层、骨架的制作、运输、安装、刷漆 2.该项包含本项工作所有工作内容，所有工作内容含垂直运输机械等，所有工作内容含垂直运输机械等，未详尽列举特征，详见施工图纸、设计规范、施工方案事项均包含在综合单价中。 | E36: t | F36: 70.9 | G36: 8726.4 | H36: =F36*G36 -> 618701.76 | I36: =南川一标段!$I$48 -> 10536 | J36: =F36*I36 -> 747002.4 | K36: 按设计图示尺寸以实际安装根数以重量计算 | L36: 此项工作的全费用综合单价 | Q36: =N36+O36+P36 -> 0 | R36: =Q36*$R$4 -> 0
A37: 31 | B37: 天棚喷刷深灰色涂料 | C37: 1、基层类型：砼天棚；2、深灰A级无机涂料喷涂，厚度、装饰效果满足设计要求3、超高增加的措施费用 | D37: [工作内容] 1.基层清理 2.刮腻子 3.刷、喷涂料 | E37: m2 | F37: 3900 | G37: 12.89 | H37: =F37*G37 -> 50271 | I37: =南川一标段!$I$34 -> 24.6 | J37: =F37*I37 -> 95940 | K37: 按设计图示尺寸以面积计算（梁侧并入此项计算） | L37: 全费用综合单价 | Q37: =N37+O37+P37 -> 0 | R37: =Q37*$R$4 -> 0
A38: 32 | B38: 洗漱台 | C38: 1、石材面台 2、石材挡水 3、2.5MM铝单板挡板 | D38: 1.材料品种、规格、品牌、颜色：详设计图纸 2.基层：阻燃板基层厚度综合 3.支架、配件品种、规格、品牌：热镀锌矩管，规格间距综合 5.其他：所有工作内容含垂直运输机械等，未详尽列举特征，详见施工图纸、设计规范、施工方案事项均包含在综合单价中 | E38: m | F38: 24.79 | G38: 420.78 | H38: =F38*G38 -> 10431.14 | I38: =南川一标段!$I$35 -> 639.9 | J38: =F38*I38 -> 15863.12 | K38: 按设计图示尺寸长度以“米”计量。 | L38: 除基层龙骨外，此项工作的全费用综合单价 | Q38: =N38+O38+P38 -> 0 | R38: =Q38*$R$4 -> 0
A39: 33 | B39: 母婴设施 | C39: 成品母婴设备安装，完成该项工作所需的全部工作内容，完成工作区域的安全文明施工,清理施工遗留下的垃圾。 | D39: [工作内容] 1.台面及支架运输、安装 2.杆、环、盒、配件安装 3.刷油漆 | E39: 副 | F39: 1 | G39: 16920 | H39: =ROUND(F39*G39,2) -> 16920 | I39: =南川一标段!$I$51 -> 20304 | J39: =F39*I39 -> 20304 | K39: 按设计图示个数以套计算 | L39: 此项工作的全费用综合单价 | Q39: =N39+O39+P39 -> 0 | R39: =Q39*$R$4 -> 0
A40: 34 | B40: 镜面玻璃 | C40: 1.30*30mm方管龙骨（刷防火、防腐） 2.6mm厚双层硅酸钙板基层（涂刷防腐） 3.5mm厚银镜及安装。 4.顶部及底部LED贴片灯带、灯槽制作安装 5.不锈钢边框包边；6.完成该项工作所需的全部工作内容 | D40: [工作内容] 1.基层安装 2.玻璃及框制作、运输、安装 3.该项包含本项工作所有工作内容，所有工作内容含垂直运输机械等，所有工作内容含垂直运输机械等，未详尽列举特征，详见施工图纸、设计规范、施工方案事项均包含在综合单价中。 | E40: m2 | F40: 27 | G40: 220 | H40: =F40*G40 -> 5940 | I40: =南川一标段!$I$36 -> 526.8 | J40: =F40*I40 -> 14223.6 | K40: 按设计图示尺寸以面积计算 | L40: 除基层龙骨外，此项工作的全费用综合单价 | Q40: =N40+O40+P40 -> 0 | R40: =Q40*$R$4 -> 0
A41: 35 | B41: 蹲位隔断 | C41: 抗倍特板 | D41: 1.隔断材料品种、规格、颜色：抗倍特板隔断 2.配件品种、规格：综合单价包含所有五金材料3.4.其他：所有工作内容含垂直运输机械等，未详尽列举特征，详见施工图纸、设计规范、施工方案事项均包含在综合单价中 | E41: 间 | F41: 105 | G41: 1250 | H41: =F41*G41 -> 131250 | I41: =南川一标段!$I$37 -> 3490.32 | J41: =F41*I41 -> 366483.6 | K41: 以间计量，按设计间的数量计算。 | L41: 除基层龙骨外，此项工作的全费用综合单价 | M41: 市场不含税成本单价385元一平米，平均每个蹲位7.46㎡， | Q41: =N41+O41+P41 -> 0 | R41: =Q41*$R$4 -> 0
A42: 36 | B42: 小便斗隔板 | C42: 抗倍特板 | D42: 1.隔断材料品种、规格、颜色：抗倍特板,厂家定制安装 2.配件品种、规格：不锈钢五金配件、铰链、边框等，费用包含在综合单价中 3.具体详卫生间节点大样图 4.其他：所有工作内容含垂直运输机械等，未详尽列举特征，详见施工图纸、设计规范、施工方案事项均包含在综合单价中 | E42: 间 | F42: 35 | G42: 184.36 | H42: =F42*G42 -> 6452.6 | I42: =南川一标段!$I$38 -> 254.09 | J42: =F42*I42 -> 8893.15 | K42: 按照设计图示以数量计算 | L42: 全费用综合单价 | Q42: =N42+O42+P42 -> 0 | R42: =Q42*$R$4 -> 0
A43: 37 | B43: 卫生纸盒 | C43: 卫生纸盒 | D43: 1.材料品种、规格、品牌、颜色不锈钢纸巾盒 2.其他：所有工作内容含垂直运输机械等，未详尽列举特征，详见施工图纸、设计规范、施工方案事项均包含在综合单价中 | E43: 个 | F43: 105 | G43: 12.6 | H43: =F43*G43 -> 1323 | I43: =南川一标段!$I$39 -> 72.6 | J43: =F43*I43 -> 7623 | K43: 按设计图示个数以个计算 | L43: 全费用综合单价 | Q43: =N43+O43+P43 -> 0 | R43: =Q43*$R$4 -> 0
A44: 38 | B44: 烘手器 | C44: 烘手器 | D44: 1.材料品种、规格、品牌、颜色：烘手器，综合，选样 2.支架、配件品种、规格、品牌：综合 3.详卫生间放大图 4.其它:所有工作内容含垂直运输机械等，未详尽列举特征，详见施工图纸、设计规范、施工方案事项均包含在综合单价中 | E44: 副 | F44: 7 | G44: 265 | H44: =F44*G44 -> 1855 | I44: =南川一标段!$I$40 -> 369 | J44: =F44*I44 -> 2583 | K44: 按设计图示以个数计算 | L44: 全费用综合单价 | Q44: =N44+O44+P44 -> 0 | R44: =Q44*$R$4 -> 0
A45: 39 | B45: 1.1米高玻璃栏板 | C45: 1、1.1米高玻璃栏板 2、玻璃栏板不锈钢方管立柱90*12mm不锈钢扁钢立柱 3、玻璃栏板扶手φ63*4mm异形拉丝不锈钢圆管 4、玻璃栏板防撞栏杆φ51*1.5不锈钢圆管 5、玻璃栏板：6+1.52PVB+6mm钢化夹胶玻璃 5、其他：该项包含本项工作所有工作内容含垂直运输机械等，未详尽列举特征，详见施工图纸、设计规范、施工方案事项均包含在综合单价中。 | D45: 1.预埋件制作、运输、埋设安装； 2.玻璃栏板制作、运输、安装、防护，安装驳接爪； 3.综合单价含栏板送样的材料费用、检验、试验等费用; 4.材料的运输、摆放、清运及场内多次搬运； 5.对已施工完成的成品及其他专业已完成的成品进行保护工作，无论是否由该单位导致的损坏，该单位都应履行修复处理责任； 6.对施工需要拆除或移动的材料，待施工完毕后，恢复原状； 7.完成工作区域的安全文明施工,清理施工遗留下的垃圾； 8.所有工作内容含垂直运输机械等，未详尽列举特征，详见施工图纸、设计规范、施工方案事项均包含在综合单价中 | E45: m | F45: 65.27 | G45: 692.73 | H45: =F45*G45 -> 45214.49 | I45: =南川一标段!$I$42 -> 986.77 | J45: =F45*I45 -> 64406.48 | K45: 按设计图示尺寸以长度计算 | L45: 全费用综合单价 | Q45: =N45+O45+P45 -> 0 | R45: =Q45*$R$4 -> 0
A46: 40 | B46: 3米高玻璃栏板 | C46: 3米高玻璃栏板 | D46: 1.制作 2.运输 3.安装 4.刷防护材料 5.所有工作内容含垂直运输机械等，未详尽列举特征，详见施工图纸、设计规范、施工方案事项均包含在综合单价中 | E46: m | F46: 65.27 | G46: 1254 | H46: =F46*G46 -> 81848.58 | I46: =R46 -> 2458.25 | J46: =F46*I46 -> 160449.98 | K46: 按设计图示尺寸以长度计算 | L46: 全费用综合单价 | N46: =主材表!$L$46*3+主材表!$L$33*3+主材表!$L$32 -> 1803.54 | O46: 45 | P46: 200 | Q46: =N46+O46+P46 -> 2048.54 | R46: =Q46*$R$4 -> 2458.25
A47: 41 | B47: 玻璃幕墙防撞杆 | C47: 1、玻璃幕墙防撞杆 2、H=250mm 3、其他：该项包含本项工作所有工作内容含垂直运输机械等，未详尽列举特征，详见施工图纸、设计规范、施工方案事项均包含在综合单价中。 | D47: [工作内容] 1.制作 2.运输 3.安装 4.刷防护材料 5.该项包含本项工作所有工作内容含垂直运输机械等，所有工作内容含垂直运输机械等，未详尽列举特征，详见施工图纸、设计规范、施工方案事项均包含在综合单价中。 | E47: m | F47: 37.6 | G47: 71.24 | H47: =F47*G47 -> 2678.62 | I47: =南川一标段!$I$44 -> 109.6 | J47: =F47*I47 -> 4120.96 | K47: 按设计图示尺寸以长度计算 | L47: 全费用综合单价 | Q47: =N47+O47+P47 -> 0 | R47: =Q47*$R$4 -> 0
A48: 42 | B48: 定制成品不锈钢票槽 | C48: 定制成品不锈钢票槽 | D48: 1、部位:站房 2、台柜规格:定制成品不锈钢票槽 3、工作内容：售票槽加工、制作、开孔、安装固定、材料运输等全部内容。所有工作内容含垂直运输机械等，未详尽列举特征，详见施工图纸、设计规范、施工方案事项均包含在综合单价中 | E48: m2 | F48: 7.2 | G48: 442 | H48: =F48*G48 -> 3182.4 | I48: =R48 -> 512.98 | J48: =F48*I48 -> 3693.46 | K48: 按设计图示尺寸以面积计算 | L48: 全费用综合单价 | N48: =主材表!L38 -> 353.98 | O48: 8.5 | P48: 65 | Q48: =N48+O48+P48 -> 427.48 | R48: =Q48*$R$4 -> 512.98
A49: 43 | B49: 铝单板门套 | C49: 1、部位：综合考虑，有门、无门部位均按此项计算 2、墙体类型：砼、砖墙综合考虑； 3、骨架种类、规格：型材，规格详见设计图纸，间距应满足施工要求并由投标人综合考虑； 4、面层材料种类、规格：不锈钢； 5、嵌缝、打胶； 6、具体要求详设计图纸 7、根据安装需要开孔 | D49: 1、后置件、骨架的制作、运输、安装；2、铝板下料，安装；3、嵌缝、打胶；4、该项包含不锈钢门套线的所有工作内容，所有工作内容含垂直运输机械等，未详尽列举特征，详见施工图纸、设计规范、施工方案事项均包含在综合单价中 | E49: m2 | F49: 172.8 | G49: 110 | H49: =F49*G49 -> 19008 | I49: =南川一标段!$I$46 -> 226.2 | J49: =F49*I49 -> 39087.36 | K49: 按设计图示尺寸以室外可视铝板面积进行计算 | L49: 除基层龙骨及甲供材外，此项工作的全费用综合单价 | M49: 甲供材：铝板 | Q49: =N49+O49+P49 -> 0 | R49: =Q49*$R$4 -> 0
A50: 44 | B50: 服务台 | C50: 服务台 | D50: 1.部位:综合服务中心 2.材料品种、规格、颜色:人造石台面、人造石立面、镀锌方钢龙骨及阻燃板 3.工作内容：镀锌方钢等龙骨加工制作及安装；基层阻燃板安装固定；人造石台面及立面加工及安装；灯带固定及安装；材料运输，成品及半成品保护等。所有工作内容含垂直运输机械等，未详尽列举特征，详见施工图纸、设计规范、施工方案事项均包含在综合单价中 | E50: m | F50: 17.6 | G50: 4522.11 | H50: =F50*G50 -> 79589.14 | I50: =南川一标段!$I$50 -> 2109 | J50: =F50*I50 -> 37118.4 | K50: 按设计图示以中心线长度计算 | L50: 全费用综合单价 | Q50: =N50+O50+P50 -> 0 | R50: =Q50*$R$4 -> 0
A51: 45 | B51: 电缆沟盖板 | C51: 施工部位：变电所 6mm花纹钢板 | D51: [工作内容] 1.盖板制作、运输、安装 | E51: m2 | F51: 20.64 | G51: 300 | H51: =F51*G51 -> 6192 | I51: =南川一标段!$I$56 -> 346.13 | J51: =F51*I51 -> 7144.12 | K51: 按设计图纸尺寸以面积计算 | L51: 此项工作的全费用综合单价 | Q51: =N51+O51+P51 -> 0 | R51: =Q51*$R$4 -> 0
A52: 46 | B52: 风口百叶 | C52: （1）面板：铝合金百叶； （2）龙骨及连接件：详见施工方案及图纸要求； （3）密封胶：详见施工方案及图纸要求； （4）完成本项目的所需的材料及相应的工序(包括但不限于加工制作、储运、安装、嵌缝、塞口、清洗、试验检测等内容） （5）未详尽列举特征，详见设计图纸、设计规范、施工方案。 | D52: （1）百叶窗安装、防虫网安装，百叶喷涂氟碳漆 （2）包含基层处理（打磨找补清理）、成品保护、负责工作区域的安全文明施工,施工遗留垃圾的清理及外运等； （3）含材料费管理费、措施费、夜间施工费、赶工措施费、安全文明施工费、规费、税金、临近既有线施工费用以及可能出现的人员窝工及机械停滞费用等施工所发生的一切费用 （4）其他未尽事宜详见招标文件技术要求及图纸 | E52: m2 | F52: 5.4 | G52: 367.83 | H52: =F52*G52 -> 1986.28 | I52: =南川一标段!$I$59 -> 510 | J52: =F52*I52 -> 2754 | K52: 按百叶窗的垂直投影面积进行计算 | L52: 全费用综合单价 | Q52: =N52+O52+P52 -> 0 | R52: =Q52*$R$4 -> 0
A53: 47 | B53: 线性灯槽 | C53: LED灯带制作安装 | D53: [工作内容] 1、LED灯带制作、安装 2、所有工作内容含垂直运输机械等，未详尽列举特征，详见施工图纸、设计规范、施工方案事项均包含在综合单价中。 | E53: m | F53: 1795.8 | G53: 20 | H53: =F53*G53 -> 35916 | I53: =南川一标段!$I$55 -> 65.04 | J53: =F53*I53 -> 116798.83 | K53: 按设计图示尺寸以米计算。 | L53: 全费用综合单价 | Q53: =N53+O53+P53 -> 0 | R53: =Q53*$R$4 -> 0
A54: 48 | B54: 排水沟盖板 | C54: 1、5mm厚钢板预埋 2、20mm厚橡胶胶垫 3、花岗石水篦子铺面 | D54: [工作内容] 1、预埋板制作、安装 2、胶垫安装嵌缝、塞口 3、石材水篦子面板安装 4、该项包含本项工作所有工作内容，所有工作内容含垂直运输机械等，所有工作内容含垂直运输机械等，未详尽列举特征，详见施工图纸、设计规范、施工方案事项均包含在综合单价中。 | E54: m | F54: 77.91 | G54: 71 | H54: =F54*G54 -> 5531.61 | I54: =南川一标段!$I$58 -> 78 | J54: =F54*I54 -> 6076.98 | K54: 按设计图示尺寸以米计算。 | L54: 除甲供材外，此项工作的全费用综合单价 | M54: 甲供材：花岗石 | Q54: =N54+O54+P54 -> 0 | R54: =Q54*$R$4 -> 0
A55: （二） | B55: 楼扶梯区域
A56: 1 | B56: 花岗石梯面 | C56: 1、25厚花岗石(室外烧毛),同色水泥浆擦缝 2、50厚1:3干硬性水泥粘结层,撒素水泥粉 3、水泥浆一道(内掺建筑胶) 4、嵌缝材料种类：按甲方要求嵌缝、打胶，挡水条制作； 5、防护层材料：防护剂六面处理，满足设计和相关规范要求； 6、酸洗、打蜡要求：满足设计和相关规范要求； 7、楼地面伸缩缝、变形缝的处理； 8、其他：该项包含本项工作所有工作内容含垂直运输机械等，未详尽列举特征，详见施工图纸、设计规范、施工方案事项均包含在综合单价中。 | D56: 1.清理基层，试排弹线，锯板磨边，调铺砂浆；铺板、灌缝擦缝、清理净面等全部操作过程； 2.找平层、结合层施工； 3.石材刷防护液、铺贴、水泥浆勾缝，挡水条制作； 4.材料的运输、堆码、清运及场内多次搬运； 5.综合单价包含切角、倒角、磨边、加厚、弧形加工、嵌缝、拉槽、排版损耗、晶面处理等费用，送样的材料费用、检验、试验等工作费用，还包括地砖铺贴前排版图设计工作; 6.配合安装队伍进行多次预留预埋及相关开槽、开洞的修补工作； 7.对已施工完成的成品及其他专业已完成的成品进行保护工作，无论是否由该单位导致的损坏，该单位都应履行修复处理责任； 8.对施工需要拆除或移动的材料，待施工完毕后，恢复原状； 9.完成工作区域的安全文明施工,清理施工遗留下的垃圾； 10.该项包含本项工作所有工作内容含垂直运输机械等，未详尽列举特征，详见施工图纸、设计规范、施工方案事项均包含在综合单价中。 | E56: m2 | F56: 1872.35 | G56: 110 | H56: =F56*G56 -> 205958.5 | I56: =南川一标段!$I$8 -> 160.32 | J56: =F56*I56 -> 300175.15 | K56: 按设计图示尺寸以展开面积计算 | L56: 1、除甲供材外全费用综合单价； 2、甲供材：花岗石 | Q56: =N56+O56+P56 -> 0 | R56: =Q56*$R$4 -> 0
A57: 2 | B57: 石材止灰带 | C57: 石材止灰带 | D57: 1.后置件 2.钢骨架 3.用石材胶粘贴石材 4.石材 5.六面刷界面处理剂，水泥浆檫缝 6.其它:所有工作内容含垂直运输机械等，未详尽列举特征，详见施工图纸、设计规范、施工方案事项均包含在综合单价中 | E57: m2 | F57: 285.08 | G57: 125 | H57: =F57*G57 -> 35635 | I57: =南川一标段!$I$80 -> 228 | J57: =F57*I57 -> 64998.24 | K57: 按设计图示尺寸以展开面积计算 | L57: 1、除甲供材外全费用综合单价； 2、甲供材：石材 | Q57: =N57+O57+P57 -> 0 | R57: =Q57*$R$4 -> 0
A58: 3 | B58: 铝合金条板(锤片)吊顶 | C58: 1、铝合金条板与配套专用龙骨固定(宽150mm,缝75mm,厚1mm) 2、与铝合金方通配套的专用龙骨,间距≤1200,用吊件与钢筋吊杆连接后找平 3、10号镀锌低碳钢丝(或%%C6钢筋)吊杆,双向中距≤1200,吊杆上部与板底预留吊环(勾)固定 4、现浇钢筋混凝土板底预留%%C10钢筋吊环(勾),双向中距≤1200(吊杆长度超过1.5米后需要做反支撑,吊杆长度超过2.5米需做转换层,做法详见二次结构施工安装详图)(转换层另列） 5、天棚伸缩缝、变形缝的处理； 其他：该项包含本项工作所有工作内容含垂直运输机械等，未详尽列举特征，详见施工图纸、设计规范、施工方案事项均包含在综合单价中。 | D58: 基层清理；吊杆制作；吊杆、龙骨安装；面板固定、安装；洞口、检查孔、灯槽等留置、处理及收边收口，按照图纸要求吊顶四周设置圆形收边条、顶棚喷黑处理；材料场内运输；脚手架搭拆，成品保护等。所有工作内容含垂直运输机械等，未详尽列举特征，详见施工图纸、设计规范、施工方案事项均包含在综合单价中 | E58: m2 | F58: 2182.47 | G58: 110 | H58: =F58*G58 -> 240071.7 | I58: =南川一标段!$I$31 -> 182.4 | J58: =F58*I58 -> 398082.53 | K58: 按设计图示尺寸以水平投影面积计算 | L58: 1、除甲供材外全费用综合单价； 2、甲供材：铝板 | Q58: =N58+O58+P58 -> 0 | R58: =Q58*$R$4 -> 0
A59: 4 | B59: 铝合金单板装饰吊顶 | C59: 1、2.5厚铝合金单板与配套专用龙骨固定 2、与铝合金单板配套的专用下层副龙骨联结,间距≤600 3、与安装型式配套的专用上层主龙骨,间距≤1200,用吊件与钢筋吊杆联结后找平 4、10号镀锌低碳钢丝(或%%C8钢筋)吊杆,双向中距≤1200,吊杆上部与板底预留吊环固定 5、现浇钢筋混凝土板底预留%%C10钢筋吊环,双向中距≤1200 6、天棚伸缩缝、变形缝； 其他：该项包含本项工作所有工作内容含垂直运输机械等，未详尽列举特征，详见施工图纸、设计规范、施工方案事项均包含在综合单价中。 | D59: 基层清理；吊杆制作；吊杆、龙骨安装；面板固定、安装；洞口、检查孔、灯槽等留置、处理及收边收口，按照图纸要求吊顶四周设置圆形收边条、顶棚喷黑处理；材料场内运输；脚手架搭拆，成品保护等。所有工作内容含垂直运输机械等，未详尽列举特征，详见施工图纸、设计规范、施工方案事项均包含在综合单价中 | E59: m2 | F59: 460.27 | G59: 120 | H59: =F59*G59 -> 55232.4 | I59: =南川一标段!$I$31 -> 182.4 | J59: =F59*I59 -> 83953.25 | K59: 按设计图示尺寸以水平投影面积计算 | L59: 1、除型钢龙骨及甲供材外全费用综合单价； 2、甲供材：铝板 | Q59: =N59+O59+P59 -> 0 | R59: =Q59*$R$4 -> 0
A60: 5 | B60: 1.3米高玻璃栏板 | C60: 1、1.3米高玻璃栏板 2、玻璃栏板不锈钢方管立柱90*12mm不锈钢扁钢立柱 3、玻璃栏板扶手φ63*3mm异形拉丝不锈钢圆管 4、玻璃栏板防撞栏杆φ51*1.5不锈钢圆管 5、玻璃栏板：8+1.52PVB+8mm钢化夹胶玻璃 5、其他：该项包含本项工作所有工作内容含垂直运输机械等，未详尽列举特征，详见施工图纸、设计规范、施工方案事项均包含在综合单价中。 | D60: 1、后置件的制作、运输、安装；2、金属扶手、栏杆、栏板的制作、运输、安装；3、刷防护材料；4、该项包含金属扶手、栏杆、栏板的所有工作内容，所有工作内容含垂直运输机械等，未详尽列举特征，详见施工图纸、设计规范、施工方案事项均包含在综合单价中 | E60: m | F60: 570.16 | G60: 619.35 | H60: =F60*G60 -> 353128.6 | I60: =南川一标段!$I$85 -> 1085.53 | J60: =F60*I60 -> 618925.78 | K60: 按设计图示尺寸以栏杆扶手的中心线长度计算 | L60: 全费用综合单价 | Q60: =N60+O60+P60 -> 0 | R60: =Q60*$R$4 -> 0
A61: （三） | B61: 雨棚区域
A62: 1 | B62: 混凝土冲劲带 | C62: 1、站台外侧混凝土冲劲带浇筑； 2、冲劲带宽度200mm，高度110mm,具体详见图纸； 3、地面伸缩缝、变形缝的处理； 其它：垂直运输费用已包含在综合单价中，满足设计规范及图纸要求;未详尽列举特征，详见施工图纸、设计规范、施工方案 | D62: 1.清理基层清理净面等全部操作过程； 2.混凝土浇筑施工、养护、搓平，平整顺直； 3.材料的运输、堆码、清运及场内多次搬运； 4.综合单价包含送样的材料费用、检验、试验等工作费用，还包括地砖铺贴前排版图设计工作; 5.配合安装队伍进行多次预留预埋及相关开槽、开洞的修补工作； 6.对已施工完成的成品及其他专业已完成的成品进行保护工作，无论是否由该单位导致的损坏，该单位都应履行修复处理责任； 7.对施工需要拆除或移动的材料，待施工完毕后，恢复原状； 8.完成工作区域的安全文明施工,清理施工遗留下的垃圾； 9.该项包含本项工作所有工作内容含垂直运输机械等，未详尽列举特征，详见施工图纸、设计规范、施工方案事项均包含在综合单价中。 | E62: m | F62: =450*2 -> 900 | G62: 20 | H62: =F62*G62 -> 18000 | I62: =南川一标段!$I$88 -> 71.88 | J62: =F62*I62 -> 64692 | K62: 按设计图示尺寸以延长米计算。 | L62: 除甲供材外，此项工作的全费用综合单价 甲供材：混凝土 | Q62: =N62+O62+P62 -> 0 | R62: =Q62*$R$4 -> 0
A63: 2 | B63: 站台盲道砖 | C63: 1、玻化砖安全线盲道砖面层; 2、5厚坐浆层; 3、45厚1:3干硬性水泥砂浆粘结层; 4、地面伸缩缝、变形缝的处理； 其它：垂直运输费用已包含在综合单价中，满足设计规范及图纸要求;未详尽列举特征，详见施工图纸、设计规范、施工方案 | D63: 1.位置：1、2、3和4站台 2.面层材料：20mm站台盲道砖300*300mm； 3.面层处理：石材养护剂； 贴结层：素水泥浆1道，内掺建筑胶； 4.结合层：45厚1:3干硬性水泥砂浆粘结层； 5.勾缝：水泥砂浆勾缝。 6.该项包含本项工作所有工作内容含垂直运输机械等，未详尽列举特征，详见施工图纸、设计规范、施工方案事项均包含在综合单价中。 | E63: m2 | F63: 540 | G63: 80 | H63: =F63*G63 -> 43200 | I63: =南川一标段!$I$95 -> 96 | J63: =F63*I63 -> 51840 | K63: 按设计图示尺寸以面积计算 | L63: 1、除甲供材外全费用综合单价； 2、甲供材：盲道砖 | Q63: =N63+O63+P63 -> 0 | R63: =Q63*$R$4 -> 0
A64: 3 | B64: 站台安全线 | C64: 1、玻化砖安全线盲道砖面层; 2、5厚坐浆层; 3、45厚1:3干硬性水泥砂浆粘结层; 4、地面伸缩缝、变形缝的处理； 其它：垂直运输费用已包含在综合单价中，满足设计规范及图纸要求;未详尽列举特征，详见施工图纸、设计规范、施工方案 | D64: 1.下料、清理基层、局部涂刷石材防护剂、面层铺设、嵌缝；砂浆制备；开孔、套边处理、成品保护及半成品保护等； 2.该项包含本项工作所有工作内容含垂直运输机械等，未详尽列举特征，详见施工图纸、设计规范、施工方案事项均包含在综合单价中。 | E64: m2 | F64: 90 | G64: 80 | H64: =F64*G64 -> 7200 | I64: =南川一标段!$I$96 -> 96 | J64: =F64*I64 -> 8640 | K64: 按设计图示尺寸以面积计算 | L64: 1、除甲供材外全费用综合单价； 2、甲供材：盲道砖 | Q64: =N64+O64+P64 -> 0 | R64: =Q64*$R$4 -> 0
A65: 4 | B65: 站台帽石 | C65: 1、50厚红色花岗岩(磨光机刨6面满涂防护剂、; 2、5厚坐浆层; 3、30厚1:3干硬性水泥砂浆粘结层; 4、地面伸缩缝、变形缝的处理； 其它：垂直运输费用已包含在综合单价中，满足设计规范及图纸要求;未详尽列举特征，详见施工图纸、设计规范、施工方案 | D65: 1.下料、清理基层、局部涂刷石材防护剂、面层铺设、嵌缝；砂浆制备；开孔、套边处理、成品保护及半成品保护等； 2.该项包含本项工作所有工作内容含垂直运输机械等，未详尽列举特征，详见施工图纸、设计规范、施工方案事项均包含在综合单价中。 | E65: m2 | F65: 900 | G65: 80 | H65: =F65*G65 -> 72000 | I65: =南川一标段!$I$97 -> 126 | J65: =F65*I65 -> 113400 | K65: 按设计图示尺寸以面积计算 | L65: 1、除甲供材外全费用综合单价； 2、甲供材：石材 | Q65: =N65+O65+P65 -> 0 | R65: =Q65*$R$4 -> 0
A66: 5 | B66: 第一站台石材铺面 | C66: 1、600x900 30厚白麻花岗岩(火烧6面满涂防护剂、; 2、5厚坐浆层; 3、30厚1:3干硬性水泥砂浆粘结层; 4、地面伸缩缝、变形缝的处理； 其它：垂直运输费用已包含在综合单价中，满足设计规范及图纸要求;未详尽列举特征，详见施工图纸、设计规范、施工方案 | D66: 1、位置：站台其他铺面、旅客活动平台； 2、工作内容：下料、清理基层、局部涂刷石材防护剂、面层铺设、嵌缝；砂浆制备；开孔、套边处理、成品保护及半成品保护等； 3.该项包含本项工作所有工作内容含垂直运输机械等，未详尽列举特征，详见施工图纸、设计规范、施工方案事项均包含在综合单价中。 | E66: m2 | F66: 2835 | G66: 80 | H66: =F66*G66 -> 226800 | I66: =南川一标段!$I$98 -> 118.32 | J66: =F66*I66 -> 335437.2 | K66: 按设计图示尺寸以面积计算 | L66: 1、除甲供材外全费用综合单价； 2、甲供材：石材 | Q66: =N66+O66+P66 -> 0 | R66: =Q66*$R$4 -> 0
A67: 6 | B67: 第二站台石材铺面 | C67: 1、600x900 30厚白麻花岗岩(火烧6面满涂防护剂、 2、5厚坐浆层; 3、30厚1:3干硬性水泥砂浆粘结层; 4、地面伸缩缝、变形缝的处理； 其它：垂直运输费用已包含在综合单价中，满足设计规范及图纸要求;未详尽列举特征，详见施工图纸、设计规范、施工方案 | D67: 1.工作内容：下料、清理基层、局部涂刷石材防护剂、面层铺设、嵌缝；砂浆制备；开孔、套边处理、成品保护及半成品保护等； 2.该项包含本项工作所有工作内容含垂直运输机械等，未详尽列举特征，详见施工图纸、设计规范、施工方案事项均包含在综合单价中。 | E67: m2 | F67: 2835 | G67: 80 | H67: =F67*G67 -> 226800 | I67: =南川一标段!$I$98 -> 118.32 | J67: =F67*I67 -> 335437.2 | K67: 按设计图示尺寸以面积计算 | L67: 1、除甲供材外全费用综合单价； 2、甲供材：石材 | Q67: =N67+O67+P67 -> 0 | R67: =Q67*$R$4 -> 0
A68: 7 | B68: 灰色氟碳漆踢脚 | C68: 1、清理基面:清理钢筋混凝土基面 2、基层处理:专用腻子找平、修复,厚度不大于5mm 3、灰色涂料底漆涂装:涂刷一遍 4、灰色涂料中涂涂装:涂刷一遍 5、面漆涂装:涂刷两遍 6、其它：垂直运输费用已包含在综合单价中，满足设计规范及图纸要求;未详尽列举特征，详见施工图纸、设计规范、施工方案 | D68: 1.墙体基层处理、找平抹灰、压实； 2.踢脚线制作、运输、安装，面砖背面涂专用粘接剂，用专用勾缝剂勾缝； 3.材料的运输、堆码、清运及场内多次搬运； 4.单价已包括送样的材料费用、检验、试验等工作; 5.配合安装队伍进行多次预留预埋及相关开槽、开洞的修补工作； 6.对已施工完成的成品及其他专业已完成的成品进行保护工作，无论是否由该单位导致的损坏，该单位都应履行修复处理责任； 7.对施工需要拆除或移动的材料，待施工完毕后，恢复原状； 8.完成工作区域的安全文明施工,清理施工遗留下的垃圾； 9.该项包含本项工作所有工作内容含垂直运输机械等，未详尽列举特征，详见施工图纸、设计规范、施工方案事项均包含在综合单价中。 | E68: m2 | F68: =44*3*0.15*2 -> 39.6 | G68: 23.5 | H68: =F68*G68 -> 930.6 | I68: =南川一标段!$I$99 -> 251.4 | J68: =F68*I68 -> 9955.44 | K68: 以平方米计量，按设计图示长度乘高度以面积计算； | L68: 此项工作的全费用综合单价 | Q68: =N68+O68+P68 -> 0 | R68: =Q68*$R$4 -> 0
A69: 8 | B69: 栏杆基础 | C69: 站台栏杆基础200*200 4C8主筋，箍筋C8-200，预埋件预埋 | D69: 1、钢筋绑扎、模板及支撑制作、安装、拆除、堆放、运输及清理模内杂物、刷隔离剂等； 2、混凝土制作、运输、浇筑、振捣、养护； 3、栏杆预埋件预埋 4、合同中明示或暗示的其他工作内容 | E69: m | F69: =F70+F71 -> 967.76 | G69: =N69*50+(O69+P69)*0.9+0.4*1*50 -> 20 | H69: =F69*G69 -> 19355.2 | I69: =南川一标段!$I$107 -> 67.8 | J69: =F69*I69 -> 65614.13 | K69: 按设计图示尺寸以长度计算 | L69: 1、除甲供材外全费用综合单价； 2、甲供材：钢筋、模板、混凝土 | Q69: =N69+O69+P69 -> 0 | R69: =Q69*$R$4 -> 0
A70: 9 | B70: 1.4米高不锈钢栏杆 | C70: 1、1.4米高栏杆 2、70*4拉丝不锈钢碳素钢管 3、玻璃栏板扶手、横杆φ63*4mm异形拉丝不锈钢圆管 4、竖向栏杆30*4拉丝不锈钢碳素复合钢管 5、其它：垂直运输费用已包含在综合单价中，满足设计规范及图纸要求;未详尽列举特征，详见施工图纸、设计规范、施工方案 | D70: 1.预埋件制作、运输、埋设安装； 2.栏杆制作、运输、安装、防护； 3.综合单价含送样的材料费用、检验、试验等费用; 4.材料的运输、摆放、清运及场内多次搬运； 5.对已施工完成的成品及其他专业已完成的成品进行保护工作，无论是否由该单位导致的损坏，该单位都应履行修复处理责任； 6.对施工需要拆除或移动的材料，待施工完毕后，恢复原状； 7.完成工作区域的安全文明施工,清理施工遗留下的垃圾； 8.该项包含本项工作所有工作内容含垂直运输机械等，未详尽列举特征，详见施工图纸、设计规范、施工方案事项均包含在综合单价中。 | E70: m | F70: 914.8 | G70: 931.71 | H70: =F70*G70 -> 852328.31 | I70: =R70 -> 690.28 | J70: =F70*I70 -> 631468.14 | K70: 按设计图示尺寸以长度计算 | L70: 全费用综合单价 | N70: =主材表!$L$35 -> 486.73 | O70: 3.5 | P70: =南川一标段!P109 -> 85 | Q70: =N70+O70+P70 -> 575.23 | R70: =Q70*$R$4 -> 690.28
A71: 10 | B71: 1.1米高不锈钢栏杆 | C71: 1、1.1米高玻璃栏板 2、玻璃栏板不锈钢方管立柱63*25*5mm拉丝不锈钢管 3、玻璃栏板扶手φ63*3mm异形拉丝不锈钢圆管 4、玻璃栏板防撞栏杆φ51*1.5不锈钢圆管 5、其它：垂直运输费用已包含在综合单价中，满足设计规范及图纸要求;未详尽列举特征，详见施工图纸、设计规范、施工方案 | D71: 1.预埋件制作、运输、埋设安装； 2.玻璃栏板制作、运输、安装、防护，安装驳接爪； 3.综合单价含栏板送样的材料费用、检验、试验等费用; 4.材料的运输、摆放、清运及场内多次搬运； 5.对已施工完成的成品及其他专业已完成的成品进行保护工作，无论是否由该单位导致的损坏，该单位都应履行修复处理责任； 6.对施工需要拆除或移动的材料，待施工完毕后，恢复原状； 7.完成工作区域的安全文明施工,清理施工遗留下的垃圾； 8.该项包含本项工作所有工作内容含垂直运输机械等，未详尽列举特征，详见施工图纸、设计规范、施工方案事项均包含在综合单价中。 | E71: m | F71: 52.96 | G71: 692.73 | H71: =F71*G71 -> 36686.98 | I71: =南川一标段!$I$109 -> 493.81 | J71: =F71*I71 -> 26152.18 | K71: 按设计图示尺寸以长度计算 | L71: 全费用综合单价 | Q71: =N71+O71+P71 -> 0 | R71: =Q71*$R$4 -> 0
A72: 11 | B72: 地面沉降缝 | C72: 1、桥面沉降伸缩缝,宽度约360mm 1.嵌缝材料种类:非收缩嵌缝胶2.止水带材料种类:详图纸及设计说明；3.盖缝材料:同地面饰面4.连接件:铝合金基座、配件5.其它:详见设计图纸及招标文件6.部位:楼地面 | D72: 1.建筑岩棉铺底、止水带安装； 2.机械螺丝、抗震弹簧安装、铝合金支座安装； 3.成品沉降缝铝合金配件安装、侧架安装，成品胶条封堵; 4.与石材交接部位采用填缝剂封堵； 5.对已施工完成的成品及其他专业已完成的成品进行保护工作，无论是否由该单位导致的损坏，该单位都应履行修复处理责任； 6.对施工需要拆除或移动的材料，待施工完毕后，恢复原状； 7.完成工作区域的安全文明施工,清理施工遗留下的垃圾； 8.该项包含本项工作所有工作内容含垂直运输机械等，未详尽列举特征，详见施工图纸、设计规范、施工方案事项均包含在综合单价中。 | E72: m | F72: =450/6*2 -> 150 | G72: 130 | H72: =F72*G72 -> 19500 | I72: =R72 -> 204.6 | J72: =F72*I72 -> 30690 | K72: 按设计图示尺寸以长度计算 | L72: 除甲供材外，此项工作的全费用综合单价 甲供材：花岗石面层 | N72: 120 | O72: 5.5 | P72: 45 | Q72: =N72+O72+P72 -> 170.5 | R72: =Q72*$R$4 -> 204.6 | S72: =_xlfn.DISPIMG("ID_B49BE2396C3145B2BC1CDC2722487EEF",1) -> =DISPIMG("ID_B49BE2396C3145B2BC1CDC2722487EEF",1)
A73: 12 | B73: 沉砂井盖板 | C73: 规格型号：900*600盖板 1、花岗石水篦子铺面，提手50*20矩形洞口，不锈钢包边 2、30厚1：3干硬性水泥砂浆 3、60mm厚C25钢筋混凝土盖板 4、其它：垂直运输费用已包含在综合单价中，满足设计规范及图纸要求;未详尽列举特征，详见施工图纸、设计规范、施工方案 | D73: [工作内容] 1、盖板板制作、安装 2、盖板安装嵌缝、塞口 3、石材水篦子面板不锈钢包边处理、安装 4、该项包含本项工作所有工作内容含垂直运输机械等，未详尽列举特征，详见施工图纸、设计规范、施工方案事项均包含在综合单价中。 | E73: 个 | F73: 88 | G73: 340 | H73: =F73*G73 -> 29920 | I73: =南川一标段!$I$110 -> 358.86 | J73: =F73*I73 -> 31579.68 | K73: 按设计图示尺寸以个计算。 | L73: 除甲供材外，此项工作的全费用综合单价 甲供材：花岗石面层 | Q73: =N73+O73+P73 -> 0 | R73: =Q73*$R$4 -> 0
A74: 13 | B74: 站台端部检修爬梯 | C74: 带护笼钢爬梯，做法参考15J401（D19-C3,D18-B1,D18-B3,WT2B-6.4)，护笼做法参考15J401-D15-AC 其它：垂直运输费用已包含在综合单价中，满足设计规范及图纸要求;未详尽列举特征，详见施工图纸、设计规范、施工方案 | D74: 1、钢爬梯预埋件200*300*10制作、安装，刷防腐防锈涂料； 2、护笼安装 3、钢爬梯安装 4、该项包含本项工作所有工作内容所有工作内容含垂直运输机械等，未详尽列举特征，详见施工图纸、设计规范、施工方案事项均包含在综合单价中。 | E74: t | F74: 4 | G74: 8726.4 | H74: =ROUND(F74*G74,2) -> 34905.6 | I74: =南川一标段!$I$111 -> 10536 | J74: =F74*I74 -> 42144 | K74: 按设计图示尺寸乘以理论质量计算，不扣除单个≤0.3m2的孔洞，焊条、铆钉、螺栓等不另增加质量 | L74: 全费用综合单价 | Q74: =N74+O74+P74 -> 0 | R74: =Q74*$R$4 -> 0
A75: 14 | B75: 防坠落系统 | C75: 1、预埋200*200*10厚钢板，表面刷防腐防锈涂料，下埋12钢筋植入混凝土； 2、防坠落钢拉索基座制安，直径10，间距3m布置，纵向穿直径10不锈钢拉索，顶部与基座环形钢筋焊接； 3、防坠落措施制作通常30*3圆钢管，间距6m 4、其它：垂直运输费用已包含在综合单价中，满足设计规范及图纸要求;未详尽列举特征，详见施工图纸、设计规范、施工方案 | D75: 1.预埋件制作、运输、埋设安装； 2.防坠落基座及拉绳制作、运输、安装、防护； 3.综合单价含送样的材料费用、检验、试验等费用; 4.材料的运输、摆放、清运及场内多次搬运； 5.对已施工完成的成品及其他专业已完成的成品进行保护工作，无论是否由该单位导致的损坏，该单位都应履行修复处理责任； 6.对施工需要拆除或移动的材料，待施工完毕后，恢复原状； 7.完成工作区域的安全文明施工,清理施工遗留下的垃圾； 8.该项包含本项工作所有工作内容含垂直运输机械等，未详尽列举特征，详见施工图纸、设计规范、施工方案事项均包含在综合单价中。 | E75: m | F75: 900 | G75: 93 | H75: =F75*G75 -> 83700 | I75: =南川一标段!$I$112 -> 360.13 | J75: =F75*I75 -> 324117 | K75: 按设计图示以长度计算 | L75: 此项工作的全费用综合单价 | Q75: =N75+O75+P75 -> 0 | R75: =Q75*$R$4 -> 0
B76: 室外铺装
A77: 1 | B77: ST 01 白麻花岗石材-室外（非架空） | C77: 1、50mm水洗火烧面(磨光度30度)(750mm×750mm) 2、50mm厚1:3干硬性水泥砂浆结合层 3、150厚C20混凝土,按4~6m分仓跳格浇筑 4、200厚3:7灰土垫层或级配砂石 5、素土夯实,压实系数≥0.94 | D77: 1.清理基层，试排弹线，锯板磨边，调铺砂浆；铺板、灌缝擦缝、清理净面等全部操作过程； 2.找平层、结合层施工； 3.石材刷防护液、铺贴、水泥浆勾缝； 4.材料的运输、堆码、清运及场内多次搬运； 5.综合单价包含切角、倒角、磨边、加厚、弧形加工、嵌缝、拉槽、排版损耗、晶面处理等费用，送样的材料费用、检验、试验等工作费用，还包括地砖铺贴前排版图设计工作; 6.配合安装队伍进行多次预留预埋及相关开槽、开洞的修补工作； 7.对已施工完成的成品及其他专业已完成的成品进行保护工作，无论是否由该单位导致的损坏，该单位都应履行修复处理责任； 8.对施工需要拆除或移动的材料，待施工完毕后，恢复原状； 9.完成工作区域的安全文明施工,清理施工遗留下的垃圾； 10.该项包含本项工作所有工作内容，未详尽列举特征，详见施工图纸、设计规范、施工方案事项均包含在综合单价中。 | E77: m2 | F77: =3092.47+890 -> 3982.47 | G77: 80 | H77: =F77*G77 -> 318597.6 | I77: =南川一标段!$I$114 -> 118.32 | J77: =F77*I77 -> 471205.85 | K77: 按设计图示尺寸以面积计算。 | L77: 除甲供材外，此项工作的全费用综合单价 甲供材：石材、混凝土、级配砂石 | Q77: =N77+O77+P77 -> 0 | R77: =Q77*$R$4 -> 0
A78: 2 | B78: 外墙3 真石漆外墙 | C78: 1、涂刷罩面清漆 2、涂饰第二遍面层涂料(透明) 3、涂饰面层涂料(透明) 4、喷主层涂料 5、辊、刷或喷底层涂料 6、5厚干粉类聚合物水泥防水砂浆,中间压入一层耐碱玻璃纤维网布 7、6厚1:2.5水泥砂浆找平 8、9厚1:3水泥砂浆 9、刷专用界面剂一道 | D78: 1.基层处理； 2.满刮腻子，涂刷封闭漆； 3.喷刷真石漆面层，收边收口、勾缝； 4.材料的运输、堆码、清运及场内多次搬运； 5.单价已包括送样的材料费用、检验、试验等工作; 6.配合安装队伍进行多次预留预埋及相关开槽、开洞的修补工作； 7.对已施工完成的成品及其他专业已完成的成品进行保护工作，无论是否由该单位导致的损坏，该单位都应履行修复处理责任； 8.对施工需要拆除或移动的材料，待施工完毕后，恢复原状； 9.完成工作区域的安全文明施工,清理施工遗留下的垃圾； 10.该项包含本项工作所有工作内容，未详尽列举特征，详见施工图纸、设计规范、施工方案事项均包含在综合单价中。 | E78: m2 | F78: 1540.46 | G78: 53.11 | H78: =F78*G78 -> 81813.83 | I78: =南川一标段!$I$115 -> 70.2 | J78: =F78*I78 -> 108140.29 | K78: 按设计图示尺寸以水平投影面积计算。 | L78: 相关工作全部费用 | Q78: =N78+O78+P78 -> 0 | R78: =Q78*$R$4 -> 0
A79: 3 | B79: 防撞墩 | C79: 石材防撞墩 | D79: 1、材质：球型石材 2、工作内容：石材底座固定、防撞墩安装及固定、材料运输等 | E79: 个 | F79: 186 | G79: 210 | H79: =F79*G79 -> 39060 | I79: =南川一标段!$I$116 -> 270 | J79: =F79*I79 -> 50220 | K79: 根据图纸及技术交底，按现场实际完成的数量按个数计算。 | L79: 相关工作全部费用 | Q79: =N79+O79+P79 -> 0 | R79: =Q79*$R$4 -> 0
A80: 4 | B80: 围墙钢制大门 | C80: 围墙钢制大门 | D80: 1、龙骨及面层钢板制安，油漆喷涂；2、规格：综合，详图纸； 3、包括除以上工作内容外，完成钢大门制安的所有工序及采取的各种技术措施等工作。 | E80: m2 | F80: 25.25 | G80: 340 | H80: =F80*G80 -> 8585 | I80: =南川一标段!$I$117 -> 504.6 | J80: =F80*I80 -> 12741.15 | K80: 根据图纸及技术交底，按现场实际完成的数量按面积计算。 | L80: 相关工作全部费用 | Q80: =N80+O80+P80 -> 0 | R80: =Q80*$R$4 -> 0
B81: 不含税合计 | H81: =SUM(H7:H80) -> 9001905.6 | J81: =SUM(J7:J80) -> 12447829
B82: 税金（9%） | H82: =H81*0.09 -> 810171.5 | J82: =J81*0.09 -> 1120304.6
B83: 含税合计 | H83: =H82+H81 -> 9812077.1 | J83: =J82+J81 -> 13568134
J84: =J83/H83 -> 1.38

Sheet 巴南三标段
A1: 重庆站房2标装饰装修三标段巴南站分包工程招标控制价审核表
A2: 项目名称：中铁建工集团有限公司重庆至黔江铁路站房工程2标项目经理部 | N2: 单位：元
A3: 序号 | B3: 项目名称 | C3: 项目特征 | D3: 工作内容 | E3: 单位 | F3: 工程量 | G3: 控制价 | I3: 上报金额 | K3: 单价差额 | L3: 工程量计算规则 | M3: 费用组成 | N3: 备注 | O3: 主材 | P3: 辅材 | Q3: 人工 | R3: 单价 | S3: 取费
G4: 不含税单价（元） | H4: 不含税合价（元） | I4: 不含税单价（元） | J4: 不含税合价（元） | S4: =南川一标段!$R$4 -> 1.2
A5: 一 | B5: 巴南站
A6: （一） | B6: 站房非公共区
A7: 1 | B7: 花岗石地面 | C7: 1、铺25厚磨光花岗石板(六面涂刷石材保护剂),同色稀水泥浆擦 2、50厚1:3干硬性水泥粘结层,撒素水泥粉 3、水泥浆一道(内掺建筑胶) 4、嵌缝材料种类：按甲方要求嵌缝、打胶； 5、防护层材料：防护剂六面处理，满足设计和相关规范要求； 6、酸洗、打蜡要求：满足设计和相关规范要求； 7、楼地面伸缩缝、变形缝的处理； 8、其它：该项包含本项工作所有工作内容含垂直运输机械等，未详尽列举特征，详见施工图纸、设计规范、施工方案事项均包含在综合单价中。 (石材规格800*800) | D7: 1.清理基层，试排弹线，锯板磨边，调铺砂浆；铺板、灌缝擦缝、清理净面等全部操作过程； 2.找平层、结合层施工； 3.石材刷防护液、铺贴、水泥浆勾缝； 4.材料的运输、堆码、清运及场内多次搬运； 5.综合单价包含切角、倒角、磨边、加厚、弧形加工、嵌缝、拉槽、排版损耗、晶面处理等费用，送样的材料费用、检验、试验等工作费用，还包括地砖铺贴前排版图设计工作; 6.配合安装队伍进行多次预留预埋及相关开槽、开洞的修补工作； 7.对已施工完成的成品及其他专业已完成的成品进行保护工作，无论是否由该单位导致的损坏，该单位都应履行修复处理责任； 8.对施工需要拆除或移动的材料，待施工完毕后，恢复原状； 9.完成工作区域的安全文明施工,清理施工遗留下的垃圾； 10.该项包含本项工作所有工作内容含垂直运输机械等，未详尽列举特征，详见施工图纸、设计规范、施工方案事项均包含在综合单价中。 | E7: m2 | F7: 365.77 | G7: 85 | H7: =F7*G7 -> 31090.45 | I7: =南川一标段!$I$7 -> 118.32 | J7: =F7*I7 -> 43277.91 | K7: =G7-I7 -> -33.32 | L7: 按设计图示尺寸以面积计算。 | M7: 除甲供外，此项工作的全费用综合单价 | N7: 甲供材料：石材 | R7: =O7+P7+Q7 -> 0 | S7: =R7*$S$4 -> 0
A8: 2 | B8: 防滑地砖地面 | C8: 1、面层：10厚玻化砖(防滑),同色水泥浆擦缝 2、30厚1:3干硬性水泥砂浆,表面撒水泥粉 3、嵌缝材料种类：按甲方要求嵌缝、打胶； 4、防护层材料：满足设计和相关规范要求； 5、酸洗、打蜡要求：满足设计和相关规范要求； 6、楼地面伸缩缝、变形缝的处理； 7、其它：该项包含本项工作所有工作内容含垂直运输机械等，未详尽列举特征，详见施工图纸、设计规范、施工方案事项均包含在综合单价中。 (地砖规格600*600) | D8: 1.基层清理、找平、打磨、甩浆、弹线、定位； 2.结合层施工； 3.防滑地砖铺贴，干水泥擦缝； 4.材料的运输、堆码、清运及场内多次搬运； 5.单价已包括送样的材料费用、检验、试验等工作，还包括地砖铺贴前排版图设计工作; 6.配合安装队伍进行多次预留预埋及相关开槽、开洞的修补工作； 7.对已施工完成的成品及其他专业已完成的成品进行保护工作，无论是否由该单位导致的损坏，该单位都应履行修复处理责任； 8.对施工需要拆除或移动的材料，待施工完毕后，恢复原状； 9.完成工作区域的安全文明施工,清理施工遗留下的垃圾； 10.该项包含本项工作所有工作内容含垂直运输机械等，未详尽列举特征，详见施工图纸、设计规范、施工方案事项均包含在综合单价中。 | E8: m2 | F8: 664.72 | G8: 120 | H8: =F8*G8 -> 79766.4 | I8: =南川一标段!$I$10 -> 165.22 | J8: =F8*I8 -> 109825.04 | K8: =G8-I8 -> -45.22 | L8: 按设计图示尺寸以面积计算。 | M8: 此项工作的全费用综合单价 | R8: =O8+P8+Q8 -> 0 | S8: =R8*$S$4 -> 0
A9: 3 | B9: 防静电架空地面 | C9: 1、300高防静电活动地板,耐压强度10kN/㎡,配成套支架 2、10厚地砖(色另定) 3、20厚1:3干硬性砂浆,表面撒水泥粉 4、其它：该项包含本项工作所有工作内容含垂直运输机械等，未详尽列举特征，详见施工图纸、设计规范、施工方案事项均包含在综合单价中。 | D9: 1.基层清理、找平、打磨、甩浆、弹线、定位； 2.水泥砂浆找平； 3.安装固定支柱、横梁，防静电活动地板铺装； 4.材料的运输、堆码、清运及场内多次搬运； 5.单价已包括送样的材料费用、检验、试验等工作; 6.配合安装队伍进行多次预留预埋及相关开槽、开洞的修补工作； 7.对已施工完成的成品及其他专业已完成的成品进行保护工作，无论是否由该单位导致的损坏，该单位都应履行修复处理责任； 8.对施工需要拆除或移动的材料，待施工完毕后，恢复原状； 9.完成工作区域的安全文明施工,清理施工遗留下的垃圾。 10.该项包含本项工作所有工作内容含垂直运输机械等，未详尽列举特征，详见施工图纸、设计规范、施工方案事项均包含在综合单价中 | E9: m2 | F9: 199.77 | G9: 316.06 | H9: =F9*G9 -> 63139.31 | I9: =南川一标段!$I$14 -> 391.2 | J9: =F9*I9 -> 78150.02 | K9: =G9-I9 -> -75.14 | L9: 按设计图示尺寸以面积计算。 | M9: 此项工作的全费用综合单价 | R9: =O9+P9+Q9 -> 0 | S9: =R9*$S$4 -> 0
A10: 4 | B10: 水泥基自流平地面 | C10: 1、5厚水泥基自流平面层 2、涂刷自流平界面剂 3、其他：该项包含本项工作所有工作内容含垂直运输机械等，未详尽列举特征，详见施工图纸、设计规范、施工方案事项均包含在综合单价中。 | D10: 1.基层清理、找平、打磨、甩浆、定位、弹线； 2.刷界面剂一道； 3.自流平水泥施工、刮平、分格、养护、填塞分格缝、打磨面层； 4.材料的运输、堆码、清运及场内多次搬运； 5.单价已包括送样的材料费用、检验、试验等工作; 6.配合安装队伍进行多次预留预埋及相关开槽、开洞的修补工作； 7.对已施工完成的成品及其他专业已完成的成品进行保护工作，无论是否由该单位导致的损坏，该单位都应履行修复处理责任； 8.对施工需要拆除或移动的材料，待施工完毕后，恢复原状； 9.完成工作区域的安全文明施工,清理施工遗留下的垃圾； 10.该项包含本项工作所有工作内容含垂直运输机械等，未详尽列举特征，详见施工图纸、设计规范、施工方案事项均包含在综合单价中。 | E10: m2 | F10: 235.52 | G10: 47.92 | H10: =F10*G10 -> 11286.12 | I10: =南川一标段!$I$13 -> 28.8 | J10: =F10*I10 -> 6782.98 | K10: =G10-I10 -> 19.12 | L10: 按设计图示尺寸以面积计算。 | M10: 此项工作的全费用综合单价 | R10: =O10+P10+Q10 -> 0 | S10: =R10*$S$4 -> 0
A11: 5 | B11: 防滑地砖梯面 | C11: 1、面层：10厚玻化砖(防滑),同色水泥浆擦缝 2、30厚1:3干硬性水泥砂浆,表面撒水泥粉 3、嵌缝材料种类：按甲方要求嵌缝、打胶，挡水条制作； 4、防护层材料：满足设计和相关规范要求； 5、酸洗、打蜡要求：满足设计和相关规范要求； 6、楼地面伸缩缝、变形缝的处理； 7、其他：该项包含本项工作所有工作内容含垂直运输机械等，未详尽列举特征，详见施工图纸、设计规范、施工方案事项均包含在综合单价中。 (地砖规格600*600) | D11: 1.基层清理、找平、打磨、甩浆、弹线、定位； 2.结合层施工； 3.防滑地砖铺贴，干水泥擦缝，挡水条制作； 4.材料的运输、堆码、清运及场内多次搬运； 5.单价已包括送样的材料费用、检验、试验等工作，还包括地砖铺贴前排版图设计工作; 6.配合安装队伍进行多次预留预埋及相关开槽、开洞的修补工作； 7.对已施工完成的成品及其他专业已完成的成品进行保护工作，无论是否由该单位导致的损坏，该单位都应履行修复处理责任； 8.对施工需要拆除或移动的材料，待施工完毕后，恢复原状； 9.完成工作区域的安全文明施工,清理施工遗留下的垃圾； 10.该项包含本项工作所有工作内容含垂直运输机械等，未详尽列举特征，详见施工图纸、设计规范、施工方案事项均包含在综合单价中。 | E11: m2 | F11: 119.87 | G11: 135 | H11: =F11*G11 -> 16182.45 | I11: =南川一标段!$I$11 -> 175.84 | J11: =F11*I11 -> 21077.94 | K11: =G11-I11 -> -40.84 | L11: 按设计图示尺寸以展开面积计算。 | M11: 此项工作的全费用综合单价 | R11: =O11+P11+Q11 -> 0 | S11: =R11*$S$4 -> 0
A12: 6 | B12: 防滑地砖楼面 | C12: 1、面层：10厚玻化砖(防滑),同色水泥浆擦缝 2、30厚1:3干硬性水泥砂浆,表面撒水泥粉 3、嵌缝材料种类：按甲方要求嵌缝、打胶； 4、防护层材料：满足设计和相关规范要求； 5、酸洗、打蜡要求：满足设计和相关规范要求； 6、楼地面伸缩缝、变形缝的处理； 7、其他：该项包含本项工作所有工作内容含垂直运输机械等，未详尽列举特征，详见施工图纸、设计规范、施工方案事项均包含在综合单价中。 (地砖规格600*600) | D12: 1.基层清理、找平、打磨、甩浆、弹线、定位； 2.结合层施工； 3.防滑地砖铺贴，干水泥擦缝； 4.材料的运输、堆码、清运及场内多次搬运； 5.单价已包括送样的材料费用、检验、试验等工作，还包括地砖铺贴前排版图设计工作; 6.配合安装队伍进行多次预留预埋及相关开槽、开洞的修补工作； 7.对已施工完成的成品及其他专业已完成的成品进行保护工作，无论是否由该单位导致的损坏，该单位都应履行修复处理责任； 8.对施工需要拆除或移动的材料，待施工完毕后，恢复原状； 9.完成工作区域的安全文明施工,清理施工遗留下的垃圾； 10.该项包含本项工作所有工作内容含垂直运输机械等，未详尽列举特征，详见施工图纸、设计规范、施工方案事项均包含在综合单价中。 | E12: m2 | F12: 257.7 | G12: 120 | H12: =F12*G12 -> 30924 | I12: =南川一标段!$I$12 -> 165.22 | J12: =F12*I12 -> 42577.19 | K12: =G12-I12 -> -45.22 | L12: 按设计图示尺寸以面积计算。 | M12: 此项工作的全费用综合单价 | R12: =O12+P12+Q12 -> 0 | S12: =R12*$S$4 -> 0
A13: 7 | B13: 水泥踢脚 | C13: 1、6厚1:2.5水泥砂浆抹面压实赶光 2、刷素水泥浆一道 3、7厚1:1:6水泥石灰膏砂浆打底骚猫或划出纹道 4、3厚外加剂专用砂浆抹基底刮糙(抹前用水喷湿墙面) 5、其他：该项包含本项工作所有工作内容含垂直运输机械等，未详尽列举特征，详见施工图纸、设计规范、施工方案事项均包含在综合单价中。 | D13: 1.墙体基层处理、找平抹灰、压实； 2.踢脚线制作、运输、安装，抹面压实赶光； 3.材料的运输、堆码、清运及场内多次搬运； 4.单价已包括送样的材料费用、检验、试验等工作; 5.配合安装队伍进行多次预留预埋及相关开槽、开洞的修补工作； 6.对已施工完成的成品及其他专业已完成的成品进行保护工作，无论是否由该单位导致的损坏，该单位都应履行修复处理责任； 7.对施工需要拆除或移动的材料，待施工完毕后，恢复原状； 8.完成工作区域的安全文明施工,清理施工遗留下的垃圾； 9.该项包含本项工作所有工作内容含垂直运输机械等，未详尽列举特征，详见施工图纸、设计规范、施工方案事项均包含在综合单价中。 | E13: m2 | F13: 20.46 | G13: 35 | H13: =F13*G13 -> 716.1 | I13: =南川一标段!$I$17 -> 174.1 | J13: =F13*I13 -> 3562.09 | K13: =G13-I13 -> -139.1 | L13: 以平方米计量，按设计图示长度乘高度以面积计算。 | M13: 此项工作的全费用综合单价 | R13: =O13+P13+Q13 -> 0 | S13: =R13*$S$4 -> 0
A14: 8 | B14: 地砖踢脚 | C14: 1、粘贴10厚地砖,专用勾缝剂勾缝 2、9厚1:2水泥砂浆(内掺3%超密聚合物防水剂)粘结层 3、素水泥浆一道(内掺建筑胶) 4、其他：该项包含本项工作所有工作内容含垂直运输机械等，未详尽列举特征，详见施工图纸、设计规范、施工方案事项均包含在综合单价中。 | D14: 1.墙体基层处理、找平抹灰、压实； 2.踢脚线制作、运输、安装，面砖背面涂专用粘接剂，用专用勾缝剂勾缝； 3.材料的运输、堆码、清运及场内多次搬运； 4.单价已包括送样的材料费用、检验、试验等工作; 5.配合安装队伍进行多次预留预埋及相关开槽、开洞的修补工作； 6.对已施工完成的成品及其他专业已完成的成品进行保护工作，无论是否由该单位导致的损坏，该单位都应履行修复处理责任； 7.对施工需要拆除或移动的材料，待施工完毕后，恢复原状； 8.完成工作区域的安全文明施工,清理施工遗留下的垃圾； 9.该项包含本项工作所有工作内容含垂直运输机械等，未详尽列举特征，详见施工图纸、设计规范、施工方案事项均包含在综合单价中。 | E14: m2 | F14: 59.69 | G14: 130 | H14: =F14*G14 -> 7759.7 | I14: =南川一标段!$I$18 -> 233.83 | J14: =F14*I14 -> 13957.31 | K14: =G14-I14 -> -103.83 | L14: 以平方米计量，按设计图示长度乘高度以面积计算。 | M14: 此项工作的全费用综合单价 | R14: =O14+P14+Q14 -> 0 | S14: =R14*$S$4 -> 0
A15: 9 | B15: 不锈钢踢脚 | C15: 1、1.0厚不锈钢金属踢脚板,下端用水泥钉钉入地面垫层,中距300 2、10厚1:3水泥砂浆压实抹平 3、素水泥浆一道(内掺建筑胶)(用于混凝土空心砌块墙);3厚外加剂专用砂浆抹基底刮糙(抹灰前用水喷湿墙面)(用于蒸 压加气混凝土砌块墙) 4、水泥钉固定踢脚上端,中距300 5、其他：该项包含本项工作所有工作内容含垂直运输机械等，未详尽列举特征，详见施工图纸、设计规范、施工方案事项均包含在综合单价中。 | D15: 1.墙体基层处理； 2.粘贴、固定不锈钢踢脚线； 3.材料的运输、堆码、清运及场内多次搬运； 4.单价已包括送样的材料费用、检验、试验等工作; 5.配合安装队伍进行多次预留预埋及相关开槽、开洞的修补工作； 6.对已施工完成的成品及其他专业已完成的成品进行保护工作，无论是否由该单位导致的损坏，该单位都应履行修复处理责任； 7.对施工需要拆除或移动的材料，待施工完毕后，恢复原状； 8.完成工作区域的安全文明施工,清理施工遗留下的垃圾； 9.该项包含本项工作所有工作内容含垂直运输机械等，未详尽列举特征，详见施工图纸、设计规范、施工方案事项均包含在综合单价中。 | E15: m2 | F15: 9.23 | G15: 272.98 | H15: =F15*G15 -> 2519.61 | I15: =南川一标段!$I$19 -> 519.74 | J15: =F15*I15 -> 4797.2 | K15: =G15-I15 -> -246.76 | L15: 以平方米计量，按设计图示长度乘高度以面积计算。 | M15: 此项工作的全费用综合单价 | R15: =O15+P15+Q15 -> 0 | S15: =R15*$S$4 -> 0
A16: 10 | B16: 穿孔吸声板墙面 | C16: 1、10厚穿孔板用螺钉固定于龙骨上 2、玻璃布一层绷紧固定于龙骨表面 3、40厚岩棉(或玻璃棉)毡,建筑胶粘济粘贴于龙骨档内 4、75X50X0.7轻钢龙骨用膨胀螺栓宇墙面固定,中距按板规格设计 6、在混凝土梁、柱或现浇混凝土条带、砌块上钻孔打入M6X75膨胀螺栓,中距按穿孔板规格设计 7、6~9厚DP-HR砂浆修补墙面抹平 8、3厚外加剂专用砂浆抹基底,抹前喷湿墙面(用于加气混凝土砌块墙) 9、其他：该项包含本项工作所有工作内容含垂直运输机械等，未详尽列举特征，详见施工图纸、设计规范、施工方案事项均包含在综合单价中。 | D16: 1.基层处理; 2.龙骨安装； 3.填充40厚岩棉(或玻璃棉)毡,； 4.穿孔板用螺钉固定于龙骨上； 5.材料的运输、堆码、清运及场内多次搬运； 6.单价已包括送样的材料费用、检验、试验等工作; 7.配合安装队伍进行多次预留预埋及相关开槽、开洞的修补工作； 8.对已施工完成的成品及其他专业已完成的成品进行保护工作，无论是否由该单位导致的损坏，该单位都应履行修复处理责任； 9.对施工需要拆除或移动的材料，待施工完毕后，恢复原状； 10.完成工作区域的安全文明施工,清理施工遗留下的垃圾； 11.该项包含本项工作所有工作内容含垂直运输机械等，未详尽列举特征，详见施工图纸、设计规范、施工方案事项均包含在综合单价中。 | E16: m2 | F16: 272.11 | G16: 136.53 | H16: =F16*G16 -> 37151.18 | I16: =南川一标段!$I$24 -> 294.36 | J16: =F16*I16 -> 80098.3 | K16: =G16-I16 -> -157.83 | L16: 按设计图示尺寸以硅酸钙板吊顶水平投影面积计算 | M16: 此项工作的全费用综合单价 | R16: =O16+P16+Q16 -> 0 | S16: =R16*$S$4 -> 0
A17: 11 | B17: 无机涂料墙面 | C17: 1、喷(刷、辊)无机内墙薄涂涂料2道 2、满刮2厚腻子砂磨平 3、其他：该项包含本项工作所有工作内容含垂直运输机械等，未详尽列举特征，详见施工图纸、设计规范、施工方案事项均包含在综合单价中。 | D17: 1.内墙基层处理； 2.水泥砂浆找平打底扫毛，内掺建筑胶； 3.水泥砂浆找平层、水泥砂浆罩面压光施工； 4.满刮腻子两遍，找平磨光； 5.喷（刷）无机涂料2道； 6.材料的运输、堆码、清运及场内多次搬运； 7.单价已包括送样的材料费用、检验、试验等工作; 8.配合安装队伍进行多次预留预埋及相关开槽、开洞的修补工作； 9.对已施工完成的成品及其他专业已完成的成品进行保护工作，无论是否由该单位导致的损坏，该单位都应履行修复处理责任； 10.对施工需要拆除或移动的材料，待施工完毕后，恢复原状； 11.完成工作区域的安全文明施工,清理施工遗留下的垃圾。 12.该项包含本项工作所有工作内容含垂直运输机械等，未详尽列举特征，详见施工图纸、设计规范、施工方案事项均包含在综合单价中。 | E17: m2 | F17: 4386.41 | G17: 27 | H17: =F17*G17 -> 118433.07 | I17: =南川一标段!$I$20 -> 44.4 | J17: =F17*I17 -> 194756.6 | K17: =G17-I17 -> -17.4 | L17: 按设计图示尺寸以面积计算（有吊顶房间算至吊顶底，无吊顶房间算至梁底或者板底） | M17: 此项工作的全费用综合单价 | R17: =O17+P17+Q17 -> 0 | S17: =R17*$S$4 -> 0
A18: 12 | B18: 防水面砖墙面 | C18: 1、同色水泥擦缝 2、8-10厚墙面砖(粘贴前墙砖充分浸湿) 3、8厚1:2水泥砂浆粘结层(内掺建筑胶) 4、缝宽、嵌缝材料：按甲方要求嵌缝、打胶； 5、酸洗、打蜡要求：满足设计和相关规范要求； 6、墙面伸缩缝、变形缝的处理； 7、根据安装需要开孔 8、其他：该项包含本项工作所有工作内容含垂直运输机械等，未详尽列举特征，详见施工图纸、设计规范、施工方案事项均包含在综合单价中。 (600×300墙砖) | D18: 1.内墙基层处理； 2.水泥砂浆粘结层，内掺建筑胶； 3.墙面面砖运输、制作、铺贴、擦缝 4.材料的运输、堆码、清运及场内多次搬运； 5.综合单价包含切角、倒角、磨边、加厚、弧形加工、嵌缝、拉槽、排版损耗、晶面处理等费用，送样的材料费用、检验、试验等工作费用，还包括地砖铺贴前排版图设计工作; 6.配合安装队伍进行多次预留预埋及相关开槽、开洞的修补工作； 7.对已施工完成的成品及其他专业已完成的成品进行保护工作，无论是否由该单位导致的损坏，该单位都应履行修复处理责任； 8.对施工需要拆除或移动的材料，待施工完毕后，恢复原状； 9.完成工作区域的安全文明施工,清理施工遗留下的垃圾。 10.该项包含本项工作所有工作内容含垂直运输机械等，未详尽列举特征，详见施工图纸、设计规范、施工方案事项均包含在综合单价中。 | E18: m2 | F18: 958.65 | G18: 120 | H18: =F18*G18 -> 115038 | I18: =南川一标段!$I$21 -> 153.02 | J18: =F18*I18 -> 146692.62 | K18: =G18-I18 -> -33.02 | L18: 按设计图示尺寸以面积计算（有吊顶房间算至吊顶底） | M18: 全费用综合单价 | R18: =O18+P18+Q18 -> 0 | S18: =R18*$S$4 -> 0
A19: 13 | B19: 耐擦洗涂料墙面 | C19: 1、防火型无机耐擦洗涂料两道饰面(白色) 2、满刮2厚耐水腻子找平 3、其他：该项包含本项工作所有工作内容含垂直运输机械等，未详尽列举特征，详见施工图纸、设计规范、施工方案事项均包含在综合单价中。 | D19: 1.内墙基层处理； 2.外加剂专用砂浆打底刮糙或专用界面剂一道甩毛； 3.石灰膏砂浆分层抹平； 4.满刮腻子两遍，找平磨光； 5.防火型无机耐擦洗涂料两道饰面； 6.材料的运输、堆码、清运及场内多次搬运； 7.单价已包括送样的材料费用、检验、试验等工作; 8.配合安装队伍进行多次预留预埋及相关开槽、开洞的修补工作； 9.对已施工完成的成品及其他专业已完成的成品进行保护工作，无论是否由该单位导致的损坏，该单位都应履行修复处理责任； 10.对施工需要拆除或移动的材料，待施工完毕后，恢复原状； 11.完成工作区域的安全文明施工,清理施工遗留下的垃圾。 12.该项包含本项工作所有工作内容含垂直运输机械等，未详尽列举特征，详见施工图纸、设计规范、施工方案事项均包含在综合单价中。 | E19: m2 | F19: 342.79 | G19: 30 | H19: =F19*G19 -> 10283.7 | I19: =南川一标段!$I$100 -> 44.4 | J19: =F19*I19 -> 15219.88 | K19: =G19-I19 -> -14.4 | L19: 按设计图示尺寸以面积计算（有吊顶房间算至吊顶底，无吊顶房间算至梁底或者板底） | M19: 此项工作的全费用综合单价 | R19: =O19+P19+Q19 -> 0 | S19: =R19*$S$4 -> 0
A20: 14 | B20: 白色仿铝板金属漆 | C20: 1、涂刷罩面清漆 2、涂饰第二遍面层涂料(透明) 3、涂饰面层涂料(透明) 4、喷主层涂料 5、辊、刷或喷底层涂料 10、其他：该项包含本项工作所有工作内容含垂直运输机械等，未详尽列举特征，详见施工图纸、设计规范、施工方案事项均包含在综合单价中。 | D20: 1.刷底层涂料、主层涂料、面层涂料； 2.涂刷罩面清漆； 3.材料的运输、堆码、清运及场内多次搬运； 4.单价已包括送样的材料费用、检验、试验等工作; 5.配合安装队伍进行多次预留预埋及相关开槽、开洞的修补工作； 6.对已施工完成的成品及其他专业已完成的成品进行保护工作，无论是否由该单位导致的损坏，该单位都应履行修复处理责任； 7.对施工需要拆除或移动的材料，待施工完毕后，恢复原状； 8.完成工作区域的安全文明施工,清理施工遗留下的垃圾。 9.该项包含本项工作所有工作内容含垂直运输机械等，未详尽列举特征，详见施工图纸、设计规范、施工方案事项均包含在综合单价中。 | E20: m2 | F20: 420.7 | G20: 85.06 | H20: =F20*G20 -> 35784.74 | I20: =S20 -> 117 | J20: =F20*I20 -> 49221.9 | K20: =G20-I20 -> -31.94 | L20: 按设计图示尺寸以面积计算。 | M20: 除甲供材外，此项工作的全费用综合单价 | O20: 65 | P20: 4.5 | Q20: 28 | R20: =O20+P20+Q20 -> 97.5 | S20: =R20*$S$4 -> 117
A21: 15 | B21: 铝合金扣板顶棚 | C21: 1、600*600*1.0铝合金扣板(折边20) 2、与铝合金扣板配套的专用暗架龙骨,间距≤300,通过十字连扣连接件与承载龙骨连接 3、D38承载龙骨,间距≤1200,用吊杆与钢筋吊杆联结后找平 4、10厚镀锌低碳钢丝(或%%C8钢筋)吊杆,双向中距≤1200,吊杆上部与板底(或钢结构)预留吊环(勾)固定 5、结构层预埋%%C10(或钢结构预留)钢筋吊环(勾),双向中距≤1200 6、顶棚伸缩缝、变形缝； 6、其他：该项包含本项工作所有工作内容含垂直运输机械等，未详尽列举特征，详见施工图纸、设计规范、施工方案事项均包含在综合单价中。 | D21: 1.基层处理 2.轻钢龙骨、吊杆安装； 3.铝扣板安装、收边线； 4.材料的运输、堆码、清运及场内多次搬运； 5.单价已包括送样的材料费用、检验、试验等工作; 6.配合安装队伍进行多次预留预埋及相关开槽、开洞的修补工作； 7.对已施工完成的成品及其他专业已完成的成品进行保护工作，无论是否由该单位导致的损坏，该单位都应履行修复处理责任； 8.对施工需要拆除或移动的材料，待施工完毕后，恢复原状； 9.完成工作区域的安全文明施工,清理施工遗留下的垃圾； 10.该项包含本项工作所有工作内容含垂直运输机械等，未详尽列举特征，详见施工图纸、设计规范、施工方案事项均包含在综合单价中。 | E21: m2 | F21: 262.6 | G21: 136.14 | H21: =F21*G21 -> 35750.36 | I21: =南川一标段!$I$29 -> 160.04 | J21: =F21*I21 -> 42026.5 | K21: =G21-I21 -> -23.9 | L21: 按设计图示尺寸以水平投影面积计算。 | M21: 除型钢龙骨外的全费用综合单价 | R21: =O21+P21+Q21 -> 0 | S21: =R21*$S$4 -> 0
A22: 16 | B22: 硅酸钙板面层吊顶 | C22: 1、喷(刷、辊)涂料面层两遍(每道间隔2小时) 2、封底漆一道(干燥后再做面层) 3、满刮2厚面层耐水腻子找平,板面接缝处贴嵌缝带,刮腻子抹平 4、错缝粘贴第二层9.5厚耐水耐火纸面石膏板 5、双层6mm厚硅酸钙板用自攻螺丝与龙骨固定,中距≤200,螺丝距板长边≥10,短边≥15 6、U型轻钢覆面横撑龙骨CB60x27,间距1200,用挂插件与次龙骨联结 7、U型轻钢覆面次龙骨CB60x27,间距400,用挂件与承接龙骨联结 8、U型轻钢承接龙骨CS50x15,间距≤1200,用吊杆与钢筋吊杆联结后找平 9、%%C8钢筋吊杆并加反支撑,双向中距≤1200,吊杆上部与预留钢筋吊环固定 10、现浇钢筋混凝土板底预埋%%C10钢筋吊环(勾),双向中距≤1200(转换层另列） 11.其他：该项包含本项工作所有工作内容含垂直运输机械等，未详尽列举特征，详见施工图纸、设计规范、施工方案事项均包含在综合单价中。 | D22: 1.基层处理； 2.龙骨、吊杆安装； 3.耐水耐火纸面石膏板安装、收边收口； 4.满刮腻子找平、贴嵌缝，刷底漆、面层涂料； 5.材料的运输、堆码、清运及场内多次搬运； 6.单价已包括送样的材料费用、检验、试验等工作; 7.配合安装队伍进行多次预留预埋及相关开槽、开洞的修补工作； 8.对已施工完成的成品及其他专业已完成的成品进行保护工作，无论是否由该单位导致的损坏，该单位都应履行修复处理责任； 9.对施工需要拆除或移动的材料，待施工完毕后，恢复原状； 10.完成工作区域的安全文明施工,清理施工遗留下的垃圾。 11.该项包含本项工作所有工作内容含垂直运输机械等，未详尽列举特征，详见施工图纸、设计规范、施工方案事项均包含在综合单价中。 | E22: m2 | F22: 9.71 | G22: 185.86 | H22: =F22*G22 -> 1804.7 | I22: =南川一标段!$I$30 -> 348 | J22: =F22*I22 -> 3379.08 | K22: =G22-I22 -> -162.14 | L22: 按设计图示尺寸以水平投影面积计算。 | M22: 除甲供材外，此项工作的全费用综合单价 | R22: =O22+P22+Q22 -> 0 | S22: =R22*$S$4 -> 0
A23: 17 | B23: 石膏面层板吊顶 | C23: 1、12厚石膏面层板面层,规格592x592 2、T型次龙骨TB24x30,间距600,与主龙骨插接 3、T型主龙骨TB24X30,间距600,通过D-T挂件与承载龙骨连接 4、D38承载龙骨,间距1200,用吊件与钢筋吊杆联结后找平 5、%%C8螺纹吊杆,双向中距≤1200,吊杆上部与吊顶转换层固定 7、50*5镀锌角钢吊顶转换层,井字型网格间距≤2400*1200(转换层另列） 8、顶棚伸缩缝、变形缝； 9、其他：该项包含本项工作所有工作内容含垂直运输机械等，未详尽列举特征，详见施工图纸、设计规范、施工方案事项均包含在综合单价中。 | D23: 1.基层处理； 2.主、次龙骨、角钢、吊杆安装； 3.纸面石膏板面层安装，收边收口； 4.材料的运输、堆码、清运及场内多次搬运； 5.单价已包括送样的材料费用、检验、试验等工作; 6.配合安装队伍进行多次预留预埋及相关开槽、开洞的修补工作； 7.对已施工完成的成品及其他专业已完成的成品进行保护工作，无论是否由该单位导致的损坏，该单位都应履行修复处理责任； 8.对施工需要拆除或移动的材料，待施工完毕后，恢复原状； 9.完成工作区域的安全文明施工,清理施工遗留下的垃圾； 10.该项包含本项工作所有工作内容含垂直运输机械等，未详尽列举特征，详见施工图纸、设计规范、施工方案事项均包含在综合单价中。 | E23: m2 | F23: 1071.2 | G23: 98.94 | H23: =F23*G23 -> 105984.53 | I23: =彭水二标段!$I$32 -> 108.6 | J23: =F23*I23 -> 116332.32 | K23: =G23-I23 -> -9.66 | L23: 按设计图示尺寸以水平投影面积计算。 | M23: 此项工作的全费用综合单价 | R23: =O23+P23+Q23 -> 0 | S23: =R23*$S$4 -> 0
A24: 18 | B24: 轻钢龙骨整体石膏板吊顶 | C24: 1、整体石膏板 2、配套龙骨及吊杆 3、其他：该项包含本项工作所有工作内容含垂直运输机械等，未详尽列举特征，详见施工图纸、设计规范、施工方案事项均包含在综合单价中。 | D24: 1.基层处理； 2.龙骨、吊杆安装； 3.石膏板面层安装，收边收口； 4.材料的运输、堆码、清运及场内多次搬运； 5.单价已包括送样的材料费用、检验、试验等工作; 6.配合安装队伍进行多次预留预埋及相关开槽、开洞的修补工作； 7.对已施工完成的成品及其他专业已完成的成品进行保护工作，无论是否由该单位导致的损坏，该单位都应履行修复处理责任； 8.对施工需要拆除或移动的材料，待施工完毕后，恢复原状； 9.完成工作区域的安全文明施工,清理施工遗留下的垃圾； 10.该项包含本项工作所有工作内容含垂直运输机械等，未详尽列举特征，详见施工图纸、设计规范、施工方案事项均包含在综合单价中。 | E24: m2 | F24: 34.55 | G24: 98.94 | H24: =F24*G24 -> 3418.38 | I24: =$I$23 -> 108.6 | J24: =F24*I24 -> 3752.13 | K24: =G24-I24 -> -9.66 | L24: 按设计图示尺寸以水平投影面积计算。 | M24: 此项工作的全费用综合单价 | R24: =O24+P24+Q24 -> 0 | S24: =R24*$S$4 -> 0
A25: 19 | B25: 无机涂料顶棚 | C25: 1、防火型无机耐擦洗涂料两道饰面(白色) 2、2厚面层耐水腻子刮平 3、顶棚伸缩缝、变形缝； 其他：该项包含本项工作所有工作内容含垂直运输机械等，未详尽列举特征，详见施工图纸、设计规范、施工方案事项均包含在综合单价中。 | D25: 1.基层处理、甩浆； 2.水泥砂浆打底找平； 2.满刮腻子找平、磨光； 4.防火型无机耐擦洗涂料两道饰面(； 5.材料的运输、堆码、清运及场内多次搬运； 6.单价已包括送样的材料费用、检验、试验等工作; 7.配合安装队伍进行多次预留预埋及相关开槽、开洞的修补工作； 8.对已施工完成的成品及其他专业已完成的成品进行保护工作，无论是否由该单位导致的损坏，该单位都应履行修复处理责任； 9.对施工需要拆除或移动的材料，待施工完毕后，恢复原状； 10.完成工作区域的安全文明施工,清理施工遗留下的垃圾。 11.该项包含本项工作所有工作内容含垂直运输机械等，未详尽列举特征，详见施工图纸、设计规范、施工方案事项均包含在综合单价中。 | E25: m2 | F25: 625.79 | G25: 32 | H25: =F25*G25 -> 20025.28 | I25: =南川一标段!$I$28 -> 44.4 | J25: =F25*I25 -> 27785.08 | K25: =G25-I25 -> -12.4 | L25: 按设计图示尺寸以水平投影面积计算。 | M25: 此项工作的全费用综合单价 | R25: =O25+P25+Q25 -> 0 | S25: =R25*$S$4 -> 0
A26: 20 | B26: 吸顶玻璃棉毡铝板网吸声吊顶 | C26: 1、1.5厚穿孔铝合金饰面板 2、50厚超细玻璃丝棉吸声层,玻璃丝布袋装填于龙骨间 3、T型轻钢横撑龙骨TB24X28,间距600,与主龙骨插接 4、T型轻钢主龙骨TB24X38,间距≤1200,用吸顶吊件联结 5、龙骨吸顶吊件,中距横向≤1200,纵向600,用膨胀螺栓与钢筋砼板固定 6、顶棚伸缩缝、变形缝； 其他：该项包含本项工作所有工作内容含垂直运输机械等，未详尽列举特征，详见施工图纸、设计规范、施工方案事项均包含在综合单价中。 | D26: 1.基层处理; 2.吊杆及预埋件焊接或后置紧固件连接； 3.龙骨安装； 4.填充50mm厚超细玻璃丝棉吸声层； 5.穿孔铝合金饰面板安装； 6.材料的运输、堆码、清运及场内多次搬运； 7.单价已包括送样的材料费用、检验、试验等工作; 8.配合安装队伍进行多次预留预埋及相关开槽、开洞的修补工作； 9.对已施工完成的成品及其他专业已完成的成品进行保护工作，无论是否由该单位导致的损坏，该单位都应履行修复处理责任； 10.对施工需要拆除或移动的材料，待施工完毕后，恢复原状； 11.完成工作区域的安全文明施工,清理施工遗留下的垃圾； 12.该项包含本项工作所有工作内容含垂直运输机械等，未详尽列举特征，详见施工图纸、设计规范、施工方案事项均包含在综合单价中。 | E26: m2 | F26: 144.68 | G26: 121.02 | H26: =F26*G26 -> 17509.17 | I26: =S26 -> 201.6 | J26: =F26*I26 -> 29167.49 | K26: =G26-I26 -> -80.58 | L26: 按设计图示尺寸以水平投影面积计算。 | M26: 除甲供材外，此项工作的全费用综合单价 | N26: 甲供材料：1.5厚穿孔铝合金饰面板 | O26: 0 | P26: =16+22 -> 38 | Q26: 130 | R26: =O26+P26+Q26 -> 168 | S26: =R26*$S$4 -> 201.6
A27: 21 | B27: 吊顶转换层--网架转换层 | C27: 网架转换层龙骨 | D27: 1.镀锌型钢龙骨转换层、骨架的制作、运输、安装、刷漆 2.该项包含本项工作所有工作内容含垂直运输机械等，未详尽列举特征，详见施工图纸、设计规范、施工方案事项均包含在综合单价中。 | E27: t | F27: 37.51 | G27: 8726.4 | H27: =F27*G27 -> 327327.26 | I27: =南川一标段!$I$47 -> 10536 | J27: =F27*I27 -> 395205.36 | K27: =G27-I27 -> -1809.6 | L27: 按设计图示尺寸以实际安装根数以重量计算 | M27: 此项工作的全费用综合单价 | R27: =O27+P27+Q27 -> 0 | S27: =R27*$S$4 -> 0
A28: 22 | B28: 镀锌方管转换层 | C28: 主次龙骨50*50*5镀锌方管、埋板等 | D28: 1.镀锌型钢龙骨转换层、骨架的制作、运输、安装、刷漆 2.该项包含本项工作所有工作内容含垂直运输机械等，未详尽列举特征，详见施工图纸、设计规范、施工方案事项均包含在综合单价中。 | E28: t | F28: 55.317 | G28: 8726.4 | H28: =F28*G28 -> 482718.27 | I28: =南川一标段!$I$47 -> 10536 | J28: =F28*I28 -> 582819.91 | K28: =G28-I28 -> -1809.6 | L28: 按设计图示尺寸以实际安装根数以重量计算 | M28: 此项工作的全费用综合单价 | R28: =O28+P28+Q28 -> 0 | S28: =R28*$S$4 -> 0
A29: 23 | B29: 干挂型钢龙骨 | C29: 1、石材、铝板墙面龙骨、埋板等； 2、骨架种类、规格：具体规格、尺寸、连接方式详见图纸； | D29: 1.镀锌型钢龙骨转换层、骨架的制作、运输、安装、刷漆 2.该项包含本项工作所有工作内容含垂直运输机械等，未详尽列举特征，详见施工图纸、设计规范、施工方案事项均包含在综合单价中。 | E29: t | F29: 96.34 | G29: 8726.4 | H29: =F29*G29 -> 840701.38 | I29: =南川一标段!$I$48 -> 10536 | J29: =F29*I29 -> 1015038.2 | K29: =G29-I29 -> -1809.6 | L29: 按设计图示尺寸以实际安装根数以重量计算 | M29: 此项工作的全费用综合单价 | R29: =O29+P29+Q29 -> 0 | S29: =R29*$S$4 -> 0
A30: 24 | B30: 洗漱台 | C30: 1、部位：具体详设计图纸要求； 2、石材规格：综合详见图纸； 3、2.5mm铝单板挡板 4、台面、挡水 5、其它：满足设计规范及图纸要求。 | D30: 1.洗漱台面层石材制作、运输、铺贴 2.铝板安装、收边收口 3.材料的运输、摆放、清运及场内多次搬运； 4.对已施工完成的成品及其他专业已完成的成品进行保护工作，无论是否由该单位导致的损坏，该单位都应履行修复处理责任； 5.对施工需要拆除或移动的材料，待施工完毕后，恢复原状； 6.完成工作区域的安全文明施工,清理施工遗留下的垃圾； 7、该项包含本项工作所有工作内容含垂直运输机械等，未详尽列举特征，详见施工图纸、设计规范、施工方案事项均包含在综合单价中。 | E30: m | F30: 27.93 | G30: 420.78 | H30: =F30*G30 -> 11752.39 | I30: =南川一标段!$I$35 -> 639.9 | J30: =F30*I30 -> 17872.41 | K30: =G30-I30 -> -219.12 | L30: 按设计图示尺寸以米计算 | M30: 除基层龙骨外，此项工作的全费用综合单价 | R30: =O30+P30+Q30 -> 0 | S30: =R30*$S$4 -> 0
A31: 25 | B31: 镜面玻璃 | C31: 1.30*30mm方管龙骨（刷防火、防腐） 2.6mm厚双层硅酸钙板基层（涂刷防腐） 3.5mm厚银镜及安装。 4.顶部及底部LED贴片灯带、灯槽制作安装 5.不锈钢边框包边；6.完成该项工作所需的全部工作内容 | D31: [工作内容] 1.基层安装 2.玻璃及框制作、运输、安装 3.该项包含本项工作所有工作内容含垂直运输机械等，未详尽列举特征，详见施工图纸、设计规范、施工方案事项均包含在综合单价中。 | E31: m2 | F31: 36.31 | G31: 220 | H31: =F31*G31 -> 7988.2 | I31: =南川一标段!$I$36 -> 526.8 | J31: =F31*I31 -> 19128.11 | K31: =G31-I31 -> -306.8 | L31: 按设计图示尺寸以面积计算 | M31: 除基层龙骨外，此项工作的全费用综合单价 | R31: =O31+P31+Q31 -> 0 | S31: =R31*$S$4 -> 0
A32: 26 | B32: 蹲位隔断 | C32: 1.50*4不锈钢角码固定隔板，膨胀螺丝与墙面固定 2.20mm厚金属复合板制作安装，含不锈钢挂衣钩固定安装； 3.复合板面不锈钢把手、不锈钢锁（红绿）隔门不锈钢合页安装； 4.隔板交接处50*4不锈钢角码纵向安装，专用平头螺丝固定，隔板与地面交接位置装100mm高不锈钢踢脚，防水胶嵌缝，2mm厚不锈钢U形抵扣封边； 5.未尽部分详见图纸； 6.完成该项工作所需的全部工作内容，完成工作区域的安全文明施工,清理施工遗留下的垃圾。 | D32: [工作内容] 1.隔断运输、安装 2.嵌缝、塞口 3.该项包含本项工作所有工作内容含垂直运输机械等，未详尽列举特征，详见施工图纸、设计规范、施工方案事项均包含在综合单价中。 | E32: 间 | F32: 28 | G32: 1250 | H32: =F32*G32 -> 35000 | I32: =南川一标段!$I$37 -> 3490.32 | J32: =F32*I32 -> 97728.96 | K32: =G32-I32 -> -2240.32 | L32: 按设计图示尺寸以数量计算 | M32: 此项工作的全费用综合单价 | N32: 市场不含税成本单价385元一平米，平均每个蹲位7.46㎡，见后附图计算方式 | R32: =O32+P32+Q32 -> 0 | S32: =R32*$S$4 -> 0 | T32: =_xlfn.DISPIMG("ID_4623C4A5D8DD4C8C87355E0655E9876F",1) -> =DISPIMG("ID_4623C4A5D8DD4C8C87355E0655E9876F",1)
A33: 27 | B33: 小便斗隔板 | C33: 1.50*4不锈钢角码固定隔板，膨胀螺丝与墙面固定 2.20mm厚金属复合板制作安装 3.完成该项工作所需的全部工作内容，完成工作区域的安全文明施工,清理施工遗留下的垃圾。 | D33: [工作内容] 1.隔断运输、安装 2.嵌缝、塞口 3.该项包含本项工作所有工作内容含垂直运输机械等，未详尽列举特征，详见施工图纸、设计规范、施工方案事项均包含在综合单价中。 | E33: 间 | F33: 8 | G33: 184.36 | H33: =F33*G33 -> 1474.88 | I33: =南川一标段!$I$38 -> 254.09 | J33: =F33*I33 -> 2032.72 | K33: =G33-I33 -> -69.73 | L33: 按设计图示尺寸以数量计算 | M33: 此项工作的全费用综合单价 | R33: =O33+P33+Q33 -> 0 | S33: =R33*$S$4 -> 0
A34: 28 | B34: 母婴设施 | C34: 成品母婴设备安装，完成该项工作所需的全部工作内容，完成工作区域的安全文明施工,清理施工遗留下的垃圾。 | D34: [工作内容] 1.台面及支架运输、安装 2.杆、环、盒、配件安装 3.刷油漆 | E34: 副 | F34: 1 | G34: 16920 | H34: =ROUND(F34*G34,2) -> 16920 | I34: =南川一标段!$I$51 -> 20304 | J34: =F34*I34 -> 20304 | K34: =G34-I34 -> -3384 | L34: 按设计图示个数以套计算 | M34: 此项工作的全费用综合单价 | R34: =O34+P34+Q34 -> 0 | S34: =R34*$S$4 -> 0
A35: 29 | B35: 卫生纸盒 | C35: 1、成品304#不锈钢嵌入纸巾盒；2、完成该项工作所需的全部工作内容，完成工作区域的安全文明施工,清理施工遗留下的垃圾。 | D35: [工作内容] 1.台面及支架制作、运输、安装 2.杆、环、盒、螺栓等配件安装 3.刷油漆 4.该项包含本项工作所有工作内容含垂直运输机械等，未详尽列举特征，详见施工图纸、设计规范、施工方案事项均包含在综合单价中。 | E35: 个 | F35: 28 | G35: 12.6 | H35: =F35*G35 -> 352.8 | I35: =南川一标段!$I$39 -> 72.6 | J35: =F35*I35 -> 2032.8 | K35: =G35-I35 -> -60 | L35: 按设计图示尺寸以数量计算 | M35: 此项工作的全费用综合单价 | R35: =O35+P35+Q35 -> 0 | S35: =R35*$S$4 -> 0
A36: 30 | B36: 烘手器 | C36: 1、成品烘手器安装；2.完成该项工作所需的全部工作内容，完成工作区域的安全文明施工,清理施工遗留下的垃圾。 | D36: [工作内容] 1.台面及支架制作、运输、安装 2.杆、环、盒、配件安装 3.刷油漆 4.该项包含本项工作所有工作内容含垂直运输机械等，未详尽列举特征，详见施工图纸、设计规范、施工方案事项均包含在综合单价中。 | E36: 副 | F36: 9 | G36: 265 | H36: =F36*G36 -> 2385 | I36: =南川一标段!$I$40 -> 369 | J36: =F36*I36 -> 3321 | K36: =G36-I36 -> -104 | L36: 按设计图示尺寸以数量计算 | M36: 此项工作的全费用综合单价 | R36: =O36+P36+Q36 -> 0 | S36: =R36*$S$4 -> 0
A37: 31 | B37: 小便池石材台面 | C37: 1.30*30*3镀锌方管龙骨（刷防火、防腐） 2.人造石台面及侧台面安装，接缝处防水处理；3.完成该项工作所需的全部工作内容，完成工作区域的安全文明施工,清理施工遗留下的垃圾。 | D37: [工作内容] 1.基层清理 2.抹找平层 3.窗台板制作、安装 4.该项包含本项工作所有工作内容含垂直运输机械等，未详尽列举特征，详见施工图纸、设计规范、施工方案事项均包含在综合单价中。 | E37: m2 | F37: 0.98 | G37: 517.56 | H37: =F37*G37 -> 507.21 | I37: =南川一标段!$I$41 -> 660 | J37: =F37*I37 -> 646.8 | K37: =G37-I37 -> -142.44 | L37: 按设计图示尺寸以数面积计算 | M37: 除基层龙骨外，此项工作的全费用综合单价 | R37: =O37+P37+Q37 -> 0 | S37: =R37*$S$4 -> 0
A38: 32 | B38: 1.1米高不锈钢栏杆 | C38: 1、立柱为70*40*5不锈钢方立管；2、扶手为63*3拉丝不锈钢钢管；3、水平向为38*1.5不锈钢复合管；4、竖向短管为30*1.5哑光不锈钢管；5、预埋螺栓；6、材料的水平及垂直转运（详参图纸） | D38: 1.预埋件制作、运输、埋设安装； 2.栏杆制作、运输、安装、防护； 3.综合单价含送样的材料费用、检验、试验等费用; 4.材料的运输、摆放、清运及场内多次搬运； 5.对已施工完成的成品及其他专业已完成的成品进行保护工作，无论是否由该单位导致的损坏，该单位都应履行修复处理责任； 6.对施工需要拆除或移动的材料，待施工完毕后，恢复原状； 7.完成工作区域的安全文明施工,清理施工遗留下的垃圾； 8.该项包含本项工作所有工作内容含垂直运输机械等，未详尽列举特征，详见施工图纸、设计规范、施工方案事项均包含在综合单价中。 | E38: m | F38: 44.42 | G38: 417.6 | H38: =F38*G38 -> 18549.79 | I38: =南川一标段!$I$109 -> 493.81 | J38: =F38*I38 -> 21935.04 | K38: =G38-I38 -> -76.21 | L38: 按设计图示尺寸以长度计算 | M38: 此项工作的全费用综合单价 | R38: =O38+P38+Q38 -> 0 | S38: =R38*$S$4 -> 0
A39: 33 | B39: 木色屏风（厚度100mm）2.5mm厚木色铝板包边 | C39: 定制100厚铝板包边木色屏风 | D39: [工作内容] 1.制作 2.运输 3.安装 4.刷防护材料 5.该项包含本项工作所有工作内容含垂直运输机械等，未详尽列举特征，详见施工图纸、设计规范、施工方案事项均包含在综合单价中。 | E39: m2 | F39: 33.97 | G39: 432 | H39: =F39*G39 -> 14675.04 | I39: =S39 -> 644.02 | J39: =F39*I39 -> 21877.36 | K39: =G39-I39 -> -212.02 | L39: 按设计图示尺寸以面积计算。 | M39: 此项工作的全费用综合单价 | O39: =主材表!L39 -> 371.68 | P39: 35 | Q39: 130 | R39: =O39+P39+Q39 -> 536.68 | S39: =R39*$S$4 -> 644.02 | T39: =_xlfn.DISPIMG("ID_DEAC0200EEB74B508027F909905D60B5",1) -> =DISPIMG("ID_DEAC0200EEB74B508027F909905D60B5",1)
A40: 34 | B40: 电缆沟盖板 | C40: 施工部位：变电所 6mm花纹钢板 | D40: [工作内容] 1.盖板制作、运输、安装 | E40: m2 | F40: 18 | G40: 300 | H40: =F40*G40 -> 5400 | I40: =南川一标段!$I$56 -> 346.13 | J40: =F40*I40 -> 6230.34 | K40: =G40-I40 -> -46.13 | L40: 按设计图纸尺寸以面积计算 | M40: 此项工作的全费用综合单价 | R40: =O40+P40+Q40 -> 0 | S40: =R40*$S$4 -> 0
A41: （二） | B41: 站房公共区 | H41: =F41*G41 -> 0 | K41: =G41-I41 -> 0
A42: 1 | B42: 花岗石地面 | C42: 1、铺25厚磨光花岗石板(六面涂刷石材保护剂),同色稀水泥浆擦 2、50厚1:3干硬性水泥粘结层,撒素水泥粉 3、水泥浆一道(内掺建筑胶) 4、嵌缝材料种类：按甲方要求嵌缝、打胶； 5、防护层材料：防护剂六面处理，满足设计和相关规范要求； 6、酸洗、打蜡要求：满足设计和相关规范要求； 7、楼地面伸缩缝、变形缝的处理； 8、其他：该项包含本项工作所有工作内容含垂直运输机械等，未详尽列举特征，详见施工图纸、设计规范、施工方案事项均包含在综合单价中。 (石材规格800*800) | D42: 1.清理基层，试排弹线，锯板磨边，调铺砂浆；铺板、灌缝擦缝、清理净面等全部操作过程； 2.找平层、结合层施工； 3.石材刷防护液、铺贴、水泥浆勾缝； 4.材料的运输、堆码、清运及场内多次搬运； 5.综合单价包含切角、倒角、磨边、加厚、弧形加工、嵌缝、拉槽、排版损耗、晶面处理等费用，送样的材料费用、检验、试验等工作费用，还包括地砖铺贴前排版图设计工作; 6.配合安装队伍进行多次预留预埋及相关开槽、开洞的修补工作； 7.对已施工完成的成品及其他专业已完成的成品进行保护工作，无论是否由该单位导致的损坏，该单位都应履行修复处理责任； 8.对施工需要拆除或移动的材料，待施工完毕后，恢复原状； 9.完成工作区域的安全文明施工,清理施工遗留下的垃圾； 10.该项包含本项工作所有工作内容含垂直运输机械等，未详尽列举特征，详见施工图纸、设计规范、施工方案事项均包含在综合单价中。 | E42: m2 | F42: 4025.78 | G42: 85 | H42: =F42*G42 -> 342191.3 | I42: =南川一标段!$I$7 -> 118.32 | J42: =F42*I42 -> 476330.29 | K42: =G42-I42 -> -33.32 | L42: 按设计图示尺寸以面积计算。 | M42: 除甲供材外，此项工作的全费用综合单价 | N42: 甲供材：石材 | R42: =O42+P42+Q42 -> 0 | S42: =R42*$S$4 -> 0
A43: 2 | B43: 防滑地砖地面(防水) | C43: 1、面层：10厚玻化砖(防滑),同色水泥浆擦缝 2、30厚1:3干硬性水泥砂浆,表面撒水泥粉 3、嵌缝材料种类：按甲方要求嵌缝、打胶； 4、防护层材料：满足设计和相关规范要求； 5、酸洗、打蜡要求：满足设计和相关规范要求； 6、楼地面伸缩缝、变形缝的处理； 7、其他：该项包含本项工作所有工作内容含垂直运输机械等，未详尽列举特征，详见施工图纸、设计规范、施工方案事项均包含在综合单价中。 (地砖规格600*600) | D43: 1.基层清理、找平、打磨、甩浆、弹线、定位； 2.结合层施工； 3.防滑地砖铺贴，干水泥擦缝； 4.材料的运输、堆码、清运及场内多次搬运； 5.单价已包括送样的材料费用、检验、试验等工作，还包括地砖铺贴前排版图设计工作; 6.配合安装队伍进行多次预留预埋及相关开槽、开洞的修补工作； 7.对已施工完成的成品及其他专业已完成的成品进行保护工作，无论是否由该单位导致的损坏，该单位都应履行修复处理责任； 8.对施工需要拆除或移动的材料，待施工完毕后，恢复原状； 9.完成工作区域的安全文明施工,清理施工遗留下的垃圾； 10.该项包含本项工作所有工作内容含垂直运输机械等，未详尽列举特征，详见施工图纸、设计规范、施工方案事项均包含在综合单价中。 | E43: m2 | F43: 46.22 | G43: 120 | H43: =F43*G43 -> 5546.4 | I43: =南川一标段!$I$10 -> 165.22 | J43: =F43*I43 -> 7636.47 | K43: =G43-I43 -> -45.22 | L43: 按设计图示尺寸以面积计算。 | M43: 此项工作的全费用综合单价 | R43: =O43+P43+Q43 -> 0 | S43: =R43*$S$4 -> 0
A44: 3 | B44: 花岗石梯面 | C44: 1、25厚花岗石(室外烧毛),同色水泥浆擦缝 2、50厚1:3干硬性水泥粘结层,撒素水泥粉 3、水泥浆一道(内掺建筑胶) 4、嵌缝材料种类：按甲方要求嵌缝、打胶，挡水条制作； 5、防护层材料：防护剂六面处理，满足设计和相关规范要求； 6、酸洗、打蜡要求：满足设计和相关规范要求； 7、楼地面伸缩缝、变形缝的处理； 8、其他：该项包含本项工作所有工作内容含垂直运输机械等，未详尽列举特征，详见施工图纸、设计规范、施工方案事项均包含在综合单价中。 | D44: 1.清理基层，试排弹线，锯板磨边，调铺砂浆；铺板、灌缝擦缝、清理净面等全部操作过程； 2.找平层、结合层施工； 3.石材刷防护液、铺贴、水泥浆勾缝，挡水条制作； 4.材料的运输、堆码、清运及场内多次搬运； 5.综合单价包含切角、倒角、磨边、加厚、弧形加工、嵌缝、拉槽、排版损耗、晶面处理等费用，送样的材料费用、检验、试验等工作费用，还包括地砖铺贴前排版图设计工作; 6.配合安装队伍进行多次预留预埋及相关开槽、开洞的修补工作； 7.对已施工完成的成品及其他专业已完成的成品进行保护工作，无论是否由该单位导致的损坏，该单位都应履行修复处理责任； 8.对施工需要拆除或移动的材料，待施工完毕后，恢复原状； 9.完成工作区域的安全文明施工,清理施工遗留下的垃圾； 10.该项包含本项工作所有工作内容含垂直运输机械等，未详尽列举特征，详见施工图纸、设计规范、施工方案事项均包含在综合单价中。 | E44: m2 | F44: 559.29 | G44: 110 | H44: =F44*G44 -> 61521.9 | I44: =南川一标段!$I$8 -> 160.32 | J44: =F44*I44 -> 89665.37 | K44: =G44-I44 -> -50.32 | L44: 按设计图示尺寸以展开面积计算。 | M44: 除甲供材外，此项工作的全费用综合单价 | R44: =O44+P44+Q44 -> 0 | S44: =R44*$S$4 -> 0
A45: 4 | B45: 25MM厚深灰麻过门石 | C45: 1、铺25厚磨光花岗石板(六面涂刷石材保护剂),同色稀水泥浆擦 2、50厚1:3干硬性水泥粘结层,撒素水泥粉 3、水泥浆一道(内掺建筑胶) 4、嵌缝材料种类：按甲方要求嵌缝、打胶； 5、防护层材料：防护剂六面处理，满足设计和相关规范要求； 6、酸洗、打蜡要求：满足设计和相关规范要求； 7、楼地面伸缩缝、变形缝的处理； 8、其他：该项包含本项工作所有工作内容含垂直运输机械等，未详尽列举特征，详见施工图纸、设计规范、施工方案事项均包含在综合单价中。 (石材规格800*800) | D45: [工作内容] 1.基层清理 2.抹找平层 3.面层铺设、切边、磨边 4.嵌缝 5.刷防护材料 6.酸洗、打蜡 7.材料运输 | E45: m2 | F45: 29.43 | G45: 80 | H45: =F45*G45 -> 2354.4 | I45: =南川一标段!$I$16 -> 156 | J45: =F45*I45 -> 4591.08 | K45: =G45-I45 -> -76 | L45: 按设计图示尺寸以面积计算。 | M45: 除甲供材外，此项工作的全费用综合单价 | N45: 甲供材：石材 | R45: =O45+P45+Q45 -> 0 | S45: =R45*$S$4 -> 0
A46: 5 | B46: 100高铝合金踢脚 | C46: 1、1.0厚不锈钢金属踢脚板,下端用水泥钉钉入地面垫层,中距300 2、10厚1:3水泥砂浆压实抹平 3、素水泥浆一道(内掺建筑胶)(用于混凝土空心砌块墙); 3厚外加剂专用砂浆抹基底刮糙(抹灰前用水喷湿墙面)(用于蒸 压加气混凝土砌块墙) 4、水泥钉固定踢脚上端,中距300 5、其他：该项包含本项工作所有工作内容含垂直运输机械等，未详尽列举特征，详见施工图纸、设计规范、施工方案事项均包含在综合单价中。 | D46: 1.墙体基层处理；刷水泥浆内掺建筑胶；水泥砂浆找平； 2.粘贴、固定不锈钢踢脚线； 3.材料的运输、堆码、清运及场内多次搬运； 4.单价已包括送样的材料费用、检验、试验等工作; 5.配合安装队伍进行多次预留预埋及相关开槽、开洞的修补工作； 6.对已施工完成的成品及其他专业已完成的成品进行保护工作，无论是否由该单位导致的损坏，该单位都应履行修复处理责任； 7.对施工需要拆除或移动的材料，待施工完毕后，恢复原状； 8.完成工作区域的安全文明施工,清理施工遗留下的垃圾； 9.该项包含本项工作所有工作内容含垂直运输机械等，未详尽列举特征，详见施工图纸、设计规范、施工方案事项均包含在综合单价中。 | E46: m2 | F46: 26.84 | G46: 272.98 | H46: =F46*G46 -> 7326.78 | I46: =南川一标段!$I$19 -> 519.74 | J46: =F46*I46 -> 13949.82 | K46: =G46-I46 -> -246.76 | L46: 以平方米计量，按设计图示长度乘高度以面积计算； | M46: 此项工作的全费用综合单价 | R46: =O46+P46+Q46 -> 0 | S46: =R46*$S$4 -> 0
A47: 6 | B47: 铝条板吊顶 （候车大厅） | C47: 1、铝合金条板与配套专用龙骨固定(宽150mm,缝80mm,厚1mm) 2、与铝合金方通配套的专用龙骨,间距≤1200,用吊件与钢筋吊杆连接后找平 3、10号镀锌低碳钢丝(或%%C6钢筋)吊杆,双向中距≤1200,吊杆上部与板底预留吊环(勾)固定 4、现浇钢筋混凝土板底预留%%C10钢筋吊环(勾),双向中距≤1200(吊杆长度超过1.5米后需要做反支撑,吊杆长度超过2.5米需做转换层,做法详见二次结构施工安装详图)(转换层另列） 5、顶棚伸缩缝、变形缝； 其他：该项包含本项工作所有工作内容含垂直运输机械等，未详尽列举特征，详见施工图纸、设计规范、施工方案事项均包含在综合单价中。 | D47: [工作内容] 1.基层清理 2.龙骨制作、运输、安装 3.钉隔离层 4.基层铺钉 5.面层铺贴 | E47: m2 | F47: 2266.57 | G47: 125 | H47: =F47*G47 -> 283321.25 | I47: =南川一标段!$I$31 -> 182.4 | J47: =F47*I47 -> 413422.37 | K47: =G47-I47 -> -57.4 | L47: 按设计图示尺寸以水平投影面积计算。 | M47: 除型钢龙骨及甲供材外，此项工作的全费用综合单价 | N47: 甲供材：铝条板 | R47: =O47+P47+Q47 -> 0 | S47: =R47*$S$4 -> 0
A48: 7 | B48: 铝条板吊顶 （候车大厅） | C48: 1、铝合金条板与配套专用龙骨固定(宽200mm,缝120mm,厚1mm) 2、与铝合金方通配套的专用龙骨,间距≤1200,用吊件与钢筋吊杆连接后找平 3、10号镀锌低碳钢丝(或%%C6钢筋)吊杆,双向中距≤1200,吊杆上部与板底预留吊环(勾)固定 4、现浇钢筋混凝土板底预留%%C10钢筋吊环(勾),双向中距≤1200(吊杆长度超过1.5米后需要做反支撑,吊杆长度超过2.5米需做转换层,做法详见二次结构施工安装详图)(转换层另列） 5、顶棚伸缩缝、变形缝； 其他：该项包含本项工作所有工作内容含垂直运输机械等，未详尽列举特征，详见施工图纸、设计规范、施工方案事项均包含在综合单价中。 | D48: [工作内容] 1.基层清理 2.龙骨制作、运输、安装 3.钉隔离层 4.基层铺钉 5.面层铺贴 | E48: m2 | F48: 1269.51 | G48: 125 | H48: =F48*G48 -> 158688.75 | I48: =南川一标段!$I$31 -> 182.4 | J48: =F48*I48 -> 231558.62 | K48: =G48-I48 -> -57.4 | L48: 按设计图示尺寸以水平投影面积计算。 | M48: 除型钢龙骨及甲供材外，此项工作的全费用综合单价 | N48: 甲供材：铝条板 | R48: =O48+P48+Q48 -> 0 | S48: =R48*$S$4 -> 0
A49: 8 | B49: 2.5mm白色铝单板 （候车大厅） | C49: 1、2.5厚铝合金单板与配套专用龙骨固定 2、与铝合金单板配套的专用下层副龙骨联结,间距≤600 3、与安装型式配套的专用上层主龙骨,间距≤1200,用吊件与钢筋吊杆联结后找平 4、10号镀锌低碳钢丝(或%%C8钢筋)吊杆,双向中距≤1200,吊杆上部与板底预留吊环固定 5、现浇钢筋混凝土板底预留%%C10钢筋吊环,双向中距≤1200 6、顶棚伸缩缝、变形缝； 其他：该项包含本项工作所有工作内容含垂直运输机械等，未详尽列举特征，详见施工图纸、设计规范、施工方案事项均包含在综合单价中。 | D49: 1.基层处理； 2.龙骨、吊杆安装； 4.铝合金条板面层安装； 5.材料的运输、堆码、清运及场内多次搬运； 6.单价已包括送样的材料费用、检验、试验等工作; 7.配合安装队伍进行多次预留预埋及相关开槽、开洞的修补工作； 8.对已施工完成的成品及其他专业已完成的成品进行保护工作，无论是否由该单位导致的损坏，该单位都应履行修复处理责任； 9.对施工需要拆除或移动的材料，待施工完毕后，恢复原状； 10.完成工作区域的安全文明施工,清理施工遗留下的垃圾。 11.该项包含本项工作所有工作内容含垂直运输机械等，未详尽列举特征，详见施工图纸、设计规范、施工方案事项均包含在综合单价中。 | E49: m2 | F49: 1273.32 | G49: 135 | H49: =F49*G49 -> 171898.2 | I49: =南川一标段!$I$31 -> 182.4 | J49: =F49*I49 -> 232253.57 | K49: =G49-I49 -> -47.4 | L49: 按设计图示尺寸以水平投影面积计算。 | M49: 除型钢龙骨及甲供材外，此项工作的全费用综合单价 | N49: 甲供材：铝单板 | R49: =O49+P49+Q49 -> 0 | S49: =R49*$S$4 -> 0
A50: 9 | B50: 双层6.0mm厚硅酸盖板吊顶 | C50: 1、喷(刷、辊)无机涂料(湿涂覆比<1.5Kg/㎡)面层两遍(每道间隔2小时) 2、封底漆一道(干燥后再做面层) 3、满刮2厚面层耐水腻子找平,板面接缝处贴嵌缝带,刮腻子抹平 4、错缝粘贴第二层9.5厚耐水耐火纸面石膏板 5、双层6.0MM厚硅酸钙板用自攻螺丝与龙骨固定,中距≤200,螺丝距板长边≥10,短边≥15 6、U型轻钢覆面横撑龙骨CB60x27,间距1200,用挂插件与次龙骨联结 7、U型轻钢覆面次龙骨CB60x27,间距400,用挂件与承接龙骨联结 8、U型轻钢承接龙骨CS50x15,间距≤1200,用吊杆与钢筋吊杆联结后找平 9、%%C8钢筋吊杆并加反支撑,双向中距≤1200,吊杆上部与预留钢筋吊环固定 10、现浇钢筋混凝土板底预埋%%C10钢筋吊环(勾),双向中距≤1200商务候车、商务候车服务间卫生间等 11、顶棚伸缩缝、变形缝； 其他：该项包含本项工作所有工作内容含垂直运输机械等，未详尽列举特征，详见施工图纸、设计规范、施工方案事项均包含在综合单价中。 | D50: 1.基层处理； 2.主、次龙骨、角钢、吊杆安装； 3.耐火纸面石膏板面层安装； 4.满刮防水腻子找平，封底漆施工； 5.涂料面层两遍； 6.材料的运输、堆码、清运及场内多次搬运； 7.单价已包括送样的材料费用、检验、试验等工作; 8.配合安装队伍进行多次预留预埋及相关开槽、开洞的修补工作； 9.对已施工完成的成品及其他专业已完成的成品进行保护工作，无论是否由该单位导致的损坏，该单位都应履行修复处理责任； 10.对施工需要拆除或移动的材料，待施工完毕后，恢复原状； 11.完成工作区域的安全文明施工,清理施工遗留下的垃圾； 12.该项包含本项工作所有工作内容含垂直运输机械等，未详尽列举特征，详见施工图纸、设计规范、施工方案事项均包含在综合单价中。 | E50: m2 | F50: 35.98 | G50: 185.86 | H50: =F50*G50 -> 6687.24 | I50: =南川一标段!$I$30 -> 348 | J50: =F50*I50 -> 12521.04 | K50: =G50-I50 -> -162.14 | L50: 按设计图示尺寸以水平投影面积计算。 | M50: 此项工作的全费用综合单价 | R50: =O50+P50+Q50 -> 0 | S50: =R50*$S$4 -> 0
A51: 10 | B51: 2.5mm木色铝单板灯带 | C51: 1、2.5厚木色铝合金单板与配套专用龙骨固定 2、与铝合金单板配套的专用下层副龙骨联结,间距≤600 3、与安装型式配套的专用上层主龙骨,间距≤1200,用吊件与钢筋吊杆联结后找平 4、10号镀锌低碳钢丝(或%%C8钢筋)吊杆,双向中距≤1200,吊杆上部与板底预留吊环固定 5、现浇钢筋混凝土板底预留%%C10钢筋吊环,双向中距≤1200 6、顶棚伸缩缝、变形缝； 其他：该项包含本项工作所有工作内容含垂直运输机械等，未详尽列举特征，详见施工图纸、设计规范、施工方案事项均包含在综合单价中。 | D51: 1.基层处理； 2.龙骨、吊杆安装； 4.铝合金条板面层安装； 5.材料的运输、堆码、清运及场内多次搬运； 6.单价已包括送样的材料费用、检验、试验等工作; 7.配合安装队伍进行多次预留预埋及相关开槽、开洞的修补工作； 8.对已施工完成的成品及其他专业已完成的成品进行保护工作，无论是否由该单位导致的损坏，该单位都应履行修复处理责任； 9.对施工需要拆除或移动的材料，待施工完毕后，恢复原状； 10.完成工作区域的安全文明施工,清理施工遗留下的垃圾。 11.该项包含本项工作所有工作内容含垂直运输机械等，未详尽列举特征，详见施工图纸、设计规范、施工方案事项均包含在综合单价中。 | E51: m2 | F51: 82.84 | G51: 125 | H51: =F51*G51 -> 10355 | I51: =南川一标段!$I$31 -> 182.4 | J51: =F51*I51 -> 15110.02 | K51: =G51-I51 -> -57.4 | L51: 按设计图示尺寸以水平投影面积计算。 | M51: 除型钢龙骨及甲供材外，此项工作的全费用综合单价 | N51: 甲供材：铝单板 | R51: =O51+P51+Q51 -> 0 | S51: =R51*$S$4 -> 0
A52: 11 | B52: 天棚喷刷深灰色涂料 | C52: 1、基层类型：砼天棚；2、深灰A级无机涂料喷涂，厚度、装饰效果满足设计要求3、超高增加的措施费用 | D52: [工作内容] 1.基层清理 2.刮腻子 3.刷、喷涂料 | E52: m2 | F52: 3143.65 | G52: 12.89 | H52: =F52*G52 -> 40521.65 | I52: =南川一标段!$I$34 -> 24.6 | J52: =F52*I52 -> 77333.79 | K52: =G52-I52 -> -11.71 | L52: 按设计图示尺寸以水平投影面积计算。 | M52: 此项工作的全费用综合单价 | R52: =O52+P52+Q52 -> 0 | S52: =R52*$S$4 -> 0
A53: 12 | B53: 干挂2.5mm白色铝板墙面（含消防暗门） | C53: 1、2.5mm厚铝合金饰面面层,接缝处密缝;(2米以下加肋,衬6mm厚硅酸钙板)。 2、金属板材用抽芯铆钉或自攻螺钉固定于铝方型材纵横方向龙骨上,板材带折边采用搭接式,带挂耳采用对接式; 3、60X40X4铝方型材龙骨,横向间距同金属板材宽度,纵向间距同金属板材长度,用螺栓与角钢连接。 4、8#槽钢竖向龙骨连接件螺栓连接, 5、连接件与预埋板焊接 6、预埋件 7、墙面伸缩缝、变形缝； 其他：该项包含本项工作所有工作内容含垂直运输机械等，未详尽列举特征，详见施工图纸、设计规范、施工方案事项均包含在综合单价中。 候车大厅、商务候车、出站厅等 | D53: 1.基层墙面处理； 2.龙骨、吊杆安装； 4.铝合金饰面面层安装； 5.材料的运输、堆码、清运及场内多次搬运； 6.单价已包括送样的材料费用、检验、试验等工作; 7.配合安装队伍进行多次预留预埋及相关开槽、开洞的修补工作； 8.对已施工完成的成品及其他专业已完成的成品进行保护工作，无论是否由该单位导致的损坏，该单位都应履行修复处理责任； 9.对施工需要拆除或移动的材料，待施工完毕后，恢复原状； 10.完成工作区域的安全文明施工,清理施工遗留下的垃圾。 11.该项包含本项工作所有工作内容含垂直运输机械等，未详尽列举特征，详见施工图纸、设计规范、施工方案事项均包含在综合单价中。 | E53: m2 | F53: 3950.86 | G53: 120 | H53: =F53*G53 -> 474103.2 | I53: =南川一标段!$I$22 -> 177 | J53: =F53*I53 -> 699302.22 | K53: =G53-I53 -> -57 | L53: 按设计图示尺寸以水平投影面积计算。 | M53: 除型钢龙骨及甲供材外，此项工作的全费用综合单价 | N53: 甲供材：铝单板 | R53: =O53+P53+Q53 -> 0 | S53: =R53*$S$4 -> 0
A54: 13 | B54: 干挂2.5mm灰色鱼骨纹造型铝板腐蚀墙面（含消防暗门） | C54: 1、2.5mm厚鱼骨纹造型铝板,接缝处密缝; 2、金属板材用抽芯铆钉或自攻螺钉固定于铝方型材纵横方向龙骨上,板材带折边采用搭接式,带挂耳采用对接式; 3、60X40X4铝方型材龙骨,横向间距同金属板材宽度,纵向间距同金属板材长度,用螺栓与角钢连接。 4、8#槽钢竖向龙骨连接件螺栓连接, 5、连接件与预埋板焊接 6、预埋件 7、顶棚伸缩缝、变形缝； 其他：该项包含本项工作所有工作内容含垂直运输机械等，未详尽列举特征，详见施工图纸、设计规范、施工方案事项均包含在综合单价中。 候车大厅、商务候车、出站厅等 | D54: 1.基层墙面处理； 2.龙骨、吊杆安装； 4.铝合金饰面面层安装； 5.材料的运输、堆码、清运及场内多次搬运； 6.单价已包括送样的材料费用、检验、试验等工作; 7.配合安装队伍进行多次预留预埋及相关开槽、开洞的修补工作； 8.对已施工完成的成品及其他专业已完成的成品进行保护工作，无论是否由该单位导致的损坏，该单位都应履行修复处理责任； 9.对施工需要拆除或移动的材料，待施工完毕后，恢复原状； 10.完成工作区域的安全文明施工,清理施工遗留下的垃圾。 11.该项包含本项工作所有工作内容含垂直运输机械等，未详尽列举特征，详见施工图纸、设计规范、施工方案事项均包含在综合单价中。 | E54: m2 | F54: 63.14 | G54: 120 | H54: =F54*G54 -> 7576.8 | I54: =南川一标段!$I$22 -> 177 | J54: =F54*I54 -> 11175.78 | K54: =G54-I54 -> -57 | L54: 按设计图示尺寸以水平投影面积计算。 | M54: 除型钢龙骨及甲供材外，此项工作的全费用综合单价 | N54: 甲供材：铝单板 | R54: =O54+P54+Q54 -> 0 | S54: =R54*$S$4 -> 0
A55: 14 | B55: 防水面砖墙面 | C55: 1、同色水泥擦缝 2、8-10厚墙面砖(粘贴前墙砖充分浸湿) 3、8厚1:2水泥砂浆粘结层(内掺建筑胶) 4、缝宽、嵌缝材料：按甲方要求嵌缝、打胶； 5、酸洗、打蜡要求：满足设计和相关规范要求； 6、墙面伸缩缝、变形缝的处理； 7、根据安装需要开孔 8、其他：该项包含本项工作所有工作内容含垂直运输机械等，未详尽列举特征，详见施工图纸、设计规范、施工方案事项均包含在综合单价中。 (600×300墙砖) | D55: 1.内墙基层处理； 2.水泥砂浆粘结层，内掺建筑胶； 3.墙面面砖运输、制作、铺贴、擦缝 4.材料的运输、堆码、清运及场内多次搬运； 5.综合单价包含切角、倒角、磨边、加厚、弧形加工、嵌缝、拉槽、排版损耗、晶面处理等费用，送样的材料费用、检验、试验等工作费用，还包括地砖铺贴前排版图设计工作; 6.配合安装队伍进行多次预留预埋及相关开槽、开洞的修补工作； 7.对已施工完成的成品及其他专业已完成的成品进行保护工作，无论是否由该单位导致的损坏，该单位都应履行修复处理责任； 8.对施工需要拆除或移动的材料，待施工完毕后，恢复原状； 9.完成工作区域的安全文明施工,清理施工遗留下的垃圾。 10.该项包含本项工作所有工作内容含垂直运输机械等，未详尽列举特征，详见施工图纸、设计规范、施工方案事项均包含在综合单价中。 | E55: m2 | F55: 82.22 | G55: 120 | H55: =F55*G55 -> 9866.4 | I55: =南川一标段!$I$21 -> 153.02 | J55: =F55*I55 -> 12581.3 | K55: =G55-I55 -> -33.02 | L55: 按设计图示尺寸以水平投影面积计算。 | M55: 此项工作的全费用综合单价 | R55: =O55+P55+Q55 -> 0 | S55: =R55*$S$4 -> 0
A56: 15 | B56: 防火玻璃隔断（旅客服务房间） | C56: 1、施工部位：旅客服务室外围隔断； 2、面层材料：8HS+1.52PVB+8HS（low-e）+12Ar+27mm全超白中空夹胶防火玻璃（A类，1小时防火），具体施工要求与细部分格等详见图纸及方案，包含通长支座、副框、扣盖、压板、压块、垫块、连接件等，不同规格的钢板等； 3、底部塞防火岩棉、外包1.5mm厚镀锌钢板； 4、底部及顶部采用通长钢U槽连接； 5、接缝、嵌缝及塞口材料：泡沫棒、结构密封胶、耐候密封胶、EPDM胶条、防火胶条等详图纸及方案要求； 6、所有保温防火封堵、不锈钢自攻钉、不锈钢销钉、不锈钢螺栓、断热条、防脱螺钉、硬质玻璃垫块、钢托板、φ12压力间隔套等其他所有辅材需满足图纸及方案要求，其施工费及材料费等均已含在综合单价中； 7、与其他装饰面收口打胶； | D56: 1、防火岩棉及镀锌钢板的制作、运输、安装；2、型材的制作、运输、安装；3、玻璃安装；4、嵌缝、塞口；5、清洗；6、施工区域的安全文明施工；7、该项包含本项工作所有工作内容，未详尽列举的图纸、方案事项均包含在综合单价中 | E56: m2 | F56: 153.68 | G56: 1429.33 | H56: =F56*G56 -> 219659.43 | I56: =南川一标段!$I$45 -> 1243.27 | J56: =F56*I56 -> 191065.73 | K56: =G56-I56 -> 186.06 | L56: 按设计图示尺寸以面积计算 | M56: 全费用综合单价 | R56: =O56+P56+Q56 -> 0 | S56: =R56*$S$4 -> 0
A57: 16 | B57: 木色屏风（厚度100mm）2.5mm厚木色铝板包边 | C57: 木色屏风（厚度100mm）2.5mm厚木色铝板包边 | D57: [工作内容] 1.边框制作、运输、安装 2.屏风制作、运输、安装 3.嵌缝、塞口 4.该项包含本项工作所有工作内容含垂直运输机械等，未详尽列举特征，详见施工图纸、设计规范、施工方案事项均包含在综合单价中。 | E57: m2 | F57: 33.97 | G57: 517.29 | H57: =F57*G57 -> 17572.34 | I57: =$I$39 -> 644.02 | J57: =F57*I57 -> 21877.36 | K57: =G57-I57 -> -126.73 | L57: 按设计图示尺寸以面积计算。 | M57: 此项工作的全费用综合单价 | R57: =O57+P57+Q57 -> 0 | S57: =R57*$S$4 -> 0
A58: 17 | B58: 2.2米高玻璃栏板 | C58: 1、2.2米高玻璃栏板 2、玻璃栏板不锈钢型材立柱125*55 3、玻璃栏板8+1.14PVB+8夹胶钢化玻璃 4、50*4防撞栏杆 5、其他：该项包含本项工作所有工作内容含垂直运输机械等，未详尽列举特征，详见施工图纸、设计规范、施工方案事项均包含在综合单价中。 | D58: 1.预埋件制作、运输、埋设安装； 2.玻璃栏板制作、运输、安装、防护，安装驳接爪； 3.综合单价含栏板送样的材料费用、检验、试验等费用; 4.材料的运输、摆放、清运及场内多次搬运； 5.对已施工完成的成品及其他专业已完成的成品进行保护工作，无论是否由该单位导致的损坏，该单位都应履行修复处理责任； 6.对施工需要拆除或移动的材料，待施工完毕后，恢复原状； 7.完成工作区域的安全文明施工,清理施工遗留下的垃圾； 4.该项包含本项工作所有工作内容含垂直运输机械等，未详尽列举特征，详见施工图纸、设计规范、施工方案事项均包含在综合单价中。 | E58: m | F58: 21.08 | G58: 1377.88 | H58: =F58*G58 -> 29045.71 | I58: =南川一标段!$I$43 -> 1879.54 | J58: =F58*I58 -> 39620.7 | K58: =G58-I58 -> -501.66 | L58: 按设计图示以扶手中心线长度计算。 | M58: 此项工作的全费用综合单价 | R58: =O58+P58+Q58 -> 0 | S58: =R58*$S$4 -> 0
A59: 18 | B59: 1.1米高玻璃栏板 | C59: 1、1.1米高玻璃栏板 2、玻璃栏板不锈钢方管立柱63*25*5mm拉丝不锈钢管 3、玻璃栏板扶手φ63*3mm异形拉丝不锈钢圆管 4、玻璃栏板防撞栏杆φ51*1.5不锈钢圆管 玻璃：8+1.14PVB+8钢化夹胶玻璃 5、其他：该项包含本项工作所有工作内容含垂直运输机械等，未详尽列举特征，详见施工图纸、设计规范、施工方案事项均包含在综合单价中。 | D59: 1.预埋件制作、运输、埋设安装； 2.玻璃栏板制作、运输、安装、防护，安装驳接爪； 3.综合单价含栏板送样的材料费用、检验、试验等费用; 4.材料的运输、摆放、清运及场内多次搬运； 5.对已施工完成的成品及其他专业已完成的成品进行保护工作，无论是否由该单位导致的损坏，该单位都应履行修复处理责任； 6.对施工需要拆除或移动的材料，待施工完毕后，恢复原状； 7.完成工作区域的安全文明施工,清理施工遗留下的垃圾； 4.该项包含本项工作所有工作内容含垂直运输机械等，未详尽列举特征，详见施工图纸、设计规范、施工方案事项均包含在综合单价中。 | E59: m | F59: 34.6 | G59: 692.73 | H59: =F59*G59 -> 23968.46 | I59: =南川一标段!$I$42 -> 986.77 | J59: =F59*I59 -> 34142.24 | K59: =G59-I59 -> -294.04 | L59: 按设计图示以扶手中心线长度计算。 | M59: 此项工作的全费用综合单价 | R59: =O59+P59+Q59 -> 0 | S59: =R59*$S$4 -> 0
A60: 19 | B60: 玻璃幕墙防撞杆 | C60: 1、玻璃幕墙防撞杆 2、H=250mm 3、其他：该项包含本项工作所有工作内容含垂直运输机械等，未详尽列举特征，详见施工图纸、设计规范、施工方案事项均包含在综合单价中。 | D60: [工作内容] 1.制作 2.运输 3.安装 4.刷防护材料 5.该项包含本项工作所有工作内容含垂直运输机械等，未详尽列举特征，详见施工图纸、设计规范、施工方案事项均包含在综合单价中。 | E60: m | F60: 83.05 | G60: 71.24 | H60: =F60*G60 -> 5916.48 | I60: =南川一标段!$I$44 -> 109.6 | J60: =F60*I60 -> 9102.28 | K60: =G60-I60 -> -38.36 | L60: 按设计图示以扶手中心线长度计算。 | M60: 此项工作的全费用综合单价 | R60: =O60+P60+Q60 -> 0 | S60: =R60*$S$4 -> 0
A61: 20 | B61: 服务台 | C61: [工作内容] 1.台柜制作、运输、安装(安放) 2.刷防护材料、油漆 3.五金件安装 | D61: [工作内容] 1.台面及支架运输、安装 2.杆、环、盒、配件安装 3.刷油漆 4.该项包含本项工作所有工作内容含垂直运输机械等，未详尽列举特征，详见施工图纸、设计规范、施工方案事项均包含在综合单价中。 | E61: m | F61: 17.6 | G61: 4522.11 | H61: =F61*G61 -> 79589.14 | I61: =南川一标段!$I$50 -> 2109 | J61: =F61*I61 -> 37118.4 | K61: =G61-I61 -> 2413.11 | L61: 按设计图示以中心线长度计算 | M61: 此项工作的全费用综合单价 | R61: =O61+P61+Q61 -> 0 | S61: =R61*$S$4 -> 0
A62: 21 | B62: 1.3米高玻璃栏板 | C62: 1、1.3米高玻璃栏板 2、玻璃栏板拉丝不锈钢矩管（渐变）80~63*40*4mm 3、玻璃栏板扶手φ63*3mm异形拉丝不锈钢圆管 4、玻璃栏板防撞栏杆φ51*3不锈钢圆管 5、玻璃栏板8+1.14PVB+8夹胶钢化玻璃 其他：该项包含本项工作所有工作内容含垂直运输机械等，未详尽列举特征，详见施工图纸、设计规范、施工方案事项均包含在综合单价中。 | D62: 1.预埋件制作、运输、埋设安装； 2.玻璃栏板制作、运输、安装、防护，安装驳接爪； 3.综合单价含栏板送样的材料费用、检验、试验等费用; 4.材料的运输、摆放、清运及场内多次搬运； 5.对已施工完成的成品及其他专业已完成的成品进行保护工作，无论是否由该单位导致的损坏，该单位都应履行修复处理责任； 6.对施工需要拆除或移动的材料，待施工完毕后，恢复原状； 7.完成工作区域的安全文明施工,清理施工遗留下的垃圾； 8.该项包含本项工作所有工作内容含垂直运输机械等，未详尽列举特征，详见施工图纸、设计规范、施工方案事项均包含在综合单价中。 | E62: m | F62: 310.32 | G62: 795.1 | H62: =F62*G62 -> 246735.43 | I62: =南川一标段!$I$85 -> 1085.53 | J62: =F62*I62 -> 336861.67 | K62: =G62-I62 -> -290.43 | L62: 按设计图示以扶手中心线长度计算。 | M62: 此项工作的全费用综合单价 | R62: =O62+P62+Q62 -> 0 | S62: =R62*$S$4 -> 0
A63: 22 | B63: 文化元素雕刻铝单板 | C63: 1、3mm厚铝合金饰面面层,接缝处密缝;(2米以下加肋,衬6mm厚硅酸钙板)。 2、金属板材用抽芯铆钉或自攻螺钉固定于铝方型材纵横方向龙骨上,板材带折边采用搭接式,带挂耳采用对接式; 3、60X40X4铝方型材龙骨,横向间距同金属板材宽度,纵向间距同金属板材长度,用螺栓与角钢连接。 4、8#槽钢竖向龙骨连接件螺栓连接, 5、连接件与预埋板焊接 6、预埋件 7、墙面伸缩缝、变形缝的处理； 完成该项工作所需的全部工作内容，完成工作区域的安全文明施工,清理施工遗留下的垃圾。 | D63: [工作内容] 1.基层清理 2.龙骨制作、运输、安装 3.钉隔离层 4.基层铺钉 5.面层铺贴 | E63: m2 | F63: 63.14 | G63: 456.83 | H63: =F63*G63 -> 28844.25 | I63: =S63 -> 1117.87 | J63: =F63*I63 -> 70582.31 | K63: =G63-I63 -> -661.04 | L63: 按设计图示框外围尺寸以面积计算。 | M63: 此项工作的全费用综合单价 | O63: =主材表!$L$40 -> 761.06 | P63: =35+5.5 -> 40.5 | Q63: 130 | R63: =O63+P63+Q63 -> 931.56 | S63: =R63*$S$4 -> 1117.87
A64: 23 | B64: 20mm 金属复合板(隔断) | C64: 1、50*4不锈钢角码固定隔板，膨胀螺丝与墙面固定 2、20mm厚金属复合板制作安装。3、完成该项工作所需的全部工作内容，完成工作区域的安全文明施工,清理施工遗留下的垃圾。 | D64: [工作内容] 1.隔断运输、安装 2.嵌缝、塞口 3.该项包含本项工作所有工作内容含垂直运输机械等，未详尽列举特征，详见施工图纸、设计规范、施工方案事项均包含在综合单价中。 | E64: m2 | F64: 12.81 | G64: 250.46 | H64: =F64*G64 -> 3208.39 | I64: =S64 -> 636 | J64: =F64*I64 -> 8147.16 | K64: =G64-I64 -> -385.54 | L64: 按设计图示尺寸以面积计算。 | M64: 此项工作的全费用综合单价 | N64: 市场不含税成本单价385元一平米 | O64: 385 | P64: 15 | Q64: 130 | R64: =O64+P64+Q64 -> 530 | S64: =R64*$S$4 -> 636
A65: 24 | B65: 排水沟盖板 | C65: 1、5mm厚钢板预埋 2、20mm厚橡胶胶垫 3、花岗石水篦子铺面 | D65: [工作内容] 1、预埋板制作、安装 2、胶垫安装嵌缝、塞口 3、石材水篦子面板安装 4、该项包含本项工作所有工作内容含垂直运输机械等，未详尽列举特征，详见施工图纸、设计规范、施工方案事项均包含在综合单价中。 | E65: m | F65: 150 | G65: 71 | H65: =F65*G65 -> 10650 | I65: =南川一标段!$I$58 -> 78 | J65: =F65*I65 -> 11700 | K65: =G65-I65 -> -7 | L65: 按设计图示尺寸以米计算。 | M65: 除甲供材外，此项工作的全费用综合单价 甲供材：花岗石 | R65: =O65+P65+Q65 -> 0 | S65: =R65*$S$4 -> 0
A66: 25 | B66: 风口百叶 | C66: （1）面板：铝合金百叶； （2）龙骨及连接件：详见施工方案及图纸要求； （3）密封胶：详见施工方案及图纸要求； （4）完成本项目的所需的材料及相应的工序(包括但不限于加工制作、储运、安装、嵌缝、塞口、清洗、试验检测等内容） （5）该项包含本项工作所有工作内容含垂直运输机械等，未详尽列举特征，详见施工图纸、设计规范、施工方案事项均包含在综合单价中。 | D66: （1）百叶窗安装、防虫网安装，百叶喷涂氟碳漆 （2）包含基层处理（打磨找补清理）、成品保护、负责工作区域的安全文明施工,施工遗留垃圾的清理及外运等； （3）含材料费管理费、措施费、夜间施工费、赶工措施费、安全文明施工费、规费、税金、临近既有线施工费用以及可能出现的人员窝工及机械停滞费用等施工所发生的一切费用 （4）其他未尽事宜详见招标文件技术要求及图纸 | E66: m2 | F66: 49.69 | G66: 367.83 | H66: =F66*G66 -> 18277.47 | I66: =南川一标段!$I$59 -> 510 | J66: =F66*I66 -> 25341.9 | K66: =G66-I66 -> -142.17 | L66: 按百叶窗的垂直投影面积进行计算 | M66: 全费用综合单价 | R66: =O66+P66+Q66 -> 0 | S66: =R66*$S$4 -> 0
A67: 26 | B67: 线性灯槽 | C67: LED灯带制作安装 | D67: [工作内容] 1、LED灯带制作、安装 2、工作内容，未详尽列举特征，详见施工图纸、设计规范、施工方案事项均包含在综合单价中。 | E67: m | F67: 311.64 | G67: 20 | H67: =F67*G67 -> 6232.8 | I67: =南川一标段!$I$55 -> 65.04 | J67: =F67*I67 -> 20269.07 | K67: =G67-I67 -> -45.04 | L67: 按设计图示尺寸以米计算。 | M67: 全费用综合单价 | R67: =O67+P67+Q67 -> 0 | S67: =R67*$S$4 -> 0
A68: 27 | B68: 软膜灯棚(白色) | C68: 软膜灯带安装 | D68: 1、基层清理，弹线定位。 2、基层龙骨，基层板安装 3、安装透光灯膜 | E68: m2 | F68: 15.67 | G68: 220 | H68: =F68*G68 -> 3447.4 | I68: =南川一标段!$I$53 -> 360 | J68: =F68*I68 -> 5641.2 | K68: =G68-I68 -> -140 | L68: 按设计图示尺寸以水平投影面积计算。 | M68: 此项工作的全费用综合单价 | R68: =O68+P68+Q68 -> 0 | S68: =R68*$S$4 -> 0
A69: （三） | B69: 站台雨棚 | H69: =F69*G69 -> 0 | K69: =G69-I69 -> 0
A70: 1 | B70: 混凝土冲劲带 | C70: 1、站台外侧混凝土冲劲带浇筑； 2、冲劲带宽度200mm，高度110mm,具体详见图纸； 3、地面伸缩缝、变形缝的处理； 其它：垂直运输费用已包含在综合单价中，满足设计规范及图纸要求;未详尽列举特征，详见施工图纸、设计规范、施工方案 | D70: 1.清理基层清理净面等全部操作过程； 2.混凝土浇筑施工、养护、搓平，平整顺直； 3.材料的运输、堆码、清运及场内多次搬运； 4.综合单价包含送样的材料费用、检验、试验等工作费用，还包括地砖铺贴前排版图设计工作; 5.配合安装队伍进行多次预留预埋及相关开槽、开洞的修补工作； 6.对已施工完成的成品及其他专业已完成的成品进行保护工作，无论是否由该单位导致的损坏，该单位都应履行修复处理责任； 7.对施工需要拆除或移动的材料，待施工完毕后，恢复原状； 8.完成工作区域的安全文明施工,清理施工遗留下的垃圾； 9.该项包含本项工作所有工作内容含垂直运输机械等，未详尽列举特征，详见施工图纸、设计规范、施工方案事项均包含在综合单价中。 | E70: m | F70: =450*2 -> 900 | G70: 20 | H70: =F70*G70 -> 18000 | I70: =南川一标段!$I$88 -> 71.88 | J70: =F70*I70 -> 64692 | K70: =G70-I70 -> -51.88 | L70: 按设计图示尺寸以延长米计算。 | M70: 除甲供材外，此项工作的全费用综合单价 甲供材：混凝土 | R70: =O70+P70+Q70 -> 0 | S70: =R70*$S$4 -> 0
A71: 2 | B71: 站台面石材铺装-路基段 | C71: 1、30mm厚白麻花岗石 2、5mm坐浆层 3、3、30厚1:3干硬性水泥砂浆粘结层 4、地面伸缩缝、变形缝的处理； 其它：垂直运输费用已包含在综合单价中，满足设计规范及图纸要求;未详尽列举特征，详见施工图纸、设计规范、施工方案 | D71: 1.清理基层，试排弹线，锯板磨边，调铺砂浆；铺板、灌缝擦缝、清理净面等全部操作过程； 2.找平层、结合层、坐浆层施工； 3.红色花岗岩(磨光机刨6面满涂防护剂)； 4.材料的运输、堆码、清运及场内多次搬运； 5.综合单价包含切角、倒角、磨边、加厚、弧形加工、嵌缝、拉槽、排版损耗、晶面处理等费用，送样的材料费用、检验、试验等工作费用，还包括地砖铺贴前排版图设计工作; 6.配合安装队伍进行多次预留预埋及相关开槽、开洞的修补工作； 7.对已施工完成的成品及其他专业已完成的成品进行保护工作，无论是否由该单位导致的损坏，该单位都应履行修复处理责任； 8.对施工需要拆除或移动的材料，待施工完毕后，恢复原状； 9.完成工作区域的安全文明施工,清理施工遗留下的垃圾； 10.该项包含本项工作所有工作内容含垂直运输机械等，未详尽列举特征，详见施工图纸、设计规范、施工方案事项均包含在综合单价中。 | E71: m2 | F71: 5630.13 | G71: 80 | H71: =F71*G71 -> 450410.4 | I71: =南川一标段!$I$98 -> 118.32 | J71: =F71*I71 -> 666156.98 | K71: =G71-I71 -> -38.32 | L71: 按设计图示尺寸以面积计算。 | M71: 除甲供材外，此项工作的全费用综合单价 甲供材：石材 | N71: 同站房单价 | R71: =O71+P71+Q71 -> 0 | S71: =R71*$S$4 -> 0
A72: 3 | B72: 站台面石材铺装-桥基段 | C72: 1、30mm厚红色花岗岩安全石 2、5mm坐浆层 3、30厚1:3干硬性水泥砂浆粘结层 4、地面伸缩缝、变形缝的处理； 其它：垂直运输费用已包含在综合单价中，满足设计规范及图纸要求;未详尽列举特征，详见施工图纸、设计规范、施工方案 | D72: 1.清理基层，试排弹线，锯板磨边，调铺砂浆；铺板、灌缝擦缝、清理净面等全部操作过程； 2.找平层、结合层、坐浆层施工； 3.红色花岗岩(磨光机刨6面满涂防护剂)； 4.材料的运输、堆码、清运及场内多次搬运； 5.综合单价包含切角、倒角、磨边、加厚、弧形加工、嵌缝、拉槽、排版损耗、晶面处理等费用，送样的材料费用、检验、试验等工作费用，还包括地砖铺贴前排版图设计工作; 6.配合安装队伍进行多次预留预埋及相关开槽、开洞的修补工作； 7.对已施工完成的成品及其他专业已完成的成品进行保护工作，无论是否由该单位导致的损坏，该单位都应履行修复处理责任； 8.对施工需要拆除或移动的材料，待施工完毕后，恢复原状； 9.完成工作区域的安全文明施工,清理施工遗留下的垃圾； 10.该项包含本项工作所有工作内容含垂直运输机械等，未详尽列举特征，详见施工图纸、设计规范、施工方案事项均包含在综合单价中。 | E72: m2 | F72: 5630.13 | G72: 80 | H72: =F72*G72 -> 450410.4 | I72: =南川一标段!$I$98 -> 118.32 | J72: =F72*I72 -> 666156.98 | K72: =G72-I72 -> -38.32 | L72: 按设计图示尺寸以面积计算。 | M72: 除甲供材外，此项工作的全费用综合单价 甲供材：石材 | N72: 同站房单价 | R72: =O72+P72+Q72 -> 0 | S72: =R72*$S$4 -> 0
A73: 4 | B73: 站台面石材铺装-楼梯上站台处 | C73: 1、50mm厚红色花岗岩安全石 2、5mm坐浆层 3、30厚1:3干硬性水泥砂浆粘结层 4、地面伸缩缝、变形缝的处理； 其它：垂直运输费用已包含在综合单价中，满足设计规范及图纸要求;未详尽列举特征，详见施工图纸、设计规范、施工方案 | D73: 1.清理基层，试排弹线，锯板磨边，调铺砂浆；铺板、灌缝擦缝、清理净面等全部操作过程； 2.找平层、结合层、坐浆层施工； 3.红色花岗岩(磨光机刨6面满涂防护剂)； 4.材料的运输、堆码、清运及场内多次搬运； 5.综合单价包含切角、倒角、磨边、加厚、弧形加工、嵌缝、拉槽、排版损耗、晶面处理等费用，送样的材料费用、检验、试验等工作费用，还包括地砖铺贴前排版图设计工作; 6.配合安装队伍进行多次预留预埋及相关开槽、开洞的修补工作； 7.对已施工完成的成品及其他专业已完成的成品进行保护工作，无论是否由该单位导致的损坏，该单位都应履行修复处理责任； 8.对施工需要拆除或移动的材料，待施工完毕后，恢复原状； 9.完成工作区域的安全文明施工,清理施工遗留下的垃圾； 10.该项包含本项工作所有工作内容含垂直运输机械等，未详尽列举特征，详见施工图纸、设计规范、施工方案事项均包含在综合单价中。 | E73: m2 | F73: 356.75 | G73: 80 | H73: =F73*G73 -> 28540 | I73: =南川一标段!$I$98 -> 118.32 | J73: =F73*I73 -> 42210.66 | K73: =G73-I73 -> -38.32 | L73: 按设计图示尺寸以面积计算。 | M73: 除甲供材外，此项工作的全费用综合单价 甲供材：石材 | N73: 同站房单价 | R73: =O73+P73+Q73 -> 0 | S73: =R73*$S$4 -> 0
A74: 5 | B74: 站台帽石铺装-50厚红色花岗石 | C74: 1、50厚红色花岗岩(磨光机刨6面满涂防护剂) 2、5厚坐浆层 3、30厚1:3干硬性水泥砂浆粘结层 4、地面伸缩缝、变形缝的处理； 其它：垂直运输费用已包含在综合单价中，满足设计规范及图纸要求;未详尽列举特征，详见施工图纸、设计规范、施工方案 | D74: 1.清理基层，试排弹线，锯板磨边，调铺砂浆；铺板、灌缝擦缝、清理净面等全部操作过程； 2.找平层、结合层、坐浆层施工； 3.红色花岗岩(磨光机刨6面满涂防护剂)； 4.材料的运输、堆码、清运及场内多次搬运； 5.综合单价包含切角、倒角、磨边、加厚、弧形加工、嵌缝、拉槽、排版损耗、晶面处理等费用，送样的材料费用、检验、试验等工作费用，还包括地砖铺贴前排版图设计工作; 6.配合安装队伍进行多次预留预埋及相关开槽、开洞的修补工作； 7.对已施工完成的成品及其他专业已完成的成品进行保护工作，无论是否由该单位导致的损坏，该单位都应履行修复处理责任； 8.对施工需要拆除或移动的材料，待施工完毕后，恢复原状； 9.完成工作区域的安全文明施工,清理施工遗留下的垃圾； 10.该项包含本项工作所有工作内容含垂直运输机械等，未详尽列举特征，详见施工图纸、设计规范、施工方案事项均包含在综合单价中。 | E74: m2 | F74: 900 | G74: 80 | H74: =F74*G74 -> 72000 | I74: =南川一标段!$I$98 -> 118.32 | J74: =F74*I74 -> 106488 | K74: =G74-I74 -> -38.32 | L74: 按设计图示尺寸以面积计算。 | M74: 除甲供材外，此项工作的全费用综合单价 甲供材：石材 | N74: 同站房单价 | R74: =O74+P74+Q74 -> 0 | S74: =R74*$S$4 -> 0
A75: 6 | B75: 站台白色安全线铺装-15厚白色玻化砖 | C75: 1、玻化砖安全线盲道砖面层; 2、5厚坐浆层; 3、45厚1:3干硬性水泥砂浆粘结层; 4、地面伸缩缝、变形缝的处理； 其它：垂直运输费用已包含在综合单价中，满足设计规范及图纸要求;未详尽列举特征，详见施工图纸、设计规范、施工方案 | D75: 1.清理基层，试排弹线，锯板磨边，调铺砂浆；铺板、灌缝擦缝、清理净面等全部操作过程； 2.找平层、结合层、坐浆层施工； 3.玻化砖安全线盲道砖铺贴、水泥浆勾缝； 4.材料的运输、堆码、清运及场内多次搬运； 5.综合单价包含切角、倒角、磨边、加厚、弧形加工、嵌缝、拉槽、排版损耗、晶面处理等费用，送样的材料费用、检验、试验等工作费用，还包括地砖铺贴前排版图设计工作; 6.配合安装队伍进行多次预留预埋及相关开槽、开洞的修补工作； 7.对已施工完成的成品及其他专业已完成的成品进行保护工作，无论是否由该单位导致的损坏，该单位都应履行修复处理责任； 8.对施工需要拆除或移动的材料，待施工完毕后，恢复原状； 9.完成工作区域的安全文明施工,清理施工遗留下的垃圾； 10.该项包含本项工作所有工作内容含垂直运输机械等，未详尽列举特征，详见施工图纸、设计规范、施工方案事项均包含在综合单价中。 | E75: m2 | F75: 90 | G75: 80 | H75: =F75*G75 -> 7200 | I75: =南川一标段!$I$95 -> 96 | J75: =F75*I75 -> 8640 | K75: =G75-I75 -> -16 | L75: 按设计图示尺寸以面积计算。 | M75: 除甲供材外，此项工作的全费用综合单价 甲供材：盲道砖 | N75: 同站房单价 | R75: =O75+P75+Q75 -> 0 | S75: =R75*$S$4 -> 0
A76: 7 | B76: 站台盲道铺装-20厚黄色盲道砖 | C76: 1、玻化砖安全线盲道砖面层; 2、5厚坐浆层; 3、45厚1:3干硬性水泥砂浆粘结层; 4、地面伸缩缝、变形缝的处理； 其它：垂直运输费用已包含在综合单价中，满足设计规范及图纸要求;未详尽列举特征，详见施工图纸、设计规范、施工方案 | D76: 1.清理基层，试排弹线，锯板磨边，调铺砂浆；铺板、灌缝擦缝、清理净面等全部操作过程； 2.找平层、结合层、坐浆层施工； 3.盲道砖铺贴、水泥浆勾缝； 4.材料的运输、堆码、清运及场内多次搬运； 5.综合单价包含切角、倒角、磨边、加厚、弧形加工、嵌缝、拉槽、排版损耗、晶面处理等费用，送样的材料费用、检验、试验等工作费用，还包括地砖铺贴前排版图设计工作; 6.配合安装队伍进行多次预留预埋及相关开槽、开洞的修补工作； 7.对已施工完成的成品及其他专业已完成的成品进行保护工作，无论是否由该单位导致的损坏，该单位都应履行修复处理责任； 8.对施工需要拆除或移动的材料，待施工完毕后，恢复原状； 9.完成工作区域的安全文明施工,清理施工遗留下的垃圾； 10.该项包含本项工作所有工作内容含垂直运输机械等，未详尽列举特征，详见施工图纸、设计规范、施工方案事项均包含在综合单价中。 | E76: m2 | F76: 540 | G76: 80 | H76: =F76*G76 -> 43200 | I76: =南川一标段!$I$95 -> 96 | J76: =F76*I76 -> 51840 | K76: =G76-I76 -> -16 | L76: 按设计图示尺寸以面积计算。 | M76: 除甲供材外，此项工作的全费用综合单价 甲供材：盲道砖 | N76: 同站房单价 | R76: =O76+P76+Q76 -> 0 | S76: =R76*$S$4 -> 0
A77: 8 | B77: 灰色氟碳漆踢脚 | C77: 1、清理基面:清理钢筋混凝土基面 2、基层处理:专用腻子找平、修复,厚度不大于5mm 3、灰色涂料底漆涂装:涂刷一遍 4、灰色涂料中涂涂装:涂刷一遍 5、面漆涂装:涂刷两遍 6、其它：垂直运输费用已包含在综合单价中，满足设计规范及图纸要求;未详尽列举特征，详见施工图纸、设计规范、施工方案 | D77: 1.墙体基层处理、找平抹灰、压实； 2.踢脚线制作、运输、安装，面砖背面涂专用粘接剂，用专用勾缝剂勾缝； 3.材料的运输、堆码、清运及场内多次搬运； 4.单价已包括送样的材料费用、检验、试验等工作; 5.配合安装队伍进行多次预留预埋及相关开槽、开洞的修补工作； 6.对已施工完成的成品及其他专业已完成的成品进行保护工作，无论是否由该单位导致的损坏，该单位都应履行修复处理责任； 7.对施工需要拆除或移动的材料，待施工完毕后，恢复原状； 8.完成工作区域的安全文明施工,清理施工遗留下的垃圾； 9.该项包含本项工作所有工作内容含垂直运输机械等，未详尽列举特征，详见施工图纸、设计规范、施工方案事项均包含在综合单价中。 | E77: m2 | F77: =45*3*0.15*2 -> 40.5 | G77: 23.5 | H77: =F77*G77 -> 951.75 | I77: =南川一标段!$I$99 -> 251.4 | J77: =F77*I77 -> 10181.7 | K77: =G77-I77 -> -227.9 | L77: 以平方米计量，按设计图示长度乘高度以面积计算； | M77: 此项工作的全费用综合单价 | R77: =O77+P77+Q77 -> 0 | S77: =R77*$S$4 -> 0
A78: 9 | B78: 金属格栅门 | C78: 金属格栅门制作安装 其它：垂直运输费用已包含在综合单价中，满足设计规范及图纸要求;未详尽列举特征，详见施工图纸、设计规范、施工方案 | D78: [工作内容] 1.门安装 2.启动装置、五金配件安装 | E78: m2 | F78: 13.2 | G78: 453.13 | H78: =F78*G78 -> 5981.32 | I78: =S78 -> 1108.51 | J78: =F78*I78 -> 14632.33 | K78: =G78-I78 -> -655.38 | L78: 按设计图示尺寸以面积计算。 | M78: 此项工作的全费用综合单价 | O78: =主材表!$L$41 -> 778.76 | P78: 15 | Q78: 130 | R78: =O78+P78+Q78 -> 923.76 | S78: =R78*$S$4 -> 1108.51
A79: 10 | B79: 铝单板门套 | C79: 1、部位：综合考虑，有门、无门部位均按此项计算 2、墙体类型：砼、砖墙综合考虑； 3、骨架种类、规格：型材，规格详见设计图纸，间距应满足施工要求并由投标人综合考虑； 4、面层材料种类、规格：不锈钢； 5、嵌缝、打胶； 6、具体要求详设计图纸 7、根据安装需要开孔 8、其它：垂直运输费用已包含在综合单价中，满足设计规范及图纸要求;未详尽列举特征，详见施工图纸、设计规范、施工方案 | D79: 1、后置件、骨架的制作、运输、安装；2、铝板下料，安装；3、嵌缝、打胶；4、该项包含不锈钢门套线的所有工作内容，含垂直运输机械等，未详尽列举特征，详见施工图纸、设计规范、施工方案事项均包含在综合单价中。 | E79: m2 | F79: 77.6 | G79: 105.79 | H79: =F79*G79 -> 8209.3 | I79: =南川一标段!$I$46 -> 226.2 | J79: =F79*I79 -> 17553.12 | K79: =G79-I79 -> -120.41 | L79: 按设计图示尺寸以室外可视铝板面积进行计算 | M79: 除基层龙骨及甲供材外，此项工作的全费用综合单价 甲供材：铝板 | N79: 同站房单价 | R79: =O79+P79+Q79 -> 0 | S79: =R79*$S$4 -> 0
A80: 11 | B80: 栏杆基础 | C80: 站台栏杆基础200*200 4C8主筋，箍筋C8-200，预埋件预埋 | D80: 1、钢筋绑扎、模板及支撑制作、安装、拆除、堆放、运输及清理模内杂物、刷隔离剂等； 2、混凝土制作、运输、浇筑、振捣、养护； 3、栏杆预埋件预埋 4、合同中明示或暗示的其他工作内容 | E80: m | F80: =F81+F82 -> 897.72 | G80: =O80*50+(P80+Q80)*0.9+0.4*1*50 -> 20 | H80: =F80*G80 -> 17954.4 | I80: =南川一标段!$I$107 -> 67.8 | J80: =F80*I80 -> 60865.42 | K80: =G80-I80 -> -47.8 | L80: 按设计图示尺寸以长度计算 | M80: 1、除甲供材外全费用综合单价； 2、甲供材：钢筋、模板、混凝土 | R80: =O80+P80+Q80 -> 0 | S80: =R80*$S$4 -> 0
A81: 12 | B81: 2.2米高不锈钢栏杆 | C81: 1、立柱为76*3.5拉丝不锈钢钢管；2、扶手为76*2拉丝不锈钢钢管；3、水平向为50*30*2不锈钢复合管；4、竖向短管为25*1.5不锈钢复合管；5、预埋螺栓；6、材料的水平及垂直转运（详参图纸）7、其它：垂直运输费用已包含在综合单价中，满足设计规范及图纸要求;未详尽列举特征，详见施工图纸、设计规范、施工方案 | D81: 1.预埋件制作、运输、埋设安装； 2.栏杆制作、运输、安装、防护； 3.综合单价含送样的材料费用、检验、试验等费用; 4.材料的运输、摆放、清运及场内多次搬运； 5.对已施工完成的成品及其他专业已完成的成品进行保护工作，无论是否由该单位导致的损坏，该单位都应履行修复处理责任； 6.对施工需要拆除或移动的材料，待施工完毕后，恢复原状； 7.完成工作区域的安全文明施工,清理施工遗留下的垃圾； 8.该项包含本项工作所有工作内容含垂直运输机械等，未详尽列举特征，详见施工图纸、设计规范、施工方案事项均包含在综合单价中。 | E81: m | F81: 858.21 | G81: 714.61 | H81: =F81*G81 -> 613285.45 | I81: =S81 -> 756.37 | J81: =F81*I81 -> 649124.3 | K81: =G81-I81 -> -41.76 | L81: 按设计图示以扶手中心线长度计算。 | M81: 此项工作的全费用综合单价 | O81: =主材表!$L$42 -> 516.81 | P81: 3.5 | Q81: 110 | R81: =O81+P81+Q81 -> 630.31 | S81: =R81*$S$4 -> 756.37
A82: 13 | B82: 1.1米高不锈钢栏杆 | C82: 1、立柱为70*40*5不锈钢方立管；2、扶手为63*3拉丝不锈钢钢管；3、水平向为38*1.5不锈钢复合管；4、竖向短管为30*1.5哑光不锈钢管；5、预埋螺栓；6、材料的水平及垂直转运（详参图纸）7其它：垂直运输费用已包含在综合单价中，满足设计规范及图纸要求;未详尽列举特征，详见施工图纸、设计规范、施工方案 | D82: 1.预埋件制作、运输、埋设安装； 2.栏杆制作、运输、安装、防护； 3.综合单价含送样的材料费用、检验、试验等费用; 4.材料的运输、摆放、清运及场内多次搬运； 5.对已施工完成的成品及其他专业已完成的成品进行保护工作，无论是否由该单位导致的损坏，该单位都应履行修复处理责任； 6.对施工需要拆除或移动的材料，待施工完毕后，恢复原状； 7.完成工作区域的安全文明施工,清理施工遗留下的垃圾； 8.该项包含本项工作所有工作内容含垂直运输机械等，未详尽列举特征，详见施工图纸、设计规范、施工方案事项均包含在综合单价中。 | E82: m | F82: 39.51 | G82: 423.09 | H82: =F82*G82 -> 16716.29 | I82: =南川一标段!$I$109 -> 493.81 | J82: =F82*I82 -> 19510.43 | K82: =G82-I82 -> -70.72 | L82: 按设计图示以扶手中心线长度计算。 | M82: 此项工作的全费用综合单价 | R82: =O82+P82+Q82 -> 0 | S82: =R82*$S$4 -> 0
A83: 14 | B83: 沉砂井盖板 | C83: 规格型号：900*600盖板 1、花岗石水篦子铺面，提手50*20矩形洞口，不锈钢包边 2、30厚1：3干硬性水泥砂浆 3、60mm厚C25钢筋混凝土盖板 4、其它：垂直运输费用已包含在综合单价中，满足设计规范及图纸要求;未详尽列举特征，详见施工图纸、设计规范、施工方案 | D83: [工作内容] 1、盖板板制作、安装 2、盖板安装嵌缝、塞口 3、石材水篦子面板不锈钢包边处理、安装 4、该项包含本项工作所有工作内容含垂直运输机械等，未详尽列举特征，详见施工图纸、设计规范、施工方案事项均包含在综合单价中。 | E83: 个 | F83: 90 | G83: 340 | H83: =F83*G83 -> 30600 | I83: =南川一标段!$I$110 -> 358.86 | J83: =F83*I83 -> 32297.4 | K83: =G83-I83 -> -18.86 | L83: 按设计图示数量以个计算。 | M83: 除甲供材外，此项工作的全费用综合单价 甲供材：花岗石 | R83: =O83+P83+Q83 -> 0 | S83: =R83*$S$4 -> 0
A84: 15 | B84: 地面沉降缝 | C84: 1、桥面沉降伸缩缝,宽度约360mm 1.嵌缝材料种类:非收缩嵌缝胶2.止水带材料种类:详图纸及设计说明；3.盖缝材料:同地面饰面4.连接件:铝合金基座、配件5.其它:详见设计图纸及招标文件6.部位:楼地面 | D84: 1.建筑岩棉铺底、止水带安装； 2.机械螺丝、抗震弹簧安装、铝合金支座安装； 3.成品沉降缝铝合金配件安装、侧架安装，成品胶条封堵; 4.与石材交接部位采用填缝剂封堵； 5.对已施工完成的成品及其他专业已完成的成品进行保护工作，无论是否由该单位导致的损坏，该单位都应履行修复处理责任； 6.对施工需要拆除或移动的材料，待施工完毕后，恢复原状； 7.完成工作区域的安全文明施工,清理施工遗留下的垃圾； 8.该项包含本项工作所有工作内容含垂直运输机械等，未详尽列举特征，详见施工图纸、设计规范、施工方案事项均包含在综合单价中。 | E84: m | F84: =450/6*2 -> 150 | G84: 130 | H84: =F84*G84 -> 19500 | I84: =彭水二标段!$I$72 -> 204.6 | J84: =F84*I84 -> 30690 | K84: =G84-I84 -> -74.6 | L84: 按设计图示尺寸以长度计算 | M84: 除甲供材外，此项工作的全费用综合单价 甲供材：花岗石面层 | R84: =O84+P84+Q84 -> 0 | S84: =R84*$S$4 -> 0 | T84: =_xlfn.DISPIMG("ID_4AFB36732161415B924144DC60C14344",1) -> =DISPIMG("ID_4AFB36732161415B924144DC60C14344",1)
A85: 16 | B85: 站台端部检修爬梯 | C85: 带护笼钢爬梯，做法参考15J401（D19-C3,D18-B1,D18-B3,WT2B-6.4)，护笼做法参考15J401-D15-AC 其它：垂直运输费用已包含在综合单价中，满足设计规范及图纸要求;未详尽列举特征，详见施工图纸、设计规范、施工方案 | D85: 1、钢爬梯预埋件200*300*10制作、安装，刷防腐防锈涂料； 2、护笼安装 3、钢爬梯安装 4、该项包含本项工作所有工作内容所有工作内容含垂直运输机械等，未详尽列举特征，详见施工图纸、设计规范、施工方案事项均包含在综合单价中。 | E85: t | F85: 4 | G85: 8726.4 | H85: =ROUND(F85*G85,2) -> 34905.6 | I85: =南川一标段!$I$111 -> 10536 | J85: =F85*I85 -> 42144 | K85: =G85-I85 -> -1809.6 | L85: 按设计图示尺寸乘以理论质量计算，不扣除单个≤0.3m2的孔洞，焊条、铆钉、螺栓等不另增加质量 | M85: 全费用综合单价 | R85: =O85+P85+Q85 -> 0 | S85: =R85*$S$4 -> 0
A86: 17 | B86: 防坠落系统 | C86: 1、预埋200*200*10厚钢板，表面刷防腐防锈涂料，下埋12钢筋植入混凝土； 2、防坠落钢拉索基座制安，直径10，间距3m布置，纵向穿直径10不锈钢拉索，顶部与基座环形钢筋焊接； 3、防坠落措施制作通常30*3圆钢管，间距6m 4、其它：垂直运输费用已包含在综合单价中，满足设计规范及图纸要求;未详尽列举特征，详见施工图纸、设计规范、施工方案 | D86: 1.预埋件制作、运输、埋设安装； 2.防坠落基座及拉绳制作、运输、安装、防护； 3.综合单价含送样的材料费用、检验、试验等费用; 4.材料的运输、摆放、清运及场内多次搬运； 5.对已施工完成的成品及其他专业已完成的成品进行保护工作，无论是否由该单位导致的损坏，该单位都应履行修复处理责任； 6.对施工需要拆除或移动的材料，待施工完毕后，恢复原状； 7.完成工作区域的安全文明施工,清理施工遗留下的垃圾； 8.该项包含本项工作所有工作内容含垂直运输机械等，未详尽列举特征，详见施工图纸、设计规范、施工方案事项均包含在综合单价中。 | E86: m | F86: 900 | G86: 93 | H86: =F86*G86 -> 83700 | I86: =南川一标段!$I$112 -> 360.13 | J86: =F86*I86 -> 324117 | K86: =G86-I86 -> -267.13 | L86: 按设计图示以长度计算 | M86: 此项工作的全费用综合单价 | R86: =O86+P86+Q86 -> 0 | S86: =R86*$S$4 -> 0
A87: （四） | B87: 室外铺装 | H87: =F87*G87 -> 0 | K87: =G87-I87 -> 0
A88: 1 | B88: 铺1 烧毛花岗岩铺面 | C88: 1、50mm水洗火烧面(磨光度30度)(750mm×750mm) 2、50mm厚1:3干硬性水泥砂浆结合层 3、150厚C20混凝土,按4~6m分仓跳格浇筑 4、200厚3:7灰土垫层或级配砂石 5、素土夯实,压实系数≥0.94 | D88: 1.清理基层，试排弹线，锯板磨边，调铺砂浆；铺板、灌缝擦缝、清理净面等全部操作过程； 2.找平层、结合层施工； 3.石材刷防护液、铺贴、水泥浆勾缝； 4.材料的运输、堆码、清运及场内多次搬运； 5.综合单价包含切角、倒角、磨边、加厚、弧形加工、嵌缝、拉槽、排版损耗、晶面处理等费用，送样的材料费用、检验、试验等工作费用，还包括地砖铺贴前排版图设计工作; 6.配合安装队伍进行多次预留预埋及相关开槽、开洞的修补工作； 7.对已施工完成的成品及其他专业已完成的成品进行保护工作，无论是否由该单位导致的损坏，该单位都应履行修复处理责任； 8.对施工需要拆除或移动的材料，待施工完毕后，恢复原状； 9.完成工作区域的安全文明施工,清理施工遗留下的垃圾； 10.该项包含本项工作所有工作内容，未详尽列举特征，详见施工图纸、设计规范、施工方案事项均包含在综合单价中。 | E88: m2 | F88: 5458.68 | G88: 80 | H88: =F88*G88 -> 436694.4 | I88: =南川一标段!$I$114 -> 118.32 | J88: =F88*I88 -> 645871.02 | K88: =G88-I88 -> -38.32 | L88: 按设计图示尺寸以面积计算。 | M88: 除甲供材外，此项工作的全费用综合单价 甲供材：石材、混凝土、级配砂石 | N88: 同站房单价 | R88: =O88+P88+Q88 -> 0 | S88: =R88*$S$4 -> 0
A89: 2 | B89: 铺1 烧毛花岗岩铺面-排水沟篦子 | C89: 1、50mm水洗火烧面(磨光度30度)(750mm×750mm)-排水沟篦子 2、350mm厚1:3干硬性水泥砂浆结合层 3、150厚C20混凝土,按4~6m分仓跳格浇筑 4、200厚3:7灰土垫层或级配砂石 5、素土夯实,压实系数≥0.94 | D89: 1.清理基层，试排弹线，锯板磨边，调铺砂浆；铺板、灌缝擦缝、清理净面等全部操作过程； 2.找平层、结合层施工； 3.石材刷防护液、铺贴、水泥浆勾缝； 4.材料的运输、堆码、清运及场内多次搬运； 5.综合单价包含切角、倒角、磨边、加厚、弧形加工、嵌缝、拉槽、排版损耗、晶面处理等费用，送样的材料费用、检验、试验等工作费用，还包括地砖铺贴前排版图设计工作; 6.配合安装队伍进行多次预留预埋及相关开槽、开洞的修补工作； 7.对已施工完成的成品及其他专业已完成的成品进行保护工作，无论是否由该单位导致的损坏，该单位都应履行修复处理责任； 8.对施工需要拆除或移动的材料，待施工完毕后，恢复原状； 9.完成工作区域的安全文明施工,清理施工遗留下的垃圾； 10.该项包含本项工作所有工作内容，未详尽列举特征，详见施工图纸、设计规范、施工方案事项均包含在综合单价中。 | E89: m2 | F89: 280.93 | G89: 80 | H89: =F89*G89 -> 22474.4 | I89: =南川一标段!$I$114 -> 118.32 | J89: =F89*I89 -> 33239.64 | K89: =G89-I89 -> -38.32 | L89: 按设计图示尺寸以面积计算。 | M89: 除甲供材外，此项工作的全费用综合单价 甲供材：石材、混凝土、级配砂石 | N89: 同站房单价 | R89: =O89+P89+Q89 -> 0 | S89: =R89*$S$4 -> 0
A90: 3 | B90: 烧毛花岗岩铺面 | C90: 1、50mm水洗火烧面(磨光度30度)(750mm×750mm) 2、50mm厚1:3干硬性水泥砂浆结合层 3、150厚C20混凝土,按4~6m分仓跳格浇筑 4、200厚3:7灰土垫层或级配砂石 5、素土夯实 | D90: 1.清理基层，试排弹线，锯板磨边，调铺砂浆；铺板、灌缝擦缝、清理净面等全部操作过程； 2.找平层、结合层施工； 3.石材刷防护液、铺贴、水泥浆勾缝； 4.材料的运输、堆码、清运及场内多次搬运； 5.综合单价包含切角、倒角、磨边、加厚、弧形加工、嵌缝、拉槽、排版损耗、晶面处理等费用，送样的材料费用、检验、试验等工作费用，还包括地砖铺贴前排版图设计工作; 6.配合安装队伍进行多次预留预埋及相关开槽、开洞的修补工作； 7.对已施工完成的成品及其他专业已完成的成品进行保护工作，无论是否由该单位导致的损坏，该单位都应履行修复处理责任； 8.对施工需要拆除或移动的材料，待施工完毕后，恢复原状； 9.完成工作区域的安全文明施工,清理施工遗留下的垃圾； 10.该项包含本项工作所有工作内容，未详尽列举特征，详见施工图纸、设计规范、施工方案事项均包含在综合单价中。 | E90: m2 | F90: 333.21 | G90: 80 | H90: =F90*G90 -> 26656.8 | I90: =南川一标段!$I$114 -> 118.32 | J90: =F90*I90 -> 39425.41 | K90: =G90-I90 -> -38.32 | L90: 按设计图示尺寸以面积计算。 | M90: 除甲供材外，此项工作的全费用综合单价 甲供材：石材、混凝土、级配砂石 | N90: 同站房单价 | R90: =O90+P90+Q90 -> 0 | S90: =R90*$S$4 -> 0
A91: 4 | B91: 混凝土道路 | C91: 1.180厚C25混凝土硬化面,内配10钢筋@150单层双向 2.300厚3:7灰土分两步夯实 3.素土夯实,压实度≥0.94（单列） | D91: [工作内容] 1.模板制作、安装、拆除 2.混凝土拌和、运输、浇筑 3.拉毛 4.压痕或刻防滑槽 5.伸缝 6.缩缝 7.锯缝、嵌缝 8.路面养护 | E91: m2 | F91: 480.19 | G91: 15 | H91: =F91*G91 -> 7202.85 | I91: =S91 -> 67.8 | J91: =F91*I91 -> 32556.88 | K91: =G91-I91 -> -52.8 | L91: 按设计图示尺寸以面积计算。 | M91: 除甲供材外，此项工作的全费用综合单价 甲供材：钢筋、混凝土、回填土 | P91: 1.5 | Q91: 55 | R91: =O91+P91+Q91 -> 56.5 | S91: =R91*$S$4 -> 67.8
A92: 5 | B92: 铺1嵌草砖铺面 | C92: 1、80厚嵌草砖,孔内填黄土拌草子种子 2、30厚1:1黄土粗砂层 3、100厚1:6水泥豆石(无砂)大孔混凝土 4、300厚天然级配碎砾石 5、素土夯实 6、单价包含包含综上所述材料费、辅材费、人工费、机械费、风险费、管理费、利润、措施费、运输倒运、含税单价中包含税金等所有费用。措施费包含安全文明施工费、雨季施工费、夜间施工增加费，施工抢工费等相关措施费用。 | D92: 1、测量定位、弹线、材料倒运； 2、砂干铺； 混凝土浇筑， 3、掏缝、修理刷水； 4、清理工作面；成品保护工作； | E92: m2 | F92: 89.04 | G92: 189.54 | H92: =F92*G92 -> 16876.64 | I92: =S92 -> 517.94 | J92: =F92*I92 -> 46117.38 | K92: =G92-I92 -> -328.4 | L92: 按设计图示尺寸以面积计算。 | M92: 相关工作全部费用 | O92: =主材表!L11 -> 75.22 | P92: =420*0.42 -> 176.4 | Q92: 180 | R92: =O92+P92+Q92 -> 431.62 | S92: =R92*$S$4 -> 517.94
A93: 6 | B93: 外墙3 真石漆外墙 | C93: 1、涂刷罩面清漆 2、涂饰第二遍面层涂料(透明) 3、涂饰面层涂料(透明) 4、喷主层涂料 5、辊、刷或喷底层涂料 6、5厚干粉类聚合物水泥防水砂浆,中间压入一层耐碱玻璃纤维网布 7、6厚1:2.5水泥砂浆找平 8、9厚1:3水泥砂浆 9、刷专用界面剂一道 | D93: 1.基层处理； 2.满刮腻子，涂刷封闭漆； 3.喷刷真石漆面层，收边收口、勾缝； 4.材料的运输、堆码、清运及场内多次搬运； 5.单价已包括送样的材料费用、检验、试验等工作; 6.配合安装队伍进行多次预留预埋及相关开槽、开洞的修补工作； 7.对已施工完成的成品及其他专业已完成的成品进行保护工作，无论是否由该单位导致的损坏，该单位都应履行修复处理责任； 8.对施工需要拆除或移动的材料，待施工完毕后，恢复原状； 9.完成工作区域的安全文明施工,清理施工遗留下的垃圾； 10.该项包含本项工作所有工作内容，未详尽列举特征，详见施工图纸、设计规范、施工方案事项均包含在综合单价中。 | E93: m2 | F93: 1053.41 | G93: 53.11 | H93: =F93*G93 -> 55946.61 | I93: =南川一标段!$I$115 -> 70.2 | J93: =F93*I93 -> 73949.38 | K93: =G93-I93 -> -17.09 | L93: 按设计图示尺寸以水平投影面积计算。 | M93: 相关工作全部费用 | R93: =O93+P93+Q93 -> 0 | S93: =R93*$S$4 -> 0
A94: 7 | B94: 防撞墩 | C94: 石材防撞墩 | D94: 1、材质：球型石材 2、工作内容：石材底座固定、防撞墩安装及固定、材料运输等 | E94: 个 | F94: 228 | G94: 210 | H94: =F94*G94 -> 47880 | I94: =南川一标段!$I$116 -> 270 | J94: =F94*I94 -> 61560 | K94: =G94-I94 -> -60 | L94: 根据图纸及技术交底，按现场实际完成的数量按个数计算。 | M94: 相关工作全部费用 | R94: =O94+P94+Q94 -> 0 | S94: =R94*$S$4 -> 0
A95: 8 | B95: 围墙钢制大门 | C95: 围墙钢制大门 | D95: 1、龙骨及面层钢板制安，油漆喷涂；2、规格：综合，详图纸； 3、包括除以上工作内容外，完成钢大门制安的所有工序及采取的各种技术措施等工作。 | E95: m2 | F95: 27 | G95: 340 | H95: =F95*G95 -> 9180 | I95: =南川一标段!$I$117 -> 504.6 | J95: =F95*I95 -> 13624.2 | K95: =G95-I95 -> -164.6 | L95: 根据图纸及技术交底，按现场实际完成的数量按面积计算。 | M95: 相关工作全部费用 | R95: =O95+P95+Q95 -> 0 | S95: =R95*$S$4 -> 0
B96: 不含税合计 | H96: =SUM(H7:H95) -> 7309902.7 | J96: =SUM(J7:J95) -> 10101159
B97: 税金（9%） | H97: =H96*0.09 -> 657891.24 | J97: =J96*0.09 -> 909104.28
B98: 含税合计 | H98: =H97+H96 -> 7967793.9 | J98: =J97+J96 -> 11010263

Sheet 水江四标段
A1: 重庆站房2标装饰装修一标段南川北站一标分包工程招标控制价审核表
A2: 项目名称：中铁建工集团有限公司重庆至黔江铁路站房工程2标项目经理部 | M2: 单位：元
A3: 序号 | B3: 项目名称 | C3: 项目特征 | D3: 工作内容 | E3: 单位 | F3: 工程量 | G3: 控制价 | I3: 上报金额 | K3: 工程量计算规则 | L3: 费用组成 | M3: 备注 | N3: 主材 | O3: 辅材 | P3: 人工 | Q3: 单价 | R3: 取费
G4: 不含税单价（元） | H4: 不含税合价（元） | I4: 不含税单价（元） | J4: 不含税合价（元） | R4: =南川一标段!$R$4 -> 1.2
A5: 三 | B5: 水江北站
A6: （一） | B6: 站房区域
A7: 1 | B7: 花岗石地面 | C7: 1、铺25厚磨光花岗石板(六面涂刷石材保护剂),同色稀水泥浆擦 2、50厚1:3干硬性水泥粘结层,撒素水泥粉 3、水泥浆一道(内掺建筑胶) 4、嵌缝材料种类：按甲方要求嵌缝、打胶； 5、防护层材料：防护剂六面处理，满足设计和相关规范要求； 6、酸洗、打蜡要求：满足设计和相关规范要求； 7、楼地面伸缩缝、变形缝的处理； 8、其它：该项包含本项工作所有工作内容含垂直运输机械等，未详尽列举特征，详见施工图纸、设计规范、施工方案事项均包含在综合单价中。 (石材规格800*800) | D7: 1.清理基层，试排弹线，锯板磨边，调铺砂浆；铺板、灌缝擦缝、清理净面等全部操作过程； 2.找平层、结合层施工； 3.石材刷防护液、铺贴、水泥浆勾缝； 4.材料的运输、堆码、清运及场内多次搬运； 5.综合单价包含切角、倒角、磨边、加厚、弧形加工、嵌缝、拉槽、排版损耗、晶面处理等费用，送样的材料费用、检验、试验等工作费用，还包括地砖铺贴前排版图设计工作; 6.配合安装队伍进行多次预留预埋及相关开槽、开洞的修补工作； 7.对已施工完成的成品及其他专业已完成的成品进行保护工作，无论是否由该单位导致的损坏，该单位都应履行修复处理责任； 8.对施工需要拆除或移动的材料，待施工完毕后，恢复原状； 9.完成工作区域的安全文明施工,清理施工遗留下的垃圾； 10.该项包含本项工作所有工作内容含垂直运输机械等，未详尽列举特征，详见施工图纸、设计规范、施工方案事项均包含在综合单价中。 | E7: m2 | F7: 1369.58 | G7: 85 | H7: =ROUND(F7*G7,2) -> 116414.3 | I7: =南川一标段!$I$7 -> 118.32 | J7: =F7*I7 -> 162048.71 | K7: 按设计图示尺寸以面积计算。 | L7: 1、除甲供材外全费用综合单价； 2、甲供材：石材 | Q7: =N7+O7+P7 -> 0 | R7: =Q7*$R$4 -> 0
A8: 2 | B8: 防滑地砖地面 | C8: 1、面层：10厚玻化砖(防滑),同色水泥浆擦缝 2、30厚1:3干硬性水泥砂浆,表面撒水泥粉 3、嵌缝材料种类：按甲方要求嵌缝、打胶； 4、防护层材料：满足设计和相关规范要求； 5、酸洗、打蜡要求：满足设计和相关规范要求； 6、楼地面伸缩缝、变形缝的处理； 7、其它：该项包含本项工作所有工作内容含垂直运输机械等，未详尽列举特征，详见施工图纸、设计规范、施工方案事项均包含在综合单价中。 (地砖规格600*600) | D8: 1.基层清理、找平、打磨、甩浆、弹线、定位； 2.结合层施工； 3.防滑地砖铺贴，干水泥擦缝； 4.材料的运输、堆码、清运及场内多次搬运； 5.单价已包括送样的材料费用、检验、试验等工作，还包括地砖铺贴前排版图设计工作; 6.配合安装队伍进行多次预留预埋及相关开槽、开洞的修补工作； 7.对已施工完成的成品及其他专业已完成的成品进行保护工作，无论是否由该单位导致的损坏，该单位都应履行修复处理责任； 8.对施工需要拆除或移动的材料，待施工完毕后，恢复原状； 9.完成工作区域的安全文明施工,清理施工遗留下的垃圾； 10.该项包含本项工作所有工作内容含垂直运输机械等，未详尽列举特征，详见施工图纸、设计规范、施工方案事项均包含在综合单价中。 | E8: m2 | F8: 209.59 | G8: 120 | H8: =ROUND(F8*G8,2) -> 25150.8 | I8: =南川一标段!$I$10 -> 165.22 | J8: =F8*I8 -> 34628.46 | K8: 按设计图示尺寸以面积计算。 | L8: 此项工作的全费用综合单价 | Q8: =N8+O8+P8 -> 0 | R8: =Q8*$R$4 -> 0
A9: 3 | B9: 防滑地砖地面(防水) | C9: 1、面层：10厚玻化砖(防滑),同色水泥浆擦缝 2、30厚1:3干硬性水泥砂浆,表面撒水泥粉 3、嵌缝材料种类：按甲方要求嵌缝、打胶； 4、防护层材料：满足设计和相关规范要求； 5、酸洗、打蜡要求：满足设计和相关规范要求； 6、楼地面伸缩缝、变形缝的处理； 7、其它：该项包含本项工作所有工作内容含垂直运输机械等，未详尽列举特征，详见施工图纸、设计规范、施工方案事项均包含在综合单价中。 (地砖规格600*600) | D9: 1.基层清理、找平、打磨、甩浆、弹线、定位； 2.结合层施工； 3.防滑地砖铺贴，干水泥擦缝； 4.材料的运输、堆码、清运及场内多次搬运； 5.单价已包括送样的材料费用、检验、试验等工作，还包括地砖铺贴前排版图设计工作; 6.配合安装队伍进行多次预留预埋及相关开槽、开洞的修补工作； 7.对已施工完成的成品及其他专业已完成的成品进行保护工作，无论是否由该单位导致的损坏，该单位都应履行修复处理责任； 8.对施工需要拆除或移动的材料，待施工完毕后，恢复原状； 9.完成工作区域的安全文明施工,清理施工遗留下的垃圾； 10.该项包含本项工作所有工作内容含垂直运输机械等，未详尽列举特征，详见施工图纸、设计规范、施工方案事项均包含在综合单价中。 | E9: m2 | F9: 144.4 | G9: 120 | H9: =ROUND(F9*G9,2) -> 17328 | I9: =南川一标段!$I$10 -> 165.22 | J9: =F9*I9 -> 23857.77 | K9: 按设计图示尺寸以面积计算。 | L9: 此项工作的全费用综合单价 | Q9: =N9+O9+P9 -> 0 | R9: =Q9*$R$4 -> 0
A10: 4 | B10: 防静电架空地面 | C10: 1、300高防静电活动地板,耐压强度10kN/㎡,配成套支架 2、10厚地砖(色另定) 3、20厚1:3干硬性砂浆,表面撒水泥粉 4、其他：该项包含本项工作所有工作内容含垂直运输机械等，未详尽列举特征，详见施工图纸、设计规范、施工方案事项均包含在综合单价中。 | D10: 1.基层清理、找平、打磨、甩浆、弹线、定位； 2.水泥砂浆找平； 3.安装固定支柱、横梁，防静电活动地板铺装； 4.材料的运输、堆码、清运及场内多次搬运； 5.单价已包括送样的材料费用、检验、试验等工作; 6.配合安装队伍进行多次预留预埋及相关开槽、开洞的修补工作； 7.对已施工完成的成品及其他专业已完成的成品进行保护工作，无论是否由该单位导致的损坏，该单位都应履行修复处理责任； 8.对施工需要拆除或移动的材料，待施工完毕后，恢复原状； 9.完成工作区域的安全文明施工,清理施工遗留下的垃圾。 10.该项包含本项工作所有工作内容含垂直运输机械等，未详尽列举特征，详见施工图纸、设计规范、施工方案事项均包含在综合单价中 | E10: m2 | F10: 67.05 | G10: 316.06 | H10: =ROUND(F10*G10,2) -> 21191.82 | I10: =南川一标段!$I$14 -> 391.2 | J10: =F10*I10 -> 26229.96 | K10: 按设计图示尺寸以面积计算。 | L10: 此项工作的全费用综合单价 | Q10: =N10+O10+P10 -> 0 | R10: =Q10*$R$4 -> 0
A11: 5 | B11: 水泥基自流平地面 | C11: 1、5厚水泥基自流平面层 2、涂刷自流平界面剂 3、其他：该项包含本项工作所有工作内容含垂直运输机械等，未详尽列举特征，详见施工图纸、设计规范、施工方案事项均包含在综合单价中。 | D11: 1.基层清理、找平、打磨、甩浆、定位、弹线； 2.刷界面剂一道； 3.自流平水泥施工、刮平、分格、养护、填塞分格缝、打磨面层； 4.材料的运输、堆码、清运及场内多次搬运； 5.单价已包括送样的材料费用、检验、试验等工作; 6.配合安装队伍进行多次预留预埋及相关开槽、开洞的修补工作； 7.对已施工完成的成品及其他专业已完成的成品进行保护工作，无论是否由该单位导致的损坏，该单位都应履行修复处理责任； 8.对施工需要拆除或移动的材料，待施工完毕后，恢复原状； 9.完成工作区域的安全文明施工,清理施工遗留下的垃圾； 10.该项包含本项工作所有工作内容含垂直运输机械等，未详尽列举特征，详见施工图纸、设计规范、施工方案事项均包含在综合单价中。 | E11: m2 | F11: 168.28 | G11: 47.92 | H11: =ROUND(F11*G11,2) -> 8063.98 | I11: =南川一标段!$I$13 -> 28.8 | J11: =F11*I11 -> 4846.46 | K11: 按设计图示尺寸以面积计算。 | L11: 此项工作的全费用综合单价 | Q11: =N11+O11+P11 -> 0 | R11: =Q11*$R$4 -> 0
A12: 6 | B12: 防滑地砖楼面 | C12: 1、面层：10厚玻化砖(防滑),同色水泥浆擦缝 2、30厚1:3干硬性水泥砂浆,表面撒水泥粉 3、嵌缝材料种类：按甲方要求嵌缝、打胶； 4、防护层材料：满足设计和相关规范要求； 5、酸洗、打蜡要求：满足设计和相关规范要求； 6、楼地面伸缩缝、变形缝的处理； 7、其它：该项包含本项工作所有工作内容含垂直运输机械等，未详尽列举特征，详见施工图纸、设计规范、施工方案事项均包含在综合单价中。 (地砖规格600*600) | D12: 1.基层清理、找平、打磨、甩浆、弹线、定位； 2.结合层施工； 3.防滑地砖铺贴，干水泥擦缝； 4.材料的运输、堆码、清运及场内多次搬运； 5.单价已包括送样的材料费用、检验、试验等工作，还包括地砖铺贴前排版图设计工作; 6.配合安装队伍进行多次预留预埋及相关开槽、开洞的修补工作； 7.对已施工完成的成品及其他专业已完成的成品进行保护工作，无论是否由该单位导致的损坏，该单位都应履行修复处理责任； 8.对施工需要拆除或移动的材料，待施工完毕后，恢复原状； 9.完成工作区域的安全文明施工,清理施工遗留下的垃圾； 10.该项包含本项工作所有工作内容含垂直运输机械等，未详尽列举特征，详见施工图纸、设计规范、施工方案事项均包含在综合单价中。 | E12: m2 | F12: 323.6 | G12: 120 | H12: =ROUND(F12*G12,2) -> 38832 | I12: =南川一标段!$I$10 -> 165.22 | J12: =F12*I12 -> 53465.19 | K12: 按设计图示尺寸以面积计算。 | L12: 此项工作的全费用综合单价 | Q12: =N12+O12+P12 -> 0 | R12: =Q12*$R$4 -> 0
A13: 7 | B13: 防滑地砖楼面(防水) | C13: 1、面层：10厚玻化砖(防滑),同色水泥浆擦缝 2、30厚1:3干硬性水泥砂浆,表面撒水泥粉 3、嵌缝材料种类：按甲方要求嵌缝、打胶； 4、防护层材料：满足设计和相关规范要求； 5、酸洗、打蜡要求：满足设计和相关规范要求； 6、楼地面伸缩缝、变形缝的处理； 7、其它：该项包含本项工作所有工作内容含垂直运输机械等，未详尽列举特征，详见施工图纸、设计规范、施工方案事项均包含在综合单价中。 (地砖规格600*600) | D13: 1.基层清理、找平、打磨、甩浆、弹线、定位； 2.结合层施工； 3.防滑地砖铺贴，干水泥擦缝； 4.材料的运输、堆码、清运及场内多次搬运； 5.单价已包括送样的材料费用、检验、试验等工作，还包括地砖铺贴前排版图设计工作; 6.配合安装队伍进行多次预留预埋及相关开槽、开洞的修补工作； 7.对已施工完成的成品及其他专业已完成的成品进行保护工作，无论是否由该单位导致的损坏，该单位都应履行修复处理责任； 8.对施工需要拆除或移动的材料，待施工完毕后，恢复原状； 9.完成工作区域的安全文明施工,清理施工遗留下的垃圾； 10.该项包含本项工作所有工作内容含垂直运输机械等，未详尽列举特征，详见施工图纸、设计规范、施工方案事项均包含在综合单价中。 | E13: m2 | F13: 37.42 | G13: 120 | H13: =ROUND(F13*G13,2) -> 4490.4 | I13: =南川一标段!$I$10 -> 165.22 | J13: =F13*I13 -> 6182.53 | K13: 按设计图示尺寸以面积计算。 | L13: 此项工作的全费用综合单价 | Q13: =N13+O13+P13 -> 0 | R13: =Q13*$R$4 -> 0
A14: 8 | B14: 防静电活动楼面 | C14: 1、300高防静电活动地板,耐压强度10kN/㎡ 2、10厚地砖(色另定) 3、20厚1:3干硬性砂浆,表面撒水泥粉 4、水泥浆一道,内掺建筑胶 5、其他：该项包含本项工作所有工作内容含垂直运输机械等，未详尽列举特征，详见施工图纸、设计规范、施工方案事项均包含在综合单价中。 | D14: 1.基层清理、找平、打磨、甩浆、弹线、定位； 2.水泥砂浆找平； 3.安装固定支柱、横梁，防静电活动地板铺装； 4.材料的运输、堆码、清运及场内多次搬运； 5.单价已包括送样的材料费用、检验、试验等工作; 6.配合安装队伍进行多次预留预埋及相关开槽、开洞的修补工作； 7.对已施工完成的成品及其他专业已完成的成品进行保护工作，无论是否由该单位导致的损坏，该单位都应履行修复处理责任； 8.对施工需要拆除或移动的材料，待施工完毕后，恢复原状； 9.完成工作区域的安全文明施工,清理施工遗留下的垃圾； 10.该项包含本项工作所有工作内容含垂直运输机械等，未详尽列举特征，详见施工图纸、设计规范、施工方案事项均包含在综合单价中。 | E14: m2 | F14: 125.11 | G14: 316.06 | H14: =ROUND(F14*G14,2) -> 39542.27 | I14: =南川一标段!$I$14 -> 391.2 | J14: =F14*I14 -> 48943.03 | K14: 按设计图示尺寸以面积计算。 | L14: 此项工作的全费用综合单价 | Q14: =N14+O14+P14 -> 0 | R14: =Q14*$R$4 -> 0
A15: 9 | B15: 防滑玻化砖梯面 | C15: 1、面层：10厚玻化砖(防滑),同色水泥浆擦缝 2、30厚1:3干硬性水泥砂浆,表面撒水泥粉 3、嵌缝材料种类：按甲方要求嵌缝、打胶，挡水条制作； 4、防护层材料：满足设计和相关规范要求； 5、酸洗、打蜡要求：满足设计和相关规范要求； 6、楼地面伸缩缝、变形缝的处理； 7、其它：该项包含本项工作所有工作内容含垂直运输机械等，未详尽列举特征，详见施工图纸、设计规范、施工方案事项均包含在综合单价中。 (地砖规格600*600) | D15: 1.基层清理、找平、打磨、甩浆、弹线、定位； 2.结合层施工，挡水条制作； 3.刷素水泥浆一道(内掺建筑胶)；面层施工、擦缝 4.材料的运输、堆码、清运及场内多次搬运； 5.综合单价包含切角、倒角、磨边、排版损耗等费用，送样的材料费用、检验、试验等工作，还包括地砖铺贴前排版图设计工作; 6.配合安装队伍进行多次预留预埋及相关开槽、开洞的修补工作； 7.对已施工完成的成品及其他专业已完成的成品进行保护工作，无论是否由该单位导致的损坏，该单位都应履行修复处理责任； 8.对施工需要拆除或移动的材料，待施工完毕后，恢复原状； 9.完成工作区域的安全文明施工,清理施工遗留下的垃圾； 10.该项包含本项工作所有工作内容含垂直运输机械等，未详尽列举特征，详见施工图纸、设计规范、施工方案事项均包含在综合单价中。 | E15: m2 | F15: 256.33 | G15: 135 | H15: =ROUND(F15*G15,2) -> 34604.55 | I15: =南川一标段!$I$11 -> 175.84 | J15: =F15*I15 -> 45073.07 | K15: 按设计图示尺寸以展开面积计算 | L15: 此项工作的全费用综合单价 | Q15: =N15+O15+P15 -> 0 | R15: =Q15*$R$4 -> 0
A16: 10 | B16: 25MM厚深灰麻过门石 | C16: 1、铺25厚磨光花岗石板(六面涂刷石材保护剂),同色稀水泥浆擦 2、50厚1:3干硬性水泥粘结层,撒素水泥粉 3、水泥浆一道(内掺建筑胶) 4、嵌缝材料种类：按甲方要求嵌缝、打胶； 5、防护层材料：防护剂六面处理，满足设计和相关规范要求； 6、酸洗、打蜡要求：满足设计和相关规范要求； 7、楼地面伸缩缝、变形缝的处理； 8、其它：该项包含本项工作所有工作内容含垂直运输机械等，未详尽列举特征，详见施工图纸、设计规范、施工方案事项均包含在综合单价中。 (石材规格800*800) | D16: [工作内容] 1.基层清理 2.抹找平层 3.面层铺设、切边、磨边 4.嵌缝 5.刷防护材料 6.酸洗、打蜡 7.材料运输 8.该项包含本项工作所有工作内容含垂直运输机械等，未详尽列举特征，详见施工图纸、设计规范、施工方案事项均包含在综合单价中。 | E16: m2 | F16: 24.47 | G16: 85 | H16: =ROUND(F16*G16,2) -> 2079.95 | I16: =南川一标段!$I$16 -> 156 | J16: =F16*I16 -> 3817.32 | K16: 按设计图示尺寸以面积计算。 | L16: 1、除甲供材外全费用综合单价； 2、甲供材：石材 | Q16: =N16+O16+P16 -> 0 | R16: =Q16*$R$4 -> 0
A17: 11 | B17: 水泥踢脚 | C17: 1、6厚1:2.5水泥砂浆抹面压实赶光 2、刷素水泥浆一道 3、7厚1:1:6水泥石灰膏砂浆打底骚猫或划出纹道 4、3厚外加剂专用砂浆抹基底刮糙(抹前用水喷湿墙面) 5、其他：该项包含本项工作所有工作内容含垂直运输机械等，未详尽列举特征，详见施工图纸、设计规范、施工方案事项均包含在综合单价中。 | D17: 1.墙体基层处理、找平抹灰、压实； 2.踢脚线制作、运输、安装，抹面压实赶光； 3.材料的运输、堆码、清运及场内多次搬运； 4.单价已包括送样的材料费用、检验、试验等工作; 5.配合安装队伍进行多次预留预埋及相关开槽、开洞的修补工作； 6.对已施工完成的成品及其他专业已完成的成品进行保护工作，无论是否由该单位导致的损坏，该单位都应履行修复处理责任； 7.对施工需要拆除或移动的材料，待施工完毕后，恢复原状； 8.完成工作区域的安全文明施工,清理施工遗留下的垃圾； 9.该项包含本项工作所有工作内容含垂直运输机械等，未详尽列举特征，详见施工图纸、设计规范、施工方案事项均包含在综合单价中。 | E17: m2 | F17: 27.73 | G17: 35 | H17: =ROUND(F17*G17,2) -> 970.55 | I17: =南川一标段!$I$17 -> 174.1 | J17: =F17*I17 -> 4827.79 | K17: 以平方米计量，按设计图示长度乘高度以面积计算 | L17: 此项工作的全费用综合单价 | Q17: =N17+O17+P17 -> 0 | R17: =Q17*$R$4 -> 0
A18: 12 | B18: 地砖踢脚 | C18: 1、粘贴10厚地砖,专用勾缝剂勾缝 2、9厚1:2水泥砂浆(内掺3%超密聚合物防水剂)粘结层 3、素水泥浆一道(内掺建筑胶) 4、基层墙体 5、其他：该项包含本项工作所有工作内容含垂直运输机械等，未详尽列举特征，详见施工图纸、设计规范、施工方案事项均包含在综合单价中。 | D18: 1.墙体基层处理、找平抹灰、压实； 2.踢脚线制作、运输、安装，面砖背面涂专用粘接剂，用专用勾缝剂勾缝； 3.材料的运输、堆码、清运及场内多次搬运； 4.单价已包括送样的材料费用、检验、试验等工作; 5.配合安装队伍进行多次预留预埋及相关开槽、开洞的修补工作； 6.对已施工完成的成品及其他专业已完成的成品进行保护工作，无论是否由该单位导致的损坏，该单位都应履行修复处理责任； 7.对施工需要拆除或移动的材料，待施工完毕后，恢复原状； 8.完成工作区域的安全文明施工,清理施工遗留下的垃圾； 9.该项包含本项工作所有工作内容含垂直运输机械等，未详尽列举特征，详见施工图纸、设计规范、施工方案事项均包含在综合单价中。 | E18: m2 | F18: 62.84 | G18: 130 | H18: =ROUND(F18*G18,2) -> 8169.2 | I18: =南川一标段!$I$18 -> 233.83 | J18: =F18*I18 -> 14693.88 | K18: 以平方米计量，按设计图示长度乘高度以面积计算 | L18: 此项工作的全费用综合单价 | Q18: =N18+O18+P18 -> 0 | R18: =Q18*$R$4 -> 0
A19: 13 | B19: 不锈钢踢脚 | C19: 1、板缝处理 2、1.0厚不锈钢板与卡件安装 3、金属踢脚卡件固定,间距500mm 4、基层墙面 5、其他：该项包含本项工作所有工作内容含垂直运输机械等，未详尽列举特征，详见施工图纸、设计规范、施工方案事项均包含在综合单价中。 | D19: 1.墙体基层处理； 2.粘贴、固定不锈钢踢脚线； 3.材料的运输、堆码、清运及场内多次搬运； 4.单价已包括送样的材料费用、检验、试验等工作; 5.配合安装队伍进行多次预留预埋及相关开槽、开洞的修补工作； 6.对已施工完成的成品及其他专业已完成的成品进行保护工作，无论是否由该单位导致的损坏，该单位都应履行修复处理责任； 7.对施工需要拆除或移动的材料，待施工完毕后，恢复原状； 8.完成工作区域的安全文明施工,清理施工遗留下的垃圾； 9.该项包含本项工作所有工作内容含垂直运输机械等，未详尽列举特征，详见施工图纸、设计规范、施工方案事项均包含在综合单价中。 | E19: m2 | F19: 35.29 | G19: 272.98 | H19: =ROUND(F19*G19,2) -> 9633.46 | I19: =南川一标段!$I$19 -> 519.74 | J19: =F19*I19 -> 18341.62 | K19: 以平方米计量，按设计图示长度乘高度以面积计算 | L19: 此项工作的全费用综合单价 | Q19: =N19+O19+P19 -> 0 | R19: =Q19*$R$4 -> 0
A20: 14 | B20: 干挂铝板墙面（含消防暗门） | C20: 1、3厚铝合金饰面面层,接缝处密缝(或10*10MM凹槽);(3米以下加肋,衬6mm厚硅酸钙板)。 2、金属板材用抽芯铆钉或自攻螺钉固定于铝方型材纵横方向龙骨上,板材带折边采用搭接式,带挂耳采用对接式; 3、60X40X4铝方型材龙骨,横向间距同金属板材宽度,纵向间距同金属板材长度,用螺栓与角钢连接。 4、8#槽钢竖向龙骨连接件螺栓连接, 5、连接件与预埋板焊接 6、预埋件 7、墙面伸缩缝、变形缝的处理 其他：该项包含本项工作所有工作内容含垂直运输机械等，未详尽列举特征，详见施工图纸、设计规范、施工方案事项均包含在综合单价中。 | D20: 1.墙体基层处理； 2.预埋件埋设、连接件、龙骨的制作、运输、安装；将其固定在墙体上； 3.铝合金饰面面层的制作、运输、安装； 4.材料的运输、堆码、清运及场内多次搬运； 5.单价已包括送样的材料费用、检验、试验等工作; 6.配合安装队伍进行多次预留预埋及相关开槽、开洞的修补工作； 7.对已施工完成的成品及其他专业已完成的成品进行保护工作，无论是否由该单位导致的损坏，该单位都应履行修复处理责任； 8.对施工需要拆除或移动的材料，待施工完毕后，恢复原状； 9.完成工作区域的安全文明施工,清理施工遗留下的垃圾； 10.该项包含本项工作所有工作内容含垂直运输机械等，未详尽列举特征，详见施工图纸、设计规范、施工方案事项均包含在综合单价中。 | E20: m2 | F20: 2195.44 | G20: 120 | H20: =ROUND(F20*G20,2) -> 263452.8 | I20: =南川一标段!$I$22 -> 177 | J20: =F20*I20 -> 388592.88 | K20: 按设计图示尺寸以面积计算 | L20: 1、除型钢龙骨及甲供材外全费用综合单价； 2、甲供材：铝板 | Q20: =N20+O20+P20 -> 0 | R20: =Q20*$R$4 -> 0
A21: 15 | B21: 无机涂料墙面 | C21: 1、喷(刷、辊)无机内墙薄涂涂料2道 2、满刮2厚腻子砂磨平 3、其他：该项包含本项工作所有工作内容含垂直运输机械等，未详尽列举特征，详见施工图纸、设计规范、施工方案事项均包含在综合单价中。 | D21: 1.内墙基层处理； 2.水泥砂浆找平打底扫毛，内掺建筑胶； 3.水泥砂浆找平层、水泥砂浆罩面压光施工； 4.满刮腻子两遍，找平磨光； 5.喷（刷）无机涂料2道； 6.材料的运输、堆码、清运及场内多次搬运； 7.单价已包括送样的材料费用、检验、试验等工作; 8.配合安装队伍进行多次预留预埋及相关开槽、开洞的修补工作； 9.对已施工完成的成品及其他专业已完成的成品进行保护工作，无论是否由该单位导致的损坏，该单位都应履行修复处理责任； 10.对施工需要拆除或移动的材料，待施工完毕后，恢复原状； 11.完成工作区域的安全文明施工,清理施工遗留下的垃圾。 12.该项包含本项工作所有工作内容含垂直运输机械等，未详尽列举特征，详见施工图纸、设计规范、施工方案事项均包含在综合单价中。 | E21: m2 | F21: 3148.33 | G21: 27 | H21: =ROUND(F21*G21,2) -> 85004.91 | I21: =南川一标段!$I$20 -> 44.4 | J21: =F21*I21 -> 139785.85 | K21: 按设计图示尺寸以面积计算（有吊顶房间算至吊顶底，无吊顶房间算至梁底或者板底） | L21: 此项工作的全费用综合单价 | Q21: =N21+O21+P21 -> 0 | R21: =Q21*$R$4 -> 0
A22: 16 | B22: 防水面砖墙面 | C22: 1、同色水泥擦缝 2、8-10厚墙面砖(粘贴前墙砖充分浸湿) 3、8厚1:2水泥砂浆粘结层(内掺建筑胶) 4、缝宽、嵌缝材料：按甲方要求嵌缝、打胶； 5、酸洗、打蜡要求：满足设计和相关规范要求； 6、墙面伸缩缝、变形缝的处理； 7、根据安装需要开孔 8、其他：该项包含本项工作所有工作内容含垂直运输机械等，未详尽列举特征，详见施工图纸、设计规范、施工方案事项均包含在综合单价中。 (600×300墙砖) | D22: 1.内墙基层处理； 2.水泥砂浆粘结层，内掺建筑胶； 3.墙面面砖运输、制作、铺贴、擦缝 4.材料的运输、堆码、清运及场内多次搬运； 5.综合单价包含切角、倒角、磨边、加厚、弧形加工、嵌缝、拉槽、排版损耗、晶面处理等费用，送样的材料费用、检验、试验等工作费用，还包括地砖铺贴前排版图设计工作; 6.配合安装队伍进行多次预留预埋及相关开槽、开洞的修补工作； 7.对已施工完成的成品及其他专业已完成的成品进行保护工作，无论是否由该单位导致的损坏，该单位都应履行修复处理责任； 8.对施工需要拆除或移动的材料，待施工完毕后，恢复原状； 9.完成工作区域的安全文明施工,清理施工遗留下的垃圾。 10.该项包含本项工作所有工作内容含垂直运输机械等，未详尽列举特征，详见施工图纸、设计规范、施工方案事项均包含在综合单价中。 | E22: m2 | F22: 641.12 | G22: 120 | H22: =ROUND(F22*G22,2) -> 76934.4 | I22: =南川一标段!$I$21 -> 153.02 | J22: =F22*I22 -> 98104.18 | K22: 按设计图示尺寸以面积计算（有吊顶房间算至吊顶底） | L22: 此项工作的全费用综合单价 | Q22: =N22+O22+P22 -> 0 | R22: =Q22*$R$4 -> 0
A23: 17 | B23: 耐擦洗涂料墙面 | C23: 1、防火型无机耐擦洗涂料两道饰面(白色) 2、满刮2厚耐水腻子找平 3、其他：该项包含本项工作所有工作内容含垂直运输机械等，未详尽列举特征，详见施工图纸、设计规范、施工方案事项均包含在综合单价中。 | D23: 1.内墙基层处理； 2.外加剂专用砂浆打底刮糙或专用界面剂一道甩毛； 3.石灰膏砂浆分层抹平； 4.满刮腻子两遍，找平磨光； 5.防火型无机耐擦洗涂料两道饰面； 6.材料的运输、堆码、清运及场内多次搬运； 7.单价已包括送样的材料费用、检验、试验等工作; 8.配合安装队伍进行多次预留预埋及相关开槽、开洞的修补工作； 9.对已施工完成的成品及其他专业已完成的成品进行保护工作，无论是否由该单位导致的损坏，该单位都应履行修复处理责任； 10.对施工需要拆除或移动的材料，待施工完毕后，恢复原状； 11.完成工作区域的安全文明施工,清理施工遗留下的垃圾。 12.该项包含本项工作所有工作内容含垂直运输机械等，未详尽列举特征，详见施工图纸、设计规范、施工方案事项均包含在综合单价中。 | E23: m2 | F23: 638.91 | G23: 30 | H23: =ROUND(F23*G23,2) -> 19167.3 | I23: =南川一标段!$I$100 -> 44.4 | J23: =F23*I23 -> 28367.6 | K23: 按设计图示尺寸以面积计算（有吊顶房间算至吊顶底，无吊顶房间算至梁底或者板底） | L23: 此项工作的全费用综合单价 | Q23: =N23+O23+P23 -> 0 | R23: =Q23*$R$4 -> 0
A24: 18 | B24: 陶瓷马赛克墙面(防水) | C24: 1、同色水泥擦缝 2、8-10厚墙面砖(粘贴前墙砖充分浸湿) 3、8厚1:2水泥砂浆粘结层(内掺建筑胶) 4、缝宽、嵌缝材料：按甲方要求嵌缝、打胶； 5、酸洗、打蜡要求：满足设计和相关规范要求； 6、墙面伸缩缝、变形缝的处理； 7、根据安装需要开孔 8、其他：该项包含本项工作所有工作内容含垂直运输机械等，未详尽列举特征，详见施工图纸、设计规范、施工方案事项均包含在综合单价中。 (600×300墙砖) | D24: 1.内墙基层处理； 2.水泥砂浆找平打底扫毛，内掺建筑胶； 3.面砖制作、运输、铺贴，同色水泥擦缝； 4.材料的运输、堆码、清运及场内多次搬运； 5.综合单价包含切角、倒角、磨边、加厚、弧形加工、嵌缝、拉槽、排版损耗、晶面处理等费用，送样的材料费用、检验、试验等工作费用，还包括地砖铺贴前排版图设计工作; 6.配合安装队伍进行多次预留预埋及相关开槽、开洞的修补工作； 7.对已施工完成的成品及其他专业已完成的成品进行保护工作，无论是否由该单位导致的损坏，该单位都应履行修复处理责任； 8.对施工需要拆除或移动的材料，待施工完毕后，恢复原状； 9.完成工作区域的安全文明施工,清理施工遗留下的垃圾。 10.该项包含本项工作所有工作内容含垂直运输机械等，未详尽列举特征，详见施工图纸、设计规范、施工方案事项均包含在综合单价中。 | E24: m2 | F24: 4.99 | G24: 107.72 | H24: =ROUND(F24*G24,2) -> 537.52 | I24: =R24 -> 174.26 | J24: =F24*I24 -> 869.56 | K24: 按设计图示尺寸以面积计算。 | L24: 此项工作的全费用综合单价 | N24: =主材表!$L$12 -> 75.22 | O24: 10 | P24: 60 | Q24: =N24+O24+P24 -> 145.22 | R24: =Q24*$R$4 -> 174.26
A25: 19 | B25: 铝合金条板(锤片)吊顶（候车大厅） | C25: 1、铝合金条板与配套专用龙骨固定(宽150mm,缝75mm,厚1mm) 2、与铝合金方通配套的专用龙骨,间距≤1200,用吊件与钢筋吊杆连接后找平 3、10号镀锌低碳钢丝(或%%C6钢筋)吊杆,双向中距≤1200,吊杆上部与板底预留吊环(勾)固定 4、现浇钢筋混凝土板底预留%%C10钢筋吊环(勾),双向中距≤1200(吊杆长度超过1.5米后需要做反支撑,吊杆长度超过2.5米需做转换层,做法详见二次结构施工安装详图)(转换层另列） 5、天棚伸缩缝、变形缝的处理； 其他：该项包含本项工作所有工作内容含垂直运输机械等，未详尽列举特征，详见施工图纸、设计规范、施工方案事项均包含在综合单价中。 | D25: 1.基层处理； 2.龙骨、吊杆安装； 4.铝合金条板面层安装； 5.材料的运输、堆码、清运及场内多次搬运； 6.单价已包括送样的材料费用、检验、试验等工作; 7.配合安装队伍进行多次预留预埋及相关开槽、开洞的修补工作； 8.对已施工完成的成品及其他专业已完成的成品进行保护工作，无论是否由该单位导致的损坏，该单位都应履行修复处理责任； 9.对施工需要拆除或移动的材料，待施工完毕后，恢复原状； 10.完成工作区域的安全文明施工,清理施工遗留下的垃圾。 11.该项包含本项工作所有工作内容含垂直运输机械等，未详尽列举特征，详见施工图纸、设计规范、施工方案事项均包含在综合单价中。 | E25: m2 | F25: 972.3 | G25: 125 | H25: =ROUND(F25*G25,2) -> 121537.5 | I25: =南川一标段!$I$33 -> 182.4 | J25: =F25*I25 -> 177347.52 | K25: 按设计图示尺寸以水平投影面积计算。 | L25: 1、除甲供材外全费用综合单价； 2、甲供材：铝板 | Q25: =N25+O25+P25 -> 0 | R25: =Q25*$R$4 -> 0
A26: 20 | B26: 铝合金单板装饰吊顶（含包梁）（候车大厅） | C26: 1、2.5厚铝合金单板与配套专用龙骨固定 2、与铝合金单板配套的专用下层副龙骨联结,间距≤600 3、与安装型式配套的专用上层主龙骨,间距≤1200,用吊件与钢筋吊杆联结后找平 4、10号镀锌低碳钢丝(或%%C8钢筋)吊杆,双向中距≤1200,吊杆上部与板底预留吊环固定 5、现浇钢筋混凝土板底预留%%C10钢筋吊环,双向中距≤1200； 6、天棚伸缩缝、变形缝的处理； 其他：该项包含本项工作所有工作内容含垂直运输机械等，未详尽列举特征，详见施工图纸、设计规范、施工方案事项均包含在综合单价中。 | D26: 1.基层处理； 2.龙骨、吊杆安装； 4.铝合金条板面层安装； 5.材料的运输、堆码、清运及场内多次搬运； 6.单价已包括送样的材料费用、检验、试验等工作; 7.配合安装队伍进行多次预留预埋及相关开槽、开洞的修补工作； 8.对已施工完成的成品及其他专业已完成的成品进行保护工作，无论是否由该单位导致的损坏，该单位都应履行修复处理责任； 9.对施工需要拆除或移动的材料，待施工完毕后，恢复原状； 10.完成工作区域的安全文明施工,清理施工遗留下的垃圾。 11.该项包含本项工作所有工作内容含垂直运输机械等，未详尽列举特征，详见施工图纸、设计规范、施工方案事项均包含在综合单价中。 | E26: m2 | F26: 334.84 | G26: 135 | H26: =ROUND(F26*G26,2) -> 45203.4 | I26: =南川一标段!$I$31 -> 182.4 | J26: =F26*I26 -> 61074.82 | K26: 按设计图示尺寸以水平投影面积计算。 | L26: 1、除型钢龙骨及甲供材外全费用综合单价； 2、甲供材：铝板 | Q26: =N26+O26+P26 -> 0 | R26: =Q26*$R$4 -> 0
A27: 21 | B27: 铝合金扣板顶棚 | C27: 1、600*600*1.0铝合金扣板(折边20) 2、与铝合金扣板配套的专用暗架龙骨,间距≤300,通过十字连扣连接件与承载龙骨连接 3、D38承载龙骨,间距≤1200,用吊杆与钢筋吊杆联结后找平 4、10厚镀锌低碳钢丝(或%%C8钢筋)吊杆,双向中距≤1200,吊杆上部与板底(或钢结构)预留吊环(勾)固定 5、结构层预埋%%C10(或钢结构预留)钢筋吊环(勾),双向中距≤1200 6、天棚伸缩缝、变形缝的处理； 其他：该项包含本项工作所有工作内容含垂直运输机械等，未详尽列举特征，详见施工图纸、设计规范、施工方案事项均包含在综合单价中。 | D27: 1.基层处理 2.轻钢龙骨、吊杆安装； 3.铝扣板安装、收边线； 4.材料的运输、堆码、清运及场内多次搬运； 5.单价已包括送样的材料费用、检验、试验等工作; 6.配合安装队伍进行多次预留预埋及相关开槽、开洞的修补工作； 7.对已施工完成的成品及其他专业已完成的成品进行保护工作，无论是否由该单位导致的损坏，该单位都应履行修复处理责任； 8.对施工需要拆除或移动的材料，待施工完毕后，恢复原状； 9.完成工作区域的安全文明施工,清理施工遗留下的垃圾； 10.该项包含本项工作所有工作内容含垂直运输机械等，未详尽列举特征，详见施工图纸、设计规范、施工方案事项均包含在综合单价中。 | E27: m2 | F27: 155.48 | G27: 136.14 | H27: =ROUND(F27*G27,2) -> 21167.05 | I27: =南川一标段!$I$29 -> 160.04 | J27: =F27*I27 -> 24883.02 | K27: 按设计图示尺寸以水平投影面积计算。 | L27: 除型钢龙骨外的全费用综合单价 | Q27: =N27+O27+P27 -> 0 | R27: =Q27*$R$4 -> 0
A28: 22 | B28: 硅酸钙板(防潮石膏板)涂料顶棚(防水) | C28: 1、喷(刷、辊)涂料面层两遍(每道间隔2小时) 2、封底漆一道(干燥后再做面层) 3、满刮2厚面层耐水腻子找平,板面接缝处贴嵌缝带,刮腻子抹平 4、错缝粘贴第二层9.5厚耐水耐火纸面石膏板 5、9.5厚耐水耐火纸面石膏板用自攻螺丝与龙骨固定,中距≤200,螺丝距板长边≥10,短边≥15 6、U型轻钢覆面横撑龙骨CB60x27,间距1200,用挂插件与次龙骨联结 7、U型轻钢覆面次龙骨CB60x27,间距400,用挂件与承接龙骨联结 8、U型轻钢承接龙骨CS50x15,间距≤1200,用吊杆与钢筋吊杆联结后找平 9、%%C8钢筋吊杆并加反支撑,双向中距≤1200,吊杆上部与预留钢筋吊环固定 10、现浇钢筋混凝土板底预埋%%C10钢筋吊环(勾),双向中距≤1200 11、天棚伸缩缝、变形缝的处理； 其他：该项包含本项工作所有工作内容含垂直运输机械等，未详尽列举特征，详见施工图纸、设计规范、施工方案事项均包含在综合单价中。 | D28: 1.基层处理； 2.主、次龙骨、角钢、吊杆安装； 3.耐火纸面石膏板面层安装； 4.满刮防水腻子找平，封底漆施工； 5.涂料面层两遍； 6.材料的运输、堆码、清运及场内多次搬运； 7.单价已包括送样的材料费用、检验、试验等工作; 8.配合安装队伍进行多次预留预埋及相关开槽、开洞的修补工作； 9.对已施工完成的成品及其他专业已完成的成品进行保护工作，无论是否由该单位导致的损坏，该单位都应履行修复处理责任； 10.对施工需要拆除或移动的材料，待施工完毕后，恢复原状； 11.完成工作区域的安全文明施工,清理施工遗留下的垃圾； 12.该项包含本项工作所有工作内容含垂直运输机械等，未详尽列举特征，详见施工图纸、设计规范、施工方案事项均包含在综合单价中。 | E28: m2 | F28: 163.59 | G28: 166.94 | H28: =ROUND(F28*G28,2) -> 27309.71 | I28: =彭水二标段!$I$29 -> 177.6 | J28: =F28*I28 -> 29053.58 | K28: 按设计图示尺寸以水平投影面积计算。 | L28: 此项工作的全费用综合单价 | Q28: =N28+O28+P28 -> 0 | R28: =Q28*$R$4 -> 0
A29: 23 | B29: 石膏面层板吊顶 | C29: 1、12厚石膏面层板面层,规格592x592 2、T型次龙骨TB24x30,间距600,与主龙骨插接 3、T型主龙骨TB24X30,间距600,通过D-T挂件与承载龙骨连接 4、D38承载龙骨,间距1200,用吊件与钢筋吊杆联结后找平 5、%%C8螺纹吊杆,双向中距≤1200,吊杆上部与吊顶转换层固定 7、50*5镀锌角钢吊顶转换层,井字型网格间距≤2400*1200(转换层另列） 8、其他：该项包含本项工作所有工作内容含垂直运输机械等，未详尽列举特征，详见施工图纸、设计规范、施工方案事项均包含在综合单价中。 | D29: 1.基层处理； 2.主、次龙骨、角钢、吊杆安装； 3.纸面石膏板面层安装，收边收口； 4.材料的运输、堆码、清运及场内多次搬运； 5.单价已包括送样的材料费用、检验、试验等工作; 6.配合安装队伍进行多次预留预埋及相关开槽、开洞的修补工作； 7.对已施工完成的成品及其他专业已完成的成品进行保护工作，无论是否由该单位导致的损坏，该单位都应履行修复处理责任； 8.对施工需要拆除或移动的材料，待施工完毕后，恢复原状； 9.完成工作区域的安全文明施工,清理施工遗留下的垃圾； 10.该项包含本项工作所有工作内容含垂直运输机械等，未详尽列举特征，详见施工图纸、设计规范、施工方案事项均包含在综合单价中。 | E29: m2 | F29: 463.01 | G29: 98.94 | H29: =ROUND(F29*G29,2) -> 45810.21 | I29: =彭水二标段!$I$32 -> 108.6 | J29: =F29*I29 -> 50282.89 | K29: 按设计图示尺寸以水平投影面积计算。 | L29: 此项工作的全费用综合单价 | Q29: =N29+O29+P29 -> 0 | R29: =Q29*$R$4 -> 0
A30: 24 | B30: 无机涂料顶棚 | C30: 1、防火型无机耐擦洗涂料两道饰面(白色) 2、2厚面层耐水腻子刮平 3、其他：该项包含本项工作所有工作内容含垂直运输机械等，未详尽列举特征，详见施工图纸、设计规范、施工方案事项均包含在综合单价中。 | D30: 1.基层处理、甩浆； 2.水泥砂浆打底找平； 2.满刮腻子找平、磨光； 4.防火型无机耐擦洗涂料两道饰面(； 5.材料的运输、堆码、清运及场内多次搬运； 6.单价已包括送样的材料费用、检验、试验等工作; 7.配合安装队伍进行多次预留预埋及相关开槽、开洞的修补工作； 8.对已施工完成的成品及其他专业已完成的成品进行保护工作，无论是否由该单位导致的损坏，该单位都应履行修复处理责任； 9.对施工需要拆除或移动的材料，待施工完毕后，恢复原状； 10.完成工作区域的安全文明施工,清理施工遗留下的垃圾。 11.该项包含本项工作所有工作内容含垂直运输机械等，未详尽列举特征，详见施工图纸、设计规范、施工方案事项均包含在综合单价中。 | E30: m2 | F30: 969.32 | G30: 32 | H30: =ROUND(F30*G30,2) -> 31018.24 | I30: =南川一标段!$I$20 -> 44.4 | J30: =F30*I30 -> 43037.81 | K30: 按设计图示尺寸以水平投影面积计算。 | L30: 此项工作的全费用综合单价 | Q30: =N30+O30+P30 -> 0 | R30: =Q30*$R$4 -> 0
A31: 25 | B31: 吸顶玻璃棉毡铝板网吸声吊顶 | C31: 1、1.5厚穿孔铝合金饰面板 2、50厚超细玻璃丝棉吸声层,玻璃丝布袋装填于龙骨间 3、T型轻钢横撑龙骨TB24X28,间距600,与主龙骨插接 4、T型轻钢主龙骨TB24X38,间距≤1200,用吸顶吊件联结 5、龙骨吸顶吊件,中距横向≤1200,纵向600,用膨胀螺栓与钢筋砼板固定 6、现浇钢筋混凝土板底原浆抹平 7、其他：该项包含本项工作所有工作内容含垂直运输机械等，未详尽列举特征，详见施工图纸、设计规范、施工方案事项均包含在综合单价中。 | D31: 1.基层处理; 2.吊杆及预埋件焊接或后置紧固件连接； 3.龙骨安装； 4.填充50mm厚超细玻璃丝棉吸声层； 5.穿孔铝合金饰面板安装； 6.材料的运输、堆码、清运及场内多次搬运； 7.单价已包括送样的材料费用、检验、试验等工作; 8.配合安装队伍进行多次预留预埋及相关开槽、开洞的修补工作； 9.对已施工完成的成品及其他专业已完成的成品进行保护工作，无论是否由该单位导致的损坏，该单位都应履行修复处理责任； 10.对施工需要拆除或移动的材料，待施工完毕后，恢复原状； 11.完成工作区域的安全文明施工,清理施工遗留下的垃圾； 12.该项包含本项工作所有工作内容含垂直运输机械等，未详尽列举特征，详见施工图纸、设计规范、施工方案事项均包含在综合单价中。 | E31: m2 | F31: 79.5 | G31: 121.02 | H31: =ROUND(F31*G31,2) -> 9621.09 | I31: =巴南三标段!I26 -> 201.6 | J31: =F31*I31 -> 16027.2 | K31: 按设计图示尺寸以水平投影面积计算。 | L31: 1、除型钢龙骨及甲供材外全费用综合单价； 2、甲供材：铝板 | Q31: =N31+O31+P31 -> 0 | R31: =Q31*$R$4 -> 0
A32: 26 | B32: 软膜灯棚(白色) | C32: 软膜灯带安装 | D32: 1、基层清理，弹线定位。 2、基层龙骨，基层板安装 3、安装透光灯膜 4、该项包含本项工作所有工作内容含垂直运输机械等，未详尽列举特征，详见施工图纸、设计规范、施工方案事项均包含在综合单价中。 | E32: m2 | F32: 10.27 | G32: 220 | H32: =ROUND(F32*G32,2) -> 2259.4 | I32: =南川一标段!$I$53 -> 360 | J32: =F32*I32 -> 3697.2 | K32: 按设计图示尺寸以水平投影面积计算。 | L32: 此项工作的全费用综合单价 | Q32: =N32+O32+P32 -> 0 | R32: =Q32*$R$4 -> 0
A33: 27 | B33: 吊顶转换层 | C33: 吊顶转换层 | D33: 1.镀锌型钢龙骨转换层、骨架的制作、运输、安装、刷漆 2.该项包含本项工作所有工作内容含垂直运输机械等，未详尽列举特征，详见施工图纸、设计规范、施工方案事项均包含在综合单价中。 | E33: t | F33: 29.89 | G33: 8726.4 | H33: =ROUND(F33*G33,2) -> 260832.1 | I33: =南川一标段!$I$47 -> 10536 | J33: =F33*I33 -> 314921.04 | K33: 按设计图示尺寸以实际安装根数以重量计算 | L33: 此项工作的全费用综合单价 | Q33: =N33+O33+P33 -> 0 | R33: =Q33*$R$4 -> 0
A34: 28 | B34: 干挂型钢龙骨 | C34: 1、石材、铝板墙面龙骨、埋板等； 2、骨架种类、规格：具体规格、尺寸、连接方式详见图纸； | D34: 1.镀锌型钢龙骨转换层、骨架的制作、运输、安装、刷漆 2.该项包含本项工作所有工作内容含垂直运输机械等，未详尽列举特征，详见施工图纸、设计规范、施工方案事项均包含在综合单价中。 | E34: t | F34: 68.61 | G34: 8726.4 | H34: =ROUND(F34*G34,2) -> 598718.3 | I34: =南川一标段!$I$48 -> 10536 | J34: =F34*I34 -> 722874.96 | K34: 按设计图示尺寸以实际安装根数以重量计算 | L34: 此项工作的全费用综合单价 | Q34: =N34+O34+P34 -> 0 | R34: =Q34*$R$4 -> 0
A35: 29 | B35: 天棚喷刷深灰色涂料 | C35: 1、基层类型：砼天棚；2、深灰A级无机涂料喷涂，厚度、装饰效果满足设计要求3、超高增加的措施费用 | D35: [工作内容] 1.基层清理 2.刮腻子 3.刷、喷涂料 4.该项包含本项工作所有工作内容含垂直运输机械等，未详尽列举特征，详见施工图纸、设计规范、施工方案事项均包含在综合单价中。 | E35: m2 | F35: 1458.44 | G35: 12.89 | H35: =ROUND(F35*G35,2) -> 18799.29 | I35: =南川一标段!$I$34 -> 24.6 | J35: =F35*I35 -> 35877.62 | K35: 按设计图示尺寸以面积计算。 | L35: 此项工作的全费用综合单价 | Q35: =N35+O35+P35 -> 0 | R35: =Q35*$R$4 -> 0
A36: 30 | B36: 洗漱台 | C36: 1、部位：具体详设计图纸要求； 2、石材规格：综合详见图纸； 3、2.5mm铝单板挡板 4、台面、挡水 5、其它：满足设计规范及图纸要求。 | D36: [工作内容] 1.台面及支架运输、安装 2.杆、环、盒、配件安装 3.刷油漆 | E36: m | F36: 18.24 | G36: 420.78 | H36: =ROUND(F36*G36,2) -> 7675.03 | I36: =南川一标段!$I$35 -> 639.9 | J36: =F36*I36 -> 11671.78 | K36: 按设计图示尺寸长度以“米”计量。 | L36: 除基层龙骨外，此项工作的全费用综合单价 | Q36: =N36+O36+P36 -> 0 | R36: =Q36*$R$4 -> 0
A37: 31 | B37: 镜面玻璃 | C37: 1.30*30mm方管龙骨（刷防火、防腐） 2.6mm厚双层硅酸钙板基层（涂刷防腐） 3.5mm厚银镜及安装。 4.顶部及底部LED贴片灯带、灯槽制作安装 5.不锈钢边框包边；6.完成该项工作所需的全部工作内容 | D37: [工作内容] 1.基层安装 2.玻璃及框制作、运输、安装 | E37: m2 | F37: 25.73 | G37: 220 | H37: =ROUND(F37*G37,2) -> 5660.6 | I37: =南川一标段!$I$36 -> 526.8 | J37: =F37*I37 -> 13554.56 | K37: 按设计图示尺寸以面积计算。 | L37: 除基层龙骨外，此项工作的全费用综合单价 | Q37: =N37+O37+P37 -> 0 | R37: =Q37*$R$4 -> 0
A38: 32 | B38: 蹲位隔断 | C38: 1.50*4不锈钢角码固定隔板，膨胀螺丝与墙面固定 2.20mm厚金属复合板制作安装，含不锈钢挂衣钩固定安装； 3.复合板面不锈钢把手、不锈钢锁（红绿）隔门不锈钢合页安装； 4.隔板交接处50*4不锈钢角码纵向安装，专用平头螺丝固定，隔板与地面交接位置装100mm高不锈钢踢脚，防水胶嵌缝，2mm厚不锈钢U形抵扣封边； 5.未尽部分详见图纸； 6.完成该项工作所需的全部工作内容，完成工作区域的安全文明施工,清理施工遗留下的垃圾。 | D38: [工作内容] 1.隔断运输、安装 2.嵌缝、塞口 3.该项包含本项工作所有工作内容含垂直运输机械等，未详尽列举特征，详见施工图纸、设计规范、施工方案事项均包含在综合单价中。 | E38: 间 | F38: 15 | G38: 1250 | H38: =ROUND(F38*G38,2) -> 18750 | I38: =南川一标段!$I$37 -> 3490.32 | J38: =F38*I38 -> 52354.8 | K38: 以间计量，按设计间的数量计算。 | L38: 除基层龙骨外，此项工作的全费用综合单价 | M38: 市场不含税成本单价385元一平米，平均每个蹲位7.46㎡， | Q38: =N38+O38+P38 -> 0 | R38: =Q38*$R$4 -> 0
A39: 33 | B39: 小便斗隔板 | C39: 1.50*4不锈钢角码固定隔板，膨胀螺丝与墙面固定 2.20mm厚金属复合板制作安装 3.完成该项工作所需的全部工作内容，完成工作区域的安全文明施工,清理施工遗留下的垃圾。 | D39: [工作内容] 1.隔断运输、安装 2.嵌缝、塞口 3.该项包含本项工作所有工作内容含垂直运输机械等，未详尽列举特征，详见施工图纸、设计规范、施工方案事项均包含在综合单价中。 | E39: 间 | F39: 5 | G39: 184.36 | H39: =ROUND(F39*G39,2) -> 921.8 | I39: =南川一标段!$I$38 -> 254.09 | J39: =F39*I39 -> 1270.45 | K39: 以间计量，按设计间的数量计算。 | L39: 此项工作的全费用综合单价 | Q39: =N39+O39+P39 -> 0 | R39: =Q39*$R$4 -> 0
A40: 34 | B40: 卫生纸盒 | C40: 1、成品304#不锈钢嵌入纸巾盒（抽纸盒垃圾箱一体）2、完成该项工作所需的全部工作内容，完成工作区域的安全文明施工,清理施工遗留下的垃圾。 | D40: [工作内容] 1.台面及支架制作、运输、安装 2.杆、环、盒、螺栓等配件安装 3.刷油漆 4.该项包含本项工作所有工作内容含垂直运输机械等，未详尽列举特征，详见施工图纸、设计规范、施工方案事项均包含在综合单价中。 | E40: 个 | F40: 17 | G40: 12.6 | H40: =ROUND(F40*G40,2) -> 214.2 | I40: =南川一标段!$I$39 -> 72.6 | J40: =F40*I40 -> 1234.2 | K40: 按设计图示数量计算。 | L40: 此项工作的全费用综合单价 | Q40: =N40+O40+P40 -> 0 | R40: =Q40*$R$4 -> 0
A41: 35 | B41: 烘手器 | C41: 1、成品烘手器安装；2.完成该项工作所需的全部工作内容，完成工作区域的安全文明施工,清理施工遗留下的垃圾。 | D41: [工作内容] 1.台面及支架制作、运输、安装 2.杆、环、盒、配件安装 3.刷油漆 4.该项包含本项工作所有工作内容含垂直运输机械等，未详尽列举特征，详见施工图纸、设计规范、施工方案事项均包含在综合单价中。 | E41: 副 | F41: 7 | G41: 265 | H41: =ROUND(F41*G41,2) -> 1855 | I41: =南川一标段!$I$40 -> 369 | J41: =F41*I41 -> 2583 | K41: 按设计图示数量计算。 | L41: 此项工作的全费用综合单价 | Q41: =N41+O41+P41 -> 0 | R41: =Q41*$R$4 -> 0
A42: 36 | B42: 小便池石材台面 | C42: 1.30*30*3镀锌方管龙骨（刷防火、防腐） 2.人造石台面及侧台面安装，接缝处防水处理；3.完成该项工作所需的全部工作内容，完成工作区域的安全文明施工,清理施工遗留下的垃圾。 | D42: [工作内容] 1.基层清理 2.抹找平层 3.窗台板制作、安装 4.该项包含本项工作所有工作内容含垂直运输机械等，未详尽列举特征，详见施工图纸、设计规范、施工方案事项均包含在综合单价中。 | E42: m2 | F42: 1.2 | G42: 517.56 | H42: =ROUND(F42*G42,2) -> 621.07 | I42: =南川一标段!$I$41 -> 660 | J42: =F42*I42 -> 792 | K42: 按设计图示尺寸以面积计算。 | L42: 除基层龙骨外，此项工作的全费用综合单价 | Q42: =N42+O42+P42 -> 0 | R42: =Q42*$R$4 -> 0
A43: 37 | B43: 1.1米高玻璃栏板 | C43: 1.1米高玻璃栏板 | D43: [工作内容] 1.制作 2.运输 3.安装 4.刷防护材料 5.该项包含本项工作所有工作内容含垂直运输机械等，未详尽列举特征，详见施工图纸、设计规范、施工方案事项均包含在综合单价中。 | E43: m | F43: 6.94 | G43: 692.73 | H43: =ROUND(F43*G43,2) -> 4807.55 | I43: =南川一标段!$I$42 -> 986.77 | J43: =F43*I43 -> 6848.18 | K43: 按设计图示以扶手中心线长度计算。 | L43: 此项工作的全费用综合单价 | Q43: =N43+O43+P43 -> 0 | R43: =Q43*$R$4 -> 0
A44: 38 | B44: 2.2米高玻璃栏板 | C44: 主次龙骨50*50*5镀锌方管、埋板等 | D44: [工作内容] 1.制作 2.运输 3.安装 4.刷防护材料 5.该项包含本项工作所有工作内容含垂直运输机械等，未详尽列举特征，详见施工图纸、设计规范、施工方案事项均包含在综合单价中。 | E44: m | F44: 24 | G44: 1377.88 | H44: =ROUND(F44*G44,2) -> 33069.12 | I44: =南川一标段!$I$43 -> 1879.54 | J44: =F44*I44 -> 45108.96 | K44: 按设计图示以扶手中心线长度计算。 | L44: 此项工作的全费用综合单价 | Q44: =N44+O44+P44 -> 0 | R44: =Q44*$R$4 -> 0
A45: 39 | B45: 玻璃幕墙防撞杆 | C45: 1、玻璃幕墙防撞杆 2、H=250mm | D45: [工作内容] 1.制作 2.运输 3.安装 4.刷防护材料 | E45: m | F45: 39.2 | G45: 71.24 | H45: =ROUND(F45*G45,2) -> 2792.61 | I45: =南川一标段!$I$44 -> 109.6 | J45: =F45*I45 -> 4296.32 | K45: 按设计图示以扶手中心线长度计算。 | L45: 此项工作的全费用综合单价 | Q45: =N45+O45+P45 -> 0 | R45: =Q45*$R$4 -> 0
A46: 40 | B46: 定制金属屏风隔断仿铜不锈钢 | C46: 定制金属屏风隔断仿铜不锈钢 | D46: [工作内容] 1.制作 2.运输 3.安装 4.刷防护材料 | E46: m2 | F46: 51.59 | G46: 490 | H46: =ROUND(F46*G46,2) -> 25279.1 | I46: =R46 -> 1075.27 | J46: =F46*I46 -> 55473.18 | K46: 按设计图示尺寸以面积计算。 | L46: 此项工作的全费用综合单价 | N46: =主材表!L43 -> 761.06 | O46: 15 | P46: 120 | Q46: =N46+O46+P46 -> 896.06 | R46: =Q46*$R$4 -> 1075.27
A47: 41 | B47: 铝单板门套 | C47: 1、部位：综合考虑，有门、无门部位均按此项计算 2、墙体类型：砼、砖墙综合考虑； 3、骨架种类、规格：型材，规格详见设计图纸，间距应满足施工要求并由投标人综合考虑； 4、面层材料种类、规格：不锈钢； 5、嵌缝、打胶； 6、具体要求详设计图纸 7、根据安装需要开孔 | D47: 1、后置件、骨架的制作、运输、安装；2、铝板下料，安装；3、嵌缝、打胶；4.该项包含本项工作所有工作内容含垂直运输机械等，未详尽列举特征，详见施工图纸、设计规范、施工方案事项均包含在综合单价中。 | E47: m2 | F47: 35.85 | G47: 110 | H47: =ROUND(F47*G47,2) -> 3943.5 | I47: =南川一标段!$I$46 -> 226.2 | J47: =F47*I47 -> 8109.27 | K47: 按设计图示尺寸以室外可视铝板面积进行计算 | L47: 除基层龙骨及甲供材外，此项工作的全费用综合单价 | M47: 同干挂铝板墙面单价 | Q47: =N47+O47+P47 -> 0 | R47: =Q47*$R$4 -> 0
A48: 42 | B48: 100mm不锈钢收口线条 | C48: 100mm不锈钢收口线条 | D48: [工作内容] 1.制作 2.运输 3.安装 4.刷防护材料 | E48: m | F48: 6 | G48: 14.65 | H48: =ROUND(F48*G48,2) -> 87.9 | I48: =R48 -> 66 | J48: =F48*I48 -> 396 | K48: 按设计图示尺寸以长度计算。 | L48: 此项工作的全费用综合单价 | N48: =385*0.1 -> 38.5 | O48: 1.5 | P48: 15 | Q48: =N48+O48+P48 -> 55 | R48: =Q48*$R$4 -> 66
A49: 43 | B49: 50mm不锈钢收口线条 | C49: 50mm不锈钢收口线条 | D49: [工作内容] 1.制作 2.运输 3.安装 4.刷防护材料 | E49: m | F49: 3 | G49: 14.65 | H49: =ROUND(F49*G49,2) -> 43.95 | I49: =R49 -> 39.3 | J49: =F49*I49 -> 117.9 | K49: 按设计图示尺寸以长度计算。 | L49: 此项工作的全费用综合单价 | N49: =385*0.05 -> 19.25 | O49: 1.5 | P49: 12 | Q49: =N49+O49+P49 -> 32.75 | R49: =Q49*$R$4 -> 39.3
A50: 44 | B50: 仿铜不锈钢装饰线条10+50+10 | C50: 仿铜不锈钢装饰线条10+50+10 | D50: [工作内容] 1.制作 2.运输 3.安装 4.刷防护材料 | E50: m | F50: 18.2 | G50: 14.65 | H50: =ROUND(F50*G50,2) -> 266.63 | I50: =R50 -> 48.54 | J50: =F50*I50 -> 883.43 | K50: 按设计图示尺寸以长度计算。 | L50: 此项工作的全费用综合单价 | N50: =385*0.07 -> 26.95 | O50: 1.5 | P50: 12 | Q50: =N50+O50+P50 -> 40.45 | R50: =Q50*$R$4 -> 48.54
A51: 45 | B51: 仿铜不锈钢装饰线条30+80+50+10 | C51: 仿铜不锈钢装饰线条30+80+50+10 | D51: [工作内容] 1.制作 2.运输 3.安装 4.刷防护材料 | E51: m | F51: 25 | G51: 14.65 | H51: =ROUND(F51*G51,2) -> 366.25 | I51: =R51 -> 99.36 | J51: =F51*I51 -> 2484 | K51: 按设计图示尺寸以长度计算。 | L51: 此项工作的全费用综合单价 | N51: =385*0.18 -> 69.3 | O51: 1.5 | P51: 12 | Q51: =N51+O51+P51 -> 82.8 | R51: =Q51*$R$4 -> 99.36
A52: 46 | B52: 10MM不锈钢收口-装饰线条 | C52: 10MM不锈钢收口-装饰线条 | D52: [工作内容] 1.制作 2.运输 3.安装 4.刷防护材料 | E52: m | F52: 8.52 | G52: 14.65 | H52: =ROUND(F52*G52,2) -> 124.82 | I52: =R52 -> 26.46 | J52: =F52*I52 -> 225.44 | K52: 按设计图示尺寸以长度计算。 | L52: 此项工作的全费用综合单价 | N52: =385*0.03 -> 11.55 | O52: 0.5 | P52: 10 | Q52: =N52+O52+P52 -> 22.05 | R52: =Q52*$R$4 -> 26.46
A53: 47 | B53: 金属扶手、栏杆、栏板-1.1米高不锈钢栏杆 | C53: 1.1米高不锈钢栏杆 | D53: 1.预埋件制作、运输、埋设安装； 2.栏杆制作、运输、安装、防护； 3.综合单价含送样的材料费用、检验、试验等费用; 4.材料的运输、摆放、清运及场内多次搬运； 5.对已施工完成的成品及其他专业已完成的成品进行保护工作，无论是否由该单位导致的损坏，该单位都应履行修复处理责任； 6.对施工需要拆除或移动的材料，待施工完毕后，恢复原状； 7.完成工作区域的安全文明施工,清理施工遗留下的垃圾。 | E53: m | F53: 7.64 | G53: 423.09 | H53: =ROUND(F53*G53,2) -> 3232.41 | I53: =南川一标段!$I$109 -> 493.81 | J53: =F53*I53 -> 3772.71 | K53: 按设计图示以扶手中心线长度计算。 | L53: 此项工作的全费用综合单价 | Q53: =N53+O53+P53 -> 0 | R53: =Q53*$R$4 -> 0
A54: 48 | B54: 服务台 | C54: [工作内容] 1.台柜制作、运输、安装(安放) 2.刷防护材料、油漆 3.五金件安装 | D54: [工作内容] 1.台面及支架运输、安装 2.杆、环、盒、配件安装 3.刷油漆 4.该项包含本项工作所有工作内容含垂直运输机械等，未详尽列举特征，详见施工图纸、设计规范、施工方案事项均包含在综合单价中。 | E54: m | F54: 7.1 | G54: 4522.11 | H54: =ROUND(F54*G54,2) -> 32106.98 | I54: =南川一标段!$I$50 -> 2109 | J54: =F54*I54 -> 14973.9 | K54: 按设计图示以中心线长度计算 | L54: 此项工作的全费用综合单价 | Q54: =N54+O54+P54 -> 0 | R54: =Q54*$R$4 -> 0
A55: 49 | B55: 残疾人扶手 | C55: 残疾人扶手 | D55: 1.台面及支架运输、安装 2.杆、环、盒、配件安装 3.刷油漆 4.该项包含本项工作所有工作内容含垂直运输机械等，未详尽列举特征，详见施工图纸、设计规范、施工方案事项均包含在综合单价中。 | E55: 副 | F55: 3 | G55: 123.99 | H55: =ROUND(F55*G55,2) -> 371.97 | I55: =南川一标段!$I$49 -> 270.6 | J55: =F55*I55 -> 811.8 | K55: 按设计图示以数量计算。 | L55: 此项工作的全费用综合单价 | Q55: =N55+O55+P55 -> 0 | R55: =Q55*$R$4 -> 0
A56: 50 | B56: 挡烟垂壁 | C56: 1、L50*5镀锌角钢型钢龙骨；2、3mm钢U型卡槽（L=100）,M6*45不锈钢螺栓固定，单片玻璃不少于2处挂点；3、6mm钢化透明防火玻璃分格；4、玻璃高度为1200~1500mm高，出吊顶不低于800mm金属边收口；5、材料的水平及垂直转运（详见DQ-04-01） | D56: 1、L50*5镀锌角钢型钢龙骨；2、3mm钢U型卡槽（L=100）,M6*45不锈钢螺栓固定，单片玻璃不少于2处挂点；3、86mm钢化透明防火玻璃分格；4、玻璃高度为1200~1500mm高，出吊顶不低于800mm，金属边收口；5、材料的水平及垂直转运（详见DQ-04-01） 6、该项包含本项工作所有工作内容含垂直运输机械等，未详尽列举特征，详见施工图纸、设计规范、施工方案事项均包含在综合单价中。 | E56: m | F56: 7.2 | G56: 927.4 | H56: =ROUND(F56*G56,2) -> 6677.28 | I56: =R56 -> 650.7 | J56: =F56*I56 -> 4685.04 | K56: 按设计图示以扶手中心线长度计算。 | L56: 此项工作的全费用综合单价 | N56: =165*1.5+385*0.1*1.5 -> 305.25 | O56: =62+15 -> 77 | P56: 160 | Q56: =N56+O56+P56 -> 542.25 | R56: =Q56*$R$4 -> 650.7
A57: 51 | B57: 防火玻璃隔断（旅客服务房间） | C57: 1、施工部位：旅客服务室外围隔断； 2、面层材料：8HS+1.52PVB+8HS（low-e）+12Ar+27mm全超白中空夹胶防火玻璃（A类，1小时防火），具体施工要求与细部分格等详见图纸及方案，包含通长支座、副框、扣盖、压板、压块、垫块、连接件等，不同规格的钢板等； 3、底部塞防火岩棉、外包1.5mm厚镀锌钢板； 4、底部及顶部采用通长钢U槽连接； 5、接缝、嵌缝及塞口材料：泡沫棒、结构密封胶、耐候密封胶、EPDM胶条、防火胶条等详图纸及方案要求； 6、所有保温防火封堵、不锈钢自攻钉、不锈钢销钉、不锈钢螺栓、断热条、防脱螺钉、硬质玻璃垫块、钢托板、φ12压力间隔套等其他所有辅材需满足图纸及方案要求，其施工费及材料费等均已含在综合单价中； 7、与其他装饰面收口打胶； | D57: 1、防火岩棉及镀锌钢板的制作、运输、安装；2、型材的制作、运输、安装；3、玻璃安装；4、嵌缝、塞口；5、清洗；6、施工区域的安全文明施工；7、该项包含本项工作所有工作内容，未详尽列举的图纸、方案事项均包含在综合单价中 | E57: m2 | F57: 59.04 | G57: 1429.33 | H57: =ROUND(F57*G57,2) -> 84387.64 | I57: =南川一标段!$I$45 -> 1243.27 | J57: =F57*I57 -> 73402.66 | K57: 按设计图示尺寸以面积计算 | L57: 全费用综合单价 | Q57: =N57+O57+P57 -> 0 | R57: =Q57*$R$4 -> 0
A58: 52 | B58: 母婴设施 | C58: 成品母婴设备安装，完成该项工作所需的全部工作内容，完成工作区域的安全文明施工,清理施工遗留下的垃圾。 | D58: [工作内容] 1.台面及支架运输、安装 2.杆、环、盒、配件安装 3.刷油漆 | E58: 副 | F58: 1 | G58: 16920 | H58: =ROUND(F58*G58,2) -> 16920 | I58: =南川一标段!$I$51 -> 20304 | J58: =F58*I58 -> 20304 | K58: 按设计图示个数以套计算 | L58: 此项工作的全费用综合单价 | Q58: =N58+O58+P58 -> 0 | R58: =Q58*$R$4 -> 0
A59: 53 | B59: 电缆沟盖板 | C59: 施工部位：变电所 6mm花纹钢板 | D59: [工作内容] 1.盖板制作、运输、安装 | E59: m2 | F59: 14.24 | G59: 300 | H59: =ROUND(F59*G59,2) -> 4272 | I59: =南川一标段!$I$56 -> 346.13 | J59: =F59*I59 -> 4928.89 | K59: 按设计图纸尺寸以面积计算 | L59: 此项工作的全费用综合单价 | Q59: =N59+O59+P59 -> 0 | R59: =Q59*$R$4 -> 0
A60: 54 | B60: 线性灯槽 | C60: LED灯带制作安装 | D60: [工作内容] 1、LED灯带制作、安装 2、工作内容，未详尽列举特征，详见施工图纸、设计规范、施工方案事项均包含在综合单价中。 | E60: m | F60: 26 | G60: 20 | H60: =ROUND(F60*G60,2) -> 520 | I60: =南川一标段!$I$55 -> 65.04 | J60: =F60*I60 -> 1691.04 | K60: 按设计图示尺寸以米计算。 | L60: 全费用综合单价 | Q60: =N60+O60+P60 -> 0 | R60: =Q60*$R$4 -> 0
A61: 55 | B61: 2.5mm木色铝单板灯带 | C61: 1、2.5厚木色铝合金单板与配套专用龙骨固定 2、与铝合金单板配套的专用下层副龙骨联结,间距≤600 3、与安装型式配套的专用上层主龙骨,间距≤1200,用吊件与钢筋吊杆联结后找平 4、10号镀锌低碳钢丝(或%%C8钢筋)吊杆,双向中距≤1200,吊杆上部与板底预留吊环固定 5、现浇钢筋混凝土板底预留%%C10钢筋吊环,双向中距≤1200 6、顶棚伸缩缝、变形缝； 其他：该项包含本项工作所有工作内容含垂直运输机械等，未详尽列举特征，详见施工图纸、设计规范、施工方案事项均包含在综合单价中。 | D61: 1.基层处理； 2.龙骨、吊杆安装； 4.铝合金条板面层安装； 5.材料的运输、堆码、清运及场内多次搬运； 6.单价已包括送样的材料费用、检验、试验等工作; 7.配合安装队伍进行多次预留预埋及相关开槽、开洞的修补工作； 8.对已施工完成的成品及其他专业已完成的成品进行保护工作，无论是否由该单位导致的损坏，该单位都应履行修复处理责任； 9.对施工需要拆除或移动的材料，待施工完毕后，恢复原状； 10.完成工作区域的安全文明施工,清理施工遗留下的垃圾。 11.该项包含本项工作所有工作内容含垂直运输机械等，未详尽列举特征，详见施工图纸、设计规范、施工方案事项均包含在综合单价中。 | E61: m2 | F61: 185.2 | G61: 125 | H61: =ROUND(F61*G61,2) -> 23150 | I61: =南川一标段!$I$31 -> 182.4 | J61: =F61*I61 -> 33780.48 | K61: 按设计图示尺寸以水平投影面积计算。 | L61: 除型钢龙骨及甲供材外，此项工作的全费用综合单价 甲供材：铝单板 | Q61: =N61+O61+P61 -> 0 | R61: =Q61*$R$4 -> 0
A62: 56 | B62: 风口百叶 | C62: （1）面板：铝合金百叶； （2）龙骨及连接件：详见施工方案及图纸要求； （3）密封胶：详见施工方案及图纸要求； （4）完成本项目的所需的材料及相应的工序(包括但不限于加工制作、储运、安装、嵌缝、塞口、清洗、试验检测等内容） （5）未详尽列举特征，详见设计图纸、设计规范、施工方案。 | D62: （1）百叶窗安装、防虫网安装，百叶喷涂氟碳漆 （2）包含基层处理（打磨找补清理）、成品保护、负责工作区域的安全文明施工,施工遗留垃圾的清理及外运等； （3）含材料费管理费、措施费、夜间施工费、赶工措施费、安全文明施工费、规费、税金、临近既有线施工费用以及可能出现的人员窝工及机械停滞费用等施工所发生的一切费用 （4）其他未尽事宜详见招标文件技术要求及图纸 | E62: m2 | F62: 5.4 | G62: 367.83 | H62: =ROUND(F62*G62,2) -> 1986.28 | I62: =南川一标段!$I$59 -> 510 | J62: =F62*I62 -> 2754 | K62: 按百叶窗的垂直投影面积进行计算 | L62: 全费用综合单价 | Q62: =N62+O62+P62 -> 0 | R62: =Q62*$R$4 -> 0
A63: 57 | B63: 排水沟盖板 | C63: 1、5mm厚钢板预埋 2、20mm厚橡胶胶垫 3、花岗石水篦子铺面 | D63: [工作内容] 1、预埋板制作、安装 2、脚垫安装嵌缝、塞口 3、石材水篦子面板安装 4、该项包含本项工作所有工作内容含垂直运输机械等，未详尽列举特征，详见施工图纸、设计规范、施工方案事项均包含在综合单价中。 | E63: m | F63: 86 | G63: 340 | H63: =ROUND(F63*G63,2) -> 29240 | I63: =南川一标段!$I$58 -> 78 | J63: =F63*I63 -> 6708 | K63: 按设计图示尺寸以米计算。 | L63: 除甲供材外，此项工作的全费用综合单价 甲供材：花岗石 | Q63: =N63+O63+P63 -> 0 | R63: =Q63*$R$4 -> 0
A64: （二） | B64: 地下通道区域
A65: 1 | B65: 花岗石楼面 | C65: 1、25厚磨光花岗石,水泥浆擦缝; 2、30厚1:3干硬性水泥砂浆,表面撒水泥粉; 3、地面伸缩缝、变形缝的处理； 其他：该项包含本项工作所有工作内容含垂直运输机械等，未详尽列举特征，详见施工图纸、设计规范、施工方案事项均包含在综合单价中。 | D65: 1.清理基层，试排弹线，锯板磨边，调铺砂浆；铺板、灌缝擦缝、清理净面等全部操作过程； 2.找平层、结合层施工； 3.石材刷防护液、铺贴、水泥浆勾缝； 4.材料的运输、堆码、清运及场内多次搬运； 5.综合单价包含切角、倒角、磨边、加厚、弧形加工、嵌缝、拉槽、排版损耗、晶面处理等费用，送样的材料费用、检验、试验等工作费用，还包括地砖铺贴前排版图设计工作; 6.配合安装队伍进行多次预留预埋及相关开槽、开洞的修补工作； 7.对已施工完成的成品及其他专业已完成的成品进行保护工作，无论是否由该单位导致的损坏，该单位都应履行修复处理责任； 8.对施工需要拆除或移动的材料，待施工完毕后，恢复原状； 9.完成工作区域的安全文明施工,清理施工遗留下的垃圾； 10.该项包含本项工作所有工作内容含垂直运输机械等，未详尽列举特征，详见施工图纸、设计规范、施工方案事项均包含在综合单价中。 | E65: m2 | F65: 444.71 | G65: 85 | H65: =ROUND(F65*G65,2) -> 37800.35 | I65: =南川一标段!$I$7 -> 118.32 | J65: =F65*I65 -> 52618.09 | K65: 按设计图示尺寸以面积计算。 | L65: 1、除甲供材外全费用综合单价； 2、甲供材：石材 | Q65: =N65+O65+P65 -> 0 | R65: =Q65*$R$4 -> 0
A66: 2 | B66: 花岗石楼面--穿孔石材盖板 | C66: 1、5mm厚钢板预埋 2、20mm厚橡胶胶垫 3、花岗石水篦子铺面 | D66: [工作内容] 1、预埋板制作、安装 2、脚垫安装嵌缝、塞口 3、石材水篦子面板安装 4、该项包含本项工作所有工作内容含垂直运输机械等，未详尽列举特征，详见施工图纸、设计规范、施工方案事项均包含在综合单价中。 | E66: m2 | F66: 12.4 | G66: 85 | H66: =ROUND(F66*G66,2) -> 1054 | I66: =南川一标段!$I$7 -> 118.32 | J66: =F66*I66 -> 1467.17 | K66: 按设计图示尺寸以面积计算。 | L66: 1、除甲供材外全费用综合单价； 2、甲供材：石材 | Q66: =N66+O66+P66 -> 0 | R66: =Q66*$R$4 -> 0
A67: 3 | B67: 梯2花岗石梯面 | C67: 1、25厚花岗石(室外烧毛),同色水泥浆擦缝 2、25厚1:3干硬性水泥砂浆,表面撒水泥粉 3、素水泥浆一道(内掺建筑胶)，挡水条制作 4、地面伸缩缝、变形缝的处理； 其他：该项包含本项工作所有工作内容含垂直运输机械等，未详尽列举特征，详见施工图纸、设计规范、施工方案事项均包含在综合单价中。 | D67: 1.清理基层，试排弹线，锯板磨边，调铺砂浆；铺板、灌缝擦缝、清理净面等全部操作过程； 2.找平层、结合层施工，挡水条制作； 3.石材铺贴、水泥浆勾缝； 4.材料的运输、堆码、清运及场内多次搬运； 5.综合单价包含切角、倒角、磨边、加厚、弧形加工、嵌缝、拉槽、排版损耗、晶面处理等费用，送样的材料费用、检验、试验等工作费用，还包括地砖铺贴前排版图设计工作; 6.配合安装队伍进行多次预留预埋及相关开槽、开洞的修补工作； 7.对已施工完成的成品及其他专业已完成的成品进行保护工作，无论是否由该单位导致的损坏，该单位都应履行修复处理责任； 8.对施工需要拆除或移动的材料，待施工完毕后，恢复原状； 9.完成工作区域的安全文明施工,清理施工遗留下的垃圾； 10.该项包含本项工作所有工作内容含垂直运输机械等，未详尽列举特征，详见施工图纸、设计规范、施工方案事项均包含在综合单价中。 | E67: m2 | F67: 131.46 | G67: 110 | H67: =ROUND(F67*G67,2) -> 14460.6 | I67: =南川一标段!$I$8 -> 160.32 | J67: =F67*I67 -> 21075.67 | K67: 按设计图示尺寸以展开面积计算 | L67: 1、除甲供材外全费用综合单价； 2、甲供材：石材 | Q67: =N67+O67+P67 -> 0 | R67: =Q67*$R$4 -> 0
A68: 4 | B68: 石材止灰带 | C68: 石材止灰带 | D68: 1.后置件 2.钢骨架 3.用石材胶粘贴石材 4.石材 5.六面刷界面处理剂，水泥浆檫缝 6.该项包含本项工作所有工作内容含垂直运输机械等，未详尽列举特征，详见施工图纸、设计规范、施工方案事项均包含在综合单价中。 | E68: m2 | F68: 45.37 | G68: 125 | H68: =ROUND(F68*G68,2) -> 5671.25 | I68: =南川一标段!$I$80 -> 228 | J68: =F68*I68 -> 10344.36 | K68: 按设计图示尺寸以展开面积计算。 | L68: 1、除甲供材外全费用综合单价； 2、甲供材：石材 | Q68: =N68+O68+P68 -> 0 | R68: =Q68*$R$4 -> 0
A69: 5 | B69: 25MM厚深灰麻过门石 | C69: 1、铺25厚磨光花岗石板(六面涂刷石材保护剂),同色稀水泥浆擦 2、50厚1:3干硬性水泥粘结层,撒素水泥粉 3、水泥浆一道(内掺建筑胶) 4、嵌缝材料种类：按甲方要求嵌缝、打胶； 5、防护层材料：防护剂六面处理，满足设计和相关规范要求； 6、酸洗、打蜡要求：满足设计和相关规范要求； 7、楼地面伸缩缝、变形缝的处理； 8、其他：该项包含本项工作所有工作内容含垂直运输机械等，未详尽列举特征，详见施工图纸、设计规范、施工方案事项均包含在综合单价中。 (石材规格800*800) | D69: 1.清理基层，试排弹线，锯板磨边，调铺砂浆；铺板、灌缝擦缝、清理净面等全部操作过程； 2.找平层、结合层施工； 3.石材铺贴、水泥浆勾缝； 4.材料的运输、堆码、清运及场内多次搬运； 5.综合单价包含切角、倒角、磨边、加厚、弧形加工、嵌缝、拉槽、排版损耗、晶面处理等费用，送样的材料费用、检验、试验等工作费用，还包括地砖铺贴前排版图设计工作; 6.配合安装队伍进行多次预留预埋及相关开槽、开洞的修补工作； 7.对已施工完成的成品及其他专业已完成的成品进行保护工作，无论是否由该单位导致的损坏，该单位都应履行修复处理责任； 8.对施工需要拆除或移动的材料，待施工完毕后，恢复原状； 9.完成工作区域的安全文明施工,清理施工遗留下的垃圾； 10.该项包含本项工作所有工作内容含垂直运输机械等，未详尽列举特征，详见施工图纸、设计规范、施工方案事项均包含在综合单价中。 | E69: m2 | F69: 2.02 | G69: 85 | H69: =ROUND(F69*G69,2) -> 171.7 | I69: =南川一标段!$I$16 -> 156 | J69: =F69*I69 -> 315.12 | K69: 按设计图示尺寸以面积计算。 | L69: 1、除甲供材外全费用综合单价； 2、甲供材：石材 | Q69: =N69+O69+P69 -> 0 | R69: =Q69*$R$4 -> 0
A70: 6 | B70: 干挂花岗岩墙面（含消防暗门） | C70: 1、干挂25mm厚石材墙面（含消防暗门） 2、石材背栓挂件,L50*5角钢连接件与横向龙骨(L50*5角钢)螺栓连接 3、L50*5角钢横向龙骨,与竖向槽钢(8#槽钢)焊接 4、8#槽钢,与连接件焊接, 5、连接件,与预埋件M3焊接 6、预埋件M3 7、墙面伸缩缝、变形缝的处理； 8、根据安装需要开孔 9、其他：该项包含本项工作所有工作内容含垂直运输机械等，未详尽列举特征，详见施工图纸、设计规范、施工方案事项均包含在综合单价中。； | D70: 1.墙体基层处理 2.预埋件埋设，安装型钢龙骨，将其固定在混凝土墙体上； 3.安装石材挂件，连接石材面层与龙骨； 4.安装好石材面层后，填缝，刷防护液； 5.材料的运输、堆码、清运及场内多次搬运； 6.综合单价包含切角、倒角、磨边、加厚、弧形加工、嵌缝、拉槽、排版损耗、晶面处理等费用，送样的材料费用、检验、试验等工作费用，还包括地砖铺贴前排版图设计工作; 7.配合安装队伍进行多次预留预埋及相关开槽、开洞的修补工作； 8.对已施工完成的成品及其他专业已完成的成品进行保护工作，无论是否由该单位导致的损坏，该单位都应履行修复处理责任； 9.对施工需要拆除或移动的材料，待施工完毕后，恢复原状； 10.完成工作区域的安全文明施工,清理施工遗留下的垃圾； 11.该项包含本项工作所有工作内容含垂直运输机械等，未详尽列举特征，详见施工图纸、设计规范、施工方案事项均包含在综合单价中。 | E70: m2 | F70: 663.18 | G70: 150 | H70: =ROUND(F70*G70,2) -> 99477 | I70: =南川一标段!$I$64 -> 255.6 | J70: =F70*I70 -> 169508.81 | K70: 按设计图示尺寸以面积计算（有吊顶房间算至吊顶底，无吊顶房间算至梁底或者板底） | L70: 除型钢龙骨及甲供材外，此项工作的全费用综合单价 | Q70: =N70+O70+P70 -> 0 | R70: =Q70*$R$4 -> 0
A71: 7 | B71: 铝合金单板装饰吊顶 | C71: 1、2.5厚铝合金单板与配套专用龙骨固定 2、与铝合金单板配套的专用下层副龙骨联结,间距≤600 3、与安装型式配套的专用上层主龙骨,间距≤1200,用吊件与钢筋吊杆联结后找平 4、10号镀锌低碳钢丝(或%%C8钢筋)吊杆,双向中距≤1200,吊杆上部与板底预留吊环固定 5、现浇钢筋混凝土板底预留%%C10钢筋吊环,双向中距≤1200 6、天棚伸缩缝、变形缝的处理； 7、根据安装需要开孔 8、其他：该项包含本项工作所有工作内容含垂直运输机械等，未详尽列举特征，详见施工图纸、设计规范、施工方案事项均包含在综合单价中。； | D71: 1.基层处理 2.轻钢龙骨、吊杆安装； 3.铝扣板安装、收边线； 4.材料的运输、堆码、清运及场内多次搬运； 5.单价已包括送样的材料费用、检验、试验等工作; 6.配合安装队伍进行多次预留预埋及相关开槽、开洞的修补工作； 7.对已施工完成的成品及其他专业已完成的成品进行保护工作，无论是否由该单位导致的损坏，该单位都应履行修复处理责任； 8.对施工需要拆除或移动的材料，待施工完毕后，恢复原状； 9.完成工作区域的安全文明施工,清理施工遗留下的垃圾； 10.该项包含本项工作所有工作内容含垂直运输机械等，未详尽列举特征，详见施工图纸、设计规范、施工方案事项均包含在综合单价中。 | E71: m2 | F71: 514.31 | G71: 120 | H71: =ROUND(F71*G71,2) -> 61717.2 | I71: =南川一标段!$I$31 -> 182.4 | J71: =F71*I71 -> 93810.14 | K71: 按设计图示尺寸以水平投影面积计算。 | L71: 1、除型钢龙骨及甲供材外全费用综合单价； 2、甲供材：铝板 | Q71: =N71+O71+P71 -> 0 | R71: =Q71*$R$4 -> 0
A72: 8 | B72: 无机涂料顶棚 | C72: 1、防火型无机耐擦洗涂料两道饰面(白色) 2、2厚面层耐水腻子刮平 3、其他：该项包含本项工作所有工作内容含垂直运输机械等，未详尽列举特征，详见施工图纸、设计规范、施工方案事项均包含在综合单价中。 | D72: 1.基层处理、甩浆； 2.满刮腻子找平、磨光； 4.防火型无机耐擦洗涂料两道饰面(； 5.材料的运输、堆码、清运及场内多次搬运； 6.单价已包括送样的材料费用、检验、试验等工作; 7.配合安装队伍进行多次预留预埋及相关开槽、开洞的修补工作； 8.对已施工完成的成品及其他专业已完成的成品进行保护工作，无论是否由该单位导致的损坏，该单位都应履行修复处理责任； 9.对施工需要拆除或移动的材料，待施工完毕后，恢复原状； 10.完成工作区域的安全文明施工,清理施工遗留下的垃圾。 11.该项包含本项工作所有工作内容含垂直运输机械等，未详尽列举特征，详见施工图纸、设计规范、施工方案事项均包含在综合单价中。 | E72: m2 | F72: 242.25 | G72: 32 | H72: =ROUND(F72*G72,2) -> 7752 | I72: =南川一标段!$I$20 -> 44.4 | J72: =F72*I72 -> 10755.9 | K72: 按设计图示尺寸以水平投影面积计算。 | L72: 此项工作的全费用综合单价 | Q72: =N72+O72+P72 -> 0 | R72: =Q72*$R$4 -> 0
A73: 9 | B73: 不锈钢靠墙扶手 | C73: 1.不锈钢靠墙扶手 2.其他：该项包含本项工作所有工作内容含垂直运输机械等，未详尽列举特征，详见施工图纸、设计规范、施工方案事项均包含在综合单价中。 | D73: 1.不锈钢扶手采购、运输、安装； 2.综合单价含送样的材料费用、检验、试验等工作; 3.材料的运输、摆放、清运及场内多次搬运； 4.对已施工完成的成品及其他专业已完成的成品进行保护工作，无论是否由该单位导致的损坏，该单位都应履行修复处理责任； 5.对施工需要拆除或移动的材料，待施工完毕后，恢复原状； 6.完成工作区域的安全文明施工,清理施工遗留下的垃圾； 7.该项包含本项工作所有工作内容含垂直运输机械等，未详尽列举特征，详见施工图纸、设计规范、施工方案事项均包含在综合单价中。 | E73: m | F73: 133.8 | G73: 108.95 | H73: =ROUND(F73*G73,2) -> 14577.51 | I73: =R73 -> 190.2 | J73: =F73*I73 -> 25448.76 | K73: 按设计图示以扶手中心线长度计算。 | L73: 此项工作的全费用综合单价 | N73: 115 | O73: 3.5 | P73: 40 | Q73: =N73+O73+P73 -> 158.5 | R73: =Q73*$R$4 -> 190.2
A74: 10 | B74: 线性灯槽 | C74: LED灯带制作安装 | D74: [工作内容] 1、LED灯带制作、安装 2、工作内容，未详尽列举特征，详见施工图纸、设计规范、施工方案事项均包含在综合单价中。 | E74: m | F74: 172 | G74: 20 | H74: =ROUND(F74*G74,2) -> 3440 | I74: =南川一标段!$I$55 -> 65.04 | J74: =F74*I74 -> 11186.88 | K74: 按设计图示尺寸以米计算。 | L74: 全费用综合单价 | Q74: =N74+O74+P74 -> 0 | R74: =Q74*$R$4 -> 0
A75: 11 | B75: 1.3米高玻璃栏板 | C75: 1、1.3米高玻璃栏板 2、玻璃栏板拉丝不锈钢矩管（渐变）80~63*40*4mm 3、玻璃栏板扶手φ63*3mm异形拉丝不锈钢圆管 4、玻璃栏板防撞栏杆φ51*3不锈钢圆管 5、玻璃栏板8+1.14PVB+8夹胶钢化玻璃 其他：该项包含本项工作所有工作内容含垂直运输机械等，未详尽列举特征，详见施工图纸、设计规范、施工方案事项均包含在综合单价中。 | D75: 1.预埋件制作、运输、埋设安装； 2.玻璃栏板制作、运输、安装、防护，安装驳接爪； 3.综合单价含栏板送样的材料费用、检验、试验等费用; 4.材料的运输、摆放、清运及场内多次搬运； 5.对已施工完成的成品及其他专业已完成的成品进行保护工作，无论是否由该单位导致的损坏，该单位都应履行修复处理责任； 6.对施工需要拆除或移动的材料，待施工完毕后，恢复原状； 7.完成工作区域的安全文明施工,清理施工遗留下的垃圾； 8.该项包含本项工作所有工作内容含垂直运输机械等，未详尽列举特征，详见施工图纸、设计规范、施工方案事项均包含在综合单价中。 | E75: m | F75: 569.61 | G75: 795.1 | H75: =ROUND(F75*G75,2) -> 452896.91 | I75: =南川一标段!$I$108 -> 1085.53 | J75: =F75*I75 -> 618328.74 | K75: 按设计图示以扶手中心线长度计算。 | L75: 此项工作的全费用综合单价 | Q75: =N75+O75+P75 -> 0 | R75: =Q75*$R$4 -> 0
A76: （三） | B76: 雨棚区域
A77: 1 | B77: 混凝土冲劲带 | C77: 1、站台外侧混凝土冲劲带浇筑； 2、冲劲带宽度200mm，高度110mm,具体详见图纸； 3、地面伸缩缝、变形缝的处理； 其它：垂直运输费用已包含在综合单价中，满足设计规范及图纸要求;未详尽列举特征，详见施工图纸、设计规范、施工方案 | D77: 1.清理基层清理净面等全部操作过程； 2.混凝土浇筑施工、养护、搓平，平整顺直； 3.材料的运输、堆码、清运及场内多次搬运； 4.综合单价包含送样的材料费用、检验、试验等工作费用，还包括地砖铺贴前排版图设计工作; 5.配合安装队伍进行多次预留预埋及相关开槽、开洞的修补工作； 6.对已施工完成的成品及其他专业已完成的成品进行保护工作，无论是否由该单位导致的损坏，该单位都应履行修复处理责任； 7.对施工需要拆除或移动的材料，待施工完毕后，恢复原状； 8.完成工作区域的安全文明施工,清理施工遗留下的垃圾； 9.该项包含本项工作所有工作内容含垂直运输机械等，未详尽列举特征，详见施工图纸、设计规范、施工方案事项均包含在综合单价中。 | E77: m | F77: =450*2 -> 900 | G77: 20 | H77: =ROUND(F77*G77,2) -> 18000 | I77: =南川一标段!$I$88 -> 71.88 | J77: =F77*I77 -> 64692 | K77: 按设计图示尺寸以延长米计算。 | L77: 除甲供材外，此项工作的全费用综合单价 甲供材：混凝土 | Q77: =N77+O77+P77 -> 0 | R77: =Q77*$R$4 -> 0
A78: 2 | B78: 站台盲道砖 | C78: 1、玻化砖安全线盲道砖面层; 2、5厚坐浆层; 3、45厚1:3干硬性水泥砂浆粘结层; 4、地面伸缩缝、变形缝的处理； 其它：垂直运输费用已包含在综合单价中，满足设计规范及图纸要求;未详尽列举特征，详见施工图纸、设计规范、施工方案 | D78: 1.清理基层，试排弹线，锯板磨边，调铺砂浆；铺板、灌缝擦缝、清理净面等全部操作过程； 2.找平层、结合层、坐浆层施工； 3.盲道砖铺贴、水泥浆勾缝； 4.材料的运输、堆码、清运及场内多次搬运； 5.综合单价包含切角、倒角、磨边、加厚、弧形加工、嵌缝、拉槽、排版损耗、晶面处理等费用，送样的材料费用、检验、试验等工作费用，还包括地砖铺贴前排版图设计工作; 6.配合安装队伍进行多次预留预埋及相关开槽、开洞的修补工作； 7.对已施工完成的成品及其他专业已完成的成品进行保护工作，无论是否由该单位导致的损坏，该单位都应履行修复处理责任； 8.对施工需要拆除或移动的材料，待施工完毕后，恢复原状； 9.完成工作区域的安全文明施工,清理施工遗留下的垃圾； 10.该项包含本项工作所有工作内容含垂直运输机械等，未详尽列举特征，详见施工图纸、设计规范、施工方案事项均包含在综合单价中。 | E78: m2 | F78: 540 | G78: 70 | H78: =ROUND(F78*G78,2) -> 37800 | I78: =南川一标段!$I$95 -> 96 | J78: =F78*I78 -> 51840 | K78: 按设计图示尺寸以面积计算。 | L78: 除甲供材外，此项工作的全费用综合单价 甲供材：盲道砖 | M78: 同站房石材铺装单价 | Q78: =N78+O78+P78 -> 0 | R78: =Q78*$R$4 -> 0
A79: 3 | B79: 站台安全线 | C79: 1、玻化砖安全线盲道砖面层; 2、5厚坐浆层; 3、45厚1:3干硬性水泥砂浆粘结层; 4、地面伸缩缝、变形缝的处理； 其它：垂直运输费用已包含在综合单价中，满足设计规范及图纸要求;未详尽列举特征，详见施工图纸、设计规范、施工方案 | D79: 1.清理基层，试排弹线，锯板磨边，调铺砂浆；铺板、灌缝擦缝、清理净面等全部操作过程； 2.找平层、结合层、坐浆层施工； 3.玻化砖安全线盲道砖铺贴、水泥浆勾缝； 4.材料的运输、堆码、清运及场内多次搬运； 5.综合单价包含切角、倒角、磨边、加厚、弧形加工、嵌缝、拉槽、排版损耗、晶面处理等费用，送样的材料费用、检验、试验等工作费用，还包括地砖铺贴前排版图设计工作； 6.配合安装队伍进行多次预留预埋及相关开槽、开洞的修补工作； 7.对已施工完成的成品及其他专业已完成的成品进行保护工作，无论是否由该单位导致的损坏，该单位都应履行修复处理责任； 8.对施工需要拆除或移动的材料，待施工完毕后，恢复原状； 9.完成工作区域的安全文明施工,清理施工遗留下的垃圾； 10.该项包含本项工作所有工作内容含垂直运输机械等，未详尽列举特征，详见施工图纸、设计规范、施工方案事项均包含在综合单价中。 | E79: m2 | F79: 90 | G79: 70 | H79: =ROUND(F79*G79,2) -> 6300 | I79: =南川一标段!$I$96 -> 96 | J79: =F79*I79 -> 8640 | K79: 按设计图示尺寸以面积计算。 | L79: 除甲供材外，此项工作的全费用综合单价 甲供材：盲道砖 | M79: 同站房石材铺装单价 | Q79: =N79+O79+P79 -> 0 | R79: =Q79*$R$4 -> 0
A80: 4 | B80: 站台帽石 | C80: 1、50厚红色花岗岩(磨光机刨6面满涂防护剂； 2、5厚坐浆层; 3、30厚1:3干硬性水泥砂浆粘结层; 4、地面伸缩缝、变形缝的处理； 其它：垂直运输费用已包含在综合单价中，满足设计规范及图纸要求;未详尽列举特征，详见施工图纸、设计规范、施工方案 | D80: 1.清理基层，试排弹线，锯板磨边，调铺砂浆；铺板、灌缝擦缝、清理净面等全部操作过程； 2.找平层、结合层、坐浆层施工； 3.红色花岗岩(磨光机刨6面满涂防护剂)； 4.材料的运输、堆码、清运及场内多次搬运； 5.综合单价包含切角、倒角、磨边、加厚、弧形加工、嵌缝、拉槽、排版损耗、晶面处理等费用，送样的材料费用、检验、试验等工作费用，还包括地砖铺贴前排版图设计工作； 6.配合安装队伍进行多次预留预埋及相关开槽、开洞的修补工作； 7.对已施工完成的成品及其他专业已完成的成品进行保护工作，无论是否由该单位导致的损坏，该单位都应履行修复处理责任； 8.对施工需要拆除或移动的材料，待施工完毕后，恢复原状； 9.完成工作区域的安全文明施工,清理施工遗留下的垃圾； 10.该项包含本项工作所有工作内容含垂直运输机械等，未详尽列举特征，详见施工图纸、设计规范、施工方案事项均包含在综合单价中。 | E80: m2 | F80: 899.9 | G80: 80 | H80: =ROUND(F80*G80,2) -> 71992 | I80: =南川一标段!$I$98 -> 118.32 | J80: =F80*I80 -> 106476.17 | K80: 按设计图示尺寸以面积计算。 | L80: 1、除甲供材外全费用综合单价； 2、甲供材：石材 | M80: 同站房石材铺装单价 | Q80: =N80+O80+P80 -> 0 | R80: =Q80*$R$4 -> 0
A81: 5 | B81: 第一站台石材铺面 | C81: 1、600x900 30厚白麻花岗岩(火烧6面满涂防护剂、; 2、5厚坐浆层; 3、30厚1:3干硬性水泥砂浆粘结层; 4、地面伸缩缝、变形缝的处理； 其它：垂直运输费用已包含在综合单价中，满足设计规范及图纸要求;未详尽列举特征，详见施工图纸、设计规范、施工方案 | D81: 1.清理基层，试排弹线，锯板磨边，调铺砂浆；铺板、灌缝擦缝、清理净面等全部操作过程； 2.找平层、结合层、坐浆层施工； 3.石材铺贴； 4.材料的运输、堆码、清运及场内多次搬运； 5.综合单价包含切角、倒角、磨边、加厚、弧形加工、嵌缝、拉槽、排版损耗、晶面处理等费用，送样的材料费用、检验、试验等工作费用，还包括地砖铺贴前排版图设计工作; 6.配合安装队伍进行多次预留预埋及相关开槽、开洞的修补工作； 7.对已施工完成的成品及其他专业已完成的成品进行保护工作，无论是否由该单位导致的损坏，该单位都应履行修复处理责任； 8.对施工需要拆除或移动的材料，待施工完毕后，恢复原状； 9.完成工作区域的安全文明施工,清理施工遗留下的垃圾； 10.该项包含本项工作所有工作内容含垂直运输机械等，未详尽列举特征，详见施工图纸、设计规范、施工方案事项均包含在综合单价中。 | E81: m2 | F81: 3665.99 | G81: 80 | H81: =ROUND(F81*G81,2) -> 293279.2 | I81: =南川一标段!$I$98 -> 118.32 | J81: =F81*I81 -> 433759.94 | K81: 按设计图示尺寸以面积计算。 | L81: 1、除甲供材外全费用综合单价； 2、甲供材：石材 | M81: 同站房石材铺装单价 | Q81: =N81+O81+P81 -> 0 | R81: =Q81*$R$4 -> 0
A82: 6 | B82: 第二站台石材铺面 | C82: 1、600x900 30厚白麻花岗岩(火烧6面满涂防护剂、 2、5厚坐浆层; 3、30厚1:3干硬性水泥砂浆粘结层; 4、地面伸缩缝、变形缝的处理； 其它：垂直运输费用已包含在综合单价中，满足设计规范及图纸要求;未详尽列举特征，详见施工图纸、设计规范、施工方案 | D82: 1.清理基层，试排弹线，锯板磨边，调铺砂浆；铺板、灌缝擦缝、清理净面等全部操作过程； 2.找平层、结合层、坐浆层施工； 3.石材铺贴； 4.材料的运输、堆码、清运及场内多次搬运； 5.综合单价包含切角、倒角、磨边、加厚、弧形加工、嵌缝、拉槽、排版损耗、晶面处理等费用，送样的材料费用、检验、试验等工作费用，还包括地砖铺贴前排版图设计工作； 6.配合安装队伍进行多次预留预埋及相关开槽、开洞的修补工作； 7.对已施工完成的成品及其他专业已完成的成品进行保护工作，无论是否由该单位导致的损坏，该单位都应履行修复处理责任； 8.对施工需要拆除或移动的材料，待施工完毕后，恢复原状； 9.完成工作区域的安全文明施工,清理施工遗留下的垃圾； 10.该项包含本项工作所有工作内容含垂直运输机械等，未详尽列举特征，详见施工图纸、设计规范、施工方案事项均包含在综合单价中。 | E82: m2 | F82: 3201.67 | G82: 80 | H82: =ROUND(F82*G82,2) -> 256133.6 | I82: =南川一标段!$I$98 -> 118.32 | J82: =F82*I82 -> 378821.59 | K82: 按设计图示尺寸以面积计算。 | L82: 1、除甲供材外全费用综合单价； 2、甲供材：石材 | M82: 同站房石材铺装单价 | Q82: =N82+O82+P82 -> 0 | R82: =Q82*$R$4 -> 0
A83: 7 | B83: 灰色氟碳漆踢脚 | C83: 1、清理基面:清理钢筋混凝土基面 2、基层处理:专用腻子找平、修复,厚度不大于5mm 3、灰色涂料底漆涂装:涂刷一遍 4、灰色涂料中涂涂装:涂刷一遍 5、面漆涂装:涂刷两遍 6、其它：垂直运输费用已包含在综合单价中，满足设计规范及图纸要求;未详尽列举特征，详见施工图纸、设计规范、施工方案 | D83: 1.墙体基层处理、找平抹灰、压实； 2.踢脚线制作、运输、安装，面砖背面涂专用粘接剂，用专用勾缝剂勾缝； 3.材料的运输、堆码、清运及场内多次搬运； 4.单价已包括送样的材料费用、检验、试验等工作; 5.配合安装队伍进行多次预留预埋及相关开槽、开洞的修补工作； 6.对已施工完成的成品及其他专业已完成的成品进行保护工作，无论是否由该单位导致的损坏，该单位都应履行修复处理责任； 7.对施工需要拆除或移动的材料，待施工完毕后，恢复原状； 8.完成工作区域的安全文明施工,清理施工遗留下的垃圾； 9.该项包含本项工作所有工作内容含垂直运输机械等，未详尽列举特征，详见施工图纸、设计规范、施工方案事项均包含在综合单价中。 | E83: m2 | F83: =50*3*0.15*2 -> 45 | G83: 23.5 | H83: =ROUND(F83*G83,2) -> 1057.5 | I83: =南川一标段!$I$99 -> 251.4 | J83: =F83*I83 -> 11313 | K83: 以平方米计量，按设计图示长度乘高度以面积计算； | L83: 此项工作的全费用综合单价 | Q83: =N83+O83+P83 -> 0 | R83: =Q83*$R$4 -> 0
A84: 8 | B84: 栏杆基础 | C84: 站台栏杆基础200*200 4C8主筋，箍筋C8-200，预埋件预埋 | D84: 1、钢筋绑扎、模板及支撑制作、安装、拆除、堆放、运输及清理模内杂物、刷隔离剂等； 2、混凝土制作、运输、浇筑、振捣、养护； 3、栏杆预埋件预埋 4、合同中明示或暗示的其他工作内容 | E84: m | F84: =F85+F86+F87 -> 945.1 | G84: =N84*50+(O84+P84)*0.9+0.4*1*50 -> 20 | H84: =ROUND(F84*G84,2) -> 18902 | I84: =南川一标段!$I$107 -> 67.8 | J84: =F84*I84 -> 64077.78 | K84: 按设计图示尺寸以长度计算 | L84: 1、除甲供材外全费用综合单价； 2、甲供材：钢筋、模板、混凝土 | Q84: =N84+O84+P84 -> 0 | R84: =Q84*$R$4 -> 0
A85: 9 | B85: 1.3米高玻璃栏板 | C85: 1、1.3米高玻璃栏板 2、玻璃栏板拉丝不锈钢矩管（渐变）80~63*40*4mm 3、玻璃栏板扶手φ63*3mm异形拉丝不锈钢圆管 4、玻璃栏板防撞栏杆φ51*3不锈钢圆管 5、玻璃栏板8+1.14PVB+8夹胶钢化玻璃 其它：垂直运输费用已包含在综合单价中，满足设计规范及图纸要求;未详尽列举特征，详见施工图纸、设计规范、施工方案 | D85: 1.预埋件制作、运输、埋设安装； 2.玻璃栏板制作、运输、安装、防护，安装驳接爪； 3.综合单价含栏板送样的材料费用、检验、试验等费用; 4.材料的运输、摆放、清运及场内多次搬运； 5.对已施工完成的成品及其他专业已完成的成品进行保护工作，无论是否由该单位导致的损坏，该单位都应履行修复处理责任； 6.对施工需要拆除或移动的材料，待施工完毕后，恢复原状； 7.完成工作区域的安全文明施工,清理施工遗留下的垃圾； 8.该项包含本项工作所有工作内容含垂直运输机械等，未详尽列举特征，详见施工图纸、设计规范、施工方案事项均包含在综合单价中 | E85: m | F85: 100.36 | G85: 795.1 | H85: =ROUND(F85*G85,2) -> 79796.24 | I85: =南川一标段!$I$108 -> 1085.53 | J85: =F85*I85 -> 108943.79 | K85: 按设计图示以扶手中心线长度计算。 | L85: 此项工作的全费用综合单价 | Q85: =N85+O85+P85 -> 0 | R85: =Q85*$R$4 -> 0
A86: 10 | B86: 1.3米高不锈钢栏杆 | C86: 1、立柱为76*3.5拉丝不锈钢钢管；2、扶手为76*2拉丝不锈钢钢管；3、水平向为50*30*2不锈钢复合管；4、竖向短管为25*1.5不锈钢复合管；5、预埋螺栓；6、材料的水平及垂直转运（详参图纸）7、其它：垂直运输费用已包含在综合单价中，满足设计规范及图纸要求;未详尽列举特征，详见施工图纸、设计规范、施工方案 | D86: 1.预埋件制作、运输、埋设安装； 2.栏杆制作、运输、安装、防护； 3.综合单价含送样的材料费用、检验、试验等费用; 4.材料的运输、摆放、清运及场内多次搬运； 5.对已施工完成的成品及其他专业已完成的成品进行保护工作，无论是否由该单位导致的损坏，该单位都应履行修复处理责任； 6.对施工需要拆除或移动的材料，待施工完毕后，恢复原状； 7.完成工作区域的安全文明施工,清理施工遗留下的垃圾； 8.该项包含本项工作所有工作内容含垂直运输机械等，未详尽列举特征，详见施工图纸、设计规范、施工方案事项均包含在综合单价中。 | E86: m | F86: 791.78 | G86: 612.28 | H86: =ROUND(F86*G86,2) -> 484791.06 | I86: =彭水二标段!$I$70 -> 690.28 | J86: =F86*I86 -> 546549.9 | K86: 按设计图示以扶手中心线长度计算。 | L86: 此项工作的全费用综合单价 | Q86: =N86+O86+P86 -> 0 | R86: =Q86*$R$4 -> 0
A87: 11 | B87: 1.1米高不锈钢栏杆 | C87: 1、立柱为70*40*5不锈钢方立管；2、扶手为63*3拉丝不锈钢钢管；3、水平向为38*1.5不锈钢复合管；4、竖向短管为30*1.5哑光不锈钢管；5、预埋螺栓；6、材料的水平及垂直转运（详参图纸）7、其它：垂直运输费用已包含在综合单价中，满足设计规范及图纸要求;未详尽列举特征，详见施工图纸、设计规范、施工方案 | D87: 1.预埋件制作、运输、埋设安装； 2.栏杆制作、运输、安装、防护； 3.综合单价含送样的材料费用、检验、试验等费用; 4.材料的运输、摆放、清运及场内多次搬运； 5.对已施工完成的成品及其他专业已完成的成品进行保护工作，无论是否由该单位导致的损坏，该单位都应履行修复处理责任； 6.对施工需要拆除或移动的材料，待施工完毕后，恢复原状； 7.完成工作区域的安全文明施工,清理施工遗留下的垃圾； 8.该项包含本项工作所有工作内容含垂直运输机械等，未详尽列举特征，详见施工图纸、设计规范、施工方案事项均包含在综合单价中 | E87: m | F87: 52.96 | G87: 423.09 | H87: =ROUND(F87*G87,2) -> 22406.85 | I87: =南川一标段!$I$109 -> 493.81 | J87: =F87*I87 -> 26152.18 | K87: 按设计图示以扶手中心线长度计算。 | L87: 此项工作的全费用综合单价 | Q87: =N87+O87+P87 -> 0 | R87: =Q87*$R$4 -> 0
A88: 12 | B88: 沉砂井盖板 | C88: 规格型号：900*600盖板 1、花岗石水篦子铺面，提手50*20矩形洞口，不锈钢包边 2、30厚1：3干硬性水泥砂浆 3、60mm厚C25钢筋混凝土盖板 4、其它：垂直运输费用已包含在综合单价中，满足设计规范及图纸要求;未详尽列举特征，详见施工图纸、设计规范、施工方案 | D88: 1、盖板板制作、安装 2、盖板安装嵌缝、塞口 3、石材水篦子面板不锈钢包边处理、安装； 4、该项包含本项工作所有工作内容含垂直运输机械等，未详尽列举特征，详见施工图纸、设计规范、施工方案事项均包含在综合单价中 | E88: 个 | F88: 102 | G88: 340 | H88: =ROUND(F88*G88,2) -> 34680 | I88: =南川一标段!$I$110 -> 358.86 | J88: =F88*I88 -> 36603.72 | K88: 按设计图示尺寸以个计算。 | L88: 除甲供材外，此项工作的全费用综合单价 甲供材：花岗石 | Q88: =N88+O88+P88 -> 0 | R88: =Q88*$R$4 -> 0
A89: 13 | B89: 站台端部检修爬梯 | C89: 带护笼钢爬梯，做法参考15J401（D19-C3,D18-B1,D18-B3,WT2B-6.4)，护笼做法参考15J401-D15-AC 其它：垂直运输费用已包含在综合单价中，满足设计规范及图纸要求;未详尽列举特征，详见施工图纸、设计规范、施工方案 | D89: 1、钢爬梯预埋件200*300*10制作、安装，刷防腐防锈涂料； 2、护笼安装 3、钢爬梯安装 4、该项包含本项工作所有工作内容所有工作内容含垂直运输机械等，未详尽列举特征，详见施工图纸、设计规范、施工方案事项均包含在综合单价中。 | E89: t | F89: 4 | G89: 8726.4 | H89: =ROUND(F89*G89,2) -> 34905.6 | I89: =南川一标段!$I$111 -> 10536 | J89: =F89*I89 -> 42144 | K89: 按设计图示尺寸乘以理论质量计算，不扣除单个≤0.3m2的孔洞，焊条、铆钉、螺栓等不另增加质量 | L89: 全费用综合单价 | Q89: =N89+O89+P89 -> 0 | R89: =Q89*$R$4 -> 0
