Workbook

Sheet 1-清单及价格说明
A1: 编制说明
A2: 一 | B2: 工程量清单编制依据：
A3: 1 | B3: 长城智选设计、施工一体化项目工程图纸、效果图（1.0、2.0版本）
A4: 2 | B4: 《建设工程工程量清单计价规范 GB 50500-2013》
A5: 3 | B5: 《建筑工程建筑面积计算规范》GB 55031-2022
A6: 二 | B6: 工程量清单及控制价注意事项说明:
A7: 1 | B7: 本工程采用设计施工一体化，包工包料的全费用固定综合单价组价。固定综合单价包括现场人工费、材料费、机械费、管理费、措施费、规费、利润、税金、合同备案费、水电费、工程当地所要求必须缴纳的费用以及采用固定价格的工程所测算的风险金、相关的材料试验费、检测费（包括但不限于空气、材料、结构等第三方检测、鉴定等费用）及各系统施工完成后系统调试费、资料整理归档等一切费用。
A8: 2 | B8: 措施费用包含在固定综合单价中，不单独体现。措施费费用包括但不限于安全文明施工费用（应满足项目所在地的政府及物业要求的安全文明施工标准）、临时设施（办公住宿临设、临水临电、临时道路等）、夜间施工、非夜间施工照明、二次搬运、冬雨季施工、已完工程及设备成品保护等与项目相关的措施费用。
A9: 3 | B9: 本项目中涉及脚手架、垂直运输、超高增加费、垃圾清运费、垃圾消纳费含在固定综合单价中，不再单独体现。
A10: 4 | B10: 消防设备复检、玻璃幕墙、石材幕墙的检测以及当地政府要求的检测相关费用包含在固定综合单价中，不再单独体现。消防验收在招标范围内，消防的备案、验收、办证，单独组价。其它相关建设手续费（含物业及政府相关备案、开工、建设、验收等所有手续相关费用）含在固定综合单价中，不再单独体现。
A11: 5 | B11: 强弱电、给排水、消防、暖通等专业开洞、封堵、套管等，包含在对应专业的管道固定综合单价中，不再单独列清单。
A12: 6 | B12: 方案图纸设计费（包括但不限于涉及本项目的各专业工程（建筑、装饰、结构、幕墙、消防、电气、照明、给排水、暖通等）图纸深化、报审、审图、现场施工指导配合、竣工图编制等所有图纸相关费用），按照平方米进行计价，未使用区域、室内、外停车位不计算，部分店面涉及室外院落、隔离墙、道路规划，不计量，不单独计价。
A13: 7 | B13: 需进行政府竣工验收的费用，及因验收产生的检测费用均含在综合单价内。
A14: 8 | B14: 投标单位在投标前应踏勘现场，充分考虑现场、方案设计等实际情况(如:运输条件、施工场地、地质条件、施工时间区段等)；综合考虑现场实际地面找平厚度与清单、方案设计不一致时，价格不进行调整，投标单位也应深入理解技术要求和验收要求,所有在招标时提供的文件均认为已完整无误包含在报价之中；
A15: 9 | B15: 无节点做法，可自行深化，经甲方确认后实施，费用包含在综合单价相关子目中。
A16: 10 | B16: 对于新增项目或签证、设计变更产生的工程项目造价的调整按以下顺序执行：
A17: 10.1 | B17: 工程量清单表中有相同工程内容的项目，按相同项目综合单价执行，根据工程量增减进行总价调整；同标段或是同期其他分包合同有相同项目或类似项目单价，按照该单价计取。
A18: 10.2 | B18: 工程量清单表中有类似工程内容的项目，如某项清单发包人要求主要材料更换，则原综合单价不变，只调整主材价差，土建材料价差=（双方确定含税材料价格-本合同清单表内注明的主材价格）× (1+税金)。
... A20: 11 | B20: 本页不得删除,将作为合同清单的有效组成部分。

Sheet 2-报价汇总
A1: 工程报价汇总表 | F1: 其他 综合费率 | G1: 0.207
A2: 公司名称：深圳市广湾建设科技有限公司 | D2: 单位：元
A3: 序号 | B3: 单 位 工 程 名 称 | C3: 报价汇总 | D3: 备注
A4: 1 | B4: 装饰工程 | C4: ='2.1装饰工程'!M370 -> 4086904.2 | E4: 4126563.6 | F4: =C4-E4 -> -39659.318
A5: 2 | B5: 强电工程 | C5: ='2.2强电工程'!M211 -> 466528.86 | E5: 467688.42 | F5: =C5-E5 -> -1159.5581
A6: 3 | B6: 弱电工程 | C6: ='2.3弱电工程'!M98 -> 334909.49 | E6: 335741.91 | F6: =C6-E6 -> -832.41796
A7: 4 | B7: 给排水工程 | C7: ='2.4给排水工程'!M113 -> 36186.655 | E7: 36276.597 | F7: =C7-E7 -> -89.941975
A8: 5 | B8: 消防工程 | C8: ='2.5消防工程'!M265 -> 344458.75 | E8: 345692.79 | F8: =C8-E8 -> -1234.0357
A9: 6 | B9: 暖通工程 | C9: ='2.6暖通工程'!M145 -> 694220.44 | E9: 695945.92 | F9: =C9-E9 -> -1725.4858
A10: 7 | B10: 合计 | C10: =SUM(C4:C9) -> 5963208.4 | E10: 6007909.2 | F10: =C10-E10 -> -44700.757

Sheet 2.1装饰工程
A1: 长城智选中心店装修项目装饰工程
A2: 序号 | B2: 分部分项名称 | C2: 项目特征 | D2: 计量规则 | E2: 单位 | F2: 工程量 | G2: 综合单价 | H2: 人工 | I2: 主材 | J2: 辅材 | K2: 机械 | L2: 其他 综合费率 | M2: 合计 | N2: 备注
A3: 一 | B3: 方案设计费
A4: 1 | B4: 方案图纸设计费 | C4: 1.包含建筑及装饰、结构、电气、暖通、给排水、消防、幕墙等专业，前期需现场踏勘，出具平面图、效果图等 2.包括但不限于图纸深化、报审、审图、竣工图编制等图纸相关费用 | D4: 以设计图纸尺寸按室内空间净面积计量（含不与墙面交集的柱面积），未使用区域、室内、外停车位不计算 | E4: m2 | F4: 2900 | G4: =(H4+I4+J4+K4)*(1+L4) -> 48.28 | H4: =VLOOKUP(B4,'[1]2.1装饰工程'!$B$4:$H$354,7,0) -> 40 | I4: =VLOOKUP(B4,'[1]2.1装饰工程'!$B$4:$I$354,8,0) -> 0 | J4: =VLOOKUP(B4,'[1]2.1装饰工程'!$B$4:$J$354,9,0) -> 0 | K4: =VLOOKUP(B4,'[1]2.1装饰工程'!$B$4:$K$354,10,0) -> 0 | L4: ='2-报价汇总'!$G$1 -> 0.207 | M4: =F4*G4 -> 140012
A5: 二 | B5: 拆除工程
A6: 1 | B6: 素混凝土拆除 | C6: 1.素混凝土构件拆除（含平面、立面、基础等） 2.包括：墙体内的管线、开关、插座等，达到不妨碍后期装修的程度，拆除后的所有材料施工单位自行处理 3.其他：满足施工要求 | D6: 工程量按拆除构件的混凝土体积计算 | E6: m3 | G6: =(H6+I6+J6+K6)*(1+L6) -> 411.56286 | H6: =VLOOKUP(B6,'[1]2.1装饰工程'!$B$4:$H$354,7,0) -> 250.88 | I6: =VLOOKUP(B6,'[1]2.1装饰工程'!$B$4:$I$354,8,0) -> 0 | J6: =VLOOKUP(B6,'[1]2.1装饰工程'!$B$4:$J$354,9,0) -> 7.47 | K6: =VLOOKUP(B6,'[1]2.1装饰工程'!$B$4:$K$354,10,0) -> 82.63 | L6: =$L$4 -> 0.207 | M6: =F6*G6 -> 0
A7: 2 | B7: 钢筋混凝土构件拆除 | C7: 1.钢筋混凝土构件拆除（含平面、立面、基础等） 2.包括：墙体内的管线、开关、插座等，达到不妨碍后期装修的程度，拆除后的所有材料施工单位自行处理 3.其他：满足施工要求 | D7: 工程量按拆除构件的混凝土体积计算 | E7: m3 | F7: 3.09 | G7: =(H7+I7+J7+K7)*(1+L7) -> 569.18499 | H7: =VLOOKUP(B7,'[1]2.1装饰工程'!$B$4:$H$354,7,0) -> 339 | I7: =VLOOKUP(B7,'[1]2.1装饰工程'!$B$4:$I$354,8,0) -> 0 | J7: =VLOOKUP(B7,'[1]2.1装饰工程'!$B$4:$J$354,9,0) -> 9.2 | K7: =VLOOKUP(B7,'[1]2.1装饰工程'!$B$4:$K$354,10,0) -> 123.37 | L7: =$L$4 -> 0.207 | M7: =F7*G7 -> 1758.7816
A8: 3 | B8: 金属构件拆除 | C8: 1.金属构件拆除（综合考虑钢构件规格尺寸） 2.包括：其中的管线、开关、插座等，达到不妨碍后期装修的程度，拆除后的所有材料施工单位自行处理 3.其他：满足施工要求 | D8: 工程量按拆除构件的质量计算 | E8: t | G8: =(H8+I8+J8+K8)*(1+L8) -> 830.09011 | H8: =VLOOKUP(B8,'[1]2.1装饰工程'!$B$4:$H$354,7,0) -> 674.73 | I8: =VLOOKUP(B8,'[1]2.1装饰工程'!$B$4:$I$354,8,0) -> 0 | J8: =VLOOKUP(B8,'[1]2.1装饰工程'!$B$4:$J$354,9,0) -> 0 | K8: =VLOOKUP(B8,'[1]2.1装饰工程'!$B$4:$K$354,10,0) -> 13 | L8: =$L$4 -> 0.207 | M8: =F8*G8 -> 0
A9: 4 | B9: 砌体墙拆除 | C9: 1.砌筑墙体拆除，连墙体内砼柱破碎后装袋 2.包括：砌体墙及附属的基层面层，墙体内的管线、开关、插座等，达到不妨碍装修的程度，拆除后的所有材料施工单位自行处理 3.其他：满足施工要求 | D9: 工程量按拆除部位的体积计算 | E9: m3 | F9: 310 | G9: =(H9+I9+J9+K9)*(1+L9) -> 243.66916 | H9: =VLOOKUP(B9,'[1]2.1装饰工程'!$B$4:$H$354,7,0) -> 136.88 | I9: =VLOOKUP(B9,'[1]2.1装饰工程'!$B$4:$I$354,8,0) -> 0 | J9: =VLOOKUP(B9,'[1]2.1装饰工程'!$B$4:$J$354,9,0) -> 0 | K9: =VLOOKUP(B9,'[1]2.1装饰工程'!$B$4:$K$354,10,0) -> 65 | L9: =$L$4 -> 0.207 | M9: =F9*G9 -> 75537.44
A10: 5 | B10: 玻璃隔墙拆除 | C10: 1.玻璃隔墙拆除 2.包括：玻璃隔墙及附属的基层面层，墙体内的管线、开关、插座等，达到不妨碍装修的程度，拆除后的所有材料施工单位自行处理 3.墙体厚度：综合考虑 4.其他：满足施工要求 | D10: 工程量按拆除部位的面积计算 | E10: m2 | G10: =(H10+I10+J10+K10)*(1+L10) -> 28.85937 | H10: =VLOOKUP(B10,'[1]2.1装饰工程'!$B$4:$H$354,7,0) -> 10.91 | I10: =VLOOKUP(B10,'[1]2.1装饰工程'!$B$4:$I$354,8,0) -> 0 | J10: =VLOOKUP(B10,'[1]2.1装饰工程'!$B$4:$J$354,9,0) -> 0 | K10: =VLOOKUP(B10,'[1]2.1装饰工程'!$B$4:$K$354,10,0) -> 13 | L10: =$L$4 -> 0.207 | M10: =F10*G10 -> 0
A11: 6 | B11: 石膏板隔墙拆除 | C11: 1.石膏板隔墙拆除 2.包括：石膏板隔墙及附属的基层面层，墙体内的管线、开关、插座等，达到不妨碍装修的程度，拆除后的所有材料施工单位自行处理 3.墙体厚度：综合考虑， 4.其他：满足施工要求 | D11: 工程量按拆除部位的面积计算 | E11: m2 | G11: =(H11+I11+J11+K11)*(1+L11) -> 30.06637 | H11: =VLOOKUP(B11,'[1]2.1装饰工程'!$B$4:$H$354,7,0) -> 14.91 | I11: =VLOOKUP(B11,'[1]2.1装饰工程'!$B$4:$I$354,8,0) -> 0 | J11: =VLOOKUP(B11,'[1]2.1装饰工程'!$B$4:$J$354,9,0) -> 0 | K11: =VLOOKUP(B11,'[1]2.1装饰工程'!$B$4:$K$354,10,0) -> 10 | L11: =$L$4 -> 0.207 | M11: =F11*G11 -> 0
A12: 7 | B12: 砌体墙开门洞（含修补） | C12: 1.砌体墙开门洞（含修补） 2.包括：砌体墙隔墙及附属的基层面层，墙体内的管线、开关、插座等，达到不妨碍装修的程度，拆除后的所有材料施工单位自行处理 3.墙体厚度：综合考虑，包含开门洞的修补工作 4.其他：满足施工要求 | D12: 工程量按拆除部位的面积计算 | E12: m2 | G12: =(H12+I12+J12+K12)*(1+L12) -> 99.27575 | H12: =VLOOKUP(B12,'[1]2.1装饰工程'!$B$4:$H$354,7,0) -> 66.66 | I12: =VLOOKUP(B12,'[1]2.1装饰工程'!$B$4:$I$354,8,0) -> 0 | J12: =VLOOKUP(B12,'[1]2.1装饰工程'!$B$4:$J$354,9,0) -> 2.59 | K12: =VLOOKUP(B12,'[1]2.1装饰工程'!$B$4:$K$354,10,0) -> 13 | L12: =$L$4 -> 0.207 | M12: =F12*G12 -> 0
A13: 8 | B13: 门窗拆除（包括门框、门套） | C13: 1.门窗拆除 2.包括：门框、门套，不区分门窗材质，达到不妨碍装修的程度，拆除后的所有材料施工单位自行处理 3.其他：满足施工要求 | D13: 工程量按拆除面积计算 | E13: m2 | F13: 25.2 | G13: =(H13+I13+J13+K13)*(1+L13) -> 34.59262 | H13: =VLOOKUP(B13,'[1]2.1装饰工程'!$B$4:$H$354,7,0) -> 15.66 | I13: =VLOOKUP(B13,'[1]2.1装饰工程'!$B$4:$I$354,8,0) -> 0 | J13: =VLOOKUP(B13,'[1]2.1装饰工程'!$B$4:$J$354,9,0) -> 0 | K13: =VLOOKUP(B13,'[1]2.1装饰工程'!$B$4:$K$354,10,0) -> 13 | L13: =$L$4 -> 0.207 | M13: =F13*G13 -> 871.73402
A14: 9 | B14: 楼地面装饰物拆除 | C14: 1.楼地面装饰物拆除（包括但不限于地砖、地板、地毯、玻璃、PVC、环氧地坪等材质） 2.包括：装饰地面面层及基层，地面内的管线、开关、插座等，达到不妨碍后期地面装修的程度，拆除后的所有材料施工单位自行处理 3.其他：满足施工要求 | D14: 工程量按拆除面积计算 | E14: m2 | F14: 80 | G14: =(H14+I14+J14+K14)*(1+L14) -> 39.40855 | H14: =VLOOKUP(B14,'[1]2.1装饰工程'!$B$4:$H$354,7,0) -> 26.15 | I14: =VLOOKUP(B14,'[1]2.1装饰工程'!$B$4:$I$354,8,0) -> 0 | J14: =VLOOKUP(B14,'[1]2.1装饰工程'!$B$4:$J$354,9,0) -> 0 | K14: =VLOOKUP(B14,'[1]2.1装饰工程'!$B$4:$K$354,10,0) -> 6.5 | L14: =$L$4 -> 0.207 | M14: =F14*G14 -> 3152.684
A15: 10 | B15: 楼地面地毯拆除 | C15: 1.楼地面地毯拆除 2.包括：装饰地面面层及基层，地面内的管线、开关、插座等，达到不妨碍后期地面装修的程度，拆除后的所有材料施工单位自行处理 3.其他：满足施工要求 | D15: 工程量按拆除面积计算 | E15: m2 | G15: =(H15+I15+J15+K15)*(1+L15) -> 6.3304799 | H15: 4.9748052 | I15: 0 | J15: 0.05 | K15: 0.22 | L15: =$L$4 -> 0.207 | M15: =F15*G15 -> 0
A16: 11 | B16: 楼地面地砖拆除 | C16: 1.楼地面地砖拆除 2.包括：装饰地面面层及基层，地面内的管线、开关、插座等，达到不妨碍后期地面装修的程度，拆除后的所有材料施工单位自行处理 4.其他：满足施工要求 | D16: 工程量按拆除面积计算 | E16: m2 | G16: =(H16+I16+J16+K16)*(1+L16) -> 33.7751 | H16: 27.005628 | I16: 0 | J16: 0.27705628 | K16: 0.7 | L16: =$L$4 -> 0.207 | M16: =F16*G16 -> 0
A17: 12 | B17: 楼地面地板拆除 | C17: 1.楼地面地板拆除 2.包括：装饰地面面层及基层，地面内的管线、开关、插座等，达到不妨碍后期地面装修的程度，拆除后的所有材料施工单位自行处理 5.其他：满足施工要求 | D17: 工程量按拆除面积计算 | E17: m2 | G17: =(H17+I17+J17+K17)*(1+L17) -> 6.3304799 | H17: =H15 -> 4.9748052 | I17: =I15 -> 0 | J17: =J15 -> 0.05 | K17: =K15 -> 0.22 | L17: =$L$4 -> 0.207 | M17: =F17*G17 -> 0
A18: 13 | B18: 墙面、柱（梁）面装饰物拆除（含龙骨） | C18: 1.墙面装饰物拆除，含龙骨及基层板（包括但不限于石材、铝板、金属、木饰面、石膏板等材质） 2.包括：拆除装饰墙面龙骨、基层板及面层，地面内的管线、开关、插座等，达到不妨碍后期墙面装修的程度，拆除后的所有材料施工单位自行处理 3.其他：满足施工要求 | D18: 工程量按拆除面积计算 | E18: m2 | G18: =(H18+I18+J18+K18)*(1+L18) -> 34.18224 | H18: =VLOOKUP(B18,'[1]2.1装饰工程'!$B$4:$H$354,7,0) -> 21.82 | I18: =VLOOKUP(B18,'[1]2.1装饰工程'!$B$4:$I$354,8,0) -> 0 | J18: =VLOOKUP(B18,'[1]2.1装饰工程'!$B$4:$J$354,9,0) -> 0 | K18: =VLOOKUP(B18,'[1]2.1装饰工程'!$B$4:$K$354,10,0) -> 6.5 | L18: =$L$4 -> 0.207 | M18: =F18*G18 -> 0
A19: 14 | B19: 墙面、柱（梁）面装饰物拆除（不含龙骨） | C19: 1.墙面装饰物拆除，不含龙骨（包括但不限于石材、铝板、金属、木饰面等材质） 2.包括：拆除装饰墙面基层及面层，地面内的管线、开关、插座等，达到不妨碍后期墙面装修的程度，拆除后的所有材料施工单位自行处理 3.其他：满足施工要求 | D19: 工程量按拆除面积计算 | E19: m2 | G19: =(H19+I19+J19+K19)*(1+L19) -> 27.04887 | H19: =VLOOKUP(B19,'[1]2.1装饰工程'!$B$4:$H$354,7,0) -> 15.91 | I19: =VLOOKUP(B19,'[1]2.1装饰工程'!$B$4:$I$354,8,0) -> 0 | J19: =VLOOKUP(B19,'[1]2.1装饰工程'!$B$4:$J$354,9,0) -> 0 | K19: =VLOOKUP(B19,'[1]2.1装饰工程'!$B$4:$K$354,10,0) -> 6.5 | L19: =$L$4 -> 0.207 | M19: =F19*G19 -> 0
A20: 15 | B20: 铲除涂料、裱糊面 | C20: 1.铲除涂料、裱糊面（综合考虑铲除部位） 2.包括：拆除装饰墙面涂料、腻子，地面内的管线、开关、插座等，达到不妨碍后期装修的程度，拆除后的所有材料施工单位自行处理 3.其他：满足施工要求 | D20: 工程量按拆除面积计算 | E20: m2 | G20: =(H20+I20+J20+K20)*(1+L20) -> 9.02836 | H20: 4.23 | K20: 3.25 | L20: =$L$4 -> 0.207 | M20: =F20*G20 -> 0
A21: 16 | B21: 钢结构表面油漆铲除 | C21: 1.钢结构表面油漆铲除 2.包括：表面油漆铲除及钢结构表面清理，达到不妨碍后期装修的程度，拆除后的所有材料施工单位自行处理 3.其他：满足施工要求 | D21: 工程量按拆除面积计算 | E21: m2 | G21: =(H21+I21+J21+K21)*(1+L21) -> 16.59625 | H21: 8.5 | K21: 5.25 | L21: =$L$4 -> 0.207 | M21: =F21*G21 -> 0
A22: 17 | B22: 玻璃贴膜拆除 | C22: 1.玻璃贴膜拆除 2.包括：清除玻璃贴膜，达到不妨碍装修的程度，拆除后的所有材料施工单位自行处理 3.其他：满足施工要求 | D22: 工程量按拆除面积计算 | E22: m2 | G22: =(H22+I22+J22+K22)*(1+L22) -> 9.57151 | H22: =VLOOKUP(B22,'[1]2.1装饰工程'!$B$4:$H$354,7,0) -> 4.68 | I22: =VLOOKUP(B22,'[1]2.1装饰工程'!$B$4:$I$354,8,0) -> 0 | J22: =VLOOKUP(B22,'[1]2.1装饰工程'!$B$4:$J$354,9,0) -> 0 | K22: =VLOOKUP(B22,'[1]2.1装饰工程'!$B$4:$K$354,10,0) -> 3.25 | L22: =$L$4 -> 0.207 | M22: =F22*G22 -> 0
A23: 18 | B23: 吊顶拆除 | C23: 1.吊顶拆除（包括但不限于石膏板、铝扣板、矿棉板等材质） 2.包括：转换层、龙骨、基层、面层及配套的风口、灯具、线管、吊顶上水管风管等所有材料，达到不妨碍吊顶装修的程度，拆除后的所有材料施工单位自行处理 3.其他：满足施工要求 | D23: 工程量按拆除面积计算 | E23: m2 | F23: 79 | G23: =(H23+I23+J23+K23)*(1+L23) -> 22.86058 | H23: =VLOOKUP(B23,'[1]2.1装饰工程'!$B$4:$H$354,7,0) -> 12.44 | I23: =VLOOKUP(B23,'[1]2.1装饰工程'!$B$4:$I$354,8,0) -> 0 | J23: =VLOOKUP(B23,'[1]2.1装饰工程'!$B$4:$J$354,9,0) -> 0 | K23: =VLOOKUP(B23,'[1]2.1装饰工程'!$B$4:$K$354,10,0) -> 6.5 | L23: =$L$4 -> 0.207 | M23: =F23*G23 -> 1805.9858
A24: 19 | B24: 玻璃幕墙拆除 | C24: 1.玻璃幕墙拆除 2.包括：幕墙、基层板、龙骨及辅材（包含破碎后装袋），达到不妨碍装修的程度，拆除后的所有材料施工单位自行处理 3.其他：满足施工要求 | D24: 工程量按拆除面积计算 | E24: m2 | G24: =(H24+I24+J24+K24)*(1+L24) -> 51.44234 | H24: 36.12 | I24: 0 | J24: 0 | K24: 6.5 | L24: =$L$4 -> 0.207 | M24: =F24*G24 -> 0
A25: 20 | B25: 金属幕墙拆除 | C25: 1.金属幕墙拆除 2.包括：幕墙、基层板、龙骨及辅材（包含破碎后装袋），达到不妨碍装修的程度，拆除后的所有材料施工单位自行处理 3.其他：满足施工要求 | D25: 工程量按拆除面积计算 | E25: m2 | G25: =(H25+I25+J25+K25)*(1+L25) -> 51.44234 | H25: 36.12 | I25: 0 | J25: 0 | K25: 6.5 | L25: =$L$4 -> 0.207 | M25: =F25*G25 -> 0
A26: 21 | B26: 外幕墙拆除 | C26: 1.外幕墙拆除（包括石材、铝塑板等材质） 2.包括：幕墙、基层板、龙骨及辅材（包含破碎后装袋），达到不妨碍装修的程度，拆除后的所有材料施工单位自行处理 3.其他：满足施工要求 | D26: 工程量按拆除面积计算 | E26: m2 | G26: =(H26+I26+J26+K26)*(1+L26) -> 51.44234 | H26: =VLOOKUP(B26,'[1]2.1装饰工程'!$B$4:$H$354,7,0) -> 36.12 | I26: =VLOOKUP(B26,'[1]2.1装饰工程'!$B$4:$I$354,8,0) -> 0 | J26: =VLOOKUP(B26,'[1]2.1装饰工程'!$B$4:$J$354,9,0) -> 0 | K26: =VLOOKUP(B26,'[1]2.1装饰工程'!$B$4:$K$354,10,0) -> 6.5 | L26: =$L$4 -> 0.207 | M26: =F26*G26 -> 0
A27: 22 | B27: 栏杆、栏板拆除 | C27: 1.栏杆、栏板拆除（综合考虑栏杆、栏板的材质及高度） 2.包括：达到不妨碍装修的程度，拆除后的所有材料施工单位自行处理 3.其他：满足施工要求 | D27: 工程量按拆除长度计算 | E27: m | G27: =(H27+I27+J27+K27)*(1+L27) -> 20.80868 | H27: =VLOOKUP(B27,'[1]2.1装饰工程'!$B$4:$H$354,7,0) -> 10.74 | I27: =VLOOKUP(B27,'[1]2.1装饰工程'!$B$4:$I$354,8,0) -> 0 | J27: =VLOOKUP(B27,'[1]2.1装饰工程'!$B$4:$J$354,9,0) -> 0 | K27: =VLOOKUP(B27,'[1]2.1装饰工程'!$B$4:$K$354,10,0) -> 6.5 | L27: =$L$4 -> 0.207 | M27: =F27*G27 -> 0
A28: 23 | B28: 电气、暖通等拆除费用 | C28: 1.电气、暖通等拆除费用（裸顶） 2.包括：达到不妨碍装修的程度，拆除后的所有材料施工单位自行处理 3.其他：满足施工要求 | D28: 工程量按拆除裸顶天棚水平投影面积计算 | E28: m2 | G28: =(H28+I28+J28+K28)*(1+L28) -> 17.19975 | H28: =VLOOKUP(B28,'[1]2.1装饰工程'!$B$4:$H$354,7,0) -> 11 | I28: =VLOOKUP(B28,'[1]2.1装饰工程'!$B$4:$I$354,8,0) -> 0 | J28: =VLOOKUP(B28,'[1]2.1装饰工程'!$B$4:$J$354,9,0) -> 0 | K28: =VLOOKUP(B28,'[1]2.1装饰工程'!$B$4:$K$354,10,0) -> 3.25 | L28: =$L$4 -> 0.207 | M28: =F28*G28 -> 0
A29: 24 | B29: 卷帘拆除 | C29: 1.卷帘及配置等拆除 2.拆除后的所有材料施工单位自行处理 3.其他：满足施工要求 | D29: 工程量按拆除面积计算 | E29: m2 | G29: =(H29+I29+J29+K29)*(1+L29) -> 15.854076 | H29: 12.435108 | I29: 0 | J29: 0.15 | K29: 0.55 | L29: =$L$4 -> 0.207 | M29: =F29*G29 -> 0
A30: 25 | B30: 保洁费 | C30: 1.保洁费 2.包括：精保洁，满足开业条件 3.其他:详见SI手册、品牌表及标准节点等，满足施工要求及国家规范 | D30: 工程量按装修店面装修面积计算 | E30: m2 | F30: 2900 | G30: =(H30+I30+J30+K30)*(1+L30) -> 16.898 | H30: =VLOOKUP(B30,'[1]2.1装饰工程'!$B$4:$H$354,7,0) -> 14 | I30: =VLOOKUP(B30,'[1]2.1装饰工程'!$B$4:$I$354,8,0) -> 0 | J30: =VLOOKUP(B30,'[1]2.1装饰工程'!$B$4:$J$354,9,0) -> 0 | K30: =VLOOKUP(B30,'[1]2.1装饰工程'!$B$4:$K$354,10,0) -> 0 | L30: =$L$4 -> 0.207 | M30: =F30*G30 -> 49004.2
A31: 三 | B31: 结构及结构加固工程
A32: 1 | B32: 构造柱/抱框柱 | C32: 1.混凝土种类:商品砼（含钢筋及模板） 2.混凝土强度等级:C25 3.构造柱带马牙槎 4.工作内容:混凝土制作、运输、浇筑、振捣、养护 5.其他:详见SI手册、品牌表及标准节点等，满足施工要求及国家规范 | D32: 按设计图示尺寸以体积计算 | E32: m3 | F32: 12 | G32: =(H32+I32+J32+K32)*(1+L32) -> 1818.1765 | H32: =VLOOKUP(B32,'[1]2.1装饰工程'!$B$4:$H$354,7,0) -> 375.87 | I32: =VLOOKUP(B32,'[1]2.1装饰工程'!$B$4:$I$354,8,0) -> 1010.57 | J32: =VLOOKUP(B32,'[1]2.1装饰工程'!$B$4:$J$354,9,0) -> 0 | K32: =VLOOKUP(B32,'[1]2.1装饰工程'!$B$4:$K$354,10,0) -> 119.92 | L32: =$L$4 -> 0.207 | M32: =F32*G32 -> 21818.118
A33: 2 | B33: 圈梁/水平系梁/导墙 | C33: 1.混凝土种类:商品砼（含钢筋及模板） 2.混凝土强度等级:C25 3.工作内容:混凝土制作、运输、浇筑、振捣、养护 4.其他:详见SI手册、品牌表及标准节点等，满足施工要求及国家规范 | D33: 按设计图示尺寸以体积计算 | E33: m3 | G33: =(H33+I33+J33+K33)*(1+L33) -> 1737.6093 | H33: =VLOOKUP(B33,'[1]2.1装饰工程'!$B$4:$H$354,7,0) -> 375.87 | I33: =VLOOKUP(B33,'[1]2.1装饰工程'!$B$4:$I$354,8,0) -> 1044.42 | J33: =VLOOKUP(B33,'[1]2.1装饰工程'!$B$4:$J$354,9,0) -> 0 | K33: =VLOOKUP(B33,'[1]2.1装饰工程'!$B$4:$K$354,10,0) -> 19.32 | L33: =$L$4 -> 0.207 | M33: =F33*G33 -> 0
A34: 3 | B34: 过梁 | C34: 1.混凝土种类:商品砼（含钢筋及模板） 2.混凝土强度等级:C25 3.工作内容:混凝土制作、运输、浇筑、振捣、养护 4.其他:详见SI手册、品牌表及标准节点等，满足施工要求及国家规范 | D34: 按设计图示尺寸以体积计算 | E34: m3 | G34: =(H34+I34+J34+K34)*(1+L34) -> 1764.2478 | H34: =VLOOKUP(B34,'[1]2.1装饰工程'!$B$4:$H$354,7,0) -> 375.87 | I34: =VLOOKUP(B34,'[1]2.1装饰工程'!$B$4:$I$354,8,0) -> 957.89 | J34: =VLOOKUP(B34,'[1]2.1装饰工程'!$B$4:$J$354,9,0) -> 0 | K34: =VLOOKUP(B34,'[1]2.1装饰工程'!$B$4:$K$354,10,0) -> 127.92 | L34: =$L$4 -> 0.207 | M34: =F34*G34 -> 0
A35: 4 | B35: 化粪池 | C35: 1.成品玻璃钢化粪池 2.包含地面破碎开挖回填夯实及余土外运、成品化粪池制作运输及安装、套管等所有内容 3.按有效容积计算 4.其他:详见SI手册、品牌表及标准节点等，满足施工要求及国家规范 | D35: 按设计图示尺寸以体积计算 | E35: m3 | G35: =(H35+I35+J35+K35)*(1+L35) -> 783.60854 | H35: 87.12 | I35: 550 | J35: 6.3 | K35: 5.8 | L35: =$L$4 -> 0.207 | M35: =F35*G35 -> 0
A36: 5 | B36: 加气砌块砌筑墙 | C36: 1.加气砌块砌筑墙 2.墙体类型:综合考虑 3.砂浆强度等级:综合考虑 4.工作内容:砂浆制作、运输；砌砖、砌块；勾缝；材料运输 5.其他:详见SI手册、品牌表及标准节点等，满足施工要求及国家规范 | D36: 按设计图示尺寸以体积计算 | E36: m3 | F36: 150 | G36: =(H36+I36+J36+K36)*(1+L36) -> 934.22001 | H36: 216.03 | I36: 528.18 | J36: =4.5*(1/0.24) -> 18.75 | K36: =2.65*(1/0.24) -> 11.041667 | L36: =$L$4 -> 0.207 | M36: =F36*G36 -> 140133
A37: 6 | B37: 砖砌筑墙 | C37: 1.砖砌墙 2.墙体类型:综合考虑 3.砂浆强度等级:综合考虑 4.工作内容:砂浆制作、运输；砌砖、砌块；勾缝；材料运输 6.其他:详见SI手册、品牌表及标准节点等，满足施工要求及国家规范 | D37: 按设计图示尺寸以体积计算 | E37: m3 | F37: 150 | G37: =(H37+I37+J37+K37)*(1+L37) -> 1173.556 | H37: =55*(1/0.24) -> 229.16667 | I37: =200*(1/0.24)-120 -> 713.33333 | J37: =4.5*(1/0.24) -> 18.75 | K37: =2.65*(1/0.24) -> 11.041667 | L37: =$L$4 -> 0.207 | M37: =F37*G37 -> 176033.41
A38: 7 | B38: 预埋铁件 | C38: 1.钢材种类:钢板、锚筋等 2.规格:综合考虑 3.工作内容:铁件制作、运输、安装 4.其他:详见SI手册、品牌表及标准节点等，满足施工要求及国家规范 | D38: 按设计图示尺寸以质量计算，不扣除孔眼的质量，焊条、铆钉、螺栓等不另增加质量 | E38: t | F38: 0.5 | G38: =(H38+I38+J38+K38)*(1+L38) -> 10314.612 | H38: =VLOOKUP(B38,'[1]2.1装饰工程'!$B$4:$H$354,7,0) -> 2047.71 | I38: =VLOOKUP(B38,'[1]2.1装饰工程'!$B$4:$I$354,8,0) -> 6045.67 | J38: =VLOOKUP(B38,'[1]2.1装饰工程'!$B$4:$J$354,9,0) -> 0 | K38: =VLOOKUP(B38,'[1]2.1装饰工程'!$B$4:$K$354,10,0) -> 452.28 | L38: =$L$4 -> 0.207 | M38: =F38*G38 -> 5157.3058
A39: 8 | B39: 钢构件 | C39: 1.构件名称:综合考虑 2.钢材品种、规格:综合考虑 3.工作内容:构件场内外驳运、构件制作、安装 4.其他:详见SI手册、品牌表及标准节点等，满足施工要求及国家规范 | D39: 按设计图示尺寸以质量计算，不扣除孔眼的质量，焊条、铆钉、螺栓等不另增加质量 | E39: t | F39: 0.5 | G39: =(H39+I39+J39+K39)*(1+L39) -> 9875.5774 | H39: =VLOOKUP(B39,'[1]2.1装饰工程'!$B$4:$H$354,7,0) -> 2047.71 | I39: =VLOOKUP(B39,'[1]2.1装饰工程'!$B$4:$I$354,8,0) -> 5921.58 | J39: =VLOOKUP(B39,'[1]2.1装饰工程'!$B$4:$J$354,9,0) -> 0 | K39: =VLOOKUP(B39,'[1]2.1装饰工程'!$B$4:$K$354,10,0) -> 212.63 | L39: =$L$4 -> 0.207 | M39: =F39*G39 -> 4937.7887
A40: 9 | B40: 新做钢梯 | C40: 1.钢材品种、规格:综合考虑 2.钢梯形式:踏步式 3.螺栓种类:普通螺栓含在单价内，高强螺栓另行计取 4.包括:钢梯柱、钢梯梁、踏步板、休息平台、连接板等 5.其他:详见SI手册、品牌表及标准节点等，满足施工要求及国家规范 | D40: 按设计图示尺寸以质量计算，不扣除孔眼的质量，焊条、铆钉、螺栓等不另增加质量 | E40: t | F40: 2 | G40: =(H40+I40+J40+K40)*(1+L40) -> 11166.416 | H40: =VLOOKUP(B40,'[1]2.1装饰工程'!$B$4:$H$354,7,0) -> 918.01 | I40: =VLOOKUP(B40,'[1]2.1装饰工程'!$B$4:$I$354,8,0) -> 8020.14 | J40: =VLOOKUP(B40,'[1]2.1装饰工程'!$B$4:$J$354,9,0) -> 0 | K40: =VLOOKUP(B40,'[1]2.1装饰工程'!$B$4:$K$354,10,0) -> 313.23 | L40: =$L$4 -> 0.207 | M40: =F40*G40 -> 22332.831
A41: 10 | B41: 金属面油漆 | C41: 1.油漆品种、刷漆遍数:具体油漆品种、遍数参考招标文件、图纸等（有防火涂料时取消该面漆） | D41: 以平方米计量，按设计展开面积计算 | E41: m2 | G41: =(H41+I41+J41+K41)*(1+L41) -> 67.08506 | H41: =VLOOKUP(B41,'[1]2.1装饰工程'!$B$4:$H$354,7,0) -> 32.58 | I41: =VLOOKUP(B41,'[1]2.1装饰工程'!$B$4:$I$354,8,0) -> 23 | J41: =VLOOKUP(B41,'[1]2.1装饰工程'!$B$4:$J$354,9,0) -> 0 | K41: =VLOOKUP(B41,'[1]2.1装饰工程'!$B$4:$K$354,10,0) -> 0 | L41: =$L$4 -> 0.207 | M41: =F41*G41 -> 0
A42: 11 | B42: 金属氟碳漆 | C42: 1.油漆品种、刷漆遍数:具体油漆品种、遍数参考招标文件、图纸等（有防火涂料时取消该面漆） | D42: 以平方米计量，按设计展开面积计算 | E42: m2 | G42: =(H42+I42+J42+K42)*(1+L42) -> 101.03797 | H42: =VLOOKUP(B42,'[1]2.1装饰工程'!$B$4:$H$354,7,0) -> 23.02 | I42: =VLOOKUP(B42,'[1]2.1装饰工程'!$B$4:$I$354,8,0) -> 60.69 | J42: =VLOOKUP(B42,'[1]2.1装饰工程'!$B$4:$J$354,9,0) -> 0 | K42: =VLOOKUP(B42,'[1]2.1装饰工程'!$B$4:$K$354,10,0) -> 0 | L42: =$L$4 -> 0.207 | M42: =F42*G42 -> 0
A43: 12 | B43: 金属构件刷防火涂料2.5h | C43: 1.喷刷防火涂料构件名称:钢柱 2.防火等级要求:2.5小时 3.涂料品种、喷刷遍数:满足施工要求及技术规范 | D43: 以平方米计量，按设计展开面积计算 | E43: m2 | G43: =(H43+I43+J43+K43)*(1+L43) -> 72.93901 | H43: =VLOOKUP(B43,'[1]2.1装饰工程'!$B$4:$H$354,7,0) -> 19.75 | I43: =VLOOKUP(B43,'[1]2.1装饰工程'!$B$4:$I$354,8,0) -> 40.68 | J43: =VLOOKUP(B43,'[1]2.1装饰工程'!$B$4:$J$354,9,0) -> 0 | K43: =VLOOKUP(B43,'[1]2.1装饰工程'!$B$4:$K$354,10,0) -> 0 | L43: =$L$4 -> 0.207 | M43: =F43*G43 -> 0
A44: 13 | B44: 金属构件刷防火涂料2h | C44: 1.喷刷防火涂料构件名称:钢梁 2.防火等级要求:2小时 3.涂料品种、喷刷遍数:满足施工要求及技术规范 | D44: 以平方米计量，按设计展开面积计算 | E44: m2 | G44: =(H44+I44+J44+K44)*(1+L44) -> 64.2124 | H44: =VLOOKUP(B44,'[1]2.1装饰工程'!$B$4:$H$354,7,0) -> 17 | I44: =VLOOKUP(B44,'[1]2.1装饰工程'!$B$4:$I$354,8,0) -> 36.2 | J44: =VLOOKUP(B44,'[1]2.1装饰工程'!$B$4:$J$354,9,0) -> 0 | K44: =VLOOKUP(B44,'[1]2.1装饰工程'!$B$4:$K$354,10,0) -> 0 | L44: =$L$4 -> 0.207 | M44: =F44*G44 -> 0
A45: 14 | B45: 金属构件刷防火涂料1.5h | C45: 1.喷刷防火涂料构件名称:其他承重构件 2.防火等级要求:1.5小时 3.涂料品种、喷刷遍数:满足施工要求及技术规范 | D45: 以平方米计量，按设计展开面积计算 | E45: m2 | G45: =(H45+I45+J45+K45)*(1+L45) -> 57.17559 | H45: =VLOOKUP(B45,'[1]2.1装饰工程'!$B$4:$H$354,7,0) -> 20.25 | I45: =VLOOKUP(B45,'[1]2.1装饰工程'!$B$4:$I$354,8,0) -> 27.12 | J45: =VLOOKUP(B45,'[1]2.1装饰工程'!$B$4:$J$354,9,0) -> 0 | K45: =VLOOKUP(B45,'[1]2.1装饰工程'!$B$4:$K$354,10,0) -> 0 | L45: =$L$4 -> 0.207 | M45: =F45*G45 -> 0
A46: 15 | B46: 钢筋混凝土面种植化学锚栓M8 | C46: 1.锚栓型号、规格:M8 2.化学胶管品牌:满足施工要求及技术规范 | D46: 按设计图示数量计算 | E46: 根 | G46: =(H46+I46+J46+K46)*(1+L46) -> 12.26312 | H46: =VLOOKUP(B46,'[1]2.1装饰工程'!$B$4:$H$354,7,0) -> 4.96 | I46: =VLOOKUP(B46,'[1]2.1装饰工程'!$B$4:$I$354,8,0) -> 5.06 | J46: =VLOOKUP(B46,'[1]2.1装饰工程'!$B$4:$J$354,9,0) -> 0 | K46: =VLOOKUP(B46,'[1]2.1装饰工程'!$B$4:$K$354,10,0) -> 0.14 | L46: =$L$4 -> 0.207 | M46: =F46*G46 -> 0
A47: 16 | B47: 钢筋混凝土面植化学锚栓M10 | C47: 1.锚栓型号、规格:M10 2.化学胶管品牌:满足施工要求及技术规范 | D47: 按设计图示数量计算 | E47: 根 | G47: =(H47+I47+J47+K47)*(1+L47) -> 13.38563 | H47: =VLOOKUP(B47,'[1]2.1装饰工程'!$B$4:$H$354,7,0) -> 5.32 | I47: =VLOOKUP(B47,'[1]2.1装饰工程'!$B$4:$I$354,8,0) -> 5.54 | J47: =VLOOKUP(B47,'[1]2.1装饰工程'!$B$4:$J$354,9,0) -> 0 | K47: =VLOOKUP(B47,'[1]2.1装饰工程'!$B$4:$K$354,10,0) -> 0.23 | L47: =$L$4 -> 0.207 | M47: =F47*G47 -> 0
A48: 17 | B48: 钢筋混凝土面植化学锚栓M12 | C48: 1.锚栓型号、规格:M12 2.化学胶管品牌:满足施工要求及技术规范 | D48: 按设计图示数量计算 | E48: 根 | G48: =(H48+I48+J48+K48)*(1+L48) -> 16.16173 | H48: =VLOOKUP(B48,'[1]2.1装饰工程'!$B$4:$H$354,7,0) -> 5.55 | I48: =VLOOKUP(B48,'[1]2.1装饰工程'!$B$4:$I$354,8,0) -> 7.59 | J48: =VLOOKUP(B48,'[1]2.1装饰工程'!$B$4:$J$354,9,0) -> 0 | K48: =VLOOKUP(B48,'[1]2.1装饰工程'!$B$4:$K$354,10,0) -> 0.25 | L48: =$L$4 -> 0.207 | M48: =F48*G48 -> 0
A49: 18 | B49: 钢筋混凝土面植化学锚栓M16 | C49: 1.锚栓型号、规格:M16 2.化学胶管品牌:满足施工要求及技术规范 | D49: 按设计图示数量计算 | E49: 根 | G49: =(H49+I49+J49+K49)*(1+L49) -> 20.98973 | H49: =VLOOKUP(B49,'[1]2.1装饰工程'!$B$4:$H$354,7,0) -> 7.97 | I49: =VLOOKUP(B49,'[1]2.1装饰工程'!$B$4:$I$354,8,0) -> 9.13 | J49: =VLOOKUP(B49,'[1]2.1装饰工程'!$B$4:$J$354,9,0) -> 0 | K49: =VLOOKUP(B49,'[1]2.1装饰工程'!$B$4:$K$354,10,0) -> 0.29 | L49: =$L$4 -> 0.207 | M49: =F49*G49 -> 0
A50: 19 | B50: 钢筋混凝土面植化学锚栓M20 | C50: 1.锚栓型号、规格:M20 2.化学胶管品牌:满足施工要求及技术规范 | D50: 按设计图示数量计算 | E50: 根 | G50: =(H50+I50+J50+K50)*(1+L50) -> 31.05611 | H50: =VLOOKUP(B50,'[1]2.1装饰工程'!$B$4:$H$354,7,0) -> 10.15 | I50: =VLOOKUP(B50,'[1]2.1装饰工程'!$B$4:$I$354,8,0) -> 15.19 | J50: =VLOOKUP(B50,'[1]2.1装饰工程'!$B$4:$J$354,9,0) -> 0 | K50: =VLOOKUP(B50,'[1]2.1装饰工程'!$B$4:$K$354,10,0) -> 0.39 | L50: =$L$4 -> 0.207 | M50: =F50*G50 -> 0
A51: 20 | B51: 钢筋混凝土面植化学锚栓M24 | C51: 1.锚栓型号、规格:M24 2.化学胶管品牌:满足施工要求及技术规范 | D51: 按设计图示数量计算 | E51: 根 | G51: =(H51+I51+J51+K51)*(1+L51) -> 40.25345 | H51: =VLOOKUP(B51,'[1]2.1装饰工程'!$B$4:$H$354,7,0) -> 10.22 | I51: =VLOOKUP(B51,'[1]2.1装饰工程'!$B$4:$I$354,8,0) -> 22.6 | J51: =VLOOKUP(B51,'[1]2.1装饰工程'!$B$4:$J$354,9,0) -> 0 | K51: =VLOOKUP(B51,'[1]2.1装饰工程'!$B$4:$K$354,10,0) -> 0.53 | L51: =$L$4 -> 0.207 | M51: =F51*G51 -> 0
A52: 21 | B52: 钢筋混凝土面植化学锚栓M28 | C52: 1.锚栓型号、规格:M28 2.化学胶管品牌:满足施工要求及技术规范 | D52: 按设计图示数量计算 | E52: 根 | G52: =(H52+I52+J52+K52)*(1+L52) -> 50.70607 | H52: =VLOOKUP(B52,'[1]2.1装饰工程'!$B$4:$H$354,7,0) -> 13.22 | I52: =VLOOKUP(B52,'[1]2.1装饰工程'!$B$4:$I$354,8,0) -> 28.26 | J52: =VLOOKUP(B52,'[1]2.1装饰工程'!$B$4:$J$354,9,0) -> 0 | K52: =VLOOKUP(B52,'[1]2.1装饰工程'!$B$4:$K$354,10,0) -> 0.53 | L52: =$L$4 -> 0.207 | M52: =F52*G52 -> 0
... A55: 24 | B55: 单层瓦楞板 | C55: 1.钢材品种、规格:综合考虑 2.规格：0.6mm，780板型热镀铝锌压型钢板 3.其他:详见SI手册、品牌表及标准节点等，满足施工要求及国家规范 | D55: 按设计图示尺寸以面积计算 | E55: m2 | G55: =(H55+I55+J55+K55)*(1+L55) -> 143.74163 | H55: =VLOOKUP(B55,'[1]2.1装饰工程'!$B$4:$H$354,7,0) -> 24.58 | I55: =VLOOKUP(B55,'[1]2.1装饰工程'!$B$4:$I$354,8,0) -> 93.07 | J55: =VLOOKUP(B55,'[1]2.1装饰工程'!$B$4:$J$354,9,0) -> 0 | K55: =VLOOKUP(B55,'[1]2.1装饰工程'!$B$4:$K$354,10,0) -> 1.44 | L55: =$L$4 -> 0.207 | M55: =F55*G55 -> 0
A56: 四 | B56: 装饰地面工程
A57: 1 | B57: 原地面做拉毛处理 | C57: 1.原始地面拉毛 2.其他:详见SI手册、品牌表及标准节点等，满足施工要求及国家规范 | D57: 工程量按设计图示尺寸以面积计算 | E57: m2 | F57: 2411.24 | G57: =(H57+I57+J57+K57)*(1+L57) -> 16.54797 | H57: =VLOOKUP(B57,'[1]2.1装饰工程'!$B$4:$H$354,7,0) -> 13.71 | I57: =VLOOKUP(B57,'[1]2.1装饰工程'!$B$4:$I$354,8,0) -> 0 | J57: =VLOOKUP(B57,'[1]2.1装饰工程'!$B$4:$J$354,9,0) -> 0 | K57: =VLOOKUP(B57,'[1]2.1装饰工程'!$B$4:$K$354,10,0) -> 0 | L57: =$L$4 -> 0.207 | M57: =F57*G57 -> 39901.127
A58: 2 | B58: 零星混凝土C15 | C58: 1.零星混凝土C15 2.工程量按体积计算 3.综合考虑模板、模板不另外计取 4.其他:详见SI手册、品牌表及标准节点等，满足施工要求及国家规范 | D58: 工程量按设计图示尺寸以体积计算 | E58: m3 | G58: =(H58+I58+J58+K58)*(1+L58) -> 787.49508 | H58: =VLOOKUP(B58,'[1]2.1装饰工程'!$B$4:$H$354,7,0) -> 187.87 | I58: =VLOOKUP(B58,'[1]2.1装饰工程'!$B$4:$I$354,8,0) -> 462.94 | J58: =VLOOKUP(B58,'[1]2.1装饰工程'!$B$4:$J$354,9,0) -> 0 | K58: =VLOOKUP(B58,'[1]2.1装饰工程'!$B$4:$K$354,10,0) -> 1.63 | L58: =$L$4 -> 0.207 | M58: =F58*G58 -> 0
A59: 3 | B59: 零星混凝土C20 | C59: 1.零星混凝土C20 2.工程量按体积计算 3.综合考虑模板、模板不另外计取 4.其他:详见SI手册、品牌表及标准节点等，满足施工要求及国家规范 | D59: 按设计图示尺寸以体积计算 | E59: m3 | G59: =(H59+I59+J59+K59)*(1+L59) -> 811.40575 | H59: =VLOOKUP(B59,'[1]2.1装饰工程'!$B$4:$H$354,7,0) -> 197.87 | I59: =VLOOKUP(B59,'[1]2.1装饰工程'!$B$4:$I$354,8,0) -> 472.75 | J59: =VLOOKUP(B59,'[1]2.1装饰工程'!$B$4:$J$354,9,0) -> 0 | K59: =VLOOKUP(B59,'[1]2.1装饰工程'!$B$4:$K$354,10,0) -> 1.63 | L59: =$L$4 -> 0.207 | M59: =F59*G59 -> 0
A60: 4 | B60: 零星混凝土C25 | C60: 1.零星混凝土C25 2.工程量按体积计算 3.综合考虑模板、模板不另外计取 4.其他:详见SI手册、品牌表及标准节点等，满足施工要求及国家规范 | D60: 按设计图示尺寸以体积计算 | E60: m3 | G60: =(H60+I60+J60+K60)*(1+L60) -> 859.45642 | H60: =VLOOKUP(B60,'[1]2.1装饰工程'!$B$4:$H$354,7,0) -> 187.87 | I60: =VLOOKUP(B60,'[1]2.1装饰工程'!$B$4:$I$354,8,0) -> 522.56 | J60: =VLOOKUP(B60,'[1]2.1装饰工程'!$B$4:$J$354,9,0) -> 0 | K60: =VLOOKUP(B60,'[1]2.1装饰工程'!$B$4:$K$354,10,0) -> 1.63 | L60: =$L$4 -> 0.207 | M60: =F60*G60 -> 0
A61: 5 | B61: 陶粒填充 | C61: 1.陶粒填充 2.其他:详见SI手册、品牌表及标准节点等，满足施工要求及国家规范 | D61: 按设计图示尺寸以体积计算 | E61: m3 | G61: =(H61+I61+J61+K61)*(1+L61) -> 582.95686 | H61: =VLOOKUP(B61,'[1]2.1装饰工程'!$B$4:$H$354,7,0) -> 97.06 | I61: =VLOOKUP(B61,'[1]2.1装饰工程'!$B$4:$I$354,8,0) -> 385.92 | J61: =VLOOKUP(B61,'[1]2.1装饰工程'!$B$4:$J$354,9,0) -> 0 | K61: =VLOOKUP(B61,'[1]2.1装饰工程'!$B$4:$K$354,10,0) -> 0 | L61: =$L$4 -> 0.207 | M61: =F61*G61 -> 0
A62: 6 | B62: 5mm水泥自流平基层 | C62: 1.5mm水泥自流平 2.其他:详见SI手册、品牌表及标准节点等，满足施工要求及国家规范 | D62: 工程量按设计图示尺寸以面积计算 | E62: m2 | F62: 106.33 | G62: =(H62+I62+J62+K62)*(1+L62) -> 46.11947 | H62: =VLOOKUP(B62,'[1]2.1装饰工程'!$B$4:$H$354,7,0) -> 26.26 | I62: =VLOOKUP(B62,'[1]2.1装饰工程'!$B$4:$I$354,8,0) -> 11.95 | J62: =VLOOKUP(B62,'[1]2.1装饰工程'!$B$4:$J$354,9,0) -> 0 | K62: =VLOOKUP(B62,'[1]2.1装饰工程'!$B$4:$K$354,10,0) -> 0 | L62: =$L$4 -> 0.207 | M62: =F62*G62 -> 4903.8832
A63: 7 | B63: 水泥自流平基层厚度每增减1mm | C63: 1.水泥自流平厚度每增减1mm 2.其他:详见SI手册、品牌表及标准节点等，满足施工要求及国家规范 | D63: 工程量按设计图示尺寸以面积计算 | E63: m2 | G63: =(H63+I63+J63+K63)*(1+L63) -> 8.12311 | H63: =VLOOKUP(B63,'[1]2.1装饰工程'!$B$4:$H$354,7,0) -> 3.54 | I63: =VLOOKUP(B63,'[1]2.1装饰工程'!$B$4:$I$354,8,0) -> 3.19 | J63: =VLOOKUP(B63,'[1]2.1装饰工程'!$B$4:$J$354,9,0) -> 0 | K63: =VLOOKUP(B63,'[1]2.1装饰工程'!$B$4:$K$354,10,0) -> 0 | L63: =$L$4 -> 0.207 | M63: =F63*G63 -> 0
A64: 8 | B64: 20mm地面水泥砂浆 | C64: 1.20厚水泥砂浆 2.其他:详见SI手册、品牌表及标准节点等，满足施工要求及国家规范 | D64: 工程量按设计图示尺寸以面积计算 | E64: m2 | F64: 106.33 | G64: =(H64+I64+J64+K64)*(1+L64) -> 31.04404 | H64: =VLOOKUP(B64,'[1]2.1装饰工程'!$B$4:$H$354,7,0) -> 11.6 | I64: =VLOOKUP(B64,'[1]2.1装饰工程'!$B$4:$I$354,8,0) -> 14.12 | J64: =VLOOKUP(B64,'[1]2.1装饰工程'!$B$4:$J$354,9,0) -> 0 | K64: =VLOOKUP(B64,'[1]2.1装饰工程'!$B$4:$K$354,10,0) -> 0 | L64: =$L$4 -> 0.207 | M64: =F64*G64 -> 3300.9128
A65: 9 | B65: 地面水泥砂浆厚度每增减10mm | C65: 1.地面水泥砂浆厚度每增减10mm 2.其他:详见SI手册、品牌表及标准节点等，满足施工要求及国家规范 | D65: 工程量按设计图示尺寸以面积计算 | E65: m2 | G65: =(H65+I65+J65+K65)*(1+L65) -> 11.49064 | H65: =VLOOKUP(B65,'[1]2.1装饰工程'!$B$4:$H$354,7,0) -> 2.66 | I65: =VLOOKUP(B65,'[1]2.1装饰工程'!$B$4:$I$354,8,0) -> 6.86 | J65: =VLOOKUP(B65,'[1]2.1装饰工程'!$B$4:$J$354,9,0) -> 0 | K65: =VLOOKUP(B65,'[1]2.1装饰工程'!$B$4:$K$354,10,0) -> 0 | L65: =$L$4 -> 0.207 | M65: =F65*G65 -> 0
A66: 10 | B66: 20mm厚细石混凝土找平（C15) | C66: 1.20厚细石混凝土找平+素水泥浆一道 2.混凝土等级：C15 3.包含止水坎综合考虑，其他:详见SI手册、品牌表及标准节点等，满足施工要求及国家规范 | D66: 工程量按设计图示尺寸以面积计算 | E66: m2 | F66: 1568.88 | G66: =(H66+I66+J66+K66)*(1+L66) -> 36.42726 | H66: 7.62 | I66: 22.5 | K66: 0.06 | L66: =$L$4 -> 0.207 | M66: =F66*G66 -> 57150
A67: 11 | B67: 20mm厚细石混凝土找平（C25) | C67: 1.20厚细石混凝土找平+素水泥浆一道 2.混凝土等级：C25 3.包含止水坎综合考虑，其他:详见SI手册、品牌表及标准节点等，满足施工要求及国家规范 | D67: 工程量按设计图示尺寸以面积计算 | E67: m2 | F67: 1568.88 | G67: =(H67+I67+J67+K67)*(1+L67) -> 39.60167 | H67: 7.62 | I67: 25.13 | K67: 0.06 | L67: =$L$4 -> 0.207 | M67: =F67*G67 -> 62130.268
A68: 12 | B68: 20mm厚细石混凝土找平（C30) | C68: 1.20厚细石混凝土找平+素水泥浆一道 2.混凝土等级：C30 3.包含止水坎综合考虑，其他:详见SI手册、品牌表及标准节点等，满足施工要求及国家规范 | D68: 工程量按设计图示尺寸以面积计算 | E68: m2 | G68: =(H68+I68+J68+K68)*(1+L68) -> 40.89316 | H68: 7.62 | I68: 26.2 | K68: 0.06 | L68: =$L$4 -> 0.207 | M68: =F68*G68 -> 0
A69: 13 | B69: 细石混凝土厚度每增减10mm（C15) | C69: 1.细石混凝土厚度每增减10mm 2.混凝土等级：C15 3.其他:详见SI手册、品牌表及标准节点等，满足施工要求及国家规范 | D69: 工程量按设计图示尺寸以面积计算 | E69: m2 | G69: =(H69+I69+J69+K69)*(1+L69) -> 9.94568 | H69: 0.74 | I69: 7.5 | K69: 0 | L69: =$L$4 -> 0.207 | M69: =F69*G69 -> 0
A70: 14 | B70: 细石混凝土厚度每增减10mm（C25) | C70: 1.细石混凝土厚度每增减10mm 2.混凝土等级：C25 3.其他:详见SI手册、品牌表及标准节点等，满足施工要求及国家规范 | D70: 工程量按设计图示尺寸以面积计算 | E70: m2 | G70: =(H70+I70+J70+K70)*(1+L70) -> 11.15268 | H70: 0.74 | I70: 8.5 | K70: 0 | L70: =$L$4 -> 0.207 | M70: =F70*G70 -> 0
A71: 15 | B71: 细石混凝土厚度每增减10mm（C30) | C71: 1.细石混凝土厚度每增减10mm 2.混凝土等级：C30 3.其他:详见SI手册、品牌表及标准节点等，满足施工要求及国家规范 | D71: 工程量按设计图示尺寸以面积计算 | E71: m2 | G71: =(H71+I71+J71+K71)*(1+L71) -> 11.99758 | H71: 0.74 | I71: 9.2 | K71: 0 | L71: =$L$4 -> 0.207 | M71: =F71*G71 -> 0
A72: 16 | B72: 钢丝网片满铺 | C72: 1.钢丝网片满铺 2.规格：直径6@200 3.其他:详见SI手册、品牌表及标准节点等，满足施工要求及国家规范 | D72: 工程量按设计图示尺寸以面积计算 | E72: m2 | F72: 732 | G72: =(H72+I72+J72+K72)*(1+L72) -> 24.11586 | H72: =VLOOKUP(B72,'[1]2.1装饰工程'!$B$4:$H$354,7,0) -> 7.28 | I72: =VLOOKUP(B72,'[1]2.1装饰工程'!$B$4:$I$354,8,0) -> 12.7 | J72: =VLOOKUP(B72,'[1]2.1装饰工程'!$B$4:$J$354,9,0) -> 0 | K72: =VLOOKUP(B72,'[1]2.1装饰工程'!$B$4:$K$354,10,0) -> 0 | L72: =$L$4 -> 0.207 | M72: =F72*G72 -> 17652.81
A73: 17 | B73: 界面剂一道 | C73: 1.界面剂一道 2.其他:详见SI手册、品牌表及标准节点等，满足施工要求及国家规范 | D73: 工程量按设计图示尺寸以面积计算 | E73: m2 | G73: =(H73+I73+J73+K73)*(1+L73) -> 9.36632 | H73: =VLOOKUP(B73,'[1]2.1装饰工程'!$B$4:$H$354,7,0) -> 5.79 | I73: =VLOOKUP(B73,'[1]2.1装饰工程'!$B$4:$I$354,8,0) -> 1.46 | J73: =VLOOKUP(B73,'[1]2.1装饰工程'!$B$4:$J$354,9,0) -> 0 | K73: =VLOOKUP(B73,'[1]2.1装饰工程'!$B$4:$K$354,10,0) -> 0.51 | L73: =$L$4 -> 0.207 | M73: =F73*G73 -> 0
A74: 18 | B74: 200*200地砖地面 | C74: 1.200*200防滑地砖+专用瓷砖胶（10mm厚，哑光面，颜色综合考虑） 2.地砖间留5mm缝隙，勾缝 3.60厚水泥砂浆找平层，30厚1:3干性水泥砂浆粘结层 4..包含止水坎、卫生间找坡，卫生间蹲坑侧面等综合考虑，地插、地漏部位提前预留 5.其他:详见SI手册、品牌表及标准节点等，满足施工要求及国家规范 | D74: 工程量按设计图示尺寸以实铺面积计算 | E74: m2 | F74: 630.76 | G74: =(H74+I74+J74+K74)*(1+L74) -> 224.94859 | H74: =VLOOKUP(B74,'[1]2.1装饰工程'!$B$4:$H$354,7,0) -> 45.1 | I74: =VLOOKUP(B74,'[1]2.1装饰工程'!$B$4:$I$354,8,0) -> 141.27 | J74: =VLOOKUP(B74,'[1]2.1装饰工程'!$B$4:$J$354,9,0) -> 0 | K74: =VLOOKUP(B74,'[1]2.1装饰工程'!$B$4:$K$354,10,0) -> 0 | L74: =$L$4 -> 0.207 | M74: =F74*G74 -> 141888.57
A75: 19 | B75: 300*600地砖地面 | C75: 1.300*600防滑地砖+专用瓷砖胶（10mm±1mm厚，哑光面，颜色综合考虑） 2.地砖间留2mm缝隙，美缝剂填缝 3.60厚水泥砂浆找平层，30厚1:3干性水泥砂浆粘结层 4.包含止水坎、卫生间找坡，卫生间蹲坑侧面等综合考虑，地插、地漏部位提前预留 5.其他:详见SI手册、品牌表及标准节点等，满足施工要求及国家规范 | D75: 工程量按设计图示尺寸以实铺面积计算 | E75: m2 | G75: =(H75+I75+J75+K75)*(1+L75) -> 223.66917 | H75: =VLOOKUP(B75,'[1]2.1装饰工程'!$B$4:$H$354,7,0) -> 44.03 | I75: =VLOOKUP(B75,'[1]2.1装饰工程'!$B$4:$I$354,8,0) -> 141.28 | J75: =VLOOKUP(B75,'[1]2.1装饰工程'!$B$4:$J$354,9,0) -> 0 | K75: =VLOOKUP(B75,'[1]2.1装饰工程'!$B$4:$K$354,10,0) -> 0 | L75: =$L$4 -> 0.207 | M75: =F75*G75 -> 0
A76: 20 | B76: 600*600地砖地面 | C76: 1.600*600防滑地砖+专用瓷砖胶（10mm±1mm厚，哑光面，颜色综合考虑） 2.地砖间留2mm缝隙，美缝剂填缝 3.60厚水泥砂浆找平层，30厚1:3干性水泥砂浆粘结层 4.包含止水坎、卫生间找坡，卫生间蹲坑侧面等综合考虑，地插、地漏部位提前预留 5.其他:详见SI手册、品牌表及标准节点等，满足施工要求及国家规范 | D76: 工程量按设计图示尺寸以实铺面积计算 | E76: m2 | F76: 101.75 | G76: =(H76+I76+J76+K76)*(1+L76) -> 218.84117 | H76: =VLOOKUP(B76,'[1]2.1装饰工程'!$B$4:$H$354,7,0) -> 40.03 | I76: =VLOOKUP(B76,'[1]2.1装饰工程'!$B$4:$I$354,8,0) -> 141.28 | J76: =VLOOKUP(B76,'[1]2.1装饰工程'!$B$4:$J$354,9,0) -> 0 | K76: =VLOOKUP(B76,'[1]2.1装饰工程'!$B$4:$K$354,10,0) -> 0 | L76: =$L$4 -> 0.207 | M76: =F76*G76 -> 22267.089
A77: 21 | B77: 仿木纹砖地面 | C77: 1.仿木纹砖地面+专用瓷砖胶（1200*1200mm，10mm±2mm厚，同色美缝剂，颜色综合考虑） 2.地砖间留2mm缝隙，美缝剂填缝 3.60厚水泥砂浆找平层，30厚1:3干性水泥砂浆粘结层 4.包含止水坎、卫生间找坡，卫生间蹲坑侧面等综合考虑，地插、地漏部位提前预留 5.整体厚度综合考虑，含找平等基层，其他:详见SI手册、品牌表及标准节点等，满足施工要求及国家规范 | D77: 工程量按设计图示尺寸以实铺面积计算 | E77: m2 | G77: =(H77+I77+J77+K77)*(1+L77) -> 242.92082 | H77: =VLOOKUP(B77,'[1]2.1装饰工程'!$B$4:$H$354,7,0) -> 44.03 | I77: =VLOOKUP(B77,'[1]2.1装饰工程'!$B$4:$I$354,8,0) -> 157.23 | J77: =VLOOKUP(B77,'[1]2.1装饰工程'!$B$4:$J$354,9,0) -> 0 | K77: =VLOOKUP(B77,'[1]2.1装饰工程'!$B$4:$K$354,10,0) -> 0 | L77: =$L$4 -> 0.207 | M77: =F77*G77 -> 0
A78: 22 | B78: 水磨石砖地面 | C78: 1.600*1200水磨石砖地砖+专用瓷砖胶（10mm±1mm厚，颜色综合考虑） 2.地砖间留2mm缝隙，美缝剂填缝 3.60厚水泥砂浆找平层，30厚1:3干性水泥砂浆粘结层 4.包含止水坎、卫生间找坡，卫生间蹲坑侧面等综合考虑，地插、地漏部位提前预留 5.其他:详见SI手册、品牌表及标准节点等，满足施工要求及国家规范 | D78: 工程量按设计图示尺寸以实铺面积计算 | E78: m2 | F78: 730.04 | G78: =(H78+I78+J78+K78)*(1+L78) -> 247.1936 | H78: =VLOOKUP(B78,'[1]2.1装饰工程'!$B$4:$H$354,7,0) -> 44.03 | I78: =VLOOKUP(B78,'[1]2.1装饰工程'!$B$4:$I$354,8,0) -> 160.77 | J78: =VLOOKUP(B78,'[1]2.1装饰工程'!$B$4:$J$354,9,0) -> 0 | K78: =VLOOKUP(B78,'[1]2.1装饰工程'!$B$4:$K$354,10,0) -> 0 | L78: =$L$4 -> 0.207 | M78: =F78*G78 -> 180461.22
A79: 23 | B79: 仿水磨石地胶 | C79: 1.仿水磨石地胶 2.规格：3mm厚卷材 3.基层：专用粘结剂 4.其他:详见SI手册、品牌表及标准节点等，满足施工要求及国家规范 | D79: 工程量按设计图示尺寸以实铺面积计算 | E79: m2 | G79: =(H79+I79+J79+K79)*(1+L79) -> 155.79956 | H79: 59.71 | I79: 69.31 | K79: 0.06 | L79: =$L$4 -> 0.207 | M79: =F79*G79 -> 0
A80: 24 | B80: 过门石地面 | C80: 1.过门石地面+专用胶（15mm厚，颜色综合考虑） 2.地砖间留2mm缝隙，美缝剂填缝 3.60厚水泥砂浆找平层，30厚1:3干性水泥砂浆粘结层 4.整体厚度综合考虑，含找平等基层，其他:详见SI手册、品牌表及标准节点等，满足施工要求及国家规范 | D80: 工程量按设计图示尺寸以实铺面积计算 | E80: m2 | G80: =(H80+I80+J80+K80)*(1+L80) -> 427.68838 | H80: =VLOOKUP(B80,'[1]2.1装饰工程'!$B$4:$H$354,7,0) -> 50.28 | I80: =VLOOKUP(B80,'[1]2.1装饰工程'!$B$4:$I$354,8,0) -> 304.06 | J80: =VLOOKUP(B80,'[1]2.1装饰工程'!$B$4:$J$354,9,0) -> 0 | K80: =VLOOKUP(B80,'[1]2.1装饰工程'!$B$4:$K$354,10,0) -> 0 | L80: =$L$4 -> 0.207 | M80: =F80*G80 -> 0
A81: 25 | B81: 网络防静电地板 | C81: 1.网络静电地板（600*600mm，颜色综合考虑） 2.可调节支架系统（铜带防静电） 3.1：3水泥砂浆抹面压实赶光 4.其他:详见SI手册、品牌表及标准节点等，满足施工要求及国家规范 | D81: 工程量按设计图示尺寸以实铺面积计算 | E81: m2 | F81: 14.8 | G81: =(H81+I81+J81+K81)*(1+L81) -> 319.855 | H81: =VLOOKUP(B81,'[1]2.1装饰工程'!$B$4:$H$354,7,0) -> 56.82 | I81: =VLOOKUP(B81,'[1]2.1装饰工程'!$B$4:$I$354,8,0) -> 208.18 | J81: =VLOOKUP(B81,'[1]2.1装饰工程'!$B$4:$J$354,9,0) -> 0 | K81: =VLOOKUP(B81,'[1]2.1装饰工程'!$B$4:$K$354,10,0) -> 0 | L81: =$L$4 -> 0.207 | M81: =F81*G81 -> 4733.854
A82: 26 | B82: 环氧自流平地面 | C82: 1.3mm环氧自流平 2.其他:详见SI手册、品牌表及标准节点等，满足施工要求及国家规范 | D82: 工程量按设计图示尺寸以实铺面积计算 | E82: m2 | F82: 758.4 | G82: =(H82+I82+J82+K82)*(1+L82) -> 93.09591 | H82: =VLOOKUP(B82,'[1]2.1装饰工程'!$B$4:$H$354,7,0) -> 26.99 | I82: =VLOOKUP(B82,'[1]2.1装饰工程'!$B$4:$I$354,8,0) -> 50.14 | J82: =VLOOKUP(B82,'[1]2.1装饰工程'!$B$4:$J$354,9,0) -> 0 | K82: =VLOOKUP(B82,'[1]2.1装饰工程'!$B$4:$K$354,10,0) -> 0 | L82: =$L$4 -> 0.207 | M82: =F82*G82 -> 70603.938
A83: 27 | B83: 室内地面划线 | C83: 1.室内地面划线 2.材质：环氧地坪漆 3.颜色：按图纸要求 4.宽度：100mm企业标准字体 5.其他:详见SI手册、品牌表及标准节点等，满足施工要求及国家规范 | D83: 工程量按设计图示尺寸以米计算 | E83: m | G83: =(H83+I83+J83+K83)*(1+L83) -> 15.832078 | H83: 2.487013 | I83: 10 | J83: 0.5 | K83: 0.12987013 | L83: =$L$4 -> 0.207 | M83: =F83*G83 -> 0
A84: 28 | B84: 室内地面喷字 | C84: 1.室内地面喷字 2.材质：环氧地坪漆 3.颜色：按图纸要求 4.宽度：100mm企业标准字体 5.其他:详见SI手册、品牌表及标准节点等，满足施工要求及国家规范 | D84: 工程量按设计图示数量以个计算 | E84: 个 | G84: =(H84+I84+J84+K84)*(1+L84) -> 55.32888 | H84: 12.44 | I84: 23.4 | J84: 8.5 | K84: 1.5 | L84: =$L$4 -> 0.207 | M84: =F84*G84 -> 0
A85: 29 | B85: 石材散水台 | C85: 1.石材散水台（20mm）+专用瓷砖胶 2.20水泥砂浆找平层 3.20细石混凝土填充层 4.包含止水坎综合考虑 5.其他:详见SI手册、品牌表及标准节点等，满足施工要求及国家规范 | D85: 工程量按设计图示尺寸以实铺面积计算 | E85: m2 | G85: =(H85+I85+J85+K85)*(1+L85) -> 481.56886 | H85: =VLOOKUP(B85,'[1]2.1装饰工程'!$B$4:$H$354,7,0) -> 59.82 | I85: =VLOOKUP(B85,'[1]2.1装饰工程'!$B$4:$I$354,8,0) -> 339.1 | J85: =VLOOKUP(B85,'[1]2.1装饰工程'!$B$4:$J$354,9,0) -> 0 | K85: =VLOOKUP(B85,'[1]2.1装饰工程'!$B$4:$K$354,10,0) -> 0.06 | L85: =$L$4 -> 0.207 | M85: =F85*G85 -> 0
A86: 30 | B86: 防滑瓷砖楼梯踏步面层 | C86: 1.防滑瓷砖面层（10mm±1mm厚）+专用粘接剂 2.防滑槽处理+不锈钢金属条综合考虑 3.20厚水泥砂浆找平层 4.其他:详见SI手册、品牌表及标准节点等，满足施工要求及国家规范 | D86: 工程量按设计图示尺寸以实铺面积计算 | E86: m2 | G86: =(H86+I86+J86+K86)*(1+L86) -> 271.24911 | H86: =VLOOKUP(B86,'[1]2.1装饰工程'!$B$4:$H$354,7,0) -> 104.08 | I86: =VLOOKUP(B86,'[1]2.1装饰工程'!$B$4:$I$354,8,0) -> 120.65 | J86: =VLOOKUP(B86,'[1]2.1装饰工程'!$B$4:$J$354,9,0) -> 0 | K86: =VLOOKUP(B86,'[1]2.1装饰工程'!$B$4:$K$354,10,0) -> 0 | L86: =$L$4 -> 0.207 | M86: =F86*G86 -> 0
A87: 31 | B87: 防尘垫 | C87: 1.防尘垫（厚度：20mm铝型材壁厚度≥2mm，颜色综合考虑） 2.包含四周金属嵌条等综合考虑 3.其他:详见SI手册、品牌表及标准节点等，满足施工要求及国家规范 | D87: 工程量按设计图示尺寸以面积计算 | E87: m2 | F87: 4.98 | G87: =(H87+I87+J87+K87)*(1+L87) -> 657.05459 | H87: =VLOOKUP(B87,'[1]2.1装饰工程'!$B$4:$H$354,7,0) -> 56.94 | I87: =VLOOKUP(B87,'[1]2.1装饰工程'!$B$4:$I$354,8,0) -> 487.43 | J87: =VLOOKUP(B87,'[1]2.1装饰工程'!$B$4:$J$354,9,0) -> 0 | K87: =VLOOKUP(B87,'[1]2.1装饰工程'!$B$4:$K$354,10,0) -> 0 | L87: =$L$4 -> 0.207 | M87: =F87*G87 -> 3272.1319
A88: 32 | B88: 塑料格栅 | C88: 1.塑料格栅 2.厚度：不低于30mm 3.包含止水坎综合考虑 4.其他:详见SI手册、品牌表及标准节点等，满足施工要求及国家规范 | D88: 工程量按设计图示尺寸以实铺面积计算 | E88: m2 | F88: 106.33 | G88: =(H88+I88+J88+K88)*(1+L88) -> 134.88225 | H88: =VLOOKUP(B88,'[1]2.1装饰工程'!$B$4:$H$354,7,0) -> 37.33 | I88: =VLOOKUP(B88,'[1]2.1装饰工程'!$B$4:$I$354,8,0) -> 73.85 | J88: =VLOOKUP(B88,'[1]2.1装饰工程'!$B$4:$J$354,9,0) -> 0 | K88: =VLOOKUP(B88,'[1]2.1装饰工程'!$B$4:$K$354,10,0) -> 0.57 | L88: =$L$4 -> 0.207 | M88: =F88*G88 -> 14342.03
A89: 33 | B89: 3mm成品实心不锈钢收口条 | C89: 1.展厅地面不同材质处拼接处用3mm成品不锈钢金属嵌条，高度尺寸可调 2.其他:详见SI手册、品牌表及标准节点等，满足施工要求及国家规范 | D89: 按设计图示以长度计算 | E89: m | G89: =(H89+I89+J89+K89)*(1+L89) -> 39.44476 | H89: =VLOOKUP(B89,'[1]2.1装饰工程'!$B$4:$H$354,7,0) -> 3.24 | I89: =VLOOKUP(B89,'[1]2.1装饰工程'!$B$4:$I$354,8,0) -> 29.44 | J89: =VLOOKUP(B89,'[1]2.1装饰工程'!$B$4:$J$354,9,0) -> 0 | K89: =VLOOKUP(B89,'[1]2.1装饰工程'!$B$4:$K$354,10,0) -> 0 | L89: =$L$4 -> 0.207 | M89: =F89*G89 -> 0
A90: 34 | B90: 5mm成品实心不锈钢收口条 | C90: 1.成品实心金属收口条1.展厅地面不同材质处拼接处用5mm成品不锈钢金属嵌条，高度尺寸可调 2.工程量按水平长度计算 3.其他:详见SI手册、品牌表及标准节点等，满足施工要求及国家规范 | D90: 按设计图示以长度计算 | E90: m | F90: 29.03 | G90: =(H90+I90+J90+K90)*(1+L90) -> 45.1418 | H90: =VLOOKUP(B90,'[1]2.1装饰工程'!$B$4:$H$354,7,0) -> 3.24 | I90: =VLOOKUP(B90,'[1]2.1装饰工程'!$B$4:$I$354,8,0) -> 34.16 | J90: =VLOOKUP(B90,'[1]2.1装饰工程'!$B$4:$J$354,9,0) -> 0 | K90: =VLOOKUP(B90,'[1]2.1装饰工程'!$B$4:$K$354,10,0) -> 0 | L90: =$L$4 -> 0.207 | M90: =F90*G90 -> 1310.4665
A91: 35 | B91: 平面防水层（JS防水） | C91: 1.JS防水层一道+防水保护层 2.其他:详见SI手册、品牌表及标准节点等，满足施工要求及国家规范 | D91: 工程量按设计图示尺寸以面积计算 | E91: m2 | G91: =(H91+I91+J91+K91)*(1+L91) -> 71.626724 | H91: =VLOOKUP(B91,'[1]2.1装饰工程'!$B$4:$H$354,7,0) -> 16.15 | I91: =VLOOKUP(B91,'[1]2.1装饰工程'!$B$4:$I$354,8,0) -> 42.08 | J91: 0.55 | K91: 0.56277056 | L91: =$L$4 -> 0.207 | M91: =F91*G91 -> 0
A92: 36 | B92: 平面防水层（聚氨酯防水） | C92: 1.聚氨酯防水层一道+防水保护层 2.其他:详见SI手册、品牌表及标准节点等，满足施工要求及国家规范 | D92: 工程量按设计图示尺寸以面积计算 | E92: m2 | G92: =(H92+I92+J92+K92)*(1+L92) -> 68.605671 | H92: 15.727056 | I92: 40 | J92: 0.55 | K92: 0.56277056 | L92: =$L$4 -> 0.207 | M92: =F92*G92 -> 0
A93: 37 | B93: 立面防水层（JS防水） | C93: 1.JS防水层一道+防水保护层 2.其他:详见SI手册、品牌表及标准节点等，满足施工要求及国家规范 | D93: 工程量按设计图示尺寸以面积计算 | E93: m2 | F93: 414.71 | G93: =(H93+I93+J93+K93)*(1+L93) -> 67.160824 | H93: =VLOOKUP(B93,'[1]2.1装饰工程'!$B$4:$H$354,7,0) -> 19.33 | I93: =VLOOKUP(B93,'[1]2.1装饰工程'!$B$4:$I$354,8,0) -> 35.2 | J93: 0.55 | K93: 0.56277056 | L93: =$L$4 -> 0.207 | M93: =F93*G93 -> 27852.265
A94: 38 | B94: 立面防水层（聚氨酯防水） | C94: 1.聚氨酯防水层一道+防水保护层 2.其他:详见SI手册、品牌表及标准节点等，满足施工要求及国家规范 | D94: 工程量按设计图示尺寸以面积计算 | E94: m2 | G94: =(H94+I94+J94+K94)*(1+L94) -> 67.550199 | H94: 19.851255 | I94: 35 | J94: 0.56 | K94: 0.55411255 | L94: =$L$4 -> 0.207 | M94: =F94*G94 -> 0
A95: 39 | B95: 2mm厚高密度聚乙烯 | C95: 1.2mm厚高密度聚乙烯 2.其他:详见SI手册、品牌表及标准节点等，满足施工要求及国家规范 | D95: 工程量按设计图示尺寸以面积计算 | E95: m2 | G95: =(H95+I95+J95+K95)*(1+L95) -> 65.25042 | H95: =VLOOKUP(B95,'[1]2.1装饰工程'!$B$4:$H$354,7,0) -> 4.42 | I95: =VLOOKUP(B95,'[1]2.1装饰工程'!$B$4:$I$354,8,0) -> 49.64 | J95: =VLOOKUP(B95,'[1]2.1装饰工程'!$B$4:$J$354,9,0) -> 0 | K95: =VLOOKUP(B95,'[1]2.1装饰工程'!$B$4:$K$354,10,0) -> 0 | L95: =$L$4 -> 0.207 | M95: =F95*G95 -> 0
A96: 40 | B96: 地面钢盖板排水沟 | C96: 1.地面钢盖板排水沟（350mm宽） 2.包含：镀锌钢盖板+下挂防漏铁丝网(厚3.8mm，承重6T)，30*30*3镀锌角铁，10mm厚1:2水泥砂浆抹面，C30混凝土找坡，1.5mm厚防水层 2.其他:详见SI手册、品牌表及标准节点等，满足施工要求及国家规范 | D96: 工程量按设计图示尺寸以长度计算 | E96: m | G96: =(H96+I96+J96+K96)*(1+L96) -> 603.27067 | H96: =VLOOKUP(B96,'[1]2.1装饰工程'!$B$4:$H$354,7,0) -> 78.84 | I96: =VLOOKUP(B96,'[1]2.1装饰工程'!$B$4:$I$354,8,0) -> 412.93 | J96: =VLOOKUP(B96,'[1]2.1装饰工程'!$B$4:$J$354,9,0) -> 0 | K96: =VLOOKUP(B96,'[1]2.1装饰工程'!$B$4:$K$354,10,0) -> 8.04 | L96: =$L$4 -> 0.207 | M96: =F96*G96 -> 0
A97: 41 | B97: 地面玻璃钢格栅盖板排水沟 | C97: 1.地面玻璃钢格栅盖板排水沟（350mm宽） 2.包含：玻璃钢格栅盖板+下挂防漏铁丝网(厚3.8mm，承重6T)，30*30*3镀锌角铁，10mm厚1:2水泥砂浆抹面，C30混凝土找坡，1.5mm厚防水层 2.其他:详见SI手册、品牌表及标准节点等，满足施工要求及国家规范 | D97: 工程量按设计图示尺寸以长度计算 | E97: m | G97: =(H97+I97+J97+K97)*(1+L97) -> 379.69806 | H97: =VLOOKUP(B97,'[1]2.1装饰工程'!$B$4:$H$354,7,0) -> 78.84 | I97: =VLOOKUP(B97,'[1]2.1装饰工程'!$B$4:$I$354,8,0) -> 227.7 | J97: =VLOOKUP(B97,'[1]2.1装饰工程'!$B$4:$J$354,9,0) -> 0 | K97: =VLOOKUP(B97,'[1]2.1装饰工程'!$B$4:$K$354,10,0) -> 8.04 | L97: =$L$4 -> 0.207 | M97: =F97*G97 -> 0
A98: 42 | B98: 地面塑料格栅盖板排水沟 | C98: 1.地面塑料格栅盖板排水沟（350mm宽） 2.包含：塑料格栅盖板+下挂防漏铁丝网(厚3.8mm，承重6T)，30*30*3镀锌角铁，10mm厚1:2水泥砂浆抹面，C30混凝土找坡，1.5mm厚防水层 2.其他:详见SI手册、品牌表及标准节点等，满足施工要求及国家规范 | D98: 工程量按设计图示尺寸以长度计算 | E98: m | G98: =(H98+I98+J98+K98)*(1+L98) -> 347.9781 | H98: =VLOOKUP(B98,'[1]2.1装饰工程'!$B$4:$H$354,7,0) -> 78.84 | I98: =VLOOKUP(B98,'[1]2.1装饰工程'!$B$4:$I$354,8,0) -> 201.42 | J98: =VLOOKUP(B98,'[1]2.1装饰工程'!$B$4:$J$354,9,0) -> 0 | K98: =VLOOKUP(B98,'[1]2.1装饰工程'!$B$4:$K$354,10,0) -> 8.04 | L98: =$L$4 -> 0.207 | M98: =F98*G98 -> 0
A99: 43 | B99: 零星钢构件 | C99: 1.零星钢构件 2.钢材品种、规格：根据图纸综合考虑、螺栓不另外计取 3.工作内容：场内外驳运、制作、安装 4.其他:详见SI手册、品牌表及标准节点等，满足施工要求及国家规范 | D99: 按设计图示以质量计算 | E99: t | F99: 9.26 | G99: =(H99+I99+J99+K99)*(1+L99) -> 10639.319 | H99: =VLOOKUP(B99,'[1]2.1装饰工程'!$B$4:$H$354,7,0) -> 1499.31 | I99: =VLOOKUP(B99,'[1]2.1装饰工程'!$B$4:$I$354,8,0) -> 6890.11 | J99: =VLOOKUP(B99,'[1]2.1装饰工程'!$B$4:$J$354,9,0) -> 0 | K99: =VLOOKUP(B99,'[1]2.1装饰工程'!$B$4:$K$354,10,0) -> 425.26 | L99: =$L$4 -> 0.207 | M99: =F99*G99 -> 98520.092
A100: 44 | B100: 建筑伸缩缝处理 | C100: 1.3mm厚铝合金中心板 2.中轴控制杆、止水带等包含制作所需的所有工艺及材料 3.其他:详见SI手册、品牌表及标准节点等，满足施工要求及国家规范 | D100: 按设计图示以长度计算 | E100: m | G100: =(H100+I100+J100+K100)*(1+L100) -> 190.53702 | H100: =VLOOKUP(B100,'[1]2.1装饰工程'!$B$4:$H$354,7,0) -> 44.66 | I100: =VLOOKUP(B100,'[1]2.1装饰工程'!$B$4:$I$354,8,0) -> 113.2 | J100: =VLOOKUP(B100,'[1]2.1装饰工程'!$B$4:$J$354,9,0) -> 0 | K100: =VLOOKUP(B100,'[1]2.1装饰工程'!$B$4:$K$354,10,0) -> 0 | L100: =$L$4 -> 0.207 | M100: =F100*G100 -> 0
A101: 45 | B101: 铝合金踢脚线 | C101: 1.1mm成品材质铝合金板,高度50mm（颜色见设计图），内衬基层板 2.明装、暗装综合考虑，详见图纸设计要求 3.其他:详见SI手册、品牌表及标准节点等，满足施工要求及国家规范 | D101: 按设计图示以长度计算 | E101: m | F101: 60 | G101: =(H101+I101+J101+K101)*(1+L101) -> 50.30776 | H101: =VLOOKUP(B101,'[1]2.1装饰工程'!$B$4:$H$354,7,0) -> 19.04 | I101: =VLOOKUP(B101,'[1]2.1装饰工程'!$B$4:$I$354,8,0) -> 22.64 | J101: =VLOOKUP(B101,'[1]2.1装饰工程'!$B$4:$J$354,9,0) -> 0 | K101: =VLOOKUP(B101,'[1]2.1装饰工程'!$B$4:$K$354,10,0) -> 0 | L101: =$L$4 -> 0.207 | M101: =F101*G101 -> 3018.4656
A102: 46 | B102: 不锈钢踢脚线 | C102: 1.1.2mm黑色不锈钢+基层板（颜色见设计图）,高度50mm 2.明装、暗装综合考虑，详见图纸设计要求 3.其他:详见SI手册、品牌表及标准节点等，满足施工要求及国家规范 | D102: 按设计图示以长度计算 | E102: m | F102: 60 | G102: =(H102+I102+J102+K102)*(1+L102) -> 54.23051 | H102: =VLOOKUP(B102,'[1]2.1装饰工程'!$B$4:$H$354,7,0) -> 19.04 | I102: =VLOOKUP(B102,'[1]2.1装饰工程'!$B$4:$I$354,8,0) -> 25.89 | J102: =VLOOKUP(B102,'[1]2.1装饰工程'!$B$4:$J$354,9,0) -> 0 | K102: =VLOOKUP(B102,'[1]2.1装饰工程'!$B$4:$K$354,10,0) -> 0 | L102: =$L$4 -> 0.207 | M102: =F102*G102 -> 3253.8306
...

Sheet 2.2强电工程
A1: 长城智选中心店装修项目装饰工程
A2: 序号 | B2: 分部分项名称 | C2: 项目特征 | D2: 计量规则 | E2: 单位 | F2: 工程量 | G2: 综合单价 | H2: 人工 | I2: 主材 | J2: 辅材 | K2: 机械 | L2: 其他综合费率 | M2: 合计 | N2: 备注
A3: 一 | B3: 配电系统
A4: 1 | B4: 落地式配电箱 | C4: 1.名称:落地式配电箱 2.基础形式、材质、规格:10#基础槽钢 3.接线端子材质、规格:按设计及规范要求 4.端子板外部接线材质、规格:按设计及规范要求 5.安装方式:落地式 6.其他:含智能电表、时控开关、电气元器件及配套附件成套费用 | D4: 按设计图示数量计算 | E4: 台 | F4: 2 | G4: =(H4+I4+J4+K4)*(1+L4) -> 9919.126 | H4: =VLOOKUP(B4,'[1]2.2强电工程'!$B$4:$H$254,7,0) -> 524.73 | I4: =VLOOKUP(B4,'[1]2.2强电工程'!$B$4:$I$254,8,0) -> 7637.4 | J4: =VLOOKUP(B4,'[1]2.2强电工程'!$B$4:$J$254,9,0) -> 36.96 | K4: =VLOOKUP(B4,'[1]2.2强电工程'!$B$4:$K$254,10,0) -> 18.91 | L4: ='2.1装饰工程'!$L$4 -> 0.207 | M4: =F4*G4 -> 19838.252
A5: 2 | B5: 落地式配电箱（IP65防水型） | C5: 1.名称:落地式配电箱（IP65防水型） 2.基础形式、材质、规格:10#基础槽钢 3.接线端子材质、规格:按设计及规范要求 4.端子板外部接线材质、规格:按设计及规范要求 5.安装方式:落地式 6.其他:含智能电表、时控开关、电气元器件及配套附件成套费用 | D5: 按设计图示数量计算 | E5: 台 | F5: 2 | G5: =(H5+I5+J5+K5)*(1+L5) -> 10239.572 | H5: =VLOOKUP(B5,'[1]2.2强电工程'!$B$4:$H$254,7,0) -> 524.73 | I5: =VLOOKUP(B5,'[1]2.2强电工程'!$B$4:$I$254,8,0) -> 7902.89 | J5: =VLOOKUP(B5,'[1]2.2强电工程'!$B$4:$J$254,9,0) -> 36.96 | K5: =VLOOKUP(B5,'[1]2.2强电工程'!$B$4:$K$254,10,0) -> 18.91 | L5: =$L$4 -> 0.207 | M5: =F5*G5 -> 20479.145
A6: 3 | B6: 配电箱 | C6: 1.名称::配电箱（嵌入/悬挂） 2.规格:半周长2.5m 3.接线端子材质、规格:按设计及规范要求 4.端子板外部接线材质、规格:按设计及规范要求 5.安装方式:悬挂式 6.其他:含智能电表、时控开关、电气元器件及配套附件成套费用 | D6: 按设计图示数量计算 | E6: 台 | F6: 2 | G6: =(H6+I6+J6+K6)*(1+L6) -> 4683.7876 | H6: 448.4 | I6: 3407.08 | J6: 21.43 | K6: 3.61 | L6: =$L$4 -> 0.207 | M6: =F6*G6 -> 9367.5753
A7: 4 | B7: 配电箱 | C7: 1.名称::配电箱（嵌入/悬挂） 2.规格:半周长1.5m 3.接线端子材质、规格:按设计及规范要求 4.端子板外部接线材质、规格:按设计及规范要求 5.安装方式:悬挂式 6.其他:含智能电表、时控开关、电气元器件及配套附件成套费用 | D7: 按设计图示数量计算 | E7: 台 | F7: 3 | G7: =(H7+I7+J7+K7)*(1+L7) -> 2698.9003 | H7: 373.78 | I7: 1840.71 | J7: 17.94 | K7: 3.61 | L7: =$L$4 -> 0.207 | M7: =F7*G7 -> 8096.7008
A8: 5 | B8: 配电箱 | C8: 1.名称::配电箱（嵌入/悬挂） 2.规格:半周长1.0m 3.接线端子材质、规格:按设计及规范要求 4.端子板外部接线材质、规格:按设计及规范要求 5.安装方式:悬挂式 6.其他:含智能电表、时控开关、电气元器件及配套附件成套费用 | D8: 按设计图示数量计算 | E8: 台 | F8: 3 | G8: =(H8+I8+J8+K8)*(1+L8) -> 1447.5551 | H8: 249.11 | I8: 929.2 | J8: 17.38 | K8: 3.61 | L8: =$L$4 -> 0.207 | M8: =F8*G8 -> 4342.6653
A9: 6 | B9: 配电箱 | C9: 1.名称::配电箱（嵌入/悬挂） 2.规格:半周长0.5m 3.接线端子材质、规格:按设计及规范要求 4.端子板外部接线材质、规格:按设计及规范要求 5.安装方式:悬挂式 6.其他:含智能电表、时控开关、电气元器件及配套附件成套费用 | D9: 按设计图示数量计算 | E9: 台 | F9: 3 | G9: =(H9+I9+J9+K9)*(1+L9) -> 844.86379 | H9: 166.08 | I9: 513.27 | J9: 17.01 | K9: 3.61 | L9: =$L$4 -> 0.207 | M9: =F9*G9 -> 2534.5914
A10: 7 | B10: 应急照明配电箱 | C10: 1.名称:应急照明配电箱 2.接线端子材质、规格:按设计及规范要求 3.端子板外部接线材质、规格:按设计及规范要求 4.其他:含元器件及配套附件成套费用 | D10: 按设计图示数量计算 | E10: 台 | F10: 1 | G10: =(H10+I10+J10+K10)*(1+L10) -> 3570.5836 | H10: =VLOOKUP(B10,'[1]2.2强电工程'!$B$4:$H$254,7,0) -> 398.21 | I10: =VLOOKUP(B10,'[1]2.2强电工程'!$B$4:$I$254,8,0) -> 2500 | J10: =VLOOKUP(B10,'[1]2.2强电工程'!$B$4:$J$254,9,0) -> 41.11 | K10: =VLOOKUP(B10,'[1]2.2强电工程'!$B$4:$K$254,10,0) -> 18.91 | L10: =$L$4 -> 0.207 | M10: =F10*G10 -> 3570.5836
A11: 8 | B11: 电缆WDZA-YJV-3*240+2*120 | C11: 1.名称:电力电缆 2.型号:WDZA-YJV 3.规格:3*240+2*120 4.材质:铜芯 5.敷设方式、部位:桥架内及配管内敷设 6.电压等级(kV):1.0KV | D11: 按设计图示尺寸以长度计算（含预留长度及附加长度） | E11: m | G11: =(H11+I11+J11+K11)*(1+L11) -> 856.16131 | H11: =VLOOKUP(B11,'[1]2.2强电工程'!$B$4:$H$254,7,0) -> 28.73 | I11: =VLOOKUP(B11,'[1]2.2强电工程'!$B$4:$I$254,8,0) -> 676.29 | J11: =VLOOKUP(B11,'[1]2.2强电工程'!$B$4:$J$254,9,0) -> 1.99 | K11: =VLOOKUP(B11,'[1]2.2强电工程'!$B$4:$K$254,10,0) -> 2.32 | L11: =$L$4 -> 0.207 | M11: =F11*G11 -> 0
A12: 9 | B12: 电缆WDZA-YJV-3*185+2*95 | C12: 1.名称:电力电缆 2.型号:WDZA-YJV 3.规格:3*185+2*95 4.材质:铜芯 5.敷设方式、部位:桥架内及配管内敷设 6.电压等级(kV):1.0KV | D12: 按设计图示尺寸以长度计算（含预留长度及附加长度） | E12: m | F12: 162.21 | G12: =(H12+I12+J12+K12)*(1+L12) -> 670.39194 | H12: =VLOOKUP(B12,'[1]2.2强电工程'!$B$4:$H$254,7,0) -> 28.73 | I12: =VLOOKUP(B12,'[1]2.2强电工程'!$B$4:$I$254,8,0) -> 522.38 | J12: =VLOOKUP(B12,'[1]2.2强电工程'!$B$4:$J$254,9,0) -> 1.99 | K12: =VLOOKUP(B12,'[1]2.2强电工程'!$B$4:$K$254,10,0) -> 2.32 | L12: =$L$4 -> 0.207 | M12: =F12*G12 -> 108744.28
A13: 10 | B13: 电缆WDZA-YJV-3*150+2*70 | C13: 1.名称:电力电缆 2.型号:WDZA-YJV 3.规格:3*150+2*70 4.材质:铜芯 5.敷设方式、部位:桥架内及配管内敷设 6.电压等级(kV):1.0KV | D13: 按设计图示尺寸以长度计算（含预留长度及附加长度） | E13: m | G13: =(H13+I13+J13+K13)*(1+L13) -> 532.84222 | H13: =VLOOKUP(B13,'[1]2.2强电工程'!$B$4:$H$254,7,0) -> 28.73 | I13: =VLOOKUP(B13,'[1]2.2强电工程'!$B$4:$I$254,8,0) -> 408.42 | J13: =VLOOKUP(B13,'[1]2.2强电工程'!$B$4:$J$254,9,0) -> 1.99 | K13: =VLOOKUP(B13,'[1]2.2强电工程'!$B$4:$K$254,10,0) -> 2.32 | L13: =$L$4 -> 0.207 | M13: =F13*G13 -> 0
A14: 11 | B14: 电缆WDZA-YJV-3*120+2*70 | C14: 1.名称:电力电缆 2.型号:WDZA-YJV 3.规格:3*120+2*70 4.材质:铜芯 5.敷设方式、部位:桥架内及配管内敷设 6.电压等级(kV):1.0KV | D14: 按设计图示尺寸以长度计算（含预留长度及附加长度） | E14: m | F14: 20 | G14: =(H14+I14+J14+K14)*(1+L14) -> 451.06797 | H14: =VLOOKUP(B14,'[1]2.2强电工程'!$B$4:$H$254,7,0) -> 20.72 | I14: =VLOOKUP(B14,'[1]2.2强电工程'!$B$4:$I$254,8,0) -> 350.6 | J14: =VLOOKUP(B14,'[1]2.2强电工程'!$B$4:$J$254,9,0) -> 1.25 | K14: =VLOOKUP(B14,'[1]2.2强电工程'!$B$4:$K$254,10,0) -> 1.14 | L14: =$L$4 -> 0.207 | M14: =F14*G14 -> 9021.3594
A15: 12 | B15: 电缆WDZA-YJV-3*95+2*50 | C15: 1.名称:电力电缆 2.型号:WDZA-YJV 3.规格:3*95+2*50 4.材质:铜芯 5.敷设方式、部位:桥架内及配管内敷设 6.电压等级(kV):1.0KV | D15: 按设计图示尺寸以长度计算（含预留长度及附加长度） | E15: m | G15: =(H15+I15+J15+K15)*(1+L15) -> 353.13199 | H15: =VLOOKUP(B15,'[1]2.2强电工程'!$B$4:$H$254,7,0) -> 20.72 | I15: =VLOOKUP(B15,'[1]2.2强电工程'!$B$4:$I$254,8,0) -> 269.46 | J15: =VLOOKUP(B15,'[1]2.2强电工程'!$B$4:$J$254,9,0) -> 1.25 | K15: =VLOOKUP(B15,'[1]2.2强电工程'!$B$4:$K$254,10,0) -> 1.14 | L15: =$L$4 -> 0.207 | M15: =F15*G15 -> 0
A16: 13 | B16: 电缆WDZA-YJV-3*70+2*35 | C16: 1.名称:电力电缆 2.型号:WDZA-YJV 3.规格:3*70+2*35 4.材质:铜芯 5.敷设方式、部位:桥架内及配管内敷设 6.电压等级(kV):1.0KV | D16: 按设计图示尺寸以长度计算（含预留长度及附加长度） | E16: m | G16: =(H16+I16+J16+K16)*(1+L16) -> 261.15859 | H16: =VLOOKUP(B16,'[1]2.2强电工程'!$B$4:$H$254,7,0) -> 17.42 | I16: =VLOOKUP(B16,'[1]2.2强电工程'!$B$4:$I$254,8,0) -> 196.8 | J16: =VLOOKUP(B16,'[1]2.2强电工程'!$B$4:$J$254,9,0) -> 1.01 | K16: =VLOOKUP(B16,'[1]2.2强电工程'!$B$4:$K$254,10,0) -> 1.14 | L16: =$L$4 -> 0.207 | M16: =F16*G16 -> 0
A17: 14 | B17: 电缆WDZA-YJV-3*50+2*25 | C17: 1.名称:电力电缆 2.型号:WDZA-YJV 3.规格:3*50+2*25 4.材质:铜芯 5.敷设方式、部位:桥架内及配管内敷设 6.电压等级(kV):1.0KV | D17: 按设计图示尺寸以长度计算（含预留长度及附加长度） | E17: m | G17: =(H17+I17+J17+K17)*(1+L17) -> 191.50262 | H17: =VLOOKUP(B17,'[1]2.2强电工程'!$B$4:$H$254,7,0) -> 17.42 | I17: =VLOOKUP(B17,'[1]2.2强电工程'!$B$4:$I$254,8,0) -> 139.09 | J17: =VLOOKUP(B17,'[1]2.2强电工程'!$B$4:$J$254,9,0) -> 1.01 | K17: =VLOOKUP(B17,'[1]2.2强电工程'!$B$4:$K$254,10,0) -> 1.14 | L17: =$L$4 -> 0.207 | M17: =F17*G17 -> 0
A18: 15 | B18: 电缆WDZA-YJV-3*35+2*16 | C18: 1.名称:电力电缆 2.型号:WDZA-YJV 3.规格:3*35+2*16 4.材质:铜芯 5.敷设方式、部位:桥架内及配管内敷设 6.电压等级(kV):1.0KV | D18: 按设计图示尺寸以长度计算（含预留长度及附加长度） | E18: m | G18: =(H18+I18+J18+K18)*(1+L18) -> 134.84604 | H18: =VLOOKUP(B18,'[1]2.2强电工程'!$B$4:$H$254,7,0) -> 11.07 | I18: =VLOOKUP(B18,'[1]2.2强电工程'!$B$4:$I$254,8,0) -> 99.38 | J18: =VLOOKUP(B18,'[1]2.2强电工程'!$B$4:$J$254,9,0) -> 1.11 | K18: =VLOOKUP(B18,'[1]2.2强电工程'!$B$4:$K$254,10,0) -> 0.16 | L18: =$L$4 -> 0.207 | M18: =F18*G18 -> 0
A19: 16 | B19: 电缆WDZA-YJV-3*25+2*16 | C19: 1.名称:电力电缆 2.型号:WDZA-YJV 3.规格:3*25+2*16 4.材质:铜芯 5.敷设方式、部位:桥架内及配管内敷设 6.电压等级(kV):1.0KV | D19: 按设计图示尺寸以长度计算（含预留长度及附加长度） | E19: m | G19: =(H19+I19+J19+K19)*(1+L19) -> 112.16651 | H19: =VLOOKUP(B19,'[1]2.2强电工程'!$B$4:$H$254,7,0) -> 11.07 | I19: =VLOOKUP(B19,'[1]2.2强电工程'!$B$4:$I$254,8,0) -> 80.59 | J19: =VLOOKUP(B19,'[1]2.2强电工程'!$B$4:$J$254,9,0) -> 1.11 | K19: =VLOOKUP(B19,'[1]2.2强电工程'!$B$4:$K$254,10,0) -> 0.16 | L19: =$L$4 -> 0.207 | M19: =F19*G19 -> 0
A20: 17 | B20: 电缆WDZA-YJV-4*185+1*95 | C20: 1.名称:电力电缆 2.型号:WDZA-YJV 3.规格:4*185+1*95 4.材质:铜芯 5.敷设方式、部位:桥架内及配管内敷设 6.电压等级(kV):1.0KV | D20: 按设计图示尺寸以长度计算（含预留长度及附加长度） | E20: m | G20: =(H20+I20+J20+K20)*(1+L20) -> 745.47941 | H20: =VLOOKUP(B20,'[1]2.2强电工程'!$B$4:$H$254,7,0) -> 28.73 | I20: =VLOOKUP(B20,'[1]2.2强电工程'!$B$4:$I$254,8,0) -> 584.59 | J20: =VLOOKUP(B20,'[1]2.2强电工程'!$B$4:$J$254,9,0) -> 1.99 | K20: =VLOOKUP(B20,'[1]2.2强电工程'!$B$4:$K$254,10,0) -> 2.32 | L20: =$L$4 -> 0.207 | M20: =F20*G20 -> 0
A21: 18 | B21: 电缆WDZA-YJV-4*150+1*70 | C21: 1.名称:电力电缆 2.型号:WDZA-YJV 3.规格:4*150+1*70 4.材质:铜芯 5.敷设方式、部位:桥架内及配管内敷设 6.电压等级(kV):1.0KV | D21: 按设计图示尺寸以长度计算（含预留长度及附加长度） | E21: m | G21: =(H21+I21+J21+K21)*(1+L21) -> 599.09445 | H21: =VLOOKUP(B21,'[1]2.2强电工程'!$B$4:$H$254,7,0) -> 28.73 | I21: =VLOOKUP(B21,'[1]2.2强电工程'!$B$4:$I$254,8,0) -> 463.31 | J21: =VLOOKUP(B21,'[1]2.2强电工程'!$B$4:$J$254,9,0) -> 1.99 | K21: =VLOOKUP(B21,'[1]2.2强电工程'!$B$4:$K$254,10,0) -> 2.32 | L21: =$L$4 -> 0.207 | M21: =F21*G21 -> 0
A22: 19 | B22: 电缆WDZA-YJV-4*120+1*70 | C22: 1.名称:电力电缆 2.型号:WDZA-YJV 3.规格:4*120+1*70 4.材质:铜芯 5.敷设方式、部位:桥架内及配管内敷设 6.电压等级(kV):1.0KV | D22: 按设计图示尺寸以长度计算（含预留长度及附加长度） | E22: m | G22: =(H22+I22+J22+K22)*(1+L22) -> 493.72335 | H22: =VLOOKUP(B22,'[1]2.2强电工程'!$B$4:$H$254,7,0) -> 20.72 | I22: =VLOOKUP(B22,'[1]2.2强电工程'!$B$4:$I$254,8,0) -> 385.94 | J22: =VLOOKUP(B22,'[1]2.2强电工程'!$B$4:$J$254,9,0) -> 1.25 | K22: =VLOOKUP(B22,'[1]2.2强电工程'!$B$4:$K$254,10,0) -> 1.14 | L22: =$L$4 -> 0.207 | M22: =F22*G22 -> 0
A23: 20 | B23: 电缆WDZA-YJV-4*95+1*50 | C23: 1.名称:电力电缆 2.型号:WDZA-YJV 3.规格:4*95+1*50 4.材质:铜芯 5.敷设方式、部位:桥架内及配管内敷设 6.电压等级(kV):1.0KV | D23: 按设计图示尺寸以长度计算（含预留长度及附加长度） | E23: m | G23: =(H23+I23+J23+K23)*(1+L23) -> 392.74573 | H23: =VLOOKUP(B23,'[1]2.2强电工程'!$B$4:$H$254,7,0) -> 20.72 | I23: =VLOOKUP(B23,'[1]2.2强电工程'!$B$4:$I$254,8,0) -> 302.28 | J23: =VLOOKUP(B23,'[1]2.2强电工程'!$B$4:$J$254,9,0) -> 1.25 | K23: =VLOOKUP(B23,'[1]2.2强电工程'!$B$4:$K$254,10,0) -> 1.14 | L23: =$L$4 -> 0.207 | M23: =F23*G23 -> 0
A24: 21 | B24: 电缆WDZA-YJV-4*70+1*35 | C24: 1.名称:电力电缆 2.型号:WDZA-YJV 3.规格:4*70+1*35 4.材质:铜芯 5.敷设方式、部位:桥架内及配管内敷设 6.电压等级(kV):1.0KV | D24: 按设计图示尺寸以长度计算（含预留长度及附加长度） | E24: m | G24: =(H24+I24+J24+K24)*(1+L24) -> 289.53516 | H24: =VLOOKUP(B24,'[1]2.2强电工程'!$B$4:$H$254,7,0) -> 17.42 | I24: =VLOOKUP(B24,'[1]2.2强电工程'!$B$4:$I$254,8,0) -> 220.31 | J24: =VLOOKUP(B24,'[1]2.2强电工程'!$B$4:$J$254,9,0) -> 1.01 | K24: =VLOOKUP(B24,'[1]2.2强电工程'!$B$4:$K$254,10,0) -> 1.14 | L24: =$L$4 -> 0.207 | M24: =F24*G24 -> 0
A25: 22 | B25: 电缆WDZA-YJV-4*50+1*25 | C25: 1.名称:电力电缆 2.型号:WDZA-YJV 3.规格:4*50+1*25 4.材质:铜芯 5.敷设方式、部位:桥架内及配管内敷设 6.电压等级(kV):1.0KV | D25: 按设计图示尺寸以长度计算（含预留长度及附加长度） | E25: m | G25: =(H25+I25+J25+K25)*(1+L25) -> 209.64383 | H25: =VLOOKUP(B25,'[1]2.2强电工程'!$B$4:$H$254,7,0) -> 17.42 | I25: =VLOOKUP(B25,'[1]2.2强电工程'!$B$4:$I$254,8,0) -> 154.12 | J25: =VLOOKUP(B25,'[1]2.2强电工程'!$B$4:$J$254,9,0) -> 1.01 | K25: =VLOOKUP(B25,'[1]2.2强电工程'!$B$4:$K$254,10,0) -> 1.14 | L25: =$L$4 -> 0.207 | M25: =F25*G25 -> 0
A26: 23 | B26: 电缆WDZA-YJV-4*35+1*16 | C26: 1.名称:电力电缆 2.型号:WDZA-YJV 3.规格:4*35+1*16 4.材质:铜芯 5.敷设方式、部位:桥架内及配管内敷设 6.电压等级(kV):1.0KV | D26: 按设计图示尺寸以长度计算（含预留长度及附加长度） | E26: m | G26: =(H26+I26+J26+K26)*(1+L26) -> 150.33185 | H26: =VLOOKUP(B26,'[1]2.2强电工程'!$B$4:$H$254,7,0) -> 11.07 | I26: =VLOOKUP(B26,'[1]2.2强电工程'!$B$4:$I$254,8,0) -> 112.21 | J26: =VLOOKUP(B26,'[1]2.2强电工程'!$B$4:$J$254,9,0) -> 1.11 | K26: =VLOOKUP(B26,'[1]2.2强电工程'!$B$4:$K$254,10,0) -> 0.16 | L26: =$L$4 -> 0.207 | M26: =F26*G26 -> 0
A27: 24 | B27: 电缆WDZA-YJV-4*25+1*16 | C27: 1.名称:电力电缆 2.型号:WDZA-YJV 3.规格:4*25+1*16 4.材质:铜芯 5.敷设方式、部位:桥架内及配管内敷设 6.电压等级(kV):1.0KV | D27: 按设计图示尺寸以长度计算（含预留长度及附加长度） | E27: m | G27: =(H27+I27+J27+K27)*(1+L27) -> 119.6137 | H27: =VLOOKUP(B27,'[1]2.2强电工程'!$B$4:$H$254,7,0) -> 11.07 | I27: =VLOOKUP(B27,'[1]2.2强电工程'!$B$4:$I$254,8,0) -> 86.76 | J27: =VLOOKUP(B27,'[1]2.2强电工程'!$B$4:$J$254,9,0) -> 1.11 | K27: =VLOOKUP(B27,'[1]2.2强电工程'!$B$4:$K$254,10,0) -> 0.16 | L27: =$L$4 -> 0.207 | M27: =F27*G27 -> 0
A28: 25 | B28: 电缆WDZA-YJV-5*16 | C28: 1.名称:电力电缆 2.型号:WDZA-YJV 3.规格:5*16 4.材质:铜芯 5.敷设方式、部位:桥架内及配管内敷设 6.电压等级(kV):1.0KV | D28: 按设计图示尺寸以长度计算（含预留长度及附加长度） | E28: m | F28: 65.01 | G28: =(H28+I28+J28+K28)*(1+L28) -> 89.46284 | H28: =VLOOKUP(B28,'[1]2.2强电工程'!$B$4:$H$254,7,0) -> 11.07 | I28: =VLOOKUP(B28,'[1]2.2强电工程'!$B$4:$I$254,8,0) -> 61.78 | J28: =VLOOKUP(B28,'[1]2.2强电工程'!$B$4:$J$254,9,0) -> 1.11 | K28: =VLOOKUP(B28,'[1]2.2强电工程'!$B$4:$K$254,10,0) -> 0.16 | L28: =$L$4 -> 0.207 | M28: =F28*G28 -> 5815.9792
A29: 26 | B29: 电缆WDZA-YJV-5*10 | C29: 1.名称:电力电缆 2.型号:WDZA-YJV 3.规格:5*10 4.材质:铜芯 5.敷设方式、部位:桥架内及配管内敷设 6.电压等级(kV):1.0KV | D29: 按设计图示尺寸以长度计算（含预留长度及附加长度） | E29: m | G29: =(H29+I29+J29+K29)*(1+L29) -> 57.51355 | H29: =VLOOKUP(B29,'[1]2.2强电工程'!$B$4:$H$254,7,0) -> 6.12 | I29: =VLOOKUP(B29,'[1]2.2强电工程'!$B$4:$I$254,8,0) -> 40.53 | J29: =VLOOKUP(B29,'[1]2.2强电工程'!$B$4:$J$254,9,0) -> 1 | K29: =VLOOKUP(B29,'[1]2.2强电工程'!$B$4:$K$254,10,0) -> 0 | L29: =$L$4 -> 0.207 | M29: =F29*G29 -> 0
A30: 27 | B30: 电缆WDZA-YJV-5*6 | C30: 1.名称:电力电缆 2.型号:WDZA-YJV 3.规格:5*6 4.材质:铜芯 5.敷设方式、部位:桥架内及配管内敷设 6.电压等级(kV):1.0KV | D30: 按设计图示尺寸以长度计算（含预留长度及附加长度） | E30: m | F30: 450.46 | G30: =(H30+I30+J30+K30)*(1+L30) -> 57.86358 | H30: =VLOOKUP(B30,'[1]2.2强电工程'!$B$4:$H$254,7,0) -> 11.07 | I30: 35.6 | J30: =VLOOKUP(B30,'[1]2.2强电工程'!$B$4:$J$254,9,0) -> 1.11 | K30: =VLOOKUP(B30,'[1]2.2强电工程'!$B$4:$K$254,10,0) -> 0.16 | L30: =$L$4 -> 0.207 | M30: =F30*G30 -> 26065.228
A31: 28 | B31: 电缆WDZA-YJV-5*4 | C31: 1.名称:电力电缆 2.型号:WDZA-YJV 3.规格:5*4 4.材质:铜芯 5.敷设方式、部位:桥架内及配管内敷设 6.电压等级(kV):1.0KV | D31: 按设计图示尺寸以长度计算（含预留长度及附加长度） | E31: m | F31: 14.3 | G31: =(H31+I31+J31+K31)*(1+L31) -> 30.44054 | H31: =VLOOKUP(B31,'[1]2.2强电工程'!$B$4:$H$254,7,0) -> 4.57 | I31: =VLOOKUP(B31,'[1]2.2强电工程'!$B$4:$I$254,8,0) -> 19.57 | J31: =VLOOKUP(B31,'[1]2.2强电工程'!$B$4:$J$254,9,0) -> 1.08 | K31: =VLOOKUP(B31,'[1]2.2强电工程'!$B$4:$K$254,10,0) -> 0 | L31: =$L$4 -> 0.207 | M31: =F31*G31 -> 435.29972
A32: 29 | B32: 电缆WDZA-YJV-3*6 | C32: 1.名称:电力电缆 2.型号:WDZA-YJV 3.规格:3*6 4.材质:铜芯 5.敷设方式、部位:桥架内及配管内敷设 6.电压等级(kV):1.0KV | D32: 按设计图示尺寸以长度计算（含预留长度及附加长度） | E32: m | G32: =(H32+I32+J32+K32)*(1+L32) -> 50.50088 | H32: =VLOOKUP(B32,'[1]2.2强电工程'!$B$4:$H$254,7,0) -> 11.07 | I32: 29.5 | J32: =VLOOKUP(B32,'[1]2.2强电工程'!$B$4:$J$254,9,0) -> 1.11 | K32: =VLOOKUP(B32,'[1]2.2强电工程'!$B$4:$K$254,10,0) -> 0.16 | L32: =$L$4 -> 0.207 | M32: =F32*G32 -> 0
A33: 30 | B33: 电缆WDZA-YJV-3*10 | C33: 1.名称:电力电缆 2.型号:WDZA-YJV 3.规格:3*10 4.材质:铜芯 5.敷设方式、部位:桥架内及配管内敷设 6.电压等级(kV):1.0KV | D33: 按设计图示尺寸以长度计算（含预留长度及附加长度） | E33: m | G33: =(H33+I33+J33+K33)*(1+L33) -> 38.841365 | H33: 4.5614719 | I33: 27.17 | J33: 0.13 | K33: 0.31861472 | L33: =$L$4 -> 0.207 | M33: =F33*G33 -> 0
A34: 31 | B34: 电缆WDZB-YJV-3*240+2*120 | C34: 1.名称:电力电缆 2.型号:WDZB-YJV 3.规格:3*240+2*120 4.材质:铜芯 5.敷设方式、部位:桥架内及配管内敷设 6.电压等级(kV):1.0KV | D34: 按设计图示尺寸以长度计算（含预留长度及附加长度） | E34: m | G34: =(H34+I34+J34+K34)*(1+L34) -> 848.21925 | H34: =VLOOKUP(B34,'[1]2.2强电工程'!$B$4:$H$254,7,0) -> 28.73 | I34: =VLOOKUP(B34,'[1]2.2强电工程'!$B$4:$I$254,8,0) -> 669.71 | J34: =VLOOKUP(B34,'[1]2.2强电工程'!$B$4:$J$254,9,0) -> 1.99 | K34: =VLOOKUP(B34,'[1]2.2强电工程'!$B$4:$K$254,10,0) -> 2.32 | L34: =$L$4 -> 0.207 | M34: =F34*G34 -> 0
A35: 32 | B35: 电缆WDZB-YJV-3*185+2*95 | C35: 1.名称:电力电缆 2.型号:WDZB-YJV 3.规格:3*185+2*95 4.材质:铜芯 5.敷设方式、部位:桥架内及配管内敷设 6.电压等级(kV):1.0KV | D35: 按设计图示尺寸以长度计算（含预留长度及附加长度） | E35: m | G35: =(H35+I35+J35+K35)*(1+L35) -> 663.7293 | H35: =VLOOKUP(B35,'[1]2.2强电工程'!$B$4:$H$254,7,0) -> 28.73 | I35: =VLOOKUP(B35,'[1]2.2强电工程'!$B$4:$I$254,8,0) -> 516.86 | J35: =VLOOKUP(B35,'[1]2.2强电工程'!$B$4:$J$254,9,0) -> 1.99 | K35: =VLOOKUP(B35,'[1]2.2强电工程'!$B$4:$K$254,10,0) -> 2.32 | L35: =$L$4 -> 0.207 | M35: =F35*G35 -> 0
A36: 33 | B36: 电缆WDZB-YJV-3*150+2*70 | C36: 1.名称:电力电缆 2.型号:WDZB-YJV 3.规格:3*150+2*70 4.材质:铜芯 5.敷设方式、部位:桥架内及配管内敷设 6.电压等级(kV):1.0KV | D36: 按设计图示尺寸以长度计算（含预留长度及附加长度） | E36: m | G36: =(H36+I36+J36+K36)*(1+L36) -> 527.27795 | H36: =VLOOKUP(B36,'[1]2.2强电工程'!$B$4:$H$254,7,0) -> 28.73 | I36: =VLOOKUP(B36,'[1]2.2强电工程'!$B$4:$I$254,8,0) -> 403.81 | J36: =VLOOKUP(B36,'[1]2.2强电工程'!$B$4:$J$254,9,0) -> 1.99 | K36: =VLOOKUP(B36,'[1]2.2强电工程'!$B$4:$K$254,10,0) -> 2.32 | L36: =$L$4 -> 0.207 | M36: =F36*G36 -> 0
A37: 34 | B37: 电缆WDZB-YJV-3*120+2*70 | C37: 1.名称:电力电缆 2.型号:WDZB-YJV 3.规格:3*120+2*70 4.材质:铜芯 5.敷设方式、部位:桥架内及配管内敷设 6.电压等级(kV):1.0KV | D37: 按设计图示尺寸以长度计算（含预留长度及附加长度） | E37: m | G37: =(H37+I37+J37+K37)*(1+L37) -> 446.14341 | H37: =VLOOKUP(B37,'[1]2.2强电工程'!$B$4:$H$254,7,0) -> 20.72 | I37: =VLOOKUP(B37,'[1]2.2强电工程'!$B$4:$I$254,8,0) -> 346.52 | J37: =VLOOKUP(B37,'[1]2.2强电工程'!$B$4:$J$254,9,0) -> 1.25 | K37: =VLOOKUP(B37,'[1]2.2强电工程'!$B$4:$K$254,10,0) -> 1.14 | L37: =$L$4 -> 0.207 | M37: =F37*G37 -> 0
A38: 35 | B38: 电缆WDZB-YJV-3*95+2*50 | C38: 1.名称:电力电缆 2.型号:WDZB-YJV 3.规格:3*95+2*50 4.材质:铜芯 5.敷设方式、部位:桥架内及配管内敷设 6.电压等级(kV):1.0KV | D38: 按设计图示尺寸以长度计算（含预留长度及附加长度） | E38: m | F38: 124.67 | G38: =(H38+I38+J38+K38)*(1+L38) -> 348.96784 | H38: =VLOOKUP(B38,'[1]2.2强电工程'!$B$4:$H$254,7,0) -> 20.72 | I38: =VLOOKUP(B38,'[1]2.2强电工程'!$B$4:$I$254,8,0) -> 266.01 | J38: =VLOOKUP(B38,'[1]2.2强电工程'!$B$4:$J$254,9,0) -> 1.25 | K38: =VLOOKUP(B38,'[1]2.2强电工程'!$B$4:$K$254,10,0) -> 1.14 | L38: =$L$4 -> 0.207 | M38: =F38*G38 -> 43505.821
A39: 36 | B39: 电缆WDZB-YJV-3*70+2*35 | C39: 1.名称:电力电缆 2.型号:WDZB-YJV 3.规格:3*70+2*35 4.材质:铜芯 5.敷设方式、部位:桥架内及配管内敷设 6.电压等级(kV):1.0KV | D39: 按设计图示尺寸以长度计算（含预留长度及附加长度） | E39: m | G39: =(H39+I39+J39+K39)*(1+L39) -> 257.48931 | H39: =VLOOKUP(B39,'[1]2.2强电工程'!$B$4:$H$254,7,0) -> 17.42 | I39: =VLOOKUP(B39,'[1]2.2强电工程'!$B$4:$I$254,8,0) -> 193.76 | J39: =VLOOKUP(B39,'[1]2.2强电工程'!$B$4:$J$254,9,0) -> 1.01 | K39: =VLOOKUP(B39,'[1]2.2强电工程'!$B$4:$K$254,10,0) -> 1.14 | L39: =$L$4 -> 0.207 | M39: =F39*G39 -> 0
A40: 37 | B40: 电缆WDZB-YJV-3*50+2*25 | C40: 1.名称:电力电缆 2.型号:WDZB-YJV 3.规格:3*50+2*25 4.材质:铜芯 5.敷设方式、部位:桥架内及配管内敷设 6.电压等级(kV):1.0KV | D40: 按设计图示尺寸以长度计算（含预留长度及附加长度） | E40: m | G40: =(H40+I40+J40+K40)*(1+L40) -> 188.59375 | H40: =VLOOKUP(B40,'[1]2.2强电工程'!$B$4:$H$254,7,0) -> 17.42 | I40: =VLOOKUP(B40,'[1]2.2强电工程'!$B$4:$I$254,8,0) -> 136.68 | J40: =VLOOKUP(B40,'[1]2.2强电工程'!$B$4:$J$254,9,0) -> 1.01 | K40: =VLOOKUP(B40,'[1]2.2强电工程'!$B$4:$K$254,10,0) -> 1.14 | L40: =$L$4 -> 0.207 | M40: =F40*G40 -> 0
A41: 38 | B41: 电缆WDZB-YJV-3*35+2*16 | C41: 1.名称:电力电缆 2.型号:WDZB-YJV 3.规格:3*35+2*16 4.材质:铜芯 5.敷设方式、部位:桥架内及配管内敷设 6.电压等级(kV):1.0KV | D41: 按设计图示尺寸以长度计算（含预留长度及附加长度） | E41: m | G41: =(H41+I41+J41+K41)*(1+L41) -> 133.6149 | H41: =VLOOKUP(B41,'[1]2.2强电工程'!$B$4:$H$254,7,0) -> 11.07 | I41: =VLOOKUP(B41,'[1]2.2强电工程'!$B$4:$I$254,8,0) -> 98.36 | J41: =VLOOKUP(B41,'[1]2.2强电工程'!$B$4:$J$254,9,0) -> 1.11 | K41: =VLOOKUP(B41,'[1]2.2强电工程'!$B$4:$K$254,10,0) -> 0.16 | L41: =$L$4 -> 0.207 | M41: =F41*G41 -> 0
A42: 39 | B42: 电缆WDZB-YJV-3*25+2*16 | C42: 1.名称:电力电缆 2.型号:WDZB-YJV 3.规格:3*25+2*16 4.材质:铜芯 5.敷设方式、部位:桥架内及配管内敷设 6.电压等级(kV):1.0KV | D42: 按设计图示尺寸以长度计算（含预留长度及附加长度） | E42: m | F42: 124.67 | G42: =(H42+I42+J42+K42)*(1+L42) -> 110.33187 | H42: =VLOOKUP(B42,'[1]2.2强电工程'!$B$4:$H$254,7,0) -> 11.07 | I42: =VLOOKUP(B42,'[1]2.2强电工程'!$B$4:$I$254,8,0) -> 79.07 | J42: =VLOOKUP(B42,'[1]2.2强电工程'!$B$4:$J$254,9,0) -> 1.11 | K42: =VLOOKUP(B42,'[1]2.2强电工程'!$B$4:$K$254,10,0) -> 0.16 | L42: =$L$4 -> 0.207 | M42: =F42*G42 -> 13755.074
A43: 40 | B43: 电缆WDZB-YJV-4*185+1*95 | C43: 1.名称:电力电缆 2.型号:WDZB-YJV 3.规格:4*185+1*95 4.材质:铜芯 5.敷设方式、部位:桥架内及配管内敷设 6.电压等级(kV):1.0KV | D43: 按设计图示尺寸以长度计算（含预留长度及附加长度） | E43: m | G43: =(H43+I43+J43+K43)*(1+L43) -> 738.28569 | H43: =VLOOKUP(B43,'[1]2.2强电工程'!$B$4:$H$254,7,0) -> 28.73 | I43: =VLOOKUP(B43,'[1]2.2强电工程'!$B$4:$I$254,8,0) -> 578.63 | J43: =VLOOKUP(B43,'[1]2.2强电工程'!$B$4:$J$254,9,0) -> 1.99 | K43: =VLOOKUP(B43,'[1]2.2强电工程'!$B$4:$K$254,10,0) -> 2.32 | L43: =$L$4 -> 0.207 | M43: =F43*G43 -> 0
A44: 41 | B44: 电缆WDZB-YJV-4*150+1*70 | C44: 1.名称:电力电缆 2.型号:WDZB-YJV 3.规格:4*150+1*70 4.材质:铜芯 5.敷设方式、部位:桥架内及配管内敷设 6.电压等级(kV):1.0KV | D44: 按设计图示尺寸以长度计算（含预留长度及附加长度） | E44: m | G44: =(H44+I44+J44+K44)*(1+L44) -> 592.91461 | H44: =VLOOKUP(B44,'[1]2.2强电工程'!$B$4:$H$254,7,0) -> 28.73 | I44: =VLOOKUP(B44,'[1]2.2强电工程'!$B$4:$I$254,8,0) -> 458.19 | J44: =VLOOKUP(B44,'[1]2.2强电工程'!$B$4:$J$254,9,0) -> 1.99 | K44: =VLOOKUP(B44,'[1]2.2强电工程'!$B$4:$K$254,10,0) -> 2.32 | L44: =$L$4 -> 0.207 | M44: =F44*G44 -> 0
A45: 42 | B45: 电缆WDZB-YJV-4*120+1*70 | C45: 1.名称:电力电缆 2.型号:WDZB-YJV 3.规格:4*120+1*70 4.材质:铜芯 5.敷设方式、部位:桥架内及配管内敷设 6.电压等级(kV):1.0KV | D45: 按设计图示尺寸以长度计算（含预留长度及附加长度） | E45: m | G45: =(H45+I45+J45+K45)*(1+L45) -> 488.30392 | H45: =VLOOKUP(B45,'[1]2.2强电工程'!$B$4:$H$254,7,0) -> 20.72 | I45: =VLOOKUP(B45,'[1]2.2强电工程'!$B$4:$I$254,8,0) -> 381.45 | J45: =VLOOKUP(B45,'[1]2.2强电工程'!$B$4:$J$254,9,0) -> 1.25 | K45: =VLOOKUP(B45,'[1]2.2强电工程'!$B$4:$K$254,10,0) -> 1.14 | L45: =$L$4 -> 0.207 | M45: =F45*G45 -> 0
A46: 43 | B46: 电缆WDZB-YJV-4*95+1*50 | C46: 1.名称:电力电缆 2.型号:WDZB-YJV 3.规格:4*95+1*50 4.材质:铜芯 5.敷设方式、部位:桥架内及配管内敷设 6.电压等级(kV):1.0KV | D46: 按设计图示尺寸以长度计算（含预留长度及附加长度） | E46: m | G46: =(H46+I46+J46+K46)*(1+L46) -> 388.34018 | H46: =VLOOKUP(B46,'[1]2.2强电工程'!$B$4:$H$254,7,0) -> 20.72 | I46: =VLOOKUP(B46,'[1]2.2强电工程'!$B$4:$I$254,8,0) -> 298.63 | J46: =VLOOKUP(B46,'[1]2.2强电工程'!$B$4:$J$254,9,0) -> 1.25 | K46: =VLOOKUP(B46,'[1]2.2强电工程'!$B$4:$K$254,10,0) -> 1.14 | L46: =$L$4 -> 0.207 | M46: =F46*G46 -> 0
A47: 44 | B47: 电缆WDZB-YJV-4*70+1*35 | C47: 1.名称:电力电缆 2.型号:WDZB-YJV 3.规格:4*70+1*35 4.材质:铜芯 5.敷设方式、部位:桥架内及配管内敷设 6.电压等级(kV):1.0KV | D47: 按设计图示尺寸以长度计算（含预留长度及附加长度） | E47: m | G47: =(H47+I47+J47+K47)*(1+L47) -> 285.63655 | H47: =VLOOKUP(B47,'[1]2.2强电工程'!$B$4:$H$254,7,0) -> 17.42 | I47: =VLOOKUP(B47,'[1]2.2强电工程'!$B$4:$I$254,8,0) -> 217.08 | J47: =VLOOKUP(B47,'[1]2.2强电工程'!$B$4:$J$254,9,0) -> 1.01 | K47: =VLOOKUP(B47,'[1]2.2强电工程'!$B$4:$K$254,10,0) -> 1.14 | L47: =$L$4 -> 0.207 | M47: =F47*G47 -> 0
A48: 45 | B48: 电缆WDZB-YJV-4*50+1*25 | C48: 1.名称:电力电缆 2.型号:WDZB-YJV 3.规格:4*50+1*25 4.材质:铜芯 5.敷设方式、部位:桥架内及配管内敷设 6.电压等级(kV):1.0KV | D48: 按设计图示尺寸以长度计算（含预留长度及附加长度） | E48: m | G48: =(H48+I48+J48+K48)*(1+L48) -> 206.62633 | H48: =VLOOKUP(B48,'[1]2.2强电工程'!$B$4:$H$254,7,0) -> 17.42 | I48: =VLOOKUP(B48,'[1]2.2强电工程'!$B$4:$I$254,8,0) -> 151.62 | J48: =VLOOKUP(B48,'[1]2.2强电工程'!$B$4:$J$254,9,0) -> 1.01 | K48: =VLOOKUP(B48,'[1]2.2强电工程'!$B$4:$K$254,10,0) -> 1.14 | L48: =$L$4 -> 0.207 | M48: =F48*G48 -> 0
A49: 46 | B49: 电缆WDZB-YJV-4*35+1*16 | C49: 1.名称:电力电缆 2.型号:WDZB-YJV 3.规格:4*35+1*16 4.材质:铜芯 5.敷设方式、部位:桥架内及配管内敷设 6.电压等级(kV):1.0KV | D49: 按设计图示尺寸以长度计算（含预留长度及附加长度） | E49: m | G49: =(H49+I49+J49+K49)*(1+L49) -> 148.9438 | H49: =VLOOKUP(B49,'[1]2.2强电工程'!$B$4:$H$254,7,0) -> 11.07 | I49: =VLOOKUP(B49,'[1]2.2强电工程'!$B$4:$I$254,8,0) -> 111.06 | J49: =VLOOKUP(B49,'[1]2.2强电工程'!$B$4:$J$254,9,0) -> 1.11 | K49: =VLOOKUP(B49,'[1]2.2强电工程'!$B$4:$K$254,10,0) -> 0.16 | L49: =$L$4 -> 0.207 | M49: =F49*G49 -> 0
A50: 47 | B50: 电缆WDZB-YJV-4*25+1*16 | C50: 1.名称:电力电缆 2.型号:WDZB-YJV 3.规格:4*25+1*16 4.材质:铜芯 5.敷设方式、部位:桥架内及配管内敷设 6.电压等级(kV):1.0KV | D50: 按设计图示尺寸以长度计算（含预留长度及附加长度） | E50: m | G50: =(H50+I50+J50+K50)*(1+L50) -> 117.70664 | H50: =VLOOKUP(B50,'[1]2.2强电工程'!$B$4:$H$254,7,0) -> 11.07 | I50: =VLOOKUP(B50,'[1]2.2强电工程'!$B$4:$I$254,8,0) -> 85.18 | J50: =VLOOKUP(B50,'[1]2.2强电工程'!$B$4:$J$254,9,0) -> 1.11 | K50: =VLOOKUP(B50,'[1]2.2强电工程'!$B$4:$K$254,10,0) -> 0.16 | L50: =$L$4 -> 0.207 | M50: =F50*G50 -> 0
A51: 48 | B51: 电缆WDZB-YJV-5*16 | C51: 1.名称:电力电缆 2.型号:WDZB-YJV 3.规格:5*16 4.材质:铜芯 5.敷设方式、部位:桥架内及配管内敷设 6.电压等级(kV):1.0KV | D51: 按设计图示尺寸以长度计算（含预留长度及附加长度） | E51: m | G51: =(H51+I51+J51+K51)*(1+L51) -> 87.94202 | H51: =VLOOKUP(B51,'[1]2.2强电工程'!$B$4:$H$254,7,0) -> 11.07 | I51: =VLOOKUP(B51,'[1]2.2强电工程'!$B$4:$I$254,8,0) -> 60.52 | J51: =VLOOKUP(B51,'[1]2.2强电工程'!$B$4:$J$254,9,0) -> 1.11 | K51: =VLOOKUP(B51,'[1]2.2强电工程'!$B$4:$K$254,10,0) -> 0.16 | L51: =$L$4 -> 0.207 | M51: =F51*G51 -> 0
A52: 49 | B52: 电缆WDZB-YJV-5*10 | C52: 1.名称:电力电缆 2.型号:WDZB-YJV 3.规格:5*10 4.材质:铜芯 5.敷设方式、部位:桥架内及配管内敷设 6.电压等级(kV):1.0KV | D52: 按设计图示尺寸以长度计算（含预留长度及附加长度） | E52: m | G52: =(H52+I52+J52+K52)*(1+L52) -> 56.29448 | H52: =VLOOKUP(B52,'[1]2.2强电工程'!$B$4:$H$254,7,0) -> 6.12 | I52: =VLOOKUP(B52,'[1]2.2强电工程'!$B$4:$I$254,8,0) -> 39.52 | J52: =VLOOKUP(B52,'[1]2.2强电工程'!$B$4:$J$254,9,0) -> 1 | K52: =VLOOKUP(B52,'[1]2.2强电工程'!$B$4:$K$254,10,0) -> 0 | L52: =$L$4 -> 0.207 | M52: =F52*G52 -> 0
A53: 50 | B53: 电缆WDZB-YJV-5*6 | C53: 1.名称:电力电缆 2.型号:WDZB-YJV 3.规格:5*6 4.材质:铜芯 5.敷设方式、部位:桥架内及配管内敷设 6.电压等级(kV):1.0KV | D53: 按设计图示尺寸以长度计算（含预留长度及附加长度） | E53: m | G53: =(H53+I53+J53+K53)*(1+L53) -> 87.94202 | H53: =VLOOKUP(B53,'[1]2.2强电工程'!$B$4:$H$254,7,0) -> 11.07 | I53: =VLOOKUP(B53,'[1]2.2强电工程'!$B$4:$I$254,8,0) -> 60.52 | J53: =VLOOKUP(B53,'[1]2.2强电工程'!$B$4:$J$254,9,0) -> 1.11 | K53: =VLOOKUP(B53,'[1]2.2强电工程'!$B$4:$K$254,10,0) -> 0.16 | L53: =$L$4 -> 0.207 | M53: =F53*G53 -> 0
A54: 51 | B54: 电缆WDZB-YJV-5*4 | C54: 1.名称:电力电缆 2.型号:WDZB-YJV 3.规格:5*4 4.材质:铜芯 5.敷设方式、部位:桥架内及配管内敷设 6.电压等级(kV):1.0KV | D54: 按设计图示尺寸以长度计算（含预留长度及附加长度） | E54: m | G54: =(H54+I54+J54+K54)*(1+L54) -> 29.63185 | H54: =VLOOKUP(B54,'[1]2.2强电工程'!$B$4:$H$254,7,0) -> 4.57 | I54: =VLOOKUP(B54,'[1]2.2强电工程'!$B$4:$I$254,8,0) -> 18.9 | J54: =VLOOKUP(B54,'[1]2.2强电工程'!$B$4:$J$254,9,0) -> 1.08 | K54: =VLOOKUP(B54,'[1]2.2强电工程'!$B$4:$K$254,10,0) -> 0 | L54: =$L$4 -> 0.207 | M54: =F54*G54 -> 0
A55: 52 | B55: 电缆WDZB-YJV-3*6 | C55: 1.名称:电力电缆 2.型号:WDZB-YJV 3.规格:3*6 4.材质:铜芯 5.敷设方式、部位:桥架内及配管内敷设 6.电压等级(kV):1.0KV | D55: 按设计图示尺寸以长度计算（含预留长度及附加长度） | E55: m | G55: =(H55+I55+J55+K55)*(1+L55) -> 59.55338 | H55: =VLOOKUP(B55,'[1]2.2强电工程'!$B$4:$H$254,7,0) -> 11.07 | I55: 37 | J55: =VLOOKUP(B55,'[1]2.2强电工程'!$B$4:$J$254,9,0) -> 1.11 | K55: =VLOOKUP(B55,'[1]2.2强电工程'!$B$4:$K$254,10,0) -> 0.16 | L55: =$L$4 -> 0.207 | M55: =F55*G55 -> 0
A56: 53 | B56: 电缆WDZB-YJV-3*10 | C56: 1.名称:电力电缆 2.型号:WDZB-YJV 3.规格:3*10 4.材质:铜芯 5.敷设方式、部位:桥架内及配管内敷设 6.电压等级(kV):1.0KV | D56: 按设计图示尺寸以长度计算（含预留长度及附加长度） | E56: m | G56: =(H56+I56+J56+K56)*(1+L56) -> 41.617465 | H56: 4.5614719 | I56: 29.47 | J56: 0.13 | K56: 0.31861472 | L56: =$L$4 -> 0.207 | M56: =F56*G56 -> 0
A57: 54 | B57: 电缆 ZR-YJV-3*240+2*120 | C57: 1.名称:电力电缆 2.型号:ZR-YJV 3.规格:3*240+2*120 4.材质:铜芯 5.敷设方式、部位:桥架内及配管内敷设 6.电压等级(kV):1.0KV | D57: 按设计图示尺寸以长度计算（含预留长度及附加长度） | E57: m | G57: =(H57+I57+J57+K57)*(1+L57) -> 856.16131 | H57: 28.73 | I57: 676.29 | J57: 1.99 | K57: 2.32 | L57: =$L$4 -> 0.207 | M57: =F57*G57 -> 0
A58: 55 | B58: 电缆 ZR-YJV-3*185+2*95 | C58: 1.名称:电力电缆 2.型号:ZR-YJV 3.规格:3*185+2*95 4.材质:铜芯 5.敷设方式、部位:桥架内及配管内敷设 6.电压等级(kV):1.0KV | D58: 按设计图示尺寸以长度计算（含预留长度及附加长度） | E58: m | G58: =(H58+I58+J58+K58)*(1+L58) -> 670.39194 | H58: 28.73 | I58: 522.38 | J58: 1.99 | K58: 2.32 | L58: =$L$4 -> 0.207 | M58: =F58*G58 -> 0
A59: 56 | B59: 电缆 ZR-YJV-3*150+2*70 | C59: 1.名称:电力电缆 2.型号:ZR-YJV 3.规格:3*150+2*70 4.材质:铜芯 5.敷设方式、部位:桥架内及配管内敷设 6.电压等级(kV):1.0KV | D59: 按设计图示尺寸以长度计算（含预留长度及附加长度） | E59: m | G59: =(H59+I59+J59+K59)*(1+L59) -> 532.84222 | H59: 28.73 | I59: 408.42 | J59: 1.99 | K59: 2.32 | L59: =$L$4 -> 0.207 | M59: =F59*G59 -> 0
A60: 57 | B60: 电缆 ZR-YJV-3*120+2*70 | C60: 1.名称:电力电缆 2.型号:ZR-YJV 3.规格:3*120+2*70 4.材质:铜芯 5.敷设方式、部位:桥架内及配管内敷设 6.电压等级(kV):1.0KV | D60: 按设计图示尺寸以长度计算（含预留长度及附加长度） | E60: m | G60: =(H60+I60+J60+K60)*(1+L60) -> 451.06797 | H60: 20.72 | I60: 350.6 | J60: 1.25 | K60: 1.14 | L60: =$L$4 -> 0.207 | M60: =F60*G60 -> 0
A61: 58 | B61: 电缆 ZR-YJV-3*95+2*50 | C61: 1.名称:电力电缆 2.型号:ZR-YJV 3.规格:3*95+2*50 4.材质:铜芯 5.敷设方式、部位:桥架内及配管内敷设 6.电压等级(kV):1.0KV | D61: 按设计图示尺寸以长度计算（含预留长度及附加长度） | E61: m | G61: =(H61+I61+J61+K61)*(1+L61) -> 353.13199 | H61: 20.72 | I61: 269.46 | J61: 1.25 | K61: 1.14 | L61: =$L$4 -> 0.207 | M61: =F61*G61 -> 0
A62: 59 | B62: 电缆 ZR-YJV-3*70+2*35 | C62: 1.名称:电力电缆 2.型号:ZR-YJV 3.规格:3*70+2*35 4.材质:铜芯 5.敷设方式、部位:桥架内及配管内敷设 6.电压等级(kV):1.0KV | D62: 按设计图示尺寸以长度计算（含预留长度及附加长度） | E62: m | G62: =(H62+I62+J62+K62)*(1+L62) -> 261.15859 | H62: 17.42 | I62: 196.8 | J62: 1.01 | K62: 1.14 | L62: =$L$4 -> 0.207 | M62: =F62*G62 -> 0
A63: 60 | B63: 电缆 ZR-YJV-3*50+2*25 | C63: 1.名称:电力电缆 2.型号:ZR-YJV 3.规格:3*50+2*25 4.材质:铜芯 5.敷设方式、部位:桥架内及配管内敷设 6.电压等级(kV):1.0KV | D63: 按设计图示尺寸以长度计算（含预留长度及附加长度） | E63: m | G63: =(H63+I63+J63+K63)*(1+L63) -> 191.50262 | H63: 17.42 | I63: 139.09 | J63: 1.01 | K63: 1.14 | L63: =$L$4 -> 0.207 | M63: =F63*G63 -> 0
A64: 61 | B64: 电缆 ZR-YJV-3*35+2*16 | C64: 1.名称:电力电缆 2.型号:ZR-YJV 3.规格:3*35+2*16 4.材质:铜芯 5.敷设方式、部位:桥架内及配管内敷设 6.电压等级(kV):1.0KV | D64: 按设计图示尺寸以长度计算（含预留长度及附加长度） | E64: m | G64: =(H64+I64+J64+K64)*(1+L64) -> 134.84604 | H64: =H18 -> 11.07 | I64: =I18 -> 99.38 | J64: =J18 -> 1.11 | K64: =K18 -> 0.16 | L64: =$L$4 -> 0.207 | M64: =F64*G64 -> 0
A65: 62 | B65: 电缆 ZR-YJV-3*25+2*16 | C65: 1.名称:电力电缆 2.型号:ZR-YJV 3.规格:3*25+2*16 4.材质:铜芯 5.敷设方式、部位:桥架内及配管内敷设 6.电压等级(kV):1.0KV | D65: 按设计图示尺寸以长度计算（含预留长度及附加长度） | E65: m | G65: =(H65+I65+J65+K65)*(1+L65) -> 112.16651 | H65: =H19 -> 11.07 | I65: =I19 -> 80.59 | J65: =J19 -> 1.11 | K65: =K19 -> 0.16 | L65: =$L$4 -> 0.207 | M65: =F65*G65 -> 0
A66: 63 | B66: 电缆 ZR-YJV-4*240+1*120 | C66: 1.名称:电力电缆 2.型号:ZR-YJV 3.规格:4*240+1*120 4.材质:铜芯 5.敷设方式、部位:桥架内及配管内敷设 6.电压等级(kV):1.0KV | D66: 按设计图示尺寸以长度计算（含预留长度及附加长度） | E66: m | G66: =(H66+I66+J66+K66)*(1+L66) -> 1044.9171 | H66: 49.322857 | I66: 803.66 | J66: 4.16 | K66: =(H66+I66+J66)*'[2]2-报价汇总'!$H$5 -> 8.5714286 | L66: =$L$4 -> 0.207 | M66: =F66*G66 -> 0
A67: 64 | B67: 电缆 ZR-YJV-4*185+1*95 | C67: 1.名称:电力电缆 2.型号:ZR-YJV 3.规格:4*185+1*95 4.材质:铜芯 5.敷设方式、部位:桥架内及配管内敷设 6.电压等级(kV):1.0KV | D67: 按设计图示尺寸以长度计算（含预留长度及附加长度） | E67: m | G67: =(H67+I67+J67+K67)*(1+L67) -> 745.47941 | H67: =H20 -> 28.73 | I67: =I20 -> 584.59 | J67: =J20 -> 1.99 | K67: =K20 -> 2.32 | L67: =$L$4 -> 0.207 | M67: =F67*G67 -> 0
A68: 65 | B68: 电缆 ZR-YJV-4*150+1*70 | C68: 1.名称:电力电缆 2.型号:ZR-YJV 3.规格:4*150+1*70 4.材质:铜芯 5.敷设方式、部位:桥架内及配管内敷设 6.电压等级(kV):1.0KV | D68: 按设计图示尺寸以长度计算（含预留长度及附加长度） | E68: m | G68: =(H68+I68+J68+K68)*(1+L68) -> 599.09445 | H68: =H21 -> 28.73 | I68: =I21 -> 463.31 | J68: =J21 -> 1.99 | K68: =K21 -> 2.32 | L68: =$L$4 -> 0.207 | M68: =F68*G68 -> 0
A69: 66 | B69: 电缆 ZR-YJV-4*120+1*70 | C69: 1.名称:电力电缆 2.型号:ZR-YJV 3.规格:4*120+1*70 4.材质:铜芯 5.敷设方式、部位:桥架内及配管内敷设 6.电压等级(kV):1.0KV | D69: 按设计图示尺寸以长度计算（含预留长度及附加长度） | E69: m | G69: =(H69+I69+J69+K69)*(1+L69) -> 493.72335 | H69: =H22 -> 20.72 | I69: =I22 -> 385.94 | J69: =J22 -> 1.25 | K69: =K22 -> 1.14 | L69: =$L$4 -> 0.207 | M69: =F69*G69 -> 0
A70: 67 | B70: 电缆 ZR-YJV-4*95+1*50 | C70: 1.名称:电力电缆 2.型号:ZR-YJV 3.规格:4*95+1*50 4.材质:铜芯 5.敷设方式、部位:桥架内及配管内敷设 6.电压等级(kV):1.0KV | D70: 按设计图示尺寸以长度计算（含预留长度及附加长度） | E70: m | G70: =(H70+I70+J70+K70)*(1+L70) -> 392.74573 | H70: =H23 -> 20.72 | I70: =I23 -> 302.28 | J70: =J23 -> 1.25 | K70: =K23 -> 1.14 | L70: =$L$4 -> 0.207 | M70: =F70*G70 -> 0
A71: 68 | B71: 电缆 ZR-YJV-4*70+1*35 | C71: 1.名称:电力电缆 2.型号:ZR-YJV 3.规格:4*70+1*35 4.材质:铜芯 5.敷设方式、部位:桥架内及配管内敷设 6.电压等级(kV):1.0KV | D71: 按设计图示尺寸以长度计算（含预留长度及附加长度） | E71: m | G71: =(H71+I71+J71+K71)*(1+L71) -> 289.53516 | H71: =H24 -> 17.42 | I71: =I24 -> 220.31 | J71: =J24 -> 1.01 | K71: =K24 -> 1.14 | L71: =$L$4 -> 0.207 | M71: =F71*G71 -> 0
A72: 69 | B72: 电缆 ZR-YJV-4*50+1*25 | C72: 1.名称:电力电缆 2.型号:ZR-YJV 3.规格:4*50+1*25 4.材质:铜芯 5.敷设方式、部位:桥架内及配管内敷设 6.电压等级(kV):1.0KV | D72: 按设计图示尺寸以长度计算（含预留长度及附加长度） | E72: m | G72: =(H72+I72+J72+K72)*(1+L72) -> 209.64383 | H72: =H25 -> 17.42 | I72: =I25 -> 154.12 | J72: =J25 -> 1.01 | K72: =K25 -> 1.14 | L72: =$L$4 -> 0.207 | M72: =F72*G72 -> 0
A73: 70 | B73: 电缆 ZR-YJV-4*35+1*16 | C73: 1.名称:电力电缆 2.型号:ZR-YJV 3.规格:4*35+1*16 4.材质:铜芯 5.敷设方式、部位:桥架内及配管内敷设 6.电压等级(kV):1.0KV | D73: 按设计图示尺寸以长度计算（含预留长度及附加长度） | E73: m | G73: =(H73+I73+J73+K73)*(1+L73) -> 150.33185 | H73: =H26 -> 11.07 | I73: =I26 -> 112.21 | J73: =J26 -> 1.11 | K73: =K26 -> 0.16 | L73: =$L$4 -> 0.207 | M73: =F73*G73 -> 0
A74: 71 | B74: 电缆 ZR-YJV-4*25+1*16 | C74: 1.名称:电力电缆 2.型号:ZR-YJV 3.规格:4*25+1*16 4.材质:铜芯 5.敷设方式、部位:桥架内及配管内敷设 6.电压等级(kV):1.0KV | D74: 按设计图示尺寸以长度计算（含预留长度及附加长度） | E74: m | G74: =(H74+I74+J74+K74)*(1+L74) -> 119.6137 | H74: =H27 -> 11.07 | I74: =I27 -> 86.76 | J74: =J27 -> 1.11 | K74: =K27 -> 0.16 | L74: =$L$4 -> 0.207 | M74: =F74*G74 -> 0
A75: 72 | B75: 电缆 ZR-YJV-4*16+1*10 | C75: 1.名称:电力电缆 2.型号:ZR-YJV 3.规格:4*16+1*10 4.材质:铜芯 5.敷设方式、部位:桥架内及配管内敷设 6.电压等级(kV):1.0KV | D75: 按设计图示尺寸以长度计算（含预留长度及附加长度） | E75: m | G75: =(H75+I75+J75+K75)*(1+L75) -> 85.98668 | H75: 11.07 | I75: 58.9 | J75: 1.11 | K75: 0.16 | L75: =$L$4 -> 0.207 | M75: =F75*G75 -> 0
A76: 73 | B76: 电缆 ZR-YJV-5*16 | C76: 1.名称:电力电缆 2.型号:ZR-YJV 3.规格:5*16 4.材质:铜芯 5.敷设方式、部位:桥架内及配管内敷设 6.电压等级(kV):1.0KV | D76: 按设计图示尺寸以长度计算（含预留长度及附加长度） | E76: m | G76: =(H76+I76+J76+K76)*(1+L76) -> 89.46284 | H76: =H28 -> 11.07 | I76: =I28 -> 61.78 | J76: =J28 -> 1.11 | K76: =K28 -> 0.16 | L76: =$L$4 -> 0.207 | M76: =F76*G76 -> 0
A77: 74 | B77: 电缆 ZR-YJV-5*10 | C77: 1.名称:电力电缆 2.型号:ZR-YJV 3.规格:5*10 4.材质:铜芯 5.敷设方式、部位:桥架内及配管内敷设 6.电压等级(kV):1.0KV | D77: 按设计图示尺寸以长度计算（含预留长度及附加长度） | E77: m | F77: 125.44 | G77: =(H77+I77+J77+K77)*(1+L77) -> 57.51355 | H77: =H29 -> 6.12 | I77: =I29 -> 40.53 | J77: =J29 -> 1 | K77: =K29 -> 0 | L77: =$L$4 -> 0.207 | M77: =F77*G77 -> 7214.4997
A78: 75 | B78: 电缆 ZR-YJV-5*6 | C78: 1.名称:电力电缆 2.型号:ZR-YJV 3.规格:5*6 4.材质:铜芯 5.敷设方式、部位:桥架内及配管内敷设 6.电压等级(kV):1.0KV | D78: 按设计图示尺寸以长度计算（含预留长度及附加长度） | E78: m | G78: =(H78+I78+J78+K78)*(1+L78) -> 51.86479 | H78: =H30 -> 11.07 | I78: 30.63 | J78: =J30 -> 1.11 | K78: =K30 -> 0.16 | L78: =$L$4 -> 0.207 | M78: =F78*G78 -> 0
A79: 76 | B79: 电缆ZR-YJV-3*4 | C79: 1.名称:电力电缆 2.型号:ZR-YJV 3.规格:3*4 4.材质:铜芯 5.敷设方式、部位:桥架内及配管内敷设 6.电压等级(kV):1.0KV | D79: 按设计图示尺寸以长度计算（含预留长度及附加长度） | E79: m | G79: =(H79+I79+J79+K79)*(1+L79) -> 27.659842 | H79: 9.3052381 | I79: 13.2 | J79: 0.13 | K79: 0.28095238 | L79: =$L$4 -> 0.207 | M79: =F79*G79 -> 0
A80: 77 | B80: 电缆WDZ-YJV-3*240+2*120 | C80: 1.名称:电力电缆 2.型号:WDZ-YJV 3.规格:3*240+2*120 4.材质:铜芯 5.敷设方式、部位:桥架内及配管内敷设 6.电压等级(kV):1.0KV | D80: 按设计图示尺寸以长度计算（含预留长度及附加长度） | E80: m | G80: =(H80+I80+J80+K80)*(1+L80) -> 856.16131 | H80: 28.73 | I80: 676.29 | J80: 1.99 | K80: 2.32 | L80: =$L$4 -> 0.207 | M80: =F80*G80 -> 0
A81: 78 | B81: 电缆WDZ-YJV-3*185+2*95 | C81: 1.名称:电力电缆 2.型号:WDZ-YJV 3.规格:3*185+2*95 4.材质:铜芯 5.敷设方式、部位:桥架内及配管内敷设 6.电压等级(kV):1.0KV | D81: 按设计图示尺寸以长度计算（含预留长度及附加长度） | E81: m | G81: =(H81+I81+J81+K81)*(1+L81) -> 670.39194 | H81: 28.73 | I81: 522.38 | J81: 1.99 | K81: 2.32 | L81: =$L$4 -> 0.207 | M81: =F81*G81 -> 0
A82: 79 | B82: 电缆WDZ-YJV-3*150+2*70 | C82: 1.名称:电力电缆 2.型号:WDZ-YJV 3.规格:3*150+2*70 4.材质:铜芯 5.敷设方式、部位:桥架内及配管内敷设 6.电压等级(kV):1.0KV | D82: 按设计图示尺寸以长度计算（含预留长度及附加长度） | E82: m | G82: =(H82+I82+J82+K82)*(1+L82) -> 532.84222 | H82: 28.73 | I82: 408.42 | J82: 1.99 | K82: 2.32 | L82: =$L$4 -> 0.207 | M82: =F82*G82 -> 0
A83: 80 | B83: 电缆WDZ-YJV-3*120+2*70 | C83: 1.名称:电力电缆 2.型号:WDZ-YJV 3.规格:3*120+2*70 4.材质:铜芯 5.敷设方式、部位:桥架内及配管内敷设 6.电压等级(kV):1.0KV | D83: 按设计图示尺寸以长度计算（含预留长度及附加长度） | E83: m | G83: =(H83+I83+J83+K83)*(1+L83) -> 451.06797 | H83: 20.72 | I83: 350.6 | J83: 1.25 | K83: 1.14 | L83: =$L$4 -> 0.207 | M83: =F83*G83 -> 0
A84: 81 | B84: 电缆WDZ-YJV-3*95+2*50 | C84: 1.名称:电力电缆 2.型号:WDZ-YJV 3.规格:3*95+2*50 4.材质:铜芯 5.敷设方式、部位:桥架内及配管内敷设 6.电压等级(kV):1.0KV | D84: 按设计图示尺寸以长度计算（含预留长度及附加长度） | E84: m | G84: =(H84+I84+J84+K84)*(1+L84) -> 353.13199 | H84: 20.72 | I84: 269.46 | J84: 1.25 | K84: 1.14 | L84: =$L$4 -> 0.207 | M84: =F84*G84 -> 0
A85: 82 | B85: 电缆WDZ-YJV-3*70+2*35 | C85: 1.名称:电力电缆 2.型号:WDZ-YJV 3.规格:3*70+2*35 4.材质:铜芯 5.敷设方式、部位:桥架内及配管内敷设 6.电压等级(kV):1.0KV | D85: 按设计图示尺寸以长度计算（含预留长度及附加长度） | E85: m | G85: =(H85+I85+J85+K85)*(1+L85) -> 261.15859 | H85: 17.42 | I85: 196.8 | J85: 1.01 | K85: 1.14 | L85: =$L$4 -> 0.207 | M85: =F85*G85 -> 0
A86: 83 | B86: 电缆WDZ-YJV-3*50+2*25 | C86: 1.名称:电力电缆 2.型号:WDZ-YJV 3.规格:3*50+2*25 4.材质:铜芯 5.敷设方式、部位:桥架内及配管内敷设 6.电压等级(kV):1.0KV | D86: 按设计图示尺寸以长度计算（含预留长度及附加长度） | E86: m | G86: =(H86+I86+J86+K86)*(1+L86) -> 191.50262 | H86: 17.42 | I86: 139.09 | J86: 1.01 | K86: 1.14 | L86: =$L$4 -> 0.207 | M86: =F86*G86 -> 0
A87: 84 | B87: 电缆WDZ-YJV-3*35+2*16 | C87: 1.名称:电力电缆 2.型号:WDZ-YJV 3.规格:3*35+2*16 4.材质:铜芯 5.敷设方式、部位:桥架内及配管内敷设 6.电压等级(kV):1.0KV | D87: 按设计图示尺寸以长度计算（含预留长度及附加长度） | E87: m | G87: =(H87+I87+J87+K87)*(1+L87) -> 134.84604 | H87: =H18 -> 11.07 | I87: =I18 -> 99.38 | J87: =J18 -> 1.11 | K87: =K18 -> 0.16 | L87: =$L$4 -> 0.207 | M87: =F87*G87 -> 0
A88: 85 | B88: 电缆WDZ-YJV-3*25+2*16 | C88: 1.名称:电力电缆 2.型号:WDZ-YJV 3.规格:3*25+2*16 4.材质:铜芯 5.敷设方式、部位:桥架内及配管内敷设 6.电压等级(kV):1.0KV | D88: 按设计图示尺寸以长度计算（含预留长度及附加长度） | E88: m | G88: =(H88+I88+J88+K88)*(1+L88) -> 112.16651 | H88: =H19 -> 11.07 | I88: =I19 -> 80.59 | J88: =J19 -> 1.11 | K88: =K19 -> 0.16 | L88: =$L$4 -> 0.207 | M88: =F88*G88 -> 0
A89: 86 | B89: 电缆WDZ-YJV-4*185+1*95 | C89: 1.名称:电力电缆 2.型号:WDZ-YJV 3.规格:4*185+1*95 4.材质:铜芯 5.敷设方式、部位:桥架内及配管内敷设 6.电压等级(kV):1.0KV | D89: 按设计图示尺寸以长度计算（含预留长度及附加长度） | E89: m | G89: =(H89+I89+J89+K89)*(1+L89) -> 745.47941 | H89: =H20 -> 28.73 | I89: =I20 -> 584.59 | J89: =J20 -> 1.99 | K89: =K20 -> 2.32 | L89: =$L$4 -> 0.207 | M89: =F89*G89 -> 0
A90: 87 | B90: 电缆WDZ-YJV-4*150+1*70 | C90: 1.名称:电力电缆 2.型号:WDZ-YJV 3.规格:4*150+1*70 4.材质:铜芯 5.敷设方式、部位:桥架内及配管内敷设 6.电压等级(kV):1.0KV | D90: 按设计图示尺寸以长度计算（含预留长度及附加长度） | E90: m | G90: =(H90+I90+J90+K90)*(1+L90) -> 599.09445 | H90: =H21 -> 28.73 | I90: =I21 -> 463.31 | J90: =J21 -> 1.99 | K90: =K21 -> 2.32 | L90: =$L$4 -> 0.207 | M90: =F90*G90 -> 0
A91: 88 | B91: 电缆WDZ-YJV-4*120+1*70 | C91: 1.名称:电力电缆 2.型号:WDZ-YJV 3.规格:4*120+1*70 4.材质:铜芯 5.敷设方式、部位:桥架内及配管内敷设 6.电压等级(kV):1.0KV | D91: 按设计图示尺寸以长度计算（含预留长度及附加长度） | E91: m | G91: =(H91+I91+J91+K91)*(1+L91) -> 493.72335 | H91: =H22 -> 20.72 | I91: =I22 -> 385.94 | J91: =J22 -> 1.25 | K91: =K22 -> 1.14 | L91: =$L$4 -> 0.207 | M91: =F91*G91 -> 0
A92: 89 | B92: 电缆WDZ-YJV-4*95+1*50 | C92: 1.名称:电力电缆 2.型号:WDZ-YJV 3.规格:4*95+1*50 4.材质:铜芯 5.敷设方式、部位:桥架内及配管内敷设 6.电压等级(kV):1.0KV | D92: 按设计图示尺寸以长度计算（含预留长度及附加长度） | E92: m | G92: =(H92+I92+J92+K92)*(1+L92) -> 392.74573 | H92: =H23 -> 20.72 | I92: =I23 -> 302.28 | J92: =J23 -> 1.25 | K92: =K23 -> 1.14 | L92: =$L$4 -> 0.207 | M92: =F92*G92 -> 0
A93: 90 | B93: 电缆WDZ-YJV-4*70+1*35 | C93: 1.名称:电力电缆 2.型号:WDZ-YJV 3.规格:4*70+1*35 4.材质:铜芯 5.敷设方式、部位:桥架内及配管内敷设 6.电压等级(kV):1.0KV | D93: 按设计图示尺寸以长度计算（含预留长度及附加长度） | E93: m | G93: =(H93+I93+J93+K93)*(1+L93) -> 289.53516 | H93: =H24 -> 17.42 | I93: =I24 -> 220.31 | J93: =J24 -> 1.01 | K93: =K24 -> 1.14 | L93: =$L$4 -> 0.207 | M93: =F93*G93 -> 0
A94: 91 | B94: 电缆WDZ-YJV-4*50+1*25 | C94: 1.名称:电力电缆 2.型号:WDZ-YJV 3.规格:4*50+1*25 4.材质:铜芯 5.敷设方式、部位:桥架内及配管内敷设 6.电压等级(kV):1.0KV | D94: 按设计图示尺寸以长度计算（含预留长度及附加长度） | E94: m | G94: =(H94+I94+J94+K94)*(1+L94) -> 209.64383 | H94: =H25 -> 17.42 | I94: =I25 -> 154.12 | J94: =J25 -> 1.01 | K94: =K25 -> 1.14 | L94: =$L$4 -> 0.207 | M94: =F94*G94 -> 0
A95: 92 | B95: 电缆WDZ-YJV-4*35+1*16 | C95: 1.名称:电力电缆 2.型号:WDZ-YJV 3.规格:4*35+1*16 4.材质:铜芯 5.敷设方式、部位:桥架内及配管内敷设 6.电压等级(kV):1.0KV | D95: 按设计图示尺寸以长度计算（含预留长度及附加长度） | E95: m | G95: =(H95+I95+J95+K95)*(1+L95) -> 150.33185 | H95: =H26 -> 11.07 | I95: =I26 -> 112.21 | J95: =J26 -> 1.11 | K95: =K26 -> 0.16 | L95: =$L$4 -> 0.207 | M95: =F95*G95 -> 0
A96: 93 | B96: 电缆WDZ-YJV-4*25+1*16 | C96: 1.名称:电力电缆 2.型号:WDZ-YJV 3.规格:4*25+1*16 4.材质:铜芯 5.敷设方式、部位:桥架内及配管内敷设 6.电压等级(kV):1.0KV | D96: 按设计图示尺寸以长度计算（含预留长度及附加长度） | E96: m | G96: =(H96+I96+J96+K96)*(1+L96) -> 119.6137 | H96: =H27 -> 11.07 | I96: =I27 -> 86.76 | J96: =J27 -> 1.11 | K96: =K27 -> 0.16 | L96: =$L$4 -> 0.207 | M96: =F96*G96 -> 0
A97: 94 | B97: 电缆WDZ-YJV-5*16 | C97: 1.名称:电力电缆 2.型号:WDZ-YJV 3.规格:5*16 4.材质:铜芯 5.敷设方式、部位:桥架内及配管内敷设 6.电压等级(kV):1.0KV | D97: 按设计图示尺寸以长度计算（含预留长度及附加长度） | E97: m | G97: =(H97+I97+J97+K97)*(1+L97) -> 89.46284 | H97: =H28 -> 11.07 | I97: =I28 -> 61.78 | J97: =J28 -> 1.11 | K97: =K28 -> 0.16 | L97: =$L$4 -> 0.207 | M97: =F97*G97 -> 0
A98: 95 | B98: 电缆WDZ-YJV-5*10 | C98: 1.名称:电力电缆 2.型号:WDZ-YJV 3.规格:5*10 4.材质:铜芯 5.敷设方式、部位:桥架内及配管内敷设 6.电压等级(kV):1.0KV | D98: 按设计图示尺寸以长度计算（含预留长度及附加长度） | E98: m | G98: =(H98+I98+J98+K98)*(1+L98) -> 57.51355 | H98: =H29 -> 6.12 | I98: =I29 -> 40.53 | J98: =J29 -> 1 | K98: =K29 -> 0 | L98: =$L$4 -> 0.207 | M98: =F98*G98 -> 0
A99: 96 | B99: 电缆WDZ-YJV-5*6 | C99: 1.名称:电力电缆 2.型号:WDZ-YJV 3.规格:5*6 4.材质:铜芯 5.敷设方式、部位:桥架内及配管内敷设 6.电压等级(kV):1.0KV | D99: 按设计图示尺寸以长度计算（含预留长度及附加长度） | E99: m | G99: =(H99+I99+J99+K99)*(1+L99) -> 57.86358 | H99: =H30 -> 11.07 | I99: =I30 -> 35.6 | J99: =J30 -> 1.11 | K99: =K30 -> 0.16 | L99: =$L$4 -> 0.207 | M99: =F99*G99 -> 0
A100: 97 | B100: 电缆WDZ-YJV-5*4 | C100: 1.名称:电力电缆 2.型号:WDZ-YJV 3.规格:5*4 4.材质:铜芯 5.敷设方式、部位:桥架内及配管内敷设 6.电压等级(kV):1.0KV | D100: 按设计图示尺寸以长度计算（含预留长度及附加长度） | E100: m | G100: =(H100+I100+J100+K100)*(1+L100) -> 34.250062 | H100: 9.3052381 | I100: 18.66 | J100: 0.13 | K100: 0.28095238 | L100: =$L$4 -> 0.207 | M100: =F100*G100 -> 0
...

Sheet 2.3弱电工程
A1: 长城智选中心店装修项目装饰工程
A2: 序号 | B2: 分部分项名称 | C2: 项目特征 | D2: 计量规则 | E2: 单位 | F2: 工程量 | G2: 综合单价 | H2: 人工 | I2: 主材 | J2: 辅材 | K2: 机械 | L2: 其他综合费率 | M2: 合计 | N2: 备注
A3: 一 | B3: 综合布线
A4: 1 | B4: 弱电机柜12U | C4: 1.名称:弱电机柜12U 2.规格:包含PDU插排，用于放置交换机、路由器等设备，留有冗余空间 3.安装方式:落地 | D4: 按设计图示数量计算 | E4: 台 | G4: =(H4+I4+J4+K4)*(1+L4) -> 799.91511 | H4: =VLOOKUP(B4,'[1]2.3弱电工程'!$B$4:$H$195,7,0) -> 270.73 | I4: =VLOOKUP(B4,'[1]2.3弱电工程'!$B$4:$I$195,8,0) -> 380.53 | J4: =VLOOKUP(B4,'[1]2.3弱电工程'!$B$4:$J$195,9,0) -> 10.49 | K4: =VLOOKUP(B4,'[1]2.3弱电工程'!$B$4:$K$195,10,0) -> 0.98 | L4: ='2.1装饰工程'!$L$4 -> 0.207 | M4: =F4*G4 -> 0
A5: 2 | B5: 弱电机柜24U | C5: 1.名称:弱电机柜24U 2.规格:包含PDU插排，用于放置交换机、路由器等设备，留有冗余空间 3.安装方式:落地 | D5: 按设计图示数量计算 | E5: 台 | G5: =(H5+I5+J5+K5)*(1+L5) -> 1152.4074 | H5: =VLOOKUP(B5,'[1]2.3弱电工程'!$B$4:$H$195,7,0) -> 270.73 | I5: =VLOOKUP(B5,'[1]2.3弱电工程'!$B$4:$I$195,8,0) -> 672.57 | J5: =VLOOKUP(B5,'[1]2.3弱电工程'!$B$4:$J$195,9,0) -> 10.49 | K5: =VLOOKUP(B5,'[1]2.3弱电工程'!$B$4:$K$195,10,0) -> 0.98 | L5: =$L$4 -> 0.207 | M5: =F5*G5 -> 0
A6: 3 | B6: 弱电机柜27U | C6: 1.名称:弱电机柜27U 2.规格:包含PDU插排，用于放置交换机、路由器等设备，留有冗余空间 3.安装方式:落地 | D6: 按设计图示数量计算 | E6: 台 | F6: 2 | G6: =(H6+I6+J6+K6)*(1+L6) -> 1227.169 | H6: =VLOOKUP(B6,'[1]2.3弱电工程'!$B$4:$H$195,7,0) -> 270.73 | I6: =VLOOKUP(B6,'[1]2.3弱电工程'!$B$4:$I$195,8,0) -> 734.51 | J6: =VLOOKUP(B6,'[1]2.3弱电工程'!$B$4:$J$195,9,0) -> 10.49 | K6: =VLOOKUP(B6,'[1]2.3弱电工程'!$B$4:$K$195,10,0) -> 0.98 | L6: =$L$4 -> 0.207 | M6: =F6*G6 -> 2454.3379
A7: 4 | B7: 弱电机柜42U | C7: 1.名称:弱电机柜42U 2.规格:包含PDU插排，用于放置交换机、路由器等设备，留有冗余空间 3.安装方式:落地 | D7: 按设计图示数量计算 | E7: 台 | G7: =(H7+I7+J7+K7)*(1+L7) -> 1686.4687 | H7: =VLOOKUP(B7,'[1]2.3弱电工程'!$B$4:$H$195,7,0) -> 270.73 | I7: =VLOOKUP(B7,'[1]2.3弱电工程'!$B$4:$I$195,8,0) -> 1115.04 | J7: =VLOOKUP(B7,'[1]2.3弱电工程'!$B$4:$J$195,9,0) -> 10.49 | K7: =VLOOKUP(B7,'[1]2.3弱电工程'!$B$4:$K$195,10,0) -> 0.98 | L7: =$L$4 -> 0.207 | M7: =F7*G7 -> 0
A8: 5 | B8: USP不间断电源 | C8: 1.名称:USP不间断电源 2.型号:参考英威腾HT1103CL，内置电池，后备时间＞30分钟 | D8: 按设计图示数量计算 | E8: 个 | F8: 2 | G8: =(H8+I8+J8+K8)*(1+L8) -> 5482.9303 | H8: =VLOOKUP(B8,'[1]2.3弱电工程'!$B$4:$H$195,7,0) -> 860.41 | I8: =VLOOKUP(B8,'[1]2.3弱电工程'!$B$4:$I$195,8,0) -> 700.6 | J8: =VLOOKUP(B8,'[1]2.3弱电工程'!$B$4:$J$195,9,0) -> 2981.6 | K8: =VLOOKUP(B8,'[1]2.3弱电工程'!$B$4:$K$195,10,0) -> 0 | L8: =$L$4 -> 0.207 | M8: =F8*G8 -> 10965.861
A9: 6 | B9: 24口配线架 | C9: 1.名称:24口配线架 2.规格:1U,24口，含同品牌非屏蔽模块，模块满配 | D9: 按设计图示数量计算 | E9: 个 | G9: =(H9+I9+J9+K9)*(1+L9) -> 434.8821 | H9: =VLOOKUP(B9,'[1]2.3弱电工程'!$B$4:$H$195,7,0) -> 216.23 | I9: =VLOOKUP(B9,'[1]2.3弱电工程'!$B$4:$I$195,8,0) -> 144.07 | J9: =VLOOKUP(B9,'[1]2.3弱电工程'!$B$4:$J$195,9,0) -> 0 | K9: =VLOOKUP(B9,'[1]2.3弱电工程'!$B$4:$K$195,10,0) -> 0 | L9: =$L$4 -> 0.207 | M9: =F9*G9 -> 0
A10: 7 | B10: 48口配线架 | C10: 1.名称:48口配线架 2.规格:48口，含同品牌非屏蔽模块，模块满配 | D10: 按设计图示数量计算 | E10: 个 | G10: =(H10+I10+J10+K10)*(1+L10) -> 665.35875 | H10: =VLOOKUP(B10,'[1]2.3弱电工程'!$B$4:$H$195,7,0) -> 235.65 | I10: =VLOOKUP(B10,'[1]2.3弱电工程'!$B$4:$I$195,8,0) -> 315.6 | J10: =VLOOKUP(B10,'[1]2.3弱电工程'!$B$4:$J$195,9,0) -> 0 | K10: =VLOOKUP(B10,'[1]2.3弱电工程'!$B$4:$K$195,10,0) -> 0 | L10: =$L$4 -> 0.207 | M10: =F10*G10 -> 0
A11: 8 | B11: 24口理线架 | C11: 1.名称:24口理线架 2.规格:1U,金属材质 | D11: 按设计图示数量计算 | E11: 个 | F11: 35 | G11: =(H11+I11+J11+K11)*(1+L11) -> 64.84004 | H11: =VLOOKUP(B11,'[1]2.3弱电工程'!$B$4:$H$195,7,0) -> 22.75 | I11: =VLOOKUP(B11,'[1]2.3弱电工程'!$B$4:$I$195,8,0) -> 30.97 | J11: =VLOOKUP(B11,'[1]2.3弱电工程'!$B$4:$J$195,9,0) -> 0 | K11: =VLOOKUP(B11,'[1]2.3弱电工程'!$B$4:$K$195,10,0) -> 0 | L11: =$L$4 -> 0.207 | M11: =F11*G11 -> 2269.4014
A12: 9 | B12: 48口理线架 | C12: 1.名称:48口理线架 2.规格:金属材质 | D12: 按设计图示数量计算 | E12: 个 | G12: =(H12+I12+J12+K12)*(1+L12) -> 70.18705 | H12: =VLOOKUP(B12,'[1]2.3弱电工程'!$B$4:$H$195,7,0) -> 22.75 | I12: =VLOOKUP(B12,'[1]2.3弱电工程'!$B$4:$I$195,8,0) -> 35.4 | J12: =VLOOKUP(B12,'[1]2.3弱电工程'!$B$4:$J$195,9,0) -> 0 | K12: =VLOOKUP(B12,'[1]2.3弱电工程'!$B$4:$K$195,10,0) -> 0 | L12: =$L$4 -> 0.207 | M12: =F12*G12 -> 0
A13: 10 | B13: 24口交换机 | C13: 1.名称:24口交换机 2.功能:可网管、不低于24口，POE供电，参考TP-LINK | D13: 按设计图示数量计算 | E13: 台 | G13: =(H13+I13+J13+K13)*(1+L13) -> 2012.0569 | H13: =VLOOKUP(B13,'[1]2.3弱电工程'!$B$4:$H$195,7,0) -> 614.25 | I13: =VLOOKUP(B13,'[1]2.3弱电工程'!$B$4:$I$195,8,0) -> 1031.86 | J13: =VLOOKUP(B13,'[1]2.3弱电工程'!$B$4:$J$195,9,0) -> 10.49 | K13: =VLOOKUP(B13,'[1]2.3弱电工程'!$B$4:$K$195,10,0) -> 10.39 | L13: =$L$4 -> 0.207 | M13: =F13*G13 -> 0
A14: 11 | B14: 48口交换机 | C14: 1.名称:48口交换机 2.功能:可网管、不低于48口，POE供电，参考TP-LINK：TL-SG3452P | D14: 按设计图示数量计算 | E14: 台 | G14: =(H14+I14+J14+K14)*(1+L14) -> 5148.7723 | H14: =VLOOKUP(B14,'[1]2.3弱电工程'!$B$4:$H$195,7,0) -> 1023.75 | I14: =VLOOKUP(B14,'[1]2.3弱电工程'!$B$4:$I$195,8,0) -> 3215.93 | J14: =VLOOKUP(B14,'[1]2.3弱电工程'!$B$4:$J$195,9,0) -> 10.49 | K14: =VLOOKUP(B14,'[1]2.3弱电工程'!$B$4:$K$195,10,0) -> 15.59 | L14: =$L$4 -> 0.207 | M14: =F14*G14 -> 0
A15: 12 | B15: 千兆可网管交换机 | C15: 1.名称：交换机 2.规格型号：TP-LINK：TL-SG2226P，可网管、不低于24口，POE供电 3.包括为满足设计、验收规范规定施工所需的一切工序 | D15: 按设计图示数量计算 | E15: 台 | F15: 2 | G15: =(H15+I15+J15+K15)*(1+L15) -> 1530.3191 | H15: =VLOOKUP(B15,'[1]2.3弱电工程'!$B$4:$H$195,7,0) -> 614.25 | I15: =VLOOKUP(B15,'[1]2.3弱电工程'!$B$4:$I$195,8,0) -> 632.74 | J15: =VLOOKUP(B15,'[1]2.3弱电工程'!$B$4:$J$195,9,0) -> 10.49 | K15: =VLOOKUP(B15,'[1]2.3弱电工程'!$B$4:$K$195,10,0) -> 10.39 | L15: =$L$4 -> 0.207 | M15: =F15*G15 -> 3060.6382
A16: 13 | B16: 工业级以太网交换机 | C16: 1.名称:工业级以太网交换机 2.功能:不低于4个千兆电口+2千兆SFP光口插槽，含光模块、含电源适配器 | D16: 按设计图示数量计算 | E16: 台 | G16: =(H16+I16+J16+K16)*(1+L16) -> 1270.2347 | H16: =VLOOKUP(B16,'[1]2.3弱电工程'!$B$4:$H$195,7,0) -> 614.25 | I16: =VLOOKUP(B16,'[1]2.3弱电工程'!$B$4:$I$195,8,0) -> 417.26 | J16: =VLOOKUP(B16,'[1]2.3弱电工程'!$B$4:$J$195,9,0) -> 10.49 | K16: =VLOOKUP(B16,'[1]2.3弱电工程'!$B$4:$K$195,10,0) -> 10.39 | L16: =$L$4 -> 0.207 | M16: =F16*G16 -> 0
A17: 14 | B17: 路由器 | C17: 1.名称：路由器 2.规格型号：TP-LINK：TL-ER3200G千兆企业级， 3.包括为满足设计、验收规范规定施工所需的一切工序 | D17: 按设计图示数量计算 | E17: 台 | F17: 4 | G17: =(H17+I17+J17+K17)*(1+L17) -> 744.67072 | H17: =VLOOKUP(B17,'[1]2.3弱电工程'!$B$4:$H$195,7,0) -> 182 | I17: =VLOOKUP(B17,'[1]2.3弱电工程'!$B$4:$I$195,8,0) -> 420.31 | J17: =VLOOKUP(B17,'[1]2.3弱电工程'!$B$4:$J$195,9,0) -> 10.49 | K17: =VLOOKUP(B17,'[1]2.3弱电工程'!$B$4:$K$195,10,0) -> 4.16 | L17: =$L$4 -> 0.207 | M17: =F17*G17 -> 2978.6829
A18: 15 | B18: 显示器 | C18: 1.名称:显示器 2.规格:尺寸23.8英寸，分辨率：1920*1080像素，接口：DP、HDMI，附带一根3米HDMI线、键盘1个、鼠标1个 | D18: 按设计图示数量计算 | E18: 台 | F18: 4 | G18: =(H18+I18+J18+K18)*(1+L18) -> 606.38473 | H18: =VLOOKUP(B18,'[1]2.3弱电工程'!$B$4:$H$195,7,0) -> 54.6 | I18: =VLOOKUP(B18,'[1]2.3弱电工程'!$B$4:$I$195,8,0) -> 447.79 | J18: =VLOOKUP(B18,'[1]2.3弱电工程'!$B$4:$J$195,9,0) -> 0 | K18: =VLOOKUP(B18,'[1]2.3弱电工程'!$B$4:$K$195,10,0) -> 0 | L18: =$L$4 -> 0.207 | M18: =F18*G18 -> 2425.5389
A19: 16 | B19: 100寸电视(包括电视伸缩支架的采购、安装) | C19: 1.名称:100寸电视 2.类别:(包括电视支架的采购、安装) 3.规格:100寸，选用酷开创维 | D19: 按设计图示数量计算 | E19: 台 | F19: 1 | G19: =(H19+I19+J19+K19)*(1+L19) -> 11828.503 | H19: =VLOOKUP(B19,'[1]2.3弱电工程'!$B$4:$H$195,7,0) -> 63.7 | I19: =VLOOKUP(B19,'[1]2.3弱电工程'!$B$4:$I$195,8,0) -> 9734.51 | J19: =VLOOKUP(B19,'[1]2.3弱电工程'!$B$4:$J$195,9,0) -> 1.71 | K19: =VLOOKUP(B19,'[1]2.3弱电工程'!$B$4:$K$195,10,0) -> 0 | L19: =$L$4 -> 0.207 | M19: =F19*G19 -> 11828.503
A20: 17 | B20: 75寸电视(包括伸缩支架的采购、安装) | C20: 1.名称:75寸电视 2.类别:(包括电视支架的采购、安装) 3.规格:75寸，选用酷开创维 | D20: 按设计图示数量计算 | E20: 台 | F20: 1 | G20: =(H20+I20+J20+K20)*(1+L20) -> 4609.4244 | H20: 63.7 | I20: 3750 | J20: 1.71 | K20: 3.5 | L20: =$L$4 -> 0.207 | M20: =F20*G20 -> 4609.4244
A21: 18 | B21: 65寸电视(包括伸缩支架的采购、安装) | C21: 1.名称:65寸电视 2.类别:(包括电视支架的采购、安装) 3.规格:65寸，选用酷开创维 | D21: 按设计图示数量计算 | E21: 台 | F21: 1 | G21: =(H21+I21+J21+K21)*(1+L21) -> 3523.1244 | H21: 63.7 | I21: 2850 | J21: 1.71 | K21: 3.5 | L21: =$L$4 -> 0.207 | M21: =F21*G21 -> 3523.1244
A22: 19 | B22: 智能电表 | C22: 1.名称:智能电表 2.规格:采用4G无线联网，赠送至少8年流量，无需采集器，赠送平台，可查看用电量情况 | D22: 按设计图示数量计算 | E22: 台 | F22: 4 | G22: =(H22+I22+J22+K22)*(1+L22) -> 444.51396 | H22: =VLOOKUP(B22,'[1]2.3弱电工程'!$B$4:$H$195,7,0) -> 250.25 | I22: =VLOOKUP(B22,'[1]2.3弱电工程'!$B$4:$I$195,8,0) -> 116.81 | J22: =VLOOKUP(B22,'[1]2.3弱电工程'!$B$4:$J$195,9,0) -> 1.22 | K22: =VLOOKUP(B22,'[1]2.3弱电工程'!$B$4:$K$195,10,0) -> 0 | L22: =$L$4 -> 0.207 | M22: =F22*G22 -> 1778.0558
A23: 20 | B23: 桌面型防火墙 | C23: 1.名称：桌面型防火墙 2.规格型号：TP-LINK：TL-FW5600，支持配置安全策略、审计策略、带宽策略，包含2年病毒库免费升级服务 3.包括为满足设计、验收规范规定施工所需的一切工序 | D23: 按设计图示数量计算 | E23: 台 | F23: 21 | G23: =(H23+I23+J23+K23)*(1+L23) -> 2450.2221 | H23: =VLOOKUP(B23,'[1]2.3弱电工程'!$B$4:$H$195,7,0) -> 364 | I23: =VLOOKUP(B23,'[1]2.3弱电工程'!$B$4:$I$195,8,0) -> 1645.13 | J23: =VLOOKUP(B23,'[1]2.3弱电工程'!$B$4:$J$195,9,0) -> 10.49 | K23: =VLOOKUP(B23,'[1]2.3弱电工程'!$B$4:$K$195,10,0) -> 10.39 | L23: =$L$4 -> 0.207 | M23: =F23*G23 -> 51454.663
A24: 21 | B24: 无线AP | C24: 1.名称：无线AP 2.规格型号：TP-LINK：TL-XAP1506GC-PoE/DC易展版、千兆、802.11ax、双频WIFI，参考 3.包括为满足设计、验收规范规定施工所需的一切工序 | D24: 按设计图示数量计算 | E24: 台 | F24: 11 | G24: =(H24+I24+J24+K24)*(1+L24) -> 434.87003 | H24: =VLOOKUP(B24,'[1]2.3弱电工程'!$B$4:$H$195,7,0) -> 68.25 | I24: =VLOOKUP(B24,'[1]2.3弱电工程'!$B$4:$I$195,8,0) -> 292.04 | J24: =VLOOKUP(B24,'[1]2.3弱电工程'!$B$4:$J$195,9,0) -> 0 | K24: =VLOOKUP(B24,'[1]2.3弱电工程'!$B$4:$K$195,10,0) -> 0 | L24: =$L$4 -> 0.207 | M24: =F24*G24 -> 4783.5703
A25: 22 | B25: 单口信息插座 | C25: 1.名称:单口信息插座 2.规格:白色，含同等品牌六类非屏蔽模块 3.安装方式:暗装 | D25: 按设计图示数量计算 | E25: 个 | F25: 26 | G25: =(H25+I25+J25+K25)*(1+L25) -> 38.84126 | H25: =VLOOKUP(B25,'[1]2.3弱电工程'!$B$4:$H$195,7,0) -> 11.38 | I25: =VLOOKUP(B25,'[1]2.3弱电工程'!$B$4:$I$195,8,0) -> 20.8 | J25: =VLOOKUP(B25,'[1]2.3弱电工程'!$B$4:$J$195,9,0) -> 0 | K25: =VLOOKUP(B25,'[1]2.3弱电工程'!$B$4:$K$195,10,0) -> 0 | L25: =$L$4 -> 0.207 | M25: =F25*G25 -> 1009.8728
A26: 23 | B26: 双口信息插座 | C26: 1.名称:双口信息插座 2.规格:白色，含同等品牌六类非屏蔽模块 3.安装方式:暗装 | D26: 按设计图示数量计算 | E26: 个 | G26: =(H26+I26+J26+K26)*(1+L26) -> 51.35785 | H26: =VLOOKUP(B26,'[1]2.3弱电工程'!$B$4:$H$195,7,0) -> 13.65 | I26: =VLOOKUP(B26,'[1]2.3弱电工程'!$B$4:$I$195,8,0) -> 28.9 | J26: =VLOOKUP(B26,'[1]2.3弱电工程'!$B$4:$J$195,9,0) -> 0 | K26: =VLOOKUP(B26,'[1]2.3弱电工程'!$B$4:$K$195,10,0) -> 0 | L26: =$L$4 -> 0.207 | M26: =F26*G26 -> 0
A27: 24 | B27: 六类非屏蔽网线 | C27: 1.名称:六类非屏蔽网线 2.敷设方式:综合考虑 | D27: 按设计图示尺寸以长度计算 | E27: m | F27: 3569.5 | G27: =(H27+I27+J27+K27)*(1+L27) -> 5.05733 | H27: =VLOOKUP(B27,'[1]2.3弱电工程'!$B$4:$H$195,7,0) -> 1.57 | I27: =VLOOKUP(B27,'[1]2.3弱电工程'!$B$4:$I$195,8,0) -> 2.61 | J27: =VLOOKUP(B27,'[1]2.3弱电工程'!$B$4:$J$195,9,0) -> 0.01 | K27: =VLOOKUP(B27,'[1]2.3弱电工程'!$B$4:$K$195,10,0) -> 0 | L27: =$L$4 -> 0.207 | M27: =F27*G27 -> 18052.139
A28: 25 | B28: RVV-2*1.0 | C28: 1.名称:RVV-2*1.0 2.敷设方式:综合考虑 | D28: 按设计图示尺寸以长度计算 | E28: m | F28: 125 | G28: =(H28+I28+J28+K28)*(1+L28) -> 5.82981 | H28: =VLOOKUP(B28,'[1]2.3弱电工程'!$B$4:$H$195,7,0) -> 1.73 | I28: =VLOOKUP(B28,'[1]2.3弱电工程'!$B$4:$I$195,8,0) -> 2.92 | J28: =VLOOKUP(B28,'[1]2.3弱电工程'!$B$4:$J$195,9,0) -> 0.18 | K28: =VLOOKUP(B28,'[1]2.3弱电工程'!$B$4:$K$195,10,0) -> 0 | L28: =$L$4 -> 0.207 | M28: =F28*G28 -> 728.72625
A29: 26 | B29: RVV-2*2.5 | C29: 1.名称:RVV-2*2.5 2.敷设方式:综合考虑 | D29: 按设计图示尺寸以长度计算 | E29: m | F29: 1113.3 | G29: =(H29+I29+J29+K29)*(1+L29) -> 9.2939 | H29: =VLOOKUP(B29,'[1]2.3弱电工程'!$B$4:$H$195,7,0) -> 1.73 | I29: =VLOOKUP(B29,'[1]2.3弱电工程'!$B$4:$I$195,8,0) -> 5.79 | J29: =VLOOKUP(B29,'[1]2.3弱电工程'!$B$4:$J$195,9,0) -> 0.18 | K29: =VLOOKUP(B29,'[1]2.3弱电工程'!$B$4:$K$195,10,0) -> 0 | L29: =$L$4 -> 0.207 | M29: =F29*G29 -> 10346.899
A30: 27 | B30: 六类非屏蔽成品跳线 | C30: 1.名称:六类非屏蔽成品跳线 | D30: 按设计图示数量计算 | E30: 条 | F30: 1 | G30: =(H30+I30+J30+K30)*(1+L30) -> 25.16595 | H30: 4.55 | I30: 15.6 | J30: 0.5 | K30: 0.2 | L30: =$L$4 -> 0.207 | M30: =F30*G30 -> 25.16595
A31: 28 | B31: 双光纤跳线 | C31: 1.名称:双光纤跳线 2.类别:单模，双芯，2M，支持FC/SC/ST/LC互转 | D31: 按设计图示数量计算 | E31: 条 | G31: =(H31+I31+J31+K31)*(1+L31) -> 33.36148 | H31: 4.55 | I31: 22.39 | J31: 0.5 | K31: 0.2 | L31: =$L$4 -> 0.207 | M31: =F31*G31 -> 0
A32: 29 | B32: 尾纤2m | C32: 1.名称:尾纤2m | D32: 按设计图示数量计算 | E32: 根 | G32: =(H32+I32+J32+K32)*(1+L32) -> 28.15931 | H32: =VLOOKUP(B32,'[1]2.3弱电工程'!$B$4:$H$195,7,0) -> 18.13 | I32: =VLOOKUP(B32,'[1]2.3弱电工程'!$B$4:$I$195,8,0) -> 3.1 | J32: =VLOOKUP(B32,'[1]2.3弱电工程'!$B$4:$J$195,9,0) -> 0 | K32: =VLOOKUP(B32,'[1]2.3弱电工程'!$B$4:$K$195,10,0) -> 2.1 | L32: =$L$4 -> 0.207 | M32: =F32*G32 -> 0
A33: 30 | B33: 配管JDG20 | C33: 1.名称:配管JDG20 2.材质:镀锌薄钢管 3.规格:Φ20 4.配置形式:明配 5.接地要求:按规范要求 6.其他:含支、吊架制作安装 | D33: 按设计图示尺寸以长度计算 | E33: m | F33: 258.5 | G33: =(H33+I33+J33+K33)*(1+L33) -> 20.53107 | H33: 10.09 | I33: 4.84 | J33: 1.58 | K33: 0.5 | L33: =$L$4 -> 0.207 | M33: =F33*G33 -> 5307.2816
A34: 31 | B34: 配管JDG20 | C34: 1.名称:配管JDG20 2.材质:镀锌薄钢管 3.规格Φ20 4.配置形式:暗配 5.接地要求:按规范要求 | D34: 按设计图示尺寸以长度计算 | E34: m | G34: =(H34+I34+J34+K34)*(1+L34) -> 19.93964 | H34: 10.74 | I34: 4.84 | J34: 0.44 | K34: 0.5 | L34: =$L$4 -> 0.207 | M34: =F34*G34 -> 0
A35: 32 | B35: 配管JDG25 | C35: 1.名称:配管JDG25 2.材质:镀锌薄钢管 3.规格:Φ25 4.配置形式:明配 5.接地要求:按规范要求 6.其他:含支、吊架制作安装 | D35: 按设计图示尺寸以长度计算 | E35: m | G35: =(H35+I35+J35+K35)*(1+L35) -> 22.80023 | H35: 11.59 | I35: 5.65 | J35: 1.15 | K35: 0.5 | L35: =$L$4 -> 0.207 | M35: =F35*G35 -> 0
A36: 33 | B36: 配管JDG25 | C36: 1.名称:配管JDG25 2.材质:镀锌薄钢管 3.规格Φ25 4.配置形式:暗配 5.接地要求:按规范要求 | D36: 按设计图示尺寸以长度计算 | E36: m | G36: =(H36+I36+J36+K36)*(1+L36) -> 20.42244 | H36: 10.33 | I36: 5.65 | J36: 0.44 | K36: 0.5 | L36: =$L$4 -> 0.207 | M36: =F36*G36 -> 0
A37: 34 | B37: 配管JDG32 | C37: 1.名称:配管JDG32 2.材质:镀锌薄钢管 3.规格:Φ32 4.配置形式:明配 5.接地要求:按规范要求 6.其他:含支、吊架制作安装 | D37: 按设计图示尺寸以长度计算 | E37: m | G37: =(H37+I37+J37+K37)*(1+L37) -> 29.05249 | H37: 13.56 | I37: 8.32 | J37: 1.69 | K37: 0.5 | L37: =$L$4 -> 0.207 | M37: =F37*G37 -> 0
A38: 35 | B38: 配管JDG32 | C38: 1.名称:配管JDG32 2.材质:镀锌薄钢管 3.规格Φ32 4.配置形式:暗配 5.接地要求:按规范要求 | D38: 按设计图示尺寸以长度计算 | E38: m | G38: =(H38+I38+J38+K38)*(1+L38) -> 25.92636 | H38: 11.78 | I38: 8.32 | J38: 0.88 | K38: 0.5 | L38: =$L$4 -> 0.207 | M38: =F38*G38 -> 0
A39: 36 | B39: 配管PCDN20 | C39: 1.名称:配管PCDN20 2.材质:PC 3.规格:DN20mm 4.配置形式:明配 5.接地要求:按规范要求 | D39: 按设计图示尺寸以长度计算 | E39: m | G39: =(H39+I39+J39+K39)*(1+L39) -> 14.42365 | H39: =VLOOKUP(B39,'[1]2.3弱电工程'!$B$4:$H$195,7,0) -> 9.21 | I39: =VLOOKUP(B39,'[1]2.3弱电工程'!$B$4:$I$195,8,0) -> 1.67 | J39: =VLOOKUP(B39,'[1]2.3弱电工程'!$B$4:$J$195,9,0) -> 1.07 | K39: =VLOOKUP(B39,'[1]2.3弱电工程'!$B$4:$K$195,10,0) -> 0 | L39: =$L$4 -> 0.207 | M39: =F39*G39 -> 0
A40: 37 | B40: 配管PCDN20 | C40: 1.名称:配管PCDN20 2.材质:PC 3.规格:DN20mm 4.配置形式:暗配 5.接地要求:按规范要求 | D40: 按设计图示尺寸以长度计算 | E40: m | G40: =(H40+I40+J40+K40)*(1+L40) -> 14.42365 | H40: =VLOOKUP(B40,'[1]2.3弱电工程'!$B$4:$H$195,7,0) -> 9.21 | I40: =VLOOKUP(B40,'[1]2.3弱电工程'!$B$4:$I$195,8,0) -> 1.67 | J40: =VLOOKUP(B40,'[1]2.3弱电工程'!$B$4:$J$195,9,0) -> 1.07 | K40: =VLOOKUP(B40,'[1]2.3弱电工程'!$B$4:$K$195,10,0) -> 0 | L40: =$L$4 -> 0.207 | M40: =F40*G40 -> 0
A41: 38 | B41: 配管PCDN25 | C41: 1.名称:配管PCDN25 2.材质:PC 3.规格:DN25mm 4.配置形式:明配 5.接地要求:按规范要求 | D41: 按设计图示尺寸以长度计算 | E41: m | G41: =(H41+I41+J41+K41)*(1+L41) -> 16.7773 | H41: =VLOOKUP(B41,'[1]2.3弱电工程'!$B$4:$H$195,7,0) -> 11.1 | I41: =VLOOKUP(B41,'[1]2.3弱电工程'!$B$4:$I$195,8,0) -> 1.7 | J41: =VLOOKUP(B41,'[1]2.3弱电工程'!$B$4:$J$195,9,0) -> 1.1 | K41: =VLOOKUP(B41,'[1]2.3弱电工程'!$B$4:$K$195,10,0) -> 0 | L41: =$L$4 -> 0.207 | M41: =F41*G41 -> 0
A42: 39 | B42: 配管PCDN25 | C42: 1.名称:配管PCDN25 2.材质:PC 3.规格:DN25mm 4.配置形式:暗配 5.接地要求:按规范要求 | D42: 按设计图示尺寸以长度计算 | E42: m | G42: =(H42+I42+J42+K42)*(1+L42) -> 16.7773 | H42: =VLOOKUP(B42,'[1]2.3弱电工程'!$B$4:$H$195,7,0) -> 11.1 | I42: =VLOOKUP(B42,'[1]2.3弱电工程'!$B$4:$I$195,8,0) -> 1.7 | J42: =VLOOKUP(B42,'[1]2.3弱电工程'!$B$4:$J$195,9,0) -> 1.1 | K42: =VLOOKUP(B42,'[1]2.3弱电工程'!$B$4:$K$195,10,0) -> 0 | L42: =$L$4 -> 0.207 | M42: =F42*G42 -> 0
A43: 40 | B43: 配管PCDN32 | C43: 1.名称:配管PCDN32 2.材质:PC 3.规格:DN32mm 4.配置形式:明配 5.接地要求:按规范要求 | D43: 按设计图示尺寸以长度计算 | E43: m | G43: =(H43+I43+J43+K43)*(1+L43) -> 19.34821 | H43: =VLOOKUP(B43,'[1]2.3弱电工程'!$B$4:$H$195,7,0) -> 10.6 | I43: =VLOOKUP(B43,'[1]2.3弱电工程'!$B$4:$I$195,8,0) -> 3.94 | J43: =VLOOKUP(B43,'[1]2.3弱电工程'!$B$4:$J$195,9,0) -> 1.49 | K43: =VLOOKUP(B43,'[1]2.3弱电工程'!$B$4:$K$195,10,0) -> 0 | L43: =$L$4 -> 0.207 | M43: =F43*G43 -> 0
A44: 41 | B44: 配管PCDN32 | C44: 1.名称:配管PCDN32 2.材质:PC 3.规格:DN32mm 4.配置形式:暗配 5.接地要求:按规范要求 | D44: 按设计图示尺寸以长度计算 | E44: m | G44: =(H44+I44+J44+K44)*(1+L44) -> 19.34821 | H44: =VLOOKUP(B44,'[1]2.3弱电工程'!$B$4:$H$195,7,0) -> 10.6 | I44: =VLOOKUP(B44,'[1]2.3弱电工程'!$B$4:$I$195,8,0) -> 3.94 | J44: =VLOOKUP(B44,'[1]2.3弱电工程'!$B$4:$J$195,9,0) -> 1.49 | K44: =VLOOKUP(B44,'[1]2.3弱电工程'!$B$4:$K$195,10,0) -> 0 | L44: =$L$4 -> 0.207 | M44: =F44*G44 -> 0
A45: 42 | B45: 金属软管DN20 | C45: 1.名称:金属软管DN20 2.材质:金属软管 3.规格:DN20mm 4.配置形式:明配 5.接地要求:按规范要求 | D45: 按设计图示尺寸以长度计算 | E45: m | G45: =(H45+I45+J45+K45)*(1+L45) -> 13.28907 | H45: =VLOOKUP(B45,'[1]2.3弱电工程'!$B$4:$H$195,7,0) -> 6.9 | I45: =VLOOKUP(B45,'[1]2.3弱电工程'!$B$4:$I$195,8,0) -> 3 | J45: =VLOOKUP(B45,'[1]2.3弱电工程'!$B$4:$J$195,9,0) -> 1.11 | K45: =VLOOKUP(B45,'[1]2.3弱电工程'!$B$4:$K$195,10,0) -> 0 | L45: =$L$4 -> 0.207 | M45: =F45*G45 -> 0
A46: 43 | B46: 金属软管DN25 | C46: 1.名称:金属软管DN25 2.材质:金属软管 3.规格:DN25mm 4.配置形式:明配 5.接地要求:按规范要求 | D46: 按设计图示尺寸以长度计算 | E46: m | G46: =(H46+I46+J46+K46)*(1+L46) -> 14.74954 | H46: =VLOOKUP(B46,'[1]2.3弱电工程'!$B$4:$H$195,7,0) -> 8 | I46: =VLOOKUP(B46,'[1]2.3弱电工程'!$B$4:$I$195,8,0) -> 3.2 | J46: =VLOOKUP(B46,'[1]2.3弱电工程'!$B$4:$J$195,9,0) -> 1.02 | K46: =VLOOKUP(B46,'[1]2.3弱电工程'!$B$4:$K$195,10,0) -> 0 | L46: =$L$4 -> 0.207 | M46: =F46*G46 -> 0
A47: 44 | B47: 弱电线槽100*50 | C47: 1.名称:弱电线槽100*50 2.材质:PVC 3.接地方式:按规范要求 4.其他:含支、吊架制作安装 | D47: 按设计图示尺寸以长度计算 | E47: m | G47: =(H47+I47+J47+K47)*(1+L47) -> 44.04343 | H47: =VLOOKUP(B47,'[1]2.3弱电工程'!$B$4:$H$195,7,0) -> 29.8 | I47: =VLOOKUP(B47,'[1]2.3弱电工程'!$B$4:$I$195,8,0) -> 6 | J47: =VLOOKUP(B47,'[1]2.3弱电工程'!$B$4:$J$195,9,0) -> 0.69 | K47: =VLOOKUP(B47,'[1]2.3弱电工程'!$B$4:$K$195,10,0) -> 0 | L47: =$L$4 -> 0.207 | M47: =F47*G47 -> 0
A48: 45 | B48: 弱电桥架100*50 | C48: 1.名称:弱电桥架100*50 2.材质:钢制 3.接地方式:按规范要求 4.其他:含支、吊架制作安装 | D48: 按设计图示尺寸以长度计算 | E48: m | G48: =(H48+I48+J48+K48)*(1+L48) -> 64.91246 | H48: =VLOOKUP(B48,'[1]2.3弱电工程'!$B$4:$H$195,7,0) -> 29.8 | I48: =VLOOKUP(B48,'[1]2.3弱电工程'!$B$4:$I$195,8,0) -> 14.9 | J48: =VLOOKUP(B48,'[1]2.3弱电工程'!$B$4:$J$195,9,0) -> 8.56 | K48: =VLOOKUP(B48,'[1]2.3弱电工程'!$B$4:$K$195,10,0) -> 0.52 | L48: =$L$4 -> 0.207 | M48: =F48*G48 -> 0
A49: 46 | B49: 弱电桥架100*100 | C49: 1.名称:弱电桥架100*100 2.材质:钢制 3.接地方式:按规范要求 4.其他:含支、吊架制作安装 | D49: 按设计图示尺寸以长度计算 | E49: m | G49: =(H49+I49+J49+K49)*(1+L49) -> 76.70485 | H49: =VLOOKUP(B49,'[1]2.3弱电工程'!$B$4:$H$195,7,0) -> 24.57 | I49: =VLOOKUP(B49,'[1]2.3弱电工程'!$B$4:$I$195,8,0) -> 29.9 | J49: =VLOOKUP(B49,'[1]2.3弱电工程'!$B$4:$J$195,9,0) -> 8.56 | K49: =VLOOKUP(B49,'[1]2.3弱电工程'!$B$4:$K$195,10,0) -> 0.52 | L49: =$L$4 -> 0.207 | M49: =F49*G49 -> 0
A50: 47 | B50: 弱电桥架150*100 | C50: 1.名称:弱电桥架150*100 2.材质:钢制 3.接地方式:按规范要求 4.其他:含支、吊架制作安装 | D50: 按设计图示尺寸以长度计算 | E50: m | G50: =(H50+I50+J50+K50)*(1+L50) -> 89.02832 | H50: =VLOOKUP(B50,'[1]2.3弱电工程'!$B$4:$H$195,7,0) -> 30.95 | I50: =VLOOKUP(B50,'[1]2.3弱电工程'!$B$4:$I$195,8,0) -> 33.19 | J50: =VLOOKUP(B50,'[1]2.3弱电工程'!$B$4:$J$195,9,0) -> 8.61 | K50: =VLOOKUP(B50,'[1]2.3弱电工程'!$B$4:$K$195,10,0) -> 1.01 | L50: =$L$4 -> 0.207 | M50: =F50*G50 -> 0
A51: 48 | B51: 弱电桥架200*100 | C51: 1.名称:弱电桥架200*100 2.材质:钢制 3.接地方式:按规范要求 4.其他:含支、吊架制作安装 | D51: 按设计图示尺寸以长度计算 | E51: m | F51: 269.73 | G51: =(H51+I51+J51+K51)*(1+L51) -> 95.92029 | H51: =VLOOKUP(B51,'[1]2.3弱电工程'!$B$4:$H$195,7,0) -> 30.95 | I51: =VLOOKUP(B51,'[1]2.3弱电工程'!$B$4:$I$195,8,0) -> 38.9 | J51: =VLOOKUP(B51,'[1]2.3弱电工程'!$B$4:$J$195,9,0) -> 8.61 | K51: =VLOOKUP(B51,'[1]2.3弱电工程'!$B$4:$K$195,10,0) -> 1.01 | L51: =$L$4 -> 0.207 | M51: =F51*G51 -> 25872.58
A52: 49 | B52: 弱电桥架200*150 | C52: 1.名称:弱电桥架200*150 2.材质:钢制 3.接地方式:按规范要求 4.其他:含支、吊架制作安装 | D52: 按设计图示尺寸以长度计算 | E52: m | G52: =(H52+I52+J52+K52)*(1+L52) -> 107.02469 | H52: =VLOOKUP(B52,'[1]2.3弱电工程'!$B$4:$H$195,7,0) -> 30.95 | I52: =VLOOKUP(B52,'[1]2.3弱电工程'!$B$4:$I$195,8,0) -> 48.1 | J52: =VLOOKUP(B52,'[1]2.3弱电工程'!$B$4:$J$195,9,0) -> 8.61 | K52: =VLOOKUP(B52,'[1]2.3弱电工程'!$B$4:$K$195,10,0) -> 1.01 | L52: =$L$4 -> 0.207 | M52: =F52*G52 -> 0
A53: 50 | B53: 接线盒 | C53: 1.名称:接线盒 2.材质:铁质 3.安装形式:明装 | D53: 按设计图示数量计算 | E53: 个 | G53: =(H53+I53+J53+K53)*(1+L53) -> 8.60591 | H53: =VLOOKUP(B53,'[1]2.3弱电工程'!$B$4:$H$195,7,0) -> 5.1 | I53: =VLOOKUP(B53,'[1]2.3弱电工程'!$B$4:$I$195,8,0) -> 1.61 | J53: =VLOOKUP(B53,'[1]2.3弱电工程'!$B$4:$J$195,9,0) -> 0.42 | K53: =VLOOKUP(B53,'[1]2.3弱电工程'!$B$4:$K$195,10,0) -> 0 | L53: =$L$4 -> 0.207 | M53: =F53*G53 -> 0
A54: 51 | B54: 接线盒 | C54: 1.名称:接线盒 2.材质:铁质 3.安装形式:暗装 | D54: 按设计图示数量计算 | E54: 个 | G54: =(H54+I54+J54+K54)*(1+L54) -> 8.60591 | H54: =VLOOKUP(B54,'[1]2.3弱电工程'!$B$4:$H$195,7,0) -> 5.1 | I54: =VLOOKUP(B54,'[1]2.3弱电工程'!$B$4:$I$195,8,0) -> 1.61 | J54: =VLOOKUP(B54,'[1]2.3弱电工程'!$B$4:$J$195,9,0) -> 0.42 | K54: =VLOOKUP(B54,'[1]2.3弱电工程'!$B$4:$K$195,10,0) -> 0 | L54: =$L$4 -> 0.207 | M54: =F54*G54 -> 0
A55: 52 | B55: 接线盒 | C55: 1.名称:接线盒 2.材质:PC 3.安装形式:明装 | D55: 按设计图示数量计算 | E55: 个 | G55: =(H55+I55+J55+K55)*(1+L55) -> 8.60591 | H55: =VLOOKUP(B55,'[1]2.3弱电工程'!$B$4:$H$195,7,0) -> 5.1 | I55: =VLOOKUP(B55,'[1]2.3弱电工程'!$B$4:$I$195,8,0) -> 1.61 | J55: =VLOOKUP(B55,'[1]2.3弱电工程'!$B$4:$J$195,9,0) -> 0.42 | K55: =VLOOKUP(B55,'[1]2.3弱电工程'!$B$4:$K$195,10,0) -> 0 | L55: =$L$4 -> 0.207 | M55: =F55*G55 -> 0
A56: 53 | B56: 接线盒 | C56: 1.名称:接线盒 2.材质:PC 3.安装形式:暗装 | D56: 按设计图示数量计算 | E56: 个 | G56: =(H56+I56+J56+K56)*(1+L56) -> 8.60591 | H56: =VLOOKUP(B56,'[1]2.3弱电工程'!$B$4:$H$195,7,0) -> 5.1 | I56: =VLOOKUP(B56,'[1]2.3弱电工程'!$B$4:$I$195,8,0) -> 1.61 | J56: =VLOOKUP(B56,'[1]2.3弱电工程'!$B$4:$J$195,9,0) -> 0.42 | K56: =VLOOKUP(B56,'[1]2.3弱电工程'!$B$4:$K$195,10,0) -> 0 | L56: =$L$4 -> 0.207 | M56: =F56*G56 -> 0
A57: 二 | B57: 监控系统
A58: 1 | B58: 8T专用硬盘 | C58: 1.名称:8T专用硬盘 2.规格:参考海康威视ST8000HKVS002(标配)/监控盘 | D58: 按设计图示数量计算 | E58: 块 | F58: 2 | G58: =(H58+I58+J58+K58)*(1+L58) -> 1558.7319 | H58: =VLOOKUP(B58,'[1]2.3弱电工程'!$B$4:$H$195,7,0) -> 218.4 | I58: =VLOOKUP(B58,'[1]2.3弱电工程'!$B$4:$I$195,8,0) -> 1070.8 | J58: =VLOOKUP(B58,'[1]2.3弱电工程'!$B$4:$J$195,9,0) -> 2.21 | K58: =VLOOKUP(B58,'[1]2.3弱电工程'!$B$4:$K$195,10,0) -> 0 | L58: =$L$4 -> 0.207 | M58: =F58*G58 -> 3117.4637
A59: 2 | B59: 硬盘录像机 | C59: 1.名称:硬盘录像机 2.规格:海康威视DS-7608N-I3-V3(标配)(2×4T定制盘)，录像时间大于45天 | D59: 按设计图示数量计算 | E59: 台 | F59: 2 | G59: =(H59+I59+J59+K59)*(1+L59) -> 2682.0626 | H59: =VLOOKUP(B59,'[1]2.3弱电工程'!$B$4:$H$195,7,0) -> 1685.63 | I59: =VLOOKUP(B59,'[1]2.3弱电工程'!$B$4:$I$195,8,0) -> 500.6 | J59: =VLOOKUP(B59,'[1]2.3弱电工程'!$B$4:$J$195,9,0) -> 10.49 | K59: =VLOOKUP(B59,'[1]2.3弱电工程'!$B$4:$K$195,10,0) -> 25.37 | L59: =$L$4 -> 0.207 | M59: =F59*G59 -> 5364.1253
A60: 3 | B60: 硬盘录像机 | C60: 1.名称:硬盘录像机 2.规格:海康威视DS-7632N-I3-V3(标配)(2×4T定制盘)，录像时间大于45天 | D60: 按设计图示数量计算 | E60: 台 | G60: =(H60+I60+J60+K60)*(1+L60) -> 2682.0626 | H60: =VLOOKUP(B60,'[1]2.3弱电工程'!$B$4:$H$195,7,0) -> 1685.63 | I60: =VLOOKUP(B60,'[1]2.3弱电工程'!$B$4:$I$195,8,0) -> 500.6 | J60: =VLOOKUP(B60,'[1]2.3弱电工程'!$B$4:$J$195,9,0) -> 10.49 | K60: =VLOOKUP(B60,'[1]2.3弱电工程'!$B$4:$K$195,10,0) -> 25.37 | L60: =$L$4 -> 0.207 | M60: =F60*G60 -> 0
A61: 4 | B61: 高清红外球机 | C61: 1.名称：高清红外球机 2.规格型号：海康威视：DS-2PT2A2GYL-DEY 3.包括为满足设计、验收规范规定施工所需的一切工序 | D61: 按设计图示数量计算 | E61: 台 | G61: =(H61+I61+J61+K61)*(1+L61) -> 1297.4646 | H61: =VLOOKUP(B61,'[1]2.3弱电工程'!$B$4:$H$195,7,0) -> 389.03 | I61: =VLOOKUP(B61,'[1]2.3弱电工程'!$B$4:$I$195,8,0) -> 676.99 | J61: =VLOOKUP(B61,'[1]2.3弱电工程'!$B$4:$J$195,9,0) -> 0 | K61: =VLOOKUP(B61,'[1]2.3弱电工程'!$B$4:$K$195,10,0) -> 8.93 | L61: =$L$4 -> 0.207 | M61: =F61*G61 -> 0
A62: 5 | B62: 半球摄像机 | C62: 1.名称：半球机 2.规格型号：海康威视：DS-2CD2725CGL3-IZS(2.7-8mm) 3.包括为满足设计、验收规范规定施工所需的一切工序 | D62: 按设计图示数量计算 | E62: 台 | F62: 21 | G62: =(H62+I62+J62+K62)*(1+L62) -> 611.49034 | H62: =VLOOKUP(B62,'[1]2.3弱电工程'!$B$4:$H$195,7,0) -> 150.9 | I62: =VLOOKUP(B62,'[1]2.3弱电工程'!$B$4:$I$195,8,0) -> 340.56 | J62: =VLOOKUP(B62,'[1]2.3弱电工程'!$B$4:$J$195,9,0) -> 0.18 | K62: =VLOOKUP(B62,'[1]2.3弱电工程'!$B$4:$K$195,10,0) -> 14.98 | L62: =$L$4 -> 0.207 | M62: =F62*G62 -> 12841.297
A63: 6 | B63: 枪型摄像机 | C63: 1.名称:枪型摄像机 2.类别:参考海康威视：DS-2CD264XY-GLZS(2.7-12mm) 3.安装方式:吸顶 | D63: 按设计图示数量计算 | E63: 台 | G63: =(H63+I63+J63+K63)*(1+L63) -> 752.11791 | H63: =VLOOKUP(B63,'[1]2.3弱电工程'!$B$4:$H$195,7,0) -> 150.15 | I63: =VLOOKUP(B63,'[1]2.3弱电工程'!$B$4:$I$195,8,0) -> 458 | J63: =VLOOKUP(B63,'[1]2.3弱电工程'!$B$4:$J$195,9,0) -> 0 | K63: =VLOOKUP(B63,'[1]2.3弱电工程'!$B$4:$K$195,10,0) -> 14.98 | L63: =$L$4 -> 0.207 | M63: =F63*G63 -> 0
A64: 7 | B64: 4K摄像头 | C64: 1.名称:4K摄像头 2.类别:K高清可旋转摄像头，视频存储时间完工后60天，摄像头账号权限对招标方开放 | D64: 按设计图示数量计算 | E64: 台 | G64: =(H64+I64+J64+K64)*(1+L64) -> 948.97961 | H64: =VLOOKUP(B64,'[1]2.3弱电工程'!$B$4:$H$195,7,0) -> 259.35 | I64: =VLOOKUP(B64,'[1]2.3弱电工程'!$B$4:$I$195,8,0) -> 511.9 | J64: =VLOOKUP(B64,'[1]2.3弱电工程'!$B$4:$J$195,9,0) -> 0 | K64: =VLOOKUP(B64,'[1]2.3弱电工程'!$B$4:$K$195,10,0) -> 14.98 | L64: =$L$4 -> 0.207 | M64: =F64*G64 -> 0
A65: 8 | B65: 枪球一体摄像机 | C65: 1.名称:枪球一体摄像机 2.类别:参考海康威视：iDS-2SE7C23GLW-XYZ 3.安装方式:吸顶 | D65: 按设计图示数量计算 | E65: 台 | F65: 4 | G65: =(H65+I65+J65+K65)*(1+L65) -> 1805.153 | H65: =VLOOKUP(B65,'[1]2.3弱电工程'!$B$4:$H$195,7,0) -> 259.35 | I65: =VLOOKUP(B65,'[1]2.3弱电工程'!$B$4:$I$195,8,0) -> 1221.24 | J65: =VLOOKUP(B65,'[1]2.3弱电工程'!$B$4:$J$195,9,0) -> 0 | K65: =VLOOKUP(B65,'[1]2.3弱电工程'!$B$4:$K$195,10,0) -> 14.98 | L65: =$L$4 -> 0.207 | M65: =F65*G65 -> 7220.612
A66: 9 | B66: 客流统计摄像机 | C66: 1.名称：客流统计摄像机 2.规格型号：海康威视：DS-2XD8147FGL/MC-IZS(2.8-12mm)，根据安装需要配备支架 3.包括为满足设计、验收规范规定施工所需的一切工序 | D66: 按设计图示数量计算 | E66: 台 | F66: 1 | G66: =(H66+I66+J66+K66)*(1+L66) -> 2407.4943 | H66: =VLOOKUP(B66,'[1]2.3弱电工程'!$B$4:$H$195,7,0) -> 305.03 | I66: =VLOOKUP(B66,'[1]2.3弱电工程'!$B$4:$I$195,8,0) -> 1680.65 | J66: =VLOOKUP(B66,'[1]2.3弱电工程'!$B$4:$J$195,9,0) -> 0 | K66: =VLOOKUP(B66,'[1]2.3弱电工程'!$B$4:$K$195,10,0) -> 8.93 | L66: =$L$4 -> 0.207 | M66: =F66*G66 -> 2407.4943
A67: 三 | B67: 背景音乐系统
A68: 1 | B68: 广播系统控制器 | C68: 1.名称:广播系统控制器 2.规格:参考ITC:T-6232A，包含SD存储卡及设备间互联的音频跳线 | D68: 按设计图示数量计算 | E68: 台 | F68: 1 | G68: =(H68+I68+J68+K68)*(1+L68) -> 11740.525 | H68: =VLOOKUP(B68,'[1]2.3弱电工程'!$B$4:$H$195,7,0) -> 523.25 | I68: =VLOOKUP(B68,'[1]2.3弱电工程'!$B$4:$I$195,8,0) -> 9201.61 | J68: =VLOOKUP(B68,'[1]2.3弱电工程'!$B$4:$J$195,9,0) -> 0 | K68: =VLOOKUP(B68,'[1]2.3弱电工程'!$B$4:$K$195,10,0) -> 2.17 | L68: =$L$4 -> 0.207 | M68: =F68*G68 -> 11740.525
A69: 2 | B69: 数字合并式功放 | C69: 1.名称:数字合并式功放 2.规格:参考ITC:T-120D，包含设备间互联的音频跳线 | D69: 按设计图示数量计算 | E69: 台 | F69: 10 | G69: =(H69+I69+J69+K69)*(1+L69) -> 5885.8872 | H69: =VLOOKUP(B69,'[1]2.3弱电工程'!$B$4:$H$195,7,0) -> 116.63 | I69: =VLOOKUP(B69,'[1]2.3弱电工程'!$B$4:$I$195,8,0) -> 4759.29 | J69: =VLOOKUP(B69,'[1]2.3弱电工程'!$B$4:$J$195,9,0) -> 0 | K69: =VLOOKUP(B69,'[1]2.3弱电工程'!$B$4:$K$195,10,0) -> 0.54 | L69: =$L$4 -> 0.207 | M69: =F69*G69 -> 58858.872
A70: 3 | B70: 信号发生器 | C70: 1.名称:信号发生器 2.规格:参考ITC:T-6203，包含设备间互联的音频跳线 | D70: 按设计图示数量计算 | E70: 台 | F70: 4 | G70: =(H70+I70+J70+K70)*(1+L70) -> 5019.2612 | H70: =VLOOKUP(B70,'[1]2.3弱电工程'!$B$4:$H$195,7,0) -> 625.63 | I70: =VLOOKUP(B70,'[1]2.3弱电工程'!$B$4:$I$195,8,0) -> 3526.55 | J70: =VLOOKUP(B70,'[1]2.3弱电工程'!$B$4:$J$195,9,0) -> 0 | K70: =VLOOKUP(B70,'[1]2.3弱电工程'!$B$4:$K$195,10,0) -> 6.28 | L70: =$L$4 -> 0.207 | M70: =F70*G70 -> 20077.045
A71: 4 | B71: 寻呼话筒 | C71: 1.名称:寻呼话筒 2.规格:参考ITC:T-621A，包含设备间互联的音频跳线 | D71: 按设计图示数量计算 | E71: 台 | F71: 2 | G71: =(H71+I71+J71+K71)*(1+L71) -> 1261.484 | H71: =VLOOKUP(B71,'[1]2.3弱电工程'!$B$4:$H$195,7,0) -> 22.75 | I71: =VLOOKUP(B71,'[1]2.3弱电工程'!$B$4:$I$195,8,0) -> 1022.12 | J71: =VLOOKUP(B71,'[1]2.3弱电工程'!$B$4:$J$195,9,0) -> 0 | K71: =VLOOKUP(B71,'[1]2.3弱电工程'!$B$4:$K$195,10,0) -> 0.27 | L71: =$L$4 -> 0.207 | M71: =F71*G71 -> 2522.968
A72: 5 | B72: 壁挂喇叭 | C72: 1.名称:壁挂喇叭 2.规格:参考ITC:T-601 3.安装方式:壁挂式 | D72: 按设计图示数量计算 | E72: 台 | G72: =(H72+I72+J72+K72)*(1+L72) -> 537.51331 | H72: =VLOOKUP(B72,'[1]2.3弱电工程'!$B$4:$H$195,7,0) -> 50.05 | I72: =VLOOKUP(B72,'[1]2.3弱电工程'!$B$4:$I$195,8,0) -> 380.63 | J72: =VLOOKUP(B72,'[1]2.3弱电工程'!$B$4:$J$195,9,0) -> 1.72 | K72: =VLOOKUP(B72,'[1]2.3弱电工程'!$B$4:$K$195,10,0) -> 12.93 | L72: =$L$4 -> 0.207 | M72: =F72*G72 -> 0
A73: 6 | B73: 天花喇叭 | C73: 1.名称:天花喇叭 2.规格:参考ITC:T-105A 3.安装方式:吸顶式 | D73: 按设计图示数量计算 | E73: 台 | G73: =(H73+I73+J73+K73)*(1+L73) -> 483.34315 | H73: =VLOOKUP(B73,'[1]2.3弱电工程'!$B$4:$H$195,7,0) -> 102.38 | I73: =VLOOKUP(B73,'[1]2.3弱电工程'!$B$4:$I$195,8,0) -> 283.19 | J73: =VLOOKUP(B73,'[1]2.3弱电工程'!$B$4:$J$195,9,0) -> 0.86 | K73: =VLOOKUP(B73,'[1]2.3弱电工程'!$B$4:$K$195,10,0) -> 14.02 | L73: =$L$4 -> 0.207 | M73: =F73*G73 -> 0
A74: 四 | B74: 门禁系统
A75: 1 | B75: 人脸门禁+人脸考勤 | C75: 1.名称：人脸门禁 2.规格型号：熵基FS600，摄像头≥200万像素，屏幕≥4.3英寸；识别准确率≥99.99%；支持数据网络上传功能及本地权限管理；能与飞书进行系统对接；包含出门按钮、开关电源、电磁锁（单双门依据现场门确定）及附属管线 3.包括为满足设计、验收规范规定施工所需的一切工序 | D75: 按设计图示数量计算 | E75: 台 | F75: 8 | G75: =(H75+I75+J75+K75)*(1+L75) -> 2196.6555 | H75: =VLOOKUP(B75,'[1]2.3弱电工程'!$B$4:$H$195,7,0) -> 193.38 | I75: =VLOOKUP(B75,'[1]2.3弱电工程'!$B$4:$I$195,8,0) -> 1626.55 | J75: =VLOOKUP(B75,'[1]2.3弱电工程'!$B$4:$J$195,9,0) -> 0 | K75: =VLOOKUP(B75,'[1]2.3弱电工程'!$B$4:$K$195,10,0) -> 0 | L75: =$L$4 -> 0.207 | M75: =F75*G75 -> 17573.244
A76: 2 | B76: 电磁门锁 | C76: 1.名称:电磁门锁 | D76: 按设计图示数量计算 | E76: 套 | G76: =(H76+I76+J76+K76)*(1+L76) -> 173.36141 | H76: =VLOOKUP(B76,'[1]2.3弱电工程'!$B$4:$H$195,7,0) -> 65.98 | I76: =VLOOKUP(B76,'[1]2.3弱电工程'!$B$4:$I$195,8,0) -> 75.22 | J76: =VLOOKUP(B76,'[1]2.3弱电工程'!$B$4:$J$195,9,0) -> 1.62 | K76: =VLOOKUP(B76,'[1]2.3弱电工程'!$B$4:$K$195,10,0) -> 0.81 | L76: =$L$4 -> 0.207 | M76: =F76*G76 -> 0
A77: 3 | B77: 出门按钮 | C77: 1.名称:出门按钮 | D77: 按设计图示数量计算 | E77: 个 | G77: =(H77+I77+J77+K77)*(1+L77) -> 45.21422 | H77: =VLOOKUP(B77,'[1]2.3弱电工程'!$B$4:$H$195,7,0) -> 10.2 | I77: =VLOOKUP(B77,'[1]2.3弱电工程'!$B$4:$I$195,8,0) -> 27 | J77: =VLOOKUP(B77,'[1]2.3弱电工程'!$B$4:$J$195,9,0) -> 0.04 | K77: =VLOOKUP(B77,'[1]2.3弱电工程'!$B$4:$K$195,10,0) -> 0.22 | L77: =$L$4 -> 0.207 | M77: =F77*G77 -> 0
A78: 五 | B78: 会议室投影系统
A79: 1 | B79: 多功能插座 | C79: 1.名称:多功能插座 2.规格:包含五孔插座、3.0USB接口、HDIM接口、音频接口等 3.安装方式:暗装 | D79: 按设计图示数量计算 | E79: 个 | G79: =(H79+I79+J79+K79)*(1+L79) -> 142.76396 | H79: =VLOOKUP(B79,'[1]2.3弱电工程'!$B$4:$H$195,7,0) -> 12.97 | I79: =VLOOKUP(B79,'[1]2.3弱电工程'!$B$4:$I$195,8,0) -> 102.9 | J79: =VLOOKUP(B79,'[1]2.3弱电工程'!$B$4:$J$195,9,0) -> 2.41 | K79: =VLOOKUP(B79,'[1]2.3弱电工程'!$B$4:$K$195,10,0) -> 0 | L79: =$L$4 -> 0.207 | M79: =F79*G79 -> 0
A80: 2 | B80: 投影幕布 | C80: 1.名称:投影幕布 2.规格:120寸4:3，材质；白玻纤；带遥控 | D80: 按设计图示数量计算 | E80: 套 | G80: =(H80+I80+J80+K80)*(1+L80) -> 1464.8152 | H80: =VLOOKUP(B80,'[1]2.3弱电工程'!$B$4:$H$195,7,0) -> 1020.31 | I80: =VLOOKUP(B80,'[1]2.3弱电工程'!$B$4:$I$195,8,0) -> 183.19 | J80: =VLOOKUP(B80,'[1]2.3弱电工程'!$B$4:$J$195,9,0) -> 7.69 | K80: =VLOOKUP(B80,'[1]2.3弱电工程'!$B$4:$K$195,10,0) -> 2.41 | L80: =$L$4 -> 0.207 | M80: =F80*G80 -> 0
A81: 3 | B81: 六类非屏蔽网线 | C81: 1.名称:六类非屏蔽网线 2.敷设方式:综合考虑 | D81: 按设计图示尺寸以长度计算 | E81: m | G81: =(H81+I81+J81+K81)*(1+L81) -> 5.05733 | H81: =VLOOKUP(B81,'[1]2.3弱电工程'!$B$4:$H$195,7,0) -> 1.57 | I81: =VLOOKUP(B81,'[1]2.3弱电工程'!$B$4:$I$195,8,0) -> 2.61 | J81: =VLOOKUP(B81,'[1]2.3弱电工程'!$B$4:$J$195,9,0) -> 0.01 | K81: =VLOOKUP(B81,'[1]2.3弱电工程'!$B$4:$K$195,10,0) -> 0 | L81: =$L$4 -> 0.207 | M81: =F81*G81 -> 0
A82: 4 | B82: HDIM高清视频线 | C82: 1.名称:HDIM高清视频线 2.敷设方式:综合考虑 | D82: 按设计图示尺寸以长度计算 | E82: m | G82: =(H82+I82+J82+K82)*(1+L82) -> 13.10802 | H82: =VLOOKUP(B82,'[1]2.3弱电工程'!$B$4:$H$195,7,0) -> 1.57 | I82: =VLOOKUP(B82,'[1]2.3弱电工程'!$B$4:$I$195,8,0) -> 9.28 | J82: =VLOOKUP(B82,'[1]2.3弱电工程'!$B$4:$J$195,9,0) -> 0.01 | K82: =VLOOKUP(B82,'[1]2.3弱电工程'!$B$4:$K$195,10,0) -> 0 | L82: =$L$4 -> 0.207 | M82: =F82*G82 -> 0
A83: 5 | B83: RVJF-2*2 | C83: 1.名称:RVJF-2*2 2.敷设方式:综合考虑 | D83: 按设计图示尺寸以长度计算 | E83: m | G83: =(H83+I83+J83+K83)*(1+L83) -> 6.38503 | H83: =VLOOKUP(B83,'[1]2.3弱电工程'!$B$4:$H$195,7,0) -> 2.07 | I83: =VLOOKUP(B83,'[1]2.3弱电工程'!$B$4:$I$195,8,0) -> 3.21 | J83: =VLOOKUP(B83,'[1]2.3弱电工程'!$B$4:$J$195,9,0) -> 0.01 | K83: =VLOOKUP(B83,'[1]2.3弱电工程'!$B$4:$K$195,10,0) -> 0 | L83: =$L$4 -> 0.207 | M83: =F83*G83 -> 0
A84: 六 | B84: 车辆道闸系统
A85: 1 | B85: 一体式车牌识别道闸 | C85: 1.名称:一体式车牌识别道闸 2.类别:一体式直杆闸机，包含快速道闸、智能抓拍机、补光灯、LCD屏、防砸雷达、语音播报及水泥基础等，参考海康威视：DS-TMC405-EHR(LCD)、DS-TMC405-EHL(LCD)，直杆的长度根据现场环境确定 | D85: 按设计图示数量计算 | E85: 台 | F85: 1 | G85: =(H85+I85+J85+K85)*(1+L85) -> 16480.161 | H85: =VLOOKUP(B85,'[1]2.3弱电工程'!$B$4:$H$195,7,0) -> 273 | I85: =VLOOKUP(B85,'[1]2.3弱电工程'!$B$4:$I$195,8,0) -> 13300.08 | J85: =VLOOKUP(B85,'[1]2.3弱电工程'!$B$4:$J$195,9,0) -> 1.72 | K85: =VLOOKUP(B85,'[1]2.3弱电工程'!$B$4:$K$195,10,0) -> 79.02 | L85: =$L$4 -> 0.207 | M85: =F85*G85 -> 16480.161
A86: 2 | B86: 分体式车牌识别道闸 | C86: 1.名称:分体式车牌识别道闸 2.类别:抓拍显示一体机（含摄像机、LED显示屏、补光灯、镜头、喇叭功放）、直杆闸机及水泥基础等。参考型号DS-TMC403-E(LCD)/3106、DS-TMG520-M(长度根据现场环境确定，含雷达) | D86: 按设计图示数量计算 | E86: 台 | F86: 1 | G86: =(H86+I86+J86+K86)*(1+L86) -> 10596.398 | H86: =VLOOKUP(B86,'[1]2.3弱电工程'!$B$4:$H$195,7,0) -> 82.4 | I86: =VLOOKUP(B86,'[1]2.3弱电工程'!$B$4:$I$195,8,0) -> 8500.69 | J86: =VLOOKUP(B86,'[1]2.3弱电工程'!$B$4:$J$195,9,0) -> 6.84 | K86: =VLOOKUP(B86,'[1]2.3弱电工程'!$B$4:$K$195,10,0) -> 189.19 | L86: =$L$4 -> 0.207 | M86: =F86*G86 -> 10596.398
A87: 3 | B87: 车牌识别道闸出入口控制终端 | C87: 1.名称:车牌识别道闸出入口控制终端 2.规格:参考海康威视：DS-TPE204-S(P)，含管理软件 | D87: 按设计图示数量计算 | E87: 套 | G87: =(H87+I87+J87+K87)*(1+L87) -> 4967.0705 | H87: =VLOOKUP(B87,'[1]2.3弱电工程'!$B$4:$H$195,7,0) -> 54.6 | I87: =VLOOKUP(B87,'[1]2.3弱电工程'!$B$4:$I$195,8,0) -> 4060.62 | J87: =VLOOKUP(B87,'[1]2.3弱电工程'!$B$4:$J$195,9,0) -> 0 | K87: =VLOOKUP(B87,'[1]2.3弱电工程'!$B$4:$K$195,10,0) -> 0 | L87: =$L$4 -> 0.207 | M87: =F87*G87 -> 0
A88: 七 | B88: 室外弱电系统
A89: 1 | B89: 6芯室外光缆 | C89: 1.名称:6芯室外光缆 2.规格:GYTA、单模、OS2 3.敷设方式:综合考虑 | D89: 按设计图示尺寸以长度计算 | E89: m | F89: 346.5 | G89: =(H89+I89+J89+K89)*(1+L89) -> 7.6041 | H89: =VLOOKUP(B89,'[1]2.3弱电工程'!$B$4:$H$195,7,0) -> 4.16 | I89: =VLOOKUP(B89,'[1]2.3弱电工程'!$B$4:$I$195,8,0) -> 2.14 | J89: =VLOOKUP(B89,'[1]2.3弱电工程'!$B$4:$J$195,9,0) -> 0 | K89: =VLOOKUP(B89,'[1]2.3弱电工程'!$B$4:$K$195,10,0) -> 0 | L89: =$L$4 -> 0.207 | M89: =F89*G89 -> 2634.8207
A90: 2 | B90: 光纤收发器 | C90: 1.名称:光纤收发器 | D90: 按设计图示数量计算 | E90: 台 | G90: =(H90+I90+J90+K90)*(1+L90) -> 293.45791 | H90: =VLOOKUP(B90,'[1]2.3弱电工程'!$B$4:$H$195,7,0) -> 81.9 | I90: =VLOOKUP(B90,'[1]2.3弱电工程'!$B$4:$I$195,8,0) -> 160.69 | J90: =VLOOKUP(B90,'[1]2.3弱电工程'!$B$4:$J$195,9,0) -> 0 | K90: =VLOOKUP(B90,'[1]2.3弱电工程'!$B$4:$K$195,10,0) -> 0.54 | L90: =$L$4 -> 0.207 | M90: =F90*G90 -> 0
A91: 3 | B91: 光缆终端盒 | C91: 1.光缆芯数:6芯 | D91: 按设计图示数量计算 | E91: 个 | G91: =(H91+I91+J91+K91)*(1+L91) -> 147.04881 | H91: =VLOOKUP(B91,'[1]2.3弱电工程'!$B$4:$H$195,7,0) -> 79.63 | I91: =VLOOKUP(B91,'[1]2.3弱电工程'!$B$4:$I$195,8,0) -> 40.11 | J91: =VLOOKUP(B91,'[1]2.3弱电工程'!$B$4:$J$195,9,0) -> 0 | K91: =VLOOKUP(B91,'[1]2.3弱电工程'!$B$4:$K$195,10,0) -> 2.09 | L91: =$L$4 -> 0.207 | M91: =F91*G91 -> 0
A92: 4 | B92: 配管PE50 | C92: 1.名称:配管PE50 2.材质:PE 3.规格:DN40mm 4.配置形式:埋地敷设 5.接地要求:按规范要求 | D92: 按设计图示尺寸以质量计算 | E92: m | G92: =(H92+I92+J92+K92)*(1+L92) -> 25.33493 | H92: =VLOOKUP(B92,'[1]2.3弱电工程'!$B$4:$H$195,7,0) -> 13.92 | I92: =VLOOKUP(B92,'[1]2.3弱电工程'!$B$4:$I$195,8,0) -> 7.05 | J92: =VLOOKUP(B92,'[1]2.3弱电工程'!$B$4:$J$195,9,0) -> 0.02 | K92: =VLOOKUP(B92,'[1]2.3弱电工程'!$B$4:$K$195,10,0) -> 0 | L92: =$L$4 -> 0.207 | M92: =F92*G92 -> 0
A93: 5 | B93: 配管七孔梅花管 | C93: 1.名称:配管七孔梅花管 2.材质:PVC 3.规格:PVC32*7 4.配置形式:埋地敷设 5.接地要求:按规范要求 | D93: 按设计图示尺寸以质量计算 | E93: m | G93: =(H93+I93+J93+K93)*(1+L93) -> 39.67409 | H93: =VLOOKUP(B93,'[1]2.3弱电工程'!$B$4:$H$195,7,0) -> 18.84 | I93: =VLOOKUP(B93,'[1]2.3弱电工程'!$B$4:$I$195,8,0) -> 14.01 | J93: =VLOOKUP(B93,'[1]2.3弱电工程'!$B$4:$J$195,9,0) -> 0.02 | K93: =VLOOKUP(B93,'[1]2.3弱电工程'!$B$4:$K$195,10,0) -> 0 | L93: =$L$4 -> 0.207 | M93: =F93*G93 -> 0
A94: 6 | B94: 挖沟槽土方 | C94: 1.挖土深度:综合考虑 2.土壤类别:综合考虑 3.弃土运距:综合考虑 | D94: 按设计图示尺寸以基础垫层底面积乘以挖土深度计算 | E94: m3 | G94: =(H94+I94+J94+K94)*(1+L94) -> 87.94202 | H94: =VLOOKUP(B94,'[1]2.3弱电工程'!$B$4:$H$195,7,0) -> 72.86 | I94: =VLOOKUP(B94,'[1]2.3弱电工程'!$B$4:$I$195,8,0) -> 0 | J94: =VLOOKUP(B94,'[1]2.3弱电工程'!$B$4:$J$195,9,0) -> 0 | K94: =VLOOKUP(B94,'[1]2.3弱电工程'!$B$4:$K$195,10,0) -> 0 | L94: =$L$4 -> 0.207 | M94: =F94*G94 -> 0
A95: 7 | B95: 回填砂 | C95: 1.密实度要求:满足规范要求 2.填方材料品种:回填砂 | D95: 基础回填：挖方清单项目工程量减去自然地坪以下埋设的基础体积（包括基础垫层及其他构筑物） | E95: m3 | G95: =(H95+I95+J95+K95)*(1+L95) -> 295.48567 | H95: =VLOOKUP(B95,'[1]2.3弱电工程'!$B$4:$H$195,7,0) -> 53.6 | I95: =VLOOKUP(B95,'[1]2.3弱电工程'!$B$4:$I$195,8,0) -> 0 | J95: =VLOOKUP(B95,'[1]2.3弱电工程'!$B$4:$J$195,9,0) -> 190.96 | K95: =VLOOKUP(B95,'[1]2.3弱电工程'!$B$4:$K$195,10,0) -> 0.25 | L95: =$L$4 -> 0.207 | M95: =F95*G95 -> 0
A96: 8 | B96: 原土回填 | C96: 1.密实度要求:满足规范要求 2.填方材料品种:原土回填 | D96: 基础回填：挖方清单项目工程量减去自然地坪以下埋设的基础体积（包括基础垫层及其他构筑物） | E96: m3 | G96: =(H96+I96+J96+K96)*(1+L96) -> 48.0386 | H96: =VLOOKUP(B96,'[1]2.3弱电工程'!$B$4:$H$195,7,0) -> 39.8 | I96: =VLOOKUP(B96,'[1]2.3弱电工程'!$B$4:$I$195,8,0) -> 0 | J96: =VLOOKUP(B96,'[1]2.3弱电工程'!$B$4:$J$195,9,0) -> 0 | K96: =VLOOKUP(B96,'[1]2.3弱电工程'!$B$4:$K$195,10,0) -> 0 | L96: =$L$4 -> 0.207 | M96: =F96*G96 -> 0
A97: 9 | B97: 余方弃置 | C97: 1.运距:综合考虑 | D97: 按挖方清单项目工程量减利用回填方体积(正数)计算 | E97: m3 | G97: =(H97+I97+J97+K97)*(1+L97) -> 16.97042 | H97: =VLOOKUP(B97,'[1]2.3弱电工程'!$B$4:$H$195,7,0) -> 0.76 | I97: =VLOOKUP(B97,'[1]2.3弱电工程'!$B$4:$I$195,8,0) -> 0 | J97: =VLOOKUP(B97,'[1]2.3弱电工程'!$B$4:$J$195,9,0) -> 0 | K97: =VLOOKUP(B97,'[1]2.3弱电工程'!$B$4:$K$195,10,0) -> 13.3 | L97: =$L$4 -> 0.207 | M97: =F97*G97 -> 0
A98: 合计 | M98: =SUM(M3:M97) -> 334909.49

Sheet 2.4给排水工程
A1: 长城智选中心店装修项目装饰工程
A2: 序号 | B2: 分部分项名称 | C2: 项目特征 | D2: 计量规则 | E2: 单位 | F2: 工程量 | G2: 综合单价 | H2: 人工 | I2: 主材 | J2: 辅材 | K2: 机械 | L2: 其他综合费率 | M2: 合计 | N2: 备注
A3: 1 | B3: 钢塑复合管DN150 | C3: 1.安装部位:室内 2.介质:水 3.连接形式:按设计及规范要求 4.压力试验及吹、洗设计要求:按设计及规范要求 5.管道穿内墙、楼板、吊顶开洞及封堵套管:按设计及规范要求 6.管道支架及抗震支架：按设计及规范要求 7.其他:按设计及规范要求 | D3: 按设计图示管道中心线以长度计算 | E3: m | G3: =(H3+I3+J3+K3)*(1+L3) -> 251.27326 | H3: =VLOOKUP(B3,'[1]2.4给排水工程'!$B$3:$H$113,7,0) -> 89.38 | I3: =VLOOKUP(B3,'[1]2.4给排水工程'!$B$3:$I$113,8,0) -> 93 | J3: =VLOOKUP(B3,'[1]2.4给排水工程'!$B$3:$J$113,9,0) -> 0.99 | K3: =VLOOKUP(B3,'[1]2.4给排水工程'!$B$3:$K$113,10,0) -> 24.81 | L3: ='2.1装饰工程'!$L$4 -> 0.207 | M3: =F3*G3 -> 0
A4: 2 | B4: 钢塑复合管DN100 | C4: 1.安装部位:室内 2.介质:水 3.连接形式:按设计及规范要求 4.压力试验及吹、洗设计要求:按设计及规范要求 5.管道穿内墙、楼板、吊顶开洞及封堵套管:按设计及规范要求 6.管道支架及抗震支架：按设计及规范要求 7.其他:按设计及规范要求 | D4: 按设计图示管道中心线以长度计算 | E4: m | G4: =(H4+I4+J4+K4)*(1+L4) -> 169.68006 | H4: =VLOOKUP(B4,'[1]2.4给排水工程'!$B$3:$H$113,7,0) -> 82.38 | I4: =VLOOKUP(B4,'[1]2.4给排水工程'!$B$3:$I$113,8,0) -> 40.3 | J4: =VLOOKUP(B4,'[1]2.4给排水工程'!$B$3:$J$113,9,0) -> 0.97 | K4: =VLOOKUP(B4,'[1]2.4给排水工程'!$B$3:$K$113,10,0) -> 16.93 | L4: =$L$3 -> 0.207 | M4: =F4*G4 -> 0
A5: 3 | B5: 钢塑复合管DN80 | C5: 1.安装部位:室内 2.介质:水 3.连接形式:按设计及规范要求 4.压力试验及吹、洗设计要求:按设计及规范要求 5.管道穿内墙、楼板、吊顶开洞及封堵套管:按设计及规范要求 6.管道支架及抗震支架：按设计及规范要求 7.其他:按设计及规范要求 | D5: 按设计图示管道中心线以长度计算 | E5: m | G5: =(H5+I5+J5+K5)*(1+L5) -> 137.61007 | H5: =VLOOKUP(B5,'[1]2.4给排水工程'!$B$3:$H$113,7,0) -> 72.69 | I5: =VLOOKUP(B5,'[1]2.4给排水工程'!$B$3:$I$113,8,0) -> 37.06 | J5: =VLOOKUP(B5,'[1]2.4给排水工程'!$B$3:$J$113,9,0) -> 0.9 | K5: =VLOOKUP(B5,'[1]2.4给排水工程'!$B$3:$K$113,10,0) -> 3.36 | L5: =$L$3 -> 0.207 | M5: =F5*G5 -> 0
A6: 4 | B6: 钢塑复合管DN65 | C6: 1.安装部位:室内 2.介质:水 3.连接形式:按设计及规范要求 4.压力试验及吹、洗设计要求:按设计及规范要求 5.管道穿内墙、楼板、吊顶开洞及封堵套管:按设计及规范要求 6.管道支架及抗震支架：按设计及规范要求 7.其他:按设计及规范要求 | D6: 按设计图示管道中心线以长度计算 | E6: m | G6: =(H6+I6+J6+K6)*(1+L6) -> 115.23229 | H6: =VLOOKUP(B6,'[1]2.4给排水工程'!$B$3:$H$113,7,0) -> 66.88 | I6: =VLOOKUP(B6,'[1]2.4给排水工程'!$B$3:$I$113,8,0) -> 25.1 | J6: =VLOOKUP(B6,'[1]2.4给排水工程'!$B$3:$J$113,9,0) -> 0.83 | K6: =VLOOKUP(B6,'[1]2.4给排水工程'!$B$3:$K$113,10,0) -> 2.66 | L6: =$L$3 -> 0.207 | M6: =F6*G6 -> 0
A7: 5 | B7: 钢塑复合管DN50 | C7: 1.安装部位:室内 2.介质:水 3.连接形式:按设计及规范要求 4.压力试验及吹、洗设计要求:按设计及规范要求 5.管道穿内墙、楼板、吊顶开洞及封堵套管:按设计及规范要求 6.管道支架及抗震支架：按设计及规范要求 7.其他:按设计及规范要求 | D7: 按设计图示管道中心线以长度计算 | E7: m | G7: =(H7+I7+J7+K7)*(1+L7) -> 96.01685 | H7: =VLOOKUP(B7,'[1]2.4给排水工程'!$B$3:$H$113,7,0) -> 64.31 | I7: =VLOOKUP(B7,'[1]2.4给排水工程'!$B$3:$I$113,8,0) -> 12.19 | J7: =VLOOKUP(B7,'[1]2.4给排水工程'!$B$3:$J$113,9,0) -> 0.81 | K7: =VLOOKUP(B7,'[1]2.4给排水工程'!$B$3:$K$113,10,0) -> 2.24 | L7: =$L$3 -> 0.207 | M7: =F7*G7 -> 0
A8: 6 | B8: 钢塑复合管DN40 | C8: 1.安装部位:室内 2.介质:水 3.连接形式:按设计及规范要求 4.压力试验及吹、洗设计要求:按设计及规范要求 5.管道穿内墙、楼板、吊顶开洞及封堵套管:按设计及规范要求 6.管道支架及抗震支架：按设计及规范要求 7.其他:按设计及规范要求 | D8: 按设计图示管道中心线以长度计算 | E8: m | G8: =(H8+I8+J8+K8)*(1+L8) -> 80.57932 | H8: =VLOOKUP(B8,'[1]2.4给排水工程'!$B$3:$H$113,7,0) -> 53.19 | I8: =VLOOKUP(B8,'[1]2.4给排水工程'!$B$3:$I$113,8,0) -> 11.1 | J8: =VLOOKUP(B8,'[1]2.4给排水工程'!$B$3:$J$113,9,0) -> 0.77 | K8: =VLOOKUP(B8,'[1]2.4给排水工程'!$B$3:$K$113,10,0) -> 1.7 | L8: =$L$3 -> 0.207 | M8: =F8*G8 -> 0
A9: 7 | B9: 钢塑复合管DN32 | C9: 1.安装部位:室内 2.介质:水 3.连接形式:按设计及规范要求 4.压力试验及吹、洗设计要求:按设计及规范要求 5.管道穿内墙、楼板、吊顶开洞及封堵套管:按设计及规范要求 6.管道支架及抗震支架：按设计及规范要求 7.其他:按设计及规范要求 | D9: 按设计图示管道中心线以长度计算 | E9: m | G9: =(H9+I9+J9+K9)*(1+L9) -> 72.77003 | H9: =VLOOKUP(B9,'[1]2.4给排水工程'!$B$3:$H$113,7,0) -> 52.6 | I9: =VLOOKUP(B9,'[1]2.4给排水工程'!$B$3:$I$113,8,0) -> 5.5 | J9: =VLOOKUP(B9,'[1]2.4给排水工程'!$B$3:$J$113,9,0) -> 0.75 | K9: =VLOOKUP(B9,'[1]2.4给排水工程'!$B$3:$K$113,10,0) -> 1.44 | L9: =$L$3 -> 0.207 | M9: =F9*G9 -> 0
A10: 8 | B10: 钢塑复合管DN25 | C10: 1.安装部位:室内 2.介质:水 3.连接形式:按设计及规范要求 4.压力试验及吹、洗设计要求:按设计及规范要求 5.管道穿内墙、楼板、吊顶开洞及封堵套管:按设计及规范要求 6.管道支架及抗震支架：按设计及规范要求 7.其他:按设计及规范要求 | D10: 按设计图示管道中心线以长度计算 | E10: m | G10: =(H10+I10+J10+K10)*(1+L10) -> 61.72598 | H10: =VLOOKUP(B10,'[1]2.4给排水工程'!$B$3:$H$113,7,0) -> 46.2 | I10: =VLOOKUP(B10,'[1]2.4给排水工程'!$B$3:$I$113,8,0) -> 3.2 | J10: =VLOOKUP(B10,'[1]2.4给排水工程'!$B$3:$J$113,9,0) -> 0.65 | K10: =VLOOKUP(B10,'[1]2.4给排水工程'!$B$3:$K$113,10,0) -> 1.09 | L10: =$L$3 -> 0.207 | M10: =F10*G10 -> 0
A11: 9 | B11: 钢塑复合管DN20 | C11: 1.安装部位:室内 2.介质:水 3.连接形式:按设计及规范要求 4.压力试验及吹、洗设计要求:按设计及规范要求 5.管道穿内墙、楼板、吊顶开洞及封堵套管:按设计及规范要求 6.管道支架及抗震支架：按设计及规范要求 7.其他:按设计及规范要求 | D11: 按设计图示管道中心线以长度计算 | E11: m | G11: =(H11+I11+J11+K11)*(1+L11) -> 56.01687 | H11: =VLOOKUP(B11,'[1]2.4给排水工程'!$B$3:$H$113,7,0) -> 42.1 | I11: =VLOOKUP(B11,'[1]2.4给排水工程'!$B$3:$I$113,8,0) -> 3.2 | J11: =VLOOKUP(B11,'[1]2.4给排水工程'!$B$3:$J$113,9,0) -> 0.5 | K11: =VLOOKUP(B11,'[1]2.4给排水工程'!$B$3:$K$113,10,0) -> 0.61 | L11: =$L$3 -> 0.207 | M11: =F11*G11 -> 0
A12: 10 | B12: 球磨铸铁管DN150 | C12: 1.安装部位:室内 2.介质:水 3.连接形式:按设计及规范要求 4.压力试验及吹、洗设计要求:按设计及规范要求 5.管道穿内墙、楼板、吊顶开洞及封堵套管:按设计及规范要求 6.管道支架及抗震支架：按设计及规范要求 7.其他:按设计及规范要求 | D12: 按设计图示管道中心线以长度计算 | E12: m | G12: =(H12+I12+J12+K12)*(1+L12) -> 258.32214 | H12: =VLOOKUP(B12,'[1]2.4给排水工程'!$B$3:$H$113,7,0) -> 54.87 | I12: =VLOOKUP(B12,'[1]2.4给排水工程'!$B$3:$I$113,8,0) -> 132.1 | J12: =VLOOKUP(B12,'[1]2.4给排水工程'!$B$3:$J$113,9,0) -> 2.64 | K12: =VLOOKUP(B12,'[1]2.4给排水工程'!$B$3:$K$113,10,0) -> 24.41 | L12: =$L$3 -> 0.207 | M12: =F12*G12 -> 0
A13: 11 | B13: 球磨铸铁管DN100 | C13: 1.安装部位:室内 2.介质:水 3.连接形式:按设计及规范要求 4.压力试验及吹、洗设计要求:按设计及规范要求 5.管道穿内墙、楼板、吊顶开洞及封堵套管:按设计及规范要求 6.管道支架及抗震支架：按设计及规范要求 7.其他:按设计及规范要求 | D13: 按设计图示管道中心线以长度计算 | E13: m | G13: =(H13+I13+J13+K13)*(1+L13) -> 209.14896 | H13: =VLOOKUP(B13,'[1]2.4给排水工程'!$B$3:$H$113,7,0) -> 45.82 | I13: =VLOOKUP(B13,'[1]2.4给排水工程'!$B$3:$I$113,8,0) -> 107.5 | J13: =VLOOKUP(B13,'[1]2.4给排水工程'!$B$3:$J$113,9,0) -> 1.84 | K13: =VLOOKUP(B13,'[1]2.4给排水工程'!$B$3:$K$113,10,0) -> 18.12 | L13: =$L$3 -> 0.207 | M13: =F13*G13 -> 0
A14: 12 | B14: 球磨铸铁管DN80 | C14: 1.安装部位:室内 2.介质:水 3.连接形式:按设计及规范要求 4.压力试验及吹、洗设计要求:按设计及规范要求 5.管道穿内墙、楼板、吊顶开洞及封堵套管:按设计及规范要求 6.管道支架及抗震支架：按设计及规范要求 7.其他:按设计及规范要求 | D14: 按设计图示管道中心线以长度计算 | E14: m | G14: =(H14+I14+J14+K14)*(1+L14) -> 180.15682 | H14: =VLOOKUP(B14,'[1]2.4给排水工程'!$B$3:$H$113,7,0) -> 29.83 | I14: =VLOOKUP(B14,'[1]2.4给排水工程'!$B$3:$I$113,8,0) -> 115.26 | J14: =VLOOKUP(B14,'[1]2.4给排水工程'!$B$3:$J$113,9,0) -> 1.26 | K14: =VLOOKUP(B14,'[1]2.4给排水工程'!$B$3:$K$113,10,0) -> 2.91 | L14: =$L$3 -> 0.207 | M14: =F14*G14 -> 0
A15: 13 | B15: 球磨铸铁管DN65 | C15: 1.安装部位:室内 2.介质:水 3.连接形式:按设计及规范要求 4.压力试验及吹、洗设计要求:按设计及规范要求 5.管道穿内墙、楼板、吊顶开洞及封堵套管:按设计及规范要求 6.管道支架及抗震支架：按设计及规范要求 7.其他:按设计及规范要求 | D15: 按设计图示管道中心线以长度计算 | E15: m | G15: =(H15+I15+J15+K15)*(1+L15) -> 154.55635 | H15: =VLOOKUP(B15,'[1]2.4给排水工程'!$B$3:$H$113,7,0) -> 29.83 | I15: =VLOOKUP(B15,'[1]2.4给排水工程'!$B$3:$I$113,8,0) -> 94.05 | J15: =VLOOKUP(B15,'[1]2.4给排水工程'!$B$3:$J$113,9,0) -> 1.26 | K15: =VLOOKUP(B15,'[1]2.4给排水工程'!$B$3:$K$113,10,0) -> 2.91 | L15: =$L$3 -> 0.207 | M15: =F15*G15 -> 0
... A20: 18 | B20: PPR给水管De63 | C20: 1.安装部位:室内 2.介质:水 3.连接形式:热熔连接 4.阻火圈设计要求:设计及规范要求 5.压力试验及吹、洗设计要求:按规范要求 6.管道穿内墙、楼板、吊顶开洞及封堵套管:按设计及规范要求 7.管道支架及抗震支架：按设计及规范要求 8.其他:按设计及规范要求 | D20: 按设计图示管道中心线以长度计算 | E20: m | G20: =(H20+I20+J20+K20)*(1+L20) -> 78.15325 | H20: =VLOOKUP(B20,'[1]2.4给排水工程'!$B$3:$H$113,7,0) -> 23.68 | I20: =VLOOKUP(B20,'[1]2.4给排水工程'!$B$3:$I$113,8,0) -> 40.6 | J20: =VLOOKUP(B20,'[1]2.4给排水工程'!$B$3:$J$113,9,0) -> 0.42 | K20: =VLOOKUP(B20,'[1]2.4给排水工程'!$B$3:$K$113,10,0) -> 0.05 | L20: =$L$3 -> 0.207 | M20: =F20*G20 -> 0
A21: 19 | B21: PPR给水管De50 | C21: 1.安装部位:室内 2.介质:水 3.连接形式:热熔连接 4.阻火圈设计要求:设计及规范要求 5.压力试验及吹、洗设计要求:按规范要求 6.管道穿内墙、楼板、吊顶开洞及封堵套管:按设计及规范要求 7.管道支架及抗震支架：按设计及规范要求 8.其他:按设计及规范要求 | D21: 按设计图示管道中心线以长度计算 | E21: m | F21: 18.54 | G21: =(H21+I21+J21+K21)*(1+L21) -> 63.17438 | H21: =VLOOKUP(B21,'[1]2.4给排水工程'!$B$3:$H$113,7,0) -> 23.68 | I21: =VLOOKUP(B21,'[1]2.4给排水工程'!$B$3:$I$113,8,0) -> 28.24 | J21: =VLOOKUP(B21,'[1]2.4给排水工程'!$B$3:$J$113,9,0) -> 0.37 | K21: =VLOOKUP(B21,'[1]2.4给排水工程'!$B$3:$K$113,10,0) -> 0.05 | L21: =$L$3 -> 0.207 | M21: =F21*G21 -> 1171.253
A22: 20 | B22: PPR给水管De40 | C22: 1.安装部位:室内 2.介质:水 3.连接形式:热熔连接 4.阻火圈设计要求:设计及规范要求 5.压力试验及吹、洗设计要求:按规范要求 6.管道穿内墙、楼板、吊顶开洞及封堵套管:按设计及规范要求 7.管道支架及抗震支架：按设计及规范要求 8.其他:按设计及规范要求 | D22: 按设计图示管道中心线以长度计算 | E22: m | G22: =(H22+I22+J22+K22)*(1+L22) -> 50.76642 | H22: =VLOOKUP(B22,'[1]2.4给排水工程'!$B$3:$H$113,7,0) -> 23.68 | I22: =VLOOKUP(B22,'[1]2.4给排水工程'!$B$3:$I$113,8,0) -> 18 | J22: =VLOOKUP(B22,'[1]2.4给排水工程'!$B$3:$J$113,9,0) -> 0.35 | K22: =VLOOKUP(B22,'[1]2.4给排水工程'!$B$3:$K$113,10,0) -> 0.03 | L22: =$L$3 -> 0.207 | M22: =F22*G22 -> 0
A23: 21 | B23: PPR给水管De32 | C23: 1.安装部位:室内 2.介质:水 3.连接形式:热熔连接 4.阻火圈设计要求:设计及规范要求 5.压力试验及吹、洗设计要求:按规范要求 6.管道穿内墙、楼板、吊顶开洞及封堵套管:按设计及规范要求 7.管道支架及抗震支架：按设计及规范要求 8.其他:按设计及规范要求 | D23: 按设计图示管道中心线以长度计算 | E23: m | F23: 21.69 | G23: =(H23+I23+J23+K23)*(1+L23) -> 41.6415 | H23: =VLOOKUP(B23,'[1]2.4给排水工程'!$B$3:$H$113,7,0) -> 23.68 | I23: =VLOOKUP(B23,'[1]2.4给排水工程'!$B$3:$I$113,8,0) -> 10.5 | J23: =VLOOKUP(B23,'[1]2.4给排水工程'!$B$3:$J$113,9,0) -> 0.29 | K23: =VLOOKUP(B23,'[1]2.4给排水工程'!$B$3:$K$113,10,0) -> 0.03 | L23: =$L$3 -> 0.207 | M23: =F23*G23 -> 903.20413
A24: 22 | B24: PPR给水管De25 | C24: 1.安装部位:室内 2.介质:水 3.连接形式:热熔连接 4.阻火圈设计要求:设计及规范要求 5.压力试验及吹、洗设计要求:按规范要求 6.管道穿内墙、楼板、吊顶开洞及封堵套管:按设计及规范要求 7.管道支架及抗震支架：按设计及规范要求 8.其他:按设计及规范要求 | D24: 按设计图示管道中心线以长度计算 | E24: m | F24: 13.25 | G24: =(H24+I24+J24+K24)*(1+L24) -> 33.27699 | H24: =VLOOKUP(B24,'[1]2.4给排水工程'!$B$3:$H$113,7,0) -> 23.68 | I24: =VLOOKUP(B24,'[1]2.4给排水工程'!$B$3:$I$113,8,0) -> 3.6 | J24: =VLOOKUP(B24,'[1]2.4给排水工程'!$B$3:$J$113,9,0) -> 0.26 | K24: =VLOOKUP(B24,'[1]2.4给排水工程'!$B$3:$K$113,10,0) -> 0.03 | L24: =$L$3 -> 0.207 | M24: =F24*G24 -> 440.92012
A25: 23 | B25: PPR给水管De20 | C25: 1.安装部位:室内 2.介质:水 3.连接形式:热熔连接 4.阻火圈设计要求:设计及规范要求 5.压力试验及吹、洗设计要求:按规范要求 6.管道穿内墙、楼板、吊顶开洞及封堵套管:按设计及规范要求 7.管道支架及抗震支架：按设计及规范要求 8.其他:按设计及规范要求 | D25: 按设计图示管道中心线以长度计算 | E25: m | F25: 9.64 | G25: =(H25+I25+J25+K25)*(1+L25) -> 27.08508 | H25: =VLOOKUP(B25,'[1]2.4给排水工程'!$B$3:$H$113,7,0) -> 20.68 | I25: =VLOOKUP(B25,'[1]2.4给排水工程'!$B$3:$I$113,8,0) -> 1.49 | J25: =VLOOKUP(B25,'[1]2.4给排水工程'!$B$3:$J$113,9,0) -> 0.24 | K25: =VLOOKUP(B25,'[1]2.4给排水工程'!$B$3:$K$113,10,0) -> 0.03 | L25: =$L$3 -> 0.207 | M25: =F25*G25 -> 261.10017
A26: 24 | B26: PPR热给水管De90 | C26: 1.安装部位:室内 2.介质:水 3.连接形式:热熔连接 4.阻火圈设计要求:设计及规范要求 5.压力试验及吹、洗设计要求:按规范要求 6.管道穿内墙、楼板、吊顶开洞及封堵套管:按设计及规范要求 7.管道支架及抗震支架：按设计及规范要求 8.其他:按设计及规范要求 | D26: 按设计图示管道中心线以长度计算 | E26: m | G26: =(H26+I26+J26+K26)*(1+L26) -> 125.72112 | H26: =VLOOKUP(B26,'[1]2.4给排水工程'!$B$3:$H$113,7,0) -> 23.68 | I26: =VLOOKUP(B26,'[1]2.4给排水工程'!$B$3:$I$113,8,0) -> 79.88 | J26: =VLOOKUP(B26,'[1]2.4给排水工程'!$B$3:$J$113,9,0) -> 0.55 | K26: =VLOOKUP(B26,'[1]2.4给排水工程'!$B$3:$K$113,10,0) -> 0.05 | L26: =$L$3 -> 0.207 | M26: =F26*G26 -> 0
A27: 25 | B27: PPR热给水管De75 | C27: 1.安装部位:室内 2.介质:水 3.连接形式:热熔连接 4.阻火圈设计要求:设计及规范要求 5.压力试验及吹、洗设计要求:按规范要求 6.管道穿内墙、楼板、吊顶开洞及封堵套管:按设计及规范要求 7.管道支架及抗震支架：按设计及规范要求 8.其他:按设计及规范要求 | D27: 按设计图示管道中心线以长度计算 | E27: m | G27: =(H27+I27+J27+K27)*(1+L27) -> 104.13996 | H27: =VLOOKUP(B27,'[1]2.4给排水工程'!$B$3:$H$113,7,0) -> 23.68 | I27: =VLOOKUP(B27,'[1]2.4给排水工程'!$B$3:$I$113,8,0) -> 62.07 | J27: =VLOOKUP(B27,'[1]2.4给排水工程'!$B$3:$J$113,9,0) -> 0.48 | K27: =VLOOKUP(B27,'[1]2.4给排水工程'!$B$3:$K$113,10,0) -> 0.05 | L27: =$L$3 -> 0.207 | M27: =F27*G27 -> 0
A28: 26 | B28: PPR热给水管De63 | C28: 1.安装部位:室内 2.介质:水 3.连接形式:热熔连接 4.阻火圈设计要求:设计及规范要求 5.压力试验及吹、洗设计要求:按规范要求 6.管道穿内墙、楼板、吊顶开洞及封堵套管:按设计及规范要求 7.管道支架及抗震支架：按设计及规范要求 8.其他:按设计及规范要求 | D28: 按设计图示管道中心线以长度计算 | E28: m | G28: =(H28+I28+J28+K28)*(1+L28) -> 85.99875 | H28: =VLOOKUP(B28,'[1]2.4给排水工程'!$B$3:$H$113,7,0) -> 23.68 | I28: =VLOOKUP(B28,'[1]2.4给排水工程'!$B$3:$I$113,8,0) -> 47.1 | J28: =VLOOKUP(B28,'[1]2.4给排水工程'!$B$3:$J$113,9,0) -> 0.42 | K28: =VLOOKUP(B28,'[1]2.4给排水工程'!$B$3:$K$113,10,0) -> 0.05 | L28: =$L$3 -> 0.207 | M28: =F28*G28 -> 0
A29: 27 | B29: PPR热给水管De50 | C29: 1.安装部位:室内 2.介质:水 3.连接形式:热熔连接 4.阻火圈设计要求:设计及规范要求 5.压力试验及吹、洗设计要求:按规范要求 6.管道穿内墙、楼板、吊顶开洞及封堵套管:按设计及规范要求 7.管道支架及抗震支架：按设计及规范要求 8.其他:按设计及规范要求 | D29: 按设计图示管道中心线以长度计算 | E29: m | G29: =(H29+I29+J29+K29)*(1+L29) -> 66.30051 | H29: =VLOOKUP(B29,'[1]2.4给排水工程'!$B$3:$H$113,7,0) -> 23.68 | I29: =VLOOKUP(B29,'[1]2.4给排水工程'!$B$3:$I$113,8,0) -> 30.83 | J29: =VLOOKUP(B29,'[1]2.4给排水工程'!$B$3:$J$113,9,0) -> 0.37 | K29: =VLOOKUP(B29,'[1]2.4给排水工程'!$B$3:$K$113,10,0) -> 0.05 | L29: =$L$3 -> 0.207 | M29: =F29*G29 -> 0
A30: 28 | B30: PPR热给水管De40 | C30: 1.安装部位:室内 2.介质:水 3.连接形式:热熔连接 4.阻火圈设计要求:设计及规范要求 5.压力试验及吹、洗设计要求:按规范要求 6.管道穿内墙、楼板、吊顶开洞及封堵套管:按设计及规范要求 7.管道支架及抗震支架：按设计及规范要求 8.其他:按设计及规范要求 | D30: 按设计图示管道中心线以长度计算 | E30: m | G30: =(H30+I30+J30+K30)*(1+L30) -> 53.32526 | H30: =VLOOKUP(B30,'[1]2.4给排水工程'!$B$3:$H$113,7,0) -> 23.68 | I30: =VLOOKUP(B30,'[1]2.4给排水工程'!$B$3:$I$113,8,0) -> 20.12 | J30: =VLOOKUP(B30,'[1]2.4给排水工程'!$B$3:$J$113,9,0) -> 0.35 | K30: =VLOOKUP(B30,'[1]2.4给排水工程'!$B$3:$K$113,10,0) -> 0.03 | L30: =$L$3 -> 0.207 | M30: =F30*G30 -> 0
A31: 29 | B31: PPR热给水管De32 | C31: 1.安装部位:室内 2.介质:水 3.连接形式:热熔连接 4.阻火圈设计要求:设计及规范要求 5.压力试验及吹、洗设计要求:按规范要求 6.管道穿内墙、楼板、吊顶开洞及封堵套管:按设计及规范要求 7.管道支架及抗震支架：按设计及规范要求 8.其他:按设计及规范要求 | D31: 按设计图示管道中心线以长度计算 | E31: m | G31: =(H31+I31+J31+K31)*(1+L31) -> 42.95713 | H31: =VLOOKUP(B31,'[1]2.4给排水工程'!$B$3:$H$113,7,0) -> 23.68 | I31: =VLOOKUP(B31,'[1]2.4给排水工程'!$B$3:$I$113,8,0) -> 11.59 | J31: =VLOOKUP(B31,'[1]2.4给排水工程'!$B$3:$J$113,9,0) -> 0.29 | K31: =VLOOKUP(B31,'[1]2.4给排水工程'!$B$3:$K$113,10,0) -> 0.03 | L31: =$L$3 -> 0.207 | M31: =F31*G31 -> 0
A32: 30 | B32: PPR热给水管De20 | C32: 1.安装部位:室内 2.介质:水 3.连接形式:热熔连接 4.阻火圈设计要求:设计及规范要求 5.压力试验及吹、洗设计要求:按规范要求 6.管道穿内墙、楼板、吊顶开洞及封堵套管:按设计及规范要求 7.管道支架及抗震支架：按设计及规范要求 8.其他:按设计及规范要求 | D32: 按设计图示管道中心线以长度计算 | E32: m | F32: 20 | G32: =(H32+I32+J32+K32)*(1+L32) -> 28.78695 | H32: =VLOOKUP(B32,'[1]2.4给排水工程'!$B$3:$H$113,7,0) -> 22.09 | I32: =VLOOKUP(B32,'[1]2.4给排水工程'!$B$3:$I$113,8,0) -> 1.49 | J32: =VLOOKUP(B32,'[1]2.4给排水工程'!$B$3:$J$113,9,0) -> 0.24 | K32: =VLOOKUP(B32,'[1]2.4给排水工程'!$B$3:$K$113,10,0) -> 0.03 | L32: =$L$3 -> 0.207 | M32: =F32*G32 -> 575.739
A33: 31 | B33: PVC排水管De200 | C33: 1.安装部位:室内 2.介质:污水 3.连接形式:承插粘结 4.阻火圈设计要求:按设计及规范要求 5.管道穿内墙、楼板、吊顶开洞及封堵套管:按设计及规范要求 6.管道支架及抗震支架：按设计及规范要求 7.其他:按设计及规范要求 | D33: 按设计图示管道中心线以长度计算 | E33: m | G33: =(H33+I33+J33+K33)*(1+L33) -> 130.73017 | H33: =VLOOKUP(B33,'[1]2.4给排水工程'!$B$3:$H$113,7,0) -> 72.97 | I33: =VLOOKUP(B33,'[1]2.4给排水工程'!$B$3:$I$113,8,0) -> 29 | J33: =VLOOKUP(B33,'[1]2.4给排水工程'!$B$3:$J$113,9,0) -> 0.82 | K33: =VLOOKUP(B33,'[1]2.4给排水工程'!$B$3:$K$113,10,0) -> 5.52 | L33: =$L$3 -> 0.207 | M33: =F33*G33 -> 0
A34: 32 | B34: PVC排水管De160 | C34: 1.安装部位:室内 2.介质:污水 3.连接形式:承插粘结 4.阻火圈设计要求:按设计及规范要求 5.管道穿内墙、楼板、吊顶开洞及封堵套管:按设计及规范要求 6.管道支架及抗震支架：按设计及规范要求 7.其他:按设计及规范要求 | D34: 按设计图示管道中心线以长度计算 | E34: m | F34: 10 | G34: =(H34+I34+J34+K34)*(1+L34) -> 99.55336 | H34: =VLOOKUP(B34,'[1]2.4给排水工程'!$B$3:$H$113,7,0) -> 55.32 | I34: =VLOOKUP(B34,'[1]2.4给排水工程'!$B$3:$I$113,8,0) -> 23 | J34: =VLOOKUP(B34,'[1]2.4给排水工程'!$B$3:$J$113,9,0) -> 0.66 | K34: =VLOOKUP(B34,'[1]2.4给排水工程'!$B$3:$K$113,10,0) -> 3.5 | L34: =$L$3 -> 0.207 | M34: =F34*G34 -> 995.5336
A35: 33 | B35: PVC排水管De110 | C35: 1.安装部位:室内 2.介质:污水 3.连接形式:承插粘结 4.阻火圈设计要求:按设计及规范要求 5.管道穿内墙、楼板、吊顶开洞及封堵套管:按设计及规范要求 6.管道支架及抗震支架：按设计及规范要求 7.其他:按设计及规范要求 | D35: 按设计图示管道中心线以长度计算 | E35: m | F35: 26.14 | G35: =(H35+I35+J35+K35)*(1+L35) -> 67.55579 | H35: =VLOOKUP(B35,'[1]2.4给排水工程'!$B$3:$H$113,7,0) -> 40.54 | I35: =VLOOKUP(B35,'[1]2.4给排水工程'!$B$3:$I$113,8,0) -> 14.9 | J35: =VLOOKUP(B35,'[1]2.4给排水工程'!$B$3:$J$113,9,0) -> 0.52 | K35: =VLOOKUP(B35,'[1]2.4给排水工程'!$B$3:$K$113,10,0) -> 0.01 | L35: =$L$3 -> 0.207 | M35: =F35*G35 -> 1765.9084
A36: 34 | B36: PVC排水管De75 | C36: 1.安装部位:室内 2.介质:污水 3.连接形式:承插粘结 4.阻火圈设计要求:按设计及规范要求 5.管道穿内墙、楼板、吊顶开洞及封堵套管:按设计及规范要求 6.管道支架及抗震支架：按设计及规范要求 7.其他:按设计及规范要求 | D36: 按设计图示管道中心线以长度计算 | E36: m | F36: 5 | G36: =(H36+I36+J36+K36)*(1+L36) -> 52.78211 | H36: =VLOOKUP(B36,'[1]2.4给排水工程'!$B$3:$H$113,7,0) -> 29.38 | I36: =VLOOKUP(B36,'[1]2.4给排水工程'!$B$3:$I$113,8,0) -> 14 | J36: =VLOOKUP(B36,'[1]2.4给排水工程'!$B$3:$J$113,9,0) -> 0.35 | K36: =VLOOKUP(B36,'[1]2.4给排水工程'!$B$3:$K$113,10,0) -> 0 | L36: =$L$3 -> 0.207 | M36: =F36*G36 -> 263.91055
A37: 35 | B37: PVC排水管De50 | C37: 1.安装部位:室内 2.介质:污水 3.连接形式:承插粘结 4.阻火圈设计要求:按设计及规范要求 5.管道穿内墙、楼板、吊顶开洞及封堵套管:按设计及规范要求 6.管道支架及抗震支架：按设计及规范要求 7.其他:按设计及规范要求 | D37: 按设计图示管道中心线以长度计算 | E37: m | F37: 13.25 | G37: =(H37+I37+J37+K37)*(1+L37) -> 39.25164 | H37: =VLOOKUP(B37,'[1]2.4给排水工程'!$B$3:$H$113,7,0) -> 24.32 | I37: =VLOOKUP(B37,'[1]2.4给排水工程'!$B$3:$I$113,8,0) -> 8 | J37: =VLOOKUP(B37,'[1]2.4给排水工程'!$B$3:$J$113,9,0) -> 0.2 | K37: =VLOOKUP(B37,'[1]2.4给排水工程'!$B$3:$K$113,10,0) -> 0 | L37: =$L$3 -> 0.207 | M37: =F37*G37 -> 520.08423
A38: 36 | B38: 铸铁排水管DN200 | C38: 1.安装部位:室内 2.介质:污水 3.连接形式:按设计及规范要求 4.管道穿内墙、楼板、吊顶开洞及封堵套管:按设计及规范要求 5.管道支架及抗震支架：按设计及规范要求 6.其他:按设计及规范要求 | D38: 按设计图示管道中心线以长度计算 | E38: m | G38: =(H38+I38+J38+K38)*(1+L38) -> 288.67819 | H38: =VLOOKUP(B38,'[1]2.4给排水工程'!$B$3:$H$113,7,0) -> 77.35 | I38: =VLOOKUP(B38,'[1]2.4给排水工程'!$B$3:$I$113,8,0) -> 123.62 | J38: =VLOOKUP(B38,'[1]2.4给排水工程'!$B$3:$J$113,9,0) -> 4.33 | K38: =VLOOKUP(B38,'[1]2.4给排水工程'!$B$3:$K$113,10,0) -> 33.87 | L38: =$L$3 -> 0.207 | M38: =F38*G38 -> 0
A39: 37 | B39: 铸铁排水管DN150 | C39: 1.安装部位:室内 2.介质:污水 3.连接形式:按设计及规范要求 4.管道穿内墙、楼板、吊顶开洞及封堵套管:按设计及规范要求 5.管道支架及抗震支架：按设计及规范要求 6.其他:按设计及规范要求 | D39: 按设计图示管道中心线以长度计算 | E39: m | G39: =(H39+I39+J39+K39)*(1+L39) -> 232.99928 | H39: =VLOOKUP(B39,'[1]2.4给排水工程'!$B$3:$H$113,7,0) -> 72.96 | I39: =VLOOKUP(B39,'[1]2.4给排水工程'!$B$3:$I$113,8,0) -> 92.1 | J39: =VLOOKUP(B39,'[1]2.4给排水工程'!$B$3:$J$113,9,0) -> 3.85 | K39: =VLOOKUP(B39,'[1]2.4给排水工程'!$B$3:$K$113,10,0) -> 24.13 | L39: =$L$3 -> 0.207 | M39: =F39*G39 -> 0
A40: 38 | B40: 铸铁排水管DN100 | C40: 1.安装部位:室内 2.介质:污水 3.连接形式:按设计及规范要求 4.管道穿内墙、楼板、吊顶开洞及封堵套管:按设计及规范要求 5.管道支架及抗震支架：按设计及规范要求 6.其他:按设计及规范要求 | D40: 按设计图示管道中心线以长度计算 | E40: m | G40: =(H40+I40+J40+K40)*(1+L40) -> 181.35175 | H40: =VLOOKUP(B40,'[1]2.4给排水工程'!$B$3:$H$113,7,0) -> 68.8 | I40: =VLOOKUP(B40,'[1]2.4给排水工程'!$B$3:$I$113,8,0) -> 62.1 | J40: =VLOOKUP(B40,'[1]2.4给排水工程'!$B$3:$J$113,9,0) -> 3.76 | K40: =VLOOKUP(B40,'[1]2.4给排水工程'!$B$3:$K$113,10,0) -> 15.59 | L40: =$L$3 -> 0.207 | M40: =F40*G40 -> 0
A41: 39 | B41: 铸铁排水管DN65 | C41: 1.安装部位:室内 2.介质:污水 3.连接形式:按设计及规范要求 4.管道穿内墙、楼板、吊顶开洞及封堵套管:按设计及规范要求 5.管道支架及抗震支架：按设计及规范要求 6.其他:按设计及规范要求 | D41: 按设计图示管道中心线以长度计算 | E41: m | G41: =(H41+I41+J41+K41)*(1+L41) -> 133.60283 | H41: =VLOOKUP(B41,'[1]2.4给排水工程'!$B$3:$H$113,7,0) -> 49.08 | I41: =VLOOKUP(B41,'[1]2.4给排水工程'!$B$3:$I$113,8,0) -> 56.2 | J41: =VLOOKUP(B41,'[1]2.4给排水工程'!$B$3:$J$113,9,0) -> 2.78 | K41: =VLOOKUP(B41,'[1]2.4给排水工程'!$B$3:$K$113,10,0) -> 2.63 | L41: =$L$3 -> 0.207 | M41: =F41*G41 -> 0
A42: 40 | B42: 铸铁排水管DN50 | C42: 1.安装部位:室内 2.介质:污水 3.连接形式:按设计及规范要求 4.管道穿内墙、楼板、吊顶开洞及封堵套管:按设计及规范要求 5.管道支架及抗震支架：按设计及规范要求 6.其他:按设计及规范要求 | D42: 按设计图示管道中心线以长度计算 | E42: m | G42: =(H42+I42+J42+K42)*(1+L42) -> 114.65293 | H42: =VLOOKUP(B42,'[1]2.4给排水工程'!$B$3:$H$113,7,0) -> 39.55 | I42: =VLOOKUP(B42,'[1]2.4给排水工程'!$B$3:$I$113,8,0) -> 52.5 | J42: =VLOOKUP(B42,'[1]2.4给排水工程'!$B$3:$J$113,9,0) -> 1.63 | K42: =VLOOKUP(B42,'[1]2.4给排水工程'!$B$3:$K$113,10,0) -> 1.31 | L42: =$L$3 -> 0.207 | M42: =F42*G42 -> 0
A43: 41 | B43: 闸阀DN150及以上 | C43: 1.连接形式:综合考虑 2.其他:按设计及规范要求 | D43: 按设计图示数量计算 | E43: 个 | G43: =(H43+I43+J43+K43)*(1+L43) -> 1042.0031 | H43: =VLOOKUP(B43,'[1]2.4给排水工程'!$B$3:$H$113,7,0) -> 232.6 | I43: =VLOOKUP(B43,'[1]2.4给排水工程'!$B$3:$I$113,8,0) -> 432.83 | J43: =VLOOKUP(B43,'[1]2.4给排水工程'!$B$3:$J$113,9,0) -> 40.98 | K43: =VLOOKUP(B43,'[1]2.4给排水工程'!$B$3:$K$113,10,0) -> 156.89 | L43: =$L$3 -> 0.207 | M43: =F43*G43 -> 0
A44: 42 | B44: 闸阀DN100-125 | C44: 1.连接形式:综合考虑 2.其他:按设计及规范要求 | D44: 按设计图示数量计算 | E44: 个 | G44: =(H44+I44+J44+K44)*(1+L44) -> 791.77993 | H44: =VLOOKUP(B44,'[1]2.4给排水工程'!$B$3:$H$113,7,0) -> 175.18 | I44: =VLOOKUP(B44,'[1]2.4给排水工程'!$B$3:$I$113,8,0) -> 390.7 | J44: =VLOOKUP(B44,'[1]2.4给排水工程'!$B$3:$J$113,9,0) -> 10.56 | K44: =VLOOKUP(B44,'[1]2.4给排水工程'!$B$3:$K$113,10,0) -> 79.55 | L44: =$L$3 -> 0.207 | M44: =F44*G44 -> 0
A45: 43 | B45: 闸阀DN50-80 | C45: 1.连接形式:综合考虑 2.其他:按设计及规范要求 | D45: 按设计图示数量计算 | E45: 个 | G45: =(H45+I45+J45+K45)*(1+L45) -> 431.49043 | H45: =VLOOKUP(B45,'[1]2.4给排水工程'!$B$3:$H$113,7,0) -> 169.46 | I45: =VLOOKUP(B45,'[1]2.4给排水工程'!$B$3:$I$113,8,0) -> 150 | J45: =VLOOKUP(B45,'[1]2.4给排水工程'!$B$3:$J$113,9,0) -> 19.99 | K45: =VLOOKUP(B45,'[1]2.4给排水工程'!$B$3:$K$113,10,0) -> 18.04 | L45: =$L$3 -> 0.207 | M45: =F45*G45 -> 0
A46: 44 | B46: 蝶阀DN150及以上 | C46: 1.连接形式:综合考虑 2.其他:按设计及规范要求 | D46: 按设计图示数量计算 | E46: 个 | G46: =(H46+I46+J46+K46)*(1+L46) -> 576.64425 | H46: =VLOOKUP(B46,'[1]2.4给排水工程'!$B$3:$H$113,7,0) -> 129.88 | I46: =VLOOKUP(B46,'[1]2.4给排水工程'!$B$3:$I$113,8,0) -> 250 | J46: =VLOOKUP(B46,'[1]2.4给排水工程'!$B$3:$J$113,9,0) -> 40.98 | K46: =VLOOKUP(B46,'[1]2.4给排水工程'!$B$3:$K$113,10,0) -> 56.89 | L46: =$L$3 -> 0.207 | M46: =F46*G46 -> 0
A47: 45 | B47: 蝶阀DN100-125 | C47: 1.连接形式:综合考虑 2.其他:按设计及规范要求 | D47: 按设计图示数量计算 | E47: 个 | G47: =(H47+I47+J47+K47)*(1+L47) -> 428.83503 | H47: =VLOOKUP(B47,'[1]2.4给排水工程'!$B$3:$H$113,7,0) -> 125.18 | I47: =VLOOKUP(B47,'[1]2.4给排水工程'!$B$3:$I$113,8,0) -> 170 | J47: =VLOOKUP(B47,'[1]2.4给排水工程'!$B$3:$J$113,9,0) -> 10.56 | K47: =VLOOKUP(B47,'[1]2.4给排水工程'!$B$3:$K$113,10,0) -> 49.55 | L47: =$L$3 -> 0.207 | M47: =F47*G47 -> 0
A48: 46 | B48: 蝶阀DN50-80 | C48: 1.连接形式:综合考虑 2.其他:按设计及规范要求 | D48: 按设计图示数量计算 | E48: 个 | G48: =(H48+I48+J48+K48)*(1+L48) -> 272.16643 | H48: =VLOOKUP(B48,'[1]2.4给排水工程'!$B$3:$H$113,7,0) -> 107.46 | I48: =VLOOKUP(B48,'[1]2.4给排水工程'!$B$3:$I$113,8,0) -> 80 | J48: =VLOOKUP(B48,'[1]2.4给排水工程'!$B$3:$J$113,9,0) -> 19.99 | K48: =VLOOKUP(B48,'[1]2.4给排水工程'!$B$3:$K$113,10,0) -> 18.04 | L48: =$L$3 -> 0.207 | M48: =F48*G48 -> 0
A49: 47 | B49: 截止阀DN40 | C49: 1.连接形式:综合考虑 2.其他:按设计及规范要求 | D49: 按设计图示数量计算 | E49: 个 | F49: 2 | G49: =(H49+I49+J49+K49)*(1+L49) -> 109.01624 | H49: 25 | I49: 39.66 | J49: 24.16 | K49: 1.5 | L49: =$L$3 -> 0.207 | M49: =F49*G49 -> 218.03248
A50: 48 | B50: 截止阀DN32 | C50: 1.连接形式:综合考虑 2.其他:按设计及规范要求 | D50: 按设计图示数量计算 | E50: 个 | F50: 2 | G50: =(H50+I50+J50+K50)*(1+L50) -> 93.3011 | H50: 25 | I50: 32.8 | J50: 18 | K50: 1.5 | L50: =$L$3 -> 0.207 | M50: =F50*G50 -> 186.6022
A51: 49 | B51: 截止阀DN25 | C51: 1.连接形式:综合考虑 2.其他:按设计及规范要求 | D51: 按设计图示数量计算 | E51: 个 | F51: 2 | G51: =(H51+I51+J51+K51)*(1+L51) -> 80.7483 | H51: 25 | I51: 25.4 | J51: 15 | K51: 1.5 | L51: =$L$3 -> 0.207 | M51: =F51*G51 -> 161.4966
A52: 50 | B52: 截止阀DN20 | C52: 1.连接形式:综合考虑 2.其他:按设计及规范要求 | D52: 按设计图示数量计算 | E52: 个 | F52: 2 | G52: =(H52+I52+J52+K52)*(1+L52) -> 76.7652 | H52: 25 | I52: 22.6 | J52: 15 | K52: 1 | L52: =$L$3 -> 0.207 | M52: =F52*G52 -> 153.5304
A53: 51 | B53: 截止阀DN15 | C53: 1.连接形式:综合考虑 2.其他:按设计及规范要求 | D53: 按设计图示数量计算 | E53: 个 | F53: 2 | G53: =(H53+I53+J53+K53)*(1+L53) -> 63.8503 | H53: 25 | I53: 16.9 | J53: 10 | K53: 1 | L53: =$L$3 -> 0.207 | M53: =F53*G53 -> 127.7006
A54: 52 | B54: Y型过滤器DN150 | C54: 1.连接形式:按设计及规范要求 2.其他:按设计及规范要求 | D54: 按设计图示数量计算 | E54: 个 | G54: =(H54+I54+J54+K54)*(1+L54) -> 849.70386 | H54: =VLOOKUP(B54,'[1]2.4给排水工程'!$B$3:$H$113,7,0) -> 129.88 | I54: =VLOOKUP(B54,'[1]2.4给排水工程'!$B$3:$I$113,8,0) -> 436.23 | J54: =VLOOKUP(B54,'[1]2.4给排水工程'!$B$3:$J$113,9,0) -> 40.98 | K54: =VLOOKUP(B54,'[1]2.4给排水工程'!$B$3:$K$113,10,0) -> 96.89 | L54: =$L$3 -> 0.207 | M54: =F54*G54 -> 0
A55: 53 | B55: Y型过滤器DN100 | C55: 1.连接形式:按设计及规范要求 2.其他:按设计及规范要求 | D55: 按设计图示数量计算 | E55: 个 | G55: =(H55+I55+J55+K55)*(1+L55) -> 573.25258 | H55: =VLOOKUP(B55,'[1]2.4给排水工程'!$B$3:$H$113,7,0) -> 122.96 | I55: =VLOOKUP(B55,'[1]2.4给排水工程'!$B$3:$I$113,8,0) -> 273.96 | J55: =VLOOKUP(B55,'[1]2.4给排水工程'!$B$3:$J$113,9,0) -> 32.81 | K55: =VLOOKUP(B55,'[1]2.4给排水工程'!$B$3:$K$113,10,0) -> 45.21 | L55: =$L$3 -> 0.207 | M55: =F55*G55 -> 0
A56: 54 | B56: Y型过滤器DN80 | C56: 1.连接形式:按设计及规范要求 2.其他:按设计及规范要求 | D56: 按设计图示数量计算 | E56: 个 | G56: =(H56+I56+J56+K56)*(1+L56) -> 427.00039 | H56: =VLOOKUP(B56,'[1]2.4给排水工程'!$B$3:$H$113,7,0) -> 117.46 | I56: =VLOOKUP(B56,'[1]2.4给排水工程'!$B$3:$I$113,8,0) -> 198.28 | J56: =VLOOKUP(B56,'[1]2.4给排水工程'!$B$3:$J$113,9,0) -> 19.99 | K56: =VLOOKUP(B56,'[1]2.4给排水工程'!$B$3:$K$113,10,0) -> 18.04 | L56: =$L$3 -> 0.207 | M56: =F56*G56 -> 0
A57: 55 | B57: Y型过滤器DN65 | C57: 1.连接形式:按设计及规范要求 2.其他:按设计及规范要求 | D57: 按设计图示数量计算 | E57: 个 | G57: =(H57+I57+J57+K57)*(1+L57) -> 328.88336 | H57: =VLOOKUP(B57,'[1]2.4给排水工程'!$B$3:$H$113,7,0) -> 86.51 | I57: =VLOOKUP(B57,'[1]2.4给排水工程'!$B$3:$I$113,8,0) -> 155.47 | J57: =VLOOKUP(B57,'[1]2.4给排水工程'!$B$3:$J$113,9,0) -> 13.51 | K57: =VLOOKUP(B57,'[1]2.4给排水工程'!$B$3:$K$113,10,0) -> 16.99 | L57: =$L$3 -> 0.207 | M57: =F57*G57 -> 0
A58: 56 | B58: Y型过滤器DN50 | C58: 1.连接形式:按设计及规范要求 2.其他:按设计及规范要求 | D58: 按设计图示数量计算 | E58: 个 | G58: =(H58+I58+J58+K58)*(1+L58) -> 220.25336 | H58: =VLOOKUP(B58,'[1]2.4给排水工程'!$B$3:$H$113,7,0) -> 61.43 | I58: =VLOOKUP(B58,'[1]2.4给排水工程'!$B$3:$I$113,8,0) -> 103.01 | J58: =VLOOKUP(B58,'[1]2.4给排水工程'!$B$3:$J$113,9,0) -> 13.51 | K58: =VLOOKUP(B58,'[1]2.4给排水工程'!$B$3:$K$113,10,0) -> 4.53 | L58: =$L$3 -> 0.207 | M58: =F58*G58 -> 0
A59: 57 | B59: Y型过滤器DN40 | C59: 1.连接形式:按设计及规范要求 2.其他:按设计及规范要求 | D59: 按设计图示数量计算 | E59: 个 | G59: =(H59+I59+J59+K59)*(1+L59) -> 186.9643 | H59: =VLOOKUP(B59,'[1]2.4给排水工程'!$B$3:$H$113,7,0) -> 45.05 | I59: =VLOOKUP(B59,'[1]2.4给排水工程'!$B$3:$I$113,8,0) -> 82.19 | J59: =VLOOKUP(B59,'[1]2.4给排水工程'!$B$3:$J$113,9,0) -> 24.16 | K59: =VLOOKUP(B59,'[1]2.4给排水工程'!$B$3:$K$113,10,0) -> 3.5 | L59: =$L$3 -> 0.207 | M59: =F59*G59 -> 0
A60: 58 | B60: Y型过滤器DN32 | C60: 1.连接形式:按设计及规范要求 2.其他:按设计及规范要求 | D60: 按设计图示数量计算 | E60: 个 | G60: =(H60+I60+J60+K60)*(1+L60) -> 153.09588 | H60: =VLOOKUP(B60,'[1]2.4给排水工程'!$B$3:$H$113,7,0) -> 31.85 | I60: =VLOOKUP(B60,'[1]2.4给排水工程'!$B$3:$I$113,8,0) -> 79.38 | J60: =VLOOKUP(B60,'[1]2.4给排水工程'!$B$3:$J$113,9,0) -> 12.6 | K60: =VLOOKUP(B60,'[1]2.4给排水工程'!$B$3:$K$113,10,0) -> 3.01 | L60: =$L$3 -> 0.207 | M60: =F60*G60 -> 0
A61: 59 | B61: Y型过滤器DN25 | C61: 1.连接形式:按设计及规范要求 2.其他:按设计及规范要求 | D61: 按设计图示数量计算 | E61: 个 | G61: =(H61+I61+J61+K61)*(1+L61) -> 124.87622 | H61: =VLOOKUP(B61,'[1]2.4给排水工程'!$B$3:$H$113,7,0) -> 25.03 | I61: =VLOOKUP(B61,'[1]2.4给排水工程'!$B$3:$I$113,8,0) -> 67.04 | J61: =VLOOKUP(B61,'[1]2.4给排水工程'!$B$3:$J$113,9,0) -> 9.14 | K61: =VLOOKUP(B61,'[1]2.4给排水工程'!$B$3:$K$113,10,0) -> 2.25 | L61: =$L$3 -> 0.207 | M61: =F61*G61 -> 0
A62: 60 | B62: Y型过滤器DN20 | C62: 1.连接形式:按设计及规范要求 2.其他:按设计及规范要求 | D62: 按设计图示数量计算 | E62: 个 | G62: =(H62+I62+J62+K62)*(1+L62) -> 92.39585 | H62: =VLOOKUP(B62,'[1]2.4给排水工程'!$B$3:$H$113,7,0) -> 22.75 | I62: =VLOOKUP(B62,'[1]2.4给排水工程'!$B$3:$I$113,8,0) -> 45.1 | J62: =VLOOKUP(B62,'[1]2.4给排水工程'!$B$3:$J$113,9,0) -> 6.86 | K62: =VLOOKUP(B62,'[1]2.4给排水工程'!$B$3:$K$113,10,0) -> 1.84 | L62: =$L$3 -> 0.207 | M62: =F62*G62 -> 0
A63: 61 | B63: 止回阀DN150 | C63: 1.连接形式:按设计及规范要求 2.其他:按设计及规范要求 | D63: 按设计图示数量计算 | E63: 个 | G63: =(H63+I63+J63+K63)*(1+L63) -> 994.49558 | H63: =VLOOKUP(B63,'[1]2.4给排水工程'!$B$3:$H$113,7,0) -> 227.88 | I63: =VLOOKUP(B63,'[1]2.4给排水工程'!$B$3:$I$113,8,0) -> 498.19 | J63: =VLOOKUP(B63,'[1]2.4给排水工程'!$B$3:$J$113,9,0) -> 40.98 | K63: =VLOOKUP(B63,'[1]2.4给排水工程'!$B$3:$K$113,10,0) -> 56.89 | L63: =$L$3 -> 0.207 | M63: =F63*G63 -> 0
A64: 62 | B64: 止回阀DN100 | C64: 1.连接形式:按设计及规范要求 2.其他:按设计及规范要求 | D64: 按设计图示数量计算 | E64: 个 | G64: =(H64+I64+J64+K64)*(1+L64) -> 694.49573 | H64: =VLOOKUP(B64,'[1]2.4给排水工程'!$B$3:$H$113,7,0) -> 162.96 | I64: =VLOOKUP(B64,'[1]2.4给排水工程'!$B$3:$I$113,8,0) -> 334.41 | J64: =VLOOKUP(B64,'[1]2.4给排水工程'!$B$3:$J$113,9,0) -> 32.81 | K64: =VLOOKUP(B64,'[1]2.4给排水工程'!$B$3:$K$113,10,0) -> 45.21 | L64: =$L$3 -> 0.207 | M64: =F64*G64 -> 0
A65: 63 | B65: 止回阀DN80 | C65: 1.连接形式:按设计及规范要求 2.其他:按设计及规范要求 | D65: 按设计图示数量计算 | E65: 个 | G65: =(H65+I65+J65+K65)*(1+L65) -> 517.40469 | H65: =VLOOKUP(B65,'[1]2.4给排水工程'!$B$3:$H$113,7,0) -> 127.46 | I65: =VLOOKUP(B65,'[1]2.4给排水工程'!$B$3:$I$113,8,0) -> 263.18 | J65: =VLOOKUP(B65,'[1]2.4给排水工程'!$B$3:$J$113,9,0) -> 19.99 | K65: =VLOOKUP(B65,'[1]2.4给排水工程'!$B$3:$K$113,10,0) -> 18.04 | L65: =$L$3 -> 0.207 | M65: =F65*G65 -> 0
... A74: 72 | B74: 水表DN65 | C74: 1.连接形式:按设计及规范要求 2.其他:按设计及规范要求 | D74: 按设计图示数量计算 | E74: 块 | G74: =(H74+I74+J74+K74)*(1+L74) -> 566.89169 | H74: =VLOOKUP(B74,'[1]2.4给排水工程'!$B$3:$H$113,7,0) -> 136.5 | I74: =VLOOKUP(B74,'[1]2.4给排水工程'!$B$3:$I$113,8,0) -> 318.58 | J74: =VLOOKUP(B74,'[1]2.4给排水工程'!$B$3:$J$113,9,0) -> 13.54 | K74: =VLOOKUP(B74,'[1]2.4给排水工程'!$B$3:$K$113,10,0) -> 1.05 | L74: =$L$3 -> 0.207 | M74: =F74*G74 -> 0
A75: 73 | B75: 水表DN50 | C75: 1.连接形式:按设计及规范要求 2.其他:按设计及规范要求 | D75: 按设计图示数量计算 | E75: 块 | F75: 1 | G75: =(H75+I75+J75+K75)*(1+L75) -> 386.26414 | H75: =VLOOKUP(B75,'[1]2.4给排水工程'!$B$3:$H$113,7,0) -> 91 | I75: =VLOOKUP(B75,'[1]2.4给排水工程'!$B$3:$I$113,8,0) -> 219.29 | J75: =VLOOKUP(B75,'[1]2.4给排水工程'!$B$3:$J$113,9,0) -> 9.03 | K75: =VLOOKUP(B75,'[1]2.4给排水工程'!$B$3:$K$113,10,0) -> 0.7 | L75: =$L$3 -> 0.207 | M75: =F75*G75 -> 386.26414
A76: 74 | B76: 水表DN40 | C76: 1.连接形式:按设计及规范要求 2.其他:按设计及规范要求 | D76: 按设计图示数量计算 | E76: 块 | G76: =(H76+I76+J76+K76)*(1+L76) -> 255.78744 | H76: =VLOOKUP(B76,'[1]2.4给排水工程'!$B$3:$H$113,7,0) -> 72.8 | I76: =VLOOKUP(B76,'[1]2.4给排水工程'!$B$3:$I$113,8,0) -> 131.27 | J76: =VLOOKUP(B76,'[1]2.4给排水工程'!$B$3:$J$113,9,0) -> 7.28 | K76: =VLOOKUP(B76,'[1]2.4给排水工程'!$B$3:$K$113,10,0) -> 0.57 | L76: =$L$3 -> 0.207 | M76: =F76*G76 -> 0
A77: 75 | B77: 水表DN32 | C77: 1.连接形式:按设计及规范要求 2.其他:按设计及规范要求 | D77: 按设计图示数量计算 | E77: 块 | G77: =(H77+I77+J77+K77)*(1+L77) -> 205.75729 | H77: =VLOOKUP(B77,'[1]2.4给排水工程'!$B$3:$H$113,7,0) -> 59.15 | I77: =VLOOKUP(B77,'[1]2.4给排水工程'!$B$3:$I$113,8,0) -> 105.02 | J77: =VLOOKUP(B77,'[1]2.4给排水工程'!$B$3:$J$113,9,0) -> 5.84 | K77: =VLOOKUP(B77,'[1]2.4给排水工程'!$B$3:$K$113,10,0) -> 0.46 | L77: =$L$3 -> 0.207 | M77: =F77*G77 -> 0
A78: 76 | B78: 水表DN25 | C78: 1.连接形式:按设计及规范要求 2.其他:按设计及规范要求 | D78: 按设计图示数量计算 | E78: 块 | G78: =(H78+I78+J78+K78)*(1+L78) -> 169.25761 | H78: =VLOOKUP(B78,'[1]2.4给排水工程'!$B$3:$H$113,7,0) -> 47.78 | I78: =VLOOKUP(B78,'[1]2.4给排水工程'!$B$3:$I$113,8,0) -> 87.53 | J78: =VLOOKUP(B78,'[1]2.4给排水工程'!$B$3:$J$113,9,0) -> 4.57 | K78: =VLOOKUP(B78,'[1]2.4给排水工程'!$B$3:$K$113,10,0) -> 0.35 | L78: =$L$3 -> 0.207 | M78: =F78*G78 -> 0
A79: 77 | B79: 水表DN20 | C79: 1.连接形式:按设计及规范要求 2.其他:按设计及规范要求 | D79: 按设计图示数量计算 | E79: 块 | G79: =(H79+I79+J79+K79)*(1+L79) -> 159.52919 | H79: =VLOOKUP(B79,'[1]2.4给排水工程'!$B$3:$H$113,7,0) -> 40.95 | I79: =VLOOKUP(B79,'[1]2.4给排水工程'!$B$3:$I$113,8,0) -> 87.53 | J79: =VLOOKUP(B79,'[1]2.4给排水工程'!$B$3:$J$113,9,0) -> 3.51 | K79: =VLOOKUP(B79,'[1]2.4给排水工程'!$B$3:$K$113,10,0) -> 0.18 | L79: =$L$3 -> 0.207 | M79: =F79*G79 -> 0
A80: 78 | B80: 台盆 | C80: 1.材质:陶瓷 2.附件名称、数量:含不锈钢混水龙头、金属软管、下水配件等洗脸盆所需所有附件 3.其他:按设计及规范要求 | D80: 按设计图示数量计算 | E80: 组 | F80: 8 | G80: =(H80+I80+J80+K80)*(1+L80) -> 1062.9566 | H80: =VLOOKUP(B80,'[1]2.4给排水工程'!$B$3:$H$113,7,0) -> 118.53 | I80: =VLOOKUP(B80,'[1]2.4给排水工程'!$B$3:$I$113,8,0) -> 759.73 | J80: =VLOOKUP(B80,'[1]2.4给排水工程'!$B$3:$J$113,9,0) -> 2.4 | K80: =VLOOKUP(B80,'[1]2.4给排水工程'!$B$3:$K$113,10,0) -> 0 | L80: =$L$3 -> 0.207 | M80: =F80*G80 -> 8503.653
A81: 79 | B81: 蹲便器 | C81: 1.材质:陶瓷 2.规格、类型:蹲式 3.附件名称、数量:含水箱、阀、金属软管等蹲便器所需所有附件 4.其他:按设计及规范要求 | D81: 按设计图示数量计算 | E81: 组 | F81: 5 | G81: =(H81+I81+J81+K81)*(1+L81) -> 896.00438 | H81: =VLOOKUP(B81,'[1]2.4给排水工程'!$B$3:$H$113,7,0) -> 180.86 | I81: =VLOOKUP(B81,'[1]2.4给排水工程'!$B$3:$I$113,8,0) -> 527.79 | J81: =VLOOKUP(B81,'[1]2.4给排水工程'!$B$3:$J$113,9,0) -> 33.69 | K81: =VLOOKUP(B81,'[1]2.4给排水工程'!$B$3:$K$113,10,0) -> 0 | L81: =$L$3 -> 0.207 | M81: =F81*G81 -> 4480.0219
A82: 80 | B82: 坐便器 | C82: 1.材质:陶瓷 2.规格、类型:坐式 3.附件名称、数量:含水箱、阀、金属软管等坐便器所需所有附件 4.其他:按设计及规范要求 | D82: 按设计图示数量计算 | E82: 组 | F82: 5 | G82: =(H82+I82+J82+K82)*(1+L82) -> 923.02911 | H82: =VLOOKUP(B82,'[1]2.4给排水工程'!$B$3:$H$113,7,0) -> 133.77 | I82: =VLOOKUP(B82,'[1]2.4给排水工程'!$B$3:$I$113,8,0) -> 614.08 | J82: =VLOOKUP(B82,'[1]2.4给排水工程'!$B$3:$J$113,9,0) -> 16.88 | K82: =VLOOKUP(B82,'[1]2.4给排水工程'!$B$3:$K$113,10,0) -> 0 | L82: =$L$3 -> 0.207 | M82: =F82*G82 -> 4615.1456
A83: 81 | B83: 小便器 | C83: 1.材质:陶瓷 2.规格、类型:感应自动冲洗 3.组装形式:壁挂式 4.附件名称、数量:含金属软管、阀门、感应器等小便器所需所有附件 5.其他:按设计及规范要求 | D83: 按设计图示数量计算 | E83: 组 | F83: 7 | G83: =(H83+I83+J83+K83)*(1+L83) -> 862.55841 | H83: =VLOOKUP(B83,'[1]2.4给排水工程'!$B$3:$H$113,7,0) -> 73.94 | I83: =VLOOKUP(B83,'[1]2.4给排水工程'!$B$3:$I$113,8,0) -> 636.59 | J83: =VLOOKUP(B83,'[1]2.4给排水工程'!$B$3:$J$113,9,0) -> 4.1 | K83: =VLOOKUP(B83,'[1]2.4给排水工程'!$B$3:$K$113,10,0) -> 0 | L83: =$L$3 -> 0.207 | M83: =F83*G83 -> 6037.9089
A84: 82 | B84: 拖布池 | C84: 1.材质:陶瓷 2.附件名称、数量:含龙头、下水配件等拖布池所需所有附件 | D84: 按设计图示数量计算 | E84: 组 | F84: 1 | G84: =(H84+I84+J84+K84)*(1+L84) -> 720.84454 | H84: =VLOOKUP(B84,'[1]2.4给排水工程'!$B$3:$H$113,7,0) -> 72.8 | I84: =VLOOKUP(B84,'[1]2.4给排水工程'!$B$3:$I$113,8,0) -> 518.41 | J84: =VLOOKUP(B84,'[1]2.4给排水工程'!$B$3:$J$113,9,0) -> 6.01 | K84: =VLOOKUP(B84,'[1]2.4给排水工程'!$B$3:$K$113,10,0) -> 0 | L84: =$L$3 -> 0.207 | M84: =F84*G84 -> 720.84454
A85: 83 | B85: 不锈钢洗涤盆单槽 | C85: 1.材质:不锈钢 2.规格、类型:单槽 3.附件名称、数量:含龙头、下水配件等洗涤盆所需所有附件 | D85: 按设计图示数量计算 | E85: 组 | G85: =(H85+I85+J85+K85)*(1+L85) -> 306.02278 | H85: =VLOOKUP(B85,'[1]2.4给排水工程'!$B$3:$H$113,7,0) -> 72.8 | I85: =VLOOKUP(B85,'[1]2.4给排水工程'!$B$3:$I$113,8,0) -> 176.97 | J85: =VLOOKUP(B85,'[1]2.4给排水工程'!$B$3:$J$113,9,0) -> 3.77 | K85: =VLOOKUP(B85,'[1]2.4给排水工程'!$B$3:$K$113,10,0) -> 0 | L85: =$L$3 -> 0.207 | M85: =F85*G85 -> 0
A86: 84 | B86: 不锈钢洗涤盆双槽 | C86: 1.材质:不锈钢 2.规格、类型:双槽 3.附件名称、数量:含龙头、下水配件等洗涤盆所需所有附件 | D86: 按设计图示数量计算 | E86: 组 | G86: =(H86+I86+J86+K86)*(1+L86) -> 425.27438 | H86: =VLOOKUP(B86,'[1]2.4给排水工程'!$B$3:$H$113,7,0) -> 83.04 | I86: =VLOOKUP(B86,'[1]2.4给排水工程'!$B$3:$I$113,8,0) -> 265.46 | J86: =VLOOKUP(B86,'[1]2.4给排水工程'!$B$3:$J$113,9,0) -> 3.84 | K86: =VLOOKUP(B86,'[1]2.4给排水工程'!$B$3:$K$113,10,0) -> 0 | L86: =$L$3 -> 0.207 | M86: =F86*G86 -> 0
A87: 85 | B87: 不锈钢地漏DN50 | C87: 1.材质:不锈钢 2.安装方式:埋地 3.其他:按设计及规范要求 | D87: 按设计图示数量计算 | E87: 个 | F87: 1 | G87: =(H87+I87+J87+K87)*(1+L87) -> 116.78932 | H87: =VLOOKUP(B87,'[1]2.4给排水工程'!$B$3:$H$113,7,0) -> 34.35 | I87: =VLOOKUP(B87,'[1]2.4给排水工程'!$B$3:$I$113,8,0) -> 62.37 | J87: =VLOOKUP(B87,'[1]2.4给排水工程'!$B$3:$J$113,9,0) -> 0.04 | K87: =VLOOKUP(B87,'[1]2.4给排水工程'!$B$3:$K$113,10,0) -> 0 | L87: =$L$3 -> 0.207 | M87: =F87*G87 -> 116.78932
A88: 86 | B88: 不锈钢地漏DN75 | C88: 1.材质:不锈钢 2.安装方式:埋地 3.其他:按设计及规范要求 | D88: 按设计图示数量计算 | E88: 个 | F88: 2 | G88: =(H88+I88+J88+K88)*(1+L88) -> 144.09166 | H88: =VLOOKUP(B88,'[1]2.4给排水工程'!$B$3:$H$113,7,0) -> 56.43 | I88: =VLOOKUP(B88,'[1]2.4给排水工程'!$B$3:$I$113,8,0) -> 62.89 | J88: =VLOOKUP(B88,'[1]2.4给排水工程'!$B$3:$J$113,9,0) -> 0.06 | K88: =VLOOKUP(B88,'[1]2.4给排水工程'!$B$3:$K$113,10,0) -> 0 | L88: =$L$3 -> 0.207 | M88: =F88*G88 -> 288.18332
A89: 87 | B89: 不锈钢地漏DN100 | C89: 1.材质:不锈钢 2.安装方式:埋地 3.其他:按设计及规范要求 | D89: 按设计图示数量计算 | E89: 个 | F89: 7 | G89: =(H89+I89+J89+K89)*(1+L89) -> 165.37107 | H89: =VLOOKUP(B89,'[1]2.4给排水工程'!$B$3:$H$113,7,0) -> 70.81 | I89: =VLOOKUP(B89,'[1]2.4给排水工程'!$B$3:$I$113,8,0) -> 66.13 | J89: =VLOOKUP(B89,'[1]2.4给排水工程'!$B$3:$J$113,9,0) -> 0.07 | K89: =VLOOKUP(B89,'[1]2.4给排水工程'!$B$3:$K$113,10,0) -> 0 | L89: =$L$3 -> 0.207 | M89: =F89*G89 -> 1157.5975
A90: 88 | B90: 不锈钢地漏DN150 | C90: 1.材质:不锈钢 2.安装方式:埋地 3.其他:按设计及规范要求 | D90: 按设计图示数量计算 | E90: 个 | F90: 4 | G90: =(H90+I90+J90+K90)*(1+L90) -> 244.76753 | H90: =VLOOKUP(B90,'[1]2.4给排水工程'!$B$3:$H$113,7,0) -> 122.85 | I90: =VLOOKUP(B90,'[1]2.4给排水工程'!$B$3:$I$113,8,0) -> 79.82 | J90: =VLOOKUP(B90,'[1]2.4给排水工程'!$B$3:$J$113,9,0) -> 0.12 | K90: =VLOOKUP(B90,'[1]2.4给排水工程'!$B$3:$K$113,10,0) -> 0 | L90: =$L$3 -> 0.207 | M90: =F90*G90 -> 979.07012
A91: 89 | B91: 地面清扫口DN150 | C91: 1.材质:铜盖铸铁 2.安装方式:暗装 3.其他:按设计及规范要求 | D91: 按设计图示数量计算 | E91: 个 | G91: =(H91+I91+J91+K91)*(1+L91) -> 90.68191 | H91: =VLOOKUP(B91,'[1]2.4给排水工程'!$B$3:$H$113,7,0) -> 25.94 | I91: =VLOOKUP(B91,'[1]2.4给排水工程'!$B$3:$I$113,8,0) -> 49.07 | J91: =VLOOKUP(B91,'[1]2.4给排水工程'!$B$3:$J$113,9,0) -> 0.12 | K91: =VLOOKUP(B91,'[1]2.4给排水工程'!$B$3:$K$113,10,0) -> 0 | L91: =$L$3 -> 0.207 | M91: =F91*G91 -> 0
A92: 90 | B92: 地面清扫口DN100 | C92: 1.材质:铜盖铸铁 2.安装方式:暗装 3.其他:按设计及规范要求 | D92: 按设计图示数量计算 | E92: 个 | G92: =(H92+I92+J92+K92)*(1+L92) -> 67.07299 | H92: =VLOOKUP(B92,'[1]2.4给排水工程'!$B$3:$H$113,7,0) -> 20.25 | I92: =VLOOKUP(B92,'[1]2.4给排水工程'!$B$3:$I$113,8,0) -> 35.25 | J92: =VLOOKUP(B92,'[1]2.4给排水工程'!$B$3:$J$113,9,0) -> 0.07 | K92: =VLOOKUP(B92,'[1]2.4给排水工程'!$B$3:$K$113,10,0) -> 0 | L92: =$L$3 -> 0.207 | M92: =F92*G92 -> 0
A93: 91 | B93: 地面清扫口DN75 | C93: 1.材质:铜盖铸铁 2.安装方式:暗装 3.其他:按设计及规范要求 | D93: 按设计图示数量计算 | E93: 个 | G93: =(H93+I93+J93+K93)*(1+L93) -> 48.81108 | H93: =VLOOKUP(B93,'[1]2.4给排水工程'!$B$3:$H$113,7,0) -> 19.79 | I93: =VLOOKUP(B93,'[1]2.4给排水工程'!$B$3:$I$113,8,0) -> 20.59 | J93: =VLOOKUP(B93,'[1]2.4给排水工程'!$B$3:$J$113,9,0) -> 0.06 | K93: =VLOOKUP(B93,'[1]2.4给排水工程'!$B$3:$K$113,10,0) -> 0 | L93: =$L$3 -> 0.207 | M93: =F93*G93 -> 0
A94: 92 | B94: 地面清扫口DN50 | C94: 1.材质:铜盖铸铁 2.安装方式:暗装 3.其他:按设计及规范要求 | D94: 按设计图示数量计算 | E94: 个 | G94: =(H94+I94+J94+K94)*(1+L94) -> 40.5552 | H94: =VLOOKUP(B94,'[1]2.4给排水工程'!$B$3:$H$113,7,0) -> 15.7 | I94: =VLOOKUP(B94,'[1]2.4给排水工程'!$B$3:$I$113,8,0) -> 17.86 | J94: =VLOOKUP(B94,'[1]2.4给排水工程'!$B$3:$J$113,9,0) -> 0.04 | K94: =VLOOKUP(B94,'[1]2.4给排水工程'!$B$3:$K$113,10,0) -> 0 | L94: =$L$3 -> 0.207 | M94: =F94*G94 -> 0
A95: 93 | B95: 小厨宝5L-7L | C95: 1.能源种类:电能 2.型号、容积:5L-7L 3.其他:按设计及规范要求 | D95: 按设计图示数量计算 | E95: 台 | F95: 2 | G95: =(H95+I95+J95+K95)*(1+L95) -> 578.08058 | H95: =VLOOKUP(B95,'[1]2.4给排水工程'!$B$3:$H$113,7,0) -> 119.89 | I95: =VLOOKUP(B95,'[1]2.4给排水工程'!$B$3:$I$113,8,0) -> 353.98 | J95: =VLOOKUP(B95,'[1]2.4给排水工程'!$B$3:$J$113,9,0) -> 5.07 | K95: =VLOOKUP(B95,'[1]2.4给排水工程'!$B$3:$K$113,10,0) -> 0 | L95: =$L$3 -> 0.207 | M95: =F95*G95 -> 1156.1612
A96: 94 | B96: 小厨宝8L-10L | C96: 1.能源种类:电能 2.型号、容积:8L-10L 3.其他:按设计及规范要求 | D96: 按设计图示数量计算 | E96: 台 | G96: =(H96+I96+J96+K96)*(1+L96) -> 738.30983 | H96: =VLOOKUP(B96,'[1]2.4给排水工程'!$B$3:$H$113,7,0) -> 119.89 | I96: =VLOOKUP(B96,'[1]2.4给排水工程'!$B$3:$I$113,8,0) -> 486.73 | J96: =VLOOKUP(B96,'[1]2.4给排水工程'!$B$3:$J$113,9,0) -> 5.07 | K96: =VLOOKUP(B96,'[1]2.4给排水工程'!$B$3:$K$113,10,0) -> 0 | L96: =$L$3 -> 0.207 | M96: =F96*G96 -> 0
A97: 95 | B97: 小厨宝11L-15L | C97: 1.能源种类:电能 2.型号、容积:11L-15L 3.其他:按设计及规范要求 | D97: 按设计图示数量计算 | E97: 台 | G97: =(H97+I97+J97+K97)*(1+L97) -> 791.70751 | H97: =VLOOKUP(B97,'[1]2.4给排水工程'!$B$3:$H$113,7,0) -> 119.89 | I97: =VLOOKUP(B97,'[1]2.4给排水工程'!$B$3:$I$113,8,0) -> 530.97 | J97: =VLOOKUP(B97,'[1]2.4给排水工程'!$B$3:$J$113,9,0) -> 5.07 | K97: =VLOOKUP(B97,'[1]2.4给排水工程'!$B$3:$K$113,10,0) -> 0 | L97: =$L$3 -> 0.207 | M97: =F97*G97 -> 0
A98: 96 | B98: 热水器50L-60L | C98: 1.能源种类:电能 2.型号、容积:50L-60L 3.其他:按设计及规范要求 | D98: 按设计图示数量计算 | E98: 台 | G98: =(H98+I98+J98+K98)*(1+L98) -> 1565.4669 | H98: =VLOOKUP(B98,'[1]2.4给排水工程'!$B$3:$H$113,7,0) -> 335.79 | I98: =VLOOKUP(B98,'[1]2.4给排水工程'!$B$3:$I$113,8,0) -> 958 | J98: =VLOOKUP(B98,'[1]2.4给排水工程'!$B$3:$J$113,9,0) -> 3.2 | K98: =VLOOKUP(B98,'[1]2.4给排水工程'!$B$3:$K$113,10,0) -> 0 | L98: =$L$3 -> 0.207 | M98: =F98*G98 -> 0
A99: 97 | B99: 热水器70L-80L | C99: 1.能源种类:电能 2.型号、容积:70L-80L 3.其他:按设计及规范要求 | D99: 按设计图示数量计算 | E99: 台 | G99: =(H99+I99+J99+K99)*(1+L99) -> 1686.1669 | H99: =VLOOKUP(B99,'[1]2.4给排水工程'!$B$3:$H$113,7,0) -> 335.79 | I99: =VLOOKUP(B99,'[1]2.4给排水工程'!$B$3:$I$113,8,0) -> 1058 | J99: =VLOOKUP(B99,'[1]2.4给排水工程'!$B$3:$J$113,9,0) -> 3.2 | K99: =VLOOKUP(B99,'[1]2.4给排水工程'!$B$3:$K$113,10,0) -> 0 | L99: =$L$3 -> 0.207 | M99: =F99*G99 -> 0
A100: 98 | B100: 淋浴花洒 | C100: 1.附件：含花洒，软管，阀门等 2.其他：按设计及规范要求 | D100: 按设计图示数量计算 | E100: 套 | G100: =(H100+I100+J100+K100)*(1+L100) -> 1245.2498 | H100: =VLOOKUP(B100,'[1]2.4给排水工程'!$B$3:$H$113,7,0) -> 101.49 | I100: =VLOOKUP(B100,'[1]2.4给排水工程'!$B$3:$I$113,8,0) -> 903.54 | J100: =VLOOKUP(B100,'[1]2.4给排水工程'!$B$3:$J$113,9,0) -> 26.66 | K100: =VLOOKUP(B100,'[1]2.4给排水工程'!$B$3:$K$113,10,0) -> 0 | L100: =$L$3 -> 0.207 | M100: =F100*G100 -> 0
A101: 99 | B101: 管道绝热厚度15mm | C101: 1.绝热材料品种:橡塑 2.其他:按设计及规范要求 | D101: 依据2013清单工程量计算规则，按图示表面积加绝热层厚度计算 | E101: m3 | G101: =(H101+I101+J101+K101)*(1+L101) -> 2610.9703 | H101: =VLOOKUP(B101,'[1]2.4给排水工程'!$B$3:$H$113,7,0) -> 1184.38 | I101: =VLOOKUP(B101,'[1]2.4给排水工程'!$B$3:$I$113,8,0) -> 752.39 | J101: =VLOOKUP(B101,'[1]2.4给排水工程'!$B$3:$J$113,9,0) -> 226.42 | K101: =VLOOKUP(B101,'[1]2.4给排水工程'!$B$3:$K$113,10,0) -> 0 | L101: =$L$3 -> 0.207 | M101: =F101*G101 -> 0
A102: 100 | B102: 管道绝热厚度20mm | C102: 1.绝热材料品种:橡塑 2.其他:按设计及规范要求 | D102: 依据2013清单工程量计算规则，按图示表面积加绝热层厚度计算 | E102: m3 | G102: =(H102+I102+J102+K102)*(1+L102) -> 2404.7423 | H102: =VLOOKUP(B102,'[1]2.4给排水工程'!$B$3:$H$113,7,0) -> 1076.08 | I102: =VLOOKUP(B102,'[1]2.4给排水工程'!$B$3:$I$113,8,0) -> 752.39 | J102: =VLOOKUP(B102,'[1]2.4给排水工程'!$B$3:$J$113,9,0) -> 163.86 | K102: =VLOOKUP(B102,'[1]2.4给排水工程'!$B$3:$K$113,10,0) -> 0 | L102: =$L$3 -> 0.207 | M102: =F102*G102 -> 0
A103: 101 | B103: 管道绝热厚度25mm | C103: 1.绝热材料品种:橡塑 2.其他:按设计及规范要求 | D103: 依据2013清单工程量计算规则，按图示表面积加绝热层厚度计算 | E103: m3 | G103: =(H103+I103+J103+K103)*(1+L103) -> 2383.3301 | H103: =VLOOKUP(B103,'[1]2.4给排水工程'!$B$3:$H$113,7,0) -> 971.43 | I103: =VLOOKUP(B103,'[1]2.4给排水工程'!$B$3:$I$113,8,0) -> 902.39 | J103: =VLOOKUP(B103,'[1]2.4给排水工程'!$B$3:$J$113,9,0) -> 100.77 | K103: =VLOOKUP(B103,'[1]2.4给排水工程'!$B$3:$K$113,10,0) -> 0 | L103: =$L$3 -> 0.207 | M103: =F103*G103 -> 0
A104: 102 | B104: 管道绝热厚度30mm | C104: 1.绝热材料品种:橡塑 2.其他:按设计及规范要求 | D104: 依据2013清单工程量计算规则，按图示表面积加绝热层厚度计算 | E104: m3 | G104: =(H104+I104+J104+K104)*(1+L104) -> 2383.3301 | H104: =VLOOKUP(B104,'[1]2.4给排水工程'!$B$3:$H$113,7,0) -> 971.43 | I104: =VLOOKUP(B104,'[1]2.4给排水工程'!$B$3:$I$113,8,0) -> 902.39 | J104: =VLOOKUP(B104,'[1]2.4给排水工程'!$B$3:$J$113,9,0) -> 100.77 | K104: =VLOOKUP(B104,'[1]2.4给排水工程'!$B$3:$K$113,10,0) -> 0 | L104: =$L$3 -> 0.207 | M104: =F104*G104 -> 0
A105: 103 | B105: 管道绝热厚度40mm | C105: 1.绝热材料品种:橡塑 2.其他:按设计及规范要求 | D105: 依据2013清单工程量计算规则，按图示表面积加绝热层厚度计算 | E105: m3 | G105: =(H105+I105+J105+K105)*(1+L105) -> 2205.9132 | H105: =VLOOKUP(B105,'[1]2.4给排水工程'!$B$3:$H$113,7,0) -> 855.4 | I105: =VLOOKUP(B105,'[1]2.4给排水工程'!$B$3:$I$113,8,0) -> 902.39 | J105: =VLOOKUP(B105,'[1]2.4给排水工程'!$B$3:$J$113,9,0) -> 69.81 | K105: =VLOOKUP(B105,'[1]2.4给排水工程'!$B$3:$K$113,10,0) -> 0 | L105: =$L$3 -> 0.207 | M105: =F105*G105 -> 0
A106: 104 | B106: 管道绝热厚度50mm | C106: 1.绝热材料品种:橡塑 2.其他:按设计及规范要求 | D106: 依据2013清单工程量计算规则，按图示表面积加绝热层厚度计算 | E106: m3 | G106: =(H106+I106+J106+K106)*(1+L106) -> 2044.7666 | H106: =VLOOKUP(B106,'[1]2.4给排水工程'!$B$3:$H$113,7,0) -> 739.38 | I106: =VLOOKUP(B106,'[1]2.4给排水工程'!$B$3:$I$113,8,0) -> 902.39 | J106: =VLOOKUP(B106,'[1]2.4给排水工程'!$B$3:$J$113,9,0) -> 52.32 | K106: =VLOOKUP(B106,'[1]2.4给排水工程'!$B$3:$K$113,10,0) -> 0 | L106: =$L$3 -> 0.207 | M106: =F106*G106 -> 0
A107: 105 | B107: 铁皮保护层厚度0.5mm | C107: 1.材料:铁皮 2.其他:按设计及规范要求 | D107: 依据2013清单计算规则，按图示表面积加绝热层厚度计算 | E107: m2 | G107: =(H107+I107+J107+K107)*(1+L107) -> 44.18827 | H107: =VLOOKUP(B107,'[1]2.4给排水工程'!$B$3:$H$113,7,0) -> 6.67 | I107: =VLOOKUP(B107,'[1]2.4给排水工程'!$B$3:$I$113,8,0) -> 25.62 | J107: =VLOOKUP(B107,'[1]2.4给排水工程'!$B$3:$J$113,9,0) -> 4.32 | K107: =VLOOKUP(B107,'[1]2.4给排水工程'!$B$3:$K$113,10,0) -> 0 | L107: =$L$3 -> 0.207 | M107: =F107*G107 -> 0
... A112: 110 | B112: 雨水篦子 | C112: 1.材质:铸铁 | D112: 按设计图示数量计算 | E112: 个 | G112: =(H112+I112+J112+K112)*(1+L112) -> 236.43923 | H112: =VLOOKUP(B112,'[1]2.4给排水工程'!$B$3:$H$113,7,0) -> 8.7 | I112: =VLOOKUP(B112,'[1]2.4给排水工程'!$B$3:$I$113,8,0) -> 171.73 | J112: =VLOOKUP(B112,'[1]2.4给排水工程'!$B$3:$J$113,9,0) -> 15.46 | K112: =VLOOKUP(B112,'[1]2.4给排水工程'!$B$3:$K$113,10,0) -> 0 | L112: =$L$3 -> 0.207 | M112: =F112*G112 -> 0
A113: 合计 | M113: =SUM(M3:M112) -> 36186.655

Sheet 2.5消防工程
A1: 长城智选中心店装修项目装饰工程
A2: 序号 | B2: 分部分项名称 | C2: 项目特征 | D2: 计量规则 | E2: 单位 | F2: 工程量 | G2: 综合单价 | H2: 人工 | I2: 主材 | J2: 辅材 | K2: 机械 | L2: 其他综合费率 | M2: 合计 | N2: 备注
A3: 一 | B3: 自动火灾报警系统
A4: 1 | B4: 消防端子箱 | C4: 1.名称:消防端子箱 2.规格:与原有系统匹配 | D4: 按设计图示数量计算 | E4: 台 | G4: =(H4+I4+J4+K4)*(1+L4) -> 245.63657 | H4: =VLOOKUP(B4,'[1]2.5消防工程 '!$B$4:$H$276,7,0) -> 73.71 | I4: =VLOOKUP(B4,'[1]2.5消防工程 '!$B$4:$I$276,8,0) -> 96.64 | J4: =VLOOKUP(B4,'[1]2.5消防工程 '!$B$4:$J$276,9,0) -> 4.43 | K4: =VLOOKUP(B4,'[1]2.5消防工程 '!$B$4:$K$276,10,0) -> 28.73 | L4: ='2.1装饰工程'!$L$4 -> 0.207 | M4: =F4*G4 -> 0
A5: 2 | B5: 火灾报警系统控制主机300点位以下 | C5: 1.名称:火灾报警系统控制主机300点位以下 2.规格:与原有系统匹配 | D5: 按设计图示数量计算 | E5: 台 | G5: =(H5+I5+J5+K5)*(1+L5) -> 5447.6255 | H5: =VLOOKUP(B5,'[1]2.5消防工程 '!$B$4:$H$276,7,0) -> 1254.25 | I5: =VLOOKUP(B5,'[1]2.5消防工程 '!$B$4:$I$276,8,0) -> 2878.97 | J5: =VLOOKUP(B5,'[1]2.5消防工程 '!$B$4:$J$276,9,0) -> 3.83 | K5: =VLOOKUP(B5,'[1]2.5消防工程 '!$B$4:$K$276,10,0) -> 376.31 | L5: =$L$4 -> 0.207 | M5: =F5*G5 -> 0
A6: 3 | B6: 火灾报警系统控制主机500点位以下 | C6: 1.名称:火灾报警系统控制主机500点位以下 2.规格:与原有系统匹配 | D6: 按设计图示数量计算 | E6: 台 | G6: =(H6+I6+J6+K6)*(1+L6) -> 7212.7665 | H6: =VLOOKUP(B6,'[1]2.5消防工程 '!$B$4:$H$276,7,0) -> 1254.25 | I6: =VLOOKUP(B6,'[1]2.5消防工程 '!$B$4:$I$276,8,0) -> 4341.39 | J6: =VLOOKUP(B6,'[1]2.5消防工程 '!$B$4:$J$276,9,0) -> 3.83 | K6: =VLOOKUP(B6,'[1]2.5消防工程 '!$B$4:$K$276,10,0) -> 376.31 | L6: =$L$4 -> 0.207 | M6: =F6*G6 -> 0
A7: 4 | B7: 感烟火灾探测器 | C7: 1.名称:感烟火灾探测器 2.规格:与原有系统匹配 3.线制:与原有系统匹配 | D7: 按设计图示数量计算 | E7: 个 | F7: 64 | G7: =(H7+I7+J7+K7)*(1+L7) -> 133.82009 | H7: =VLOOKUP(B7,'[1]2.5消防工程 '!$B$4:$H$276,7,0) -> 60.34 | I7: =VLOOKUP(B7,'[1]2.5消防工程 '!$B$4:$I$276,8,0) -> 40.31 | J7: =VLOOKUP(B7,'[1]2.5消防工程 '!$B$4:$J$276,9,0) -> 1.17 | K7: =VLOOKUP(B7,'[1]2.5消防工程 '!$B$4:$K$276,10,0) -> 9.05 | L7: =$L$4 -> 0.207 | M7: =F7*G7 -> 8564.4858
A8: 5 | B8: 感温火灾探测器 | C8: 1.名称:感温火灾探测器 2.规格:与原有系统匹配 3.线制:与原有系统匹配 | D8: 按设计图示数量计算 | E8: 个 | G8: =(H8+I8+J8+K8)*(1+L8) -> 143.65714 | H8: =VLOOKUP(B8,'[1]2.5消防工程 '!$B$4:$H$276,7,0) -> 62.34 | I8: =VLOOKUP(B8,'[1]2.5消防工程 '!$B$4:$I$276,8,0) -> 46.46 | J8: =VLOOKUP(B8,'[1]2.5消防工程 '!$B$4:$J$276,9,0) -> 1.17 | K8: =VLOOKUP(B8,'[1]2.5消防工程 '!$B$4:$K$276,10,0) -> 9.05 | L8: =$L$4 -> 0.207 | M8: =F8*G8 -> 0
A9: 6 | B9: 消火栓按钮 | C9: 1.名称:消火栓按钮 2.规格:与原有系统匹配 | D9: 按设计图示数量计算 | E9: 个 | F9: 4 | G9: =(H9+I9+J9+K9)*(1+L9) -> 89.59561 | H9: =VLOOKUP(B9,'[1]2.5消防工程 '!$B$4:$H$276,7,0) -> 26.39 | I9: =VLOOKUP(B9,'[1]2.5消防工程 '!$B$4:$I$276,8,0) -> 47.08 | J9: =VLOOKUP(B9,'[1]2.5消防工程 '!$B$4:$J$276,9,0) -> 0.38 | K9: =VLOOKUP(B9,'[1]2.5消防工程 '!$B$4:$K$276,10,0) -> 0.38 | L9: =$L$4 -> 0.207 | M9: =F9*G9 -> 358.38244
A10: 7 | B10: 声光报警器 | C10: 1.名称:声光报警器 2.规格:与原有系统匹配 | D10: 按设计图示数量计算 | E10: 个 | F10: 4 | G10: =(H10+I10+J10+K10)*(1+L10) -> 160.78447 | H10: =VLOOKUP(B10,'[1]2.5消防工程 '!$B$4:$H$276,7,0) -> 66.43 | I10: =VLOOKUP(B10,'[1]2.5消防工程 '!$B$4:$I$276,8,0) -> 65.38 | J10: =VLOOKUP(B10,'[1]2.5消防工程 '!$B$4:$J$276,9,0) -> 0.96 | K10: =VLOOKUP(B10,'[1]2.5消防工程 '!$B$4:$K$276,10,0) -> 0.44 | L10: =$L$4 -> 0.207 | M10: =F10*G10 -> 643.13788
A11: 8 | B11: 带电话插孔的手动报警按钮 | C11: 1.名称:带电话插孔的手动报警按钮 2.规格:与原有系统匹配 | D11: 按设计图示数量计算 | E11: 个 | F11: 8 | G11: =(H11+I11+J11+K11)*(1+L11) -> 86.60225 | H11: =VLOOKUP(B11,'[1]2.5消防工程 '!$B$4:$H$276,7,0) -> 26.39 | I11: =VLOOKUP(B11,'[1]2.5消防工程 '!$B$4:$I$276,8,0) -> 44.6 | J11: =VLOOKUP(B11,'[1]2.5消防工程 '!$B$4:$J$276,9,0) -> 0.38 | K11: =VLOOKUP(B11,'[1]2.5消防工程 '!$B$4:$K$276,10,0) -> 0.38 | L11: =$L$4 -> 0.207 | M11: =F11*G11 -> 692.818
A12: 9 | B12: 消防扬声器 | C12: 1.名称:消防扬声器 2.功率:与原有系统匹配 3.安装方式:壁装 | D12: 按设计图示数量计算 | E12: 个 | F12: 14 | G12: =(H12+I12+J12+K12)*(1+L12) -> 69.96979 | H12: =VLOOKUP(B12,'[1]2.5消防工程 '!$B$4:$H$276,7,0) -> 30.49 | I12: =VLOOKUP(B12,'[1]2.5消防工程 '!$B$4:$I$276,8,0) -> 24.78 | J12: =VLOOKUP(B12,'[1]2.5消防工程 '!$B$4:$J$276,9,0) -> 0.58 | K12: =VLOOKUP(B12,'[1]2.5消防工程 '!$B$4:$K$276,10,0) -> 2.12 | L12: =$L$4 -> 0.207 | M12: =F12*G12 -> 979.57706
A13: 10 | B13: 消防扬声器 | C13: 1.名称:消防扬声器 2.功率:与原有系统匹配 3.安装方式:吸顶安装 | D13: 按设计图示数量计算 | E13: 个 | G13: =(H13+I13+J13+K13)*(1+L13) -> 69.96979 | H13: =VLOOKUP(B13,'[1]2.5消防工程 '!$B$4:$H$276,7,0) -> 30.49 | I13: =VLOOKUP(B13,'[1]2.5消防工程 '!$B$4:$I$276,8,0) -> 24.78 | J13: =VLOOKUP(B13,'[1]2.5消防工程 '!$B$4:$J$276,9,0) -> 0.58 | K13: =VLOOKUP(B13,'[1]2.5消防工程 '!$B$4:$K$276,10,0) -> 2.12 | L13: =$L$4 -> 0.207 | M13: =F13*G13 -> 0
A14: 11 | B14: 短路隔离模块 | C14: 1.名称:短路隔离模块 2.类型:与原有系统匹配 | D14: 按设计图示数量计算 | E14: 个 | G14: =(H14+I14+J14+K14)*(1+L14) -> 200.18095 | H14: =VLOOKUP(B14,'[1]2.5消防工程 '!$B$4:$H$276,7,0) -> 126.75 | I14: =VLOOKUP(B14,'[1]2.5消防工程 '!$B$4:$I$276,8,0) -> 37.17 | J14: =VLOOKUP(B14,'[1]2.5消防工程 '!$B$4:$J$276,9,0) -> 1.23 | K14: =VLOOKUP(B14,'[1]2.5消防工程 '!$B$4:$K$276,10,0) -> 0.7 | L14: =$L$4 -> 0.207 | M14: =F14*G14 -> 0
A15: 12 | B15: 输入模块 | C15: 1.名称:输入模块 2.类型:与原有系统匹配 | D15: 按设计图示数量计算 | E15: 个 | F15: 6 | G15: =(H15+I15+J15+K15)*(1+L15) -> 206.7591 | H15: =VLOOKUP(B15,'[1]2.5消防工程 '!$B$4:$H$276,7,0) -> 116.75 | I15: =VLOOKUP(B15,'[1]2.5消防工程 '!$B$4:$I$276,8,0) -> 52.65 | J15: =VLOOKUP(B15,'[1]2.5消防工程 '!$B$4:$J$276,9,0) -> 1.3 | K15: =VLOOKUP(B15,'[1]2.5消防工程 '!$B$4:$K$276,10,0) -> 0.6 | L15: =$L$4 -> 0.207 | M15: =F15*G15 -> 1240.5546
A16: 13 | B16: 输出模块 | C16: 1.名称:输出模块 2.类型:与原有系统匹配 | D16: 按设计图示数量计算 | E16: 个 | G16: =(H16+I16+J16+K16)*(1+L16) -> 215.2081 | H16: =VLOOKUP(B16,'[1]2.5消防工程 '!$B$4:$H$276,7,0) -> 116.75 | I16: =VLOOKUP(B16,'[1]2.5消防工程 '!$B$4:$I$276,8,0) -> 59.65 | J16: =VLOOKUP(B16,'[1]2.5消防工程 '!$B$4:$J$276,9,0) -> 1.3 | K16: =VLOOKUP(B16,'[1]2.5消防工程 '!$B$4:$K$276,10,0) -> 0.6 | L16: =$L$4 -> 0.207 | M16: =F16*G16 -> 0
A17: 14 | B17: 输入输出模块 | C17: 1.名称:输入输出模块 2.类型:与原有系统匹配 | D17: 按设计图示数量计算 | E17: 个 | F17: 7 | G17: =(H17+I17+J17+K17)*(1+L17) -> 283.54844 | H17: =VLOOKUP(B17,'[1]2.5消防工程 '!$B$4:$H$276,7,0) -> 116.75 | I17: =VLOOKUP(B17,'[1]2.5消防工程 '!$B$4:$I$276,8,0) -> 115.75 | J17: =VLOOKUP(B17,'[1]2.5消防工程 '!$B$4:$J$276,9,0) -> 1.5 | K17: =VLOOKUP(B17,'[1]2.5消防工程 '!$B$4:$K$276,10,0) -> 0.92 | L17: =$L$4 -> 0.207 | M17: =F17*G17 -> 1984.8391
A18: 15 | B18: 火灾显示盘 | C18: 1.总线制:火灾显示盘 2.安装方式:壁挂式 3.显示器类型:与原有系统匹配 | D18: 按设计图示数量计算 | E18: 台 | F18: 2 | G18: =(H18+I18+J18+K18)*(1+L18) -> 1346.9637 | H18: =VLOOKUP(B18,'[1]2.5消防工程 '!$B$4:$H$276,7,0) -> 604.24 | I18: =VLOOKUP(B18,'[1]2.5消防工程 '!$B$4:$I$276,8,0) -> 422.79 | J18: =VLOOKUP(B18,'[1]2.5消防工程 '!$B$4:$J$276,9,0) -> 2.92 | K18: =VLOOKUP(B18,'[1]2.5消防工程 '!$B$4:$K$276,10,0) -> 86.01 | L18: =$L$4 -> 0.207 | M18: =F18*G18 -> 2693.9274
A19: 16 | B19: 消防桥架100*50 | C19: 1.名称:消防桥架100*50 2.材质:钢制 3.接地方式:按规范要求 4.支吊架:含支吊架制作、安装 | D19: 按设计图示尺寸以长度计算 | E19: m | G19: =(H19+I19+J19+K19)*(1+L19) -> 57.79116 | H19: =VLOOKUP(B19,'[1]2.5消防工程 '!$B$4:$H$276,7,0) -> 18.57 | I19: =VLOOKUP(B19,'[1]2.5消防工程 '!$B$4:$I$276,8,0) -> 20.23 | J19: =VLOOKUP(B19,'[1]2.5消防工程 '!$B$4:$J$276,9,0) -> 8.56 | K19: =VLOOKUP(B19,'[1]2.5消防工程 '!$B$4:$K$276,10,0) -> 0.52 | L19: =$L$4 -> 0.207 | M19: =F19*G19 -> 0
A20: 17 | B20: 消防桥架100*100 | C20: 1.名称:消防桥架100*100 2.材质:钢制 3.接地方式:按规范要求 4.支吊架:含支吊架制作、安装 | D20: 按设计图示尺寸以长度计算 | E20: m | G20: =(H20+I20+J20+K20)*(1+L20) -> 69.46285 | H20: =VLOOKUP(B20,'[1]2.5消防工程 '!$B$4:$H$276,7,0) -> 18.57 | I20: =VLOOKUP(B20,'[1]2.5消防工程 '!$B$4:$I$276,8,0) -> 29.9 | J20: =VLOOKUP(B20,'[1]2.5消防工程 '!$B$4:$J$276,9,0) -> 8.56 | K20: =VLOOKUP(B20,'[1]2.5消防工程 '!$B$4:$K$276,10,0) -> 0.52 | L20: =$L$4 -> 0.207 | M20: =F20*G20 -> 0
A21: 18 | B21: 消防桥架150*100 | C21: 1.名称:消防桥架150*100 2.材质:钢制 3.接地方式:按规范要求 4.支吊架:含支吊架制作、安装 | D21: 按设计图示尺寸以长度计算 | E21: m | G21: =(H21+I21+J21+K21)*(1+L21) -> 81.32766 | H21: =VLOOKUP(B21,'[1]2.5消防工程 '!$B$4:$H$276,7,0) -> 18.57 | I21: =VLOOKUP(B21,'[1]2.5消防工程 '!$B$4:$I$276,8,0) -> 39.19 | J21: =VLOOKUP(B21,'[1]2.5消防工程 '!$B$4:$J$276,9,0) -> 8.61 | K21: =VLOOKUP(B21,'[1]2.5消防工程 '!$B$4:$K$276,10,0) -> 1.01 | L21: =$L$4 -> 0.207 | M21: =F21*G21 -> 0
A22: 19 | B22: 消防桥架200*100 | C22: 1.名称:消防桥架200*100 2.材质:钢制 3.接地方式:按规范要求 4.支吊架:含支吊架制作、安装 | D22: 按设计图示尺寸以长度计算 | E22: m | G22: =(H22+I22+J22+K22)*(1+L22) -> 95.20816 | H22: =VLOOKUP(B22,'[1]2.5消防工程 '!$B$4:$H$276,7,0) -> 18.57 | I22: =VLOOKUP(B22,'[1]2.5消防工程 '!$B$4:$I$276,8,0) -> 50.69 | J22: =VLOOKUP(B22,'[1]2.5消防工程 '!$B$4:$J$276,9,0) -> 8.61 | K22: =VLOOKUP(B22,'[1]2.5消防工程 '!$B$4:$K$276,10,0) -> 1.01 | L22: =$L$4 -> 0.207 | M22: =F22*G22 -> 0
A23: 20 | B23: 消防桥架200*150 | C23: 1.名称:消防桥架200*150 2.材质:钢制 3.接地方式:按规范要求 4.支吊架:含支吊架制作、安装 | D23: 按设计图示尺寸以长度计算 | E23: m | G23: =(H23+I23+J23+K23)*(1+L23) -> 105.46766 | H23: =VLOOKUP(B23,'[1]2.5消防工程 '!$B$4:$H$276,7,0) -> 18.57 | I23: =VLOOKUP(B23,'[1]2.5消防工程 '!$B$4:$I$276,8,0) -> 59.19 | J23: =VLOOKUP(B23,'[1]2.5消防工程 '!$B$4:$J$276,9,0) -> 8.61 | K23: =VLOOKUP(B23,'[1]2.5消防工程 '!$B$4:$K$276,10,0) -> 1.01 | L23: =$L$4 -> 0.207 | M23: =F23*G23 -> 0
A24: 21 | B24: 配管JDG20 | C24: 1.名称:配管JDG20 2.材质:镀锌薄钢管 3.规格:Φ20 4.配置形式:明配 5.接地要求:按规范要求 6.其他:含支、吊架制作安装 | D24: 按设计图示尺寸以长度计算 | E24: m | F24: 941.6 | G24: =(H24+I24+J24+K24)*(1+L24) -> 17.42908 | H24: 6.66 | I24: 6 | J24: 1.58 | K24: 0.2 | L24: =$L$4 -> 0.207 | M24: =F24*G24 -> 16411.222
A25: 22 | B25: 配管JDG20 | C25: 1.名称:配管JDG20 2.材质:镀锌薄钢管 3.规格Φ20 4.配置形式:暗配 5.接地要求:按规范要求 | D25: 按设计图示尺寸以长度计算 | E25: m | G25: =(H25+I25+J25+K25)*(1+L25) -> 17.35666 | H25: 7.74 | I25: 6 | J25: 0.44 | K25: 0.2 | L25: =$L$4 -> 0.207 | M25: =F25*G25 -> 0
A26: 23 | B26: 配管JDG25 | C26: 1.名称:配管JDG25 2.材质:镀锌薄钢管 3.规格:Φ25 4.配置形式:明配 5.接地要求:按规范要求 6.其他:含支、吊架制作安装 | D26: 按设计图示尺寸以长度计算 | E26: m | G26: =(H26+I26+J26+K26)*(1+L26) -> 19.92757 | H26: 6.66 | I26: 8.5 | J26: 1.15 | K26: 0.2 | L26: =$L$4 -> 0.207 | M26: =F26*G26 -> 0
A27: 24 | B27: 配管JDG25 | C27: 1.名称:配管JDG25 2.材质:镀锌薄钢管 3.规格Φ25 4.配置形式:暗配 5.接地要求:按规范要求 | D27: 按设计图示尺寸以长度计算 | E27: m | G27: =(H27+I27+J27+K27)*(1+L27) -> 19.0706 | H27: 6.66 | I27: 8.5 | J27: 0.44 | K27: 0.2 | L27: =$L$4 -> 0.207 | M27: =F27*G27 -> 0
A28: 25 | B28: 配线ZRNH-RVV-2*1.5 | C28: 1.名称:配线ZRNH-RVV-2*1.5 2.型号:ZRNH-RVV 3.规格:2*1.5 4.材质:铜芯 | D28: 按设计图示尺寸以长度计算 | E28: m | G28: =(H28+I28+J28+K28)*(1+L28) -> 7.47133 | H28: =VLOOKUP(B28,'[1]2.5消防工程 '!$B$4:$H$276,7,0) -> 1.73 | I28: =VLOOKUP(B28,'[1]2.5消防工程 '!$B$4:$I$276,8,0) -> 4.28 | J28: =VLOOKUP(B28,'[1]2.5消防工程 '!$B$4:$J$276,9,0) -> 0.18 | K28: =VLOOKUP(B28,'[1]2.5消防工程 '!$B$4:$K$276,10,0) -> 0 | L28: =$L$4 -> 0.207 | M28: =F28*G28 -> 0
A29: 26 | B29: 配线ZRNH-RVV-2*1.0 | C29: 1.名称:配线ZRNH-RVV-2*1.0 2.型号:ZRNH-RVV 3.规格:2*1.0 4.材质:铜芯 | D29: 按设计图示尺寸以长度计算 | E29: m | G29: =(H29+I29+J29+K29)*(1+L29) -> 6.17984 | H29: =VLOOKUP(B29,'[1]2.5消防工程 '!$B$4:$H$276,7,0) -> 1.73 | I29: =VLOOKUP(B29,'[1]2.5消防工程 '!$B$4:$I$276,8,0) -> 3.21 | J29: =VLOOKUP(B29,'[1]2.5消防工程 '!$B$4:$J$276,9,0) -> 0.18 | K29: =VLOOKUP(B29,'[1]2.5消防工程 '!$B$4:$K$276,10,0) -> 0 | L29: =$L$4 -> 0.207 | M29: =F29*G29 -> 0
A30: 27 | B30: 配线ZRNH-RVS-2*2.5 | C30: 1.名称:配线ZRNH-RVS-2*2.5 2.型号:ZRNH-RVS 3.规格:2*2.5 4.材质:铜芯 | D30: 按设计图示尺寸以长度计算 | E30: m | G30: =(H30+I30+J30+K30)*(1+L30) -> 9.80084 | H30: =VLOOKUP(B30,'[1]2.5消防工程 '!$B$4:$H$276,7,0) -> 1.73 | I30: =VLOOKUP(B30,'[1]2.5消防工程 '!$B$4:$I$276,8,0) -> 6.21 | J30: =VLOOKUP(B30,'[1]2.5消防工程 '!$B$4:$J$276,9,0) -> 0.18 | K30: =VLOOKUP(B30,'[1]2.5消防工程 '!$B$4:$K$276,10,0) -> 0 | L30: =$L$4 -> 0.207 | M30: =F30*G30 -> 0
A31: 28 | B31: 配线ZRNH-RVS-2*1.5 | C31: 1.名称:配线ZRNH-RVS-2*1.5 2.型号:ZRNH-RVS 3.规格:2*1.5 4.材质:铜芯 | D31: 按设计图示尺寸以长度计算 | E31: m | G31: =(H31+I31+J31+K31)*(1+L31) -> 6.89197 | H31: =VLOOKUP(B31,'[1]2.5消防工程 '!$B$4:$H$276,7,0) -> 1.73 | I31: =VLOOKUP(B31,'[1]2.5消防工程 '!$B$4:$I$276,8,0) -> 3.8 | J31: =VLOOKUP(B31,'[1]2.5消防工程 '!$B$4:$J$276,9,0) -> 0.18 | K31: =VLOOKUP(B31,'[1]2.5消防工程 '!$B$4:$K$276,10,0) -> 0 | L31: =$L$4 -> 0.207 | M31: =F31*G31 -> 0
A32: 29 | B32: 配线ZRNH-RVS-2*1.0 | C32: 1.名称:配线ZRNH-RVS-2*1.0 2.型号:ZRNH-RVS 3.规格:2*1.0 4.材质:铜芯 | D32: 按设计图示尺寸以长度计算 | E32: m | G32: =(H32+I32+J32+K32)*(1+L32) -> 5.61255 | H32: =VLOOKUP(B32,'[1]2.5消防工程 '!$B$4:$H$276,7,0) -> 1.73 | I32: =VLOOKUP(B32,'[1]2.5消防工程 '!$B$4:$I$276,8,0) -> 2.74 | J32: =VLOOKUP(B32,'[1]2.5消防工程 '!$B$4:$J$276,9,0) -> 0.18 | K32: =VLOOKUP(B32,'[1]2.5消防工程 '!$B$4:$K$276,10,0) -> 0 | L32: =$L$4 -> 0.207 | M32: =F32*G32 -> 0
A33: 30 | B33: 配线ZRNH-RVVP-2*1.5 | C33: 1.名称:配线ZRNH-RVVP-2*1.5 2.型号:ZRNH-RVVP 3.规格:2*1.5 4.材质:铜芯 | D33: 按设计图示尺寸以长度计算 | E33: m | F33: 941.6 | G33: =(H33+I33+J33+K33)*(1+L33) -> 10.09052 | H33: =VLOOKUP(B33,'[1]2.5消防工程 '!$B$4:$H$276,7,0) -> 1.73 | I33: =VLOOKUP(B33,'[1]2.5消防工程 '!$B$4:$I$276,8,0) -> 6.45 | J33: =VLOOKUP(B33,'[1]2.5消防工程 '!$B$4:$J$276,9,0) -> 0.18 | K33: =VLOOKUP(B33,'[1]2.5消防工程 '!$B$4:$K$276,10,0) -> 0 | L33: =$L$4 -> 0.207 | M33: =F33*G33 -> 9501.2336
A34: 31 | B34: 配线ZRNH-RVVP-2*1.0 | C34: 1.名称:配线ZRNH-RVVP-2*1.0 2.型号:ZRNH-RVVP 3.规格:2*1.0 4.材质:铜芯 | D34: 按设计图示尺寸以长度计算 | E34: m | G34: =(H34+I34+J34+K34)*(1+L34) -> 8.61798 | H34: =VLOOKUP(B34,'[1]2.5消防工程 '!$B$4:$H$276,7,0) -> 1.73 | I34: =VLOOKUP(B34,'[1]2.5消防工程 '!$B$4:$I$276,8,0) -> 5.23 | J34: =VLOOKUP(B34,'[1]2.5消防工程 '!$B$4:$J$276,9,0) -> 0.18 | K34: =VLOOKUP(B34,'[1]2.5消防工程 '!$B$4:$K$276,10,0) -> 0 | L34: =$L$4 -> 0.207 | M34: =F34*G34 -> 0
A35: 32 | B35: 配线ZRNH-BV-2.5 | C35: 1.名称:配线ZRNH-BV-2.5 2.型号:ZRNH-BV 3.规格:2.5 4.材质:铜芯 | D35: 按设计图示尺寸以长度计算 | E35: m | F35: 1519.1 | G35: =(H35+I35+J35+K35)*(1+L35) -> 5.32287 | H35: =VLOOKUP(B35,'[1]2.5消防工程 '!$B$4:$H$276,7,0) -> 1.43 | I35: =VLOOKUP(B35,'[1]2.5消防工程 '!$B$4:$I$276,8,0) -> 2.81 | J35: =VLOOKUP(B35,'[1]2.5消防工程 '!$B$4:$J$276,9,0) -> 0.17 | K35: =VLOOKUP(B35,'[1]2.5消防工程 '!$B$4:$K$276,10,0) -> 0 | L35: =$L$4 -> 0.207 | M35: =F35*G35 -> 8085.9718
A36: 33 | B36: 配线ZRNH-BV-4 | C36: 1.名称:配线ZRNH-BV-4 2.型号:ZRNH-BV 3.规格:4 4.材质:铜芯 | D36: 按设计图示尺寸以长度计算 | E36: m | G36: =(H36+I36+J36+K36)*(1+L36) -> 7.30235 | H36: =VLOOKUP(B36,'[1]2.5消防工程 '!$B$4:$H$276,7,0) -> 1.64 | I36: =VLOOKUP(B36,'[1]2.5消防工程 '!$B$4:$I$276,8,0) -> 4.21 | J36: =VLOOKUP(B36,'[1]2.5消防工程 '!$B$4:$J$276,9,0) -> 0.2 | K36: =VLOOKUP(B36,'[1]2.5消防工程 '!$B$4:$K$276,10,0) -> 0 | L36: =$L$4 -> 0.207 | M36: =F36*G36 -> 0
A37: 34 | B37: 配线WDZBN-BYJ-1.5 | C37: 1.名称:配线WDZBN-BYJ-1.5 2.型号:WDZBN-BYJ 3.规格:1.5 4.材质:铜芯 5.配线部位:管内、线槽内敷设 | D37: 按设计图示尺寸以单线长度计算（含预留长度） | E37: m | G37: =(H37+I37+J37+K37)*(1+L37) -> 7.66445 | H37: 3.54 | I37: 2.63 | J37: 0.18 | K37: 0 | L37: =$L$4 -> 0.207 | M37: =F37*G37 -> 0
A38: 35 | B38: 配线WDZBN-BYJ-1.5 | C38: 1.名称:配线WDZBN-BYJ-1.5 2.型号:WDZBN-BYJ 3.规格:1.5 4.材质:铜芯 5.配线部位:管内、线槽内敷设 | D38: 按设计图示尺寸以单线长度计算（含预留长度） | E38: m | G38: =(H38+I38+J38+K38)*(1+L38) -> 7.66445 | H38: 3.54 | I38: 2.63 | J38: 0.18 | K38: 0 | L38: =$L$4 -> 0.207 | M38: =F38*G38 -> 0
A39: 36 | B39: WDZBN-RYJS-2x1.5 | C39: 1.名称:配线WDZBN-RYJS-2x1.5 2.型号:WDZBN-RYJS 3.规格:1.5 4.材质:铜芯 5.配线部位:管内、线槽内敷设 | D39: 按设计图示尺寸以单线长度计算（含预留长度） | E39: m | G39: =(H39+I39+J39+K39)*(1+L39) -> 9.11285 | H39: 4.28 | I39: 3.09 | J39: 0.18 | K39: 0 | L39: =$L$4 -> 0.207 | M39: =F39*G39 -> 0
A40: 37 | B40: WDZBN-RYJSP-2x1.5 | C40: 1.名称:配线WDZBN-RYJSP-2x1.5 2.型号:WDZBN-RYJSP 3.规格:1.5 4.材质:铜芯 5.配线部位:管内、线槽内敷设 | D40: 按设计图示尺寸以单线长度计算（含预留长度） | E40: m | G40: =(H40+I40+J40+K40)*(1+L40) -> 9.11285 | H40: 4.28 | I40: 3.09 | J40: 0.18 | K40: 0 | L40: =$L$4 -> 0.207 | M40: =F40*G40 -> 0
A41: 38 | B41: 接线盒 | C41: 1.名称:接线盒 2.材质:铁质 3.安装形式:明装 | D41: 按设计图示数量计算 | E41: 个 | F41: 93 | G41: =(H41+I41+J41+K41)*(1+L41) -> 9.34218 | H41: =VLOOKUP(B41,'[1]2.5消防工程 '!$B$4:$H$276,7,0) -> 5.51 | I41: =VLOOKUP(B41,'[1]2.5消防工程 '!$B$4:$I$276,8,0) -> 1.81 | J41: =VLOOKUP(B41,'[1]2.5消防工程 '!$B$4:$J$276,9,0) -> 0.42 | K41: =VLOOKUP(B41,'[1]2.5消防工程 '!$B$4:$K$276,10,0) -> 0 | L41: =$L$4 -> 0.207 | M41: =F41*G41 -> 868.82274
A42: 39 | B42: 接线盒 | C42: 1.名称:接线盒 2.材质:铁质 3.安装形式:暗装 | D42: 按设计图示数量计算 | E42: 个 | G42: =(H42+I42+J42+K42)*(1+L42) -> 9.34218 | H42: =VLOOKUP(B42,'[1]2.5消防工程 '!$B$4:$H$276,7,0) -> 5.51 | I42: =VLOOKUP(B42,'[1]2.5消防工程 '!$B$4:$I$276,8,0) -> 1.81 | J42: =VLOOKUP(B42,'[1]2.5消防工程 '!$B$4:$J$276,9,0) -> 0.42 | K42: =VLOOKUP(B42,'[1]2.5消防工程 '!$B$4:$K$276,10,0) -> 0 | L42: =$L$4 -> 0.207 | M42: =F42*G42 -> 0
A43: 二 | B43: 自动火灾报警系统（主材利旧、含保护性拆除）
A44: 1 | B44: 消防端子箱（主材利旧） | C44: 1.名称:消防端子箱 2.规格:与原有系统匹配 | D44: 按设计图示数量计算 | E44: 台 | G44: =(H44+I44+J44+K44)*(1+L44) -> 128.99209 | H44: =VLOOKUP(B44,'[1]2.5消防工程 '!$B$4:$H$276,7,0) -> 73.71 | I44: =VLOOKUP(B44,'[1]2.5消防工程 '!$B$4:$I$276,8,0) -> 0 | J44: =VLOOKUP(B44,'[1]2.5消防工程 '!$B$4:$J$276,9,0) -> 4.43 | K44: =VLOOKUP(B44,'[1]2.5消防工程 '!$B$4:$K$276,10,0) -> 28.73 | L44: =$L$4 -> 0.207 | M44: =F44*G44 -> 0
A45: 2 | B45: 感烟火灾探测器（主材利旧） | C45: 1.名称:感烟火灾探测器 2.规格:与原有系统匹配 3.线制:与原有系统匹配 | D45: 按设计图示数量计算 | E45: 个 | G45: =(H45+I45+J45+K45)*(1+L45) -> 87.57992 | H45: =VLOOKUP(B45,'[1]2.5消防工程 '!$B$4:$H$276,7,0) -> 62.34 | I45: =VLOOKUP(B45,'[1]2.5消防工程 '!$B$4:$I$276,8,0) -> 0 | J45: =VLOOKUP(B45,'[1]2.5消防工程 '!$B$4:$J$276,9,0) -> 1.17 | K45: =VLOOKUP(B45,'[1]2.5消防工程 '!$B$4:$K$276,10,0) -> 9.05 | L45: =$L$4 -> 0.207 | M45: =F45*G45 -> 0
A46: 3 | B46: 感温火灾探测器（主材利旧） | C46: 1.名称:感温火灾探测器 2.规格:与原有系统匹配 3.线制:与原有系统匹配 | D46: 按设计图示数量计算 | E46: 个 | G46: =(H46+I46+J46+K46)*(1+L46) -> 87.57992 | H46: =VLOOKUP(B46,'[1]2.5消防工程 '!$B$4:$H$276,7,0) -> 62.34 | I46: =VLOOKUP(B46,'[1]2.5消防工程 '!$B$4:$I$276,8,0) -> 0 | J46: =VLOOKUP(B46,'[1]2.5消防工程 '!$B$4:$J$276,9,0) -> 1.17 | K46: =VLOOKUP(B46,'[1]2.5消防工程 '!$B$4:$K$276,10,0) -> 9.05 | L46: =$L$4 -> 0.207 | M46: =F46*G46 -> 0
A47: 4 | B47: 消火栓按钮（主材利旧） | C47: 1.名称:消火栓按钮 2.规格:与原有系统匹配 | D47: 按设计图示数量计算 | E47: 个 | G47: =(H47+I47+J47+K47)*(1+L47) -> 32.77005 | H47: =VLOOKUP(B47,'[1]2.5消防工程 '!$B$4:$H$276,7,0) -> 26.39 | I47: =VLOOKUP(B47,'[1]2.5消防工程 '!$B$4:$I$276,8,0) -> 0 | J47: =VLOOKUP(B47,'[1]2.5消防工程 '!$B$4:$J$276,9,0) -> 0.38 | K47: =VLOOKUP(B47,'[1]2.5消防工程 '!$B$4:$K$276,10,0) -> 0.38 | L47: =$L$4 -> 0.207 | M47: =F47*G47 -> 0
A48: 5 | B48: 声光报警器（主材利旧） | C48: 1.名称:声光报警器 2.规格:与原有系统匹配 | D48: 按设计图示数量计算 | E48: 个 | G48: =(H48+I48+J48+K48)*(1+L48) -> 105.4918 | H48: =VLOOKUP(B48,'[1]2.5消防工程 '!$B$4:$H$276,7,0) -> 86 | I48: =VLOOKUP(B48,'[1]2.5消防工程 '!$B$4:$I$276,8,0) -> 0 | J48: =VLOOKUP(B48,'[1]2.5消防工程 '!$B$4:$J$276,9,0) -> 0.96 | K48: =VLOOKUP(B48,'[1]2.5消防工程 '!$B$4:$K$276,10,0) -> 0.44 | L48: =$L$4 -> 0.207 | M48: =F48*G48 -> 0
A49: 6 | B49: 带电话插孔的手动报警按钮（主材利旧） | C49: 1.名称:带电话插孔的手动报警按钮 2.规格:与原有系统匹配 | D49: 按设计图示数量计算 | E49: 个 | G49: =(H49+I49+J49+K49)*(1+L49) -> 32.77005 | H49: =VLOOKUP(B49,'[1]2.5消防工程 '!$B$4:$H$276,7,0) -> 26.39 | I49: =VLOOKUP(B49,'[1]2.5消防工程 '!$B$4:$I$276,8,0) -> 0 | J49: =VLOOKUP(B49,'[1]2.5消防工程 '!$B$4:$J$276,9,0) -> 0.38 | K49: =VLOOKUP(B49,'[1]2.5消防工程 '!$B$4:$K$276,10,0) -> 0.38 | L49: =$L$4 -> 0.207 | M49: =F49*G49 -> 0
A50: 7 | B50: 消防扬声器（主材利旧） | C50: 1.名称:消防扬声器 2.功率:与原有系统匹配 3.安装方式:壁装 | D50: 按设计图示数量计算 | E50: 个 | G50: =(H50+I50+J50+K50)*(1+L50) -> 40.06033 | H50: =VLOOKUP(B50,'[1]2.5消防工程 '!$B$4:$H$276,7,0) -> 30.49 | I50: =VLOOKUP(B50,'[1]2.5消防工程 '!$B$4:$I$276,8,0) -> 0 | J50: =VLOOKUP(B50,'[1]2.5消防工程 '!$B$4:$J$276,9,0) -> 0.58 | K50: =VLOOKUP(B50,'[1]2.5消防工程 '!$B$4:$K$276,10,0) -> 2.12 | L50: =$L$4 -> 0.207 | M50: =F50*G50 -> 0
A51: 8 | B51: 消防扬声器（主材利旧） | C51: 1.名称:消防扬声器 2.功率:与原有系统匹配 3.安装方式:吸顶安装 | D51: 按设计图示数量计算 | E51: 个 | G51: =(H51+I51+J51+K51)*(1+L51) -> 40.06033 | H51: =VLOOKUP(B51,'[1]2.5消防工程 '!$B$4:$H$276,7,0) -> 30.49 | I51: =VLOOKUP(B51,'[1]2.5消防工程 '!$B$4:$I$276,8,0) -> 0 | J51: =VLOOKUP(B51,'[1]2.5消防工程 '!$B$4:$J$276,9,0) -> 0.58 | K51: =VLOOKUP(B51,'[1]2.5消防工程 '!$B$4:$K$276,10,0) -> 2.12 | L51: =$L$4 -> 0.207 | M51: =F51*G51 -> 0
A52: 9 | B52: 短路隔离模块（主材利旧） | C52: 1.名称:短路隔离模块 2.类型:与原有系统匹配 | D52: 按设计图示数量计算 | E52: 个 | G52: =(H52+I52+J52+K52)*(1+L52) -> 123.93476 | H52: =VLOOKUP(B52,'[1]2.5消防工程 '!$B$4:$H$276,7,0) -> 100.75 | I52: =VLOOKUP(B52,'[1]2.5消防工程 '!$B$4:$I$276,8,0) -> 0 | J52: =VLOOKUP(B52,'[1]2.5消防工程 '!$B$4:$J$276,9,0) -> 1.23 | K52: =VLOOKUP(B52,'[1]2.5消防工程 '!$B$4:$K$276,10,0) -> 0.7 | L52: =$L$4 -> 0.207 | M52: =F52*G52 -> 0
A53: 10 | B53: 输入模块（主材利旧） | C53: 1.名称:输入模块 2.类型:与原有系统匹配 | D53: 按设计图示数量计算 | E53: 个 | G53: =(H53+I53+J53+K53)*(1+L53) -> 141.41212 | H53: =VLOOKUP(B53,'[1]2.5消防工程 '!$B$4:$H$276,7,0) -> 115.26 | I53: =VLOOKUP(B53,'[1]2.5消防工程 '!$B$4:$I$276,8,0) -> 0 | J53: =VLOOKUP(B53,'[1]2.5消防工程 '!$B$4:$J$276,9,0) -> 1.3 | K53: =VLOOKUP(B53,'[1]2.5消防工程 '!$B$4:$K$276,10,0) -> 0.6 | L53: =$L$4 -> 0.207 | M53: =F53*G53 -> 0
A54: 11 | B54: 输出模块（主材利旧） | C54: 1.名称:输出模块 2.类型:与原有系统匹配 | D54: 按设计图示数量计算 | E54: 个 | G54: =(H54+I54+J54+K54)*(1+L54) -> 138.99812 | H54: =VLOOKUP(B54,'[1]2.5消防工程 '!$B$4:$H$276,7,0) -> 113.26 | I54: =VLOOKUP(B54,'[1]2.5消防工程 '!$B$4:$I$276,8,0) -> 0 | J54: =VLOOKUP(B54,'[1]2.5消防工程 '!$B$4:$J$276,9,0) -> 1.3 | K54: =VLOOKUP(B54,'[1]2.5消防工程 '!$B$4:$K$276,10,0) -> 0.6 | L54: =$L$4 -> 0.207 | M54: =F54*G54 -> 0
A55: 12 | B55: 输入输出模块（主材利旧） | C55: 1.名称:输入输出模块 2.类型:与原有系统匹配 | D55: 按设计图示数量计算 | E55: 个 | G55: =(H55+I55+J55+K55)*(1+L55) -> 147.8575 | H55: =VLOOKUP(B55,'[1]2.5消防工程 '!$B$4:$H$276,7,0) -> 120.08 | I55: =VLOOKUP(B55,'[1]2.5消防工程 '!$B$4:$I$276,8,0) -> 0 | J55: =VLOOKUP(B55,'[1]2.5消防工程 '!$B$4:$J$276,9,0) -> 1.5 | K55: =VLOOKUP(B55,'[1]2.5消防工程 '!$B$4:$K$276,10,0) -> 0.92 | L55: =$L$4 -> 0.207 | M55: =F55*G55 -> 0
... A62: 19 | B62: 支吊架（主材利旧） | C62: 1.名称:支吊架 2.材质:铁构件 3.其它:包含制作、安装、除锈、刷漆防腐 | D62: 按设计图示尺寸以质量计算 | E62: kg | G62: =(H62+I62+J62+K62)*(1+L62) -> 14.70126 | H62: =VLOOKUP(B62,'[1]2.5消防工程 '!$B$4:$H$276,7,0) -> 10.1 | I62: =VLOOKUP(B62,'[1]2.5消防工程 '!$B$4:$I$276,8,0) -> 0 | J62: =VLOOKUP(B62,'[1]2.5消防工程 '!$B$4:$J$276,9,0) -> 1.1 | K62: =VLOOKUP(B62,'[1]2.5消防工程 '!$B$4:$K$276,10,0) -> 0.98 | L62: =$L$4 -> 0.207 | M62: =F62*G62 -> 0
A63: 三 | B63: 消防水系统
A64: 1 | B64: 内外壁热镀锌钢管DN25 | C64: 1.安装部位:室内 2.材质、规格:内外壁热镀锌钢管DN25 3.连接形式:螺纹连接 4.压力试验及冲洗设计要求:按设计及规范要求 5.管道标识设计要求:按设计及规范要求 6.管道支架：按设计及规范要求 | D64: 按设计图示管道中心线以长度计算 | E64: m | F64: 495.55 | G64: =(H64+I64+J64+K64)*(1+L64) -> 60.74831 | H64: =VLOOKUP(B64,'[1]2.5消防工程 '!$B$4:$H$276,7,0) -> 35.08 | I64: =VLOOKUP(B64,'[1]2.5消防工程 '!$B$4:$I$276,8,0) -> 14.26 | J64: =VLOOKUP(B64,'[1]2.5消防工程 '!$B$4:$J$276,9,0) -> 0.44 | K64: =VLOOKUP(B64,'[1]2.5消防工程 '!$B$4:$K$276,10,0) -> 0.55 | L64: =$L$4 -> 0.207 | M64: =F64*G64 -> 30103.825
A65: 2 | B65: 内外壁热镀锌钢管DN32 | C65: 1.安装部位:室内 2.材质、规格:内外壁热镀锌钢管DN32 3.连接形式:螺纹连接 4.压力试验及冲洗设计要求:按设计及规范要求 5.管道标识设计要求:按设计及规范要求 6.管道支架：按设计及规范要求 | D65: 按设计图示管道中心线以长度计算 | E65: m | F65: 235.69 | G65: =(H65+I65+J65+K65)*(1+L65) -> 66.8678 | H65: =VLOOKUP(B65,'[1]2.5消防工程 '!$B$4:$H$276,7,0) -> 33.68 | I65: =VLOOKUP(B65,'[1]2.5消防工程 '!$B$4:$I$276,8,0) -> 20.14 | J65: =VLOOKUP(B65,'[1]2.5消防工程 '!$B$4:$J$276,9,0) -> 0.81 | K65: =VLOOKUP(B65,'[1]2.5消防工程 '!$B$4:$K$276,10,0) -> 0.77 | L65: =$L$4 -> 0.207 | M65: =F65*G65 -> 15760.072
A66: 3 | B66: 内外壁热镀锌钢管DN40 | C66: 1.安装部位:室内 2.材质、规格:内外壁热镀锌钢管DN40 3.连接形式:螺纹连接 4.压力试验及冲洗设计要求:按设计及规范要求 5.管道标识设计要求:按设计及规范要求 6.管道支架：按设计及规范要求 | D66: 按设计图示管道中心线以长度计算 | E66: m | F66: 64.16 | G66: =(H66+I66+J66+K66)*(1+L66) -> 83.4037 | H66: =VLOOKUP(B66,'[1]2.5消防工程 '!$B$4:$H$276,7,0) -> 42.14 | I66: =VLOOKUP(B66,'[1]2.5消防工程 '!$B$4:$I$276,8,0) -> 25.26 | J66: =VLOOKUP(B66,'[1]2.5消防工程 '!$B$4:$J$276,9,0) -> 0.86 | K66: =VLOOKUP(B66,'[1]2.5消防工程 '!$B$4:$K$276,10,0) -> 0.84 | L66: =$L$4 -> 0.207 | M66: =F66*G66 -> 5351.1814
A67: 4 | B67: 内外壁热镀锌钢管DN50 | C67: 1.安装部位:室内 2.材质、规格:内外壁热镀锌钢管DN50 3.连接形式:螺纹连接 4.压力试验及冲洗设计要求:按设计及规范要求 5.管道标识设计要求:按设计及规范要求 6.管道支架：按设计及规范要求 | D67: 按设计图示管道中心线以长度计算 | E67: m | F67: 77.31 | G67: =(H67+I67+J67+K67)*(1+L67) -> 94.21842 | H67: =VLOOKUP(B67,'[1]2.5消防工程 '!$B$4:$H$276,7,0) -> 41.96 | I67: =VLOOKUP(B67,'[1]2.5消防工程 '!$B$4:$I$276,8,0) -> 34.35 | J67: =VLOOKUP(B67,'[1]2.5消防工程 '!$B$4:$J$276,9,0) -> 0.87 | K67: =VLOOKUP(B67,'[1]2.5消防工程 '!$B$4:$K$276,10,0) -> 0.88 | L67: =$L$4 -> 0.207 | M67: =F67*G67 -> 7284.0261
A68: 5 | B68: 内外壁热镀锌钢管DN65 | C68: 1.安装部位:室内 2.材质、规格:内外壁热镀锌钢管DN65 3.连接形式:沟槽式连接 4.压力试验及冲洗设计要求:按设计及规范要求 5.管道标识设计要求:按设计及规范要求 6.管道支架：按设计及规范要求 | D68: 按设计图示管道中心线以长度计算 | E68: m | F68: 29.32 | G68: =(H68+I68+J68+K68)*(1+L68) -> 100.36205 | H68: =VLOOKUP(B68,'[1]2.5消防工程 '!$B$4:$H$276,7,0) -> 43.34 | I68: =VLOOKUP(B68,'[1]2.5消防工程 '!$B$4:$I$276,8,0) -> 38.26 | J68: =VLOOKUP(B68,'[1]2.5消防工程 '!$B$4:$J$276,9,0) -> 1.14 | K68: =VLOOKUP(B68,'[1]2.5消防工程 '!$B$4:$K$276,10,0) -> 0.41 | L68: =$L$4 -> 0.207 | M68: =F68*G68 -> 2942.6153
A69: 6 | B69: 内外壁热镀锌钢管DN80 | C69: 1.安装部位:室内 2.材质、规格:内外壁热镀锌钢管DN80 3.连接形式:沟槽式连接 4.压力试验及冲洗设计要求:按设计及规范要求 5.管道标识设计要求:按设计及规范要求 6.管道支架：按设计及规范要求 | D69: 按设计图示管道中心线以长度计算 | E69: m | F69: 65.55 | G69: =(H69+I69+J69+K69)*(1+L69) -> 118.27393 | H69: =VLOOKUP(B69,'[1]2.5消防工程 '!$B$4:$H$276,7,0) -> 47.78 | I69: =VLOOKUP(B69,'[1]2.5消防工程 '!$B$4:$I$276,8,0) -> 48.61 | J69: =VLOOKUP(B69,'[1]2.5消防工程 '!$B$4:$J$276,9,0) -> 1.16 | K69: =VLOOKUP(B69,'[1]2.5消防工程 '!$B$4:$K$276,10,0) -> 0.44 | L69: =$L$4 -> 0.207 | M69: =F69*G69 -> 7752.8561
A70: 7 | B70: 内外壁热镀锌钢管DN100 | C70: 1.安装部位:室内 2.材质、规格:内外壁热镀锌钢管DN100 3.连接形式:沟槽式连接 4.压力试验及冲洗设计要求:按设计及规范要求 5.管道标识设计要求:按设计及规范要求 6.管道支架：按设计及规范要求 | D70: 按设计图示管道中心线以长度计算 | E70: m | F70: 4.28 | G70: =(H70+I70+J70+K70)*(1+L70) -> 141.67766 | H70: =VLOOKUP(B70,'[1]2.5消防工程 '!$B$4:$H$276,7,0) -> 51.39 | I70: =VLOOKUP(B70,'[1]2.5消防工程 '!$B$4:$I$276,8,0) -> 64.25 | J70: =VLOOKUP(B70,'[1]2.5消防工程 '!$B$4:$J$276,9,0) -> 1.19 | K70: =VLOOKUP(B70,'[1]2.5消防工程 '!$B$4:$K$276,10,0) -> 0.55 | L70: =$L$4 -> 0.207 | M70: =F70*G70 -> 606.38038
A71: 8 | B71: 内外壁热镀锌钢管DN150 | C71: 1.安装部位:室内 2.材质、规格:内外壁热镀锌钢管DN150 3.连接形式:沟槽式连接 4.压力试验及冲洗设计要求:按设计及规范要求 5.管道标识设计要求:按设计及规范要求 6.管道支架：按设计及规范要求 | D71: 按设计图示管道中心线以长度计算 | E71: m | F71: 47.1 | G71: =(H71+I71+J71+K71)*(1+L71) -> 205.68487 | H71: =VLOOKUP(B71,'[1]2.5消防工程 '!$B$4:$H$276,7,0) -> 63.7 | I71: =VLOOKUP(B71,'[1]2.5消防工程 '!$B$4:$I$276,8,0) -> 103.08 | J71: =VLOOKUP(B71,'[1]2.5消防工程 '!$B$4:$J$276,9,0) -> 2.67 | K71: =VLOOKUP(B71,'[1]2.5消防工程 '!$B$4:$K$276,10,0) -> 0.96 | L71: =$L$4 -> 0.207 | M71: =F71*G71 -> 9687.7574
A72: 9 | B72: 抗震支架-一根管 | C72: 1.材质:钢制 2.除锈及刷漆:按设计及规范要求 3.其他:按设计及规范要求 | D72: 按设计图示数量计算 | E72: 套 | G72: =(H72+I72+J72+K72)*(1+L72) -> 264.97271 | H72: =VLOOKUP(B72,'[1]2.5消防工程 '!$B$4:$H$276,7,0) -> 98.34 | I72: =VLOOKUP(B72,'[1]2.5消防工程 '!$B$4:$I$276,8,0) -> 69.69 | J72: =VLOOKUP(B72,'[1]2.5消防工程 '!$B$4:$J$276,9,0) -> 11.25 | K72: =VLOOKUP(B72,'[1]2.5消防工程 '!$B$4:$K$276,10,0) -> 40.25 | L72: =$L$4 -> 0.207 | M72: =F72*G72 -> 0
A73: 10 | B73: 抗震支架-二根管 | C73: 1.材质:抗震支架 2.其他:按设计及规范要求 | D73: 按设计图示数量计算 | E73: 套 | G73: =(H73+I73+J73+K73)*(1+L73) -> 317.98415 | H73: =VLOOKUP(B73,'[1]2.5消防工程 '!$B$4:$H$276,7,0) -> 118.01 | I73: =VLOOKUP(B73,'[1]2.5消防工程 '!$B$4:$I$276,8,0) -> 83.63 | J73: =VLOOKUP(B73,'[1]2.5消防工程 '!$B$4:$J$276,9,0) -> 13.5 | K73: =VLOOKUP(B73,'[1]2.5消防工程 '!$B$4:$K$276,10,0) -> 48.31 | L73: =$L$4 -> 0.207 | M73: =F73*G73 -> 0
A74: 11 | B74: 抗震支架-三根管 | C74: 1.材质:抗震支架 2.其他:按设计及规范要求 | D74: 按设计图示数量计算 | E74: 套 | G74: =(H74+I74+J74+K74)*(1+L74) -> 370.94731 | H74: =VLOOKUP(B74,'[1]2.5消防工程 '!$B$4:$H$276,7,0) -> 137.67 | I74: =VLOOKUP(B74,'[1]2.5消防工程 '!$B$4:$I$276,8,0) -> 97.56 | J74: =VLOOKUP(B74,'[1]2.5消防工程 '!$B$4:$J$276,9,0) -> 15.75 | K74: =VLOOKUP(B74,'[1]2.5消防工程 '!$B$4:$K$276,10,0) -> 56.35 | L74: =$L$4 -> 0.207 | M74: =F74*G74 -> 0
A75: 12 | B75: 抗震支架-四根管 | C75: 1.材质:抗震支架 2.其他:按设计及规范要求 | D75: 按设计图示数量计算 | E75: 套 | G75: =(H75+I75+J75+K75)*(1+L75) -> 423.95875 | H75: =VLOOKUP(B75,'[1]2.5消防工程 '!$B$4:$H$276,7,0) -> 157.34 | I75: =VLOOKUP(B75,'[1]2.5消防工程 '!$B$4:$I$276,8,0) -> 111.5 | J75: =VLOOKUP(B75,'[1]2.5消防工程 '!$B$4:$J$276,9,0) -> 18 | K75: =VLOOKUP(B75,'[1]2.5消防工程 '!$B$4:$K$276,10,0) -> 64.41 | L75: =$L$4 -> 0.207 | M75: =F75*G75 -> 0
A76: 13 | B76: 抗震支架-五根管 | C76: 1.材质:抗震支架 2.其他:按设计及规范要求 | D76: 按设计图示数量计算 | E76: 套 | G76: =(H76+I76+J76+K76)*(1+L76) -> 476.94605 | H76: =VLOOKUP(B76,'[1]2.5消防工程 '!$B$4:$H$276,7,0) -> 177.01 | I76: =VLOOKUP(B76,'[1]2.5消防工程 '!$B$4:$I$276,8,0) -> 125.44 | J76: =VLOOKUP(B76,'[1]2.5消防工程 '!$B$4:$J$276,9,0) -> 20.25 | K76: =VLOOKUP(B76,'[1]2.5消防工程 '!$B$4:$K$276,10,0) -> 72.45 | L76: =$L$4 -> 0.207 | M76: =F76*G76 -> 0
A77: 14 | B77: 湿式报警阀组DN150 | C77: 1.型号、规格:包含湿式报警阀体、系统侧压力表、供水侧压力表、补偿器、放水测试阀（常闭）、报警控制阀（常开）、报警试验阀（常闭）、过滤器、延迟器、压力开关、水力警铃等 | D77: 按设计图示数量计算 | E77: 组 | G77: =(H77+I77+J77+K77)*(1+L77) -> 2804.8628 | H77: =VLOOKUP(B77,'[1]2.5消防工程 '!$B$4:$H$276,7,0) -> 703.71 | I77: =VLOOKUP(B77,'[1]2.5消防工程 '!$B$4:$I$276,8,0) -> 1516.58 | J77: =VLOOKUP(B77,'[1]2.5消防工程 '!$B$4:$J$276,9,0) -> 101.74 | K77: =VLOOKUP(B77,'[1]2.5消防工程 '!$B$4:$K$276,10,0) -> 1.8 | L77: =$L$4 -> 0.207 | M77: =F77*G77 -> 0
A78: 15 | B78: 湿式报警阀组DN100 | C78: 1.型号、规格:包含湿式报警阀体、系统侧压力表、供水侧压力表、补偿器、放水测试阀（常闭）、报警控制阀（常开）、报警试验阀（常闭）、过滤器、延迟器、压力开关、水力警铃等 | D78: 按设计图示数量计算 | E78: 组 | G78: =(H78+I78+J78+K78)*(1+L78) -> 2346.1787 | H78: =VLOOKUP(B78,'[1]2.5消防工程 '!$B$4:$H$276,7,0) -> 610.43 | I78: =VLOOKUP(B78,'[1]2.5消防工程 '!$B$4:$I$276,8,0) -> 1251.1 | J78: =VLOOKUP(B78,'[1]2.5消防工程 '!$B$4:$J$276,9,0) -> 80.83 | K78: =VLOOKUP(B78,'[1]2.5消防工程 '!$B$4:$K$276,10,0) -> 1.45 | L78: =$L$4 -> 0.207 | M78: =F78*G78 -> 0
A79: 16 | B79: 信号阀DN150 | C79: 1.规格、压力等级:DN150；1.6MPa 2.连接形式:沟槽法兰连接 3.其他:按设计及规范要求 | D79: 按设计图示数量计算 | E79: 个 | G79: =(H79+I79+J79+K79)*(1+L79) -> 809.6556 | H79: =VLOOKUP(B79,'[1]2.5消防工程 '!$B$4:$H$276,7,0) -> 189.88 | I79: =VLOOKUP(B79,'[1]2.5消防工程 '!$B$4:$I$276,8,0) -> 383.05 | J79: =VLOOKUP(B79,'[1]2.5消防工程 '!$B$4:$J$276,9,0) -> 40.98 | K79: =VLOOKUP(B79,'[1]2.5消防工程 '!$B$4:$K$276,10,0) -> 56.89 | L79: =$L$4 -> 0.207 | M79: =F79*G79 -> 0
A80: 17 | B80: 信号阀DN100 | C80: 1.规格、压力等级:DN100；1.6MPa 2.连接形式:沟槽法兰连接 3.其他:按设计及规范要求 | D80: 按设计图示数量计算 | E80: 个 | G80: =(H80+I80+J80+K80)*(1+L80) -> 633.49395 | H80: =VLOOKUP(B80,'[1]2.5消防工程 '!$B$4:$H$276,7,0) -> 152.96 | I80: =VLOOKUP(B80,'[1]2.5消防工程 '!$B$4:$I$276,8,0) -> 293.87 | J80: =VLOOKUP(B80,'[1]2.5消防工程 '!$B$4:$J$276,9,0) -> 32.81 | K80: =VLOOKUP(B80,'[1]2.5消防工程 '!$B$4:$K$276,10,0) -> 45.21 | L80: =$L$4 -> 0.207 | M80: =F80*G80 -> 0
A81: 18 | B81: 闸阀DN150 | C81: 1.规格、压力等级:1.6MPa 2.连接形式:沟槽法兰连接 3.其他:按设计及规范要求 | D81: 按设计图示数量计算 | E81: 个 | G81: =(H81+I81+J81+K81)*(1+L81) -> 998.5511 | H81: =VLOOKUP(B81,'[1]2.5消防工程 '!$B$4:$H$276,7,0) -> 198.6 | I81: =VLOOKUP(B81,'[1]2.5消防工程 '!$B$4:$I$276,8,0) -> 430.83 | J81: =VLOOKUP(B81,'[1]2.5消防工程 '!$B$4:$J$276,9,0) -> 40.98 | K81: =VLOOKUP(B81,'[1]2.5消防工程 '!$B$4:$K$276,10,0) -> 156.89 | L81: =$L$4 -> 0.207 | M81: =F81*G81 -> 0
A82: 19 | B82: 闸阀DN100 | C82: 1.规格、压力等级:1.6MPa 2.连接形式:沟槽法兰连接 3.其他:按设计及规范要求 | D82: 按设计图示数量计算 | E82: 个 | G82: =(H82+I82+J82+K82)*(1+L82) -> 655.2803 | H82: =VLOOKUP(B82,'[1]2.5消防工程 '!$B$4:$H$276,7,0) -> 105.18 | I82: =VLOOKUP(B82,'[1]2.5消防工程 '!$B$4:$I$276,8,0) -> 359.7 | J82: =VLOOKUP(B82,'[1]2.5消防工程 '!$B$4:$J$276,9,0) -> 32.81 | K82: =VLOOKUP(B82,'[1]2.5消防工程 '!$B$4:$K$276,10,0) -> 45.21 | L82: =$L$4 -> 0.207 | M82: =F82*G82 -> 0
A83: 20 | B83: 闸阀DN80 | C83: 1.规格、压力等级:1.6MPa 2.连接形式:沟槽法兰连接 3.其他:按设计及规范要求 | D83: 按设计图示数量计算 | E83: 个 | G83: =(H83+I83+J83+K83)*(1+L83) -> 488.64188 | H83: =VLOOKUP(B83,'[1]2.5消防工程 '!$B$4:$H$276,7,0) -> 177.46 | I83: =VLOOKUP(B83,'[1]2.5消防工程 '!$B$4:$I$276,8,0) -> 189.35 | J83: =VLOOKUP(B83,'[1]2.5消防工程 '!$B$4:$J$276,9,0) -> 19.99 | K83: =VLOOKUP(B83,'[1]2.5消防工程 '!$B$4:$K$276,10,0) -> 18.04 | L83: =$L$4 -> 0.207 | M83: =F83*G83 -> 0
... A105: 42 | B105: 流量计 | C105: 1.名称:流量计 2.其他:按设计及规范要求 | D105: 按设计图示数量计算 | E105: 台 | G105: =(H105+I105+J105+K105)*(1+L105) -> 660.90492 | H105: =VLOOKUP(B105,'[1]2.5消防工程 '!$B$4:$H$276,7,0) -> 57.52 | I105: =VLOOKUP(B105,'[1]2.5消防工程 '!$B$4:$I$276,8,0) -> 460.56 | J105: =VLOOKUP(B105,'[1]2.5消防工程 '!$B$4:$J$276,9,0) -> 9.35 | K105: =VLOOKUP(B105,'[1]2.5消防工程 '!$B$4:$K$276,10,0) -> 20.13 | L105: =$L$4 -> 0.207 | M105: =F105*G105 -> 0
A106: 43 | B106: 上喷头 | C106: 1.安装部位:室内 2.材质、型号、规格:DN20 3.连接形式:螺纹连接 | D106: 按设计图示数量计算 | E106: 个 | F106: 200 | G106: =(H106+I106+J106+K106)*(1+L106) -> 47.84548 | H106: =VLOOKUP(B106,'[1]2.5消防工程 '!$B$4:$H$276,7,0) -> 23.89 | I106: =VLOOKUP(B106,'[1]2.5消防工程 '!$B$4:$I$276,8,0) -> 11.47 | J106: =VLOOKUP(B106,'[1]2.5消防工程 '!$B$4:$J$276,9,0) -> 4.13 | K106: =VLOOKUP(B106,'[1]2.5消防工程 '!$B$4:$K$276,10,0) -> 0.15 | L106: =$L$4 -> 0.207 | M106: =F106*G106 -> 9569.096
A107: 44 | B107: 下喷头 | C107: 1.安装部位:室内 2.材质、型号、规格:DN20 3.连接形式:螺纹连接 4.装饰盘设计要求:按设计及规范要求 | D107: 按设计图示数量计算 | E107: 个 | F107: 195 | G107: =(H107+I107+J107+K107)*(1+L107) -> 55.58235 | H107: =VLOOKUP(B107,'[1]2.5消防工程 '!$B$4:$H$276,7,0) -> 26.31 | I107: =VLOOKUP(B107,'[1]2.5消防工程 '!$B$4:$I$276,8,0) -> 13.26 | J107: =VLOOKUP(B107,'[1]2.5消防工程 '!$B$4:$J$276,9,0) -> 6.13 | K107: =VLOOKUP(B107,'[1]2.5消防工程 '!$B$4:$K$276,10,0) -> 0.35 | L107: =$L$4 -> 0.207 | M107: =F107*G107 -> 10838.558
A108: 45 | B108: 侧喷（含窗喷） | C108: 1.安装部位:室内 2.材质、型号、规格:DN20 3.连接形式:螺纹连接 4.装饰盘设计要求:按设计及规范要求 | D108: 按设计图示数量计算 | E108: 个 | F108: 6 | G108: =(H108+I108+J108+K108)*(1+L108) -> 0 | L108: =$L$4 -> 0.207 | M108: =F108*G108 -> 0
A109: 46 | B109: 组合式消火栓 | C109: 1.安装方式:按设计及规范要求 2.型号、规格:DN65 3.其他:按设计及规范要求 | D109: 按设计图示数量计算 | E109: 套 | F109: 10 | G109: =(H109+I109+J109+K109)*(1+L109) -> 1522.9443 | H109: =VLOOKUP(B109,'[1]2.5消防工程 '!$B$4:$H$276,7,0) -> 193.38 | I109: =VLOOKUP(B109,'[1]2.5消防工程 '!$B$4:$I$276,8,0) -> 1061.95 | J109: =VLOOKUP(B109,'[1]2.5消防工程 '!$B$4:$J$276,9,0) -> 5.78 | K109: =VLOOKUP(B109,'[1]2.5消防工程 '!$B$4:$K$276,10,0) -> 0.65 | L109: =$L$4 -> 0.207 | M109: =F109*G109 -> 15229.443
A110: 47 | B110: 室内消火栓 | C110: 1.安装方式:按设计及规范要求 2.型号、规格:DN65 3.其他:按设计及规范要求 | D110: 按设计图示数量计算 | E110: 套 | F110: 2 | G110: =(H110+I110+J110+K110)*(1+L110) -> 967.50706 | H110: =VLOOKUP(B110,'[1]2.5消防工程 '!$B$4:$H$276,7,0) -> 193.38 | I110: =VLOOKUP(B110,'[1]2.5消防工程 '!$B$4:$I$276,8,0) -> 601.77 | J110: =VLOOKUP(B110,'[1]2.5消防工程 '!$B$4:$J$276,9,0) -> 5.78 | K110: =VLOOKUP(B110,'[1]2.5消防工程 '!$B$4:$K$276,10,0) -> 0.65 | L110: =$L$4 -> 0.207 | M110: =F110*G110 -> 1935.0141
A111: 48 | B111: 试验消火栓 | C111: 1.安装方式:按设计及规范要求 2.型号、规格:DN65 3.其他:按设计及规范要求 | D111: 按设计图示数量计算 | E111: 套 | F111: 1 | G111: =(H111+I111+J111+K111)*(1+L111) -> 1020.9168 | H111: =VLOOKUP(B111,'[1]2.5消防工程 '!$B$4:$H$276,7,0) -> 193.38 | I111: =VLOOKUP(B111,'[1]2.5消防工程 '!$B$4:$I$276,8,0) -> 646.02 | J111: =VLOOKUP(B111,'[1]2.5消防工程 '!$B$4:$J$276,9,0) -> 5.78 | K111: =VLOOKUP(B111,'[1]2.5消防工程 '!$B$4:$K$276,10,0) -> 0.65 | L111: =$L$4 -> 0.207 | M111: =F111*G111 -> 1020.9168
A112: 49 | B112: 灭火器箱 | C112: 1.形式:灭火器箱明装含灭火器*2 2.其他:按设计及规范要求 | D112: 按设计图示数量计算 | E112: 组 | F112: 25 | G112: =(H112+I112+J112+K112)*(1+L112) -> 177.50142 | H112: =VLOOKUP(B112,'[1]2.5消防工程 '!$B$4:$H$276,7,0) -> 5.46 | I112: =VLOOKUP(B112,'[1]2.5消防工程 '!$B$4:$I$276,8,0) -> 141.6 | J112: =VLOOKUP(B112,'[1]2.5消防工程 '!$B$4:$J$276,9,0) -> 0 | K112: =VLOOKUP(B112,'[1]2.5消防工程 '!$B$4:$K$276,10,0) -> 0 | L112: =$L$4 -> 0.207 | M112: =F112*G112 -> 4437.5355
A113: 四 | B113: 消防水系统（主材利旧、含保护性拆除）
A114: 1 | B114: 内外壁热镀锌钢管DN25（主材利旧） | C114: 1.安装部位:室内 2.材质、规格:内外壁热镀锌钢管DN25 3.连接形式:螺纹连接 4.管道穿内墙、楼板、吊顶开洞及封堵套管:按设计及规范要求 5.压力试验及冲洗设计要求:按设计及规范要求 6.管道标识设计要求:按设计及规范要求 7.管道支架：按设计及规范要求 | D114: 按设计图示管道中心线以长度计算 | E114: m | G114: =(H114+I114+J114+K114)*(1+L114) -> 43.46407 | H114: =VLOOKUP(B114,'[1]2.5消防工程 '!$B$4:$H$276,7,0) -> 35.02 | I114: =VLOOKUP(B114,'[1]2.5消防工程 '!$B$4:$I$276,8,0) -> 0 | J114: =VLOOKUP(B114,'[1]2.5消防工程 '!$B$4:$J$276,9,0) -> 0.44 | K114: =VLOOKUP(B114,'[1]2.5消防工程 '!$B$4:$K$276,10,0) -> 0.55 | L114: =$L$4 -> 0.207 | M114: =F114*G114 -> 0
A115: 2 | B115: 内外壁热镀锌钢管DN32（主材利旧） | C115: 1.安装部位:室内 2.材质、规格:内外壁热镀锌钢管DN32 3.连接形式:螺纹连接 4.管道穿内墙、楼板、吊顶开洞及封堵套管:按设计及规范要求 5.压力试验及冲洗设计要求:按设计及规范要求 6.管道标识设计要求:按设计及规范要求 7.管道支架：按设计及规范要求 | D115: 按设计图示管道中心线以长度计算 | E115: m | G115: =(H115+I115+J115+K115)*(1+L115) -> 50.19913 | H115: =VLOOKUP(B115,'[1]2.5消防工程 '!$B$4:$H$276,7,0) -> 40.01 | I115: =VLOOKUP(B115,'[1]2.5消防工程 '!$B$4:$I$276,8,0) -> 0 | J115: =VLOOKUP(B115,'[1]2.5消防工程 '!$B$4:$J$276,9,0) -> 0.81 | K115: =VLOOKUP(B115,'[1]2.5消防工程 '!$B$4:$K$276,10,0) -> 0.77 | L115: =$L$4 -> 0.207 | M115: =F115*G115 -> 0
A116: 3 | B116: 内外壁热镀锌钢管DN40（主材利旧） | C116: 1.安装部位:室内 2.材质、规格:内外壁热镀锌钢管DN40 3.连接形式:螺纹连接 4.管道穿内墙、楼板、吊顶开洞及封堵套管:按设计及规范要求 5.压力试验及冲洗设计要求:按设计及规范要求 6.管道标识设计要求:按设计及规范要求 7.管道支架：按设计及规范要求 | D116: 按设计图示管道中心线以长度计算 | E116: m | G116: =(H116+I116+J116+K116)*(1+L116) -> 57.8153 | H116: =VLOOKUP(B116,'[1]2.5消防工程 '!$B$4:$H$276,7,0) -> 46.2 | I116: =VLOOKUP(B116,'[1]2.5消防工程 '!$B$4:$I$276,8,0) -> 0 | J116: =VLOOKUP(B116,'[1]2.5消防工程 '!$B$4:$J$276,9,0) -> 0.86 | K116: =VLOOKUP(B116,'[1]2.5消防工程 '!$B$4:$K$276,10,0) -> 0.84 | L116: =$L$4 -> 0.207 | M116: =F116*G116 -> 0
A117: 4 | B117: 内外壁热镀锌钢管DN50（主材利旧） | C117: 1.安装部位:室内 2.材质、规格:内外壁热镀锌钢管DN50 3.连接形式:螺纹连接 4.管道穿内墙、楼板、吊顶开洞及封堵套管:按设计及规范要求 5.压力试验及冲洗设计要求:按设计及规范要求 6.管道标识设计要求:按设计及规范要求 7.管道支架：按设计及规范要求 | D117: 按设计图示管道中心线以长度计算 | E117: m | G117: =(H117+I117+J117+K117)*(1+L117) -> 63.58476 | H117: =VLOOKUP(B117,'[1]2.5消防工程 '!$B$4:$H$276,7,0) -> 50.93 | I117: =VLOOKUP(B117,'[1]2.5消防工程 '!$B$4:$I$276,8,0) -> 0 | J117: =VLOOKUP(B117,'[1]2.5消防工程 '!$B$4:$J$276,9,0) -> 0.87 | K117: =VLOOKUP(B117,'[1]2.5消防工程 '!$B$4:$K$276,10,0) -> 0.88 | L117: =$L$4 -> 0.207 | M117: =F117*G117 -> 0
A118: 5 | B118: 内外壁热镀锌钢管DN65（主材利旧） | C118: 1.安装部位:室内 2.材质、规格:内外壁热镀锌钢管DN65 3.连接形式:沟槽式连接 4.管道穿内墙、楼板、吊顶开洞及封堵套管:按设计及规范要求 5.压力试验及冲洗设计要求:按设计及规范要求 6.管道标识设计要求:按设计及规范要求 7.管道支架：按设计及规范要求 | D118: 按设计图示管道中心线以长度计算 | E118: m | G118: =(H118+I118+J118+K118)*(1+L118) -> 70.68192 | H118: =VLOOKUP(B118,'[1]2.5消防工程 '!$B$4:$H$276,7,0) -> 57.01 | I118: =VLOOKUP(B118,'[1]2.5消防工程 '!$B$4:$I$276,8,0) -> 0 | J118: =VLOOKUP(B118,'[1]2.5消防工程 '!$B$4:$J$276,9,0) -> 1.14 | K118: =VLOOKUP(B118,'[1]2.5消防工程 '!$B$4:$K$276,10,0) -> 0.41 | L118: =$L$4 -> 0.207 | M118: =F118*G118 -> 0
A119: 6 | B119: 内外壁热镀锌钢管DN80（主材利旧） | C119: 1.安装部位:室内 2.材质、规格:内外壁热镀锌钢管DN80 3.连接形式:沟槽式连接 4.管道穿内墙、楼板、吊顶开洞及封堵套管:按设计及规范要求 5.压力试验及冲洗设计要求:按设计及规范要求 6.管道标识设计要求:按设计及规范要求 7.管道支架：按设计及规范要求 | D119: 按设计图示管道中心线以长度计算 | E119: m | G119: =(H119+I119+J119+K119)*(1+L119) -> 78.76882 | H119: =VLOOKUP(B119,'[1]2.5消防工程 '!$B$4:$H$276,7,0) -> 63.66 | I119: =VLOOKUP(B119,'[1]2.5消防工程 '!$B$4:$I$276,8,0) -> 0 | J119: =VLOOKUP(B119,'[1]2.5消防工程 '!$B$4:$J$276,9,0) -> 1.16 | K119: =VLOOKUP(B119,'[1]2.5消防工程 '!$B$4:$K$276,10,0) -> 0.44 | L119: =$L$4 -> 0.207 | M119: =F119*G119 -> 0
A120: 7 | B120: 内外壁热镀锌钢管DN100（主材利旧） | C120: 1.安装部位:室内 2.材质、规格:内外壁热镀锌钢管DN100 3.连接形式:沟槽式连接 4.管道穿内墙、楼板、吊顶开洞及封堵套管:按设计及规范要求 5.压力试验及冲洗设计要求:按设计及规范要求 6.管道标识设计要求:按设计及规范要求 7.管道支架：按设计及规范要求 | D120: 按设计图示管道中心线以长度计算 | E120: m | G120: =(H120+I120+J120+K120)*(1+L120) -> 86.69881 | H120: =VLOOKUP(B120,'[1]2.5消防工程 '!$B$4:$H$276,7,0) -> 70.09 | I120: =VLOOKUP(B120,'[1]2.5消防工程 '!$B$4:$I$276,8,0) -> 0 | J120: =VLOOKUP(B120,'[1]2.5消防工程 '!$B$4:$J$276,9,0) -> 1.19 | K120: =VLOOKUP(B120,'[1]2.5消防工程 '!$B$4:$K$276,10,0) -> 0.55 | L120: =$L$4 -> 0.207 | M120: =F120*G120 -> 0
A121: 8 | B121: 内外壁热镀锌钢管DN150（主材利旧） | C121: 1.安装部位:室内 2.材质、规格:内外壁热镀锌钢管DN150 3.连接形式:沟槽式连接 4.管道穿内墙、楼板、吊顶开洞及封堵套管:按设计及规范要求 5.压力试验及冲洗设计要求:按设计及规范要求 6.管道标识设计要求:按设计及规范要求 7.管道支架：按设计及规范要求 | D121: 按设计图示管道中心线以长度计算 | E121: m | G121: =(H121+I121+J121+K121)*(1+L121) -> 119.71026 | H121: =VLOOKUP(B121,'[1]2.5消防工程 '!$B$4:$H$276,7,0) -> 95.55 | I121: =VLOOKUP(B121,'[1]2.5消防工程 '!$B$4:$I$276,8,0) -> 0 | J121: =VLOOKUP(B121,'[1]2.5消防工程 '!$B$4:$J$276,9,0) -> 2.67 | K121: =VLOOKUP(B121,'[1]2.5消防工程 '!$B$4:$K$276,10,0) -> 0.96 | L121: =$L$4 -> 0.207 | M121: =F121*G121 -> 0
