Workbook

Sheet 1-清单及价格说明
A1: 编制说明
A3: 一 | B3: 工程量清单编制依据：
A4: 1 | B4: 长城智选设计、施工一体化项目工程图纸、效果图（1.0、2.0版本）
A5: 2 | B5: 《建设工程工程量清单计价规范 GB 50500-2013》
A6: 3 | B6: 《建筑工程建筑面积计算规范》GB 55031-2022
A7: 二 | B7: 工程量清单及控制价注意事项说明:
A8: 1 | B8: 本工程采用设计施工一体化，包工包料的全费用固定综合单价组价。固定综合单价包括现场人工费、材料费、机械费、管理费、措施费、规费、利润、税金、合同备案费、水电费、工程当地所要求必须缴纳的费用以及采用固定价格的工程所测算的风险金、相关的材料试验费、检测费（包括但不限于空气、材料、结构等第三方检测、鉴定等费用）及各系统施工完成后系统调试费、资料整理归档等一切费用。
A9: 2 | B9: 措施费用包含在固定综合单价中，不单独体现。措施费费用包括但不限于安全文明施工费用（应满足项目所在地的政府及物业要求的安全文明施工标准）、临时设施（办公住宿临设、临水临电、临时道路等）、夜间施工、非夜间施工照明、二次搬运、冬雨季施工、已完工程及设备成品保护等与项目相关的措施费用。
A10: 3 | B10: 本项目中涉及脚手架、垂直运输、超高增加费、垃圾清运费、垃圾消纳费含在固定综合单价中，不再单独体现。
A11: 4 | B11: 消防设备复检、玻璃幕墙、石材幕墙的检测以及当地政府要求的检测相关费用包含在固定综合单价中，不再单独体现。消防验收在招标范围内，消防的备案、验收、办证，单独组价。其它相关建设手续费（含物业及政府相关备案、开工、建设、验收等所有手续相关费用）含在固定综合单价中，不再单独体现。
A12: 5 | B12: 强弱电、给排水、消防、暖通等专业开洞、封堵、套管等，包含在对应专业的管道固定综合单价中，不再单独列清单。
A13: 6 | B13: 方案图纸设计费（包括但不限于涉及本项目的各专业工程（建筑、装饰、结构、幕墙、消防、电气、照明、给排水、暖通等）图纸深化、报审、审图、现场施工指导配合、竣工图编制等所有图纸相关费用），按照平方米进行计价，未使用区域、室内、外停车位不计算，部分店面涉及室外院落、隔离墙、道路规划，不计量，不单独计价。
A14: 7 | B14: 需进行政府竣工验收的费用，及因验收产生的检测费用均含在综合单价内。
A15: 8 | B15: 投标单位在投标前应踏勘现场，充分考虑现场、方案设计等实际情况(如:运输条件、施工场地、地质条件、施工时间区段等)；综合考虑现场实际地面找平厚度与清单、方案设计不一致时，价格不进行调整，投标单位也应深入理解技术要求和验收要求,所有在招标时提供的文件均认为已完整无误包含在报价之中；
A16: 9 | B16: 无节点做法，可自行深化，经甲方确认后实施，费用包含在综合单价相关子目中。
A17: 10 | B17: 对于新增项目或签证、设计变更产生的工程项目造价的调整按以下顺序执行：
A18: 10.1 | B18: 工程量清单表中有相同工程内容的项目，按相同项目综合单价执行，根据工程量增减进行总价调整；同标段或是同期其他分包合同有相同项目或类似项目单价，按照该单价计取。
A19: 10.2 | B19: 工程量清单表中有类似工程内容的项目，如某项清单发包人要求主要材料更换，则原综合单价不变，只调整主材价差，土建材料价差=（双方确定含税材料价格-本合同清单表内注明的主材价格）× (1+税金)。
... A21: 11 | B21: 本页不得删除,将作为合同清单的有效组成部分。

Sheet 2-报价汇总
A1: 工程报价汇总表
A2: 公司名称：深圳市广湾建设科技有限公司 | D2: 单位：元
A3: 序号 | B3: 单 位 工 程 名 称 | C3: 报价汇总 | D3: 备注
A4: 1 | B4: 装饰工程 | C4: ='2.1装饰工程'!M230 -> 640705.34 | E4: 642437.17 | F4: =C4-E4 -> -1731.8326
A5: 2 | B5: 强电工程 | C5: ='2.2强电工程'!M143 -> 80496.588 | E5: 80696.663 | F5: =C5-E5 -> -200.07437
A6: 3 | B6: 弱电工程 | C6: ='2.3弱电工程'!M83 -> 93628.43 | E6: 93861.144 | F6: =C6-E6 -> -232.71358
A7: 4 | B7: 消防工程 | C7: ='2.4消防工程 '!M15 -> 399026.96 | E7: 400018.74 | F7: =C7-E7 -> -991.782
A8: 5 | B8: 暖通工程 | C8: ='2.5暖通工程'!M90 -> 97546.873 | E8: 97789.326 | F8: =C8-E8 -> -242.45287
A9: 6 | B9: 合计 | C9: =SUM(C4:C8) -> 1311404.2 | E9: 1314803 | F9: =C9-E9 -> -3398.8555

Sheet 2.1装饰工程
A1: 长城智选商超店装修项目装饰工程
A2: 序号 | B2: 分部分项名称 | C2: 项目特征 | D2: 计量规则 | E2: 单位 | F2: 工程量 | G2: 综合单价 | H2: 人工 | I2: 主材 | J2: 辅材 | K2: 机械 | L2: 其他综合费率 | M2: 合计 | N2: 备注
A3: 一 | B3: 方案设计费
A4: 1 | B4: 方案图纸设计费 | C4: 1.包含建筑及装饰、结构、电气、暖通、给排水、消防、幕墙等专业，前期需现场踏勘，出具平面图、效果图等 2.包括但不限于图纸深化、报审、审图、竣工图编制等图纸相关费用 | D4: 1.使用面积<300平方米 2.以设计图纸尺寸按室内空间净面积计量（含不与墙面交集的柱面积），未使用区域、室内、外停车位不计算 | E4: m2 | F4: 300 | G4: =(H4+I4+J4+K4)*(1+L4) -> 108.63 | H4: =VLOOKUP(B4,'[1]2.1装饰工程'!$B$4:$H$231,7,0) -> 90 | I4: =VLOOKUP(B4,'[1]2.1装饰工程'!$B$4:$I$231,8,0) -> 0 | J4: =VLOOKUP(B4,'[1]2.1装饰工程'!$B$4:$J$231,9,0) -> 0 | K4: =VLOOKUP(B4,'[1]2.1装饰工程'!$B$4:$K$231,10,0) -> 0 | L4: ='[2]2-报价汇总'!$G$1 -> 0.207 | M4: =F4*G4 -> 32589
A5: 2 | B5: 方案图纸设计费 | C5: 1.包含建筑及装饰、结构、电气、暖通、给排水、消防、幕墙等专业，前期需现场踏勘，出具平面图、效果图等 2.包括但不限于图纸深化、报审、审图、竣工图编制等图纸相关费用 | D5: 1.使用面积≥300平方米 2.以设计图纸尺寸按室内空间净面积计量（含不与墙面交集的柱面积），未使用区域、室内、外停车位不计算 | E5: m2 | G5: =(H5+I5+J5+K5)*(1+L5) -> 96.56 | H5: 80 | I5: 0 | J5: 0 | K5: 0 | L5: =$L$4 -> 0.207 | M5: =F5*G5 -> 0
A6: 二 | B6: 拆除工程
A7: 1 | B7: 素混凝土拆除 | C7: 1.素混凝土构件拆除（含平面、立面、基础等） 2.包括：墙体内的管线、开关、插座等，达到不妨碍后期装修的程度，拆除后的所有材料施工单位自行处理 3.其他：满足施工要求 | D7: 工程量按拆除构件的混凝土体积计算 | E7: m3 | G7: =(H7+I7+J7+K7)*(1+L7) -> 483.98286 | H7: =VLOOKUP(B7,'[1]2.1装饰工程'!$B$4:$H$231,7,0) -> 280.88 | I7: =VLOOKUP(B7,'[1]2.1装饰工程'!$B$4:$I$231,8,0) -> 0 | J7: =VLOOKUP(B7,'[1]2.1装饰工程'!$B$4:$J$231,9,0) -> 7.47 | K7: =VLOOKUP(B7,'[1]2.1装饰工程'!$B$4:$K$231,10,0) -> 112.63 | L7: =$L$4 -> 0.207 | M7: =F7*G7 -> 0
A8: 2 | B8: 钢筋混凝土构件拆除 | C8: 1.钢筋混凝土构件拆除（含平面、立面、基础等） 2.包括：墙体内的管线、开关、插座等，达到不妨碍后期装修的程度，拆除后的所有材料施工单位自行处理 3.其他：满足施工要求 | D8: 工程量按拆除构件的混凝土体积计算 | E8: m3 | G8: =(H8+I8+J8+K8)*(1+L8) -> 617.46499 | H8: =VLOOKUP(B8,'[1]2.1装饰工程'!$B$4:$H$231,7,0) -> 359 | I8: =VLOOKUP(B8,'[1]2.1装饰工程'!$B$4:$I$231,8,0) -> 0 | J8: =VLOOKUP(B8,'[1]2.1装饰工程'!$B$4:$J$231,9,0) -> 9.2 | K8: =VLOOKUP(B8,'[1]2.1装饰工程'!$B$4:$K$231,10,0) -> 143.37 | L8: =$L$4 -> 0.207 | M8: =F8*G8 -> 0
A9: 3 | B9: 砌体墙拆除 | C9: 1.砌筑墙体拆除，连墙体内砼柱破碎后装袋 2.包括：砌体墙及附属的基层面层，墙体内的管线、开关、插座、等，达到不妨碍装修的程度，拆除后的所有材料施工单位自行处理 3.其他：满足施工要求 | D9: 工程量按拆除部位的体积计算 | E9: m3 | G9: =(H9+I9+J9+K9)*(1+L9) -> 231.59916 | H9: =VLOOKUP(B9,'[1]2.1装饰工程'!$B$4:$H$231,7,0) -> 126.88 | I9: =VLOOKUP(B9,'[1]2.1装饰工程'!$B$4:$I$231,8,0) -> 0 | J9: =VLOOKUP(B9,'[1]2.1装饰工程'!$B$4:$J$231,9,0) -> 0 | K9: =VLOOKUP(B9,'[1]2.1装饰工程'!$B$4:$K$231,10,0) -> 65 | L9: =$L$4 -> 0.207 | M9: =F9*G9 -> 0
A10: 4 | B10: 玻璃隔墙拆除 | C10: 1.玻璃隔墙拆除 2.包括：玻璃隔墙及附属的基层面层，墙体内的管线、开关、插座等，达到不妨碍装修的程度，拆除后的所有材料施工单位自行处理 3.墙体厚度：综合考虑 4.其他：满足施工要求 | D10: 工程量按拆除部位的面积计算 | E10: m2 | G10: =(H10+I10+J10+K10)*(1+L10) -> 32.48037 | H10: =VLOOKUP(B10,'[1]2.1装饰工程'!$B$4:$H$231,7,0) -> 13.91 | I10: =VLOOKUP(B10,'[1]2.1装饰工程'!$B$4:$I$231,8,0) -> 0 | J10: =VLOOKUP(B10,'[1]2.1装饰工程'!$B$4:$J$231,9,0) -> 0 | K10: =VLOOKUP(B10,'[1]2.1装饰工程'!$B$4:$K$231,10,0) -> 13 | L10: =$L$4 -> 0.207 | M10: =F10*G10 -> 0
A11: 5 | B11: 石膏板隔墙拆除 | C11: 1.石膏板隔墙拆除 2.包括：石膏板隔墙及附属的基层面层，墙体内的管线、开关、插座等，达到不妨碍装修的程度，拆除后的所有材料施工单位自行处理 3.墙体厚度：综合考虑， 4.其他：满足施工要求 | D11: 工程量按拆除部位的面积计算 | E11: m2 | G11: =(H11+I11+J11+K11)*(1+L11) -> 33.68737 | H11: =VLOOKUP(B11,'[1]2.1装饰工程'!$B$4:$H$231,7,0) -> 14.91 | I11: =VLOOKUP(B11,'[1]2.1装饰工程'!$B$4:$I$231,8,0) -> 0 | J11: =VLOOKUP(B11,'[1]2.1装饰工程'!$B$4:$J$231,9,0) -> 0 | K11: =VLOOKUP(B11,'[1]2.1装饰工程'!$B$4:$K$231,10,0) -> 13 | L11: =$L$4 -> 0.207 | M11: =F11*G11 -> 0
A12: 6 | B12: 砌体墙开门洞（含修补） | C12: 1.砌体墙开门洞（含修补） 2.包括：砌体墙隔墙及附属的基层面层，墙体内的管线、开关、插座等，达到不妨碍装修的程度，拆除后的所有材料施工单位自行处理 3.墙体厚度：综合考虑，包含开门洞的修补工作 4.其他：满足施工要求 | D12: 工程量按拆除部位的面积计算 | E12: m2 | G12: =(H12+I12+J12+K12)*(1+L12) -> 87.20575 | H12: =VLOOKUP(B12,'[1]2.1装饰工程'!$B$4:$H$231,7,0) -> 56.66 | I12: =VLOOKUP(B12,'[1]2.1装饰工程'!$B$4:$I$231,8,0) -> 0 | J12: =VLOOKUP(B12,'[1]2.1装饰工程'!$B$4:$J$231,9,0) -> 2.59 | K12: =VLOOKUP(B12,'[1]2.1装饰工程'!$B$4:$K$231,10,0) -> 13 | L12: =$L$4 -> 0.207 | M12: =F12*G12 -> 0
A13: 7 | B13: 门窗拆除（包括门框、门套） | C13: 1.门窗拆除 2.包括：门框、门套，不区分门窗材质，达到不妨碍装修的程度，拆除后的所有材料施工单位自行处理 3.其他：满足施工要求 | D13: 工程量按拆除面积计算 | E13: m2 | G13: =(H13+I13+J13+K13)*(1+L13) -> 34.59262 | H13: =VLOOKUP(B13,'[1]2.1装饰工程'!$B$4:$H$231,7,0) -> 15.66 | I13: =VLOOKUP(B13,'[1]2.1装饰工程'!$B$4:$I$231,8,0) -> 0 | J13: =VLOOKUP(B13,'[1]2.1装饰工程'!$B$4:$J$231,9,0) -> 0 | K13: =VLOOKUP(B13,'[1]2.1装饰工程'!$B$4:$K$231,10,0) -> 13 | L13: =$L$4 -> 0.207 | M13: =F13*G13 -> 0
A14: 8 | B14: 楼地面装饰物拆除 | C14: 1.楼地面装饰物拆除（包括但不限于玻璃、PVC、环氧地坪等材质） 2.包括：装饰地面面层及基层，地面内的管线、开关、插座等，达到不妨碍后期地面装修的程度，拆除后的所有材料施工单位自行处理 3.其他：满足施工要求 | D14: 工程量按拆除面积计算 | E14: m2 | G14: =(H14+I14+J14+K14)*(1+L14) -> 41.82255 | H14: =VLOOKUP(B14,'[1]2.1装饰工程'!$B$4:$H$231,7,0) -> 28.15 | I14: =VLOOKUP(B14,'[1]2.1装饰工程'!$B$4:$I$231,8,0) -> 0 | J14: =VLOOKUP(B14,'[1]2.1装饰工程'!$B$4:$J$231,9,0) -> 0 | K14: =VLOOKUP(B14,'[1]2.1装饰工程'!$B$4:$K$231,10,0) -> 6.5 | L14: =$L$4 -> 0.207 | M14: =F14*G14 -> 0
A15: 9 | B15: 楼地面地毯拆除 | C15: 1.楼地面地毯拆除 2.包括：地面面层及基层，地面内的管线、开关、插座等，达到不妨碍后期地面装修的程度，拆除后的所有材料施工单位自行处理 3.其他：满足施工要求 | D15: 工程量按拆除面积计算 | E15: m2 | G15: =(H15+I15+J15+K15)*(1+L15) -> 7.2244985 | H15: =4.97*1.15 -> 5.7155 | I15: 0 | J15: 0.05 | K15: 0.22 | L15: =$L$4 -> 0.207 | M15: =F15*G15 -> 0
A16: 10 | B16: 楼地面地砖拆除 | C16: 1.楼地面地砖拆除 2.包括：地面面层及基层，地面内的管线、开关、插座等，达到不妨碍后期地面装修的程度，拆除后的所有材料施工单位自行处理 3.其他：满足施工要求 | D16: 工程量按拆除面积计算 | E16: m2 | G16: =(H16+I16+J16+K16)*(1+L16) -> 38.656657 | H16: =27*1.15 -> 31.05 | I16: 0 | J16: 0.27705628 | K16: 0.7 | L16: =$L$4 -> 0.207 | M16: =F16*G16 -> 0
A17: 11 | B17: 楼地面地板拆除 | C17: 1.楼地面地板拆除 2.包括：地面面层及基层，地面内的管线、开关、插座等，达到不妨碍后期地面装修的程度，拆除后的所有材料施工单位自行处理 3.其他：满足施工要求 | D17: 工程量按拆除面积计算 | E17: m2 | G17: =(H17+I17+J17+K17)*(1+L17) -> 7.2244985 | H17: =4.97*1.15 -> 5.7155 | I17: 0 | J17: 0.05 | K17: 0.22 | L17: =$L$4 -> 0.207 | M17: =F17*G17 -> 0
A18: 12 | B18: 墙面、柱（梁）面装饰物拆除（含龙骨） | C18: 1.墙面装饰物拆除，含龙骨及基层板（包括但不限于石材、铝板、金属、木饰面、石膏板等材质） 2.包括：拆除装饰墙面龙骨、基层板及面层，地面内的管线、开关、插座等，达到不妨碍后期墙面装修的程度，拆除后的所有材料施工单位自行处理 3.其他：满足施工要求 | D18: 工程量按拆除面积计算 | E18: m2 | G18: =(H18+I18+J18+K18)*(1+L18) -> 36.59624 | H18: =VLOOKUP(B18,'[1]2.1装饰工程'!$B$4:$H$231,7,0) -> 23.82 | I18: =VLOOKUP(B18,'[1]2.1装饰工程'!$B$4:$I$231,8,0) -> 0 | J18: =VLOOKUP(B18,'[1]2.1装饰工程'!$B$4:$J$231,9,0) -> 0 | K18: =VLOOKUP(B18,'[1]2.1装饰工程'!$B$4:$K$231,10,0) -> 6.5 | L18: =$L$4 -> 0.207 | M18: =F18*G18 -> 0
A19: 13 | B19: 墙面、柱（梁）面装饰物拆除（不含龙骨） | C19: 1.墙面装饰物拆除，不含龙骨（包括但不限于石材、铝板、金属、木饰面等材质） 2.包括：拆除装饰墙面基层及面层，地面内的管线、开关、插座等，达到不妨碍后期墙面装修的程度，拆除后的所有材料施工单位自行处理 3.其他：满足施工要求 | D19: 工程量按拆除面积计算 | E19: m2 | G19: =(H19+I19+J19+K19)*(1+L19) -> 30.18707 | H19: =VLOOKUP(B19,'[1]2.1装饰工程'!$B$4:$H$231,7,0) -> 18.51 | I19: =VLOOKUP(B19,'[1]2.1装饰工程'!$B$4:$I$231,8,0) -> 0 | J19: =VLOOKUP(B19,'[1]2.1装饰工程'!$B$4:$J$231,9,0) -> 0 | K19: =VLOOKUP(B19,'[1]2.1装饰工程'!$B$4:$K$231,10,0) -> 6.5 | L19: =$L$4 -> 0.207 | M19: =F19*G19 -> 0
A20: 14 | B20: 铲除墙面涂料、裱糊面 | C20: 1.铲除涂料、裱糊面（综合考虑铲除部位） 2.包括：拆除装饰墙面涂料、腻子及砂浆找平层，地面内的管线、开关、插座等，达到不妨碍后期装修的程度，拆除后的所有材料施工单位自行处理 3.其他：满足施工要求 | D20: 工程量按拆除面积计算 | E20: m2 | G20: =(H20+I20+J20+K20)*(1+L20) -> 10.382614 | H20: =1.15*4.23 -> 4.8645 | K20: =1.15*3.25 -> 3.7375 | L20: =$L$4 -> 0.207 | M20: =F20*G20 -> 0
A21: 15 | B21: 铲除钢结构面油漆 | C21: 1.铲除油漆（综合考虑铲除部位） 2.包括：拆除钢结构面层涂料 3.其他：满足施工要求 | D21: 工程量按拆除面积计算 | E21: m2 | G21: =(H21+I21+J21+K21)*(1+L21) -> 19.085687 | H21: =1.15*8.5 -> 9.775 | K21: =1.15*5.25 -> 6.0375 | L21: =$L$4 -> 0.207 | M21: =F21*G21 -> 0
A22: 16 | B22: 玻璃贴膜拆除 | C22: 1.玻璃贴膜拆除 2.包括：清除玻璃贴膜，达到不妨碍装修的程度，拆除后的所有材料施工单位自行处理 3.其他：满足施工要求 | D22: 工程量按拆除面积计算 | E22: m2 | G22: =(H22+I22+J22+K22)*(1+L22) -> 11.62341 | H22: =VLOOKUP(B22,'[1]2.1装饰工程'!$B$4:$H$231,7,0) -> 6.38 | I22: =VLOOKUP(B22,'[1]2.1装饰工程'!$B$4:$I$231,8,0) -> 0 | J22: =VLOOKUP(B22,'[1]2.1装饰工程'!$B$4:$J$231,9,0) -> 0 | K22: =VLOOKUP(B22,'[1]2.1装饰工程'!$B$4:$K$231,10,0) -> 3.25 | L22: =$L$4 -> 0.207 | M22: =F22*G22 -> 0
A23: 17 | B23: 吊顶拆除 | C23: 1.吊顶拆除（包括但不限于石膏板、铝扣板、矿棉板等材质） 2.包括：转换层、龙骨、基层、面层及配套的风口、灯具、线管、吊顶上水管风管等所有材料，达到不妨碍吊顶装修的程度，拆除后的所有材料施工单位自行处理 3.其他：满足施工要求 | D23: 工程量按拆除面积计算 | E23: m2 | G23: =(H23+I23+J23+K23)*(1+L23) -> 27.08508 | H23: =VLOOKUP(B23,'[1]2.1装饰工程'!$B$4:$H$231,7,0) -> 15.94 | I23: =VLOOKUP(B23,'[1]2.1装饰工程'!$B$4:$I$231,8,0) -> 0 | J23: =VLOOKUP(B23,'[1]2.1装饰工程'!$B$4:$J$231,9,0) -> 0 | K23: =VLOOKUP(B23,'[1]2.1装饰工程'!$B$4:$K$231,10,0) -> 6.5 | L23: =$L$4 -> 0.207 | M23: =F23*G23 -> 0
A24: 18 | B24: 电气、暖通等拆除费用 | C24: 1.电气、暖通等拆除费用（裸顶） 2.包括：达到不妨碍装修的程度，拆除后的所有材料施工单位自行处理 3.其他：满足施工要求 | D24: 工程量按拆除裸顶天棚水平投影面积计算 | E24: m2 | G24: =(H24+I24+J24+K24)*(1+L24) -> 21.42425 | H24: =VLOOKUP(B24,'[1]2.1装饰工程'!$B$4:$H$231,7,0) -> 14.5 | I24: =VLOOKUP(B24,'[1]2.1装饰工程'!$B$4:$I$231,8,0) -> 0 | J24: =VLOOKUP(B24,'[1]2.1装饰工程'!$B$4:$J$231,9,0) -> 0 | K24: =VLOOKUP(B24,'[1]2.1装饰工程'!$B$4:$K$231,10,0) -> 3.25 | L24: =$L$4 -> 0.207 | M24: =F24*G24 -> 0
A25: 19 | B25: 外幕墙拆除 | C25: 1.外幕墙拆除（包括但不限于石材等材质） 2.包括：幕墙、基层板、龙骨及辅材（包含破碎后装袋），达到不妨碍装修的程度，拆除后的所有材料施工单位自行处理 3.其他：满足施工要求 | D25: 工程量按拆除面积计算 | E25: m2 | G25: =(H25+I25+J25+K25)*(1+L25) -> 56.27034 | H25: =VLOOKUP(B25,'[1]2.1装饰工程'!$B$4:$H$231,7,0) -> 40.12 | I25: =VLOOKUP(B25,'[1]2.1装饰工程'!$B$4:$I$231,8,0) -> 0 | J25: =VLOOKUP(B25,'[1]2.1装饰工程'!$B$4:$J$231,9,0) -> 0 | K25: =VLOOKUP(B25,'[1]2.1装饰工程'!$B$4:$K$231,10,0) -> 6.5 | L25: =$L$4 -> 0.207 | M25: =F25*G25 -> 0
A26: 20 | B26: 外幕墙金属拆除 | C26: 1.外幕墙金属面拆除 2.包括：幕墙、基层板、龙骨及辅材（包含破碎后装袋），达到不妨碍装修的程度，拆除后的所有材料施工单位自行处理 3.其他：满足施工要求 | D26: 工程量按拆除面积计算 | E26: m2 | G26: =(H26+I26+J26+K26)*(1+L26) -> 59.158691 | H26: =1.15*36.12 -> 41.538 | I26: 0 | J26: 0 | K26: =1.15*6.5 -> 7.475 | L26: =$L$4 -> 0.207 | M26: =F26*G26 -> 0
A27: 21 | B27: 外幕墙玻璃拆除 | C27: 1.外幕墙玻璃拆除 2.包括：幕墙、辅材（包含破碎后装袋），达到不妨碍装修的程度，拆除后的所有材料施工单位自行处理 3.其他：满足施工要求 | D27: 工程量按拆除面积计算 | E27: m2 | G27: =(H27+I27+J27+K27)*(1+L27) -> 59.158691 | H27: =1.15*36.12 -> 41.538 | I27: 0 | J27: 0 | K27: =1.15*6.5 -> 7.475 | L27: =$L$4 -> 0.207 | M27: =F27*G27 -> 0
A28: 22 | B28: 栏杆、栏板拆除 | C28: 1.栏杆、栏板拆除（综合考虑栏杆、栏板的材质及高度） 2.包括：达到不妨碍装修的程度，拆除后的所有材料施工单位自行处理 3.其他：满足施工要求 | D28: 工程量按拆除长度计算 | E28: m | G28: =(H28+I28+J28+K28)*(1+L28) -> 19.60168 | H28: =VLOOKUP(B28,'[1]2.1装饰工程'!$B$4:$H$231,7,0) -> 9.74 | I28: =VLOOKUP(B28,'[1]2.1装饰工程'!$B$4:$I$231,8,0) -> 0 | J28: =VLOOKUP(B28,'[1]2.1装饰工程'!$B$4:$J$231,9,0) -> 0 | K28: =VLOOKUP(B28,'[1]2.1装饰工程'!$B$4:$K$231,10,0) -> 6.5 | L28: =$L$4 -> 0.207 | M28: =F28*G28 -> 0
A29: 23 | B29: 店铺吊挂logo拆除 | C29: 1.店铺吊挂logo拆除，墙面logo不计（logo尺寸综合考虑） 2.包括：达到不妨碍装修的程度，拆除后的所有材料施工单位自行处理 3.其他：满足施工要求 | D29: 工程量按个计算 | E29: 个 | G29: =(H29+I29+J29+K29)*(1+L29) -> 65.93841 | H29: =VLOOKUP(B29,'[1]2.1装饰工程'!$B$4:$H$231,7,0) -> 48.13 | I29: =VLOOKUP(B29,'[1]2.1装饰工程'!$B$4:$I$231,8,0) -> 0 | J29: =VLOOKUP(B29,'[1]2.1装饰工程'!$B$4:$J$231,9,0) -> 0 | K29: =VLOOKUP(B29,'[1]2.1装饰工程'!$B$4:$K$231,10,0) -> 6.5 | L29: =$L$4 -> 0.207 | M29: =F29*G29 -> 0
A30: 24 | B30: 墙面logo拆除 | C30: 1.店铺墙面logo拆除（logo尺寸综合考虑） 2.包括：达到不妨碍装修的程度，拆除后的所有材料施工单位自行处理 3.其他：满足施工要求 | D30: 工程量按个计算 | E30: 个 | G30: =(H30+I30+J30+K30)*(1+L30) -> 90.07841 | H30: =VLOOKUP(B30,'[1]2.1装饰工程'!$B$4:$H$231,7,0) -> 68.13 | I30: =VLOOKUP(B30,'[1]2.1装饰工程'!$B$4:$I$231,8,0) -> 0 | J30: =VLOOKUP(B30,'[1]2.1装饰工程'!$B$4:$J$231,9,0) -> 0 | K30: =VLOOKUP(B30,'[1]2.1装饰工程'!$B$4:$K$231,10,0) -> 6.5 | L30: =$L$4 -> 0.207 | M30: =F30*G30 -> 0
A31: 25 | B31: 保洁费 | C31: 1.保洁费 2.包括：精保洁，满足开业条件 3.其他详见SI手册、品牌表及标准节点等，满足施工要求及国家规范 | D31: 工程量按装修店面占地面积计算 | E31: m2 | F31: 300 | G31: =(H31+I31+J31+K31)*(1+L31) -> 18.105 | H31: =VLOOKUP(B31,'[1]2.1装饰工程'!$B$4:$H$231,7,0) -> 15 | I31: =VLOOKUP(B31,'[1]2.1装饰工程'!$B$4:$I$231,8,0) -> 0 | J31: =VLOOKUP(B31,'[1]2.1装饰工程'!$B$4:$J$231,9,0) -> 0 | K31: =VLOOKUP(B31,'[1]2.1装饰工程'!$B$4:$K$231,10,0) -> 0 | L31: =$L$4 -> 0.207 | M31: =F31*G31 -> 5431.5
A32: 三 | B32: 装饰地面工程
A33: 1 | B33: 原地面做拉毛处理 | C33: 1.原始地面拉毛 2.其他详见SI手册、品牌表及标准节点等，满足施工要求及国家规范 | D33: 工程量按设计图示尺寸以面积计算 | E33: m2 | G33: =(H33+I33+J33+K33)*(1+L33) -> 14.13397 | H33: =VLOOKUP(B33,'[1]2.1装饰工程'!$B$4:$H$231,7,0) -> 11.71 | I33: =VLOOKUP(B33,'[1]2.1装饰工程'!$B$4:$I$231,8,0) -> 0 | J33: =VLOOKUP(B33,'[1]2.1装饰工程'!$B$4:$J$231,9,0) -> 0 | K33: =VLOOKUP(B33,'[1]2.1装饰工程'!$B$4:$K$231,10,0) -> 0 | L33: =$L$4 -> 0.207 | M33: =F33*G33 -> 0
A34: 2 | B34: 5mm水泥自流平基层 | C34: 1.5mm水泥自流平 2.其他详见SI手册、品牌表及标准节点等，满足施工要求及国家规范 | D34: 工程量按设计图示尺寸以面积计算 | E34: m2 | G34: =(H34+I34+J34+K34)*(1+L34) -> 46.11947 | H34: =VLOOKUP(B34,'[1]2.1装饰工程'!$B$4:$H$231,7,0) -> 26.26 | I34: =VLOOKUP(B34,'[1]2.1装饰工程'!$B$4:$I$231,8,0) -> 11.95 | J34: =VLOOKUP(B34,'[1]2.1装饰工程'!$B$4:$J$231,9,0) -> 0 | K34: =VLOOKUP(B34,'[1]2.1装饰工程'!$B$4:$K$231,10,0) -> 0 | L34: =$L$4 -> 0.207 | M34: =F34*G34 -> 0
A35: 3 | B35: 水泥自流平基层厚度每增减1mm | C35: 1.水泥自流平厚度每增减1mm 2.其他详见SI手册、品牌表及标准节点等，满足施工要求及国家规范 | D35: 工程量按设计图示尺寸以面积计算 | E35: m2 | G35: =(H35+I35+J35+K35)*(1+L35) -> 8.12311 | H35: =VLOOKUP(B35,'[1]2.1装饰工程'!$B$4:$H$231,7,0) -> 3.54 | I35: =VLOOKUP(B35,'[1]2.1装饰工程'!$B$4:$I$231,8,0) -> 3.19 | J35: =VLOOKUP(B35,'[1]2.1装饰工程'!$B$4:$J$231,9,0) -> 0 | K35: =VLOOKUP(B35,'[1]2.1装饰工程'!$B$4:$K$231,10,0) -> 0 | L35: =$L$4 -> 0.207 | M35: =F35*G35 -> 0
A36: 4 | B36: 20mm地面水泥砂浆 | C36: 1.20厚水泥砂浆 2.其他详见SI手册、品牌表及标准节点等，满足施工要求及国家规范 | D36: 工程量按设计图示尺寸以面积计算 | E36: m2 | F36: 60 | G36: =(H36+I36+J36+K36)*(1+L36) -> 33.45804 | H36: =VLOOKUP(B36,'[1]2.1装饰工程'!$B$4:$H$231,7,0) -> 11.6 | I36: =VLOOKUP(B36,'[1]2.1装饰工程'!$B$4:$I$231,8,0) -> 16.12 | J36: =VLOOKUP(B36,'[1]2.1装饰工程'!$B$4:$J$231,9,0) -> 0 | K36: =VLOOKUP(B36,'[1]2.1装饰工程'!$B$4:$K$231,10,0) -> 0 | L36: =$L$4 -> 0.207 | M36: =F36*G36 -> 2007.4824
A37: 5 | B37: 地面水泥砂浆厚度每增减10mm | C37: 1.地面水泥砂浆厚度每增减10mm 2.其他详见SI手册、品牌表及标准节点等，满足施工要求及国家规范 | D37: 工程量按设计图示尺寸以面积计算 | E37: m2 | F37: 60 | G37: =(H37+I37+J37+K37)*(1+L37) -> 11.49064 | H37: =VLOOKUP(B37,'[1]2.1装饰工程'!$B$4:$H$231,7,0) -> 3.66 | I37: =VLOOKUP(B37,'[1]2.1装饰工程'!$B$4:$I$231,8,0) -> 5.86 | J37: =VLOOKUP(B37,'[1]2.1装饰工程'!$B$4:$J$231,9,0) -> 0 | K37: =VLOOKUP(B37,'[1]2.1装饰工程'!$B$4:$K$231,10,0) -> 0 | L37: =$L$4 -> 0.207 | M37: =F37*G37 -> 689.4384
A38: 6 | B38: 20mm厚C15细石混凝土找平 | C38: 1.20厚15细石混凝土找平+素水泥浆一道 2.包含止水坎综合考虑，其他详见SI手册、品牌表及标准节点等，满足施工要求及国家规范 | D38: 工程量按设计图示尺寸以面积计算，有厚度变化进行则算 | E38: m2 | G38: =(H38+I38+J38+K38)*(1+L38) -> 41.891349 | H38: =1.15*7.62 -> 8.763 | I38: =1.15*22.5 -> 25.875 | K38: =1.15*0.06 -> 0.069 | L38: =$L$4 -> 0.207 | M38: =F38*G38 -> 0
A39: 7 | B39: 20mm厚C25细石混凝土找平 | C39: 1.20厚C25细石混凝土找平+素水泥浆一道 2.包含止水坎综合考虑，其他详见SI手册、品牌表及标准节点等，满足施工要求及国家规范 | D39: 工程量按设计图示尺寸以面积计算，有厚度变化进行则算 | E39: m2 | F39: 60 | G39: =(H39+I39+J39+K39)*(1+L39) -> 45.541921 | H39: =1.15*7.62 -> 8.763 | I39: =1.15*25.13 -> 28.8995 | K39: =1.15*0.06 -> 0.069 | L39: =$L$4 -> 0.207 | M39: =F39*G39 -> 2732.5152
A40: 8 | B40: 20mm厚C30细石混凝土找平 | C40: 1.20厚C30细石混凝土找平+素水泥浆一道 2.包含止水坎综合考虑，其他详见SI手册、品牌表及标准节点等，满足施工要求及国家规范 | D40: 工程量按设计图示尺寸以面积计算，有厚度变化进行则算 | E40: m2 | G40: =(H40+I40+J40+K40)*(1+L40) -> 47.027134 | H40: =1.15*7.62 -> 8.763 | I40: =1.15*26.2 -> 30.13 | K40: =1.15*0.06 -> 0.069 | L40: =$L$4 -> 0.207 | M40: =F40*G40 -> 0
A41: 9 | B41: 界面剂一道 | C41: 1.界面剂一道 2.其他详见SI手册、品牌表及标准节点等，满足施工要求及国家规范 | D41: 工程量按设计图示尺寸以面积计算 | E41: m2 | F41: 257.78 | G41: =(H41+I41+J41+K41)*(1+L41) -> 8.15932 | H41: =VLOOKUP(B41,'[1]2.1装饰工程'!$B$4:$H$231,7,0) -> 3.79 | I41: =VLOOKUP(B41,'[1]2.1装饰工程'!$B$4:$I$231,8,0) -> 2.46 | J41: =VLOOKUP(B41,'[1]2.1装饰工程'!$B$4:$J$231,9,0) -> 0 | K41: =VLOOKUP(B41,'[1]2.1装饰工程'!$B$4:$K$231,10,0) -> 0.51 | L41: =$L$4 -> 0.207 | M41: =F41*G41 -> 2103.3095
A42: 10 | B42: 零星混凝土C15 | C42: 1.零星混凝土C15 2.工程量按体积计算 3.综合考虑模板、模板不另外计取 4.其他详见SI手册、品牌表及标准节点等，满足施工要求及国家规范 | D42: 工程量按设计图示尺寸以体积计算 | E42: m3 | G42: =(H42+I42+J42+K42)*(1+L42) -> 811.63508 | H42: =VLOOKUP(B42,'[1]2.1装饰工程'!$B$4:$H$231,7,0) -> 187.87 | I42: =VLOOKUP(B42,'[1]2.1装饰工程'!$B$4:$I$231,8,0) -> 482.94 | J42: =VLOOKUP(B42,'[1]2.1装饰工程'!$B$4:$J$231,9,0) -> 0 | K42: =VLOOKUP(B42,'[1]2.1装饰工程'!$B$4:$K$231,10,0) -> 1.63 | L42: =$L$4 -> 0.207 | M42: =F42*G42 -> 0
A43: 11 | B43: 零星混凝土C20 | C43: 1.零星混凝土C25 2.工程量按体积计算 3.综合考虑模板、模板不另外计取 4.其他详见SI手册、品牌表及标准节点等，满足施工要求及国家规范 | D43: 按设计图示尺寸以体积计算 | E43: m3 | G43: =(H43+I43+J43+K43)*(1+L43) -> 859.68575 | H43: =VLOOKUP(B43,'[1]2.1装饰工程'!$B$4:$H$231,7,0) -> 187.87 | I43: =VLOOKUP(B43,'[1]2.1装饰工程'!$B$4:$I$231,8,0) -> 522.75 | J43: =VLOOKUP(B43,'[1]2.1装饰工程'!$B$4:$J$231,9,0) -> 0 | K43: =VLOOKUP(B43,'[1]2.1装饰工程'!$B$4:$K$231,10,0) -> 1.63 | L43: =$L$4 -> 0.207 | M43: =F43*G43 -> 0
A44: 12 | B44: 零星混凝土C25 | C44: 1.零星混凝土C25 2.工程量按体积计算 3.综合考虑模板、模板不另外计取 4.其他详见SI手册、品牌表及标准节点等，满足施工要求及国家规范 | D44: 按设计图示尺寸以体积计算 | E44: m3 | G44: =(H44+I44+J44+K44)*(1+L44) -> 907.73642 | H44: =VLOOKUP(B44,'[1]2.1装饰工程'!$B$4:$H$231,7,0) -> 187.87 | I44: =VLOOKUP(B44,'[1]2.1装饰工程'!$B$4:$I$231,8,0) -> 562.56 | J44: =VLOOKUP(B44,'[1]2.1装饰工程'!$B$4:$J$231,9,0) -> 0 | K44: =VLOOKUP(B44,'[1]2.1装饰工程'!$B$4:$K$231,10,0) -> 1.63 | L44: =$L$4 -> 0.207 | M44: =F44*G44 -> 0
A45: 13 | B45: 200*200地砖地面 | C45: 1.200*200防滑地砖+专用瓷砖胶（200*200mm，12mm厚，哑光面，填缝剂与砖同颜色，防火等级：A级） 2.地砖间留2mm缝隙，美缝剂填缝 3.60厚水泥砂浆找平层， 30mm厚1:3干性水泥砂浆粘接层 4..包含止水坎、卫生间找坡，卫生间蹲坑侧面等综合考虑，地插、地漏部位提前预留 5.其他详见SI手册、品牌表及标准节点等，满足施工要求及国家规范 | D45: 工程量按设计图示尺寸以实铺面积计算 | E45: m2 | G45: =(H45+I45+J45+K45)*(1+L45) -> 249.08859 | H45: =VLOOKUP(B45,'[1]2.1装饰工程'!$B$4:$H$231,7,0) -> 45.1 | I45: =VLOOKUP(B45,'[1]2.1装饰工程'!$B$4:$I$231,8,0) -> 161.27 | J45: =VLOOKUP(B45,'[1]2.1装饰工程'!$B$4:$J$231,9,0) -> 0 | K45: =VLOOKUP(B45,'[1]2.1装饰工程'!$B$4:$K$231,10,0) -> 0 | L45: =$L$4 -> 0.207 | M45: =F45*G45 -> 0
A46: 14 | B46: 300*600地砖地面 | C46: 1.300*600防滑地砖+专用瓷砖胶（厚度和颜色综合考虑） 2.地砖间留2mm缝隙，美缝剂填缝 3.60厚水泥砂浆找平层， 30mm厚1:3干性水泥砂浆粘接层 4.包含止水坎、卫生间找坡，卫生间蹲坑侧面等综合考虑，地插、地漏部位提前预留 5.其他详见SI手册、品牌表及标准节点等，满足施工要求及国家规范 | D46: 工程量按设计图示尺寸以实铺面积计算 | E46: m2 | G46: =(H46+I46+J46+K46)*(1+L46) -> 235.73917 | H46: =VLOOKUP(B46,'[1]2.1装饰工程'!$B$4:$H$231,7,0) -> 44.03 | I46: =VLOOKUP(B46,'[1]2.1装饰工程'!$B$4:$I$231,8,0) -> 151.28 | J46: =VLOOKUP(B46,'[1]2.1装饰工程'!$B$4:$J$231,9,0) -> 0 | K46: =VLOOKUP(B46,'[1]2.1装饰工程'!$B$4:$K$231,10,0) -> 0 | L46: =$L$4 -> 0.207 | M46: =F46*G46 -> 0
A47: 15 | B47: 600*600地砖地面 | C47: 1.600*600防滑地砖+专用瓷砖胶（600*600mm，10mm±1mm厚，哑光面，灰色美缝剂，防火等级：A级） 2.地砖间留2mm缝隙，美缝剂填缝 3.60厚水泥砂浆找平层， 30mm厚1:3干性水泥砂浆粘接层 4.包含止水坎、卫生间找坡，卫生间蹲坑侧面等综合考虑，地插、地漏部位提前预留 5.其他详见SI手册、品牌表及标准节点等，满足施工要求及国家规范 | D47: 工程量按设计图示尺寸以实铺面积计算 | E47: m2 | G47: =(H47+I47+J47+K47)*(1+L47) -> 223.66917 | H47: =VLOOKUP(B47,'[1]2.1装饰工程'!$B$4:$H$231,7,0) -> 44.03 | I47: =VLOOKUP(B47,'[1]2.1装饰工程'!$B$4:$I$231,8,0) -> 141.28 | J47: =VLOOKUP(B47,'[1]2.1装饰工程'!$B$4:$J$231,9,0) -> 0 | K47: =VLOOKUP(B47,'[1]2.1装饰工程'!$B$4:$K$231,10,0) -> 0 | L47: =$L$4 -> 0.207 | M47: =F47*G47 -> 0
A48: 16 | B48: 600*1200地砖地面 | C48: 1.600*1200防滑地砖+专用瓷砖胶（600*1200mm，10mm±1mm厚，哑光面，灰色美缝剂， 防火等级：A级） 2.地砖间留2mm缝隙，美缝剂填缝 3.60厚水泥砂浆找平层， 30mm厚1:3干性水泥砂浆粘接层 4.包含止水坎、卫生间找坡，卫生间蹲坑侧面等综合考虑，地插、地漏部位提前预留 5.其他详见SI手册、品牌表及标准节点等，满足施工要求及国家规范 | D48: 工程量按设计图示尺寸以实铺面积计算 | E48: m2 | F48: 50 | G48: =(H48+I48+J48+K48)*(1+L48) -> 304.18814 | H48: =1.15*44.03 -> 50.6345 | I48: =1.15*160.77 -> 184.8855 | J48: 15 | K48: 1.5 | L48: =$L$4 -> 0.207 | M48: =F48*G48 -> 15209.407
A49: 17 | B49: 木纹砖地面 | C49: 1.仿木纹砖地面+专用瓷砖胶（1200*200mm，10mm±2mm厚，同色美缝剂，防火等级：A） 2.地砖间留2mm缝隙，美缝剂填缝 3.60厚水泥砂浆找平层， 30mm厚1:3干性水泥砂浆粘接层 4.包含止水坎、卫生间找坡，卫生间蹲坑侧面等综合考虑，地插、地漏部位提前预留 5.其他详见SI手册、品牌表及标准节点等，满足施工要求及国家规范 | D49: 工程量按设计图示尺寸以实铺面积计算 | E49: m2 | F49: 50 | G49: =(H49+I49+J49+K49)*(1+L49) -> 299.27444 | H49: =1.15*44.03 -> 50.6345 | I49: =1.15*157.23 -> 180.8145 | J49: 15 | K49: 1.5 | L49: =$L$4 -> 0.207 | M49: =F49*G49 -> 14963.722
A50: 18 | B50: 水磨石砖地面600*1200 | C50: 1.水磨石砖地砖+专用瓷砖胶（10mm±1mm厚，哑光面，水磨石纹理，灰色美缝剂，防火等级：A级） 2.地砖间留2mm缝隙，美缝剂填缝 3.60厚水泥砂浆找平层， 30mm厚1:3干性水泥砂浆粘接层 4.包含止水坎、卫生间找坡，卫生间蹲坑侧面等综合考虑，地插、地漏部位提前预留 5.其他详见SI手册、品牌表及标准节点等，满足施工要求及国家规范 | D50: 工程量按设计图示尺寸以实铺面积计算 | E50: m2 | F50: 50 | G50: =(H50+I50+J50+K50)*(1+L50) -> 304.18814 | H50: =1.15*44.03 -> 50.6345 | I50: =1.15*160.77 -> 184.8855 | J50: 15 | K50: 1.5 | L50: =$L$4 -> 0.207 | M50: =F50*G50 -> 15209.407
A51: 19 | B51: 过门石地面 | C51: 1.过门石地面+专用胶（大理石尺寸厚度和颜色综合考虑） 2.地砖间留2mm缝隙，美缝剂填缝 3.60厚水泥砂浆找平层， 30mm厚1:3干性水泥砂浆粘接层 4.包含止水坎、卫生间找坡，卫生间蹲坑侧面等综合考虑，地插、地漏部位提前预留 5.其他详见SI手册、品牌表及标准节点等，满足施工要求及国家规范 | D51: 工程量按设计图示尺寸以实铺面积计算 | E51: m2 | F51: 1.5 | G51: =(H51+I51+J51+K51)*(1+L51) -> 475.96838 | H51: =VLOOKUP(B51,'[1]2.1装饰工程'!$B$4:$H$231,7,0) -> 50.28 | I51: =VLOOKUP(B51,'[1]2.1装饰工程'!$B$4:$I$231,8,0) -> 344.06 | J51: =VLOOKUP(B51,'[1]2.1装饰工程'!$B$4:$J$231,9,0) -> 0 | K51: =VLOOKUP(B51,'[1]2.1装饰工程'!$B$4:$K$231,10,0) -> 0 | L51: =$L$4 -> 0.207 | M51: =F51*G51 -> 713.95257
A52: 20 | B52: 网络防静电地板 | C52: 1.网络静电地板600*600（尺寸、厚度和颜色综合考虑） 2.可调节支架系统（铜带防静电） 3.1：3水泥砂浆抹面压实赶光 4.其他详见SI手册、品牌表及标准节点等，满足施工要求及国家规范 | D52: 工程量按设计图示尺寸以实铺面积计算 | E52: m2 | G52: =(H52+I52+J52+K52)*(1+L52) -> 356.065 | H52: =VLOOKUP(B52,'[1]2.1装饰工程'!$B$4:$H$231,7,0) -> 56.82 | I52: =VLOOKUP(B52,'[1]2.1装饰工程'!$B$4:$I$231,8,0) -> 238.18 | J52: =VLOOKUP(B52,'[1]2.1装饰工程'!$B$4:$J$231,9,0) -> 0 | K52: =VLOOKUP(B52,'[1]2.1装饰工程'!$B$4:$K$231,10,0) -> 0 | L52: =$L$4 -> 0.207 | M52: =F52*G52 -> 0
A53: 21 | B53: 防滑瓷砖楼梯踏步面层 | C53: 1.防滑瓷砖面层（尺寸、厚度和颜色综合考虑）+专用粘接剂 2.防滑槽处理+不锈钢金属条综合考虑 3.20厚水泥砂浆找平层 4.其他详见SI手册、品牌表及标准节点等，满足施工要求及国家规范 | D53: 工程量按设计图示尺寸以实铺面积计算 | E53: m2 | G53: =(H53+I53+J53+K53)*(1+L53) -> 283.31911 | H53: =VLOOKUP(B53,'[1]2.1装饰工程'!$B$4:$H$231,7,0) -> 134.08 | I53: =VLOOKUP(B53,'[1]2.1装饰工程'!$B$4:$I$231,8,0) -> 100.65 | J53: =VLOOKUP(B53,'[1]2.1装饰工程'!$B$4:$J$231,9,0) -> 0 | K53: =VLOOKUP(B53,'[1]2.1装饰工程'!$B$4:$K$231,10,0) -> 0 | L53: =$L$4 -> 0.207 | M53: =F53*G53 -> 0
A54: 22 | B54: 防尘垫 | C54: 1.防尘垫（（厚度：20mm 铝型材壁厚度>2mm，颜色综合考虑） 2.包含四周金属嵌条等综合考虑 3.其他详见SI手册、品牌表及标准节点等，满足施工要求及国家规范 | D54: 工程量按设计图示尺寸以面积计算 | E54: m2 | F54: 2 | G54: =(H54+I54+J54+K54)*(1+L54) -> 669.12459 | H54: =VLOOKUP(B54,'[1]2.1装饰工程'!$B$4:$H$231,7,0) -> 56.94 | I54: =VLOOKUP(B54,'[1]2.1装饰工程'!$B$4:$I$231,8,0) -> 497.43 | J54: =VLOOKUP(B54,'[1]2.1装饰工程'!$B$4:$J$231,9,0) -> 0 | K54: =VLOOKUP(B54,'[1]2.1装饰工程'!$B$4:$K$231,10,0) -> 0 | L54: =$L$4 -> 0.207 | M54: =F54*G54 -> 1338.2492
A55: 23 | B55: 3mm成品实心金属不锈钢收口条 | C55: 1.展厅地面不同材质处拼接处用3mm成品金属嵌条，高度尺寸可调 2.其他详见SI手册、品牌表及标准节点等，满足施工要求及国家规范 | D55: 按设计图示以长度计算 | E55: m | G55: =(H55+I55+J55+K55)*(1+L55) -> 49.585974 | H55: =1.15*3.24 -> 3.726 | I55: =1.15*29.44 -> 33.856 | J55: 3.5 | K55: 0 | L55: =$L$4 -> 0.207 | M55: =F55*G55 -> 0
A56: 24 | B56: 5mm成品实心金属不锈钢收口条 | C56: 1.成品实心金属收口条 2.展厅地面不同材质处拼接处用5mm成品金属嵌条，高度尺寸可调 3.工程量按水平长度计算 4.其他详见SI手册、品牌表及标准节点等，满足施工要求及国家规范 | D56: 按设计图示以长度计算 | E56: m | F56: 14.62 | G56: =(H56+I56+J56+K56)*(1+L56) -> 56.13757 | H56: =1.15*3.24 -> 3.726 | I56: =1.15*34.16 -> 39.284 | J56: 3.5 | K56: 0 | L56: =$L$4 -> 0.207 | M56: =F56*G56 -> 820.73127
A57: 25 | B57: 铝合金踢脚线 | C57: 1.1mm成品材质铝合金板（颜色见设计图）,高度50mm,内衬基层板 2.明装、暗装综合考虑，详见图纸设计要求 3.其他详见SI手册、品牌表及标准节点等，满足施工要求及国家规范 | D57: 按设计图示以长度计算 | E57: m | F57: 30 | G57: =(H57+I57+J57+K57)*(1+L57) -> 52.72176 | H57: =VLOOKUP(B57,'[1]2.1装饰工程'!$B$4:$H$231,7,0) -> 19.04 | I57: =VLOOKUP(B57,'[1]2.1装饰工程'!$B$4:$I$231,8,0) -> 24.64 | J57: =VLOOKUP(B57,'[1]2.1装饰工程'!$B$4:$J$231,9,0) -> 0 | K57: =VLOOKUP(B57,'[1]2.1装饰工程'!$B$4:$K$231,10,0) -> 0 | L57: =$L$4 -> 0.207 | M57: =F57*G57 -> 1581.6528
A58: 26 | B58: 不锈钢踢脚线 | C58: 1.1mm黑色不锈钢+基层板（颜色见设计图）,高度50mm 2.明装、暗装综合考虑，详见图纸设计要求 3.其他详见SI手册、品牌表及标准节点等，满足施工要求及国家规范 | D58: 按设计图示以长度计算 | E58: m | F58: 30 | G58: =(H58+I58+J58+K58)*(1+L58) -> 61.47251 | H58: =VLOOKUP(B58,'[1]2.1装饰工程'!$B$4:$H$231,7,0) -> 19.04 | I58: =VLOOKUP(B58,'[1]2.1装饰工程'!$B$4:$I$231,8,0) -> 31.89 | J58: =VLOOKUP(B58,'[1]2.1装饰工程'!$B$4:$J$231,9,0) -> 0 | K58: =VLOOKUP(B58,'[1]2.1装饰工程'!$B$4:$K$231,10,0) -> 0 | L58: =$L$4 -> 0.207 | M58: =F58*G58 -> 1844.1753
A59: 27 | B59: 烤漆不锈钢踢脚线 | C59: 1.1.2mm烤漆不锈钢（颜色见设计图）+基层板,高度50mm 2.明装、暗装综合考虑，详见图纸设计要求 3.其他详见SI手册、品牌表及标准节点等，满足施工要求及国家规范 | D59: 按设计图示以长度计算 | E59: m | F59: 30 | G59: =(H59+I59+J59+K59)*(1+L59) -> 64.74348 | H59: =VLOOKUP(B59,'[1]2.1装饰工程'!$B$4:$H$231,7,0) -> 19.04 | I59: =VLOOKUP(B59,'[1]2.1装饰工程'!$B$4:$I$231,8,0) -> 34.6 | J59: =VLOOKUP(B59,'[1]2.1装饰工程'!$B$4:$J$231,9,0) -> 0 | K59: =VLOOKUP(B59,'[1]2.1装饰工程'!$B$4:$K$231,10,0) -> 0 | L59: =$L$4 -> 0.207 | M59: =F59*G59 -> 1942.3044
A60: 28 | B60: PVC踢脚线 | C60: 1.PVC踢脚线（厚度颜色见设计图综合考虑）+粘接剂, 高度50mm 2.明装、暗装综合考虑，详见图纸设计要求 3.其他详见SI手册、品牌表及标准节点等，满足施工要求及国家规范 | D60: 按设计图示以长度计算 | E60: m | G60: =(H60+I60+J60+K60)*(1+L60) -> 32.32346 | H60: =VLOOKUP(B60,'[1]2.1装饰工程'!$B$4:$H$231,7,0) -> 6.59 | I60: =VLOOKUP(B60,'[1]2.1装饰工程'!$B$4:$I$231,8,0) -> 20.19 | J60: =VLOOKUP(B60,'[1]2.1装饰工程'!$B$4:$J$231,9,0) -> 0 | K60: =VLOOKUP(B60,'[1]2.1装饰工程'!$B$4:$K$231,10,0) -> 0 | L60: =$L$4 -> 0.207 | M60: =F60*G60 -> 0
A61: 29 | B61: 木踢脚线 | C61: 1.木质踢脚线（厚度颜色见设计图综合考虑）,高度50mm 2.明装、暗装综合考虑，详见图纸设计要求 3.其他详见SI手册、品牌表及标准节点等，满足施工要求及国家规范 | D61: 按设计图示以长度计算 | E61: m | G61: =(H61+I61+J61+K61)*(1+L61) -> 49.69219 | H61: =VLOOKUP(B61,'[1]2.1装饰工程'!$B$4:$H$231,7,0) -> 6.97 | I61: =VLOOKUP(B61,'[1]2.1装饰工程'!$B$4:$I$231,8,0) -> 34.2 | J61: =VLOOKUP(B61,'[1]2.1装饰工程'!$B$4:$J$231,9,0) -> 0 | K61: =VLOOKUP(B61,'[1]2.1装饰工程'!$B$4:$K$231,10,0) -> 0 | L61: =$L$4 -> 0.207 | M61: =F61*G61 -> 0
A62: 30 | B62: 地面暗藏灯槽 | C62: 1.地面暗藏灯槽 2.尺寸：L*W30*H50 3.材质：PCB+铝型材，散热性能佳，地踩灯，可抗车压，IP65至IP68 4.包含地面开槽，灯槽及灯罩等费用，不含灯带，其他详见SI手册、品牌表及标准节点等，满足施工要求及国家规范 | D62: 按设计图示以长度计算 | E62: m | G62: =(H62+I62+J62+K62)*(1+L62) -> 86.15566 | H62: =VLOOKUP(B62,'[1]2.1装饰工程'!$B$4:$H$231,7,0) -> 23.06 | I62: =VLOOKUP(B62,'[1]2.1装饰工程'!$B$4:$I$231,8,0) -> 48.32 | J62: =VLOOKUP(B62,'[1]2.1装饰工程'!$B$4:$J$231,9,0) -> 0 | K62: =VLOOKUP(B62,'[1]2.1装饰工程'!$B$4:$K$231,10,0) -> 0 | L62: =$L$4 -> 0.207 | M62: =F62*G62 -> 0
A63: 四 | B63: 墙面工程
A64: 1 | B64: 双面双层 防火石膏板墙 | C64: 1.骨架、边框材料种类、规格:100轻钢龙骨，厚度综合考虑详设计图纸及招标文件 2.基层:12mm防火纸面石膏板，详设计图纸 3.面层:12mm防火纸面石膏板，详设计图纸 4.内部:内衬防火岩棉，填岩棉容重100kg/m3 5.其他:龙骨、顶部接缝处理、防火密封胶、圆弧处收边、墙面检修口及其他等所需做法包含在综合单价内，高度综合考虑 | D64: 按设计图示尺寸以面积计算 | E64: m2 | F64: 20 | G64: =(H64+I64+J64+K64)*(1+L64) -> 308.35048 | H64: =1.15*104.8 -> 120.52 | I64: =1.15*110.39 -> 126.9485 | J64: 5.5 | K64: 2.5 | L64: =$L$4 -> 0.207 | M64: =F64*G64 -> 6167.0096
A65: 2 | B65: 双面双层 石膏板墙 | C65: 1.骨架、边框材料种类、规格:75轻钢龙骨，厚度综合考虑详设计图纸及招标文件 2.基层:9.5mm纸面石膏板，详设计图纸 3.面层:9.5mm纸面石膏板，详设计图纸 4.内部:内衬防火岩棉，填岩棉容重100kg/m3 5.其他:龙骨、顶部接缝处理、防火密封胶、圆弧处收边、墙面检修口及其他等所需做法包含在综合单价内，高度综合考虑 | D65: 按设计图示尺寸以面积计算 | E65: m2 | F65: 20 | G65: =(H65+I65+J65+K65)*(1+L65) -> 254.52009 | H65: =VLOOKUP(B65,'[1]2.1装饰工程'!$B$4:$H$231,7,0) -> 106.8 | I65: =VLOOKUP(B65,'[1]2.1装饰工程'!$B$4:$I$231,8,0) -> 104.07 | J65: =VLOOKUP(B65,'[1]2.1装饰工程'!$B$4:$J$231,9,0) -> 0 | K65: =VLOOKUP(B65,'[1]2.1装饰工程'!$B$4:$K$231,10,0) -> 0 | L65: =$L$4 -> 0.207 | M65: =F65*G65 -> 5090.4018
A66: 3 | B66: 单面双层 石膏板墙 | C66: 1.骨架、边框材料种类、规格:75轻钢龙骨，厚度综合考虑详设计图纸及招标文件 2.面层:9.5mm纸面石膏板，详设计图纸 3.内部:内衬防火岩棉，填岩棉容重100kg/m3 4.其他:龙骨、顶部接缝处理、防火密封胶、圆弧处收边、墙面检修口及其他等所需做法包含在综合单价内，高度综合考虑 | D66: 按设计图示尺寸以面积计算 | E66: m2 | F66: 20 | G66: =(H66+I66+J66+K66)*(1+L66) -> 195.67884 | H66: =VLOOKUP(B66,'[1]2.1装饰工程'!$B$4:$H$231,7,0) -> 60.46 | I66: =VLOOKUP(B66,'[1]2.1装饰工程'!$B$4:$I$231,8,0) -> 101.66 | J66: =VLOOKUP(B66,'[1]2.1装饰工程'!$B$4:$J$231,9,0) -> 0 | K66: =VLOOKUP(B66,'[1]2.1装饰工程'!$B$4:$K$231,10,0) -> 0 | L66: =$L$4 -> 0.207 | M66: =F66*G66 -> 3913.5768
A67: 4 | B67: 双面单层 石膏板墙 | C67: 1.骨架、边框材料种类、规格:75轻钢龙骨，厚度综合考虑详设计图纸及招标文件 2.面层:9.5mm纸面石膏板，详设计图纸 3.内部:内衬防火岩棉，填岩棉容重100kg/m3 4.其他:龙骨、顶部接缝处理、防火密封胶、圆弧处收边、墙面检修口及其他等所需做法包含在综合单价内，高度综合考虑 | D67: 按设计图示尺寸以面积计算 | E67: m2 | F67: 20 | G67: =(H67+I67+J67+K67)*(1+L67) -> 201.91903 | H67: =VLOOKUP(B67,'[1]2.1装饰工程'!$B$4:$H$231,7,0) -> 60.46 | I67: =VLOOKUP(B67,'[1]2.1装饰工程'!$B$4:$I$231,8,0) -> 106.83 | J67: =VLOOKUP(B67,'[1]2.1装饰工程'!$B$4:$J$231,9,0) -> 0 | K67: =VLOOKUP(B67,'[1]2.1装饰工程'!$B$4:$K$231,10,0) -> 0 | L67: =$L$4 -> 0.207 | M67: =F67*G67 -> 4038.3806
A68: 5 | B68: 单面单层 石膏板墙 | C68: 1.骨架、边框材料种类、规格:75轻钢龙骨，厚度综合考虑详设计图纸及招标文件 2.面层:12mm纸面石膏板，详设计图纸 3.内部:内衬防火岩棉，填岩棉容重100kg/m3 4.其他:龙骨、顶部接缝处理、防火密封胶、圆弧处收边、墙面检修口及其他等所需做法包含在综合单价内，高度综合考虑 | D68: 按设计图示尺寸以面积计算 | E68: m2 | F68: 20 | G68: =(H68+I68+J68+K68)*(1+L68) -> 167.0488 | H68: =VLOOKUP(B68,'[1]2.1装饰工程'!$B$4:$H$231,7,0) -> 57.61 | I68: =VLOOKUP(B68,'[1]2.1装饰工程'!$B$4:$I$231,8,0) -> 80.79 | J68: =VLOOKUP(B68,'[1]2.1装饰工程'!$B$4:$J$231,9,0) -> 0 | K68: =VLOOKUP(B68,'[1]2.1装饰工程'!$B$4:$K$231,10,0) -> 0 | L68: =$L$4 -> 0.207 | M68: =F68*G68 -> 3340.976
A69: 6 | B69: 单面单层 水泥板墙 | C69: 1.骨架、边框材料种类、规格:厚度：9.5mm 75轻钢龙骨，详设计图纸及招标文件 2.面层:单层单面水泥板，详设计图纸 3.其他:龙骨、顶部接缝处理、防火密封胶、圆弧处收边、墙面检修口及其他等所需做法包含在综合单价内，高度综合考虑 | D69: 按设计图示尺寸以面积计算 | E69: m2 | F69: 20 | G69: =(H69+I69+J69+K69)*(1+L69) -> 171.78024 | H69: =VLOOKUP(B69,'[1]2.1装饰工程'!$B$4:$H$231,7,0) -> 49.85 | I69: =VLOOKUP(B69,'[1]2.1装饰工程'!$B$4:$I$231,8,0) -> 92.47 | J69: =VLOOKUP(B69,'[1]2.1装饰工程'!$B$4:$J$231,9,0) -> 0 | K69: =VLOOKUP(B69,'[1]2.1装饰工程'!$B$4:$K$231,10,0) -> 0 | L69: =$L$4 -> 0.207 | M69: =F69*G69 -> 3435.6048
A70: 7 | B70: 单面单层 水泥板墙 | C70: 1.骨架、边框材料种类、规格:厚度：12mm 75轻钢龙骨，详设计图纸及招标文件 2.面层:单层单面水泥板，详设计图纸 3.其他:龙骨、顶部接缝处理、防火密封胶、圆弧处收边、墙面检修口及其他等所需做法包含在综合单价内，高度综合考虑 | D70: 按设计图示尺寸以面积计算 | E70: m2 | F70: 20 | G70: =(H70+I70+J70+K70)*(1+L70) -> 171.78024 | H70: =VLOOKUP(B70,'[1]2.1装饰工程'!$B$4:$H$231,7,0) -> 49.85 | I70: =VLOOKUP(B70,'[1]2.1装饰工程'!$B$4:$I$231,8,0) -> 92.47 | J70: =VLOOKUP(B70,'[1]2.1装饰工程'!$B$4:$J$231,9,0) -> 0 | K70: =VLOOKUP(B70,'[1]2.1装饰工程'!$B$4:$K$231,10,0) -> 0 | L70: =$L$4 -> 0.207 | M70: =F70*G70 -> 3435.6048
A71: 8 | B71: 单层单面硅酸钙板墙 | C71: 1.骨架、边框材料种类、规格:75轻钢龙骨，厚度综合考虑详设计图纸及招标文件 2.面层:硅酸钙板，详设计图纸 3.内部:内衬防火岩棉，填岩棉容重80kg/m3 4.其他:龙骨、顶部接缝处理、防火密封胶、圆弧处收边、墙面检修口及其他等所需做法包含在综合单价内，高度综合考虑 | D71: 按设计图示尺寸以面积计算 | E71: m2 | F71: 20 | G71: =(H71+I71+J71+K71)*(1+L71) -> 184.57444 | H71: =VLOOKUP(B71,'[1]2.1装饰工程'!$B$4:$H$231,7,0) -> 57.61 | I71: =VLOOKUP(B71,'[1]2.1装饰工程'!$B$4:$I$231,8,0) -> 95.31 | J71: =VLOOKUP(B71,'[1]2.1装饰工程'!$B$4:$J$231,9,0) -> 0 | K71: =VLOOKUP(B71,'[1]2.1装饰工程'!$B$4:$K$231,10,0) -> 0 | L71: =$L$4 -> 0.207 | M71: =F71*G71 -> 3691.4888
A72: 9 | B72: 砌块墙 | C72: 1.砌块品种、规格、强度等级详见节点图 2.墙体类型:综合考虑 3.砂浆强度等级:综合考虑 4.工作内容:砂浆制作、运输；砌砖、砌块；勾缝；材料运输 5.其他:详见招标文件、技术协议及效果图等，满足施工要求及技术规范 | D72: 按设计图示尺寸以体积计算 | E72: m3 | F72: 5 | G72: =(H72+I72+J72+K72)*(1+L72) -> 1053.3453 | H72: =1.15*216 -> 248.4 | I72: =1.15*528.18 -> 607.407 | J72: 15 | K72: 1.89 | L72: =$L$4 -> 0.207 | M72: =F72*G72 -> 5266.7264
A73: 10 | B73: 内墙面抹灰 | C73: 1.基层清理； 2.108胶素水泥砂浆一道，或界面剂一道 3.综合各类砂浆，做法综合考虑 | D73: 按设计图示尺寸以体积计算 | E73: m2 | G73: =(H73+I73+J73+K73)*(1+L73) -> 47.919107 | H73: =1.15*20.74 -> 23.851 | I73: 15 | J73: 0.85 | K73: 0 | L73: =$L$4 -> 0.207 | M73: =F73*G73 -> 0
A74: 11 | B74: 超白长虹玻璃隔断 | C74: 1.15mm超白长虹玻璃隔断 2.其他详见SI手册、品牌表及标准节点等，满足施工要求及国家规范 | D74: 按设计图示尺寸以面积计算 | E74: m2 | G74: =(H74+I74+J74+K74)*(1+L74) -> 677.40461 | H74: =VLOOKUP(B74,'[1]2.1装饰工程'!$B$4:$H$231,7,0) -> 63.87 | I74: =VLOOKUP(B74,'[1]2.1装饰工程'!$B$4:$I$231,8,0) -> 497.36 | J74: =VLOOKUP(B74,'[1]2.1装饰工程'!$B$4:$J$231,9,0) -> 0 | K74: =VLOOKUP(B74,'[1]2.1装饰工程'!$B$4:$K$231,10,0) -> 0 | L74: =$L$4 -> 0.207 | M74: =F74*G74 -> 0
A75: 12 | B75: 调差-增减一道9.5mm石膏板 | C75: 1.增减一道9.5mm石膏板 2.其他详见SI手册、品牌表及标准节点等，满足施工要求及国家规范 | D75: 按设计图示尺寸以面积计算 | E75: m2 | G75: =(H75+I75+J75+K75)*(1+L75) -> 32.29932 | H75: =VLOOKUP(B75,'[1]2.1装饰工程'!$B$4:$H$231,7,0) -> 15.85 | I75: =VLOOKUP(B75,'[1]2.1装饰工程'!$B$4:$I$231,8,0) -> 10.91 | J75: =VLOOKUP(B75,'[1]2.1装饰工程'!$B$4:$J$231,9,0) -> 0 | K75: =VLOOKUP(B75,'[1]2.1装饰工程'!$B$4:$K$231,10,0) -> 0 | L75: =$L$4 -> 0.207 | M75: =F75*G75 -> 0
A76: 13 | B76: 调差-增减一道12mm石膏板 | C76: 1.增减一道12mm石膏板 2.其他详见SI手册、品牌表及标准节点等，满足施工要求及国家规范 | D76: 按设计图示尺寸以面积计算 | E76: m2 | G76: =(H76+I76+J76+K76)*(1+L76) -> 33.47011 | H76: =VLOOKUP(B76,'[1]2.1装饰工程'!$B$4:$H$231,7,0) -> 15.85 | I76: =VLOOKUP(B76,'[1]2.1装饰工程'!$B$4:$I$231,8,0) -> 11.88 | J76: =VLOOKUP(B76,'[1]2.1装饰工程'!$B$4:$J$231,9,0) -> 0 | K76: =VLOOKUP(B76,'[1]2.1装饰工程'!$B$4:$K$231,10,0) -> 0 | L76: =$L$4 -> 0.207 | M76: =F76*G76 -> 0
A77: 14 | B77: 调差-增减一道12mm防火石膏板 | C77: 1.增减一道12mm防火石膏板 2.其他详见SI手册、品牌表及标准节点等，满足施工要求及国家规范 | D77: 按设计图示尺寸以面积计算 | E77: m2 | G77: =(H77+I77+J77+K77)*(1+L77) -> 41.25526 | H77: =VLOOKUP(B77,'[1]2.1装饰工程'!$B$4:$H$231,7,0) -> 20.85 | I77: =VLOOKUP(B77,'[1]2.1装饰工程'!$B$4:$I$231,8,0) -> 13.33 | J77: =VLOOKUP(B77,'[1]2.1装饰工程'!$B$4:$J$231,9,0) -> 0 | K77: =VLOOKUP(B77,'[1]2.1装饰工程'!$B$4:$K$231,10,0) -> 0 | L77: =$L$4 -> 0.207 | M77: =F77*G77 -> 0
A78: 15 | B78: 调差-增减一道9mm阻燃板 | C78: 1.增减一道9mm阻燃板 2.其他详见SI手册、品牌表及标准节点等，满足施工要求及国家规范 | D78: 按设计图示尺寸以面积计算 | E78: m2 | G78: =(H78+I78+J78+K78)*(1+L78) -> 61.6777 | H78: =VLOOKUP(B78,'[1]2.1装饰工程'!$B$4:$H$231,7,0) -> 11.97 | I78: =VLOOKUP(B78,'[1]2.1装饰工程'!$B$4:$I$231,8,0) -> 39.13 | J78: =VLOOKUP(B78,'[1]2.1装饰工程'!$B$4:$J$231,9,0) -> 0 | K78: =VLOOKUP(B78,'[1]2.1装饰工程'!$B$4:$K$231,10,0) -> 0 | L78: =$L$4 -> 0.207 | M78: =F78*G78 -> 0
A79: 16 | B79: 调差-增减一道12mm阻燃板 | C79: 1.增减一道12mm阻燃板 2.其他详见SI手册、品牌表及标准节点等，满足施工要求及国家规范 | D79: 按设计图示尺寸以面积计算 | E79: m2 | G79: =(H79+I79+J79+K79)*(1+L79) -> 70.11463 | H79: =VLOOKUP(B79,'[1]2.1装饰工程'!$B$4:$H$231,7,0) -> 11.97 | I79: =VLOOKUP(B79,'[1]2.1装饰工程'!$B$4:$I$231,8,0) -> 46.12 | J79: =VLOOKUP(B79,'[1]2.1装饰工程'!$B$4:$J$231,9,0) -> 0 | K79: =VLOOKUP(B79,'[1]2.1装饰工程'!$B$4:$K$231,10,0) -> 0 | L79: =$L$4 -> 0.207 | M79: =F79*G79 -> 0
A80: 17 | B80: 调差-增减一道15mm阻燃板 | C80: 1.增减一道15mm阻燃板 2.其他详见SI手册、品牌表及标准节点等，满足施工要求及国家规范 | D80: 按设计图示尺寸以面积计算 | E80: m2 | G80: =(H80+I80+J80+K80)*(1+L80) -> 78.44293 | H80: =VLOOKUP(B80,'[1]2.1装饰工程'!$B$4:$H$231,7,0) -> 11.97 | I80: =VLOOKUP(B80,'[1]2.1装饰工程'!$B$4:$I$231,8,0) -> 53.02 | J80: =VLOOKUP(B80,'[1]2.1装饰工程'!$B$4:$J$231,9,0) -> 0 | K80: =VLOOKUP(B80,'[1]2.1装饰工程'!$B$4:$K$231,10,0) -> 0 | L80: =$L$4 -> 0.207 | M80: =F80*G80 -> 0
A81: 18 | B81: 调差-增减一道18mm阻燃板 | C81: 1.增减一道18mm阻燃板 2.其他详见SI手册、品牌表及标准节点等，满足施工要求及国家规范 | D81: 按设计图示尺寸以面积计算 | E81: m2 | G81: =(H81+I81+J81+K81)*(1+L81) -> 89.29386 | H81: =VLOOKUP(B81,'[1]2.1装饰工程'!$B$4:$H$231,7,0) -> 11.97 | I81: =VLOOKUP(B81,'[1]2.1装饰工程'!$B$4:$I$231,8,0) -> 62.01 | J81: =VLOOKUP(B81,'[1]2.1装饰工程'!$B$4:$J$231,9,0) -> 0 | K81: =VLOOKUP(B81,'[1]2.1装饰工程'!$B$4:$K$231,10,0) -> 0 | L81: =$L$4 -> 0.207 | M81: =F81*G81 -> 0
A82: 19 | B82: 调差-增减一道75龙骨（含岩棉） | C82: 1.增减一道75龙骨（含岩棉） 2.其他详见SI手册、品牌表及标准节点等，满足施工要求及国家规范 | D82: 按设计图示尺寸以面积计算 | E82: m2 | G82: =(H82+I82+J82+K82)*(1+L82) -> 101.23109 | H82: =VLOOKUP(B82,'[1]2.1装饰工程'!$B$4:$H$231,7,0) -> 30.12 | I82: =VLOOKUP(B82,'[1]2.1装饰工程'!$B$4:$I$231,8,0) -> 53.75 | J82: =VLOOKUP(B82,'[1]2.1装饰工程'!$B$4:$J$231,9,0) -> 0 | K82: =VLOOKUP(B82,'[1]2.1装饰工程'!$B$4:$K$231,10,0) -> 0 | L82: =$L$4 -> 0.207 | M82: =F82*G82 -> 0
A83: 20 | B83: 调差-增减一道100龙骨（含岩棉） | C83: 1.增减一道100龙骨（含岩棉） 2.其他详见SI手册、品牌表及标准节点等，满足施工要求及国家规范 | D83: 按设计图示尺寸以面积计算 | E83: m2 | G83: =(H83+I83+J83+K83)*(1+L83) -> 116.2341 | H83: =VLOOKUP(B83,'[1]2.1装饰工程'!$B$4:$H$231,7,0) -> 30.12 | I83: =VLOOKUP(B83,'[1]2.1装饰工程'!$B$4:$I$231,8,0) -> 66.18 | J83: =VLOOKUP(B83,'[1]2.1装饰工程'!$B$4:$J$231,9,0) -> 0 | K83: =VLOOKUP(B83,'[1]2.1装饰工程'!$B$4:$K$231,10,0) -> 0 | L83: =$L$4 -> 0.207 | M83: =F83*G83 -> 0
A84: 21 | B84: 调差-增减一道120龙骨（含岩棉） | C84: 1.增减一道120龙骨（含岩棉） 2.其他详见SI手册、品牌表及标准节点等，满足施工要求及国家规范 | D84: 按设计图示尺寸以面积计算 | E84: m2 | G84: =(H84+I84+J84+K84)*(1+L84) -> 131.49058 | H84: =VLOOKUP(B84,'[1]2.1装饰工程'!$B$4:$H$231,7,0) -> 30.12 | I84: =VLOOKUP(B84,'[1]2.1装饰工程'!$B$4:$I$231,8,0) -> 78.82 | J84: =VLOOKUP(B84,'[1]2.1装饰工程'!$B$4:$J$231,9,0) -> 0 | K84: =VLOOKUP(B84,'[1]2.1装饰工程'!$B$4:$K$231,10,0) -> 0 | L84: =$L$4 -> 0.207 | M84: =F84*G84 -> 0
A85: 22 | B85: 调差-增减一道150龙骨（含岩棉） | C85: 1.增减一道150龙骨（含岩棉） 2.其他详见SI手册、品牌表及标准节点等，满足施工要求及国家规范 | D85: 按设计图示尺寸以面积计算 | E85: m2 | G85: =(H85+I85+J85+K85)*(1+L85) -> 143.19848 | H85: =VLOOKUP(B85,'[1]2.1装饰工程'!$B$4:$H$231,7,0) -> 52.48 | I85: =VLOOKUP(B85,'[1]2.1装饰工程'!$B$4:$I$231,8,0) -> 66.16 | J85: =VLOOKUP(B85,'[1]2.1装饰工程'!$B$4:$J$231,9,0) -> 0 | K85: =VLOOKUP(B85,'[1]2.1装饰工程'!$B$4:$K$231,10,0) -> 0 | L85: =$L$4 -> 0.207 | M85: =F85*G85 -> 0
A86: 23 | B86: 人造石干挂 | C86: 1.钢管+不锈钢挂件+20mm人造石，规格详见节点图 2.人造石颜色厚度综合考虑,阳角采用半径不小于50mm成品圆弧，详见施工图,不锈钢挂件、龙骨根据高度和位置深化设计，其费用含在固定综合单价中 3.如墙面有暗门，该报价包含暗门施工费用 4.其他详见SI手册、品牌表及标准节点等，满足施工要求及国家规范 | D86: 按设计图示尺寸以面积计算 | E86: m2 | F86: 15 | G86: =(H86+I86+J86+K86)*(1+L86) -> 845.31038 | H86: =VLOOKUP(B86,'[1]2.1装饰工程'!$B$4:$H$231,7,0) -> 144.9 | I86: =VLOOKUP(B86,'[1]2.1装饰工程'!$B$4:$I$231,8,0) -> 555.44 | J86: =VLOOKUP(B86,'[1]2.1装饰工程'!$B$4:$J$231,9,0) -> 0 | K86: =VLOOKUP(B86,'[1]2.1装饰工程'!$B$4:$K$231,10,0) -> 0 | L86: =$L$4 -> 0.207 | M86: =F86*G86 -> 12679.656
A87: 24 | B87: 人造石粘贴 | C87: 1.20mm人造石（含粘结剂） 2.人造石颜色厚度综合考虑,阳角采用半径不小于50mm成品圆弧，详见施工图 3.如墙面有暗门，该报价包含暗门施工费用,如涉及到包消防栓，其施工费用也含在该单价中 4.其他详见SI手册、品牌表及标准节点等，满足施工要求及国家规范 | D87: 按设计图示尺寸以面积计算 | E87: m2 | F87: 15 | G87: =(H87+I87+J87+K87)*(1+L87) -> 611.51448 | H87: =VLOOKUP(B87,'[1]2.1装饰工程'!$B$4:$H$231,7,0) -> 106.19 | I87: =VLOOKUP(B87,'[1]2.1装饰工程'!$B$4:$I$231,8,0) -> 400.45 | J87: =VLOOKUP(B87,'[1]2.1装饰工程'!$B$4:$J$231,9,0) -> 0 | K87: =VLOOKUP(B87,'[1]2.1装饰工程'!$B$4:$K$231,10,0) -> 0 | L87: =$L$4 -> 0.207 | M87: =F87*G87 -> 9172.7172
A88: 25 | B88: 柔光石英石粘贴 | C88: 1.20mm石英石（含粘结剂） 2.石英石颜色厚度综合考虑,阳角采用半径不小于50mm成品圆弧，详见施工图 3.如墙面有暗门，该报价包含暗门施工费用,如涉及到包消防栓，其施工费用也含在该单价中 4.其他详见SI手册、品牌表及标准节点等，满足施工要求及国家规范 | D88: 按设计图示尺寸以面积计算 | E88: m2 | F88: 15 | G88: =(H88+I88+J88+K88)*(1+L88) -> 671.86448 | H88: =VLOOKUP(B88,'[1]2.1装饰工程'!$B$4:$H$231,7,0) -> 106.19 | I88: =VLOOKUP(B88,'[1]2.1装饰工程'!$B$4:$I$231,8,0) -> 450.45 | J88: =VLOOKUP(B88,'[1]2.1装饰工程'!$B$4:$J$231,9,0) -> 0 | K88: =VLOOKUP(B88,'[1]2.1装饰工程'!$B$4:$K$231,10,0) -> 0 | L88: =$L$4 -> 0.207 | M88: =F88*G88 -> 10077.967
A89: 26 | B89: 铝塑板墙面 | C89: 1.3mm铝塑板面层（含基层及龙骨） 2.铝塑板颜色、厚度综合考虑,阳角采用半径不小于50mm成品圆弧，详见施工图，其费用含在固定综合单价中 3.如墙面有暗门，该报价包含暗门施工费用 4.其他详见SI手册、品牌表及标准节点等，满足施工要求及国家规范 | D89: 按设计图示尺寸以面积计算 | E89: m2 | F89: 15 | G89: =(H89+I89+J89+K89)*(1+L89) -> 434.6407 | H89: =VLOOKUP(B89,'[1]2.1装饰工程'!$B$4:$H$231,7,0) -> 251.56 | I89: =VLOOKUP(B89,'[1]2.1装饰工程'!$B$4:$I$231,8,0) -> 108.54 | J89: =VLOOKUP(B89,'[1]2.1装饰工程'!$B$4:$J$231,9,0) -> 0 | K89: =VLOOKUP(B89,'[1]2.1装饰工程'!$B$4:$K$231,10,0) -> 0 | L89: =$L$4 -> 0.207 | M89: =F89*G89 -> 6519.6105
A90: 27 | B90: 铝单板墙面 | C90: 1.2mm铝单板面层（含基层及龙骨） 2.铝单板颜色、厚度综合考虑,阳角采用半径不小于50mm成品圆弧，详见施工图，其费用含在固定综合单价中 3.如墙面有暗门，该报价包含暗门施工费用 4.其他详见SI手册、品牌表及标准节点等，满足施工要求及国家规范 | D90: 按设计图示尺寸以面积计算 | E90: m2 | F90: 15 | G90: =(H90+I90+J90+K90)*(1+L90) -> 619.38412 | H90: =VLOOKUP(B90,'[1]2.1装饰工程'!$B$4:$H$231,7,0) -> 168.17 | I90: =VLOOKUP(B90,'[1]2.1装饰工程'!$B$4:$I$231,8,0) -> 344.99 | J90: =VLOOKUP(B90,'[1]2.1装饰工程'!$B$4:$J$231,9,0) -> 0 | K90: =VLOOKUP(B90,'[1]2.1装饰工程'!$B$4:$K$231,10,0) -> 0 | L90: =$L$4 -> 0.207 | M90: =F90*G90 -> 9290.7618
A91: 28 | B91: 蜂窝铝板墙面 | C91: 1.面层:木纹蜂窝铝板（颜色综合考虑），详设计图纸 2.厚度：4mm（金属板） 3.基层:15厚阻燃板基层（含龙骨） 4.其他:顶部接缝处理、防火密封胶、圆弧处收边及其他等所需做法包含在综合单价内，详见招标文件、技术协议及效果图 | D91: 按设计图示尺寸以面积计算 | E91: m2 | F91: 10 | G91: =(H91+I91+J91+K91)*(1+L91) -> 792.8783 | H91: =VLOOKUP(B91,'[1]2.1装饰工程'!$B$4:$H$231,7,0) -> 148.17 | I91: =VLOOKUP(B91,'[1]2.1装饰工程'!$B$4:$I$231,8,0) -> 508.73 | J91: =VLOOKUP(B91,'[1]2.1装饰工程'!$B$4:$J$231,9,0) -> 0 | K91: =VLOOKUP(B91,'[1]2.1装饰工程'!$B$4:$K$231,10,0) -> 0 | L91: =$L$4 -> 0.207 | M91: =F91*G91 -> 7928.783
A92: 29 | B92: 制布纹复合板 | C92: 1.制布纹复合板面层4mm（含基层及龙骨），厚度及颜色综合考虑详设计图纸 2.顶部接缝处理、防火密封胶、圆弧处收边及其他等所需做法包含在综合单价内，详见招标文件、技术协议及效果图 | D92: 工程量按垂直投影面积计算 | E92: m2 | F92: 10 | G92: =(H92+I92+J92+K92)*(1+L92) -> 547.47106 | H92: =VLOOKUP(B92,'[1]2.1装饰工程'!$B$4:$H$231,7,0) -> 64.44 | I92: =VLOOKUP(B92,'[1]2.1装饰工程'!$B$4:$I$231,8,0) -> 378.79 | J92: =VLOOKUP(B92,'[1]2.1装饰工程'!$B$4:$J$231,9,0) -> 0 | K92: =VLOOKUP(B92,'[1]2.1装饰工程'!$B$4:$K$231,10,0) -> 10.35 | L92: =$L$4 -> 0.207 | M92: =F92*G92 -> 5474.7106
A93: 30 | B93: 木饰面墙面 | C93: 1.面层木饰面（贴面），厚度及颜色综合考虑详设计图纸 2.规格：1200*2400mm 3.基层；含粘贴剂 4.其他:顶部接缝处理、防火密封胶、圆弧处收边、沉头自攻螺丝及其他等所需做法包含在综合单价内，详见招标文件、技术协议及效果图 | D93: 按设计图示尺寸以面积计算 | E93: m2 | F93: 10 | G93: =(H93+I93+J93+K93)*(1+L93) -> 619.89106 | H93: =VLOOKUP(B93,'[1]2.1装饰工程'!$B$4:$H$231,7,0) -> 64.44 | I93: =VLOOKUP(B93,'[1]2.1装饰工程'!$B$4:$I$231,8,0) -> 438.79 | J93: =VLOOKUP(B93,'[1]2.1装饰工程'!$B$4:$J$231,9,0) -> 0 | K93: =VLOOKUP(B93,'[1]2.1装饰工程'!$B$4:$K$231,10,0) -> 10.35 | L93: =$L$4 -> 0.207 | M93: =F93*G93 -> 6198.9106
A94: 31 | B94: 木饰面墙面 | C94: 1.成品木饰面，厚度及颜色综合考虑详设计图纸 2.基层:详见施工图,不锈钢挂件、龙骨根据高度和位置深化设计，其费用含在固定综合单价中 3.其他:顶部接缝处理、防火密封胶、圆弧处收边、沉头自攻螺丝及其他等所需做法包含在综合单价内，详见招标文件、技术协议及效果图 | D94: 按设计图示尺寸以面积计算 | E94: m2 | F94: 10 | G94: =(H94+I94+J94+K94)*(1+L94) -> 619.89106 | H94: =VLOOKUP(B94,'[1]2.1装饰工程'!$B$4:$H$231,7,0) -> 64.44 | I94: =VLOOKUP(B94,'[1]2.1装饰工程'!$B$4:$I$231,8,0) -> 438.79 | J94: =VLOOKUP(B94,'[1]2.1装饰工程'!$B$4:$J$231,9,0) -> 0 | K94: =VLOOKUP(B94,'[1]2.1装饰工程'!$B$4:$K$231,10,0) -> 10.35 | L94: =$L$4 -> 0.207 | M94: =F94*G94 -> 6198.9106
A95: 32 | B95: 木饰面墙面 | C95: 1.铝板木皮饰面，1200*2400mm/1500*3000mm厚度2mm厚度及颜色综合考虑详设计图纸 2.基层:含粘接剂 3.其他:顶部接缝处理、防火密封胶、圆弧处收边、沉头自攻螺丝及其他等所需做法包含在综合单价内，详见招标文件、技术协议及效果图 | D95: 按设计图示尺寸以面积计算 | E95: m2 | F95: 10 | G95: =(H95+I95+J95+K95)*(1+L95) -> 619.89106 | H95: =VLOOKUP(B95,'[1]2.1装饰工程'!$B$4:$H$231,7,0) -> 64.44 | I95: =VLOOKUP(B95,'[1]2.1装饰工程'!$B$4:$I$231,8,0) -> 438.79 | J95: =VLOOKUP(B95,'[1]2.1装饰工程'!$B$4:$J$231,9,0) -> 0 | K95: =VLOOKUP(B95,'[1]2.1装饰工程'!$B$4:$K$231,10,0) -> 10.35 | L95: =$L$4 -> 0.207 | M95: =F95*G95 -> 6198.9106
A96: 33 | B96: 铝格栅墙面 | C96: 1.面层:铝格栅+铝制基层（含龙骨），厚度及颜色详设计图纸 2.规格：25*25*1.2mm 3.基层:专用连接件 4.其他:顶部接缝处理、防火密封胶、圆弧处收边、沉头自攻螺丝及其他等所需做法包含在综合单价内，详见招标文件、技术协议及效果图 | D96: 按设计图示尺寸以面积计算 | E96: m2 | F96: 10 | G96: =(H96+I96+J96+K96)*(1+L96) -> 624.63457 | H96: =VLOOKUP(B96,'[1]2.1装饰工程'!$B$4:$H$231,7,0) -> 68.17 | I96: =VLOOKUP(B96,'[1]2.1装饰工程'!$B$4:$I$231,8,0) -> 449.34 | J96: =VLOOKUP(B96,'[1]2.1装饰工程'!$B$4:$J$231,9,0) -> 0 | K96: =VLOOKUP(B96,'[1]2.1装饰工程'!$B$4:$K$231,10,0) -> 0 | L96: =$L$4 -> 0.207 | M96: =F96*G96 -> 6246.3457
A97: 34 | B97: 定制布纹金属复合板模块 | C97: 1.面层:定制布纹金属复合板模块（含基层及龙骨），颜色综合考虑详设计图纸 2.规格：200*2400mm/3000mm；4mm 3.基层:专用连接件 4.其他:顶部接缝处理、防火密封胶、圆弧处收边、沉头自攻螺丝及其他等所需做法包含在综合单价内，详见招标文件、技术协议及效果图 | D97: 按设计图示尺寸以面积计算 | E97: m2 | F97: 10 | G97: =(H97+I97+J97+K97)*(1+L97) -> 567.29 | H97: =VLOOKUP(B97,'[1]2.1装饰工程'!$B$4:$H$231,7,0) -> 0 | I97: =VLOOKUP(B97,'[1]2.1装饰工程'!$B$4:$I$231,8,0) -> 470 | J97: =VLOOKUP(B97,'[1]2.1装饰工程'!$B$4:$J$231,9,0) -> 0 | K97: =VLOOKUP(B97,'[1]2.1装饰工程'!$B$4:$K$231,10,0) -> 0 | L97: =$L$4 -> 0.207 | M97: =F97*G97 -> 5672.9
A98: 35 | B98: 定制木纹金属复合板模块 | C98: 1.面层:定制木纹金属复合板模块（含基层及龙骨），颜色综合考虑详设计图纸 2.厚度：4mm（金属板） 3.基层:专用连接件 4.其他:顶部接缝处理、防火密封胶、圆弧处收边、沉头自攻螺丝及其他等所需做法包含在综合单价内，详见招标文件、技术协议及效果图 | D98: 按设计图示尺寸以面积计算 | E98: m2 | F98: 10 | G98: =(H98+I98+J98+K98)*(1+L98) -> 579.36 | H98: =VLOOKUP(B98,'[1]2.1装饰工程'!$B$4:$H$231,7,0) -> 0 | I98: =VLOOKUP(B98,'[1]2.1装饰工程'!$B$4:$I$231,8,0) -> 480 | J98: =VLOOKUP(B98,'[1]2.1装饰工程'!$B$4:$J$231,9,0) -> 0 | K98: =VLOOKUP(B98,'[1]2.1装饰工程'!$B$4:$K$231,10,0) -> 0 | L98: =$L$4 -> 0.207 | M98: =F98*G98 -> 5793.6
A99: 36 | B99: 毛毡吸音板 | C99: 1.毛毡吸音板 2.厚度：9mm 3.其他:其他等所需做法包含在综合单价内，详见招标文件、技术协议及效果图 | D99: 按设计图示尺寸以面积计算 | E99: m2 | G99: =(H99+I99+J99+K99)*(1+L99) -> 240.50682 | H99: =VLOOKUP(B99,'[1]2.1装饰工程'!$B$4:$H$231,7,0) -> 52.07 | I99: =VLOOKUP(B99,'[1]2.1装饰工程'!$B$4:$I$231,8,0) -> 147.19 | J99: =VLOOKUP(B99,'[1]2.1装饰工程'!$B$4:$J$231,9,0) -> 0 | K99: =VLOOKUP(B99,'[1]2.1装饰工程'!$B$4:$K$231,10,0) -> 0 | L99: =$L$4 -> 0.207 | M99: =F99*G99 -> 0
A100: 37 | B100: 内墙水泥砂浆 | C100: 1.墙面刷20厚水泥砂浆基层 2.其他详见SI手册、品牌表及标准节点等，满足施工要求及国家规范 | D100: 按设计图示尺寸以面积计算 | E100: m2 | G100: =(H100+I100+J100+K100)*(1+L100) -> 41.46045 | H100: =VLOOKUP(B100,'[1]2.1装饰工程'!$B$4:$H$231,7,0) -> 26.74 | I100: =VLOOKUP(B100,'[1]2.1装饰工程'!$B$4:$I$231,8,0) -> 7.61 | J100: =VLOOKUP(B100,'[1]2.1装饰工程'!$B$4:$J$231,9,0) -> 0 | K100: =VLOOKUP(B100,'[1]2.1装饰工程'!$B$4:$K$231,10,0) -> 0 | L100: =$L$4 -> 0.207 | M100: =F100*G100 -> 0
...

Sheet 2.2强电工程
A1: 长城智选商超店装修项目装饰工程
A2: 序号 | B2: 分部分项名称 | C2: 项目特征 | D2: 计量规则 | E2: 单位 | F2: 工程量 | G2: 综合单价 | H2: 人工 | I2: 主材 | J2: 辅材 | K2: 机械 | L2: 其他综合费率 | M2: 合计 | N2: 备注
A3: 一 | B3: 配电系统
A4: 1 | B4: 落地式配电箱 | C4: 1.名称:落地式配电箱 2.基础形式、材质、规格:10#基础槽钢 3.接线端子材质、规格:按设计及规范要求 4.端子板外部接线材质、规格:按设计及规范要求 5.安装方式:落地式 6.其他:含智能电表、时控开关、电气元器件及配套附件成套费用 | D4: 按设计图示数量计算 | E4: 台 | F4: 1 | G4: =(H4+I4+J4+K4)*(1+L4) -> 11126.126 | H4: =VLOOKUP(B4,'[1]2.2强电工程'!$B$4:$H$254,7,0) -> 524.73 | I4: =VLOOKUP(B4,'[1]2.2强电工程'!$B$4:$I$254,8,0) -> 8637.4 | J4: =VLOOKUP(B4,'[1]2.2强电工程'!$B$4:$J$254,9,0) -> 36.96 | K4: =VLOOKUP(B4,'[1]2.2强电工程'!$B$4:$K$254,10,0) -> 18.91 | L4: ='2.1装饰工程'!$L$4 -> 0.207 | M4: =F4*G4 -> 11126.126
A5: 2 | B5: 落地式配电箱（IP65防水型） | C5: 1.名称:落地式配电箱（IP65防水型） 2.基础形式、材质、规格:10#基础槽钢 3.接线端子材质、规格:按设计及规范要求 4.端子板外部接线材质、规格:按设计及规范要求 5.安装方式:落地式 6.其他:含智能电表、时控开关、电气元器件及配套附件成套费用 | D5: 按设计图示数量计算 | E5: 台 | G5: =(H5+I5+J5+K5)*(1+L5) -> 11446.572 | H5: =VLOOKUP(B5,'[1]2.2强电工程'!$B$4:$H$254,7,0) -> 524.73 | I5: =VLOOKUP(B5,'[1]2.2强电工程'!$B$4:$I$254,8,0) -> 8902.89 | J5: =VLOOKUP(B5,'[1]2.2强电工程'!$B$4:$J$254,9,0) -> 36.96 | K5: =VLOOKUP(B5,'[1]2.2强电工程'!$B$4:$K$254,10,0) -> 18.91 | L5: =$L$4 -> 0.207 | M5: =F5*G5 -> 0
A6: 3 | B6: 配电箱 | C6: 1.名称:配电箱（嵌入/悬挂） 2.规格:半周长2.5m 3.接线端子材质、规格:按设计及规范要求 4.端子板外部接线材质、规格:按设计及规范要求 5.安装方式:悬挂式 6.其他:含智能电表、时控开关、电气元器件及配套附件成套费用 | D6: 按设计图示数量计算 | E6: 台 | G6: =(H6+I6+J6+K6)*(1+L6) -> 7821.9876 | H6: 448.4 | I6: 6007.08 | J6: 21.43 | K6: 3.61 | L6: =$L$4 -> 0.207 | M6: =F6*G6 -> 0
A7: 4 | B7: 配电箱 | C7: 1.名称:配电箱（嵌入/悬挂） 2.规格:半周长1.5m 3.接线端子材质、规格:按设计及规范要求 4.端子板外部接线材质、规格:按设计及规范要求 5.安装方式:悬挂式 6.其他:含智能电表、时控开关、电气元器件及配套附件成套费用 | D7: 按设计图示数量计算 | E7: 台 | F7: 1 | G7: =(H7+I7+J7+K7)*(1+L7) -> 4871.5003 | H7: 373.78 | I7: 3640.71 | J7: 17.94 | K7: 3.61 | L7: =$L$4 -> 0.207 | M7: =F7*G7 -> 4871.5003
A8: 5 | B8: 配电箱 | C8: 1.名称:配电箱（嵌入/悬挂） 2.规格:半周长1.0m 3.接线端子材质、规格:按设计及规范要求 4.端子板外部接线材质、规格:按设计及规范要求 5.安装方式:悬挂式 6.其他:含智能电表、时控开关、电气元器件及配套附件成套费用 | D8: 按设计图示数量计算 | E8: 台 | G8: =(H8+I8+J8+K8)*(1+L8) -> 3437.7653 | H8: 298 | I8: 2529.2 | J8: 17.38 | K8: 3.61 | L8: =$L$4 -> 0.207 | M8: =F8*G8 -> 0
A9: 6 | B9: 配电箱 | C9: 1.名称:配电箱（嵌入/悬挂） 2.规格:半周长0.5m 3.接线端子材质、规格:按设计及规范要求 4.端子板外部接线材质、规格:按设计及规范要求 5.安装方式:悬挂式 6.其他:含智能电表、时控开关、电气元器件及配套附件成套费用 | D9: 按设计图示数量计算 | E9: 台 | G9: =(H9+I9+J9+K9)*(1+L9) -> 1670.6811 | H9: 250.27 | I9: 1113.27 | J9: 17.01 | K9: 3.61 | L9: =$L$4 -> 0.207 | M9: =F9*G9 -> 0
A10: 7 | B10: 应急照明配电箱 | C10: 1.名称:应急照明配电箱 2.接线端子材质、规格:按设计及规范要求 3.端子板外部接线材质、规格:按设计及规范要求 4.其他:含元器件及配套附件成套费用 | D10: 按设计图示数量计算 | E10: 台 | G10: =(H10+I10+J10+K10)*(1+L10) -> 3651.0302 | H10: =VLOOKUP(B10,'[1]2.2强电工程'!$B$4:$H$254,7,0) -> 464.21 | I10: =VLOOKUP(B10,'[1]2.2强电工程'!$B$4:$I$254,8,0) -> 2500.65 | J10: =VLOOKUP(B10,'[1]2.2强电工程'!$B$4:$J$254,9,0) -> 41.11 | K10: =VLOOKUP(B10,'[1]2.2强电工程'!$B$4:$K$254,10,0) -> 18.91 | L10: =$L$4 -> 0.207 | M10: =F10*G10 -> 0
A11: 8 | B11: 电缆WDZB-YJV-3*240+2*120 | C11: 1.名称:电力电缆 2.型号:WDZB-YJV 3.规格:3*240+2*120 4.材质:铜芯 5.敷设方式、部位:桥架内及配管内敷设 6.电压等级(kV):1.0KV | D11: 按设计图示尺寸以长度计算（含预留长度及附加长度） | E11: m | G11: =(H11+I11+J11+K11)*(1+L11) -> 1089.6192 | H11: =VLOOKUP(B11,'[1]2.2强电工程'!$B$4:$H$254,7,0) -> 28.73 | I11: =VLOOKUP(B11,'[1]2.2强电工程'!$B$4:$I$254,8,0) -> 869.71 | J11: =VLOOKUP(B11,'[1]2.2强电工程'!$B$4:$J$254,9,0) -> 1.99 | K11: =VLOOKUP(B11,'[1]2.2强电工程'!$B$4:$K$254,10,0) -> 2.32 | L11: =$L$4 -> 0.207 | M11: =F11*G11 -> 0
A12: 9 | B12: 电缆WDZB-YJV-3*185+2*95 | C12: 1.名称:电力电缆 2.型号:WDZB-YJV 3.规格:3*185+2*95 4.材质:铜芯 5.敷设方式、部位:桥架内及配管内敷设 6.电压等级(kV):1.0KV | D12: 按设计图示尺寸以长度计算（含预留长度及附加长度） | E12: m | G12: =(H12+I12+J12+K12)*(1+L12) -> 784.4293 | H12: =VLOOKUP(B12,'[1]2.2强电工程'!$B$4:$H$254,7,0) -> 28.73 | I12: =VLOOKUP(B12,'[1]2.2强电工程'!$B$4:$I$254,8,0) -> 616.86 | J12: =VLOOKUP(B12,'[1]2.2强电工程'!$B$4:$J$254,9,0) -> 1.99 | K12: =VLOOKUP(B12,'[1]2.2强电工程'!$B$4:$K$254,10,0) -> 2.32 | L12: =$L$4 -> 0.207 | M12: =F12*G12 -> 0
A13: 10 | B13: 电缆WDZB-YJV-3*150+2*70 | C13: 1.名称:电力电缆 2.型号:WDZB-YJV 3.规格:3*150+2*70 4.材质:铜芯 5.敷设方式、部位:桥架内及配管内敷设 6.电压等级(kV):1.0KV | D13: 按设计图示尺寸以长度计算（含预留长度及附加长度） | E13: m | G13: =(H13+I13+J13+K13)*(1+L13) -> 720.39795 | H13: =VLOOKUP(B13,'[1]2.2强电工程'!$B$4:$H$254,7,0) -> 28.73 | I13: =VLOOKUP(B13,'[1]2.2强电工程'!$B$4:$I$254,8,0) -> 563.81 | J13: =VLOOKUP(B13,'[1]2.2强电工程'!$B$4:$J$254,9,0) -> 1.99 | K13: =VLOOKUP(B13,'[1]2.2强电工程'!$B$4:$K$254,10,0) -> 2.32 | L13: =$L$4 -> 0.207 | M13: =F13*G13 -> 0
A14: 11 | B14: 电缆WDZB-YJV-3*120+2*70 | C14: 1.名称:电力电缆 2.型号:WDZB-YJV 3.规格:3*120+2*70 4.材质:铜芯 5.敷设方式、部位:桥架内及配管内敷设 6.电压等级(kV):1.0KV | D14: 按设计图示尺寸以长度计算（含预留长度及附加长度） | E14: m | G14: =(H14+I14+J14+K14)*(1+L14) -> 566.84341 | H14: =VLOOKUP(B14,'[1]2.2强电工程'!$B$4:$H$254,7,0) -> 20.72 | I14: =VLOOKUP(B14,'[1]2.2强电工程'!$B$4:$I$254,8,0) -> 446.52 | J14: =VLOOKUP(B14,'[1]2.2强电工程'!$B$4:$J$254,9,0) -> 1.25 | K14: =VLOOKUP(B14,'[1]2.2强电工程'!$B$4:$K$254,10,0) -> 1.14 | L14: =$L$4 -> 0.207 | M14: =F14*G14 -> 0
A15: 12 | B15: 电缆WDZB-YJV-3*95+2*50 | C15: 1.名称:电力电缆 2.型号:WDZB-YJV 3.规格:3*95+2*50 4.材质:铜芯 5.敷设方式、部位:桥架内及配管内敷设 6.电压等级(kV):1.0KV | D15: 按设计图示尺寸以长度计算（含预留长度及附加长度） | E15: m | G15: =(H15+I15+J15+K15)*(1+L15) -> 385.17784 | H15: =VLOOKUP(B15,'[1]2.2强电工程'!$B$4:$H$254,7,0) -> 20.72 | I15: =VLOOKUP(B15,'[1]2.2强电工程'!$B$4:$I$254,8,0) -> 296.01 | J15: =VLOOKUP(B15,'[1]2.2强电工程'!$B$4:$J$254,9,0) -> 1.25 | K15: =VLOOKUP(B15,'[1]2.2强电工程'!$B$4:$K$254,10,0) -> 1.14 | L15: =$L$4 -> 0.207 | M15: =F15*G15 -> 0
A16: 13 | B16: 电缆WDZB-YJV-3*70+2*35 | C16: 1.名称:电力电缆 2.型号:WDZB-YJV 3.规格:3*70+2*35 4.材质:铜芯 5.敷设方式、部位:桥架内及配管内敷设 6.电压等级(kV):1.0KV | D16: 按设计图示尺寸以长度计算（含预留长度及附加长度） | E16: m | G16: =(H16+I16+J16+K16)*(1+L16) -> 317.83931 | H16: =VLOOKUP(B16,'[1]2.2强电工程'!$B$4:$H$254,7,0) -> 17.42 | I16: =VLOOKUP(B16,'[1]2.2强电工程'!$B$4:$I$254,8,0) -> 243.76 | J16: =VLOOKUP(B16,'[1]2.2强电工程'!$B$4:$J$254,9,0) -> 1.01 | K16: =VLOOKUP(B16,'[1]2.2强电工程'!$B$4:$K$254,10,0) -> 1.14 | L16: =$L$4 -> 0.207 | M16: =F16*G16 -> 0
A17: 14 | B17: 电缆WDZB-YJV-3*50+2*25 | C17: 1.名称:电力电缆 2.型号:WDZB-YJV 3.规格:3*50+2*25 4.材质:铜芯 5.敷设方式、部位:桥架内及配管内敷设 6.电压等级(kV):1.0KV | D17: 按设计图示尺寸以长度计算（含预留长度及附加长度） | E17: m | G17: =(H17+I17+J17+K17)*(1+L17) -> 236.87375 | H17: =VLOOKUP(B17,'[1]2.2强电工程'!$B$4:$H$254,7,0) -> 17.42 | I17: =VLOOKUP(B17,'[1]2.2强电工程'!$B$4:$I$254,8,0) -> 176.68 | J17: =VLOOKUP(B17,'[1]2.2强电工程'!$B$4:$J$254,9,0) -> 1.01 | K17: =VLOOKUP(B17,'[1]2.2强电工程'!$B$4:$K$254,10,0) -> 1.14 | L17: =$L$4 -> 0.207 | M17: =F17*G17 -> 0
A18: 15 | B18: 电缆WDZB-YJV-3*35+2*16 | C18: 1.名称:电力电缆 2.型号:WDZB-YJV 3.规格:3*35+2*16 4.材质:铜芯 5.敷设方式、部位:桥架内及配管内敷设 6.电压等级(kV):1.0KV | D18: 按设计图示尺寸以长度计算（含预留长度及附加长度） | E18: m | G18: =(H18+I18+J18+K18)*(1+L18) -> 181.8949 | H18: =VLOOKUP(B18,'[1]2.2强电工程'!$B$4:$H$254,7,0) -> 11.07 | I18: =VLOOKUP(B18,'[1]2.2强电工程'!$B$4:$I$254,8,0) -> 138.36 | J18: =VLOOKUP(B18,'[1]2.2强电工程'!$B$4:$J$254,9,0) -> 1.11 | K18: =VLOOKUP(B18,'[1]2.2强电工程'!$B$4:$K$254,10,0) -> 0.16 | L18: =$L$4 -> 0.207 | M18: =F18*G18 -> 0
A19: 16 | B19: 电缆WDZB-YJV-3*25+2*16 | C19: 1.名称:电力电缆 2.型号:WDZB-YJV 3.规格:3*25+2*16 4.材质:铜芯 5.敷设方式、部位:桥架内及配管内敷设 6.电压等级(kV):1.0KV | D19: 按设计图示尺寸以长度计算（含预留长度及附加长度） | E19: m | G19: =(H19+I19+J19+K19)*(1+L19) -> 134.47187 | H19: =VLOOKUP(B19,'[1]2.2强电工程'!$B$4:$H$254,7,0) -> 11.07 | I19: =VLOOKUP(B19,'[1]2.2强电工程'!$B$4:$I$254,8,0) -> 99.07 | J19: =VLOOKUP(B19,'[1]2.2强电工程'!$B$4:$J$254,9,0) -> 1.11 | K19: =VLOOKUP(B19,'[1]2.2强电工程'!$B$4:$K$254,10,0) -> 0.16 | L19: =$L$4 -> 0.207 | M19: =F19*G19 -> 0
A20: 17 | B20: 电缆WDZB-YJV-4*185+1*95 | C20: 1.名称:电力电缆 2.型号:WDZB-YJV 3.规格:4*185+1*95 4.材质:铜芯 5.敷设方式、部位:桥架内及配管内敷设 6.电压等级(kV):1.0KV | D20: 按设计图示尺寸以长度计算（含预留长度及附加长度） | E20: m | G20: =(H20+I20+J20+K20)*(1+L20) -> 883.12569 | H20: =VLOOKUP(B20,'[1]2.2强电工程'!$B$4:$H$254,7,0) -> 28.73 | I20: =VLOOKUP(B20,'[1]2.2强电工程'!$B$4:$I$254,8,0) -> 698.63 | J20: =VLOOKUP(B20,'[1]2.2强电工程'!$B$4:$J$254,9,0) -> 1.99 | K20: =VLOOKUP(B20,'[1]2.2强电工程'!$B$4:$K$254,10,0) -> 2.32 | L20: =$L$4 -> 0.207 | M20: =F20*G20 -> 0
A21: 18 | B21: 电缆WDZB-YJV-4*150+1*70 | C21: 1.名称:电力电缆 2.型号:WDZB-YJV 3.规格:4*150+1*70 4.材质:铜芯 5.敷设方式、部位:桥架内及配管内敷设 6.电压等级(kV):1.0KV | D21: 按设计图示尺寸以长度计算（含预留长度及附加长度） | E21: m | G21: =(H21+I21+J21+K21)*(1+L21) -> 761.89461 | H21: =VLOOKUP(B21,'[1]2.2强电工程'!$B$4:$H$254,7,0) -> 28.73 | I21: =VLOOKUP(B21,'[1]2.2强电工程'!$B$4:$I$254,8,0) -> 598.19 | J21: =VLOOKUP(B21,'[1]2.2强电工程'!$B$4:$J$254,9,0) -> 1.99 | K21: =VLOOKUP(B21,'[1]2.2强电工程'!$B$4:$K$254,10,0) -> 2.32 | L21: =$L$4 -> 0.207 | M21: =F21*G21 -> 0
... A29: 26 | B29: 电缆WDZB-YJV-5*10 | C29: 1.名称:电力电缆 2.型号:WDZB-YJV 3.规格:5*10 4.材质:铜芯 5.敷设方式、部位:桥架内及配管内敷设 6.电压等级(kV):1.0KV | D29: 按设计图示尺寸以长度计算（含预留长度及附加长度） | E29: m | G29: =(H29+I29+J29+K29)*(1+L29) -> 68.36448 | H29: =VLOOKUP(B29,'[1]2.2强电工程'!$B$4:$H$254,7,0) -> 6.12 | I29: =VLOOKUP(B29,'[1]2.2强电工程'!$B$4:$I$254,8,0) -> 49.52 | J29: =VLOOKUP(B29,'[1]2.2强电工程'!$B$4:$J$254,9,0) -> 1 | K29: =VLOOKUP(B29,'[1]2.2强电工程'!$B$4:$K$254,10,0) -> 0 | L29: =$L$4 -> 0.207 | M29: =F29*G29 -> 0
A30: 27 | B30: 电缆WDZB-YJV-5*6 | C30: 1.名称:电力电缆 2.型号:WDZB-YJV 3.规格:5*6 4.材质:铜芯 5.敷设方式、部位:桥架内及配管内敷设 6.电压等级(kV):1.0KV | D30: 按设计图示尺寸以长度计算（含预留长度及附加长度） | E30: m | G30: =(H30+I30+J30+K30)*(1+L30) -> 98.899166 | H30: =VLOOKUP(B30,'[1]2.2强电工程'!$B$4:$H$254,7,0) -> 11.07 | I30: 69.598 | J30: =VLOOKUP(B30,'[1]2.2强电工程'!$B$4:$J$254,9,0) -> 1.11 | K30: =VLOOKUP(B30,'[1]2.2强电工程'!$B$4:$K$254,10,0) -> 0.16 | L30: =$L$4 -> 0.207 | M30: =F30*G30 -> 0
A31: 28 | B31: 电缆WDZB-YJV-5*4 | C31: 1.名称:电力电缆 2.型号:WDZB-YJV 3.规格:5*4 4.材质:铜芯 5.敷设方式、部位:桥架内及配管内敷设 6.电压等级(kV):1.0KV | D31: 按设计图示尺寸以长度计算（含预留长度及附加长度） | E31: m | G31: =(H31+I31+J31+K31)*(1+L31) -> 35.66685 | H31: =VLOOKUP(B31,'[1]2.2强电工程'!$B$4:$H$254,7,0) -> 4.57 | I31: =VLOOKUP(B31,'[1]2.2强电工程'!$B$4:$I$254,8,0) -> 23.9 | J31: =VLOOKUP(B31,'[1]2.2强电工程'!$B$4:$J$254,9,0) -> 1.08 | K31: =VLOOKUP(B31,'[1]2.2强电工程'!$B$4:$K$254,10,0) -> 0 | L31: =$L$4 -> 0.207 | M31: =F31*G31 -> 0
A32: 29 | B32: 电缆WDZB-YJV-3*6 | C32: 1.名称:电力电缆 2.型号:WDZB-YJV 3.规格:3*6 4.材质:铜芯 5.敷设方式、部位:桥架内及配管内敷设 6.电压等级(kV):1.0KV | D32: 按设计图示尺寸以长度计算（含预留长度及附加长度） | E32: m | G32: =(H32+I32+J32+K32)*(1+L32) -> 66.25223 | H32: =VLOOKUP(B32,'[1]2.2强电工程'!$B$4:$H$254,7,0) -> 11.07 | I32: 42.55 | J32: =VLOOKUP(B32,'[1]2.2强电工程'!$B$4:$J$254,9,0) -> 1.11 | K32: =VLOOKUP(B32,'[1]2.2强电工程'!$B$4:$K$254,10,0) -> 0.16 | L32: =$L$4 -> 0.207 | M32: =F32*G32 -> 0
A33: 30 | B33: 电缆WDZB-YJV-3*10 | C33: 1.名称:电力电缆 2.型号:WDZB-YJV 3.规格:3*10 4.材质:铜芯 5.敷设方式、部位:桥架内及配管内敷设 6.电压等级(kV):1.0KV | D33: 按设计图示尺寸以长度计算（含预留长度及附加长度） | E33: m | G33: =(H33+I33+J33+K33)*(1+L33) -> 47.915486 | H33: =1.15*4.6 -> 5.29 | I33: =1.15*29.47 -> 33.8905 | J33: =1.15*0.13 -> 0.1495 | K33: =1.15*0.32 -> 0.368 | L33: =$L$4 -> 0.207 | M33: =F33*G33 -> 0
A34: 31 | B34: 电缆ZR-YJV-3*240+2*120 | C34: 1.名称:电力电缆 2.型号:ZR-YJV 3.规格:3*240+2*120 4.材质:铜芯 5.敷设方式、部位:桥架内及配管内敷设 6.电压等级(kV):1.0KV | D34: 按设计图示尺寸以长度计算（含预留长度及附加长度） | E34: m | G34: =(H34+I34+J34+K34)*(1+L34) -> 967.98986 | H34: =VLOOKUP(B34,'[1]2.2强电工程'!$B$4:$H$254,7,0) -> 28.73 | I34: =VLOOKUP(B34,'[1]2.2强电工程'!$B$4:$I$254,8,0) -> 768.94 | J34: =VLOOKUP(B34,'[1]2.2强电工程'!$B$4:$J$254,9,0) -> 1.99 | K34: =VLOOKUP(B34,'[1]2.2强电工程'!$B$4:$K$254,10,0) -> 2.32 | L34: =$L$4 -> 0.207 | M34: =F34*G34 -> 0
A35: 32 | B35: 电缆ZR-YJV-3*185+2*95 | C35: 1.名称:电力电缆 2.型号:ZR-YJV 3.规格:3*185+2*95 4.材质:铜芯 5.敷设方式、部位:桥架内及配管内敷设 6.电压等级(kV):1.0KV | D35: 按设计图示尺寸以长度计算（含预留长度及附加长度） | E35: m | G35: =(H35+I35+J35+K35)*(1+L35) -> 785.91391 | H35: =VLOOKUP(B35,'[1]2.2强电工程'!$B$4:$H$254,7,0) -> 28.73 | I35: =VLOOKUP(B35,'[1]2.2强电工程'!$B$4:$I$254,8,0) -> 618.09 | J35: =VLOOKUP(B35,'[1]2.2强电工程'!$B$4:$J$254,9,0) -> 1.99 | K35: =VLOOKUP(B35,'[1]2.2强电工程'!$B$4:$K$254,10,0) -> 2.32 | L35: =$L$4 -> 0.207 | M35: =F35*G35 -> 0
A36: 33 | B36: 电缆ZR-YJV-3*150+2*70 | C36: 1.名称:电力电缆 2.型号:ZR-YJV 3.规格:3*150+2*70 4.材质:铜芯 5.敷设方式、部位:桥架内及配管内敷设 6.电压等级(kV):1.0KV | D36: 按设计图示尺寸以长度计算（含预留长度及附加长度） | E36: m | G36: =(H36+I36+J36+K36)*(1+L36) -> 648.89527 | H36: =VLOOKUP(B36,'[1]2.2强电工程'!$B$4:$H$254,7,0) -> 28.73 | I36: =VLOOKUP(B36,'[1]2.2强电工程'!$B$4:$I$254,8,0) -> 504.57 | J36: =VLOOKUP(B36,'[1]2.2强电工程'!$B$4:$J$254,9,0) -> 1.99 | K36: =VLOOKUP(B36,'[1]2.2强电工程'!$B$4:$K$254,10,0) -> 2.32 | L36: =$L$4 -> 0.207 | M36: =F36*G36 -> 0
A37: 34 | B37: 电缆ZR-YJV-3*120+2*70 | C37: 1.名称:电力电缆 2.型号:ZR-YJV 3.规格:3*120+2*70 4.材质:铜芯 5.敷设方式、部位:桥架内及配管内敷设 6.电压等级(kV):1.0KV | D37: 按设计图示尺寸以长度计算（含预留长度及附加长度） | E37: m | G37: =(H37+I37+J37+K37)*(1+L37) -> 567.60382 | H37: =VLOOKUP(B37,'[1]2.2强电工程'!$B$4:$H$254,7,0) -> 20.72 | I37: =VLOOKUP(B37,'[1]2.2强电工程'!$B$4:$I$254,8,0) -> 447.15 | J37: =VLOOKUP(B37,'[1]2.2强电工程'!$B$4:$J$254,9,0) -> 1.25 | K37: =VLOOKUP(B37,'[1]2.2强电工程'!$B$4:$K$254,10,0) -> 1.14 | L37: =$L$4 -> 0.207 | M37: =F37*G37 -> 0
A38: 35 | B38: 电缆ZR-YJV-3*95+2*50 | C38: 1.名称:电力电缆 2.型号:ZR-YJV 3.规格:3*95+2*50 4.材质:铜芯 5.敷设方式、部位:桥架内及配管内敷设 6.电压等级(kV):1.0KV | D38: 按设计图示尺寸以长度计算（含预留长度及附加长度） | E38: m | G38: =(H38+I38+J38+K38)*(1+L38) -> 422.34137 | H38: =VLOOKUP(B38,'[1]2.2强电工程'!$B$4:$H$254,7,0) -> 20.72 | I38: =VLOOKUP(B38,'[1]2.2强电工程'!$B$4:$I$254,8,0) -> 326.8 | J38: =VLOOKUP(B38,'[1]2.2强电工程'!$B$4:$J$254,9,0) -> 1.25 | K38: =VLOOKUP(B38,'[1]2.2强电工程'!$B$4:$K$254,10,0) -> 1.14 | L38: =$L$4 -> 0.207 | M38: =F38*G38 -> 0
A39: 36 | B39: 电缆ZR-YJV-3*70+2*35 | C39: 1.名称:电力电缆 2.型号:ZR-YJV 3.规格:3*70+2*35 4.材质:铜芯 5.敷设方式、部位:桥架内及配管内敷设 6.电压等级(kV):1.0KV | D39: 按设计图示尺寸以长度计算（含预留长度及附加长度） | E39: m | G39: =(H39+I39+J39+K39)*(1+L39) -> 293.61482 | H39: =VLOOKUP(B39,'[1]2.2强电工程'!$B$4:$H$254,7,0) -> 17.42 | I39: =VLOOKUP(B39,'[1]2.2强电工程'!$B$4:$I$254,8,0) -> 223.69 | J39: =VLOOKUP(B39,'[1]2.2强电工程'!$B$4:$J$254,9,0) -> 1.01 | K39: =VLOOKUP(B39,'[1]2.2强电工程'!$B$4:$K$254,10,0) -> 1.14 | L39: =$L$4 -> 0.207 | M39: =F39*G39 -> 0
A40: 37 | B40: 电缆ZR-YJV-3*50+2*25 | C40: 1.名称:电力电缆 2.型号:ZR-YJV 3.规格:3*50+2*25 4.材质:铜芯 5.敷设方式、部位:桥架内及配管内敷设 6.电压等级(kV):1.0KV | D40: 按设计图示尺寸以长度计算（含预留长度及附加长度） | E40: m | G40: =(H40+I40+J40+K40)*(1+L40) -> 212.34751 | H40: =VLOOKUP(B40,'[1]2.2强电工程'!$B$4:$H$254,7,0) -> 17.42 | I40: =VLOOKUP(B40,'[1]2.2强电工程'!$B$4:$I$254,8,0) -> 156.36 | J40: =VLOOKUP(B40,'[1]2.2强电工程'!$B$4:$J$254,9,0) -> 1.01 | K40: =VLOOKUP(B40,'[1]2.2强电工程'!$B$4:$K$254,10,0) -> 1.14 | L40: =$L$4 -> 0.207 | M40: =F40*G40 -> 0
A41: 38 | B41: 电缆ZR-YJV-3*35+2*16 | C41: 1.名称:电力电缆 2.型号:ZR-YJV 3.规格:3*35+2*16 4.材质:铜芯 5.敷设方式、部位:桥架内及配管内敷设 6.电压等级(kV):1.0KV | D41: 按设计图示尺寸以长度计算（含预留长度及附加长度） | E41: m | G41: =(H41+I41+J41+K41)*(1+L41) -> 169.07656 | H41: =VLOOKUP(B41,'[1]2.2强电工程'!$B$4:$H$254,7,0) -> 11.07 | I41: =VLOOKUP(B41,'[1]2.2强电工程'!$B$4:$I$254,8,0) -> 127.74 | J41: =VLOOKUP(B41,'[1]2.2强电工程'!$B$4:$J$254,9,0) -> 1.11 | K41: =VLOOKUP(B41,'[1]2.2强电工程'!$B$4:$K$254,10,0) -> 0.16 | L41: =$L$4 -> 0.207 | M41: =F41*G41 -> 0
A42: 39 | B42: 电缆ZR-YJV-3*25+2*16 | C42: 1.名称:电力电缆 2.型号:ZR-YJV 3.规格:3*25+2*16 4.材质:铜芯 5.敷设方式、部位:桥架内及配管内敷设 6.电压等级(kV):1.0KV | D42: 按设计图示尺寸以长度计算（含预留长度及附加长度） | E42: m | G42: =(H42+I42+J42+K42)*(1+L42) -> 109.31799 | H42: =VLOOKUP(B42,'[1]2.2强电工程'!$B$4:$H$254,7,0) -> 11.07 | I42: =VLOOKUP(B42,'[1]2.2强电工程'!$B$4:$I$254,8,0) -> 78.23 | J42: =VLOOKUP(B42,'[1]2.2强电工程'!$B$4:$J$254,9,0) -> 1.11 | K42: =VLOOKUP(B42,'[1]2.2强电工程'!$B$4:$K$254,10,0) -> 0.16 | L42: =$L$4 -> 0.207 | M42: =F42*G42 -> 0
A43: 40 | B43: 电缆ZR-YJV-4*240+1*120 | C43: 1.名称:电力电缆 2.型号:ZR-YJV 3.规格:4*240+1*120 4.材质:铜芯 5.敷设方式、部位:桥架内及配管内敷设 6.电压等级(kV):1.0KV | D43: 按设计图示尺寸以长度计算（含预留长度及附加长度） | E43: m | G43: =(H43+I43+J43+K43)*(1+L43) -> 947.89331 | H43: =VLOOKUP(B43,'[1]2.2强电工程'!$B$4:$H$254,7,0) -> 28.73 | I43: =VLOOKUP(B43,'[1]2.2强电工程'!$B$4:$I$254,8,0) -> 752.29 | J43: =VLOOKUP(B43,'[1]2.2强电工程'!$B$4:$J$254,9,0) -> 1.99 | K43: =VLOOKUP(B43,'[1]2.2强电工程'!$B$4:$K$254,10,0) -> 2.32 | L43: =$L$4 -> 0.207 | M43: =F43*G43 -> 0
A44: 41 | B44: 电缆ZR-YJV-4*185+1*95 | C44: 1.名称:电力电缆 2.型号:ZR-YJV 3.规格:4*185+1*95 4.材质:铜芯 5.敷设方式、部位:桥架内及配管内敷设 6.电压等级(kV):1.0KV | D44: 按设计图示尺寸以长度计算（含预留长度及附加长度） | E44: m | G44: =(H44+I44+J44+K44)*(1+L44) -> 739.83065 | H44: =VLOOKUP(B44,'[1]2.2强电工程'!$B$4:$H$254,7,0) -> 28.73 | I44: =VLOOKUP(B44,'[1]2.2强电工程'!$B$4:$I$254,8,0) -> 579.91 | J44: =VLOOKUP(B44,'[1]2.2强电工程'!$B$4:$J$254,9,0) -> 1.99 | K44: =VLOOKUP(B44,'[1]2.2强电工程'!$B$4:$K$254,10,0) -> 2.32 | L44: =$L$4 -> 0.207 | M44: =F44*G44 -> 0
A45: 42 | B45: 电缆ZR-YJV-4*150+1*70 | C45: 1.名称:电力电缆 2.型号:ZR-YJV 3.规格:4*150+1*70 4.材质:铜芯 5.敷设方式、部位:桥架内及配管内敷设 6.电压等级(kV):1.0KV | D45: 按设计图示尺寸以长度计算（含预留长度及附加长度） | E45: m | G45: =(H45+I45+J45+K45)*(1+L45) -> 594.2061 | H45: =VLOOKUP(B45,'[1]2.2强电工程'!$B$4:$H$254,7,0) -> 28.73 | I45: =VLOOKUP(B45,'[1]2.2强电工程'!$B$4:$I$254,8,0) -> 459.26 | J45: =VLOOKUP(B45,'[1]2.2强电工程'!$B$4:$J$254,9,0) -> 1.99 | K45: =VLOOKUP(B45,'[1]2.2强电工程'!$B$4:$K$254,10,0) -> 2.32 | L45: =$L$4 -> 0.207 | M45: =F45*G45 -> 0
... A51: 48 | B51: 电缆ZR-YJV-4*25+1*16 | C51: 1.名称:电力电缆 2.型号:ZR-YJV 3.规格:4*25+1*16 4.材质:铜芯 5.敷设方式、部位:桥架内及配管内敷设 6.电压等级(kV):1.0KV | D51: 按设计图示尺寸以长度计算（含预留长度及附加长度） | E51: m | G51: =(H51+I51+J51+K51)*(1+L51) -> 116.76518 | H51: =VLOOKUP(B51,'[1]2.2强电工程'!$B$4:$H$254,7,0) -> 11.07 | I51: =VLOOKUP(B51,'[1]2.2强电工程'!$B$4:$I$254,8,0) -> 84.4 | J51: =VLOOKUP(B51,'[1]2.2强电工程'!$B$4:$J$254,9,0) -> 1.11 | K51: =VLOOKUP(B51,'[1]2.2强电工程'!$B$4:$K$254,10,0) -> 0.16 | L51: =$L$4 -> 0.207 | M51: =F51*G51 -> 0
A52: 49 | B52: 电缆ZR-YJV-4*16+1*10 | C52: 1.名称:电力电缆 2.型号:ZR-YJV 3.规格:4*16+1*10 4.材质:铜芯 5.敷设方式、部位:桥架内及配管内敷设 6.电压等级(kV):1.0KV | D52: 按设计图示尺寸以长度计算（含预留长度及附加长度） | E52: m | G52: =(H52+I52+J52+K52)*(1+L52) -> 98.884682 | H52: =1.15*11.07 -> 12.7305 | I52: =1.15*58.9 -> 67.735 | J52: =1.15*1.11 -> 1.2765 | K52: =1.15*0.16 -> 0.184 | L52: =$L$4 -> 0.207 | M52: =F52*G52 -> 0
A53: 50 | B53: 电缆ZR-YJV-5*16 | C53: 1.名称:电力电缆 2.型号:ZR-YJV 3.规格:5*16 4.材质:铜芯 5.敷设方式、部位:桥架内及配管内敷设 6.电压等级(kV):1.0KV | D53: 按设计图示尺寸以长度计算（含预留长度及附加长度） | E53: m | G53: =(H53+I53+J53+K53)*(1+L53) -> 86.92814 | H53: =VLOOKUP(B53,'[1]2.2强电工程'!$B$4:$H$254,7,0) -> 11.07 | I53: =VLOOKUP(B53,'[1]2.2强电工程'!$B$4:$I$254,8,0) -> 59.68 | J53: =VLOOKUP(B53,'[1]2.2强电工程'!$B$4:$J$254,9,0) -> 1.11 | K53: =VLOOKUP(B53,'[1]2.2强电工程'!$B$4:$K$254,10,0) -> 0.16 | L53: =$L$4 -> 0.207 | M53: =F53*G53 -> 0
A54: 51 | B54: 电缆ZR-YJV-5*10 | C54: 1.名称:电力电缆 2.型号:ZR-YJV 3.规格:5*10 4.材质:铜芯 5.敷设方式、部位:桥架内及配管内敷设 6.电压等级(kV):1.0KV | D54: 按设计图示尺寸以长度计算（含预留长度及附加长度） | E54: m | G54: =(H54+I54+J54+K54)*(1+L54) -> 55.26853 | H54: =VLOOKUP(B54,'[1]2.2强电工程'!$B$4:$H$254,7,0) -> 6.12 | I54: =VLOOKUP(B54,'[1]2.2强电工程'!$B$4:$I$254,8,0) -> 38.67 | J54: =VLOOKUP(B54,'[1]2.2强电工程'!$B$4:$J$254,9,0) -> 1 | K54: =VLOOKUP(B54,'[1]2.2强电工程'!$B$4:$K$254,10,0) -> 0 | L54: =$L$4 -> 0.207 | M54: =F54*G54 -> 0
A55: 52 | B55: 电缆ZR-YJV-5*6 | C55: 1.名称:电力电缆 2.型号:ZR-YJV 3.规格:5*6 4.材质:铜芯 5.敷设方式、部位:桥架内及配管内敷设 6.电压等级(kV):1.0KV | D55: 按设计图示尺寸以长度计算（含预留长度及附加长度） | E55: m | G55: =(H55+I55+J55+K55)*(1+L55) -> 57.410351 | H55: =VLOOKUP(B55,'[1]2.2强电工程'!$B$4:$H$254,7,0) -> 11.07 | I55: 35.2245 | J55: =VLOOKUP(B55,'[1]2.2强电工程'!$B$4:$J$254,9,0) -> 1.11 | K55: =VLOOKUP(B55,'[1]2.2强电工程'!$B$4:$K$254,10,0) -> 0.16 | L55: =$L$4 -> 0.207 | M55: =F55*G55 -> 0
A56: 53 | B56: 电缆ZR-YJV-3*4 | C56: 1.名称:电力电缆 2.型号:ZR-YJV 3.规格:3*4 4.材质:铜芯 5.敷设方式、部位:桥架内及配管内敷设 6.电压等级(kV):1.0KV | D56: 按设计图示尺寸以长度计算（含预留长度及附加长度） | E56: m | G56: =(H56+I56+J56+K56)*(1+L56) -> 31.800225 | H56: =1.15*9.3 -> 10.695 | I56: =1.15*13.2 -> 15.18 | J56: =1.15*0.13 -> 0.1495 | K56: =1.15*0.28 -> 0.322 | L56: =$L$4 -> 0.207 | M56: =F56*G56 -> 0
A57: 54 | B57: 电力电缆头（10mm2以下） | C57: 1.名称:电力电缆头 2.规格:10mm2以下 3.材质、类型:铜质 4.安装部位:户内 5.电压等级（kV):1.0 | D57: 按设计图示数量计算 | E57: 个 | G57: =(H57+I57+J57+K57)*(1+L57) -> 58.88953 | H57: =VLOOKUP(B57,'[1]2.2强电工程'!$B$4:$H$254,7,0) -> 42.32 | I57: =VLOOKUP(B57,'[1]2.2强电工程'!$B$4:$I$254,8,0) -> 0 | J57: =VLOOKUP(B57,'[1]2.2强电工程'!$B$4:$J$254,9,0) -> 6.47 | K57: =VLOOKUP(B57,'[1]2.2强电工程'!$B$4:$K$254,10,0) -> 0 | L57: =$L$4 -> 0.207 | M57: =F57*G57 -> 0
A58: 55 | B58: 电力电缆头（16mm2以下） | C58: 1.名称:电力电缆头 2.规格:16mm2以下 3.材质、类型:铜质 4.安装部位:户内 5.电压等级（kV):1.0 | D58: 按设计图示数量计算 | E58: 个 | G58: =(H58+I58+J58+K58)*(1+L58) -> 72.26309 | H58: =VLOOKUP(B58,'[1]2.2强电工程'!$B$4:$H$254,7,0) -> 49.1 | I58: =VLOOKUP(B58,'[1]2.2强电工程'!$B$4:$I$254,8,0) -> 0 | J58: =VLOOKUP(B58,'[1]2.2强电工程'!$B$4:$J$254,9,0) -> 10.5 | K58: =VLOOKUP(B58,'[1]2.2强电工程'!$B$4:$K$254,10,0) -> 0.27 | L58: =$L$4 -> 0.207 | M58: =F58*G58 -> 0
A59: 56 | B59: 电力电缆头（35mm2以下） | C59: 1.名称:电力电缆头 2.规格:35mm2以下 3.材质、类型:铜质 4.安装部位:户内 5.电压等级（kV):1.0 | D59: 按设计图示数量计算 | E59: 个 | F59: 2 | G59: =(H59+I59+J59+K59)*(1+L59) -> 104.85209 | H59: =VLOOKUP(B59,'[1]2.2强电工程'!$B$4:$H$254,7,0) -> 65.8 | I59: =VLOOKUP(B59,'[1]2.2强电工程'!$B$4:$I$254,8,0) -> 0 | J59: =VLOOKUP(B59,'[1]2.2强电工程'!$B$4:$J$254,9,0) -> 20.8 | K59: =VLOOKUP(B59,'[1]2.2强电工程'!$B$4:$K$254,10,0) -> 0.27 | L59: =$L$4 -> 0.207 | M59: =F59*G59 -> 209.70418
A60: 57 | B60: 电力电缆头（70mm2以下） | C60: 1.名称:电力电缆头 2.规格:70mm2以下 3.材质、类型:铜质 4.安装部位:户内 5.电压等级（kV):1.0 | D60: 按设计图示数量计算 | E60: 个 | G60: =(H60+I60+J60+K60)*(1+L60) -> 150.52497 | H60: =VLOOKUP(B60,'[1]2.2强电工程'!$B$4:$H$254,7,0) -> 81.2 | I60: =VLOOKUP(B60,'[1]2.2强电工程'!$B$4:$I$254,8,0) -> 0 | J60: =VLOOKUP(B60,'[1]2.2强电工程'!$B$4:$J$254,9,0) -> 42.8 | K60: =VLOOKUP(B60,'[1]2.2强电工程'!$B$4:$K$254,10,0) -> 0.71 | L60: =$L$4 -> 0.207 | M60: =F60*G60 -> 0
A61: 58 | B61: 电力电缆头（120mm2以下） | C61: 1.名称:电力电缆头 2.规格:120mm2以下 3.材质、类型:铜质 4.安装部位:户内 5.电压等级（kV):1.0 | D61: 按设计图示数量计算 | E61: 个 | F61: 2 | G61: =(H61+I61+J61+K61)*(1+L61) -> 196.14957 | H61: =VLOOKUP(B61,'[1]2.2强电工程'!$B$4:$H$254,7,0) -> 81.2 | I61: =VLOOKUP(B61,'[1]2.2强电工程'!$B$4:$I$254,8,0) -> 0 | J61: =VLOOKUP(B61,'[1]2.2强电工程'!$B$4:$J$254,9,0) -> 80.6 | K61: =VLOOKUP(B61,'[1]2.2强电工程'!$B$4:$K$254,10,0) -> 0.71 | L61: =$L$4 -> 0.207 | M61: =F61*G61 -> 392.29914
A62: 59 | B62: 电力电缆头（185mm2以下） | C62: 1.名称:电力电缆头 2.规格:185mm2以下 3.材质、类型:铜质 4.安装部位:户内 5.电压等级（kV):1.0 | D62: 按设计图示数量计算 | E62: 个 | G62: =(H62+I62+J62+K62)*(1+L62) -> 253.89245 | H62: =VLOOKUP(B62,'[1]2.2强电工程'!$B$4:$H$254,7,0) -> 100.5 | I62: =VLOOKUP(B62,'[1]2.2强电工程'!$B$4:$I$254,8,0) -> 0 | J62: =VLOOKUP(B62,'[1]2.2强电工程'!$B$4:$J$254,9,0) -> 108 | K62: =VLOOKUP(B62,'[1]2.2强电工程'!$B$4:$K$254,10,0) -> 1.85 | L62: =$L$4 -> 0.207 | M62: =F62*G62 -> 0
A63: 60 | B63: 电力电缆头（240mm2以下） | C63: 1.名称:电力电缆头 2.规格:240mm2以下 3.材质、类型:铜质 4.安装部位:户内 5.电压等级（kV):1.0 | D63: 按设计图示数量计算 | E63: 个 | G63: =(H63+I63+J63+K63)*(1+L63) -> 290.82665 | H63: =VLOOKUP(B63,'[1]2.2强电工程'!$B$4:$H$254,7,0) -> 100.5 | I63: =VLOOKUP(B63,'[1]2.2强电工程'!$B$4:$I$254,8,0) -> 0 | J63: =VLOOKUP(B63,'[1]2.2强电工程'!$B$4:$J$254,9,0) -> 138.6 | K63: =VLOOKUP(B63,'[1]2.2强电工程'!$B$4:$K$254,10,0) -> 1.85 | L63: =$L$4 -> 0.207 | M63: =F63*G63 -> 0
A64: 61 | B64: 镀锌线槽200*150 | C64: 1.名称:热镀锌钢制槽式桥架 2.规格:200*150 3.材质:钢制 4.接地方式:铜质编织带连接 5.附件:桥架及弯头、三通、盖板等所有附件 6.支吊架:含支吊架制作、安装 7.其他:预留洞口及防火封堵 | D64: 按设计图示尺寸以长度计算 | E64: m | G64: =(H64+I64+J64+K64)*(1+L64) -> 114.20634 | H64: =VLOOKUP(B64,'[1]2.2强电工程'!$B$4:$H$254,7,0) -> 35 | I64: =VLOOKUP(B64,'[1]2.2强电工程'!$B$4:$I$254,8,0) -> 50 | J64: =VLOOKUP(B64,'[1]2.2强电工程'!$B$4:$J$254,9,0) -> 8.61 | K64: =VLOOKUP(B64,'[1]2.2强电工程'!$B$4:$K$254,10,0) -> 1.01 | L64: =$L$4 -> 0.207 | M64: =F64*G64 -> 0
A65: 62 | B65: 镀锌线槽200*100 | C65: 1.名称:热镀锌钢制槽式桥架 2.规格:200*100 3.材质:钢制 4.接地方式:铜质编织带连接 5.附件:桥架及弯头、三通、盖板等所有附件 6.支吊架:含支吊架制作、安装 7.其他:预留洞口及防火封堵 | D65: 按设计图示尺寸以长度计算 | E65: m | G65: =(H65+I65+J65+K65)*(1+L65) -> 102.25704 | H65: =VLOOKUP(B65,'[1]2.2强电工程'!$B$4:$H$254,7,0) -> 35 | I65: =VLOOKUP(B65,'[1]2.2强电工程'!$B$4:$I$254,8,0) -> 40.1 | J65: =VLOOKUP(B65,'[1]2.2强电工程'!$B$4:$J$254,9,0) -> 8.61 | K65: =VLOOKUP(B65,'[1]2.2强电工程'!$B$4:$K$254,10,0) -> 1.01 | L65: =$L$4 -> 0.207 | M65: =F65*G65 -> 0
A66: 63 | B66: 镀锌线槽150*100 | C66: 1.名称:热镀锌钢制槽式桥架 2.规格:150*100 3.材质:钢制 4.接地方式:铜质编织带连接 5.附件:桥架及弯头、三通、盖板等所有附件 6.支吊架:含支吊架制作、安装 7.其他:预留洞口及防火封堵 | D66: 按设计图示尺寸以长度计算 | E66: m | G66: =(H66+I66+J66+K66)*(1+L66) -> 92.48034 | H66: =VLOOKUP(B66,'[1]2.2强电工程'!$B$4:$H$254,7,0) -> 35 | I66: =VLOOKUP(B66,'[1]2.2强电工程'!$B$4:$I$254,8,0) -> 32 | J66: =VLOOKUP(B66,'[1]2.2强电工程'!$B$4:$J$254,9,0) -> 8.61 | K66: =VLOOKUP(B66,'[1]2.2强电工程'!$B$4:$K$254,10,0) -> 1.01 | L66: =$L$4 -> 0.207 | M66: =F66*G66 -> 0
A67: 64 | B67: 镀锌线槽100*100 | C67: 1.名称:热镀锌钢制槽式桥架 2.规格:100*100 3.材质:钢制 4.接地方式:铜质编织带连接 5.附件:桥架及弯头、三通、盖板等所有附件 6.支吊架:含支吊架制作、安装 7.其他:含预留洞口及防火封堵 | D67: 按设计图示尺寸以长度计算 | E67: m | F67: 28.5 | G67: =(H67+I67+J67+K67)*(1+L67) -> 77.10316 | H67: =VLOOKUP(B67,'[1]2.2强电工程'!$B$4:$H$254,7,0) -> 29.8 | I67: =VLOOKUP(B67,'[1]2.2强电工程'!$B$4:$I$254,8,0) -> 25 | J67: =VLOOKUP(B67,'[1]2.2强电工程'!$B$4:$J$254,9,0) -> 8.56 | K67: =VLOOKUP(B67,'[1]2.2强电工程'!$B$4:$K$254,10,0) -> 0.52 | L67: =$L$4 -> 0.207 | M67: =F67*G67 -> 2197.4401
A68: 65 | B68: 镀锌线槽100*50 | C68: 1.名称:热镀锌钢制槽式桥架 2.规格:100*50 3.材质:钢制 4.接地方式:铜质编织带连接 5.附件:桥架及弯头、三通、盖板等所有附件 6.支吊架:含支吊架制作、安装 7.其他:含预留洞口及防火封堵 | D68: 按设计图示尺寸以长度计算 | E68: m | G68: =(H68+I68+J68+K68)*(1+L68) -> 69.86116 | H68: =VLOOKUP(B68,'[1]2.2强电工程'!$B$4:$H$254,7,0) -> 29.8 | I68: =VLOOKUP(B68,'[1]2.2强电工程'!$B$4:$I$254,8,0) -> 19 | J68: =VLOOKUP(B68,'[1]2.2强电工程'!$B$4:$J$254,9,0) -> 8.56 | K68: =VLOOKUP(B68,'[1]2.2强电工程'!$B$4:$K$254,10,0) -> 0.52 | L68: =$L$4 -> 0.207 | M68: =F68*G68 -> 0
A69: 66 | B69: 镀锌线槽50*50 | C69: 1.名称:热镀锌钢制槽式桥架 2.规格:50*50 3.材质:钢制 4.接地方式:铜质编织带连接 5.附件:桥架及弯头、三通、盖板等所有附件 6.支吊架:含支吊架制作、安装 7.其他:含预留洞口及防火封堵 | D69: 按设计图示尺寸以长度计算 | E69: m | G69: =(H69+I69+J69+K69)*(1+L69) -> 66.36086 | H69: =VLOOKUP(B69,'[1]2.2强电工程'!$B$4:$H$254,7,0) -> 29.8 | I69: =VLOOKUP(B69,'[1]2.2强电工程'!$B$4:$I$254,8,0) -> 16.1 | J69: =VLOOKUP(B69,'[1]2.2强电工程'!$B$4:$J$254,9,0) -> 8.56 | K69: =VLOOKUP(B69,'[1]2.2强电工程'!$B$4:$K$254,10,0) -> 0.52 | L69: =$L$4 -> 0.207 | M69: =F69*G69 -> 0
A70: 67 | B70: 配管DN50 | C70: 1.名称:电气配管 2.材质:镀锌钢管 3.规格:DN50 4.配置形式:暗配 5.接地要求:按设计及规范要求 | D70: 按设计图示尺寸以长度计算 | E70: m | G70: =(H70+I70+J70+K70)*(1+L70) -> 60.35 | H70: =VLOOKUP(B70,'[1]2.2强电工程'!$B$4:$H$254,7,0) -> 23.34 | I70: =VLOOKUP(B70,'[1]2.2强电工程'!$B$4:$I$254,8,0) -> 24.62 | J70: =VLOOKUP(B70,'[1]2.2强电工程'!$B$4:$J$254,9,0) -> 1.93 | K70: =VLOOKUP(B70,'[1]2.2强电工程'!$B$4:$K$254,10,0) -> 0.11 | L70: =$L$4 -> 0.207 | M70: =F70*G70 -> 0
A71: 68 | B71: 配管DN50 | C71: 1.名称:电气配管 2.材质:镀锌钢管 3.规格:DN50 4.配置形式:明配 5.其他:含支、吊架制作安装 | D71: 按设计图示尺寸以长度计算 | E71: m | G71: =(H71+I71+J71+K71)*(1+L71) -> 60.35 | H71: =VLOOKUP(B71,'[1]2.2强电工程'!$B$4:$H$254,7,0) -> 23.34 | I71: =VLOOKUP(B71,'[1]2.2强电工程'!$B$4:$I$254,8,0) -> 24.62 | J71: =VLOOKUP(B71,'[1]2.2强电工程'!$B$4:$J$254,9,0) -> 1.93 | K71: =VLOOKUP(B71,'[1]2.2强电工程'!$B$4:$K$254,10,0) -> 0.11 | L71: =$L$4 -> 0.207 | M71: =F71*G71 -> 0
A72: 69 | B72: 配管JDG40 | C72: 1.名称:配管JDG40 2.规格:Φ40 3.配置形式:明配 4.接地要求:按设计及规范要求 5.其他:含支、吊架制作安装 | D72: 按设计图示尺寸以长度计算 | E72: m | G72: =(H72+I72+J72+K72)*(1+L72) -> 32.744099 | H72: =1.15*10.6 -> 12.19 | I72: =1.15*11.3 -> 12.995 | J72: =1.15*1.69 -> 1.9435 | K72: 0 | L72: =$L$4 -> 0.207 | M72: =F72*G72 -> 0
A73: 70 | B73: 配管JDG32 | C73: 1.名称:配管JDG32 2.规格:Φ32 3.配置形式:明配 4.接地要求:按设计及规范要求 5.其他:支、吊架制作安装 | D73: 按设计图示尺寸以长度计算 | E73: m | G73: =(H73+I73+J73+K73)*(1+L73) -> 29.99576 | H73: =1.15*10.6 -> 12.19 | I73: =1.15*9.32 -> 10.718 | J73: =1.15*1.69 -> 1.9435 | K73: 0 | L73: =$L$4 -> 0.207 | M73: =F73*G73 -> 0
A74: 71 | B74: 配管JDG25 | C74: 1.名称:配管JDG25 2.规格:Φ25 3.配置形式:明配 4.接地要求:按设计及规范要求 5.其他:含支、吊架制作安装 | D74: 按设计图示尺寸以长度计算 | E74: m | G74: =(H74+I74+J74+K74)*(1+L74) -> 25.609523 | H74: =1.15*10.8 -> 12.42 | I74: =1.15*6.5 -> 7.475 | J74: =1.15*1.15 -> 1.3225 | K74: 0 | L74: =$L$4 -> 0.207 | M74: =F74*G74 -> 0
A75: 72 | B75: 配管JDG20 | C75: 1.名称:配管JDG20 2.规格:Φ20 3.配置形式:明配 4.接地要求:按设计及规范要求 5.其他:含支、吊架制作安装 | D75: 按设计图示尺寸以长度计算 | E75: m | F75: 120 | G75: =(H75+I75+J75+K75)*(1+L75) -> 22.736259 | H75: =1.15*9.8 -> 11.27 | I75: =1.15*5 -> 5.75 | J75: =1.15*1.58 -> 1.817 | K75: 0 | L75: =$L$4 -> 0.207 | M75: =F75*G75 -> 2728.3511
A76: 73 | B76: 配管JDG15 | C76: 1.名称:配管JDG15 2.规格:Φ15 3.配置形式:明配 4.接地要求:按设计及规范要求 5.其他:含支、吊架制作安装 | D76: 按设计图示尺寸以长度计算 | E76: m | G76: =(H76+I76+J76+K76)*(1+L76) -> 18.835839 | H76: =1.15*9.8 -> 11.27 | I76: =1.15*2.4 -> 2.76 | J76: =1.15*1.37 -> 1.5755 | K76: 0 | L76: =$L$4 -> 0.207 | M76: =F76*G76 -> 0
A77: 74 | B77: 配管JDG40 | C77: 1.名称:配管JDG40 2.规格:Φ40 3.配置形式:暗配 4.接地要求:按设计及规范要求 | D77: 按设计图示尺寸以长度计算 | E77: m | G77: =(H77+I77+J77+K77)*(1+L77) -> 30.509339 | H77: =1.15*9.8 -> 11.27 | I77: =1.15*11.3 -> 12.995 | J77: =1.15*0.88 -> 1.012 | K77: 0 | L77: =$L$4 -> 0.207 | M77: =F77*G77 -> 0
A78: 75 | B78: 配管JDG32 | C78: 1.名称:配管JDG32 2.规格:Φ32 3.配置形式:暗配 4.接地要求:按设计及规范要求 | D78: 按设计图示尺寸以长度计算 | E78: m | G78: =(H78+I78+J78+K78)*(1+L78) -> 27.761 | H78: =1.15*9.8 -> 11.27 | I78: =1.15*9.32 -> 10.718 | J78: =1.15*0.88 -> 1.012 | K78: 0 | L78: =$L$4 -> 0.207 | M78: =F78*G78 -> 0
A79: 76 | B79: 配管JDG25 | C79: 1.名称:配管JDG25 2.规格:Φ25 3.配置形式:暗配 4.接地要求:按设计及规范要求 | D79: 按设计图示尺寸以长度计算 | E79: m | F79: 90 | G79: =(H79+I79+J79+K79)*(1+L79) -> 24.9849 | H79: =1.15*10.06 -> 11.569 | I79: =1.15*7.5 -> 8.625 | J79: =1.15*0.44 -> 0.506 | K79: 0 | L79: =$L$4 -> 0.207 | M79: =F79*G79 -> 2248.641
A80: 77 | B80: 配管JDG20 | C80: 1.名称:配管JDG20 2.规格:Φ20 3.配置形式:暗配 4.接地要求:按设计及规范要求 | D80: 按设计图示尺寸以长度计算 | E80: m | F80: 680 | G80: =(H80+I80+J80+K80)*(1+L80) -> 19.682549 | H80: =1.15*7.74 -> 8.901 | I80: =1.15*6 -> 6.9 | J80: =1.15*0.44 -> 0.506 | K80: 0 | L80: =$L$4 -> 0.207 | M80: =F80*G80 -> 13384.133
A81: 78 | B81: 配管JDG15 | C81: 1.名称:配管JDG15 2.规格:Φ15 3.配置形式:暗配 4.其他:含支、吊架制作安装 | D81: 按设计图示尺寸以长度计算 | E81: m | G81: =(H81+I81+J81+K81)*(1+L81) -> 15.796009 | H81: =1.15*7.37 -> 8.4755 | I81: =1.15*3.68 -> 4.232 | J81: =1.15*0.33 -> 0.3795 | K81: 0 | L81: =$L$4 -> 0.207 | M81: =F81*G81 -> 0
A82: 二 | B82: 照明、插座系统
A83: 1 | B83: 单联单控开关 | C83: 1.名称:单联单控开关 2.规格:250V10A | D83: 按设计图示数量计算 | E83: 个 | F83: 6 | G83: =(H83+I83+J83+K83)*(1+L83) -> 32.81833 | H83: =VLOOKUP(B83,'[1]2.2强电工程'!$B$4:$H$254,7,0) -> 12.97 | I83: =VLOOKUP(B83,'[1]2.2强电工程'!$B$4:$I$254,8,0) -> 13.54 | J83: =VLOOKUP(B83,'[1]2.2强电工程'!$B$4:$J$254,9,0) -> 0.68 | K83: =VLOOKUP(B83,'[1]2.2强电工程'!$B$4:$K$254,10,0) -> 0 | L83: =$L$4 -> 0.207 | M83: =F83*G83 -> 196.90998
A84: 2 | B84: 双联单控开关 | C84: 1.名称:双联单控开关 2.规格:250V10A | D84: 按设计图示数量计算 | E84: 个 | F84: 4 | G84: =(H84+I84+J84+K84)*(1+L84) -> 34.93058 | H84: =VLOOKUP(B84,'[1]2.2强电工程'!$B$4:$H$254,7,0) -> 13.56 | I84: =VLOOKUP(B84,'[1]2.2强电工程'!$B$4:$I$254,8,0) -> 14.44 | J84: =VLOOKUP(B84,'[1]2.2强电工程'!$B$4:$J$254,9,0) -> 0.94 | K84: =VLOOKUP(B84,'[1]2.2强电工程'!$B$4:$K$254,10,0) -> 0 | L84: =$L$4 -> 0.207 | M84: =F84*G84 -> 139.72232
A85: 3 | B85: 三联单控开关 | C85: 1.名称:三联单控开关 2.规格:250V10A | D85: 按设计图示数量计算 | E85: 个 | F85: 1 | G85: =(H85+I85+J85+K85)*(1+L85) -> 35.35303 | H85: =VLOOKUP(B85,'[1]2.2强电工程'!$B$4:$H$254,7,0) -> 13.65 | I85: =VLOOKUP(B85,'[1]2.2强电工程'!$B$4:$I$254,8,0) -> 14.44 | J85: =VLOOKUP(B85,'[1]2.2强电工程'!$B$4:$J$254,9,0) -> 1.2 | K85: =VLOOKUP(B85,'[1]2.2强电工程'!$B$4:$K$254,10,0) -> 0 | L85: =$L$4 -> 0.207 | M85: =F85*G85 -> 35.35303
A86: 4 | B86: 四联单控开关 | C86: 1.名称:四联单控开关 2.规格:250V10A | D86: 按设计图示数量计算 | E86: 个 | G86: =(H86+I86+J86+K86)*(1+L86) -> 39.42062 | H86: =VLOOKUP(B86,'[1]2.2强电工程'!$B$4:$H$254,7,0) -> 14.95 | I86: =VLOOKUP(B86,'[1]2.2强电工程'!$B$4:$I$254,8,0) -> 16.25 | J86: =VLOOKUP(B86,'[1]2.2强电工程'!$B$4:$J$254,9,0) -> 1.46 | K86: =VLOOKUP(B86,'[1]2.2强电工程'!$B$4:$K$254,10,0) -> 0 | L86: =$L$4 -> 0.207 | M86: =F86*G86 -> 0
A87: 5 | B87: 单联双控开关 | C87: 1.名称:单联双控开关 2.规格:250V10A | D87: 按设计图示数量计算 | E87: 个 | G87: =(H87+I87+J87+K87)*(1+L87) -> 32.81833 | H87: =VLOOKUP(B87,'[1]2.2强电工程'!$B$4:$H$254,7,0) -> 12.97 | I87: =VLOOKUP(B87,'[1]2.2强电工程'!$B$4:$I$254,8,0) -> 13.54 | J87: =VLOOKUP(B87,'[1]2.2强电工程'!$B$4:$J$254,9,0) -> 0.68 | K87: =VLOOKUP(B87,'[1]2.2强电工程'!$B$4:$K$254,10,0) -> 0 | L87: =$L$4 -> 0.207 | M87: =F87*G87 -> 0
A88: 6 | B88: 空调控制面板 | C88: 1.名称:空调控制面板 2.规格:样式参照选型表 | D88: 按设计图示数量计算 | E88: 个 | F88: 8 | G88: =(H88+I88+J88+K88)*(1+L88) -> 188.7748 | H88: =VLOOKUP(B88,'[1]2.2强电工程'!$B$4:$H$254,7,0) -> 27.07 | I88: =VLOOKUP(B88,'[1]2.2强电工程'!$B$4:$I$254,8,0) -> 129.16 | J88: =VLOOKUP(B88,'[1]2.2强电工程'!$B$4:$J$254,9,0) -> 0.17 | K88: =VLOOKUP(B88,'[1]2.2强电工程'!$B$4:$K$254,10,0) -> 0 | L88: =$L$4 -> 0.207 | M88: =F88*G88 -> 1510.1984
A89: 7 | B89: 安全型二三孔插座 | C89: 1.名称:安全型二三孔插座 2.规格:250V10A | D89: 按设计图示数量计算 | E89: 个 | F89: 44 | G89: =(H89+I89+J89+K89)*(1+L89) -> 43.917902 | H89: =1.15*15.47 -> 17.7905 | I89: =1.15*14.86 -> 17.089 | J89: =1.15*1.31 -> 1.5065 | K89: 0 | L89: =$L$4 -> 0.207 | M89: =F89*G89 -> 1932.3877
A90: 8 | B90: 安全型二三孔插座 | C90: 1.名称:安全型二三孔插座 2.规格:250V16A | D90: 按设计图示数量计算 | E90: 个 | G90: =(H90+I90+J90+K90)*(1+L90) -> 50.858152 | H90: =1.15*15.47 -> 17.7905 | I90: =1.15*19.86 -> 22.839 | J90: =1.15*1.31 -> 1.5065 | K90: 0 | L90: =$L$4 -> 0.207 | M90: =F90*G90 -> 0
A91: 9 | B91: 三相四孔插座 | C91: 1.名称:三相四孔插座 2.规格:250V22A | D91: 按设计图示数量计算 | E91: 个 | F91: 44 | G91: =(H91+I91+J91+K91)*(1+L91) -> 53.634252 | H91: =1.15*15.47 -> 17.7905 | I91: =1.15*21.86 -> 25.139 | J91: =1.15*1.31 -> 1.5065 | K91: 0 | L91: =$L$4 -> 0.207 | M91: =F91*G91 -> 2359.9071
A92: 10 | B92: 三孔插座 | C92: 1.名称:三孔插座 2.规格:250V16A | D92: 按设计图示数量计算 | E92: 个 | G92: =(H92+I92+J92+K92)*(1+L92) -> 43.917902 | H92: =1.15*15.47 -> 17.7905 | I92: =1.15*14.86 -> 17.089 | J92: =1.15*1.31 -> 1.5065 | K92: 0 | L92: =$L$4 -> 0.207 | M92: =F92*G92 -> 0
A93: 11 | B93: 防水地插 | C93: 1.名称:防水地插 2.规格:250V16A | D93: 按设计图示数量计算 | E93: 个 | F93: 4 | G93: =(H93+I93+J93+K93)*(1+L93) -> 60.074804 | H93: =1.15*15.47 -> 17.7905 | I93: =1.15*26.5 -> 30.475 | J93: =1.15*1.31 -> 1.5065 | K93: 0 | L93: =$L$4 -> 0.207 | M93: =F93*G93 -> 240.29922
A94: 12 | B94: 防水地插 | C94: 1.名称:防水地插 2.规格:250V10A | D94: 按设计图示数量计算 | E94: 个 | F94: 6 | G94: =(H94+I94+J94+K94)*(1+L94) -> 56.188264 | H94: =1.15*15.47 -> 17.7905 | I94: =1.15*23.7 -> 27.255 | J94: =1.15*1.31 -> 1.5065 | K94: 0 | L94: =$L$4 -> 0.207 | M94: =F94*G94 -> 337.12958
A95: 13 | B95: 五孔插座带USB+typeC | C95: 1.名称:五孔插座带USB+typeC 2.规格:250V10A | D95: 按设计图示数量计算 | E95: 个 | G95: =(H95+I95+J95+K95)*(1+L95) -> 120.43446 | H95: =VLOOKUP(B95,'[1]2.2强电工程'!$B$4:$H$254,7,0) -> 13.04 | I95: =VLOOKUP(B95,'[1]2.2强电工程'!$B$4:$I$254,8,0) -> 85.8 | J95: =VLOOKUP(B95,'[1]2.2强电工程'!$B$4:$J$254,9,0) -> 0.94 | K95: =VLOOKUP(B95,'[1]2.2强电工程'!$B$4:$K$254,10,0) -> 0 | L95: =$L$4 -> 0.207 | M95: =F95*G95 -> 0
A96: 14 | B96: 接线盒（明装） | C96: 1.名称:接线盒 2.材质:铁质 3.规格:86H 4.安装形式:明装 | D96: 按设计图示数量计算 | E96: 个 | F96: 155 | G96: =(H96+I96+J96+K96)*(1+L96) -> 10.05431 | H96: =VLOOKUP(B96,'[1]2.2强电工程'!$B$4:$H$254,7,0) -> 6.1 | I96: =VLOOKUP(B96,'[1]2.2强电工程'!$B$4:$I$254,8,0) -> 1.81 | J96: =VLOOKUP(B96,'[1]2.2强电工程'!$B$4:$J$254,9,0) -> 0.42 | K96: =VLOOKUP(B96,'[1]2.2强电工程'!$B$4:$K$254,10,0) -> 0 | L96: =$L$4 -> 0.207 | M96: =F96*G96 -> 1558.418
A97: 15 | B97: 接线盒（暗装） | C97: 1.名称:接线盒 2.材质:铁质 3.规格:86H 4.安装形式:暗装 | D97: 按设计图示数量计算 | E97: 个 | G97: =(H97+I97+J97+K97)*(1+L97) -> 11.45443 | H97: =VLOOKUP(B97,'[1]2.2强电工程'!$B$4:$H$254,7,0) -> 7.51 | I97: =VLOOKUP(B97,'[1]2.2强电工程'!$B$4:$I$254,8,0) -> 1.81 | J97: =VLOOKUP(B97,'[1]2.2强电工程'!$B$4:$J$254,9,0) -> 0.17 | K97: =VLOOKUP(B97,'[1]2.2强电工程'!$B$4:$K$254,10,0) -> 0 | L97: =$L$4 -> 0.207 | M97: =F97*G97 -> 0
A98: 16 | B98: 配线ZR-BV-10 | C98: 1.名称:配线ZR-BV-10 2.型号:ZR-BV 3.规格:10 4.材质:铜芯 5.配线部位:管内、线槽内敷设 | D98: 按设计图示尺寸以单线长度计算（含预留长度） | E98: m | G98: =(H98+I98+J98+K98)*(1+L98) -> 14.283034 | H98: =1.15*1.84 -> 2.116 | I98: =1.15*8.21 -> 9.4415 | J98: =1.15*0.24 -> 0.276 | K98: 0 | L98: =$L$4 -> 0.207 | M98: =F98*G98 -> 0
A99: 17 | B99: 配线ZR-BV-6 | C99: 1.名称:配线ZR-BV-6 2.型号:ZR-BV 3.规格:6 4.材质:铜芯 5.配线部位:管内、线槽内敷设 | D99: 按设计图示尺寸以单线长度计算（含预留长度） | E99: m | G99: =(H99+I99+J99+K99)*(1+L99) -> 9.4248595 | H99: =1.15*1.64 -> 1.886 | I99: =1.15*4.94 -> 5.681 | J99: =1.15*0.21 -> 0.2415 | K99: 0 | L99: =$L$4 -> 0.207 | M99: =F99*G99 -> 0
A100: 18 | B100: 配线ZR-BV-4 | C100: 1.名称:配线ZR-BV-4 2.型号:ZR-BV 3.规格:4 4.材质:铜芯 5.配线部位:管内、线槽内敷设 | D100: 按设计图示尺寸以单线长度计算（含预留长度） | E100: m | G100: =(H100+I100+J100+K100)*(1+L100) -> 6.8430865 | H100: =1.15*1.23 -> 1.4145 | I100: =1.15*3.49 -> 4.0135 | J100: =1.15*0.21 -> 0.2415 | K100: 0 | L100: =$L$4 -> 0.207 | M100: =F100*G100 -> 0
A101: 19 | B101: 配线ZR-BV-2.5 | C101: 1.名称:配线ZR-BV-2.5 2.型号:ZR-BV 3.规格:2.5 4.材质:铜芯 5.配线部位:管内、线槽内敷设 | D101: 按设计图示尺寸以单线长度计算（含预留长度） | E101: m | G101: =(H101+I101+J101+K101)*(1+L101) -> 6.218464 | H101: =1.15*1.84 -> 2.116 | I101: =1.15*2.42 -> 2.783 | J101: =1.15*0.22 -> 0.253 | K101: 0 | L101: =$L$4 -> 0.207 | M101: =F101*G101 -> 0
A102: 20 | B102: 配线WDZ-BYJ-10 | C102: 1.名称:配线WDZ-BYJ-10 2.型号:WDZ-BYJ 3.规格:10 4.材质:铜芯 5.配线部位:管内、线槽内敷设 | D102: 按设计图示尺寸以单线长度计算（含预留长度） | E102: m | G102: =(H102+I102+J102+K102)*(1+L102) -> 14.283034 | H102: =1.15*1.84 -> 2.116 | I102: =1.15*8.21 -> 9.4415 | J102: =1.15*0.24 -> 0.276 | K102: 0 | L102: =$L$4 -> 0.207 | M102: =F102*G102 -> 0
A103: 21 | B103: 配线WDZ-BYJ-6 | C103: 1.名称:配线WDZ-BYJ-6 2.型号:WDZ-BYJ 3.规格:6 4.材质:铜芯 5.配线部位:管内、线槽内敷设 | D103: 按设计图示尺寸以单线长度计算（含预留长度） | E103: m | F103: 300 | G103: =(H103+I103+J103+K103)*(1+L103) -> 9.4248595 | H103: =1.15*1.64 -> 1.886 | I103: =1.15*4.94 -> 5.681 | J103: =1.15*0.21 -> 0.2415 | K103: 0 | L103: =$L$4 -> 0.207 | M103: =F103*G103 -> 2827.4578
A104: 22 | B104: 配线WDZ-BYJ-4 | C104: 1.名称:配线WDZ-BYJ-4 2.型号:WDZ-BYJ 3.规格:4 4.材质:铜芯 5.配线部位:管内、线槽内敷设 | D104: 按设计图示尺寸以单线长度计算（含预留长度） | E104: m | F104: 1400 | G104: =(H104+I104+J104+K104)*(1+L104) -> 6.8430865 | H104: =1.15*1.23 -> 1.4145 | I104: =1.15*3.49 -> 4.0135 | J104: =1.15*0.21 -> 0.2415 | K104: 0 | L104: =$L$4 -> 0.207 | M104: =F104*G104 -> 9580.3211
A105: 23 | B105: 配线WDZ-BYJ-2.5 | C105: 1.名称:配线WDZ-BYJ-2.5 2.型号:WDZ-BYJ 3.规格:2.5 4.材质:铜芯 5.配线部位:管内、线槽内敷设 | D105: 按设计图示尺寸以单线长度计算（含预留长度） | E105: m | F105: 2100 | G105: =(H105+I105+J105+K105)*(1+L105) -> 6.218464 | H105: =1.15*1.84 -> 2.116 | I105: =1.15*2.42 -> 2.783 | J105: =1.15*0.22 -> 0.253 | K105: 0 | L105: =$L$4 -> 0.207 | M105: =F105*G105 -> 13058.774
A106: 24 | B106: 配线WDZB-BYJ-10 | C106: 1.名称:配线WDZB-BYJ-10 2.型号:WDZB-BYJ 3.规格:10 4.材质:铜芯 5.配线部位:管内、线槽内敷设 | D106: 按设计图示尺寸以单线长度计算（含预留长度） | E106: m | G106: =(H106+I106+J106+K106)*(1+L106) -> 14.283034 | H106: =1.15*1.84 -> 2.116 | I106: =1.15*8.21 -> 9.4415 | J106: =1.15*0.24 -> 0.276 | K106: 0 | L106: =$L$4 -> 0.207 | M106: =F106*G106 -> 0
A107: 25 | B107: 配线WDZB-BYJ-6 | C107: 1.名称:配线WDZB-BYJ-6 2.型号:WDZB-BYJ 3.规格:6 4.材质:铜芯 5.配线部位:管内、线槽内敷设 | D107: 按设计图示尺寸以单线长度计算（含预留长度） | E107: m | G107: =(H107+I107+J107+K107)*(1+L107) -> 9.4248595 | H107: =1.15*1.64 -> 1.886 | I107: =1.15*4.94 -> 5.681 | J107: =1.15*0.21 -> 0.2415 | K107: 0 | L107: =$L$4 -> 0.207 | M107: =F107*G107 -> 0
A108: 26 | B108: 配线WDZB-BYJ-4 | C108: 1.名称:配线WDZB-BYJ-4 2.型号:WDZB-BYJ 3.规格:4 4.材质:铜芯 5.配线部位:管内、线槽内敷设 | D108: 按设计图示尺寸以单线长度计算（含预留长度） | E108: m | G108: =(H108+I108+J108+K108)*(1+L108) -> 6.8430865 | H108: =1.15*1.23 -> 1.4145 | I108: =1.15*3.49 -> 4.0135 | J108: =1.15*0.21 -> 0.2415 | K108: 0 | L108: =$L$4 -> 0.207 | M108: =F108*G108 -> 0
A109: 27 | B109: 配线WDZB-BYJ-2.5 | C109: 1.名称:配线WDZB-BYJ-2.5 2.型号:WDZB-BYJ 3.规格:2.5 4.材质:铜芯 5.配线部位:管内、线槽内敷设 | D109: 按设计图示尺寸以单线长度计算（含预留长度） | E109: m | G109: =(H109+I109+J109+K109)*(1+L109) -> 6.218464 | H109: =1.15*1.84 -> 2.116 | I109: =1.15*2.42 -> 2.783 | J109: =1.15*0.22 -> 0.253 | K109: 0 | L109: =$L$4 -> 0.207 | M109: =F109*G109 -> 0
A110: 28 | B110: 配线RVV-7*0.75 | C110: 1.名称:配线RVV-7*0.75 2.型号:RVV 3.规格:7*0.75 4.材质:铜芯 5.配线部位:管内、线槽内敷设 | D110: 按设计图示尺寸以单线长度计算（含预留长度） | E110: m | F110: 120 | G110: =(H110+I110+J110+K110)*(1+L110) -> 22.469753 | H110: =1.15*6.76 -> 7.774 | I110: =1.15*9.208 -> 10.5892 | J110: =1.15*0.22 -> 0.253 | K110: 0 | L110: =$L$4 -> 0.207 | M110: =F110*G110 -> 2696.3704
A111: 29 | B111: 配线RVV-2*0.75 | C111: 1.名称:配线RVV-2*0.75 2.型号:RVV 3.规格:2*0.75 4.材质:铜芯 5.配线部位:管内、线槽内敷设 | D111: 按设计图示尺寸以单线长度计算（含预留长度） | E111: m | F111: 12 | G111: =(H111+I111+J111+K111)*(1+L111) -> 6.0657785 | H111: =1.15*1.73 -> 1.9895 | I111: =1.15*2.46 -> 2.829 | J111: =1.15*0.18 -> 0.207 | K111: 0 | L111: =$L$4 -> 0.207 | M111: =F111*G111 -> 72.789342
A112: 30 | B112: 配线RVV-2*0.75 | C112: 1.名称:配线RVV-2*1.0 2.型号:RVV 3.规格:2*1.0 4.材质:铜芯 5.配线部位:管内、线槽内敷设 | D112: 按设计图示尺寸以单线长度计算（含预留长度） | E112: m | G112: =(H112+I112+J112+K112)*(1+L112) -> 6.0657785 | H112: =1.15*1.73 -> 1.9895 | I112: =1.15*2.46 -> 2.829 | J112: =1.15*0.18 -> 0.207 | K112: 0 | L112: =$L$4 -> 0.207 | M112: =F112*G112 -> 0
...

Sheet 2.3弱电工程
A1: 长城智选商超店装修项目装饰工程
A2: 序号 | B2: 分部分项名称 | C2: 项目特征 | D2: 计量规则 | E2: 单位 | F2: 工程量 | G2: 综合单价 | H2: 人工 | I2: 主材 | J2: 辅材 | K2: 机械 | L2: 其他综合费率 | M2: 合计 | N2: 备注
A3: 一 | B3: 综合布线
A4: 1 | B4: 弱电机柜12U | C4: 1.名称:弱电机柜12U 2.规格:包含PDU插排，用于放置交换机、路由器等设备，留有冗余空间 3.安装方式:落地 | D4: 按设计图示数量计算 | E4: 台 | G4: =(H4+I4+J4+K4)*(1+L4) -> 920.61511 | H4: =VLOOKUP(B4,'[1]2.3弱电工程'!$B$4:$H$195,7,0) -> 270.73 | I4: =VLOOKUP(B4,'[1]2.3弱电工程'!$B$4:$I$195,8,0) -> 480.53 | J4: =VLOOKUP(B4,'[1]2.3弱电工程'!$B$4:$J$195,9,0) -> 10.49 | K4: =VLOOKUP(B4,'[1]2.3弱电工程'!$B$4:$K$195,10,0) -> 0.98 | L4: ='2.1装饰工程'!$L$4 -> 0.207 | M4: =F4*G4 -> 0
A5: 2 | B5: 弱电机柜24U | C5: 1.名称:弱电机柜24U 2.规格:包含PDU插排，用于放置交换机、路由器等设备，留有冗余空间 3.安装方式:落地 | D5: 按设计图示数量计算 | E5: 台 | G5: =(H5+I5+J5+K5)*(1+L5) -> 1755.9074 | H5: =VLOOKUP(B5,'[1]2.3弱电工程'!$B$4:$H$195,7,0) -> 270.73 | I5: =VLOOKUP(B5,'[1]2.3弱电工程'!$B$4:$I$195,8,0) -> 1172.57 | J5: =VLOOKUP(B5,'[1]2.3弱电工程'!$B$4:$J$195,9,0) -> 10.49 | K5: =VLOOKUP(B5,'[1]2.3弱电工程'!$B$4:$K$195,10,0) -> 0.98 | L5: =$L$4 -> 0.207 | M5: =F5*G5 -> 0
A6: 3 | B6: 弱电机柜27U | C6: 1.名称:弱电机柜27U 2.规格:包含PDU插排，用于放置交换机、路由器等设备，留有冗余空间 3.安装方式:落地 | D6: 按设计图示数量计算 | E6: 台 | F6: 1 | G6: =(H6+I6+J6+K6)*(1+L6) -> 2072.069 | H6: =VLOOKUP(B6,'[1]2.3弱电工程'!$B$4:$H$195,7,0) -> 270.73 | I6: =VLOOKUP(B6,'[1]2.3弱电工程'!$B$4:$I$195,8,0) -> 1434.51 | J6: =VLOOKUP(B6,'[1]2.3弱电工程'!$B$4:$J$195,9,0) -> 10.49 | K6: =VLOOKUP(B6,'[1]2.3弱电工程'!$B$4:$K$195,10,0) -> 0.98 | L6: =$L$4 -> 0.207 | M6: =F6*G6 -> 2072.069
A7: 4 | B7: 弱电机柜42U | C7: 1.名称:弱电机柜42U 2.规格:包含PDU插排，用于放置交换机、路由器等设备，留有冗余空间 3.安装方式:落地 | D7: 按设计图示数量计算 | E7: 台 | G7: =(H7+I7+J7+K7)*(1+L7) -> 3134.8687 | H7: =VLOOKUP(B7,'[1]2.3弱电工程'!$B$4:$H$195,7,0) -> 270.73 | I7: =VLOOKUP(B7,'[1]2.3弱电工程'!$B$4:$I$195,8,0) -> 2315.04 | J7: =VLOOKUP(B7,'[1]2.3弱电工程'!$B$4:$J$195,9,0) -> 10.49 | K7: =VLOOKUP(B7,'[1]2.3弱电工程'!$B$4:$K$195,10,0) -> 0.98 | L7: =$L$4 -> 0.207 | M7: =F7*G7 -> 0
A8: 5 | B8: USP不间断电源 | C8: 1.名称:USP不间断电源 2.型号:参考英威腾HT1103CL，内置电池，后备时间＞30分钟 | D8: 按设计图示数量计算 | E8: 个 | G8: =(H8+I8+J8+K8)*(1+L8) -> 5603.6303 | H8: =VLOOKUP(B8,'[1]2.3弱电工程'!$B$4:$H$195,7,0) -> 960.41 | I8: =VLOOKUP(B8,'[1]2.3弱电工程'!$B$4:$I$195,8,0) -> 2981.6 | J8: =VLOOKUP(B8,'[1]2.3弱电工程'!$B$4:$J$195,9,0) -> 700.6 | K8: =VLOOKUP(B8,'[1]2.3弱电工程'!$B$4:$K$195,10,0) -> 0 | L8: =$L$4 -> 0.207 | M8: =F8*G8 -> 0
A9: 6 | B9: 24口配线架 | C9: 1.名称:24口配线架 2.规格:1U,24口，含同品牌非屏蔽模块，模块满配 | D9: 按设计图示数量计算 | E9: 个 | G9: =(H9+I9+J9+K9)*(1+L9) -> 434.8821 | H9: =VLOOKUP(B9,'[1]2.3弱电工程'!$B$4:$H$195,7,0) -> 216.23 | I9: =VLOOKUP(B9,'[1]2.3弱电工程'!$B$4:$I$195,8,0) -> 144.07 | J9: =VLOOKUP(B9,'[1]2.3弱电工程'!$B$4:$J$195,9,0) -> 0 | K9: =VLOOKUP(B9,'[1]2.3弱电工程'!$B$4:$K$195,10,0) -> 0 | L9: =$L$4 -> 0.207 | M9: =F9*G9 -> 0
A10: 7 | B10: 48口配线架 | C10: 1.名称:48口配线架 2.规格:48口，含同品牌非屏蔽模块，模块满配 | D10: 按设计图示数量计算 | E10: 个 | G10: =(H10+I10+J10+K10)*(1+L10) -> 665.35875 | H10: =VLOOKUP(B10,'[1]2.3弱电工程'!$B$4:$H$195,7,0) -> 235.65 | I10: =VLOOKUP(B10,'[1]2.3弱电工程'!$B$4:$I$195,8,0) -> 315.6 | J10: =VLOOKUP(B10,'[1]2.3弱电工程'!$B$4:$J$195,9,0) -> 0 | K10: =VLOOKUP(B10,'[1]2.3弱电工程'!$B$4:$K$195,10,0) -> 0 | L10: =$L$4 -> 0.207 | M10: =F10*G10 -> 0
A11: 8 | B11: 24口理线架 | C11: 1.名称:24口理线架 2.规格:1U,金属材质 | D11: 按设计图示数量计算 | E11: 个 | F11: 1 | G11: =(H11+I11+J11+K11)*(1+L11) -> 107.08504 | H11: =VLOOKUP(B11,'[1]2.3弱电工程'!$B$4:$H$195,7,0) -> 22.75 | I11: =VLOOKUP(B11,'[1]2.3弱电工程'!$B$4:$I$195,8,0) -> 65.97 | J11: =VLOOKUP(B11,'[1]2.3弱电工程'!$B$4:$J$195,9,0) -> 0 | K11: =VLOOKUP(B11,'[1]2.3弱电工程'!$B$4:$K$195,10,0) -> 0 | L11: =$L$4 -> 0.207 | M11: =F11*G11 -> 107.08504
A12: 9 | B12: 48口理线架 | C12: 1.名称:48口理线架 2.规格:金属材质 | D12: 按设计图示数量计算 | E12: 个 | G12: =(H12+I12+J12+K12)*(1+L12) -> 142.60705 | H12: =VLOOKUP(B12,'[1]2.3弱电工程'!$B$4:$H$195,7,0) -> 22.75 | I12: =VLOOKUP(B12,'[1]2.3弱电工程'!$B$4:$I$195,8,0) -> 95.4 | J12: =VLOOKUP(B12,'[1]2.3弱电工程'!$B$4:$J$195,9,0) -> 0 | K12: =VLOOKUP(B12,'[1]2.3弱电工程'!$B$4:$K$195,10,0) -> 0 | L12: =$L$4 -> 0.207 | M12: =F12*G12 -> 0
A13: 10 | B13: 24口交换机 | C13: 1.名称:24口交换机 2.功能:可网管、不低于24口，POE供电，参考TP-LINK | D13: 按设计图示数量计算 | E13: 台 | G13: =(H13+I13+J13+K13)*(1+L13) -> 2977.6569 | H13: =VLOOKUP(B13,'[1]2.3弱电工程'!$B$4:$H$195,7,0) -> 614.25 | I13: =VLOOKUP(B13,'[1]2.3弱电工程'!$B$4:$I$195,8,0) -> 1831.86 | J13: =VLOOKUP(B13,'[1]2.3弱电工程'!$B$4:$J$195,9,0) -> 10.49 | K13: =VLOOKUP(B13,'[1]2.3弱电工程'!$B$4:$K$195,10,0) -> 10.39 | L13: =$L$4 -> 0.207 | M13: =F13*G13 -> 0
A14: 11 | B14: 48口交换机 | C14: 1.名称:48口交换机 2.功能:可网管、不低于48口，POE供电，参考TP-LINK：TL-SG3452P | D14: 按设计图示数量计算 | E14: 台 | G14: =(H14+I14+J14+K14)*(1+L14) -> 5148.7723 | H14: =VLOOKUP(B14,'[1]2.3弱电工程'!$B$4:$H$195,7,0) -> 1023.75 | I14: =VLOOKUP(B14,'[1]2.3弱电工程'!$B$4:$I$195,8,0) -> 3215.93 | J14: =VLOOKUP(B14,'[1]2.3弱电工程'!$B$4:$J$195,9,0) -> 10.49 | K14: =VLOOKUP(B14,'[1]2.3弱电工程'!$B$4:$K$195,10,0) -> 15.59 | L14: =$L$4 -> 0.207 | M14: =F14*G14 -> 0
A15: 12 | B15: 千兆可网管交换机 | C15: 1.名称：交换机 2.规格型号：TP-LINK：TL-SG2226P，可网管、不低于24口，POE供电 3.包括为满足设计、验收规范规定施工所需的一切工序 | D15: 按设计图示数量计算 | E15: 台 | F15: 1 | G15: =(H15+I15+J15+K15)*(1+L15) -> 2737.3191 | H15: =VLOOKUP(B15,'[1]2.3弱电工程'!$B$4:$H$195,7,0) -> 614.25 | I15: =VLOOKUP(B15,'[1]2.3弱电工程'!$B$4:$I$195,8,0) -> 1632.74 | J15: =VLOOKUP(B15,'[1]2.3弱电工程'!$B$4:$J$195,9,0) -> 10.49 | K15: =VLOOKUP(B15,'[1]2.3弱电工程'!$B$4:$K$195,10,0) -> 10.39 | L15: =$L$4 -> 0.207 | M15: =F15*G15 -> 2737.3191
A16: 13 | B16: 工业级以太网交换机 | C16: 1.名称:工业级以太网交换机 2.功能:不低于4个千兆电口+2千兆SFP光口插槽，含光模块、含电源适配器 | D16: 按设计图示数量计算 | E16: 台 | G16: =(H16+I16+J16+K16)*(1+L16) -> 3201.4347 | H16: =VLOOKUP(B16,'[1]2.3弱电工程'!$B$4:$H$195,7,0) -> 614.25 | I16: =VLOOKUP(B16,'[1]2.3弱电工程'!$B$4:$I$195,8,0) -> 2017.26 | J16: =VLOOKUP(B16,'[1]2.3弱电工程'!$B$4:$J$195,9,0) -> 10.49 | K16: =VLOOKUP(B16,'[1]2.3弱电工程'!$B$4:$K$195,10,0) -> 10.39 | L16: =$L$4 -> 0.207 | M16: =F16*G16 -> 0
A17: 14 | B17: 路由器 | C17: 1.名称：路由器 2.规格型号：TP-LINK：TL-ER3200G千兆企业级， 3.包括为满足设计、验收规范规定施工所需的一切工序 | D17: 按设计图示数量计算 | E17: 台 | F17: 1 | G17: =(H17+I17+J17+K17)*(1+L17) -> 986.07072 | H17: =VLOOKUP(B17,'[1]2.3弱电工程'!$B$4:$H$195,7,0) -> 182 | I17: =VLOOKUP(B17,'[1]2.3弱电工程'!$B$4:$I$195,8,0) -> 620.31 | J17: =VLOOKUP(B17,'[1]2.3弱电工程'!$B$4:$J$195,9,0) -> 10.49 | K17: =VLOOKUP(B17,'[1]2.3弱电工程'!$B$4:$K$195,10,0) -> 4.16 | L17: =$L$4 -> 0.207 | M17: =F17*G17 -> 986.07072
A18: 15 | B18: 显示器 | C18: 1.名称:显示器 2.规格:尺寸23.8英寸，分辨率：1920*1080像素，接口：DP、HDMI，附带一根3米HDMI线、键盘1个、鼠标1个 | D18: 按设计图示数量计算 | E18: 台 | F18: 1 | G18: =(H18+I18+J18+K18)*(1+L18) -> 1330.5847 | H18: =VLOOKUP(B18,'[1]2.3弱电工程'!$B$4:$H$195,7,0) -> 54.6 | I18: =VLOOKUP(B18,'[1]2.3弱电工程'!$B$4:$I$195,8,0) -> 1047.79 | J18: =VLOOKUP(B18,'[1]2.3弱电工程'!$B$4:$J$195,9,0) -> 0 | K18: =VLOOKUP(B18,'[1]2.3弱电工程'!$B$4:$K$195,10,0) -> 0 | L18: =$L$4 -> 0.207 | M18: =F18*G18 -> 1330.5847
A19: 16 | B19: 100寸电视(包括电视伸缩支架的采购、安装) | C19: 1.名称:100寸电视 2.类别:(包括电视支架的采购、安装) 3.规格:100寸，选用酷开创维 | D19: 按设计图示数量计算 | E19: 台 | F19: 1 | G19: =(H19+I19+J19+K19)*(1+L19) -> 15449.503 | H19: =VLOOKUP(B19,'[1]2.3弱电工程'!$B$4:$H$195,7,0) -> 63.7 | I19: =VLOOKUP(B19,'[1]2.3弱电工程'!$B$4:$I$195,8,0) -> 12734.51 | J19: =VLOOKUP(B19,'[1]2.3弱电工程'!$B$4:$J$195,9,0) -> 1.71 | K19: =VLOOKUP(B19,'[1]2.3弱电工程'!$B$4:$K$195,10,0) -> 0 | L19: =$L$4 -> 0.207 | M19: =F19*G19 -> 15449.503
A20: 17 | B20: 75寸电视(包括伸缩支架的采购、安装) | C20: 1.名称:75寸电视 2.类别:(包括电视支架的采购、安装) 3.规格:75寸，选用酷开创维 | D20: 按设计图示数量计算 | E20: 台 | F20: 1 | G20: =(H20+I20+J20+K20)*(1+L20) -> 5300.838 | H20: =1.15*63.7 -> 73.255 | I20: 4312.5 | J20: =1.15*1.71 -> 1.9665 | K20: =1.15*3.5 -> 4.025 | L20: =$L$4 -> 0.207 | M20: =F20*G20 -> 5300.838
A21: 18 | B21: 65寸电视(包括伸缩支架的采购、安装) | C21: 1.名称:65寸电视 2.类别:(包括电视支架的采购、安装) 3.规格:65寸，选用酷开创维 | D21: 按设计图示数量计算 | E21: 台 | F21: 1 | G21: =(H21+I21+J21+K21)*(1+L21) -> 4051.593 | H21: =1.15*63.7 -> 73.255 | I21: 3277.5 | J21: =1.15*1.71 -> 1.9665 | K21: =1.15*3.5 -> 4.025 | L21: =$L$4 -> 0.207 | M21: =F21*G21 -> 4051.593
A22: 19 | B22: 智能电表 | C22: 1.名称:智能电表 2.规格:采用4G无线联网，赠送至少8年流量，无需采集器，赠送平台，可查看用电量情况 | D22: 按设计图示数量计算 | E22: 台 | F22: 1 | G22: =(H22+I22+J22+K22)*(1+L22) -> 1168.714 | H22: =VLOOKUP(B22,'[1]2.3弱电工程'!$B$4:$H$195,7,0) -> 250.25 | I22: =VLOOKUP(B22,'[1]2.3弱电工程'!$B$4:$I$195,8,0) -> 716.81 | J22: =VLOOKUP(B22,'[1]2.3弱电工程'!$B$4:$J$195,9,0) -> 1.22 | K22: =VLOOKUP(B22,'[1]2.3弱电工程'!$B$4:$K$195,10,0) -> 0 | L22: =$L$4 -> 0.207 | M22: =F22*G22 -> 1168.714
A23: 20 | B23: 桌面型防火墙 | C23: 1.名称：桌面型防火墙 2.规格型号：TP-LINK：TL-FW5600，支持配置安全策略、审计策略、带宽策略，包含2年病毒库免费升级服务 3.包括为满足设计、验收规范规定施工所需的一切工序 | D23: 按设计图示数量计算 | E23: 台 | F23: 1 | G23: =(H23+I23+J23+K23)*(1+L23) -> 2691.6221 | H23: =VLOOKUP(B23,'[1]2.3弱电工程'!$B$4:$H$195,7,0) -> 364 | I23: =VLOOKUP(B23,'[1]2.3弱电工程'!$B$4:$I$195,8,0) -> 1845.13 | J23: =VLOOKUP(B23,'[1]2.3弱电工程'!$B$4:$J$195,9,0) -> 10.49 | K23: =VLOOKUP(B23,'[1]2.3弱电工程'!$B$4:$K$195,10,0) -> 10.39 | L23: =$L$4 -> 0.207 | M23: =F23*G23 -> 2691.6221
A24: 21 | B24: 无线AP | C24: 1.名称：无线AP 2.规格型号：TP-LINK：TL-XAP1506GC-PoE/DC易展版、千兆、802.11ax、双频WIFI，参考 3.包括为满足设计、验收规范规定施工所需的一切工序 | D24: 按设计图示数量计算 | E24: 台 | F24: 2 | G24: =(H24+I24+J24+K24)*(1+L24) -> 603.85003 | H24: =VLOOKUP(B24,'[1]2.3弱电工程'!$B$4:$H$195,7,0) -> 68.25 | I24: =VLOOKUP(B24,'[1]2.3弱电工程'!$B$4:$I$195,8,0) -> 432.04 | J24: =VLOOKUP(B24,'[1]2.3弱电工程'!$B$4:$J$195,9,0) -> 0 | K24: =VLOOKUP(B24,'[1]2.3弱电工程'!$B$4:$K$195,10,0) -> 0 | L24: =$L$4 -> 0.207 | M24: =F24*G24 -> 1207.7001
A25: 22 | B25: 单口信息插座 | C25: 1.名称:单口信息插座 2.规格:白色，含同等品牌六类非屏蔽模块 3.安装方式:暗装 | D25: 按设计图示数量计算 | E25: 个 | F25: 6 | G25: =(H25+I25+J25+K25)*(1+L25) -> 38.84126 | H25: =VLOOKUP(B25,'[1]2.3弱电工程'!$B$4:$H$195,7,0) -> 11.38 | I25: =VLOOKUP(B25,'[1]2.3弱电工程'!$B$4:$I$195,8,0) -> 20.8 | J25: =VLOOKUP(B25,'[1]2.3弱电工程'!$B$4:$J$195,9,0) -> 0 | K25: =VLOOKUP(B25,'[1]2.3弱电工程'!$B$4:$K$195,10,0) -> 0 | L25: =$L$4 -> 0.207 | M25: =F25*G25 -> 233.04756
A26: 23 | B26: 双口信息插座 | C26: 1.名称:双口信息插座 2.规格:白色，含同等品牌六类非屏蔽模块 3.安装方式:暗装 | D26: 按设计图示数量计算 | E26: 个 | F26: 4 | G26: =(H26+I26+J26+K26)*(1+L26) -> 51.35785 | H26: =VLOOKUP(B26,'[1]2.3弱电工程'!$B$4:$H$195,7,0) -> 13.65 | I26: =VLOOKUP(B26,'[1]2.3弱电工程'!$B$4:$I$195,8,0) -> 28.9 | J26: =VLOOKUP(B26,'[1]2.3弱电工程'!$B$4:$J$195,9,0) -> 0 | K26: =VLOOKUP(B26,'[1]2.3弱电工程'!$B$4:$K$195,10,0) -> 0 | L26: =$L$4 -> 0.207 | M26: =F26*G26 -> 205.4314
A27: 24 | B27: 六类非屏蔽网线 | C27: 1.名称:六类非屏蔽网线 2.敷设方式:综合考虑 | D27: 按设计图示尺寸以长度计算 | E27: m | F27: 480 | G27: =(H27+I27+J27+K27)*(1+L27) -> 5.05733 | H27: =VLOOKUP(B27,'[1]2.3弱电工程'!$B$4:$H$195,7,0) -> 1.57 | I27: =VLOOKUP(B27,'[1]2.3弱电工程'!$B$4:$I$195,8,0) -> 2.61 | J27: =VLOOKUP(B27,'[1]2.3弱电工程'!$B$4:$J$195,9,0) -> 0.01 | K27: =VLOOKUP(B27,'[1]2.3弱电工程'!$B$4:$K$195,10,0) -> 0 | L27: =$L$4 -> 0.207 | M27: =F27*G27 -> 2427.5184
A28: 25 | B28: 六类非屏蔽成品跳线 | C28: 1.名称:六类非屏蔽成品跳线 | D28: 按设计图示数量计算 | E28: 条 | G28: =(H28+I28+J28+K28)*(1+L28) -> 28.940842 | H28: =1.15*4.55 -> 5.2325 | I28: =1.15*15.6 -> 17.94 | J28: =1.15*0.5 -> 0.575 | K28: =1.15*0.2 -> 0.23 | L28: =$L$4 -> 0.207 | M28: =F28*G28 -> 0
A29: 26 | B29: RVV-2*1.0 | C29: 1.名称:RVV-2*1.0 2.敷设方式:综合考虑 | D29: 按设计图示尺寸以长度计算 | E29: m | F29: 35 | G29: =(H29+I29+J29+K29)*(1+L29) -> 5.82981 | H29: =VLOOKUP(B29,'[1]2.3弱电工程'!$B$4:$H$195,7,0) -> 1.73 | I29: =VLOOKUP(B29,'[1]2.3弱电工程'!$B$4:$I$195,8,0) -> 2.92 | J29: =VLOOKUP(B29,'[1]2.3弱电工程'!$B$4:$J$195,9,0) -> 0.18 | K29: =VLOOKUP(B29,'[1]2.3弱电工程'!$B$4:$K$195,10,0) -> 0 | L29: =$L$4 -> 0.207 | M29: =F29*G29 -> 204.04335
A30: 27 | B30: RVV-2*2.5 | C30: 1.名称:RVV-2*2.5 2.敷设方式:综合考虑 | D30: 按设计图示尺寸以长度计算 | E30: m | G30: =(H30+I30+J30+K30)*(1+L30) -> 9.75256 | H30: =VLOOKUP(B30,'[1]2.3弱电工程'!$B$4:$H$195,7,0) -> 1.73 | I30: =VLOOKUP(B30,'[1]2.3弱电工程'!$B$4:$I$195,8,0) -> 6.17 | J30: =VLOOKUP(B30,'[1]2.3弱电工程'!$B$4:$J$195,9,0) -> 0.18 | K30: =VLOOKUP(B30,'[1]2.3弱电工程'!$B$4:$K$195,10,0) -> 0 | L30: =$L$4 -> 0.207 | M30: =F30*G30 -> 0
A31: 28 | B31: 双光纤跳线 | C31: 1.名称:双光纤跳线 2.类别:单模，双芯，2M，支持FC/SC/ST/LC互转 | D31: 按设计图示数量计算 | E31: 条 | G31: =(H31+I31+J31+K31)*(1+L31) -> 38.365702 | H31: =1.15*4.55 -> 5.2325 | I31: =1.15*22.39 -> 25.7485 | J31: =1.15*0.5 -> 0.575 | K31: =1.15*0.2 -> 0.23 | L31: =$L$4 -> 0.207 | M31: =F31*G31 -> 0
A32: 29 | B32: 尾纤2m | C32: 1.名称:尾纤2m | D32: 按设计图示数量计算 | E32: 根 | G32: =(H32+I32+J32+K32)*(1+L32) -> 28.15931 | H32: =VLOOKUP(B32,'[1]2.3弱电工程'!$B$4:$H$195,7,0) -> 18.13 | I32: =VLOOKUP(B32,'[1]2.3弱电工程'!$B$4:$I$195,8,0) -> 3.1 | J32: =VLOOKUP(B32,'[1]2.3弱电工程'!$B$4:$J$195,9,0) -> 0 | K32: =VLOOKUP(B32,'[1]2.3弱电工程'!$B$4:$K$195,10,0) -> 2.1 | L32: =$L$4 -> 0.207 | M32: =F32*G32 -> 0
A33: 30 | B33: 配管JDG20 | C33: 1.名称:配管JDG20 2.材质:镀锌薄钢管 3.规格:Φ20 4.配置形式:明配 5.接地要求:按规范要求 6.其他:含支、吊架制作安装 | D33: 按设计图示尺寸以长度计算 | E33: m | F33: 190 | G33: =(H33+I33+J33+K33)*(1+L33) -> 23.61073 | H33: =1.15*10.09 -> 11.6035 | I33: =1.15*4.84 -> 5.566 | J33: =1.15*1.58 -> 1.817 | K33: =1.15*0.5 -> 0.575 | L33: =$L$4 -> 0.207 | M33: =F33*G33 -> 4486.0388
A34: 31 | B34: 配管JDG20 | C34: 1.名称:配管JDG20 2.材质:镀锌薄钢管 3.规格Φ20 4.配置形式:暗配 5.接地要求:按规范要求 | D34: 按设计图示尺寸以长度计算 | E34: m | G34: =(H34+I34+J34+K34)*(1+L34) -> 22.930586 | H34: =1.15*10.74 -> 12.351 | I34: =1.15*4.84 -> 5.566 | J34: =1.15*0.44 -> 0.506 | K34: =1.15*0.5 -> 0.575 | L34: =$L$4 -> 0.207 | M34: =F34*G34 -> 0
A35: 32 | B35: 配管JDG25 | C35: 1.名称:配管JDG25 2.材质:镀锌薄钢管 3.规格:Φ25 4.配置形式:明配 5.接地要求:按规范要求 6.其他:含支、吊架制作安装 | D35: 按设计图示尺寸以长度计算 | E35: m | G35: =(H35+I35+J35+K35)*(1+L35) -> 26.220264 | H35: =1.15*11.59 -> 13.3285 | I35: =1.15*5.65 -> 6.4975 | J35: =1.15*1.15 -> 1.3225 | K35: =1.15*0.5 -> 0.575 | L35: =$L$4 -> 0.207 | M35: =F35*G35 -> 0
A36: 33 | B36: 配管JDG25 | C36: 1.名称:配管JDG25 2.材质:镀锌薄钢管 3.规格Φ25 4.配置形式:暗配 5.接地要求:按规范要求 | D36: 按设计图示尺寸以长度计算 | E36: m | G36: =(H36+I36+J36+K36)*(1+L36) -> 23.485806 | H36: =1.15*10.33 -> 11.8795 | I36: =1.15*5.65 -> 6.4975 | J36: =1.15*0.44 -> 0.506 | K36: =1.15*0.5 -> 0.575 | L36: =$L$4 -> 0.207 | M36: =F36*G36 -> 0
A37: 34 | B37: 配管JDG32 | C37: 1.名称:配管JDG32 2.材质:镀锌薄钢管 3.规格:Φ32 4.配置形式:明配 5.接地要求:按规范要求 6.其他:含支、吊架制作安装 | D37: 按设计图示尺寸以长度计算 | E37: m | G37: =(H37+I37+J37+K37)*(1+L37) -> 33.410364 | H37: =1.15*13.56 -> 15.594 | I37: =1.15*8.32 -> 9.568 | J37: =1.15*1.69 -> 1.9435 | K37: =1.15*0.5 -> 0.575 | L37: =$L$4 -> 0.207 | M37: =F37*G37 -> 0
A38: 35 | B38: 配管JDG32 | C38: 1.名称:配管JDG32 2.材质:镀锌薄钢管 3.规格Φ32 4.配置形式:暗配 5.接地要求:按规范要求 | D38: 按设计图示尺寸以长度计算 | E38: m | G38: =(H38+I38+J38+K38)*(1+L38) -> 29.815314 | H38: =1.15*11.78 -> 13.547 | I38: =1.15*8.32 -> 9.568 | J38: =1.15*0.88 -> 1.012 | K38: =1.15*0.5 -> 0.575 | L38: =$L$4 -> 0.207 | M38: =F38*G38 -> 0
A39: 36 | B39: 配管PCDN20 | C39: 1.名称:配管PCDN20 2.材质:PC 3.规格:DN20mm 4.配置形式:明配 5.接地要求:按规范要求 | D39: 按设计图示尺寸以长度计算 | E39: m | G39: =(H39+I39+J39+K39)*(1+L39) -> 14.42365 | H39: =VLOOKUP(B39,'[1]2.3弱电工程'!$B$4:$H$195,7,0) -> 9.21 | I39: =VLOOKUP(B39,'[1]2.3弱电工程'!$B$4:$I$195,8,0) -> 1.67 | J39: =VLOOKUP(B39,'[1]2.3弱电工程'!$B$4:$J$195,9,0) -> 1.07 | K39: =VLOOKUP(B39,'[1]2.3弱电工程'!$B$4:$K$195,10,0) -> 0 | L39: =$L$4 -> 0.207 | M39: =F39*G39 -> 0
A40: 37 | B40: 配管PCDN20 | C40: 1.名称:配管PCDN20 2.材质:PC 3.规格:DN20mm 4.配置形式:暗配 5.接地要求:按规范要求 | D40: 按设计图示尺寸以长度计算 | E40: m | G40: =(H40+I40+J40+K40)*(1+L40) -> 14.42365 | H40: =VLOOKUP(B40,'[1]2.3弱电工程'!$B$4:$H$195,7,0) -> 9.21 | I40: =VLOOKUP(B40,'[1]2.3弱电工程'!$B$4:$I$195,8,0) -> 1.67 | J40: =VLOOKUP(B40,'[1]2.3弱电工程'!$B$4:$J$195,9,0) -> 1.07 | K40: =VLOOKUP(B40,'[1]2.3弱电工程'!$B$4:$K$195,10,0) -> 0 | L40: =$L$4 -> 0.207 | M40: =F40*G40 -> 0
A41: 38 | B41: 配管PCDN25 | C41: 1.名称:配管PCDN25 2.材质:PC 3.规格:DN25mm 4.配置形式:明配 5.接地要求:按规范要求 | D41: 按设计图示尺寸以长度计算 | E41: m | G41: =(H41+I41+J41+K41)*(1+L41) -> 16.7773 | H41: =VLOOKUP(B41,'[1]2.3弱电工程'!$B$4:$H$195,7,0) -> 11.1 | I41: =VLOOKUP(B41,'[1]2.3弱电工程'!$B$4:$I$195,8,0) -> 1.7 | J41: =VLOOKUP(B41,'[1]2.3弱电工程'!$B$4:$J$195,9,0) -> 1.1 | K41: =VLOOKUP(B41,'[1]2.3弱电工程'!$B$4:$K$195,10,0) -> 0 | L41: =$L$4 -> 0.207 | M41: =F41*G41 -> 0
A42: 39 | B42: 配管PCDN25 | C42: 1.名称:配管PCDN25 2.材质:PC 3.规格:DN25mm 4.配置形式:暗配 5.接地要求:按规范要求 | D42: 按设计图示尺寸以长度计算 | E42: m | G42: =(H42+I42+J42+K42)*(1+L42) -> 16.7773 | H42: =VLOOKUP(B42,'[1]2.3弱电工程'!$B$4:$H$195,7,0) -> 11.1 | I42: =VLOOKUP(B42,'[1]2.3弱电工程'!$B$4:$I$195,8,0) -> 1.7 | J42: =VLOOKUP(B42,'[1]2.3弱电工程'!$B$4:$J$195,9,0) -> 1.1 | K42: =VLOOKUP(B42,'[1]2.3弱电工程'!$B$4:$K$195,10,0) -> 0 | L42: =$L$4 -> 0.207 | M42: =F42*G42 -> 0
A43: 40 | B43: 配管PCDN32 | C43: 1.名称:配管PCDN32 2.材质:PC 3.规格:DN32mm 4.配置形式:明配 5.接地要求:按规范要求 | D43: 按设计图示尺寸以长度计算 | E43: m | G43: =(H43+I43+J43+K43)*(1+L43) -> 19.34821 | H43: =VLOOKUP(B43,'[1]2.3弱电工程'!$B$4:$H$195,7,0) -> 10.6 | I43: =VLOOKUP(B43,'[1]2.3弱电工程'!$B$4:$I$195,8,0) -> 3.94 | J43: =VLOOKUP(B43,'[1]2.3弱电工程'!$B$4:$J$195,9,0) -> 1.49 | K43: =VLOOKUP(B43,'[1]2.3弱电工程'!$B$4:$K$195,10,0) -> 0 | L43: =$L$4 -> 0.207 | M43: =F43*G43 -> 0
A44: 41 | B44: 配管PCDN32 | C44: 1.名称:配管PCDN32 2.材质:PC 3.规格:DN32mm 4.配置形式:暗配 5.接地要求:按规范要求 | D44: 按设计图示尺寸以长度计算 | E44: m | G44: =(H44+I44+J44+K44)*(1+L44) -> 19.34821 | H44: =VLOOKUP(B44,'[1]2.3弱电工程'!$B$4:$H$195,7,0) -> 10.6 | I44: =VLOOKUP(B44,'[1]2.3弱电工程'!$B$4:$I$195,8,0) -> 3.94 | J44: =VLOOKUP(B44,'[1]2.3弱电工程'!$B$4:$J$195,9,0) -> 1.49 | K44: =VLOOKUP(B44,'[1]2.3弱电工程'!$B$4:$K$195,10,0) -> 0 | L44: =$L$4 -> 0.207 | M44: =F44*G44 -> 0
A45: 42 | B45: 金属软管DN20 | C45: 1.名称:金属软管DN20 2.材质:金属软管 3.规格:DN20mm 4.配置形式:明配 5.接地要求:按规范要求 | D45: 按设计图示尺寸以长度计算 | E45: m | G45: =(H45+I45+J45+K45)*(1+L45) -> 13.28907 | H45: =VLOOKUP(B45,'[1]2.3弱电工程'!$B$4:$H$195,7,0) -> 6.9 | I45: =VLOOKUP(B45,'[1]2.3弱电工程'!$B$4:$I$195,8,0) -> 3 | J45: =VLOOKUP(B45,'[1]2.3弱电工程'!$B$4:$J$195,9,0) -> 1.11 | K45: =VLOOKUP(B45,'[1]2.3弱电工程'!$B$4:$K$195,10,0) -> 0 | L45: =$L$4 -> 0.207 | M45: =F45*G45 -> 0
A46: 43 | B46: 金属软管DN25 | C46: 1.名称:金属软管DN25 2.材质:金属软管 3.规格:DN25mm 4.配置形式:明配 5.接地要求:按规范要求 | D46: 按设计图示尺寸以长度计算 | E46: m | G46: =(H46+I46+J46+K46)*(1+L46) -> 14.74954 | H46: =VLOOKUP(B46,'[1]2.3弱电工程'!$B$4:$H$195,7,0) -> 8 | I46: =VLOOKUP(B46,'[1]2.3弱电工程'!$B$4:$I$195,8,0) -> 3.2 | J46: =VLOOKUP(B46,'[1]2.3弱电工程'!$B$4:$J$195,9,0) -> 1.02 | K46: =VLOOKUP(B46,'[1]2.3弱电工程'!$B$4:$K$195,10,0) -> 0 | L46: =$L$4 -> 0.207 | M46: =F46*G46 -> 0
A47: 44 | B47: 弱电线槽100*50 | C47: 1.名称:弱电线槽100*50 2.材质:PVC 3.接地方式:按规范要求 4.其他:含支、吊架制作安装 | D47: 按设计图示尺寸以长度计算 | E47: m | G47: =(H47+I47+J47+K47)*(1+L47) -> 44.04343 | H47: =VLOOKUP(B47,'[1]2.3弱电工程'!$B$4:$H$195,7,0) -> 29.8 | I47: =VLOOKUP(B47,'[1]2.3弱电工程'!$B$4:$I$195,8,0) -> 6 | J47: =VLOOKUP(B47,'[1]2.3弱电工程'!$B$4:$J$195,9,0) -> 0.69 | K47: =VLOOKUP(B47,'[1]2.3弱电工程'!$B$4:$K$195,10,0) -> 0 | L47: =$L$4 -> 0.207 | M47: =F47*G47 -> 0
A48: 45 | B48: 弱电桥架100*50 | C48: 1.名称:弱电桥架100*50 2.材质:钢制 3.接地方式:按规范要求 4.其他:含支、吊架制作安装 | D48: 按设计图示尺寸以长度计算 | E48: m | F48: 10 | G48: =(H48+I48+J48+K48)*(1+L48) -> 64.91246 | H48: =VLOOKUP(B48,'[1]2.3弱电工程'!$B$4:$H$195,7,0) -> 29.8 | I48: =VLOOKUP(B48,'[1]2.3弱电工程'!$B$4:$I$195,8,0) -> 14.9 | J48: =VLOOKUP(B48,'[1]2.3弱电工程'!$B$4:$J$195,9,0) -> 8.56 | K48: =VLOOKUP(B48,'[1]2.3弱电工程'!$B$4:$K$195,10,0) -> 0.52 | L48: =$L$4 -> 0.207 | M48: =F48*G48 -> 649.1246
A49: 46 | B49: 弱电桥架100*100 | C49: 1.名称:弱电桥架100*100 2.材质:钢制 3.接地方式:按规范要求 4.其他:含支、吊架制作安装 | D49: 按设计图示尺寸以长度计算 | E49: m | F49: 27.5 | G49: =(H49+I49+J49+K49)*(1+L49) -> 76.70485 | H49: =VLOOKUP(B49,'[1]2.3弱电工程'!$B$4:$H$195,7,0) -> 24.57 | I49: =VLOOKUP(B49,'[1]2.3弱电工程'!$B$4:$I$195,8,0) -> 29.9 | J49: =VLOOKUP(B49,'[1]2.3弱电工程'!$B$4:$J$195,9,0) -> 8.56 | K49: =VLOOKUP(B49,'[1]2.3弱电工程'!$B$4:$K$195,10,0) -> 0.52 | L49: =$L$4 -> 0.207 | M49: =F49*G49 -> 2109.3834
A50: 47 | B50: 弱电桥架150*100 | C50: 1.名称:弱电桥架150*100 2.材质:钢制 3.接地方式:按规范要求 4.其他:含支、吊架制作安装 | D50: 按设计图示尺寸以长度计算 | E50: m | G50: =(H50+I50+J50+K50)*(1+L50) -> 89.02832 | H50: =VLOOKUP(B50,'[1]2.3弱电工程'!$B$4:$H$195,7,0) -> 30.95 | I50: =VLOOKUP(B50,'[1]2.3弱电工程'!$B$4:$I$195,8,0) -> 33.19 | J50: =VLOOKUP(B50,'[1]2.3弱电工程'!$B$4:$J$195,9,0) -> 8.61 | K50: =VLOOKUP(B50,'[1]2.3弱电工程'!$B$4:$K$195,10,0) -> 1.01 | L50: =$L$4 -> 0.207 | M50: =F50*G50 -> 0
A51: 48 | B51: 弱电桥架200*100 | C51: 1.名称:弱电桥架200*100 2.材质:钢制 3.接地方式:按规范要求 4.其他:含支、吊架制作安装 | D51: 按设计图示尺寸以长度计算 | E51: m | F51: 5 | G51: =(H51+I51+J51+K51)*(1+L51) -> 95.92029 | H51: =VLOOKUP(B51,'[1]2.3弱电工程'!$B$4:$H$195,7,0) -> 30.95 | I51: =VLOOKUP(B51,'[1]2.3弱电工程'!$B$4:$I$195,8,0) -> 38.9 | J51: =VLOOKUP(B51,'[1]2.3弱电工程'!$B$4:$J$195,9,0) -> 8.61 | K51: =VLOOKUP(B51,'[1]2.3弱电工程'!$B$4:$K$195,10,0) -> 1.01 | L51: =$L$4 -> 0.207 | M51: =F51*G51 -> 479.60145
A52: 49 | B52: 弱电桥架200*150 | C52: 1.名称:弱电桥架200*150 2.材质:钢制 3.接地方式:按规范要求 4.其他:含支、吊架制作安装 | D52: 按设计图示尺寸以长度计算 | E52: m | G52: =(H52+I52+J52+K52)*(1+L52) -> 107.02469 | H52: =VLOOKUP(B52,'[1]2.3弱电工程'!$B$4:$H$195,7,0) -> 30.95 | I52: =VLOOKUP(B52,'[1]2.3弱电工程'!$B$4:$I$195,8,0) -> 48.1 | J52: =VLOOKUP(B52,'[1]2.3弱电工程'!$B$4:$J$195,9,0) -> 8.61 | K52: =VLOOKUP(B52,'[1]2.3弱电工程'!$B$4:$K$195,10,0) -> 1.01 | L52: =$L$4 -> 0.207 | M52: =F52*G52 -> 0
A53: 50 | B53: 接线盒 | C53: 1.名称:接线盒 2.材质:铁质 3.安装形式:明装 | D53: 按设计图示数量计算 | E53: 个 | F53: 12 | G53: =(H53+I53+J53+K53)*(1+L53) -> 8.60591 | H53: =VLOOKUP(B53,'[1]2.3弱电工程'!$B$4:$H$195,7,0) -> 5.1 | I53: =VLOOKUP(B53,'[1]2.3弱电工程'!$B$4:$I$195,8,0) -> 1.61 | J53: =VLOOKUP(B53,'[1]2.3弱电工程'!$B$4:$J$195,9,0) -> 0.42 | K53: =VLOOKUP(B53,'[1]2.3弱电工程'!$B$4:$K$195,10,0) -> 0 | L53: =$L$4 -> 0.207 | M53: =F53*G53 -> 103.27092
A54: 51 | B54: 接线盒 | C54: 1.名称:接线盒 2.材质:铁质 3.安装形式:暗装 | D54: 按设计图示数量计算 | E54: 个 | G54: =(H54+I54+J54+K54)*(1+L54) -> 8.60591 | H54: =VLOOKUP(B54,'[1]2.3弱电工程'!$B$4:$H$195,7,0) -> 5.1 | I54: =VLOOKUP(B54,'[1]2.3弱电工程'!$B$4:$I$195,8,0) -> 1.61 | J54: =VLOOKUP(B54,'[1]2.3弱电工程'!$B$4:$J$195,9,0) -> 0.42 | K54: =VLOOKUP(B54,'[1]2.3弱电工程'!$B$4:$K$195,10,0) -> 0 | L54: =$L$4 -> 0.207 | M54: =F54*G54 -> 0
A55: 52 | B55: 接线盒 | C55: 1.名称:接线盒 2.材质:PC 3.安装形式:明装 | D55: 按设计图示数量计算 | E55: 个 | G55: =(H55+I55+J55+K55)*(1+L55) -> 8.60591 | H55: =VLOOKUP(B55,'[1]2.3弱电工程'!$B$4:$H$195,7,0) -> 5.1 | I55: =VLOOKUP(B55,'[1]2.3弱电工程'!$B$4:$I$195,8,0) -> 1.61 | J55: =VLOOKUP(B55,'[1]2.3弱电工程'!$B$4:$J$195,9,0) -> 0.42 | K55: =VLOOKUP(B55,'[1]2.3弱电工程'!$B$4:$K$195,10,0) -> 0 | L55: =$L$4 -> 0.207 | M55: =F55*G55 -> 0
A56: 53 | B56: 接线盒 | C56: 1.名称:接线盒 2.材质:PC 3.安装形式:暗装 | D56: 按设计图示数量计算 | E56: 个 | G56: =(H56+I56+J56+K56)*(1+L56) -> 8.60591 | H56: =VLOOKUP(B56,'[1]2.3弱电工程'!$B$4:$H$195,7,0) -> 5.1 | I56: =VLOOKUP(B56,'[1]2.3弱电工程'!$B$4:$I$195,8,0) -> 1.61 | J56: =VLOOKUP(B56,'[1]2.3弱电工程'!$B$4:$J$195,9,0) -> 0.42 | K56: =VLOOKUP(B56,'[1]2.3弱电工程'!$B$4:$K$195,10,0) -> 0 | L56: =$L$4 -> 0.207 | M56: =F56*G56 -> 0
A57: 二 | B57: 监控系统
A58: 1 | B58: 8T专用硬盘 | C58: 1.名称:8T专用硬盘 2.规格:参考海康威视ST8000HKVS002(标配)/监控盘 | D58: 按设计图示数量计算 | E58: 块 | F58: 1 | G58: =(H58+I58+J58+K58)*(1+L58) -> 1558.7319 | H58: =VLOOKUP(B58,'[1]2.3弱电工程'!$B$4:$H$195,7,0) -> 218.4 | I58: =VLOOKUP(B58,'[1]2.3弱电工程'!$B$4:$I$195,8,0) -> 1070.8 | J58: =VLOOKUP(B58,'[1]2.3弱电工程'!$B$4:$J$195,9,0) -> 2.21 | K58: =VLOOKUP(B58,'[1]2.3弱电工程'!$B$4:$K$195,10,0) -> 0 | L58: =$L$4 -> 0.207 | M58: =F58*G58 -> 1558.7319
A59: 2 | B59: 硬盘录像机 | C59: 1.名称:硬盘录像机 2.规格:海康威视DS-7608N-I3-V3(标配)(2×4T定制盘)，录像时间大于45天 | D59: 按设计图示数量计算 | E59: 台 | F59: 1 | G59: =(H59+I59+J59+K59)*(1+L59) -> 2682.0626 | H59: =VLOOKUP(B59,'[1]2.3弱电工程'!$B$4:$H$195,7,0) -> 1685.63 | I59: =VLOOKUP(B59,'[1]2.3弱电工程'!$B$4:$I$195,8,0) -> 500.6 | J59: =VLOOKUP(B59,'[1]2.3弱电工程'!$B$4:$J$195,9,0) -> 10.49 | K59: =VLOOKUP(B59,'[1]2.3弱电工程'!$B$4:$K$195,10,0) -> 25.37 | L59: =$L$4 -> 0.207 | M59: =F59*G59 -> 2682.0626
A60: 3 | B60: 高清红外球机 | C60: 1.名称：高清红外球机 2.规格型号：海康威视：DS-2PT2A2GYL-DEY 3.包括为满足设计、验收规范规定施工所需的一切工序 | D60: 按设计图示数量计算 | E60: 台 | F60: 5 | G60: =(H60+I60+J60+K60)*(1+L60) -> 1297.4646 | H60: =VLOOKUP(B60,'[1]2.3弱电工程'!$B$4:$H$195,7,0) -> 389.03 | I60: =VLOOKUP(B60,'[1]2.3弱电工程'!$B$4:$I$195,8,0) -> 676.99 | J60: =VLOOKUP(B60,'[1]2.3弱电工程'!$B$4:$J$195,9,0) -> 0 | K60: =VLOOKUP(B60,'[1]2.3弱电工程'!$B$4:$K$195,10,0) -> 8.93 | L60: =$L$4 -> 0.207 | M60: =F60*G60 -> 6487.3233
A61: 4 | B61: 半球摄像机 | C61: 1.名称：半球机 2.规格型号：海康威视：DS-2CD2725CGL3-IZS(2.7-8mm) 3.包括为满足设计、验收规范规定施工所需的一切工序 | D61: 按设计图示数量计算 | E61: 台 | F61: 2 | G61: =(H61+I61+J61+K61)*(1+L61) -> 611.49034 | H61: =VLOOKUP(B61,'[1]2.3弱电工程'!$B$4:$H$195,7,0) -> 150.9 | I61: =VLOOKUP(B61,'[1]2.3弱电工程'!$B$4:$I$195,8,0) -> 340.56 | J61: =VLOOKUP(B61,'[1]2.3弱电工程'!$B$4:$J$195,9,0) -> 0.18 | K61: =VLOOKUP(B61,'[1]2.3弱电工程'!$B$4:$K$195,10,0) -> 14.98 | L61: =$L$4 -> 0.207 | M61: =F61*G61 -> 1222.9807
A62: 5 | B62: 枪型摄像机 | C62: 1.名称:枪型摄像机 2.类别:参考海康威视：DS-2CD264XY-GLZS(2.7-12mm) 3.安装方式:吸顶 | D62: 按设计图示数量计算 | E62: 台 | G62: =(H62+I62+J62+K62)*(1+L62) -> 752.11791 | H62: =VLOOKUP(B62,'[1]2.3弱电工程'!$B$4:$H$195,7,0) -> 150.15 | I62: =VLOOKUP(B62,'[1]2.3弱电工程'!$B$4:$I$195,8,0) -> 458 | J62: =VLOOKUP(B62,'[1]2.3弱电工程'!$B$4:$J$195,9,0) -> 0 | K62: =VLOOKUP(B62,'[1]2.3弱电工程'!$B$4:$K$195,10,0) -> 14.98 | L62: =$L$4 -> 0.207 | M62: =F62*G62 -> 0
A63: 6 | B63: 4K摄像头 | C63: 1.名称:4K摄像头 2.类别:K高清可旋转摄像头，视频存储时间完工后60天，摄像头账号权限对招标方开放 | D63: 按设计图示数量计算 | E63: 台 | F63: 2 | G63: =(H63+I63+J63+K63)*(1+L63) -> 1190.3796 | H63: =VLOOKUP(B63,'[1]2.3弱电工程'!$B$4:$H$195,7,0) -> 259.35 | I63: =VLOOKUP(B63,'[1]2.3弱电工程'!$B$4:$I$195,8,0) -> 711.9 | J63: =VLOOKUP(B63,'[1]2.3弱电工程'!$B$4:$J$195,9,0) -> 0 | K63: =VLOOKUP(B63,'[1]2.3弱电工程'!$B$4:$K$195,10,0) -> 14.98 | L63: =$L$4 -> 0.207 | M63: =F63*G63 -> 2380.7592
A64: 7 | B64: 枪球一体摄像机 | C64: 1.名称:枪球一体摄像机 2.类别:参考海康威视：iDS-2SE7C23GLW-XYZ 3.安装方式:吸顶 | D64: 按设计图示数量计算 | E64: 台 | G64: =(H64+I64+J64+K64)*(1+L64) -> 1805.153 | H64: =VLOOKUP(B64,'[1]2.3弱电工程'!$B$4:$H$195,7,0) -> 259.35 | I64: =VLOOKUP(B64,'[1]2.3弱电工程'!$B$4:$I$195,8,0) -> 1221.24 | J64: =VLOOKUP(B64,'[1]2.3弱电工程'!$B$4:$J$195,9,0) -> 0 | K64: =VLOOKUP(B64,'[1]2.3弱电工程'!$B$4:$K$195,10,0) -> 14.98 | L64: =$L$4 -> 0.207 | M64: =F64*G64 -> 0
A65: 8 | B65: 客流统计摄像机 | C65: 1.名称：客流统计摄像机 2.规格型号：海康威视：DS-2XD8147FGL/MC-IZS(2.8-12mm)，根据安装需要配备支架 3.包括为满足设计、验收规范规定施工所需的一切工序 | D65: 按设计图示数量计算 | E65: 台 | F65: 1 | G65: =(H65+I65+J65+K65)*(1+L65) -> 2407.4943 | H65: =VLOOKUP(B65,'[1]2.3弱电工程'!$B$4:$H$195,7,0) -> 305.03 | I65: =VLOOKUP(B65,'[1]2.3弱电工程'!$B$4:$I$195,8,0) -> 1680.65 | J65: =VLOOKUP(B65,'[1]2.3弱电工程'!$B$4:$J$195,9,0) -> 0 | K65: =VLOOKUP(B65,'[1]2.3弱电工程'!$B$4:$K$195,10,0) -> 8.93 | L65: =$L$4 -> 0.207 | M65: =F65*G65 -> 2407.4943
A66: 三 | B66: 背景音乐系统
A67: 1 | B67: 广播系统控制器 | C67: 1.名称:广播系统控制器 2.规格:参考ITC:T-6232A，包含SD存储卡及设备间互联的音频跳线 | D67: 按设计图示数量计算 | E67: 台 | F67: 1 | G67: =(H67+I67+J67+K67)*(1+L67) -> 11740.525 | H67: =VLOOKUP(B67,'[1]2.3弱电工程'!$B$4:$H$195,7,0) -> 523.25 | I67: =VLOOKUP(B67,'[1]2.3弱电工程'!$B$4:$I$195,8,0) -> 9201.61 | J67: =VLOOKUP(B67,'[1]2.3弱电工程'!$B$4:$J$195,9,0) -> 0 | K67: =VLOOKUP(B67,'[1]2.3弱电工程'!$B$4:$K$195,10,0) -> 2.17 | L67: =$L$4 -> 0.207 | M67: =F67*G67 -> 11740.525
A68: 2 | B68: 数字合并式功放 | C68: 1.名称:数字合并式功放 2.规格:参考ITC:T-120D，包含设备间互联的音频跳线 | D68: 按设计图示数量计算 | E68: 台 | F68: 1 | G68: =(H68+I68+J68+K68)*(1+L68) -> 5885.8872 | H68: =VLOOKUP(B68,'[1]2.3弱电工程'!$B$4:$H$195,7,0) -> 116.63 | I68: =VLOOKUP(B68,'[1]2.3弱电工程'!$B$4:$I$195,8,0) -> 4759.29 | J68: =VLOOKUP(B68,'[1]2.3弱电工程'!$B$4:$J$195,9,0) -> 0 | K68: =VLOOKUP(B68,'[1]2.3弱电工程'!$B$4:$K$195,10,0) -> 0.54 | L68: =$L$4 -> 0.207 | M68: =F68*G68 -> 5885.8872
A69: 3 | B69: 信号发生器 | C69: 1.名称:信号发生器 2.规格:参考ITC:T-6203，包含设备间互联的音频跳线 | D69: 按设计图示数量计算 | E69: 台 | F69: 1 | G69: =(H69+I69+J69+K69)*(1+L69) -> 5019.2612 | H69: =VLOOKUP(B69,'[1]2.3弱电工程'!$B$4:$H$195,7,0) -> 625.63 | I69: =VLOOKUP(B69,'[1]2.3弱电工程'!$B$4:$I$195,8,0) -> 3526.55 | J69: =VLOOKUP(B69,'[1]2.3弱电工程'!$B$4:$J$195,9,0) -> 0 | K69: =VLOOKUP(B69,'[1]2.3弱电工程'!$B$4:$K$195,10,0) -> 6.28 | L69: =$L$4 -> 0.207 | M69: =F69*G69 -> 5019.2612
A70: 4 | B70: 寻呼话筒 | C70: 1.名称:寻呼话筒 2.规格:参考ITC:T-621A，包含设备间互联的音频跳线 | D70: 按设计图示数量计算 | E70: 台 | G70: =(H70+I70+J70+K70)*(1+L70) -> 1261.484 | H70: =VLOOKUP(B70,'[1]2.3弱电工程'!$B$4:$H$195,7,0) -> 22.75 | I70: =VLOOKUP(B70,'[1]2.3弱电工程'!$B$4:$I$195,8,0) -> 1022.12 | J70: =VLOOKUP(B70,'[1]2.3弱电工程'!$B$4:$J$195,9,0) -> 0 | K70: =VLOOKUP(B70,'[1]2.3弱电工程'!$B$4:$K$195,10,0) -> 0.27 | L70: =$L$4 -> 0.207 | M70: =F70*G70 -> 0
A71: 5 | B71: 壁挂喇叭 | C71: 1.名称:壁挂喇叭 2.规格:参考ITC:T-601 3.安装方式:壁挂式 | D71: 按设计图示数量计算 | E71: 台 | F71: 5 | G71: =(H71+I71+J71+K71)*(1+L71) -> 537.51331 | H71: =VLOOKUP(B71,'[1]2.3弱电工程'!$B$4:$H$195,7,0) -> 50.05 | I71: =VLOOKUP(B71,'[1]2.3弱电工程'!$B$4:$I$195,8,0) -> 380.63 | J71: =VLOOKUP(B71,'[1]2.3弱电工程'!$B$4:$J$195,9,0) -> 1.72 | K71: =VLOOKUP(B71,'[1]2.3弱电工程'!$B$4:$K$195,10,0) -> 12.93 | L71: =$L$4 -> 0.207 | M71: =F71*G71 -> 2687.5666
A72: 6 | B72: 天花喇叭 | C72: 1.名称:天花喇叭 2.规格:参考ITC:T-105A 3.安装方式:吸顶式 | D72: 按设计图示数量计算 | E72: 台 | F72: 2 | G72: =(H72+I72+J72+K72)*(1+L72) -> 483.34315 | H72: =VLOOKUP(B72,'[1]2.3弱电工程'!$B$4:$H$195,7,0) -> 102.38 | I72: =VLOOKUP(B72,'[1]2.3弱电工程'!$B$4:$I$195,8,0) -> 283.19 | J72: =VLOOKUP(B72,'[1]2.3弱电工程'!$B$4:$J$195,9,0) -> 0.86 | K72: =VLOOKUP(B72,'[1]2.3弱电工程'!$B$4:$K$195,10,0) -> 14.02 | L72: =$L$4 -> 0.207 | M72: =F72*G72 -> 966.6863
A73: 四 | B73: 门禁系统
A74: 1 | B74: 人脸门禁+人脸考勤 | C74: 1.名称：人脸门禁 2.规格型号：熵基FS600，摄像头≥200万像素，屏幕≥4.3英寸；识别准确率≥99.99%；支持数据网络上传功能及本地权限管理；能与飞书进行系统对接；包含出门按钮、开关电源、电磁锁（单双门依据现场门确定）及附属管线 3.包括为满足设计、验收规范规定施工所需的一切工序 | D74: 按设计图示数量计算 | E74: 台 | F74: 1 | G74: =(H74+I74+J74+K74)*(1+L74) -> 2196.6555 | H74: =VLOOKUP(B74,'[1]2.3弱电工程'!$B$4:$H$195,7,0) -> 193.38 | I74: =VLOOKUP(B74,'[1]2.3弱电工程'!$B$4:$I$195,8,0) -> 1626.55 | J74: =VLOOKUP(B74,'[1]2.3弱电工程'!$B$4:$J$195,9,0) -> 0 | K74: =VLOOKUP(B74,'[1]2.3弱电工程'!$B$4:$K$195,10,0) -> 0 | L74: =$L$4 -> 0.207 | M74: =F74*G74 -> 2196.6555
A75: 2 | B75: 电磁门锁 | C75: 1.名称:电磁门锁 | D75: 按设计图示数量计算 | E75: 套 | F75: 2 | G75: =(H75+I75+J75+K75)*(1+L75) -> 173.36141 | H75: =VLOOKUP(B75,'[1]2.3弱电工程'!$B$4:$H$195,7,0) -> 65.98 | I75: =VLOOKUP(B75,'[1]2.3弱电工程'!$B$4:$I$195,8,0) -> 75.22 | J75: =VLOOKUP(B75,'[1]2.3弱电工程'!$B$4:$J$195,9,0) -> 1.62 | K75: =VLOOKUP(B75,'[1]2.3弱电工程'!$B$4:$K$195,10,0) -> 0.81 | L75: =$L$4 -> 0.207 | M75: =F75*G75 -> 346.72282
A76: 3 | B76: 出门按钮 | C76: 1.名称:出门按钮 | D76: 按设计图示数量计算 | E76: 个 | F76: 1 | G76: =(H76+I76+J76+K76)*(1+L76) -> 45.21422 | H76: =VLOOKUP(B76,'[1]2.3弱电工程'!$B$4:$H$195,7,0) -> 10.2 | I76: =VLOOKUP(B76,'[1]2.3弱电工程'!$B$4:$I$195,8,0) -> 27 | J76: =VLOOKUP(B76,'[1]2.3弱电工程'!$B$4:$J$195,9,0) -> 0.04 | K76: =VLOOKUP(B76,'[1]2.3弱电工程'!$B$4:$K$195,10,0) -> 0.22 | L76: =$L$4 -> 0.207 | M76: =F76*G76 -> 45.21422
A77: 五 | B77: 会议室投影系统
A78: 1 | B78: 多功能插座 | C78: 1.名称:多功能插座 2.规格:包含五孔插座、3.0USB接口、HDIM接口、音频接口等 3.安装方式:暗装 | D78: 按设计图示数量计算 | E78: 个 | G78: =(H78+I78+J78+K78)*(1+L78) -> 142.76396 | H78: =VLOOKUP(B78,'[1]2.3弱电工程'!$B$4:$H$195,7,0) -> 12.97 | I78: =VLOOKUP(B78,'[1]2.3弱电工程'!$B$4:$I$195,8,0) -> 102.9 | J78: =VLOOKUP(B78,'[1]2.3弱电工程'!$B$4:$J$195,9,0) -> 2.41 | K78: =VLOOKUP(B78,'[1]2.3弱电工程'!$B$4:$K$195,10,0) -> 0 | L78: =$L$4 -> 0.207 | M78: =F78*G78 -> 0
A79: 2 | B79: 投影幕布 | C79: 1.名称:投影幕布 2.规格:120寸4:3，材质；白玻纤；带遥控 | D79: 按设计图示数量计算 | E79: 套 | G79: =(H79+I79+J79+K79)*(1+L79) -> 1435.8472 | H79: =VLOOKUP(B79,'[1]2.3弱电工程'!$B$4:$H$195,7,0) -> 1000.31 | I79: =VLOOKUP(B79,'[1]2.3弱电工程'!$B$4:$I$195,8,0) -> 179.19 | J79: =VLOOKUP(B79,'[1]2.3弱电工程'!$B$4:$J$195,9,0) -> 7.69 | K79: =VLOOKUP(B79,'[1]2.3弱电工程'!$B$4:$K$195,10,0) -> 2.41 | L79: =$L$4 -> 0.207 | M79: =F79*G79 -> 0
A80: 3 | B80: 六类非屏蔽网线 | C80: 1.名称:六类非屏蔽网线 2.敷设方式:综合考虑 | D80: 按设计图示尺寸以长度计算 | E80: m | G80: =(H80+I80+J80+K80)*(1+L80) -> 5.05733 | H80: =VLOOKUP(B80,'[1]2.3弱电工程'!$B$4:$H$195,7,0) -> 1.57 | I80: =VLOOKUP(B80,'[1]2.3弱电工程'!$B$4:$I$195,8,0) -> 2.61 | J80: =VLOOKUP(B80,'[1]2.3弱电工程'!$B$4:$J$195,9,0) -> 0.01 | K80: =VLOOKUP(B80,'[1]2.3弱电工程'!$B$4:$K$195,10,0) -> 0 | L80: =$L$4 -> 0.207 | M80: =F80*G80 -> 0
A81: 4 | B81: HDIM高清视频线 | C81: 1.名称:HDIM高清视频线 2.敷设方式:综合考虑 | D81: 按设计图示尺寸以长度计算 | E81: m | G81: =(H81+I81+J81+K81)*(1+L81) -> 46.32466 | H81: =VLOOKUP(B81,'[1]2.3弱电工程'!$B$4:$H$195,7,0) -> 1.57 | I81: =VLOOKUP(B81,'[1]2.3弱电工程'!$B$4:$I$195,8,0) -> 36.8 | J81: =VLOOKUP(B81,'[1]2.3弱电工程'!$B$4:$J$195,9,0) -> 0.01 | K81: =VLOOKUP(B81,'[1]2.3弱电工程'!$B$4:$K$195,10,0) -> 0 | L81: =$L$4 -> 0.207 | M81: =F81*G81 -> 0
A82: 5 | B82: RVJF-2*2 | C82: 1.名称:RVJF-2*2 2.敷设方式:综合考虑 | D82: 按设计图示尺寸以长度计算 | E82: m | G82: =(H82+I82+J82+K82)*(1+L82) -> 6.38503 | H82: =VLOOKUP(B82,'[1]2.3弱电工程'!$B$4:$H$195,7,0) -> 2.07 | I82: =VLOOKUP(B82,'[1]2.3弱电工程'!$B$4:$I$195,8,0) -> 3.21 | J82: =VLOOKUP(B82,'[1]2.3弱电工程'!$B$4:$J$195,9,0) -> 0.01 | K82: =VLOOKUP(B82,'[1]2.3弱电工程'!$B$4:$K$195,10,0) -> 0 | L82: =$L$4 -> 0.207 | M82: =F82*G82 -> 0
A83: 合计 | M83: =SUM(M3:M82) -> 93628.43

Sheet 2.4消防工程 
A1: 长城智选商超店装修项目装饰工程
A2: 序号 | B2: 分部分项名称 | C2: 项目特征 | D2: 计量规则 | E2: 单位 | F2: 工程量 | G2: 综合单价 | H2: 人工 | I2: 主材 | J2: 辅材 | K2: 机械 | L2: 其他综合费率 | M2: 合计 | N2: 备注
A3: 1 | B3: 消防工程 | C3: 消防工程审图、消防工程施工、检测、验收、系统接入、放水、店面内灭火器、开业检等一切消防相关费用 | D3: 按消防工程施工部分面积计算 一类城市：北京 | E3: m2 | F3: 300 | G3: =(H3+I3+J3+K3)*(1+L3) -> 482.8 | H3: 400 | I3: 0 | J3: 0 | K3: 0 | L3: ='2.1装饰工程'!$L$4 -> 0.207 | M3: =F3*G3 -> 144840
A4: 2 | B4: 消防工程 | C4: 消防工程审图、消防工程施工、检测、验收、系统接入、放水、店面内灭火器、开业检等一切消防相关费用 | D4: 按消防工程施工部分面积计算 二类城市： 直辖市、省会城市 | E4: m2 | F4: 300 | G4: =(H4+I4+J4+K4)*(1+L4) -> 458.66 | H4: 380 | I4: 0 | J4: 0 | K4: 0 | L4: =$L$3 -> 0.207 | M4: =F4*G4 -> 137598
A5: 3 | B5: 消防工程 | C5: 消防工程审图、消防工程施工、检测、验收、系统接入、放水、店面内灭火器、开业检等一切消防相关费用 | D5: 按消防工程施工部分面积计算 三类城市： 除一、二类以外城市 | E5: m2 | F5: 300 | G5: =(H5+I5+J5+K5)*(1+L5) -> 362.1 | H5: 300 | I5: 0 | J5: 0 | K5: 0 | L5: =$L$3 -> 0.207 | M5: =F5*G5 -> 108630
A6: 4 | B6: 灭火毯 | C6: 1.形式:灭火毯（停车位） 2.其他:按设计及规范要求 | D6: 依据设计要求按m2计算 | E6: m2 | F6: 3 | G6: =(H6+I6+J6+K6)*(1+L6) -> 72.42 | H6: =VLOOKUP(B6,'[1]2.4消防工程 '!$B$3:$H$10,7,0) -> 0 | I6: =VLOOKUP(B6,'[1]2.4消防工程 '!$B$3:$I$10,8,0) -> 60 | J6: =VLOOKUP(B6,'[1]2.4消防工程 '!$B$3:$J$10,9,0) -> 0 | K6: =VLOOKUP(B6,'[1]2.4消防工程 '!$B$3:$K$10,10,0) -> 0 | L6: =$L$3 -> 0.207 | M6: =F6*G6 -> 217.26
A7: 5 | B7: 灭火器箱 | C7: 1.形式:灭火器箱（停车位） 2.其他:按设计及规范要求 | D7: 按设计图示数量计算 | E7: 个 | F7: 6 | G7: =(H7+I7+J7+K7)*(1+L7) -> 96.56 | H7: =VLOOKUP(B7,'[1]2.4消防工程 '!$B$3:$H$10,7,0) -> 0 | I7: =VLOOKUP(B7,'[1]2.4消防工程 '!$B$3:$I$10,8,0) -> 80 | J7: =VLOOKUP(B7,'[1]2.4消防工程 '!$B$3:$J$10,9,0) -> 0 | K7: =VLOOKUP(B7,'[1]2.4消防工程 '!$B$3:$K$10,10,0) -> 0 | L7: =$L$3 -> 0.207 | M7: =F7*G7 -> 579.36
A8: 6 | B8: 干粉灭火器 | C8: 1.干粉灭火器3kg（停车位） 2.不限放置形式（含同规格灭火弹） | E8: 个 | F8: 12 | G8: =(H8+I8+J8+K8)*(1+L8) -> 66.385 | H8: =VLOOKUP(B8,'[1]2.4消防工程 '!$B$3:$H$10,7,0) -> 0 | I8: 55 | J8: =VLOOKUP(B8,'[1]2.4消防工程 '!$B$3:$J$10,9,0) -> 0 | K8: =VLOOKUP(B8,'[1]2.4消防工程 '!$B$3:$K$10,10,0) -> 0 | L8: =$L$3 -> 0.207 | M8: =F8*G8 -> 796.62
A9: 7 | B9: 干粉灭火器 | C9: 1.干粉灭火器4kg（停车位） 2.不限放置形式（含同规格灭火弹） | E9: 个 | F9: 12 | G9: =(H9+I9+J9+K9)*(1+L9) -> 86.904 | H9: =VLOOKUP(B9,'[1]2.4消防工程 '!$B$3:$H$10,7,0) -> 0 | I9: 72 | J9: =VLOOKUP(B9,'[1]2.4消防工程 '!$B$3:$J$10,9,0) -> 0 | K9: =VLOOKUP(B9,'[1]2.4消防工程 '!$B$3:$K$10,10,0) -> 0 | L9: =$L$3 -> 0.207 | M9: =F9*G9 -> 1042.848
A10: 8 | B10: 干粉灭火器 | C10: 1.干粉灭火器5kg（停车位） 2.不限放置形式（含同规格灭火弹） | D10: 不限放置形式（含同规格灭火弹） | E10: 个 | F10: 12 | G10: =(H10+I10+J10+K10)*(1+L10) -> 102.595 | H10: =VLOOKUP(B10,'[1]2.4消防工程 '!$B$3:$H$10,7,0) -> 0 | I10: 85 | J10: =VLOOKUP(B10,'[1]2.4消防工程 '!$B$3:$J$10,9,0) -> 0 | K10: =VLOOKUP(B10,'[1]2.4消防工程 '!$B$3:$K$10,10,0) -> 0 | L10: =$L$3 -> 0.207 | M10: =F10*G10 -> 1231.14
A11: 9 | B11: 干粉灭火器 | C11: 1.干粉灭火器8kg（停车位） 2.不限放置形式（含同规格灭火弹） | D11: 不限放置形式（含同规格灭火弹） | F11: 12 | G11: =(H11+I11+J11+K11)*(1+L11) -> 175.015 | H11: =VLOOKUP(B11,'[1]2.4消防工程 '!$B$3:$H$10,7,0) -> 0 | I11: 145 | J11: =VLOOKUP(B11,'[1]2.4消防工程 '!$B$3:$J$10,9,0) -> 0 | K11: =VLOOKUP(B11,'[1]2.4消防工程 '!$B$3:$K$10,10,0) -> 0 | L11: =$L$3 -> 0.207 | M11: =F11*G11 -> 2100.18
A12: 10 | B12: 二氧化碳灭火器 | C12: 1.二氧化碳灭火器5kg（停车位） 2.放置式灭火器 | E12: 个 | F12: 5 | G12: =(H12+I12+J12+K12)*(1+L12) -> 193.12 | H12: =VLOOKUP(B12,'[1]2.4消防工程 '!$B$3:$H$10,7,0) -> 0 | I12: =VLOOKUP(B12,'[1]2.4消防工程 '!$B$3:$I$10,8,0) -> 160 | J12: =VLOOKUP(B12,'[1]2.4消防工程 '!$B$3:$J$10,9,0) -> 0 | K12: =VLOOKUP(B12,'[1]2.4消防工程 '!$B$3:$K$10,10,0) -> 0 | L12: =$L$3 -> 0.207 | M12: =F12*G12 -> 965.6
A13: 11 | B13: 水基灭火器 | C13: 1.水基灭火器6L（停车位） 2.放置式灭火器 | E13: 个 | F13: 5 | G13: =(H13+I13+J13+K13)*(1+L13) -> 126.735 | H13: =VLOOKUP(B13,'[1]2.4消防工程 '!$B$3:$H$10,7,0) -> 0 | I13: =VLOOKUP(B13,'[1]2.4消防工程 '!$B$3:$I$10,8,0) -> 105 | J13: =VLOOKUP(B13,'[1]2.4消防工程 '!$B$3:$J$10,9,0) -> 0 | K13: =VLOOKUP(B13,'[1]2.4消防工程 '!$B$3:$K$10,10,0) -> 0 | L13: =$L$3 -> 0.207 | M13: =F13*G13 -> 633.675
A14: 12 | B14: 水基灭火器 | C14: 1.水基灭火器3L（停车位） 2.放置式灭火器 | E14: 个 | F14: 5 | G14: =(H14+I14+J14+K14)*(1+L14) -> 78.455 | H14: =VLOOKUP(B14,'[1]2.4消防工程 '!$B$3:$H$10,7,0) -> 0 | I14: 65 | J14: =VLOOKUP(B14,'[1]2.4消防工程 '!$B$3:$J$10,9,0) -> 0 | K14: =VLOOKUP(B14,'[1]2.4消防工程 '!$B$3:$K$10,10,0) -> 0 | L14: =$L$3 -> 0.207 | M14: =F14*G14 -> 392.275
A15: 合计 | M15: =SUM(M3:M14) -> 399026.96

Sheet 2.5暖通工程
A1: 长城智选商超店装修项目装饰工程
A2: 序号 | B2: 分部分项名称 | C2: 项目特征 | D2: 计量规则 | E2: 单位 | F2: 工程量 | G2: 综合单价 | H2: 人工 | I2: 主材 | J2: 辅材 | K2: 机械 | L2: 其他综合费率 | M2: 合计 | N2: 备注
A3: 1 | B3: 多联式空调机组室外机5匹 | C3: 1.名称:多联式空调机组室外机 2.其他:根据现场情况按设计及规范要求 | D3: 按设计图示数量计算 | E3: 台 | G3: =(H3+I3+J3+K3)*(1+L3) -> 9482.0713 | H3: =VLOOKUP(B3,'[1]2.5暖通工程'!$B$3:$H$94,7,0) -> 841.3 | I3: =VLOOKUP(B3,'[1]2.5暖通工程'!$B$3:$I$94,8,0) -> 6976.11 | J3: =VLOOKUP(B3,'[1]2.5暖通工程'!$B$3:$J$94,9,0) -> 5.39 | K3: =VLOOKUP(B3,'[1]2.5暖通工程'!$B$3:$K$94,10,0) -> 33.1 | L3: ='2.1装饰工程'!$L$4 -> 0.207 | M3: =F3*G3 -> 0
A4: 2 | B4: 多联式空调机组室外机8匹 | C4: 1.名称:多联式空调机组室外机 2.其他:根据现场情况按设计及规范要求 | D4: 按设计图示数量计算，如5匹-8匹之间按5匹计费 | E4: 台 | G4: =(H4+I4+J4+K4)*(1+L4) -> 19176.526 | H4: =VLOOKUP(B4,'[1]2.5暖通工程'!$B$3:$H$94,7,0) -> 841.3 | I4: =VLOOKUP(B4,'[1]2.5暖通工程'!$B$3:$I$94,8,0) -> 15007.97 | J4: =VLOOKUP(B4,'[1]2.5暖通工程'!$B$3:$J$94,9,0) -> 5.39 | K4: =VLOOKUP(B4,'[1]2.5暖通工程'!$B$3:$K$94,10,0) -> 33.1 | L4: =$L$3 -> 0.207 | M4: =F4*G4 -> 0
A5: 3 | B5: 多联式空调机组室外机10匹 | C5: 1.名称:多联式空调机组室外机 2.其他:根据现场情况按设计及规范要求 | D5: 按设计图示数量计算，如8匹-10匹之间按8匹计费 | E5: 台 | G5: =(H5+I5+J5+K5)*(1+L5) -> 19777.89 | H5: =VLOOKUP(B5,'[1]2.5暖通工程'!$B$3:$H$94,7,0) -> 841.3 | I5: =VLOOKUP(B5,'[1]2.5暖通工程'!$B$3:$I$94,8,0) -> 15506.2 | J5: =VLOOKUP(B5,'[1]2.5暖通工程'!$B$3:$J$94,9,0) -> 5.39 | K5: =VLOOKUP(B5,'[1]2.5暖通工程'!$B$3:$K$94,10,0) -> 33.1 | L5: =$L$3 -> 0.207 | M5: =F5*G5 -> 0
A6: 4 | B6: 多联式空调机组室外机12匹 | C6: 1.名称:多联式空调机组室外机 2.其他:根据现场情况按设计及规范要求 | D6: 按设计图示数量计算，如10匹-12匹之间按10匹计费 | E6: 台 | G6: =(H6+I6+J6+K6)*(1+L6) -> 21938.734 | H6: =VLOOKUP(B6,'[1]2.5暖通工程'!$B$3:$H$94,7,0) -> 841.3 | I6: =VLOOKUP(B6,'[1]2.5暖通工程'!$B$3:$I$94,8,0) -> 17296.46 | J6: =VLOOKUP(B6,'[1]2.5暖通工程'!$B$3:$J$94,9,0) -> 5.39 | K6: =VLOOKUP(B6,'[1]2.5暖通工程'!$B$3:$K$94,10,0) -> 33.1 | L6: =$L$3 -> 0.207 | M6: =F6*G6 -> 0
A7: 5 | B7: 多联式空调机组室外机14匹 | C7: 1.名称:多联式空调机组室外机 2.其他:根据现场情况按设计及规范要求 | D7: 按设计图示数量计算，如14匹-16匹之间按14匹计费 | E7: 台 | G7: =(H7+I7+J7+K7)*(1+L7) -> 23382.354 | H7: =VLOOKUP(B7,'[1]2.5暖通工程'!$B$3:$H$94,7,0) -> 1260.35 | I7: =VLOOKUP(B7,'[1]2.5暖通工程'!$B$3:$I$94,8,0) -> 18073.45 | J7: =VLOOKUP(B7,'[1]2.5暖通工程'!$B$3:$J$94,9,0) -> 5.39 | K7: =VLOOKUP(B7,'[1]2.5暖通工程'!$B$3:$K$94,10,0) -> 33.1 | L7: =$L$3 -> 0.207 | M7: =F7*G7 -> 0
A8: 6 | B8: 多联式空调机组室外机16匹 | C8: 1.名称:多联式空调机组室外机 2.其他:根据现场情况按设计及规范要求 | D8: 按设计图示数量计算，如14匹-16匹之间按14匹计费 | E8: 台 | G8: =(H8+I8+J8+K8)*(1+L8) -> 26372.081 | H8: =VLOOKUP(B8,'[1]2.5暖通工程'!$B$3:$H$94,7,0) -> 1260.35 | I8: =VLOOKUP(B8,'[1]2.5暖通工程'!$B$3:$I$94,8,0) -> 20550.44 | J8: =VLOOKUP(B8,'[1]2.5暖通工程'!$B$3:$J$94,9,0) -> 5.39 | K8: =VLOOKUP(B8,'[1]2.5暖通工程'!$B$3:$K$94,10,0) -> 33.1 | L8: =$L$3 -> 0.207 | M8: =F8*G8 -> 0
A9: 7 | B9: 多联式空调机组室外机20匹 | C9: 1.名称:多联式空调机组室外机 2.其他:根据现场情况按设计及规范要求 | D9: 按设计图示数量计算，如16匹-20匹之间按16匹计费 | E9: 台 | G9: =(H9+I9+J9+K9)*(1+L9) -> 33364.135 | H9: =VLOOKUP(B9,'[1]2.5暖通工程'!$B$3:$H$94,7,0) -> 1260.35 | I9: =VLOOKUP(B9,'[1]2.5暖通工程'!$B$3:$I$94,8,0) -> 26343.36 | J9: =VLOOKUP(B9,'[1]2.5暖通工程'!$B$3:$J$94,9,0) -> 5.39 | K9: =VLOOKUP(B9,'[1]2.5暖通工程'!$B$3:$K$94,10,0) -> 33.1 | L9: =$L$3 -> 0.207 | M9: =F9*G9 -> 0
A10: 8 | B10: 多联式空调机组室外机22匹 | C10: 1.名称:多联式空调机组室外机 2.其他:根据现场情况按设计及规范要求 | D10: 按设计图示数量计算，如20匹-22匹之间按20匹计费 | E10: 台 | G10: =(H10+I10+J10+K10)*(1+L10) -> 34688.721 | H10: =VLOOKUP(B10,'[1]2.5暖通工程'!$B$3:$H$94,7,0) -> 1557.47 | I10: =VLOOKUP(B10,'[1]2.5暖通工程'!$B$3:$I$94,8,0) -> 27143.36 | J10: =VLOOKUP(B10,'[1]2.5暖通工程'!$B$3:$J$94,9,0) -> 5.69 | K10: =VLOOKUP(B10,'[1]2.5暖通工程'!$B$3:$K$94,10,0) -> 33.1 | L10: =$L$3 -> 0.207 | M10: =F10*G10 -> 0
A11: 9 | B11: 多联式空调机组室外机24匹 | C11: 1.名称:多联式空调机组室外机 2.其他:根据现场情况按设计及规范要求 | D11: 按设计图示数量计算，如22匹-24匹之间按22匹计费 | E11: 台 | G11: =(H11+I11+J11+K11)*(1+L11) -> 36951.05 | H11: =VLOOKUP(B11,'[1]2.5暖通工程'!$B$3:$H$94,7,0) -> 1557.47 | I11: =VLOOKUP(B11,'[1]2.5暖通工程'!$B$3:$I$94,8,0) -> 29017.7 | J11: =VLOOKUP(B11,'[1]2.5暖通工程'!$B$3:$J$94,9,0) -> 5.69 | K11: =VLOOKUP(B11,'[1]2.5暖通工程'!$B$3:$K$94,10,0) -> 33.1 | L11: =$L$3 -> 0.207 | M11: =F11*G11 -> 0
A12: 10 | B12: 多联式空调机组室外机26匹 | C12: 1.名称:多联式空调机组室外机 2.其他:根据现场情况按设计及规范要求 | D12: 按设计图示数量计算，如24匹-26匹之间按24匹计费 | E12: 台 | G12: =(H12+I12+J12+K12)*(1+L12) -> 39358.641 | H12: =VLOOKUP(B12,'[1]2.5暖通工程'!$B$3:$H$94,7,0) -> 1557.47 | I12: =VLOOKUP(B12,'[1]2.5暖通工程'!$B$3:$I$94,8,0) -> 31012.39 | J12: =VLOOKUP(B12,'[1]2.5暖通工程'!$B$3:$J$94,9,0) -> 5.69 | K12: =VLOOKUP(B12,'[1]2.5暖通工程'!$B$3:$K$94,10,0) -> 33.1 | L12: =$L$3 -> 0.207 | M12: =F12*G12 -> 0
A13: 11 | B13: 多联式空调机组室外机28匹 | C13: 1.名称:多联式空调机组室外机 2.其他:根据现场情况按设计及规范要求 | D13: 按设计图示数量计算，如26匹-28匹之间按28匹计费 | E13: 台 | G13: =(H13+I13+J13+K13)*(1+L13) -> 43275.512 | H13: =VLOOKUP(B13,'[1]2.5暖通工程'!$B$3:$H$94,7,0) -> 1557.47 | I13: =VLOOKUP(B13,'[1]2.5暖通工程'!$B$3:$I$94,8,0) -> 34257.52 | J13: =VLOOKUP(B13,'[1]2.5暖通工程'!$B$3:$J$94,9,0) -> 5.69 | K13: =VLOOKUP(B13,'[1]2.5暖通工程'!$B$3:$K$94,10,0) -> 33.1 | L13: =$L$3 -> 0.207 | M13: =F13*G13 -> 0
A14: 12 | B14: 四面出风多联式空调室内机制冷量2.8kw | C14: 1.名称:四面出风多联式空调室内机 2.安装形式:吊顶式 3.减振器、支架形式、材质:按设计及规范要求 4.附件：含紫铜管、分歧器、冷凝水管等至系统验收所需附件。 5.其他:按设计及规范要求 | D14: 按设计图示数量计算，如制冷量为2.8-3.6kw之间，按2.8kw计费 | E14: 台 | G14: =(H14+I14+J14+K14)*(1+L14) -> 3597.9342 | H14: =VLOOKUP(B14,'[1]2.5暖通工程'!$B$3:$H$94,7,0) -> 596.5 | I14: =VLOOKUP(B14,'[1]2.5暖通工程'!$B$3:$I$94,8,0) -> 2311.27 | J14: =VLOOKUP(B14,'[1]2.5暖通工程'!$B$3:$J$94,9,0) -> 40.39 | K14: =VLOOKUP(B14,'[1]2.5暖通工程'!$B$3:$K$94,10,0) -> 32.73 | L14: =$L$3 -> 0.207 | M14: =F14*G14 -> 0
A15: 13 | B15: 四面出风多联式空调室内机制冷量3.6kw | C15: 1.名称:四面出风多联式空调室内机 2.安装形式:吊顶式 3.减振器、支架形式、材质:按设计及规范要求 4.附件：含紫铜管、分歧器、冷凝水管等至系统验收所需附件。 5.其他:按设计及规范要求 | D15: 按设计图示数量计算，如制冷量为3.6-5.6kw之间，按3.6kw计费 | E15: 台 | G15: =(H15+I15+J15+K15)*(1+L15) -> 3650.2697 | H15: =VLOOKUP(B15,'[1]2.5暖通工程'!$B$3:$H$94,7,0) -> 596.5 | I15: =VLOOKUP(B15,'[1]2.5暖通工程'!$B$3:$I$94,8,0) -> 2354.63 | J15: =VLOOKUP(B15,'[1]2.5暖通工程'!$B$3:$J$94,9,0) -> 40.39 | K15: =VLOOKUP(B15,'[1]2.5暖通工程'!$B$3:$K$94,10,0) -> 32.73 | L15: =$L$3 -> 0.207 | M15: =F15*G15 -> 0
... A33: 31 | B33: 风机盘管制冷量14kw | C33: 1.名称:风机盘管 2.安装形式:吊顶式 3.减振器、支架形式、材质:按设计及规范要求 4.附件：含紫铜管、分歧器、冷凝水管等至系统验收所需附件。 5.其他:按设计及规范要求 | D33: 按设计图示数量计算，如制冷量≥14kw，按14kw计费 | E33: 台 | G33: =(H33+I33+J33+K33)*(1+L33) -> 5466.4789 | H33: =VLOOKUP(B33,'[1]2.5暖通工程'!$B$3:$H$94,7,0) -> 616.98 | I33: =VLOOKUP(B33,'[1]2.5暖通工程'!$B$3:$I$94,8,0) -> 3838 | J33: =VLOOKUP(B33,'[1]2.5暖通工程'!$B$3:$J$94,9,0) -> 41.27 | K33: =VLOOKUP(B33,'[1]2.5暖通工程'!$B$3:$K$94,10,0) -> 32.73 | L33: =$L$3 -> 0.207 | M33: =F33*G33 -> 0
A34: 32 | B34: 风机盘管制冷量2.8kw（水） | C34: 1.名称:风机盘管 2.安装形式:吊顶式 3.减振器、支架形式、材质:按设计及规范要求 4.附件：含供回水管、阀门、冷凝水管等至系统验收所需附件。 5.其他:按设计及规范要求 | D34: 按设计图示数量计算，如制冷量为2.8-3.6kw之间，按2.8kw计费 | E34: 台 | F34: 2 | G34: =(H34+I34+J34+K34)*(1+L34) -> 1720.8199 | H34: 680 | I34: 678.6 | J34: 33.95 | K34: 33.15 | L34: =$L$3 -> 0.207 | M34: =F34*G34 -> 3441.6398
A35: 33 | B35: 风机盘管制冷量3.6kw（水） | C35: 1.名称:风机盘管 2.安装形式:吊顶式 3.减振器、支架形式、材质:按设计及规范要求 4.附件：含供回水管、阀门、冷凝水管等至系统验收所需附件。 5.其他:按设计及规范要求 | D35: 按设计图示数量计算，如制冷量为3.6-5.6kw之间，按3.6kw计费 | E35: 台 | F35: 2 | G35: =(H35+I35+J35+K35)*(1+L35) -> 1860.1922 | H35: =VLOOKUP(B35,'[1]2.5暖通工程'!$B$3:$H$94,7,0) -> 734.37 | I35: =VLOOKUP(B35,'[1]2.5暖通工程'!$B$3:$I$94,8,0) -> 739.7 | J35: =VLOOKUP(B35,'[1]2.5暖通工程'!$B$3:$J$94,9,0) -> 33.95 | K35: =VLOOKUP(B35,'[1]2.5暖通工程'!$B$3:$K$94,10,0) -> 33.15 | L35: =$L$3 -> 0.207 | M35: =F35*G35 -> 3720.3844
A36: 34 | B36: 风机盘管制冷量5.6kw（水） | C36: 1.名称:风机盘管 2.安装形式:吊顶式 3.减振器、支架形式、材质:按设计及规范要求 4.附件：含供回水管、阀门、冷凝水管等至系统验收所需附件。 5.其他:按设计及规范要求 | D36: 按设计图示数量计算，如制冷量为5.6-7.1kw之间，按5.6kw计费 | E36: 台 | F36: 6 | G36: =(H36+I36+J36+K36)*(1+L36) -> 1913.6019 | H36: =VLOOKUP(B36,'[1]2.5暖通工程'!$B$3:$H$94,7,0) -> 734.37 | I36: =VLOOKUP(B36,'[1]2.5暖通工程'!$B$3:$I$94,8,0) -> 783.95 | J36: =VLOOKUP(B36,'[1]2.5暖通工程'!$B$3:$J$94,9,0) -> 33.95 | K36: =VLOOKUP(B36,'[1]2.5暖通工程'!$B$3:$K$94,10,0) -> 33.15 | L36: =$L$3 -> 0.207 | M36: =F36*G36 -> 11481.612
A37: 35 | B37: 风机盘管制冷量7.1kw（水） | C37: 1.名称:风机盘管 2.安装形式:吊顶式 3.减振器、支架形式、材质:按设计及规范要求 4.附件：含供回水管、阀门、冷凝水管等至系统验收所需附件。 5.其他:按设计及规范要求 | D37: 按设计图示数量计算，如制冷量为7.1-8kw之间，按7.1kw计费 | E37: 台 | F37: 6 | G37: =(H37+I37+J37+K37)*(1+L37) -> 2067.4824 | H37: =VLOOKUP(B37,'[1]2.5暖通工程'!$B$3:$H$94,7,0) -> 772.13 | I37: =VLOOKUP(B37,'[1]2.5暖通工程'!$B$3:$I$94,8,0) -> 868.73 | J37: =VLOOKUP(B37,'[1]2.5暖通工程'!$B$3:$J$94,9,0) -> 35.07 | K37: =VLOOKUP(B37,'[1]2.5暖通工程'!$B$3:$K$94,10,0) -> 36.98 | L37: =$L$3 -> 0.207 | M37: =F37*G37 -> 12404.894
A38: 36 | B38: 风机盘管制冷量8kw（水） | C38: 1.名称:风机盘管 2.安装形式:吊顶式 3.减振器、支架形式、材质:按设计及规范要求 4.附件：含供回水管、阀门、冷凝水管等至系统验收所需附件。 5.其他:按设计及规范要求 | D38: 按设计图示数量计算，如制冷量为8-9kw之间，按8kw计费 | E38: 台 | F38: 6 | G38: =(H38+I38+J38+K38)*(1+L38) -> 2120.8801 | H38: =VLOOKUP(B38,'[1]2.5暖通工程'!$B$3:$H$94,7,0) -> 772.13 | I38: =VLOOKUP(B38,'[1]2.5暖通工程'!$B$3:$I$94,8,0) -> 912.97 | J38: =VLOOKUP(B38,'[1]2.5暖通工程'!$B$3:$J$94,9,0) -> 35.07 | K38: =VLOOKUP(B38,'[1]2.5暖通工程'!$B$3:$K$94,10,0) -> 36.98 | L38: =$L$3 -> 0.207 | M38: =F38*G38 -> 12725.28
A39: 37 | B39: 风机盘管制冷量9kw（水） | C39: 1.名称:风机盘管 2.安装形式:吊顶式 3.减振器、支架形式、材质:按设计及规范要求 4.附件：含供回水管、阀门、冷凝水管等至系统验收所需附件。 5.其他:按设计及规范要求 | D39: 按设计图示数量计算，如制冷量为9-10kw之间，按9kw计费 | E39: 台 | F39: 5 | G39: =(H39+I39+J39+K39)*(1+L39) -> 2174.2898 | H39: =VLOOKUP(B39,'[1]2.5暖通工程'!$B$3:$H$94,7,0) -> 772.13 | I39: =VLOOKUP(B39,'[1]2.5暖通工程'!$B$3:$I$94,8,0) -> 957.22 | J39: =VLOOKUP(B39,'[1]2.5暖通工程'!$B$3:$J$94,9,0) -> 35.07 | K39: =VLOOKUP(B39,'[1]2.5暖通工程'!$B$3:$K$94,10,0) -> 36.98 | L39: =$L$3 -> 0.207 | M39: =F39*G39 -> 10871.449
A40: 38 | B40: 风机盘管制冷量10kw（水） | C40: 1.名称:风机盘管 2.安装形式:吊顶式 3.减振器、支架形式、材质:按设计及规范要求 4.附件：含供回水管、阀门、冷凝水管等至系统验收所需附件。 5.其他:按设计及规范要求 | D40: 按设计图示数量计算，如制冷量为10-11.2kw之间，按10kw计费 | E40: 台 | F40: 2 | G40: =(H40+I40+J40+K40)*(1+L40) -> 2460.3729 | H40: =VLOOKUP(B40,'[1]2.5暖通工程'!$B$3:$H$94,7,0) -> 802.85 | I40: =VLOOKUP(B40,'[1]2.5暖通工程'!$B$3:$I$94,8,0) -> 1159.84 | J40: =VLOOKUP(B40,'[1]2.5暖通工程'!$B$3:$J$94,9,0) -> 35.82 | K40: =VLOOKUP(B40,'[1]2.5暖通工程'!$B$3:$K$94,10,0) -> 39.91 | L40: =$L$3 -> 0.207 | M40: =F40*G40 -> 4920.7459
A41: 39 | B41: 风机盘管制冷量11.2kw（水） | C41: 1.名称:风机盘管 2.安装形式:吊顶式 3.减振器、支架形式、材质:按设计及规范要求 4.附件：含供回水管、阀门、冷凝水管等至系统验收所需附件。 5.其他:按设计及规范要求 | D41: 按设计图示数量计算，如制冷量为11.2-12.5kw之间，按11.2kw计费 | E41: 台 | F41: 2 | G41: =(H41+I41+J41+K41)*(1+L41) -> 2513.7827 | H41: =VLOOKUP(B41,'[1]2.5暖通工程'!$B$3:$H$94,7,0) -> 802.85 | I41: =VLOOKUP(B41,'[1]2.5暖通工程'!$B$3:$I$94,8,0) -> 1204.09 | J41: =VLOOKUP(B41,'[1]2.5暖通工程'!$B$3:$J$94,9,0) -> 35.82 | K41: =VLOOKUP(B41,'[1]2.5暖通工程'!$B$3:$K$94,10,0) -> 39.91 | L41: =$L$3 -> 0.207 | M41: =F41*G41 -> 5027.5654
A42: 40 | B42: 风机盘管制冷量12.5kw（水） | C42: 1.名称:风机盘管 2.安装形式:吊顶式 3.减振器、支架形式、材质:按设计及规范要求 4.附件：含供回水管、阀门、冷凝水管等至系统验收所需附件。 5.其他:按设计及规范要求 | D42: 按设计图示数量计算，如制冷量为12.5-14kw之间，按12.5kw计费 | E42: 台 | F42: 2 | G42: =(H42+I42+J42+K42)*(1+L42) -> 2620.5901 | H42: =VLOOKUP(B42,'[1]2.5暖通工程'!$B$3:$H$94,7,0) -> 802.85 | I42: =VLOOKUP(B42,'[1]2.5暖通工程'!$B$3:$I$94,8,0) -> 1292.58 | J42: =VLOOKUP(B42,'[1]2.5暖通工程'!$B$3:$J$94,9,0) -> 35.82 | K42: =VLOOKUP(B42,'[1]2.5暖通工程'!$B$3:$K$94,10,0) -> 39.91 | L42: =$L$3 -> 0.207 | M42: =F42*G42 -> 5241.1802
A43: 41 | B43: 风机盘管制冷量14kw（水） | C43: 1.名称:风机盘管 2.安装形式:吊顶式 3.减振器、支架形式、材质:按设计及规范要求 4.附件：含供回水管、阀门、冷凝水管等至系统验收所需附件。 5.其他:按设计及规范要求 | D43: 按设计图示数量计算，如制冷量≥14kw，按14kw计费 | E43: 台 | F43: 1 | G43: =(H43+I43+J43+K43)*(1+L43) -> 3021.6642 | H43: =VLOOKUP(B43,'[1]2.5暖通工程'!$B$3:$H$94,7,0) -> 822.41 | I43: =VLOOKUP(B43,'[1]2.5暖通工程'!$B$3:$I$94,8,0) -> 1602.91 | J43: =VLOOKUP(B43,'[1]2.5暖通工程'!$B$3:$J$94,9,0) -> 36.11 | K43: =VLOOKUP(B43,'[1]2.5暖通工程'!$B$3:$K$94,10,0) -> 42.02 | L43: =$L$3 -> 0.207 | M43: =F43*G43 -> 3021.6642
A44: 42 | B44: 分体空调1匹 | C44: 1.名称:分体空调 2.安装形式:壁挂 3.附件：含内外机、紫铜管、分歧器、冷凝水管、设备支吊架等至系统验收所需附件。 4.其他:按设计及规范要求 | D44: 按设计图示数量计算 | E44: 台 | G44: =(H44+I44+J44+K44)*(1+L44) -> 3130.4993 | H44: =VLOOKUP(B44,'[1]2.5暖通工程'!$B$3:$H$94,7,0) -> 402.9 | I44: =VLOOKUP(B44,'[1]2.5暖通工程'!$B$3:$I$94,8,0) -> 2181.42 | J44: =VLOOKUP(B44,'[1]2.5暖通工程'!$B$3:$J$94,9,0) -> 4.53 | K44: =VLOOKUP(B44,'[1]2.5暖通工程'!$B$3:$K$94,10,0) -> 4.77 | L44: =$L$3 -> 0.207 | M44: =F44*G44 -> 0
A45: 43 | B45: 分体空调2匹 | C45: 1.名称:分体空调 2.安装形式:壁挂 3.附件：含内外机、紫铜管、分歧器、冷凝水管、设备支吊架等至系统验收所需附件。 4.其他:按设计及规范要求 | D45: 按设计图示数量计算 | E45: 台 | G45: =(H45+I45+J45+K45)*(1+L45) -> 3771.3801 | H45: =VLOOKUP(B45,'[1]2.5暖通工程'!$B$3:$H$94,7,0) -> 402.9 | I45: =VLOOKUP(B45,'[1]2.5暖通工程'!$B$3:$I$94,8,0) -> 2712.39 | J45: =VLOOKUP(B45,'[1]2.5暖通工程'!$B$3:$J$94,9,0) -> 4.53 | K45: =VLOOKUP(B45,'[1]2.5暖通工程'!$B$3:$K$94,10,0) -> 4.77 | L45: =$L$3 -> 0.207 | M45: =F45*G45 -> 0
A46: 44 | B46: 分体空调3匹 | C46: 1.名称:分体空调 2.安装形式:落地 3.附件：含内外机、紫铜管、分歧器、冷凝水管、设备支吊架等至系统验收所需附件。 4.其他:按设计及规范要求 | D46: 按设计图示数量计算 | E46: 台 | G46: =(H46+I46+J46+K46)*(1+L46) -> 4759.4062 | H46: =VLOOKUP(B46,'[1]2.5暖通工程'!$B$3:$H$94,7,0) -> 402.9 | I46: =VLOOKUP(B46,'[1]2.5暖通工程'!$B$3:$I$94,8,0) -> 3530.97 | J46: =VLOOKUP(B46,'[1]2.5暖通工程'!$B$3:$J$94,9,0) -> 4.53 | K46: =VLOOKUP(B46,'[1]2.5暖通工程'!$B$3:$K$94,10,0) -> 4.77 | L46: =$L$3 -> 0.207 | M46: =F46*G46 -> 0
A47: 45 | B47: 风幕机0.9m（标配遥控器） | C47: 1.名称:风幕机 0.9m（标配遥控器） 2.其他：按设计及规范要求 | D47: 按设计图示数量计算 | E47: 台 | F47: 1 | G47: =(H47+I47+J47+K47)*(1+L47) -> 1363.1496 | H47: =VLOOKUP(B47,'[1]2.5暖通工程'!$B$3:$H$94,7,0) -> 201.79 | I47: =VLOOKUP(B47,'[1]2.5暖通工程'!$B$3:$I$94,8,0) -> 876.11 | J47: =VLOOKUP(B47,'[1]2.5暖通工程'!$B$3:$J$94,9,0) -> 0 | K47: =VLOOKUP(B47,'[1]2.5暖通工程'!$B$3:$K$94,10,0) -> 51.47 | L47: =$L$3 -> 0.207 | M47: =F47*G47 -> 1363.1496
A48: 46 | B48: 风幕机1m（标配遥控器） | C48: 1.名称:风幕机 1m（标配遥控器） 2.其他：按设计及规范要求 | D48: 按设计图示数量计算 | E48: 台 | F48: 1 | G48: =(H48+I48+J48+K48)*(1+L48) -> 1572.1537 | H48: =VLOOKUP(B48,'[1]2.5暖通工程'!$B$3:$H$94,7,0) -> 269.13 | I48: =VLOOKUP(B48,'[1]2.5暖通工程'!$B$3:$I$94,8,0) -> 964.6 | J48: =VLOOKUP(B48,'[1]2.5暖通工程'!$B$3:$J$94,9,0) -> 0 | K48: =VLOOKUP(B48,'[1]2.5暖通工程'!$B$3:$K$94,10,0) -> 68.8 | L48: =$L$3 -> 0.207 | M48: =F48*G48 -> 1572.1537
A49: 47 | B49: 风幕机1.2m（标配遥控器） | C49: 1.名称:风幕机 1.2m（标配遥控器） 2.其他：按设计及规范要求 | D49: 按设计图示数量计算 | E49: 台 | F49: 1 | G49: =(H49+I49+J49+K49)*(1+L49) -> 1721.701 | H49: =VLOOKUP(B49,'[1]2.5暖通工程'!$B$3:$H$94,7,0) -> 269.13 | I49: =VLOOKUP(B49,'[1]2.5暖通工程'!$B$3:$I$94,8,0) -> 1088.5 | J49: =VLOOKUP(B49,'[1]2.5暖通工程'!$B$3:$J$94,9,0) -> 0 | K49: =VLOOKUP(B49,'[1]2.5暖通工程'!$B$3:$K$94,10,0) -> 68.8 | L49: =$L$3 -> 0.207 | M49: =F49*G49 -> 1721.701
A50: 48 | B50: 风幕机1.5m（标配遥控器） | C50: 1.名称:风幕机 1.5m（标配遥控器） 2.其他：按设计及规范要求 | D50: 按设计图示数量计算 | E50: 台 | F50: 1 | G50: =(H50+I50+J50+K50)*(1+L50) -> 2035.4124 | H50: =VLOOKUP(B50,'[1]2.5暖通工程'!$B$3:$H$94,7,0) -> 309.4 | I50: =VLOOKUP(B50,'[1]2.5暖通工程'!$B$3:$I$94,8,0) -> 1300.89 | J50: =VLOOKUP(B50,'[1]2.5暖通工程'!$B$3:$J$94,9,0) -> 0 | K50: =VLOOKUP(B50,'[1]2.5暖通工程'!$B$3:$K$94,10,0) -> 76.05 | L50: =$L$3 -> 0.207 | M50: =F50*G50 -> 2035.4124
A51: 49 | B51: 风幕机1.8m（标配遥控器） | C51: 1.名称:风幕机 1.8m（标配遥控器） 2.其他：按设计及规范要求 | D51: 按设计图示数量计算 | E51: 台 | F51: 1 | G51: =(H51+I51+J51+K51)*(1+L51) -> 2384.8027 | H51: =VLOOKUP(B51,'[1]2.5暖通工程'!$B$3:$H$94,7,0) -> 371.28 | I51: =VLOOKUP(B51,'[1]2.5暖通工程'!$B$3:$I$94,8,0) -> 1513.27 | J51: =VLOOKUP(B51,'[1]2.5暖通工程'!$B$3:$J$94,9,0) -> 0 | K51: =VLOOKUP(B51,'[1]2.5暖通工程'!$B$3:$K$94,10,0) -> 91.26 | L51: =$L$3 -> 0.207 | M51: =F51*G51 -> 2384.8027
A52: 50 | B52: 风幕机2m（标配遥控器） | C52: 1.名称:风幕机 2m（标配遥控器） 2.其他：按设计及规范要求 | D52: 按设计图示数量计算 | E52: 台 | F52: 1 | G52: =(H52+I52+J52+K52)*(1+L52) -> 2719.7331 | H52: =VLOOKUP(B52,'[1]2.5暖通工程'!$B$3:$H$94,7,0) -> 402.22 | I52: =VLOOKUP(B52,'[1]2.5暖通工程'!$B$3:$I$94,8,0) -> 1752.21 | J52: =VLOOKUP(B52,'[1]2.5暖通工程'!$B$3:$J$94,9,0) -> 0 | K52: =VLOOKUP(B52,'[1]2.5暖通工程'!$B$3:$K$94,10,0) -> 98.87 | L52: =$L$3 -> 0.207 | M52: =F52*G52 -> 2719.7331
A53: 51 | B53: 镀锌薄钢板厚度0.5mm | C53: 1.名称:镀锌薄钢板 2.管道穿内墙、楼板、吊顶开洞及封堵套管:按设计及规范要求 3.管件、法兰等附件及支架设计要求:按设计及规范要求 4.支架及抗震支架：按设计及规范要求 5.其他:按设计及规范要求 | D53: 按设计图示内径尺寸以展开面积计算，如有其他厚度按重量折算 | E53: m2 | G53: =(H53+I53+J53+K53)*(1+L53) -> 182.46219 | H53: =VLOOKUP(B53,'[1]2.5暖通工程'!$B$3:$H$94,7,0) -> 107.48 | I53: =VLOOKUP(B53,'[1]2.5暖通工程'!$B$3:$I$94,8,0) -> 19.18 | J53: =VLOOKUP(B53,'[1]2.5暖通工程'!$B$3:$J$94,9,0) -> 18.67 | K53: =VLOOKUP(B53,'[1]2.5暖通工程'!$B$3:$K$94,10,0) -> 5.84 | L53: =$L$3 -> 0.207 | M53: =F53*G53 -> 0
A54: 52 | B54: 镀锌薄钢板厚度0.6mm | C54: 1.名称:镀锌薄钢板 2.管道穿内墙、楼板、吊顶开洞及封堵套管:按设计及规范要求 3.管件、法兰等附件及支架设计要求:按设计及规范要求 4.支架及抗震支架：按设计及规范要求 5.其他:按设计及规范要求 | D54: 按设计图示内径尺寸以展开面积计算，如有其他厚度按重量折算 | E54: m2 | G54: =(H54+I54+J54+K54)*(1+L54) -> 190.18699 | H54: =VLOOKUP(B54,'[1]2.5暖通工程'!$B$3:$H$94,7,0) -> 115.06 | I54: =VLOOKUP(B54,'[1]2.5暖通工程'!$B$3:$I$94,8,0) -> 22.77 | J54: =VLOOKUP(B54,'[1]2.5暖通工程'!$B$3:$J$94,9,0) -> 16.34 | K54: =VLOOKUP(B54,'[1]2.5暖通工程'!$B$3:$K$94,10,0) -> 3.4 | L54: =$L$3 -> 0.207 | M54: =F54*G54 -> 0
A55: 53 | B55: 镀锌薄钢板厚度0.75mm | C55: 1.名称:镀锌薄钢板 2.管道穿内墙、楼板、吊顶开洞及封堵套管:按设计及规范要求 3.管件、法兰等附件及支架设计要求:按设计及规范要求 4.支架及抗震支架：按设计及规范要求 5.其他:按设计及规范要求 | D55: 按设计图示内径尺寸以展开面积计算，如有其他厚度按重量折算 | E55: m2 | G55: =(H55+I55+J55+K55)*(1+L55) -> 183.85024 | H55: =VLOOKUP(B55,'[1]2.5暖通工程'!$B$3:$H$94,7,0) -> 103.51 | I55: =VLOOKUP(B55,'[1]2.5暖通工程'!$B$3:$I$94,8,0) -> 27.94 | J55: =VLOOKUP(B55,'[1]2.5暖通工程'!$B$3:$J$94,9,0) -> 17.47 | K55: =VLOOKUP(B55,'[1]2.5暖通工程'!$B$3:$K$94,10,0) -> 3.4 | L55: =$L$3 -> 0.207 | M55: =F55*G55 -> 0
A56: 54 | B56: 镀锌薄钢板厚度1mm | C56: 1.名称:镀锌薄钢板 2.管道穿内墙、楼板、吊顶开洞及封堵套管:按设计及规范要求 3.管件、法兰等附件及支架设计要求:按设计及规范要求 4.支架及抗震支架：按设计及规范要求 5.其他:按设计及规范要求 | D56: 按设计图示内径尺寸以展开面积计算，如有其他厚度按重量折算 | E56: m2 | G56: =(H56+I56+J56+K56)*(1+L56) -> 220.80858 | H56: =VLOOKUP(B56,'[1]2.5暖通工程'!$B$3:$H$94,7,0) -> 124.9 | I56: =VLOOKUP(B56,'[1]2.5暖通工程'!$B$3:$I$94,8,0) -> 35.2 | J56: =VLOOKUP(B56,'[1]2.5暖通工程'!$B$3:$J$94,9,0) -> 20.82 | K56: =VLOOKUP(B56,'[1]2.5暖通工程'!$B$3:$K$94,10,0) -> 2.02 | L56: =$L$3 -> 0.207 | M56: =F56*G56 -> 0
A57: 55 | B57: 镀锌薄钢板厚度1.2mm | C57: 1.名称:镀锌薄钢板 2.管道穿内墙、楼板、吊顶开洞及封堵套管:按设计及规范要求 3.管件、法兰等附件及支架设计要求:按设计及规范要求 4.支架及抗震支架：按设计及规范要求 5.其他:按设计及规范要求 | D57: 按设计图示内径尺寸以展开面积计算，如有其他厚度按重量折算 | E57: m2 | F57: 15.856 | G57: =(H57+I57+J57+K57)*(1+L57) -> 232.48027 | H57: =VLOOKUP(B57,'[1]2.5暖通工程'!$B$3:$H$94,7,0) -> 122.74 | I57: =VLOOKUP(B57,'[1]2.5暖通工程'!$B$3:$I$94,8,0) -> 42.24 | J57: =VLOOKUP(B57,'[1]2.5暖通工程'!$B$3:$J$94,9,0) -> 26.16 | K57: =VLOOKUP(B57,'[1]2.5暖通工程'!$B$3:$K$94,10,0) -> 1.47 | L57: =$L$3 -> 0.207 | M57: =F57*G57 -> 3686.2072
A58: 56 | B58: 镀锌薄钢板厚度1.5mm | C58: 1.名称:镀锌薄钢板 2.管道穿内墙、楼板、吊顶开洞及封堵套管:按设计及规范要求 3.管件、法兰等附件及支架设计要求:按设计及规范要求 4.支架及抗震支架：按设计及规范要求 5.其他:按设计及规范要求 | D58: 按设计图示内径尺寸以展开面积计算，如有其他厚度按重量折算 | E58: m2 | G58: =(H58+I58+J58+K58)*(1+L58) -> 249.46276 | H58: =VLOOKUP(B58,'[1]2.5暖通工程'!$B$3:$H$94,7,0) -> 130.74 | I58: =VLOOKUP(B58,'[1]2.5暖通工程'!$B$3:$I$94,8,0) -> 48.31 | J58: =VLOOKUP(B58,'[1]2.5暖通工程'!$B$3:$J$94,9,0) -> 26.16 | K58: =VLOOKUP(B58,'[1]2.5暖通工程'!$B$3:$K$94,10,0) -> 1.47 | L58: =$L$3 -> 0.207 | M58: =F58*G58 -> 0
A59: 57 | B59: 橡塑保温通风管道(厚度)10mm | C59: 1.绝热材料品种:橡塑 2.其他:按设计及规范要求 | D59: 依据2013清单工程量计算规则，按图示表面积加绝热层厚度计算 | E59: m3 | G59: =(H59+I59+J59+K59)*(1+L59) -> 2931.3805 | H59: =VLOOKUP(B59,'[1]2.5暖通工程'!$B$3:$H$94,7,0) -> 1340.42 | I59: =VLOOKUP(B59,'[1]2.5暖通工程'!$B$3:$I$94,8,0) -> 936.64 | J59: =VLOOKUP(B59,'[1]2.5暖通工程'!$B$3:$J$94,9,0) -> 151.59 | K59: =VLOOKUP(B59,'[1]2.5暖通工程'!$B$3:$K$94,10,0) -> 0 | L59: =$L$3 -> 0.207 | M59: =F59*G59 -> 0
A60: 58 | B60: 橡塑保温通风管道(厚度)20mm | C60: 1.绝热材料品种:橡塑 2.其他:按设计及规范要求 | D60: 依据2013清单工程量计算规则，按图示表面积加绝热层厚度计算 | E60: m3 | G60: =(H60+I60+J60+K60)*(1+L60) -> 2562.5696 | H60: =VLOOKUP(B60,'[1]2.5暖通工程'!$B$3:$H$94,7,0) -> 1107.9 | I60: =VLOOKUP(B60,'[1]2.5暖通工程'!$B$3:$I$94,8,0) -> 936.64 | J60: =VLOOKUP(B60,'[1]2.5暖通工程'!$B$3:$J$94,9,0) -> 78.55 | K60: =VLOOKUP(B60,'[1]2.5暖通工程'!$B$3:$K$94,10,0) -> 0 | L60: =$L$3 -> 0.207 | M60: =F60*G60 -> 0
A61: 59 | B61: 橡塑保温通风管道(厚度)30mm | C61: 1.绝热材料品种:橡塑 2.其他:按设计及规范要求 | D61: 依据2013清单工程量计算规则，按图示表面积加绝热层厚度计算 | E61: m3 | F61: 3.54 | G61: =(H61+I61+J61+K61)*(1+L61) -> 2335.7985 | H61: =VLOOKUP(B61,'[1]2.5暖通工程'!$B$3:$H$94,7,0) -> 947.31 | I61: =VLOOKUP(B61,'[1]2.5暖通工程'!$B$3:$I$94,8,0) -> 936.64 | J61: =VLOOKUP(B61,'[1]2.5暖通工程'!$B$3:$J$94,9,0) -> 51.26 | K61: =VLOOKUP(B61,'[1]2.5暖通工程'!$B$3:$K$94,10,0) -> 0 | L61: =$L$3 -> 0.207 | M61: =F61*G61 -> 8268.7266
A62: 60 | B62: 离心玻璃棉保温通风管道(厚度)30mm | C62: 1.绝热材料品种:离心玻璃棉 2.其他:按设计及规范要求 | D62: 依据2013清单工程量计算规则，按图示表面积加绝热层厚度计算 | E62: m3 | G62: =(H62+I62+J62+K62)*(1+L62) -> 1805.8893 | H62: =VLOOKUP(B62,'[1]2.5暖通工程'!$B$3:$H$94,7,0) -> 1058.79 | I62: =VLOOKUP(B62,'[1]2.5暖通工程'!$B$3:$I$94,8,0) -> 364.88 | J62: =VLOOKUP(B62,'[1]2.5暖通工程'!$B$3:$J$94,9,0) -> 72.51 | K62: =VLOOKUP(B62,'[1]2.5暖通工程'!$B$3:$K$94,10,0) -> 0 | L62: =$L$3 -> 0.207 | M62: =F62*G62 -> 0
A63: 61 | B63: 离心玻璃棉保温通风管道(厚度)40mm | C63: 1.绝热材料品种:离心玻璃棉 2.其他:按设计及规范要求 | D63: 依据2013清单工程量计算规则，按图示表面积加绝热层厚度计算 | E63: m3 | G63: =(H63+I63+J63+K63)*(1+L63) -> 1628.7137 | H63: =VLOOKUP(B63,'[1]2.5暖通工程'!$B$3:$H$94,7,0) -> 925.7 | I63: =VLOOKUP(B63,'[1]2.5暖通工程'!$B$3:$I$94,8,0) -> 364.88 | J63: =VLOOKUP(B63,'[1]2.5暖通工程'!$B$3:$J$94,9,0) -> 58.81 | K63: =VLOOKUP(B63,'[1]2.5暖通工程'!$B$3:$K$94,10,0) -> 0 | L63: =$L$3 -> 0.207 | M63: =F63*G63 -> 0
A64: 62 | B64: 离心玻璃棉保温通风管道(厚度)50mm | C64: 1.绝热材料品种:离心玻璃棉 2.其他:按设计及规范要求 | D64: 依据2013清单工程量计算规则，按图示表面积加绝热层厚度计算 | E64: m3 | G64: =(H64+I64+J64+K64)*(1+L64) -> 1458.9854 | H64: =VLOOKUP(B64,'[1]2.5暖通工程'!$B$3:$H$94,7,0) -> 792.84 | I64: =VLOOKUP(B64,'[1]2.5暖通工程'!$B$3:$I$94,8,0) -> 364.88 | J64: =VLOOKUP(B64,'[1]2.5暖通工程'!$B$3:$J$94,9,0) -> 51.05 | K64: =VLOOKUP(B64,'[1]2.5暖通工程'!$B$3:$K$94,10,0) -> 0 | L64: =$L$3 -> 0.207 | M64: =F64*G64 -> 0
A65: 63 | B65: 离心玻璃棉保温通风管道(厚度)60mm | C65: 1.绝热材料品种:离心玻璃棉 2.其他:按设计及规范要求 | D65: 依据2013清单工程量计算规则，按图示表面积加绝热层厚度计算 | E65: m3 | G65: =(H65+I65+J65+K65)*(1+L65) -> 1292.2021 | H65: =VLOOKUP(B65,'[1]2.5暖通工程'!$B$3:$H$94,7,0) -> 659.75 | I65: =VLOOKUP(B65,'[1]2.5暖通工程'!$B$3:$I$94,8,0) -> 364.88 | J65: =VLOOKUP(B65,'[1]2.5暖通工程'!$B$3:$J$94,9,0) -> 45.96 | K65: =VLOOKUP(B65,'[1]2.5暖通工程'!$B$3:$K$94,10,0) -> 0 | L65: =$L$3 -> 0.207 | M65: =F65*G65 -> 0
A66: 64 | B66: 离心玻璃棉保温通风管道(厚度)70mm | C66: 1.绝热材料品种:离心玻璃棉 2.其他:按设计及规范要求 | D66: 依据2013清单工程量计算规则，按图示表面积加绝热层厚度计算 | E66: m3 | G66: =(H66+I66+J66+K66)*(1+L66) -> 1137.4285 | H66: =VLOOKUP(B66,'[1]2.5暖通工程'!$B$3:$H$94,7,0) -> 535.31 | I66: =VLOOKUP(B66,'[1]2.5暖通工程'!$B$3:$I$94,8,0) -> 364.88 | J66: =VLOOKUP(B66,'[1]2.5暖通工程'!$B$3:$J$94,9,0) -> 42.17 | K66: =VLOOKUP(B66,'[1]2.5暖通工程'!$B$3:$K$94,10,0) -> 0 | L66: =$L$3 -> 0.207 | M66: =F66*G66 -> 0
A67: 65 | B67: 离心玻璃棉保温通风管道(厚度)80mm | C67: 1.绝热材料品种:离心玻璃棉 2.其他:按设计及规范要求 | D67: 依据2013清单工程量计算规则，按图示表面积加绝热层厚度计算 | E67: m3 | G67: =(H67+I67+J67+K67)*(1+L67) -> 1053.53 | H67: =VLOOKUP(B67,'[1]2.5暖通工程'!$B$3:$H$94,7,0) -> 468.65 | I67: =VLOOKUP(B67,'[1]2.5暖通工程'!$B$3:$I$94,8,0) -> 364.88 | J67: =VLOOKUP(B67,'[1]2.5暖通工程'!$B$3:$J$94,9,0) -> 39.32 | K67: =VLOOKUP(B67,'[1]2.5暖通工程'!$B$3:$K$94,10,0) -> 0 | L67: =$L$3 -> 0.207 | M67: =F67*G67 -> 0
A68: 66 | B68: 70℃防火阀 | C68: 1.名称:70℃防火阀 2.规格:按风阀半周长计量 3.其他:按设计及规范要求 | D68: 按设计图示尺寸以半周长计算 | E68: m | G68: =(H68+I68+J68+K68)*(1+L68) -> 524.15182 | H68: =VLOOKUP(B68,'[1]2.5暖通工程'!$B$3:$H$94,7,0) -> 159.71 | I68: =VLOOKUP(B68,'[1]2.5暖通工程'!$B$3:$I$94,8,0) -> 264.74 | J68: =VLOOKUP(B68,'[1]2.5暖通工程'!$B$3:$J$94,9,0) -> 8.31 | K68: =VLOOKUP(B68,'[1]2.5暖通工程'!$B$3:$K$94,10,0) -> 1.5 | L68: =$L$3 -> 0.207 | M68: =F68*G68 -> 0
A69: 67 | B69: 风量调节阀 | C69: 1.名称:风量调节阀 2.规格:按风阀半周长计量 3.其他:按设计及规范要求 | D69: 按设计图示尺寸以半周长计算 | E69: m | G69: =(H69+I69+J69+K69)*(1+L69) -> 328.70231 | H69: =VLOOKUP(B69,'[1]2.5暖通工程'!$B$3:$H$94,7,0) -> 100.1 | I69: =VLOOKUP(B69,'[1]2.5暖通工程'!$B$3:$I$94,8,0) -> 159.29 | J69: =VLOOKUP(B69,'[1]2.5暖通工程'!$B$3:$J$94,9,0) -> 11.44 | K69: =VLOOKUP(B69,'[1]2.5暖通工程'!$B$3:$K$94,10,0) -> 1.5 | L69: =$L$3 -> 0.207 | M69: =F69*G69 -> 0
A70: 68 | B70: 风管止回阀 | C70: 1.名称:风管止回阀 2.规格:按风阀半周长计量 3.其他:按设计及规范要求 | D70: 按设计图示尺寸以半周长计算 | E70: m | G70: =(H70+I70+J70+K70)*(1+L70) -> 400.71193 | H70: =VLOOKUP(B70,'[1]2.5暖通工程'!$B$3:$H$94,7,0) -> 95.55 | I70: =VLOOKUP(B70,'[1]2.5暖通工程'!$B$3:$I$94,8,0) -> 226.91 | J70: =VLOOKUP(B70,'[1]2.5暖通工程'!$B$3:$J$94,9,0) -> 8.03 | K70: =VLOOKUP(B70,'[1]2.5暖通工程'!$B$3:$K$94,10,0) -> 1.5 | L70: =$L$3 -> 0.207 | M70: =F70*G70 -> 0
A71: 69 | B71: 百叶风口、散流器 | C71: 1.名称:百叶风口、散流器 2.材质：ABS塑料，颜色同饰面 3.规格:按风口面部规格长*宽计量面积 3.其他:按设计及规范要求 | D71: 按设计图示尺寸以展开面积计算 | E71: m2 | F71: 0.57 | G71: =(H71+I71+J71+K71)*(1+L71) -> 436.71674 | H71: =VLOOKUP(B71,'[1]2.5暖通工程'!$B$3:$H$94,7,0) -> 153.34 | I71: =VLOOKUP(B71,'[1]2.5暖通工程'!$B$3:$I$94,8,0) -> 200.11 | J71: =VLOOKUP(B71,'[1]2.5暖通工程'!$B$3:$J$94,9,0) -> 8.37 | K71: =VLOOKUP(B71,'[1]2.5暖通工程'!$B$3:$K$94,10,0) -> 0 | L71: =$L$3 -> 0.207 | M71: =F71*G71 -> 248.92854
A72: 70 | B72: 防雨百叶 | C72: 1.名称:防雨百叶 2.规格:按风口面部规格长*宽计量面积 3.其他:按设计及规范要求 | D72: 按设计图示尺寸以展开面积计算 | E72: m2 | G72: =(H72+I72+J72+K72)*(1+L72) -> 436.71674 | H72: =VLOOKUP(B72,'[1]2.5暖通工程'!$B$3:$H$94,7,0) -> 153.34 | I72: =VLOOKUP(B72,'[1]2.5暖通工程'!$B$3:$I$94,8,0) -> 200.11 | J72: =VLOOKUP(B72,'[1]2.5暖通工程'!$B$3:$J$94,9,0) -> 8.37 | K72: =VLOOKUP(B72,'[1]2.5暖通工程'!$B$3:$K$94,10,0) -> 0 | L72: =$L$3 -> 0.207 | M72: =F72*G72 -> 0
A73: 71 | B73: 防火帆布软接 | C73: 1.名称:防火帆布软接 2.其他:按设计及规范要求 | D73: 按设计图示内径尺寸以展开面积计算 | E73: m2 | G73: =(H73+I73+J73+K73)*(1+L73) -> 184.62272 | H73: =VLOOKUP(B73,'[1]2.5暖通工程'!$B$3:$H$94,7,0) -> 71.32 | I73: =VLOOKUP(B73,'[1]2.5暖通工程'!$B$3:$I$94,8,0) -> 19.49 | J73: =VLOOKUP(B73,'[1]2.5暖通工程'!$B$3:$J$94,9,0) -> 59.4 | K73: =VLOOKUP(B73,'[1]2.5暖通工程'!$B$3:$K$94,10,0) -> 2.75 | L73: =$L$3 -> 0.207 | M73: =F73*G73 -> 0
A74: 72 | B74: 多联式空调机组室外机（主材利旧） | C74: 1.名称:多联式空调机组室外机 2.其他:根据现场情况按设计及规范要求 | D74: 按设计图示数量计算 | E74: 台 | G74: =(H74+I74+J74+K74)*(1+L74) -> 1567.6999 | H74: =VLOOKUP(B74,'[1]2.5暖通工程'!$B$3:$H$94,7,0) -> 1260.35 | I74: =VLOOKUP(B74,'[1]2.5暖通工程'!$B$3:$I$94,8,0) -> 0 | J74: =VLOOKUP(B74,'[1]2.5暖通工程'!$B$3:$J$94,9,0) -> 5.39 | K74: =VLOOKUP(B74,'[1]2.5暖通工程'!$B$3:$K$94,10,0) -> 33.1 | L74: =$L$3 -> 0.207 | M74: =F74*G74 -> 0
A75: 73 | B75: 多联式空调机组室外机匹（保护性拆除） | C75: 1.名称:多联式空调机组室外机 2.其他:根据现场情况按设计及规范要求 | D75: 按设计图示数量计算 | E75: 台 | G75: =(H75+I75+J75+K75)*(1+L75) -> 780.60311 | H75: =VLOOKUP(B75,'[1]2.5暖通工程'!$B$3:$H$94,7,0) -> 630.18 | I75: =VLOOKUP(B75,'[1]2.5暖通工程'!$B$3:$I$94,8,0) -> 0 | J75: =VLOOKUP(B75,'[1]2.5暖通工程'!$B$3:$J$94,9,0) -> 0 | K75: =VLOOKUP(B75,'[1]2.5暖通工程'!$B$3:$K$94,10,0) -> 16.55 | L75: =$L$3 -> 0.207 | M75: =F75*G75 -> 0
A76: 74 | B76: 四面出风多联式空调室内机（主材利旧） | C76: 1.名称:四面出风多联式空调室内机 2.其他:根据现场情况按设计及规范要求 | D76: 按设计图示数量计算 | E76: 台 | G76: =(H76+I76+J76+K76)*(1+L76) -> 483.2828 | H76: =VLOOKUP(B76,'[1]2.5暖通工程'!$B$3:$H$94,7,0) -> 341.93 | I76: =VLOOKUP(B76,'[1]2.5暖通工程'!$B$3:$I$94,8,0) -> 0 | J76: =VLOOKUP(B76,'[1]2.5暖通工程'!$B$3:$J$94,9,0) -> 31.21 | K76: =VLOOKUP(B76,'[1]2.5暖通工程'!$B$3:$K$94,10,0) -> 27.26 | L76: =$L$3 -> 0.207 | M76: =F76*G76 -> 0
A77: 75 | B77: 四面出风多联式空调室内机（保护性拆除） | C77: 1.名称:四面出风多联式空调室内机 2.其他:根据现场情况按设计及规范要求 | D77: 按设计图示数量计算 | E77: 台 | G77: =(H77+I77+J77+K77)*(1+L77) -> 222.8122 | H77: =VLOOKUP(B77,'[1]2.5暖通工程'!$B$3:$H$94,7,0) -> 170.97 | I77: =VLOOKUP(B77,'[1]2.5暖通工程'!$B$3:$I$94,8,0) -> 0 | J77: =VLOOKUP(B77,'[1]2.5暖通工程'!$B$3:$J$94,9,0) -> 0 | K77: =VLOOKUP(B77,'[1]2.5暖通工程'!$B$3:$K$94,10,0) -> 13.63 | L77: =$L$3 -> 0.207 | M77: =F77*G77 -> 0
A78: 76 | B78: 风机盘管（主材利旧） | C78: 1.名称:风机盘管 2.其他:根据现场情况按设计及规范要求 | D78: 按设计图示数量计算 | E78: 台 | F78: 1 | G78: =(H78+I78+J78+K78)*(1+L78) -> 483.2828 | H78: =VLOOKUP(B78,'[1]2.5暖通工程'!$B$3:$H$94,7,0) -> 341.93 | I78: =VLOOKUP(B78,'[1]2.5暖通工程'!$B$3:$I$94,8,0) -> 0 | J78: =VLOOKUP(B78,'[1]2.5暖通工程'!$B$3:$J$94,9,0) -> 31.21 | K78: =VLOOKUP(B78,'[1]2.5暖通工程'!$B$3:$K$94,10,0) -> 27.26 | L78: =$L$3 -> 0.207 | M78: =F78*G78 -> 483.2828
A79: 77 | B79: 风机盘管（保护性拆除） | C79: 1.名称:风机盘管 2.其他:根据现场情况按设计及规范要求 | D79: 按设计图示数量计算 | E79: 台 | F79: 1 | G79: =(H79+I79+J79+K79)*(1+L79) -> 206.36079 | H79: =VLOOKUP(B79,'[1]2.5暖通工程'!$B$3:$H$94,7,0) -> 170.97 | I79: =VLOOKUP(B79,'[1]2.5暖通工程'!$B$3:$I$94,8,0) -> 0 | J79: =VLOOKUP(B79,'[1]2.5暖通工程'!$B$3:$J$94,9,0) -> 0 | K79: =VLOOKUP(B79,'[1]2.5暖通工程'!$B$3:$K$94,10,0) -> 0 | L79: =$L$3 -> 0.207 | M79: =F79*G79 -> 206.36079
A80: 78 | B80: 边墙式排风机（主材利旧） | C80: 1.名称:边墙式排风机 2.其他:按设计及规范要求 | D80: 按设计图示数量计算 | E80: 台 | G80: =(H80+I80+J80+K80)*(1+L80) -> 681.60497 | H80: =VLOOKUP(B80,'[1]2.5暖通工程'!$B$3:$H$94,7,0) -> 422.39 | I80: =VLOOKUP(B80,'[1]2.5暖通工程'!$B$3:$I$94,8,0) -> 0 | J80: =VLOOKUP(B80,'[1]2.5暖通工程'!$B$3:$J$94,9,0) -> 79.77 | K80: =VLOOKUP(B80,'[1]2.5暖通工程'!$B$3:$K$94,10,0) -> 62.55 | L80: =$L$3 -> 0.207 | M80: =F80*G80 -> 0
A81: 79 | B81: 边墙式排风机（保护性拆除） | C81: 1.名称:边墙式排风机 2.其他:按设计及规范要求 | D81: 按设计图示数量计算 | E81: 台 | G81: =(H81+I81+J81+K81)*(1+L81) -> 368.46089 | H81: =VLOOKUP(B81,'[1]2.5暖通工程'!$B$3:$H$94,7,0) -> 273.99 | I81: =VLOOKUP(B81,'[1]2.5暖通工程'!$B$3:$I$94,8,0) -> 0 | J81: =VLOOKUP(B81,'[1]2.5暖通工程'!$B$3:$J$94,9,0) -> 0 | K81: =VLOOKUP(B81,'[1]2.5暖通工程'!$B$3:$K$94,10,0) -> 31.28 | L81: =$L$3 -> 0.207 | M81: =F81*G81 -> 0
A82: 80 | B82: 直联管道式离心风机（主材利旧） | C82: 1.名称:直联管道式离心风机 2.其他:按规范要求 | D82: 按设计图示数量计算 | E82: 台 | G82: =(H82+I82+J82+K82)*(1+L82) -> 954.60423 | H82: =VLOOKUP(B82,'[1]2.5暖通工程'!$B$3:$H$94,7,0) -> 623.45 | I82: =VLOOKUP(B82,'[1]2.5暖通工程'!$B$3:$I$94,8,0) -> 0 | J82: =VLOOKUP(B82,'[1]2.5暖通工程'!$B$3:$J$94,9,0) -> 104.89 | K82: =VLOOKUP(B82,'[1]2.5暖通工程'!$B$3:$K$94,10,0) -> 62.55 | L82: =$L$3 -> 0.207 | M82: =F82*G82 -> 0
A83: 81 | B83: 直联管道式离心风机（保护性拆除） | C83: 1.名称:直联管道式离心风机 2.其他:按规范要求 | D83: 按设计图示数量计算 | E83: 台 | G83: =(H83+I83+J83+K83)*(1+L83) -> 436.94607 | H83: =VLOOKUP(B83,'[1]2.5暖通工程'!$B$3:$H$94,7,0) -> 330.73 | I83: =VLOOKUP(B83,'[1]2.5暖通工程'!$B$3:$I$94,8,0) -> 0 | J83: =VLOOKUP(B83,'[1]2.5暖通工程'!$B$3:$J$94,9,0) -> 0 | K83: =VLOOKUP(B83,'[1]2.5暖通工程'!$B$3:$K$94,10,0) -> 31.28 | L83: =$L$3 -> 0.207 | M83: =F83*G83 -> 0
A84: 82 | B84: 吸顶式房间通风器（主材利旧） | C84: 1.名称: 吸顶式房间通风器 2.其他:根据现场情况按设计及规范要求 | D84: 按设计图示数量计算 | E84: 台 | G84: =(H84+I84+J84+K84)*(1+L84) -> 107.07297 | H84: =VLOOKUP(B84,'[1]2.5暖通工程'!$B$3:$H$94,7,0) -> 82.81 | I84: =VLOOKUP(B84,'[1]2.5暖通工程'!$B$3:$I$94,8,0) -> 0 | J84: =VLOOKUP(B84,'[1]2.5暖通工程'!$B$3:$J$94,9,0) -> 5.9 | K84: =VLOOKUP(B84,'[1]2.5暖通工程'!$B$3:$K$94,10,0) -> 0 | L84: =$L$3 -> 0.207 | M84: =F84*G84 -> 0
A85: 83 | B85: 吸顶式房间通风器（保护性拆除） | C85: 1.名称: 吸顶式房间通风器 2.其他:根据现场情况按设计及规范要求 | D85: 按设计图示数量计算 | E85: 台 | G85: =(H85+I85+J85+K85)*(1+L85) -> 49.98187 | H85: =VLOOKUP(B85,'[1]2.5暖通工程'!$B$3:$H$94,7,0) -> 41.41 | I85: =VLOOKUP(B85,'[1]2.5暖通工程'!$B$3:$I$94,8,0) -> 0 | J85: =VLOOKUP(B85,'[1]2.5暖通工程'!$B$3:$J$94,9,0) -> 0 | K85: =VLOOKUP(B85,'[1]2.5暖通工程'!$B$3:$K$94,10,0) -> 0 | L85: =$L$3 -> 0.207 | M85: =F85*G85 -> 0
A86: 84 | B86: 风幕机（主材利旧） | C86: 1.名称:风幕机 2.其他:根据现场情况按设计及规范要求 | D86: 按设计图示数量计算 | E86: 台 | G86: =(H86+I86+J86+K86)*(1+L86) -> 455.58215 | H86: =VLOOKUP(B86,'[1]2.5暖通工程'!$B$3:$H$94,7,0) -> 301.4 | I86: =VLOOKUP(B86,'[1]2.5暖通工程'!$B$3:$I$94,8,0) -> 0 | J86: =VLOOKUP(B86,'[1]2.5暖通工程'!$B$3:$J$94,9,0) -> 0 | K86: =VLOOKUP(B86,'[1]2.5暖通工程'!$B$3:$K$94,10,0) -> 76.05 | L86: =$L$3 -> 0.207 | M86: =F86*G86 -> 0
A87: 85 | B87: 风幕机（保护性拆除） | C87: 1.名称:风幕机 2.其他:根据现场情况按设计及规范要求 | D87: 按设计图示数量计算 | E87: 台 | G87: =(H87+I87+J87+K87)*(1+L87) -> 214.08559 | H87: =VLOOKUP(B87,'[1]2.5暖通工程'!$B$3:$H$94,7,0) -> 125.9 | I87: =VLOOKUP(B87,'[1]2.5暖通工程'!$B$3:$I$94,8,0) -> 0 | J87: =VLOOKUP(B87,'[1]2.5暖通工程'!$B$3:$J$94,9,0) -> 0 | K87: =VLOOKUP(B87,'[1]2.5暖通工程'!$B$3:$K$94,10,0) -> 51.47 | L87: =$L$3 -> 0.207 | M87: =F87*G87 -> 0
A88: 86 | B88: 分体空调（主材利旧） | C88: 1.名称:分体空调 2.其他:根据现场情况按设计及规范要求 | D88: 按设计图示数量计算 | E88: 台 | G88: =(H88+I88+J88+K88)*(1+L88) -> 497.5254 | H88: =VLOOKUP(B88,'[1]2.5暖通工程'!$B$3:$H$94,7,0) -> 402.9 | I88: =VLOOKUP(B88,'[1]2.5暖通工程'!$B$3:$I$94,8,0) -> 0 | J88: =VLOOKUP(B88,'[1]2.5暖通工程'!$B$3:$J$94,9,0) -> 4.53 | K88: =VLOOKUP(B88,'[1]2.5暖通工程'!$B$3:$K$94,10,0) -> 4.77 | L88: =$L$3 -> 0.207 | M88: =F88*G88 -> 0
A89: 87 | B89: 分体空调（保护性拆除） | C89: 1.名称:分体空调 2.其他:根据现场情况按设计及规范要求 | D89: 按设计图示数量计算 | E89: 台 | G89: =(H89+I89+J89+K89)*(1+L89) -> 246.03488 | H89: =VLOOKUP(B89,'[1]2.5暖通工程'!$B$3:$H$94,7,0) -> 201.45 | I89: =VLOOKUP(B89,'[1]2.5暖通工程'!$B$3:$I$94,8,0) -> 0 | J89: =VLOOKUP(B89,'[1]2.5暖通工程'!$B$3:$J$94,9,0) -> 0 | K89: =VLOOKUP(B89,'[1]2.5暖通工程'!$B$3:$K$94,10,0) -> 2.39 | L89: =$L$3 -> 0.207 | M89: =F89*G89 -> 0
A90: 合计 | M90: =SUM(M3:M89) -> 97546.873
